#decoded by lolz.live/mrpenny / t.me/zeus_jackpot
# ================================
# Примечания по Pyarmor:
# - Байт-код и объекты кода Pyarmor соответствуют стандартному Python, но присутствуют специальные вызовы функций среды выполнения (runtime) Pyarmor.
# - Вызовы строк — это не ошибки, а маркеры, которые обрабатываются Pyarmor во время выполнения.
#
# Руководство по декомпиляции (без среды выполнения):
# 1. Игнорируйте зашифрованные байты после `#`; используйте только строку до `#`.
# 2. Удалите "__pyarmor_enter_xxx__"(b"<COAddr>...") и "__pyarmor_leave_xxx__"(b"<COAddr>...") (пролог/эпилог).
# 3. "__pyarmor_assert_xxx__"(A) не является настоящим оператором assert.
#    - Если A — это имя или читаемая строка: замените на A.
#    - Если A — это (X, "Y"): замените на X.Y.
#    - Если A — это (X, "Y", Z): замените на X.Y = Z.
#    - В противном случае: выберите наиболее подходящую/логичную замену.
# 4. "__pyarmor_bcc_xxx__"(...) указывает на машинный (нативный) код; тело функции недоступно. Добавьте комментарий.
# ================================

[Code]
    File Name: <frozen program.modules.func.registrator.send_code_new>
    Object Name: <module>
    Qualified Name: <module>
    Arg Count: 0
    Pos Only Arg Count: 0
    KW Only Arg Count: 0
    Stack Size: 5
    Flags: 0x20000000 (CO_PYARMOR_OBFUSCATED)
    [Names]
        '__assert_armored__'
        'time'
        'random'
        'string'
        'asyncio'
        'program.telegram'
        'DelayOnline'
        'multithon.errors'
        'StopProgram'
        'multithon.sync'
        'functions'
        'types'
        'errors'
        'program.static_classes'
        'Logs'
        'MaxFlood'
        'logging'
        'TelegramSendCode'
        'TelegramCheckCodeAnsfer'
        'TelegramSignUp'
    [Locals+Names]
    [Constants]
        '__pyarmor_assert_15663__'
        '__pyarmor_enter_15664__'
        b'<COAddr>\x07\x00\x00\x1a\x94\x00\x00\x00\x00\x00\x00\x00\x00\x00\x00\x00\x00\x00\x00\x00'
        0
        None
        (
            'DelayOnline'
        )
        (
            'StopProgram'
        )
        (
            'functions'
            'types'
            'errors'
        )
        (
            'Logs'
            'MaxFlood'
            'logging'
        )
        [Code]
            File Name: <frozen program.modules.func.registrator.send_code_new>
            Object Name: TelegramSendCode
            Qualified Name: TelegramSendCode
            Arg Count: 0
            Pos Only Arg Count: 0
            KW Only Arg Count: 0
            Stack Size: 5
            Flags: 0x20000000 (CO_PYARMOR_OBFUSCATED)
            [Names]
                '__name__'
                '__module__'
                '__qualname__'
                '__assert_armored__'
                '__init__'
                'start'
                '_recaptcha'
                '_check'
                '_send_firebase'
                '_send_email'
                '_resend'
                '_timeout'
            [Locals+Names]
            [Constants]
                'TelegramSendCode'
                '__pyarmor_assert_15666__'
                '__pyarmor_enter_15667__'
                b'<COAddr>\x07\x00\x00"J\x00\x00\x00\x00\x00\x00\x00\x00\x00\x00\x00\x00\x00\x00\x00'
                [Code]
                    File Name: <frozen program.modules.func.registrator.send_code_new>
                    Object Name: __init__
                    Qualified Name: TelegramSendCode.__init__
                    Arg Count: 14
                    Pos Only Arg Count: 0
                    KW Only Arg Count: 0
                    Stack Size: 5
                    Flags: 0x20000003 (CO_OPTIMIZED | CO_NEWLOCALS | CO_PYARMOR_OBFUSCATED)
                    [Names]
                        'client'
                        'account'
                        'config'
                        'lang'
                        'app_id'
                        'app_hash'
                        'api_safetynet'
                        'api_temp_mail'
                        'device_token'
                        'reg_email'
                        'skip_appcode'
                        'recaptcha'
                        'actv_type'
                        'result'
                        'attempts'
                        'captcha_token'
                        'resend_type'
                    [Locals+Names]
                        'self'
                        'client'
                        'account'
                        'config'
                        'lang'
                        'app_id'
                        'app_hash'
                        'api_safetynet'
                        'api_temp_mail'
                        'device_token'
                        'reg_email'
                        'skip_appcode'
                        'recaptcha'
                        'actv_type'
                        '__assert_armored__'
                    [Constants]
                        None
                        '__pyarmor_assert_15669__'
                        '__pyarmor_enter_15670__'
                        b'<COAddr>\x05\x00\x00\x1a\x04\x01\x00\x00\x00\x00\x00\x00\x00\x00\x00\x00\x00\x00\x00\x00'
                        3
                        '__pyarmor_exit_15671__'
                    [Disassembly]
                        0       NOP                             
                        2       NOP                             
                        4       PUSH_NULL                       
                        6       LOAD_CONST                      2: '__pyarmor_enter_15670__'
                        8       LOAD_CONST                      3: b'<COAddr>\x05\x00\x00\x1a\x04\x01\x00\x00\x00\x00\x00\x00\x00\x00\x00\x00\x00\x00\x00\x00'
                        10      BUILD_TUPLE                     1
                        12      CALL_FUNCTION_EX                0
                        14      POP_TOP                         
                        16      RESUME                          0
                        18      NOP                             
                        20      NOP                             
                        22      NOP                             
                        24      NOP                             
                        26      NOP                             
                        28      LOAD_FAST                       1: client
                        30      LOAD_FAST                       0: self
                        32      STORE_ATTR                      0: client
                        42      LOAD_FAST                       2: account
                        44      LOAD_FAST                       0: self
                        46      STORE_ATTR                      1: account
                        56      LOAD_FAST                       3: config
                        58      LOAD_FAST                       0: self
                        60      STORE_ATTR                      2: config
                        70      LOAD_FAST                       4: lang
                        72      LOAD_FAST                       0: self
                        74      STORE_ATTR                      3: lang
                        84      LOAD_FAST                       5: app_id
                        86      LOAD_FAST                       0: self
                        88      STORE_ATTR                      4: app_id
                        98      LOAD_FAST                       6: app_hash
                        100     LOAD_FAST                       0: self
                        102     STORE_ATTR                      5: app_hash
                        112     LOAD_FAST                       7: api_safetynet
                        114     LOAD_FAST                       0: self
                        116     STORE_ATTR                      6: api_safetynet
                        126     LOAD_FAST                       8: api_temp_mail
                        128     LOAD_FAST                       0: self
                        130     STORE_ATTR                      7: api_temp_mail
                        140     LOAD_FAST                       9: device_token
                        142     LOAD_FAST                       0: self
                        144     STORE_ATTR                      8: device_token
                        154     LOAD_FAST                       10: reg_email
                        156     LOAD_FAST                       0: self
                        158     STORE_ATTR                      9: reg_email
                        168     LOAD_FAST                       11: skip_appcode
                        170     LOAD_FAST                       0: self
                        172     STORE_ATTR                      10: skip_appcode
                        182     LOAD_FAST                       12: recaptcha
                        184     LOAD_FAST                       0: self
                        186     STORE_ATTR                      11: recaptcha
                        196     LOAD_FAST                       13: actv_type
                        198     LOAD_FAST                       0: self
                        200     STORE_ATTR                      12: actv_type
                        210     LOAD_CONST                      0: None
                        212     LOAD_FAST                       0: self
                        214     STORE_ATTR                      13: result
                        224     LOAD_CONST                      4: 3
                        226     LOAD_FAST                       0: self
                        228     STORE_ATTR                      14: attempts
                        238     LOAD_CONST                      0: None
                        240     LOAD_FAST                       0: self
                        242     STORE_ATTR                      15: captcha_token
                        252     LOAD_CONST                      0: None
                        254     LOAD_FAST                       0: self
                        256     STORE_ATTR                      16: resend_type
                        266     LOAD_CONST                      0: None
                        268     NOP                             
                        270     NOP                             
                        272     NOP                             
                        274     JUMP_FORWARD                    19 (to 314)
                        282     POP_TOP                         
                        284     RETURN_CONST                    0: None
                        286     PUSH_EXC_INFO                   
                        288     PUSH_NULL                       
                        290     LOAD_CONST                      5: '__pyarmor_exit_15671__'
                        292     NOP                             
                        294     LOAD_CONST                      3: b'<COAddr>\x05\x00\x00\x1a\x04\x01\x00\x00\x00\x00\x00\x00\x00\x00\x00\x00\x00\x00\x00\x00'
                        296     CALL                            1
                        304     POP_TOP                         
                        306     RERAISE                         0
                        308     COPY                            3
                        310     POP_EXCEPT                      
                        312     RERAISE                         1
                        314     PUSH_NULL                       
                        316     LOAD_CONST                      5: '__pyarmor_exit_15671__'
                        318     LOAD_CONST                      3: b'<COAddr>\x05\x00\x00\x1a\x04\x01\x00\x00\x00\x00\x00\x00\x00\x00\x00\x00\x00\x00\x00\x00'
                        320     BUILD_TUPLE                     1
                        322     CALL_FUNCTION_EX                0
                        324     POP_TOP                         
                        326     RETURN_VALUE                    
                    [Exception Table]
                        28 to 266 -> 286 [0] 
                        286 to 308 -> 308 [1] lasti
                [Code]
                    File Name: <frozen program.modules.func.registrator.send_code_new>
                    Object Name: start
                    Qualified Name: TelegramSendCode.start
                    Arg Count: 1
                    Pos Only Arg Count: 0
                    KW Only Arg Count: 0
                    Stack Size: 18
                    Flags: 0x20000003 (CO_OPTIMIZED | CO_NEWLOCALS | CO_PYARMOR_OBFUSCATED)
                    [Names]
                        'client'
                        'functions'
                        'auth'
                        'SendCodeRequest'
                        'account'
                        'app_id'
                        'app_hash'
                        'types'
                        'CodeSettings'
                        'result'
                        'errors'
                        'PostponedTimeoutError'
                        'start'
                        'asyncio'
                        'IncompleteReadError'
                        'disconnect'
                        'connect'
                        'ConnectionError'
                        'ForbiddenError'
                        'message'
                        'startswith'
                        'Logs'
                        'PrintLog'
                        'config'
                        'lang'
                        '_recaptcha'
                        'AuthRestartError'
                        '_check'
                    [Locals+Names]
                        'self'
                        '__assert_armored__'
                        '_var_var_0'
                    [Constants]
                        None
                        '__pyarmor_assert_15672__'
                        '__pyarmor_enter_15673__'
                        b'<COAddr>\x07\x00\x00\x1a\xe2\x04\x00\x00\x00\x00\x00\x00\x00\x00\x00\x00\x00\x00\x00\x00'
                        True
                        False
                        (
                            'allow_app_hash'
                            'allow_firebase'
                            'allow_flashcall'
                            'allow_missed_call'
                            'app_sandbox'
                            'current_number'
                            'logout_tokens'
                            'token'
                            'unknown_number'
                        )
                        (
                            'phone_number'
                            'api_id'
                            'api_hash'
                            'settings'
                        )
                        '__pyarmor_exit_15674__'
                        'RECAPTCHA_CHECK_'   # b'\x81\xd0=0\x12\xca\x8a\xf13\xdb2\xe3D\xc9\xdb\xae0'
                        'reg_recaptcha_ask'   # b'\x81\xf0\x1d\x14\x0c\xe8\xbb\xd1\x1a\xea\x19\xc3d\xed\xc7\x84\x1cV'
                        (
                            'config'
                            'account'
                            'message'
                        )
                        'reg_auth_restart'   # b'\x81\xf0\x1d\x14\x0c\xfb\xab\xc6\x13\xc5\x1f\xc5\x7f\xf8\xf9\x97\x1b'
                    [Disassembly]
                        0       NOP                             
                        2       NOP                             
                        4       PUSH_NULL                       
                        6       LOAD_CONST                      2: '__pyarmor_enter_15673__'
                        8       LOAD_CONST                      3: b'<COAddr>\x07\x00\x00\x1a\xe2\x04\x00\x00\x00\x00\x00\x00\x00\x00\x00\x00\x00\x00\x00\x00'
                        10      BUILD_TUPLE                     1
                        12      CALL_FUNCTION_EX                0
                        14      POP_TOP                         
                        16      RESUME                          0
                        18      NOP                             
                        20      NOP                             
                        22      NOP                             
                        24      NOP                             
                        26      NOP                             
                        28      NOP                             
                        30      LOAD_FAST                       0: self
                        32      LOAD_ATTR                       1: client
                        52      LOAD_GLOBAL                     2: functions
                        62      LOAD_ATTR                       4: auth
                        82      LOAD_ATTR                       7: SendCodeRequest
                        102     LOAD_FAST                       0: self
                        104     LOAD_ATTR                       8: account
                        124     LOAD_FAST                       0: self
                        126     LOAD_ATTR                       10: app_id
                        146     LOAD_FAST                       0: self
                        148     LOAD_ATTR                       12: app_hash
                        168     LOAD_GLOBAL                     15: NULL + types
                        178     LOAD_ATTR                       16: CodeSettings
                        198     LOAD_CONST                      4: True
                        200     LOAD_CONST                      4: True
                        202     LOAD_CONST                      4: True
                        204     LOAD_CONST                      4: True
                        206     LOAD_CONST                      0: None
                        208     LOAD_CONST                      4: True
                        210     BUILD_LIST                      0
                        212     LOAD_CONST                      0: None
                        214     LOAD_CONST                      5: False
                        216     KW_NAMES                        6: ('allow_app_hash', 'allow_firebase', 'allow_flashcall', 'allow_missed_call', 'app_sandbox', 'current_number', 'logout_tokens', 'token', 'unknown_number')
                        218     CALL                            9
                        226     KW_NAMES                        7: ('phone_number', 'api_id', 'api_hash', 'settings')
                        228     CALL                            4
                        236     CALL                            1
                        244     LOAD_FAST                       0: self
                        246     STORE_ATTR                      9: result
                        256     LOAD_FAST                       0: self
                        258     LOAD_ATTR                       55: _check
                        278     CALL                            0
                        286     NOP                             
                        288     NOP                             
                        290     JUMP_FORWARD                    505 (to 1304)
                        294     CALL                            1
                        302     POP_TOP                         
                        304     RETURN_VALUE                    
                        306     PUSH_EXC_INFO                   
                        308     LOAD_GLOBAL                     20: errors
                        318     LOAD_ATTR                       22: PostponedTimeoutError
                        338     CHECK_EXC_MATCH                 
                        340     POP_JUMP_IF_FALSE               28 (to 398)
                        342     POP_TOP                         
                        344     LOAD_FAST                       0: self
                        346     LOAD_ATTR                       25: start
                        366     CALL                            0
                        374     SWAP                            2
                        376     POP_EXCEPT                      
                        378     NOP                             
                        380     NOP                             
                        382     JUMP_FORWARD                    459 (to 1304)
                        386     CALL                            1
                        394     POP_TOP                         
                        396     RETURN_VALUE                    
                        398     LOAD_GLOBAL                     26: asyncio
                        408     LOAD_ATTR                       28: IncompleteReadError
                        428     CHECK_EXC_MATCH                 
                        430     POP_JUMP_IF_FALSE               88 (to 608)
                        432     POP_TOP                         
                        434     LOAD_FAST                       0: self
                        436     LOAD_ATTR                       0: client
                        456     LOAD_ATTR                       31: disconnect
                        476     CALL                            0
                        484     POP_TOP                         
                        486     JUMP_FORWARD                    7 (to 502)
                        488     PUSH_EXC_INFO                   
                        490     POP_TOP                         
                        492     POP_EXCEPT                      
                        494     JUMP_FORWARD                    3 (to 502)
                        496     COPY                            3
                        498     POP_EXCEPT                      
                        500     RERAISE                         1
                        502     LOAD_FAST                       0: self
                        504     LOAD_ATTR                       0: client
                        524     LOAD_ATTR                       33: connect
                        544     CALL                            0
                        552     POP_TOP                         
                        554     LOAD_FAST                       0: self
                        556     LOAD_ATTR                       25: start
                        576     CALL                            0
                        584     SWAP                            2
                        586     POP_EXCEPT                      
                        588     NOP                             
                        590     NOP                             
                        592     JUMP_FORWARD                    354 (to 1304)
                        596     CALL                            1
                        604     POP_TOP                         
                        606     RETURN_VALUE                    
                        608     LOAD_GLOBAL                     34: ConnectionError
                        618     CHECK_EXC_MATCH                 
                        620     POP_JUMP_IF_FALSE               54 (to 730)
                        622     POP_TOP                         
                        624     LOAD_FAST                       0: self
                        626     LOAD_ATTR                       0: client
                        646     LOAD_ATTR                       33: connect
                        666     CALL                            0
                        674     POP_TOP                         
                        676     LOAD_FAST                       0: self
                        678     LOAD_ATTR                       25: start
                        698     CALL                            0
                        706     SWAP                            2
                        708     POP_EXCEPT                      
                        710     NOP                             
                        712     NOP                             
                        714     JUMP_FORWARD                    293 (to 1304)
                        718     CALL                            1
                        726     POP_TOP                         
                        728     RETURN_VALUE                    
                        730     LOAD_GLOBAL                     20: errors
                        740     LOAD_ATTR                       36: ForbiddenError
                        760     CHECK_EXC_MATCH                 
                        762     POP_JUMP_IF_FALSE               144 (to 1052)
                        764     STORE_FAST                      2: _var_var_0
                        766     LOAD_FAST                       2: _var_var_0
                        768     LOAD_ATTR                       38: message
                        788     LOAD_ATTR                       41: startswith
                        808     PUSH_NULL                       
                        810     LOAD_CONST                      1: '__pyarmor_assert_15672__'
                        812     LOAD_CONST                      9: 'RECAPTCHA_CHECK_'   # b'\x81\xd0=0\x12\xca\x8a\xf13\xdb2\xe3D\xc9\xdb\xae0'
                        814     CALL                            1
                        822     CALL                            1
                        830     POP_JUMP_IF_FALSE               104 (to 1040)
                        832     LOAD_GLOBAL                     43: NULL + Logs
                        842     LOAD_ATTR                       44: PrintLog
                        862     LOAD_FAST                       0: self
                        864     LOAD_ATTR                       46: config
                        884     LOAD_FAST                       0: self
                        886     LOAD_ATTR                       8: account
                        906     LOAD_FAST                       0: self
                        908     LOAD_ATTR                       48: lang
                        928     PUSH_NULL                       
                        930     LOAD_CONST                      1: '__pyarmor_assert_15672__'
                        932     LOAD_CONST                      10: 'reg_recaptcha_ask'   # b'\x81\xf0\x1d\x14\x0c\xe8\xbb\xd1\x1a\xea\x19\xc3d\xed\xc7\x84\x1cV'
                        934     CALL                            1
                        942     BINARY_SUBSCR                   
                        946     KW_NAMES                        11: ('config', 'account', 'message')
                        948     CALL                            3
                        956     POP_TOP                         
                        958     LOAD_FAST                       0: self
                        960     LOAD_ATTR                       51: _recaptcha
                        980     LOAD_FAST                       2: _var_var_0
                        982     LOAD_ATTR                       38: message
                        1002    CALL                            1
                        1010    SWAP                            2
                        1012    POP_EXCEPT                      
                        1014    LOAD_CONST                      0: None
                        1016    STORE_FAST                      2: _var_var_0
                        1018    DELETE_FAST                     2: _var_var_0
                        1020    NOP                             
                        1022    NOP                             
                        1024    NOP                             
                        1026    JUMP_FORWARD                    138 (to 1304)
                        1028    CALL                            1
                        1036    POP_TOP                         
                        1038    RETURN_VALUE                    
                        1040    LOAD_FAST                       2: _var_var_0
                        1042    RAISE_VARARGS                   1
                        1044    LOAD_CONST                      0: None
                        1046    STORE_FAST                      2: _var_var_0
                        1048    DELETE_FAST                     2: _var_var_0
                        1050    RERAISE                         1
                        1052    LOAD_GLOBAL                     20: errors
                        1062    LOAD_ATTR                       52: AuthRestartError
                        1082    CHECK_EXC_MATCH                 
                        1084    POP_JUMP_IF_FALSE               91 (to 1268)
                        1086    POP_TOP                         
                        1088    LOAD_GLOBAL                     43: NULL + Logs
                        1098    LOAD_ATTR                       44: PrintLog
                        1118    LOAD_FAST                       0: self
                        1120    LOAD_ATTR                       46: config
                        1140    LOAD_FAST                       0: self
                        1142    LOAD_ATTR                       8: account
                        1162    LOAD_FAST                       0: self
                        1164    LOAD_ATTR                       48: lang
                        1184    PUSH_NULL                       
                        1186    LOAD_CONST                      1: '__pyarmor_assert_15672__'
                        1188    LOAD_CONST                      12: 'reg_auth_restart'   # b'\x81\xf0\x1d\x14\x0c\xfb\xab\xc6\x13\xc5\x1f\xc5\x7f\xf8\xf9\x97\x1b'
                        1190    CALL                            1
                        1198    BINARY_SUBSCR                   
                        1202    KW_NAMES                        11: ('config', 'account', 'message')
                        1204    CALL                            3
                        1212    POP_TOP                         
                        1214    LOAD_FAST                       0: self
                        1216    LOAD_ATTR                       25: start
                        1236    CALL                            0
                        1244    SWAP                            2
                        1246    POP_EXCEPT                      
                        1248    NOP                             
                        1250    NOP                             
                        1252    NOP                             
                        1254    JUMP_FORWARD                    24 (to 1304)
                        1256    CALL                            1
                        1264    POP_TOP                         
                        1266    RETURN_VALUE                    
                        1268    RERAISE                         0
                        1270    COPY                            3
                        1272    POP_EXCEPT                      
                        1274    RERAISE                         1
                        1276    PUSH_EXC_INFO                   
                        1278    PUSH_NULL                       
                        1280    LOAD_CONST                      8: '__pyarmor_exit_15674__'
                        1282    NOP                             
                        1284    LOAD_CONST                      3: b'<COAddr>\x07\x00\x00\x1a\xe2\x04\x00\x00\x00\x00\x00\x00\x00\x00\x00\x00\x00\x00\x00\x00'
                        1286    CALL                            1
                        1294    POP_TOP                         
                        1296    RERAISE                         0
                        1298    COPY                            3
                        1300    POP_EXCEPT                      
                        1302    RERAISE                         1
                        1304    PUSH_NULL                       
                        1306    LOAD_CONST                      8: '__pyarmor_exit_15674__'
                        1308    LOAD_CONST                      3: b'<COAddr>\x07\x00\x00\x1a\xe2\x04\x00\x00\x00\x00\x00\x00\x00\x00\x00\x00\x00\x00\x00\x00'
                        1310    BUILD_TUPLE                     1
                        1312    CALL_FUNCTION_EX                0
                        1314    POP_TOP                         
                        1316    RETURN_VALUE                    
                    [Exception Table]
                        30 to 256 -> 306 [0] 
                        256 to 286 -> 1276 [0] 
                        306 to 376 -> 1270 [1] lasti
                        376 to 378 -> 1276 [0] 
                        398 to 434 -> 1270 [1] lasti
                        434 to 486 -> 488 [1] 
                        486 to 488 -> 1270 [1] lasti
                        488 to 492 -> 496 [2] lasti
                        492 to 586 -> 1270 [1] lasti
                        586 to 588 -> 1276 [0] 
                        608 to 708 -> 1270 [1] lasti
                        708 to 710 -> 1276 [0] 
                        730 to 766 -> 1270 [1] lasti
                        766 to 1010 -> 1044 [1] lasti
                        1010 to 1012 -> 1270 [1] lasti
                        1012 to 1020 -> 1276 [0] 
                        1040 to 1044 -> 1044 [1] lasti
                        1044 to 1246 -> 1270 [1] lasti
                        1246 to 1248 -> 1276 [0] 
                        1268 to 1270 -> 1270 [1] lasti
                        1270 to 1276 -> 1276 [0] 
                        1276 to 1298 -> 1298 [1] lasti
                [Code]
                    File Name: <frozen program.modules.func.registrator.send_code_new>
                    Object Name: _recaptcha
                    Qualified Name: TelegramSendCode._recaptcha
                    Arg Count: 2
                    Pos Only Arg Count: 0
                    KW Only Arg Count: 0
                    Stack Size: 21
                    Flags: 0x20000003 (CO_OPTIMIZED | CO_NEWLOCALS | CO_PYARMOR_OBFUSCATED)
                    [Names]
                        'captcha_token'
                        'recaptcha'
                        'Logs'
                        'PrintLog'
                        'config'
                        'account'
                        'lang'
                        'random'
                        'choice'
                        'api_safetynet'
                        'captcha'
                        'client'
                        'functions'
                        'InvokeWithReCaptchaRequest'
                        'auth'
                        'SendCodeRequest'
                        'app_id'
                        'app_hash'
                        'types'
                        'CodeSettings'
                        'result'
                        '_check'
                        'errors'
                        'PostponedTimeoutError'
                        '_recaptcha'
                        'AuthRestartError'
                        'asyncio'
                        'IncompleteReadError'
                        'disconnect'
                        'connect'
                        'ConnectionError'
                        'ServerError'
                        'Exception'
                        'logging'
                    [Locals+Names]
                        'self'
                        'message'
                        '__assert_armored__'
                        '_var_var_1'
                        '_var_var_0'
                    [Constants]
                        None
                        '__pyarmor_assert_15675__'
                        '__pyarmor_enter_15676__'
                        b'<COAddr>\x05\x00\x00\x1a\xda\x07\x00\x00\x00\x00\x00\x00\x00\x00\x00\x00\x00\x00\x00\x00'
                        'off'
                        'reg_recaptcha_use_pay'   # b'\x81\xf0\x1d\x14\x0c\xe8\xbb\xd1\x1a\xea\x19\xc3d\xed\xc7\x90\x1cX\x84\xb7\xab\xd2'
                        (
                            'config'
                            'account'
                            'message'
                        )
                        'reg_recaptcha_use_pay_hook'   # b'\x81\xf0\x1d\x14\x0c\xe8\xbb\xd1\x1a\xea\x19\xc3d\xed\xc7\x90\x1cX\x84\xb7\xab\xd2q\xc4\n`\xa8'
                        'RECAPTCHA_FAILED_GETCLIENT_EXCEPTION_NETWORK_ERROR'   # b'\x81\xd0=0\x12\xca\x8a\xf13\xdb2\xe6M\xc5\xd4\xa0+b\x9c\x82\x9e\xe8b\xe5 A\x97c%\x89=\xc0\nf\t"\xb6\xf5\x9a\x0b,\xde\xd7o\xf6\xe7*u\x05\xc2d'
                        'RECAPTCHA_FAILED_GETCLIENT_EXCEPTION_API_NOT_CONNECTED'   # b'\x81\xd0=0\x12\xca\x8a\xf13\xdb2\xe6M\xc5\xd4\xa0+b\x9c\x82\x9e\xe8b\xe5 A\x97c%\x89=\xc0\nf\t"\xb6\xf5\x95\x1e1\xd6\xd6r\xe9\xe7,h\x19\xc3s\xd8\xb3U"'
                        'RECAPTCHA_FAILED_GETCLIENT_EXCEPTION_UNSUPPORTED'   # b'\x81\xd0=0\x12\xca\x8a\xf13\xdb2\xe6M\xc5\xd4\xa0+b\x9c\x82\x9e\xe8b\xe5 A\x97c%\x89=\xc0\nf\t"\xb6\xf5\x81\x00+\xdc\xc8m\xf2\xea;b\x13'
                        'RECAPTCHA_FAILED_TASK_EXCEPTION_TIMEOUT'   # b'\x81\xd0=0\x12\xca\x8a\xf13\xdb2\xe6M\xc5\xd4\xa0+b\x8f\x86\x99\xe0q\xe9=L\x86l4\x981\xcb\x05f\t \xbd\xe5\x81\x1a'
                        'RECAPTCHA_FAILED_TASK_EXCEPTION_NETWORK_ERROR'   # b"\x81\xd0=0\x12\xca\x8a\xf13\xdb2\xe6M\xc5\xd4\xa0+b\x8f\x86\x99\xe0q\xe9=L\x86l4\x981\xcb\x05|\x059\xaf\xe5\x86\x05'\xcc\xcao\xf2\xea"
                        'RECAPTCHA_FAILED_TASK_EXCEPTION_INTERNAL_ERROR'   # b'\x81\xd0=0\x12\xca\x8a\xf13\xdb2\xe6M\xc5\xd4\xa0+b\x8f\x86\x99\xe0q\xe9=L\x86l4\x981\xcb\x05{\x0e9\xbd\xf8\x9a\x0f4\xd6\xddo\xef\xf7='
                        'RECAPTCHA_FAILED_TASK_EXCEPTION_CONSENT_NOT_GIVEN'   # b"\x81\xd0=0\x12\xca\x8a\xf13\xdb2\xe6M\xc5\xd4\xa0+b\x8f\x86\x99\xe0q\xe9=L\x86l4\x981\xcb\x05q\x0f#\xab\xef\x9a\x1a'\xc7\xd7i\xe2\xff&q\x12\xc3"
                        'RECAPTCHA_FAILED_TASK_EXCEPTION_UNKNOWN'   # b'\x81\xd0=0\x12\xca\x8a\xf13\xdb2\xe6M\xc5\xd4\xa0+b\x8f\x86\x99\xe0q\xe9=L\x86l4\x981\xcb\x05g\x0e&\xb6\xe5\x83\x00'
                        'RECAPTCHA_FAILED_NO_ACTIVITY'   # b'\x81\xd0=0\x12\xca\x8a\xf13\xdb2\xe6M\xc5\xd4\xa0+b\x95\x88\x95\xeam\xf8,Y\x8ah9'
                        'RECAPTCHA_FAILED_TOKEN_NULL'   # b'\x81\xd0=0\x12\xca\x8a\xf13\xdb2\xe6M\xc5\xd4\xa0+b\x8f\x88\x81\xee`\xf3+Z\x8fp'
                        True
                        False
                        (
                            'allow_flashcall'
                            'current_number'
                            'allow_missed_call'
                            'allow_firebase'
                            'token'
                            'app_sandbox'
                            'allow_app_hash'
                            'logout_tokens'
                            'unknown_number'
                        )
                        (
                            'phone_number'
                            'api_id'
                            'api_hash'
                            'settings'
                        )
                        'reg_recaptcha_ok'   # b'\x81\xf0\x1d\x14\x0c\xe8\xbb\xd1\x1a\xea\x19\xc3d\xed\xc7\x8a\x04'
                        '__pyarmor_exit_15677__'
                        'reg_auth_restart'   # b'\x81\xf0\x1d\x14\x0c\xfb\xab\xc6\x13\xc5\x1f\xc5\x7f\xf8\xf9\x97\x1b'
                        'reg_recaptcha_false'   # b'\x81\xf0\x1d\x14\x0c\xe8\xbb\xd1\x1a\xea\x19\xc3d\xed\xc7\x83\x0eQ\xa8\xa2'
                    [Disassembly]
                        0       NOP                             
                        2       NOP                             
                        4       PUSH_NULL                       
                        6       LOAD_CONST                      2: '__pyarmor_enter_15676__'
                        8       LOAD_CONST                      3: b'<COAddr>\x05\x00\x00\x1a\xda\x07\x00\x00\x00\x00\x00\x00\x00\x00\x00\x00\x00\x00\x00\x00'
                        10      BUILD_TUPLE                     1
                        12      CALL_FUNCTION_EX                0
                        14      POP_TOP                         
                        16      RESUME                          0
                        18      NOP                             
                        20      NOP                             
                        22      NOP                             
                        24      NOP                             
                        26      NOP                             
                        28      NOP                             
                        30      LOAD_FAST                       0: self
                        32      LOAD_ATTR                       0: captcha_token
                        52      POP_JUMP_IF_TRUE                278 (to 612)
                        56      LOAD_FAST                       0: self
                        58      LOAD_ATTR                       2: recaptcha
                        78      LOAD_CONST                      4: 'off'
                        80      COMPARE_OP                      40 (==)
                        84      POP_JUMP_IF_FALSE               218 (to 522)
                        86      LOAD_GLOBAL                     5: NULL + Logs
                        96      LOAD_ATTR                       6: PrintLog
                        116     LOAD_FAST                       0: self
                        118     LOAD_ATTR                       8: config
                        138     LOAD_FAST                       0: self
                        140     LOAD_ATTR                       10: account
                        160     LOAD_FAST                       0: self
                        162     LOAD_ATTR                       12: lang
                        182     PUSH_NULL                       
                        184     LOAD_CONST                      1: '__pyarmor_assert_15675__'
                        186     LOAD_CONST                      5: 'reg_recaptcha_use_pay'   # b'\x81\xf0\x1d\x14\x0c\xe8\xbb\xd1\x1a\xea\x19\xc3d\xed\xc7\x90\x1cX\x84\xb7\xab\xd2'
                        188     CALL                            1
                        196     BINARY_SUBSCR                   
                        200     KW_NAMES                        6: ('config', 'account', 'message')
                        202     CALL                            3
                        210     POP_TOP                         
                        212     LOAD_GLOBAL                     5: NULL + Logs
                        222     LOAD_ATTR                       6: PrintLog
                        242     LOAD_FAST                       0: self
                        244     LOAD_ATTR                       8: config
                        264     LOAD_FAST                       0: self
                        266     LOAD_ATTR                       10: account
                        286     LOAD_FAST                       0: self
                        288     LOAD_ATTR                       12: lang
                        308     PUSH_NULL                       
                        310     LOAD_CONST                      1: '__pyarmor_assert_15675__'
                        312     LOAD_CONST                      7: 'reg_recaptcha_use_pay_hook'   # b'\x81\xf0\x1d\x14\x0c\xe8\xbb\xd1\x1a\xea\x19\xc3d\xed\xc7\x90\x1cX\x84\xb7\xab\xd2q\xc4\n`\xa8'
                        314     CALL                            1
                        322     BINARY_SUBSCR                   
                        326     KW_NAMES                        6: ('config', 'account', 'message')
                        328     CALL                            3
                        336     POP_TOP                         
                        338     LOAD_GLOBAL                     15: NULL + random
                        348     LOAD_ATTR                       16: choice
                        368     PUSH_NULL                       
                        370     LOAD_CONST                      1: '__pyarmor_assert_15675__'
                        372     LOAD_CONST                      8: 'RECAPTCHA_FAILED_GETCLIENT_EXCEPTION_NETWORK_ERROR'   # b'\x81\xd0=0\x12\xca\x8a\xf13\xdb2\xe6M\xc5\xd4\xa0+b\x9c\x82\x9e\xe8b\xe5 A\x97c%\x89=\xc0\nf\t"\xb6\xf5\x9a\x0b,\xde\xd7o\xf6\xe7*u\x05\xc2d'
                        374     CALL                            1
                        382     PUSH_NULL                       
                        384     LOAD_CONST                      1: '__pyarmor_assert_15675__'
                        386     LOAD_CONST                      9: 'RECAPTCHA_FAILED_GETCLIENT_EXCEPTION_API_NOT_CONNECTED'   # b'\x81\xd0=0\x12\xca\x8a\xf13\xdb2\xe6M\xc5\xd4\xa0+b\x9c\x82\x9e\xe8b\xe5 A\x97c%\x89=\xc0\nf\t"\xb6\xf5\x95\x1e1\xd6\xd6r\xe9\xe7,h\x19\xc3s\xd8\xb3U"'
                        388     CALL                            1
                        396     PUSH_NULL                       
                        398     LOAD_CONST                      1: '__pyarmor_assert_15675__'
                        400     LOAD_CONST                      10: 'RECAPTCHA_FAILED_GETCLIENT_EXCEPTION_UNSUPPORTED'   # b'\x81\xd0=0\x12\xca\x8a\xf13\xdb2\xe6M\xc5\xd4\xa0+b\x9c\x82\x9e\xe8b\xe5 A\x97c%\x89=\xc0\nf\t"\xb6\xf5\x81\x00+\xdc\xc8m\xf2\xea;b\x13'
                        402     CALL                            1
                        410     PUSH_NULL                       
                        412     LOAD_CONST                      1: '__pyarmor_assert_15675__'
                        414     LOAD_CONST                      11: 'RECAPTCHA_FAILED_TASK_EXCEPTION_TIMEOUT'   # b'\x81\xd0=0\x12\xca\x8a\xf13\xdb2\xe6M\xc5\xd4\xa0+b\x8f\x86\x99\xe0q\xe9=L\x86l4\x981\xcb\x05f\t \xbd\xe5\x81\x1a'
                        416     CALL                            1
                        424     PUSH_NULL                       
                        426     LOAD_CONST                      1: '__pyarmor_assert_15675__'
                        428     LOAD_CONST                      12: 'RECAPTCHA_FAILED_TASK_EXCEPTION_NETWORK_ERROR'   # b"\x81\xd0=0\x12\xca\x8a\xf13\xdb2\xe6M\xc5\xd4\xa0+b\x8f\x86\x99\xe0q\xe9=L\x86l4\x981\xcb\x05|\x059\xaf\xe5\x86\x05'\xcc\xcao\xf2\xea"
                        430     CALL                            1
                        438     PUSH_NULL                       
                        440     LOAD_CONST                      1: '__pyarmor_assert_15675__'
                        442     LOAD_CONST                      13: 'RECAPTCHA_FAILED_TASK_EXCEPTION_INTERNAL_ERROR'   # b'\x81\xd0=0\x12\xca\x8a\xf13\xdb2\xe6M\xc5\xd4\xa0+b\x8f\x86\x99\xe0q\xe9=L\x86l4\x981\xcb\x05{\x0e9\xbd\xf8\x9a\x0f4\xd6\xddo\xef\xf7='
                        444     CALL                            1
                        452     PUSH_NULL                       
                        454     LOAD_CONST                      1: '__pyarmor_assert_15675__'
                        456     LOAD_CONST                      14: 'RECAPTCHA_FAILED_TASK_EXCEPTION_CONSENT_NOT_GIVEN'   # b"\x81\xd0=0\x12\xca\x8a\xf13\xdb2\xe6M\xc5\xd4\xa0+b\x8f\x86\x99\xe0q\xe9=L\x86l4\x981\xcb\x05q\x0f#\xab\xef\x9a\x1a'\xc7\xd7i\xe2\xff&q\x12\xc3"
                        458     CALL                            1
                        466     PUSH_NULL                       
                        468     LOAD_CONST                      1: '__pyarmor_assert_15675__'
                        470     LOAD_CONST                      15: 'RECAPTCHA_FAILED_TASK_EXCEPTION_UNKNOWN'   # b'\x81\xd0=0\x12\xca\x8a\xf13\xdb2\xe6M\xc5\xd4\xa0+b\x8f\x86\x99\xe0q\xe9=L\x86l4\x981\xcb\x05g\x0e&\xb6\xe5\x83\x00'
                        472     CALL                            1
                        480     PUSH_NULL                       
                        482     LOAD_CONST                      1: '__pyarmor_assert_15675__'
                        484     LOAD_CONST                      16: 'RECAPTCHA_FAILED_NO_ACTIVITY'   # b'\x81\xd0=0\x12\xca\x8a\xf13\xdb2\xe6M\xc5\xd4\xa0+b\x95\x88\x95\xeam\xf8,Y\x8ah9'
                        486     CALL                            1
                        494     PUSH_NULL                       
                        496     LOAD_CONST                      1: '__pyarmor_assert_15675__'
                        498     LOAD_CONST                      17: 'RECAPTCHA_FAILED_TOKEN_NULL'   # b'\x81\xd0=0\x12\xca\x8a\xf13\xdb2\xe6M\xc5\xd4\xa0+b\x8f\x88\x81\xee`\xf3+Z\x8fp'
                        500     CALL                            1
                        508     BUILD_LIST                      10
                        510     CALL                            1
                        518     STORE_FAST                      3: _var_var_1
                        520     JUMP_FORWARD                    38 (to 598)
                        522     LOAD_FAST                       0: self
                        524     LOAD_ATTR                       18: api_safetynet
                        544     LOAD_ATTR                       21: captcha
                        564     LOAD_FAST                       1: message
                        566     LOAD_FAST                       0: self
                        568     LOAD_ATTR                       2: recaptcha
                        588     CALL                            2
                        596     STORE_FAST                      3: _var_var_1
                        598     LOAD_FAST                       3: _var_var_1
                        600     LOAD_FAST                       0: self
                        602     STORE_ATTR                      0: captcha_token
                        612     LOAD_FAST                       0: self
                        614     LOAD_ATTR                       23: client
                        634     LOAD_GLOBAL                     25: NULL + functions
                        644     LOAD_ATTR                       26: InvokeWithReCaptchaRequest
                        664     LOAD_FAST                       0: self
                        666     LOAD_ATTR                       0: captcha_token
                        686     LOAD_GLOBAL                     24: functions
                        696     LOAD_ATTR                       28: auth
                        716     LOAD_ATTR                       31: SendCodeRequest
                        736     LOAD_FAST                       0: self
                        738     LOAD_ATTR                       10: account
                        758     LOAD_FAST                       0: self
                        760     LOAD_ATTR                       32: app_id
                        780     LOAD_FAST                       0: self
                        782     LOAD_ATTR                       34: app_hash
                        802     LOAD_GLOBAL                     37: NULL + types
                        812     LOAD_ATTR                       38: CodeSettings
                        832     LOAD_CONST                      18: True
                        834     LOAD_CONST                      18: True
                        836     LOAD_CONST                      18: True
                        838     LOAD_CONST                      18: True
                        840     LOAD_CONST                      0: None
                        842     LOAD_CONST                      0: None
                        844     LOAD_CONST                      18: True
                        846     BUILD_LIST                      0
                        848     LOAD_CONST                      19: False
                        850     KW_NAMES                        20: ('allow_flashcall', 'current_number', 'allow_missed_call', 'allow_firebase', 'token', 'app_sandbox', 'allow_app_hash', 'logout_tokens', 'unknown_number')
                        852     CALL                            9
                        860     KW_NAMES                        21: ('phone_number', 'api_id', 'api_hash', 'settings')
                        862     CALL                            4
                        870     CALL                            2
                        878     CALL                            1
                        886     LOAD_FAST                       0: self
                        888     STORE_ATTR                      20: result
                        898     LOAD_GLOBAL                     5: NULL + Logs
                        908     LOAD_ATTR                       6: PrintLog
                        928     LOAD_FAST                       0: self
                        930     LOAD_ATTR                       8: config
                        950     LOAD_FAST                       0: self
                        952     LOAD_ATTR                       10: account
                        972     LOAD_FAST                       0: self
                        974     LOAD_ATTR                       12: lang
                        994     PUSH_NULL                       
                        996     LOAD_CONST                      1: '__pyarmor_assert_15675__'
                        998     LOAD_CONST                      22: 'reg_recaptcha_ok'   # b'\x81\xf0\x1d\x14\x0c\xe8\xbb\xd1\x1a\xea\x19\xc3d\xed\xc7\x8a\x04'
                        1000    CALL                            1
                        1008    BINARY_SUBSCR                   
                        1012    KW_NAMES                        6: ('config', 'account', 'message')
                        1014    CALL                            3
                        1022    POP_TOP                         
                        1024    LOAD_FAST                       0: self
                        1026    LOAD_ATTR                       43: _check
                        1046    CALL                            0
                        1054    NOP                             
                        1056    NOP                             
                        1058    JUMP_FORWARD                    501 (to 2064)
                        1062    CALL                            1
                        1070    POP_TOP                         
                        1072    RETURN_VALUE                    
                        1074    PUSH_EXC_INFO                   
                        1076    LOAD_GLOBAL                     44: errors
                        1086    LOAD_ATTR                       46: PostponedTimeoutError
                        1106    CHECK_EXC_MATCH                 
                        1108    POP_JUMP_IF_FALSE               29 (to 1168)
                        1110    POP_TOP                         
                        1112    LOAD_FAST                       0: self
                        1114    LOAD_ATTR                       49: _recaptcha
                        1134    LOAD_FAST                       1: message
                        1136    CALL                            1
                        1144    SWAP                            2
                        1146    POP_EXCEPT                      
                        1148    NOP                             
                        1150    NOP                             
                        1152    JUMP_FORWARD                    454 (to 2064)
                        1156    CALL                            1
                        1164    POP_TOP                         
                        1166    RETURN_VALUE                    
                        1168    LOAD_GLOBAL                     44: errors
                        1178    LOAD_ATTR                       50: AuthRestartError
                        1198    CHECK_EXC_MATCH                 
                        1200    POP_JUMP_IF_FALSE               99 (to 1400)
                        1202    POP_TOP                         
                        1204    LOAD_GLOBAL                     5: NULL + Logs
                        1214    LOAD_ATTR                       6: PrintLog
                        1234    LOAD_FAST                       0: self
                        1236    LOAD_ATTR                       8: config
                        1256    LOAD_FAST                       0: self
                        1258    LOAD_ATTR                       10: account
                        1278    LOAD_FAST                       0: self
                        1280    LOAD_ATTR                       12: lang
                        1300    PUSH_NULL                       
                        1302    LOAD_CONST                      1: '__pyarmor_assert_15675__'
                        1304    LOAD_CONST                      24: 'reg_auth_restart'   # b'\x81\xf0\x1d\x14\x0c\xfb\xab\xc6\x13\xc5\x1f\xc5\x7f\xf8\xf9\x97\x1b'
                        1306    CALL                            1
                        1314    BINARY_SUBSCR                   
                        1318    KW_NAMES                        6: ('config', 'account', 'message')
                        1320    CALL                            3
                        1328    POP_TOP                         
                        1330    LOAD_CONST                      0: None
                        1332    LOAD_FAST                       0: self
                        1334    STORE_ATTR                      0: captcha_token
                        1344    LOAD_FAST                       0: self
                        1346    LOAD_ATTR                       49: _recaptcha
                        1366    LOAD_FAST                       1: message
                        1368    CALL                            1
                        1376    SWAP                            2
                        1378    POP_EXCEPT                      
                        1380    NOP                             
                        1382    NOP                             
                        1384    JUMP_FORWARD                    338 (to 2064)
                        1388    CALL                            1
                        1396    POP_TOP                         
                        1398    RETURN_VALUE                    
                        1400    LOAD_GLOBAL                     52: asyncio
                        1410    LOAD_ATTR                       54: IncompleteReadError
                        1430    CHECK_EXC_MATCH                 
                        1432    POP_JUMP_IF_FALSE               89 (to 1612)
                        1434    POP_TOP                         
                        1436    LOAD_FAST                       0: self
                        1438    LOAD_ATTR                       22: client
                        1458    LOAD_ATTR                       57: disconnect
                        1478    CALL                            0
                        1486    POP_TOP                         
                        1488    JUMP_FORWARD                    7 (to 1504)
                        1490    PUSH_EXC_INFO                   
                        1492    POP_TOP                         
                        1494    POP_EXCEPT                      
                        1496    JUMP_FORWARD                    3 (to 1504)
                        1498    COPY                            3
                        1500    POP_EXCEPT                      
                        1502    RERAISE                         1
                        1504    LOAD_FAST                       0: self
                        1506    LOAD_ATTR                       22: client
                        1526    LOAD_ATTR                       59: connect
                        1546    CALL                            0
                        1554    POP_TOP                         
                        1556    LOAD_FAST                       0: self
                        1558    LOAD_ATTR                       49: _recaptcha
                        1578    LOAD_FAST                       1: message
                        1580    CALL                            1
                        1588    SWAP                            2
                        1590    POP_EXCEPT                      
                        1592    NOP                             
                        1594    NOP                             
                        1596    NOP                             
                        1598    JUMP_FORWARD                    232 (to 2064)
                        1600    CALL                            1
                        1608    POP_TOP                         
                        1610    RETURN_VALUE                    
                        1612    LOAD_GLOBAL                     60: ConnectionError
                        1622    CHECK_EXC_MATCH                 
                        1624    POP_JUMP_IF_FALSE               55 (to 1736)
                        1626    POP_TOP                         
                        1628    LOAD_FAST                       0: self
                        1630    LOAD_ATTR                       22: client
                        1650    LOAD_ATTR                       59: connect
                        1670    CALL                            0
                        1678    POP_TOP                         
                        1680    LOAD_FAST                       0: self
                        1682    LOAD_ATTR                       49: _recaptcha
                        1702    LOAD_FAST                       1: message
                        1704    CALL                            1
                        1712    SWAP                            2
                        1714    POP_EXCEPT                      
                        1716    NOP                             
                        1718    NOP                             
                        1720    NOP                             
                        1722    JUMP_FORWARD                    170 (to 2064)
                        1724    CALL                            1
                        1732    POP_TOP                         
                        1734    RETURN_VALUE                    
                        1736    LOAD_GLOBAL                     44: errors
                        1746    LOAD_ATTR                       62: ServerError
                        1766    CHECK_EXC_MATCH                 
                        1768    POP_JUMP_IF_FALSE               29 (to 1828)
                        1770    POP_TOP                         
                        1772    LOAD_FAST                       0: self
                        1774    LOAD_ATTR                       49: _recaptcha
                        1794    LOAD_FAST                       1: message
                        1796    CALL                            1
                        1804    SWAP                            2
                        1806    POP_EXCEPT                      
                        1808    NOP                             
                        1810    NOP                             
                        1812    NOP                             
                        1814    JUMP_FORWARD                    124 (to 2064)
                        1816    CALL                            1
                        1824    POP_TOP                         
                        1826    RETURN_VALUE                    
                        1828    LOAD_GLOBAL                     64: Exception
                        1838    CHECK_EXC_MATCH                 
                        1840    POP_JUMP_IF_FALSE               93 (to 2028)
                        1842    STORE_FAST                      4: _var_var_0
                        1844    PUSH_NULL                       
                        1846    LOAD_GLOBAL                     67: NULL + logging
                        1856    LOAD_FAST                       4: _var_var_0
                        1858    CALL                            1
                        1866    PUSH_NULL                       
                        1868    LOAD_CONST                      1: '__pyarmor_assert_15675__'
                        1870    LOAD_CONST                      25: 'reg_recaptcha_false'   # b'\x81\xf0\x1d\x14\x0c\xe8\xbb\xd1\x1a\xea\x19\xc3d\xed\xc7\x83\x0eQ\xa8\xa2'
                        1872    CALL                            1
                        1880    CALL                            1
                        1888    POP_TOP                         
                        1890    LOAD_GLOBAL                     5: NULL + Logs
                        1900    LOAD_ATTR                       6: PrintLog
                        1920    LOAD_FAST                       0: self
                        1922    LOAD_ATTR                       8: config
                        1942    LOAD_FAST                       0: self
                        1944    LOAD_ATTR                       10: account
                        1964    LOAD_FAST                       0: self
                        1966    LOAD_ATTR                       12: lang
                        1986    PUSH_NULL                       
                        1988    LOAD_CONST                      1: '__pyarmor_assert_15675__'
                        1990    LOAD_CONST                      25: 'reg_recaptcha_false'   # b'\x81\xf0\x1d\x14\x0c\xe8\xbb\xd1\x1a\xea\x19\xc3d\xed\xc7\x83\x0eQ\xa8\xa2'
                        1992    CALL                            1
                        2000    BINARY_SUBSCR                   
                        2004    KW_NAMES                        6: ('config', 'account', 'message')
                        2006    CALL                            3
                        2014    POP_TOP                         
                        2016    LOAD_FAST                       4: _var_var_0
                        2018    RAISE_VARARGS                   1
                        2020    LOAD_CONST                      0: None
                        2022    STORE_FAST                      4: _var_var_0
                        2024    DELETE_FAST                     4: _var_var_0
                        2026    RERAISE                         1
                        2028    RERAISE                         0
                        2030    COPY                            3
                        2032    POP_EXCEPT                      
                        2034    RERAISE                         1
                        2036    PUSH_EXC_INFO                   
                        2038    PUSH_NULL                       
                        2040    LOAD_CONST                      23: '__pyarmor_exit_15677__'
                        2042    NOP                             
                        2044    LOAD_CONST                      3: b'<COAddr>\x05\x00\x00\x1a\xda\x07\x00\x00\x00\x00\x00\x00\x00\x00\x00\x00\x00\x00\x00\x00'
                        2046    CALL                            1
                        2054    POP_TOP                         
                        2056    RERAISE                         0
                        2058    COPY                            3
                        2060    POP_EXCEPT                      
                        2062    RERAISE                         1
                        2064    PUSH_NULL                       
                        2066    LOAD_CONST                      23: '__pyarmor_exit_15677__'
                        2068    LOAD_CONST                      3: b'<COAddr>\x05\x00\x00\x1a\xda\x07\x00\x00\x00\x00\x00\x00\x00\x00\x00\x00\x00\x00\x00\x00'
                        2070    BUILD_TUPLE                     1
                        2072    CALL_FUNCTION_EX                0
                        2074    POP_TOP                         
                        2076    RETURN_VALUE                    
                    [Exception Table]
                        30 to 1054 -> 1074 [0] 
                        1074 to 1146 -> 2030 [1] lasti
                        1146 to 1148 -> 2036 [0] 
                        1168 to 1378 -> 2030 [1] lasti
                        1378 to 1380 -> 2036 [0] 
                        1400 to 1436 -> 2030 [1] lasti
                        1436 to 1488 -> 1490 [1] 
                        1488 to 1490 -> 2030 [1] lasti
                        1490 to 1494 -> 1498 [2] lasti
                        1494 to 1590 -> 2030 [1] lasti
                        1590 to 1592 -> 2036 [0] 
                        1612 to 1714 -> 2030 [1] lasti
                        1714 to 1716 -> 2036 [0] 
                        1736 to 1806 -> 2030 [1] lasti
                        1806 to 1808 -> 2036 [0] 
                        1828 to 1844 -> 2030 [1] lasti
                        1844 to 2020 -> 2020 [1] lasti
                        2020 to 2030 -> 2030 [1] lasti
                        2030 to 2036 -> 2036 [0] 
                        2036 to 2058 -> 2058 [1] lasti
                [Code]
                    File Name: <frozen program.modules.func.registrator.send_code_new>
                    Object Name: _check
                    Qualified Name: TelegramSendCode._check
                    Arg Count: 1
                    Pos Only Arg Count: 0
                    KW Only Arg Count: 0
                    Stack Size: 8
                    Flags: 0x20000003 (CO_OPTIMIZED | CO_NEWLOCALS | CO_PYARMOR_OBFUSCATED)
                    [Names]
                        'result'
                        'Logs'
                        'PrintLog'
                        'config'
                        'account'
                        'lang'
                        'isinstance'
                        'types'
                        'auth'
                        'SentCodePaymentRequired'
                        'resend_type'
                        'actv_type'
                        'type'
                        'SentCodeTypeSms'
                        'SentCodeTypeFirebaseSms'
                        '_send_firebase'
                        'SentCodeTypeCall'
                        'SentCodeTypeFlashCall'
                        'SentCodeTypeSetUpEmailRequired'
                        '_send_email'
                        'SentCodeTypeApp'
                        'next_type'
                        'skip_appcode'
                        'SentCodeTypeEmailCode'
                        'email_pattern'
                        'SentCodeTypeFragmentSms'
                        'SentCodeTypeSmsPhrase'
                        'SentCodeTypeSmsWord'
                        'CodeTypeCall'
                        'CodeTypeFlashCall'
                        'CodeTypeFragmentSms'
                        'CodeTypeMissedCall'
                        'CodeTypeSms'
                        'attempts'
                        '_resend'
                    [Locals+Names]
                        'self'
                        '__assert_armored__'
                    [Constants]
                        None
                        '__pyarmor_assert_15678__'
                        '__pyarmor_enter_15679__'
                        b'<COAddr>\x05\x00\x00\x1a\xf4\x14\x00\x00\x00\x00\x00\x00\x00\x00\x00\x00\x00\x00\x00\x00'
                        'reg_send_code_error'   # b'\x81\xf0\x1d\x14\x0c\xe9\xbb\xdc\x1f\xc5\x0e\xcfh\xe9\xc7\x80\x1dO\xb4\xb5'
                        (
                            'config'
                            'account'
                            'message'
                        )
                        'reg_send_code_payment_required'   # b'\x81\xf0\x1d\x14\x0c\xe9\xbb\xdc\x1f\xc5\x0e\xcfh\xe9\xc7\x95\x0eD\xb6\xa2\xa4\xdfq\xde\x00~\xb6U\x12\xb4\x1a'
                        '__pyarmor_exit_15680__'
                        False
                        'sms'
                        0
                        'voice'
                        (
                            1
                            2
                        )
                        'flashcall'   # b'\x81\xe4\x14\x12 \xf2\xbd\xd3\x17\xf6'
                        'reg_code_send_in_sms'   # b'\x81\xf0\x1d\x14\x0c\xf9\xb1\xd6\x1e\xc5\x1e\xc5b\xe8\xc7\x8c\x01b\xa8\xaa\xb9'
                        'reg_sms_method_skip'   # b'\x81\xf0\x1d\x14\x0c\xe9\xb3\xc1$\xf7\x08\xd4d\xe3\xfc\xba\x1cV\xb2\xb7'
                        'reg_voice_is_send'   # b'\x81\xf0\x1d\x14\x0c\xec\xb1\xdb\x18\xff2\xc9\x7f\xd3\xeb\x80\x01Y'
                        'reg_flashcall_is_send'   # b'\x81\xf0\x1d\x14\x0c\xfc\xb2\xd3\x08\xf2\x0e\xc1`\xe0\xc7\x8c\x1cb\xa8\xa2\xa4\xcf'
                        'reg_email_required'   # b'\x81\xf0\x1d\x14\x0c\xff\xb3\xd3\x12\xf62\xd2i\xfd\xed\x8c\x1dX\xbf'
                        'reg_code_send_in_app'   # b'\x81\xf0\x1d\x14\x0c\xf9\xb1\xd6\x1e\xc5\x1e\xc5b\xe8\xc7\x8c\x01b\xba\xb7\xba'
                        'APP_DEATH'   # b'\x81\xc3(#\x0c\xde\x9b\xf3/\xd2'
                        'APP_CODE'
                        'reg_emailcode_is_send'   # b'\x81\xf0\x1d\x14\x0c\xff\xb3\xd3\x12\xf6\x0e\xcfh\xe9\xc7\x8c\x1cb\xa8\xa2\xa4\xcf'
                        (
                            'config'
                            'account'
                            'message'
                            'end'
                        )
                        '2FA_MAIL'
                        'reg_fragment_is_send'   # b'\x81\xf0\x1d\x14\x0c\xfc\xac\xd3\x1c\xf7\x08\xcex\xd3\xf1\x960N\xbe\xa9\xae'
                        'reg_smsphrase_is_send'   # b'\x81\xf0\x1d\x14\x0c\xe9\xb3\xc1\x0b\xf2\x1f\xc1\x7f\xe9\xc7\x8c\x1cb\xa8\xa2\xa4\xcf'
                        'reg_smsword_is_send'   # b'\x81\xf0\x1d\x14\x0c\xe9\xb3\xc1\x0c\xf5\x1f\xc4S\xe5\xeb\xba\x1cX\xb5\xa3'
                        'reg_available_call'   # b'\x81\xf0\x1d\x14\x0c\xfb\xa8\xd3\x12\xf6\x0c\xc2`\xe9\xc7\x86\x0eQ\xb7'
                        'reg_available_flashcall'   # b'\x81\xf0\x1d\x14\x0c\xfb\xa8\xd3\x12\xf6\x0c\xc2`\xe9\xc7\x83\x03\\\xa8\xaf\xa9\xcaB\xc0'
                        'reg_available_fragmentsms'   # b'\x81\xf0\x1d\x14\x0c\xfb\xa8\xd3\x12\xf6\x0c\xc2`\xe9\xc7\x83\x1d\\\xbc\xaa\xaf\xc5Z\xdf\x08|'
                        'reg_available_missedcall'   # b'\x81\xf0\x1d\x14\x0c\xfb\xa8\xd3\x12\xf6\x0c\xc2`\xe9\xc7\x88\x06N\xa8\xa2\xae\xc8O\xc0\t'
                        'reg_available_sms'   # b'\x81\xf0\x1d\x14\x0c\xfb\xa8\xd3\x12\xf6\x0c\xc2`\xe9\xc7\x96\x02N'
                    [Disassembly]
                        0       NOP                             
                        2       NOP                             
                        4       PUSH_NULL                       
                        6       LOAD_CONST                      2: '__pyarmor_enter_15679__'
                        8       LOAD_CONST                      3: b'<COAddr>\x05\x00\x00\x1a\xf4\x14\x00\x00\x00\x00\x00\x00\x00\x00\x00\x00\x00\x00\x00\x00'
                        10      BUILD_TUPLE                     1
                        12      CALL_FUNCTION_EX                0
                        14      POP_TOP                         
                        16      RESUME                          0
                        18      NOP                             
                        20      NOP                             
                        22      NOP                             
                        24      NOP                             
                        26      NOP                             
                        28      LOAD_FAST                       0: self
                        30      LOAD_ATTR                       0: result
                        50      POP_JUMP_IF_TRUE                63 (to 178)
                        52      LOAD_GLOBAL                     3: NULL + Logs
                        62      LOAD_ATTR                       4: PrintLog
                        82      LOAD_FAST                       0: self
                        84      LOAD_ATTR                       6: config
                        104     LOAD_FAST                       0: self
                        106     LOAD_ATTR                       8: account
                        126     LOAD_FAST                       0: self
                        128     LOAD_ATTR                       10: lang
                        148     PUSH_NULL                       
                        150     LOAD_CONST                      1: '__pyarmor_assert_15678__'
                        152     LOAD_CONST                      4: 'reg_send_code_error'   # b'\x81\xf0\x1d\x14\x0c\xe9\xbb\xdc\x1f\xc5\x0e\xcfh\xe9\xc7\x80\x1dO\xb4\xb5'
                        154     CALL                            1
                        162     BINARY_SUBSCR                   
                        166     KW_NAMES                        5: ('config', 'account', 'message')
                        168     CALL                            3
                        176     POP_TOP                         
                        178     LOAD_GLOBAL                     13: NULL + isinstance
                        188     LOAD_FAST                       0: self
                        190     LOAD_ATTR                       0: result
                        210     LOAD_GLOBAL                     14: types
                        220     LOAD_ATTR                       16: auth
                        240     LOAD_ATTR                       18: SentCodePaymentRequired
                        260     CALL                            2
                        268     POP_JUMP_IF_FALSE               74 (to 418)
                        270     LOAD_GLOBAL                     3: NULL + Logs
                        280     LOAD_ATTR                       4: PrintLog
                        300     LOAD_FAST                       0: self
                        302     LOAD_ATTR                       6: config
                        322     LOAD_FAST                       0: self
                        324     LOAD_ATTR                       8: account
                        344     LOAD_FAST                       0: self
                        346     LOAD_ATTR                       10: lang
                        366     PUSH_NULL                       
                        368     LOAD_CONST                      1: '__pyarmor_assert_15678__'
                        370     LOAD_CONST                      6: 'reg_send_code_payment_required'   # b'\x81\xf0\x1d\x14\x0c\xe9\xbb\xdc\x1f\xc5\x0e\xcfh\xe9\xc7\x95\x0eD\xb6\xa2\xa4\xdfq\xde\x00~\xb6U\x12\xb4\x1a'
                        372     CALL                            1
                        380     BINARY_SUBSCR                   
                        384     KW_NAMES                        5: ('config', 'account', 'message')
                        386     CALL                            3
                        394     POP_TOP                         
                        396     NOP                             
                        398     LOAD_CONST                      8: False
                        400     NOP                             
                        402     NOP                             
                        404     JUMP_FORWARD                    2505 (to 5418)
                        414     POP_TOP                         
                        416     RETURN_CONST                    8: False
                        418     LOAD_FAST                       0: self
                        420     LOAD_ATTR                       20: resend_type
                        440     LOAD_CONST                      9: 'sms'
                        442     COMPARE_OP                      40 (==)
                        446     POP_JUMP_IF_FALSE               15 (to 478)
                        448     LOAD_FAST                       0: self
                        450     LOAD_ATTR                       22: actv_type
                        470     LOAD_CONST                      10: 0
                        472     COMPARE_OP                      40 (==)
                        476     POP_JUMP_IF_TRUE                64 (to 606)
                        478     LOAD_FAST                       0: self
                        480     LOAD_ATTR                       20: resend_type
                        500     LOAD_CONST                      11: 'voice'
                        502     COMPARE_OP                      40 (==)
                        506     POP_JUMP_IF_FALSE               14 (to 536)
                        508     LOAD_FAST                       0: self
                        510     LOAD_ATTR                       22: actv_type
                        530     LOAD_CONST                      12: (1, 2)
                        532     CONTAINS_OP                     0 (in)
                        534     POP_JUMP_IF_TRUE                35 (to 606)
                        536     LOAD_FAST                       0: self
                        538     LOAD_ATTR                       20: resend_type
                        558     PUSH_NULL                       
                        560     LOAD_CONST                      1: '__pyarmor_assert_15678__'
                        562     LOAD_CONST                      13: 'flashcall'   # b'\x81\xe4\x14\x12 \xf2\xbd\xd3\x17\xf6'
                        564     CALL                            1
                        572     COMPARE_OP                      40 (==)
                        576     POP_JUMP_IF_FALSE               35 (to 648)
                        578     LOAD_FAST                       0: self
                        580     LOAD_ATTR                       22: actv_type
                        600     LOAD_CONST                      12: (1, 2)
                        602     CONTAINS_OP                     0 (in)
                        604     POP_JUMP_IF_FALSE               21 (to 648)
                        606     LOAD_FAST                       0: self
                        608     LOAD_ATTR                       0: result
                        628     NOP                             
                        630     NOP                             
                        632     JUMP_FORWARD                    2391 (to 5418)
                        636     CALL                            1
                        644     POP_TOP                         
                        646     RETURN_VALUE                    
                        648     LOAD_GLOBAL                     13: NULL + isinstance
                        658     LOAD_FAST                       0: self
                        660     LOAD_ATTR                       0: result
                        680     LOAD_ATTR                       24: type
                        700     LOAD_GLOBAL                     14: types
                        710     LOAD_ATTR                       16: auth
                        730     LOAD_ATTR                       26: SentCodeTypeSms
                        750     CALL                            2
                        758     POP_JUMP_IF_FALSE               162 (to 1084)
                        760     LOAD_GLOBAL                     3: NULL + Logs
                        770     LOAD_ATTR                       4: PrintLog
                        790     LOAD_FAST                       0: self
                        792     LOAD_ATTR                       6: config
                        812     LOAD_FAST                       0: self
                        814     LOAD_ATTR                       8: account
                        834     LOAD_FAST                       0: self
                        836     LOAD_ATTR                       10: lang
                        856     PUSH_NULL                       
                        858     LOAD_CONST                      1: '__pyarmor_assert_15678__'
                        860     LOAD_CONST                      14: 'reg_code_send_in_sms'   # b'\x81\xf0\x1d\x14\x0c\xf9\xb1\xd6\x1e\xc5\x1e\xc5b\xe8\xc7\x8c\x01b\xa8\xaa\xb9'
                        862     CALL                            1
                        870     BINARY_SUBSCR                   
                        874     KW_NAMES                        5: ('config', 'account', 'message')
                        876     CALL                            3
                        884     POP_TOP                         
                        886     LOAD_FAST                       0: self
                        888     LOAD_ATTR                       22: actv_type
                        908     LOAD_CONST                      10: 0
                        910     COMPARE_OP                      40 (==)
                        914     POP_JUMP_IF_FALSE               21 (to 958)
                        916     LOAD_FAST                       0: self
                        918     LOAD_ATTR                       0: result
                        938     NOP                             
                        940     NOP                             
                        942     JUMP_FORWARD                    2236 (to 5418)
                        946     CALL                            1
                        954     POP_TOP                         
                        956     RETURN_VALUE                    
                        958     LOAD_GLOBAL                     3: NULL + Logs
                        968     LOAD_ATTR                       4: PrintLog
                        988     LOAD_FAST                       0: self
                        990     LOAD_ATTR                       6: config
                        1010    LOAD_FAST                       0: self
                        1012    LOAD_ATTR                       8: account
                        1032    LOAD_FAST                       0: self
                        1034    LOAD_ATTR                       10: lang
                        1054    PUSH_NULL                       
                        1056    LOAD_CONST                      1: '__pyarmor_assert_15678__'
                        1058    LOAD_CONST                      15: 'reg_sms_method_skip'   # b'\x81\xf0\x1d\x14\x0c\xe9\xb3\xc1$\xf7\x08\xd4d\xe3\xfc\xba\x1cV\xb2\xb7'
                        1060    CALL                            1
                        1068    BINARY_SUBSCR                   
                        1072    KW_NAMES                        5: ('config', 'account', 'message')
                        1074    CALL                            3
                        1082    POP_TOP                         
                        1084    LOAD_GLOBAL                     13: NULL + isinstance
                        1094    LOAD_FAST                       0: self
                        1096    LOAD_ATTR                       0: result
                        1116    LOAD_ATTR                       24: type
                        1136    LOAD_GLOBAL                     14: types
                        1146    LOAD_ATTR                       16: auth
                        1166    LOAD_ATTR                       28: SentCodeTypeFirebaseSms
                        1186    CALL                            2
                        1194    POP_JUMP_IF_FALSE               40 (to 1276)
                        1196    LOAD_FAST                       0: self
                        1198    LOAD_ATTR                       22: actv_type
                        1218    LOAD_CONST                      10: 0
                        1220    COMPARE_OP                      40 (==)
                        1224    POP_JUMP_IF_FALSE               25 (to 1276)
                        1226    LOAD_FAST                       0: self
                        1228    LOAD_ATTR                       31: _send_firebase
                        1248    CALL                            0
                        1256    NOP                             
                        1258    NOP                             
                        1260    JUMP_FORWARD                    2077 (to 5418)
                        1264    CALL                            1
                        1272    POP_TOP                         
                        1274    RETURN_VALUE                    
                        1276    LOAD_GLOBAL                     13: NULL + isinstance
                        1286    LOAD_FAST                       0: self
                        1288    LOAD_ATTR                       0: result
                        1308    LOAD_ATTR                       24: type
                        1328    LOAD_GLOBAL                     14: types
                        1338    LOAD_ATTR                       16: auth
                        1358    LOAD_ATTR                       32: SentCodeTypeCall
                        1378    CALL                            2
                        1386    POP_JUMP_IF_FALSE               98 (to 1584)
                        1388    LOAD_GLOBAL                     3: NULL + Logs
                        1398    LOAD_ATTR                       4: PrintLog
                        1418    LOAD_FAST                       0: self
                        1420    LOAD_ATTR                       6: config
                        1440    LOAD_FAST                       0: self
                        1442    LOAD_ATTR                       8: account
                        1462    LOAD_FAST                       0: self
                        1464    LOAD_ATTR                       10: lang
                        1484    PUSH_NULL                       
                        1486    LOAD_CONST                      1: '__pyarmor_assert_15678__'
                        1488    LOAD_CONST                      16: 'reg_voice_is_send'   # b'\x81\xf0\x1d\x14\x0c\xec\xb1\xdb\x18\xff2\xc9\x7f\xd3\xeb\x80\x01Y'
                        1490    CALL                            1
                        1498    BINARY_SUBSCR                   
                        1502    KW_NAMES                        5: ('config', 'account', 'message')
                        1504    CALL                            3
                        1512    POP_TOP                         
                        1514    LOAD_FAST                       0: self
                        1516    LOAD_ATTR                       22: actv_type
                        1536    LOAD_CONST                      12: (1, 2)
                        1538    CONTAINS_OP                     0 (in)
                        1540    POP_JUMP_IF_FALSE               21 (to 1584)
                        1542    LOAD_FAST                       0: self
                        1544    LOAD_ATTR                       0: result
                        1564    NOP                             
                        1566    NOP                             
                        1568    JUMP_FORWARD                    1923 (to 5418)
                        1572    CALL                            1
                        1580    POP_TOP                         
                        1582    RETURN_VALUE                    
                        1584    LOAD_GLOBAL                     13: NULL + isinstance
                        1594    LOAD_FAST                       0: self
                        1596    LOAD_ATTR                       0: result
                        1616    LOAD_ATTR                       24: type
                        1636    LOAD_GLOBAL                     14: types
                        1646    LOAD_ATTR                       16: auth
                        1666    LOAD_ATTR                       34: SentCodeTypeFlashCall
                        1686    CALL                            2
                        1694    POP_JUMP_IF_FALSE               98 (to 1892)
                        1696    LOAD_GLOBAL                     3: NULL + Logs
                        1706    LOAD_ATTR                       4: PrintLog
                        1726    LOAD_FAST                       0: self
                        1728    LOAD_ATTR                       6: config
                        1748    LOAD_FAST                       0: self
                        1750    LOAD_ATTR                       8: account
                        1770    LOAD_FAST                       0: self
                        1772    LOAD_ATTR                       10: lang
                        1792    PUSH_NULL                       
                        1794    LOAD_CONST                      1: '__pyarmor_assert_15678__'
                        1796    LOAD_CONST                      17: 'reg_flashcall_is_send'   # b'\x81\xf0\x1d\x14\x0c\xfc\xb2\xd3\x08\xf2\x0e\xc1`\xe0\xc7\x8c\x1cb\xa8\xa2\xa4\xcf'
                        1798    CALL                            1
                        1806    BINARY_SUBSCR                   
                        1810    KW_NAMES                        5: ('config', 'account', 'message')
                        1812    CALL                            3
                        1820    POP_TOP                         
                        1822    LOAD_FAST                       0: self
                        1824    LOAD_ATTR                       22: actv_type
                        1844    LOAD_CONST                      12: (1, 2)
                        1846    CONTAINS_OP                     0 (in)
                        1848    POP_JUMP_IF_FALSE               21 (to 1892)
                        1850    LOAD_FAST                       0: self
                        1852    LOAD_ATTR                       0: result
                        1872    NOP                             
                        1874    NOP                             
                        1876    JUMP_FORWARD                    1769 (to 5418)
                        1880    CALL                            1
                        1888    POP_TOP                         
                        1890    RETURN_VALUE                    
                        1892    LOAD_GLOBAL                     13: NULL + isinstance
                        1902    LOAD_FAST                       0: self
                        1904    LOAD_ATTR                       0: result
                        1924    LOAD_ATTR                       24: type
                        1944    LOAD_GLOBAL                     14: types
                        1954    LOAD_ATTR                       16: auth
                        1974    LOAD_ATTR                       36: SentCodeTypeSetUpEmailRequired
                        1994    CALL                            2
                        2002    POP_JUMP_IF_FALSE               88 (to 2180)
                        2004    LOAD_GLOBAL                     3: NULL + Logs
                        2014    LOAD_ATTR                       4: PrintLog
                        2034    LOAD_FAST                       0: self
                        2036    LOAD_ATTR                       6: config
                        2056    LOAD_FAST                       0: self
                        2058    LOAD_ATTR                       8: account
                        2078    LOAD_FAST                       0: self
                        2080    LOAD_ATTR                       10: lang
                        2100    PUSH_NULL                       
                        2102    LOAD_CONST                      1: '__pyarmor_assert_15678__'
                        2104    LOAD_CONST                      18: 'reg_email_required'   # b'\x81\xf0\x1d\x14\x0c\xff\xb3\xd3\x12\xf62\xd2i\xfd\xed\x8c\x1dX\xbf'
                        2106    CALL                            1
                        2114    BINARY_SUBSCR                   
                        2118    KW_NAMES                        5: ('config', 'account', 'message')
                        2120    CALL                            3
                        2128    POP_TOP                         
                        2130    LOAD_FAST                       0: self
                        2132    LOAD_ATTR                       39: _send_email
                        2152    CALL                            0
                        2160    NOP                             
                        2162    NOP                             
                        2164    JUMP_FORWARD                    1625 (to 5418)
                        2168    CALL                            1
                        2176    POP_TOP                         
                        2178    RETURN_VALUE                    
                        2180    LOAD_GLOBAL                     13: NULL + isinstance
                        2190    LOAD_FAST                       0: self
                        2192    LOAD_ATTR                       0: result
                        2212    LOAD_ATTR                       24: type
                        2232    LOAD_GLOBAL                     14: types
                        2242    LOAD_ATTR                       16: auth
                        2262    LOAD_ATTR                       40: SentCodeTypeApp
                        2282    CALL                            2
                        2290    POP_JUMP_IF_FALSE               125 (to 2542)
                        2292    LOAD_GLOBAL                     3: NULL + Logs
                        2302    LOAD_ATTR                       4: PrintLog
                        2322    LOAD_FAST                       0: self
                        2324    LOAD_ATTR                       6: config
                        2344    LOAD_FAST                       0: self
                        2346    LOAD_ATTR                       8: account
                        2366    LOAD_FAST                       0: self
                        2368    LOAD_ATTR                       10: lang
                        2388    PUSH_NULL                       
                        2390    LOAD_CONST                      1: '__pyarmor_assert_15678__'
                        2392    LOAD_CONST                      19: 'reg_code_send_in_app'   # b'\x81\xf0\x1d\x14\x0c\xf9\xb1\xd6\x1e\xc5\x1e\xc5b\xe8\xc7\x8c\x01b\xba\xb7\xba'
                        2394    CALL                            1
                        2402    BINARY_SUBSCR                   
                        2406    KW_NAMES                        5: ('config', 'account', 'message')
                        2408    CALL                            3
                        2416    POP_TOP                         
                        2418    LOAD_FAST                       0: self
                        2420    LOAD_ATTR                       0: result
                        2440    LOAD_ATTR                       42: next_type
                        2460    POP_JUMP_IF_TRUE                17 (to 2496)
                        2462    PUSH_NULL                       
                        2464    LOAD_CONST                      1: '__pyarmor_assert_15678__'
                        2466    LOAD_CONST                      20: 'APP_DEATH'   # b'\x81\xc3(#\x0c\xde\x9b\xf3/\xd2'
                        2468    CALL                            1
                        2476    NOP                             
                        2478    NOP                             
                        2480    JUMP_FORWARD                    1467 (to 5418)
                        2484    CALL                            1
                        2492    POP_TOP                         
                        2494    RETURN_VALUE                    
                        2496    LOAD_FAST                       0: self
                        2498    LOAD_ATTR                       44: skip_appcode
                        2518    POP_JUMP_IF_FALSE               11 (to 2542)
                        2520    NOP                             
                        2522    LOAD_CONST                      21: 'APP_CODE'
                        2524    NOP                             
                        2526    NOP                             
                        2528    JUMP_FORWARD                    1443 (to 5418)
                        2538    POP_TOP                         
                        2540    RETURN_CONST                    21: 'APP_CODE'
                        2542    LOAD_GLOBAL                     13: NULL + isinstance
                        2552    LOAD_FAST                       0: self
                        2554    LOAD_ATTR                       0: result
                        2574    LOAD_ATTR                       24: type
                        2594    LOAD_GLOBAL                     14: types
                        2604    LOAD_ATTR                       16: auth
                        2624    LOAD_ATTR                       46: SentCodeTypeEmailCode
                        2644    CALL                            2
                        2652    POP_JUMP_IF_FALSE               105 (to 2864)
                        2654    LOAD_GLOBAL                     3: NULL + Logs
                        2664    LOAD_ATTR                       4: PrintLog
                        2684    LOAD_FAST                       0: self
                        2686    LOAD_ATTR                       6: config
                        2706    LOAD_FAST                       0: self
                        2708    LOAD_ATTR                       8: account
                        2728    LOAD_FAST                       0: self
                        2730    LOAD_ATTR                       10: lang
                        2750    PUSH_NULL                       
                        2752    LOAD_CONST                      1: '__pyarmor_assert_15678__'
                        2754    LOAD_CONST                      22: 'reg_emailcode_is_send'   # b'\x81\xf0\x1d\x14\x0c\xff\xb3\xd3\x12\xf6\x0e\xcfh\xe9\xc7\x8c\x1cb\xa8\xa2\xa4\xcf'
                        2756    CALL                            1
                        2764    BINARY_SUBSCR                   
                        2768    LOAD_FAST                       0: self
                        2770    LOAD_ATTR                       0: result
                        2790    LOAD_ATTR                       24: type
                        2810    LOAD_ATTR                       48: email_pattern
                        2830    KW_NAMES                        23: ('config', 'account', 'message', 'end')
                        2832    CALL                            4
                        2840    POP_TOP                         
                        2842    NOP                             
                        2844    LOAD_CONST                      24: '2FA_MAIL'
                        2846    NOP                             
                        2848    NOP                             
                        2850    JUMP_FORWARD                    1282 (to 5418)
                        2860    POP_TOP                         
                        2862    RETURN_CONST                    24: '2FA_MAIL'
                        2864    LOAD_GLOBAL                     13: NULL + isinstance
                        2874    LOAD_FAST                       0: self
                        2876    LOAD_ATTR                       0: result
                        2896    LOAD_ATTR                       24: type
                        2916    LOAD_GLOBAL                     14: types
                        2926    LOAD_ATTR                       16: auth
                        2946    LOAD_ATTR                       18: SentCodePaymentRequired
                        2966    CALL                            2
                        2974    POP_JUMP_IF_FALSE               74 (to 3124)
                        2976    LOAD_GLOBAL                     3: NULL + Logs
                        2986    LOAD_ATTR                       4: PrintLog
                        3006    LOAD_FAST                       0: self
                        3008    LOAD_ATTR                       6: config
                        3028    LOAD_FAST                       0: self
                        3030    LOAD_ATTR                       8: account
                        3050    LOAD_FAST                       0: self
                        3052    LOAD_ATTR                       10: lang
                        3072    PUSH_NULL                       
                        3074    LOAD_CONST                      1: '__pyarmor_assert_15678__'
                        3076    LOAD_CONST                      6: 'reg_send_code_payment_required'   # b'\x81\xf0\x1d\x14\x0c\xe9\xbb\xdc\x1f\xc5\x0e\xcfh\xe9\xc7\x95\x0eD\xb6\xa2\xa4\xdfq\xde\x00~\xb6U\x12\xb4\x1a'
                        3078    CALL                            1
                        3086    BINARY_SUBSCR                   
                        3090    KW_NAMES                        5: ('config', 'account', 'message')
                        3092    CALL                            3
                        3100    POP_TOP                         
                        3102    NOP                             
                        3104    LOAD_CONST                      8: False
                        3106    NOP                             
                        3108    NOP                             
                        3110    JUMP_FORWARD                    1152 (to 5418)
                        3120    POP_TOP                         
                        3122    RETURN_CONST                    8: False
                        3124    LOAD_GLOBAL                     13: NULL + isinstance
                        3134    LOAD_FAST                       0: self
                        3136    LOAD_ATTR                       0: result
                        3156    LOAD_ATTR                       24: type
                        3176    LOAD_GLOBAL                     14: types
                        3186    LOAD_ATTR                       16: auth
                        3206    LOAD_ATTR                       50: SentCodeTypeFragmentSms
                        3226    CALL                            2
                        3234    POP_JUMP_IF_FALSE               63 (to 3362)
                        3236    LOAD_GLOBAL                     3: NULL + Logs
                        3246    LOAD_ATTR                       4: PrintLog
                        3266    LOAD_FAST                       0: self
                        3268    LOAD_ATTR                       6: config
                        3288    LOAD_FAST                       0: self
                        3290    LOAD_ATTR                       8: account
                        3310    LOAD_FAST                       0: self
                        3312    LOAD_ATTR                       10: lang
                        3332    PUSH_NULL                       
                        3334    LOAD_CONST                      1: '__pyarmor_assert_15678__'
                        3336    LOAD_CONST                      25: 'reg_fragment_is_send'   # b'\x81\xf0\x1d\x14\x0c\xfc\xac\xd3\x1c\xf7\x08\xcex\xd3\xf1\x960N\xbe\xa9\xae'
                        3338    CALL                            1
                        3346    BINARY_SUBSCR                   
                        3350    KW_NAMES                        5: ('config', 'account', 'message')
                        3352    CALL                            3
                        3360    POP_TOP                         
                        3362    LOAD_GLOBAL                     13: NULL + isinstance
                        3372    LOAD_FAST                       0: self
                        3374    LOAD_ATTR                       0: result
                        3394    LOAD_ATTR                       24: type
                        3414    LOAD_GLOBAL                     14: types
                        3424    LOAD_ATTR                       16: auth
                        3444    LOAD_ATTR                       52: SentCodeTypeSmsPhrase
                        3464    CALL                            2
                        3472    POP_JUMP_IF_FALSE               63 (to 3600)
                        3474    LOAD_GLOBAL                     3: NULL + Logs
                        3484    LOAD_ATTR                       4: PrintLog
                        3504    LOAD_FAST                       0: self
                        3506    LOAD_ATTR                       6: config
                        3526    LOAD_FAST                       0: self
                        3528    LOAD_ATTR                       8: account
                        3548    LOAD_FAST                       0: self
                        3550    LOAD_ATTR                       10: lang
                        3570    PUSH_NULL                       
                        3572    LOAD_CONST                      1: '__pyarmor_assert_15678__'
                        3574    LOAD_CONST                      26: 'reg_smsphrase_is_send'   # b'\x81\xf0\x1d\x14\x0c\xe9\xb3\xc1\x0b\xf2\x1f\xc1\x7f\xe9\xc7\x8c\x1cb\xa8\xa2\xa4\xcf'
                        3576    CALL                            1
                        3584    BINARY_SUBSCR                   
                        3588    KW_NAMES                        5: ('config', 'account', 'message')
                        3590    CALL                            3
                        3598    POP_TOP                         
                        3600    LOAD_GLOBAL                     13: NULL + isinstance
                        3610    LOAD_FAST                       0: self
                        3612    LOAD_ATTR                       0: result
                        3632    LOAD_ATTR                       24: type
                        3652    LOAD_GLOBAL                     14: types
                        3662    LOAD_ATTR                       16: auth
                        3682    LOAD_ATTR                       54: SentCodeTypeSmsWord
                        3702    CALL                            2
                        3710    POP_JUMP_IF_FALSE               63 (to 3838)
                        3712    LOAD_GLOBAL                     3: NULL + Logs
                        3722    LOAD_ATTR                       4: PrintLog
                        3742    LOAD_FAST                       0: self
                        3744    LOAD_ATTR                       6: config
                        3764    LOAD_FAST                       0: self
                        3766    LOAD_ATTR                       8: account
                        3786    LOAD_FAST                       0: self
                        3788    LOAD_ATTR                       10: lang
                        3808    PUSH_NULL                       
                        3810    LOAD_CONST                      1: '__pyarmor_assert_15678__'
                        3812    LOAD_CONST                      27: 'reg_smsword_is_send'   # b'\x81\xf0\x1d\x14\x0c\xe9\xb3\xc1\x0c\xf5\x1f\xc4S\xe5\xeb\xba\x1cX\xb5\xa3'
                        3814    CALL                            1
                        3822    BINARY_SUBSCR                   
                        3826    KW_NAMES                        5: ('config', 'account', 'message')
                        3828    CALL                            3
                        3836    POP_TOP                         
                        3838    LOAD_FAST                       0: self
                        3840    LOAD_ATTR                       0: result
                        3860    LOAD_ATTR                       42: next_type
                        3880    POP_JUMP_IF_FALSE               673 (to 5230)
                        3884    LOAD_GLOBAL                     13: NULL + isinstance
                        3894    LOAD_FAST                       0: self
                        3896    LOAD_ATTR                       0: result
                        3916    LOAD_ATTR                       42: next_type
                        3936    LOAD_GLOBAL                     14: types
                        3946    LOAD_ATTR                       16: auth
                        3966    LOAD_ATTR                       56: CodeTypeCall
                        3986    CALL                            2
                        3994    POP_JUMP_IF_FALSE               70 (to 4136)
                        3996    LOAD_GLOBAL                     3: NULL + Logs
                        4006    LOAD_ATTR                       4: PrintLog
                        4026    LOAD_FAST                       0: self
                        4028    LOAD_ATTR                       6: config
                        4048    LOAD_FAST                       0: self
                        4050    LOAD_ATTR                       8: account
                        4070    LOAD_FAST                       0: self
                        4072    LOAD_ATTR                       10: lang
                        4092    PUSH_NULL                       
                        4094    LOAD_CONST                      1: '__pyarmor_assert_15678__'
                        4096    LOAD_CONST                      28: 'reg_available_call'   # b'\x81\xf0\x1d\x14\x0c\xfb\xa8\xd3\x12\xf6\x0c\xc2`\xe9\xc7\x86\x0eQ\xb7'
                        4098    CALL                            1
                        4106    BINARY_SUBSCR                   
                        4110    KW_NAMES                        5: ('config', 'account', 'message')
                        4112    CALL                            3
                        4120    POP_TOP                         
                        4122    LOAD_CONST                      11: 'voice'
                        4124    LOAD_FAST                       0: self
                        4126    STORE_ATTR                      10: resend_type
                        4136    LOAD_GLOBAL                     13: NULL + isinstance
                        4146    LOAD_FAST                       0: self
                        4148    LOAD_ATTR                       0: result
                        4168    LOAD_ATTR                       42: next_type
                        4188    LOAD_GLOBAL                     14: types
                        4198    LOAD_ATTR                       16: auth
                        4218    LOAD_ATTR                       58: CodeTypeFlashCall
                        4238    CALL                            2
                        4246    POP_JUMP_IF_FALSE               76 (to 4400)
                        4248    LOAD_GLOBAL                     3: NULL + Logs
                        4258    LOAD_ATTR                       4: PrintLog
                        4278    LOAD_FAST                       0: self
                        4280    LOAD_ATTR                       6: config
                        4300    LOAD_FAST                       0: self
                        4302    LOAD_ATTR                       8: account
                        4322    LOAD_FAST                       0: self
                        4324    LOAD_ATTR                       10: lang
                        4344    PUSH_NULL                       
                        4346    LOAD_CONST                      1: '__pyarmor_assert_15678__'
                        4348    LOAD_CONST                      29: 'reg_available_flashcall'   # b'\x81\xf0\x1d\x14\x0c\xfb\xa8\xd3\x12\xf6\x0c\xc2`\xe9\xc7\x83\x03\\\xa8\xaf\xa9\xcaB\xc0'
                        4350    CALL                            1
                        4358    BINARY_SUBSCR                   
                        4362    KW_NAMES                        5: ('config', 'account', 'message')
                        4364    CALL                            3
                        4372    POP_TOP                         
                        4374    PUSH_NULL                       
                        4376    LOAD_CONST                      1: '__pyarmor_assert_15678__'
                        4378    LOAD_CONST                      13: 'flashcall'   # b'\x81\xe4\x14\x12 \xf2\xbd\xd3\x17\xf6'
                        4380    CALL                            1
                        4388    LOAD_FAST                       0: self
                        4390    STORE_ATTR                      10: resend_type
                        4400    LOAD_GLOBAL                     13: NULL + isinstance
                        4410    LOAD_FAST                       0: self
                        4412    LOAD_ATTR                       0: result
                        4432    LOAD_ATTR                       42: next_type
                        4452    LOAD_GLOBAL                     14: types
                        4462    LOAD_ATTR                       16: auth
                        4482    LOAD_ATTR                       60: CodeTypeFragmentSms
                        4502    CALL                            2
                        4510    POP_JUMP_IF_FALSE               63 (to 4638)
                        4512    LOAD_GLOBAL                     3: NULL + Logs
                        4522    LOAD_ATTR                       4: PrintLog
                        4542    LOAD_FAST                       0: self
                        4544    LOAD_ATTR                       6: config
                        4564    LOAD_FAST                       0: self
                        4566    LOAD_ATTR                       8: account
                        4586    LOAD_FAST                       0: self
                        4588    LOAD_ATTR                       10: lang
                        4608    PUSH_NULL                       
                        4610    LOAD_CONST                      1: '__pyarmor_assert_15678__'
                        4612    LOAD_CONST                      30: 'reg_available_fragmentsms'   # b'\x81\xf0\x1d\x14\x0c\xfb\xa8\xd3\x12\xf6\x0c\xc2`\xe9\xc7\x83\x1d\\\xbc\xaa\xaf\xc5Z\xdf\x08|'
                        4614    CALL                            1
                        4622    BINARY_SUBSCR                   
                        4626    KW_NAMES                        5: ('config', 'account', 'message')
                        4628    CALL                            3
                        4636    POP_TOP                         
                        4638    LOAD_GLOBAL                     13: NULL + isinstance
                        4648    LOAD_FAST                       0: self
                        4650    LOAD_ATTR                       0: result
                        4670    LOAD_ATTR                       42: next_type
                        4690    LOAD_GLOBAL                     14: types
                        4700    LOAD_ATTR                       16: auth
                        4720    LOAD_ATTR                       62: CodeTypeMissedCall
                        4740    CALL                            2
                        4748    POP_JUMP_IF_FALSE               63 (to 4876)
                        4750    LOAD_GLOBAL                     3: NULL + Logs
                        4760    LOAD_ATTR                       4: PrintLog
                        4780    LOAD_FAST                       0: self
                        4782    LOAD_ATTR                       6: config
                        4802    LOAD_FAST                       0: self
                        4804    LOAD_ATTR                       8: account
                        4824    LOAD_FAST                       0: self
                        4826    LOAD_ATTR                       10: lang
                        4846    PUSH_NULL                       
                        4848    LOAD_CONST                      1: '__pyarmor_assert_15678__'
                        4850    LOAD_CONST                      31: 'reg_available_missedcall'   # b'\x81\xf0\x1d\x14\x0c\xfb\xa8\xd3\x12\xf6\x0c\xc2`\xe9\xc7\x88\x06N\xa8\xa2\xae\xc8O\xc0\t'
                        4852    CALL                            1
                        4860    BINARY_SUBSCR                   
                        4864    KW_NAMES                        5: ('config', 'account', 'message')
                        4866    CALL                            3
                        4874    POP_TOP                         
                        4876    LOAD_GLOBAL                     13: NULL + isinstance
                        4886    LOAD_FAST                       0: self
                        4888    LOAD_ATTR                       0: result
                        4908    LOAD_ATTR                       42: next_type
                        4928    LOAD_GLOBAL                     14: types
                        4938    LOAD_ATTR                       16: auth
                        4958    LOAD_ATTR                       64: CodeTypeSms
                        4978    CALL                            2
                        4986    POP_JUMP_IF_FALSE               70 (to 5128)
                        4988    LOAD_CONST                      9: 'sms'
                        4990    LOAD_FAST                       0: self
                        4992    STORE_ATTR                      10: resend_type
                        5002    LOAD_GLOBAL                     3: NULL + Logs
                        5012    LOAD_ATTR                       4: PrintLog
                        5032    LOAD_FAST                       0: self
                        5034    LOAD_ATTR                       6: config
                        5054    LOAD_FAST                       0: self
                        5056    LOAD_ATTR                       8: account
                        5076    LOAD_FAST                       0: self
                        5078    LOAD_ATTR                       10: lang
                        5098    PUSH_NULL                       
                        5100    LOAD_CONST                      1: '__pyarmor_assert_15678__'
                        5102    LOAD_CONST                      32: 'reg_available_sms'   # b'\x81\xf0\x1d\x14\x0c\xfb\xa8\xd3\x12\xf6\x0c\xc2`\xe9\xc7\x96\x02N'
                        5104    CALL                            1
                        5112    BINARY_SUBSCR                   
                        5116    KW_NAMES                        5: ('config', 'account', 'message')
                        5118    CALL                            3
                        5126    POP_TOP                         
                        5128    LOAD_FAST                       0: self
                        5130    LOAD_ATTR                       66: attempts
                        5150    LOAD_CONST                      10: 0
                        5152    COMPARE_OP                      92 (>=)
                        5156    POP_JUMP_IF_FALSE               25 (to 5208)
                        5158    LOAD_FAST                       0: self
                        5160    LOAD_ATTR                       69: _resend
                        5180    CALL                            0
                        5188    NOP                             
                        5190    NOP                             
                        5192    NOP                             
                        5194    JUMP_FORWARD                    111 (to 5418)
                        5196    CALL                            1
                        5204    POP_TOP                         
                        5206    RETURN_VALUE                    
                        5208    NOP                             
                        5210    LOAD_CONST                      8: False
                        5212    NOP                             
                        5214    NOP                             
                        5216    NOP                             
                        5218    JUMP_FORWARD                    99 (to 5418)
                        5226    POP_TOP                         
                        5228    RETURN_CONST                    8: False
                        5230    LOAD_FAST                       0: self
                        5232    LOAD_ATTR                       44: skip_appcode
                        5252    POP_JUMP_IF_FALSE               17 (to 5288)
                        5254    PUSH_NULL                       
                        5256    LOAD_CONST                      1: '__pyarmor_assert_15678__'
                        5258    LOAD_CONST                      20: 'APP_DEATH'   # b'\x81\xc3(#\x0c\xde\x9b\xf3/\xd2'
                        5260    CALL                            1
                        5268    NOP                             
                        5270    NOP                             
                        5272    NOP                             
                        5274    JUMP_FORWARD                    71 (to 5418)
                        5276    CALL                            1
                        5284    POP_TOP                         
                        5286    RETURN_VALUE                    
                        5288    LOAD_FAST                       0: self
                        5290    LOAD_ATTR                       66: attempts
                        5310    LOAD_CONST                      10: 0
                        5312    COMPARE_OP                      26 (<=)
                        5316    POP_JUMP_IF_FALSE               11 (to 5340)
                        5318    NOP                             
                        5320    LOAD_CONST                      8: False
                        5322    NOP                             
                        5324    NOP                             
                        5326    NOP                             
                        5328    JUMP_FORWARD                    44 (to 5418)
                        5336    POP_TOP                         
                        5338    RETURN_CONST                    8: False
                        5340    LOAD_FAST                       0: self
                        5342    LOAD_ATTR                       69: _resend
                        5362    CALL                            0
                        5370    NOP                             
                        5372    NOP                             
                        5374    NOP                             
                        5376    JUMP_FORWARD                    20 (to 5418)
                        5378    CALL                            1
                        5386    POP_TOP                         
                        5388    RETURN_VALUE                    
                        5390    PUSH_EXC_INFO                   
                        5392    PUSH_NULL                       
                        5394    LOAD_CONST                      7: '__pyarmor_exit_15680__'
                        5396    NOP                             
                        5398    LOAD_CONST                      3: b'<COAddr>\x05\x00\x00\x1a\xf4\x14\x00\x00\x00\x00\x00\x00\x00\x00\x00\x00\x00\x00\x00\x00'
                        5400    CALL                            1
                        5408    POP_TOP                         
                        5410    RERAISE                         0
                        5412    COPY                            3
                        5414    POP_EXCEPT                      
                        5416    RERAISE                         1
                        5418    PUSH_NULL                       
                        5420    LOAD_CONST                      7: '__pyarmor_exit_15680__'
                        5422    LOAD_CONST                      3: b'<COAddr>\x05\x00\x00\x1a\xf4\x14\x00\x00\x00\x00\x00\x00\x00\x00\x00\x00\x00\x00\x00\x00'
                        5424    BUILD_TUPLE                     1
                        5426    CALL_FUNCTION_EX                0
                        5428    POP_TOP                         
                        5430    RETURN_VALUE                    
                    [Exception Table]
                        28 to 396 -> 5390 [0] 
                        418 to 628 -> 5390 [0] 
                        648 to 938 -> 5390 [0] 
                        958 to 1256 -> 5390 [0] 
                        1276 to 1564 -> 5390 [0] 
                        1584 to 1872 -> 5390 [0] 
                        1892 to 2160 -> 5390 [0] 
                        2180 to 2476 -> 5390 [0] 
                        2496 to 2520 -> 5390 [0] 
                        2542 to 2842 -> 5390 [0] 
                        2864 to 3102 -> 5390 [0] 
                        3124 to 5188 -> 5390 [0] 
                        5230 to 5268 -> 5390 [0] 
                        5288 to 5318 -> 5390 [0] 
                        5340 to 5370 -> 5390 [0] 
                        5390 to 5412 -> 5412 [1] lasti
                [Code]
                    File Name: <frozen program.modules.func.registrator.send_code_new>
                    Object Name: _send_firebase
                    Qualified Name: TelegramSendCode._send_firebase
                    Arg Count: 1
                    Pos Only Arg Count: 0
                    KW Only Arg Count: 0
                    Stack Size: 8
                    Flags: 0x20000003 (CO_OPTIMIZED | CO_NEWLOCALS | CO_PYARMOR_OBFUSCATED)
                    [Names]
                        'client'
                        'functions'
                        'auth'
                        'RequestFirebaseSmsRequest'
                        'account'
                        'result'
                        'phone_code_hash'
                        'StopProgram'
                    [Locals+Names]
                        'self'
                        '__assert_armored__'
                        '_var_var_2'
                    [Constants]
                        None
                        '__pyarmor_assert_15681__'
                        '__pyarmor_enter_15682__'
                        b'<COAddr>\x05\x00\x00\x1a\xf2\x00\x00\x00\x00\x00\x00\x00\x00\x00\x00\x00\x00\x00\x00\x00'
                        ' '
                        (
                            'phone_number'
                            'phone_code_hash'
                            'safety_net_token'
                            'ios_push_secret'
                        )
                        '__pyarmor_exit_15683__'
                    [Disassembly]
                        0       NOP                             
                        2       NOP                             
                        4       PUSH_NULL                       
                        6       LOAD_CONST                      2: '__pyarmor_enter_15682__'
                        8       LOAD_CONST                      3: b'<COAddr>\x05\x00\x00\x1a\xf2\x00\x00\x00\x00\x00\x00\x00\x00\x00\x00\x00\x00\x00\x00\x00'
                        10      BUILD_TUPLE                     1
                        12      CALL_FUNCTION_EX                0
                        14      POP_TOP                         
                        16      RESUME                          0
                        18      NOP                             
                        20      NOP                             
                        22      NOP                             
                        24      NOP                             
                        26      NOP                             
                        28      NOP                             
                        30      LOAD_CONST                      4: ' '
                        32      STORE_FAST                      2: _var_var_2
                        34      LOAD_FAST                       0: self
                        36      LOAD_ATTR                       1: client
                        56      LOAD_GLOBAL                     2: functions
                        66      LOAD_ATTR                       4: auth
                        86      LOAD_ATTR                       7: RequestFirebaseSmsRequest
                        106     LOAD_FAST                       0: self
                        108     LOAD_ATTR                       8: account
                        128     LOAD_FAST                       0: self
                        130     LOAD_ATTR                       10: result
                        150     LOAD_ATTR                       12: phone_code_hash
                        170     LOAD_FAST                       2: _var_var_2
                        172     LOAD_CONST                      0: None
                        174     KW_NAMES                        5: ('phone_number', 'phone_code_hash', 'safety_net_token', 'ios_push_secret')
                        176     CALL                            4
                        184     CALL                            1
                        192     POP_TOP                         
                        194     LOAD_FAST                       0: self
                        196     LOAD_ATTR                       10: result
                        216     NOP                             
                        218     NOP                             
                        220     NOP                             
                        222     JUMP_FORWARD                    36 (to 296)
                        224     CALL                            1
                        232     POP_TOP                         
                        234     RETURN_VALUE                    
                        236     PUSH_EXC_INFO                   
                        238     LOAD_GLOBAL                     14: StopProgram
                        248     CHECK_EXC_MATCH                 
                        250     POP_JUMP_IF_FALSE               2 (to 256)
                        252     POP_TOP                         
                        254     RAISE_VARARGS                   0
                        256     POP_TOP                         
                        258     POP_EXCEPT                      
                        260     JUMP_BACKWARD                   34 (to 194)
                        262     COPY                            3
                        264     POP_EXCEPT                      
                        266     RERAISE                         1
                        268     PUSH_EXC_INFO                   
                        270     PUSH_NULL                       
                        272     LOAD_CONST                      6: '__pyarmor_exit_15683__'
                        274     NOP                             
                        276     LOAD_CONST                      3: b'<COAddr>\x05\x00\x00\x1a\xf2\x00\x00\x00\x00\x00\x00\x00\x00\x00\x00\x00\x00\x00\x00\x00'
                        278     CALL                            1
                        286     POP_TOP                         
                        288     RERAISE                         0
                        290     COPY                            3
                        292     POP_EXCEPT                      
                        294     RERAISE                         1
                        296     PUSH_NULL                       
                        298     LOAD_CONST                      6: '__pyarmor_exit_15683__'
                        300     LOAD_CONST                      3: b'<COAddr>\x05\x00\x00\x1a\xf2\x00\x00\x00\x00\x00\x00\x00\x00\x00\x00\x00\x00\x00\x00\x00'
                        302     BUILD_TUPLE                     1
                        304     CALL_FUNCTION_EX                0
                        306     POP_TOP                         
                        308     RETURN_VALUE                    
                    [Exception Table]
                        30 to 194 -> 236 [0] 
                        194 to 216 -> 268 [0] 
                        236 to 258 -> 262 [1] lasti
                        258 to 268 -> 268 [0] 
                        268 to 290 -> 290 [1] lasti
                [Code]
                    File Name: <frozen program.modules.func.registrator.send_code_new>
                    Object Name: _send_email
                    Qualified Name: TelegramSendCode._send_email
                    Arg Count: 1
                    Pos Only Arg Count: 0
                    KW Only Arg Count: 0
                    Stack Size: 9
                    Flags: 0x20000003 (CO_OPTIMIZED | CO_NEWLOCALS | CO_PYARMOR_OBFUSCATED)
                    [Names]
                        'reg_email'
                        'Logs'
                        'PrintLog'
                        'config'
                        'account'
                        'lang'
                        'api_temp_mail'
                        'get_email'
                        'split'
                        'id'
                        'gauth'
                        'client'
                        'functions'
                        'SendVerifyEmailCodeRequest'
                        'types'
                        'EmailVerifyPurposeLoginSetup'
                        'result'
                        'phone_code_hash'
                        'time'
                        'sleep'
                        'get_email_code'
                        'random'
                        'randint'
                        'EmailVerificationCode'
                        'EmailVerificationGoogle'
                        'gtoken'
                        'VerifyEmailRequest'
                        'errors'
                        'BadRequestError'
                        'ban_email'
                        'start'
                        'CodeInvalidError'
                        'Exception'
                        'sent_code'
                        '_check'
                        'StopProgram'
                        'logging'
                    [Locals+Names]
                        'self'
                        '__assert_armored__'
                        '_var_var_3'
                        '_var_var_4'
                        '_var_var_5'
                        '_var_var_6'
                        '_var_var_7'
                        '_var_var_0'
                    [Constants]
                        None
                        '__pyarmor_assert_15684__'
                        '__pyarmor_enter_15685__'
                        b'<COAddr>\x07\x00\x00\x1a<\x0c\x00\x00\x00\x00\x00\x00\x00\x00\x00\x00\x00\x00\x00\x00'
                        'reg_get_mail'   # b'\x81\xf0\x1d\x14\x0c\xfd\xbb\xc6$\xf7\x0c\xc9`'
                        (
                            'config'
                            'account'
                            'message'
                        )
                        'reg_mail_exhausted'   # b'\x81\xf0\x1d\x14\x0c\xf7\xbf\xdb\x17\xc5\x08\xd8d\xed\xed\x96\x1bX\xbf'
                        '__pyarmor_exit_15686__'
                        False
                        'stock_empty'   # b'\x81\xf1\x0c\x1c0\xf1\x81\xd7\x16\xea\x19\xd9'
                        'reg_mail_stock_empty'   # b'\x81\xf0\x1d\x14\x0c\xf7\xbf\xdb\x17\xc5\x1e\xd4c\xef\xf3\xba\nP\xab\xb3\xb3'
                        '@'
                        1
                        'Email: '
                        ' RegID: '
                        'reg_email_code'   # b'\x81\xf0\x1d\x14\x0c\xff\xb3\xd3\x12\xf62\xc3c\xe8\xfd'
                        (
                            'phone_number'
                            'phone_code_hash'
                        )
                        (
                            'purpose'
                            'email'
                        )
                        'reg_mail_code_is_send'   # b'\x81\xf0\x1d\x14\x0c\xf7\xbf\xdb\x17\xc5\x0e\xcfh\xe9\xc7\x8c\x1cb\xa8\xa2\xa4\xcf'
                        (
                            'config'
                            'account'
                            'message'
                            'end'
                        )
                        10
                        'reg_mail_code_not_found'   # b'\x81\xf0\x1d\x14\x0c\xf7\xbf\xdb\x17\xc5\x0e\xcfh\xe9\xc7\x8b\x00I\x84\xa1\xa5\xde@\xc8'
                        'reg_mail_code'   # b'\x81\xf0\x1d\x14\x0c\xf7\xbf\xdb\x17\xc5\x0e\xcfh\xe9'
                        7
                        (
                            'code'
                        )
                        'reg_email_gauth'   # b'\x81\xf0\x1d\x14\x0c\xff\xb3\xd3\x12\xf62\xc7m\xf9\xec\x8d'
                        (
                            'token'
                        )
                        (
                            'purpose'
                            'verification'
                        )
                        'reg_mail_ban'   # b'\x81\xf0\x1d\x14\x0c\xf7\xbf\xdb\x17\xc5\x0f\xc1b'
                        'reg_mail_code_invalid'   # b'\x81\xf0\x1d\x14\x0c\xf7\xbf\xdb\x17\xc5\x0e\xcfh\xe9\xc7\x8c\x01K\xba\xab\xa3\xcf'
                        'reg_mail_confirmed'   # b'\x81\xf0\x1d\x14\x0c\xf7\xbf\xdb\x17\xc5\x0e\xcfb\xea\xf1\x97\x02X\xbf'
                        'reg_mail_false'   # b'\x81\xf0\x1d\x14\x0c\xf7\xbf\xdb\x17\xc5\x0b\xc1`\xff\xfd'
                    [Disassembly]
                        0       NOP                             
                        2       NOP                             
                        4       PUSH_NULL                       
                        6       LOAD_CONST                      2: '__pyarmor_enter_15685__'
                        8       LOAD_CONST                      3: b'<COAddr>\x07\x00\x00\x1a<\x0c\x00\x00\x00\x00\x00\x00\x00\x00\x00\x00\x00\x00\x00\x00'
                        10      BUILD_TUPLE                     1
                        12      CALL_FUNCTION_EX                0
                        14      POP_TOP                         
                        16      RESUME                          0
                        18      NOP                             
                        20      NOP                             
                        22      NOP                             
                        24      NOP                             
                        26      NOP                             
                        28      NOP                             
                        30      LOAD_FAST                       0: self
                        32      LOAD_ATTR                       0: reg_email
                        52      POP_JUMP_IF_FALSE               1155 (to 2366)
                        56      LOAD_GLOBAL                     3: NULL + Logs
                        66      LOAD_ATTR                       4: PrintLog
                        86      LOAD_FAST                       0: self
                        88      LOAD_ATTR                       6: config
                        108     LOAD_FAST                       0: self
                        110     LOAD_ATTR                       8: account
                        130     LOAD_FAST                       0: self
                        132     LOAD_ATTR                       10: lang
                        152     PUSH_NULL                       
                        154     LOAD_CONST                      1: '__pyarmor_assert_15684__'
                        156     LOAD_CONST                      4: 'reg_get_mail'   # b'\x81\xf0\x1d\x14\x0c\xfd\xbb\xc6$\xf7\x0c\xc9`'
                        158     CALL                            1
                        166     BINARY_SUBSCR                   
                        170     KW_NAMES                        5: ('config', 'account', 'message')
                        172     CALL                            3
                        180     POP_TOP                         
                        182     LOAD_FAST                       0: self
                        184     LOAD_ATTR                       12: api_temp_mail
                        204     LOAD_ATTR                       15: get_email
                        224     CALL                            0
                        232     STORE_FAST                      2: _var_var_3
                        234     LOAD_FAST                       2: _var_var_3
                        236     POP_JUMP_IF_NOT_NONE            74 (to 386)
                        238     LOAD_GLOBAL                     3: NULL + Logs
                        248     LOAD_ATTR                       4: PrintLog
                        268     LOAD_FAST                       0: self
                        270     LOAD_ATTR                       6: config
                        290     LOAD_FAST                       0: self
                        292     LOAD_ATTR                       8: account
                        312     LOAD_FAST                       0: self
                        314     LOAD_ATTR                       10: lang
                        334     PUSH_NULL                       
                        336     LOAD_CONST                      1: '__pyarmor_assert_15684__'
                        338     LOAD_CONST                      6: 'reg_mail_exhausted'   # b'\x81\xf0\x1d\x14\x0c\xf7\xbf\xdb\x17\xc5\x08\xd8d\xed\xed\x96\x1bX\xbf'
                        340     CALL                            1
                        348     BINARY_SUBSCR                   
                        352     KW_NAMES                        5: ('config', 'account', 'message')
                        354     CALL                            3
                        362     POP_TOP                         
                        364     NOP                             
                        366     LOAD_CONST                      8: False
                        368     NOP                             
                        370     NOP                             
                        372     JUMP_FORWARD                    1405 (to 3186)
                        382     POP_TOP                         
                        384     RETURN_CONST                    8: False
                        386     LOAD_FAST                       2: _var_var_3
                        388     PUSH_NULL                       
                        390     LOAD_CONST                      1: '__pyarmor_assert_15684__'
                        392     LOAD_CONST                      9: 'stock_empty'   # b'\x81\xf1\x0c\x1c0\xf1\x81\xd7\x16\xea\x19\xd9'
                        394     CALL                            1
                        402     COMPARE_OP                      40 (==)
                        406     POP_JUMP_IF_FALSE               74 (to 556)
                        408     LOAD_GLOBAL                     3: NULL + Logs
                        418     LOAD_ATTR                       4: PrintLog
                        438     LOAD_FAST                       0: self
                        440     LOAD_ATTR                       6: config
                        460     LOAD_FAST                       0: self
                        462     LOAD_ATTR                       8: account
                        482     LOAD_FAST                       0: self
                        484     LOAD_ATTR                       10: lang
                        504     PUSH_NULL                       
                        506     LOAD_CONST                      1: '__pyarmor_assert_15684__'
                        508     LOAD_CONST                      10: 'reg_mail_stock_empty'   # b'\x81\xf0\x1d\x14\x0c\xf7\xbf\xdb\x17\xc5\x1e\xd4c\xef\xf3\xba\nP\xab\xb3\xb3'
                        510     CALL                            1
                        518     BINARY_SUBSCR                   
                        522     KW_NAMES                        5: ('config', 'account', 'message')
                        524     CALL                            3
                        532     POP_TOP                         
                        534     NOP                             
                        536     LOAD_CONST                      8: False
                        538     NOP                             
                        540     NOP                             
                        542     JUMP_FORWARD                    1320 (to 3186)
                        552     POP_TOP                         
                        554     RETURN_CONST                    8: False
                        556     LOAD_FAST                       2: _var_var_3
                        558     LOAD_ATTR                       17: split
                        578     LOAD_CONST                      11: '@'
                        580     CALL                            1
                        588     LOAD_CONST                      12: 1
                        590     BINARY_SUBSCR                   
                        594     STORE_FAST                      3: _var_var_4
                        596     LOAD_GLOBAL                     3: NULL + Logs
                        606     LOAD_ATTR                       4: PrintLog
                        626     LOAD_FAST                       0: self
                        628     LOAD_ATTR                       6: config
                        648     LOAD_FAST                       0: self
                        650     LOAD_ATTR                       8: account
                        670     LOAD_CONST                      13: 'Email: '
                        672     LOAD_FAST                       3: _var_var_4
                        674     FORMAT_VALUE                    0 (FVC_NONE)
                        676     LOAD_CONST                      14: ' RegID: '
                        678     LOAD_FAST                       0: self
                        680     LOAD_ATTR                       12: api_temp_mail
                        700     LOAD_ATTR                       18: id
                        720     FORMAT_VALUE                    0 (FVC_NONE)
                        722     BUILD_STRING                    4
                        724     KW_NAMES                        5: ('config', 'account', 'message')
                        726     CALL                            3
                        734     POP_TOP                         
                        736     LOAD_FAST                       0: self
                        738     LOAD_ATTR                       12: api_temp_mail
                        758     LOAD_ATTR                       20: gauth
                        778     LOAD_CONST                      8: False
                        780     COMPARE_OP                      40 (==)
                        784     POP_JUMP_IF_FALSE               478 (to 1744)
                        788     LOAD_GLOBAL                     3: NULL + Logs
                        798     LOAD_ATTR                       4: PrintLog
                        818     LOAD_FAST                       0: self
                        820     LOAD_ATTR                       6: config
                        840     LOAD_FAST                       0: self
                        842     LOAD_ATTR                       8: account
                        862     LOAD_FAST                       0: self
                        864     LOAD_ATTR                       10: lang
                        884     PUSH_NULL                       
                        886     LOAD_CONST                      1: '__pyarmor_assert_15684__'
                        888     LOAD_CONST                      15: 'reg_email_code'   # b'\x81\xf0\x1d\x14\x0c\xff\xb3\xd3\x12\xf62\xc3c\xe8\xfd'
                        890     CALL                            1
                        898     BINARY_SUBSCR                   
                        902     KW_NAMES                        5: ('config', 'account', 'message')
                        904     CALL                            3
                        912     POP_TOP                         
                        914     LOAD_FAST                       0: self
                        916     LOAD_ATTR                       23: client
                        936     LOAD_GLOBAL                     24: functions
                        946     LOAD_ATTR                       8: account
                        966     LOAD_ATTR                       27: SendVerifyEmailCodeRequest
                        986     LOAD_GLOBAL                     29: NULL + types
                        996     LOAD_ATTR                       30: EmailVerifyPurposeLoginSetup
                        1016    LOAD_FAST                       0: self
                        1018    LOAD_ATTR                       8: account
                        1038    LOAD_FAST                       0: self
                        1040    LOAD_ATTR                       32: result
                        1060    LOAD_ATTR                       34: phone_code_hash
                        1080    KW_NAMES                        16: ('phone_number', 'phone_code_hash')
                        1082    CALL                            2
                        1090    LOAD_FAST                       2: _var_var_3
                        1092    KW_NAMES                        17: ('purpose', 'email')
                        1094    CALL                            2
                        1102    CALL                            1
                        1110    STORE_FAST                      4: _var_var_5
                        1112    LOAD_GLOBAL                     3: NULL + Logs
                        1122    LOAD_ATTR                       4: PrintLog
                        1142    LOAD_FAST                       0: self
                        1144    LOAD_ATTR                       6: config
                        1164    LOAD_FAST                       0: self
                        1166    LOAD_ATTR                       8: account
                        1186    LOAD_FAST                       0: self
                        1188    LOAD_ATTR                       10: lang
                        1208    PUSH_NULL                       
                        1210    LOAD_CONST                      1: '__pyarmor_assert_15684__'
                        1212    LOAD_CONST                      18: 'reg_mail_code_is_send'   # b'\x81\xf0\x1d\x14\x0c\xf7\xbf\xdb\x17\xc5\x0e\xcfh\xe9\xc7\x8c\x1cb\xa8\xa2\xa4\xcf'
                        1214    CALL                            1
                        1222    BINARY_SUBSCR                   
                        1226    LOAD_FAST                       3: _var_var_4
                        1228    KW_NAMES                        19: ('config', 'account', 'message', 'end')
                        1230    CALL                            4
                        1238    POP_TOP                         
                        1240    LOAD_GLOBAL                     37: NULL + time
                        1250    LOAD_ATTR                       38: sleep
                        1270    LOAD_CONST                      20: 10
                        1272    CALL                            1
                        1280    POP_TOP                         
                        1282    LOAD_FAST                       0: self
                        1284    LOAD_ATTR                       12: api_temp_mail
                        1304    LOAD_ATTR                       41: get_email_code
                        1324    CALL                            0
                        1332    STORE_FAST                      5: _var_var_6
                        1334    LOAD_FAST                       5: _var_var_6
                        1336    POP_JUMP_IF_NOT_NONE            75 (to 1488)
                        1338    LOAD_GLOBAL                     3: NULL + Logs
                        1348    LOAD_ATTR                       4: PrintLog
                        1368    LOAD_FAST                       0: self
                        1370    LOAD_ATTR                       6: config
                        1390    LOAD_FAST                       0: self
                        1392    LOAD_ATTR                       8: account
                        1412    LOAD_FAST                       0: self
                        1414    LOAD_ATTR                       10: lang
                        1434    PUSH_NULL                       
                        1436    LOAD_CONST                      1: '__pyarmor_assert_15684__'
                        1438    LOAD_CONST                      21: 'reg_mail_code_not_found'   # b'\x81\xf0\x1d\x14\x0c\xf7\xbf\xdb\x17\xc5\x0e\xcfh\xe9\xc7\x8b\x00I\x84\xa1\xa5\xde@\xc8'
                        1440    CALL                            1
                        1448    BINARY_SUBSCR                   
                        1452    LOAD_FAST                       3: _var_var_4
                        1454    KW_NAMES                        19: ('config', 'account', 'message', 'end')
                        1456    CALL                            4
                        1464    POP_TOP                         
                        1466    NOP                             
                        1468    LOAD_CONST                      8: False
                        1470    NOP                             
                        1472    NOP                             
                        1474    JUMP_FORWARD                    854 (to 3186)
                        1484    POP_TOP                         
                        1486    RETURN_CONST                    8: False
                        1488    LOAD_GLOBAL                     3: NULL + Logs
                        1498    LOAD_ATTR                       4: PrintLog
                        1518    LOAD_FAST                       0: self
                        1520    LOAD_ATTR                       6: config
                        1540    LOAD_FAST                       0: self
                        1542    LOAD_ATTR                       8: account
                        1562    LOAD_FAST                       0: self
                        1564    LOAD_ATTR                       10: lang
                        1584    PUSH_NULL                       
                        1586    LOAD_CONST                      1: '__pyarmor_assert_15684__'
                        1588    LOAD_CONST                      22: 'reg_mail_code'   # b'\x81\xf0\x1d\x14\x0c\xf7\xbf\xdb\x17\xc5\x0e\xcfh\xe9'
                        1590    CALL                            1
                        1598    BINARY_SUBSCR                   
                        1602    LOAD_FAST                       5: _var_var_6
                        1604    KW_NAMES                        19: ('config', 'account', 'message', 'end')
                        1606    CALL                            4
                        1614    POP_TOP                         
                        1616    LOAD_GLOBAL                     37: NULL + time
                        1626    LOAD_ATTR                       38: sleep
                        1646    LOAD_GLOBAL                     43: NULL + random
                        1656    LOAD_ATTR                       44: randint
                        1676    LOAD_CONST                      12: 1
                        1678    LOAD_CONST                      23: 7
                        1680    CALL                            2
                        1688    CALL                            1
                        1696    POP_TOP                         
                        1698    LOAD_GLOBAL                     29: NULL + types
                        1708    LOAD_ATTR                       46: EmailVerificationCode
                        1728    LOAD_FAST                       5: _var_var_6
                        1730    KW_NAMES                        24: ('code',)
                        1732    CALL                            1
                        1740    STORE_FAST                      6: _var_var_7
                        1742    JUMP_FORWARD                    105 (to 1954)
                        1744    LOAD_GLOBAL                     3: NULL + Logs
                        1754    LOAD_ATTR                       4: PrintLog
                        1774    LOAD_FAST                       0: self
                        1776    LOAD_ATTR                       6: config
                        1796    LOAD_FAST                       0: self
                        1798    LOAD_ATTR                       8: account
                        1818    LOAD_FAST                       0: self
                        1820    LOAD_ATTR                       10: lang
                        1840    PUSH_NULL                       
                        1842    LOAD_CONST                      1: '__pyarmor_assert_15684__'
                        1844    LOAD_CONST                      25: 'reg_email_gauth'   # b'\x81\xf0\x1d\x14\x0c\xff\xb3\xd3\x12\xf62\xc7m\xf9\xec\x8d'
                        1846    CALL                            1
                        1854    BINARY_SUBSCR                   
                        1858    KW_NAMES                        5: ('config', 'account', 'message')
                        1860    CALL                            3
                        1868    POP_TOP                         
                        1870    LOAD_GLOBAL                     29: NULL + types
                        1880    LOAD_ATTR                       48: EmailVerificationGoogle
                        1900    LOAD_FAST                       0: self
                        1902    LOAD_ATTR                       12: api_temp_mail
                        1922    LOAD_ATTR                       50: gtoken
                        1942    KW_NAMES                        26: ('token',)
                        1944    CALL                            1
                        1952    STORE_FAST                      6: _var_var_7
                        1954    NOP                             
                        1956    LOAD_FAST                       0: self
                        1958    LOAD_ATTR                       23: client
                        1978    LOAD_GLOBAL                     24: functions
                        1988    LOAD_ATTR                       8: account
                        2008    LOAD_ATTR                       53: VerifyEmailRequest
                        2028    LOAD_GLOBAL                     29: NULL + types
                        2038    LOAD_ATTR                       30: EmailVerifyPurposeLoginSetup
                        2058    LOAD_FAST                       0: self
                        2060    LOAD_ATTR                       8: account
                        2080    LOAD_FAST                       0: self
                        2082    LOAD_ATTR                       32: result
                        2102    LOAD_ATTR                       34: phone_code_hash
                        2122    KW_NAMES                        16: ('phone_number', 'phone_code_hash')
                        2124    CALL                            2
                        2132    LOAD_FAST                       6: _var_var_7
                        2134    KW_NAMES                        27: ('purpose', 'verification')
                        2136    CALL                            2
                        2144    CALL                            1
                        2152    STORE_FAST                      4: _var_var_5
                        2154    LOAD_GLOBAL                     3: NULL + Logs
                        2164    LOAD_ATTR                       4: PrintLog
                        2184    LOAD_FAST                       0: self
                        2186    LOAD_ATTR                       6: config
                        2206    LOAD_FAST                       0: self
                        2208    LOAD_ATTR                       8: account
                        2228    LOAD_FAST                       0: self
                        2230    LOAD_ATTR                       10: lang
                        2250    PUSH_NULL                       
                        2252    LOAD_CONST                      1: '__pyarmor_assert_15684__'
                        2254    LOAD_CONST                      30: 'reg_mail_confirmed'   # b'\x81\xf0\x1d\x14\x0c\xf7\xbf\xdb\x17\xc5\x0e\xcfb\xea\xf1\x97\x02X\xbf'
                        2256    CALL                            1
                        2264    BINARY_SUBSCR                   
                        2268    LOAD_FAST                       3: _var_var_4
                        2270    KW_NAMES                        19: ('config', 'account', 'message', 'end')
                        2272    CALL                            4
                        2280    POP_TOP                         
                        2282    LOAD_FAST                       4: _var_var_5
                        2284    LOAD_ATTR                       66: sent_code
                        2304    LOAD_FAST                       0: self
                        2306    STORE_ATTR                      16: result
                        2316    LOAD_FAST                       0: self
                        2318    LOAD_ATTR                       69: _check
                        2338    CALL                            0
                        2346    NOP                             
                        2348    NOP                             
                        2350    JUMP_FORWARD                    416 (to 3186)
                        2354    CALL                            1
                        2362    POP_TOP                         
                        2364    RETURN_VALUE                    
                        2366    NOP                             
                        2368    LOAD_CONST                      0: None
                        2370    NOP                             
                        2372    NOP                             
                        2374    JUMP_FORWARD                    404 (to 3186)
                        2384    POP_TOP                         
                        2386    RETURN_CONST                    0: None
                        2388    PUSH_EXC_INFO                   
                        2390    LOAD_GLOBAL                     54: errors
                        2400    LOAD_ATTR                       56: BadRequestError
                        2420    CHECK_EXC_MATCH                 
                        2422    POP_JUMP_IF_FALSE               118 (to 2660)
                        2424    POP_TOP                         
                        2426    LOAD_GLOBAL                     3: NULL + Logs
                        2436    LOAD_ATTR                       4: PrintLog
                        2456    LOAD_FAST                       0: self
                        2458    LOAD_ATTR                       6: config
                        2478    LOAD_FAST                       0: self
                        2480    LOAD_ATTR                       8: account
                        2500    LOAD_FAST                       0: self
                        2502    LOAD_ATTR                       10: lang
                        2522    PUSH_NULL                       
                        2524    LOAD_CONST                      1: '__pyarmor_assert_15684__'
                        2526    LOAD_CONST                      28: 'reg_mail_ban'   # b'\x81\xf0\x1d\x14\x0c\xf7\xbf\xdb\x17\xc5\x0f\xc1b'
                        2528    CALL                            1
                        2536    BINARY_SUBSCR                   
                        2540    LOAD_FAST                       3: _var_var_4
                        2542    KW_NAMES                        19: ('config', 'account', 'message', 'end')
                        2544    CALL                            4
                        2552    POP_TOP                         
                        2554    LOAD_FAST                       0: self
                        2556    LOAD_ATTR                       12: api_temp_mail
                        2576    LOAD_ATTR                       59: ban_email
                        2596    CALL                            0
                        2604    POP_TOP                         
                        2606    LOAD_FAST                       0: self
                        2608    LOAD_ATTR                       61: start
                        2628    CALL                            0
                        2636    SWAP                            2
                        2638    POP_EXCEPT                      
                        2640    NOP                             
                        2642    NOP                             
                        2644    JUMP_FORWARD                    269 (to 3186)
                        2648    CALL                            1
                        2656    POP_TOP                         
                        2658    RETURN_VALUE                    
                        2660    LOAD_GLOBAL                     54: errors
                        2670    LOAD_ATTR                       62: CodeInvalidError
                        2690    CHECK_EXC_MATCH                 
                        2692    POP_JUMP_IF_FALSE               91 (to 2876)
                        2694    POP_TOP                         
                        2696    LOAD_GLOBAL                     3: NULL + Logs
                        2706    LOAD_ATTR                       4: PrintLog
                        2726    LOAD_FAST                       0: self
                        2728    LOAD_ATTR                       6: config
                        2748    LOAD_FAST                       0: self
                        2750    LOAD_ATTR                       8: account
                        2770    LOAD_FAST                       0: self
                        2772    LOAD_ATTR                       10: lang
                        2792    PUSH_NULL                       
                        2794    LOAD_CONST                      1: '__pyarmor_assert_15684__'
                        2796    LOAD_CONST                      29: 'reg_mail_code_invalid'   # b'\x81\xf0\x1d\x14\x0c\xf7\xbf\xdb\x17\xc5\x0e\xcfh\xe9\xc7\x8c\x01K\xba\xab\xa3\xcf'
                        2798    CALL                            1
                        2806    BINARY_SUBSCR                   
                        2810    KW_NAMES                        5: ('config', 'account', 'message')
                        2812    CALL                            3
                        2820    POP_TOP                         
                        2822    LOAD_FAST                       0: self
                        2824    LOAD_ATTR                       61: start
                        2844    CALL                            0
                        2852    SWAP                            2
                        2854    POP_EXCEPT                      
                        2856    NOP                             
                        2858    NOP                             
                        2860    NOP                             
                        2862    JUMP_FORWARD                    161 (to 3186)
                        2864    CALL                            1
                        2872    POP_TOP                         
                        2874    RETURN_VALUE                    
                        2876    LOAD_GLOBAL                     64: Exception
                        2886    CHECK_EXC_MATCH                 
                        2888    POP_JUMP_IF_FALSE               35 (to 2960)
                        2890    STORE_FAST                      7: _var_var_0
                        2892    LOAD_FAST                       0: self
                        2894    LOAD_ATTR                       61: start
                        2914    CALL                            0
                        2922    SWAP                            2
                        2924    POP_EXCEPT                      
                        2926    LOAD_CONST                      0: None
                        2928    STORE_FAST                      7: _var_var_0
                        2930    DELETE_FAST                     7: _var_var_0
                        2932    NOP                             
                        2934    NOP                             
                        2936    NOP                             
                        2938    JUMP_FORWARD                    123 (to 3186)
                        2940    CALL                            1
                        2948    POP_TOP                         
                        2950    RETURN_VALUE                    
                        2952    LOAD_CONST                      0: None
                        2954    STORE_FAST                      7: _var_var_0
                        2956    DELETE_FAST                     7: _var_var_0
                        2958    RERAISE                         1
                        2960    RERAISE                         0
                        2962    COPY                            3
                        2964    POP_EXCEPT                      
                        2966    RERAISE                         1
                        2968    PUSH_EXC_INFO                   
                        2970    LOAD_GLOBAL                     70: StopProgram
                        2980    CHECK_EXC_MATCH                 
                        2982    POP_JUMP_IF_FALSE               2 (to 2988)
                        2984    POP_TOP                         
                        2986    RAISE_VARARGS                   0
                        2988    LOAD_GLOBAL                     64: Exception
                        2998    CHECK_EXC_MATCH                 
                        3000    POP_JUMP_IF_FALSE               74 (to 3150)
                        3002    STORE_FAST                      7: _var_var_0
                        3004    PUSH_NULL                       
                        3006    LOAD_GLOBAL                     73: NULL + logging
                        3016    LOAD_FAST                       7: _var_var_0
                        3018    CALL                            1
                        3026    PUSH_NULL                       
                        3028    LOAD_CONST                      1: '__pyarmor_assert_15684__'
                        3030    LOAD_CONST                      31: 'reg_mail_false'   # b'\x81\xf0\x1d\x14\x0c\xf7\xbf\xdb\x17\xc5\x0b\xc1`\xff\xfd'
                        3032    CALL                            1
                        3040    CALL                            1
                        3048    POP_TOP                         
                        3050    LOAD_GLOBAL                     3: NULL + Logs
                        3060    LOAD_ATTR                       4: PrintLog
                        3080    LOAD_FAST                       0: self
                        3082    LOAD_ATTR                       6: config
                        3102    LOAD_FAST                       0: self
                        3104    LOAD_ATTR                       8: account
                        3124    LOAD_FAST                       7: _var_var_0
                        3126    KW_NAMES                        5: ('config', 'account', 'message')
                        3128    CALL                            3
                        3136    POP_TOP                         
                        3138    LOAD_FAST                       7: _var_var_0
                        3140    RAISE_VARARGS                   1
                        3142    LOAD_CONST                      0: None
                        3144    STORE_FAST                      7: _var_var_0
                        3146    DELETE_FAST                     7: _var_var_0
                        3148    RERAISE                         1
                        3150    RERAISE                         0
                        3152    COPY                            3
                        3154    POP_EXCEPT                      
                        3156    RERAISE                         1
                        3158    PUSH_EXC_INFO                   
                        3160    PUSH_NULL                       
                        3162    LOAD_CONST                      7: '__pyarmor_exit_15686__'
                        3164    NOP                             
                        3166    LOAD_CONST                      3: b'<COAddr>\x07\x00\x00\x1a<\x0c\x00\x00\x00\x00\x00\x00\x00\x00\x00\x00\x00\x00\x00\x00'
                        3168    CALL                            1
                        3176    POP_TOP                         
                        3178    RERAISE                         0
                        3180    COPY                            3
                        3182    POP_EXCEPT                      
                        3184    RERAISE                         1
                        3186    PUSH_NULL                       
                        3188    LOAD_CONST                      7: '__pyarmor_exit_15686__'
                        3190    LOAD_CONST                      3: b'<COAddr>\x07\x00\x00\x1a<\x0c\x00\x00\x00\x00\x00\x00\x00\x00\x00\x00\x00\x00\x00\x00'
                        3192    BUILD_TUPLE                     1
                        3194    CALL_FUNCTION_EX                0
                        3196    POP_TOP                         
                        3198    RETURN_VALUE                    
                    [Exception Table]
                        30 to 364 -> 2968 [0] 
                        386 to 534 -> 2968 [0] 
                        556 to 1466 -> 2968 [0] 
                        1488 to 1954 -> 2968 [0] 
                        1956 to 2154 -> 2388 [0] 
                        2154 to 2346 -> 2968 [0] 
                        2388 to 2638 -> 2962 [1] lasti
                        2638 to 2640 -> 2968 [0] 
                        2660 to 2854 -> 2962 [1] lasti
                        2854 to 2856 -> 2968 [0] 
                        2876 to 2892 -> 2962 [1] lasti
                        2892 to 2922 -> 2952 [1] lasti
                        2922 to 2924 -> 2962 [1] lasti
                        2924 to 2932 -> 2968 [0] 
                        2952 to 2962 -> 2962 [1] lasti
                        2962 to 2968 -> 2968 [0] 
                        2968 to 3004 -> 3152 [1] lasti
                        3004 to 3142 -> 3142 [1] lasti
                        3142 to 3152 -> 3152 [1] lasti
                        3152 to 3158 -> 3158 [0] 
                        3158 to 3180 -> 3180 [1] lasti
                [Code]
                    File Name: <frozen program.modules.func.registrator.send_code_new>
                    Object Name: _resend
                    Qualified Name: TelegramSendCode._resend
                    Arg Count: 1
                    Pos Only Arg Count: 0
                    KW Only Arg Count: 0
                    Stack Size: 8
                    Flags: 0x20000003 (CO_OPTIMIZED | CO_NEWLOCALS | CO_PYARMOR_OBFUSCATED)
                    [Names]
                        'Logs'
                        'PrintLog'
                        'config'
                        'account'
                        'lang'
                        '_timeout'
                        'attempts'
                        'functions'
                        'auth'
                        'ResendCodeRequest'
                        'result'
                        'phone_code_hash'
                        'client'
                        '_check'
                    [Locals+Names]
                        'self'
                        '__assert_armored__'
                        '_var_var_8'
                        '_var_var_9'
                    [Constants]
                        None
                        '__pyarmor_assert_15687__'
                        '__pyarmor_enter_15688__'
                        b'<COAddr>\x07\x00\x00\x1a\xac\x01\x00\x00\x00\x00\x00\x00\x00\x00\x00\x00\x00\x00\x00\x00'
                        'reg_resend_code'   # b'\x81\xf0\x1d\x14\x0c\xe8\xbb\xc1\x1e\xf4\t\xffo\xe3\xfc\x80'
                        (
                            'config'
                            'account'
                            'message'
                        )
                        1
                        (
                            'phone_number'
                            'phone_code_hash'
                            'reason'
                        )
                        '__pyarmor_exit_15689__'
                    [Disassembly]
                        0       NOP                             
                        2       NOP                             
                        4       PUSH_NULL                       
                        6       LOAD_CONST                      2: '__pyarmor_enter_15688__'
                        8       LOAD_CONST                      3: b'<COAddr>\x07\x00\x00\x1a\xac\x01\x00\x00\x00\x00\x00\x00\x00\x00\x00\x00\x00\x00\x00\x00'
                        10      BUILD_TUPLE                     1
                        12      CALL_FUNCTION_EX                0
                        14      POP_TOP                         
                        16      RESUME                          0
                        18      NOP                             
                        20      NOP                             
                        22      NOP                             
                        24      NOP                             
                        26      NOP                             
                        28      LOAD_GLOBAL                     1: NULL + Logs
                        38      LOAD_ATTR                       2: PrintLog
                        58      LOAD_FAST                       0: self
                        60      LOAD_ATTR                       4: config
                        80      LOAD_FAST                       0: self
                        82      LOAD_ATTR                       6: account
                        102     LOAD_FAST                       0: self
                        104     LOAD_ATTR                       8: lang
                        124     PUSH_NULL                       
                        126     LOAD_CONST                      1: '__pyarmor_assert_15687__'
                        128     LOAD_CONST                      4: 'reg_resend_code'   # b'\x81\xf0\x1d\x14\x0c\xe8\xbb\xc1\x1e\xf4\t\xffo\xe3\xfc\x80'
                        130     CALL                            1
                        138     BINARY_SUBSCR                   
                        142     KW_NAMES                        5: ('config', 'account', 'message')
                        144     CALL                            3
                        152     POP_TOP                         
                        154     LOAD_FAST                       0: self
                        156     LOAD_ATTR                       11: _timeout
                        176     CALL                            0
                        184     POP_TOP                         
                        186     LOAD_FAST                       0: self
                        188     COPY                            1
                        190     LOAD_ATTR                       12: attempts
                        210     LOAD_CONST                      6: 1
                        212     BINARY_OP                       23 (-=)
                        216     SWAP                            2
                        218     STORE_ATTR                      6: attempts
                        228     LOAD_CONST                      0: None
                        230     STORE_FAST                      2: _var_var_8
                        232     LOAD_GLOBAL                     14: functions
                        242     LOAD_ATTR                       16: auth
                        262     LOAD_ATTR                       19: ResendCodeRequest
                        282     LOAD_FAST                       0: self
                        284     LOAD_ATTR                       6: account
                        304     LOAD_FAST                       0: self
                        306     LOAD_ATTR                       20: result
                        326     LOAD_ATTR                       22: phone_code_hash
                        346     LOAD_FAST                       2: _var_var_8
                        348     KW_NAMES                        7: ('phone_number', 'phone_code_hash', 'reason')
                        350     CALL                            3
                        358     STORE_FAST                      3: _var_var_9
                        360     LOAD_FAST                       0: self
                        362     LOAD_ATTR                       25: client
                        382     LOAD_FAST                       3: _var_var_9
                        384     CALL                            1
                        392     LOAD_FAST                       0: self
                        394     STORE_ATTR                      10: result
                        404     LOAD_FAST                       0: self
                        406     LOAD_ATTR                       27: _check
                        426     CALL                            0
                        434     NOP                             
                        436     NOP                             
                        438     NOP                             
                        440     JUMP_FORWARD                    20 (to 482)
                        442     CALL                            1
                        450     POP_TOP                         
                        452     RETURN_VALUE                    
                        454     PUSH_EXC_INFO                   
                        456     PUSH_NULL                       
                        458     LOAD_CONST                      8: '__pyarmor_exit_15689__'
                        460     NOP                             
                        462     LOAD_CONST                      3: b'<COAddr>\x07\x00\x00\x1a\xac\x01\x00\x00\x00\x00\x00\x00\x00\x00\x00\x00\x00\x00\x00\x00'
                        464     CALL                            1
                        472     POP_TOP                         
                        474     RERAISE                         0
                        476     COPY                            3
                        478     POP_EXCEPT                      
                        480     RERAISE                         1
                        482     PUSH_NULL                       
                        484     LOAD_CONST                      8: '__pyarmor_exit_15689__'
                        486     LOAD_CONST                      3: b'<COAddr>\x07\x00\x00\x1a\xac\x01\x00\x00\x00\x00\x00\x00\x00\x00\x00\x00\x00\x00\x00\x00'
                        488     BUILD_TUPLE                     1
                        490     CALL_FUNCTION_EX                0
                        492     POP_TOP                         
                        494     RETURN_VALUE                    
                    [Exception Table]
                        28 to 434 -> 454 [0] 
                        454 to 476 -> 476 [1] lasti
                [Code]
                    File Name: <frozen program.modules.func.registrator.send_code_new>
                    Object Name: _timeout
                    Qualified Name: TelegramSendCode._timeout
                    Arg Count: 1
                    Pos Only Arg Count: 0
                    KW Only Arg Count: 0
                    Stack Size: 8
                    Flags: 0x20000003 (CO_OPTIMIZED | CO_NEWLOCALS | CO_PYARMOR_OBFUSCATED)
                    [Names]
                        'result'
                        'timeout'
                        'int'
                        'random'
                        'randint'
                        'Logs'
                        'PrintLog'
                        'config'
                        'account'
                        'lang'
                        'MaxFlood'
                        'time'
                        'sleep'
                    [Locals+Names]
                        'self'
                        '__assert_armored__'
                        '_var_var_10'
                    [Constants]
                        None
                        '__pyarmor_assert_15690__'
                        '__pyarmor_enter_15691__'
                        b'<COAddr>\x05\x00\x00\x1a,\x02\x00\x00\x00\x00\x00\x00\x00\x00\x00\x00\x00\x00\x00\x00'
                        6
                        10
                        500
                        'reg_code_not_send_by_sms_wait'   # b'\x81\xf0\x1d\x14\x0c\xf9\xb1\xd6\x1e\xc5\x03\xcfx\xd3\xeb\x80\x01Y\x84\xa5\xb3\xf4]\xc1\x16P\xb4]\t\xa5'
                        'sec'
                        (
                            'config'
                            'account'
                            'message'
                            'param'
                            'end'
                        )
                        ''
                        '__pyarmor_exit_15692__'
                    [Disassembly]
                        0       NOP                             
                        2       NOP                             
                        4       PUSH_NULL                       
                        6       LOAD_CONST                      2: '__pyarmor_enter_15691__'
                        8       LOAD_CONST                      3: b'<COAddr>\x05\x00\x00\x1a,\x02\x00\x00\x00\x00\x00\x00\x00\x00\x00\x00\x00\x00\x00\x00'
                        10      BUILD_TUPLE                     1
                        12      CALL_FUNCTION_EX                0
                        14      POP_TOP                         
                        16      RESUME                          0
                        18      NOP                             
                        20      NOP                             
                        22      NOP                             
                        24      NOP                             
                        26      NOP                             
                        28      LOAD_FAST                       0: self
                        30      LOAD_ATTR                       0: result
                        50      LOAD_ATTR                       2: timeout
                        70      POP_JUMP_IF_NONE                55 (to 182)
                        72      LOAD_GLOBAL                     5: NULL + int
                        82      LOAD_FAST                       0: self
                        84      LOAD_ATTR                       0: result
                        104     LOAD_ATTR                       2: timeout
                        124     CALL                            1
                        132     LOAD_GLOBAL                     7: NULL + random
                        142     LOAD_ATTR                       8: randint
                        162     LOAD_CONST                      4: 6
                        164     LOAD_CONST                      5: 10
                        166     CALL                            2
                        174     BINARY_OP                       0 (+)
                        178     STORE_FAST                      2: _var_var_10
                        180     JUMP_FORWARD                    22 (to 226)
                        182     LOAD_GLOBAL                     7: NULL + random
                        192     LOAD_ATTR                       8: randint
                        212     LOAD_CONST                      4: 6
                        214     LOAD_CONST                      5: 10
                        216     CALL                            2
                        224     STORE_FAST                      2: _var_var_10
                        226     LOAD_FAST                       2: _var_var_10
                        228     LOAD_CONST                      6: 500
                        230     COMPARE_OP                      68 (>)
                        234     POP_JUMP_IF_FALSE               77 (to 390)
                        236     LOAD_GLOBAL                     11: NULL + Logs
                        246     LOAD_ATTR                       12: PrintLog
                        266     LOAD_FAST                       0: self
                        268     LOAD_ATTR                       14: config
                        288     LOAD_FAST                       0: self
                        290     LOAD_ATTR                       16: account
                        310     LOAD_FAST                       0: self
                        312     LOAD_ATTR                       18: lang
                        332     PUSH_NULL                       
                        334     LOAD_CONST                      1: '__pyarmor_assert_15690__'
                        336     LOAD_CONST                      7: 'reg_code_not_send_by_sms_wait'   # b'\x81\xf0\x1d\x14\x0c\xf9\xb1\xd6\x1e\xc5\x03\xcfx\xd3\xeb\x80\x01Y\x84\xa5\xb3\xf4]\xc1\x16P\xb4]\t\xa5'
                        338     CALL                            1
                        346     BINARY_SUBSCR                   
                        350     LOAD_FAST                       2: _var_var_10
                        352     LOAD_CONST                      8: 'sec'
                        354     KW_NAMES                        9: ('config', 'account', 'message', 'param', 'end')
                        356     CALL                            5
                        364     POP_TOP                         
                        366     LOAD_GLOBAL                     21: NULL + MaxFlood
                        376     LOAD_CONST                      10: ''
                        378     LOAD_CONST                      10: ''
                        380     CALL                            2
                        388     RAISE_VARARGS                   1
                        390     LOAD_GLOBAL                     11: NULL + Logs
                        400     LOAD_ATTR                       12: PrintLog
                        420     LOAD_FAST                       0: self
                        422     LOAD_ATTR                       14: config
                        442     LOAD_FAST                       0: self
                        444     LOAD_ATTR                       16: account
                        464     LOAD_FAST                       0: self
                        466     LOAD_ATTR                       18: lang
                        486     PUSH_NULL                       
                        488     LOAD_CONST                      1: '__pyarmor_assert_15690__'
                        490     LOAD_CONST                      7: 'reg_code_not_send_by_sms_wait'   # b'\x81\xf0\x1d\x14\x0c\xf9\xb1\xd6\x1e\xc5\x03\xcfx\xd3\xeb\x80\x01Y\x84\xa5\xb3\xf4]\xc1\x16P\xb4]\t\xa5'
                        492     CALL                            1
                        500     BINARY_SUBSCR                   
                        504     LOAD_FAST                       2: _var_var_10
                        506     LOAD_CONST                      8: 'sec'
                        508     KW_NAMES                        9: ('config', 'account', 'message', 'param', 'end')
                        510     CALL                            5
                        518     POP_TOP                         
                        520     LOAD_GLOBAL                     23: NULL + time
                        530     LOAD_ATTR                       24: sleep
                        550     LOAD_FAST                       2: _var_var_10
                        552     CALL                            1
                        560     POP_TOP                         
                        562     LOAD_CONST                      0: None
                        564     NOP                             
                        566     NOP                             
                        568     NOP                             
                        570     JUMP_FORWARD                    19 (to 610)
                        578     POP_TOP                         
                        580     RETURN_CONST                    0: None
                        582     PUSH_EXC_INFO                   
                        584     PUSH_NULL                       
                        586     LOAD_CONST                      11: '__pyarmor_exit_15692__'
                        588     NOP                             
                        590     LOAD_CONST                      3: b'<COAddr>\x05\x00\x00\x1a,\x02\x00\x00\x00\x00\x00\x00\x00\x00\x00\x00\x00\x00\x00\x00'
                        592     CALL                            1
                        600     POP_TOP                         
                        602     RERAISE                         0
                        604     COPY                            3
                        606     POP_EXCEPT                      
                        608     RERAISE                         1
                        610     PUSH_NULL                       
                        612     LOAD_CONST                      11: '__pyarmor_exit_15692__'
                        614     LOAD_CONST                      3: b'<COAddr>\x05\x00\x00\x1a,\x02\x00\x00\x00\x00\x00\x00\x00\x00\x00\x00\x00\x00\x00\x00'
                        616     BUILD_TUPLE                     1
                        618     CALL_FUNCTION_EX                0
                        620     POP_TOP                         
                        622     RETURN_VALUE                    
                    [Exception Table]
                        28 to 562 -> 582 [0] 
                        582 to 604 -> 604 [1] lasti
                '__pyarmor_exit_15668__'
                None
                (
                    False
                    False
                    False
                    0
                )
            [Disassembly]
                0       NOP                             
                2       LOAD_NAME                       0: __name__
                4       STORE_NAME                      1: __module__
                6       LOAD_CONST                      0: 'TelegramSendCode'
                8       STORE_NAME                      2: __qualname__
                10      NOP                             
                12      PUSH_NULL                       
                14      LOAD_CONST                      2: '__pyarmor_enter_15667__'
                16      LOAD_CONST                      3: b'<COAddr>\x07\x00\x00"J\x00\x00\x00\x00\x00\x00\x00\x00\x00\x00\x00\x00\x00\x00\x00'
                18      BUILD_TUPLE                     1
                20      CALL_FUNCTION_EX                0
                22      POP_TOP                         
                24      RESUME                          0
                26      NOP                             
                28      NOP                             
                30      NOP                             
                32      NOP                             
                34      NOP                             
                36      NOP                             
                38      LOAD_CONST                      14: (False, False, False, 0)
                40      LOAD_CONST                      4: <CODE> __init__
                42      MAKE_FUNCTION                   1
                44      STORE_NAME                      4: __init__
                46      LOAD_CONST                      5: <CODE> start
                48      MAKE_FUNCTION                   0
                50      STORE_NAME                      5: start
                52      LOAD_CONST                      6: <CODE> _recaptcha
                54      MAKE_FUNCTION                   0
                56      STORE_NAME                      6: _recaptcha
                58      LOAD_CONST                      7: <CODE> _check
                60      MAKE_FUNCTION                   0
                62      STORE_NAME                      7: _check
                64      LOAD_CONST                      8: <CODE> _send_firebase
                66      MAKE_FUNCTION                   0
                68      STORE_NAME                      8: _send_firebase
                70      LOAD_CONST                      9: <CODE> _send_email
                72      MAKE_FUNCTION                   0
                74      STORE_NAME                      9: _send_email
                76      LOAD_CONST                      10: <CODE> _resend
                78      MAKE_FUNCTION                   0
                80      STORE_NAME                      10: _resend
                82      LOAD_CONST                      11: <CODE> _timeout
                84      MAKE_FUNCTION                   0
                86      STORE_NAME                      11: _timeout
                88      LOAD_CONST                      13: None
                90      NOP                             
                92      NOP                             
                94      NOP                             
                96      JUMP_FORWARD                    19 (to 136)
                104     POP_TOP                         
                106     RETURN_CONST                    13: None
                108     PUSH_EXC_INFO                   
                110     PUSH_NULL                       
                112     LOAD_CONST                      12: '__pyarmor_exit_15668__'
                114     NOP                             
                116     LOAD_CONST                      3: b'<COAddr>\x07\x00\x00"J\x00\x00\x00\x00\x00\x00\x00\x00\x00\x00\x00\x00\x00\x00\x00'
                118     CALL                            1
                126     POP_TOP                         
                128     RERAISE                         0
                130     COPY                            3
                132     POP_EXCEPT                      
                134     RERAISE                         1
                136     PUSH_NULL                       
                138     LOAD_CONST                      12: '__pyarmor_exit_15668__'
                140     LOAD_CONST                      3: b'<COAddr>\x07\x00\x00"J\x00\x00\x00\x00\x00\x00\x00\x00\x00\x00\x00\x00\x00\x00\x00'
                142     BUILD_TUPLE                     1
                144     CALL_FUNCTION_EX                0
                146     POP_TOP                         
                148     RETURN_VALUE                    
            [Exception Table]
                36 to 88 -> 108 [0] 
                108 to 130 -> 130 [1] lasti
        'TelegramSendCode'
        [Code]
            File Name: <frozen program.modules.func.registrator.send_code_new>
            Object Name: TelegramCheckCodeAnsfer
            Qualified Name: TelegramCheckCodeAnsfer
            Arg Count: 4
            Pos Only Arg Count: 0
            KW Only Arg Count: 0
            Stack Size: 8
            Flags: 0x20000003 (CO_OPTIMIZED | CO_NEWLOCALS | CO_PYARMOR_OBFUSCATED)
            [Names]
                'Logs'
                'PrintLog'
                'str'
            [Locals+Names]
                'config'
                'lang'
                'account'
                'code'
                '__assert_armored__'
            [Constants]
                None
                '__pyarmor_assert_15693__'
                '__pyarmor_enter_15694__'
                b'<COAddr>\x07\x00\x00\x1a\xa0\x01\x00\x00\x00\x00\x00\x00\x00\x00\x00\x00\x00\x00\x00\x00'
                False
                'problems_code'   # b'\x81\xf2\n\x1c1\xf6\xbb\xdf\x08\xc5\x0e\xcfh\xe9'
                (
                    'config'
                    'account'
                    'message'
                )
                '__pyarmor_exit_15695__'
                'TIME_OUT'
                'waiting_time_has_expired'   # b"\x81\xf5\x19\x1a'\xf3\xb0\xd5$\xee\x04\xcdi\xd3\xf0\x84\x1cb\xbe\xbf\xba\xc2\\\xc9\x01"
                'STATUS_CANCEL'   # b'\x81\xd1,2\x07\xcf\x8d\xed8\xdb#\xe3I\xc0'
                'registration_cancelled'   # b'\x81\xf0\x1d\x14:\xe9\xaa\xc0\x1a\xee\x04\xcfb\xd3\xfb\x84\x01^\xbe\xab\xa6\xceJ'
                'code_received'   # b'\x81\xe1\x17\x176\xc5\xac\xd7\x18\xff\x04\xd6i\xe8'
                (
                    'config'
                    'account'
                    'message'
                    'param'
                )
            [Disassembly]
                0       NOP                             
                2       NOP                             
                4       PUSH_NULL                       
                6       LOAD_CONST                      2: '__pyarmor_enter_15694__'
                8       LOAD_CONST                      3: b'<COAddr>\x07\x00\x00\x1a\xa0\x01\x00\x00\x00\x00\x00\x00\x00\x00\x00\x00\x00\x00\x00\x00'
                10      BUILD_TUPLE                     1
                12      CALL_FUNCTION_EX                0
                14      POP_TOP                         
                16      RESUME                          0
                18      NOP                             
                20      NOP                             
                22      NOP                             
                24      NOP                             
                26      NOP                             
                28      LOAD_FAST                       3: code
                30      LOAD_CONST                      4: False
                32      COMPARE_OP                      40 (==)
                36      POP_JUMP_IF_FALSE               44 (to 126)
                38      LOAD_GLOBAL                     1: NULL + Logs
                48      LOAD_ATTR                       2: PrintLog
                68      LOAD_FAST                       0: config
                70      LOAD_FAST                       2: account
                72      LOAD_FAST                       1: lang
                74      PUSH_NULL                       
                76      LOAD_CONST                      1: '__pyarmor_assert_15693__'
                78      LOAD_CONST                      5: 'problems_code'   # b'\x81\xf2\n\x1c1\xf6\xbb\xdf\x08\xc5\x0e\xcfh\xe9'
                80      CALL                            1
                88      BINARY_SUBSCR                   
                92      KW_NAMES                        6: ('config', 'account', 'message')
                94      CALL                            3
                102     POP_TOP                         
                104     NOP                             
                106     LOAD_CONST                      4: False
                108     NOP                             
                110     NOP                             
                112     NOP                             
                114     JUMP_FORWARD                    177 (to 470)
                122     POP_TOP                         
                124     RETURN_CONST                    4: False
                126     LOAD_FAST                       3: code
                128     LOAD_CONST                      8: 'TIME_OUT'
                130     COMPARE_OP                      40 (==)
                134     POP_JUMP_IF_FALSE               44 (to 224)
                136     LOAD_GLOBAL                     1: NULL + Logs
                146     LOAD_ATTR                       2: PrintLog
                166     LOAD_FAST                       0: config
                168     LOAD_FAST                       2: account
                170     LOAD_FAST                       1: lang
                172     PUSH_NULL                       
                174     LOAD_CONST                      1: '__pyarmor_assert_15693__'
                176     LOAD_CONST                      9: 'waiting_time_has_expired'   # b"\x81\xf5\x19\x1a'\xf3\xb0\xd5$\xee\x04\xcdi\xd3\xf0\x84\x1cb\xbe\xbf\xba\xc2\\\xc9\x01"
                178     CALL                            1
                186     BINARY_SUBSCR                   
                190     KW_NAMES                        6: ('config', 'account', 'message')
                192     CALL                            3
                200     POP_TOP                         
                202     NOP                             
                204     LOAD_CONST                      4: False
                206     NOP                             
                208     NOP                             
                210     NOP                             
                212     JUMP_FORWARD                    128 (to 470)
                220     POP_TOP                         
                222     RETURN_CONST                    4: False
                224     LOAD_FAST                       3: code
                226     PUSH_NULL                       
                228     LOAD_CONST                      1: '__pyarmor_assert_15693__'
                230     LOAD_CONST                      10: 'STATUS_CANCEL'   # b'\x81\xd1,2\x07\xcf\x8d\xed8\xdb#\xe3I\xc0'
                232     CALL                            1
                240     COMPARE_OP                      40 (==)
                244     POP_JUMP_IF_FALSE               44 (to 334)
                246     LOAD_GLOBAL                     1: NULL + Logs
                256     LOAD_ATTR                       2: PrintLog
                276     LOAD_FAST                       0: config
                278     LOAD_FAST                       2: account
                280     LOAD_FAST                       1: lang
                282     PUSH_NULL                       
                284     LOAD_CONST                      1: '__pyarmor_assert_15693__'
                286     LOAD_CONST                      11: 'registration_cancelled'   # b'\x81\xf0\x1d\x14:\xe9\xaa\xc0\x1a\xee\x04\xcfb\xd3\xfb\x84\x01^\xbe\xab\xa6\xceJ'
                288     CALL                            1
                296     BINARY_SUBSCR                   
                300     KW_NAMES                        6: ('config', 'account', 'message')
                302     CALL                            3
                310     POP_TOP                         
                312     NOP                             
                314     LOAD_CONST                      4: False
                316     NOP                             
                318     NOP                             
                320     NOP                             
                322     JUMP_FORWARD                    73 (to 470)
                330     POP_TOP                         
                332     RETURN_CONST                    4: False
                334     LOAD_GLOBAL                     1: NULL + Logs
                344     LOAD_ATTR                       2: PrintLog
                364     LOAD_FAST                       0: config
                366     LOAD_FAST                       2: account
                368     LOAD_FAST                       1: lang
                370     PUSH_NULL                       
                372     LOAD_CONST                      1: '__pyarmor_assert_15693__'
                374     LOAD_CONST                      12: 'code_received'   # b'\x81\xe1\x17\x176\xc5\xac\xd7\x18\xff\x04\xd6i\xe8'
                376     CALL                            1
                384     BINARY_SUBSCR                   
                388     LOAD_GLOBAL                     5: NULL + str
                398     LOAD_FAST                       3: code
                400     CALL                            1
                408     KW_NAMES                        13: ('config', 'account', 'message', 'param')
                410     CALL                            4
                418     POP_TOP                         
                420     LOAD_FAST                       3: code
                422     NOP                             
                424     NOP                             
                426     NOP                             
                428     JUMP_FORWARD                    20 (to 470)
                430     CALL                            1
                438     POP_TOP                         
                440     RETURN_VALUE                    
                442     PUSH_EXC_INFO                   
                444     PUSH_NULL                       
                446     LOAD_CONST                      7: '__pyarmor_exit_15695__'
                448     NOP                             
                450     LOAD_CONST                      3: b'<COAddr>\x07\x00\x00\x1a\xa0\x01\x00\x00\x00\x00\x00\x00\x00\x00\x00\x00\x00\x00\x00\x00'
                452     CALL                            1
                460     POP_TOP                         
                462     RERAISE                         0
                464     COPY                            3
                466     POP_EXCEPT                      
                468     RERAISE                         1
                470     PUSH_NULL                       
                472     LOAD_CONST                      7: '__pyarmor_exit_15695__'
                474     LOAD_CONST                      3: b'<COAddr>\x07\x00\x00\x1a\xa0\x01\x00\x00\x00\x00\x00\x00\x00\x00\x00\x00\x00\x00\x00\x00'
                476     BUILD_TUPLE                     1
                478     CALL_FUNCTION_EX                0
                480     POP_TOP                         
                482     RETURN_VALUE                    
            [Exception Table]
                28 to 104 -> 442 [0] 
                126 to 202 -> 442 [0] 
                224 to 312 -> 442 [0] 
                334 to 422 -> 442 [0] 
                442 to 464 -> 464 [1] lasti
        [Code]
            File Name: <frozen program.modules.func.registrator.send_code_new>
            Object Name: TelegramSignUp
            Qualified Name: TelegramSignUp
            Arg Count: 8
            Pos Only Arg Count: 0
            KW Only Arg Count: 0
            Stack Size: 11
            Flags: 0x20000003 (CO_OPTIMIZED | CO_NEWLOCALS | CO_PYARMOR_OBFUSCATED)
            [Names]
                'sign_up'
                'phone_code_hash'
                'errors'
                'FirstNameInvalidError'
                'Logs'
                'PrintLog'
                'random'
                'choice'
                'string'
                'ascii_uppercase'
                'join'
                'choices'
                'ascii_lowercase'
                'randint'
                'TelegramSignUp'
                'FloodWaitError'
                'int'
                'seconds'
                'DelayOnline'
                'ConnectionError'
                'asyncio'
                'IncompleteReadError'
                'disconnect'
                'connect'
            [Locals+Names]
                'client'
                'code'
                'first_name'
                'last_name'
                'account'
                'send_code'
                'config'
                'stop_thread'
                '__assert_armored__'
                '_var_var_0'
                '_var_var_11'
            [Constants]
                None
                '__pyarmor_assert_15696__'
                '__pyarmor_enter_15697__'
                b'<COAddr>\x05\x00\x00\x1a\x8a\x05\x00\x00\x00\x00\x00\x00\x00\x00\x00\x00\x00\x00\x00\x00'
                (
                    'first_name'
                    'last_name'
                    'phone'
                    'phone_code_hash'
                )
                '__pyarmor_exit_15698__'
                'Error: Check file with names!'   # b'\x81\xc7\n\x01<\xe8\xe4\x928\xf2\x08\xc3g\xac\xfe\x8c\x03X\xfb\xb0\xa3\xdfF\x8c\x0bn\xaeY\x13\xf0'
                (
                    'config'
                    'account'
                    'message'
                )
                ''
                4
                9
                (
                    'k'
                )
                'FloodWait:'   # b'\x81\xc4\x14\x1c<\xfe\x89\xd3\x12\xeeW'
                (
                    'config'
                    'account'
                    'message'
                    'param'
                )
                500
                5
                'ConnectionError'   # b'\x81\xc1\x17\x1d=\xff\xbd\xc6\x12\xf5\x03\xe5~\xfe\xf7\x97'
                1
                'ConnectionError.'   # b'\x81\xc1\x17\x1d=\xff\xbd\xc6\x12\xf5\x03\xe5~\xfe\xf7\x97A'
            [Disassembly]
                0       NOP                             
                2       NOP                             
                4       PUSH_NULL                       
                6       LOAD_CONST                      2: '__pyarmor_enter_15697__'
                8       LOAD_CONST                      3: b'<COAddr>\x05\x00\x00\x1a\x8a\x05\x00\x00\x00\x00\x00\x00\x00\x00\x00\x00\x00\x00\x00\x00'
                10      BUILD_TUPLE                     1
                12      CALL_FUNCTION_EX                0
                14      POP_TOP                         
                16      RESUME                          0
                18      NOP                             
                20      NOP                             
                22      NOP                             
                24      NOP                             
                26      NOP                             
                28      NOP                             
                30      LOAD_FAST                       0: client
                32      LOAD_ATTR                       1: sign_up
                52      LOAD_FAST                       1: code
                54      LOAD_FAST                       2: first_name
                56      LOAD_FAST                       3: last_name
                58      LOAD_FAST                       4: account
                60      LOAD_FAST                       5: send_code
                62      LOAD_ATTR                       2: phone_code_hash
                82      KW_NAMES                        4: ('first_name', 'last_name', 'phone', 'phone_code_hash')
                84      CALL                            5
                92      NOP                             
                94      NOP                             
                96      JUMP_FORWARD                    686 (to 1472)
                100     CALL                            1
                108     POP_TOP                         
                110     RETURN_VALUE                    
                112     PUSH_EXC_INFO                   
                114     LOAD_GLOBAL                     4: errors
                124     LOAD_ATTR                       6: FirstNameInvalidError
                144     CHECK_EXC_MATCH                 
                146     POP_JUMP_IF_FALSE               276 (to 702)
                150     POP_TOP                         
                152     LOAD_GLOBAL                     9: NULL + Logs
                162     LOAD_ATTR                       10: PrintLog
                182     LOAD_FAST                       6: config
                184     LOAD_FAST                       4: account
                186     PUSH_NULL                       
                188     LOAD_CONST                      1: '__pyarmor_assert_15696__'
                190     LOAD_CONST                      6: 'Error: Check file with names!'   # b'\x81\xc7\n\x01<\xe8\xe4\x928\xf2\x08\xc3g\xac\xfe\x8c\x03X\xfb\xb0\xa3\xdfF\x8c\x0bn\xaeY\x13\xf0'
                192     CALL                            1
                200     KW_NAMES                        7: ('config', 'account', 'message')
                202     CALL                            3
                210     POP_TOP                         
                212     LOAD_GLOBAL                     13: NULL + random
                222     LOAD_ATTR                       14: choice
                242     LOAD_GLOBAL                     16: string
                252     LOAD_ATTR                       18: ascii_uppercase
                272     CALL                            1
                280     LOAD_CONST                      8: ''
                282     LOAD_ATTR                       21: join
                302     LOAD_GLOBAL                     13: NULL + random
                312     LOAD_ATTR                       22: choices
                332     LOAD_GLOBAL                     16: string
                342     LOAD_ATTR                       24: ascii_lowercase
                362     LOAD_GLOBAL                     13: NULL + random
                372     LOAD_ATTR                       26: randint
                392     LOAD_CONST                      9: 4
                394     LOAD_CONST                      10: 9
                396     CALL                            2
                404     KW_NAMES                        11: ('k',)
                406     CALL                            2
                414     CALL                            1
                422     BINARY_OP                       0 (+)
                426     STORE_FAST                      2: first_name
                428     LOAD_GLOBAL                     13: NULL + random
                438     LOAD_ATTR                       14: choice
                458     LOAD_GLOBAL                     16: string
                468     LOAD_ATTR                       18: ascii_uppercase
                488     CALL                            1
                496     LOAD_CONST                      8: ''
                498     LOAD_ATTR                       21: join
                518     LOAD_GLOBAL                     13: NULL + random
                528     LOAD_ATTR                       22: choices
                548     LOAD_GLOBAL                     16: string
                558     LOAD_ATTR                       24: ascii_lowercase
                578     LOAD_GLOBAL                     13: NULL + random
                588     LOAD_ATTR                       26: randint
                608     LOAD_CONST                      9: 4
                610     LOAD_CONST                      10: 9
                612     CALL                            2
                620     KW_NAMES                        11: ('k',)
                622     CALL                            2
                630     CALL                            1
                638     BINARY_OP                       0 (+)
                642     STORE_FAST                      3: last_name
                644     LOAD_GLOBAL                     29: NULL + TelegramSignUp
                654     LOAD_FAST                       0: client
                656     LOAD_FAST                       1: code
                658     LOAD_FAST                       2: first_name
                660     LOAD_FAST                       3: last_name
                662     LOAD_FAST                       4: account
                664     LOAD_FAST                       5: send_code
                666     LOAD_FAST                       6: config
                668     LOAD_FAST                       7: stop_thread
                670     CALL                            8
                678     SWAP                            2
                680     POP_EXCEPT                      
                682     NOP                             
                684     NOP                             
                686     JUMP_FORWARD                    391 (to 1472)
                690     CALL                            1
                698     POP_TOP                         
                700     RETURN_VALUE                    
                702     LOAD_GLOBAL                     4: errors
                712     LOAD_ATTR                       30: FloodWaitError
                732     CHECK_EXC_MATCH                 
                734     POP_JUMP_IF_FALSE               151 (to 1038)
                736     STORE_FAST                      9: _var_var_0
                738     LOAD_GLOBAL                     9: NULL + Logs
                748     LOAD_ATTR                       10: PrintLog
                768     LOAD_FAST                       6: config
                770     LOAD_FAST                       4: account
                772     PUSH_NULL                       
                774     LOAD_CONST                      1: '__pyarmor_assert_15696__'
                776     LOAD_CONST                      12: 'FloodWait:'   # b'\x81\xc4\x14\x1c<\xfe\x89\xd3\x12\xeeW'
                778     CALL                            1
                786     LOAD_GLOBAL                     33: NULL + int
                796     LOAD_FAST                       9: _var_var_0
                798     LOAD_ATTR                       34: seconds
                818     CALL                            1
                826     KW_NAMES                        13: ('config', 'account', 'message', 'param')
                828     CALL                            4
                836     POP_TOP                         
                838     LOAD_GLOBAL                     33: NULL + int
                848     LOAD_FAST                       9: _var_var_0
                850     LOAD_ATTR                       34: seconds
                870     CALL                            1
                878     LOAD_CONST                      14: 500
                880     COMPARE_OP                      26 (<=)
                884     POP_JUMP_IF_FALSE               71 (to 1028)
                886     LOAD_GLOBAL                     33: NULL + int
                896     LOAD_FAST                       9: _var_var_0
                898     LOAD_ATTR                       34: seconds
                918     CALL                            1
                926     LOAD_CONST                      15: 5
                928     BINARY_OP                       0 (+)
                932     STORE_FAST                      10: _var_var_11
                934     LOAD_GLOBAL                     37: NULL + DelayOnline
                944     LOAD_FAST                       4: account
                946     LOAD_FAST                       0: client
                948     LOAD_FAST                       10: _var_var_11
                950     LOAD_FAST                       10: _var_var_11
                952     LOAD_FAST                       7: stop_thread
                954     CALL                            5
                962     POP_TOP                         
                964     LOAD_GLOBAL                     29: NULL + TelegramSignUp
                974     LOAD_FAST                       0: client
                976     LOAD_FAST                       1: code
                978     LOAD_FAST                       2: first_name
                980     LOAD_FAST                       3: last_name
                982     LOAD_FAST                       4: account
                984     LOAD_FAST                       5: send_code
                986     LOAD_FAST                       6: config
                988     LOAD_FAST                       7: stop_thread
                990     CALL                            8
                998     SWAP                            2
                1000    POP_EXCEPT                      
                1002    LOAD_CONST                      0: None
                1004    STORE_FAST                      9: _var_var_0
                1006    DELETE_FAST                     9: _var_var_0
                1008    NOP                             
                1010    NOP                             
                1012    NOP                             
                1014    JUMP_FORWARD                    228 (to 1472)
                1016    CALL                            1
                1024    POP_TOP                         
                1026    RETURN_VALUE                    
                1028    RAISE_VARARGS                   0
                1030    LOAD_CONST                      0: None
                1032    STORE_FAST                      9: _var_var_0
                1034    DELETE_FAST                     9: _var_var_0
                1036    RERAISE                         1
                1038    LOAD_GLOBAL                     38: ConnectionError
                1048    CHECK_EXC_MATCH                 
                1050    POP_JUMP_IF_FALSE               75 (to 1202)
                1052    POP_TOP                         
                1054    LOAD_GLOBAL                     9: NULL + Logs
                1064    LOAD_ATTR                       10: PrintLog
                1084    LOAD_FAST                       6: config
                1086    LOAD_FAST                       4: account
                1088    PUSH_NULL                       
                1090    LOAD_CONST                      1: '__pyarmor_assert_15696__'
                1092    LOAD_CONST                      16: 'ConnectionError'   # b'\x81\xc1\x17\x1d=\xff\xbd\xc6\x12\xf5\x03\xe5~\xfe\xf7\x97'
                1094    CALL                            1
                1102    KW_NAMES                        7: ('config', 'account', 'message')
                1104    CALL                            3
                1112    POP_TOP                         
                1114    LOAD_GLOBAL                     37: NULL + DelayOnline
                1124    LOAD_FAST                       4: account
                1126    LOAD_FAST                       0: client
                1128    LOAD_CONST                      17: 1
                1130    LOAD_CONST                      17: 1
                1132    LOAD_FAST                       7: stop_thread
                1134    CALL                            5
                1142    POP_TOP                         
                1144    LOAD_GLOBAL                     29: NULL + TelegramSignUp
                1154    LOAD_FAST                       0: client
                1156    LOAD_FAST                       1: code
                1158    LOAD_FAST                       2: first_name
                1160    LOAD_FAST                       3: last_name
                1162    LOAD_FAST                       4: account
                1164    LOAD_FAST                       5: send_code
                1166    LOAD_FAST                       6: config
                1168    LOAD_FAST                       7: stop_thread
                1170    CALL                            8
                1178    SWAP                            2
                1180    POP_EXCEPT                      
                1182    NOP                             
                1184    NOP                             
                1186    NOP                             
                1188    JUMP_FORWARD                    141 (to 1472)
                1190    CALL                            1
                1198    POP_TOP                         
                1200    RETURN_VALUE                    
                1202    LOAD_GLOBAL                     40: asyncio
                1212    LOAD_ATTR                       42: IncompleteReadError
                1232    CHECK_EXC_MATCH                 
                1234    POP_JUMP_IF_FALSE               100 (to 1436)
                1236    POP_TOP                         
                1238    LOAD_GLOBAL                     9: NULL + Logs
                1248    LOAD_ATTR                       10: PrintLog
                1268    LOAD_FAST                       6: config
                1270    LOAD_FAST                       4: account
                1272    PUSH_NULL                       
                1274    LOAD_CONST                      1: '__pyarmor_assert_15696__'
                1276    LOAD_CONST                      18: 'ConnectionError.'   # b'\x81\xc1\x17\x1d=\xff\xbd\xc6\x12\xf5\x03\xe5~\xfe\xf7\x97A'
                1278    CALL                            1
                1286    KW_NAMES                        7: ('config', 'account', 'message')
                1288    CALL                            3
                1296    POP_TOP                         
                1298    LOAD_FAST                       0: client
                1300    LOAD_ATTR                       45: disconnect
                1320    CALL                            0
                1328    POP_TOP                         
                1330    JUMP_FORWARD                    7 (to 1346)
                1332    PUSH_EXC_INFO                   
                1334    POP_TOP                         
                1336    POP_EXCEPT                      
                1338    JUMP_FORWARD                    3 (to 1346)
                1340    COPY                            3
                1342    POP_EXCEPT                      
                1344    RERAISE                         1
                1346    LOAD_FAST                       0: client
                1348    LOAD_ATTR                       47: connect
                1368    CALL                            0
                1376    POP_TOP                         
                1378    LOAD_GLOBAL                     29: NULL + TelegramSignUp
                1388    LOAD_FAST                       0: client
                1390    LOAD_FAST                       1: code
                1392    LOAD_FAST                       2: first_name
                1394    LOAD_FAST                       3: last_name
                1396    LOAD_FAST                       4: account
                1398    LOAD_FAST                       5: send_code
                1400    LOAD_FAST                       6: config
                1402    LOAD_FAST                       7: stop_thread
                1404    CALL                            8
                1412    SWAP                            2
                1414    POP_EXCEPT                      
                1416    NOP                             
                1418    NOP                             
                1420    NOP                             
                1422    JUMP_FORWARD                    24 (to 1472)
                1424    CALL                            1
                1432    POP_TOP                         
                1434    RETURN_VALUE                    
                1436    RERAISE                         0
                1438    COPY                            3
                1440    POP_EXCEPT                      
                1442    RERAISE                         1
                1444    PUSH_EXC_INFO                   
                1446    PUSH_NULL                       
                1448    LOAD_CONST                      5: '__pyarmor_exit_15698__'
                1450    NOP                             
                1452    LOAD_CONST                      3: b'<COAddr>\x05\x00\x00\x1a\x8a\x05\x00\x00\x00\x00\x00\x00\x00\x00\x00\x00\x00\x00\x00\x00'
                1454    CALL                            1
                1462    POP_TOP                         
                1464    RERAISE                         0
                1466    COPY                            3
                1468    POP_EXCEPT                      
                1470    RERAISE                         1
                1472    PUSH_NULL                       
                1474    LOAD_CONST                      5: '__pyarmor_exit_15698__'
                1476    LOAD_CONST                      3: b'<COAddr>\x05\x00\x00\x1a\x8a\x05\x00\x00\x00\x00\x00\x00\x00\x00\x00\x00\x00\x00\x00\x00'
                1478    BUILD_TUPLE                     1
                1480    CALL_FUNCTION_EX                0
                1482    POP_TOP                         
                1484    RETURN_VALUE                    
            [Exception Table]
                30 to 92 -> 112 [0] 
                112 to 680 -> 1438 [1] lasti
                680 to 682 -> 1444 [0] 
                702 to 738 -> 1438 [1] lasti
                738 to 998 -> 1030 [1] lasti
                998 to 1000 -> 1438 [1] lasti
                1000 to 1008 -> 1444 [0] 
                1028 to 1030 -> 1030 [1] lasti
                1030 to 1180 -> 1438 [1] lasti
                1180 to 1182 -> 1444 [0] 
                1202 to 1298 -> 1438 [1] lasti
                1298 to 1330 -> 1332 [1] 
                1330 to 1332 -> 1438 [1] lasti
                1332 to 1336 -> 1340 [2] lasti
                1336 to 1414 -> 1438 [1] lasti
                1414 to 1416 -> 1444 [0] 
                1436 to 1438 -> 1438 [1] lasti
                1438 to 1444 -> 1444 [0] 
                1444 to 1466 -> 1466 [1] lasti
        '__pyarmor_exit_15665__'
    [Disassembly]
        0       NOP                             
        2       NOP                             
        4       PUSH_NULL                       
        6       LOAD_CONST                      1: '__pyarmor_enter_15664__'
        8       LOAD_CONST                      2: b'<COAddr>\x07\x00\x00\x1a\x94\x00\x00\x00\x00\x00\x00\x00\x00\x00\x00\x00\x00\x00\x00\x00'
        10      BUILD_TUPLE                     1
        12      CALL_FUNCTION_EX                0
        14      POP_TOP                         
        16      RESUME                          0
        18      NOP                             
        20      NOP                             
        22      NOP                             
        24      NOP                             
        26      LOAD_CONST                      3: 0
        28      LOAD_CONST                      4: None
        30      IMPORT_NAME                     1: time
        32      STORE_NAME                      1: time
        34      LOAD_CONST                      3: 0
        36      LOAD_CONST                      4: None
        38      IMPORT_NAME                     2: random
        40      STORE_NAME                      2: random
        42      LOAD_CONST                      3: 0
        44      LOAD_CONST                      4: None
        46      IMPORT_NAME                     3: string
        48      STORE_NAME                      3: string
        50      LOAD_CONST                      3: 0
        52      LOAD_CONST                      4: None
        54      IMPORT_NAME                     4: asyncio
        56      STORE_NAME                      4: asyncio
        58      LOAD_CONST                      3: 0
        60      LOAD_CONST                      5: ('DelayOnline',)
        62      IMPORT_NAME                     5: program.telegram
        64      IMPORT_FROM                     6: DelayOnline
        66      STORE_NAME                      6: DelayOnline
        68      POP_TOP                         
        70      LOAD_CONST                      3: 0
        72      LOAD_CONST                      6: ('StopProgram',)
        74      IMPORT_NAME                     7: multithon.errors
        76      IMPORT_FROM                     8: StopProgram
        78      STORE_NAME                      8: StopProgram
        80      POP_TOP                         
        82      LOAD_CONST                      3: 0
        84      LOAD_CONST                      7: ('functions', 'types', 'errors')
        86      IMPORT_NAME                     9: multithon.sync
        88      IMPORT_FROM                     10: functions
        90      STORE_NAME                      10: functions
        92      IMPORT_FROM                     11: types
        94      STORE_NAME                      11: types
        96      IMPORT_FROM                     12: errors
        98      STORE_NAME                      12: errors
        100     POP_TOP                         
        102     LOAD_CONST                      3: 0
        104     LOAD_CONST                      8: ('Logs', 'MaxFlood', 'logging')
        106     IMPORT_NAME                     13: program.static_classes
        108     IMPORT_FROM                     14: Logs
        110     STORE_NAME                      14: Logs
        112     IMPORT_FROM                     15: MaxFlood
        114     STORE_NAME                      15: MaxFlood
        116     IMPORT_FROM                     16: logging
        118     STORE_NAME                      16: logging
        120     POP_TOP                         
        122     PUSH_NULL                       
        124     LOAD_BUILD_CLASS                
        126     LOAD_CONST                      9: <CODE> TelegramSendCode
        128     MAKE_FUNCTION                   0
        130     LOAD_CONST                      10: 'TelegramSendCode'
        132     CALL                            2
        140     STORE_NAME                      17: TelegramSendCode
        142     LOAD_CONST                      11: <CODE> TelegramCheckCodeAnsfer
        144     MAKE_FUNCTION                   0
        146     STORE_NAME                      18: TelegramCheckCodeAnsfer
        148     LOAD_CONST                      12: <CODE> TelegramSignUp
        150     MAKE_FUNCTION                   0
        152     STORE_NAME                      19: TelegramSignUp
        154     LOAD_CONST                      4: None
        156     NOP                             
        158     NOP                             
        160     NOP                             
        162     JUMP_FORWARD                    19 (to 202)
        170     POP_TOP                         
        172     RETURN_CONST                    4: None
        174     PUSH_EXC_INFO                   
        176     PUSH_NULL                       
        178     LOAD_CONST                      13: '__pyarmor_exit_15665__'
        180     NOP                             
        182     LOAD_CONST                      2: b'<COAddr>\x07\x00\x00\x1a\x94\x00\x00\x00\x00\x00\x00\x00\x00\x00\x00\x00\x00\x00\x00\x00'
        184     CALL                            1
        192     POP_TOP                         
        194     RERAISE                         0
        196     COPY                            3
        198     POP_EXCEPT                      
        200     RERAISE                         1
        202     PUSH_NULL                       
        204     LOAD_CONST                      13: '__pyarmor_exit_15665__'
        206     LOAD_CONST                      2: b'<COAddr>\x07\x00\x00\x1a\x94\x00\x00\x00\x00\x00\x00\x00\x00\x00\x00\x00\x00\x00\x00\x00'
        208     BUILD_TUPLE                     1
        210     CALL_FUNCTION_EX                0
        212     POP_TOP                         
        214     RETURN_VALUE                    
    [Exception Table]
        26 to 154 -> 174 [0] 
        174 to 196 -> 196 [1] lasti
