#decoded by lolz.live/mrpenny / t.me/zeus_jackpot
# ================================
# Примечания по Pyarmor:
# - Байт-код и объекты кода Pyarmor соответствуют стандартному Python, но присутствуют специальные вызовы функций среды выполнения (runtime) Pyarmor.
# - Вызовы строк — это не ошибки, а маркеры, которые обрабатываются Pyarmor во время выполнения.
#
# Руководство по декомпиляции (без среды выполнения):
# 1. Игнорируйте зашифрованные байты после `#`; используйте только строку до `#`.
# 2. Удалите "__pyarmor_enter_xxx__"(b"<COAddr>...") и "__pyarmor_leave_xxx__"(b"<COAddr>...") (пролог/эпилог).
# 3. "__pyarmor_assert_xxx__"(A) не является настоящим оператором assert.
#    - Если A — это имя или читаемая строка: замените на A.
#    - Если A — это (X, "Y"): замените на X.Y.
#    - Если A — это (X, "Y", Z): замените на X.Y = Z.
#    - В противном случае: выберите наиболее подходящую/логичную замену.
# 4. "__pyarmor_bcc_xxx__"(...) указывает на машинный (нативный) код; тело функции недоступно. Добавьте комментарий.
# ================================

[Code]
    File Name: <frozen multithon.events.album>
    Object Name: <module>
    Qualified Name: <module>
    Arg Count: 0
    Pos Only Arg Count: 0
    KW Only Arg Count: 0
    Stack Size: 6
    Flags: 0x20000000 (CO_PYARMOR_OBFUSCATED)
    [Names]
        '__assert_armored__'
        'asyncio'
        'time'
        'weakref'
        'common'
        'EventBuilder'
        'EventCommon'
        'name_inner_event'
        ''
        'utils'
        'tl'
        'types'
        'tl.custom.sendergetter'
        'SenderGetter'
        '_IGNORE_MAX_SIZE'
        '_IGNORE_MAX_AGE'
        '_IGNORE_DICT'
        '_HACK_DELAY'
        'AlbumHack'
        'Album'
    [Locals+Names]
    [Constants]
        '__pyarmor_assert_22371__'
        '__pyarmor_enter_22372__'
        b'<COAddr>\x07\x00\x00\x1a\xa8\x00\x00\x00\x00\x00\x00\x00\x00\x00\x00\x00\x00\x00\x00\x00'
        0
        None
        1
        (
            'EventBuilder'
            'EventCommon'
            'name_inner_event'
        )
        2
        (
            'utils'
        )
        (
            'types'
        )
        (
            'SenderGetter'
        )
        100
        5
        0.5
        [Code]
            File Name: <frozen multithon.events.album>
            Object Name: AlbumHack
            Qualified Name: AlbumHack
            Arg Count: 0
            Pos Only Arg Count: 0
            KW Only Arg Count: 0
            Stack Size: 5
            Flags: 0x20000000 (CO_PYARMOR_OBFUSCATED)
            [Names]
                '__name__'
                '__module__'
                '__qualname__'
                '__doc__'
                '__assert_armored__'
                '__init__'
                'extend'
                'deliver_event'
            [Locals+Names]
            [Constants]
                'AlbumHack'
                '\n    When receiving an album from a different data-center, they will come in\n    separate `Updates`, so we need to temporarily remember them for a while\n    and only after produce the event.\n\n    Of course events are not designed for this kind of wizardy, so this is\n    a dirty hack that gets the job done.\n\n    When cleaning up the code base we may want to figure out a better way\n    to do this, or just leave the album problem to the users; the update\n    handling code is bad enough as it is.\n    '
                '__pyarmor_assert_22374__'
                '__pyarmor_enter_22375__'
                b'<COAddr>\x07\x00\x00&(\x00\x00\x00\x00\x00\x00\x00\x00\x00\x00\x00\x00\x00\x00\x00'
                [Code]
                    File Name: <frozen multithon.events.album>
                    Object Name: __init__
                    Qualified Name: AlbumHack.__init__
                    Arg Count: 3
                    Pos Only Arg Count: 0
                    KW Only Arg Count: 0
                    Stack Size: 6
                    Flags: 0x20000003 (CO_OPTIMIZED | CO_NEWLOCALS | CO_PYARMOR_OBFUSCATED)
                    [Names]
                        'weakref'
                        'ref'
                        '_client'
                        '_event'
                        'loop'
                        'time'
                        '_HACK_DELAY'
                        '_due'
                        'create_task'
                        'deliver_event'
                    [Locals+Names]
                        'self'
                        'client'
                        'event'
                        '__assert_armored__'
                    [Constants]
                        None
                        '__pyarmor_assert_22377__'
                        '__pyarmor_enter_22378__'
                        b'<COAddr>\x05\x00\x00\x1a\x06\x01\x00\x00\x00\x00\x00\x00\x00\x00\x00\x00\x00\x00\x00\x00'
                        'deliver_event'   # b'\x81\xe6\x1d\x1f:\xec\xbb\xc0$\xff\x1b\xc5b\xf8'
                        (
                            'name'
                        )
                        '__pyarmor_exit_22379__'
                    [Disassembly]
                        0       NOP                             
                        2       NOP                             
                        4       PUSH_NULL                       
                        6       LOAD_CONST                      2: '__pyarmor_enter_22378__'
                        8       LOAD_CONST                      3: b'<COAddr>\x05\x00\x00\x1a\x06\x01\x00\x00\x00\x00\x00\x00\x00\x00\x00\x00\x00\x00\x00\x00'
                        10      BUILD_TUPLE                     1
                        12      CALL_FUNCTION_EX                0
                        14      POP_TOP                         
                        16      RESUME                          0
                        18      NOP                             
                        20      NOP                             
                        22      NOP                             
                        24      NOP                             
                        26      NOP                             
                        28      LOAD_GLOBAL                     1: NULL + weakref
                        38      LOAD_ATTR                       2: ref
                        58      LOAD_FAST                       1: client
                        60      CALL                            1
                        68      LOAD_FAST                       0: self
                        70      STORE_ATTR                      2: _client
                        80      LOAD_FAST                       2: event
                        82      LOAD_FAST                       0: self
                        84      STORE_ATTR                      3: _event
                        94      LOAD_FAST                       1: client
                        96      LOAD_ATTR                       8: loop
                        116     LOAD_ATTR                       11: time
                        136     CALL                            0
                        144     LOAD_GLOBAL                     12: _HACK_DELAY
                        154     BINARY_OP                       0 (+)
                        158     LOAD_FAST                       0: self
                        160     STORE_ATTR                      7: _due
                        170     LOAD_FAST                       1: client
                        172     LOAD_ATTR                       8: loop
                        192     LOAD_ATTR                       17: create_task
                        212     LOAD_FAST                       0: self
                        214     LOAD_ATTR                       19: deliver_event
                        234     CALL                            0
                        242     PUSH_NULL                       
                        244     LOAD_CONST                      1: '__pyarmor_assert_22377__'
                        246     LOAD_CONST                      4: 'deliver_event'   # b'\x81\xe6\x1d\x1f:\xec\xbb\xc0$\xff\x1b\xc5b\xf8'
                        248     CALL                            1
                        256     KW_NAMES                        5: ('name',)
                        258     CALL                            2
                        266     POP_TOP                         
                        268     LOAD_CONST                      0: None
                        270     NOP                             
                        272     NOP                             
                        274     NOP                             
                        276     JUMP_FORWARD                    19 (to 316)
                        284     POP_TOP                         
                        286     RETURN_CONST                    0: None
                        288     PUSH_EXC_INFO                   
                        290     PUSH_NULL                       
                        292     LOAD_CONST                      6: '__pyarmor_exit_22379__'
                        294     NOP                             
                        296     LOAD_CONST                      3: b'<COAddr>\x05\x00\x00\x1a\x06\x01\x00\x00\x00\x00\x00\x00\x00\x00\x00\x00\x00\x00\x00\x00'
                        298     CALL                            1
                        306     POP_TOP                         
                        308     RERAISE                         0
                        310     COPY                            3
                        312     POP_EXCEPT                      
                        314     RERAISE                         1
                        316     PUSH_NULL                       
                        318     LOAD_CONST                      6: '__pyarmor_exit_22379__'
                        320     LOAD_CONST                      3: b'<COAddr>\x05\x00\x00\x1a\x06\x01\x00\x00\x00\x00\x00\x00\x00\x00\x00\x00\x00\x00\x00\x00'
                        322     BUILD_TUPLE                     1
                        324     CALL_FUNCTION_EX                0
                        326     POP_TOP                         
                        328     RETURN_VALUE                    
                    [Exception Table]
                        28 to 268 -> 288 [0] 
                        288 to 310 -> 310 [1] lasti
                [Code]
                    File Name: <frozen multithon.events.album>
                    Object Name: extend
                    Qualified Name: AlbumHack.extend
                    Arg Count: 2
                    Pos Only Arg Count: 0
                    KW Only Arg Count: 0
                    Stack Size: 5
                    Flags: 0x20000003 (CO_OPTIMIZED | CO_NEWLOCALS | CO_PYARMOR_OBFUSCATED)
                    [Names]
                        '_client'
                        '_event'
                        'messages'
                        'extend'
                        'loop'
                        'time'
                        '_HACK_DELAY'
                        '_due'
                    [Locals+Names]
                        'self'
                        'messages'
                        '__assert_armored__'
                        '_var_var_0'
                    [Constants]
                        None
                        '__pyarmor_assert_22380__'
                        '__pyarmor_enter_22381__'
                        b'<COAddr>\x05\x00\x00\x1a\xd0\x00\x00\x00\x00\x00\x00\x00\x00\x00\x00\x00\x00\x00\x00\x00'
                        '__pyarmor_exit_22382__'
                    [Disassembly]
                        0       NOP                             
                        2       NOP                             
                        4       PUSH_NULL                       
                        6       LOAD_CONST                      2: '__pyarmor_enter_22381__'
                        8       LOAD_CONST                      3: b'<COAddr>\x05\x00\x00\x1a\xd0\x00\x00\x00\x00\x00\x00\x00\x00\x00\x00\x00\x00\x00\x00\x00'
                        10      BUILD_TUPLE                     1
                        12      CALL_FUNCTION_EX                0
                        14      POP_TOP                         
                        16      RESUME                          0
                        18      NOP                             
                        20      NOP                             
                        22      NOP                             
                        24      NOP                             
                        26      NOP                             
                        28      LOAD_FAST                       0: self
                        30      LOAD_ATTR                       1: _client
                        50      CALL                            0
                        58      STORE_FAST                      3: _var_var_0
                        60      LOAD_FAST                       3: _var_var_0
                        62      POP_JUMP_IF_FALSE               75 (to 214)
                        64      LOAD_FAST                       0: self
                        66      LOAD_ATTR                       2: _event
                        86      LOAD_ATTR                       4: messages
                        106     LOAD_ATTR                       7: extend
                        126     LOAD_FAST                       1: messages
                        128     CALL                            1
                        136     POP_TOP                         
                        138     LOAD_FAST                       3: _var_var_0
                        140     LOAD_ATTR                       8: loop
                        160     LOAD_ATTR                       11: time
                        180     CALL                            0
                        188     LOAD_GLOBAL                     12: _HACK_DELAY
                        198     BINARY_OP                       0 (+)
                        202     LOAD_FAST                       0: self
                        204     STORE_ATTR                      7: _due
                        214     LOAD_CONST                      0: None
                        216     NOP                             
                        218     NOP                             
                        220     NOP                             
                        222     JUMP_FORWARD                    19 (to 262)
                        230     POP_TOP                         
                        232     RETURN_CONST                    0: None
                        234     PUSH_EXC_INFO                   
                        236     PUSH_NULL                       
                        238     LOAD_CONST                      4: '__pyarmor_exit_22382__'
                        240     NOP                             
                        242     LOAD_CONST                      3: b'<COAddr>\x05\x00\x00\x1a\xd0\x00\x00\x00\x00\x00\x00\x00\x00\x00\x00\x00\x00\x00\x00\x00'
                        244     CALL                            1
                        252     POP_TOP                         
                        254     RERAISE                         0
                        256     COPY                            3
                        258     POP_EXCEPT                      
                        260     RERAISE                         1
                        262     PUSH_NULL                       
                        264     LOAD_CONST                      4: '__pyarmor_exit_22382__'
                        266     LOAD_CONST                      3: b'<COAddr>\x05\x00\x00\x1a\xd0\x00\x00\x00\x00\x00\x00\x00\x00\x00\x00\x00\x00\x00\x00\x00'
                        268     BUILD_TUPLE                     1
                        270     CALL_FUNCTION_EX                0
                        272     POP_TOP                         
                        274     RETURN_VALUE                    
                    [Exception Table]
                        28 to 214 -> 234 [0] 
                        234 to 256 -> 256 [1] lasti
                [Code]
                    File Name: <frozen multithon.events.album>
                    Object Name: deliver_event
                    Qualified Name: AlbumHack.deliver_event
                    Arg Count: 1
                    Pos Only Arg Count: 0
                    KW Only Arg Count: 0
                    Stack Size: 5
                    Flags: 0x20000083 (CO_OPTIMIZED | CO_NEWLOCALS | CO_COROUTINE | CO_PYARMOR_OBFUSCATED)
                    [Names]
                        '_client'
                        '_due'
                        'loop'
                        'time'
                        '_dispatch_event'
                        '_event'
                        'asyncio'
                        'sleep'
                    [Locals+Names]
                        'self'
                        '__assert_armored__'
                        '_var_var_0'
                        '_var_var_1'
                    [Constants]
                        None
                        '__pyarmor_assert_22383__'
                        '__pyarmor_enter_22384__'
                        b'<COAddr>\x07\x00\x00\x1e8\x01\x00\x00\x00\x00\x00\x00\x00\x00\x00\x00\x00\x00\x00\x00'
                        '__pyarmor_exit_22385__'
                        0
                    [Disassembly]
                        0       RETURN_GENERATOR                
                        2       POP_TOP                         
                        4       NOP                             
                        6       NOP                             
                        8       PUSH_NULL                       
                        10      LOAD_CONST                      2: '__pyarmor_enter_22384__'
                        12      LOAD_CONST                      3: b'<COAddr>\x07\x00\x00\x1e8\x01\x00\x00\x00\x00\x00\x00\x00\x00\x00\x00\x00\x00\x00\x00'
                        14      BUILD_TUPLE                     1
                        16      CALL_FUNCTION_EX                0
                        18      POP_TOP                         
                        20      RESUME                          0
                        22      NOP                             
                        24      NOP                             
                        26      NOP                             
                        28      NOP                             
                        30      NOP                             
                        32      NOP                             
                        34      LOAD_FAST                       0: self
                        36      LOAD_ATTR                       1: _client
                        56      CALL                            0
                        64      STORE_FAST                      2: _var_var_0
                        66      LOAD_FAST                       2: _var_var_0
                        68      POP_JUMP_IF_NOT_NONE            11 (to 92)
                        70      NOP                             
                        72      LOAD_CONST                      0: None
                        74      NOP                             
                        76      NOP                             
                        78      NOP                             
                        80      JUMP_FORWARD                    146 (to 374)
                        88      POP_TOP                         
                        90      RETURN_CONST                    0: None
                        92      LOAD_FAST                       0: self
                        94      LOAD_ATTR                       2: _due
                        114     LOAD_FAST                       2: _var_var_0
                        116     LOAD_ATTR                       4: loop
                        136     LOAD_ATTR                       7: time
                        156     CALL                            0
                        164     BINARY_OP                       10 (-)
                        168     STORE_FAST                      3: _var_var_1
                        170     LOAD_FAST                       3: _var_var_1
                        172     LOAD_CONST                      5: 0
                        174     COMPARE_OP                      26 (<=)
                        178     POP_JUMP_IF_FALSE               46 (to 272)
                        180     LOAD_FAST                       2: _var_var_0
                        182     LOAD_ATTR                       9: _dispatch_event
                        202     LOAD_FAST                       0: self
                        204     LOAD_ATTR                       10: _event
                        224     CALL                            1
                        232     GET_AWAITABLE                   0
                        234     LOAD_CONST                      0: None
                        236     SEND                            3 (to 244)
                        240     YIELD_VALUE                     3
                        242     RESUME                          3
                        244     JUMP_BACKWARD_NO_INTERRUPT      5 (to 236)
                        246     END_SEND                        
                        248     POP_TOP                         
                        250     NOP                             
                        252     LOAD_CONST                      0: None
                        254     NOP                             
                        256     NOP                             
                        258     NOP                             
                        260     JUMP_FORWARD                    56 (to 374)
                        268     POP_TOP                         
                        270     RETURN_CONST                    0: None
                        272     DELETE_FAST                     2: _var_var_0
                        274     LOAD_GLOBAL                     13: NULL + asyncio
                        284     LOAD_ATTR                       14: sleep
                        304     LOAD_FAST                       3: _var_var_1
                        306     CALL                            1
                        314     GET_AWAITABLE                   0
                        316     LOAD_CONST                      0: None
                        318     SEND                            3 (to 326)
                        322     YIELD_VALUE                     3
                        324     RESUME                          3
                        326     JUMP_BACKWARD_NO_INTERRUPT      5 (to 318)
                        328     END_SEND                        
                        330     POP_TOP                         
                        332     JUMP_BACKWARD                   150 (to 34)
                        334     CLEANUP_THROW                   
                        336     JUMP_BACKWARD                   46 (to 246)
                        338     CLEANUP_THROW                   
                        340     JUMP_BACKWARD                   7 (to 328)
                        342     PUSH_EXC_INFO                   
                        344     PUSH_NULL                       
                        346     LOAD_CONST                      4: '__pyarmor_exit_22385__'
                        348     NOP                             
                        350     LOAD_CONST                      3: b'<COAddr>\x07\x00\x00\x1e8\x01\x00\x00\x00\x00\x00\x00\x00\x00\x00\x00\x00\x00\x00\x00'
                        352     CALL                            1
                        360     POP_TOP                         
                        362     RERAISE                         0
                        364     COPY                            3
                        366     POP_EXCEPT                      
                        368     RERAISE                         1
                        370     CALL_INTRINSIC_1                3 (INTRINSIC_STOPITERATION_ERROR)
                        372     RERAISE                         1
                        374     PUSH_NULL                       
                        376     LOAD_CONST                      4: '__pyarmor_exit_22385__'
                        378     LOAD_CONST                      3: b'<COAddr>\x07\x00\x00\x1e8\x01\x00\x00\x00\x00\x00\x00\x00\x00\x00\x00\x00\x00\x00\x00'
                        380     BUILD_TUPLE                     1
                        382     CALL_FUNCTION_EX                0
                        384     POP_TOP                         
                        386     RETURN_VALUE                    
                    [Exception Table]
                        4 to 30 -> 370 [0] lasti
                        32 to 70 -> 342 [0] 
                        72 to 92 -> 370 [0] lasti
                        92 to 240 -> 342 [0] 
                        240 to 242 -> 334 [2] 
                        242 to 250 -> 342 [0] 
                        252 to 272 -> 370 [0] lasti
                        272 to 322 -> 342 [0] 
                        322 to 324 -> 338 [2] 
                        324 to 336 -> 342 [0] 
                        338 to 340 -> 342 [0] 
                        342 to 364 -> 364 [1] lasti
                        364 to 370 -> 370 [0] lasti
                '__pyarmor_exit_22376__'
                None
            [Disassembly]
                0       NOP                             
                2       LOAD_NAME                       0: __name__
                4       STORE_NAME                      1: __module__
                6       LOAD_CONST                      0: 'AlbumHack'
                8       STORE_NAME                      2: __qualname__
                10      LOAD_CONST                      1: '\n    When receiving an album from a different data-center, they will come in\n    separate `Updates`, so we need to temporarily remember them for a while\n    and only after produce the event.\n\n    Of course events are not designed for this kind of wizardy, so this is\n    a dirty hack that gets the job done.\n\n    When cleaning up the code base we may want to figure out a better way\n    to do this, or just leave the album problem to the users; the update\n    handling code is bad enough as it is.\n    '
                12      STORE_NAME                      3: __doc__
                14      NOP                             
                16      PUSH_NULL                       
                18      LOAD_CONST                      3: '__pyarmor_enter_22375__'
                20      LOAD_CONST                      4: b'<COAddr>\x07\x00\x00&(\x00\x00\x00\x00\x00\x00\x00\x00\x00\x00\x00\x00\x00\x00\x00'
                22      BUILD_TUPLE                     1
                24      CALL_FUNCTION_EX                0
                26      POP_TOP                         
                28      RESUME                          0
                30      NOP                             
                32      NOP                             
                34      NOP                             
                36      NOP                             
                38      NOP                             
                40      LOAD_CONST                      5: <CODE> __init__
                42      MAKE_FUNCTION                   0
                44      STORE_NAME                      5: __init__
                46      LOAD_CONST                      6: <CODE> extend
                48      MAKE_FUNCTION                   0
                50      STORE_NAME                      6: extend
                52      LOAD_CONST                      7: <CODE> deliver_event
                54      MAKE_FUNCTION                   0
                56      STORE_NAME                      7: deliver_event
                58      LOAD_CONST                      9: None
                60      NOP                             
                62      NOP                             
                64      NOP                             
                66      JUMP_FORWARD                    19 (to 106)
                74      POP_TOP                         
                76      RETURN_CONST                    9: None
                78      PUSH_EXC_INFO                   
                80      PUSH_NULL                       
                82      LOAD_CONST                      8: '__pyarmor_exit_22376__'
                84      NOP                             
                86      LOAD_CONST                      4: b'<COAddr>\x07\x00\x00&(\x00\x00\x00\x00\x00\x00\x00\x00\x00\x00\x00\x00\x00\x00\x00'
                88      CALL                            1
                96      POP_TOP                         
                98      RERAISE                         0
                100     COPY                            3
                102     POP_EXCEPT                      
                104     RERAISE                         1
                106     PUSH_NULL                       
                108     LOAD_CONST                      8: '__pyarmor_exit_22376__'
                110     LOAD_CONST                      4: b'<COAddr>\x07\x00\x00&(\x00\x00\x00\x00\x00\x00\x00\x00\x00\x00\x00\x00\x00\x00\x00'
                112     BUILD_TUPLE                     1
                114     CALL_FUNCTION_EX                0
                116     POP_TOP                         
                118     RETURN_VALUE                    
            [Exception Table]
                40 to 58 -> 78 [0] 
                78 to 100 -> 100 [1] lasti
        'AlbumHack'
        [Code]
            File Name: <frozen multithon.events.album>
            Object Name: Album
            Qualified Name: Album
            Arg Count: 0
            Pos Only Arg Count: 0
            KW Only Arg Count: 0
            Stack Size: 6
            Flags: 0x20000000 (CO_PYARMOR_OBFUSCATED)
            [Names]
                '__name__'
                '__module__'
                '__qualname__'
                '__doc__'
                '__assert_armored__'
                '__init__'
                'classmethod'
                'build'
                'filter'
                'EventCommon'
                'SenderGetter'
                'Event'
                '__classcell__'
            [Locals+Names]
                '__class__'
            [Constants]
                'Album'
                "\n    Occurs whenever you receive an album. This event only exists\n    to ease dealing with an unknown amount of messages that belong\n    to the same album.\n\n    Example\n        .. code-block:: python\n\n            from multithon import events\n\n            @client.on(events.Album)\n            async def handler(event):\n                # Counting how many photos or videos the album has\n                print('Got an album with', len(event), 'items')\n\n                # Forwarding the album as a whole to some chat\n                event.forward_to(chat)\n\n                # Printing the caption\n                print(event.text)\n\n                # Replying to the fifth item in the album\n                await event.messages[4].reply('Cool!')\n    "
                '__pyarmor_assert_22386__'
                '__pyarmor_enter_22387__'
                b'<COAddr>\x05\x00\x00(f\x00\x00\x00\x00\x00\x00\x00\x00\x00\x00\x00\x00\x00\x00\x00'
                None
                False
                (
                    'blacklist_chats'
                    'func'
                )
                [Code]
                    File Name: <frozen multithon.events.album>
                    Object Name: __init__
                    Qualified Name: Album.__init__
                    Arg Count: 2
                    Pos Only Arg Count: 0
                    KW Only Arg Count: 2
                    Stack Size: 5
                    Flags: 0x20000003 (CO_OPTIMIZED | CO_NEWLOCALS | CO_PYARMOR_OBFUSCATED)
                    [Names]
                        'super'
                        '__init__'
                    [Locals+Names]
                        'self'
                        'chats'
                        'blacklist_chats'
                        'func'
                        '__assert_armored__'
                        '__class__'
                    [Constants]
                        None
                        '__pyarmor_assert_22389__'
                        '__pyarmor_enter_22390__'
                        b'<COAddr>\x07\x00\x00\x1c:\x00\x00\x00\x00\x00\x00\x00\x00\x00\x00\x00\x00\x00\x00\x00'
                        (
                            'blacklist_chats'
                            'func'
                        )
                        '__pyarmor_exit_22391__'
                    [Disassembly]
                        0       COPY_FREE_VARS                  1
                        2       NOP                             
                        4       NOP                             
                        6       PUSH_NULL                       
                        8       LOAD_CONST                      2: '__pyarmor_enter_22390__'
                        10      LOAD_CONST                      3: b'<COAddr>\x07\x00\x00\x1c:\x00\x00\x00\x00\x00\x00\x00\x00\x00\x00\x00\x00\x00\x00\x00'
                        12      BUILD_TUPLE                     1
                        14      CALL_FUNCTION_EX                0
                        16      POP_TOP                         
                        18      RESUME                          0
                        20      NOP                             
                        22      NOP                             
                        24      NOP                             
                        26      NOP                             
                        28      NOP                             
                        30      LOAD_GLOBAL                     0: super
                        40      LOAD_DEREF                      5: __class__
                        42      LOAD_FAST                       0: self
                        44      LOAD_SUPER_ATTR                 5: __init__
                        48      LOAD_FAST                       1: chats
                        50      LOAD_FAST                       2: blacklist_chats
                        52      LOAD_FAST                       3: func
                        54      KW_NAMES                        4: ('blacklist_chats', 'func')
                        56      CALL                            3
                        64      POP_TOP                         
                        66      LOAD_CONST                      0: None
                        68      NOP                             
                        70      NOP                             
                        72      NOP                             
                        74      JUMP_FORWARD                    19 (to 114)
                        82      POP_TOP                         
                        84      RETURN_CONST                    0: None
                        86      PUSH_EXC_INFO                   
                        88      PUSH_NULL                       
                        90      LOAD_CONST                      5: '__pyarmor_exit_22391__'
                        92      NOP                             
                        94      LOAD_CONST                      3: b'<COAddr>\x07\x00\x00\x1c:\x00\x00\x00\x00\x00\x00\x00\x00\x00\x00\x00\x00\x00\x00\x00'
                        96      CALL                            1
                        104     POP_TOP                         
                        106     RERAISE                         0
                        108     COPY                            3
                        110     POP_EXCEPT                      
                        112     RERAISE                         1
                        114     PUSH_NULL                       
                        116     LOAD_CONST                      5: '__pyarmor_exit_22391__'
                        118     LOAD_CONST                      3: b'<COAddr>\x07\x00\x00\x1c:\x00\x00\x00\x00\x00\x00\x00\x00\x00\x00\x00\x00\x00\x00\x00'
                        120     BUILD_TUPLE                     1
                        122     CALL_FUNCTION_EX                0
                        124     POP_TOP                         
                        126     RETURN_VALUE                    
                    [Exception Table]
                        30 to 66 -> 86 [0] 
                        86 to 108 -> 108 [1] lasti
                [Code]
                    File Name: <frozen multithon.events.album>
                    Object Name: build
                    Qualified Name: Album.build
                    Arg Count: 4
                    Pos Only Arg Count: 0
                    KW Only Arg Count: 0
                    Stack Size: 12
                    Flags: 0x20000003 (CO_OPTIMIZED | CO_NEWLOCALS | CO_PYARMOR_OBFUSCATED)
                    [Names]
                        'isinstance'
                        'types'
                        'UpdateNewMessage'
                        'UpdateNewChannelMessage'
                        'message'
                        'Message'
                        'Message_L204'
                        'Message_L199'
                        'Message_L195'
                        'grouped_id'
                        '_IGNORE_DICT'
                        'pop'
                        'id'
                        'time'
                        'len'
                        '_IGNORE_MAX_SIZE'
                        'items'
                        '_IGNORE_MAX_AGE'
                        'Event'
                    [Locals+Names]
                        'cls'
                        'update'
                        'others'
                        'self_id'
                        '__assert_armored__'
                        '_var_var_2'
                        '_var_var_3'
                        '_var_var_4'
                        '_var_var_5'
                        '_var_var_6'
                    [Constants]
                        None
                        '__pyarmor_assert_22392__'
                        '__pyarmor_enter_22393__'
                        b'<COAddr>\x07\x00\x00\x1az\x04\x00\x00\x00\x00\x00\x00\x00\x00\x00\x00\x00\x00\x00\x00'
                        '__pyarmor_exit_22394__'
                    [Disassembly]
                        0       NOP                             
                        2       NOP                             
                        4       PUSH_NULL                       
                        6       LOAD_CONST                      2: '__pyarmor_enter_22393__'
                        8       LOAD_CONST                      3: b'<COAddr>\x07\x00\x00\x1az\x04\x00\x00\x00\x00\x00\x00\x00\x00\x00\x00\x00\x00\x00\x00'
                        10      BUILD_TUPLE                     1
                        12      CALL_FUNCTION_EX                0
                        14      POP_TOP                         
                        16      RESUME                          0
                        18      NOP                             
                        20      NOP                             
                        22      NOP                             
                        24      NOP                             
                        26      NOP                             
                        28      LOAD_FAST                       1: update
                        30      BUILD_LIST                      1
                        32      STORE_FAST                      2: others
                        34      LOAD_GLOBAL                     1: NULL + isinstance
                        44      LOAD_FAST                       1: update
                        46      LOAD_GLOBAL                     2: types
                        56      LOAD_ATTR                       4: UpdateNewMessage
                        76      LOAD_GLOBAL                     2: types
                        86      LOAD_ATTR                       6: UpdateNewChannelMessage
                        106     BUILD_TUPLE                     2
                        108     CALL                            2
                        116     POP_JUMP_IF_FALSE               505 (to 1130)
                        120     LOAD_GLOBAL                     1: NULL + isinstance
                        130     LOAD_FAST                       1: update
                        132     LOAD_ATTR                       8: message
                        152     LOAD_GLOBAL                     2: types
                        162     LOAD_ATTR                       10: Message
                        182     LOAD_GLOBAL                     2: types
                        192     LOAD_ATTR                       12: Message_L204
                        212     LOAD_GLOBAL                     2: types
                        222     LOAD_ATTR                       14: Message_L199
                        242     LOAD_GLOBAL                     2: types
                        252     LOAD_ATTR                       16: Message_L195
                        272     BUILD_TUPLE                     4
                        274     CALL                            2
                        282     POP_JUMP_IF_TRUE                11 (to 306)
                        284     NOP                             
                        286     LOAD_CONST                      0: None
                        288     NOP                             
                        290     NOP                             
                        292     JUMP_FORWARD                    452 (to 1200)
                        302     POP_TOP                         
                        304     RETURN_CONST                    0: None
                        306     LOAD_FAST                       1: update
                        308     LOAD_ATTR                       8: message
                        328     LOAD_ATTR                       18: grouped_id
                        348     STORE_FAST                      5: _var_var_2
                        350     LOAD_FAST                       5: _var_var_2
                        352     POP_JUMP_IF_NOT_NONE            11 (to 376)
                        354     NOP                             
                        356     LOAD_CONST                      0: None
                        358     NOP                             
                        360     NOP                             
                        362     JUMP_FORWARD                    417 (to 1200)
                        372     POP_TOP                         
                        374     RETURN_CONST                    0: None
                        376     LOAD_GLOBAL                     20: _IGNORE_DICT
                        386     LOAD_ATTR                       23: pop
                        406     LOAD_GLOBAL                     25: NULL + id
                        416     LOAD_FAST                       1: update
                        418     CALL                            1
                        426     LOAD_CONST                      0: None
                        428     CALL                            2
                        436     POP_JUMP_IF_FALSE               11 (to 460)
                        438     NOP                             
                        440     LOAD_CONST                      0: None
                        442     NOP                             
                        444     NOP                             
                        446     JUMP_FORWARD                    375 (to 1200)
                        456     POP_TOP                         
                        458     RETURN_CONST                    0: None
                        460     LOAD_GLOBAL                     27: NULL + time
                        470     LOAD_ATTR                       26: time
                        490     CALL                            0
                        498     STORE_FAST                      6: _var_var_3
                        500     LOAD_GLOBAL                     29: NULL + len
                        510     LOAD_GLOBAL                     20: _IGNORE_DICT
                        520     CALL                            1
                        528     LOAD_GLOBAL                     30: _IGNORE_MAX_SIZE
                        538     COMPARE_OP                      68 (>)
                        542     POP_JUMP_IF_FALSE               64 (to 672)
                        544     LOAD_GLOBAL                     20: _IGNORE_DICT
                        554     LOAD_ATTR                       33: items
                        574     CALL                            0
                        582     GET_ITER                        
                        584     LOAD_FAST_AND_CLEAR             7: _var_var_4
                        586     LOAD_FAST_AND_CLEAR             8: _var_var_5
                        588     SWAP                            3
                        590     BUILD_LIST                      0
                        592     SWAP                            2
                        594     FOR_ITER                        20 (to 636)
                        598     UNPACK_SEQUENCE                 2
                        602     STORE_FAST                      7: _var_var_4
                        604     STORE_FAST                      8: _var_var_5
                        606     LOAD_FAST                       6: _var_var_3
                        608     LOAD_FAST                       8: _var_var_5
                        610     BINARY_OP                       10 (-)
                        614     LOAD_GLOBAL                     34: _IGNORE_MAX_AGE
                        624     COMPARE_OP                      68 (>)
                        628     POP_JUMP_IF_TRUE                1 (to 632)
                        630     JUMP_BACKWARD                   19 (to 594)
                        632     LOAD_FAST                       7: _var_var_4
                        634     LIST_APPEND                     2
                        636     JUMP_BACKWARD                   22 (to 594)
                        638     END_FOR                         
                        640     SWAP                            3
                        642     STORE_FAST                      8: _var_var_5
                        644     STORE_FAST                      7: _var_var_4
                        646     GET_ITER                        
                        648     FOR_ITER                        9 (to 668)
                        652     STORE_FAST                      7: _var_var_4
                        654     LOAD_GLOBAL                     20: _IGNORE_DICT
                        664     LOAD_FAST                       7: _var_var_4
                        666     DELETE_SUBSCR                   
                        668     JUMP_BACKWARD                   11 (to 648)
                        670     END_FOR                         
                        672     LOAD_FAST                       2: others
                        674     GET_ITER                        
                        676     FOR_ITER                        25 (to 728)
                        680     STORE_FAST                      9: _var_var_6
                        682     LOAD_FAST                       9: _var_var_6
                        684     LOAD_FAST                       1: update
                        686     IS_OP                           1 (is not)
                        688     POP_JUMP_IF_TRUE                1 (to 692)
                        690     JUMP_BACKWARD                   8 (to 676)
                        692     LOAD_FAST                       6: _var_var_3
                        694     LOAD_GLOBAL                     20: _IGNORE_DICT
                        704     LOAD_GLOBAL                     25: NULL + id
                        714     LOAD_FAST                       9: _var_var_6
                        716     CALL                            1
                        724     STORE_SUBSCR                    
                        728     JUMP_BACKWARD                   27 (to 676)
                        730     END_FOR                         
                        732     LOAD_FAST                       0: cls
                        734     LOAD_ATTR                       37: Event
                        754     LOAD_FAST                       2: others
                        756     GET_ITER                        
                        758     LOAD_FAST_AND_CLEAR             9: _var_var_6
                        760     SWAP                            2
                        762     BUILD_LIST                      0
                        764     SWAP                            2
                        766     FOR_ITER                        163 (to 1094)
                        770     STORE_FAST                      9: _var_var_6
                        772     LOAD_GLOBAL                     1: NULL + isinstance
                        782     LOAD_FAST                       9: _var_var_6
                        784     LOAD_GLOBAL                     2: types
                        794     LOAD_ATTR                       4: UpdateNewMessage
                        814     LOAD_GLOBAL                     2: types
                        824     LOAD_ATTR                       6: UpdateNewChannelMessage
                        844     BUILD_TUPLE                     2
                        846     CALL                            2
                        854     POP_JUMP_IF_FALSE               119 (to 1094)
                        856     LOAD_GLOBAL                     1: NULL + isinstance
                        866     LOAD_FAST                       9: _var_var_6
                        868     LOAD_ATTR                       8: message
                        888     LOAD_GLOBAL                     2: types
                        898     LOAD_ATTR                       10: Message
                        918     LOAD_GLOBAL                     2: types
                        928     LOAD_ATTR                       12: Message_L204
                        948     LOAD_GLOBAL                     2: types
                        958     LOAD_ATTR                       14: Message_L199
                        978     LOAD_GLOBAL                     2: types
                        988     LOAD_ATTR                       16: Message_L195
                        1008    BUILD_TUPLE                     4
                        1010    CALL                            2
                        1018    POP_JUMP_IF_FALSE               37 (to 1094)
                        1020    LOAD_FAST                       9: _var_var_6
                        1022    LOAD_ATTR                       8: message
                        1042    LOAD_ATTR                       18: grouped_id
                        1062    LOAD_FAST                       5: _var_var_2
                        1064    COMPARE_OP                      40 (==)
                        1068    POP_JUMP_IF_FALSE               12 (to 1094)
                        1070    LOAD_FAST                       9: _var_var_6
                        1072    LOAD_ATTR                       8: message
                        1092    LIST_APPEND                     2
                        1094    JUMP_BACKWARD                   165 (to 766)
                        1096    END_FOR                         
                        1098    SWAP                            2
                        1100    STORE_FAST                      9: _var_var_6
                        1102    CALL                            1
                        1110    NOP                             
                        1112    NOP                             
                        1114    NOP                             
                        1116    JUMP_FORWARD                    41 (to 1200)
                        1118    CALL                            1
                        1126    POP_TOP                         
                        1128    RETURN_VALUE                    
                        1130    LOAD_CONST                      0: None
                        1132    NOP                             
                        1134    NOP                             
                        1136    NOP                             
                        1138    JUMP_FORWARD                    30 (to 1200)
                        1146    POP_TOP                         
                        1148    RETURN_CONST                    0: None
                        1150    SWAP                            2
                        1152    POP_TOP                         
                        1154    SWAP                            3
                        1156    STORE_FAST                      8: _var_var_5
                        1158    STORE_FAST                      7: _var_var_4
                        1160    RERAISE                         0
                        1162    SWAP                            2
                        1164    POP_TOP                         
                        1166    SWAP                            2
                        1168    STORE_FAST                      9: _var_var_6
                        1170    RERAISE                         0
                        1172    PUSH_EXC_INFO                   
                        1174    PUSH_NULL                       
                        1176    LOAD_CONST                      4: '__pyarmor_exit_22394__'
                        1178    NOP                             
                        1180    LOAD_CONST                      3: b'<COAddr>\x07\x00\x00\x1az\x04\x00\x00\x00\x00\x00\x00\x00\x00\x00\x00\x00\x00\x00\x00'
                        1182    CALL                            1
                        1190    POP_TOP                         
                        1192    RERAISE                         0
                        1194    COPY                            3
                        1196    POP_EXCEPT                      
                        1198    RERAISE                         1
                        1200    PUSH_NULL                       
                        1202    LOAD_CONST                      4: '__pyarmor_exit_22394__'
                        1204    LOAD_CONST                      3: b'<COAddr>\x07\x00\x00\x1az\x04\x00\x00\x00\x00\x00\x00\x00\x00\x00\x00\x00\x00\x00\x00'
                        1206    BUILD_TUPLE                     1
                        1208    CALL_FUNCTION_EX                0
                        1210    POP_TOP                         
                        1212    RETURN_VALUE                    
                    [Exception Table]
                        28 to 284 -> 1172 [0] 
                        306 to 354 -> 1172 [0] 
                        376 to 438 -> 1172 [0] 
                        460 to 590 -> 1172 [0] 
                        590 to 630 -> 1150 [3] 
                        632 to 640 -> 1150 [3] 
                        640 to 690 -> 1172 [0] 
                        692 to 762 -> 1172 [0] 
                        762 to 1098 -> 1162 [4] 
                        1098 to 1110 -> 1172 [0] 
                        1150 to 1172 -> 1172 [0] 
                        1172 to 1194 -> 1194 [1] lasti
                [Code]
                    File Name: <frozen multithon.events.album>
                    Object Name: filter
                    Qualified Name: Album.filter
                    Arg Count: 2
                    Pos Only Arg Count: 0
                    KW Only Arg Count: 0
                    Stack Size: 5
                    Flags: 0x20000003 (CO_OPTIMIZED | CO_NEWLOCALS | CO_PYARMOR_OBFUSCATED)
                    [Names]
                        'len'
                        'messages'
                        'super'
                        'filter'
                    [Locals+Names]
                        'self'
                        'event'
                        '__assert_armored__'
                        '__class__'
                    [Constants]
                        None
                        '__pyarmor_assert_22395__'
                        '__pyarmor_enter_22396__'
                        b'<COAddr>\x05\x00\x00\x1cv\x00\x00\x00\x00\x00\x00\x00\x00\x00\x00\x00\x00\x00\x00\x00'
                        1
                        '__pyarmor_exit_22397__'
                    [Disassembly]
                        0       COPY_FREE_VARS                  1
                        2       NOP                             
                        4       NOP                             
                        6       PUSH_NULL                       
                        8       LOAD_CONST                      2: '__pyarmor_enter_22396__'
                        10      LOAD_CONST                      3: b'<COAddr>\x05\x00\x00\x1cv\x00\x00\x00\x00\x00\x00\x00\x00\x00\x00\x00\x00\x00\x00\x00'
                        12      BUILD_TUPLE                     1
                        14      CALL_FUNCTION_EX                0
                        16      POP_TOP                         
                        18      RESUME                          0
                        20      NOP                             
                        22      NOP                             
                        24      NOP                             
                        26      NOP                             
                        28      NOP                             
                        30      LOAD_GLOBAL                     1: NULL + len
                        40      LOAD_FAST                       1: event
                        42      LOAD_ATTR                       2: messages
                        62      CALL                            1
                        70      LOAD_CONST                      4: 1
                        72      COMPARE_OP                      68 (>)
                        76      POP_JUMP_IF_FALSE               24 (to 126)
                        78      LOAD_GLOBAL                     4: super
                        88      LOAD_DEREF                      3: __class__
                        90      LOAD_FAST                       0: self
                        92      LOAD_SUPER_ATTR                 13: filter
                        96      LOAD_FAST                       1: event
                        98      CALL                            1
                        106     NOP                             
                        108     NOP                             
                        110     NOP                             
                        112     JUMP_FORWARD                    30 (to 174)
                        114     CALL                            1
                        122     POP_TOP                         
                        124     RETURN_VALUE                    
                        126     LOAD_CONST                      0: None
                        128     NOP                             
                        130     NOP                             
                        132     NOP                             
                        134     JUMP_FORWARD                    19 (to 174)
                        142     POP_TOP                         
                        144     RETURN_CONST                    0: None
                        146     PUSH_EXC_INFO                   
                        148     PUSH_NULL                       
                        150     LOAD_CONST                      5: '__pyarmor_exit_22397__'
                        152     NOP                             
                        154     LOAD_CONST                      3: b'<COAddr>\x05\x00\x00\x1cv\x00\x00\x00\x00\x00\x00\x00\x00\x00\x00\x00\x00\x00\x00\x00'
                        156     CALL                            1
                        164     POP_TOP                         
                        166     RERAISE                         0
                        168     COPY                            3
                        170     POP_EXCEPT                      
                        172     RERAISE                         1
                        174     PUSH_NULL                       
                        176     LOAD_CONST                      5: '__pyarmor_exit_22397__'
                        178     LOAD_CONST                      3: b'<COAddr>\x05\x00\x00\x1cv\x00\x00\x00\x00\x00\x00\x00\x00\x00\x00\x00\x00\x00\x00\x00'
                        180     BUILD_TUPLE                     1
                        182     CALL_FUNCTION_EX                0
                        184     POP_TOP                         
                        186     RETURN_VALUE                    
                    [Exception Table]
                        30 to 106 -> 146 [0] 
                        146 to 168 -> 168 [1] lasti
                [Code]
                    File Name: <frozen multithon.events.album>
                    Object Name: Event
                    Qualified Name: Album.Event
                    Arg Count: 0
                    Pos Only Arg Count: 0
                    KW Only Arg Count: 0
                    Stack Size: 5
                    Flags: 0x20000000 (CO_PYARMOR_OBFUSCATED)
                    [Names]
                        '__name__'
                        '__module__'
                        '__qualname__'
                        '__doc__'
                        '__assert_armored__'
                        '__init__'
                        '_set_client'
                        'property'
                        'grouped_id'
                        'text'
                        'raw_text'
                        'is_reply'
                        'forward'
                        'get_reply_message'
                        'respond'
                        'reply'
                        'forward_to'
                        'edit'
                        'delete'
                        'mark_read'
                        'pin'
                        '__len__'
                        '__iter__'
                        '__getitem__'
                        '__classcell__'
                    [Locals+Names]
                        '__class__'
                    [Constants]
                        'Album.Event'
                        '\n        Represents the event of a new album.\n\n        Members:\n            messages (Sequence[`Message <telethon.tl.custom.message.Message>`]):\n                The list of messages belonging to the same album.\n        '
                        '__pyarmor_assert_22398__'
                        '__pyarmor_enter_22399__'
                        b'<COAddr>\x05\x00\x00(\xc8\x00\x00\x00\x00\x00\x00\x00\x00\x00\x00\x00\x00\x00\x00\x00'
                        [Code]
                            File Name: <frozen multithon.events.album>
                            Object Name: __init__
                            Qualified Name: Album.Event.__init__
                            Arg Count: 2
                            Pos Only Arg Count: 0
                            KW Only Arg Count: 0
                            Stack Size: 7
                            Flags: 0x20000003 (CO_OPTIMIZED | CO_NEWLOCALS | CO_PYARMOR_OBFUSCATED)
                            [Names]
                                'super'
                                '__init__'
                                'peer_id'
                                'id'
                                'bool'
                                'post'
                                'SenderGetter'
                                'sender_id'
                                'messages'
                            [Locals+Names]
                                'self'
                                'messages'
                                '__assert_armored__'
                                '_var_var_7'
                                '__class__'
                            [Constants]
                                None
                                '__pyarmor_assert_22401__'
                                '__pyarmor_enter_22402__'
                                b'<COAddr>\x05\x00\x00\x1c\xe0\x00\x00\x00\x00\x00\x00\x00\x00\x00\x00\x00\x00\x00\x00\x00'
                                0
                                (
                                    'chat_peer'
                                    'msg_id'
                                    'broadcast'
                                )
                                '__pyarmor_exit_22403__'
                            [Disassembly]
                                0       COPY_FREE_VARS                  1
                                2       NOP                             
                                4       NOP                             
                                6       PUSH_NULL                       
                                8       LOAD_CONST                      2: '__pyarmor_enter_22402__'
                                10      LOAD_CONST                      3: b'<COAddr>\x05\x00\x00\x1c\xe0\x00\x00\x00\x00\x00\x00\x00\x00\x00\x00\x00\x00\x00\x00\x00'
                                12      BUILD_TUPLE                     1
                                14      CALL_FUNCTION_EX                0
                                16      POP_TOP                         
                                18      RESUME                          0
                                20      NOP                             
                                22      NOP                             
                                24      NOP                             
                                26      NOP                             
                                28      NOP                             
                                30      LOAD_FAST                       1: messages
                                32      LOAD_CONST                      4: 0
                                34      BINARY_SUBSCR                   
                                38      STORE_FAST                      3: _var_var_7
                                40      LOAD_GLOBAL                     0: super
                                50      LOAD_DEREF                      4: __class__
                                52      LOAD_FAST                       0: self
                                54      LOAD_SUPER_ATTR                 5: __init__
                                58      LOAD_FAST                       3: _var_var_7
                                60      LOAD_ATTR                       4: peer_id
                                80      LOAD_FAST                       3: _var_var_7
                                82      LOAD_ATTR                       6: id
                                102     LOAD_GLOBAL                     9: NULL + bool
                                112     LOAD_FAST                       3: _var_var_7
                                114     LOAD_ATTR                       10: post
                                134     CALL                            1
                                142     KW_NAMES                        5: ('chat_peer', 'msg_id', 'broadcast')
                                144     CALL                            3
                                152     POP_TOP                         
                                154     LOAD_GLOBAL                     13: NULL + SenderGetter
                                164     LOAD_ATTR                       2: __init__
                                184     LOAD_FAST                       0: self
                                186     LOAD_FAST                       3: _var_var_7
                                188     LOAD_ATTR                       14: sender_id
                                208     CALL                            2
                                216     POP_TOP                         
                                218     LOAD_FAST                       1: messages
                                220     LOAD_FAST                       0: self
                                222     STORE_ATTR                      8: messages
                                232     LOAD_CONST                      0: None
                                234     NOP                             
                                236     NOP                             
                                238     NOP                             
                                240     JUMP_FORWARD                    19 (to 280)
                                248     POP_TOP                         
                                250     RETURN_CONST                    0: None
                                252     PUSH_EXC_INFO                   
                                254     PUSH_NULL                       
                                256     LOAD_CONST                      6: '__pyarmor_exit_22403__'
                                258     NOP                             
                                260     LOAD_CONST                      3: b'<COAddr>\x05\x00\x00\x1c\xe0\x00\x00\x00\x00\x00\x00\x00\x00\x00\x00\x00\x00\x00\x00\x00'
                                262     CALL                            1
                                270     POP_TOP                         
                                272     RERAISE                         0
                                274     COPY                            3
                                276     POP_EXCEPT                      
                                278     RERAISE                         1
                                280     PUSH_NULL                       
                                282     LOAD_CONST                      6: '__pyarmor_exit_22403__'
                                284     LOAD_CONST                      3: b'<COAddr>\x05\x00\x00\x1c\xe0\x00\x00\x00\x00\x00\x00\x00\x00\x00\x00\x00\x00\x00\x00\x00'
                                286     BUILD_TUPLE                     1
                                288     CALL_FUNCTION_EX                0
                                290     POP_TOP                         
                                292     RETURN_VALUE                    
                            [Exception Table]
                                30 to 232 -> 252 [0] 
                                252 to 274 -> 274 [1] lasti
                        [Code]
                            File Name: <frozen multithon.events.album>
                            Object Name: _set_client
                            Qualified Name: Album.Event._set_client
                            Arg Count: 2
                            Pos Only Arg Count: 0
                            KW Only Arg Count: 0
                            Stack Size: 6
                            Flags: 0x20000003 (CO_OPTIMIZED | CO_NEWLOCALS | CO_PYARMOR_OBFUSCATED)
                            [Names]
                                'super'
                                '_set_client'
                                'utils'
                                '_get_entity_pair'
                                'sender_id'
                                '_entities'
                                '_mb_entity_cache'
                                '_sender'
                                '_input_sender'
                                'messages'
                                '_finish_init'
                                'len'
                                '_albums'
                                'get'
                                'grouped_id'
                                'AlbumHack'
                                'extend'
                            [Locals+Names]
                                'self'
                                'client'
                                '__assert_armored__'
                                '_var_var_8'
                                '_var_var_9'
                                '__class__'
                            [Constants]
                                None
                                '__pyarmor_assert_22404__'
                                '__pyarmor_enter_22405__'
                                b'<COAddr>\x07\x00\x00\x1c\x10\x02\x00\x00\x00\x00\x00\x00\x00\x00\x00\x00\x00\x00\x00\x00'
                                1
                                '__pyarmor_exit_22406__'
                            [Disassembly]
                                0       COPY_FREE_VARS                  1
                                2       NOP                             
                                4       NOP                             
                                6       PUSH_NULL                       
                                8       LOAD_CONST                      2: '__pyarmor_enter_22405__'
                                10      LOAD_CONST                      3: b'<COAddr>\x07\x00\x00\x1c\x10\x02\x00\x00\x00\x00\x00\x00\x00\x00\x00\x00\x00\x00\x00\x00'
                                12      BUILD_TUPLE                     1
                                14      CALL_FUNCTION_EX                0
                                16      POP_TOP                         
                                18      RESUME                          0
                                20      NOP                             
                                22      NOP                             
                                24      NOP                             
                                26      NOP                             
                                28      NOP                             
                                30      LOAD_GLOBAL                     0: super
                                40      LOAD_DEREF                      5: __class__
                                42      LOAD_FAST                       0: self
                                44      LOAD_SUPER_ATTR                 5: _set_client
                                48      LOAD_FAST                       1: client
                                50      CALL                            1
                                58      POP_TOP                         
                                60      LOAD_GLOBAL                     5: NULL + utils
                                70      LOAD_ATTR                       6: _get_entity_pair
                                90      LOAD_FAST                       0: self
                                92      LOAD_ATTR                       8: sender_id
                                112     LOAD_FAST                       0: self
                                114     LOAD_ATTR                       10: _entities
                                134     LOAD_FAST                       1: client
                                136     LOAD_ATTR                       12: _mb_entity_cache
                                156     CALL                            3
                                164     UNPACK_SEQUENCE                 2
                                168     LOAD_FAST                       0: self
                                170     STORE_ATTR                      7: _sender
                                180     LOAD_FAST                       0: self
                                182     STORE_ATTR                      8: _input_sender
                                192     LOAD_FAST                       0: self
                                194     LOAD_ATTR                       18: messages
                                214     GET_ITER                        
                                216     FOR_ITER                        31 (to 280)
                                220     STORE_FAST                      3: _var_var_8
                                222     LOAD_FAST                       3: _var_var_8
                                224     LOAD_ATTR                       21: _finish_init
                                244     LOAD_FAST                       1: client
                                246     LOAD_FAST                       0: self
                                248     LOAD_ATTR                       10: _entities
                                268     LOAD_CONST                      0: None
                                270     CALL                            3
                                278     POP_TOP                         
                                280     JUMP_BACKWARD                   33 (to 216)
                                282     END_FOR                         
                                284     LOAD_GLOBAL                     23: NULL + len
                                294     LOAD_FAST                       0: self
                                296     LOAD_ATTR                       18: messages
                                316     CALL                            1
                                324     LOAD_CONST                      4: 1
                                326     COMPARE_OP                      40 (==)
                                330     POP_JUMP_IF_FALSE               102 (to 536)
                                332     LOAD_FAST                       1: client
                                334     LOAD_ATTR                       24: _albums
                                354     LOAD_ATTR                       27: get
                                374     LOAD_FAST                       0: self
                                376     LOAD_ATTR                       28: grouped_id
                                396     CALL                            1
                                404     STORE_FAST                      4: _var_var_9
                                406     LOAD_FAST                       4: _var_var_9
                                408     POP_JUMP_IF_NOT_NONE            36 (to 482)
                                410     LOAD_GLOBAL                     31: NULL + AlbumHack
                                420     LOAD_FAST                       1: client
                                422     LOAD_FAST                       0: self
                                424     CALL                            2
                                432     LOAD_FAST                       1: client
                                434     LOAD_ATTR                       24: _albums
                                454     LOAD_FAST                       0: self
                                456     LOAD_ATTR                       28: grouped_id
                                476     STORE_SUBSCR                    
                                480     JUMP_FORWARD                    27 (to 536)
                                482     LOAD_FAST                       4: _var_var_9
                                484     LOAD_ATTR                       33: extend
                                504     LOAD_FAST                       0: self
                                506     LOAD_ATTR                       18: messages
                                526     CALL                            1
                                534     POP_TOP                         
                                536     LOAD_CONST                      0: None
                                538     NOP                             
                                540     NOP                             
                                542     NOP                             
                                544     JUMP_FORWARD                    19 (to 584)
                                552     POP_TOP                         
                                554     RETURN_CONST                    0: None
                                556     PUSH_EXC_INFO                   
                                558     PUSH_NULL                       
                                560     LOAD_CONST                      5: '__pyarmor_exit_22406__'
                                562     NOP                             
                                564     LOAD_CONST                      3: b'<COAddr>\x07\x00\x00\x1c\x10\x02\x00\x00\x00\x00\x00\x00\x00\x00\x00\x00\x00\x00\x00\x00'
                                566     CALL                            1
                                574     POP_TOP                         
                                576     RERAISE                         0
                                578     COPY                            3
                                580     POP_EXCEPT                      
                                582     RERAISE                         1
                                584     PUSH_NULL                       
                                586     LOAD_CONST                      5: '__pyarmor_exit_22406__'
                                588     LOAD_CONST                      3: b'<COAddr>\x07\x00\x00\x1c\x10\x02\x00\x00\x00\x00\x00\x00\x00\x00\x00\x00\x00\x00\x00\x00'
                                590     BUILD_TUPLE                     1
                                592     CALL_FUNCTION_EX                0
                                594     POP_TOP                         
                                596     RETURN_VALUE                    
                            [Exception Table]
                                30 to 536 -> 556 [0] 
                                556 to 578 -> 578 [1] lasti
                        [Code]
                            File Name: <frozen multithon.events.album>
                            Object Name: grouped_id
                            Qualified Name: Album.Event.grouped_id
                            Arg Count: 1
                            Pos Only Arg Count: 0
                            KW Only Arg Count: 0
                            Stack Size: 5
                            Flags: 0x20000003 (CO_OPTIMIZED | CO_NEWLOCALS | CO_PYARMOR_OBFUSCATED)
                            [Names]
                                'messages'
                                'grouped_id'
                            [Locals+Names]
                                'self'
                                '__assert_armored__'
                            [Constants]
                                '\n            The shared ``grouped_id`` between all the messages.\n            '
                                '__pyarmor_assert_22407__'
                                '__pyarmor_enter_22408__'
                                b'<COAddr>\x07\x00\x00\x1aF\x00\x00\x00\x00\x00\x00\x00\x00\x00\x00\x00\x00\x00\x00\x00'
                                0
                                '__pyarmor_exit_22409__'
                            [Disassembly]
                                0       NOP                             
                                2       NOP                             
                                4       PUSH_NULL                       
                                6       LOAD_CONST                      2: '__pyarmor_enter_22408__'
                                8       LOAD_CONST                      3: b'<COAddr>\x07\x00\x00\x1aF\x00\x00\x00\x00\x00\x00\x00\x00\x00\x00\x00\x00\x00\x00\x00'
                                10      BUILD_TUPLE                     1
                                12      CALL_FUNCTION_EX                0
                                14      POP_TOP                         
                                16      RESUME                          0
                                18      NOP                             
                                20      NOP                             
                                22      NOP                             
                                24      NOP                             
                                26      NOP                             
                                28      LOAD_FAST                       0: self
                                30      LOAD_ATTR                       0: messages
                                50      LOAD_CONST                      4: 0
                                52      BINARY_SUBSCR                   
                                56      LOAD_ATTR                       2: grouped_id
                                76      NOP                             
                                78      NOP                             
                                80      NOP                             
                                82      JUMP_FORWARD                    20 (to 124)
                                84      CALL                            1
                                92      POP_TOP                         
                                94      RETURN_VALUE                    
                                96      PUSH_EXC_INFO                   
                                98      PUSH_NULL                       
                                100     LOAD_CONST                      5: '__pyarmor_exit_22409__'
                                102     NOP                             
                                104     LOAD_CONST                      3: b'<COAddr>\x07\x00\x00\x1aF\x00\x00\x00\x00\x00\x00\x00\x00\x00\x00\x00\x00\x00\x00\x00'
                                106     CALL                            1
                                114     POP_TOP                         
                                116     RERAISE                         0
                                118     COPY                            3
                                120     POP_EXCEPT                      
                                122     RERAISE                         1
                                124     PUSH_NULL                       
                                126     LOAD_CONST                      5: '__pyarmor_exit_22409__'
                                128     LOAD_CONST                      3: b'<COAddr>\x07\x00\x00\x1aF\x00\x00\x00\x00\x00\x00\x00\x00\x00\x00\x00\x00\x00\x00\x00'
                                130     BUILD_TUPLE                     1
                                132     CALL_FUNCTION_EX                0
                                134     POP_TOP                         
                                136     RETURN_VALUE                    
                            [Exception Table]
                                28 to 76 -> 96 [0] 
                                96 to 118 -> 118 [1] lasti
                        [Code]
                            File Name: <frozen multithon.events.album>
                            Object Name: text
                            Qualified Name: Album.Event.text
                            Arg Count: 1
                            Pos Only Arg Count: 0
                            KW Only Arg Count: 0
                            Stack Size: 5
                            Flags: 0x20000003 (CO_OPTIMIZED | CO_NEWLOCALS | CO_PYARMOR_OBFUSCATED)
                            [Names]
                                'next'
                                'messages'
                            [Locals+Names]
                                'self'
                                '__assert_armored__'
                            [Constants]
                                "\n            The message text of the first photo with a caption,\n            formatted using the client's default parse mode.\n            "
                                '__pyarmor_assert_22410__'
                                '__pyarmor_enter_22411__'
                                b'<COAddr>\x07\x00\x00\x1aN\x00\x00\x00\x00\x00\x00\x00\x00\x00\x00\x00\x00\x00\x00\x00'
                                [Code]
                                    File Name: <frozen multithon.events.album>
                                    Object Name: <genexpr>
                                    Qualified Name: Album.Event.text.<locals>.<genexpr>
                                    Arg Count: 1
                                    Pos Only Arg Count: 0
                                    KW Only Arg Count: 0
                                    Stack Size: 2
                                    Flags: 0x00000033 (CO_OPTIMIZED | CO_NEWLOCALS | CO_NESTED | CO_GENERATOR)
                                    [Names]
                                        'text'
                                    [Locals+Names]
                                        '.0'
                                        '_var_var_10'
                                    [Constants]
                                        None
                                    [Disassembly]
                                        0       RETURN_GENERATOR                
                                        2       POP_TOP                         
                                        4       RESUME                          0
                                        6       LOAD_FAST                       0: .0
                                        8       FOR_ITER                        29 (to 68)
                                        12      STORE_FAST                      1: _var_var_10
                                        14      LOAD_FAST                       1: _var_var_10
                                        16      LOAD_ATTR                       0: text
                                        36      POP_JUMP_IF_TRUE                1 (to 40)
                                        38      JUMP_BACKWARD                   16 (to 8)
                                        40      LOAD_FAST                       1: _var_var_10
                                        42      LOAD_ATTR                       0: text
                                        62      YIELD_VALUE                     1
                                        64      RESUME                          1
                                        66      POP_TOP                         
                                        68      JUMP_BACKWARD                   31 (to 8)
                                        70      END_FOR                         
                                        72      RETURN_CONST                    0: None
                                        74      CALL_INTRINSIC_1                3 (INTRINSIC_STOPITERATION_ERROR)
                                        76      RERAISE                         1
                                    [Exception Table]
                                        4 to 38 -> 74 [0] lasti
                                        40 to 74 -> 74 [0] lasti
                                ''
                                '__pyarmor_exit_22412__'
                            [Disassembly]
                                0       NOP                             
                                2       NOP                             
                                4       PUSH_NULL                       
                                6       LOAD_CONST                      2: '__pyarmor_enter_22411__'
                                8       LOAD_CONST                      3: b'<COAddr>\x07\x00\x00\x1aN\x00\x00\x00\x00\x00\x00\x00\x00\x00\x00\x00\x00\x00\x00\x00'
                                10      BUILD_TUPLE                     1
                                12      CALL_FUNCTION_EX                0
                                14      POP_TOP                         
                                16      RESUME                          0
                                18      NOP                             
                                20      NOP                             
                                22      NOP                             
                                24      NOP                             
                                26      NOP                             
                                28      LOAD_GLOBAL                     1: NULL + next
                                38      LOAD_CONST                      4: <CODE> <genexpr>
                                40      MAKE_FUNCTION                   0
                                42      LOAD_FAST                       0: self
                                44      LOAD_ATTR                       2: messages
                                64      GET_ITER                        
                                66      CALL                            0
                                74      LOAD_CONST                      5: ''
                                76      CALL                            2
                                84      NOP                             
                                86      NOP                             
                                88      NOP                             
                                90      JUMP_FORWARD                    20 (to 132)
                                92      CALL                            1
                                100     POP_TOP                         
                                102     RETURN_VALUE                    
                                104     PUSH_EXC_INFO                   
                                106     PUSH_NULL                       
                                108     LOAD_CONST                      6: '__pyarmor_exit_22412__'
                                110     NOP                             
                                112     LOAD_CONST                      3: b'<COAddr>\x07\x00\x00\x1aN\x00\x00\x00\x00\x00\x00\x00\x00\x00\x00\x00\x00\x00\x00\x00'
                                114     CALL                            1
                                122     POP_TOP                         
                                124     RERAISE                         0
                                126     COPY                            3
                                128     POP_EXCEPT                      
                                130     RERAISE                         1
                                132     PUSH_NULL                       
                                134     LOAD_CONST                      6: '__pyarmor_exit_22412__'
                                136     LOAD_CONST                      3: b'<COAddr>\x07\x00\x00\x1aN\x00\x00\x00\x00\x00\x00\x00\x00\x00\x00\x00\x00\x00\x00\x00'
                                138     BUILD_TUPLE                     1
                                140     CALL_FUNCTION_EX                0
                                142     POP_TOP                         
                                144     RETURN_VALUE                    
                            [Exception Table]
                                28 to 84 -> 104 [0] 
                                104 to 126 -> 126 [1] lasti
                        [Code]
                            File Name: <frozen multithon.events.album>
                            Object Name: raw_text
                            Qualified Name: Album.Event.raw_text
                            Arg Count: 1
                            Pos Only Arg Count: 0
                            KW Only Arg Count: 0
                            Stack Size: 5
                            Flags: 0x20000003 (CO_OPTIMIZED | CO_NEWLOCALS | CO_PYARMOR_OBFUSCATED)
                            [Names]
                                'next'
                                'messages'
                            [Locals+Names]
                                'self'
                                '__assert_armored__'
                            [Constants]
                                '\n            The raw message text of the first photo\n            with a caption, ignoring any formatting.\n            '
                                '__pyarmor_assert_22413__'
                                '__pyarmor_enter_22414__'
                                b'<COAddr>\x07\x00\x00\x1aN\x00\x00\x00\x00\x00\x00\x00\x00\x00\x00\x00\x00\x00\x00\x00'
                                [Code]
                                    File Name: <frozen multithon.events.album>
                                    Object Name: <genexpr>
                                    Qualified Name: Album.Event.raw_text.<locals>.<genexpr>
                                    Arg Count: 1
                                    Pos Only Arg Count: 0
                                    KW Only Arg Count: 0
                                    Stack Size: 2
                                    Flags: 0x00000033 (CO_OPTIMIZED | CO_NEWLOCALS | CO_NESTED | CO_GENERATOR)
                                    [Names]
                                        'raw_text'
                                    [Locals+Names]
                                        '.0'
                                        '_var_var_10'
                                    [Constants]
                                        None
                                    [Disassembly]
                                        0       RETURN_GENERATOR                
                                        2       POP_TOP                         
                                        4       RESUME                          0
                                        6       LOAD_FAST                       0: .0
                                        8       FOR_ITER                        29 (to 68)
                                        12      STORE_FAST                      1: _var_var_10
                                        14      LOAD_FAST                       1: _var_var_10
                                        16      LOAD_ATTR                       0: raw_text
                                        36      POP_JUMP_IF_TRUE                1 (to 40)
                                        38      JUMP_BACKWARD                   16 (to 8)
                                        40      LOAD_FAST                       1: _var_var_10
                                        42      LOAD_ATTR                       0: raw_text
                                        62      YIELD_VALUE                     1
                                        64      RESUME                          1
                                        66      POP_TOP                         
                                        68      JUMP_BACKWARD                   31 (to 8)
                                        70      END_FOR                         
                                        72      RETURN_CONST                    0: None
                                        74      CALL_INTRINSIC_1                3 (INTRINSIC_STOPITERATION_ERROR)
                                        76      RERAISE                         1
                                    [Exception Table]
                                        4 to 38 -> 74 [0] lasti
                                        40 to 74 -> 74 [0] lasti
                                ''
                                '__pyarmor_exit_22415__'
                            [Disassembly]
                                0       NOP                             
                                2       NOP                             
                                4       PUSH_NULL                       
                                6       LOAD_CONST                      2: '__pyarmor_enter_22414__'
                                8       LOAD_CONST                      3: b'<COAddr>\x07\x00\x00\x1aN\x00\x00\x00\x00\x00\x00\x00\x00\x00\x00\x00\x00\x00\x00\x00'
                                10      BUILD_TUPLE                     1
                                12      CALL_FUNCTION_EX                0
                                14      POP_TOP                         
                                16      RESUME                          0
                                18      NOP                             
                                20      NOP                             
                                22      NOP                             
                                24      NOP                             
                                26      NOP                             
                                28      LOAD_GLOBAL                     1: NULL + next
                                38      LOAD_CONST                      4: <CODE> <genexpr>
                                40      MAKE_FUNCTION                   0
                                42      LOAD_FAST                       0: self
                                44      LOAD_ATTR                       2: messages
                                64      GET_ITER                        
                                66      CALL                            0
                                74      LOAD_CONST                      5: ''
                                76      CALL                            2
                                84      NOP                             
                                86      NOP                             
                                88      NOP                             
                                90      JUMP_FORWARD                    20 (to 132)
                                92      CALL                            1
                                100     POP_TOP                         
                                102     RETURN_VALUE                    
                                104     PUSH_EXC_INFO                   
                                106     PUSH_NULL                       
                                108     LOAD_CONST                      6: '__pyarmor_exit_22415__'
                                110     NOP                             
                                112     LOAD_CONST                      3: b'<COAddr>\x07\x00\x00\x1aN\x00\x00\x00\x00\x00\x00\x00\x00\x00\x00\x00\x00\x00\x00\x00'
                                114     CALL                            1
                                122     POP_TOP                         
                                124     RERAISE                         0
                                126     COPY                            3
                                128     POP_EXCEPT                      
                                130     RERAISE                         1
                                132     PUSH_NULL                       
                                134     LOAD_CONST                      6: '__pyarmor_exit_22415__'
                                136     LOAD_CONST                      3: b'<COAddr>\x07\x00\x00\x1aN\x00\x00\x00\x00\x00\x00\x00\x00\x00\x00\x00\x00\x00\x00\x00'
                                138     BUILD_TUPLE                     1
                                140     CALL_FUNCTION_EX                0
                                142     POP_TOP                         
                                144     RETURN_VALUE                    
                            [Exception Table]
                                28 to 84 -> 104 [0] 
                                104 to 126 -> 126 [1] lasti
                        [Code]
                            File Name: <frozen multithon.events.album>
                            Object Name: is_reply
                            Qualified Name: Album.Event.is_reply
                            Arg Count: 1
                            Pos Only Arg Count: 0
                            KW Only Arg Count: 0
                            Stack Size: 5
                            Flags: 0x20000003 (CO_OPTIMIZED | CO_NEWLOCALS | CO_PYARMOR_OBFUSCATED)
                            [Names]
                                'messages'
                                'is_reply'
                            [Locals+Names]
                                'self'
                                '__assert_armored__'
                            [Constants]
                                '\n            `True` if the album is a reply to some other message.\n\n            Remember that you can access the ID of the message\n            this one is replying to through `reply_to_msg_id`,\n            and the `Message` object with `get_reply_message()`.\n            '
                                '__pyarmor_assert_22416__'
                                '__pyarmor_enter_22417__'
                                b'<COAddr>\x05\x00\x00\x1aF\x00\x00\x00\x00\x00\x00\x00\x00\x00\x00\x00\x00\x00\x00\x00'
                                0
                                '__pyarmor_exit_22418__'
                            [Disassembly]
                                0       NOP                             
                                2       NOP                             
                                4       PUSH_NULL                       
                                6       LOAD_CONST                      2: '__pyarmor_enter_22417__'
                                8       LOAD_CONST                      3: b'<COAddr>\x05\x00\x00\x1aF\x00\x00\x00\x00\x00\x00\x00\x00\x00\x00\x00\x00\x00\x00\x00'
                                10      BUILD_TUPLE                     1
                                12      CALL_FUNCTION_EX                0
                                14      POP_TOP                         
                                16      RESUME                          0
                                18      NOP                             
                                20      NOP                             
                                22      NOP                             
                                24      NOP                             
                                26      NOP                             
                                28      LOAD_FAST                       0: self
                                30      LOAD_ATTR                       0: messages
                                50      LOAD_CONST                      4: 0
                                52      BINARY_SUBSCR                   
                                56      LOAD_ATTR                       2: is_reply
                                76      NOP                             
                                78      NOP                             
                                80      NOP                             
                                82      JUMP_FORWARD                    20 (to 124)
                                84      CALL                            1
                                92      POP_TOP                         
                                94      RETURN_VALUE                    
                                96      PUSH_EXC_INFO                   
                                98      PUSH_NULL                       
                                100     LOAD_CONST                      5: '__pyarmor_exit_22418__'
                                102     NOP                             
                                104     LOAD_CONST                      3: b'<COAddr>\x05\x00\x00\x1aF\x00\x00\x00\x00\x00\x00\x00\x00\x00\x00\x00\x00\x00\x00\x00'
                                106     CALL                            1
                                114     POP_TOP                         
                                116     RERAISE                         0
                                118     COPY                            3
                                120     POP_EXCEPT                      
                                122     RERAISE                         1
                                124     PUSH_NULL                       
                                126     LOAD_CONST                      5: '__pyarmor_exit_22418__'
                                128     LOAD_CONST                      3: b'<COAddr>\x05\x00\x00\x1aF\x00\x00\x00\x00\x00\x00\x00\x00\x00\x00\x00\x00\x00\x00\x00'
                                130     BUILD_TUPLE                     1
                                132     CALL_FUNCTION_EX                0
                                134     POP_TOP                         
                                136     RETURN_VALUE                    
                            [Exception Table]
                                28 to 76 -> 96 [0] 
                                96 to 118 -> 118 [1] lasti
                        [Code]
                            File Name: <frozen multithon.events.album>
                            Object Name: forward
                            Qualified Name: Album.Event.forward
                            Arg Count: 1
                            Pos Only Arg Count: 0
                            KW Only Arg Count: 0
                            Stack Size: 5
                            Flags: 0x20000003 (CO_OPTIMIZED | CO_NEWLOCALS | CO_PYARMOR_OBFUSCATED)
                            [Names]
                                'messages'
                                'forward'
                            [Locals+Names]
                                'self'
                                '__assert_armored__'
                            [Constants]
                                '\n            The `Forward <telethon.tl.custom.forward.Forward>`\n            information for the first message in the album if it was forwarded.\n            '
                                '__pyarmor_assert_22419__'
                                '__pyarmor_enter_22420__'
                                b'<COAddr>\x05\x00\x00\x1aF\x00\x00\x00\x00\x00\x00\x00\x00\x00\x00\x00\x00\x00\x00\x00'
                                0
                                '__pyarmor_exit_22421__'
                            [Disassembly]
                                0       NOP                             
                                2       NOP                             
                                4       PUSH_NULL                       
                                6       LOAD_CONST                      2: '__pyarmor_enter_22420__'
                                8       LOAD_CONST                      3: b'<COAddr>\x05\x00\x00\x1aF\x00\x00\x00\x00\x00\x00\x00\x00\x00\x00\x00\x00\x00\x00\x00'
                                10      BUILD_TUPLE                     1
                                12      CALL_FUNCTION_EX                0
                                14      POP_TOP                         
                                16      RESUME                          0
                                18      NOP                             
                                20      NOP                             
                                22      NOP                             
                                24      NOP                             
                                26      NOP                             
                                28      LOAD_FAST                       0: self
                                30      LOAD_ATTR                       0: messages
                                50      LOAD_CONST                      4: 0
                                52      BINARY_SUBSCR                   
                                56      LOAD_ATTR                       2: forward
                                76      NOP                             
                                78      NOP                             
                                80      NOP                             
                                82      JUMP_FORWARD                    20 (to 124)
                                84      CALL                            1
                                92      POP_TOP                         
                                94      RETURN_VALUE                    
                                96      PUSH_EXC_INFO                   
                                98      PUSH_NULL                       
                                100     LOAD_CONST                      5: '__pyarmor_exit_22421__'
                                102     NOP                             
                                104     LOAD_CONST                      3: b'<COAddr>\x05\x00\x00\x1aF\x00\x00\x00\x00\x00\x00\x00\x00\x00\x00\x00\x00\x00\x00\x00'
                                106     CALL                            1
                                114     POP_TOP                         
                                116     RERAISE                         0
                                118     COPY                            3
                                120     POP_EXCEPT                      
                                122     RERAISE                         1
                                124     PUSH_NULL                       
                                126     LOAD_CONST                      5: '__pyarmor_exit_22421__'
                                128     LOAD_CONST                      3: b'<COAddr>\x05\x00\x00\x1aF\x00\x00\x00\x00\x00\x00\x00\x00\x00\x00\x00\x00\x00\x00\x00'
                                130     BUILD_TUPLE                     1
                                132     CALL_FUNCTION_EX                0
                                134     POP_TOP                         
                                136     RETURN_VALUE                    
                            [Exception Table]
                                28 to 76 -> 96 [0] 
                                96 to 118 -> 118 [1] lasti
                        [Code]
                            File Name: <frozen multithon.events.album>
                            Object Name: get_reply_message
                            Qualified Name: Album.Event.get_reply_message
                            Arg Count: 1
                            Pos Only Arg Count: 0
                            KW Only Arg Count: 0
                            Stack Size: 5
                            Flags: 0x20000083 (CO_OPTIMIZED | CO_NEWLOCALS | CO_COROUTINE | CO_PYARMOR_OBFUSCATED)
                            [Names]
                                'messages'
                                'get_reply_message'
                            [Locals+Names]
                                'self'
                                '__assert_armored__'
                            [Constants]
                                '\n            The `Message <telethon.tl.custom.message.Message>`\n            that this album is replying to, or `None`.\n\n            The result will be cached after its first use.\n            '
                                '__pyarmor_assert_22422__'
                                '__pyarmor_enter_22423__'
                                b'<COAddr>\x05\x00\x00\x1eb\x00\x00\x00\x00\x00\x00\x00\x00\x00\x00\x00\x00\x00\x00\x00'
                                0
                                None
                                '__pyarmor_exit_22424__'
                            [Disassembly]
                                0       RETURN_GENERATOR                
                                2       POP_TOP                         
                                4       NOP                             
                                6       NOP                             
                                8       PUSH_NULL                       
                                10      LOAD_CONST                      2: '__pyarmor_enter_22423__'
                                12      LOAD_CONST                      3: b'<COAddr>\x05\x00\x00\x1eb\x00\x00\x00\x00\x00\x00\x00\x00\x00\x00\x00\x00\x00\x00\x00'
                                14      BUILD_TUPLE                     1
                                16      CALL_FUNCTION_EX                0
                                18      POP_TOP                         
                                20      RESUME                          0
                                22      NOP                             
                                24      NOP                             
                                26      NOP                             
                                28      NOP                             
                                30      NOP                             
                                32      LOAD_FAST                       0: self
                                34      LOAD_ATTR                       0: messages
                                54      LOAD_CONST                      4: 0
                                56      BINARY_SUBSCR                   
                                60      LOAD_ATTR                       3: get_reply_message
                                80      CALL                            0
                                88      GET_AWAITABLE                   0
                                90      LOAD_CONST                      5: None
                                92      SEND                            3 (to 100)
                                96      YIELD_VALUE                     3
                                98      RESUME                          3
                                100     JUMP_BACKWARD_NO_INTERRUPT      5 (to 92)
                                102     END_SEND                        
                                104     NOP                             
                                106     NOP                             
                                108     NOP                             
                                110     JUMP_FORWARD                    24 (to 160)
                                112     CALL                            1
                                120     POP_TOP                         
                                122     RETURN_VALUE                    
                                124     CLEANUP_THROW                   
                                126     JUMP_BACKWARD                   13 (to 102)
                                128     PUSH_EXC_INFO                   
                                130     PUSH_NULL                       
                                132     LOAD_CONST                      6: '__pyarmor_exit_22424__'
                                134     NOP                             
                                136     LOAD_CONST                      3: b'<COAddr>\x05\x00\x00\x1eb\x00\x00\x00\x00\x00\x00\x00\x00\x00\x00\x00\x00\x00\x00\x00'
                                138     CALL                            1
                                146     POP_TOP                         
                                148     RERAISE                         0
                                150     COPY                            3
                                152     POP_EXCEPT                      
                                154     RERAISE                         1
                                156     CALL_INTRINSIC_1                3 (INTRINSIC_STOPITERATION_ERROR)
                                158     RERAISE                         1
                                160     PUSH_NULL                       
                                162     LOAD_CONST                      6: '__pyarmor_exit_22424__'
                                164     LOAD_CONST                      3: b'<COAddr>\x05\x00\x00\x1eb\x00\x00\x00\x00\x00\x00\x00\x00\x00\x00\x00\x00\x00\x00\x00'
                                166     BUILD_TUPLE                     1
                                168     CALL_FUNCTION_EX                0
                                170     POP_TOP                         
                                172     RETURN_VALUE                    
                            [Exception Table]
                                4 to 30 -> 156 [0] lasti
                                32 to 96 -> 128 [0] 
                                96 to 98 -> 124 [2] 
                                98 to 104 -> 128 [0] 
                                104 to 124 -> 156 [0] lasti
                                124 to 126 -> 128 [0] 
                                128 to 150 -> 150 [1] lasti
                                150 to 156 -> 156 [0] lasti
                        [Code]
                            File Name: <frozen multithon.events.album>
                            Object Name: respond
                            Qualified Name: Album.Event.respond
                            Arg Count: 1
                            Pos Only Arg Count: 0
                            KW Only Arg Count: 0
                            Stack Size: 5
                            Flags: 0x2000008F (CO_OPTIMIZED | CO_NEWLOCALS | CO_VARARGS | CO_VARKEYWORDS | CO_COROUTINE | CO_PYARMOR_OBFUSCATED)
                            [Names]
                                'messages'
                                'respond'
                            [Locals+Names]
                                'self'
                                'args'
                                'kwargs'
                                '__assert_armored__'
                            [Constants]
                                '\n            Responds to the album (not as a reply). Shorthand for\n            `telethon.client.messages.MessageMethods.send_message`\n            with ``entity`` already set.\n            '
                                '__pyarmor_assert_22425__'
                                '__pyarmor_enter_22426__'
                                b'<COAddr>\x05\x00\x00\x1ef\x00\x00\x00\x00\x00\x00\x00\x00\x00\x00\x00\x00\x00\x00\x00'
                                0
                                None
                                '__pyarmor_exit_22427__'
                            [Disassembly]
                                0       RETURN_GENERATOR                
                                2       POP_TOP                         
                                4       NOP                             
                                6       NOP                             
                                8       PUSH_NULL                       
                                10      LOAD_CONST                      2: '__pyarmor_enter_22426__'
                                12      LOAD_CONST                      3: b'<COAddr>\x05\x00\x00\x1ef\x00\x00\x00\x00\x00\x00\x00\x00\x00\x00\x00\x00\x00\x00\x00'
                                14      BUILD_TUPLE                     1
                                16      CALL_FUNCTION_EX                0
                                18      POP_TOP                         
                                20      RESUME                          0
                                22      NOP                             
                                24      NOP                             
                                26      NOP                             
                                28      NOP                             
                                30      NOP                             
                                32      PUSH_NULL                       
                                34      LOAD_FAST                       0: self
                                36      LOAD_ATTR                       0: messages
                                56      LOAD_CONST                      4: 0
                                58      BINARY_SUBSCR                   
                                62      LOAD_ATTR                       2: respond
                                82      LOAD_FAST                       1: args
                                84      BUILD_MAP                       0
                                86      LOAD_FAST                       2: kwargs
                                88      DICT_MERGE                      1
                                90      CALL_FUNCTION_EX                1
                                92      GET_AWAITABLE                   0
                                94      LOAD_CONST                      5: None
                                96      SEND                            3 (to 104)
                                100     YIELD_VALUE                     3
                                102     RESUME                          3
                                104     JUMP_BACKWARD_NO_INTERRUPT      5 (to 96)
                                106     END_SEND                        
                                108     NOP                             
                                110     NOP                             
                                112     NOP                             
                                114     JUMP_FORWARD                    24 (to 164)
                                116     CALL                            1
                                124     POP_TOP                         
                                126     RETURN_VALUE                    
                                128     CLEANUP_THROW                   
                                130     JUMP_BACKWARD                   13 (to 106)
                                132     PUSH_EXC_INFO                   
                                134     PUSH_NULL                       
                                136     LOAD_CONST                      6: '__pyarmor_exit_22427__'
                                138     NOP                             
                                140     LOAD_CONST                      3: b'<COAddr>\x05\x00\x00\x1ef\x00\x00\x00\x00\x00\x00\x00\x00\x00\x00\x00\x00\x00\x00\x00'
                                142     CALL                            1
                                150     POP_TOP                         
                                152     RERAISE                         0
                                154     COPY                            3
                                156     POP_EXCEPT                      
                                158     RERAISE                         1
                                160     CALL_INTRINSIC_1                3 (INTRINSIC_STOPITERATION_ERROR)
                                162     RERAISE                         1
                                164     PUSH_NULL                       
                                166     LOAD_CONST                      6: '__pyarmor_exit_22427__'
                                168     LOAD_CONST                      3: b'<COAddr>\x05\x00\x00\x1ef\x00\x00\x00\x00\x00\x00\x00\x00\x00\x00\x00\x00\x00\x00\x00'
                                170     BUILD_TUPLE                     1
                                172     CALL_FUNCTION_EX                0
                                174     POP_TOP                         
                                176     RETURN_VALUE                    
                            [Exception Table]
                                4 to 30 -> 160 [0] lasti
                                32 to 100 -> 132 [0] 
                                100 to 102 -> 128 [2] 
                                102 to 108 -> 132 [0] 
                                108 to 128 -> 160 [0] lasti
                                128 to 130 -> 132 [0] 
                                132 to 154 -> 154 [1] lasti
                                154 to 160 -> 160 [0] lasti
                        [Code]
                            File Name: <frozen multithon.events.album>
                            Object Name: reply
                            Qualified Name: Album.Event.reply
                            Arg Count: 1
                            Pos Only Arg Count: 0
                            KW Only Arg Count: 0
                            Stack Size: 5
                            Flags: 0x2000008F (CO_OPTIMIZED | CO_NEWLOCALS | CO_VARARGS | CO_VARKEYWORDS | CO_COROUTINE | CO_PYARMOR_OBFUSCATED)
                            [Names]
                                'messages'
                                'reply'
                            [Locals+Names]
                                'self'
                                'args'
                                'kwargs'
                                '__assert_armored__'
                            [Constants]
                                '\n            Replies to the first photo in the album (as a reply). Shorthand\n            for `telethon.client.messages.MessageMethods.send_message`\n            with both ``entity`` and ``reply_to`` already set.\n            '
                                '__pyarmor_assert_22428__'
                                '__pyarmor_enter_22429__'
                                b'<COAddr>\x05\x00\x00\x1ef\x00\x00\x00\x00\x00\x00\x00\x00\x00\x00\x00\x00\x00\x00\x00'
                                0
                                None
                                '__pyarmor_exit_22430__'
                            [Disassembly]
                                0       RETURN_GENERATOR                
                                2       POP_TOP                         
                                4       NOP                             
                                6       NOP                             
                                8       PUSH_NULL                       
                                10      LOAD_CONST                      2: '__pyarmor_enter_22429__'
                                12      LOAD_CONST                      3: b'<COAddr>\x05\x00\x00\x1ef\x00\x00\x00\x00\x00\x00\x00\x00\x00\x00\x00\x00\x00\x00\x00'
                                14      BUILD_TUPLE                     1
                                16      CALL_FUNCTION_EX                0
                                18      POP_TOP                         
                                20      RESUME                          0
                                22      NOP                             
                                24      NOP                             
                                26      NOP                             
                                28      NOP                             
                                30      NOP                             
                                32      PUSH_NULL                       
                                34      LOAD_FAST                       0: self
                                36      LOAD_ATTR                       0: messages
                                56      LOAD_CONST                      4: 0
                                58      BINARY_SUBSCR                   
                                62      LOAD_ATTR                       2: reply
                                82      LOAD_FAST                       1: args
                                84      BUILD_MAP                       0
                                86      LOAD_FAST                       2: kwargs
                                88      DICT_MERGE                      1
                                90      CALL_FUNCTION_EX                1
                                92      GET_AWAITABLE                   0
                                94      LOAD_CONST                      5: None
                                96      SEND                            3 (to 104)
                                100     YIELD_VALUE                     3
                                102     RESUME                          3
                                104     JUMP_BACKWARD_NO_INTERRUPT      5 (to 96)
                                106     END_SEND                        
                                108     NOP                             
                                110     NOP                             
                                112     NOP                             
                                114     JUMP_FORWARD                    24 (to 164)
                                116     CALL                            1
                                124     POP_TOP                         
                                126     RETURN_VALUE                    
                                128     CLEANUP_THROW                   
                                130     JUMP_BACKWARD                   13 (to 106)
                                132     PUSH_EXC_INFO                   
                                134     PUSH_NULL                       
                                136     LOAD_CONST                      6: '__pyarmor_exit_22430__'
                                138     NOP                             
                                140     LOAD_CONST                      3: b'<COAddr>\x05\x00\x00\x1ef\x00\x00\x00\x00\x00\x00\x00\x00\x00\x00\x00\x00\x00\x00\x00'
                                142     CALL                            1
                                150     POP_TOP                         
                                152     RERAISE                         0
                                154     COPY                            3
                                156     POP_EXCEPT                      
                                158     RERAISE                         1
                                160     CALL_INTRINSIC_1                3 (INTRINSIC_STOPITERATION_ERROR)
                                162     RERAISE                         1
                                164     PUSH_NULL                       
                                166     LOAD_CONST                      6: '__pyarmor_exit_22430__'
                                168     LOAD_CONST                      3: b'<COAddr>\x05\x00\x00\x1ef\x00\x00\x00\x00\x00\x00\x00\x00\x00\x00\x00\x00\x00\x00\x00'
                                170     BUILD_TUPLE                     1
                                172     CALL_FUNCTION_EX                0
                                174     POP_TOP                         
                                176     RETURN_VALUE                    
                            [Exception Table]
                                4 to 30 -> 160 [0] lasti
                                32 to 100 -> 132 [0] 
                                100 to 102 -> 128 [2] 
                                102 to 108 -> 132 [0] 
                                108 to 128 -> 160 [0] lasti
                                128 to 130 -> 132 [0] 
                                132 to 154 -> 154 [1] lasti
                                154 to 160 -> 160 [0] lasti
                        [Code]
                            File Name: <frozen multithon.events.album>
                            Object Name: forward_to
                            Qualified Name: Album.Event.forward_to
                            Arg Count: 1
                            Pos Only Arg Count: 0
                            KW Only Arg Count: 0
                            Stack Size: 5
                            Flags: 0x2000008F (CO_OPTIMIZED | CO_NEWLOCALS | CO_VARARGS | CO_VARKEYWORDS | CO_COROUTINE | CO_PYARMOR_OBFUSCATED)
                            [Names]
                                '_client'
                                'messages'
                                'get_input_chat'
                                'forward_messages'
                            [Locals+Names]
                                'self'
                                'args'
                                'kwargs'
                                '__assert_armored__'
                            [Constants]
                                '\n            Forwards the entire album. Shorthand for\n            `telethon.client.messages.MessageMethods.forward_messages`\n            with both ``messages`` and ``from_peer`` already set.\n            '
                                '__pyarmor_assert_22431__'
                                '__pyarmor_enter_22432__'
                                b'<COAddr>\x07\x00\x00\x1e\xf0\x00\x00\x00\x00\x00\x00\x00\x00\x00\x00\x00\x00\x00\x00\x00'
                                'messages'
                                None
                                'from_peer'   # b'\x81\xe4\n\x1c>\xc5\xae\xd7\x1e\xe8'
                                '__pyarmor_exit_22433__'
                            [Disassembly]
                                0       RETURN_GENERATOR                
                                2       POP_TOP                         
                                4       NOP                             
                                6       NOP                             
                                8       PUSH_NULL                       
                                10      LOAD_CONST                      2: '__pyarmor_enter_22432__'
                                12      LOAD_CONST                      3: b'<COAddr>\x07\x00\x00\x1e\xf0\x00\x00\x00\x00\x00\x00\x00\x00\x00\x00\x00\x00\x00\x00\x00'
                                14      BUILD_TUPLE                     1
                                16      CALL_FUNCTION_EX                0
                                18      POP_TOP                         
                                20      RESUME                          0
                                22      NOP                             
                                24      NOP                             
                                26      NOP                             
                                28      NOP                             
                                30      NOP                             
                                32      LOAD_FAST                       0: self
                                34      LOAD_ATTR                       0: _client
                                54      POP_JUMP_IF_FALSE               93 (to 242)
                                56      LOAD_FAST                       0: self
                                58      LOAD_ATTR                       2: messages
                                78      LOAD_FAST                       2: kwargs
                                80      LOAD_CONST                      4: 'messages'
                                82      STORE_SUBSCR                    
                                86      LOAD_FAST                       0: self
                                88      LOAD_ATTR                       5: get_input_chat
                                108     CALL                            0
                                116     GET_AWAITABLE                   0
                                118     LOAD_CONST                      5: None
                                120     SEND                            3 (to 128)
                                124     YIELD_VALUE                     3
                                126     RESUME                          3
                                128     JUMP_BACKWARD_NO_INTERRUPT      5 (to 120)
                                130     END_SEND                        
                                132     LOAD_FAST                       2: kwargs
                                134     PUSH_NULL                       
                                136     LOAD_CONST                      1: '__pyarmor_assert_22431__'
                                138     LOAD_CONST                      6: 'from_peer'   # b'\x81\xe4\n\x1c>\xc5\xae\xd7\x1e\xe8'
                                140     CALL                            1
                                148     STORE_SUBSCR                    
                                152     PUSH_NULL                       
                                154     LOAD_FAST                       0: self
                                156     LOAD_ATTR                       0: _client
                                176     LOAD_ATTR                       6: forward_messages
                                196     LOAD_FAST                       1: args
                                198     BUILD_MAP                       0
                                200     LOAD_FAST                       2: kwargs
                                202     DICT_MERGE                      1
                                204     CALL_FUNCTION_EX                1
                                206     GET_AWAITABLE                   0
                                208     LOAD_CONST                      5: None
                                210     SEND                            3 (to 218)
                                214     YIELD_VALUE                     3
                                216     RESUME                          3
                                218     JUMP_BACKWARD_NO_INTERRUPT      5 (to 210)
                                220     END_SEND                        
                                222     NOP                             
                                224     NOP                             
                                226     NOP                             
                                228     JUMP_FORWARD                    36 (to 302)
                                230     CALL                            1
                                238     POP_TOP                         
                                240     RETURN_VALUE                    
                                242     LOAD_CONST                      5: None
                                244     NOP                             
                                246     NOP                             
                                248     NOP                             
                                250     JUMP_FORWARD                    25 (to 302)
                                258     POP_TOP                         
                                260     RETURN_CONST                    5: None
                                262     CLEANUP_THROW                   
                                264     JUMP_BACKWARD                   68 (to 130)
                                266     CLEANUP_THROW                   
                                268     JUMP_BACKWARD                   25 (to 220)
                                270     PUSH_EXC_INFO                   
                                272     PUSH_NULL                       
                                274     LOAD_CONST                      7: '__pyarmor_exit_22433__'
                                276     NOP                             
                                278     LOAD_CONST                      3: b'<COAddr>\x07\x00\x00\x1e\xf0\x00\x00\x00\x00\x00\x00\x00\x00\x00\x00\x00\x00\x00\x00\x00'
                                280     CALL                            1
                                288     POP_TOP                         
                                290     RERAISE                         0
                                292     COPY                            3
                                294     POP_EXCEPT                      
                                296     RERAISE                         1
                                298     CALL_INTRINSIC_1                3 (INTRINSIC_STOPITERATION_ERROR)
                                300     RERAISE                         1
                                302     PUSH_NULL                       
                                304     LOAD_CONST                      7: '__pyarmor_exit_22433__'
                                306     LOAD_CONST                      3: b'<COAddr>\x07\x00\x00\x1e\xf0\x00\x00\x00\x00\x00\x00\x00\x00\x00\x00\x00\x00\x00\x00\x00'
                                308     BUILD_TUPLE                     1
                                310     CALL_FUNCTION_EX                0
                                312     POP_TOP                         
                                314     RETURN_VALUE                    
                            [Exception Table]
                                4 to 30 -> 298 [0] lasti
                                32 to 124 -> 270 [0] 
                                124 to 126 -> 262 [2] 
                                126 to 214 -> 270 [0] 
                                214 to 216 -> 266 [2] 
                                216 to 222 -> 270 [0] 
                                222 to 262 -> 298 [0] lasti
                                262 to 264 -> 270 [0] 
                                266 to 268 -> 270 [0] 
                                270 to 292 -> 292 [1] lasti
                                292 to 298 -> 298 [0] lasti
                        [Code]
                            File Name: <frozen multithon.events.album>
                            Object Name: edit
                            Qualified Name: Album.Event.edit
                            Arg Count: 1
                            Pos Only Arg Count: 0
                            KW Only Arg Count: 0
                            Stack Size: 6
                            Flags: 0x2000008F (CO_OPTIMIZED | CO_NEWLOCALS | CO_VARARGS | CO_VARKEYWORDS | CO_COROUTINE | CO_PYARMOR_OBFUSCATED)
                            [Names]
                                'messages'
                                'raw_text'
                                'edit'
                            [Locals+Names]
                                'self'
                                'args'
                                'kwargs'
                                '__assert_armored__'
                                '_var_var_8'
                            [Constants]
                                "\n            Edits the first caption or the message, or the first messages'\n            caption if no caption is set, iff it's outgoing. Shorthand for\n            `telethon.client.messages.MessageMethods.edit_message`\n            with both ``entity`` and ``message`` already set.\n\n            Returns `None` if the message was incoming,\n            or the edited `Message` otherwise.\n\n            .. note::\n\n                This is different from `client.edit_message\n                <telethon.client.messages.MessageMethods.edit_message>`\n                and **will respect** the previous state of the message.\n                For example, if the message didn't have a link preview,\n                the edit won't add one by default, and you should force\n                it by setting it to `True` if you want it.\n\n                This is generally the most desired and convenient behaviour,\n                and will work for link previews and message buttons.\n            "
                                '__pyarmor_assert_22434__'
                                '__pyarmor_enter_22435__'
                                b'<COAddr>\x05\x00\x00\x1e\xee\x00\x00\x00\x00\x00\x00\x00\x00\x00\x00\x00\x00\x00\x00\x00'
                                None
                                '__pyarmor_exit_22436__'
                                0
                            [Disassembly]
                                0       RETURN_GENERATOR                
                                2       POP_TOP                         
                                4       NOP                             
                                6       NOP                             
                                8       PUSH_NULL                       
                                10      LOAD_CONST                      2: '__pyarmor_enter_22435__'
                                12      LOAD_CONST                      3: b'<COAddr>\x05\x00\x00\x1e\xee\x00\x00\x00\x00\x00\x00\x00\x00\x00\x00\x00\x00\x00\x00\x00'
                                14      BUILD_TUPLE                     1
                                16      CALL_FUNCTION_EX                0
                                18      POP_TOP                         
                                20      RESUME                          0
                                22      NOP                             
                                24      NOP                             
                                26      NOP                             
                                28      NOP                             
                                30      NOP                             
                                32      LOAD_FAST                       0: self
                                34      LOAD_ATTR                       0: messages
                                54      GET_ITER                        
                                56      FOR_ITER                        51 (to 160)
                                60      STORE_FAST                      4: _var_var_8
                                62      LOAD_FAST                       4: _var_var_8
                                64      LOAD_ATTR                       2: raw_text
                                84      POP_JUMP_IF_TRUE                1 (to 88)
                                86      JUMP_BACKWARD                   16 (to 56)
                                88      PUSH_NULL                       
                                90      LOAD_FAST                       4: _var_var_8
                                92      LOAD_ATTR                       4: edit
                                112     LOAD_FAST                       1: args
                                114     BUILD_MAP                       0
                                116     LOAD_FAST                       2: kwargs
                                118     DICT_MERGE                      1
                                120     CALL_FUNCTION_EX                1
                                122     GET_AWAITABLE                   0
                                124     LOAD_CONST                      4: None
                                126     SEND                            3 (to 134)
                                130     YIELD_VALUE                     3
                                132     RESUME                          3
                                134     JUMP_BACKWARD_NO_INTERRUPT      5 (to 126)
                                136     END_SEND                        
                                138     SWAP                            2
                                140     POP_TOP                         
                                142     NOP                             
                                144     NOP                             
                                146     NOP                             
                                148     JUMP_FORWARD                    75 (to 300)
                                150     CALL                            1
                                158     POP_TOP                         
                                160     RETURN_VALUE                    
                                162     END_FOR                         
                                164     PUSH_NULL                       
                                166     LOAD_FAST                       0: self
                                168     LOAD_ATTR                       0: messages
                                188     LOAD_CONST                      6: 0
                                190     BINARY_SUBSCR                   
                                194     LOAD_ATTR                       4: edit
                                214     LOAD_FAST                       1: args
                                216     BUILD_MAP                       0
                                218     LOAD_FAST                       2: kwargs
                                220     DICT_MERGE                      1
                                222     CALL_FUNCTION_EX                1
                                224     GET_AWAITABLE                   0
                                226     LOAD_CONST                      4: None
                                228     SEND                            3 (to 236)
                                232     YIELD_VALUE                     3
                                234     RESUME                          3
                                236     JUMP_BACKWARD_NO_INTERRUPT      5 (to 228)
                                238     END_SEND                        
                                240     NOP                             
                                242     NOP                             
                                244     NOP                             
                                246     JUMP_FORWARD                    26 (to 300)
                                248     CALL                            1
                                256     POP_TOP                         
                                258     RETURN_VALUE                    
                                260     CLEANUP_THROW                   
                                262     JUMP_BACKWARD                   64 (to 136)
                                264     CLEANUP_THROW                   
                                266     JUMP_BACKWARD                   15 (to 238)
                                268     PUSH_EXC_INFO                   
                                270     PUSH_NULL                       
                                272     LOAD_CONST                      5: '__pyarmor_exit_22436__'
                                274     NOP                             
                                276     LOAD_CONST                      3: b'<COAddr>\x05\x00\x00\x1e\xee\x00\x00\x00\x00\x00\x00\x00\x00\x00\x00\x00\x00\x00\x00\x00'
                                278     CALL                            1
                                286     POP_TOP                         
                                288     RERAISE                         0
                                290     COPY                            3
                                292     POP_EXCEPT                      
                                294     RERAISE                         1
                                296     CALL_INTRINSIC_1                3 (INTRINSIC_STOPITERATION_ERROR)
                                298     RERAISE                         1
                                300     PUSH_NULL                       
                                302     LOAD_CONST                      5: '__pyarmor_exit_22436__'
                                304     LOAD_CONST                      3: b'<COAddr>\x05\x00\x00\x1e\xee\x00\x00\x00\x00\x00\x00\x00\x00\x00\x00\x00\x00\x00\x00\x00'
                                306     BUILD_TUPLE                     1
                                308     CALL_FUNCTION_EX                0
                                310     POP_TOP                         
                                312     RETURN_VALUE                    
                            [Exception Table]
                                4 to 30 -> 296 [0] lasti
                                32 to 86 -> 268 [0] 
                                88 to 130 -> 268 [0] 
                                130 to 132 -> 260 [3] 
                                132 to 142 -> 268 [0] 
                                142 to 162 -> 296 [0] lasti
                                162 to 232 -> 268 [0] 
                                232 to 234 -> 264 [2] 
                                234 to 240 -> 268 [0] 
                                240 to 260 -> 296 [0] lasti
                                260 to 262 -> 268 [0] 
                                264 to 266 -> 268 [0] 
                                268 to 290 -> 290 [1] lasti
                                290 to 296 -> 296 [0] lasti
                        [Code]
                            File Name: <frozen multithon.events.album>
                            Object Name: delete
                            Qualified Name: Album.Event.delete
                            Arg Count: 1
                            Pos Only Arg Count: 0
                            KW Only Arg Count: 0
                            Stack Size: 5
                            Flags: 0x2000008F (CO_OPTIMIZED | CO_NEWLOCALS | CO_VARARGS | CO_VARKEYWORDS | CO_COROUTINE | CO_PYARMOR_OBFUSCATED)
                            [Names]
                                '_client'
                                'delete_messages'
                                'get_input_chat'
                                'messages'
                            [Locals+Names]
                                'self'
                                'args'
                                'kwargs'
                                '__assert_armored__'
                            [Constants]
                                "\n            Deletes the entire album. You're responsible for checking whether\n            you have the permission to do so, or to except the error otherwise.\n            Shorthand for\n            `telethon.client.messages.MessageMethods.delete_messages` with\n            ``entity`` and ``message_ids`` already set.\n            "
                                '__pyarmor_assert_22437__'
                                '__pyarmor_enter_22438__'
                                b'<COAddr>\x07\x00\x00\x1e\xda\x00\x00\x00\x00\x00\x00\x00\x00\x00\x00\x00\x00\x00\x00\x00'
                                None
                                '__pyarmor_exit_22439__'
                            [Disassembly]
                                0       RETURN_GENERATOR                
                                2       POP_TOP                         
                                4       NOP                             
                                6       NOP                             
                                8       PUSH_NULL                       
                                10      LOAD_CONST                      2: '__pyarmor_enter_22438__'
                                12      LOAD_CONST                      3: b'<COAddr>\x07\x00\x00\x1e\xda\x00\x00\x00\x00\x00\x00\x00\x00\x00\x00\x00\x00\x00\x00\x00'
                                14      BUILD_TUPLE                     1
                                16      CALL_FUNCTION_EX                0
                                18      POP_TOP                         
                                20      RESUME                          0
                                22      NOP                             
                                24      NOP                             
                                26      NOP                             
                                28      NOP                             
                                30      NOP                             
                                32      LOAD_FAST                       0: self
                                34      LOAD_ATTR                       0: _client
                                54      POP_JUMP_IF_FALSE               82 (to 220)
                                56      PUSH_NULL                       
                                58      LOAD_FAST                       0: self
                                60      LOAD_ATTR                       0: _client
                                80      LOAD_ATTR                       2: delete_messages
                                100     LOAD_FAST                       0: self
                                102     LOAD_ATTR                       5: get_input_chat
                                122     CALL                            0
                                130     GET_AWAITABLE                   0
                                132     LOAD_CONST                      4: None
                                134     SEND                            3 (to 142)
                                138     YIELD_VALUE                     3
                                140     RESUME                          3
                                142     JUMP_BACKWARD_NO_INTERRUPT      5 (to 134)
                                144     END_SEND                        
                                146     LOAD_FAST                       0: self
                                148     LOAD_ATTR                       6: messages
                                168     BUILD_LIST                      2
                                170     LOAD_FAST                       1: args
                                172     LIST_EXTEND                     1
                                174     CALL_INTRINSIC_1                6 (INTRINSIC_LIST_TO_TUPLE)
                                176     BUILD_MAP                       0
                                178     LOAD_FAST                       2: kwargs
                                180     DICT_MERGE                      1
                                182     CALL_FUNCTION_EX                1
                                184     GET_AWAITABLE                   0
                                186     LOAD_CONST                      4: None
                                188     SEND                            3 (to 196)
                                192     YIELD_VALUE                     3
                                194     RESUME                          3
                                196     JUMP_BACKWARD_NO_INTERRUPT      5 (to 188)
                                198     END_SEND                        
                                200     NOP                             
                                202     NOP                             
                                204     NOP                             
                                206     JUMP_FORWARD                    36 (to 280)
                                208     CALL                            1
                                216     POP_TOP                         
                                218     RETURN_VALUE                    
                                220     LOAD_CONST                      4: None
                                222     NOP                             
                                224     NOP                             
                                226     NOP                             
                                228     JUMP_FORWARD                    25 (to 280)
                                236     POP_TOP                         
                                238     RETURN_CONST                    4: None
                                240     CLEANUP_THROW                   
                                242     JUMP_BACKWARD                   50 (to 144)
                                244     CLEANUP_THROW                   
                                246     JUMP_BACKWARD                   25 (to 198)
                                248     PUSH_EXC_INFO                   
                                250     PUSH_NULL                       
                                252     LOAD_CONST                      5: '__pyarmor_exit_22439__'
                                254     NOP                             
                                256     LOAD_CONST                      3: b'<COAddr>\x07\x00\x00\x1e\xda\x00\x00\x00\x00\x00\x00\x00\x00\x00\x00\x00\x00\x00\x00\x00'
                                258     CALL                            1
                                266     POP_TOP                         
                                268     RERAISE                         0
                                270     COPY                            3
                                272     POP_EXCEPT                      
                                274     RERAISE                         1
                                276     CALL_INTRINSIC_1                3 (INTRINSIC_STOPITERATION_ERROR)
                                278     RERAISE                         1
                                280     PUSH_NULL                       
                                282     LOAD_CONST                      5: '__pyarmor_exit_22439__'
                                284     LOAD_CONST                      3: b'<COAddr>\x07\x00\x00\x1e\xda\x00\x00\x00\x00\x00\x00\x00\x00\x00\x00\x00\x00\x00\x00\x00'
                                286     BUILD_TUPLE                     1
                                288     CALL_FUNCTION_EX                0
                                290     POP_TOP                         
                                292     RETURN_VALUE                    
                            [Exception Table]
                                4 to 30 -> 276 [0] lasti
                                32 to 138 -> 248 [0] 
                                138 to 140 -> 240 [4] 
                                140 to 192 -> 248 [0] 
                                192 to 194 -> 244 [2] 
                                194 to 200 -> 248 [0] 
                                200 to 240 -> 276 [0] lasti
                                240 to 242 -> 248 [0] 
                                244 to 246 -> 248 [0] 
                                248 to 270 -> 270 [1] lasti
                                270 to 276 -> 276 [0] lasti
                        [Code]
                            File Name: <frozen multithon.events.album>
                            Object Name: mark_read
                            Qualified Name: Album.Event.mark_read
                            Arg Count: 1
                            Pos Only Arg Count: 0
                            KW Only Arg Count: 0
                            Stack Size: 5
                            Flags: 0x20000083 (CO_OPTIMIZED | CO_NEWLOCALS | CO_COROUTINE | CO_PYARMOR_OBFUSCATED)
                            [Names]
                                '_client'
                                'send_read_acknowledge'
                                'get_input_chat'
                                'messages'
                                'id'
                            [Locals+Names]
                                'self'
                                '__assert_armored__'
                            [Constants]
                                '\n            Marks the entire album as read. Shorthand for\n            `client.send_read_acknowledge()\n            <telethon.client.messages.MessageMethods.send_read_acknowledge>`\n            with both ``entity`` and ``message`` already set.\n            '
                                '__pyarmor_assert_22440__'
                                '__pyarmor_enter_22441__'
                                b'<COAddr>\x05\x00\x00\x1e\xda\x00\x00\x00\x00\x00\x00\x00\x00\x00\x00\x00\x00\x00\x00\x00'
                                None
                                -1
                                (
                                    'max_id'
                                )
                                '__pyarmor_exit_22442__'
                            [Disassembly]
                                0       RETURN_GENERATOR                
                                2       POP_TOP                         
                                4       NOP                             
                                6       NOP                             
                                8       PUSH_NULL                       
                                10      LOAD_CONST                      2: '__pyarmor_enter_22441__'
                                12      LOAD_CONST                      3: b'<COAddr>\x05\x00\x00\x1e\xda\x00\x00\x00\x00\x00\x00\x00\x00\x00\x00\x00\x00\x00\x00\x00'
                                14      BUILD_TUPLE                     1
                                16      CALL_FUNCTION_EX                0
                                18      POP_TOP                         
                                20      RESUME                          0
                                22      NOP                             
                                24      NOP                             
                                26      NOP                             
                                28      NOP                             
                                30      NOP                             
                                32      LOAD_FAST                       0: self
                                34      LOAD_ATTR                       0: _client
                                54      POP_JUMP_IF_FALSE               82 (to 220)
                                56      LOAD_FAST                       0: self
                                58      LOAD_ATTR                       0: _client
                                78      LOAD_ATTR                       3: send_read_acknowledge
                                98      LOAD_FAST                       0: self
                                100     LOAD_ATTR                       5: get_input_chat
                                120     CALL                            0
                                128     GET_AWAITABLE                   0
                                130     LOAD_CONST                      4: None
                                132     SEND                            3 (to 140)
                                136     YIELD_VALUE                     3
                                138     RESUME                          3
                                140     JUMP_BACKWARD_NO_INTERRUPT      5 (to 132)
                                142     END_SEND                        
                                144     LOAD_FAST                       0: self
                                146     LOAD_ATTR                       6: messages
                                166     LOAD_CONST                      5: -1
                                168     BINARY_SUBSCR                   
                                172     LOAD_ATTR                       8: id
                                192     KW_NAMES                        6: ('max_id',)
                                194     CALL                            2
                                202     GET_AWAITABLE                   0
                                204     LOAD_CONST                      4: None
                                206     SEND                            3 (to 214)
                                210     YIELD_VALUE                     3
                                212     RESUME                          3
                                214     JUMP_BACKWARD_NO_INTERRUPT      5 (to 206)
                                216     END_SEND                        
                                218     POP_TOP                         
                                220     LOAD_CONST                      4: None
                                222     NOP                             
                                224     NOP                             
                                226     NOP                             
                                228     JUMP_FORWARD                    25 (to 280)
                                236     POP_TOP                         
                                238     RETURN_CONST                    4: None
                                240     CLEANUP_THROW                   
                                242     JUMP_BACKWARD                   51 (to 142)
                                244     CLEANUP_THROW                   
                                246     JUMP_BACKWARD                   16 (to 216)
                                248     PUSH_EXC_INFO                   
                                250     PUSH_NULL                       
                                252     LOAD_CONST                      7: '__pyarmor_exit_22442__'
                                254     NOP                             
                                256     LOAD_CONST                      3: b'<COAddr>\x05\x00\x00\x1e\xda\x00\x00\x00\x00\x00\x00\x00\x00\x00\x00\x00\x00\x00\x00\x00'
                                258     CALL                            1
                                266     POP_TOP                         
                                268     RERAISE                         0
                                270     COPY                            3
                                272     POP_EXCEPT                      
                                274     RERAISE                         1
                                276     CALL_INTRINSIC_1                3 (INTRINSIC_STOPITERATION_ERROR)
                                278     RERAISE                         1
                                280     PUSH_NULL                       
                                282     LOAD_CONST                      7: '__pyarmor_exit_22442__'
                                284     LOAD_CONST                      3: b'<COAddr>\x05\x00\x00\x1e\xda\x00\x00\x00\x00\x00\x00\x00\x00\x00\x00\x00\x00\x00\x00\x00'
                                286     BUILD_TUPLE                     1
                                288     CALL_FUNCTION_EX                0
                                290     POP_TOP                         
                                292     RETURN_VALUE                    
                            [Exception Table]
                                4 to 30 -> 276 [0] lasti
                                32 to 136 -> 248 [0] 
                                136 to 138 -> 240 [4] 
                                138 to 210 -> 248 [0] 
                                210 to 212 -> 244 [2] 
                                212 to 220 -> 248 [0] 
                                220 to 240 -> 276 [0] lasti
                                240 to 242 -> 248 [0] 
                                244 to 246 -> 248 [0] 
                                248 to 270 -> 270 [1] lasti
                                270 to 276 -> 276 [0] lasti
                        False
                        (
                            'notify'
                        )
                        [Code]
                            File Name: <frozen multithon.events.album>
                            Object Name: pin
                            Qualified Name: Album.Event.pin
                            Arg Count: 1
                            Pos Only Arg Count: 0
                            KW Only Arg Count: 1
                            Stack Size: 5
                            Flags: 0x20000083 (CO_OPTIMIZED | CO_NEWLOCALS | CO_COROUTINE | CO_PYARMOR_OBFUSCATED)
                            [Names]
                                'messages'
                                'pin'
                            [Locals+Names]
                                'self'
                                'notify'
                                '__assert_armored__'
                            [Constants]
                                '\n            Pins the first photo in the album. Shorthand for\n            `telethon.client.messages.MessageMethods.pin_message`\n            with both ``entity`` and ``message`` already set.\n            '
                                '__pyarmor_assert_22443__'
                                '__pyarmor_enter_22444__'
                                b'<COAddr>\x07\x00\x00\x1ef\x00\x00\x00\x00\x00\x00\x00\x00\x00\x00\x00\x00\x00\x00\x00'
                                0
                                (
                                    'notify'
                                )
                                None
                                '__pyarmor_exit_22445__'
                            [Disassembly]
                                0       RETURN_GENERATOR                
                                2       POP_TOP                         
                                4       NOP                             
                                6       NOP                             
                                8       PUSH_NULL                       
                                10      LOAD_CONST                      2: '__pyarmor_enter_22444__'
                                12      LOAD_CONST                      3: b'<COAddr>\x07\x00\x00\x1ef\x00\x00\x00\x00\x00\x00\x00\x00\x00\x00\x00\x00\x00\x00\x00'
                                14      BUILD_TUPLE                     1
                                16      CALL_FUNCTION_EX                0
                                18      POP_TOP                         
                                20      RESUME                          0
                                22      NOP                             
                                24      NOP                             
                                26      NOP                             
                                28      NOP                             
                                30      NOP                             
                                32      LOAD_FAST                       0: self
                                34      LOAD_ATTR                       0: messages
                                54      LOAD_CONST                      4: 0
                                56      BINARY_SUBSCR                   
                                60      LOAD_ATTR                       3: pin
                                80      LOAD_FAST                       1: notify
                                82      KW_NAMES                        5: ('notify',)
                                84      CALL                            1
                                92      GET_AWAITABLE                   0
                                94      LOAD_CONST                      6: None
                                96      SEND                            3 (to 104)
                                100     YIELD_VALUE                     3
                                102     RESUME                          3
                                104     JUMP_BACKWARD_NO_INTERRUPT      5 (to 96)
                                106     END_SEND                        
                                108     NOP                             
                                110     NOP                             
                                112     NOP                             
                                114     JUMP_FORWARD                    24 (to 164)
                                116     CALL                            1
                                124     POP_TOP                         
                                126     RETURN_VALUE                    
                                128     CLEANUP_THROW                   
                                130     JUMP_BACKWARD                   13 (to 106)
                                132     PUSH_EXC_INFO                   
                                134     PUSH_NULL                       
                                136     LOAD_CONST                      7: '__pyarmor_exit_22445__'
                                138     NOP                             
                                140     LOAD_CONST                      3: b'<COAddr>\x07\x00\x00\x1ef\x00\x00\x00\x00\x00\x00\x00\x00\x00\x00\x00\x00\x00\x00\x00'
                                142     CALL                            1
                                150     POP_TOP                         
                                152     RERAISE                         0
                                154     COPY                            3
                                156     POP_EXCEPT                      
                                158     RERAISE                         1
                                160     CALL_INTRINSIC_1                3 (INTRINSIC_STOPITERATION_ERROR)
                                162     RERAISE                         1
                                164     PUSH_NULL                       
                                166     LOAD_CONST                      7: '__pyarmor_exit_22445__'
                                168     LOAD_CONST                      3: b'<COAddr>\x07\x00\x00\x1ef\x00\x00\x00\x00\x00\x00\x00\x00\x00\x00\x00\x00\x00\x00\x00'
                                170     BUILD_TUPLE                     1
                                172     CALL_FUNCTION_EX                0
                                174     POP_TOP                         
                                176     RETURN_VALUE                    
                            [Exception Table]
                                4 to 30 -> 160 [0] lasti
                                32 to 100 -> 132 [0] 
                                100 to 102 -> 128 [2] 
                                102 to 108 -> 132 [0] 
                                108 to 128 -> 160 [0] lasti
                                128 to 130 -> 132 [0] 
                                132 to 154 -> 154 [1] lasti
                                154 to 160 -> 160 [0] lasti
                        [Code]
                            File Name: <frozen multithon.events.album>
                            Object Name: __len__
                            Qualified Name: Album.Event.__len__
                            Arg Count: 1
                            Pos Only Arg Count: 0
                            KW Only Arg Count: 0
                            Stack Size: 5
                            Flags: 0x20000003 (CO_OPTIMIZED | CO_NEWLOCALS | CO_PYARMOR_OBFUSCATED)
                            [Names]
                                'len'
                                'messages'
                            [Locals+Names]
                                'self'
                                '__assert_armored__'
                            [Constants]
                                '\n            Return the amount of messages in the album.\n\n            Equivalent to ``len(self.messages)``.\n            '
                                '__pyarmor_assert_22446__'
                                '__pyarmor_enter_22447__'
                                b'<COAddr>\x05\x00\x00\x1a>\x00\x00\x00\x00\x00\x00\x00\x00\x00\x00\x00\x00\x00\x00\x00'
                                '__pyarmor_exit_22448__'
                            [Disassembly]
                                0       NOP                             
                                2       NOP                             
                                4       PUSH_NULL                       
                                6       LOAD_CONST                      2: '__pyarmor_enter_22447__'
                                8       LOAD_CONST                      3: b'<COAddr>\x05\x00\x00\x1a>\x00\x00\x00\x00\x00\x00\x00\x00\x00\x00\x00\x00\x00\x00\x00'
                                10      BUILD_TUPLE                     1
                                12      CALL_FUNCTION_EX                0
                                14      POP_TOP                         
                                16      RESUME                          0
                                18      NOP                             
                                20      NOP                             
                                22      NOP                             
                                24      NOP                             
                                26      NOP                             
                                28      LOAD_GLOBAL                     1: NULL + len
                                38      LOAD_FAST                       0: self
                                40      LOAD_ATTR                       2: messages
                                60      CALL                            1
                                68      NOP                             
                                70      NOP                             
                                72      NOP                             
                                74      JUMP_FORWARD                    20 (to 116)
                                76      CALL                            1
                                84      POP_TOP                         
                                86      RETURN_VALUE                    
                                88      PUSH_EXC_INFO                   
                                90      PUSH_NULL                       
                                92      LOAD_CONST                      4: '__pyarmor_exit_22448__'
                                94      NOP                             
                                96      LOAD_CONST                      3: b'<COAddr>\x05\x00\x00\x1a>\x00\x00\x00\x00\x00\x00\x00\x00\x00\x00\x00\x00\x00\x00\x00'
                                98      CALL                            1
                                106     POP_TOP                         
                                108     RERAISE                         0
                                110     COPY                            3
                                112     POP_EXCEPT                      
                                114     RERAISE                         1
                                116     PUSH_NULL                       
                                118     LOAD_CONST                      4: '__pyarmor_exit_22448__'
                                120     LOAD_CONST                      3: b'<COAddr>\x05\x00\x00\x1a>\x00\x00\x00\x00\x00\x00\x00\x00\x00\x00\x00\x00\x00\x00\x00'
                                122     BUILD_TUPLE                     1
                                124     CALL_FUNCTION_EX                0
                                126     POP_TOP                         
                                128     RETURN_VALUE                    
                            [Exception Table]
                                28 to 68 -> 88 [0] 
                                88 to 110 -> 110 [1] lasti
                        [Code]
                            File Name: <frozen multithon.events.album>
                            Object Name: __iter__
                            Qualified Name: Album.Event.__iter__
                            Arg Count: 1
                            Pos Only Arg Count: 0
                            KW Only Arg Count: 0
                            Stack Size: 5
                            Flags: 0x20000003 (CO_OPTIMIZED | CO_NEWLOCALS | CO_PYARMOR_OBFUSCATED)
                            [Names]
                                'iter'
                                'messages'
                            [Locals+Names]
                                'self'
                                '__assert_armored__'
                            [Constants]
                                '\n            Iterate over the messages in the album.\n\n            Equivalent to ``iter(self.messages)``.\n            '
                                '__pyarmor_assert_22449__'
                                '__pyarmor_enter_22450__'
                                b'<COAddr>\x07\x00\x00\x1a>\x00\x00\x00\x00\x00\x00\x00\x00\x00\x00\x00\x00\x00\x00\x00'
                                '__pyarmor_exit_22451__'
                            [Disassembly]
                                0       NOP                             
                                2       NOP                             
                                4       PUSH_NULL                       
                                6       LOAD_CONST                      2: '__pyarmor_enter_22450__'
                                8       LOAD_CONST                      3: b'<COAddr>\x07\x00\x00\x1a>\x00\x00\x00\x00\x00\x00\x00\x00\x00\x00\x00\x00\x00\x00\x00'
                                10      BUILD_TUPLE                     1
                                12      CALL_FUNCTION_EX                0
                                14      POP_TOP                         
                                16      RESUME                          0
                                18      NOP                             
                                20      NOP                             
                                22      NOP                             
                                24      NOP                             
                                26      NOP                             
                                28      LOAD_GLOBAL                     1: NULL + iter
                                38      LOAD_FAST                       0: self
                                40      LOAD_ATTR                       2: messages
                                60      CALL                            1
                                68      NOP                             
                                70      NOP                             
                                72      NOP                             
                                74      JUMP_FORWARD                    20 (to 116)
                                76      CALL                            1
                                84      POP_TOP                         
                                86      RETURN_VALUE                    
                                88      PUSH_EXC_INFO                   
                                90      PUSH_NULL                       
                                92      LOAD_CONST                      4: '__pyarmor_exit_22451__'
                                94      NOP                             
                                96      LOAD_CONST                      3: b'<COAddr>\x07\x00\x00\x1a>\x00\x00\x00\x00\x00\x00\x00\x00\x00\x00\x00\x00\x00\x00\x00'
                                98      CALL                            1
                                106     POP_TOP                         
                                108     RERAISE                         0
                                110     COPY                            3
                                112     POP_EXCEPT                      
                                114     RERAISE                         1
                                116     PUSH_NULL                       
                                118     LOAD_CONST                      4: '__pyarmor_exit_22451__'
                                120     LOAD_CONST                      3: b'<COAddr>\x07\x00\x00\x1a>\x00\x00\x00\x00\x00\x00\x00\x00\x00\x00\x00\x00\x00\x00\x00'
                                122     BUILD_TUPLE                     1
                                124     CALL_FUNCTION_EX                0
                                126     POP_TOP                         
                                128     RETURN_VALUE                    
                            [Exception Table]
                                28 to 68 -> 88 [0] 
                                88 to 110 -> 110 [1] lasti
                        [Code]
                            File Name: <frozen multithon.events.album>
                            Object Name: __getitem__
                            Qualified Name: Album.Event.__getitem__
                            Arg Count: 2
                            Pos Only Arg Count: 0
                            KW Only Arg Count: 0
                            Stack Size: 5
                            Flags: 0x20000003 (CO_OPTIMIZED | CO_NEWLOCALS | CO_PYARMOR_OBFUSCATED)
                            [Names]
                                'messages'
                            [Locals+Names]
                                'self'
                                'n'
                                '__assert_armored__'
                            [Constants]
                                "\n            Access the n'th message in the album.\n\n            Equivalent to ``event.messages[n]``.\n            "
                                '__pyarmor_assert_22452__'
                                '__pyarmor_enter_22453__'
                                b'<COAddr>\x05\x00\x00\x1a2\x00\x00\x00\x00\x00\x00\x00\x00\x00\x00\x00\x00\x00\x00\x00'
                                '__pyarmor_exit_22454__'
                            [Disassembly]
                                0       NOP                             
                                2       NOP                             
                                4       PUSH_NULL                       
                                6       LOAD_CONST                      2: '__pyarmor_enter_22453__'
                                8       LOAD_CONST                      3: b'<COAddr>\x05\x00\x00\x1a2\x00\x00\x00\x00\x00\x00\x00\x00\x00\x00\x00\x00\x00\x00\x00'
                                10      BUILD_TUPLE                     1
                                12      CALL_FUNCTION_EX                0
                                14      POP_TOP                         
                                16      RESUME                          0
                                18      NOP                             
                                20      NOP                             
                                22      NOP                             
                                24      NOP                             
                                26      NOP                             
                                28      LOAD_FAST                       0: self
                                30      LOAD_ATTR                       0: messages
                                50      LOAD_FAST                       1: n
                                52      BINARY_SUBSCR                   
                                56      NOP                             
                                58      NOP                             
                                60      NOP                             
                                62      JUMP_FORWARD                    20 (to 104)
                                64      CALL                            1
                                72      POP_TOP                         
                                74      RETURN_VALUE                    
                                76      PUSH_EXC_INFO                   
                                78      PUSH_NULL                       
                                80      LOAD_CONST                      4: '__pyarmor_exit_22454__'
                                82      NOP                             
                                84      LOAD_CONST                      3: b'<COAddr>\x05\x00\x00\x1a2\x00\x00\x00\x00\x00\x00\x00\x00\x00\x00\x00\x00\x00\x00\x00'
                                86      CALL                            1
                                94      POP_TOP                         
                                96      RERAISE                         0
                                98      COPY                            3
                                100     POP_EXCEPT                      
                                102     RERAISE                         1
                                104     PUSH_NULL                       
                                106     LOAD_CONST                      4: '__pyarmor_exit_22454__'
                                108     LOAD_CONST                      3: b'<COAddr>\x05\x00\x00\x1a2\x00\x00\x00\x00\x00\x00\x00\x00\x00\x00\x00\x00\x00\x00\x00'
                                110     BUILD_TUPLE                     1
                                112     CALL_FUNCTION_EX                0
                                114     POP_TOP                         
                                116     RETURN_VALUE                    
                            [Exception Table]
                                28 to 56 -> 76 [0] 
                                76 to 98 -> 98 [1] lasti
                        '__pyarmor_exit_22400__'
                    [Disassembly]
                        0       MAKE_CELL                       0: __class__
                        2       NOP                             
                        4       LOAD_NAME                       0: __name__
                        6       STORE_NAME                      1: __module__
                        8       LOAD_CONST                      0: 'Album.Event'
                        10      STORE_NAME                      2: __qualname__
                        12      LOAD_CONST                      1: '\n        Represents the event of a new album.\n\n        Members:\n            messages (Sequence[`Message <telethon.tl.custom.message.Message>`]):\n                The list of messages belonging to the same album.\n        '
                        14      STORE_NAME                      3: __doc__
                        16      NOP                             
                        18      PUSH_NULL                       
                        20      LOAD_CONST                      3: '__pyarmor_enter_22399__'
                        22      LOAD_CONST                      4: b'<COAddr>\x05\x00\x00(\xc8\x00\x00\x00\x00\x00\x00\x00\x00\x00\x00\x00\x00\x00\x00\x00'
                        24      BUILD_TUPLE                     1
                        26      CALL_FUNCTION_EX                0
                        28      POP_TOP                         
                        30      RESUME                          0
                        32      NOP                             
                        34      NOP                             
                        36      NOP                             
                        38      NOP                             
                        40      NOP                             
                        42      LOAD_CLOSURE                    0: __class__
                        44      BUILD_TUPLE                     1
                        46      LOAD_CONST                      5: <CODE> __init__
                        48      MAKE_FUNCTION                   8
                        50      STORE_NAME                      5: __init__
                        52      LOAD_CLOSURE                    0: __class__
                        54      BUILD_TUPLE                     1
                        56      LOAD_CONST                      6: <CODE> _set_client
                        58      MAKE_FUNCTION                   8
                        60      STORE_NAME                      6: _set_client
                        62      LOAD_NAME                       7: property
                        64      LOAD_CONST                      7: <CODE> grouped_id
                        66      MAKE_FUNCTION                   0
                        68      CALL                            0
                        76      STORE_NAME                      8: grouped_id
                        78      LOAD_NAME                       7: property
                        80      LOAD_CONST                      8: <CODE> text
                        82      MAKE_FUNCTION                   0
                        84      CALL                            0
                        92      STORE_NAME                      9: text
                        94      LOAD_NAME                       7: property
                        96      LOAD_CONST                      9: <CODE> raw_text
                        98      MAKE_FUNCTION                   0
                        100     CALL                            0
                        108     STORE_NAME                      10: raw_text
                        110     LOAD_NAME                       7: property
                        112     LOAD_CONST                      10: <CODE> is_reply
                        114     MAKE_FUNCTION                   0
                        116     CALL                            0
                        124     STORE_NAME                      11: is_reply
                        126     LOAD_NAME                       7: property
                        128     LOAD_CONST                      11: <CODE> forward
                        130     MAKE_FUNCTION                   0
                        132     CALL                            0
                        140     STORE_NAME                      12: forward
                        142     LOAD_CONST                      12: <CODE> get_reply_message
                        144     MAKE_FUNCTION                   0
                        146     STORE_NAME                      13: get_reply_message
                        148     LOAD_CONST                      13: <CODE> respond
                        150     MAKE_FUNCTION                   0
                        152     STORE_NAME                      14: respond
                        154     LOAD_CONST                      14: <CODE> reply
                        156     MAKE_FUNCTION                   0
                        158     STORE_NAME                      15: reply
                        160     LOAD_CONST                      15: <CODE> forward_to
                        162     MAKE_FUNCTION                   0
                        164     STORE_NAME                      16: forward_to
                        166     LOAD_CONST                      16: <CODE> edit
                        168     MAKE_FUNCTION                   0
                        170     STORE_NAME                      17: edit
                        172     LOAD_CONST                      17: <CODE> delete
                        174     MAKE_FUNCTION                   0
                        176     STORE_NAME                      18: delete
                        178     LOAD_CONST                      18: <CODE> mark_read
                        180     MAKE_FUNCTION                   0
                        182     STORE_NAME                      19: mark_read
                        184     LOAD_CONST                      19: False
                        186     LOAD_CONST                      20: ('notify',)
                        188     BUILD_CONST_KEY_MAP             1
                        190     LOAD_CONST                      21: <CODE> pin
                        192     MAKE_FUNCTION                   2
                        194     STORE_NAME                      20: pin
                        196     LOAD_CONST                      22: <CODE> __len__
                        198     MAKE_FUNCTION                   0
                        200     STORE_NAME                      21: __len__
                        202     LOAD_CONST                      23: <CODE> __iter__
                        204     MAKE_FUNCTION                   0
                        206     STORE_NAME                      22: __iter__
                        208     LOAD_CONST                      24: <CODE> __getitem__
                        210     MAKE_FUNCTION                   0
                        212     STORE_NAME                      23: __getitem__
                        214     LOAD_CLOSURE                    0: __class__
                        216     COPY                            1
                        218     STORE_NAME                      24: __classcell__
                        220     NOP                             
                        222     NOP                             
                        224     NOP                             
                        226     JUMP_FORWARD                    20 (to 268)
                        230     POP_TOP                         
                        232     LOAD_CLOSURE                    0: __class__
                        234     COPY                            1
                        236     STORE_NAME                      24: __classcell__
                        238     RETURN_VALUE                    
                        240     PUSH_EXC_INFO                   
                        242     PUSH_NULL                       
                        244     LOAD_CONST                      25: '__pyarmor_exit_22400__'
                        246     NOP                             
                        248     LOAD_CONST                      4: b'<COAddr>\x05\x00\x00(\xc8\x00\x00\x00\x00\x00\x00\x00\x00\x00\x00\x00\x00\x00\x00\x00'
                        250     CALL                            1
                        258     POP_TOP                         
                        260     RERAISE                         0
                        262     COPY                            3
                        264     POP_EXCEPT                      
                        266     RERAISE                         1
                        268     PUSH_NULL                       
                        270     LOAD_CONST                      25: '__pyarmor_exit_22400__'
                        272     LOAD_CONST                      4: b'<COAddr>\x05\x00\x00(\xc8\x00\x00\x00\x00\x00\x00\x00\x00\x00\x00\x00\x00\x00\x00\x00'
                        274     BUILD_TUPLE                     1
                        276     CALL_FUNCTION_EX                0
                        278     POP_TOP                         
                        280     RETURN_VALUE                    
                    [Exception Table]
                        42 to 214 -> 240 [0] 
                        240 to 262 -> 262 [1] lasti
                'Event'
                '__pyarmor_exit_22388__'
                (
                    None
                )
                (
                    None
                    None
                )
            [Disassembly]
                0       MAKE_CELL                       0: __class__
                2       NOP                             
                4       LOAD_NAME                       0: __name__
                6       STORE_NAME                      1: __module__
                8       LOAD_CONST                      0: 'Album'
                10      STORE_NAME                      2: __qualname__
                12      LOAD_CONST                      1: "\n    Occurs whenever you receive an album. This event only exists\n    to ease dealing with an unknown amount of messages that belong\n    to the same album.\n\n    Example\n        .. code-block:: python\n\n            from multithon import events\n\n            @client.on(events.Album)\n            async def handler(event):\n                # Counting how many photos or videos the album has\n                print('Got an album with', len(event), 'items')\n\n                # Forwarding the album as a whole to some chat\n                event.forward_to(chat)\n\n                # Printing the caption\n                print(event.text)\n\n                # Replying to the fifth item in the album\n                await event.messages[4].reply('Cool!')\n    "
                14      STORE_NAME                      3: __doc__
                16      NOP                             
                18      PUSH_NULL                       
                20      LOAD_CONST                      3: '__pyarmor_enter_22387__'
                22      LOAD_CONST                      4: b'<COAddr>\x05\x00\x00(f\x00\x00\x00\x00\x00\x00\x00\x00\x00\x00\x00\x00\x00\x00\x00'
                24      BUILD_TUPLE                     1
                26      CALL_FUNCTION_EX                0
                28      POP_TOP                         
                30      RESUME                          0
                32      NOP                             
                34      NOP                             
                36      NOP                             
                38      NOP                             
                40      NOP                             
                42      NOP                             
                44      LOAD_CONST                      14: (None,)
                46      LOAD_CONST                      6: False
                48      LOAD_CONST                      5: None
                50      LOAD_CONST                      7: ('blacklist_chats', 'func')
                52      BUILD_CONST_KEY_MAP             2
                54      LOAD_CLOSURE                    0: __class__
                56      BUILD_TUPLE                     1
                58      LOAD_CONST                      8: <CODE> __init__
                60      MAKE_FUNCTION                   11
                62      STORE_NAME                      5: __init__
                64      LOAD_NAME                       6: classmethod
                66      LOAD_CONST                      15: (None, None)
                68      LOAD_CONST                      9: <CODE> build
                70      MAKE_FUNCTION                   1
                72      CALL                            0
                80      STORE_NAME                      7: build
                82      LOAD_CLOSURE                    0: __class__
                84      BUILD_TUPLE                     1
                86      LOAD_CONST                      10: <CODE> filter
                88      MAKE_FUNCTION                   8
                90      STORE_NAME                      8: filter
                92      PUSH_NULL                       
                94      LOAD_BUILD_CLASS                
                96      LOAD_CONST                      11: <CODE> Event
                98      MAKE_FUNCTION                   0
                100     LOAD_CONST                      12: 'Event'
                102     LOAD_NAME                       9: EventCommon
                104     LOAD_NAME                       10: SenderGetter
                106     CALL                            4
                114     STORE_NAME                      11: Event
                116     LOAD_CLOSURE                    0: __class__
                118     COPY                            1
                120     STORE_NAME                      12: __classcell__
                122     NOP                             
                124     NOP                             
                126     NOP                             
                128     JUMP_FORWARD                    20 (to 170)
                132     POP_TOP                         
                134     LOAD_CLOSURE                    0: __class__
                136     COPY                            1
                138     STORE_NAME                      12: __classcell__
                140     RETURN_VALUE                    
                142     PUSH_EXC_INFO                   
                144     PUSH_NULL                       
                146     LOAD_CONST                      13: '__pyarmor_exit_22388__'
                148     NOP                             
                150     LOAD_CONST                      4: b'<COAddr>\x05\x00\x00(f\x00\x00\x00\x00\x00\x00\x00\x00\x00\x00\x00\x00\x00\x00\x00'
                152     CALL                            1
                160     POP_TOP                         
                162     RERAISE                         0
                164     COPY                            3
                166     POP_EXCEPT                      
                168     RERAISE                         1
                170     PUSH_NULL                       
                172     LOAD_CONST                      13: '__pyarmor_exit_22388__'
                174     LOAD_CONST                      4: b'<COAddr>\x05\x00\x00(f\x00\x00\x00\x00\x00\x00\x00\x00\x00\x00\x00\x00\x00\x00\x00'
                176     BUILD_TUPLE                     1
                178     CALL_FUNCTION_EX                0
                180     POP_TOP                         
                182     RETURN_VALUE                    
            [Exception Table]
                42 to 116 -> 142 [0] 
                142 to 164 -> 164 [1] lasti
        'Album'
        '__pyarmor_exit_22373__'
    [Disassembly]
        0       NOP                             
        2       NOP                             
        4       PUSH_NULL                       
        6       LOAD_CONST                      1: '__pyarmor_enter_22372__'
        8       LOAD_CONST                      2: b'<COAddr>\x07\x00\x00\x1a\xa8\x00\x00\x00\x00\x00\x00\x00\x00\x00\x00\x00\x00\x00\x00\x00'
        10      BUILD_TUPLE                     1
        12      CALL_FUNCTION_EX                0
        14      POP_TOP                         
        16      RESUME                          0
        18      NOP                             
        20      NOP                             
        22      NOP                             
        24      NOP                             
        26      LOAD_CONST                      3: 0
        28      LOAD_CONST                      4: None
        30      IMPORT_NAME                     1: asyncio
        32      STORE_NAME                      1: asyncio
        34      LOAD_CONST                      3: 0
        36      LOAD_CONST                      4: None
        38      IMPORT_NAME                     2: time
        40      STORE_NAME                      2: time
        42      LOAD_CONST                      3: 0
        44      LOAD_CONST                      4: None
        46      IMPORT_NAME                     3: weakref
        48      STORE_NAME                      3: weakref
        50      LOAD_CONST                      5: 1
        52      LOAD_CONST                      6: ('EventBuilder', 'EventCommon', 'name_inner_event')
        54      IMPORT_NAME                     4: common
        56      IMPORT_FROM                     5: EventBuilder
        58      STORE_NAME                      5: EventBuilder
        60      IMPORT_FROM                     6: EventCommon
        62      STORE_NAME                      6: EventCommon
        64      IMPORT_FROM                     7: name_inner_event
        66      STORE_NAME                      7: name_inner_event
        68      POP_TOP                         
        70      LOAD_CONST                      7: 2
        72      LOAD_CONST                      8: ('utils',)
        74      IMPORT_NAME                     8: 
        76      IMPORT_FROM                     9: utils
        78      STORE_NAME                      9: utils
        80      POP_TOP                         
        82      LOAD_CONST                      7: 2
        84      LOAD_CONST                      9: ('types',)
        86      IMPORT_NAME                     10: tl
        88      IMPORT_FROM                     11: types
        90      STORE_NAME                      11: types
        92      POP_TOP                         
        94      LOAD_CONST                      7: 2
        96      LOAD_CONST                      10: ('SenderGetter',)
        98      IMPORT_NAME                     12: tl.custom.sendergetter
        100     IMPORT_FROM                     13: SenderGetter
        102     STORE_NAME                      13: SenderGetter
        104     POP_TOP                         
        106     LOAD_CONST                      11: 100
        108     STORE_NAME                      14: _IGNORE_MAX_SIZE
        110     LOAD_CONST                      12: 5
        112     STORE_NAME                      15: _IGNORE_MAX_AGE
        114     BUILD_MAP                       0
        116     STORE_NAME                      16: _IGNORE_DICT
        118     LOAD_CONST                      13: 0.5
        120     STORE_NAME                      17: _HACK_DELAY
        122     PUSH_NULL                       
        124     LOAD_BUILD_CLASS                
        126     LOAD_CONST                      14: <CODE> AlbumHack
        128     MAKE_FUNCTION                   0
        130     LOAD_CONST                      15: 'AlbumHack'
        132     CALL                            2
        140     STORE_NAME                      18: AlbumHack
        142     LOAD_NAME                       7: name_inner_event
        144     PUSH_NULL                       
        146     LOAD_BUILD_CLASS                
        148     LOAD_CONST                      16: <CODE> Album
        150     MAKE_FUNCTION                   0
        152     LOAD_CONST                      17: 'Album'
        154     LOAD_NAME                       5: EventBuilder
        156     CALL                            3
        164     CALL                            0
        172     STORE_NAME                      19: Album
        174     LOAD_CONST                      4: None
        176     NOP                             
        178     NOP                             
        180     NOP                             
        182     JUMP_FORWARD                    19 (to 222)
        190     POP_TOP                         
        192     RETURN_CONST                    4: None
        194     PUSH_EXC_INFO                   
        196     PUSH_NULL                       
        198     LOAD_CONST                      18: '__pyarmor_exit_22373__'
        200     NOP                             
        202     LOAD_CONST                      2: b'<COAddr>\x07\x00\x00\x1a\xa8\x00\x00\x00\x00\x00\x00\x00\x00\x00\x00\x00\x00\x00\x00\x00'
        204     CALL                            1
        212     POP_TOP                         
        214     RERAISE                         0
        216     COPY                            3
        218     POP_EXCEPT                      
        220     RERAISE                         1
        222     PUSH_NULL                       
        224     LOAD_CONST                      18: '__pyarmor_exit_22373__'
        226     LOAD_CONST                      2: b'<COAddr>\x07\x00\x00\x1a\xa8\x00\x00\x00\x00\x00\x00\x00\x00\x00\x00\x00\x00\x00\x00\x00'
        228     BUILD_TUPLE                     1
        230     CALL_FUNCTION_EX                0
        232     POP_TOP                         
        234     RETURN_VALUE                    
    [Exception Table]
        26 to 174 -> 194 [0] 
        194 to 216 -> 216 [1] lasti
