#decoded by lolz.live/mrpenny / t.me/zeus_jackpot
# ================================
# Примечания по Pyarmor:
# - Байт-код и объекты кода Pyarmor соответствуют стандартному Python, но присутствуют специальные вызовы функций среды выполнения (runtime) Pyarmor.
# - Вызовы строк — это не ошибки, а маркеры, которые обрабатываются Pyarmor во время выполнения.
#
# Руководство по декомпиляции (без среды выполнения):
# 1. Игнорируйте зашифрованные байты после `#`; используйте только строку до `#`.
# 2. Удалите "__pyarmor_enter_xxx__"(b"<COAddr>...") и "__pyarmor_leave_xxx__"(b"<COAddr>...") (пролог/эпилог).
# 3. "__pyarmor_assert_xxx__"(A) не является настоящим оператором assert.
#    - Если A — это имя или читаемая строка: замените на A.
#    - Если A — это (X, "Y"): замените на X.Y.
#    - Если A — это (X, "Y", Z): замените на X.Y = Z.
#    - В противном случае: выберите наиболее подходящую/логичную замену.
# 4. "__pyarmor_bcc_xxx__"(...) указывает на машинный (нативный) код; тело функции недоступно. Добавьте комментарий.
# ================================

[Code]
    File Name: <frozen multithon.events.userupdate>
    Object Name: <module>
    Qualified Name: <module>
    Arg Count: 0
    Pos Only Arg Count: 0
    KW Only Arg Count: 0
    Stack Size: 6
    Flags: 0x20000000 (CO_PYARMOR_OBFUSCATED)
    [Names]
        '__assert_armored__'
        'datetime'
        'functools'
        'common'
        'EventBuilder'
        'EventCommon'
        'name_inner_event'
        ''
        'utils'
        'tl'
        'types'
        'tl.custom.sendergetter'
        'SenderGetter'
        '_requires_action'
        '_requires_status'
        'UserUpdate'
    [Locals+Names]
    [Constants]
        '__pyarmor_assert_22794__'
        '__pyarmor_enter_22795__'
        b'<COAddr>\x05\x00\x00\x1a\x88\x00\x00\x00\x00\x00\x00\x00\x00\x00\x00\x00\x00\x00\x00\x00'
        0
        None
        1
        (
            'EventBuilder'
            'EventCommon'
            'name_inner_event'
        )
        2
        (
            'utils'
        )
        (
            'types'
        )
        (
            'SenderGetter'
        )
        [Code]
            File Name: <frozen multithon.events.userupdate>
            Object Name: _requires_action
            Qualified Name: _requires_action
            Arg Count: 1
            Pos Only Arg Count: 0
            KW Only Arg Count: 0
            Stack Size: 5
            Flags: 0x20000003 (CO_OPTIMIZED | CO_NEWLOCALS | CO_PYARMOR_OBFUSCATED)
            [Names]
                'functools'
                'wraps'
            [Locals+Names]
                'function'
                '__assert_armored__'
                '_var_var_0'
            [Constants]
                None
                '__pyarmor_assert_22797__'
                '__pyarmor_enter_22798__'
                b'<COAddr>\x05\x00\x00\x1cR\x00\x00\x00\x00\x00\x00\x00\x00\x00\x00\x00\x00\x00\x00\x00'
                [Code]
                    File Name: <frozen multithon.events.userupdate>
                    Object Name: wrapped
                    Qualified Name: _requires_action.<locals>.wrapped
                    Arg Count: 1
                    Pos Only Arg Count: 0
                    KW Only Arg Count: 0
                    Stack Size: 5
                    Flags: 0x20000013 (CO_OPTIMIZED | CO_NEWLOCALS | CO_NESTED | CO_PYARMOR_OBFUSCATED)
                    [Names]
                        'action'
                    [Locals+Names]
                        'self'
                        '__assert_armored__'
                        'function'
                    [Constants]
                        None
                        '__pyarmor_assert_22800__'
                        '__pyarmor_enter_22801__'
                        b'<COAddr>\x05\x00\x00\x1c@\x00\x00\x00\x00\x00\x00\x00\x00\x00\x00\x00\x00\x00\x00\x00'
                        '__pyarmor_exit_22802__'
                    [Disassembly]
                        0       COPY_FREE_VARS                  1
                        2       NOP                             
                        4       NOP                             
                        6       PUSH_NULL                       
                        8       LOAD_CONST                      2: '__pyarmor_enter_22801__'
                        10      LOAD_CONST                      3: b'<COAddr>\x05\x00\x00\x1c@\x00\x00\x00\x00\x00\x00\x00\x00\x00\x00\x00\x00\x00\x00\x00'
                        12      BUILD_TUPLE                     1
                        14      CALL_FUNCTION_EX                0
                        16      POP_TOP                         
                        18      RESUME                          0
                        20      NOP                             
                        22      NOP                             
                        24      NOP                             
                        26      NOP                             
                        28      NOP                             
                        30      LOAD_FAST                       0: self
                        32      LOAD_ATTR                       0: action
                        52      POP_JUMP_IF_NOT_NONE            2 (to 58)
                        54      LOAD_CONST                      0: None
                        56      JUMP_FORWARD                    7 (to 72)
                        58      PUSH_NULL                       
                        60      LOAD_DEREF                      2: function
                        62      LOAD_FAST                       0: self
                        64      CALL                            1
                        72      NOP                             
                        74      NOP                             
                        76      NOP                             
                        78      JUMP_FORWARD                    20 (to 120)
                        80      CALL                            1
                        88      POP_TOP                         
                        90      RETURN_VALUE                    
                        92      PUSH_EXC_INFO                   
                        94      PUSH_NULL                       
                        96      LOAD_CONST                      4: '__pyarmor_exit_22802__'
                        98      NOP                             
                        100     LOAD_CONST                      3: b'<COAddr>\x05\x00\x00\x1c@\x00\x00\x00\x00\x00\x00\x00\x00\x00\x00\x00\x00\x00\x00\x00'
                        102     CALL                            1
                        110     POP_TOP                         
                        112     RERAISE                         0
                        114     COPY                            3
                        116     POP_EXCEPT                      
                        118     RERAISE                         1
                        120     PUSH_NULL                       
                        122     LOAD_CONST                      4: '__pyarmor_exit_22802__'
                        124     LOAD_CONST                      3: b'<COAddr>\x05\x00\x00\x1c@\x00\x00\x00\x00\x00\x00\x00\x00\x00\x00\x00\x00\x00\x00\x00'
                        126     BUILD_TUPLE                     1
                        128     CALL_FUNCTION_EX                0
                        130     POP_TOP                         
                        132     RETURN_VALUE                    
                    [Exception Table]
                        30 to 72 -> 92 [0] 
                        92 to 114 -> 114 [1] lasti
                '__pyarmor_exit_22799__'
            [Disassembly]
                0       MAKE_CELL                       0: function
                2       NOP                             
                4       NOP                             
                6       PUSH_NULL                       
                8       LOAD_CONST                      2: '__pyarmor_enter_22798__'
                10      LOAD_CONST                      3: b'<COAddr>\x05\x00\x00\x1cR\x00\x00\x00\x00\x00\x00\x00\x00\x00\x00\x00\x00\x00\x00\x00'
                12      BUILD_TUPLE                     1
                14      CALL_FUNCTION_EX                0
                16      POP_TOP                         
                18      RESUME                          0
                20      NOP                             
                22      NOP                             
                24      NOP                             
                26      NOP                             
                28      NOP                             
                30      LOAD_GLOBAL                     1: NULL + functools
                40      LOAD_ATTR                       2: wraps
                60      LOAD_DEREF                      0: function
                62      CALL                            1
                70      LOAD_CLOSURE                    0: function
                72      BUILD_TUPLE                     1
                74      LOAD_CONST                      4: <CODE> wrapped
                76      MAKE_FUNCTION                   8
                78      CALL                            0
                86      STORE_FAST                      2: _var_var_0
                88      LOAD_FAST                       2: _var_var_0
                90      NOP                             
                92      NOP                             
                94      NOP                             
                96      JUMP_FORWARD                    20 (to 138)
                98      CALL                            1
                106     POP_TOP                         
                108     RETURN_VALUE                    
                110     PUSH_EXC_INFO                   
                112     PUSH_NULL                       
                114     LOAD_CONST                      5: '__pyarmor_exit_22799__'
                116     NOP                             
                118     LOAD_CONST                      3: b'<COAddr>\x05\x00\x00\x1cR\x00\x00\x00\x00\x00\x00\x00\x00\x00\x00\x00\x00\x00\x00\x00'
                120     CALL                            1
                128     POP_TOP                         
                130     RERAISE                         0
                132     COPY                            3
                134     POP_EXCEPT                      
                136     RERAISE                         1
                138     PUSH_NULL                       
                140     LOAD_CONST                      5: '__pyarmor_exit_22799__'
                142     LOAD_CONST                      3: b'<COAddr>\x05\x00\x00\x1cR\x00\x00\x00\x00\x00\x00\x00\x00\x00\x00\x00\x00\x00\x00\x00'
                144     BUILD_TUPLE                     1
                146     CALL_FUNCTION_EX                0
                148     POP_TOP                         
                150     RETURN_VALUE                    
            [Exception Table]
                30 to 90 -> 110 [0] 
                110 to 132 -> 132 [1] lasti
        [Code]
            File Name: <frozen multithon.events.userupdate>
            Object Name: _requires_status
            Qualified Name: _requires_status
            Arg Count: 1
            Pos Only Arg Count: 0
            KW Only Arg Count: 0
            Stack Size: 5
            Flags: 0x20000003 (CO_OPTIMIZED | CO_NEWLOCALS | CO_PYARMOR_OBFUSCATED)
            [Names]
                'functools'
                'wraps'
            [Locals+Names]
                'function'
                '__assert_armored__'
                '_var_var_0'
            [Constants]
                None
                '__pyarmor_assert_22803__'
                '__pyarmor_enter_22804__'
                b'<COAddr>\x05\x00\x00\x1cR\x00\x00\x00\x00\x00\x00\x00\x00\x00\x00\x00\x00\x00\x00\x00'
                [Code]
                    File Name: <frozen multithon.events.userupdate>
                    Object Name: wrapped
                    Qualified Name: _requires_status.<locals>.wrapped
                    Arg Count: 1
                    Pos Only Arg Count: 0
                    KW Only Arg Count: 0
                    Stack Size: 5
                    Flags: 0x20000013 (CO_OPTIMIZED | CO_NEWLOCALS | CO_NESTED | CO_PYARMOR_OBFUSCATED)
                    [Names]
                        'status'
                    [Locals+Names]
                        'self'
                        '__assert_armored__'
                        'function'
                    [Constants]
                        None
                        '__pyarmor_assert_22806__'
                        '__pyarmor_enter_22807__'
                        b'<COAddr>\x07\x00\x00\x1c@\x00\x00\x00\x00\x00\x00\x00\x00\x00\x00\x00\x00\x00\x00\x00'
                        '__pyarmor_exit_22808__'
                    [Disassembly]
                        0       COPY_FREE_VARS                  1
                        2       NOP                             
                        4       NOP                             
                        6       PUSH_NULL                       
                        8       LOAD_CONST                      2: '__pyarmor_enter_22807__'
                        10      LOAD_CONST                      3: b'<COAddr>\x07\x00\x00\x1c@\x00\x00\x00\x00\x00\x00\x00\x00\x00\x00\x00\x00\x00\x00\x00'
                        12      BUILD_TUPLE                     1
                        14      CALL_FUNCTION_EX                0
                        16      POP_TOP                         
                        18      RESUME                          0
                        20      NOP                             
                        22      NOP                             
                        24      NOP                             
                        26      NOP                             
                        28      NOP                             
                        30      LOAD_FAST                       0: self
                        32      LOAD_ATTR                       0: status
                        52      POP_JUMP_IF_NOT_NONE            2 (to 58)
                        54      LOAD_CONST                      0: None
                        56      JUMP_FORWARD                    7 (to 72)
                        58      PUSH_NULL                       
                        60      LOAD_DEREF                      2: function
                        62      LOAD_FAST                       0: self
                        64      CALL                            1
                        72      NOP                             
                        74      NOP                             
                        76      NOP                             
                        78      JUMP_FORWARD                    20 (to 120)
                        80      CALL                            1
                        88      POP_TOP                         
                        90      RETURN_VALUE                    
                        92      PUSH_EXC_INFO                   
                        94      PUSH_NULL                       
                        96      LOAD_CONST                      4: '__pyarmor_exit_22808__'
                        98      NOP                             
                        100     LOAD_CONST                      3: b'<COAddr>\x07\x00\x00\x1c@\x00\x00\x00\x00\x00\x00\x00\x00\x00\x00\x00\x00\x00\x00\x00'
                        102     CALL                            1
                        110     POP_TOP                         
                        112     RERAISE                         0
                        114     COPY                            3
                        116     POP_EXCEPT                      
                        118     RERAISE                         1
                        120     PUSH_NULL                       
                        122     LOAD_CONST                      4: '__pyarmor_exit_22808__'
                        124     LOAD_CONST                      3: b'<COAddr>\x07\x00\x00\x1c@\x00\x00\x00\x00\x00\x00\x00\x00\x00\x00\x00\x00\x00\x00\x00'
                        126     BUILD_TUPLE                     1
                        128     CALL_FUNCTION_EX                0
                        130     POP_TOP                         
                        132     RETURN_VALUE                    
                    [Exception Table]
                        30 to 72 -> 92 [0] 
                        92 to 114 -> 114 [1] lasti
                '__pyarmor_exit_22805__'
            [Disassembly]
                0       MAKE_CELL                       0: function
                2       NOP                             
                4       NOP                             
                6       PUSH_NULL                       
                8       LOAD_CONST                      2: '__pyarmor_enter_22804__'
                10      LOAD_CONST                      3: b'<COAddr>\x05\x00\x00\x1cR\x00\x00\x00\x00\x00\x00\x00\x00\x00\x00\x00\x00\x00\x00\x00'
                12      BUILD_TUPLE                     1
                14      CALL_FUNCTION_EX                0
                16      POP_TOP                         
                18      RESUME                          0
                20      NOP                             
                22      NOP                             
                24      NOP                             
                26      NOP                             
                28      NOP                             
                30      LOAD_GLOBAL                     1: NULL + functools
                40      LOAD_ATTR                       2: wraps
                60      LOAD_DEREF                      0: function
                62      CALL                            1
                70      LOAD_CLOSURE                    0: function
                72      BUILD_TUPLE                     1
                74      LOAD_CONST                      4: <CODE> wrapped
                76      MAKE_FUNCTION                   8
                78      CALL                            0
                86      STORE_FAST                      2: _var_var_0
                88      LOAD_FAST                       2: _var_var_0
                90      NOP                             
                92      NOP                             
                94      NOP                             
                96      JUMP_FORWARD                    20 (to 138)
                98      CALL                            1
                106     POP_TOP                         
                108     RETURN_VALUE                    
                110     PUSH_EXC_INFO                   
                112     PUSH_NULL                       
                114     LOAD_CONST                      5: '__pyarmor_exit_22805__'
                116     NOP                             
                118     LOAD_CONST                      3: b'<COAddr>\x05\x00\x00\x1cR\x00\x00\x00\x00\x00\x00\x00\x00\x00\x00\x00\x00\x00\x00\x00'
                120     CALL                            1
                128     POP_TOP                         
                130     RERAISE                         0
                132     COPY                            3
                134     POP_EXCEPT                      
                136     RERAISE                         1
                138     PUSH_NULL                       
                140     LOAD_CONST                      5: '__pyarmor_exit_22805__'
                142     LOAD_CONST                      3: b'<COAddr>\x05\x00\x00\x1cR\x00\x00\x00\x00\x00\x00\x00\x00\x00\x00\x00\x00\x00\x00\x00'
                144     BUILD_TUPLE                     1
                146     CALL_FUNCTION_EX                0
                148     POP_TOP                         
                150     RETURN_VALUE                    
            [Exception Table]
                30 to 90 -> 110 [0] 
                110 to 132 -> 132 [1] lasti
        [Code]
            File Name: <frozen multithon.events.userupdate>
            Object Name: UserUpdate
            Qualified Name: UserUpdate
            Arg Count: 0
            Pos Only Arg Count: 0
            KW Only Arg Count: 0
            Stack Size: 6
            Flags: 0x20000000 (CO_PYARMOR_OBFUSCATED)
            [Names]
                '__name__'
                '__module__'
                '__qualname__'
                '__doc__'
                '__assert_armored__'
                'classmethod'
                'build'
                'EventCommon'
                'SenderGetter'
                'Event'
            [Locals+Names]
            [Constants]
                'UserUpdate'
                "\n    Occurs whenever a user goes online, starts typing, etc.\n\n    Example\n        .. code-block:: python\n\n            from multithon import events\n\n            @client.on(events.UserUpdate)\n            async def handler(event):\n                # If someone is uploading, say something\n                if event.uploading:\n                    await client.send_message(event.user_id, 'What are you sending?')\n    "
                '__pyarmor_assert_22809__'
                '__pyarmor_enter_22810__'
                b'<COAddr>\x05\x00\x00&@\x00\x00\x00\x00\x00\x00\x00\x00\x00\x00\x00\x00\x00\x00\x00'
                None
                [Code]
                    File Name: <frozen multithon.events.userupdate>
                    Object Name: build
                    Qualified Name: UserUpdate.build
                    Arg Count: 4
                    Pos Only Arg Count: 0
                    KW Only Arg Count: 0
                    Stack Size: 6
                    Flags: 0x20000003 (CO_OPTIMIZED | CO_NEWLOCALS | CO_PYARMOR_OBFUSCATED)
                    [Names]
                        'isinstance'
                        'types'
                        'UpdateUserStatus'
                        'Event'
                        'PeerUser'
                        'user_id'
                        'status'
                        'UpdateChannelUserTyping'
                        'from_id'
                        'PeerChannel'
                        'channel_id'
                        'action'
                        'UpdateChatUserTyping'
                        'PeerChat'
                        'chat_id'
                        'UpdateUserTyping'
                    [Locals+Names]
                        'cls'
                        'update'
                        'others'
                        'self_id'
                        '__assert_armored__'
                    [Constants]
                        None
                        '__pyarmor_assert_22812__'
                        '__pyarmor_enter_22813__'
                        b'<COAddr>\x07\x00\x00\x1a\x06\x03\x00\x00\x00\x00\x00\x00\x00\x00\x00\x00\x00\x00\x00\x00'
                        (
                            'status'
                        )
                        '__pyarmor_exit_22814__'
                        (
                            'chat_peer'
                            'typing'
                        )
                        (
                            'typing'
                        )
                    [Disassembly]
                        0       NOP                             
                        2       NOP                             
                        4       PUSH_NULL                       
                        6       LOAD_CONST                      2: '__pyarmor_enter_22813__'
                        8       LOAD_CONST                      3: b'<COAddr>\x07\x00\x00\x1a\x06\x03\x00\x00\x00\x00\x00\x00\x00\x00\x00\x00\x00\x00\x00\x00'
                        10      BUILD_TUPLE                     1
                        12      CALL_FUNCTION_EX                0
                        14      POP_TOP                         
                        16      RESUME                          0
                        18      NOP                             
                        20      NOP                             
                        22      NOP                             
                        24      NOP                             
                        26      NOP                             
                        28      LOAD_GLOBAL                     1: NULL + isinstance
                        38      LOAD_FAST                       1: update
                        40      LOAD_GLOBAL                     2: types
                        50      LOAD_ATTR                       4: UpdateUserStatus
                        70      CALL                            2
                        78      POP_JUMP_IF_FALSE               67 (to 214)
                        80      LOAD_FAST                       0: cls
                        82      LOAD_ATTR                       7: Event
                        102     LOAD_GLOBAL                     3: NULL + types
                        112     LOAD_ATTR                       8: PeerUser
                        132     LOAD_FAST                       1: update
                        134     LOAD_ATTR                       10: user_id
                        154     CALL                            1
                        162     LOAD_FAST                       1: update
                        164     LOAD_ATTR                       12: status
                        184     KW_NAMES                        4: ('status',)
                        186     CALL                            2
                        194     NOP                             
                        196     NOP                             
                        198     JUMP_FORWARD                    313 (to 828)
                        202     CALL                            1
                        210     POP_TOP                         
                        212     RETURN_VALUE                    
                        214     LOAD_GLOBAL                     1: NULL + isinstance
                        224     LOAD_FAST                       1: update
                        226     LOAD_GLOBAL                     2: types
                        236     LOAD_ATTR                       14: UpdateChannelUserTyping
                        256     CALL                            2
                        264     POP_JUMP_IF_FALSE               78 (to 422)
                        266     LOAD_FAST                       0: cls
                        268     LOAD_ATTR                       7: Event
                        288     LOAD_FAST                       1: update
                        290     LOAD_ATTR                       16: from_id
                        310     LOAD_GLOBAL                     3: NULL + types
                        320     LOAD_ATTR                       18: PeerChannel
                        340     LOAD_FAST                       1: update
                        342     LOAD_ATTR                       20: channel_id
                        362     CALL                            1
                        370     LOAD_FAST                       1: update
                        372     LOAD_ATTR                       22: action
                        392     KW_NAMES                        6: ('chat_peer', 'typing')
                        394     CALL                            3
                        402     NOP                             
                        404     NOP                             
                        406     NOP                             
                        408     JUMP_FORWARD                    209 (to 828)
                        410     CALL                            1
                        418     POP_TOP                         
                        420     RETURN_VALUE                    
                        422     LOAD_GLOBAL                     1: NULL + isinstance
                        432     LOAD_FAST                       1: update
                        434     LOAD_GLOBAL                     2: types
                        444     LOAD_ATTR                       24: UpdateChatUserTyping
                        464     CALL                            2
                        472     POP_JUMP_IF_FALSE               78 (to 630)
                        474     LOAD_FAST                       0: cls
                        476     LOAD_ATTR                       7: Event
                        496     LOAD_FAST                       1: update
                        498     LOAD_ATTR                       16: from_id
                        518     LOAD_GLOBAL                     3: NULL + types
                        528     LOAD_ATTR                       26: PeerChat
                        548     LOAD_FAST                       1: update
                        550     LOAD_ATTR                       28: chat_id
                        570     CALL                            1
                        578     LOAD_FAST                       1: update
                        580     LOAD_ATTR                       22: action
                        600     KW_NAMES                        6: ('chat_peer', 'typing')
                        602     CALL                            3
                        610     NOP                             
                        612     NOP                             
                        614     NOP                             
                        616     JUMP_FORWARD                    105 (to 828)
                        618     CALL                            1
                        626     POP_TOP                         
                        628     RETURN_VALUE                    
                        630     LOAD_GLOBAL                     1: NULL + isinstance
                        640     LOAD_FAST                       1: update
                        642     LOAD_GLOBAL                     2: types
                        652     LOAD_ATTR                       30: UpdateUserTyping
                        672     CALL                            2
                        680     POP_JUMP_IF_FALSE               48 (to 778)
                        682     LOAD_FAST                       0: cls
                        684     LOAD_ATTR                       7: Event
                        704     LOAD_FAST                       1: update
                        706     LOAD_ATTR                       10: user_id
                        726     LOAD_FAST                       1: update
                        728     LOAD_ATTR                       22: action
                        748     KW_NAMES                        7: ('typing',)
                        750     CALL                            2
                        758     NOP                             
                        760     NOP                             
                        762     NOP                             
                        764     JUMP_FORWARD                    31 (to 828)
                        766     CALL                            1
                        774     POP_TOP                         
                        776     RETURN_VALUE                    
                        778     NOP                             
                        780     LOAD_CONST                      0: None
                        782     NOP                             
                        784     NOP                             
                        786     NOP                             
                        788     JUMP_FORWARD                    19 (to 828)
                        796     POP_TOP                         
                        798     RETURN_CONST                    0: None
                        800     PUSH_EXC_INFO                   
                        802     PUSH_NULL                       
                        804     LOAD_CONST                      5: '__pyarmor_exit_22814__'
                        806     NOP                             
                        808     LOAD_CONST                      3: b'<COAddr>\x07\x00\x00\x1a\x06\x03\x00\x00\x00\x00\x00\x00\x00\x00\x00\x00\x00\x00\x00\x00'
                        810     CALL                            1
                        818     POP_TOP                         
                        820     RERAISE                         0
                        822     COPY                            3
                        824     POP_EXCEPT                      
                        826     RERAISE                         1
                        828     PUSH_NULL                       
                        830     LOAD_CONST                      5: '__pyarmor_exit_22814__'
                        832     LOAD_CONST                      3: b'<COAddr>\x07\x00\x00\x1a\x06\x03\x00\x00\x00\x00\x00\x00\x00\x00\x00\x00\x00\x00\x00\x00'
                        834     BUILD_TUPLE                     1
                        836     CALL_FUNCTION_EX                0
                        838     POP_TOP                         
                        840     RETURN_VALUE                    
                    [Exception Table]
                        28 to 194 -> 800 [0] 
                        214 to 402 -> 800 [0] 
                        422 to 610 -> 800 [0] 
                        630 to 758 -> 800 [0] 
                        800 to 822 -> 822 [1] lasti
                [Code]
                    File Name: <frozen multithon.events.userupdate>
                    Object Name: Event
                    Qualified Name: UserUpdate.Event
                    Arg Count: 0
                    Pos Only Arg Count: 0
                    KW Only Arg Count: 0
                    Stack Size: 5
                    Flags: 0x20000000 (CO_PYARMOR_OBFUSCATED)
                    [Names]
                        '__name__'
                        '__module__'
                        '__qualname__'
                        '__doc__'
                        '__assert_armored__'
                        '__init__'
                        '_set_client'
                        'property'
                        'user'
                        'get_user'
                        'input_user'
                        'get_input_user'
                        'user_id'
                        '_requires_action'
                        'typing'
                        'uploading'
                        'recording'
                        'playing'
                        'cancel'
                        'geo'
                        'audio'
                        'round'
                        'video'
                        'contact'
                        'document'
                        'sticker'
                        'photo'
                        '_requires_status'
                        'last_seen'
                        'until'
                        '_last_seen_delta'
                        'online'
                        'recently'
                        'within_weeks'
                        'within_months'
                        '__classcell__'
                    [Locals+Names]
                        '__class__'
                    [Constants]
                        'UserUpdate.Event'
                        '\n        Represents the event of a user update\n        such as gone online, started typing, etc.\n\n        Members:\n            status (:tl:`UserStatus`, optional):\n                The user status if the update is about going online or offline.\n\n                You should check this attribute first before checking any\n                of the seen within properties, since they will all be `None`\n                if the status is not set.\n\n            action (:tl:`SendMessageAction`, optional):\n                The "typing" action if any the user is performing if any.\n\n                You should check this attribute first before checking any\n                of the typing properties, since they will all be `None`\n                if the action is not set.\n        '
                        '__pyarmor_assert_22815__'
                        '__pyarmor_enter_22816__'
                        b'<COAddr>\x07\x00\x00(j\x02\x00\x00\x00\x00\x00\x00\x00\x00\x00\x00\x00\x00\x00\x00'
                        None
                        (
                            'status'
                            'chat_peer'
                            'typing'
                        )
                        [Code]
                            File Name: <frozen multithon.events.userupdate>
                            Object Name: __init__
                            Qualified Name: UserUpdate.Event.__init__
                            Arg Count: 2
                            Pos Only Arg Count: 0
                            KW Only Arg Count: 3
                            Stack Size: 6
                            Flags: 0x20000003 (CO_OPTIMIZED | CO_NEWLOCALS | CO_PYARMOR_OBFUSCATED)
                            [Names]
                                'super'
                                '__init__'
                                'SenderGetter'
                                'utils'
                                'get_peer_id'
                                'status'
                                'action'
                            [Locals+Names]
                                'self'
                                'peer'
                                'status'
                                'chat_peer'
                                'typing'
                                '__assert_armored__'
                                '__class__'
                            [Constants]
                                None
                                '__pyarmor_assert_22818__'
                                '__pyarmor_enter_22819__'
                                b'<COAddr>\x05\x00\x00\x1c\xaa\x00\x00\x00\x00\x00\x00\x00\x00\x00\x00\x00\x00\x00\x00\x00'
                                '__pyarmor_exit_22820__'
                            [Disassembly]
                                0       COPY_FREE_VARS                  1
                                2       NOP                             
                                4       NOP                             
                                6       PUSH_NULL                       
                                8       LOAD_CONST                      2: '__pyarmor_enter_22819__'
                                10      LOAD_CONST                      3: b'<COAddr>\x05\x00\x00\x1c\xaa\x00\x00\x00\x00\x00\x00\x00\x00\x00\x00\x00\x00\x00\x00\x00'
                                12      BUILD_TUPLE                     1
                                14      CALL_FUNCTION_EX                0
                                16      POP_TOP                         
                                18      RESUME                          0
                                20      NOP                             
                                22      NOP                             
                                24      NOP                             
                                26      NOP                             
                                28      NOP                             
                                30      LOAD_GLOBAL                     0: super
                                40      LOAD_DEREF                      6: __class__
                                42      LOAD_FAST                       0: self
                                44      LOAD_SUPER_ATTR                 5: __init__
                                48      LOAD_FAST                       3: chat_peer
                                50      COPY                            1
                                52      POP_JUMP_IF_TRUE                2 (to 58)
                                54      POP_TOP                         
                                56      LOAD_FAST                       1: peer
                                58      CALL                            1
                                66      POP_TOP                         
                                68      LOAD_GLOBAL                     5: NULL + SenderGetter
                                78      LOAD_ATTR                       2: __init__
                                98      LOAD_FAST                       0: self
                                100     LOAD_GLOBAL                     7: NULL + utils
                                110     LOAD_ATTR                       8: get_peer_id
                                130     LOAD_FAST                       1: peer
                                132     CALL                            1
                                140     CALL                            2
                                148     POP_TOP                         
                                150     LOAD_FAST                       2: status
                                152     LOAD_FAST                       0: self
                                154     STORE_ATTR                      5: status
                                164     LOAD_FAST                       4: typing
                                166     LOAD_FAST                       0: self
                                168     STORE_ATTR                      6: action
                                178     LOAD_CONST                      0: None
                                180     NOP                             
                                182     NOP                             
                                184     NOP                             
                                186     JUMP_FORWARD                    19 (to 226)
                                194     POP_TOP                         
                                196     RETURN_CONST                    0: None
                                198     PUSH_EXC_INFO                   
                                200     PUSH_NULL                       
                                202     LOAD_CONST                      4: '__pyarmor_exit_22820__'
                                204     NOP                             
                                206     LOAD_CONST                      3: b'<COAddr>\x05\x00\x00\x1c\xaa\x00\x00\x00\x00\x00\x00\x00\x00\x00\x00\x00\x00\x00\x00\x00'
                                208     CALL                            1
                                216     POP_TOP                         
                                218     RERAISE                         0
                                220     COPY                            3
                                222     POP_EXCEPT                      
                                224     RERAISE                         1
                                226     PUSH_NULL                       
                                228     LOAD_CONST                      4: '__pyarmor_exit_22820__'
                                230     LOAD_CONST                      3: b'<COAddr>\x05\x00\x00\x1c\xaa\x00\x00\x00\x00\x00\x00\x00\x00\x00\x00\x00\x00\x00\x00\x00'
                                232     BUILD_TUPLE                     1
                                234     CALL_FUNCTION_EX                0
                                236     POP_TOP                         
                                238     RETURN_VALUE                    
                            [Exception Table]
                                30 to 178 -> 198 [0] 
                                198 to 220 -> 220 [1] lasti
                        [Code]
                            File Name: <frozen multithon.events.userupdate>
                            Object Name: _set_client
                            Qualified Name: UserUpdate.Event._set_client
                            Arg Count: 2
                            Pos Only Arg Count: 0
                            KW Only Arg Count: 0
                            Stack Size: 5
                            Flags: 0x20000003 (CO_OPTIMIZED | CO_NEWLOCALS | CO_PYARMOR_OBFUSCATED)
                            [Names]
                                'super'
                                '_set_client'
                                'utils'
                                '_get_entity_pair'
                                'sender_id'
                                '_entities'
                                '_mb_entity_cache'
                                '_sender'
                                '_input_sender'
                            [Locals+Names]
                                'self'
                                'client'
                                '__assert_armored__'
                                '__class__'
                            [Constants]
                                None
                                '__pyarmor_assert_22821__'
                                '__pyarmor_enter_22822__'
                                b'<COAddr>\x05\x00\x00\x1c\xb8\x00\x00\x00\x00\x00\x00\x00\x00\x00\x00\x00\x00\x00\x00\x00'
                                '__pyarmor_exit_22823__'
                            [Disassembly]
                                0       COPY_FREE_VARS                  1
                                2       NOP                             
                                4       NOP                             
                                6       PUSH_NULL                       
                                8       LOAD_CONST                      2: '__pyarmor_enter_22822__'
                                10      LOAD_CONST                      3: b'<COAddr>\x05\x00\x00\x1c\xb8\x00\x00\x00\x00\x00\x00\x00\x00\x00\x00\x00\x00\x00\x00\x00'
                                12      BUILD_TUPLE                     1
                                14      CALL_FUNCTION_EX                0
                                16      POP_TOP                         
                                18      RESUME                          0
                                20      NOP                             
                                22      NOP                             
                                24      NOP                             
                                26      NOP                             
                                28      NOP                             
                                30      LOAD_GLOBAL                     0: super
                                40      LOAD_DEREF                      3: __class__
                                42      LOAD_FAST                       0: self
                                44      LOAD_SUPER_ATTR                 5: _set_client
                                48      LOAD_FAST                       1: client
                                50      CALL                            1
                                58      POP_TOP                         
                                60      LOAD_GLOBAL                     5: NULL + utils
                                70      LOAD_ATTR                       6: _get_entity_pair
                                90      LOAD_FAST                       0: self
                                92      LOAD_ATTR                       8: sender_id
                                112     LOAD_FAST                       0: self
                                114     LOAD_ATTR                       10: _entities
                                134     LOAD_FAST                       1: client
                                136     LOAD_ATTR                       12: _mb_entity_cache
                                156     CALL                            3
                                164     UNPACK_SEQUENCE                 2
                                168     LOAD_FAST                       0: self
                                170     STORE_ATTR                      7: _sender
                                180     LOAD_FAST                       0: self
                                182     STORE_ATTR                      8: _input_sender
                                192     LOAD_CONST                      0: None
                                194     NOP                             
                                196     NOP                             
                                198     NOP                             
                                200     JUMP_FORWARD                    19 (to 240)
                                208     POP_TOP                         
                                210     RETURN_CONST                    0: None
                                212     PUSH_EXC_INFO                   
                                214     PUSH_NULL                       
                                216     LOAD_CONST                      4: '__pyarmor_exit_22823__'
                                218     NOP                             
                                220     LOAD_CONST                      3: b'<COAddr>\x05\x00\x00\x1c\xb8\x00\x00\x00\x00\x00\x00\x00\x00\x00\x00\x00\x00\x00\x00\x00'
                                222     CALL                            1
                                230     POP_TOP                         
                                232     RERAISE                         0
                                234     COPY                            3
                                236     POP_EXCEPT                      
                                238     RERAISE                         1
                                240     PUSH_NULL                       
                                242     LOAD_CONST                      4: '__pyarmor_exit_22823__'
                                244     LOAD_CONST                      3: b'<COAddr>\x05\x00\x00\x1c\xb8\x00\x00\x00\x00\x00\x00\x00\x00\x00\x00\x00\x00\x00\x00\x00'
                                246     BUILD_TUPLE                     1
                                248     CALL_FUNCTION_EX                0
                                250     POP_TOP                         
                                252     RETURN_VALUE                    
                            [Exception Table]
                                30 to 192 -> 212 [0] 
                                212 to 234 -> 234 [1] lasti
                        [Code]
                            File Name: <frozen multithon.events.userupdate>
                            Object Name: user
                            Qualified Name: UserUpdate.Event.user
                            Arg Count: 1
                            Pos Only Arg Count: 0
                            KW Only Arg Count: 0
                            Stack Size: 5
                            Flags: 0x20000003 (CO_OPTIMIZED | CO_NEWLOCALS | CO_PYARMOR_OBFUSCATED)
                            [Names]
                                'sender'
                            [Locals+Names]
                                'self'
                                '__assert_armored__'
                            [Constants]
                                'Alias for `sender <telethon.tl.custom.sendergetter.SenderGetter.sender>`.'
                                '__pyarmor_assert_22824__'
                                '__pyarmor_enter_22825__'
                                b'<COAddr>\x05\x00\x00\x1a,\x00\x00\x00\x00\x00\x00\x00\x00\x00\x00\x00\x00\x00\x00\x00'
                                '__pyarmor_exit_22826__'
                            [Disassembly]
                                0       NOP                             
                                2       NOP                             
                                4       PUSH_NULL                       
                                6       LOAD_CONST                      2: '__pyarmor_enter_22825__'
                                8       LOAD_CONST                      3: b'<COAddr>\x05\x00\x00\x1a,\x00\x00\x00\x00\x00\x00\x00\x00\x00\x00\x00\x00\x00\x00\x00'
                                10      BUILD_TUPLE                     1
                                12      CALL_FUNCTION_EX                0
                                14      POP_TOP                         
                                16      RESUME                          0
                                18      NOP                             
                                20      NOP                             
                                22      NOP                             
                                24      NOP                             
                                26      NOP                             
                                28      LOAD_FAST                       0: self
                                30      LOAD_ATTR                       0: sender
                                50      NOP                             
                                52      NOP                             
                                54      NOP                             
                                56      JUMP_FORWARD                    20 (to 98)
                                58      CALL                            1
                                66      POP_TOP                         
                                68      RETURN_VALUE                    
                                70      PUSH_EXC_INFO                   
                                72      PUSH_NULL                       
                                74      LOAD_CONST                      4: '__pyarmor_exit_22826__'
                                76      NOP                             
                                78      LOAD_CONST                      3: b'<COAddr>\x05\x00\x00\x1a,\x00\x00\x00\x00\x00\x00\x00\x00\x00\x00\x00\x00\x00\x00\x00'
                                80      CALL                            1
                                88      POP_TOP                         
                                90      RERAISE                         0
                                92      COPY                            3
                                94      POP_EXCEPT                      
                                96      RERAISE                         1
                                98      PUSH_NULL                       
                                100     LOAD_CONST                      4: '__pyarmor_exit_22826__'
                                102     LOAD_CONST                      3: b'<COAddr>\x05\x00\x00\x1a,\x00\x00\x00\x00\x00\x00\x00\x00\x00\x00\x00\x00\x00\x00\x00'
                                104     BUILD_TUPLE                     1
                                106     CALL_FUNCTION_EX                0
                                108     POP_TOP                         
                                110     RETURN_VALUE                    
                            [Exception Table]
                                28 to 50 -> 70 [0] 
                                70 to 92 -> 92 [1] lasti
                        [Code]
                            File Name: <frozen multithon.events.userupdate>
                            Object Name: get_user
                            Qualified Name: UserUpdate.Event.get_user
                            Arg Count: 1
                            Pos Only Arg Count: 0
                            KW Only Arg Count: 0
                            Stack Size: 5
                            Flags: 0x20000083 (CO_OPTIMIZED | CO_NEWLOCALS | CO_COROUTINE | CO_PYARMOR_OBFUSCATED)
                            [Names]
                                'get_sender'
                            [Locals+Names]
                                'self'
                                '__assert_armored__'
                            [Constants]
                                'Alias for `get_sender <telethon.tl.custom.sendergetter.SenderGetter.get_sender>`.'
                                '__pyarmor_assert_22827__'
                                '__pyarmor_enter_22828__'
                                b'<COAddr>\x07\x00\x00\x1eH\x00\x00\x00\x00\x00\x00\x00\x00\x00\x00\x00\x00\x00\x00\x00'
                                None
                                '__pyarmor_exit_22829__'
                            [Disassembly]
                                0       RETURN_GENERATOR                
                                2       POP_TOP                         
                                4       NOP                             
                                6       NOP                             
                                8       PUSH_NULL                       
                                10      LOAD_CONST                      2: '__pyarmor_enter_22828__'
                                12      LOAD_CONST                      3: b'<COAddr>\x07\x00\x00\x1eH\x00\x00\x00\x00\x00\x00\x00\x00\x00\x00\x00\x00\x00\x00\x00'
                                14      BUILD_TUPLE                     1
                                16      CALL_FUNCTION_EX                0
                                18      POP_TOP                         
                                20      RESUME                          0
                                22      NOP                             
                                24      NOP                             
                                26      NOP                             
                                28      NOP                             
                                30      NOP                             
                                32      LOAD_FAST                       0: self
                                34      LOAD_ATTR                       1: get_sender
                                54      CALL                            0
                                62      GET_AWAITABLE                   0
                                64      LOAD_CONST                      4: None
                                66      SEND                            3 (to 74)
                                70      YIELD_VALUE                     3
                                72      RESUME                          3
                                74      JUMP_BACKWARD_NO_INTERRUPT      5 (to 66)
                                76      END_SEND                        
                                78      NOP                             
                                80      NOP                             
                                82      NOP                             
                                84      JUMP_FORWARD                    24 (to 134)
                                86      CALL                            1
                                94      POP_TOP                         
                                96      RETURN_VALUE                    
                                98      CLEANUP_THROW                   
                                100     JUMP_BACKWARD                   13 (to 76)
                                102     PUSH_EXC_INFO                   
                                104     PUSH_NULL                       
                                106     LOAD_CONST                      5: '__pyarmor_exit_22829__'
                                108     NOP                             
                                110     LOAD_CONST                      3: b'<COAddr>\x07\x00\x00\x1eH\x00\x00\x00\x00\x00\x00\x00\x00\x00\x00\x00\x00\x00\x00\x00'
                                112     CALL                            1
                                120     POP_TOP                         
                                122     RERAISE                         0
                                124     COPY                            3
                                126     POP_EXCEPT                      
                                128     RERAISE                         1
                                130     CALL_INTRINSIC_1                3 (INTRINSIC_STOPITERATION_ERROR)
                                132     RERAISE                         1
                                134     PUSH_NULL                       
                                136     LOAD_CONST                      5: '__pyarmor_exit_22829__'
                                138     LOAD_CONST                      3: b'<COAddr>\x07\x00\x00\x1eH\x00\x00\x00\x00\x00\x00\x00\x00\x00\x00\x00\x00\x00\x00\x00'
                                140     BUILD_TUPLE                     1
                                142     CALL_FUNCTION_EX                0
                                144     POP_TOP                         
                                146     RETURN_VALUE                    
                            [Exception Table]
                                4 to 30 -> 130 [0] lasti
                                32 to 70 -> 102 [0] 
                                70 to 72 -> 98 [2] 
                                72 to 78 -> 102 [0] 
                                78 to 98 -> 130 [0] lasti
                                98 to 100 -> 102 [0] 
                                102 to 124 -> 124 [1] lasti
                                124 to 130 -> 130 [0] lasti
                        [Code]
                            File Name: <frozen multithon.events.userupdate>
                            Object Name: input_user
                            Qualified Name: UserUpdate.Event.input_user
                            Arg Count: 1
                            Pos Only Arg Count: 0
                            KW Only Arg Count: 0
                            Stack Size: 5
                            Flags: 0x20000003 (CO_OPTIMIZED | CO_NEWLOCALS | CO_PYARMOR_OBFUSCATED)
                            [Names]
                                'input_sender'
                            [Locals+Names]
                                'self'
                                '__assert_armored__'
                            [Constants]
                                'Alias for `input_sender <telethon.tl.custom.sendergetter.SenderGetter.input_sender>`.'
                                '__pyarmor_assert_22830__'
                                '__pyarmor_enter_22831__'
                                b'<COAddr>\x07\x00\x00\x1a,\x00\x00\x00\x00\x00\x00\x00\x00\x00\x00\x00\x00\x00\x00\x00'
                                '__pyarmor_exit_22832__'
                            [Disassembly]
                                0       NOP                             
                                2       NOP                             
                                4       PUSH_NULL                       
                                6       LOAD_CONST                      2: '__pyarmor_enter_22831__'
                                8       LOAD_CONST                      3: b'<COAddr>\x07\x00\x00\x1a,\x00\x00\x00\x00\x00\x00\x00\x00\x00\x00\x00\x00\x00\x00\x00'
                                10      BUILD_TUPLE                     1
                                12      CALL_FUNCTION_EX                0
                                14      POP_TOP                         
                                16      RESUME                          0
                                18      NOP                             
                                20      NOP                             
                                22      NOP                             
                                24      NOP                             
                                26      NOP                             
                                28      LOAD_FAST                       0: self
                                30      LOAD_ATTR                       0: input_sender
                                50      NOP                             
                                52      NOP                             
                                54      NOP                             
                                56      JUMP_FORWARD                    20 (to 98)
                                58      CALL                            1
                                66      POP_TOP                         
                                68      RETURN_VALUE                    
                                70      PUSH_EXC_INFO                   
                                72      PUSH_NULL                       
                                74      LOAD_CONST                      4: '__pyarmor_exit_22832__'
                                76      NOP                             
                                78      LOAD_CONST                      3: b'<COAddr>\x07\x00\x00\x1a,\x00\x00\x00\x00\x00\x00\x00\x00\x00\x00\x00\x00\x00\x00\x00'
                                80      CALL                            1
                                88      POP_TOP                         
                                90      RERAISE                         0
                                92      COPY                            3
                                94      POP_EXCEPT                      
                                96      RERAISE                         1
                                98      PUSH_NULL                       
                                100     LOAD_CONST                      4: '__pyarmor_exit_22832__'
                                102     LOAD_CONST                      3: b'<COAddr>\x07\x00\x00\x1a,\x00\x00\x00\x00\x00\x00\x00\x00\x00\x00\x00\x00\x00\x00\x00'
                                104     BUILD_TUPLE                     1
                                106     CALL_FUNCTION_EX                0
                                108     POP_TOP                         
                                110     RETURN_VALUE                    
                            [Exception Table]
                                28 to 50 -> 70 [0] 
                                70 to 92 -> 92 [1] lasti
                        [Code]
                            File Name: <frozen multithon.events.userupdate>
                            Object Name: get_input_user
                            Qualified Name: UserUpdate.Event.get_input_user
                            Arg Count: 1
                            Pos Only Arg Count: 0
                            KW Only Arg Count: 0
                            Stack Size: 5
                            Flags: 0x20000083 (CO_OPTIMIZED | CO_NEWLOCALS | CO_COROUTINE | CO_PYARMOR_OBFUSCATED)
                            [Names]
                                'get_input_sender'
                            [Locals+Names]
                                'self'
                                '__assert_armored__'
                            [Constants]
                                'Alias for `get_input_sender <telethon.tl.custom.sendergetter.SenderGetter.get_input_sender>`.'
                                '__pyarmor_assert_22833__'
                                '__pyarmor_enter_22834__'
                                b'<COAddr>\x05\x00\x00\x1eH\x00\x00\x00\x00\x00\x00\x00\x00\x00\x00\x00\x00\x00\x00\x00'
                                None
                                '__pyarmor_exit_22835__'
                            [Disassembly]
                                0       RETURN_GENERATOR                
                                2       POP_TOP                         
                                4       NOP                             
                                6       NOP                             
                                8       PUSH_NULL                       
                                10      LOAD_CONST                      2: '__pyarmor_enter_22834__'
                                12      LOAD_CONST                      3: b'<COAddr>\x05\x00\x00\x1eH\x00\x00\x00\x00\x00\x00\x00\x00\x00\x00\x00\x00\x00\x00\x00'
                                14      BUILD_TUPLE                     1
                                16      CALL_FUNCTION_EX                0
                                18      POP_TOP                         
                                20      RESUME                          0
                                22      NOP                             
                                24      NOP                             
                                26      NOP                             
                                28      NOP                             
                                30      NOP                             
                                32      LOAD_FAST                       0: self
                                34      LOAD_ATTR                       1: get_input_sender
                                54      CALL                            0
                                62      GET_AWAITABLE                   0
                                64      LOAD_CONST                      4: None
                                66      SEND                            3 (to 74)
                                70      YIELD_VALUE                     3
                                72      RESUME                          3
                                74      JUMP_BACKWARD_NO_INTERRUPT      5 (to 66)
                                76      END_SEND                        
                                78      NOP                             
                                80      NOP                             
                                82      NOP                             
                                84      JUMP_FORWARD                    24 (to 134)
                                86      CALL                            1
                                94      POP_TOP                         
                                96      RETURN_VALUE                    
                                98      CLEANUP_THROW                   
                                100     JUMP_BACKWARD                   13 (to 76)
                                102     PUSH_EXC_INFO                   
                                104     PUSH_NULL                       
                                106     LOAD_CONST                      5: '__pyarmor_exit_22835__'
                                108     NOP                             
                                110     LOAD_CONST                      3: b'<COAddr>\x05\x00\x00\x1eH\x00\x00\x00\x00\x00\x00\x00\x00\x00\x00\x00\x00\x00\x00\x00'
                                112     CALL                            1
                                120     POP_TOP                         
                                122     RERAISE                         0
                                124     COPY                            3
                                126     POP_EXCEPT                      
                                128     RERAISE                         1
                                130     CALL_INTRINSIC_1                3 (INTRINSIC_STOPITERATION_ERROR)
                                132     RERAISE                         1
                                134     PUSH_NULL                       
                                136     LOAD_CONST                      5: '__pyarmor_exit_22835__'
                                138     LOAD_CONST                      3: b'<COAddr>\x05\x00\x00\x1eH\x00\x00\x00\x00\x00\x00\x00\x00\x00\x00\x00\x00\x00\x00\x00'
                                140     BUILD_TUPLE                     1
                                142     CALL_FUNCTION_EX                0
                                144     POP_TOP                         
                                146     RETURN_VALUE                    
                            [Exception Table]
                                4 to 30 -> 130 [0] lasti
                                32 to 70 -> 102 [0] 
                                70 to 72 -> 98 [2] 
                                72 to 78 -> 102 [0] 
                                78 to 98 -> 130 [0] lasti
                                98 to 100 -> 102 [0] 
                                102 to 124 -> 124 [1] lasti
                                124 to 130 -> 130 [0] lasti
                        [Code]
                            File Name: <frozen multithon.events.userupdate>
                            Object Name: user_id
                            Qualified Name: UserUpdate.Event.user_id
                            Arg Count: 1
                            Pos Only Arg Count: 0
                            KW Only Arg Count: 0
                            Stack Size: 5
                            Flags: 0x20000003 (CO_OPTIMIZED | CO_NEWLOCALS | CO_PYARMOR_OBFUSCATED)
                            [Names]
                                'sender_id'
                            [Locals+Names]
                                'self'
                                '__assert_armored__'
                            [Constants]
                                'Alias for `sender_id <telethon.tl.custom.sendergetter.SenderGetter.sender_id>`.'
                                '__pyarmor_assert_22836__'
                                '__pyarmor_enter_22837__'
                                b'<COAddr>\x05\x00\x00\x1a,\x00\x00\x00\x00\x00\x00\x00\x00\x00\x00\x00\x00\x00\x00\x00'
                                '__pyarmor_exit_22838__'
                            [Disassembly]
                                0       NOP                             
                                2       NOP                             
                                4       PUSH_NULL                       
                                6       LOAD_CONST                      2: '__pyarmor_enter_22837__'
                                8       LOAD_CONST                      3: b'<COAddr>\x05\x00\x00\x1a,\x00\x00\x00\x00\x00\x00\x00\x00\x00\x00\x00\x00\x00\x00\x00'
                                10      BUILD_TUPLE                     1
                                12      CALL_FUNCTION_EX                0
                                14      POP_TOP                         
                                16      RESUME                          0
                                18      NOP                             
                                20      NOP                             
                                22      NOP                             
                                24      NOP                             
                                26      NOP                             
                                28      LOAD_FAST                       0: self
                                30      LOAD_ATTR                       0: sender_id
                                50      NOP                             
                                52      NOP                             
                                54      NOP                             
                                56      JUMP_FORWARD                    20 (to 98)
                                58      CALL                            1
                                66      POP_TOP                         
                                68      RETURN_VALUE                    
                                70      PUSH_EXC_INFO                   
                                72      PUSH_NULL                       
                                74      LOAD_CONST                      4: '__pyarmor_exit_22838__'
                                76      NOP                             
                                78      LOAD_CONST                      3: b'<COAddr>\x05\x00\x00\x1a,\x00\x00\x00\x00\x00\x00\x00\x00\x00\x00\x00\x00\x00\x00\x00'
                                80      CALL                            1
                                88      POP_TOP                         
                                90      RERAISE                         0
                                92      COPY                            3
                                94      POP_EXCEPT                      
                                96      RERAISE                         1
                                98      PUSH_NULL                       
                                100     LOAD_CONST                      4: '__pyarmor_exit_22838__'
                                102     LOAD_CONST                      3: b'<COAddr>\x05\x00\x00\x1a,\x00\x00\x00\x00\x00\x00\x00\x00\x00\x00\x00\x00\x00\x00\x00'
                                104     BUILD_TUPLE                     1
                                106     CALL_FUNCTION_EX                0
                                108     POP_TOP                         
                                110     RETURN_VALUE                    
                            [Exception Table]
                                28 to 50 -> 70 [0] 
                                70 to 92 -> 92 [1] lasti
                        [Code]
                            File Name: <frozen multithon.events.userupdate>
                            Object Name: typing
                            Qualified Name: UserUpdate.Event.typing
                            Arg Count: 1
                            Pos Only Arg Count: 0
                            KW Only Arg Count: 0
                            Stack Size: 5
                            Flags: 0x20000003 (CO_OPTIMIZED | CO_NEWLOCALS | CO_PYARMOR_OBFUSCATED)
                            [Names]
                                'isinstance'
                                'action'
                                'types'
                                'SendMessageTypingAction'
                            [Locals+Names]
                                'self'
                                '__assert_armored__'
                            [Constants]
                                '\n            `True` if the action is typing a message.\n            '
                                '__pyarmor_assert_22839__'
                                '__pyarmor_enter_22840__'
                                b'<COAddr>\x05\x00\x00\x1a\\\x00\x00\x00\x00\x00\x00\x00\x00\x00\x00\x00\x00\x00\x00\x00'
                                '__pyarmor_exit_22841__'
                            [Disassembly]
                                0       NOP                             
                                2       NOP                             
                                4       PUSH_NULL                       
                                6       LOAD_CONST                      2: '__pyarmor_enter_22840__'
                                8       LOAD_CONST                      3: b'<COAddr>\x05\x00\x00\x1a\\\x00\x00\x00\x00\x00\x00\x00\x00\x00\x00\x00\x00\x00\x00\x00'
                                10      BUILD_TUPLE                     1
                                12      CALL_FUNCTION_EX                0
                                14      POP_TOP                         
                                16      RESUME                          0
                                18      NOP                             
                                20      NOP                             
                                22      NOP                             
                                24      NOP                             
                                26      NOP                             
                                28      LOAD_GLOBAL                     1: NULL + isinstance
                                38      LOAD_FAST                       0: self
                                40      LOAD_ATTR                       2: action
                                60      LOAD_GLOBAL                     4: types
                                70      LOAD_ATTR                       6: SendMessageTypingAction
                                90      CALL                            2
                                98      NOP                             
                                100     NOP                             
                                102     NOP                             
                                104     JUMP_FORWARD                    20 (to 146)
                                106     CALL                            1
                                114     POP_TOP                         
                                116     RETURN_VALUE                    
                                118     PUSH_EXC_INFO                   
                                120     PUSH_NULL                       
                                122     LOAD_CONST                      4: '__pyarmor_exit_22841__'
                                124     NOP                             
                                126     LOAD_CONST                      3: b'<COAddr>\x05\x00\x00\x1a\\\x00\x00\x00\x00\x00\x00\x00\x00\x00\x00\x00\x00\x00\x00\x00'
                                128     CALL                            1
                                136     POP_TOP                         
                                138     RERAISE                         0
                                140     COPY                            3
                                142     POP_EXCEPT                      
                                144     RERAISE                         1
                                146     PUSH_NULL                       
                                148     LOAD_CONST                      4: '__pyarmor_exit_22841__'
                                150     LOAD_CONST                      3: b'<COAddr>\x05\x00\x00\x1a\\\x00\x00\x00\x00\x00\x00\x00\x00\x00\x00\x00\x00\x00\x00\x00'
                                152     BUILD_TUPLE                     1
                                154     CALL_FUNCTION_EX                0
                                156     POP_TOP                         
                                158     RETURN_VALUE                    
                            [Exception Table]
                                28 to 98 -> 118 [0] 
                                118 to 140 -> 140 [1] lasti
                        [Code]
                            File Name: <frozen multithon.events.userupdate>
                            Object Name: uploading
                            Qualified Name: UserUpdate.Event.uploading
                            Arg Count: 1
                            Pos Only Arg Count: 0
                            KW Only Arg Count: 0
                            Stack Size: 10
                            Flags: 0x20000003 (CO_OPTIMIZED | CO_NEWLOCALS | CO_PYARMOR_OBFUSCATED)
                            [Names]
                                'isinstance'
                                'action'
                                'types'
                                'SendMessageChooseContactAction'
                                'SendMessageChooseStickerAction'
                                'SendMessageUploadAudioAction'
                                'SendMessageUploadDocumentAction'
                                'SendMessageUploadPhotoAction'
                                'SendMessageUploadRoundAction'
                                'SendMessageUploadVideoAction'
                            [Locals+Names]
                                'self'
                                '__assert_armored__'
                            [Constants]
                                '\n            `True` if the action is uploading something.\n            '
                                '__pyarmor_assert_22842__'
                                '__pyarmor_enter_22843__'
                                b'<COAddr>\x05\x00\x00\x1a\x12\x01\x00\x00\x00\x00\x00\x00\x00\x00\x00\x00\x00\x00\x00\x00'
                                '__pyarmor_exit_22844__'
                            [Disassembly]
                                0       NOP                             
                                2       NOP                             
                                4       PUSH_NULL                       
                                6       LOAD_CONST                      2: '__pyarmor_enter_22843__'
                                8       LOAD_CONST                      3: b'<COAddr>\x05\x00\x00\x1a\x12\x01\x00\x00\x00\x00\x00\x00\x00\x00\x00\x00\x00\x00\x00\x00'
                                10      BUILD_TUPLE                     1
                                12      CALL_FUNCTION_EX                0
                                14      POP_TOP                         
                                16      RESUME                          0
                                18      NOP                             
                                20      NOP                             
                                22      NOP                             
                                24      NOP                             
                                26      NOP                             
                                28      LOAD_GLOBAL                     1: NULL + isinstance
                                38      LOAD_FAST                       0: self
                                40      LOAD_ATTR                       2: action
                                60      LOAD_GLOBAL                     4: types
                                70      LOAD_ATTR                       6: SendMessageChooseContactAction
                                90      LOAD_GLOBAL                     4: types
                                100     LOAD_ATTR                       8: SendMessageChooseStickerAction
                                120     LOAD_GLOBAL                     4: types
                                130     LOAD_ATTR                       10: SendMessageUploadAudioAction
                                150     LOAD_GLOBAL                     4: types
                                160     LOAD_ATTR                       12: SendMessageUploadDocumentAction
                                180     LOAD_GLOBAL                     4: types
                                190     LOAD_ATTR                       14: SendMessageUploadPhotoAction
                                210     LOAD_GLOBAL                     4: types
                                220     LOAD_ATTR                       16: SendMessageUploadRoundAction
                                240     LOAD_GLOBAL                     4: types
                                250     LOAD_ATTR                       18: SendMessageUploadVideoAction
                                270     BUILD_TUPLE                     7
                                272     CALL                            2
                                280     NOP                             
                                282     NOP                             
                                284     NOP                             
                                286     JUMP_FORWARD                    20 (to 328)
                                288     CALL                            1
                                296     POP_TOP                         
                                298     RETURN_VALUE                    
                                300     PUSH_EXC_INFO                   
                                302     PUSH_NULL                       
                                304     LOAD_CONST                      4: '__pyarmor_exit_22844__'
                                306     NOP                             
                                308     LOAD_CONST                      3: b'<COAddr>\x05\x00\x00\x1a\x12\x01\x00\x00\x00\x00\x00\x00\x00\x00\x00\x00\x00\x00\x00\x00'
                                310     CALL                            1
                                318     POP_TOP                         
                                320     RERAISE                         0
                                322     COPY                            3
                                324     POP_EXCEPT                      
                                326     RERAISE                         1
                                328     PUSH_NULL                       
                                330     LOAD_CONST                      4: '__pyarmor_exit_22844__'
                                332     LOAD_CONST                      3: b'<COAddr>\x05\x00\x00\x1a\x12\x01\x00\x00\x00\x00\x00\x00\x00\x00\x00\x00\x00\x00\x00\x00'
                                334     BUILD_TUPLE                     1
                                336     CALL_FUNCTION_EX                0
                                338     POP_TOP                         
                                340     RETURN_VALUE                    
                            [Exception Table]
                                28 to 280 -> 300 [0] 
                                300 to 322 -> 322 [1] lasti
                        [Code]
                            File Name: <frozen multithon.events.userupdate>
                            Object Name: recording
                            Qualified Name: UserUpdate.Event.recording
                            Arg Count: 1
                            Pos Only Arg Count: 0
                            KW Only Arg Count: 0
                            Stack Size: 6
                            Flags: 0x20000003 (CO_OPTIMIZED | CO_NEWLOCALS | CO_PYARMOR_OBFUSCATED)
                            [Names]
                                'isinstance'
                                'action'
                                'types'
                                'SendMessageRecordAudioAction'
                                'SendMessageRecordRoundAction'
                                'SendMessageRecordVideoAction'
                            [Locals+Names]
                                'self'
                                '__assert_armored__'
                            [Constants]
                                '\n            `True` if the action is recording something.\n            '
                                '__pyarmor_assert_22845__'
                                '__pyarmor_enter_22846__'
                                b'<COAddr>\x07\x00\x00\x1a\x9a\x00\x00\x00\x00\x00\x00\x00\x00\x00\x00\x00\x00\x00\x00\x00'
                                '__pyarmor_exit_22847__'
                            [Disassembly]
                                0       NOP                             
                                2       NOP                             
                                4       PUSH_NULL                       
                                6       LOAD_CONST                      2: '__pyarmor_enter_22846__'
                                8       LOAD_CONST                      3: b'<COAddr>\x07\x00\x00\x1a\x9a\x00\x00\x00\x00\x00\x00\x00\x00\x00\x00\x00\x00\x00\x00\x00'
                                10      BUILD_TUPLE                     1
                                12      CALL_FUNCTION_EX                0
                                14      POP_TOP                         
                                16      RESUME                          0
                                18      NOP                             
                                20      NOP                             
                                22      NOP                             
                                24      NOP                             
                                26      NOP                             
                                28      LOAD_GLOBAL                     1: NULL + isinstance
                                38      LOAD_FAST                       0: self
                                40      LOAD_ATTR                       2: action
                                60      LOAD_GLOBAL                     4: types
                                70      LOAD_ATTR                       6: SendMessageRecordAudioAction
                                90      LOAD_GLOBAL                     4: types
                                100     LOAD_ATTR                       8: SendMessageRecordRoundAction
                                120     LOAD_GLOBAL                     4: types
                                130     LOAD_ATTR                       10: SendMessageRecordVideoAction
                                150     BUILD_TUPLE                     3
                                152     CALL                            2
                                160     NOP                             
                                162     NOP                             
                                164     NOP                             
                                166     JUMP_FORWARD                    20 (to 208)
                                168     CALL                            1
                                176     POP_TOP                         
                                178     RETURN_VALUE                    
                                180     PUSH_EXC_INFO                   
                                182     PUSH_NULL                       
                                184     LOAD_CONST                      4: '__pyarmor_exit_22847__'
                                186     NOP                             
                                188     LOAD_CONST                      3: b'<COAddr>\x07\x00\x00\x1a\x9a\x00\x00\x00\x00\x00\x00\x00\x00\x00\x00\x00\x00\x00\x00\x00'
                                190     CALL                            1
                                198     POP_TOP                         
                                200     RERAISE                         0
                                202     COPY                            3
                                204     POP_EXCEPT                      
                                206     RERAISE                         1
                                208     PUSH_NULL                       
                                210     LOAD_CONST                      4: '__pyarmor_exit_22847__'
                                212     LOAD_CONST                      3: b'<COAddr>\x07\x00\x00\x1a\x9a\x00\x00\x00\x00\x00\x00\x00\x00\x00\x00\x00\x00\x00\x00\x00'
                                214     BUILD_TUPLE                     1
                                216     CALL_FUNCTION_EX                0
                                218     POP_TOP                         
                                220     RETURN_VALUE                    
                            [Exception Table]
                                28 to 160 -> 180 [0] 
                                180 to 202 -> 202 [1] lasti
                        [Code]
                            File Name: <frozen multithon.events.userupdate>
                            Object Name: playing
                            Qualified Name: UserUpdate.Event.playing
                            Arg Count: 1
                            Pos Only Arg Count: 0
                            KW Only Arg Count: 0
                            Stack Size: 5
                            Flags: 0x20000003 (CO_OPTIMIZED | CO_NEWLOCALS | CO_PYARMOR_OBFUSCATED)
                            [Names]
                                'isinstance'
                                'action'
                                'types'
                                'SendMessageGamePlayAction'
                            [Locals+Names]
                                'self'
                                '__assert_armored__'
                            [Constants]
                                '\n            `True` if the action is playing a game.\n            '
                                '__pyarmor_assert_22848__'
                                '__pyarmor_enter_22849__'
                                b'<COAddr>\x07\x00\x00\x1a\\\x00\x00\x00\x00\x00\x00\x00\x00\x00\x00\x00\x00\x00\x00\x00'
                                '__pyarmor_exit_22850__'
                            [Disassembly]
                                0       NOP                             
                                2       NOP                             
                                4       PUSH_NULL                       
                                6       LOAD_CONST                      2: '__pyarmor_enter_22849__'
                                8       LOAD_CONST                      3: b'<COAddr>\x07\x00\x00\x1a\\\x00\x00\x00\x00\x00\x00\x00\x00\x00\x00\x00\x00\x00\x00\x00'
                                10      BUILD_TUPLE                     1
                                12      CALL_FUNCTION_EX                0
                                14      POP_TOP                         
                                16      RESUME                          0
                                18      NOP                             
                                20      NOP                             
                                22      NOP                             
                                24      NOP                             
                                26      NOP                             
                                28      LOAD_GLOBAL                     1: NULL + isinstance
                                38      LOAD_FAST                       0: self
                                40      LOAD_ATTR                       2: action
                                60      LOAD_GLOBAL                     4: types
                                70      LOAD_ATTR                       6: SendMessageGamePlayAction
                                90      CALL                            2
                                98      NOP                             
                                100     NOP                             
                                102     NOP                             
                                104     JUMP_FORWARD                    20 (to 146)
                                106     CALL                            1
                                114     POP_TOP                         
                                116     RETURN_VALUE                    
                                118     PUSH_EXC_INFO                   
                                120     PUSH_NULL                       
                                122     LOAD_CONST                      4: '__pyarmor_exit_22850__'
                                124     NOP                             
                                126     LOAD_CONST                      3: b'<COAddr>\x07\x00\x00\x1a\\\x00\x00\x00\x00\x00\x00\x00\x00\x00\x00\x00\x00\x00\x00\x00'
                                128     CALL                            1
                                136     POP_TOP                         
                                138     RERAISE                         0
                                140     COPY                            3
                                142     POP_EXCEPT                      
                                144     RERAISE                         1
                                146     PUSH_NULL                       
                                148     LOAD_CONST                      4: '__pyarmor_exit_22850__'
                                150     LOAD_CONST                      3: b'<COAddr>\x07\x00\x00\x1a\\\x00\x00\x00\x00\x00\x00\x00\x00\x00\x00\x00\x00\x00\x00\x00'
                                152     BUILD_TUPLE                     1
                                154     CALL_FUNCTION_EX                0
                                156     POP_TOP                         
                                158     RETURN_VALUE                    
                            [Exception Table]
                                28 to 98 -> 118 [0] 
                                118 to 140 -> 140 [1] lasti
                        [Code]
                            File Name: <frozen multithon.events.userupdate>
                            Object Name: cancel
                            Qualified Name: UserUpdate.Event.cancel
                            Arg Count: 1
                            Pos Only Arg Count: 0
                            KW Only Arg Count: 0
                            Stack Size: 5
                            Flags: 0x20000003 (CO_OPTIMIZED | CO_NEWLOCALS | CO_PYARMOR_OBFUSCATED)
                            [Names]
                                'isinstance'
                                'action'
                                'types'
                                'SendMessageCancelAction'
                            [Locals+Names]
                                'self'
                                '__assert_armored__'
                            [Constants]
                                '\n            `True` if the action was cancelling other actions.\n            '
                                '__pyarmor_assert_22851__'
                                '__pyarmor_enter_22852__'
                                b'<COAddr>\x05\x00\x00\x1a\\\x00\x00\x00\x00\x00\x00\x00\x00\x00\x00\x00\x00\x00\x00\x00'
                                '__pyarmor_exit_22853__'
                            [Disassembly]
                                0       NOP                             
                                2       NOP                             
                                4       PUSH_NULL                       
                                6       LOAD_CONST                      2: '__pyarmor_enter_22852__'
                                8       LOAD_CONST                      3: b'<COAddr>\x05\x00\x00\x1a\\\x00\x00\x00\x00\x00\x00\x00\x00\x00\x00\x00\x00\x00\x00\x00'
                                10      BUILD_TUPLE                     1
                                12      CALL_FUNCTION_EX                0
                                14      POP_TOP                         
                                16      RESUME                          0
                                18      NOP                             
                                20      NOP                             
                                22      NOP                             
                                24      NOP                             
                                26      NOP                             
                                28      LOAD_GLOBAL                     1: NULL + isinstance
                                38      LOAD_FAST                       0: self
                                40      LOAD_ATTR                       2: action
                                60      LOAD_GLOBAL                     4: types
                                70      LOAD_ATTR                       6: SendMessageCancelAction
                                90      CALL                            2
                                98      NOP                             
                                100     NOP                             
                                102     NOP                             
                                104     JUMP_FORWARD                    20 (to 146)
                                106     CALL                            1
                                114     POP_TOP                         
                                116     RETURN_VALUE                    
                                118     PUSH_EXC_INFO                   
                                120     PUSH_NULL                       
                                122     LOAD_CONST                      4: '__pyarmor_exit_22853__'
                                124     NOP                             
                                126     LOAD_CONST                      3: b'<COAddr>\x05\x00\x00\x1a\\\x00\x00\x00\x00\x00\x00\x00\x00\x00\x00\x00\x00\x00\x00\x00'
                                128     CALL                            1
                                136     POP_TOP                         
                                138     RERAISE                         0
                                140     COPY                            3
                                142     POP_EXCEPT                      
                                144     RERAISE                         1
                                146     PUSH_NULL                       
                                148     LOAD_CONST                      4: '__pyarmor_exit_22853__'
                                150     LOAD_CONST                      3: b'<COAddr>\x05\x00\x00\x1a\\\x00\x00\x00\x00\x00\x00\x00\x00\x00\x00\x00\x00\x00\x00\x00'
                                152     BUILD_TUPLE                     1
                                154     CALL_FUNCTION_EX                0
                                156     POP_TOP                         
                                158     RETURN_VALUE                    
                            [Exception Table]
                                28 to 98 -> 118 [0] 
                                118 to 140 -> 140 [1] lasti
                        [Code]
                            File Name: <frozen multithon.events.userupdate>
                            Object Name: geo
                            Qualified Name: UserUpdate.Event.geo
                            Arg Count: 1
                            Pos Only Arg Count: 0
                            KW Only Arg Count: 0
                            Stack Size: 5
                            Flags: 0x20000003 (CO_OPTIMIZED | CO_NEWLOCALS | CO_PYARMOR_OBFUSCATED)
                            [Names]
                                'isinstance'
                                'action'
                                'types'
                                'SendMessageGeoLocationAction'
                            [Locals+Names]
                                'self'
                                '__assert_armored__'
                            [Constants]
                                "\n            `True` if what's being uploaded is a geo.\n            "
                                '__pyarmor_assert_22854__'
                                '__pyarmor_enter_22855__'
                                b'<COAddr>\x07\x00\x00\x1a\\\x00\x00\x00\x00\x00\x00\x00\x00\x00\x00\x00\x00\x00\x00\x00'
                                '__pyarmor_exit_22856__'
                            [Disassembly]
                                0       NOP                             
                                2       NOP                             
                                4       PUSH_NULL                       
                                6       LOAD_CONST                      2: '__pyarmor_enter_22855__'
                                8       LOAD_CONST                      3: b'<COAddr>\x07\x00\x00\x1a\\\x00\x00\x00\x00\x00\x00\x00\x00\x00\x00\x00\x00\x00\x00\x00'
                                10      BUILD_TUPLE                     1
                                12      CALL_FUNCTION_EX                0
                                14      POP_TOP                         
                                16      RESUME                          0
                                18      NOP                             
                                20      NOP                             
                                22      NOP                             
                                24      NOP                             
                                26      NOP                             
                                28      LOAD_GLOBAL                     1: NULL + isinstance
                                38      LOAD_FAST                       0: self
                                40      LOAD_ATTR                       2: action
                                60      LOAD_GLOBAL                     4: types
                                70      LOAD_ATTR                       6: SendMessageGeoLocationAction
                                90      CALL                            2
                                98      NOP                             
                                100     NOP                             
                                102     NOP                             
                                104     JUMP_FORWARD                    20 (to 146)
                                106     CALL                            1
                                114     POP_TOP                         
                                116     RETURN_VALUE                    
                                118     PUSH_EXC_INFO                   
                                120     PUSH_NULL                       
                                122     LOAD_CONST                      4: '__pyarmor_exit_22856__'
                                124     NOP                             
                                126     LOAD_CONST                      3: b'<COAddr>\x07\x00\x00\x1a\\\x00\x00\x00\x00\x00\x00\x00\x00\x00\x00\x00\x00\x00\x00\x00'
                                128     CALL                            1
                                136     POP_TOP                         
                                138     RERAISE                         0
                                140     COPY                            3
                                142     POP_EXCEPT                      
                                144     RERAISE                         1
                                146     PUSH_NULL                       
                                148     LOAD_CONST                      4: '__pyarmor_exit_22856__'
                                150     LOAD_CONST                      3: b'<COAddr>\x07\x00\x00\x1a\\\x00\x00\x00\x00\x00\x00\x00\x00\x00\x00\x00\x00\x00\x00\x00'
                                152     BUILD_TUPLE                     1
                                154     CALL_FUNCTION_EX                0
                                156     POP_TOP                         
                                158     RETURN_VALUE                    
                            [Exception Table]
                                28 to 98 -> 118 [0] 
                                118 to 140 -> 140 [1] lasti
                        [Code]
                            File Name: <frozen multithon.events.userupdate>
                            Object Name: audio
                            Qualified Name: UserUpdate.Event.audio
                            Arg Count: 1
                            Pos Only Arg Count: 0
                            KW Only Arg Count: 0
                            Stack Size: 5
                            Flags: 0x20000003 (CO_OPTIMIZED | CO_NEWLOCALS | CO_PYARMOR_OBFUSCATED)
                            [Names]
                                'isinstance'
                                'action'
                                'types'
                                'SendMessageRecordAudioAction'
                                'SendMessageUploadAudioAction'
                            [Locals+Names]
                                'self'
                                '__assert_armored__'
                            [Constants]
                                "\n            `True` if what's being recorded/uploaded is an audio.\n            "
                                '__pyarmor_assert_22857__'
                                '__pyarmor_enter_22858__'
                                b'<COAddr>\x07\x00\x00\x1a|\x00\x00\x00\x00\x00\x00\x00\x00\x00\x00\x00\x00\x00\x00\x00'
                                '__pyarmor_exit_22859__'
                            [Disassembly]
                                0       NOP                             
                                2       NOP                             
                                4       PUSH_NULL                       
                                6       LOAD_CONST                      2: '__pyarmor_enter_22858__'
                                8       LOAD_CONST                      3: b'<COAddr>\x07\x00\x00\x1a|\x00\x00\x00\x00\x00\x00\x00\x00\x00\x00\x00\x00\x00\x00\x00'
                                10      BUILD_TUPLE                     1
                                12      CALL_FUNCTION_EX                0
                                14      POP_TOP                         
                                16      RESUME                          0
                                18      NOP                             
                                20      NOP                             
                                22      NOP                             
                                24      NOP                             
                                26      NOP                             
                                28      LOAD_GLOBAL                     1: NULL + isinstance
                                38      LOAD_FAST                       0: self
                                40      LOAD_ATTR                       2: action
                                60      LOAD_GLOBAL                     4: types
                                70      LOAD_ATTR                       6: SendMessageRecordAudioAction
                                90      LOAD_GLOBAL                     4: types
                                100     LOAD_ATTR                       8: SendMessageUploadAudioAction
                                120     BUILD_TUPLE                     2
                                122     CALL                            2
                                130     NOP                             
                                132     NOP                             
                                134     NOP                             
                                136     JUMP_FORWARD                    20 (to 178)
                                138     CALL                            1
                                146     POP_TOP                         
                                148     RETURN_VALUE                    
                                150     PUSH_EXC_INFO                   
                                152     PUSH_NULL                       
                                154     LOAD_CONST                      4: '__pyarmor_exit_22859__'
                                156     NOP                             
                                158     LOAD_CONST                      3: b'<COAddr>\x07\x00\x00\x1a|\x00\x00\x00\x00\x00\x00\x00\x00\x00\x00\x00\x00\x00\x00\x00'
                                160     CALL                            1
                                168     POP_TOP                         
                                170     RERAISE                         0
                                172     COPY                            3
                                174     POP_EXCEPT                      
                                176     RERAISE                         1
                                178     PUSH_NULL                       
                                180     LOAD_CONST                      4: '__pyarmor_exit_22859__'
                                182     LOAD_CONST                      3: b'<COAddr>\x07\x00\x00\x1a|\x00\x00\x00\x00\x00\x00\x00\x00\x00\x00\x00\x00\x00\x00\x00'
                                184     BUILD_TUPLE                     1
                                186     CALL_FUNCTION_EX                0
                                188     POP_TOP                         
                                190     RETURN_VALUE                    
                            [Exception Table]
                                28 to 130 -> 150 [0] 
                                150 to 172 -> 172 [1] lasti
                        [Code]
                            File Name: <frozen multithon.events.userupdate>
                            Object Name: round
                            Qualified Name: UserUpdate.Event.round
                            Arg Count: 1
                            Pos Only Arg Count: 0
                            KW Only Arg Count: 0
                            Stack Size: 5
                            Flags: 0x20000003 (CO_OPTIMIZED | CO_NEWLOCALS | CO_PYARMOR_OBFUSCATED)
                            [Names]
                                'isinstance'
                                'action'
                                'types'
                                'SendMessageRecordRoundAction'
                                'SendMessageUploadRoundAction'
                            [Locals+Names]
                                'self'
                                '__assert_armored__'
                            [Constants]
                                "\n            `True` if what's being recorded/uploaded is a round video.\n            "
                                '__pyarmor_assert_22860__'
                                '__pyarmor_enter_22861__'
                                b'<COAddr>\x05\x00\x00\x1a|\x00\x00\x00\x00\x00\x00\x00\x00\x00\x00\x00\x00\x00\x00\x00'
                                '__pyarmor_exit_22862__'
                            [Disassembly]
                                0       NOP                             
                                2       NOP                             
                                4       PUSH_NULL                       
                                6       LOAD_CONST                      2: '__pyarmor_enter_22861__'
                                8       LOAD_CONST                      3: b'<COAddr>\x05\x00\x00\x1a|\x00\x00\x00\x00\x00\x00\x00\x00\x00\x00\x00\x00\x00\x00\x00'
                                10      BUILD_TUPLE                     1
                                12      CALL_FUNCTION_EX                0
                                14      POP_TOP                         
                                16      RESUME                          0
                                18      NOP                             
                                20      NOP                             
                                22      NOP                             
                                24      NOP                             
                                26      NOP                             
                                28      LOAD_GLOBAL                     1: NULL + isinstance
                                38      LOAD_FAST                       0: self
                                40      LOAD_ATTR                       2: action
                                60      LOAD_GLOBAL                     4: types
                                70      LOAD_ATTR                       6: SendMessageRecordRoundAction
                                90      LOAD_GLOBAL                     4: types
                                100     LOAD_ATTR                       8: SendMessageUploadRoundAction
                                120     BUILD_TUPLE                     2
                                122     CALL                            2
                                130     NOP                             
                                132     NOP                             
                                134     NOP                             
                                136     JUMP_FORWARD                    20 (to 178)
                                138     CALL                            1
                                146     POP_TOP                         
                                148     RETURN_VALUE                    
                                150     PUSH_EXC_INFO                   
                                152     PUSH_NULL                       
                                154     LOAD_CONST                      4: '__pyarmor_exit_22862__'
                                156     NOP                             
                                158     LOAD_CONST                      3: b'<COAddr>\x05\x00\x00\x1a|\x00\x00\x00\x00\x00\x00\x00\x00\x00\x00\x00\x00\x00\x00\x00'
                                160     CALL                            1
                                168     POP_TOP                         
                                170     RERAISE                         0
                                172     COPY                            3
                                174     POP_EXCEPT                      
                                176     RERAISE                         1
                                178     PUSH_NULL                       
                                180     LOAD_CONST                      4: '__pyarmor_exit_22862__'
                                182     LOAD_CONST                      3: b'<COAddr>\x05\x00\x00\x1a|\x00\x00\x00\x00\x00\x00\x00\x00\x00\x00\x00\x00\x00\x00\x00'
                                184     BUILD_TUPLE                     1
                                186     CALL_FUNCTION_EX                0
                                188     POP_TOP                         
                                190     RETURN_VALUE                    
                            [Exception Table]
                                28 to 130 -> 150 [0] 
                                150 to 172 -> 172 [1] lasti
                        [Code]
                            File Name: <frozen multithon.events.userupdate>
                            Object Name: video
                            Qualified Name: UserUpdate.Event.video
                            Arg Count: 1
                            Pos Only Arg Count: 0
                            KW Only Arg Count: 0
                            Stack Size: 5
                            Flags: 0x20000003 (CO_OPTIMIZED | CO_NEWLOCALS | CO_PYARMOR_OBFUSCATED)
                            [Names]
                                'isinstance'
                                'action'
                                'types'
                                'SendMessageRecordVideoAction'
                                'SendMessageUploadVideoAction'
                            [Locals+Names]
                                'self'
                                '__assert_armored__'
                            [Constants]
                                "\n            `True` if what's being recorded/uploaded is an video.\n            "
                                '__pyarmor_assert_22863__'
                                '__pyarmor_enter_22864__'
                                b'<COAddr>\x07\x00\x00\x1a|\x00\x00\x00\x00\x00\x00\x00\x00\x00\x00\x00\x00\x00\x00\x00'
                                '__pyarmor_exit_22865__'
                            [Disassembly]
                                0       NOP                             
                                2       NOP                             
                                4       PUSH_NULL                       
                                6       LOAD_CONST                      2: '__pyarmor_enter_22864__'
                                8       LOAD_CONST                      3: b'<COAddr>\x07\x00\x00\x1a|\x00\x00\x00\x00\x00\x00\x00\x00\x00\x00\x00\x00\x00\x00\x00'
                                10      BUILD_TUPLE                     1
                                12      CALL_FUNCTION_EX                0
                                14      POP_TOP                         
                                16      RESUME                          0
                                18      NOP                             
                                20      NOP                             
                                22      NOP                             
                                24      NOP                             
                                26      NOP                             
                                28      LOAD_GLOBAL                     1: NULL + isinstance
                                38      LOAD_FAST                       0: self
                                40      LOAD_ATTR                       2: action
                                60      LOAD_GLOBAL                     4: types
                                70      LOAD_ATTR                       6: SendMessageRecordVideoAction
                                90      LOAD_GLOBAL                     4: types
                                100     LOAD_ATTR                       8: SendMessageUploadVideoAction
                                120     BUILD_TUPLE                     2
                                122     CALL                            2
                                130     NOP                             
                                132     NOP                             
                                134     NOP                             
                                136     JUMP_FORWARD                    20 (to 178)
                                138     CALL                            1
                                146     POP_TOP                         
                                148     RETURN_VALUE                    
                                150     PUSH_EXC_INFO                   
                                152     PUSH_NULL                       
                                154     LOAD_CONST                      4: '__pyarmor_exit_22865__'
                                156     NOP                             
                                158     LOAD_CONST                      3: b'<COAddr>\x07\x00\x00\x1a|\x00\x00\x00\x00\x00\x00\x00\x00\x00\x00\x00\x00\x00\x00\x00'
                                160     CALL                            1
                                168     POP_TOP                         
                                170     RERAISE                         0
                                172     COPY                            3
                                174     POP_EXCEPT                      
                                176     RERAISE                         1
                                178     PUSH_NULL                       
                                180     LOAD_CONST                      4: '__pyarmor_exit_22865__'
                                182     LOAD_CONST                      3: b'<COAddr>\x07\x00\x00\x1a|\x00\x00\x00\x00\x00\x00\x00\x00\x00\x00\x00\x00\x00\x00\x00'
                                184     BUILD_TUPLE                     1
                                186     CALL_FUNCTION_EX                0
                                188     POP_TOP                         
                                190     RETURN_VALUE                    
                            [Exception Table]
                                28 to 130 -> 150 [0] 
                                150 to 172 -> 172 [1] lasti
                        [Code]
                            File Name: <frozen multithon.events.userupdate>
                            Object Name: contact
                            Qualified Name: UserUpdate.Event.contact
                            Arg Count: 1
                            Pos Only Arg Count: 0
                            KW Only Arg Count: 0
                            Stack Size: 5
                            Flags: 0x20000003 (CO_OPTIMIZED | CO_NEWLOCALS | CO_PYARMOR_OBFUSCATED)
                            [Names]
                                'isinstance'
                                'action'
                                'types'
                                'SendMessageChooseContactAction'
                            [Locals+Names]
                                'self'
                                '__assert_armored__'
                            [Constants]
                                "\n            `True` if what's being uploaded (selected) is a contact.\n            "
                                '__pyarmor_assert_22866__'
                                '__pyarmor_enter_22867__'
                                b'<COAddr>\x05\x00\x00\x1a\\\x00\x00\x00\x00\x00\x00\x00\x00\x00\x00\x00\x00\x00\x00\x00'
                                '__pyarmor_exit_22868__'
                            [Disassembly]
                                0       NOP                             
                                2       NOP                             
                                4       PUSH_NULL                       
                                6       LOAD_CONST                      2: '__pyarmor_enter_22867__'
                                8       LOAD_CONST                      3: b'<COAddr>\x05\x00\x00\x1a\\\x00\x00\x00\x00\x00\x00\x00\x00\x00\x00\x00\x00\x00\x00\x00'
                                10      BUILD_TUPLE                     1
                                12      CALL_FUNCTION_EX                0
                                14      POP_TOP                         
                                16      RESUME                          0
                                18      NOP                             
                                20      NOP                             
                                22      NOP                             
                                24      NOP                             
                                26      NOP                             
                                28      LOAD_GLOBAL                     1: NULL + isinstance
                                38      LOAD_FAST                       0: self
                                40      LOAD_ATTR                       2: action
                                60      LOAD_GLOBAL                     4: types
                                70      LOAD_ATTR                       6: SendMessageChooseContactAction
                                90      CALL                            2
                                98      NOP                             
                                100     NOP                             
                                102     NOP                             
                                104     JUMP_FORWARD                    20 (to 146)
                                106     CALL                            1
                                114     POP_TOP                         
                                116     RETURN_VALUE                    
                                118     PUSH_EXC_INFO                   
                                120     PUSH_NULL                       
                                122     LOAD_CONST                      4: '__pyarmor_exit_22868__'
                                124     NOP                             
                                126     LOAD_CONST                      3: b'<COAddr>\x05\x00\x00\x1a\\\x00\x00\x00\x00\x00\x00\x00\x00\x00\x00\x00\x00\x00\x00\x00'
                                128     CALL                            1
                                136     POP_TOP                         
                                138     RERAISE                         0
                                140     COPY                            3
                                142     POP_EXCEPT                      
                                144     RERAISE                         1
                                146     PUSH_NULL                       
                                148     LOAD_CONST                      4: '__pyarmor_exit_22868__'
                                150     LOAD_CONST                      3: b'<COAddr>\x05\x00\x00\x1a\\\x00\x00\x00\x00\x00\x00\x00\x00\x00\x00\x00\x00\x00\x00\x00'
                                152     BUILD_TUPLE                     1
                                154     CALL_FUNCTION_EX                0
                                156     POP_TOP                         
                                158     RETURN_VALUE                    
                            [Exception Table]
                                28 to 98 -> 118 [0] 
                                118 to 140 -> 140 [1] lasti
                        [Code]
                            File Name: <frozen multithon.events.userupdate>
                            Object Name: document
                            Qualified Name: UserUpdate.Event.document
                            Arg Count: 1
                            Pos Only Arg Count: 0
                            KW Only Arg Count: 0
                            Stack Size: 5
                            Flags: 0x20000003 (CO_OPTIMIZED | CO_NEWLOCALS | CO_PYARMOR_OBFUSCATED)
                            [Names]
                                'isinstance'
                                'action'
                                'types'
                                'SendMessageUploadDocumentAction'
                            [Locals+Names]
                                'self'
                                '__assert_armored__'
                            [Constants]
                                "\n            `True` if what's being uploaded is document.\n            "
                                '__pyarmor_assert_22869__'
                                '__pyarmor_enter_22870__'
                                b'<COAddr>\x07\x00\x00\x1a\\\x00\x00\x00\x00\x00\x00\x00\x00\x00\x00\x00\x00\x00\x00\x00'
                                '__pyarmor_exit_22871__'
                            [Disassembly]
                                0       NOP                             
                                2       NOP                             
                                4       PUSH_NULL                       
                                6       LOAD_CONST                      2: '__pyarmor_enter_22870__'
                                8       LOAD_CONST                      3: b'<COAddr>\x07\x00\x00\x1a\\\x00\x00\x00\x00\x00\x00\x00\x00\x00\x00\x00\x00\x00\x00\x00'
                                10      BUILD_TUPLE                     1
                                12      CALL_FUNCTION_EX                0
                                14      POP_TOP                         
                                16      RESUME                          0
                                18      NOP                             
                                20      NOP                             
                                22      NOP                             
                                24      NOP                             
                                26      NOP                             
                                28      LOAD_GLOBAL                     1: NULL + isinstance
                                38      LOAD_FAST                       0: self
                                40      LOAD_ATTR                       2: action
                                60      LOAD_GLOBAL                     4: types
                                70      LOAD_ATTR                       6: SendMessageUploadDocumentAction
                                90      CALL                            2
                                98      NOP                             
                                100     NOP                             
                                102     NOP                             
                                104     JUMP_FORWARD                    20 (to 146)
                                106     CALL                            1
                                114     POP_TOP                         
                                116     RETURN_VALUE                    
                                118     PUSH_EXC_INFO                   
                                120     PUSH_NULL                       
                                122     LOAD_CONST                      4: '__pyarmor_exit_22871__'
                                124     NOP                             
                                126     LOAD_CONST                      3: b'<COAddr>\x07\x00\x00\x1a\\\x00\x00\x00\x00\x00\x00\x00\x00\x00\x00\x00\x00\x00\x00\x00'
                                128     CALL                            1
                                136     POP_TOP                         
                                138     RERAISE                         0
                                140     COPY                            3
                                142     POP_EXCEPT                      
                                144     RERAISE                         1
                                146     PUSH_NULL                       
                                148     LOAD_CONST                      4: '__pyarmor_exit_22871__'
                                150     LOAD_CONST                      3: b'<COAddr>\x07\x00\x00\x1a\\\x00\x00\x00\x00\x00\x00\x00\x00\x00\x00\x00\x00\x00\x00\x00'
                                152     BUILD_TUPLE                     1
                                154     CALL_FUNCTION_EX                0
                                156     POP_TOP                         
                                158     RETURN_VALUE                    
                            [Exception Table]
                                28 to 98 -> 118 [0] 
                                118 to 140 -> 140 [1] lasti
                        [Code]
                            File Name: <frozen multithon.events.userupdate>
                            Object Name: sticker
                            Qualified Name: UserUpdate.Event.sticker
                            Arg Count: 1
                            Pos Only Arg Count: 0
                            KW Only Arg Count: 0
                            Stack Size: 5
                            Flags: 0x20000003 (CO_OPTIMIZED | CO_NEWLOCALS | CO_PYARMOR_OBFUSCATED)
                            [Names]
                                'isinstance'
                                'action'
                                'types'
                                'SendMessageChooseStickerAction'
                            [Locals+Names]
                                'self'
                                '__assert_armored__'
                            [Constants]
                                "\n            `True` if what's being uploaded is a sticker.\n            "
                                '__pyarmor_assert_22872__'
                                '__pyarmor_enter_22873__'
                                b'<COAddr>\x05\x00\x00\x1a\\\x00\x00\x00\x00\x00\x00\x00\x00\x00\x00\x00\x00\x00\x00\x00'
                                '__pyarmor_exit_22874__'
                            [Disassembly]
                                0       NOP                             
                                2       NOP                             
                                4       PUSH_NULL                       
                                6       LOAD_CONST                      2: '__pyarmor_enter_22873__'
                                8       LOAD_CONST                      3: b'<COAddr>\x05\x00\x00\x1a\\\x00\x00\x00\x00\x00\x00\x00\x00\x00\x00\x00\x00\x00\x00\x00'
                                10      BUILD_TUPLE                     1
                                12      CALL_FUNCTION_EX                0
                                14      POP_TOP                         
                                16      RESUME                          0
                                18      NOP                             
                                20      NOP                             
                                22      NOP                             
                                24      NOP                             
                                26      NOP                             
                                28      LOAD_GLOBAL                     1: NULL + isinstance
                                38      LOAD_FAST                       0: self
                                40      LOAD_ATTR                       2: action
                                60      LOAD_GLOBAL                     4: types
                                70      LOAD_ATTR                       6: SendMessageChooseStickerAction
                                90      CALL                            2
                                98      NOP                             
                                100     NOP                             
                                102     NOP                             
                                104     JUMP_FORWARD                    20 (to 146)
                                106     CALL                            1
                                114     POP_TOP                         
                                116     RETURN_VALUE                    
                                118     PUSH_EXC_INFO                   
                                120     PUSH_NULL                       
                                122     LOAD_CONST                      4: '__pyarmor_exit_22874__'
                                124     NOP                             
                                126     LOAD_CONST                      3: b'<COAddr>\x05\x00\x00\x1a\\\x00\x00\x00\x00\x00\x00\x00\x00\x00\x00\x00\x00\x00\x00\x00'
                                128     CALL                            1
                                136     POP_TOP                         
                                138     RERAISE                         0
                                140     COPY                            3
                                142     POP_EXCEPT                      
                                144     RERAISE                         1
                                146     PUSH_NULL                       
                                148     LOAD_CONST                      4: '__pyarmor_exit_22874__'
                                150     LOAD_CONST                      3: b'<COAddr>\x05\x00\x00\x1a\\\x00\x00\x00\x00\x00\x00\x00\x00\x00\x00\x00\x00\x00\x00\x00'
                                152     BUILD_TUPLE                     1
                                154     CALL_FUNCTION_EX                0
                                156     POP_TOP                         
                                158     RETURN_VALUE                    
                            [Exception Table]
                                28 to 98 -> 118 [0] 
                                118 to 140 -> 140 [1] lasti
                        [Code]
                            File Name: <frozen multithon.events.userupdate>
                            Object Name: photo
                            Qualified Name: UserUpdate.Event.photo
                            Arg Count: 1
                            Pos Only Arg Count: 0
                            KW Only Arg Count: 0
                            Stack Size: 5
                            Flags: 0x20000003 (CO_OPTIMIZED | CO_NEWLOCALS | CO_PYARMOR_OBFUSCATED)
                            [Names]
                                'isinstance'
                                'action'
                                'types'
                                'SendMessageUploadPhotoAction'
                            [Locals+Names]
                                'self'
                                '__assert_armored__'
                            [Constants]
                                "\n            `True` if what's being uploaded is a photo.\n            "
                                '__pyarmor_assert_22875__'
                                '__pyarmor_enter_22876__'
                                b'<COAddr>\x07\x00\x00\x1a\\\x00\x00\x00\x00\x00\x00\x00\x00\x00\x00\x00\x00\x00\x00\x00'
                                '__pyarmor_exit_22877__'
                            [Disassembly]
                                0       NOP                             
                                2       NOP                             
                                4       PUSH_NULL                       
                                6       LOAD_CONST                      2: '__pyarmor_enter_22876__'
                                8       LOAD_CONST                      3: b'<COAddr>\x07\x00\x00\x1a\\\x00\x00\x00\x00\x00\x00\x00\x00\x00\x00\x00\x00\x00\x00\x00'
                                10      BUILD_TUPLE                     1
                                12      CALL_FUNCTION_EX                0
                                14      POP_TOP                         
                                16      RESUME                          0
                                18      NOP                             
                                20      NOP                             
                                22      NOP                             
                                24      NOP                             
                                26      NOP                             
                                28      LOAD_GLOBAL                     1: NULL + isinstance
                                38      LOAD_FAST                       0: self
                                40      LOAD_ATTR                       2: action
                                60      LOAD_GLOBAL                     4: types
                                70      LOAD_ATTR                       6: SendMessageUploadPhotoAction
                                90      CALL                            2
                                98      NOP                             
                                100     NOP                             
                                102     NOP                             
                                104     JUMP_FORWARD                    20 (to 146)
                                106     CALL                            1
                                114     POP_TOP                         
                                116     RETURN_VALUE                    
                                118     PUSH_EXC_INFO                   
                                120     PUSH_NULL                       
                                122     LOAD_CONST                      4: '__pyarmor_exit_22877__'
                                124     NOP                             
                                126     LOAD_CONST                      3: b'<COAddr>\x07\x00\x00\x1a\\\x00\x00\x00\x00\x00\x00\x00\x00\x00\x00\x00\x00\x00\x00\x00'
                                128     CALL                            1
                                136     POP_TOP                         
                                138     RERAISE                         0
                                140     COPY                            3
                                142     POP_EXCEPT                      
                                144     RERAISE                         1
                                146     PUSH_NULL                       
                                148     LOAD_CONST                      4: '__pyarmor_exit_22877__'
                                150     LOAD_CONST                      3: b'<COAddr>\x07\x00\x00\x1a\\\x00\x00\x00\x00\x00\x00\x00\x00\x00\x00\x00\x00\x00\x00\x00'
                                152     BUILD_TUPLE                     1
                                154     CALL_FUNCTION_EX                0
                                156     POP_TOP                         
                                158     RETURN_VALUE                    
                            [Exception Table]
                                28 to 98 -> 118 [0] 
                                118 to 140 -> 140 [1] lasti
                        [Code]
                            File Name: <frozen multithon.events.userupdate>
                            Object Name: last_seen
                            Qualified Name: UserUpdate.Event.last_seen
                            Arg Count: 1
                            Pos Only Arg Count: 0
                            KW Only Arg Count: 0
                            Stack Size: 5
                            Flags: 0x20000003 (CO_OPTIMIZED | CO_NEWLOCALS | CO_PYARMOR_OBFUSCATED)
                            [Names]
                                'isinstance'
                                'status'
                                'types'
                                'UserStatusOffline'
                                'was_online'
                            [Locals+Names]
                                'self'
                                '__assert_armored__'
                            [Constants]
                                '\n            Exact `datetime.datetime` when the user was last seen if known.\n            '
                                '__pyarmor_assert_22878__'
                                '__pyarmor_enter_22879__'
                                b'<COAddr>\x07\x00\x00\x1a\x9c\x00\x00\x00\x00\x00\x00\x00\x00\x00\x00\x00\x00\x00\x00\x00'
                                '__pyarmor_exit_22880__'
                                None
                            [Disassembly]
                                0       NOP                             
                                2       NOP                             
                                4       PUSH_NULL                       
                                6       LOAD_CONST                      2: '__pyarmor_enter_22879__'
                                8       LOAD_CONST                      3: b'<COAddr>\x07\x00\x00\x1a\x9c\x00\x00\x00\x00\x00\x00\x00\x00\x00\x00\x00\x00\x00\x00\x00'
                                10      BUILD_TUPLE                     1
                                12      CALL_FUNCTION_EX                0
                                14      POP_TOP                         
                                16      RESUME                          0
                                18      NOP                             
                                20      NOP                             
                                22      NOP                             
                                24      NOP                             
                                26      NOP                             
                                28      LOAD_GLOBAL                     1: NULL + isinstance
                                38      LOAD_FAST                       0: self
                                40      LOAD_ATTR                       2: status
                                60      LOAD_GLOBAL                     4: types
                                70      LOAD_ATTR                       6: UserStatusOffline
                                90      CALL                            2
                                98      POP_JUMP_IF_FALSE               31 (to 162)
                                100     LOAD_FAST                       0: self
                                102     LOAD_ATTR                       2: status
                                122     LOAD_ATTR                       8: was_online
                                142     NOP                             
                                144     NOP                             
                                146     NOP                             
                                148     JUMP_FORWARD                    30 (to 210)
                                150     CALL                            1
                                158     POP_TOP                         
                                160     RETURN_VALUE                    
                                162     LOAD_CONST                      5: None
                                164     NOP                             
                                166     NOP                             
                                168     NOP                             
                                170     JUMP_FORWARD                    19 (to 210)
                                178     POP_TOP                         
                                180     RETURN_CONST                    5: None
                                182     PUSH_EXC_INFO                   
                                184     PUSH_NULL                       
                                186     LOAD_CONST                      4: '__pyarmor_exit_22880__'
                                188     NOP                             
                                190     LOAD_CONST                      3: b'<COAddr>\x07\x00\x00\x1a\x9c\x00\x00\x00\x00\x00\x00\x00\x00\x00\x00\x00\x00\x00\x00\x00'
                                192     CALL                            1
                                200     POP_TOP                         
                                202     RERAISE                         0
                                204     COPY                            3
                                206     POP_EXCEPT                      
                                208     RERAISE                         1
                                210     PUSH_NULL                       
                                212     LOAD_CONST                      4: '__pyarmor_exit_22880__'
                                214     LOAD_CONST                      3: b'<COAddr>\x07\x00\x00\x1a\x9c\x00\x00\x00\x00\x00\x00\x00\x00\x00\x00\x00\x00\x00\x00\x00'
                                216     BUILD_TUPLE                     1
                                218     CALL_FUNCTION_EX                0
                                220     POP_TOP                         
                                222     RETURN_VALUE                    
                            [Exception Table]
                                28 to 142 -> 182 [0] 
                                182 to 204 -> 204 [1] lasti
                        [Code]
                            File Name: <frozen multithon.events.userupdate>
                            Object Name: until
                            Qualified Name: UserUpdate.Event.until
                            Arg Count: 1
                            Pos Only Arg Count: 0
                            KW Only Arg Count: 0
                            Stack Size: 5
                            Flags: 0x20000003 (CO_OPTIMIZED | CO_NEWLOCALS | CO_PYARMOR_OBFUSCATED)
                            [Names]
                                'isinstance'
                                'status'
                                'types'
                                'UserStatusOnline'
                                'expires'
                            [Locals+Names]
                                'self'
                                '__assert_armored__'
                            [Constants]
                                '\n            The `datetime.datetime` until when the user should appear online.\n            '
                                '__pyarmor_assert_22881__'
                                '__pyarmor_enter_22882__'
                                b'<COAddr>\x07\x00\x00\x1a\x9c\x00\x00\x00\x00\x00\x00\x00\x00\x00\x00\x00\x00\x00\x00\x00'
                                '__pyarmor_exit_22883__'
                                None
                            [Disassembly]
                                0       NOP                             
                                2       NOP                             
                                4       PUSH_NULL                       
                                6       LOAD_CONST                      2: '__pyarmor_enter_22882__'
                                8       LOAD_CONST                      3: b'<COAddr>\x07\x00\x00\x1a\x9c\x00\x00\x00\x00\x00\x00\x00\x00\x00\x00\x00\x00\x00\x00\x00'
                                10      BUILD_TUPLE                     1
                                12      CALL_FUNCTION_EX                0
                                14      POP_TOP                         
                                16      RESUME                          0
                                18      NOP                             
                                20      NOP                             
                                22      NOP                             
                                24      NOP                             
                                26      NOP                             
                                28      LOAD_GLOBAL                     1: NULL + isinstance
                                38      LOAD_FAST                       0: self
                                40      LOAD_ATTR                       2: status
                                60      LOAD_GLOBAL                     4: types
                                70      LOAD_ATTR                       6: UserStatusOnline
                                90      CALL                            2
                                98      POP_JUMP_IF_FALSE               31 (to 162)
                                100     LOAD_FAST                       0: self
                                102     LOAD_ATTR                       2: status
                                122     LOAD_ATTR                       8: expires
                                142     NOP                             
                                144     NOP                             
                                146     NOP                             
                                148     JUMP_FORWARD                    30 (to 210)
                                150     CALL                            1
                                158     POP_TOP                         
                                160     RETURN_VALUE                    
                                162     LOAD_CONST                      5: None
                                164     NOP                             
                                166     NOP                             
                                168     NOP                             
                                170     JUMP_FORWARD                    19 (to 210)
                                178     POP_TOP                         
                                180     RETURN_CONST                    5: None
                                182     PUSH_EXC_INFO                   
                                184     PUSH_NULL                       
                                186     LOAD_CONST                      4: '__pyarmor_exit_22883__'
                                188     NOP                             
                                190     LOAD_CONST                      3: b'<COAddr>\x07\x00\x00\x1a\x9c\x00\x00\x00\x00\x00\x00\x00\x00\x00\x00\x00\x00\x00\x00\x00'
                                192     CALL                            1
                                200     POP_TOP                         
                                202     RERAISE                         0
                                204     COPY                            3
                                206     POP_EXCEPT                      
                                208     RERAISE                         1
                                210     PUSH_NULL                       
                                212     LOAD_CONST                      4: '__pyarmor_exit_22883__'
                                214     LOAD_CONST                      3: b'<COAddr>\x07\x00\x00\x1a\x9c\x00\x00\x00\x00\x00\x00\x00\x00\x00\x00\x00\x00\x00\x00\x00'
                                216     BUILD_TUPLE                     1
                                218     CALL_FUNCTION_EX                0
                                220     POP_TOP                         
                                222     RETURN_VALUE                    
                            [Exception Table]
                                28 to 142 -> 182 [0] 
                                182 to 204 -> 204 [1] lasti
                        [Code]
                            File Name: <frozen multithon.events.userupdate>
                            Object Name: _last_seen_delta
                            Qualified Name: UserUpdate.Event._last_seen_delta
                            Arg Count: 1
                            Pos Only Arg Count: 0
                            KW Only Arg Count: 0
                            Stack Size: 5
                            Flags: 0x20000003 (CO_OPTIMIZED | CO_NEWLOCALS | CO_PYARMOR_OBFUSCATED)
                            [Names]
                                'isinstance'
                                'status'
                                'types'
                                'UserStatusOffline'
                                'datetime'
                                'now'
                                'timezone'
                                'utc'
                                'was_online'
                                'UserStatusOnline'
                                'timedelta'
                                'UserStatusRecently'
                                'UserStatusLastWeek'
                                'UserStatusLastMonth'
                            [Locals+Names]
                                'self'
                                '__assert_armored__'
                            [Constants]
                                None
                                '__pyarmor_assert_22884__'
                                '__pyarmor_enter_22885__'
                                b'<COAddr>\x05\x00\x00\x1aP\x03\x00\x00\x00\x00\x00\x00\x00\x00\x00\x00\x00\x00\x00\x00'
                                (
                                    'tz'
                                )
                                '__pyarmor_exit_22886__'
                                0
                                (
                                    'days'
                                )
                                1
                                7
                                30
                                365
                            [Disassembly]
                                0       NOP                             
                                2       NOP                             
                                4       PUSH_NULL                       
                                6       LOAD_CONST                      2: '__pyarmor_enter_22885__'
                                8       LOAD_CONST                      3: b'<COAddr>\x05\x00\x00\x1aP\x03\x00\x00\x00\x00\x00\x00\x00\x00\x00\x00\x00\x00\x00\x00'
                                10      BUILD_TUPLE                     1
                                12      CALL_FUNCTION_EX                0
                                14      POP_TOP                         
                                16      RESUME                          0
                                18      NOP                             
                                20      NOP                             
                                22      NOP                             
                                24      NOP                             
                                26      NOP                             
                                28      LOAD_GLOBAL                     1: NULL + isinstance
                                38      LOAD_FAST                       0: self
                                40      LOAD_ATTR                       2: status
                                60      LOAD_GLOBAL                     4: types
                                70      LOAD_ATTR                       6: UserStatusOffline
                                90      CALL                            2
                                98      POP_JUMP_IF_FALSE               88 (to 276)
                                100     LOAD_GLOBAL                     8: datetime
                                110     LOAD_ATTR                       8: datetime
                                130     LOAD_ATTR                       11: now
                                150     LOAD_GLOBAL                     8: datetime
                                160     LOAD_ATTR                       12: timezone
                                180     LOAD_ATTR                       14: utc
                                200     KW_NAMES                        4: ('tz',)
                                202     CALL                            1
                                210     LOAD_FAST                       0: self
                                212     LOAD_ATTR                       2: status
                                232     LOAD_ATTR                       16: was_online
                                252     BINARY_OP                       10 (-)
                                256     NOP                             
                                258     NOP                             
                                260     JUMP_FORWARD                    319 (to 902)
                                264     CALL                            1
                                272     POP_TOP                         
                                274     RETURN_VALUE                    
                                276     LOAD_GLOBAL                     1: NULL + isinstance
                                286     LOAD_FAST                       0: self
                                288     LOAD_ATTR                       2: status
                                308     LOAD_GLOBAL                     4: types
                                318     LOAD_ATTR                       18: UserStatusOnline
                                338     CALL                            2
                                346     POP_JUMP_IF_FALSE               31 (to 410)
                                348     LOAD_GLOBAL                     9: NULL + datetime
                                358     LOAD_ATTR                       20: timedelta
                                378     LOAD_CONST                      6: 0
                                380     KW_NAMES                        7: ('days',)
                                382     CALL                            1
                                390     NOP                             
                                392     NOP                             
                                394     NOP                             
                                396     JUMP_FORWARD                    252 (to 902)
                                398     CALL                            1
                                406     POP_TOP                         
                                408     RETURN_VALUE                    
                                410     LOAD_GLOBAL                     1: NULL + isinstance
                                420     LOAD_FAST                       0: self
                                422     LOAD_ATTR                       2: status
                                442     LOAD_GLOBAL                     4: types
                                452     LOAD_ATTR                       22: UserStatusRecently
                                472     CALL                            2
                                480     POP_JUMP_IF_FALSE               31 (to 544)
                                482     LOAD_GLOBAL                     9: NULL + datetime
                                492     LOAD_ATTR                       20: timedelta
                                512     LOAD_CONST                      8: 1
                                514     KW_NAMES                        7: ('days',)
                                516     CALL                            1
                                524     NOP                             
                                526     NOP                             
                                528     NOP                             
                                530     JUMP_FORWARD                    185 (to 902)
                                532     CALL                            1
                                540     POP_TOP                         
                                542     RETURN_VALUE                    
                                544     LOAD_GLOBAL                     1: NULL + isinstance
                                554     LOAD_FAST                       0: self
                                556     LOAD_ATTR                       2: status
                                576     LOAD_GLOBAL                     4: types
                                586     LOAD_ATTR                       24: UserStatusLastWeek
                                606     CALL                            2
                                614     POP_JUMP_IF_FALSE               31 (to 678)
                                616     LOAD_GLOBAL                     9: NULL + datetime
                                626     LOAD_ATTR                       20: timedelta
                                646     LOAD_CONST                      9: 7
                                648     KW_NAMES                        7: ('days',)
                                650     CALL                            1
                                658     NOP                             
                                660     NOP                             
                                662     NOP                             
                                664     JUMP_FORWARD                    118 (to 902)
                                666     CALL                            1
                                674     POP_TOP                         
                                676     RETURN_VALUE                    
                                678     LOAD_GLOBAL                     1: NULL + isinstance
                                688     LOAD_FAST                       0: self
                                690     LOAD_ATTR                       2: status
                                710     LOAD_GLOBAL                     4: types
                                720     LOAD_ATTR                       26: UserStatusLastMonth
                                740     CALL                            2
                                748     POP_JUMP_IF_FALSE               31 (to 812)
                                750     LOAD_GLOBAL                     9: NULL + datetime
                                760     LOAD_ATTR                       20: timedelta
                                780     LOAD_CONST                      10: 30
                                782     KW_NAMES                        7: ('days',)
                                784     CALL                            1
                                792     NOP                             
                                794     NOP                             
                                796     NOP                             
                                798     JUMP_FORWARD                    51 (to 902)
                                800     CALL                            1
                                808     POP_TOP                         
                                810     RETURN_VALUE                    
                                812     LOAD_GLOBAL                     9: NULL + datetime
                                822     LOAD_ATTR                       20: timedelta
                                842     LOAD_CONST                      11: 365
                                844     KW_NAMES                        7: ('days',)
                                846     CALL                            1
                                854     NOP                             
                                856     NOP                             
                                858     NOP                             
                                860     JUMP_FORWARD                    20 (to 902)
                                862     CALL                            1
                                870     POP_TOP                         
                                872     RETURN_VALUE                    
                                874     PUSH_EXC_INFO                   
                                876     PUSH_NULL                       
                                878     LOAD_CONST                      5: '__pyarmor_exit_22886__'
                                880     NOP                             
                                882     LOAD_CONST                      3: b'<COAddr>\x05\x00\x00\x1aP\x03\x00\x00\x00\x00\x00\x00\x00\x00\x00\x00\x00\x00\x00\x00'
                                884     CALL                            1
                                892     POP_TOP                         
                                894     RERAISE                         0
                                896     COPY                            3
                                898     POP_EXCEPT                      
                                900     RERAISE                         1
                                902     PUSH_NULL                       
                                904     LOAD_CONST                      5: '__pyarmor_exit_22886__'
                                906     LOAD_CONST                      3: b'<COAddr>\x05\x00\x00\x1aP\x03\x00\x00\x00\x00\x00\x00\x00\x00\x00\x00\x00\x00\x00\x00'
                                908     BUILD_TUPLE                     1
                                910     CALL_FUNCTION_EX                0
                                912     POP_TOP                         
                                914     RETURN_VALUE                    
                            [Exception Table]
                                28 to 256 -> 874 [0] 
                                276 to 390 -> 874 [0] 
                                410 to 524 -> 874 [0] 
                                544 to 658 -> 874 [0] 
                                678 to 792 -> 874 [0] 
                                812 to 854 -> 874 [0] 
                                874 to 896 -> 896 [1] lasti
                        [Code]
                            File Name: <frozen multithon.events.userupdate>
                            Object Name: online
                            Qualified Name: UserUpdate.Event.online
                            Arg Count: 1
                            Pos Only Arg Count: 0
                            KW Only Arg Count: 0
                            Stack Size: 5
                            Flags: 0x20000003 (CO_OPTIMIZED | CO_NEWLOCALS | CO_PYARMOR_OBFUSCATED)
                            [Names]
                                '_last_seen_delta'
                                'datetime'
                                'timedelta'
                            [Locals+Names]
                                'self'
                                '__assert_armored__'
                            [Constants]
                                '\n            `True` if the user is currently online,\n            '
                                '__pyarmor_assert_22887__'
                                '__pyarmor_enter_22888__'
                                b'<COAddr>\x07\x00\x00\x1ab\x00\x00\x00\x00\x00\x00\x00\x00\x00\x00\x00\x00\x00\x00\x00'
                                0
                                (
                                    'days'
                                )
                                '__pyarmor_exit_22889__'
                            [Disassembly]
                                0       NOP                             
                                2       NOP                             
                                4       PUSH_NULL                       
                                6       LOAD_CONST                      2: '__pyarmor_enter_22888__'
                                8       LOAD_CONST                      3: b'<COAddr>\x07\x00\x00\x1ab\x00\x00\x00\x00\x00\x00\x00\x00\x00\x00\x00\x00\x00\x00\x00'
                                10      BUILD_TUPLE                     1
                                12      CALL_FUNCTION_EX                0
                                14      POP_TOP                         
                                16      RESUME                          0
                                18      NOP                             
                                20      NOP                             
                                22      NOP                             
                                24      NOP                             
                                26      NOP                             
                                28      LOAD_FAST                       0: self
                                30      LOAD_ATTR                       1: _last_seen_delta
                                50      CALL                            0
                                58      LOAD_GLOBAL                     3: NULL + datetime
                                68      LOAD_ATTR                       4: timedelta
                                88      LOAD_CONST                      4: 0
                                90      KW_NAMES                        5: ('days',)
                                92      CALL                            1
                                100     COMPARE_OP                      26 (<=)
                                104     NOP                             
                                106     NOP                             
                                108     NOP                             
                                110     JUMP_FORWARD                    20 (to 152)
                                112     CALL                            1
                                120     POP_TOP                         
                                122     RETURN_VALUE                    
                                124     PUSH_EXC_INFO                   
                                126     PUSH_NULL                       
                                128     LOAD_CONST                      6: '__pyarmor_exit_22889__'
                                130     NOP                             
                                132     LOAD_CONST                      3: b'<COAddr>\x07\x00\x00\x1ab\x00\x00\x00\x00\x00\x00\x00\x00\x00\x00\x00\x00\x00\x00\x00'
                                134     CALL                            1
                                142     POP_TOP                         
                                144     RERAISE                         0
                                146     COPY                            3
                                148     POP_EXCEPT                      
                                150     RERAISE                         1
                                152     PUSH_NULL                       
                                154     LOAD_CONST                      6: '__pyarmor_exit_22889__'
                                156     LOAD_CONST                      3: b'<COAddr>\x07\x00\x00\x1ab\x00\x00\x00\x00\x00\x00\x00\x00\x00\x00\x00\x00\x00\x00\x00'
                                158     BUILD_TUPLE                     1
                                160     CALL_FUNCTION_EX                0
                                162     POP_TOP                         
                                164     RETURN_VALUE                    
                            [Exception Table]
                                28 to 104 -> 124 [0] 
                                124 to 146 -> 146 [1] lasti
                        [Code]
                            File Name: <frozen multithon.events.userupdate>
                            Object Name: recently
                            Qualified Name: UserUpdate.Event.recently
                            Arg Count: 1
                            Pos Only Arg Count: 0
                            KW Only Arg Count: 0
                            Stack Size: 5
                            Flags: 0x20000003 (CO_OPTIMIZED | CO_NEWLOCALS | CO_PYARMOR_OBFUSCATED)
                            [Names]
                                '_last_seen_delta'
                                'datetime'
                                'timedelta'
                            [Locals+Names]
                                'self'
                                '__assert_armored__'
                            [Constants]
                                '\n            `True` if the user was seen within a day.\n            '
                                '__pyarmor_assert_22890__'
                                '__pyarmor_enter_22891__'
                                b'<COAddr>\x07\x00\x00\x1ab\x00\x00\x00\x00\x00\x00\x00\x00\x00\x00\x00\x00\x00\x00\x00'
                                1
                                (
                                    'days'
                                )
                                '__pyarmor_exit_22892__'
                            [Disassembly]
                                0       NOP                             
                                2       NOP                             
                                4       PUSH_NULL                       
                                6       LOAD_CONST                      2: '__pyarmor_enter_22891__'
                                8       LOAD_CONST                      3: b'<COAddr>\x07\x00\x00\x1ab\x00\x00\x00\x00\x00\x00\x00\x00\x00\x00\x00\x00\x00\x00\x00'
                                10      BUILD_TUPLE                     1
                                12      CALL_FUNCTION_EX                0
                                14      POP_TOP                         
                                16      RESUME                          0
                                18      NOP                             
                                20      NOP                             
                                22      NOP                             
                                24      NOP                             
                                26      NOP                             
                                28      LOAD_FAST                       0: self
                                30      LOAD_ATTR                       1: _last_seen_delta
                                50      CALL                            0
                                58      LOAD_GLOBAL                     3: NULL + datetime
                                68      LOAD_ATTR                       4: timedelta
                                88      LOAD_CONST                      4: 1
                                90      KW_NAMES                        5: ('days',)
                                92      CALL                            1
                                100     COMPARE_OP                      26 (<=)
                                104     NOP                             
                                106     NOP                             
                                108     NOP                             
                                110     JUMP_FORWARD                    20 (to 152)
                                112     CALL                            1
                                120     POP_TOP                         
                                122     RETURN_VALUE                    
                                124     PUSH_EXC_INFO                   
                                126     PUSH_NULL                       
                                128     LOAD_CONST                      6: '__pyarmor_exit_22892__'
                                130     NOP                             
                                132     LOAD_CONST                      3: b'<COAddr>\x07\x00\x00\x1ab\x00\x00\x00\x00\x00\x00\x00\x00\x00\x00\x00\x00\x00\x00\x00'
                                134     CALL                            1
                                142     POP_TOP                         
                                144     RERAISE                         0
                                146     COPY                            3
                                148     POP_EXCEPT                      
                                150     RERAISE                         1
                                152     PUSH_NULL                       
                                154     LOAD_CONST                      6: '__pyarmor_exit_22892__'
                                156     LOAD_CONST                      3: b'<COAddr>\x07\x00\x00\x1ab\x00\x00\x00\x00\x00\x00\x00\x00\x00\x00\x00\x00\x00\x00\x00'
                                158     BUILD_TUPLE                     1
                                160     CALL_FUNCTION_EX                0
                                162     POP_TOP                         
                                164     RETURN_VALUE                    
                            [Exception Table]
                                28 to 104 -> 124 [0] 
                                124 to 146 -> 146 [1] lasti
                        [Code]
                            File Name: <frozen multithon.events.userupdate>
                            Object Name: within_weeks
                            Qualified Name: UserUpdate.Event.within_weeks
                            Arg Count: 1
                            Pos Only Arg Count: 0
                            KW Only Arg Count: 0
                            Stack Size: 5
                            Flags: 0x20000003 (CO_OPTIMIZED | CO_NEWLOCALS | CO_PYARMOR_OBFUSCATED)
                            [Names]
                                '_last_seen_delta'
                                'datetime'
                                'timedelta'
                            [Locals+Names]
                                'self'
                                '__assert_armored__'
                            [Constants]
                                '\n            `True` if the user was seen within 7 days.\n            '
                                '__pyarmor_assert_22893__'
                                '__pyarmor_enter_22894__'
                                b'<COAddr>\x07\x00\x00\x1ab\x00\x00\x00\x00\x00\x00\x00\x00\x00\x00\x00\x00\x00\x00\x00'
                                7
                                (
                                    'days'
                                )
                                '__pyarmor_exit_22895__'
                            [Disassembly]
                                0       NOP                             
                                2       NOP                             
                                4       PUSH_NULL                       
                                6       LOAD_CONST                      2: '__pyarmor_enter_22894__'
                                8       LOAD_CONST                      3: b'<COAddr>\x07\x00\x00\x1ab\x00\x00\x00\x00\x00\x00\x00\x00\x00\x00\x00\x00\x00\x00\x00'
                                10      BUILD_TUPLE                     1
                                12      CALL_FUNCTION_EX                0
                                14      POP_TOP                         
                                16      RESUME                          0
                                18      NOP                             
                                20      NOP                             
                                22      NOP                             
                                24      NOP                             
                                26      NOP                             
                                28      LOAD_FAST                       0: self
                                30      LOAD_ATTR                       1: _last_seen_delta
                                50      CALL                            0
                                58      LOAD_GLOBAL                     3: NULL + datetime
                                68      LOAD_ATTR                       4: timedelta
                                88      LOAD_CONST                      4: 7
                                90      KW_NAMES                        5: ('days',)
                                92      CALL                            1
                                100     COMPARE_OP                      26 (<=)
                                104     NOP                             
                                106     NOP                             
                                108     NOP                             
                                110     JUMP_FORWARD                    20 (to 152)
                                112     CALL                            1
                                120     POP_TOP                         
                                122     RETURN_VALUE                    
                                124     PUSH_EXC_INFO                   
                                126     PUSH_NULL                       
                                128     LOAD_CONST                      6: '__pyarmor_exit_22895__'
                                130     NOP                             
                                132     LOAD_CONST                      3: b'<COAddr>\x07\x00\x00\x1ab\x00\x00\x00\x00\x00\x00\x00\x00\x00\x00\x00\x00\x00\x00\x00'
                                134     CALL                            1
                                142     POP_TOP                         
                                144     RERAISE                         0
                                146     COPY                            3
                                148     POP_EXCEPT                      
                                150     RERAISE                         1
                                152     PUSH_NULL                       
                                154     LOAD_CONST                      6: '__pyarmor_exit_22895__'
                                156     LOAD_CONST                      3: b'<COAddr>\x07\x00\x00\x1ab\x00\x00\x00\x00\x00\x00\x00\x00\x00\x00\x00\x00\x00\x00\x00'
                                158     BUILD_TUPLE                     1
                                160     CALL_FUNCTION_EX                0
                                162     POP_TOP                         
                                164     RETURN_VALUE                    
                            [Exception Table]
                                28 to 104 -> 124 [0] 
                                124 to 146 -> 146 [1] lasti
                        [Code]
                            File Name: <frozen multithon.events.userupdate>
                            Object Name: within_months
                            Qualified Name: UserUpdate.Event.within_months
                            Arg Count: 1
                            Pos Only Arg Count: 0
                            KW Only Arg Count: 0
                            Stack Size: 5
                            Flags: 0x20000003 (CO_OPTIMIZED | CO_NEWLOCALS | CO_PYARMOR_OBFUSCATED)
                            [Names]
                                '_last_seen_delta'
                                'datetime'
                                'timedelta'
                            [Locals+Names]
                                'self'
                                '__assert_armored__'
                            [Constants]
                                '\n            `True` if the user was seen within 30 days.\n            '
                                '__pyarmor_assert_22896__'
                                '__pyarmor_enter_22897__'
                                b'<COAddr>\x07\x00\x00\x1ab\x00\x00\x00\x00\x00\x00\x00\x00\x00\x00\x00\x00\x00\x00\x00'
                                30
                                (
                                    'days'
                                )
                                '__pyarmor_exit_22898__'
                            [Disassembly]
                                0       NOP                             
                                2       NOP                             
                                4       PUSH_NULL                       
                                6       LOAD_CONST                      2: '__pyarmor_enter_22897__'
                                8       LOAD_CONST                      3: b'<COAddr>\x07\x00\x00\x1ab\x00\x00\x00\x00\x00\x00\x00\x00\x00\x00\x00\x00\x00\x00\x00'
                                10      BUILD_TUPLE                     1
                                12      CALL_FUNCTION_EX                0
                                14      POP_TOP                         
                                16      RESUME                          0
                                18      NOP                             
                                20      NOP                             
                                22      NOP                             
                                24      NOP                             
                                26      NOP                             
                                28      LOAD_FAST                       0: self
                                30      LOAD_ATTR                       1: _last_seen_delta
                                50      CALL                            0
                                58      LOAD_GLOBAL                     3: NULL + datetime
                                68      LOAD_ATTR                       4: timedelta
                                88      LOAD_CONST                      4: 30
                                90      KW_NAMES                        5: ('days',)
                                92      CALL                            1
                                100     COMPARE_OP                      26 (<=)
                                104     NOP                             
                                106     NOP                             
                                108     NOP                             
                                110     JUMP_FORWARD                    20 (to 152)
                                112     CALL                            1
                                120     POP_TOP                         
                                122     RETURN_VALUE                    
                                124     PUSH_EXC_INFO                   
                                126     PUSH_NULL                       
                                128     LOAD_CONST                      6: '__pyarmor_exit_22898__'
                                130     NOP                             
                                132     LOAD_CONST                      3: b'<COAddr>\x07\x00\x00\x1ab\x00\x00\x00\x00\x00\x00\x00\x00\x00\x00\x00\x00\x00\x00\x00'
                                134     CALL                            1
                                142     POP_TOP                         
                                144     RERAISE                         0
                                146     COPY                            3
                                148     POP_EXCEPT                      
                                150     RERAISE                         1
                                152     PUSH_NULL                       
                                154     LOAD_CONST                      6: '__pyarmor_exit_22898__'
                                156     LOAD_CONST                      3: b'<COAddr>\x07\x00\x00\x1ab\x00\x00\x00\x00\x00\x00\x00\x00\x00\x00\x00\x00\x00\x00\x00'
                                158     BUILD_TUPLE                     1
                                160     CALL_FUNCTION_EX                0
                                162     POP_TOP                         
                                164     RETURN_VALUE                    
                            [Exception Table]
                                28 to 104 -> 124 [0] 
                                124 to 146 -> 146 [1] lasti
                        '__pyarmor_exit_22817__'
                    [Disassembly]
                        0       MAKE_CELL                       0: __class__
                        2       NOP                             
                        4       LOAD_NAME                       0: __name__
                        6       STORE_NAME                      1: __module__
                        8       LOAD_CONST                      0: 'UserUpdate.Event'
                        10      STORE_NAME                      2: __qualname__
                        12      LOAD_CONST                      1: '\n        Represents the event of a user update\n        such as gone online, started typing, etc.\n\n        Members:\n            status (:tl:`UserStatus`, optional):\n                The user status if the update is about going online or offline.\n\n                You should check this attribute first before checking any\n                of the seen within properties, since they will all be `None`\n                if the status is not set.\n\n            action (:tl:`SendMessageAction`, optional):\n                The "typing" action if any the user is performing if any.\n\n                You should check this attribute first before checking any\n                of the typing properties, since they will all be `None`\n                if the action is not set.\n        '
                        14      STORE_NAME                      3: __doc__
                        16      NOP                             
                        18      PUSH_NULL                       
                        20      LOAD_CONST                      3: '__pyarmor_enter_22816__'
                        22      LOAD_CONST                      4: b'<COAddr>\x07\x00\x00(j\x02\x00\x00\x00\x00\x00\x00\x00\x00\x00\x00\x00\x00\x00\x00'
                        24      BUILD_TUPLE                     1
                        26      CALL_FUNCTION_EX                0
                        28      POP_TOP                         
                        30      RESUME                          0
                        32      NOP                             
                        34      NOP                             
                        36      NOP                             
                        38      NOP                             
                        40      NOP                             
                        42      LOAD_CONST                      5: None
                        44      LOAD_CONST                      5: None
                        46      LOAD_CONST                      5: None
                        48      LOAD_CONST                      6: ('status', 'chat_peer', 'typing')
                        50      BUILD_CONST_KEY_MAP             3
                        52      LOAD_CLOSURE                    0: __class__
                        54      BUILD_TUPLE                     1
                        56      LOAD_CONST                      7: <CODE> __init__
                        58      MAKE_FUNCTION                   10
                        60      STORE_NAME                      5: __init__
                        62      LOAD_CLOSURE                    0: __class__
                        64      BUILD_TUPLE                     1
                        66      LOAD_CONST                      8: <CODE> _set_client
                        68      MAKE_FUNCTION                   8
                        70      STORE_NAME                      6: _set_client
                        72      LOAD_NAME                       7: property
                        74      LOAD_CONST                      9: <CODE> user
                        76      MAKE_FUNCTION                   0
                        78      CALL                            0
                        86      STORE_NAME                      8: user
                        88      LOAD_CONST                      10: <CODE> get_user
                        90      MAKE_FUNCTION                   0
                        92      STORE_NAME                      9: get_user
                        94      LOAD_NAME                       7: property
                        96      LOAD_CONST                      11: <CODE> input_user
                        98      MAKE_FUNCTION                   0
                        100     CALL                            0
                        108     STORE_NAME                      10: input_user
                        110     LOAD_CONST                      12: <CODE> get_input_user
                        112     MAKE_FUNCTION                   0
                        114     STORE_NAME                      11: get_input_user
                        116     LOAD_NAME                       7: property
                        118     LOAD_CONST                      13: <CODE> user_id
                        120     MAKE_FUNCTION                   0
                        122     CALL                            0
                        130     STORE_NAME                      12: user_id
                        132     LOAD_NAME                       7: property
                        134     LOAD_NAME                       13: _requires_action
                        136     LOAD_CONST                      14: <CODE> typing
                        138     MAKE_FUNCTION                   0
                        140     CALL                            0
                        148     CALL                            0
                        156     STORE_NAME                      14: typing
                        158     LOAD_NAME                       7: property
                        160     LOAD_NAME                       13: _requires_action
                        162     LOAD_CONST                      15: <CODE> uploading
                        164     MAKE_FUNCTION                   0
                        166     CALL                            0
                        174     CALL                            0
                        182     STORE_NAME                      15: uploading
                        184     LOAD_NAME                       7: property
                        186     LOAD_NAME                       13: _requires_action
                        188     LOAD_CONST                      16: <CODE> recording
                        190     MAKE_FUNCTION                   0
                        192     CALL                            0
                        200     CALL                            0
                        208     STORE_NAME                      16: recording
                        210     LOAD_NAME                       7: property
                        212     LOAD_NAME                       13: _requires_action
                        214     LOAD_CONST                      17: <CODE> playing
                        216     MAKE_FUNCTION                   0
                        218     CALL                            0
                        226     CALL                            0
                        234     STORE_NAME                      17: playing
                        236     LOAD_NAME                       7: property
                        238     LOAD_NAME                       13: _requires_action
                        240     LOAD_CONST                      18: <CODE> cancel
                        242     MAKE_FUNCTION                   0
                        244     CALL                            0
                        252     CALL                            0
                        260     STORE_NAME                      18: cancel
                        262     LOAD_NAME                       7: property
                        264     LOAD_NAME                       13: _requires_action
                        266     LOAD_CONST                      19: <CODE> geo
                        268     MAKE_FUNCTION                   0
                        270     CALL                            0
                        278     CALL                            0
                        286     STORE_NAME                      19: geo
                        288     LOAD_NAME                       7: property
                        290     LOAD_NAME                       13: _requires_action
                        292     LOAD_CONST                      20: <CODE> audio
                        294     MAKE_FUNCTION                   0
                        296     CALL                            0
                        304     CALL                            0
                        312     STORE_NAME                      20: audio
                        314     LOAD_NAME                       7: property
                        316     LOAD_NAME                       13: _requires_action
                        318     LOAD_CONST                      21: <CODE> round
                        320     MAKE_FUNCTION                   0
                        322     CALL                            0
                        330     CALL                            0
                        338     STORE_NAME                      21: round
                        340     LOAD_NAME                       7: property
                        342     LOAD_NAME                       13: _requires_action
                        344     LOAD_CONST                      22: <CODE> video
                        346     MAKE_FUNCTION                   0
                        348     CALL                            0
                        356     CALL                            0
                        364     STORE_NAME                      22: video
                        366     LOAD_NAME                       7: property
                        368     LOAD_NAME                       13: _requires_action
                        370     LOAD_CONST                      23: <CODE> contact
                        372     MAKE_FUNCTION                   0
                        374     CALL                            0
                        382     CALL                            0
                        390     STORE_NAME                      23: contact
                        392     LOAD_NAME                       7: property
                        394     LOAD_NAME                       13: _requires_action
                        396     LOAD_CONST                      24: <CODE> document
                        398     MAKE_FUNCTION                   0
                        400     CALL                            0
                        408     CALL                            0
                        416     STORE_NAME                      24: document
                        418     LOAD_NAME                       7: property
                        420     LOAD_NAME                       13: _requires_action
                        422     LOAD_CONST                      25: <CODE> sticker
                        424     MAKE_FUNCTION                   0
                        426     CALL                            0
                        434     CALL                            0
                        442     STORE_NAME                      25: sticker
                        444     LOAD_NAME                       7: property
                        446     LOAD_NAME                       13: _requires_action
                        448     LOAD_CONST                      26: <CODE> photo
                        450     MAKE_FUNCTION                   0
                        452     CALL                            0
                        460     CALL                            0
                        468     STORE_NAME                      26: photo
                        470     LOAD_NAME                       7: property
                        472     LOAD_NAME                       27: _requires_status
                        474     LOAD_CONST                      27: <CODE> last_seen
                        476     MAKE_FUNCTION                   0
                        478     CALL                            0
                        486     CALL                            0
                        494     STORE_NAME                      28: last_seen
                        496     LOAD_NAME                       7: property
                        498     LOAD_NAME                       27: _requires_status
                        500     LOAD_CONST                      28: <CODE> until
                        502     MAKE_FUNCTION                   0
                        504     CALL                            0
                        512     CALL                            0
                        520     STORE_NAME                      29: until
                        522     LOAD_CONST                      29: <CODE> _last_seen_delta
                        524     MAKE_FUNCTION                   0
                        526     STORE_NAME                      30: _last_seen_delta
                        528     LOAD_NAME                       7: property
                        530     LOAD_NAME                       27: _requires_status
                        532     LOAD_CONST                      30: <CODE> online
                        534     MAKE_FUNCTION                   0
                        536     CALL                            0
                        544     CALL                            0
                        552     STORE_NAME                      31: online
                        554     LOAD_NAME                       7: property
                        556     LOAD_NAME                       27: _requires_status
                        558     LOAD_CONST                      31: <CODE> recently
                        560     MAKE_FUNCTION                   0
                        562     CALL                            0
                        570     CALL                            0
                        578     STORE_NAME                      32: recently
                        580     LOAD_NAME                       7: property
                        582     LOAD_NAME                       27: _requires_status
                        584     LOAD_CONST                      32: <CODE> within_weeks
                        586     MAKE_FUNCTION                   0
                        588     CALL                            0
                        596     CALL                            0
                        604     STORE_NAME                      33: within_weeks
                        606     LOAD_NAME                       7: property
                        608     LOAD_NAME                       27: _requires_status
                        610     LOAD_CONST                      33: <CODE> within_months
                        612     MAKE_FUNCTION                   0
                        614     CALL                            0
                        622     CALL                            0
                        630     STORE_NAME                      34: within_months
                        632     LOAD_CLOSURE                    0: __class__
                        634     COPY                            1
                        636     STORE_NAME                      35: __classcell__
                        638     NOP                             
                        640     NOP                             
                        642     NOP                             
                        644     JUMP_FORWARD                    20 (to 686)
                        648     POP_TOP                         
                        650     LOAD_CLOSURE                    0: __class__
                        652     COPY                            1
                        654     STORE_NAME                      35: __classcell__
                        656     RETURN_VALUE                    
                        658     PUSH_EXC_INFO                   
                        660     PUSH_NULL                       
                        662     LOAD_CONST                      34: '__pyarmor_exit_22817__'
                        664     NOP                             
                        666     LOAD_CONST                      4: b'<COAddr>\x07\x00\x00(j\x02\x00\x00\x00\x00\x00\x00\x00\x00\x00\x00\x00\x00\x00\x00'
                        668     CALL                            1
                        676     POP_TOP                         
                        678     RERAISE                         0
                        680     COPY                            3
                        682     POP_EXCEPT                      
                        684     RERAISE                         1
                        686     PUSH_NULL                       
                        688     LOAD_CONST                      34: '__pyarmor_exit_22817__'
                        690     LOAD_CONST                      4: b'<COAddr>\x07\x00\x00(j\x02\x00\x00\x00\x00\x00\x00\x00\x00\x00\x00\x00\x00\x00\x00'
                        692     BUILD_TUPLE                     1
                        694     CALL_FUNCTION_EX                0
                        696     POP_TOP                         
                        698     RETURN_VALUE                    
                    [Exception Table]
                        42 to 632 -> 658 [0] 
                        658 to 680 -> 680 [1] lasti
                'Event'
                '__pyarmor_exit_22811__'
                (
                    None
                    None
                )
            [Disassembly]
                0       NOP                             
                2       LOAD_NAME                       0: __name__
                4       STORE_NAME                      1: __module__
                6       LOAD_CONST                      0: 'UserUpdate'
                8       STORE_NAME                      2: __qualname__
                10      LOAD_CONST                      1: "\n    Occurs whenever a user goes online, starts typing, etc.\n\n    Example\n        .. code-block:: python\n\n            from multithon import events\n\n            @client.on(events.UserUpdate)\n            async def handler(event):\n                # If someone is uploading, say something\n                if event.uploading:\n                    await client.send_message(event.user_id, 'What are you sending?')\n    "
                12      STORE_NAME                      3: __doc__
                14      NOP                             
                16      PUSH_NULL                       
                18      LOAD_CONST                      3: '__pyarmor_enter_22810__'
                20      LOAD_CONST                      4: b'<COAddr>\x05\x00\x00&@\x00\x00\x00\x00\x00\x00\x00\x00\x00\x00\x00\x00\x00\x00\x00'
                22      BUILD_TUPLE                     1
                24      CALL_FUNCTION_EX                0
                26      POP_TOP                         
                28      RESUME                          0
                30      NOP                             
                32      NOP                             
                34      NOP                             
                36      NOP                             
                38      NOP                             
                40      LOAD_NAME                       5: classmethod
                42      LOAD_CONST                      10: (None, None)
                44      LOAD_CONST                      6: <CODE> build
                46      MAKE_FUNCTION                   1
                48      CALL                            0
                56      STORE_NAME                      6: build
                58      PUSH_NULL                       
                60      LOAD_BUILD_CLASS                
                62      LOAD_CONST                      7: <CODE> Event
                64      MAKE_FUNCTION                   0
                66      LOAD_CONST                      8: 'Event'
                68      LOAD_NAME                       7: EventCommon
                70      LOAD_NAME                       8: SenderGetter
                72      CALL                            4
                80      STORE_NAME                      9: Event
                82      LOAD_CONST                      5: None
                84      NOP                             
                86      NOP                             
                88      NOP                             
                90      JUMP_FORWARD                    19 (to 130)
                98      POP_TOP                         
                100     RETURN_CONST                    5: None
                102     PUSH_EXC_INFO                   
                104     PUSH_NULL                       
                106     LOAD_CONST                      9: '__pyarmor_exit_22811__'
                108     NOP                             
                110     LOAD_CONST                      4: b'<COAddr>\x05\x00\x00&@\x00\x00\x00\x00\x00\x00\x00\x00\x00\x00\x00\x00\x00\x00\x00'
                112     CALL                            1
                120     POP_TOP                         
                122     RERAISE                         0
                124     COPY                            3
                126     POP_EXCEPT                      
                128     RERAISE                         1
                130     PUSH_NULL                       
                132     LOAD_CONST                      9: '__pyarmor_exit_22811__'
                134     LOAD_CONST                      4: b'<COAddr>\x05\x00\x00&@\x00\x00\x00\x00\x00\x00\x00\x00\x00\x00\x00\x00\x00\x00\x00'
                136     BUILD_TUPLE                     1
                138     CALL_FUNCTION_EX                0
                140     POP_TOP                         
                142     RETURN_VALUE                    
            [Exception Table]
                40 to 82 -> 102 [0] 
                102 to 124 -> 124 [1] lasti
        'UserUpdate'
        '__pyarmor_exit_22796__'
    [Disassembly]
        0       NOP                             
        2       NOP                             
        4       PUSH_NULL                       
        6       LOAD_CONST                      1: '__pyarmor_enter_22795__'
        8       LOAD_CONST                      2: b'<COAddr>\x05\x00\x00\x1a\x88\x00\x00\x00\x00\x00\x00\x00\x00\x00\x00\x00\x00\x00\x00\x00'
        10      BUILD_TUPLE                     1
        12      CALL_FUNCTION_EX                0
        14      POP_TOP                         
        16      RESUME                          0
        18      NOP                             
        20      NOP                             
        22      NOP                             
        24      NOP                             
        26      LOAD_CONST                      3: 0
        28      LOAD_CONST                      4: None
        30      IMPORT_NAME                     1: datetime
        32      STORE_NAME                      1: datetime
        34      LOAD_CONST                      3: 0
        36      LOAD_CONST                      4: None
        38      IMPORT_NAME                     2: functools
        40      STORE_NAME                      2: functools
        42      LOAD_CONST                      5: 1
        44      LOAD_CONST                      6: ('EventBuilder', 'EventCommon', 'name_inner_event')
        46      IMPORT_NAME                     3: common
        48      IMPORT_FROM                     4: EventBuilder
        50      STORE_NAME                      4: EventBuilder
        52      IMPORT_FROM                     5: EventCommon
        54      STORE_NAME                      5: EventCommon
        56      IMPORT_FROM                     6: name_inner_event
        58      STORE_NAME                      6: name_inner_event
        60      POP_TOP                         
        62      LOAD_CONST                      7: 2
        64      LOAD_CONST                      8: ('utils',)
        66      IMPORT_NAME                     7: 
        68      IMPORT_FROM                     8: utils
        70      STORE_NAME                      8: utils
        72      POP_TOP                         
        74      LOAD_CONST                      7: 2
        76      LOAD_CONST                      9: ('types',)
        78      IMPORT_NAME                     9: tl
        80      IMPORT_FROM                     10: types
        82      STORE_NAME                      10: types
        84      POP_TOP                         
        86      LOAD_CONST                      7: 2
        88      LOAD_CONST                      10: ('SenderGetter',)
        90      IMPORT_NAME                     11: tl.custom.sendergetter
        92      IMPORT_FROM                     12: SenderGetter
        94      STORE_NAME                      12: SenderGetter
        96      POP_TOP                         
        98      LOAD_CONST                      11: <CODE> _requires_action
        100     MAKE_FUNCTION                   0
        102     STORE_NAME                      13: _requires_action
        104     LOAD_CONST                      12: <CODE> _requires_status
        106     MAKE_FUNCTION                   0
        108     STORE_NAME                      14: _requires_status
        110     LOAD_NAME                       6: name_inner_event
        112     PUSH_NULL                       
        114     LOAD_BUILD_CLASS                
        116     LOAD_CONST                      13: <CODE> UserUpdate
        118     MAKE_FUNCTION                   0
        120     LOAD_CONST                      14: 'UserUpdate'
        122     LOAD_NAME                       4: EventBuilder
        124     CALL                            3
        132     CALL                            0
        140     STORE_NAME                      15: UserUpdate
        142     LOAD_CONST                      4: None
        144     NOP                             
        146     NOP                             
        148     NOP                             
        150     JUMP_FORWARD                    19 (to 190)
        158     POP_TOP                         
        160     RETURN_CONST                    4: None
        162     PUSH_EXC_INFO                   
        164     PUSH_NULL                       
        166     LOAD_CONST                      15: '__pyarmor_exit_22796__'
        168     NOP                             
        170     LOAD_CONST                      2: b'<COAddr>\x05\x00\x00\x1a\x88\x00\x00\x00\x00\x00\x00\x00\x00\x00\x00\x00\x00\x00\x00\x00'
        172     CALL                            1
        180     POP_TOP                         
        182     RERAISE                         0
        184     COPY                            3
        186     POP_EXCEPT                      
        188     RERAISE                         1
        190     PUSH_NULL                       
        192     LOAD_CONST                      15: '__pyarmor_exit_22796__'
        194     LOAD_CONST                      2: b'<COAddr>\x05\x00\x00\x1a\x88\x00\x00\x00\x00\x00\x00\x00\x00\x00\x00\x00\x00\x00\x00\x00'
        196     BUILD_TUPLE                     1
        198     CALL_FUNCTION_EX                0
        200     POP_TOP                         
        202     RETURN_VALUE                    
    [Exception Table]
        26 to 142 -> 162 [0] 
        162 to 184 -> 184 [1] lasti
