#decoded by lolz.live/mrpenny / t.me/zeus_jackpot
# ================================
# Примечания по Pyarmor:
# - Байт-код и объекты кода Pyarmor соответствуют стандартному Python, но присутствуют специальные вызовы функций среды выполнения (runtime) Pyarmor.
# - Вызовы строк — это не ошибки, а маркеры, которые обрабатываются Pyarmor во время выполнения.
#
# Руководство по декомпиляции (без среды выполнения):
# 1. Игнорируйте зашифрованные байты после `#`; используйте только строку до `#`.
# 2. Удалите "__pyarmor_enter_xxx__"(b"<COAddr>...") и "__pyarmor_leave_xxx__"(b"<COAddr>...") (пролог/эпилог).
# 3. "__pyarmor_assert_xxx__"(A) не является настоящим оператором assert.
#    - Если A — это имя или читаемая строка: замените на A.
#    - Если A — это (X, "Y"): замените на X.Y.
#    - Если A — это (X, "Y", Z): замените на X.Y = Z.
#    - В противном случае: выберите наиболее подходящую/логичную замену.
# 4. "__pyarmor_bcc_xxx__"(...) указывает на машинный (нативный) код; тело функции недоступно. Добавьте комментарий.
# ================================

[Code]
    File Name: <frozen program.modules.func.api.firefox>
    Object Name: <module>
    Qualified Name: <module>
    Arg Count: 0
    Pos Only Arg Count: 0
    KW Only Arg Count: 0
    Stack Size: 5
    Flags: 0x20000000 (CO_PYARMOR_OBFUSCATED)
    [Names]
        '__assert_armored__'
        'time'
        'random'
        'requests'
        'threading'
        'Event'
        'multithon.errors'
        'StopProgram'
        'requests.adapters'
        'HTTPAdapter'
        'Retry'
        'program.static_classes'
        'Logs'
        'logging'
        'FireFox'
    [Locals+Names]
    [Constants]
        '__pyarmor_assert_15558__'
        '__pyarmor_enter_15559__'
        b'<COAddr>\x05\x00\x00\x1ax\x00\x00\x00\x00\x00\x00\x00\x00\x00\x00\x00\x00\x00\x00\x00'
        0
        None
        (
            'Event'
        )
        (
            'StopProgram'
        )
        (
            'HTTPAdapter'
            'Retry'
        )
        (
            'Logs'
            'logging'
        )
        [Code]
            File Name: <frozen program.modules.func.api.firefox>
            Object Name: FireFox
            Qualified Name: FireFox
            Arg Count: 0
            Pos Only Arg Count: 0
            KW Only Arg Count: 0
            Stack Size: 5
            Flags: 0x20000000 (CO_PYARMOR_OBFUSCATED)
            [Names]
                '__name__'
                '__module__'
                '__qualname__'
                '__assert_armored__'
                'Event'
                '__init__'
                '_request'
                '_wait'
                'get_balance'
                'get_country'
                'order_number'
                'get_code'
                'set_status'
                'return_status'
            [Locals+Names]
            [Constants]
                'FireFox'
                '__pyarmor_assert_15561__'
                '__pyarmor_enter_15562__'
                b'<COAddr>\x07\x00\x00"d\x00\x00\x00\x00\x00\x00\x00\x00\x00\x00\x00\x00\x00\x00\x00'
                '1000'
                False
                [Code]
                    File Name: <frozen program.modules.func.api.firefox>
                    Object Name: __init__
                    Qualified Name: FireFox.__init__
                    Arg Count: 9
                    Pos Only Arg Count: 0
                    KW Only Arg Count: 0
                    Stack Size: 8
                    Flags: 0x20000003 (CO_OPTIMIZED | CO_NEWLOCALS | CO_PYARMOR_OBFUSCATED)
                    [Names]
                        'apikey'
                        'multikeys'
                        'last_key'
                        'split'
                        'random'
                        'choice'
                        'strip'
                        'gate'
                        'params'
                        'proxy'
                        'config'
                        'lang'
                        'service'
                        'retry'
                        'max_retry'
                        'timeout'
                        'stop_thread'
                        'api_return'
                        'rid'
                        'requests'
                        'Session'
                        '_session'
                        'HTTPAdapter'
                        'Retry'
                        'mount'
                    [Locals+Names]
                        'self'
                        'apikey'
                        'gate'
                        'proxy'
                        'config'
                        'lang'
                        'service'
                        'api_return'
                        'stop_thread'
                        '__assert_armored__'
                        '_var_var_0'
                    [Constants]
                        None
                        '__pyarmor_assert_15564__'
                        '__pyarmor_enter_15565__'
                        b'<COAddr>\x07\x00\x00\x1a\x9a\x02\x00\x00\x00\x00\x00\x00\x00\x00\x00\x00\x00\x00\x00\x00'
                        ':strix:'
                        0
                        10
                        40
                        3
                        0.3
                        (
                            429
                            500
                            502
                            503
                            504
                        )
                        (
                            'total'
                            'backoff_factor'
                            'status_forcelist'
                        )
                        (
                            'max_retries'
                        )
                        'http://'
                        'https://'
                        '__pyarmor_exit_15566__'
                    [Disassembly]
                        0       NOP                             
                        2       NOP                             
                        4       PUSH_NULL                       
                        6       LOAD_CONST                      2: '__pyarmor_enter_15565__'
                        8       LOAD_CONST                      3: b'<COAddr>\x07\x00\x00\x1a\x9a\x02\x00\x00\x00\x00\x00\x00\x00\x00\x00\x00\x00\x00\x00\x00'
                        10      BUILD_TUPLE                     1
                        12      CALL_FUNCTION_EX                0
                        14      POP_TOP                         
                        16      RESUME                          0
                        18      NOP                             
                        20      NOP                             
                        22      NOP                             
                        24      NOP                             
                        26      NOP                             
                        28      LOAD_FAST                       1: apikey
                        30      LOAD_FAST                       0: self
                        32      STORE_ATTR                      0: apikey
                        42      LOAD_CONST                      0: None
                        44      LOAD_FAST                       0: self
                        46      STORE_ATTR                      1: multikeys
                        56      LOAD_CONST                      0: None
                        58      LOAD_FAST                       0: self
                        60      STORE_ATTR                      2: last_key
                        70      LOAD_CONST                      4: ':strix:'
                        72      LOAD_FAST                       0: self
                        74      LOAD_ATTR                       0: apikey
                        94      CONTAINS_OP                     0 (in)
                        96      POP_JUMP_IF_FALSE               68 (to 234)
                        98      LOAD_FAST                       0: self
                        100     LOAD_ATTR                       0: apikey
                        120     LOAD_ATTR                       7: split
                        140     LOAD_CONST                      4: ':strix:'
                        142     CALL                            1
                        150     LOAD_FAST                       0: self
                        152     STORE_ATTR                      1: multikeys
                        162     LOAD_GLOBAL                     9: NULL + random
                        172     LOAD_ATTR                       10: choice
                        192     LOAD_FAST                       0: self
                        194     LOAD_ATTR                       2: multikeys
                        214     CALL                            1
                        222     LOAD_FAST                       0: self
                        224     STORE_ATTR                      0: apikey
                        234     LOAD_FAST                       2: gate
                        236     LOAD_ATTR                       13: strip
                        256     CALL                            0
                        264     LOAD_FAST                       0: self
                        266     STORE_ATTR                      7: gate
                        276     LOAD_CONST                      0: None
                        278     LOAD_FAST                       0: self
                        280     STORE_ATTR                      8: params
                        290     LOAD_FAST                       3: proxy
                        292     LOAD_FAST                       0: self
                        294     STORE_ATTR                      9: proxy
                        304     LOAD_FAST                       4: config
                        306     LOAD_FAST                       0: self
                        308     STORE_ATTR                      10: config
                        318     LOAD_FAST                       5: lang
                        320     LOAD_FAST                       0: self
                        322     STORE_ATTR                      11: lang
                        332     LOAD_FAST                       6: service
                        334     LOAD_ATTR                       13: strip
                        354     CALL                            0
                        362     LOAD_FAST                       0: self
                        364     STORE_ATTR                      12: service
                        374     LOAD_CONST                      5: 0
                        376     LOAD_FAST                       0: self
                        378     STORE_ATTR                      13: retry
                        388     LOAD_CONST                      6: 10
                        390     LOAD_FAST                       0: self
                        392     STORE_ATTR                      14: max_retry
                        402     LOAD_CONST                      7: 40
                        404     LOAD_FAST                       0: self
                        406     STORE_ATTR                      15: timeout
                        416     LOAD_FAST                       8: stop_thread
                        418     LOAD_FAST                       0: self
                        420     STORE_ATTR                      16: stop_thread
                        430     LOAD_FAST                       7: api_return
                        432     LOAD_FAST                       0: self
                        434     STORE_ATTR                      17: api_return
                        444     LOAD_CONST                      0: None
                        446     LOAD_FAST                       0: self
                        448     STORE_ATTR                      18: rid
                        458     LOAD_GLOBAL                     39: NULL + requests
                        468     LOAD_ATTR                       40: Session
                        488     CALL                            0
                        496     LOAD_FAST                       0: self
                        498     STORE_ATTR                      21: _session
                        508     LOAD_GLOBAL                     45: NULL + HTTPAdapter
                        518     LOAD_GLOBAL                     47: NULL + Retry
                        528     LOAD_CONST                      8: 3
                        530     LOAD_CONST                      9: 0.3
                        532     BUILD_LIST                      0
                        534     LOAD_CONST                      10: (429, 500, 502, 503, 504)
                        536     LIST_EXTEND                     1
                        538     KW_NAMES                        11: ('total', 'backoff_factor', 'status_forcelist')
                        540     CALL                            3
                        548     KW_NAMES                        12: ('max_retries',)
                        550     CALL                            1
                        558     STORE_FAST                      10: _var_var_0
                        560     LOAD_FAST                       0: self
                        562     LOAD_ATTR                       42: _session
                        582     LOAD_ATTR                       49: mount
                        602     LOAD_CONST                      13: 'http://'
                        604     LOAD_FAST                       10: _var_var_0
                        606     CALL                            2
                        614     POP_TOP                         
                        616     LOAD_FAST                       0: self
                        618     LOAD_ATTR                       42: _session
                        638     LOAD_ATTR                       49: mount
                        658     LOAD_CONST                      14: 'https://'
                        660     LOAD_FAST                       10: _var_var_0
                        662     CALL                            2
                        670     POP_TOP                         
                        672     LOAD_CONST                      0: None
                        674     NOP                             
                        676     NOP                             
                        678     NOP                             
                        680     JUMP_FORWARD                    19 (to 720)
                        688     POP_TOP                         
                        690     RETURN_CONST                    0: None
                        692     PUSH_EXC_INFO                   
                        694     PUSH_NULL                       
                        696     LOAD_CONST                      15: '__pyarmor_exit_15566__'
                        698     NOP                             
                        700     LOAD_CONST                      3: b'<COAddr>\x07\x00\x00\x1a\x9a\x02\x00\x00\x00\x00\x00\x00\x00\x00\x00\x00\x00\x00\x00\x00'
                        702     CALL                            1
                        710     POP_TOP                         
                        712     RERAISE                         0
                        714     COPY                            3
                        716     POP_EXCEPT                      
                        718     RERAISE                         1
                        720     PUSH_NULL                       
                        722     LOAD_CONST                      15: '__pyarmor_exit_15566__'
                        724     LOAD_CONST                      3: b'<COAddr>\x07\x00\x00\x1a\x9a\x02\x00\x00\x00\x00\x00\x00\x00\x00\x00\x00\x00\x00\x00\x00'
                        726     BUILD_TUPLE                     1
                        728     CALL_FUNCTION_EX                0
                        730     POP_TOP                         
                        732     RETURN_VALUE                    
                    [Exception Table]
                        28 to 672 -> 692 [0] 
                        692 to 714 -> 714 [1] lasti
                [Code]
                    File Name: <frozen program.modules.func.api.firefox>
                    Object Name: _request
                    Qualified Name: FireFox._request
                    Arg Count: 1
                    Pos Only Arg Count: 0
                    KW Only Arg Count: 0
                    Stack Size: 7
                    Flags: 0x20000003 (CO_OPTIMIZED | CO_NEWLOCALS | CO_PYARMOR_OBFUSCATED)
                    [Names]
                        '_session'
                        'get'
                        'gate'
                        'params'
                        'timeout'
                        'proxy'
                        'content'
                        'status_code'
                        'StopProgram'
                        'Exception'
                        '_wait'
                    [Locals+Names]
                        'self'
                        '__assert_armored__'
                        '_var_var_1'
                        '_var_var_2'
                        '_var_var_3'
                    [Constants]
                        None
                        '__pyarmor_assert_15567__'
                        '__pyarmor_enter_15568__'
                        b'<COAddr>\x07\x00\x00\x1a\xe4\x01\x00\x00\x00\x00\x00\x00\x00\x00\x00\x00\x00\x00\x00\x00'
                        True
                        (
                            'params'
                            'timeout'
                            'proxies'
                            'verify'
                        )
                        (
                            405
                            403
                            401
                            400
                            422
                            200
                        )
                        '__pyarmor_exit_15569__'
                        (
                            404
                        )
                        5
                        1
                    [Disassembly]
                        0       NOP                             
                        2       NOP                             
                        4       PUSH_NULL                       
                        6       LOAD_CONST                      2: '__pyarmor_enter_15568__'
                        8       LOAD_CONST                      3: b'<COAddr>\x07\x00\x00\x1a\xe4\x01\x00\x00\x00\x00\x00\x00\x00\x00\x00\x00\x00\x00\x00\x00'
                        10      BUILD_TUPLE                     1
                        12      CALL_FUNCTION_EX                0
                        14      POP_TOP                         
                        16      RESUME                          0
                        18      NOP                             
                        20      NOP                             
                        22      NOP                             
                        24      NOP                             
                        26      NOP                             
                        28      NOP                             
                        30      NOP                             
                        32      LOAD_FAST                       0: self
                        34      LOAD_ATTR                       0: _session
                        54      LOAD_ATTR                       3: get
                        74      LOAD_FAST                       0: self
                        76      LOAD_ATTR                       4: gate
                        96      LOAD_FAST                       0: self
                        98      LOAD_ATTR                       6: params
                        118     LOAD_FAST                       0: self
                        120     LOAD_ATTR                       8: timeout
                        140     LOAD_FAST                       0: self
                        142     LOAD_ATTR                       10: proxy
                        162     LOAD_CONST                      4: True
                        164     KW_NAMES                        5: ('params', 'timeout', 'proxies', 'verify')
                        166     CALL                            5
                        174     BEFORE_WITH                     
                        176     STORE_FAST                      2: _var_var_1
                        178     LOAD_FAST                       2: _var_var_1
                        180     LOAD_ATTR                       12: content
                        200     STORE_FAST                      3: _var_var_2
                        202     LOAD_FAST                       2: _var_var_1
                        204     LOAD_ATTR                       14: status_code
                        224     LOAD_CONST                      6: (405, 403, 401, 400, 422, 200)
                        226     CONTAINS_OP                     0 (in)
                        228     POP_JUMP_IF_FALSE               20 (to 270)
                        230     LOAD_FAST                       2: _var_var_1
                        232     SWAP                            2
                        234     LOAD_CONST                      0: None
                        236     LOAD_CONST                      0: None
                        238     LOAD_CONST                      0: None
                        240     CALL                            2
                        248     POP_TOP                         
                        250     NOP                             
                        252     NOP                             
                        254     NOP                             
                        256     JUMP_FORWARD                    140 (to 538)
                        258     CALL                            1
                        266     POP_TOP                         
                        268     RETURN_VALUE                    
                        270     LOAD_FAST                       2: _var_var_1
                        272     LOAD_ATTR                       14: status_code
                        292     LOAD_CONST                      8: (404,)
                        294     CONTAINS_OP                     0 (in)
                        296     POP_JUMP_IF_FALSE               19 (to 336)
                        298     NOP                             
                        300     LOAD_CONST                      0: None
                        302     LOAD_CONST                      0: None
                        304     LOAD_CONST                      0: None
                        306     CALL                            2
                        314     POP_TOP                         
                        316     LOAD_CONST                      0: None
                        318     NOP                             
                        320     NOP                             
                        322     NOP                             
                        324     JUMP_FORWARD                    106 (to 538)
                        332     POP_TOP                         
                        334     RETURN_CONST                    0: None
                        336     NOP                             
                        338     LOAD_CONST                      0: None
                        340     LOAD_CONST                      0: None
                        342     LOAD_CONST                      0: None
                        344     CALL                            2
                        352     POP_TOP                         
                        354     LOAD_FAST                       0: self
                        356     LOAD_ATTR                       21: _wait
                        376     LOAD_CONST                      10: 1
                        378     CALL                            1
                        386     POP_TOP                         
                        388     JUMP_BACKWARD                   180 (to 30)
                        390     PUSH_EXC_INFO                   
                        392     WITH_EXCEPT_START               
                        394     POP_JUMP_IF_TRUE                1 (to 398)
                        396     RERAISE                         2
                        398     POP_TOP                         
                        400     POP_EXCEPT                      
                        402     POP_TOP                         
                        404     POP_TOP                         
                        406     JUMP_BACKWARD                   27 (to 354)
                        408     COPY                            3
                        410     POP_EXCEPT                      
                        412     RERAISE                         1
                        414     PUSH_EXC_INFO                   
                        416     LOAD_GLOBAL                     16: StopProgram
                        426     CHECK_EXC_MATCH                 
                        428     POP_JUMP_IF_FALSE               2 (to 434)
                        430     POP_TOP                         
                        432     RAISE_VARARGS                   0
                        434     LOAD_GLOBAL                     18: Exception
                        444     CHECK_EXC_MATCH                 
                        446     POP_JUMP_IF_FALSE               27 (to 502)
                        448     STORE_FAST                      4: _var_var_3
                        450     LOAD_FAST                       0: self
                        452     LOAD_ATTR                       21: _wait
                        472     LOAD_CONST                      9: 5
                        474     CALL                            1
                        482     POP_TOP                         
                        484     POP_EXCEPT                      
                        486     LOAD_CONST                      0: None
                        488     STORE_FAST                      4: _var_var_3
                        490     DELETE_FAST                     4: _var_var_3
                        492     JUMP_BACKWARD                   70 (to 354)
                        494     LOAD_CONST                      0: None
                        496     STORE_FAST                      4: _var_var_3
                        498     DELETE_FAST                     4: _var_var_3
                        500     RERAISE                         1
                        502     RERAISE                         0
                        504     COPY                            3
                        506     POP_EXCEPT                      
                        508     RERAISE                         1
                        510     PUSH_EXC_INFO                   
                        512     PUSH_NULL                       
                        514     LOAD_CONST                      7: '__pyarmor_exit_15569__'
                        516     NOP                             
                        518     LOAD_CONST                      3: b'<COAddr>\x07\x00\x00\x1a\xe4\x01\x00\x00\x00\x00\x00\x00\x00\x00\x00\x00\x00\x00\x00\x00'
                        520     CALL                            1
                        528     POP_TOP                         
                        530     RERAISE                         0
                        532     COPY                            3
                        534     POP_EXCEPT                      
                        536     RERAISE                         1
                        538     PUSH_NULL                       
                        540     LOAD_CONST                      7: '__pyarmor_exit_15569__'
                        542     LOAD_CONST                      3: b'<COAddr>\x07\x00\x00\x1a\xe4\x01\x00\x00\x00\x00\x00\x00\x00\x00\x00\x00\x00\x00\x00\x00'
                        544     BUILD_TUPLE                     1
                        546     CALL_FUNCTION_EX                0
                        548     POP_TOP                         
                        550     RETURN_VALUE                    
                    [Exception Table]
                        28 to 30 -> 510 [0] 
                        32 to 176 -> 414 [0] 
                        176 to 232 -> 390 [1] lasti
                        232 to 250 -> 414 [0] 
                        270 to 300 -> 390 [1] lasti
                        300 to 316 -> 414 [0] 
                        338 to 354 -> 414 [0] 
                        354 to 390 -> 510 [0] 
                        390 to 400 -> 408 [3] lasti
                        400 to 414 -> 414 [0] 
                        414 to 450 -> 504 [1] lasti
                        450 to 484 -> 494 [1] lasti
                        484 to 494 -> 510 [0] 
                        494 to 504 -> 504 [1] lasti
                        504 to 510 -> 510 [0] 
                        510 to 532 -> 532 [1] lasti
                [Code]
                    File Name: <frozen program.modules.func.api.firefox>
                    Object Name: _wait
                    Qualified Name: FireFox._wait
                    Arg Count: 2
                    Pos Only Arg Count: 0
                    KW Only Arg Count: 0
                    Stack Size: 5
                    Flags: 0x20000003 (CO_OPTIMIZED | CO_NEWLOCALS | CO_PYARMOR_OBFUSCATED)
                    [Names]
                        'range'
                        'stop_thread'
                        'is_set'
                        'StopProgram'
                        'time'
                        'sleep'
                    [Locals+Names]
                        'self'
                        'second'
                        '__assert_armored__'
                        '_var_var_2'
                    [Constants]
                        None
                        '__pyarmor_assert_15570__'
                        '__pyarmor_enter_15571__'
                        b'<COAddr>\x05\x00\x00\x1a\xa8\x00\x00\x00\x00\x00\x00\x00\x00\x00\x00\x00\x00\x00\x00\x00'
                        1
                        '__pyarmor_exit_15572__'
                    [Disassembly]
                        0       NOP                             
                        2       NOP                             
                        4       PUSH_NULL                       
                        6       LOAD_CONST                      2: '__pyarmor_enter_15571__'
                        8       LOAD_CONST                      3: b'<COAddr>\x05\x00\x00\x1a\xa8\x00\x00\x00\x00\x00\x00\x00\x00\x00\x00\x00\x00\x00\x00\x00'
                        10      BUILD_TUPLE                     1
                        12      CALL_FUNCTION_EX                0
                        14      POP_TOP                         
                        16      RESUME                          0
                        18      NOP                             
                        20      NOP                             
                        22      NOP                             
                        24      NOP                             
                        26      NOP                             
                        28      LOAD_GLOBAL                     1: NULL + range
                        38      LOAD_FAST                       1: second
                        40      CALL                            1
                        48      GET_ITER                        
                        50      FOR_ITER                        59 (to 170)
                        54      STORE_FAST                      3: _var_var_2
                        56      LOAD_FAST                       0: self
                        58      LOAD_ATTR                       2: stop_thread
                        78      LOAD_ATTR                       5: is_set
                        98      CALL                            0
                        106     POP_JUMP_IF_FALSE               10 (to 128)
                        108     LOAD_GLOBAL                     7: NULL + StopProgram
                        118     CALL                            0
                        126     RAISE_VARARGS                   1
                        128     LOAD_GLOBAL                     9: NULL + time
                        138     LOAD_ATTR                       10: sleep
                        158     LOAD_CONST                      4: 1
                        160     CALL                            1
                        168     POP_TOP                         
                        170     JUMP_BACKWARD                   61 (to 50)
                        172     END_FOR                         
                        174     LOAD_CONST                      0: None
                        176     NOP                             
                        178     NOP                             
                        180     NOP                             
                        182     JUMP_FORWARD                    19 (to 222)
                        190     POP_TOP                         
                        192     RETURN_CONST                    0: None
                        194     PUSH_EXC_INFO                   
                        196     PUSH_NULL                       
                        198     LOAD_CONST                      5: '__pyarmor_exit_15572__'
                        200     NOP                             
                        202     LOAD_CONST                      3: b'<COAddr>\x05\x00\x00\x1a\xa8\x00\x00\x00\x00\x00\x00\x00\x00\x00\x00\x00\x00\x00\x00\x00'
                        204     CALL                            1
                        212     POP_TOP                         
                        214     RERAISE                         0
                        216     COPY                            3
                        218     POP_EXCEPT                      
                        220     RERAISE                         1
                        222     PUSH_NULL                       
                        224     LOAD_CONST                      5: '__pyarmor_exit_15572__'
                        226     LOAD_CONST                      3: b'<COAddr>\x05\x00\x00\x1a\xa8\x00\x00\x00\x00\x00\x00\x00\x00\x00\x00\x00\x00\x00\x00\x00'
                        228     BUILD_TUPLE                     1
                        230     CALL_FUNCTION_EX                0
                        232     POP_TOP                         
                        234     RETURN_VALUE                    
                    [Exception Table]
                        28 to 174 -> 194 [0] 
                        194 to 216 -> 216 [1] lasti
                [Code]
                    File Name: <frozen program.modules.func.api.firefox>
                    Object Name: get_balance
                    Qualified Name: FireFox.get_balance
                    Arg Count: 1
                    Pos Only Arg Count: 0
                    KW Only Arg Count: 0
                    Stack Size: 5
                    Flags: 0x20000003 (CO_OPTIMIZED | CO_NEWLOCALS | CO_PYARMOR_OBFUSCATED)
                    [Names]
                        'apikey'
                        'params'
                        '_request'
                        'text'
                        'split'
                    [Locals+Names]
                        'self'
                        '__assert_armored__'
                        '_var_var_1'
                        '_var_var_4'
                        '_var_var_5'
                    [Constants]
                        None
                        '__pyarmor_assert_15573__'
                        '__pyarmor_enter_15574__'
                        b'<COAddr>\x07\x00\x00\x1a\xd6\x00\x00\x00\x00\x00\x00\x00\x00\x00\x00\x00\x00\x00\x00\x00'
                        'myInfo'
                        (
                            'act'
                            'token'
                        )
                        '|'
                        0
                        '1'
                        1
                        '__pyarmor_exit_15575__'
                    [Disassembly]
                        0       NOP                             
                        2       NOP                             
                        4       PUSH_NULL                       
                        6       LOAD_CONST                      2: '__pyarmor_enter_15574__'
                        8       LOAD_CONST                      3: b'<COAddr>\x07\x00\x00\x1a\xd6\x00\x00\x00\x00\x00\x00\x00\x00\x00\x00\x00\x00\x00\x00\x00'
                        10      BUILD_TUPLE                     1
                        12      CALL_FUNCTION_EX                0
                        14      POP_TOP                         
                        16      RESUME                          0
                        18      NOP                             
                        20      NOP                             
                        22      NOP                             
                        24      NOP                             
                        26      NOP                             
                        28      NOP                             
                        30      LOAD_CONST                      4: 'myInfo'
                        32      LOAD_FAST                       0: self
                        34      LOAD_ATTR                       0: apikey
                        54      LOAD_CONST                      5: ('act', 'token')
                        56      BUILD_CONST_KEY_MAP             2
                        58      LOAD_FAST                       0: self
                        60      STORE_ATTR                      1: params
                        70      LOAD_FAST                       0: self
                        72      LOAD_ATTR                       5: _request
                        92      CALL                            0
                        100     STORE_FAST                      2: _var_var_1
                        102     LOAD_FAST                       2: _var_var_1
                        104     LOAD_ATTR                       6: text
                        124     LOAD_ATTR                       9: split
                        144     LOAD_CONST                      6: '|'
                        146     CALL                            1
                        154     STORE_FAST                      3: _var_var_4
                        156     LOAD_FAST                       3: _var_var_4
                        158     LOAD_CONST                      7: 0
                        160     BINARY_SUBSCR                   
                        164     LOAD_CONST                      8: '1'
                        166     COMPARE_OP                      40 (==)
                        170     POP_JUMP_IF_FALSE               16 (to 204)
                        172     LOAD_FAST                       3: _var_var_4
                        174     LOAD_CONST                      9: 1
                        176     BINARY_SUBSCR                   
                        180     STORE_FAST                      4: _var_var_5
                        182     LOAD_FAST                       4: _var_var_5
                        184     NOP                             
                        186     NOP                             
                        188     NOP                             
                        190     JUMP_FORWARD                    38 (to 268)
                        192     CALL                            1
                        200     POP_TOP                         
                        202     RETURN_VALUE                    
                        204     NOP                             
                        206     LOAD_CONST                      0: None
                        208     NOP                             
                        210     NOP                             
                        212     NOP                             
                        214     JUMP_FORWARD                    26 (to 268)
                        222     POP_TOP                         
                        224     RETURN_CONST                    0: None
                        226     PUSH_EXC_INFO                   
                        228     POP_TOP                         
                        230     POP_EXCEPT                      
                        232     JUMP_BACKWARD                   14 (to 206)
                        234     COPY                            3
                        236     POP_EXCEPT                      
                        238     RERAISE                         1
                        240     PUSH_EXC_INFO                   
                        242     PUSH_NULL                       
                        244     LOAD_CONST                      10: '__pyarmor_exit_15575__'
                        246     NOP                             
                        248     LOAD_CONST                      3: b'<COAddr>\x07\x00\x00\x1a\xd6\x00\x00\x00\x00\x00\x00\x00\x00\x00\x00\x00\x00\x00\x00\x00'
                        250     CALL                            1
                        258     POP_TOP                         
                        260     RERAISE                         0
                        262     COPY                            3
                        264     POP_EXCEPT                      
                        266     RERAISE                         1
                        268     PUSH_NULL                       
                        270     LOAD_CONST                      10: '__pyarmor_exit_15575__'
                        272     LOAD_CONST                      3: b'<COAddr>\x07\x00\x00\x1a\xd6\x00\x00\x00\x00\x00\x00\x00\x00\x00\x00\x00\x00\x00\x00\x00'
                        274     BUILD_TUPLE                     1
                        276     CALL_FUNCTION_EX                0
                        278     POP_TOP                         
                        280     RETURN_VALUE                    
                    [Exception Table]
                        30 to 184 -> 226 [0] 
                        204 to 206 -> 240 [0] 
                        226 to 230 -> 234 [1] lasti
                        230 to 240 -> 240 [0] 
                        240 to 262 -> 262 [1] lasti
                [Code]
                    File Name: <frozen program.modules.func.api.firefox>
                    Object Name: get_country
                    Qualified Name: FireFox.get_country
                    Arg Count: 1
                    Pos Only Arg Count: 0
                    KW Only Arg Count: 0
                    Stack Size: 6
                    Flags: 0x20000003 (CO_OPTIMIZED | CO_NEWLOCALS | CO_PYARMOR_OBFUSCATED)
                    [Names]
                    [Locals+Names]
                        'self'
                        '__assert_armored__'
                        '_var_var_6'
                    [Constants]
                        None
                        '__pyarmor_assert_15576__'
                        '__pyarmor_enter_15577__'
                        b'<COAddr>\x05\x00\x00\x1a\x1e\x04\x00\x00\x00\x00\x00\x00\x00\x00\x00\x00\x00\x00\x00\x00'
                        'afg'
                        'Afghanistan'   # b'\x81\xc3\x1e\x14;\xfb\xb0\xdb\x08\xee\x0c\xce'
                        'ago'
                        'Angola'
                        'arg'
                        'Argentina'   # b'\x81\xc3\n\x146\xf4\xaa\xdb\x15\xfb'
                        'aus'
                        'Australia'   # b"\x81\xc3\r\x00'\xe8\xbf\xde\x12\xfb"
                        'aut'
                        'Austria'
                        'aze'
                        'Azerbaijan'   # b'\x81\xc3\x02\x16!\xf8\xbf\xdb\x11\xfb\x03'
                        'bdi'
                        'Burundi'
                        'bfa'
                        'Burkinafaso'   # b'\x81\xc0\r\x018\xf3\xb0\xd3\x1d\xfb\x1e\xcf'
                        'bgd'
                        'Bangladesh'   # b'\x81\xc0\x19\x1d4\xf6\xbf\xd6\x1e\xe9\x05'
                        'blr'
                        'Belarus'
                        'bra'
                        'Brazil'
                        'caf'
                        'Caf'
                        'can'
                        'Canada'
                        'che'
                        'Switzerland'   # b"\x81\xd1\x0f\x1a'\xe0\xbb\xc0\x17\xfb\x03\xc4"
                        'chl'
                        'Chile'
                        'civ'
                        'Ivory'
                        'cmr'
                        'Cameroon'
                        'cod'
                        'Zaire'
                        'cog'
                        'Congo'
                        'col'
                        'Colombia'
                        'cze'
                        'Czech'
                        'dnk'
                        'Denmark'
                        'dom'
                        'Dominican'   # b'\x81\xc6\x17\x1e:\xf4\xb7\xd1\x1a\xf4'
                        'dza'
                        'Algeria'
                        'egy'
                        'Egypt'
                        'eng'
                        'England'
                        'esp'
                        'Spain'
                        'eth'
                        'Ethiopia'
                        'fji'
                        'Fiji'
                        'fra'
                        'France'
                        'geo'
                        'Georgia'
                        'gha'
                        'Ghana'
                        'gmb'
                        'Gambia'
                        'gtm'
                        'Guatemala'   # b"\x81\xc5\r\x12'\xff\xb3\xd3\x17\xfb"
                        'hkg'
                        'Hongkong'
                        'hrv'
                        'Croatia'
                        'idn'
                        'Indonesia'   # b'\x81\xcb\x16\x17<\xf4\xbb\xc1\x12\xfb'
                        'ind'
                        'India'
                        'irl'
                        'Ireland'
                        'irn'
                        'Iran'
                        'irq'
                        'Iraq'
                        'isr'
                        'Israel'
                        'jpn'
                        'Japan'
                        'kaz'
                        'Kazakhstan'   # b'\x81\xc9\x19\t2\xf1\xb6\xc1\x0f\xfb\x03'
                        'ken'
                        'Kenya'
                        'kgz'
                        'Kyrgyzstan'   # b'\x81\xc9\x01\x014\xe3\xa4\xc1\x0f\xfb\x03'
                        'khm'
                        'Cambodia'
                        'kor'
                        'Southkorea'   # b"\x81\xd1\x17\x06'\xf2\xb5\xdd\t\xff\x0c"
                        'lao'
                        'Laos'
                        'lbn'
                        'Lebanon'
                        'lbr'
                        'Liberia'
                        'lby'
                        'Libyan'
                        'lka'
                        'Srilanka'
                        'ltu'
                        'Lithuania'   # b'\x81\xce\x11\x07;\xef\xbf\xdc\x12\xfb'
                        'lva'
                        'Latvia'
                        'mac'
                        'Macao'
                        'mar'
                        'Morocco'
                        'mdg'
                        'Madagascar'   # b'\x81\xcf\x19\x172\xfd\xbf\xc1\x18\xfb\x1f'
                        'mdv'
                        'Maldives'
                        'mex'
                        'Mexico'
                        'mkd'
                        'Northmacedonia'   # b"\x81\xcc\x17\x01'\xf2\xb3\xd3\x18\xff\t\xcfb\xe5\xf9"
                        'mli'
                        'Mali'
                        'mmr'
                        'Myanmar'
                        'mng'
                        'Mongolia'
                        'moz'
                        'Mozambique'   # b'\x81\xcf\x17\t2\xf7\xbc\xdb\n\xef\x08'
                        'mtq'
                        'Martinique'   # b"\x81\xcf\x19\x01'\xf3\xb0\xdb\n\xef\x08"
                        'mwi'
                        'Malawi'
                        'mys'
                        'Malaysia'
                        'nga'
                        'Nigeria'
                        'nld'
                        'Netherlands'   # b'\x81\xcc\x1d\x07;\xff\xac\xde\x1a\xf4\t\xd3'
                        'nzl'
                        'Newzealand'   # b'\x81\xcc\x1d\x04)\xff\xbf\xde\x1a\xf4\t'
                        'pak'
                        'Pakistan'
                        'pan'
                        'Panama'
                        'per'
                        'Peru'
                        'phl'
                        'Philippines'   # b'\x81\xd2\x10\x1a?\xf3\xae\xc2\x12\xf4\x08\xd3'
                        'pol'
                        'Poland'
                        'prt'
                        'Portugal'
                        'rou'
                        'Romania'
                        'rus'
                        'Russia'
                        'sau'
                        'Saudiarabia'   # b'\x81\xd1\x19\x067\xf3\xbf\xc0\x1a\xf8\x04\xc1'
                        'sdn'
                        'Sudan'
                        'sen'
                        'Senegal'
                        'sgp'
                        'Singapore'   # b'\x81\xd1\x11\x1d4\xfb\xae\xdd\t\xff'
                        'sle'
                        'Sierraleone'   # b'\x81\xd1\x11\x16!\xe8\xbf\xde\x1e\xf5\x03\xc5'
                        'som'
                        'Somalia'
                        'ssd'
                        'Southsudan'   # b"\x81\xd1\x17\x06'\xf2\xad\xc7\x1f\xfb\x03"
                        'svn'
                        'Slovenia'
                        'swe'
                        'Sweden'
                        'syr'
                        'Syrian'
                        'tha'
                        'Thailand'
                        'tjk'
                        'Tajikistan'   # b'\x81\xd6\x19\x19:\xf1\xb7\xc1\x0f\xfb\x03'
                        'tls'
                        'Timorleste'   # b'\x81\xd6\x11\x1e<\xe8\xb2\xd7\x08\xee\x08'
                        'tur'
                        'Turkey'
                        'tza'
                        'Tanzania'
                        'ukr'
                        'Ukraine'
                        'usa'
                        'Usa'
                        'uzb'
                        'Uzbekistan'   # b'\x81\xd7\x02\x116\xf1\xb7\xc1\x0f\xfb\x03'
                        'vnm'
                        'Vietnam'
                        'wsm'
                        'Samoa'
                        'xkk'
                        'Kosovo'
                        'yem'
                        'Yemen'
                        'zaf'
                        'Southafrica'   # b"\x81\xd1\x17\x06'\xf2\xbf\xd4\t\xf3\x0e\xc1"
                        'Zambia'
                        'Zimbabwe'
                        (
                            'zmb'
                            'zwe'
                        )
                        '__pyarmor_exit_15578__'
                    [Disassembly]
                        0       NOP                             
                        2       NOP                             
                        4       PUSH_NULL                       
                        6       LOAD_CONST                      2: '__pyarmor_enter_15577__'
                        8       LOAD_CONST                      3: b'<COAddr>\x05\x00\x00\x1a\x1e\x04\x00\x00\x00\x00\x00\x00\x00\x00\x00\x00\x00\x00\x00\x00'
                        10      BUILD_TUPLE                     1
                        12      CALL_FUNCTION_EX                0
                        14      POP_TOP                         
                        16      RESUME                          0
                        18      NOP                             
                        20      NOP                             
                        22      NOP                             
                        24      NOP                             
                        26      NOP                             
                        28      NOP                             
                        30      BUILD_MAP                       0
                        32      LOAD_CONST                      4: 'afg'
                        34      PUSH_NULL                       
                        36      LOAD_CONST                      1: '__pyarmor_assert_15576__'
                        38      LOAD_CONST                      5: 'Afghanistan'   # b'\x81\xc3\x1e\x14;\xfb\xb0\xdb\x08\xee\x0c\xce'
                        40      CALL                            1
                        48      MAP_ADD                         1
                        50      LOAD_CONST                      6: 'ago'
                        52      LOAD_CONST                      7: 'Angola'
                        54      MAP_ADD                         1
                        56      LOAD_CONST                      8: 'arg'
                        58      PUSH_NULL                       
                        60      LOAD_CONST                      1: '__pyarmor_assert_15576__'
                        62      LOAD_CONST                      9: 'Argentina'   # b'\x81\xc3\n\x146\xf4\xaa\xdb\x15\xfb'
                        64      CALL                            1
                        72      MAP_ADD                         1
                        74      LOAD_CONST                      10: 'aus'
                        76      PUSH_NULL                       
                        78      LOAD_CONST                      1: '__pyarmor_assert_15576__'
                        80      LOAD_CONST                      11: 'Australia'   # b"\x81\xc3\r\x00'\xe8\xbf\xde\x12\xfb"
                        82      CALL                            1
                        90      MAP_ADD                         1
                        92      LOAD_CONST                      12: 'aut'
                        94      LOAD_CONST                      13: 'Austria'
                        96      MAP_ADD                         1
                        98      LOAD_CONST                      14: 'aze'
                        100     PUSH_NULL                       
                        102     LOAD_CONST                      1: '__pyarmor_assert_15576__'
                        104     LOAD_CONST                      15: 'Azerbaijan'   # b'\x81\xc3\x02\x16!\xf8\xbf\xdb\x11\xfb\x03'
                        106     CALL                            1
                        114     MAP_ADD                         1
                        116     LOAD_CONST                      16: 'bdi'
                        118     LOAD_CONST                      17: 'Burundi'
                        120     MAP_ADD                         1
                        122     LOAD_CONST                      18: 'bfa'
                        124     PUSH_NULL                       
                        126     LOAD_CONST                      1: '__pyarmor_assert_15576__'
                        128     LOAD_CONST                      19: 'Burkinafaso'   # b'\x81\xc0\r\x018\xf3\xb0\xd3\x1d\xfb\x1e\xcf'
                        130     CALL                            1
                        138     MAP_ADD                         1
                        140     LOAD_CONST                      20: 'bgd'
                        142     PUSH_NULL                       
                        144     LOAD_CONST                      1: '__pyarmor_assert_15576__'
                        146     LOAD_CONST                      21: 'Bangladesh'   # b'\x81\xc0\x19\x1d4\xf6\xbf\xd6\x1e\xe9\x05'
                        148     CALL                            1
                        156     MAP_ADD                         1
                        158     LOAD_CONST                      22: 'blr'
                        160     LOAD_CONST                      23: 'Belarus'
                        162     MAP_ADD                         1
                        164     LOAD_CONST                      24: 'bra'
                        166     LOAD_CONST                      25: 'Brazil'
                        168     MAP_ADD                         1
                        170     LOAD_CONST                      26: 'caf'
                        172     LOAD_CONST                      27: 'Caf'
                        174     MAP_ADD                         1
                        176     LOAD_CONST                      28: 'can'
                        178     LOAD_CONST                      29: 'Canada'
                        180     MAP_ADD                         1
                        182     LOAD_CONST                      30: 'che'
                        184     PUSH_NULL                       
                        186     LOAD_CONST                      1: '__pyarmor_assert_15576__'
                        188     LOAD_CONST                      31: 'Switzerland'   # b"\x81\xd1\x0f\x1a'\xe0\xbb\xc0\x17\xfb\x03\xc4"
                        190     CALL                            1
                        198     MAP_ADD                         1
                        200     LOAD_CONST                      32: 'chl'
                        202     LOAD_CONST                      33: 'Chile'
                        204     MAP_ADD                         1
                        206     LOAD_CONST                      34: 'civ'
                        208     LOAD_CONST                      35: 'Ivory'
                        210     MAP_ADD                         1
                        212     LOAD_CONST                      36: 'cmr'
                        214     LOAD_CONST                      37: 'Cameroon'
                        216     MAP_ADD                         1
                        218     BUILD_MAP                       0
                        220     LOAD_CONST                      38: 'cod'
                        222     LOAD_CONST                      39: 'Zaire'
                        224     MAP_ADD                         1
                        226     LOAD_CONST                      40: 'cog'
                        228     LOAD_CONST                      41: 'Congo'
                        230     MAP_ADD                         1
                        232     LOAD_CONST                      42: 'col'
                        234     LOAD_CONST                      43: 'Colombia'
                        236     MAP_ADD                         1
                        238     LOAD_CONST                      44: 'cze'
                        240     LOAD_CONST                      45: 'Czech'
                        242     MAP_ADD                         1
                        244     LOAD_CONST                      46: 'dnk'
                        246     LOAD_CONST                      47: 'Denmark'
                        248     MAP_ADD                         1
                        250     LOAD_CONST                      48: 'dom'
                        252     PUSH_NULL                       
                        254     LOAD_CONST                      1: '__pyarmor_assert_15576__'
                        256     LOAD_CONST                      49: 'Dominican'   # b'\x81\xc6\x17\x1e:\xf4\xb7\xd1\x1a\xf4'
                        258     CALL                            1
                        266     MAP_ADD                         1
                        268     LOAD_CONST                      50: 'dza'
                        270     LOAD_CONST                      51: 'Algeria'
                        272     MAP_ADD                         1
                        274     LOAD_CONST                      52: 'egy'
                        276     LOAD_CONST                      53: 'Egypt'
                        278     MAP_ADD                         1
                        280     LOAD_CONST                      54: 'eng'
                        282     LOAD_CONST                      55: 'England'
                        284     MAP_ADD                         1
                        286     LOAD_CONST                      56: 'esp'
                        288     LOAD_CONST                      57: 'Spain'
                        290     MAP_ADD                         1
                        292     LOAD_CONST                      58: 'eth'
                        294     LOAD_CONST                      59: 'Ethiopia'
                        296     MAP_ADD                         1
                        298     LOAD_CONST                      60: 'fji'
                        300     LOAD_CONST                      61: 'Fiji'
                        302     MAP_ADD                         1
                        304     LOAD_CONST                      62: 'fra'
                        306     LOAD_CONST                      63: 'France'
                        308     MAP_ADD                         1
                        310     LOAD_CONST                      64: 'geo'
                        312     LOAD_CONST                      65: 'Georgia'
                        314     MAP_ADD                         1
                        316     LOAD_CONST                      66: 'gha'
                        318     LOAD_CONST                      67: 'Ghana'
                        320     MAP_ADD                         1
                        322     LOAD_CONST                      68: 'gmb'
                        324     LOAD_CONST                      69: 'Gambia'
                        326     MAP_ADD                         1
                        328     LOAD_CONST                      70: 'gtm'
                        330     PUSH_NULL                       
                        332     LOAD_CONST                      1: '__pyarmor_assert_15576__'
                        334     LOAD_CONST                      71: 'Guatemala'   # b"\x81\xc5\r\x12'\xff\xb3\xd3\x17\xfb"
                        336     CALL                            1
                        344     MAP_ADD                         1
                        346     DICT_UPDATE                     1
                        348     BUILD_MAP                       0
                        350     LOAD_CONST                      72: 'hkg'
                        352     LOAD_CONST                      73: 'Hongkong'
                        354     MAP_ADD                         1
                        356     LOAD_CONST                      74: 'hrv'
                        358     LOAD_CONST                      75: 'Croatia'
                        360     MAP_ADD                         1
                        362     LOAD_CONST                      76: 'idn'
                        364     PUSH_NULL                       
                        366     LOAD_CONST                      1: '__pyarmor_assert_15576__'
                        368     LOAD_CONST                      77: 'Indonesia'   # b'\x81\xcb\x16\x17<\xf4\xbb\xc1\x12\xfb'
                        370     CALL                            1
                        378     MAP_ADD                         1
                        380     LOAD_CONST                      78: 'ind'
                        382     LOAD_CONST                      79: 'India'
                        384     MAP_ADD                         1
                        386     LOAD_CONST                      80: 'irl'
                        388     LOAD_CONST                      81: 'Ireland'
                        390     MAP_ADD                         1
                        392     LOAD_CONST                      82: 'irn'
                        394     LOAD_CONST                      83: 'Iran'
                        396     MAP_ADD                         1
                        398     LOAD_CONST                      84: 'irq'
                        400     LOAD_CONST                      85: 'Iraq'
                        402     MAP_ADD                         1
                        404     LOAD_CONST                      86: 'isr'
                        406     LOAD_CONST                      87: 'Israel'
                        408     MAP_ADD                         1
                        410     LOAD_CONST                      88: 'jpn'
                        412     LOAD_CONST                      89: 'Japan'
                        414     MAP_ADD                         1
                        416     LOAD_CONST                      90: 'kaz'
                        418     PUSH_NULL                       
                        420     LOAD_CONST                      1: '__pyarmor_assert_15576__'
                        422     LOAD_CONST                      91: 'Kazakhstan'   # b'\x81\xc9\x19\t2\xf1\xb6\xc1\x0f\xfb\x03'
                        424     CALL                            1
                        432     MAP_ADD                         1
                        434     LOAD_CONST                      92: 'ken'
                        436     LOAD_CONST                      93: 'Kenya'
                        438     MAP_ADD                         1
                        440     LOAD_CONST                      94: 'kgz'
                        442     PUSH_NULL                       
                        444     LOAD_CONST                      1: '__pyarmor_assert_15576__'
                        446     LOAD_CONST                      95: 'Kyrgyzstan'   # b'\x81\xc9\x01\x014\xe3\xa4\xc1\x0f\xfb\x03'
                        448     CALL                            1
                        456     MAP_ADD                         1
                        458     LOAD_CONST                      96: 'khm'
                        460     LOAD_CONST                      97: 'Cambodia'
                        462     MAP_ADD                         1
                        464     LOAD_CONST                      98: 'kor'
                        466     PUSH_NULL                       
                        468     LOAD_CONST                      1: '__pyarmor_assert_15576__'
                        470     LOAD_CONST                      99: 'Southkorea'   # b"\x81\xd1\x17\x06'\xf2\xb5\xdd\t\xff\x0c"
                        472     CALL                            1
                        480     MAP_ADD                         1
                        482     LOAD_CONST                      100: 'lao'
                        484     LOAD_CONST                      101: 'Laos'
                        486     MAP_ADD                         1
                        488     LOAD_CONST                      102: 'lbn'
                        490     LOAD_CONST                      103: 'Lebanon'
                        492     MAP_ADD                         1
                        494     LOAD_CONST                      104: 'lbr'
                        496     LOAD_CONST                      105: 'Liberia'
                        498     MAP_ADD                         1
                        500     DICT_UPDATE                     1
                        502     BUILD_MAP                       0
                        504     LOAD_CONST                      106: 'lby'
                        506     LOAD_CONST                      107: 'Libyan'
                        508     MAP_ADD                         1
                        510     LOAD_CONST                      108: 'lka'
                        512     LOAD_CONST                      109: 'Srilanka'
                        514     MAP_ADD                         1
                        516     LOAD_CONST                      110: 'ltu'
                        518     PUSH_NULL                       
                        520     LOAD_CONST                      1: '__pyarmor_assert_15576__'
                        522     LOAD_CONST                      111: 'Lithuania'   # b'\x81\xce\x11\x07;\xef\xbf\xdc\x12\xfb'
                        524     CALL                            1
                        532     MAP_ADD                         1
                        534     LOAD_CONST                      112: 'lva'
                        536     LOAD_CONST                      113: 'Latvia'
                        538     MAP_ADD                         1
                        540     LOAD_CONST                      114: 'mac'
                        542     LOAD_CONST                      115: 'Macao'
                        544     MAP_ADD                         1
                        546     LOAD_CONST                      116: 'mar'
                        548     LOAD_CONST                      117: 'Morocco'
                        550     MAP_ADD                         1
                        552     LOAD_CONST                      118: 'mdg'
                        554     PUSH_NULL                       
                        556     LOAD_CONST                      1: '__pyarmor_assert_15576__'
                        558     LOAD_CONST                      119: 'Madagascar'   # b'\x81\xcf\x19\x172\xfd\xbf\xc1\x18\xfb\x1f'
                        560     CALL                            1
                        568     MAP_ADD                         1
                        570     LOAD_CONST                      120: 'mdv'
                        572     LOAD_CONST                      121: 'Maldives'
                        574     MAP_ADD                         1
                        576     LOAD_CONST                      122: 'mex'
                        578     LOAD_CONST                      123: 'Mexico'
                        580     MAP_ADD                         1
                        582     LOAD_CONST                      124: 'mkd'
                        584     PUSH_NULL                       
                        586     LOAD_CONST                      1: '__pyarmor_assert_15576__'
                        588     LOAD_CONST                      125: 'Northmacedonia'   # b"\x81\xcc\x17\x01'\xf2\xb3\xd3\x18\xff\t\xcfb\xe5\xf9"
                        590     CALL                            1
                        598     MAP_ADD                         1
                        600     LOAD_CONST                      126: 'mli'
                        602     LOAD_CONST                      127: 'Mali'
                        604     MAP_ADD                         1
                        606     LOAD_CONST                      128: 'mmr'
                        608     LOAD_CONST                      129: 'Myanmar'
                        610     MAP_ADD                         1
                        612     LOAD_CONST                      130: 'mng'
                        614     LOAD_CONST                      131: 'Mongolia'
                        616     MAP_ADD                         1
                        618     LOAD_CONST                      132: 'moz'
                        620     PUSH_NULL                       
                        622     LOAD_CONST                      1: '__pyarmor_assert_15576__'
                        624     LOAD_CONST                      133: 'Mozambique'   # b'\x81\xcf\x17\t2\xf7\xbc\xdb\n\xef\x08'
                        626     CALL                            1
                        634     MAP_ADD                         1
                        636     LOAD_CONST                      134: 'mtq'
                        638     PUSH_NULL                       
                        640     LOAD_CONST                      1: '__pyarmor_assert_15576__'
                        642     LOAD_CONST                      135: 'Martinique'   # b"\x81\xcf\x19\x01'\xf3\xb0\xdb\n\xef\x08"
                        644     CALL                            1
                        652     MAP_ADD                         1
                        654     LOAD_CONST                      136: 'mwi'
                        656     LOAD_CONST                      137: 'Malawi'
                        658     MAP_ADD                         1
                        660     LOAD_CONST                      138: 'mys'
                        662     LOAD_CONST                      139: 'Malaysia'
                        664     MAP_ADD                         1
                        666     DICT_UPDATE                     1
                        668     BUILD_MAP                       0
                        670     LOAD_CONST                      140: 'nga'
                        672     LOAD_CONST                      141: 'Nigeria'
                        674     MAP_ADD                         1
                        676     LOAD_CONST                      142: 'nld'
                        678     PUSH_NULL                       
                        680     LOAD_CONST                      1: '__pyarmor_assert_15576__'
                        682     LOAD_CONST                      143: 'Netherlands'   # b'\x81\xcc\x1d\x07;\xff\xac\xde\x1a\xf4\t\xd3'
                        684     CALL                            1
                        692     MAP_ADD                         1
                        694     LOAD_CONST                      144: 'nzl'
                        696     PUSH_NULL                       
                        698     LOAD_CONST                      1: '__pyarmor_assert_15576__'
                        700     LOAD_CONST                      145: 'Newzealand'   # b'\x81\xcc\x1d\x04)\xff\xbf\xde\x1a\xf4\t'
                        702     CALL                            1
                        710     MAP_ADD                         1
                        712     LOAD_CONST                      146: 'pak'
                        714     LOAD_CONST                      147: 'Pakistan'
                        716     MAP_ADD                         1
                        718     LOAD_CONST                      148: 'pan'
                        720     LOAD_CONST                      149: 'Panama'
                        722     MAP_ADD                         1
                        724     LOAD_CONST                      150: 'per'
                        726     LOAD_CONST                      151: 'Peru'
                        728     MAP_ADD                         1
                        730     LOAD_CONST                      152: 'phl'
                        732     PUSH_NULL                       
                        734     LOAD_CONST                      1: '__pyarmor_assert_15576__'
                        736     LOAD_CONST                      153: 'Philippines'   # b'\x81\xd2\x10\x1a?\xf3\xae\xc2\x12\xf4\x08\xd3'
                        738     CALL                            1
                        746     MAP_ADD                         1
                        748     LOAD_CONST                      154: 'pol'
                        750     LOAD_CONST                      155: 'Poland'
                        752     MAP_ADD                         1
                        754     LOAD_CONST                      156: 'prt'
                        756     LOAD_CONST                      157: 'Portugal'
                        758     MAP_ADD                         1
                        760     LOAD_CONST                      158: 'rou'
                        762     LOAD_CONST                      159: 'Romania'
                        764     MAP_ADD                         1
                        766     LOAD_CONST                      160: 'rus'
                        768     LOAD_CONST                      161: 'Russia'
                        770     MAP_ADD                         1
                        772     LOAD_CONST                      162: 'sau'
                        774     PUSH_NULL                       
                        776     LOAD_CONST                      1: '__pyarmor_assert_15576__'
                        778     LOAD_CONST                      163: 'Saudiarabia'   # b'\x81\xd1\x19\x067\xf3\xbf\xc0\x1a\xf8\x04\xc1'
                        780     CALL                            1
                        788     MAP_ADD                         1
                        790     LOAD_CONST                      164: 'sdn'
                        792     LOAD_CONST                      165: 'Sudan'
                        794     MAP_ADD                         1
                        796     LOAD_CONST                      166: 'sen'
                        798     LOAD_CONST                      167: 'Senegal'
                        800     MAP_ADD                         1
                        802     LOAD_CONST                      168: 'sgp'
                        804     PUSH_NULL                       
                        806     LOAD_CONST                      1: '__pyarmor_assert_15576__'
                        808     LOAD_CONST                      169: 'Singapore'   # b'\x81\xd1\x11\x1d4\xfb\xae\xdd\t\xff'
                        810     CALL                            1
                        818     MAP_ADD                         1
                        820     LOAD_CONST                      170: 'sle'
                        822     PUSH_NULL                       
                        824     LOAD_CONST                      1: '__pyarmor_assert_15576__'
                        826     LOAD_CONST                      171: 'Sierraleone'   # b'\x81\xd1\x11\x16!\xe8\xbf\xde\x1e\xf5\x03\xc5'
                        828     CALL                            1
                        836     MAP_ADD                         1
                        838     LOAD_CONST                      172: 'som'
                        840     LOAD_CONST                      173: 'Somalia'
                        842     MAP_ADD                         1
                        844     DICT_UPDATE                     1
                        846     BUILD_MAP                       0
                        848     LOAD_CONST                      174: 'ssd'
                        850     PUSH_NULL                       
                        852     LOAD_CONST                      1: '__pyarmor_assert_15576__'
                        854     LOAD_CONST                      175: 'Southsudan'   # b"\x81\xd1\x17\x06'\xf2\xad\xc7\x1f\xfb\x03"
                        856     CALL                            1
                        864     MAP_ADD                         1
                        866     LOAD_CONST                      176: 'svn'
                        868     LOAD_CONST                      177: 'Slovenia'
                        870     MAP_ADD                         1
                        872     LOAD_CONST                      178: 'swe'
                        874     LOAD_CONST                      179: 'Sweden'
                        876     MAP_ADD                         1
                        878     LOAD_CONST                      180: 'syr'
                        880     LOAD_CONST                      181: 'Syrian'
                        882     MAP_ADD                         1
                        884     LOAD_CONST                      182: 'tha'
                        886     LOAD_CONST                      183: 'Thailand'
                        888     MAP_ADD                         1
                        890     LOAD_CONST                      184: 'tjk'
                        892     PUSH_NULL                       
                        894     LOAD_CONST                      1: '__pyarmor_assert_15576__'
                        896     LOAD_CONST                      185: 'Tajikistan'   # b'\x81\xd6\x19\x19:\xf1\xb7\xc1\x0f\xfb\x03'
                        898     CALL                            1
                        906     MAP_ADD                         1
                        908     LOAD_CONST                      186: 'tls'
                        910     PUSH_NULL                       
                        912     LOAD_CONST                      1: '__pyarmor_assert_15576__'
                        914     LOAD_CONST                      187: 'Timorleste'   # b'\x81\xd6\x11\x1e<\xe8\xb2\xd7\x08\xee\x08'
                        916     CALL                            1
                        924     MAP_ADD                         1
                        926     LOAD_CONST                      188: 'tur'
                        928     LOAD_CONST                      189: 'Turkey'
                        930     MAP_ADD                         1
                        932     LOAD_CONST                      190: 'tza'
                        934     LOAD_CONST                      191: 'Tanzania'
                        936     MAP_ADD                         1
                        938     LOAD_CONST                      192: 'ukr'
                        940     LOAD_CONST                      193: 'Ukraine'
                        942     MAP_ADD                         1
                        944     LOAD_CONST                      194: 'usa'
                        946     LOAD_CONST                      195: 'Usa'
                        948     MAP_ADD                         1
                        950     LOAD_CONST                      196: 'uzb'
                        952     PUSH_NULL                       
                        954     LOAD_CONST                      1: '__pyarmor_assert_15576__'
                        956     LOAD_CONST                      197: 'Uzbekistan'   # b'\x81\xd7\x02\x116\xf1\xb7\xc1\x0f\xfb\x03'
                        958     CALL                            1
                        966     MAP_ADD                         1
                        968     LOAD_CONST                      198: 'vnm'
                        970     LOAD_CONST                      199: 'Vietnam'
                        972     MAP_ADD                         1
                        974     LOAD_CONST                      200: 'wsm'
                        976     LOAD_CONST                      201: 'Samoa'
                        978     MAP_ADD                         1
                        980     LOAD_CONST                      202: 'xkk'
                        982     LOAD_CONST                      203: 'Kosovo'
                        984     MAP_ADD                         1
                        986     LOAD_CONST                      204: 'yem'
                        988     LOAD_CONST                      205: 'Yemen'
                        990     MAP_ADD                         1
                        992     LOAD_CONST                      206: 'zaf'
                        994     PUSH_NULL                       
                        996     LOAD_CONST                      1: '__pyarmor_assert_15576__'
                        998     LOAD_CONST                      207: 'Southafrica'   # b"\x81\xd1\x17\x06'\xf2\xbf\xd4\t\xf3\x0e\xc1"
                        1000    CALL                            1
                        1008    MAP_ADD                         1
                        1010    DICT_UPDATE                     1
                        1012    LOAD_CONST                      208: 'Zambia'
                        1014    LOAD_CONST                      209: 'Zimbabwe'
                        1016    LOAD_CONST                      210: ('zmb', 'zwe')
                        1018    BUILD_CONST_KEY_MAP             2
                        1020    DICT_UPDATE                     1
                        1022    STORE_FAST                      2: _var_var_6
                        1024    LOAD_FAST                       2: _var_var_6
                        1026    NOP                             
                        1028    NOP                             
                        1030    NOP                             
                        1032    JUMP_FORWARD                    37 (to 1108)
                        1034    CALL                            1
                        1042    POP_TOP                         
                        1044    RETURN_VALUE                    
                        1046    PUSH_EXC_INFO                   
                        1048    POP_TOP                         
                        1050    POP_EXCEPT                      
                        1052    JUMP_FORWARD                    3 (to 1060)
                        1054    COPY                            3
                        1056    POP_EXCEPT                      
                        1058    RERAISE                         1
                        1060    LOAD_CONST                      0: None
                        1062    NOP                             
                        1064    NOP                             
                        1066    NOP                             
                        1068    JUMP_FORWARD                    19 (to 1108)
                        1076    POP_TOP                         
                        1078    RETURN_CONST                    0: None
                        1080    PUSH_EXC_INFO                   
                        1082    PUSH_NULL                       
                        1084    LOAD_CONST                      211: '__pyarmor_exit_15578__'
                        1086    NOP                             
                        1088    LOAD_CONST                      3: b'<COAddr>\x05\x00\x00\x1a\x1e\x04\x00\x00\x00\x00\x00\x00\x00\x00\x00\x00\x00\x00\x00\x00'
                        1090    CALL                            1
                        1098    POP_TOP                         
                        1100    RERAISE                         0
                        1102    COPY                            3
                        1104    POP_EXCEPT                      
                        1106    RERAISE                         1
                        1108    PUSH_NULL                       
                        1110    LOAD_CONST                      211: '__pyarmor_exit_15578__'
                        1112    LOAD_CONST                      3: b'<COAddr>\x05\x00\x00\x1a\x1e\x04\x00\x00\x00\x00\x00\x00\x00\x00\x00\x00\x00\x00\x00\x00'
                        1114    BUILD_TUPLE                     1
                        1116    CALL_FUNCTION_EX                0
                        1118    POP_TOP                         
                        1120    RETURN_VALUE                    
                    [Exception Table]
                        30 to 1026 -> 1046 [0] 
                        1046 to 1050 -> 1054 [1] lasti
                        1050 to 1060 -> 1080 [0] 
                        1080 to 1102 -> 1102 [1] lasti
                None
                [Code]
                    File Name: <frozen program.modules.func.api.firefox>
                    Object Name: order_number
                    Qualified Name: FireFox.order_number
                    Arg Count: 4
                    Pos Only Arg Count: 0
                    KW Only Arg Count: 0
                    Stack Size: 8
                    Flags: 0x20000003 (CO_OPTIMIZED | CO_NEWLOCALS | CO_PYARMOR_OBFUSCATED)
                    [Names]
                        'Logs'
                        'PrintLog'
                        'lang'
                        'stop_thread'
                        'is_set'
                        'StopProgram'
                        'apikey'
                        'multikeys'
                        'random'
                        'choice'
                        'last_key'
                        'service'
                        'params'
                        '_request'
                        'text'
                        'split'
                        'rid'
                        '_wait'
                        'config'
                        'requests'
                        'exceptions'
                        'ConnectTimeout'
                        'ReadTimeout'
                        'ChunkedEncodingError'
                        'ConnectionError'
                        'RetryError'
                        'BaseException'
                        'logging'
                    [Locals+Names]
                        'self'
                        'country'
                        'max_price'
                        'phone'
                        '__assert_armored__'
                        '_var_var_7'
                        '_var_var_1'
                        '_var_var_4'
                        '_var_var_8'
                        '_var_var_9'
                        '_var_var_10'
                        '_var_var_3'
                    [Constants]
                        None
                        '__pyarmor_assert_15579__'
                        '__pyarmor_enter_15580__'
                        b'<COAddr>\x07\x00\x00\x1av\x07\x00\x00\x00\x00\x00\x00\x00\x00\x00\x00\x00\x00\x00\x00'
                        'wait_number'   # b"\x81\xf5\x19\x1a'\xc5\xb0\xc7\x16\xf8\x08\xd2"
                        (
                            'message'
                        )
                        'getPhone'
                        'TelegramExpert'   # b'\x81\xd6\x1d\x1f6\xfd\xac\xd3\x16\xdf\x15\xd0i\xfe\xec'
                        (
                            'act'
                            'token'
                            'iid'
                            'country'
                            'maxPrice'
                            'ref'
                        )
                        (
                            'act'
                            'token'
                            'iid'
                            'country'
                            'maxPrice'
                            'mobile'
                        )
                        '|'
                        0
                        '1'
                        1
                        4
                        7
                        '__pyarmor_exit_15581__'
                        '-8'
                        'NO_BALANCE'   # b'\x81\xcc7,\x11\xdb\x92\xf35\xd9('
                        '-2'
                        '-7'
                        'BAD_KEY'
                        '-1'
                        'There is no number at the moment'   # b'\x81\xd6\x10\x16!\xff\xfe\xdb\x08\xba\x03\xcf,\xe2\xed\x88\rX\xa9\xe7\xab\xdf\x0e\xd8\rj\xe3Q\x0f\xbc\x1b\xeb.'
                        'The token does not exist'   # b'\x81\xd6\x10\x16s\xee\xb1\xd9\x1e\xf4M\xc4c\xe9\xeb\xc5\x01R\xaf\xe7\xaf\xd3G\xdf\x11'
                        '-3'
                        'The project ID does not exist'   # b'\x81\xd6\x10\x16s\xea\xac\xdd\x11\xff\x0e\xd4,\xc5\xdc\xc5\x0bR\xbe\xb4\xea\xc5A\xd8Ej\xbbU\x13\xa5'
                        '-4'
                        'Incorrect country code'   # b'\x81\xcb\x16\x10<\xe8\xac\xd7\x18\xeeM\xc3c\xf9\xf6\x91\x1dD\xfb\xa4\xa5\xcfK'
                        '-5'
                        'The project has not been verified'   # b'\x81\xd6\x10\x16s\xea\xac\xdd\x11\xff\x0e\xd4,\xe4\xf9\x96OS\xb4\xb3\xea\xc9K\xc9\x0b/\xb5Y\x12\xb8\x18\xec?V'
                        '-6'
                        'The element is disabled'   # b'\x81\xd6\x10\x16s\xff\xb2\xd7\x16\xff\x03\xd4,\xe5\xeb\xc5\x0bT\xa8\xa6\xa8\xc7K\xc8'
                        'The user is disabled'   # b'\x81\xd6\x10\x16s\xef\xad\xd7\t\xba\x04\xd3,\xe8\xf1\x96\x0e_\xb7\xa2\xae'
                        'There is not enough balance, please top up'   # b'\x81\xd6\x10\x16!\xff\xfe\xdb\x08\xba\x03\xcfx\xac\xfd\x8b\x00H\xbc\xaf\xea\xc9O\xc0\x04a\xa0YL\xf1\x0e\xe9?S3\x08\xd8\xde\xbb>X\xfc\xe8'
                        '-9'
                        'Too many accounts are occupied, please top up your balance'   # b'\x81\xd6\x17\x1cs\xf7\xbf\xdc\x02\xba\x0c\xc3o\xe3\xed\x8b\x1bN\xfb\xa6\xb8\xce\x0e\xc3\x06l\xb6L\t\xb4\x1a\xa9zB,\x08\x99\xd9\xb1n\x0c\xe6\xe8\x1d\xc8\xc8O^8\xf8D\xbb\x85q\n\xec9\xe8\x9e'
                        '-10'
                        'It is forbidden to specify the quantity in projects'   # b'\x81\xcb\x0cS:\xe9\xfe\xd4\x14\xe8\x0f\xc9h\xe8\xfd\x8bOI\xb4\xe7\xb9\xdbK\xcf\x0ci\xba\x1c\x14\xb9\x1b\xa5+G!\x03\x8c\xc3\xa07X\xe0\xf6\x1d\xcd\xca\x00M2\xeeB\xe8'
                        ''
                        'The SMS service error:'   # b'\x81\xd6\x10\x16s\xc9\x93\xe1[\xe9\x08\xd2z\xe5\xfb\x80OX\xa9\xb5\xa5\xd9\x14'
                        (
                            'config'
                            'account'
                            'message'
                            'end'
                        )
                        'Ignoring the response from the api of the sms service, the response code:'   # b'\x81\xcb\x1f\x1d<\xe8\xb7\xdc\x1c\xba\x19\xc8i\xac\xea\x80\x1cM\xb4\xa9\xb9\xce\x0e\xca\x17`\xae\x1c\x14\xb9\x1b\xa5;B)M\x97\xcc\xf4:\x10\xec\xb8N\xd0\xcbOT2\xff@\xf2\x84uJ\xad#\xe3\x9e]\nN"CXF\x16\x86\x9d4\xe3\xbb\x968'
                    [Disassembly]
                        0       NOP                             
                        2       NOP                             
                        4       PUSH_NULL                       
                        6       LOAD_CONST                      2: '__pyarmor_enter_15580__'
                        8       LOAD_CONST                      3: b'<COAddr>\x07\x00\x00\x1av\x07\x00\x00\x00\x00\x00\x00\x00\x00\x00\x00\x00\x00\x00\x00'
                        10      BUILD_TUPLE                     1
                        12      CALL_FUNCTION_EX                0
                        14      POP_TOP                         
                        16      RESUME                          0
                        18      NOP                             
                        20      NOP                             
                        22      NOP                             
                        24      NOP                             
                        26      NOP                             
                        28      LOAD_GLOBAL                     1: NULL + Logs
                        38      LOAD_ATTR                       2: PrintLog
                        58      LOAD_FAST                       0: self
                        60      LOAD_ATTR                       4: lang
                        80      PUSH_NULL                       
                        82      LOAD_CONST                      1: '__pyarmor_assert_15579__'
                        84      LOAD_CONST                      4: 'wait_number'   # b"\x81\xf5\x19\x1a'\xc5\xb0\xc7\x16\xf8\x08\xd2"
                        86      CALL                            1
                        94      BINARY_SUBSCR                   
                        98      KW_NAMES                        5: ('message',)
                        100     CALL                            1
                        108     POP_TOP                         
                        110     NOP                             
                        112     LOAD_FAST                       0: self
                        114     LOAD_ATTR                       6: stop_thread
                        134     LOAD_ATTR                       9: is_set
                        154     CALL                            0
                        162     POP_JUMP_IF_FALSE               10 (to 184)
                        164     LOAD_GLOBAL                     11: NULL + StopProgram
                        174     CALL                            0
                        182     RAISE_VARARGS                   1
                        184     NOP                             
                        186     LOAD_FAST                       0: self
                        188     LOAD_ATTR                       12: apikey
                        208     STORE_FAST                      5: _var_var_7
                        210     LOAD_FAST                       0: self
                        212     LOAD_ATTR                       14: multikeys
                        232     POP_JUMP_IF_FALSE               38 (to 310)
                        234     LOAD_GLOBAL                     17: NULL + random
                        244     LOAD_ATTR                       18: choice
                        264     LOAD_FAST                       0: self
                        266     LOAD_ATTR                       14: multikeys
                        286     CALL                            1
                        294     STORE_FAST                      5: _var_var_7
                        296     LOAD_FAST                       5: _var_var_7
                        298     LOAD_FAST                       0: self
                        300     STORE_ATTR                      10: last_key
                        310     LOAD_FAST                       3: phone
                        312     POP_JUMP_IF_NOT_NONE            31 (to 376)
                        314     LOAD_CONST                      6: 'getPhone'
                        316     LOAD_FAST                       5: _var_var_7
                        318     LOAD_FAST                       0: self
                        320     LOAD_ATTR                       22: service
                        340     LOAD_FAST                       1: country
                        342     LOAD_FAST                       2: max_price
                        344     PUSH_NULL                       
                        346     LOAD_CONST                      1: '__pyarmor_assert_15579__'
                        348     LOAD_CONST                      7: 'TelegramExpert'   # b'\x81\xd6\x1d\x1f6\xfd\xac\xd3\x16\xdf\x15\xd0i\xfe\xec'
                        350     CALL                            1
                        358     LOAD_CONST                      8: ('act', 'token', 'iid', 'country', 'maxPrice', 'ref')
                        360     BUILD_CONST_KEY_MAP             6
                        362     LOAD_FAST                       0: self
                        364     STORE_ATTR                      12: params
                        374     JUMP_FORWARD                    24 (to 424)
                        376     LOAD_CONST                      6: 'getPhone'
                        378     LOAD_FAST                       5: _var_var_7
                        380     LOAD_FAST                       0: self
                        382     LOAD_ATTR                       22: service
                        402     LOAD_FAST                       1: country
                        404     LOAD_FAST                       2: max_price
                        406     LOAD_FAST                       3: phone
                        408     LOAD_CONST                      9: ('act', 'token', 'iid', 'country', 'maxPrice', 'mobile')
                        410     BUILD_CONST_KEY_MAP             6
                        412     LOAD_FAST                       0: self
                        414     STORE_ATTR                      12: params
                        424     LOAD_FAST                       0: self
                        426     LOAD_ATTR                       27: _request
                        446     CALL                            0
                        454     STORE_FAST                      6: _var_var_1
                        456     LOAD_FAST                       6: _var_var_1
                        458     LOAD_ATTR                       28: text
                        478     LOAD_ATTR                       31: split
                        498     LOAD_CONST                      10: '|'
                        500     CALL                            1
                        508     STORE_FAST                      7: _var_var_4
                        510     LOAD_FAST                       7: _var_var_4
                        512     LOAD_CONST                      11: 0
                        514     BINARY_SUBSCR                   
                        518     LOAD_CONST                      12: '1'
                        520     COMPARE_OP                      40 (==)
                        524     POP_JUMP_IF_FALSE               69 (to 664)
                        526     LOAD_FAST                       7: _var_var_4
                        528     LOAD_CONST                      13: 1
                        530     BINARY_SUBSCR                   
                        534     LOAD_FAST                       0: self
                        536     STORE_ATTR                      16: rid
                        546     LOAD_FAST                       7: _var_var_4
                        548     LOAD_CONST                      14: 4
                        550     BINARY_SUBSCR                   
                        554     FORMAT_VALUE                    0 (FVC_NONE)
                        556     LOAD_FAST                       7: _var_var_4
                        558     LOAD_CONST                      15: 7
                        560     BINARY_SUBSCR                   
                        564     FORMAT_VALUE                    0 (FVC_NONE)
                        566     BUILD_STRING                    2
                        568     STORE_FAST                      8: _var_var_8
                        570     LOAD_FAST                       7: _var_var_4
                        572     LOAD_CONST                      15: 7
                        574     BINARY_SUBSCR                   
                        578     STORE_FAST                      9: _var_var_9
                        580     LOAD_FAST                       8: _var_var_8
                        582     LOAD_FAST                       9: _var_var_9
                        584     BUILD_LIST                      2
                        586     LOAD_FAST                       0: self
                        588     LOAD_ATTR                       14: multikeys
                        608     POP_JUMP_IF_TRUE                17 (to 644)
                        610     LOAD_FAST                       0: self
                        612     LOAD_ATTR                       35: _wait
                        632     LOAD_CONST                      13: 1
                        634     CALL                            1
                        642     POP_TOP                         
                        644     NOP                             
                        646     NOP                             
                        648     JUMP_FORWARD                    656 (to 1964)
                        652     CALL                            1
                        660     POP_TOP                         
                        662     RETURN_VALUE                    
                        664     LOAD_FAST                       7: _var_var_4
                        666     LOAD_CONST                      11: 0
                        668     BINARY_SUBSCR                   
                        672     LOAD_CONST                      17: '-8'
                        674     COMPARE_OP                      40 (==)
                        678     POP_JUMP_IF_FALSE               46 (to 772)
                        680     PUSH_NULL                       
                        682     LOAD_CONST                      1: '__pyarmor_assert_15579__'
                        684     LOAD_CONST                      18: 'NO_BALANCE'   # b'\x81\xcc7,\x11\xdb\x92\xf35\xd9('
                        686     CALL                            1
                        694     LOAD_FAST                       0: self
                        696     LOAD_ATTR                       14: multikeys
                        716     POP_JUMP_IF_TRUE                17 (to 752)
                        718     LOAD_FAST                       0: self
                        720     LOAD_ATTR                       35: _wait
                        740     LOAD_CONST                      13: 1
                        742     CALL                            1
                        750     POP_TOP                         
                        752     NOP                             
                        754     NOP                             
                        756     JUMP_FORWARD                    602 (to 1964)
                        760     CALL                            1
                        768     POP_TOP                         
                        770     RETURN_VALUE                    
                        772     LOAD_FAST                       7: _var_var_4
                        774     LOAD_CONST                      11: 0
                        776     BINARY_SUBSCR                   
                        780     LOAD_CONST                      19: '-2'
                        782     COMPARE_OP                      40 (==)
                        786     POP_JUMP_IF_TRUE                8 (to 804)
                        788     LOAD_FAST                       7: _var_var_4
                        790     LOAD_CONST                      11: 0
                        792     BINARY_SUBSCR                   
                        796     LOAD_CONST                      20: '-7'
                        798     COMPARE_OP                      40 (==)
                        802     POP_JUMP_IF_FALSE               40 (to 884)
                        804     NOP                             
                        806     LOAD_FAST                       0: self
                        808     LOAD_ATTR                       14: multikeys
                        828     POP_JUMP_IF_TRUE                17 (to 864)
                        830     LOAD_FAST                       0: self
                        832     LOAD_ATTR                       35: _wait
                        852     LOAD_CONST                      13: 1
                        854     CALL                            1
                        862     POP_TOP                         
                        864     LOAD_CONST                      21: 'BAD_KEY'
                        866     NOP                             
                        868     NOP                             
                        870     JUMP_FORWARD                    545 (to 1964)
                        880     POP_TOP                         
                        882     RETURN_CONST                    21: 'BAD_KEY'
                        884     NOP                             
                        886     LOAD_FAST                       7: _var_var_4
                        888     LOAD_CONST                      13: 1
                        890     BINARY_SUBSCR                   
                        894     LOAD_CONST                      22: '-1'
                        896     COMPARE_OP                      40 (==)
                        900     POP_JUMP_IF_FALSE               8 (to 918)
                        902     PUSH_NULL                       
                        904     LOAD_CONST                      1: '__pyarmor_assert_15579__'
                        906     LOAD_CONST                      23: 'There is no number at the moment'   # b'\x81\xd6\x10\x16!\xff\xfe\xdb\x08\xba\x03\xcf,\xe2\xed\x88\rX\xa9\xe7\xab\xdf\x0e\xd8\rj\xe3Q\x0f\xbc\x1b\xeb.'
                        908     CALL                            1
                        916     STORE_FAST                      10: _var_var_10
                        918     LOAD_FAST                       7: _var_var_4
                        920     LOAD_CONST                      13: 1
                        922     BINARY_SUBSCR                   
                        926     LOAD_CONST                      19: '-2'
                        928     COMPARE_OP                      40 (==)
                        932     POP_JUMP_IF_FALSE               8 (to 950)
                        934     PUSH_NULL                       
                        936     LOAD_CONST                      1: '__pyarmor_assert_15579__'
                        938     LOAD_CONST                      24: 'The token does not exist'   # b'\x81\xd6\x10\x16s\xee\xb1\xd9\x1e\xf4M\xc4c\xe9\xeb\xc5\x01R\xaf\xe7\xaf\xd3G\xdf\x11'
                        940     CALL                            1
                        948     STORE_FAST                      10: _var_var_10
                        950     LOAD_FAST                       7: _var_var_4
                        952     LOAD_CONST                      13: 1
                        954     BINARY_SUBSCR                   
                        958     LOAD_CONST                      25: '-3'
                        960     COMPARE_OP                      40 (==)
                        964     POP_JUMP_IF_FALSE               8 (to 982)
                        966     PUSH_NULL                       
                        968     LOAD_CONST                      1: '__pyarmor_assert_15579__'
                        970     LOAD_CONST                      26: 'The project ID does not exist'   # b'\x81\xd6\x10\x16s\xea\xac\xdd\x11\xff\x0e\xd4,\xc5\xdc\xc5\x0bR\xbe\xb4\xea\xc5A\xd8Ej\xbbU\x13\xa5'
                        972     CALL                            1
                        980     STORE_FAST                      10: _var_var_10
                        982     LOAD_FAST                       7: _var_var_4
                        984     LOAD_CONST                      13: 1
                        986     BINARY_SUBSCR                   
                        990     LOAD_CONST                      27: '-4'
                        992     COMPARE_OP                      40 (==)
                        996     POP_JUMP_IF_FALSE               8 (to 1014)
                        998     PUSH_NULL                       
                        1000    LOAD_CONST                      1: '__pyarmor_assert_15579__'
                        1002    LOAD_CONST                      28: 'Incorrect country code'   # b'\x81\xcb\x16\x10<\xe8\xac\xd7\x18\xeeM\xc3c\xf9\xf6\x91\x1dD\xfb\xa4\xa5\xcfK'
                        1004    CALL                            1
                        1012    STORE_FAST                      10: _var_var_10
                        1014    LOAD_FAST                       7: _var_var_4
                        1016    LOAD_CONST                      13: 1
                        1018    BINARY_SUBSCR                   
                        1022    LOAD_CONST                      29: '-5'
                        1024    COMPARE_OP                      40 (==)
                        1028    POP_JUMP_IF_FALSE               8 (to 1046)
                        1030    PUSH_NULL                       
                        1032    LOAD_CONST                      1: '__pyarmor_assert_15579__'
                        1034    LOAD_CONST                      30: 'The project has not been verified'   # b'\x81\xd6\x10\x16s\xea\xac\xdd\x11\xff\x0e\xd4,\xe4\xf9\x96OS\xb4\xb3\xea\xc9K\xc9\x0b/\xb5Y\x12\xb8\x18\xec?V'
                        1036    CALL                            1
                        1044    STORE_FAST                      10: _var_var_10
                        1046    LOAD_FAST                       7: _var_var_4
                        1048    LOAD_CONST                      13: 1
                        1050    BINARY_SUBSCR                   
                        1054    LOAD_CONST                      31: '-6'
                        1056    COMPARE_OP                      40 (==)
                        1060    POP_JUMP_IF_FALSE               8 (to 1078)
                        1062    PUSH_NULL                       
                        1064    LOAD_CONST                      1: '__pyarmor_assert_15579__'
                        1066    LOAD_CONST                      32: 'The element is disabled'   # b'\x81\xd6\x10\x16s\xff\xb2\xd7\x16\xff\x03\xd4,\xe5\xeb\xc5\x0bT\xa8\xa6\xa8\xc7K\xc8'
                        1068    CALL                            1
                        1076    STORE_FAST                      10: _var_var_10
                        1078    LOAD_FAST                       7: _var_var_4
                        1080    LOAD_CONST                      13: 1
                        1082    BINARY_SUBSCR                   
                        1086    LOAD_CONST                      20: '-7'
                        1088    COMPARE_OP                      40 (==)
                        1092    POP_JUMP_IF_FALSE               8 (to 1110)
                        1094    PUSH_NULL                       
                        1096    LOAD_CONST                      1: '__pyarmor_assert_15579__'
                        1098    LOAD_CONST                      33: 'The user is disabled'   # b'\x81\xd6\x10\x16s\xef\xad\xd7\t\xba\x04\xd3,\xe8\xf1\x96\x0e_\xb7\xa2\xae'
                        1100    CALL                            1
                        1108    STORE_FAST                      10: _var_var_10
                        1110    LOAD_FAST                       7: _var_var_4
                        1112    LOAD_CONST                      13: 1
                        1114    BINARY_SUBSCR                   
                        1118    LOAD_CONST                      17: '-8'
                        1120    COMPARE_OP                      40 (==)
                        1124    POP_JUMP_IF_FALSE               8 (to 1142)
                        1126    PUSH_NULL                       
                        1128    LOAD_CONST                      1: '__pyarmor_assert_15579__'
                        1130    LOAD_CONST                      34: 'There is not enough balance, please top up'   # b'\x81\xd6\x10\x16!\xff\xfe\xdb\x08\xba\x03\xcfx\xac\xfd\x8b\x00H\xbc\xaf\xea\xc9O\xc0\x04a\xa0YL\xf1\x0e\xe9?S3\x08\xd8\xde\xbb>X\xfc\xe8'
                        1132    CALL                            1
                        1140    STORE_FAST                      10: _var_var_10
                        1142    LOAD_FAST                       7: _var_var_4
                        1144    LOAD_CONST                      13: 1
                        1146    BINARY_SUBSCR                   
                        1150    LOAD_CONST                      35: '-9'
                        1152    COMPARE_OP                      40 (==)
                        1156    POP_JUMP_IF_FALSE               8 (to 1174)
                        1158    PUSH_NULL                       
                        1160    LOAD_CONST                      1: '__pyarmor_assert_15579__'
                        1162    LOAD_CONST                      36: 'Too many accounts are occupied, please top up your balance'   # b'\x81\xd6\x17\x1cs\xf7\xbf\xdc\x02\xba\x0c\xc3o\xe3\xed\x8b\x1bN\xfb\xa6\xb8\xce\x0e\xc3\x06l\xb6L\t\xb4\x1a\xa9zB,\x08\x99\xd9\xb1n\x0c\xe6\xe8\x1d\xc8\xc8O^8\xf8D\xbb\x85q\n\xec9\xe8\x9e'
                        1164    CALL                            1
                        1172    STORE_FAST                      10: _var_var_10
                        1174    LOAD_FAST                       7: _var_var_4
                        1176    LOAD_CONST                      13: 1
                        1178    BINARY_SUBSCR                   
                        1182    LOAD_CONST                      37: '-10'
                        1184    COMPARE_OP                      40 (==)
                        1188    POP_JUMP_IF_FALSE               8 (to 1206)
                        1190    PUSH_NULL                       
                        1192    LOAD_CONST                      1: '__pyarmor_assert_15579__'
                        1194    LOAD_CONST                      38: 'It is forbidden to specify the quantity in projects'   # b'\x81\xcb\x0cS:\xe9\xfe\xd4\x14\xe8\x0f\xc9h\xe8\xfd\x8bOI\xb4\xe7\xb9\xdbK\xcf\x0ci\xba\x1c\x14\xb9\x1b\xa5+G!\x03\x8c\xc3\xa07X\xe0\xf6\x1d\xcd\xca\x00M2\xeeB\xe8'
                        1196    CALL                            1
                        1204    STORE_FAST                      10: _var_var_10
                        1206    LOAD_FAST                       7: _var_var_4
                        1208    LOAD_CONST                      13: 1
                        1210    BINARY_SUBSCR                   
                        1214    LOAD_CONST                      22: '-1'
                        1216    COMPARE_OP                      55 (!=)
                        1220    POP_JUMP_IF_FALSE               41 (to 1304)
                        1222    LOAD_GLOBAL                     1: NULL + Logs
                        1232    LOAD_ATTR                       2: PrintLog
                        1252    LOAD_FAST                       0: self
                        1254    LOAD_ATTR                       36: config
                        1274    LOAD_CONST                      39: ''
                        1276    PUSH_NULL                       
                        1278    LOAD_CONST                      1: '__pyarmor_assert_15579__'
                        1280    LOAD_CONST                      40: 'The SMS service error:'   # b'\x81\xd6\x10\x16s\xc9\x93\xe1[\xe9\x08\xd2z\xe5\xfb\x80OX\xa9\xb5\xa5\xd9\x14'
                        1282    CALL                            1
                        1290    LOAD_FAST_CHECK                 10: _var_var_10
                        1292    KW_NAMES                        41: ('config', 'account', 'message', 'end')
                        1294    CALL                            4
                        1302    POP_TOP                         
                        1304    LOAD_FAST                       0: self
                        1306    LOAD_ATTR                       14: multikeys
                        1326    POP_JUMP_IF_TRUE                18 (to 1364)
                        1328    LOAD_FAST                       0: self
                        1330    LOAD_ATTR                       35: _wait
                        1350    LOAD_CONST                      13: 1
                        1352    CALL                            1
                        1360    POP_TOP                         
                        1362    NOP                             
                        1364    JUMP_BACKWARD                   628 (to 112)
                        1368    PUSH_EXC_INFO                   
                        1370    POP_TOP                         
                        1372    LOAD_GLOBAL                     1: NULL + Logs
                        1382    LOAD_ATTR                       2: PrintLog
                        1402    LOAD_FAST                       0: self
                        1404    LOAD_ATTR                       36: config
                        1424    LOAD_CONST                      39: ''
                        1426    PUSH_NULL                       
                        1428    LOAD_CONST                      1: '__pyarmor_assert_15579__'
                        1430    LOAD_CONST                      42: 'Ignoring the response from the api of the sms service, the response code:'   # b'\x81\xcb\x1f\x1d<\xe8\xb7\xdc\x1c\xba\x19\xc8i\xac\xea\x80\x1cM\xb4\xa9\xb9\xce\x0e\xca\x17`\xae\x1c\x14\xb9\x1b\xa5;B)M\x97\xcc\xf4:\x10\xec\xb8N\xd0\xcbOT2\xff@\xf2\x84uJ\xad#\xe3\x9e]\nN"CXF\x16\x86\x9d4\xe3\xbb\x968'
                        1432    CALL                            1
                        1440    LOAD_FAST                       7: _var_var_4
                        1442    LOAD_CONST                      11: 0
                        1444    BINARY_SUBSCR                   
                        1448    KW_NAMES                        41: ('config', 'account', 'message', 'end')
                        1450    CALL                            4
                        1458    POP_TOP                         
                        1460    POP_EXCEPT                      
                        1462    JUMP_BACKWARD                   80 (to 1304)
                        1464    COPY                            3
                        1466    POP_EXCEPT                      
                        1468    RERAISE                         1
                        1470    PUSH_EXC_INFO                   
                        1472    LOAD_GLOBAL                     38: requests
                        1482    LOAD_ATTR                       40: exceptions
                        1502    LOAD_ATTR                       42: ConnectTimeout
                        1522    CHECK_EXC_MATCH                 
                        1524    POP_JUMP_IF_FALSE               3 (to 1532)
                        1526    POP_TOP                         
                        1528    POP_EXCEPT                      
                        1530    JUMP_BACKWARD                   114 (to 1304)
                        1532    LOAD_GLOBAL                     38: requests
                        1542    LOAD_ATTR                       40: exceptions
                        1562    LOAD_ATTR                       44: ReadTimeout
                        1582    CHECK_EXC_MATCH                 
                        1584    POP_JUMP_IF_FALSE               3 (to 1592)
                        1586    POP_TOP                         
                        1588    POP_EXCEPT                      
                        1590    JUMP_BACKWARD                   144 (to 1304)
                        1592    LOAD_GLOBAL                     38: requests
                        1602    LOAD_ATTR                       40: exceptions
                        1622    LOAD_ATTR                       46: ChunkedEncodingError
                        1642    CHECK_EXC_MATCH                 
                        1644    POP_JUMP_IF_FALSE               3 (to 1652)
                        1646    POP_TOP                         
                        1648    POP_EXCEPT                      
                        1650    JUMP_BACKWARD                   174 (to 1304)
                        1652    LOAD_GLOBAL                     38: requests
                        1662    LOAD_ATTR                       40: exceptions
                        1682    LOAD_ATTR                       48: ConnectionError
                        1702    CHECK_EXC_MATCH                 
                        1704    POP_JUMP_IF_FALSE               3 (to 1712)
                        1706    POP_TOP                         
                        1708    POP_EXCEPT                      
                        1710    JUMP_BACKWARD                   204 (to 1304)
                        1712    LOAD_GLOBAL                     38: requests
                        1722    LOAD_ATTR                       40: exceptions
                        1742    LOAD_ATTR                       50: RetryError
                        1762    CHECK_EXC_MATCH                 
                        1764    POP_JUMP_IF_FALSE               3 (to 1772)
                        1766    POP_TOP                         
                        1768    POP_EXCEPT                      
                        1770    JUMP_BACKWARD                   234 (to 1304)
                        1772    LOAD_GLOBAL                     10: StopProgram
                        1782    CHECK_EXC_MATCH                 
                        1784    POP_JUMP_IF_FALSE               2 (to 1790)
                        1786    POP_TOP                         
                        1788    RAISE_VARARGS                   0
                        1790    LOAD_GLOBAL                     52: BaseException
                        1800    CHECK_EXC_MATCH                 
                        1802    POP_JUMP_IF_FALSE               27 (to 1858)
                        1804    STORE_FAST                      11: _var_var_3
                        1806    PUSH_NULL                       
                        1808    LOAD_GLOBAL                     55: NULL + logging
                        1818    LOAD_FAST                       11: _var_var_3
                        1820    CALL                            1
                        1828    CALL                            0
                        1836    POP_TOP                         
                        1838    POP_EXCEPT                      
                        1840    LOAD_CONST                      0: None
                        1842    STORE_FAST                      11: _var_var_3
                        1844    DELETE_FAST                     11: _var_var_3
                        1846    JUMP_BACKWARD                   273 (to 1304)
                        1850    LOAD_CONST                      0: None
                        1852    STORE_FAST                      11: _var_var_3
                        1854    DELETE_FAST                     11: _var_var_3
                        1856    RERAISE                         1
                        1858    RERAISE                         0
                        1860    COPY                            3
                        1862    POP_EXCEPT                      
                        1864    RERAISE                         1
                        1866    PUSH_EXC_INFO                   
                        1868    LOAD_FAST                       0: self
                        1870    LOAD_ATTR                       14: multikeys
                        1890    POP_JUMP_IF_TRUE                18 (to 1928)
                        1892    LOAD_FAST                       0: self
                        1894    LOAD_ATTR                       35: _wait
                        1914    LOAD_CONST                      13: 1
                        1916    CALL                            1
                        1924    POP_TOP                         
                        1926    RERAISE                         0
                        1928    RERAISE                         0
                        1930    COPY                            3
                        1932    POP_EXCEPT                      
                        1934    RERAISE                         1
                        1936    PUSH_EXC_INFO                   
                        1938    PUSH_NULL                       
                        1940    LOAD_CONST                      16: '__pyarmor_exit_15581__'
                        1942    NOP                             
                        1944    LOAD_CONST                      3: b'<COAddr>\x07\x00\x00\x1av\x07\x00\x00\x00\x00\x00\x00\x00\x00\x00\x00\x00\x00\x00\x00'
                        1946    CALL                            1
                        1954    POP_TOP                         
                        1956    RERAISE                         0
                        1958    COPY                            3
                        1960    POP_EXCEPT                      
                        1962    RERAISE                         1
                        1964    PUSH_NULL                       
                        1966    LOAD_CONST                      16: '__pyarmor_exit_15581__'
                        1968    LOAD_CONST                      3: b'<COAddr>\x07\x00\x00\x1av\x07\x00\x00\x00\x00\x00\x00\x00\x00\x00\x00\x00\x00\x00\x00'
                        1970    BUILD_TUPLE                     1
                        1972    CALL_FUNCTION_EX                0
                        1974    POP_TOP                         
                        1976    RETURN_VALUE                    
                    [Exception Table]
                        28 to 184 -> 1936 [0] 
                        186 to 586 -> 1470 [0] 
                        586 to 644 -> 1936 [0] 
                        664 to 694 -> 1470 [0] 
                        694 to 752 -> 1936 [0] 
                        772 to 804 -> 1470 [0] 
                        806 to 864 -> 1936 [0] 
                        886 to 1304 -> 1368 [0] 
                        1304 to 1368 -> 1936 [0] 
                        1368 to 1460 -> 1464 [1] lasti
                        1460 to 1470 -> 1470 [0] 
                        1470 to 1528 -> 1860 [1] lasti
                        1528 to 1532 -> 1866 [0] 
                        1532 to 1588 -> 1860 [1] lasti
                        1588 to 1592 -> 1866 [0] 
                        1592 to 1648 -> 1860 [1] lasti
                        1648 to 1652 -> 1866 [0] 
                        1652 to 1708 -> 1860 [1] lasti
                        1708 to 1712 -> 1866 [0] 
                        1712 to 1768 -> 1860 [1] lasti
                        1768 to 1772 -> 1866 [0] 
                        1772 to 1806 -> 1860 [1] lasti
                        1806 to 1838 -> 1850 [1] lasti
                        1838 to 1850 -> 1866 [0] 
                        1850 to 1860 -> 1860 [1] lasti
                        1860 to 1866 -> 1866 [0] 
                        1866 to 1930 -> 1930 [1] lasti
                        1930 to 1936 -> 1936 [0] 
                        1936 to 1958 -> 1958 [1] lasti
                [Code]
                    File Name: <frozen program.modules.func.api.firefox>
                    Object Name: get_code
                    Qualified Name: FireFox.get_code
                    Arg Count: 4
                    Pos Only Arg Count: 0
                    KW Only Arg Count: 0
                    Stack Size: 8
                    Flags: 0x20000003 (CO_OPTIMIZED | CO_NEWLOCALS | CO_PYARMOR_OBFUSCATED)
                    [Names]
                        'rid'
                        'stop_thread'
                        'is_set'
                        'StopProgram'
                        'last_key'
                        'apikey'
                        'params'
                        '_request'
                        'text'
                        'split'
                        'Logs'
                        'PrintLog'
                        'config'
                        'lang'
                        '_wait'
                        'requests'
                        'exceptions'
                        'ConnectTimeout'
                        'ReadTimeout'
                        'ChunkedEncodingError'
                        'ConnectionError'
                        'RetryError'
                        'BaseException'
                        'logging'
                    [Locals+Names]
                        'self'
                        'account'
                        'timeout'
                        'retry'
                        '__assert_armored__'
                        '_var_var_7'
                        '_var_var_1'
                        '_var_var_4'
                        '_var_var_11'
                        '_var_var_12'
                        '_var_var_3'
                    [Constants]
                        None
                        '__pyarmor_assert_15582__'
                        '__pyarmor_enter_15583__'
                        b'<COAddr>\x05\x00\x00\x1a<\x04\x00\x00\x00\x00\x00\x00\x00\x00\x00\x00\x00\x00\x00\x00'
                        '__pyarmor_exit_15584__'
                        'getPhoneCode'   # b'\x81\xe5\x1d\x07\x03\xf2\xb1\xdc\x1e\xd9\x02\xc4i'
                        (
                            'act'
                            'token'
                            'pkey'
                        )
                        '|'
                        0
                        '1'
                        1
                        10
                        'times_up'
                        'сек'
                        (
                            'config'
                            'account'
                            'message'
                            'param'
                            'end'
                        )
                        'TIME_OUT'
                        'waiting_code_repeat'   # b"\x81\xf5\x19\x1a'\xf3\xb0\xd5$\xf9\x02\xc4i\xd3\xea\x80\x1fX\xba\xb3"
                    [Disassembly]
                        0       NOP                             
                        2       NOP                             
                        4       PUSH_NULL                       
                        6       LOAD_CONST                      2: '__pyarmor_enter_15583__'
                        8       LOAD_CONST                      3: b'<COAddr>\x05\x00\x00\x1a<\x04\x00\x00\x00\x00\x00\x00\x00\x00\x00\x00\x00\x00\x00\x00'
                        10      BUILD_TUPLE                     1
                        12      CALL_FUNCTION_EX                0
                        14      POP_TOP                         
                        16      RESUME                          0
                        18      NOP                             
                        20      NOP                             
                        22      NOP                             
                        24      NOP                             
                        26      NOP                             
                        28      LOAD_FAST                       0: self
                        30      LOAD_ATTR                       0: rid
                        50      POP_JUMP_IF_TRUE                11 (to 74)
                        52      NOP                             
                        54      LOAD_CONST                      0: None
                        56      NOP                             
                        58      NOP                             
                        60      JUMP_FORWARD                    537 (to 1138)
                        70      POP_TOP                         
                        72      RETURN_CONST                    0: None
                        74      NOP                             
                        76      NOP                             
                        78      LOAD_FAST                       0: self
                        80      LOAD_ATTR                       2: stop_thread
                        100     LOAD_ATTR                       5: is_set
                        120     CALL                            0
                        128     POP_JUMP_IF_FALSE               10 (to 150)
                        130     LOAD_GLOBAL                     7: NULL + StopProgram
                        140     CALL                            0
                        148     RAISE_VARARGS                   1
                        150     LOAD_FAST                       0: self
                        152     LOAD_ATTR                       8: last_key
                        172     POP_JUMP_IF_FALSE               12 (to 198)
                        174     LOAD_FAST                       0: self
                        176     LOAD_ATTR                       8: last_key
                        196     JUMP_FORWARD                    11 (to 220)
                        198     LOAD_FAST                       0: self
                        200     LOAD_ATTR                       10: apikey
                        220     STORE_FAST                      5: _var_var_7
                        222     PUSH_NULL                       
                        224     LOAD_CONST                      1: '__pyarmor_assert_15582__'
                        226     LOAD_CONST                      5: 'getPhoneCode'   # b'\x81\xe5\x1d\x07\x03\xf2\xb1\xdc\x1e\xd9\x02\xc4i'
                        228     CALL                            1
                        236     LOAD_FAST                       5: _var_var_7
                        238     LOAD_FAST                       0: self
                        240     LOAD_ATTR                       0: rid
                        260     LOAD_CONST                      6: ('act', 'token', 'pkey')
                        262     BUILD_CONST_KEY_MAP             3
                        264     LOAD_FAST                       0: self
                        266     STORE_ATTR                      6: params
                        276     LOAD_FAST                       0: self
                        278     LOAD_ATTR                       15: _request
                        298     CALL                            0
                        306     STORE_FAST                      6: _var_var_1
                        308     LOAD_FAST                       6: _var_var_1
                        310     LOAD_ATTR                       16: text
                        330     LOAD_ATTR                       19: split
                        350     LOAD_CONST                      7: '|'
                        352     CALL                            1
                        360     STORE_FAST                      7: _var_var_4
                        362     LOAD_FAST                       7: _var_var_4
                        364     LOAD_CONST                      8: 0
                        366     BINARY_SUBSCR                   
                        370     LOAD_CONST                      9: '1'
                        372     COMPARE_OP                      40 (==)
                        376     POP_JUMP_IF_FALSE               14 (to 406)
                        378     LOAD_FAST                       7: _var_var_4
                        380     LOAD_CONST                      10: 1
                        382     BINARY_SUBSCR                   
                        386     NOP                             
                        388     NOP                             
                        390     JUMP_FORWARD                    372 (to 1138)
                        394     CALL                            1
                        402     POP_TOP                         
                        404     RETURN_VALUE                    
                        406     LOAD_FAST                       3: retry
                        408     LOAD_CONST                      10: 1
                        410     BINARY_OP                       13 (+=)
                        414     STORE_FAST                      3: retry
                        416     LOAD_CONST                      11: 10
                        418     STORE_FAST                      8: _var_var_11
                        420     LOAD_FAST                       2: timeout
                        422     LOAD_FAST                       3: retry
                        424     LOAD_FAST                       8: _var_var_11
                        426     BINARY_OP                       5 (*)
                        430     BINARY_OP                       10 (-)
                        434     STORE_FAST                      9: _var_var_12
                        436     LOAD_FAST                       9: _var_var_12
                        438     LOAD_CONST                      8: 0
                        440     COMPARE_OP                      26 (<=)
                        444     POP_JUMP_IF_FALSE               60 (to 566)
                        446     LOAD_GLOBAL                     21: NULL + Logs
                        456     LOAD_ATTR                       22: PrintLog
                        476     LOAD_FAST                       0: self
                        478     LOAD_ATTR                       24: config
                        498     LOAD_FAST                       1: account
                        500     LOAD_FAST                       0: self
                        502     LOAD_ATTR                       26: lang
                        522     LOAD_CONST                      12: 'times_up'
                        524     BINARY_SUBSCR                   
                        528     LOAD_FAST                       2: timeout
                        530     LOAD_CONST                      13: 'сек'
                        532     KW_NAMES                        14: ('config', 'account', 'message', 'param', 'end')
                        534     CALL                            5
                        542     POP_TOP                         
                        544     NOP                             
                        546     LOAD_CONST                      15: 'TIME_OUT'
                        548     NOP                             
                        550     NOP                             
                        552     JUMP_FORWARD                    291 (to 1138)
                        562     POP_TOP                         
                        564     RETURN_CONST                    15: 'TIME_OUT'
                        566     LOAD_GLOBAL                     21: NULL + Logs
                        576     LOAD_ATTR                       22: PrintLog
                        596     LOAD_FAST                       0: self
                        598     LOAD_ATTR                       24: config
                        618     LOAD_FAST                       1: account
                        620     LOAD_FAST                       0: self
                        622     LOAD_ATTR                       26: lang
                        642     PUSH_NULL                       
                        644     LOAD_CONST                      1: '__pyarmor_assert_15582__'
                        646     LOAD_CONST                      16: 'waiting_code_repeat'   # b"\x81\xf5\x19\x1a'\xf3\xb0\xd5$\xf9\x02\xc4i\xd3\xea\x80\x1fX\xba\xb3"
                        648     CALL                            1
                        656     BINARY_SUBSCR                   
                        660     LOAD_FAST                       8: _var_var_11
                        662     LOAD_CONST                      13: 'сек'
                        664     KW_NAMES                        14: ('config', 'account', 'message', 'param', 'end')
                        666     CALL                            5
                        674     POP_TOP                         
                        676     LOAD_FAST                       0: self
                        678     LOAD_ATTR                       29: _wait
                        698     LOAD_FAST                       8: _var_var_11
                        700     CALL                            1
                        708     POP_TOP                         
                        710     NOP                             
                        712     JUMP_BACKWARD                   320 (to 76)
                        716     PUSH_EXC_INFO                   
                        718     LOAD_GLOBAL                     30: requests
                        728     LOAD_ATTR                       32: exceptions
                        748     LOAD_ATTR                       34: ConnectTimeout
                        768     CHECK_EXC_MATCH                 
                        770     POP_JUMP_IF_FALSE               3 (to 778)
                        772     POP_TOP                         
                        774     POP_EXCEPT                      
                        776     JUMP_BACKWARD                   33 (to 712)
                        778     LOAD_GLOBAL                     30: requests
                        788     LOAD_ATTR                       32: exceptions
                        808     LOAD_ATTR                       36: ReadTimeout
                        828     CHECK_EXC_MATCH                 
                        830     POP_JUMP_IF_FALSE               3 (to 838)
                        832     POP_TOP                         
                        834     POP_EXCEPT                      
                        836     JUMP_BACKWARD                   63 (to 712)
                        838     LOAD_GLOBAL                     30: requests
                        848     LOAD_ATTR                       32: exceptions
                        868     LOAD_ATTR                       38: ChunkedEncodingError
                        888     CHECK_EXC_MATCH                 
                        890     POP_JUMP_IF_FALSE               3 (to 898)
                        892     POP_TOP                         
                        894     POP_EXCEPT                      
                        896     JUMP_BACKWARD                   93 (to 712)
                        898     LOAD_GLOBAL                     30: requests
                        908     LOAD_ATTR                       32: exceptions
                        928     LOAD_ATTR                       40: ConnectionError
                        948     CHECK_EXC_MATCH                 
                        950     POP_JUMP_IF_FALSE               3 (to 958)
                        952     POP_TOP                         
                        954     POP_EXCEPT                      
                        956     JUMP_BACKWARD                   123 (to 712)
                        958     LOAD_GLOBAL                     30: requests
                        968     LOAD_ATTR                       32: exceptions
                        988     LOAD_ATTR                       42: RetryError
                        1008    CHECK_EXC_MATCH                 
                        1010    POP_JUMP_IF_FALSE               3 (to 1018)
                        1012    POP_TOP                         
                        1014    POP_EXCEPT                      
                        1016    JUMP_BACKWARD                   153 (to 712)
                        1018    LOAD_GLOBAL                     6: StopProgram
                        1028    CHECK_EXC_MATCH                 
                        1030    POP_JUMP_IF_FALSE               2 (to 1036)
                        1032    POP_TOP                         
                        1034    RAISE_VARARGS                   0
                        1036    LOAD_GLOBAL                     44: BaseException
                        1046    CHECK_EXC_MATCH                 
                        1048    POP_JUMP_IF_FALSE               26 (to 1102)
                        1050    STORE_FAST                      10: _var_var_3
                        1052    PUSH_NULL                       
                        1054    LOAD_GLOBAL                     47: NULL + logging
                        1064    LOAD_FAST                       10: _var_var_3
                        1066    CALL                            1
                        1074    CALL                            0
                        1082    POP_TOP                         
                        1084    POP_EXCEPT                      
                        1086    LOAD_CONST                      0: None
                        1088    STORE_FAST                      10: _var_var_3
                        1090    DELETE_FAST                     10: _var_var_3
                        1092    JUMP_BACKWARD                   191 (to 712)
                        1094    LOAD_CONST                      0: None
                        1096    STORE_FAST                      10: _var_var_3
                        1098    DELETE_FAST                     10: _var_var_3
                        1100    RERAISE                         1
                        1102    RERAISE                         0
                        1104    COPY                            3
                        1106    POP_EXCEPT                      
                        1108    RERAISE                         1
                        1110    PUSH_EXC_INFO                   
                        1112    PUSH_NULL                       
                        1114    LOAD_CONST                      4: '__pyarmor_exit_15584__'
                        1116    NOP                             
                        1118    LOAD_CONST                      3: b'<COAddr>\x05\x00\x00\x1a<\x04\x00\x00\x00\x00\x00\x00\x00\x00\x00\x00\x00\x00\x00\x00'
                        1120    CALL                            1
                        1128    POP_TOP                         
                        1130    RERAISE                         0
                        1132    COPY                            3
                        1134    POP_EXCEPT                      
                        1136    RERAISE                         1
                        1138    PUSH_NULL                       
                        1140    LOAD_CONST                      4: '__pyarmor_exit_15584__'
                        1142    LOAD_CONST                      3: b'<COAddr>\x05\x00\x00\x1a<\x04\x00\x00\x00\x00\x00\x00\x00\x00\x00\x00\x00\x00\x00\x00'
                        1144    BUILD_TUPLE                     1
                        1146    CALL_FUNCTION_EX                0
                        1148    POP_TOP                         
                        1150    RETURN_VALUE                    
                    [Exception Table]
                        28 to 52 -> 1110 [0] 
                        74 to 76 -> 1110 [0] 
                        78 to 386 -> 716 [0] 
                        406 to 544 -> 716 [0] 
                        566 to 710 -> 716 [0] 
                        710 to 716 -> 1110 [0] 
                        716 to 774 -> 1104 [1] lasti
                        774 to 778 -> 1110 [0] 
                        778 to 834 -> 1104 [1] lasti
                        834 to 838 -> 1110 [0] 
                        838 to 894 -> 1104 [1] lasti
                        894 to 898 -> 1110 [0] 
                        898 to 954 -> 1104 [1] lasti
                        954 to 958 -> 1110 [0] 
                        958 to 1014 -> 1104 [1] lasti
                        1014 to 1018 -> 1110 [0] 
                        1018 to 1052 -> 1104 [1] lasti
                        1052 to 1084 -> 1094 [1] lasti
                        1084 to 1094 -> 1110 [0] 
                        1094 to 1104 -> 1104 [1] lasti
                        1104 to 1110 -> 1110 [0] 
                        1110 to 1132 -> 1132 [1] lasti
                [Code]
                    File Name: <frozen program.modules.func.api.firefox>
                    Object Name: set_status
                    Qualified Name: FireFox.set_status
                    Arg Count: 3
                    Pos Only Arg Count: 0
                    KW Only Arg Count: 0
                    Stack Size: 8
                    Flags: 0x20000003 (CO_OPTIMIZED | CO_NEWLOCALS | CO_PYARMOR_OBFUSCATED)
                    [Names]
                        'rid'
                        'last_key'
                        'apikey'
                        'params'
                        '_request'
                        'text'
                        'split'
                        'Logs'
                        'PrintLog'
                        'config'
                        'Exception'
                    [Locals+Names]
                        'self'
                        'account'
                        'status'
                        '__assert_armored__'
                        '_var_var_7'
                        '_var_var_1'
                        '_var_var_4'
                        '_var_var_3'
                    [Constants]
                        None
                        '__pyarmor_assert_15585__'
                        '__pyarmor_enter_15586__'
                        b'<COAddr>\x05\x00\x00\x1a\x9e\x03\x00\x00\x00\x00\x00\x00\x00\x00\x00\x00\x00\x00\x00\x00'
                        '__pyarmor_exit_15587__'
                        'blacklist'   # b'\x81\xe0\x14\x120\xf1\xb2\xdb\x08\xee'
                        'addBlack'
                        'number is banned'   # b'\x81\xec\r\x1e1\xff\xac\x92\x12\xe9M\xc2m\xe2\xf6\x80\x0b'
                        (
                            'act'
                            'token'
                            'pkey'
                            'reason'
                        )
                        '|'
                        0
                        '1'
                        'Success: add to blacklist'   # b'\x81\xd1\r\x100\xff\xad\xc1A\xba\x0c\xc4h\xac\xec\x8aO_\xb7\xa6\xa9\xc0B\xc5\x16{'
                        (
                            'config'
                            'account'
                            'message'
                        )
                        'Error: add to blacklist'   # b'\x81\xc7\n\x01<\xe8\xe4\x92\x1a\xfe\t\x80x\xe3\xb8\x87\x03\\\xb8\xac\xa6\xc2]\xd8'
                        'release'
                        'setRel'
                        (
                            'act'
                            'token'
                            'pkey'
                        )
                        'Success: number release'   # b'\x81\xd1\r\x100\xff\xad\xc1A\xba\x03\xd5a\xee\xfd\x97OO\xbe\xab\xaf\xca]\xc9'
                        'Error: number release'   # b'\x81\xc7\n\x01<\xe8\xe4\x92\x15\xef\x00\xc2i\xfe\xb8\x97\nQ\xbe\xa6\xb9\xce'
                        'Error set status:'   # b'\x81\xc7\n\x01<\xe8\xfe\xc1\x1e\xeeM\xd3x\xed\xec\x90\x1c\x07'
                        (
                            'config'
                            'account'
                            'message'
                            'end'
                        )
                    [Disassembly]
                        0       NOP                             
                        2       NOP                             
                        4       PUSH_NULL                       
                        6       LOAD_CONST                      2: '__pyarmor_enter_15586__'
                        8       LOAD_CONST                      3: b'<COAddr>\x05\x00\x00\x1a\x9e\x03\x00\x00\x00\x00\x00\x00\x00\x00\x00\x00\x00\x00\x00\x00'
                        10      BUILD_TUPLE                     1
                        12      CALL_FUNCTION_EX                0
                        14      POP_TOP                         
                        16      RESUME                          0
                        18      NOP                             
                        20      NOP                             
                        22      NOP                             
                        24      NOP                             
                        26      NOP                             
                        28      NOP                             
                        30      LOAD_FAST                       0: self
                        32      LOAD_ATTR                       0: rid
                        52      POP_JUMP_IF_TRUE                11 (to 76)
                        54      NOP                             
                        56      LOAD_CONST                      0: None
                        58      NOP                             
                        60      NOP                             
                        62      JUMP_FORWARD                    457 (to 980)
                        72      POP_TOP                         
                        74      RETURN_CONST                    0: None
                        76      LOAD_FAST                       0: self
                        78      LOAD_ATTR                       2: last_key
                        98      POP_JUMP_IF_FALSE               12 (to 124)
                        100     LOAD_FAST                       0: self
                        102     LOAD_ATTR                       2: last_key
                        122     JUMP_FORWARD                    11 (to 146)
                        124     LOAD_FAST                       0: self
                        126     LOAD_ATTR                       4: apikey
                        146     STORE_FAST                      4: _var_var_7
                        148     LOAD_FAST                       2: status
                        150     PUSH_NULL                       
                        152     LOAD_CONST                      1: '__pyarmor_assert_15585__'
                        154     LOAD_CONST                      5: 'blacklist'   # b'\x81\xe0\x14\x120\xf1\xb2\xdb\x08\xee'
                        156     CALL                            1
                        164     COMPARE_OP                      40 (==)
                        168     POP_JUMP_IF_FALSE               160 (to 490)
                        170     LOAD_CONST                      6: 'addBlack'
                        172     LOAD_FAST                       4: _var_var_7
                        174     LOAD_FAST                       0: self
                        176     LOAD_ATTR                       0: rid
                        196     PUSH_NULL                       
                        198     LOAD_CONST                      1: '__pyarmor_assert_15585__'
                        200     LOAD_CONST                      7: 'number is banned'   # b'\x81\xec\r\x1e1\xff\xac\x92\x12\xe9M\xc2m\xe2\xf6\x80\x0b'
                        202     CALL                            1
                        210     LOAD_CONST                      8: ('act', 'token', 'pkey', 'reason')
                        212     BUILD_CONST_KEY_MAP             4
                        214     LOAD_FAST                       0: self
                        216     STORE_ATTR                      3: params
                        226     LOAD_FAST                       0: self
                        228     LOAD_ATTR                       9: _request
                        248     CALL                            0
                        256     STORE_FAST                      5: _var_var_1
                        258     LOAD_FAST                       5: _var_var_1
                        260     LOAD_ATTR                       10: text
                        280     LOAD_ATTR                       13: split
                        300     LOAD_CONST                      9: '|'
                        302     CALL                            1
                        310     STORE_FAST                      6: _var_var_4
                        312     LOAD_FAST                       6: _var_var_4
                        314     LOAD_CONST                      10: 0
                        316     BINARY_SUBSCR                   
                        320     LOAD_CONST                      11: '1'
                        322     COMPARE_OP                      40 (==)
                        326     POP_JUMP_IF_FALSE               41 (to 410)
                        328     LOAD_GLOBAL                     15: NULL + Logs
                        338     LOAD_ATTR                       16: PrintLog
                        358     LOAD_FAST                       0: self
                        360     LOAD_ATTR                       18: config
                        380     LOAD_FAST                       1: account
                        382     PUSH_NULL                       
                        384     LOAD_CONST                      1: '__pyarmor_assert_15585__'
                        386     LOAD_CONST                      12: 'Success: add to blacklist'   # b'\x81\xd1\r\x100\xff\xad\xc1A\xba\x0c\xc4h\xac\xec\x8aO_\xb7\xa6\xa9\xc0B\xc5\x16{'
                        388     CALL                            1
                        396     KW_NAMES                        13: ('config', 'account', 'message')
                        398     CALL                            3
                        406     POP_TOP                         
                        408     JUMP_FORWARD                    40 (to 490)
                        410     LOAD_GLOBAL                     15: NULL + Logs
                        420     LOAD_ATTR                       16: PrintLog
                        440     LOAD_FAST                       0: self
                        442     LOAD_ATTR                       18: config
                        462     LOAD_FAST                       1: account
                        464     PUSH_NULL                       
                        466     LOAD_CONST                      1: '__pyarmor_assert_15585__'
                        468     LOAD_CONST                      14: 'Error: add to blacklist'   # b'\x81\xc7\n\x01<\xe8\xe4\x92\x1a\xfe\t\x80x\xe3\xb8\x87\x03\\\xb8\xac\xa6\xc2]\xd8'
                        470     CALL                            1
                        478     KW_NAMES                        13: ('config', 'account', 'message')
                        480     CALL                            3
                        488     POP_TOP                         
                        490     LOAD_FAST                       2: status
                        492     LOAD_CONST                      15: 'release'
                        494     COMPARE_OP                      40 (==)
                        498     POP_JUMP_IF_FALSE               153 (to 806)
                        500     LOAD_CONST                      16: 'setRel'
                        502     LOAD_FAST                       4: _var_var_7
                        504     LOAD_FAST                       0: self
                        506     LOAD_ATTR                       0: rid
                        526     LOAD_CONST                      17: ('act', 'token', 'pkey')
                        528     BUILD_CONST_KEY_MAP             3
                        530     LOAD_FAST                       0: self
                        532     STORE_ATTR                      3: params
                        542     LOAD_FAST                       0: self
                        544     LOAD_ATTR                       9: _request
                        564     CALL                            0
                        572     STORE_FAST                      5: _var_var_1
                        574     LOAD_FAST                       5: _var_var_1
                        576     LOAD_ATTR                       10: text
                        596     LOAD_ATTR                       13: split
                        616     LOAD_CONST                      9: '|'
                        618     CALL                            1
                        626     STORE_FAST                      6: _var_var_4
                        628     LOAD_FAST                       6: _var_var_4
                        630     LOAD_CONST                      10: 0
                        632     BINARY_SUBSCR                   
                        636     LOAD_CONST                      11: '1'
                        638     COMPARE_OP                      40 (==)
                        642     POP_JUMP_IF_FALSE               41 (to 726)
                        644     LOAD_GLOBAL                     15: NULL + Logs
                        654     LOAD_ATTR                       16: PrintLog
                        674     LOAD_FAST                       0: self
                        676     LOAD_ATTR                       18: config
                        696     LOAD_FAST                       1: account
                        698     PUSH_NULL                       
                        700     LOAD_CONST                      1: '__pyarmor_assert_15585__'
                        702     LOAD_CONST                      18: 'Success: number release'   # b'\x81\xd1\r\x100\xff\xad\xc1A\xba\x03\xd5a\xee\xfd\x97OO\xbe\xab\xaf\xca]\xc9'
                        704     CALL                            1
                        712     KW_NAMES                        13: ('config', 'account', 'message')
                        714     CALL                            3
                        722     POP_TOP                         
                        724     JUMP_FORWARD                    40 (to 806)
                        726     LOAD_GLOBAL                     15: NULL + Logs
                        736     LOAD_ATTR                       16: PrintLog
                        756     LOAD_FAST                       0: self
                        758     LOAD_ATTR                       18: config
                        778     LOAD_FAST                       1: account
                        780     PUSH_NULL                       
                        782     LOAD_CONST                      1: '__pyarmor_assert_15585__'
                        784     LOAD_CONST                      19: 'Error: number release'   # b'\x81\xc7\n\x01<\xe8\xe4\x92\x15\xef\x00\xc2i\xfe\xb8\x97\nQ\xbe\xa6\xb9\xce'
                        786     CALL                            1
                        794     KW_NAMES                        13: ('config', 'account', 'message')
                        796     CALL                            3
                        804     POP_TOP                         
                        806     LOAD_CONST                      0: None
                        808     NOP                             
                        810     NOP                             
                        812     NOP                             
                        814     JUMP_FORWARD                    82 (to 980)
                        822     POP_TOP                         
                        824     RETURN_CONST                    0: None
                        826     PUSH_EXC_INFO                   
                        828     LOAD_GLOBAL                     20: Exception
                        838     CHECK_EXC_MATCH                 
                        840     POP_JUMP_IF_FALSE               51 (to 944)
                        842     STORE_FAST                      7: _var_var_3
                        844     LOAD_GLOBAL                     15: NULL + Logs
                        854     LOAD_ATTR                       16: PrintLog
                        874     LOAD_FAST                       0: self
                        876     LOAD_ATTR                       18: config
                        896     LOAD_FAST                       1: account
                        898     PUSH_NULL                       
                        900     LOAD_CONST                      1: '__pyarmor_assert_15585__'
                        902     LOAD_CONST                      20: 'Error set status:'   # b'\x81\xc7\n\x01<\xe8\xfe\xc1\x1e\xeeM\xd3x\xed\xec\x90\x1c\x07'
                        904     CALL                            1
                        912     LOAD_FAST                       7: _var_var_3
                        914     KW_NAMES                        21: ('config', 'account', 'message', 'end')
                        916     CALL                            4
                        924     POP_TOP                         
                        926     POP_EXCEPT                      
                        928     LOAD_CONST                      0: None
                        930     STORE_FAST                      7: _var_var_3
                        932     DELETE_FAST                     7: _var_var_3
                        934     JUMP_BACKWARD                   65 (to 806)
                        936     LOAD_CONST                      0: None
                        938     STORE_FAST                      7: _var_var_3
                        940     DELETE_FAST                     7: _var_var_3
                        942     RERAISE                         1
                        944     RERAISE                         0
                        946     COPY                            3
                        948     POP_EXCEPT                      
                        950     RERAISE                         1
                        952     PUSH_EXC_INFO                   
                        954     PUSH_NULL                       
                        956     LOAD_CONST                      4: '__pyarmor_exit_15587__'
                        958     NOP                             
                        960     LOAD_CONST                      3: b'<COAddr>\x05\x00\x00\x1a\x9e\x03\x00\x00\x00\x00\x00\x00\x00\x00\x00\x00\x00\x00\x00\x00'
                        962     CALL                            1
                        970     POP_TOP                         
                        972     RERAISE                         0
                        974     COPY                            3
                        976     POP_EXCEPT                      
                        978     RERAISE                         1
                        980     PUSH_NULL                       
                        982     LOAD_CONST                      4: '__pyarmor_exit_15587__'
                        984     LOAD_CONST                      3: b'<COAddr>\x05\x00\x00\x1a\x9e\x03\x00\x00\x00\x00\x00\x00\x00\x00\x00\x00\x00\x00\x00\x00'
                        986     BUILD_TUPLE                     1
                        988     CALL_FUNCTION_EX                0
                        990     POP_TOP                         
                        992     RETURN_VALUE                    
                    [Exception Table]
                        30 to 54 -> 826 [0] 
                        76 to 806 -> 826 [0] 
                        826 to 844 -> 946 [1] lasti
                        844 to 926 -> 936 [1] lasti
                        926 to 936 -> 952 [0] 
                        936 to 946 -> 946 [1] lasti
                        946 to 952 -> 952 [0] 
                        952 to 974 -> 974 [1] lasti
                [Code]
                    File Name: <frozen program.modules.func.api.firefox>
                    Object Name: return_status
                    Qualified Name: FireFox.return_status
                    Arg Count: 3
                    Pos Only Arg Count: 0
                    KW Only Arg Count: 0
                    Stack Size: 8
                    Flags: 0x20000003 (CO_OPTIMIZED | CO_NEWLOCALS | CO_PYARMOR_OBFUSCATED)
                    [Names]
                        'rid'
                        'api_return'
                        'last_key'
                        'apikey'
                        'params'
                        '_request'
                        'text'
                        'split'
                        'Logs'
                        'PrintLog'
                        'config'
                        'Exception'
                    [Locals+Names]
                        'self'
                        'account'
                        'status'
                        '__assert_armored__'
                        '_var_var_7'
                        '_var_var_1'
                        '_var_var_4'
                        '_var_var_10'
                        '_var_var_3'
                    [Constants]
                        None
                        '__pyarmor_assert_15588__'
                        '__pyarmor_enter_15589__'
                        b'<COAddr>\x07\x00\x00\x1a"\x03\x00\x00\x00\x00\x00\x00\x00\x00\x00\x00\x00\x00\x00\x00'
                        '__pyarmor_exit_15590__'
                        'apiReturn'   # b'\x81\xe3\x08\x1a\x01\xff\xaa\xc7\t\xf4'
                        (
                            'act'
                            'token'
                            'pkey'
                            'remark'
                        )
                        '|'
                        1
                        '-1'
                        'Token does not exist'   # b'\x81\xd6\x17\x186\xf4\xfe\xd6\x14\xff\x1e\x80b\xe3\xec\xc5\nE\xb2\xb4\xbe'
                        '-2'
                        'The pkey invalid'   # b'\x81\xd6\x10\x16s\xea\xb5\xd7\x02\xba\x04\xcez\xed\xf4\x8c\x0b'
                        '-3'
                        'The remark cannot be empty'   # b'\x81\xd6\x10\x16s\xe8\xbb\xdf\x1a\xe8\x06\x80o\xed\xf6\x8b\x00I\xfb\xa5\xaf\x8bK\xc1\x15{\xba'
                        '-4'
                        'Mobile number is unavailable, please give up its work'   # b"\x81\xcf\x17\x11:\xf6\xbb\x92\x15\xef\x00\xc2i\xfe\xb8\x8c\x1c\x1d\xae\xa9\xab\xddO\xc5\tn\xa1P\x05\xfd^\xf56W!\x1e\x9d\x8a\xb3'\x0e\xec\xb8H\xcd\x98\x06S$\xadA\xf4\x95{"
                        '-5'
                        'You dont have permission'   # b'\x81\xdb\x17\x06s\xfe\xb1\xdc\x0f\xba\x05\xc1z\xe9\xb8\x95\nO\xb6\xae\xb9\xd8G\xc3\x0b'
                        ''
                        'The SMS service error:'   # b'\x81\xd6\x10\x16s\xc9\x93\xe1[\xe9\x08\xd2z\xe5\xfb\x80OX\xa9\xb5\xa5\xd9\x14'
                        (
                            'config'
                            'account'
                            'message'
                            'end'
                        )
                        'Ignoring the response from the api of the sms service, the response code:'   # b'\x81\xcb\x1f\x1d<\xe8\xb7\xdc\x1c\xba\x19\xc8i\xac\xea\x80\x1cM\xb4\xa9\xb9\xce\x0e\xca\x17`\xae\x1c\x14\xb9\x1b\xa5;B)M\x97\xcc\xf4:\x10\xec\xb8N\xd0\xcbOT2\xff@\xf2\x84uJ\xad#\xe3\x9e]\nN"CXF\x16\x86\x9d4\xe3\xbb\x968'
                        0
                        'Error return_status:'   # b'\x81\xc7\n\x01<\xe8\xfe\xc0\x1e\xee\x18\xd2b\xd3\xeb\x91\x0eI\xae\xb4\xf0'
                    [Disassembly]
                        0       NOP                             
                        2       NOP                             
                        4       PUSH_NULL                       
                        6       LOAD_CONST                      2: '__pyarmor_enter_15589__'
                        8       LOAD_CONST                      3: b'<COAddr>\x07\x00\x00\x1a"\x03\x00\x00\x00\x00\x00\x00\x00\x00\x00\x00\x00\x00\x00\x00'
                        10      BUILD_TUPLE                     1
                        12      CALL_FUNCTION_EX                0
                        14      POP_TOP                         
                        16      RESUME                          0
                        18      NOP                             
                        20      NOP                             
                        22      NOP                             
                        24      NOP                             
                        26      NOP                             
                        28      NOP                             
                        30      LOAD_FAST                       0: self
                        32      LOAD_ATTR                       0: rid
                        52      POP_JUMP_IF_TRUE                11 (to 76)
                        54      NOP                             
                        56      LOAD_CONST                      0: None
                        58      NOP                             
                        60      NOP                             
                        62      JUMP_FORWARD                    395 (to 856)
                        72      POP_TOP                         
                        74      RETURN_CONST                    0: None
                        76      LOAD_FAST                       0: self
                        78      LOAD_ATTR                       2: api_return
                        98      POP_JUMP_IF_TRUE                11 (to 122)
                        100     NOP                             
                        102     LOAD_CONST                      0: None
                        104     NOP                             
                        106     NOP                             
                        108     JUMP_FORWARD                    372 (to 856)
                        118     POP_TOP                         
                        120     RETURN_CONST                    0: None
                        122     LOAD_FAST                       0: self
                        124     LOAD_ATTR                       4: last_key
                        144     POP_JUMP_IF_FALSE               12 (to 170)
                        146     LOAD_FAST                       0: self
                        148     LOAD_ATTR                       4: last_key
                        168     JUMP_FORWARD                    11 (to 192)
                        170     LOAD_FAST                       0: self
                        172     LOAD_ATTR                       6: apikey
                        192     STORE_FAST                      4: _var_var_7
                        194     PUSH_NULL                       
                        196     LOAD_CONST                      1: '__pyarmor_assert_15588__'
                        198     LOAD_CONST                      5: 'apiReturn'   # b'\x81\xe3\x08\x1a\x01\xff\xaa\xc7\t\xf4'
                        200     CALL                            1
                        208     LOAD_FAST                       4: _var_var_7
                        210     LOAD_FAST                       0: self
                        212     LOAD_ATTR                       0: rid
                        232     LOAD_FAST                       2: status
                        234     LOAD_CONST                      6: ('act', 'token', 'pkey', 'remark')
                        236     BUILD_CONST_KEY_MAP             4
                        238     LOAD_FAST                       0: self
                        240     STORE_ATTR                      4: params
                        250     LOAD_FAST                       0: self
                        252     LOAD_ATTR                       11: _request
                        272     CALL                            0
                        280     STORE_FAST                      5: _var_var_1
                        282     LOAD_FAST                       5: _var_var_1
                        284     LOAD_ATTR                       12: text
                        304     LOAD_ATTR                       15: split
                        324     LOAD_CONST                      7: '|'
                        326     CALL                            1
                        334     STORE_FAST                      6: _var_var_4
                        336     NOP                             
                        338     LOAD_FAST                       6: _var_var_4
                        340     LOAD_CONST                      8: 1
                        342     BINARY_SUBSCR                   
                        346     LOAD_CONST                      9: '-1'
                        348     COMPARE_OP                      40 (==)
                        352     POP_JUMP_IF_FALSE               8 (to 370)
                        354     PUSH_NULL                       
                        356     LOAD_CONST                      1: '__pyarmor_assert_15588__'
                        358     LOAD_CONST                      10: 'Token does not exist'   # b'\x81\xd6\x17\x186\xf4\xfe\xd6\x14\xff\x1e\x80b\xe3\xec\xc5\nE\xb2\xb4\xbe'
                        360     CALL                            1
                        368     STORE_FAST                      7: _var_var_10
                        370     LOAD_FAST                       6: _var_var_4
                        372     LOAD_CONST                      8: 1
                        374     BINARY_SUBSCR                   
                        378     LOAD_CONST                      11: '-2'
                        380     COMPARE_OP                      40 (==)
                        384     POP_JUMP_IF_FALSE               8 (to 402)
                        386     PUSH_NULL                       
                        388     LOAD_CONST                      1: '__pyarmor_assert_15588__'
                        390     LOAD_CONST                      12: 'The pkey invalid'   # b'\x81\xd6\x10\x16s\xea\xb5\xd7\x02\xba\x04\xcez\xed\xf4\x8c\x0b'
                        392     CALL                            1
                        400     STORE_FAST                      7: _var_var_10
                        402     LOAD_FAST                       6: _var_var_4
                        404     LOAD_CONST                      8: 1
                        406     BINARY_SUBSCR                   
                        410     LOAD_CONST                      13: '-3'
                        412     COMPARE_OP                      40 (==)
                        416     POP_JUMP_IF_FALSE               8 (to 434)
                        418     PUSH_NULL                       
                        420     LOAD_CONST                      1: '__pyarmor_assert_15588__'
                        422     LOAD_CONST                      14: 'The remark cannot be empty'   # b'\x81\xd6\x10\x16s\xe8\xbb\xdf\x1a\xe8\x06\x80o\xed\xf6\x8b\x00I\xfb\xa5\xaf\x8bK\xc1\x15{\xba'
                        424     CALL                            1
                        432     STORE_FAST                      7: _var_var_10
                        434     LOAD_FAST                       6: _var_var_4
                        436     LOAD_CONST                      8: 1
                        438     BINARY_SUBSCR                   
                        442     LOAD_CONST                      15: '-4'
                        444     COMPARE_OP                      40 (==)
                        448     POP_JUMP_IF_FALSE               8 (to 466)
                        450     PUSH_NULL                       
                        452     LOAD_CONST                      1: '__pyarmor_assert_15588__'
                        454     LOAD_CONST                      16: 'Mobile number is unavailable, please give up its work'   # b"\x81\xcf\x17\x11:\xf6\xbb\x92\x15\xef\x00\xc2i\xfe\xb8\x8c\x1c\x1d\xae\xa9\xab\xddO\xc5\tn\xa1P\x05\xfd^\xf56W!\x1e\x9d\x8a\xb3'\x0e\xec\xb8H\xcd\x98\x06S$\xadA\xf4\x95{"
                        456     CALL                            1
                        464     STORE_FAST                      7: _var_var_10
                        466     LOAD_FAST                       6: _var_var_4
                        468     LOAD_CONST                      8: 1
                        470     BINARY_SUBSCR                   
                        474     LOAD_CONST                      17: '-5'
                        476     COMPARE_OP                      40 (==)
                        480     POP_JUMP_IF_FALSE               8 (to 498)
                        482     PUSH_NULL                       
                        484     LOAD_CONST                      1: '__pyarmor_assert_15588__'
                        486     LOAD_CONST                      18: 'You dont have permission'   # b'\x81\xdb\x17\x06s\xfe\xb1\xdc\x0f\xba\x05\xc1z\xe9\xb8\x95\nO\xb6\xae\xb9\xd8G\xc3\x0b'
                        488     CALL                            1
                        496     STORE_FAST                      7: _var_var_10
                        498     LOAD_GLOBAL                     17: NULL + Logs
                        508     LOAD_ATTR                       18: PrintLog
                        528     LOAD_FAST                       0: self
                        530     LOAD_ATTR                       20: config
                        550     LOAD_CONST                      19: ''
                        552     PUSH_NULL                       
                        554     LOAD_CONST                      1: '__pyarmor_assert_15588__'
                        556     LOAD_CONST                      20: 'The SMS service error:'   # b'\x81\xd6\x10\x16s\xc9\x93\xe1[\xe9\x08\xd2z\xe5\xfb\x80OX\xa9\xb5\xa5\xd9\x14'
                        558     CALL                            1
                        566     LOAD_FAST_CHECK                 7: _var_var_10
                        568     KW_NAMES                        21: ('config', 'account', 'message', 'end')
                        570     CALL                            4
                        578     POP_TOP                         
                        580     LOAD_CONST                      0: None
                        582     NOP                             
                        584     NOP                             
                        586     NOP                             
                        588     JUMP_FORWARD                    133 (to 856)
                        596     POP_TOP                         
                        598     RETURN_CONST                    0: None
                        600     PUSH_EXC_INFO                   
                        602     POP_TOP                         
                        604     LOAD_GLOBAL                     17: NULL + Logs
                        614     LOAD_ATTR                       18: PrintLog
                        634     LOAD_FAST                       0: self
                        636     LOAD_ATTR                       20: config
                        656     LOAD_CONST                      19: ''
                        658     PUSH_NULL                       
                        660     LOAD_CONST                      1: '__pyarmor_assert_15588__'
                        662     LOAD_CONST                      22: 'Ignoring the response from the api of the sms service, the response code:'   # b'\x81\xcb\x1f\x1d<\xe8\xb7\xdc\x1c\xba\x19\xc8i\xac\xea\x80\x1cM\xb4\xa9\xb9\xce\x0e\xca\x17`\xae\x1c\x14\xb9\x1b\xa5;B)M\x97\xcc\xf4:\x10\xec\xb8N\xd0\xcbOT2\xff@\xf2\x84uJ\xad#\xe3\x9e]\nN"CXF\x16\x86\x9d4\xe3\xbb\x968'
                        664     CALL                            1
                        672     LOAD_FAST                       6: _var_var_4
                        674     LOAD_CONST                      23: 0
                        676     BINARY_SUBSCR                   
                        680     KW_NAMES                        21: ('config', 'account', 'message', 'end')
                        682     CALL                            4
                        690     POP_TOP                         
                        692     POP_EXCEPT                      
                        694     JUMP_BACKWARD                   58 (to 580)
                        696     COPY                            3
                        698     POP_EXCEPT                      
                        700     RERAISE                         1
                        702     PUSH_EXC_INFO                   
                        704     LOAD_GLOBAL                     22: Exception
                        714     CHECK_EXC_MATCH                 
                        716     POP_JUMP_IF_FALSE               51 (to 820)
                        718     STORE_FAST                      8: _var_var_3
                        720     LOAD_GLOBAL                     17: NULL + Logs
                        730     LOAD_ATTR                       18: PrintLog
                        750     LOAD_FAST                       0: self
                        752     LOAD_ATTR                       20: config
                        772     LOAD_FAST                       1: account
                        774     PUSH_NULL                       
                        776     LOAD_CONST                      1: '__pyarmor_assert_15588__'
                        778     LOAD_CONST                      24: 'Error return_status:'   # b'\x81\xc7\n\x01<\xe8\xfe\xc0\x1e\xee\x18\xd2b\xd3\xeb\x91\x0eI\xae\xb4\xf0'
                        780     CALL                            1
                        788     LOAD_FAST                       8: _var_var_3
                        790     KW_NAMES                        21: ('config', 'account', 'message', 'end')
                        792     CALL                            4
                        800     POP_TOP                         
                        802     POP_EXCEPT                      
                        804     LOAD_CONST                      0: None
                        806     STORE_FAST                      8: _var_var_3
                        808     DELETE_FAST                     8: _var_var_3
                        810     JUMP_BACKWARD                   116 (to 580)
                        812     LOAD_CONST                      0: None
                        814     STORE_FAST                      8: _var_var_3
                        816     DELETE_FAST                     8: _var_var_3
                        818     RERAISE                         1
                        820     RERAISE                         0
                        822     COPY                            3
                        824     POP_EXCEPT                      
                        826     RERAISE                         1
                        828     PUSH_EXC_INFO                   
                        830     PUSH_NULL                       
                        832     LOAD_CONST                      4: '__pyarmor_exit_15590__'
                        834     NOP                             
                        836     LOAD_CONST                      3: b'<COAddr>\x07\x00\x00\x1a"\x03\x00\x00\x00\x00\x00\x00\x00\x00\x00\x00\x00\x00\x00\x00'
                        838     CALL                            1
                        846     POP_TOP                         
                        848     RERAISE                         0
                        850     COPY                            3
                        852     POP_EXCEPT                      
                        854     RERAISE                         1
                        856     PUSH_NULL                       
                        858     LOAD_CONST                      4: '__pyarmor_exit_15590__'
                        860     LOAD_CONST                      3: b'<COAddr>\x07\x00\x00\x1a"\x03\x00\x00\x00\x00\x00\x00\x00\x00\x00\x00\x00\x00\x00\x00'
                        862     BUILD_TUPLE                     1
                        864     CALL_FUNCTION_EX                0
                        866     POP_TOP                         
                        868     RETURN_VALUE                    
                    [Exception Table]
                        30 to 54 -> 702 [0] 
                        76 to 100 -> 702 [0] 
                        122 to 336 -> 702 [0] 
                        338 to 580 -> 600 [0] 
                        600 to 692 -> 696 [1] lasti
                        692 to 702 -> 702 [0] 
                        702 to 720 -> 822 [1] lasti
                        720 to 802 -> 812 [1] lasti
                        802 to 812 -> 828 [0] 
                        812 to 822 -> 822 [1] lasti
                        822 to 828 -> 828 [0] 
                        828 to 850 -> 850 [1] lasti
                '__pyarmor_exit_15563__'
                (
                    10
                )
                (
                    0
                    None
                )
                (
                    0
                )
            [Disassembly]
                0       NOP                             
                2       LOAD_NAME                       0: __name__
                4       STORE_NAME                      1: __module__
                6       LOAD_CONST                      0: 'FireFox'
                8       STORE_NAME                      2: __qualname__
                10      NOP                             
                12      PUSH_NULL                       
                14      LOAD_CONST                      2: '__pyarmor_enter_15562__'
                16      LOAD_CONST                      3: b'<COAddr>\x07\x00\x00"d\x00\x00\x00\x00\x00\x00\x00\x00\x00\x00\x00\x00\x00\x00\x00'
                18      BUILD_TUPLE                     1
                20      CALL_FUNCTION_EX                0
                22      POP_TOP                         
                24      RESUME                          0
                26      NOP                             
                28      NOP                             
                30      NOP                             
                32      NOP                             
                34      NOP                             
                36      LOAD_CONST                      4: '1000'
                38      LOAD_CONST                      5: False
                40      PUSH_NULL                       
                42      LOAD_NAME                       4: Event
                44      CALL                            0
                52      BUILD_TUPLE                     3
                54      LOAD_CONST                      6: <CODE> __init__
                56      MAKE_FUNCTION                   1
                58      STORE_NAME                      5: __init__
                60      LOAD_CONST                      7: <CODE> _request
                62      MAKE_FUNCTION                   0
                64      STORE_NAME                      6: _request
                66      LOAD_CONST                      17: (10,)
                68      LOAD_CONST                      8: <CODE> _wait
                70      MAKE_FUNCTION                   1
                72      STORE_NAME                      7: _wait
                74      LOAD_CONST                      9: <CODE> get_balance
                76      MAKE_FUNCTION                   0
                78      STORE_NAME                      8: get_balance
                80      LOAD_CONST                      10: <CODE> get_country
                82      MAKE_FUNCTION                   0
                84      STORE_NAME                      9: get_country
                86      LOAD_CONST                      18: (0, None)
                88      LOAD_CONST                      12: <CODE> order_number
                90      MAKE_FUNCTION                   1
                92      STORE_NAME                      10: order_number
                94      LOAD_CONST                      19: (0,)
                96      LOAD_CONST                      13: <CODE> get_code
                98      MAKE_FUNCTION                   1
                100     STORE_NAME                      11: get_code
                102     LOAD_CONST                      14: <CODE> set_status
                104     MAKE_FUNCTION                   0
                106     STORE_NAME                      12: set_status
                108     LOAD_CONST                      15: <CODE> return_status
                110     MAKE_FUNCTION                   0
                112     STORE_NAME                      13: return_status
                114     LOAD_CONST                      11: None
                116     NOP                             
                118     NOP                             
                120     NOP                             
                122     JUMP_FORWARD                    19 (to 162)
                130     POP_TOP                         
                132     RETURN_CONST                    11: None
                134     PUSH_EXC_INFO                   
                136     PUSH_NULL                       
                138     LOAD_CONST                      16: '__pyarmor_exit_15563__'
                140     NOP                             
                142     LOAD_CONST                      3: b'<COAddr>\x07\x00\x00"d\x00\x00\x00\x00\x00\x00\x00\x00\x00\x00\x00\x00\x00\x00\x00'
                144     CALL                            1
                152     POP_TOP                         
                154     RERAISE                         0
                156     COPY                            3
                158     POP_EXCEPT                      
                160     RERAISE                         1
                162     PUSH_NULL                       
                164     LOAD_CONST                      16: '__pyarmor_exit_15563__'
                166     LOAD_CONST                      3: b'<COAddr>\x07\x00\x00"d\x00\x00\x00\x00\x00\x00\x00\x00\x00\x00\x00\x00\x00\x00\x00'
                168     BUILD_TUPLE                     1
                170     CALL_FUNCTION_EX                0
                172     POP_TOP                         
                174     RETURN_VALUE                    
            [Exception Table]
                36 to 114 -> 134 [0] 
                134 to 156 -> 156 [1] lasti
        'FireFox'
        '__pyarmor_exit_15560__'
    [Disassembly]
        0       NOP                             
        2       NOP                             
        4       PUSH_NULL                       
        6       LOAD_CONST                      1: '__pyarmor_enter_15559__'
        8       LOAD_CONST                      2: b'<COAddr>\x05\x00\x00\x1ax\x00\x00\x00\x00\x00\x00\x00\x00\x00\x00\x00\x00\x00\x00\x00'
        10      BUILD_TUPLE                     1
        12      CALL_FUNCTION_EX                0
        14      POP_TOP                         
        16      RESUME                          0
        18      NOP                             
        20      NOP                             
        22      NOP                             
        24      NOP                             
        26      LOAD_CONST                      3: 0
        28      LOAD_CONST                      4: None
        30      IMPORT_NAME                     1: time
        32      STORE_NAME                      1: time
        34      LOAD_CONST                      3: 0
        36      LOAD_CONST                      4: None
        38      IMPORT_NAME                     2: random
        40      STORE_NAME                      2: random
        42      LOAD_CONST                      3: 0
        44      LOAD_CONST                      4: None
        46      IMPORT_NAME                     3: requests
        48      STORE_NAME                      3: requests
        50      LOAD_CONST                      3: 0
        52      LOAD_CONST                      5: ('Event',)
        54      IMPORT_NAME                     4: threading
        56      IMPORT_FROM                     5: Event
        58      STORE_NAME                      5: Event
        60      POP_TOP                         
        62      LOAD_CONST                      3: 0
        64      LOAD_CONST                      6: ('StopProgram',)
        66      IMPORT_NAME                     6: multithon.errors
        68      IMPORT_FROM                     7: StopProgram
        70      STORE_NAME                      7: StopProgram
        72      POP_TOP                         
        74      LOAD_CONST                      3: 0
        76      LOAD_CONST                      7: ('HTTPAdapter', 'Retry')
        78      IMPORT_NAME                     8: requests.adapters
        80      IMPORT_FROM                     9: HTTPAdapter
        82      STORE_NAME                      9: HTTPAdapter
        84      IMPORT_FROM                     10: Retry
        86      STORE_NAME                      10: Retry
        88      POP_TOP                         
        90      LOAD_CONST                      3: 0
        92      LOAD_CONST                      8: ('Logs', 'logging')
        94      IMPORT_NAME                     11: program.static_classes
        96      IMPORT_FROM                     12: Logs
        98      STORE_NAME                      12: Logs
        100     IMPORT_FROM                     13: logging
        102     STORE_NAME                      13: logging
        104     POP_TOP                         
        106     PUSH_NULL                       
        108     LOAD_BUILD_CLASS                
        110     LOAD_CONST                      9: <CODE> FireFox
        112     MAKE_FUNCTION                   0
        114     LOAD_CONST                      10: 'FireFox'
        116     CALL                            2
        124     STORE_NAME                      14: FireFox
        126     LOAD_CONST                      4: None
        128     NOP                             
        130     NOP                             
        132     NOP                             
        134     JUMP_FORWARD                    19 (to 174)
        142     POP_TOP                         
        144     RETURN_CONST                    4: None
        146     PUSH_EXC_INFO                   
        148     PUSH_NULL                       
        150     LOAD_CONST                      11: '__pyarmor_exit_15560__'
        152     NOP                             
        154     LOAD_CONST                      2: b'<COAddr>\x05\x00\x00\x1ax\x00\x00\x00\x00\x00\x00\x00\x00\x00\x00\x00\x00\x00\x00\x00'
        156     CALL                            1
        164     POP_TOP                         
        166     RERAISE                         0
        168     COPY                            3
        170     POP_EXCEPT                      
        172     RERAISE                         1
        174     PUSH_NULL                       
        176     LOAD_CONST                      11: '__pyarmor_exit_15560__'
        178     LOAD_CONST                      2: b'<COAddr>\x05\x00\x00\x1ax\x00\x00\x00\x00\x00\x00\x00\x00\x00\x00\x00\x00\x00\x00\x00'
        180     BUILD_TUPLE                     1
        182     CALL_FUNCTION_EX                0
        184     POP_TOP                         
        186     RETURN_VALUE                    
    [Exception Table]
        26 to 126 -> 146 [0] 
        146 to 168 -> 168 [1] lasti
