#decoded by lolz.live/mrpenny / t.me/zeus_jackpot
# ================================
# Примечания по Pyarmor:
# - Байт-код и объекты кода Pyarmor соответствуют стандартному Python, но присутствуют специальные вызовы функций среды выполнения (runtime) Pyarmor.
# - Вызовы строк — это не ошибки, а маркеры, которые обрабатываются Pyarmor во время выполнения.
#
# Руководство по декомпиляции (без среды выполнения):
# 1. Игнорируйте зашифрованные байты после `#`; используйте только строку до `#`.
# 2. Удалите "__pyarmor_enter_xxx__"(b"<COAddr>...") и "__pyarmor_leave_xxx__"(b"<COAddr>...") (пролог/эпилог).
# 3. "__pyarmor_assert_xxx__"(A) не является настоящим оператором assert.
#    - Если A — это имя или читаемая строка: замените на A.
#    - Если A — это (X, "Y"): замените на X.Y.
#    - Если A — это (X, "Y", Z): замените на X.Y = Z.
#    - В противном случае: выберите наиболее подходящую/логичную замену.
# 4. "__pyarmor_bcc_xxx__"(...) указывает на машинный (нативный) код; тело функции недоступно. Добавьте комментарий.
# ================================

[Code]
    File Name: <frozen program.modules.func.api.vaksms>
    Object Name: <module>
    Qualified Name: <module>
    Arg Count: 0
    Pos Only Arg Count: 0
    KW Only Arg Count: 0
    Stack Size: 5
    Flags: 0x20000000 (CO_PYARMOR_OBFUSCATED)
    [Names]
        '__assert_armored__'
        'json'
        'time'
        'random'
        'requests'
        'threading'
        'Event'
        'multithon.errors'
        'StopProgram'
        'requests.adapters'
        'HTTPAdapter'
        'Retry'
        'program.static_classes'
        'Logs'
        'logging'
        'VakSMS'
    [Locals+Names]
    [Constants]
        '__pyarmor_assert_15591__'
        '__pyarmor_enter_15592__'
        b'<COAddr>\x05\x00\x00\x1a\x80\x00\x00\x00\x00\x00\x00\x00\x00\x00\x00\x00\x00\x00\x00\x00'
        0
        None
        (
            'Event'
        )
        (
            'StopProgram'
        )
        (
            'HTTPAdapter'
            'Retry'
        )
        (
            'Logs'
            'logging'
        )
        [Code]
            File Name: <frozen program.modules.func.api.vaksms>
            Object Name: VakSMS
            Qualified Name: VakSMS
            Arg Count: 0
            Pos Only Arg Count: 0
            KW Only Arg Count: 0
            Stack Size: 5
            Flags: 0x20000000 (CO_PYARMOR_OBFUSCATED)
            [Names]
                '__name__'
                '__module__'
                '__qualname__'
                '__assert_armored__'
                'Event'
                '__init__'
                '_request'
                '_wait'
                'get_balance'
                'get_country'
                'get_operators'
                'get_price'
                'order_number'
                'get_code'
                'set_status'
            [Locals+Names]
            [Constants]
                'VakSMS'
                '__pyarmor_assert_15594__'
                '__pyarmor_enter_15595__'
                b'<COAddr>\x05\x00\x00"f\x00\x00\x00\x00\x00\x00\x00\x00\x00\x00\x00\x00\x00\x00\x00'
                [Code]
                    File Name: <frozen program.modules.func.api.vaksms>
                    Object Name: __init__
                    Qualified Name: VakSMS.__init__
                    Arg Count: 6
                    Pos Only Arg Count: 0
                    KW Only Arg Count: 0
                    Stack Size: 8
                    Flags: 0x20000003 (CO_OPTIMIZED | CO_NEWLOCALS | CO_PYARMOR_OBFUSCATED)
                    [Names]
                        'apikey'
                        'split'
                        'random'
                        'choice'
                        'gate'
                        'proxy'
                        'config'
                        'lang'
                        'service'
                        'retry'
                        'max_retry'
                        'timeout'
                        'stop_thread'
                        'ref'
                        'requests'
                        'Session'
                        '_session'
                        'HTTPAdapter'
                        'Retry'
                        'mount'
                    [Locals+Names]
                        'self'
                        'apikey'
                        'proxy'
                        'config'
                        'lang'
                        'stop_thread'
                        '__assert_armored__'
                        '_var_var_0'
                        '_var_var_1'
                    [Constants]
                        None
                        '__pyarmor_assert_15597__'
                        '__pyarmor_enter_15598__'
                        b'<COAddr>\x07\x00\x00\x1a\xe0\x01\x00\x00\x00\x00\x00\x00\x00\x00\x00\x00\x00\x00\x00\x00'
                        ':strix:'
                        'https://moresms.net/api/'   # b'\x81\xea\x0c\x07#\xe9\xe4\x9dT\xf7\x02\xd2i\xff\xf5\x96AS\xbe\xb3\xe5\xca^\xc5J'
                        'tg'
                        0
                        10
                        40
                        (
                            'softId'
                            '47'
                        )
                        3
                        0.3
                        (
                            429
                            500
                            502
                            503
                            504
                        )
                        (
                            'total'
                            'backoff_factor'
                            'status_forcelist'
                        )
                        (
                            'max_retries'
                        )
                        'https://'
                        '__pyarmor_exit_15599__'
                    [Disassembly]
                        0       NOP                             
                        2       NOP                             
                        4       PUSH_NULL                       
                        6       LOAD_CONST                      2: '__pyarmor_enter_15598__'
                        8       LOAD_CONST                      3: b'<COAddr>\x07\x00\x00\x1a\xe0\x01\x00\x00\x00\x00\x00\x00\x00\x00\x00\x00\x00\x00\x00\x00'
                        10      BUILD_TUPLE                     1
                        12      CALL_FUNCTION_EX                0
                        14      POP_TOP                         
                        16      RESUME                          0
                        18      NOP                             
                        20      NOP                             
                        22      NOP                             
                        24      NOP                             
                        26      NOP                             
                        28      LOAD_FAST                       1: apikey
                        30      LOAD_FAST                       0: self
                        32      STORE_ATTR                      0: apikey
                        42      LOAD_CONST                      4: ':strix:'
                        44      LOAD_FAST                       0: self
                        46      LOAD_ATTR                       0: apikey
                        66      CONTAINS_OP                     0 (in)
                        68      POP_JUMP_IF_FALSE               53 (to 176)
                        70      LOAD_FAST                       0: self
                        72      LOAD_ATTR                       0: apikey
                        92      LOAD_ATTR                       3: split
                        112     LOAD_CONST                      4: ':strix:'
                        114     CALL                            1
                        122     STORE_FAST                      7: _var_var_0
                        124     LOAD_GLOBAL                     5: NULL + random
                        134     LOAD_ATTR                       6: choice
                        154     LOAD_FAST                       7: _var_var_0
                        156     CALL                            1
                        164     LOAD_FAST                       0: self
                        166     STORE_ATTR                      0: apikey
                        176     PUSH_NULL                       
                        178     LOAD_CONST                      1: '__pyarmor_assert_15597__'
                        180     LOAD_CONST                      5: 'https://moresms.net/api/'   # b'\x81\xea\x0c\x07#\xe9\xe4\x9dT\xf7\x02\xd2i\xff\xf5\x96AS\xbe\xb3\xe5\xca^\xc5J'
                        182     CALL                            1
                        190     LOAD_FAST                       0: self
                        192     STORE_ATTR                      4: gate
                        202     LOAD_FAST                       2: proxy
                        204     LOAD_FAST                       0: self
                        206     STORE_ATTR                      5: proxy
                        216     LOAD_FAST                       3: config
                        218     LOAD_FAST                       0: self
                        220     STORE_ATTR                      6: config
                        230     LOAD_FAST                       4: lang
                        232     LOAD_FAST                       0: self
                        234     STORE_ATTR                      7: lang
                        244     LOAD_CONST                      6: 'tg'
                        246     LOAD_FAST                       0: self
                        248     STORE_ATTR                      8: service
                        258     LOAD_CONST                      7: 0
                        260     LOAD_FAST                       0: self
                        262     STORE_ATTR                      9: retry
                        272     LOAD_CONST                      8: 10
                        274     LOAD_FAST                       0: self
                        276     STORE_ATTR                      10: max_retry
                        286     LOAD_CONST                      9: 40
                        288     LOAD_FAST                       0: self
                        290     STORE_ATTR                      11: timeout
                        300     LOAD_FAST                       5: stop_thread
                        302     LOAD_FAST                       0: self
                        304     STORE_ATTR                      12: stop_thread
                        314     LOAD_CONST                      10: ('softId', '47')
                        316     LOAD_FAST                       0: self
                        318     STORE_ATTR                      13: ref
                        328     LOAD_GLOBAL                     29: NULL + requests
                        338     LOAD_ATTR                       30: Session
                        358     CALL                            0
                        366     LOAD_FAST                       0: self
                        368     STORE_ATTR                      16: _session
                        378     LOAD_GLOBAL                     35: NULL + HTTPAdapter
                        388     LOAD_GLOBAL                     37: NULL + Retry
                        398     LOAD_CONST                      11: 3
                        400     LOAD_CONST                      12: 0.3
                        402     BUILD_LIST                      0
                        404     LOAD_CONST                      13: (429, 500, 502, 503, 504)
                        406     LIST_EXTEND                     1
                        408     KW_NAMES                        14: ('total', 'backoff_factor', 'status_forcelist')
                        410     CALL                            3
                        418     KW_NAMES                        15: ('max_retries',)
                        420     CALL                            1
                        428     STORE_FAST                      8: _var_var_1
                        430     LOAD_FAST                       0: self
                        432     LOAD_ATTR                       32: _session
                        452     LOAD_ATTR                       39: mount
                        472     LOAD_CONST                      16: 'https://'
                        474     LOAD_FAST                       8: _var_var_1
                        476     CALL                            2
                        484     POP_TOP                         
                        486     LOAD_CONST                      0: None
                        488     NOP                             
                        490     NOP                             
                        492     NOP                             
                        494     JUMP_FORWARD                    19 (to 534)
                        502     POP_TOP                         
                        504     RETURN_CONST                    0: None
                        506     PUSH_EXC_INFO                   
                        508     PUSH_NULL                       
                        510     LOAD_CONST                      17: '__pyarmor_exit_15599__'
                        512     NOP                             
                        514     LOAD_CONST                      3: b'<COAddr>\x07\x00\x00\x1a\xe0\x01\x00\x00\x00\x00\x00\x00\x00\x00\x00\x00\x00\x00\x00\x00'
                        516     CALL                            1
                        524     POP_TOP                         
                        526     RERAISE                         0
                        528     COPY                            3
                        530     POP_EXCEPT                      
                        532     RERAISE                         1
                        534     PUSH_NULL                       
                        536     LOAD_CONST                      17: '__pyarmor_exit_15599__'
                        538     LOAD_CONST                      3: b'<COAddr>\x07\x00\x00\x1a\xe0\x01\x00\x00\x00\x00\x00\x00\x00\x00\x00\x00\x00\x00\x00\x00'
                        540     BUILD_TUPLE                     1
                        542     CALL_FUNCTION_EX                0
                        544     POP_TOP                         
                        546     RETURN_VALUE                    
                    [Exception Table]
                        28 to 486 -> 506 [0] 
                        506 to 528 -> 528 [1] lasti
                [Code]
                    File Name: <frozen program.modules.func.api.vaksms>
                    Object Name: _request
                    Qualified Name: VakSMS._request
                    Arg Count: 3
                    Pos Only Arg Count: 0
                    KW Only Arg Count: 0
                    Stack Size: 7
                    Flags: 0x20000003 (CO_OPTIMIZED | CO_NEWLOCALS | CO_PYARMOR_OBFUSCATED)
                    [Names]
                        'stop_thread'
                        'is_set'
                        'StopProgram'
                        '_session'
                        'get'
                        'timeout'
                        'proxy'
                        'content'
                        'status_code'
                        'Exception'
                        '_wait'
                    [Locals+Names]
                        'self'
                        'gate'
                        'params'
                        '__assert_armored__'
                        '_var_var_2'
                        '_var_var_3'
                        '_var_var_4'
                    [Constants]
                        None
                        '__pyarmor_assert_15600__'
                        '__pyarmor_enter_15601__'
                        b'<COAddr>\x07\x00\x00\x1a\xc2\x01\x00\x00\x00\x00\x00\x00\x00\x00\x00\x00\x00\x00\x00\x00'
                        True
                        (
                            'params'
                            'timeout'
                            'proxies'
                            'verify'
                        )
                        (
                            405
                            403
                            401
                            400
                            422
                            200
                        )
                        '__pyarmor_exit_15602__'
                        5
                        1
                    [Disassembly]
                        0       NOP                             
                        2       NOP                             
                        4       PUSH_NULL                       
                        6       LOAD_CONST                      2: '__pyarmor_enter_15601__'
                        8       LOAD_CONST                      3: b'<COAddr>\x07\x00\x00\x1a\xc2\x01\x00\x00\x00\x00\x00\x00\x00\x00\x00\x00\x00\x00\x00\x00'
                        10      BUILD_TUPLE                     1
                        12      CALL_FUNCTION_EX                0
                        14      POP_TOP                         
                        16      RESUME                          0
                        18      NOP                             
                        20      NOP                             
                        22      NOP                             
                        24      NOP                             
                        26      NOP                             
                        28      NOP                             
                        30      NOP                             
                        32      LOAD_FAST                       0: self
                        34      LOAD_ATTR                       0: stop_thread
                        54      LOAD_ATTR                       3: is_set
                        74      CALL                            0
                        82      POP_JUMP_IF_FALSE               10 (to 104)
                        84      LOAD_GLOBAL                     5: NULL + StopProgram
                        94      CALL                            0
                        102     RAISE_VARARGS                   1
                        104     LOAD_FAST                       0: self
                        106     LOAD_ATTR                       6: _session
                        126     LOAD_ATTR                       9: get
                        146     LOAD_FAST                       1: gate
                        148     LOAD_FAST                       2: params
                        150     LOAD_FAST                       0: self
                        152     LOAD_ATTR                       10: timeout
                        172     LOAD_FAST                       0: self
                        174     LOAD_ATTR                       12: proxy
                        194     LOAD_CONST                      4: True
                        196     KW_NAMES                        5: ('params', 'timeout', 'proxies', 'verify')
                        198     CALL                            5
                        206     BEFORE_WITH                     
                        208     STORE_FAST                      4: _var_var_2
                        210     LOAD_FAST                       4: _var_var_2
                        212     LOAD_ATTR                       14: content
                        232     STORE_FAST                      5: _var_var_3
                        234     LOAD_FAST                       4: _var_var_2
                        236     LOAD_ATTR                       16: status_code
                        256     LOAD_CONST                      6: (405, 403, 401, 400, 422, 200)
                        258     CONTAINS_OP                     0 (in)
                        260     POP_JUMP_IF_FALSE               20 (to 302)
                        262     LOAD_FAST                       4: _var_var_2
                        264     SWAP                            2
                        266     LOAD_CONST                      0: None
                        268     LOAD_CONST                      0: None
                        270     LOAD_CONST                      0: None
                        272     CALL                            2
                        280     POP_TOP                         
                        282     NOP                             
                        284     NOP                             
                        286     NOP                             
                        288     JUMP_FORWARD                    107 (to 504)
                        290     CALL                            1
                        298     POP_TOP                         
                        300     RETURN_VALUE                    
                        302     NOP                             
                        304     LOAD_CONST                      0: None
                        306     LOAD_CONST                      0: None
                        308     LOAD_CONST                      0: None
                        310     CALL                            2
                        318     POP_TOP                         
                        320     LOAD_FAST                       0: self
                        322     LOAD_ATTR                       21: _wait
                        342     LOAD_CONST                      9: 1
                        344     CALL                            1
                        352     POP_TOP                         
                        354     JUMP_BACKWARD                   163 (to 30)
                        356     PUSH_EXC_INFO                   
                        358     WITH_EXCEPT_START               
                        360     POP_JUMP_IF_TRUE                1 (to 364)
                        362     RERAISE                         2
                        364     POP_TOP                         
                        366     POP_EXCEPT                      
                        368     POP_TOP                         
                        370     POP_TOP                         
                        372     JUMP_BACKWARD                   27 (to 320)
                        374     COPY                            3
                        376     POP_EXCEPT                      
                        378     RERAISE                         1
                        380     PUSH_EXC_INFO                   
                        382     LOAD_GLOBAL                     4: StopProgram
                        392     CHECK_EXC_MATCH                 
                        394     POP_JUMP_IF_FALSE               2 (to 400)
                        396     POP_TOP                         
                        398     RAISE_VARARGS                   0
                        400     LOAD_GLOBAL                     18: Exception
                        410     CHECK_EXC_MATCH                 
                        412     POP_JUMP_IF_FALSE               27 (to 468)
                        414     STORE_FAST                      6: _var_var_4
                        416     LOAD_FAST                       0: self
                        418     LOAD_ATTR                       21: _wait
                        438     LOAD_CONST                      8: 5
                        440     CALL                            1
                        448     POP_TOP                         
                        450     POP_EXCEPT                      
                        452     LOAD_CONST                      0: None
                        454     STORE_FAST                      6: _var_var_4
                        456     DELETE_FAST                     6: _var_var_4
                        458     JUMP_BACKWARD                   70 (to 320)
                        460     LOAD_CONST                      0: None
                        462     STORE_FAST                      6: _var_var_4
                        464     DELETE_FAST                     6: _var_var_4
                        466     RERAISE                         1
                        468     RERAISE                         0
                        470     COPY                            3
                        472     POP_EXCEPT                      
                        474     RERAISE                         1
                        476     PUSH_EXC_INFO                   
                        478     PUSH_NULL                       
                        480     LOAD_CONST                      7: '__pyarmor_exit_15602__'
                        482     NOP                             
                        484     LOAD_CONST                      3: b'<COAddr>\x07\x00\x00\x1a\xc2\x01\x00\x00\x00\x00\x00\x00\x00\x00\x00\x00\x00\x00\x00\x00'
                        486     CALL                            1
                        494     POP_TOP                         
                        496     RERAISE                         0
                        498     COPY                            3
                        500     POP_EXCEPT                      
                        502     RERAISE                         1
                        504     PUSH_NULL                       
                        506     LOAD_CONST                      7: '__pyarmor_exit_15602__'
                        508     LOAD_CONST                      3: b'<COAddr>\x07\x00\x00\x1a\xc2\x01\x00\x00\x00\x00\x00\x00\x00\x00\x00\x00\x00\x00\x00\x00'
                        510     BUILD_TUPLE                     1
                        512     CALL_FUNCTION_EX                0
                        514     POP_TOP                         
                        516     RETURN_VALUE                    
                    [Exception Table]
                        28 to 30 -> 476 [0] 
                        32 to 208 -> 380 [0] 
                        208 to 264 -> 356 [1] lasti
                        264 to 282 -> 380 [0] 
                        304 to 320 -> 380 [0] 
                        320 to 356 -> 476 [0] 
                        356 to 366 -> 374 [3] lasti
                        366 to 380 -> 380 [0] 
                        380 to 416 -> 470 [1] lasti
                        416 to 450 -> 460 [1] lasti
                        450 to 460 -> 476 [0] 
                        460 to 470 -> 470 [1] lasti
                        470 to 476 -> 476 [0] 
                        476 to 498 -> 498 [1] lasti
                [Code]
                    File Name: <frozen program.modules.func.api.vaksms>
                    Object Name: _wait
                    Qualified Name: VakSMS._wait
                    Arg Count: 2
                    Pos Only Arg Count: 0
                    KW Only Arg Count: 0
                    Stack Size: 5
                    Flags: 0x20000003 (CO_OPTIMIZED | CO_NEWLOCALS | CO_PYARMOR_OBFUSCATED)
                    [Names]
                        'range'
                        'stop_thread'
                        'is_set'
                        'StopProgram'
                        'time'
                        'sleep'
                    [Locals+Names]
                        'self'
                        'second'
                        '__assert_armored__'
                        '_var_var_3'
                    [Constants]
                        None
                        '__pyarmor_assert_15603__'
                        '__pyarmor_enter_15604__'
                        b'<COAddr>\x07\x00\x00\x1a\xa8\x00\x00\x00\x00\x00\x00\x00\x00\x00\x00\x00\x00\x00\x00\x00'
                        1
                        '__pyarmor_exit_15605__'
                    [Disassembly]
                        0       NOP                             
                        2       NOP                             
                        4       PUSH_NULL                       
                        6       LOAD_CONST                      2: '__pyarmor_enter_15604__'
                        8       LOAD_CONST                      3: b'<COAddr>\x07\x00\x00\x1a\xa8\x00\x00\x00\x00\x00\x00\x00\x00\x00\x00\x00\x00\x00\x00\x00'
                        10      BUILD_TUPLE                     1
                        12      CALL_FUNCTION_EX                0
                        14      POP_TOP                         
                        16      RESUME                          0
                        18      NOP                             
                        20      NOP                             
                        22      NOP                             
                        24      NOP                             
                        26      NOP                             
                        28      LOAD_GLOBAL                     1: NULL + range
                        38      LOAD_FAST                       1: second
                        40      CALL                            1
                        48      GET_ITER                        
                        50      FOR_ITER                        59 (to 170)
                        54      STORE_FAST                      3: _var_var_3
                        56      LOAD_FAST                       0: self
                        58      LOAD_ATTR                       2: stop_thread
                        78      LOAD_ATTR                       5: is_set
                        98      CALL                            0
                        106     POP_JUMP_IF_FALSE               10 (to 128)
                        108     LOAD_GLOBAL                     7: NULL + StopProgram
                        118     CALL                            0
                        126     RAISE_VARARGS                   1
                        128     LOAD_GLOBAL                     9: NULL + time
                        138     LOAD_ATTR                       10: sleep
                        158     LOAD_CONST                      4: 1
                        160     CALL                            1
                        168     POP_TOP                         
                        170     JUMP_BACKWARD                   61 (to 50)
                        172     END_FOR                         
                        174     LOAD_CONST                      0: None
                        176     NOP                             
                        178     NOP                             
                        180     NOP                             
                        182     JUMP_FORWARD                    19 (to 222)
                        190     POP_TOP                         
                        192     RETURN_CONST                    0: None
                        194     PUSH_EXC_INFO                   
                        196     PUSH_NULL                       
                        198     LOAD_CONST                      5: '__pyarmor_exit_15605__'
                        200     NOP                             
                        202     LOAD_CONST                      3: b'<COAddr>\x07\x00\x00\x1a\xa8\x00\x00\x00\x00\x00\x00\x00\x00\x00\x00\x00\x00\x00\x00\x00'
                        204     CALL                            1
                        212     POP_TOP                         
                        214     RERAISE                         0
                        216     COPY                            3
                        218     POP_EXCEPT                      
                        220     RERAISE                         1
                        222     PUSH_NULL                       
                        224     LOAD_CONST                      5: '__pyarmor_exit_15605__'
                        226     LOAD_CONST                      3: b'<COAddr>\x07\x00\x00\x1a\xa8\x00\x00\x00\x00\x00\x00\x00\x00\x00\x00\x00\x00\x00\x00\x00'
                        228     BUILD_TUPLE                     1
                        230     CALL_FUNCTION_EX                0
                        232     POP_TOP                         
                        234     RETURN_VALUE                    
                    [Exception Table]
                        28 to 174 -> 194 [0] 
                        194 to 216 -> 216 [1] lasti
                [Code]
                    File Name: <frozen program.modules.func.api.vaksms>
                    Object Name: get_balance
                    Qualified Name: VakSMS.get_balance
                    Arg Count: 1
                    Pos Only Arg Count: 0
                    KW Only Arg Count: 0
                    Stack Size: 6
                    Flags: 0x20000003 (CO_OPTIMIZED | CO_NEWLOCALS | CO_PYARMOR_OBFUSCATED)
                    [Names]
                        'apikey'
                        '_request'
                        'gate'
                        'json'
                        'loads'
                        'text'
                    [Locals+Names]
                        'self'
                        '__assert_armored__'
                        '_var_var_5'
                        '_var_var_2'
                        '_var_var_6'
                    [Constants]
                        None
                        '__pyarmor_assert_15606__'
                        '__pyarmor_enter_15607__'
                        b'<COAddr>\x05\x00\x00\x1a\xe6\x00\x00\x00\x00\x00\x00\x00\x00\x00\x00\x00\x00\x00\x00\x00'
                        'apiKey'
                        'getBalance/'   # b'\x81\xe5\x1d\x07\x11\xfb\xb2\xd3\x15\xf9\x08\x8f'
                        'balance'
                        '__pyarmor_exit_15608__'
                    [Disassembly]
                        0       NOP                             
                        2       NOP                             
                        4       PUSH_NULL                       
                        6       LOAD_CONST                      2: '__pyarmor_enter_15607__'
                        8       LOAD_CONST                      3: b'<COAddr>\x05\x00\x00\x1a\xe6\x00\x00\x00\x00\x00\x00\x00\x00\x00\x00\x00\x00\x00\x00\x00'
                        10      BUILD_TUPLE                     1
                        12      CALL_FUNCTION_EX                0
                        14      POP_TOP                         
                        16      RESUME                          0
                        18      NOP                             
                        20      NOP                             
                        22      NOP                             
                        24      NOP                             
                        26      NOP                             
                        28      NOP                             
                        30      LOAD_CONST                      4: 'apiKey'
                        32      LOAD_FAST                       0: self
                        34      LOAD_ATTR                       0: apikey
                        54      BUILD_MAP                       1
                        56      STORE_FAST                      2: _var_var_5
                        58      LOAD_FAST                       0: self
                        60      LOAD_ATTR                       3: _request
                        80      LOAD_FAST                       0: self
                        82      LOAD_ATTR                       4: gate
                        102     PUSH_NULL                       
                        104     LOAD_CONST                      1: '__pyarmor_assert_15606__'
                        106     LOAD_CONST                      5: 'getBalance/'   # b'\x81\xe5\x1d\x07\x11\xfb\xb2\xd3\x15\xf9\x08\x8f'
                        108     CALL                            1
                        116     BINARY_OP                       0 (+)
                        120     LOAD_FAST                       2: _var_var_5
                        122     CALL                            2
                        130     STORE_FAST                      3: _var_var_2
                        132     LOAD_GLOBAL                     7: NULL + json
                        142     LOAD_ATTR                       8: loads
                        162     LOAD_FAST                       3: _var_var_2
                        164     LOAD_ATTR                       10: text
                        184     CALL                            1
                        192     STORE_FAST                      4: _var_var_6
                        194     LOAD_FAST                       4: _var_var_6
                        196     LOAD_CONST                      6: 'balance'
                        198     BINARY_SUBSCR                   
                        202     NOP                             
                        204     NOP                             
                        206     NOP                             
                        208     JUMP_FORWARD                    37 (to 284)
                        210     CALL                            1
                        218     POP_TOP                         
                        220     RETURN_VALUE                    
                        222     PUSH_EXC_INFO                   
                        224     POP_TOP                         
                        226     POP_EXCEPT                      
                        228     JUMP_FORWARD                    3 (to 236)
                        230     COPY                            3
                        232     POP_EXCEPT                      
                        234     RERAISE                         1
                        236     LOAD_CONST                      0: None
                        238     NOP                             
                        240     NOP                             
                        242     NOP                             
                        244     JUMP_FORWARD                    19 (to 284)
                        252     POP_TOP                         
                        254     RETURN_CONST                    0: None
                        256     PUSH_EXC_INFO                   
                        258     PUSH_NULL                       
                        260     LOAD_CONST                      7: '__pyarmor_exit_15608__'
                        262     NOP                             
                        264     LOAD_CONST                      3: b'<COAddr>\x05\x00\x00\x1a\xe6\x00\x00\x00\x00\x00\x00\x00\x00\x00\x00\x00\x00\x00\x00\x00'
                        266     CALL                            1
                        274     POP_TOP                         
                        276     RERAISE                         0
                        278     COPY                            3
                        280     POP_EXCEPT                      
                        282     RERAISE                         1
                        284     PUSH_NULL                       
                        286     LOAD_CONST                      7: '__pyarmor_exit_15608__'
                        288     LOAD_CONST                      3: b'<COAddr>\x05\x00\x00\x1a\xe6\x00\x00\x00\x00\x00\x00\x00\x00\x00\x00\x00\x00\x00\x00\x00'
                        290     BUILD_TUPLE                     1
                        292     CALL_FUNCTION_EX                0
                        294     POP_TOP                         
                        296     RETURN_VALUE                    
                    [Exception Table]
                        30 to 202 -> 222 [0] 
                        222 to 226 -> 230 [1] lasti
                        226 to 236 -> 256 [0] 
                        256 to 278 -> 278 [1] lasti
                [Code]
                    File Name: <frozen program.modules.func.api.vaksms>
                    Object Name: get_country
                    Qualified Name: VakSMS.get_country
                    Arg Count: 1
                    Pos Only Arg Count: 0
                    KW Only Arg Count: 0
                    Stack Size: 8
                    Flags: 0x20000003 (CO_OPTIMIZED | CO_NEWLOCALS | CO_PYARMOR_OBFUSCATED)
                    [Names]
                        'apikey'
                        '_request'
                        'gate'
                        'json'
                        'loads'
                        'text'
                        'type'
                        'list'
                        'append'
                        'sorted'
                    [Locals+Names]
                        'self'
                        '__assert_armored__'
                        '_var_var_5'
                        '_var_var_2'
                        '_var_var_6'
                        '_var_var_7'
                        '_var_var_8'
                    [Constants]
                        None
                        '__pyarmor_assert_15609__'
                        '__pyarmor_enter_15610__'
                        b'<COAddr>\x05\x00\x00\x1az\x01\x00\x00\x00\x00\x00\x00\x00\x00\x00\x00\x00\x00\x00\x00'
                        'apiKey'
                        'getCountryList/'   # b'\x81\xe5\x1d\x07\x10\xf5\xab\xdc\x0f\xe8\x14\xece\xff\xec\xca'
                        'countryCode'   # b'\x81\xe1\x17\x06=\xee\xac\xcb8\xf5\t\xc5'
                        'countryName'   # b'\x81\xe1\x17\x06=\xee\xac\xcb5\xfb\x00\xc5'
                        [Code]
                            File Name: <frozen program.modules.func.api.vaksms>
                            Object Name: <lambda>
                            Qualified Name: VakSMS.get_country.<locals>.<lambda>
                            Arg Count: 1
                            Pos Only Arg Count: 0
                            KW Only Arg Count: 0
                            Stack Size: 2
                            Flags: 0x00000013 (CO_OPTIMIZED | CO_NEWLOCALS | CO_NESTED)
                            [Names]
                            [Locals+Names]
                                'x'
                            [Constants]
                                None
                                0
                            [Disassembly]
                                0       RESUME                          0
                                2       LOAD_FAST                       0: x
                                4       LOAD_CONST                      1: 0
                                6       BINARY_SUBSCR                   
                                10      RETURN_VALUE                    
                            [Exception Table]
                        (
                            'key'
                        )
                        '__pyarmor_exit_15611__'
                    [Disassembly]
                        0       NOP                             
                        2       NOP                             
                        4       PUSH_NULL                       
                        6       LOAD_CONST                      2: '__pyarmor_enter_15610__'
                        8       LOAD_CONST                      3: b'<COAddr>\x05\x00\x00\x1az\x01\x00\x00\x00\x00\x00\x00\x00\x00\x00\x00\x00\x00\x00\x00'
                        10      BUILD_TUPLE                     1
                        12      CALL_FUNCTION_EX                0
                        14      POP_TOP                         
                        16      RESUME                          0
                        18      NOP                             
                        20      NOP                             
                        22      NOP                             
                        24      NOP                             
                        26      NOP                             
                        28      NOP                             
                        30      LOAD_CONST                      4: 'apiKey'
                        32      LOAD_FAST                       0: self
                        34      LOAD_ATTR                       0: apikey
                        54      BUILD_MAP                       1
                        56      STORE_FAST                      2: _var_var_5
                        58      LOAD_FAST                       0: self
                        60      LOAD_ATTR                       3: _request
                        80      LOAD_FAST                       0: self
                        82      LOAD_ATTR                       4: gate
                        102     PUSH_NULL                       
                        104     LOAD_CONST                      1: '__pyarmor_assert_15609__'
                        106     LOAD_CONST                      5: 'getCountryList/'   # b'\x81\xe5\x1d\x07\x10\xf5\xab\xdc\x0f\xe8\x14\xece\xff\xec\xca'
                        108     CALL                            1
                        116     BINARY_OP                       0 (+)
                        120     LOAD_FAST                       2: _var_var_5
                        122     CALL                            2
                        130     STORE_FAST                      3: _var_var_2
                        132     LOAD_GLOBAL                     7: NULL + json
                        142     LOAD_ATTR                       8: loads
                        162     LOAD_FAST                       3: _var_var_2
                        164     LOAD_ATTR                       10: text
                        184     CALL                            1
                        192     STORE_FAST                      4: _var_var_6
                        194     BUILD_LIST                      0
                        196     STORE_FAST                      5: _var_var_7
                        198     LOAD_GLOBAL                     13: NULL + type
                        208     LOAD_FAST                       4: _var_var_6
                        210     CALL                            1
                        218     LOAD_GLOBAL                     14: list
                        228     COMPARE_OP                      40 (==)
                        232     POP_JUMP_IF_FALSE               67 (to 368)
                        234     LOAD_FAST                       4: _var_var_6
                        236     GET_ITER                        
                        238     FOR_ITER                        39 (to 318)
                        242     STORE_FAST                      6: _var_var_8
                        244     LOAD_FAST                       5: _var_var_7
                        246     LOAD_ATTR                       17: append
                        266     LOAD_FAST                       6: _var_var_8
                        268     PUSH_NULL                       
                        270     LOAD_CONST                      1: '__pyarmor_assert_15609__'
                        272     LOAD_CONST                      6: 'countryCode'   # b'\x81\xe1\x17\x06=\xee\xac\xcb8\xf5\t\xc5'
                        274     CALL                            1
                        282     BINARY_SUBSCR                   
                        286     LOAD_FAST                       6: _var_var_8
                        288     PUSH_NULL                       
                        290     LOAD_CONST                      1: '__pyarmor_assert_15609__'
                        292     LOAD_CONST                      7: 'countryName'   # b'\x81\xe1\x17\x06=\xee\xac\xcb5\xfb\x00\xc5'
                        294     CALL                            1
                        302     BINARY_SUBSCR                   
                        306     BUILD_LIST                      2
                        308     CALL                            1
                        316     POP_TOP                         
                        318     JUMP_BACKWARD                   41 (to 238)
                        320     END_FOR                         
                        322     LOAD_GLOBAL                     19: NULL + sorted
                        332     LOAD_FAST                       5: _var_var_7
                        334     LOAD_CONST                      8: <CODE> <lambda>
                        336     MAKE_FUNCTION                   0
                        338     KW_NAMES                        9: ('key',)
                        340     CALL                            2
                        348     NOP                             
                        350     NOP                             
                        352     NOP                             
                        354     JUMP_FORWARD                    38 (to 432)
                        356     CALL                            1
                        364     POP_TOP                         
                        366     RETURN_VALUE                    
                        368     NOP                             
                        370     LOAD_CONST                      0: None
                        372     NOP                             
                        374     NOP                             
                        376     NOP                             
                        378     JUMP_FORWARD                    26 (to 432)
                        386     POP_TOP                         
                        388     RETURN_CONST                    0: None
                        390     PUSH_EXC_INFO                   
                        392     POP_TOP                         
                        394     POP_EXCEPT                      
                        396     JUMP_BACKWARD                   14 (to 370)
                        398     COPY                            3
                        400     POP_EXCEPT                      
                        402     RERAISE                         1
                        404     PUSH_EXC_INFO                   
                        406     PUSH_NULL                       
                        408     LOAD_CONST                      10: '__pyarmor_exit_15611__'
                        410     NOP                             
                        412     LOAD_CONST                      3: b'<COAddr>\x05\x00\x00\x1az\x01\x00\x00\x00\x00\x00\x00\x00\x00\x00\x00\x00\x00\x00\x00'
                        414     CALL                            1
                        422     POP_TOP                         
                        424     RERAISE                         0
                        426     COPY                            3
                        428     POP_EXCEPT                      
                        430     RERAISE                         1
                        432     PUSH_NULL                       
                        434     LOAD_CONST                      10: '__pyarmor_exit_15611__'
                        436     LOAD_CONST                      3: b'<COAddr>\x05\x00\x00\x1az\x01\x00\x00\x00\x00\x00\x00\x00\x00\x00\x00\x00\x00\x00\x00'
                        438     BUILD_TUPLE                     1
                        440     CALL_FUNCTION_EX                0
                        442     POP_TOP                         
                        444     RETURN_VALUE                    
                    [Exception Table]
                        30 to 348 -> 390 [0] 
                        368 to 370 -> 404 [0] 
                        390 to 394 -> 398 [1] lasti
                        394 to 404 -> 404 [0] 
                        404 to 426 -> 426 [1] lasti
                [Code]
                    File Name: <frozen program.modules.func.api.vaksms>
                    Object Name: get_operators
                    Qualified Name: VakSMS.get_operators
                    Arg Count: 2
                    Pos Only Arg Count: 0
                    KW Only Arg Count: 0
                    Stack Size: 6
                    Flags: 0x20000003 (CO_OPTIMIZED | CO_NEWLOCALS | CO_PYARMOR_OBFUSCATED)
                    [Names]
                        'apikey'
                        '_request'
                        'gate'
                        'json'
                        'loads'
                        'text'
                        'type'
                        'list'
                        'append'
                    [Locals+Names]
                        'self'
                        'country'
                        '__assert_armored__'
                        '_var_var_5'
                        '_var_var_2'
                        '_var_var_6'
                        '_var_var_9'
                        '_var_var_8'
                        '_var_var_10'
                    [Constants]
                        None
                        '__pyarmor_assert_15612__'
                        '__pyarmor_enter_15613__'
                        b'<COAddr>\x07\x00\x00\x1ax\x01\x00\x00\x00\x00\x00\x00\x00\x00\x00\x00\x00\x00\x00\x00'
                        'apiKey'
                        'getCountryList/'   # b'\x81\xe5\x1d\x07\x10\xf5\xab\xdc\x0f\xe8\x14\xece\xff\xec\xca'
                        'countryCode'   # b'\x81\xe1\x17\x06=\xee\xac\xcb8\xf5\t\xc5'
                        'operatorList'   # b'\x81\xed\x08\x16!\xfb\xaa\xdd\t\xd6\x04\xd3x'
                        '__pyarmor_exit_15614__'
                    [Disassembly]
                        0       NOP                             
                        2       NOP                             
                        4       PUSH_NULL                       
                        6       LOAD_CONST                      2: '__pyarmor_enter_15613__'
                        8       LOAD_CONST                      3: b'<COAddr>\x07\x00\x00\x1ax\x01\x00\x00\x00\x00\x00\x00\x00\x00\x00\x00\x00\x00\x00\x00'
                        10      BUILD_TUPLE                     1
                        12      CALL_FUNCTION_EX                0
                        14      POP_TOP                         
                        16      RESUME                          0
                        18      NOP                             
                        20      NOP                             
                        22      NOP                             
                        24      NOP                             
                        26      NOP                             
                        28      NOP                             
                        30      LOAD_CONST                      4: 'apiKey'
                        32      LOAD_FAST                       0: self
                        34      LOAD_ATTR                       0: apikey
                        54      BUILD_MAP                       1
                        56      STORE_FAST                      3: _var_var_5
                        58      LOAD_FAST                       0: self
                        60      LOAD_ATTR                       3: _request
                        80      LOAD_FAST                       0: self
                        82      LOAD_ATTR                       4: gate
                        102     PUSH_NULL                       
                        104     LOAD_CONST                      1: '__pyarmor_assert_15612__'
                        106     LOAD_CONST                      5: 'getCountryList/'   # b'\x81\xe5\x1d\x07\x10\xf5\xab\xdc\x0f\xe8\x14\xece\xff\xec\xca'
                        108     CALL                            1
                        116     BINARY_OP                       0 (+)
                        120     LOAD_FAST                       3: _var_var_5
                        122     CALL                            2
                        130     STORE_FAST                      4: _var_var_2
                        132     LOAD_GLOBAL                     7: NULL + json
                        142     LOAD_ATTR                       8: loads
                        162     LOAD_FAST                       4: _var_var_2
                        164     LOAD_ATTR                       10: text
                        184     CALL                            1
                        192     STORE_FAST                      5: _var_var_6
                        194     BUILD_LIST                      0
                        196     STORE_FAST                      6: _var_var_9
                        198     LOAD_GLOBAL                     13: NULL + type
                        208     LOAD_FAST                       5: _var_var_6
                        210     CALL                            1
                        218     LOAD_GLOBAL                     14: list
                        228     COMPARE_OP                      40 (==)
                        232     POP_JUMP_IF_FALSE               66 (to 366)
                        234     LOAD_FAST                       5: _var_var_6
                        236     GET_ITER                        
                        238     FOR_ITER                        50 (to 340)
                        242     STORE_FAST                      7: _var_var_8
                        244     LOAD_FAST                       7: _var_var_8
                        246     PUSH_NULL                       
                        248     LOAD_CONST                      1: '__pyarmor_assert_15612__'
                        250     LOAD_CONST                      6: 'countryCode'   # b'\x81\xe1\x17\x06=\xee\xac\xcb8\xf5\t\xc5'
                        252     CALL                            1
                        260     BINARY_SUBSCR                   
                        264     LOAD_FAST                       1: country
                        266     COMPARE_OP                      40 (==)
                        270     POP_JUMP_IF_TRUE                1 (to 274)
                        272     JUMP_BACKWARD                   18 (to 238)
                        274     LOAD_FAST                       7: _var_var_8
                        276     PUSH_NULL                       
                        278     LOAD_CONST                      1: '__pyarmor_assert_15612__'
                        280     LOAD_CONST                      7: 'operatorList'   # b'\x81\xed\x08\x16!\xfb\xaa\xdd\t\xd6\x04\xd3x'
                        282     CALL                            1
                        290     BINARY_SUBSCR                   
                        294     GET_ITER                        
                        296     FOR_ITER                        19 (to 336)
                        300     STORE_FAST                      8: _var_var_10
                        302     LOAD_FAST                       6: _var_var_9
                        304     LOAD_ATTR                       17: append
                        324     LOAD_FAST                       8: _var_var_10
                        326     CALL                            1
                        334     POP_TOP                         
                        336     JUMP_BACKWARD                   21 (to 296)
                        338     END_FOR                         
                        340     JUMP_BACKWARD                   52 (to 238)
                        342     END_FOR                         
                        344     LOAD_FAST                       6: _var_var_9
                        346     NOP                             
                        348     NOP                             
                        350     NOP                             
                        352     JUMP_FORWARD                    38 (to 430)
                        354     CALL                            1
                        362     POP_TOP                         
                        364     RETURN_VALUE                    
                        366     NOP                             
                        368     LOAD_CONST                      0: None
                        370     NOP                             
                        372     NOP                             
                        374     NOP                             
                        376     JUMP_FORWARD                    26 (to 430)
                        384     POP_TOP                         
                        386     RETURN_CONST                    0: None
                        388     PUSH_EXC_INFO                   
                        390     POP_TOP                         
                        392     POP_EXCEPT                      
                        394     JUMP_BACKWARD                   14 (to 368)
                        396     COPY                            3
                        398     POP_EXCEPT                      
                        400     RERAISE                         1
                        402     PUSH_EXC_INFO                   
                        404     PUSH_NULL                       
                        406     LOAD_CONST                      8: '__pyarmor_exit_15614__'
                        408     NOP                             
                        410     LOAD_CONST                      3: b'<COAddr>\x07\x00\x00\x1ax\x01\x00\x00\x00\x00\x00\x00\x00\x00\x00\x00\x00\x00\x00\x00'
                        412     CALL                            1
                        420     POP_TOP                         
                        422     RERAISE                         0
                        424     COPY                            3
                        426     POP_EXCEPT                      
                        428     RERAISE                         1
                        430     PUSH_NULL                       
                        432     LOAD_CONST                      8: '__pyarmor_exit_15614__'
                        434     LOAD_CONST                      3: b'<COAddr>\x07\x00\x00\x1ax\x01\x00\x00\x00\x00\x00\x00\x00\x00\x00\x00\x00\x00\x00\x00'
                        436     BUILD_TUPLE                     1
                        438     CALL_FUNCTION_EX                0
                        440     POP_TOP                         
                        442     RETURN_VALUE                    
                    [Exception Table]
                        30 to 272 -> 388 [0] 
                        274 to 346 -> 388 [0] 
                        366 to 368 -> 402 [0] 
                        388 to 392 -> 396 [1] lasti
                        392 to 402 -> 402 [0] 
                        402 to 424 -> 424 [1] lasti
                [Code]
                    File Name: <frozen program.modules.func.api.vaksms>
                    Object Name: get_price
                    Qualified Name: VakSMS.get_price
                    Arg Count: 3
                    Pos Only Arg Count: 0
                    KW Only Arg Count: 0
                    Stack Size: 6
                    Flags: 0x20000003 (CO_OPTIMIZED | CO_NEWLOCALS | CO_PYARMOR_OBFUSCATED)
                    [Names]
                        'apikey'
                        'service'
                        'append'
                        '_request'
                        'gate'
                        'json'
                        'loads'
                        'text'
                    [Locals+Names]
                        'self'
                        'country'
                        'operator'
                        '__assert_armored__'
                        '_var_var_5'
                        '_var_var_2'
                        '_var_var_6'
                    [Constants]
                        None
                        '__pyarmor_assert_15615__'
                        '__pyarmor_enter_15616__'
                        b'<COAddr>\x05\x00\x00\x1at\x01\x00\x00\x00\x00\x00\x00\x00\x00\x00\x00\x00\x00\x00\x00'
                        'apiKey'
                        'service'
                        'country'
                        (
                            'price'
                            ''
                        )
                        'any'
                        'undefined'   # b'\x81\xf7\x16\x176\xfc\xb7\xdc\x1e\xfe'
                        'operator'
                        'getCountNumber/'   # b'\x81\xe5\x1d\x07\x10\xf5\xab\xdc\x0f\xd4\x18\xcdn\xe9\xea\xca'
                        'tg'
                        'price'
                        '__pyarmor_exit_15617__'
                        0
                    [Disassembly]
                        0       NOP                             
                        2       NOP                             
                        4       PUSH_NULL                       
                        6       LOAD_CONST                      2: '__pyarmor_enter_15616__'
                        8       LOAD_CONST                      3: b'<COAddr>\x05\x00\x00\x1at\x01\x00\x00\x00\x00\x00\x00\x00\x00\x00\x00\x00\x00\x00\x00'
                        10      BUILD_TUPLE                     1
                        12      CALL_FUNCTION_EX                0
                        14      POP_TOP                         
                        16      RESUME                          0
                        18      NOP                             
                        20      NOP                             
                        22      NOP                             
                        24      NOP                             
                        26      NOP                             
                        28      NOP                             
                        30      LOAD_CONST                      4: 'apiKey'
                        32      LOAD_FAST                       0: self
                        34      LOAD_ATTR                       0: apikey
                        54      BUILD_TUPLE                     2
                        56      LOAD_CONST                      5: 'service'
                        58      LOAD_FAST                       0: self
                        60      LOAD_ATTR                       2: service
                        80      BUILD_TUPLE                     2
                        82      LOAD_CONST                      6: 'country'
                        84      LOAD_FAST                       1: country
                        86      BUILD_TUPLE                     2
                        88      LOAD_CONST                      7: ('price', '')
                        90      BUILD_LIST                      4
                        92      STORE_FAST                      4: _var_var_5
                        94      LOAD_FAST                       2: operator
                        96      LOAD_CONST                      0: None
                        98      COMPARE_OP                      55 (!=)
                        102     POP_JUMP_IF_FALSE               35 (to 174)
                        104     LOAD_FAST                       2: operator
                        106     LOAD_CONST                      8: 'any'
                        108     COMPARE_OP                      55 (!=)
                        112     POP_JUMP_IF_FALSE               30 (to 174)
                        114     LOAD_FAST                       2: operator
                        116     PUSH_NULL                       
                        118     LOAD_CONST                      1: '__pyarmor_assert_15615__'
                        120     LOAD_CONST                      9: 'undefined'   # b'\x81\xf7\x16\x176\xfc\xb7\xdc\x1e\xfe'
                        122     CALL                            1
                        130     COMPARE_OP                      55 (!=)
                        134     POP_JUMP_IF_FALSE               19 (to 174)
                        136     LOAD_FAST                       4: _var_var_5
                        138     LOAD_ATTR                       5: append
                        158     LOAD_CONST                      10: 'operator'
                        160     LOAD_FAST                       2: operator
                        162     BUILD_TUPLE                     2
                        164     CALL                            1
                        172     POP_TOP                         
                        174     LOAD_FAST                       0: self
                        176     LOAD_ATTR                       7: _request
                        196     LOAD_FAST                       0: self
                        198     LOAD_ATTR                       8: gate
                        218     PUSH_NULL                       
                        220     LOAD_CONST                      1: '__pyarmor_assert_15615__'
                        222     LOAD_CONST                      11: 'getCountNumber/'   # b'\x81\xe5\x1d\x07\x10\xf5\xab\xdc\x0f\xd4\x18\xcdn\xe9\xea\xca'
                        224     CALL                            1
                        232     BINARY_OP                       0 (+)
                        236     LOAD_FAST                       4: _var_var_5
                        238     CALL                            2
                        246     STORE_FAST                      5: _var_var_2
                        248     LOAD_GLOBAL                     11: NULL + json
                        258     LOAD_ATTR                       12: loads
                        278     LOAD_FAST                       5: _var_var_2
                        280     LOAD_ATTR                       14: text
                        300     CALL                            1
                        308     STORE_FAST                      6: _var_var_6
                        310     LOAD_CONST                      12: 'tg'
                        312     LOAD_FAST                       6: _var_var_6
                        314     CONTAINS_OP                     0 (in)
                        316     POP_JUMP_IF_FALSE               19 (to 356)
                        318     LOAD_FAST                       6: _var_var_6
                        320     LOAD_CONST                      13: 'price'
                        322     BINARY_SUBSCR                   
                        326     LOAD_FAST                       6: _var_var_6
                        328     LOAD_CONST                      12: 'tg'
                        330     BINARY_SUBSCR                   
                        334     BUILD_LIST                      2
                        336     NOP                             
                        338     NOP                             
                        340     NOP                             
                        342     JUMP_FORWARD                    41 (to 426)
                        344     CALL                            1
                        352     POP_TOP                         
                        354     RETURN_VALUE                    
                        356     NOP                             
                        358     LOAD_CONST                      15: 0
                        360     LOAD_CONST                      15: 0
                        362     BUILD_LIST                      2
                        364     NOP                             
                        366     NOP                             
                        368     NOP                             
                        370     JUMP_FORWARD                    27 (to 426)
                        372     CALL                            1
                        380     POP_TOP                         
                        382     RETURN_VALUE                    
                        384     PUSH_EXC_INFO                   
                        386     POP_TOP                         
                        388     POP_EXCEPT                      
                        390     JUMP_BACKWARD                   17 (to 358)
                        392     COPY                            3
                        394     POP_EXCEPT                      
                        396     RERAISE                         1
                        398     PUSH_EXC_INFO                   
                        400     PUSH_NULL                       
                        402     LOAD_CONST                      14: '__pyarmor_exit_15617__'
                        404     NOP                             
                        406     LOAD_CONST                      3: b'<COAddr>\x05\x00\x00\x1at\x01\x00\x00\x00\x00\x00\x00\x00\x00\x00\x00\x00\x00\x00\x00'
                        408     CALL                            1
                        416     POP_TOP                         
                        418     RERAISE                         0
                        420     COPY                            3
                        422     POP_EXCEPT                      
                        424     RERAISE                         1
                        426     PUSH_NULL                       
                        428     LOAD_CONST                      14: '__pyarmor_exit_15617__'
                        430     LOAD_CONST                      3: b'<COAddr>\x05\x00\x00\x1at\x01\x00\x00\x00\x00\x00\x00\x00\x00\x00\x00\x00\x00\x00\x00'
                        432     BUILD_TUPLE                     1
                        434     CALL_FUNCTION_EX                0
                        436     POP_TOP                         
                        438     RETURN_VALUE                    
                    [Exception Table]
                        30 to 336 -> 384 [0] 
                        356 to 364 -> 398 [0] 
                        384 to 388 -> 392 [1] lasti
                        388 to 398 -> 398 [0] 
                        398 to 420 -> 420 [1] lasti
                None
                [Code]
                    File Name: <frozen program.modules.func.api.vaksms>
                    Object Name: order_number
                    Qualified Name: VakSMS.order_number
                    Arg Count: 3
                    Pos Only Arg Count: 0
                    KW Only Arg Count: 0
                    Stack Size: 6
                    Flags: 0x20000003 (CO_OPTIMIZED | CO_NEWLOCALS | CO_PYARMOR_OBFUSCATED)
                    [Names]
                        'Logs'
                        'PrintLog'
                        'lang'
                        'stop_thread'
                        'is_set'
                        'StopProgram'
                        'apikey'
                        'service'
                        'ref'
                        'append'
                        '_request'
                        'gate'
                        'json'
                        'loads'
                        'text'
                        'str'
                        '_wait'
                        'requests'
                        'exceptions'
                        'ConnectTimeout'
                        'ReadTimeout'
                        'ChunkedEncodingError'
                        'ConnectionError'
                        'RetryError'
                        'BaseException'
                        'logging'
                    [Locals+Names]
                        'self'
                        'country'
                        'operator'
                        '__assert_armored__'
                        '_var_var_5'
                        '_var_var_2'
                        '_var_var_6'
                        '_var_var_4'
                    [Constants]
                        None
                        '__pyarmor_assert_15618__'
                        '__pyarmor_enter_15619__'
                        b'<COAddr>\x05\x00\x00\x1a\x12\x05\x00\x00\x00\x00\x00\x00\x00\x00\x00\x00\x00\x00\x00\x00'
                        'wait_number'   # b"\x81\xf5\x19\x1a'\xc5\xb0\xc7\x16\xf8\x08\xd2"
                        (
                            'message'
                        )
                        'none'
                        'apiKey'
                        'action'
                        'getNumber'   # b'\x81\xe5\x1d\x07\x1d\xef\xb3\xd0\x1e\xe8'
                        'service'
                        'country'
                        'any'
                        'undefined'   # b'\x81\xf7\x16\x176\xfc\xb7\xdc\x1e\xfe'
                        'operator'
                        'getNumber/'   # b'\x81\xe5\x1d\x07\x1d\xef\xb3\xd0\x1e\xe8B'
                        'tel'
                        0
                        'idNum'
                        1
                        '__pyarmor_exit_15620__'
                        'error'
                        'noMoney'
                        'NO_BALANCE'   # b'\x81\xcc7,\x11\xdb\x92\xf35\xd9('
                        'apiKeyNotFound'   # b'\x81\xe3\x08\x1a\x18\xff\xa7\xfc\x14\xee+\xcfy\xe2\xfc'
                        'BAD_KEY'
                    [Disassembly]
                        0       NOP                             
                        2       NOP                             
                        4       PUSH_NULL                       
                        6       LOAD_CONST                      2: '__pyarmor_enter_15619__'
                        8       LOAD_CONST                      3: b'<COAddr>\x05\x00\x00\x1a\x12\x05\x00\x00\x00\x00\x00\x00\x00\x00\x00\x00\x00\x00\x00\x00'
                        10      BUILD_TUPLE                     1
                        12      CALL_FUNCTION_EX                0
                        14      POP_TOP                         
                        16      RESUME                          0
                        18      NOP                             
                        20      NOP                             
                        22      NOP                             
                        24      NOP                             
                        26      NOP                             
                        28      LOAD_GLOBAL                     1: NULL + Logs
                        38      LOAD_ATTR                       2: PrintLog
                        58      LOAD_FAST                       0: self
                        60      LOAD_ATTR                       4: lang
                        80      PUSH_NULL                       
                        82      LOAD_CONST                      1: '__pyarmor_assert_15618__'
                        84      LOAD_CONST                      4: 'wait_number'   # b"\x81\xf5\x19\x1a'\xc5\xb0\xc7\x16\xf8\x08\xd2"
                        86      CALL                            1
                        94      BINARY_SUBSCR                   
                        98      KW_NAMES                        5: ('message',)
                        100     CALL                            1
                        108     POP_TOP                         
                        110     NOP                             
                        112     LOAD_FAST                       0: self
                        114     LOAD_ATTR                       6: stop_thread
                        134     LOAD_ATTR                       9: is_set
                        154     CALL                            0
                        162     POP_JUMP_IF_FALSE               10 (to 184)
                        164     LOAD_GLOBAL                     11: NULL + StopProgram
                        174     CALL                            0
                        182     RAISE_VARARGS                   1
                        184     NOP                             
                        186     LOAD_FAST                       2: operator
                        188     LOAD_CONST                      6: 'none'
                        190     COMPARE_OP                      40 (==)
                        194     POP_JUMP_IF_FALSE               2 (to 200)
                        196     LOAD_CONST                      0: None
                        198     STORE_FAST                      2: operator
                        200     LOAD_CONST                      7: 'apiKey'
                        202     LOAD_FAST                       0: self
                        204     LOAD_ATTR                       12: apikey
                        224     BUILD_TUPLE                     2
                        226     LOAD_CONST                      8: 'action'
                        228     PUSH_NULL                       
                        230     LOAD_CONST                      1: '__pyarmor_assert_15618__'
                        232     LOAD_CONST                      9: 'getNumber'   # b'\x81\xe5\x1d\x07\x1d\xef\xb3\xd0\x1e\xe8'
                        234     CALL                            1
                        242     BUILD_TUPLE                     2
                        244     LOAD_CONST                      10: 'service'
                        246     LOAD_FAST                       0: self
                        248     LOAD_ATTR                       14: service
                        268     BUILD_TUPLE                     2
                        270     LOAD_FAST                       0: self
                        272     LOAD_ATTR                       16: ref
                        292     BUILD_LIST                      4
                        294     STORE_FAST                      4: _var_var_5
                        296     LOAD_FAST                       1: country
                        298     LOAD_CONST                      0: None
                        300     COMPARE_OP                      55 (!=)
                        304     POP_JUMP_IF_FALSE               19 (to 344)
                        306     LOAD_FAST                       4: _var_var_5
                        308     LOAD_ATTR                       19: append
                        328     LOAD_CONST                      11: 'country'
                        330     LOAD_FAST                       1: country
                        332     BUILD_TUPLE                     2
                        334     CALL                            1
                        342     POP_TOP                         
                        344     LOAD_FAST                       2: operator
                        346     LOAD_CONST                      0: None
                        348     COMPARE_OP                      55 (!=)
                        352     POP_JUMP_IF_FALSE               35 (to 424)
                        354     LOAD_FAST                       2: operator
                        356     LOAD_CONST                      12: 'any'
                        358     COMPARE_OP                      55 (!=)
                        362     POP_JUMP_IF_FALSE               30 (to 424)
                        364     LOAD_FAST                       2: operator
                        366     PUSH_NULL                       
                        368     LOAD_CONST                      1: '__pyarmor_assert_15618__'
                        370     LOAD_CONST                      13: 'undefined'   # b'\x81\xf7\x16\x176\xfc\xb7\xdc\x1e\xfe'
                        372     CALL                            1
                        380     COMPARE_OP                      55 (!=)
                        384     POP_JUMP_IF_FALSE               19 (to 424)
                        386     LOAD_FAST                       4: _var_var_5
                        388     LOAD_ATTR                       19: append
                        408     LOAD_CONST                      14: 'operator'
                        410     LOAD_FAST                       2: operator
                        412     BUILD_TUPLE                     2
                        414     CALL                            1
                        422     POP_TOP                         
                        424     LOAD_FAST                       0: self
                        426     LOAD_ATTR                       21: _request
                        446     LOAD_FAST                       0: self
                        448     LOAD_ATTR                       22: gate
                        468     PUSH_NULL                       
                        470     LOAD_CONST                      1: '__pyarmor_assert_15618__'
                        472     LOAD_CONST                      15: 'getNumber/'   # b'\x81\xe5\x1d\x07\x1d\xef\xb3\xd0\x1e\xe8B'
                        474     CALL                            1
                        482     BINARY_OP                       0 (+)
                        486     LOAD_FAST                       4: _var_var_5
                        488     CALL                            2
                        496     STORE_FAST                      5: _var_var_2
                        498     LOAD_GLOBAL                     25: NULL + json
                        508     LOAD_ATTR                       26: loads
                        528     LOAD_FAST                       5: _var_var_2
                        530     LOAD_ATTR                       28: text
                        550     CALL                            1
                        558     STORE_FAST                      6: _var_var_6
                        560     LOAD_CONST                      16: 'tel'
                        562     LOAD_FAST                       6: _var_var_6
                        564     CONTAINS_OP                     0 (in)
                        566     POP_JUMP_IF_FALSE               55 (to 678)
                        568     LOAD_CONST                      17: 0
                        570     LOAD_GLOBAL                     31: NULL + str
                        580     LOAD_FAST                       6: _var_var_6
                        582     LOAD_CONST                      18: 'idNum'
                        584     BINARY_SUBSCR                   
                        588     CALL                            1
                        596     LOAD_GLOBAL                     31: NULL + str
                        606     LOAD_FAST                       6: _var_var_6
                        608     LOAD_CONST                      16: 'tel'
                        610     BINARY_SUBSCR                   
                        614     CALL                            1
                        622     BUILD_LIST                      3
                        624     LOAD_FAST                       0: self
                        626     LOAD_ATTR                       33: _wait
                        646     LOAD_CONST                      19: 1
                        648     CALL                            1
                        656     POP_TOP                         
                        658     NOP                             
                        660     NOP                             
                        662     JUMP_FORWARD                    343 (to 1352)
                        666     CALL                            1
                        674     POP_TOP                         
                        676     RETURN_VALUE                    
                        678     LOAD_FAST                       6: _var_var_6
                        680     LOAD_CONST                      21: 'error'
                        682     BINARY_SUBSCR                   
                        686     LOAD_CONST                      22: 'noMoney'
                        688     COMPARE_OP                      40 (==)
                        692     POP_JUMP_IF_FALSE               34 (to 762)
                        694     PUSH_NULL                       
                        696     LOAD_CONST                      1: '__pyarmor_assert_15618__'
                        698     LOAD_CONST                      23: 'NO_BALANCE'   # b'\x81\xcc7,\x11\xdb\x92\xf35\xd9('
                        700     CALL                            1
                        708     LOAD_FAST                       0: self
                        710     LOAD_ATTR                       33: _wait
                        730     LOAD_CONST                      19: 1
                        732     CALL                            1
                        740     POP_TOP                         
                        742     NOP                             
                        744     NOP                             
                        746     JUMP_FORWARD                    301 (to 1352)
                        750     CALL                            1
                        758     POP_TOP                         
                        760     RETURN_VALUE                    
                        762     LOAD_FAST                       6: _var_var_6
                        764     LOAD_CONST                      21: 'error'
                        766     BINARY_SUBSCR                   
                        770     PUSH_NULL                       
                        772     LOAD_CONST                      1: '__pyarmor_assert_15618__'
                        774     LOAD_CONST                      24: 'apiKeyNotFound'   # b'\x81\xe3\x08\x1a\x18\xff\xa7\xfc\x14\xee+\xcfy\xe2\xfc'
                        776     CALL                            1
                        784     COMPARE_OP                      40 (==)
                        788     POP_JUMP_IF_FALSE               28 (to 846)
                        790     NOP                             
                        792     LOAD_FAST                       0: self
                        794     LOAD_ATTR                       33: _wait
                        814     LOAD_CONST                      19: 1
                        816     CALL                            1
                        824     POP_TOP                         
                        826     LOAD_CONST                      25: 'BAD_KEY'
                        828     NOP                             
                        830     NOP                             
                        832     JUMP_FORWARD                    258 (to 1352)
                        842     POP_TOP                         
                        844     RETURN_CONST                    25: 'BAD_KEY'
                        846     NOP                             
                        848     LOAD_FAST                       0: self
                        850     LOAD_ATTR                       33: _wait
                        870     LOAD_CONST                      19: 1
                        872     CALL                            1
                        880     POP_TOP                         
                        882     JUMP_BACKWARD                   387 (to 112)
                        886     PUSH_EXC_INFO                   
                        888     LOAD_GLOBAL                     34: requests
                        898     LOAD_ATTR                       36: exceptions
                        918     LOAD_ATTR                       38: ConnectTimeout
                        938     CHECK_EXC_MATCH                 
                        940     POP_JUMP_IF_FALSE               3 (to 948)
                        942     POP_TOP                         
                        944     POP_EXCEPT                      
                        946     JUMP_BACKWARD                   50 (to 848)
                        948     LOAD_GLOBAL                     34: requests
                        958     LOAD_ATTR                       36: exceptions
                        978     LOAD_ATTR                       40: ReadTimeout
                        998     CHECK_EXC_MATCH                 
                        1000    POP_JUMP_IF_FALSE               3 (to 1008)
                        1002    POP_TOP                         
                        1004    POP_EXCEPT                      
                        1006    JUMP_BACKWARD                   80 (to 848)
                        1008    LOAD_GLOBAL                     34: requests
                        1018    LOAD_ATTR                       36: exceptions
                        1038    LOAD_ATTR                       42: ChunkedEncodingError
                        1058    CHECK_EXC_MATCH                 
                        1060    POP_JUMP_IF_FALSE               3 (to 1068)
                        1062    POP_TOP                         
                        1064    POP_EXCEPT                      
                        1066    JUMP_BACKWARD                   110 (to 848)
                        1068    LOAD_GLOBAL                     34: requests
                        1078    LOAD_ATTR                       36: exceptions
                        1098    LOAD_ATTR                       44: ConnectionError
                        1118    CHECK_EXC_MATCH                 
                        1120    POP_JUMP_IF_FALSE               3 (to 1128)
                        1122    POP_TOP                         
                        1124    POP_EXCEPT                      
                        1126    JUMP_BACKWARD                   140 (to 848)
                        1128    LOAD_GLOBAL                     34: requests
                        1138    LOAD_ATTR                       36: exceptions
                        1158    LOAD_ATTR                       46: RetryError
                        1178    CHECK_EXC_MATCH                 
                        1180    POP_JUMP_IF_FALSE               3 (to 1188)
                        1182    POP_TOP                         
                        1184    POP_EXCEPT                      
                        1186    JUMP_BACKWARD                   170 (to 848)
                        1188    LOAD_GLOBAL                     10: StopProgram
                        1198    CHECK_EXC_MATCH                 
                        1200    POP_JUMP_IF_FALSE               2 (to 1206)
                        1202    POP_TOP                         
                        1204    RAISE_VARARGS                   0
                        1206    LOAD_GLOBAL                     48: BaseException
                        1216    CHECK_EXC_MATCH                 
                        1218    POP_JUMP_IF_FALSE               26 (to 1272)
                        1220    STORE_FAST                      7: _var_var_4
                        1222    PUSH_NULL                       
                        1224    LOAD_GLOBAL                     51: NULL + logging
                        1234    LOAD_FAST                       7: _var_var_4
                        1236    CALL                            1
                        1244    CALL                            0
                        1252    POP_TOP                         
                        1254    POP_EXCEPT                      
                        1256    LOAD_CONST                      0: None
                        1258    STORE_FAST                      7: _var_var_4
                        1260    DELETE_FAST                     7: _var_var_4
                        1262    JUMP_BACKWARD                   208 (to 848)
                        1264    LOAD_CONST                      0: None
                        1266    STORE_FAST                      7: _var_var_4
                        1268    DELETE_FAST                     7: _var_var_4
                        1270    RERAISE                         1
                        1272    RERAISE                         0
                        1274    COPY                            3
                        1276    POP_EXCEPT                      
                        1278    RERAISE                         1
                        1280    PUSH_EXC_INFO                   
                        1282    LOAD_FAST                       0: self
                        1284    LOAD_ATTR                       33: _wait
                        1304    LOAD_CONST                      19: 1
                        1306    CALL                            1
                        1314    POP_TOP                         
                        1316    RERAISE                         0
                        1318    COPY                            3
                        1320    POP_EXCEPT                      
                        1322    RERAISE                         1
                        1324    PUSH_EXC_INFO                   
                        1326    PUSH_NULL                       
                        1328    LOAD_CONST                      20: '__pyarmor_exit_15620__'
                        1330    NOP                             
                        1332    LOAD_CONST                      3: b'<COAddr>\x05\x00\x00\x1a\x12\x05\x00\x00\x00\x00\x00\x00\x00\x00\x00\x00\x00\x00\x00\x00'
                        1334    CALL                            1
                        1342    POP_TOP                         
                        1344    RERAISE                         0
                        1346    COPY                            3
                        1348    POP_EXCEPT                      
                        1350    RERAISE                         1
                        1352    PUSH_NULL                       
                        1354    LOAD_CONST                      20: '__pyarmor_exit_15620__'
                        1356    LOAD_CONST                      3: b'<COAddr>\x05\x00\x00\x1a\x12\x05\x00\x00\x00\x00\x00\x00\x00\x00\x00\x00\x00\x00\x00\x00'
                        1358    BUILD_TUPLE                     1
                        1360    CALL_FUNCTION_EX                0
                        1362    POP_TOP                         
                        1364    RETURN_VALUE                    
                    [Exception Table]
                        28 to 184 -> 1324 [0] 
                        186 to 624 -> 886 [0] 
                        624 to 658 -> 1324 [0] 
                        678 to 708 -> 886 [0] 
                        708 to 742 -> 1324 [0] 
                        762 to 790 -> 886 [0] 
                        792 to 826 -> 1324 [0] 
                        846 to 848 -> 1280 [0] 
                        848 to 886 -> 1324 [0] 
                        886 to 944 -> 1274 [1] lasti
                        944 to 948 -> 1280 [0] 
                        948 to 1004 -> 1274 [1] lasti
                        1004 to 1008 -> 1280 [0] 
                        1008 to 1064 -> 1274 [1] lasti
                        1064 to 1068 -> 1280 [0] 
                        1068 to 1124 -> 1274 [1] lasti
                        1124 to 1128 -> 1280 [0] 
                        1128 to 1184 -> 1274 [1] lasti
                        1184 to 1188 -> 1280 [0] 
                        1188 to 1222 -> 1274 [1] lasti
                        1222 to 1254 -> 1264 [1] lasti
                        1254 to 1264 -> 1280 [0] 
                        1264 to 1274 -> 1274 [1] lasti
                        1274 to 1280 -> 1280 [0] 
                        1280 to 1318 -> 1318 [1] lasti
                        1318 to 1324 -> 1324 [0] 
                        1324 to 1346 -> 1346 [1] lasti
                [Code]
                    File Name: <frozen program.modules.func.api.vaksms>
                    Object Name: get_code
                    Qualified Name: VakSMS.get_code
                    Arg Count: 5
                    Pos Only Arg Count: 0
                    KW Only Arg Count: 0
                    Stack Size: 8
                    Flags: 0x20000003 (CO_OPTIMIZED | CO_NEWLOCALS | CO_PYARMOR_OBFUSCATED)
                    [Names]
                        'stop_thread'
                        'is_set'
                        'StopProgram'
                        'apikey'
                        '_request'
                        'gate'
                        'json'
                        'loads'
                        'text'
                        'Logs'
                        'PrintLog'
                        'config'
                        'lang'
                        '_wait'
                        'get_code'
                        'str'
                        'requests'
                        'exceptions'
                        'ConnectTimeout'
                        'ReadTimeout'
                        'ChunkedEncodingError'
                        'ConnectionError'
                        'RetryError'
                        'BaseException'
                        'logging'
                    [Locals+Names]
                        'self'
                        'account'
                        'regid'
                        'timeout'
                        'retry'
                        '__assert_armored__'
                        '_var_var_5'
                        '_var_var_2'
                        '_var_var_6'
                        '_var_var_11'
                        '_var_var_12'
                        '_var_var_4'
                    [Constants]
                        None
                        '__pyarmor_assert_15621__'
                        '__pyarmor_enter_15622__'
                        b'<COAddr>\x05\x00\x00\x1a:\x04\x00\x00\x00\x00\x00\x00\x00\x00\x00\x00\x00\x00\x00\x00'
                        'apiKey'
                        'idNum'
                        'getSmsCode/'   # b'\x81\xe5\x1d\x07\x00\xf7\xad\xf1\x14\xfe\x08\x8f'
                        'smsCode'
                        1
                        10
                        0
                        'times_up'
                        'сек'
                        (
                            'config'
                            'account'
                            'message'
                            'param'
                            'end'
                        )
                        '__pyarmor_exit_15623__'
                        'TIME_OUT'
                        'waiting_code_repeat'   # b"\x81\xf5\x19\x1a'\xf3\xb0\xd5$\xf9\x02\xc4i\xd3\xea\x80\x1fX\xba\xb3"
                    [Disassembly]
                        0       NOP                             
                        2       NOP                             
                        4       PUSH_NULL                       
                        6       LOAD_CONST                      2: '__pyarmor_enter_15622__'
                        8       LOAD_CONST                      3: b'<COAddr>\x05\x00\x00\x1a:\x04\x00\x00\x00\x00\x00\x00\x00\x00\x00\x00\x00\x00\x00\x00'
                        10      BUILD_TUPLE                     1
                        12      CALL_FUNCTION_EX                0
                        14      POP_TOP                         
                        16      RESUME                          0
                        18      NOP                             
                        20      NOP                             
                        22      NOP                             
                        24      NOP                             
                        26      NOP                             
                        28      NOP                             
                        30      NOP                             
                        32      LOAD_FAST                       0: self
                        34      LOAD_ATTR                       0: stop_thread
                        54      LOAD_ATTR                       3: is_set
                        74      CALL                            0
                        82      POP_JUMP_IF_FALSE               10 (to 104)
                        84      LOAD_GLOBAL                     5: NULL + StopProgram
                        94      CALL                            0
                        102     RAISE_VARARGS                   1
                        104     LOAD_CONST                      4: 'apiKey'
                        106     LOAD_FAST                       0: self
                        108     LOAD_ATTR                       6: apikey
                        128     BUILD_TUPLE                     2
                        130     LOAD_CONST                      5: 'idNum'
                        132     LOAD_FAST                       2: regid
                        134     BUILD_TUPLE                     2
                        136     BUILD_TUPLE                     2
                        138     STORE_FAST                      6: _var_var_5
                        140     LOAD_FAST                       0: self
                        142     LOAD_ATTR                       9: _request
                        162     LOAD_FAST                       0: self
                        164     LOAD_ATTR                       10: gate
                        184     PUSH_NULL                       
                        186     LOAD_CONST                      1: '__pyarmor_assert_15621__'
                        188     LOAD_CONST                      6: 'getSmsCode/'   # b'\x81\xe5\x1d\x07\x00\xf7\xad\xf1\x14\xfe\x08\x8f'
                        190     CALL                            1
                        198     BINARY_OP                       0 (+)
                        202     LOAD_FAST                       6: _var_var_5
                        204     CALL                            2
                        212     STORE_FAST                      7: _var_var_2
                        214     LOAD_GLOBAL                     13: NULL + json
                        224     LOAD_ATTR                       14: loads
                        244     LOAD_FAST                       7: _var_var_2
                        246     LOAD_ATTR                       16: text
                        266     CALL                            1
                        274     STORE_FAST                      8: _var_var_6
                        276     LOAD_CONST                      7: 'smsCode'
                        278     LOAD_FAST                       8: _var_var_6
                        280     CONTAINS_OP                     0 (in)
                        282     POP_JUMP_IF_FALSE               212 (to 708)
                        284     LOAD_FAST                       8: _var_var_6
                        286     LOAD_CONST                      7: 'smsCode'
                        288     BINARY_SUBSCR                   
                        292     LOAD_CONST                      0: None
                        294     COMPARE_OP                      40 (==)
                        298     POP_JUMP_IF_FALSE               181 (to 662)
                        300     LOAD_FAST                       4: retry
                        302     LOAD_CONST                      8: 1
                        304     BINARY_OP                       13 (+=)
                        308     STORE_FAST                      4: retry
                        310     LOAD_CONST                      9: 10
                        312     STORE_FAST                      9: _var_var_11
                        314     LOAD_FAST                       3: timeout
                        316     LOAD_FAST                       4: retry
                        318     LOAD_FAST                       9: _var_var_11
                        320     BINARY_OP                       5 (*)
                        324     BINARY_OP                       10 (-)
                        328     STORE_FAST                      10: _var_var_12
                        330     LOAD_FAST                       10: _var_var_12
                        332     LOAD_CONST                      10: 0
                        334     COMPARE_OP                      26 (<=)
                        338     POP_JUMP_IF_FALSE               60 (to 460)
                        340     LOAD_GLOBAL                     19: NULL + Logs
                        350     LOAD_ATTR                       20: PrintLog
                        370     LOAD_FAST                       0: self
                        372     LOAD_ATTR                       22: config
                        392     LOAD_FAST                       1: account
                        394     LOAD_FAST                       0: self
                        396     LOAD_ATTR                       24: lang
                        416     LOAD_CONST                      11: 'times_up'
                        418     BINARY_SUBSCR                   
                        422     LOAD_FAST                       3: timeout
                        424     LOAD_CONST                      12: 'сек'
                        426     KW_NAMES                        13: ('config', 'account', 'message', 'param', 'end')
                        428     CALL                            5
                        436     POP_TOP                         
                        438     NOP                             
                        440     LOAD_CONST                      15: 'TIME_OUT'
                        442     NOP                             
                        444     NOP                             
                        446     JUMP_FORWARD                    343 (to 1136)
                        456     POP_TOP                         
                        458     RETURN_CONST                    15: 'TIME_OUT'
                        460     LOAD_GLOBAL                     19: NULL + Logs
                        470     LOAD_ATTR                       20: PrintLog
                        490     LOAD_FAST                       0: self
                        492     LOAD_ATTR                       22: config
                        512     LOAD_FAST                       1: account
                        514     LOAD_FAST                       0: self
                        516     LOAD_ATTR                       24: lang
                        536     PUSH_NULL                       
                        538     LOAD_CONST                      1: '__pyarmor_assert_15621__'
                        540     LOAD_CONST                      16: 'waiting_code_repeat'   # b"\x81\xf5\x19\x1a'\xf3\xb0\xd5$\xf9\x02\xc4i\xd3\xea\x80\x1fX\xba\xb3"
                        542     CALL                            1
                        550     BINARY_SUBSCR                   
                        554     LOAD_FAST                       9: _var_var_11
                        556     LOAD_CONST                      12: 'сек'
                        558     KW_NAMES                        13: ('config', 'account', 'message', 'param', 'end')
                        560     CALL                            5
                        568     POP_TOP                         
                        570     LOAD_FAST                       0: self
                        572     LOAD_ATTR                       27: _wait
                        592     LOAD_FAST                       9: _var_var_11
                        594     CALL                            1
                        602     POP_TOP                         
                        604     LOAD_FAST                       0: self
                        606     LOAD_ATTR                       29: get_code
                        626     LOAD_FAST                       1: account
                        628     LOAD_FAST                       2: regid
                        630     LOAD_FAST                       3: timeout
                        632     LOAD_FAST                       4: retry
                        634     CALL                            4
                        642     NOP                             
                        644     NOP                             
                        646     NOP                             
                        648     JUMP_FORWARD                    243 (to 1136)
                        650     CALL                            1
                        658     POP_TOP                         
                        660     RETURN_VALUE                    
                        662     LOAD_GLOBAL                     31: NULL + str
                        672     LOAD_FAST                       8: _var_var_6
                        674     LOAD_CONST                      7: 'smsCode'
                        676     BINARY_SUBSCR                   
                        680     CALL                            1
                        688     NOP                             
                        690     NOP                             
                        692     NOP                             
                        694     JUMP_FORWARD                    220 (to 1136)
                        696     CALL                            1
                        704     POP_TOP                         
                        706     RETURN_VALUE                    
                        708     NOP                             
                        710     JUMP_BACKWARD                   342 (to 30)
                        714     PUSH_EXC_INFO                   
                        716     LOAD_GLOBAL                     32: requests
                        726     LOAD_ATTR                       34: exceptions
                        746     LOAD_ATTR                       36: ConnectTimeout
                        766     CHECK_EXC_MATCH                 
                        768     POP_JUMP_IF_FALSE               3 (to 776)
                        770     POP_TOP                         
                        772     POP_EXCEPT                      
                        774     JUMP_BACKWARD                   33 (to 710)
                        776     LOAD_GLOBAL                     32: requests
                        786     LOAD_ATTR                       34: exceptions
                        806     LOAD_ATTR                       38: ReadTimeout
                        826     CHECK_EXC_MATCH                 
                        828     POP_JUMP_IF_FALSE               3 (to 836)
                        830     POP_TOP                         
                        832     POP_EXCEPT                      
                        834     JUMP_BACKWARD                   63 (to 710)
                        836     LOAD_GLOBAL                     32: requests
                        846     LOAD_ATTR                       34: exceptions
                        866     LOAD_ATTR                       40: ChunkedEncodingError
                        886     CHECK_EXC_MATCH                 
                        888     POP_JUMP_IF_FALSE               3 (to 896)
                        890     POP_TOP                         
                        892     POP_EXCEPT                      
                        894     JUMP_BACKWARD                   93 (to 710)
                        896     LOAD_GLOBAL                     32: requests
                        906     LOAD_ATTR                       34: exceptions
                        926     LOAD_ATTR                       42: ConnectionError
                        946     CHECK_EXC_MATCH                 
                        948     POP_JUMP_IF_FALSE               3 (to 956)
                        950     POP_TOP                         
                        952     POP_EXCEPT                      
                        954     JUMP_BACKWARD                   123 (to 710)
                        956     LOAD_GLOBAL                     32: requests
                        966     LOAD_ATTR                       34: exceptions
                        986     LOAD_ATTR                       44: RetryError
                        1006    CHECK_EXC_MATCH                 
                        1008    POP_JUMP_IF_FALSE               3 (to 1016)
                        1010    POP_TOP                         
                        1012    POP_EXCEPT                      
                        1014    JUMP_BACKWARD                   153 (to 710)
                        1016    LOAD_GLOBAL                     4: StopProgram
                        1026    CHECK_EXC_MATCH                 
                        1028    POP_JUMP_IF_FALSE               2 (to 1034)
                        1030    POP_TOP                         
                        1032    RAISE_VARARGS                   0
                        1034    LOAD_GLOBAL                     46: BaseException
                        1044    CHECK_EXC_MATCH                 
                        1046    POP_JUMP_IF_FALSE               26 (to 1100)
                        1048    STORE_FAST                      11: _var_var_4
                        1050    PUSH_NULL                       
                        1052    LOAD_GLOBAL                     49: NULL + logging
                        1062    LOAD_FAST                       11: _var_var_4
                        1064    CALL                            1
                        1072    CALL                            0
                        1080    POP_TOP                         
                        1082    POP_EXCEPT                      
                        1084    LOAD_CONST                      0: None
                        1086    STORE_FAST                      11: _var_var_4
                        1088    DELETE_FAST                     11: _var_var_4
                        1090    JUMP_BACKWARD                   191 (to 710)
                        1092    LOAD_CONST                      0: None
                        1094    STORE_FAST                      11: _var_var_4
                        1096    DELETE_FAST                     11: _var_var_4
                        1098    RERAISE                         1
                        1100    RERAISE                         0
                        1102    COPY                            3
                        1104    POP_EXCEPT                      
                        1106    RERAISE                         1
                        1108    PUSH_EXC_INFO                   
                        1110    PUSH_NULL                       
                        1112    LOAD_CONST                      14: '__pyarmor_exit_15623__'
                        1114    NOP                             
                        1116    LOAD_CONST                      3: b'<COAddr>\x05\x00\x00\x1a:\x04\x00\x00\x00\x00\x00\x00\x00\x00\x00\x00\x00\x00\x00\x00'
                        1118    CALL                            1
                        1126    POP_TOP                         
                        1128    RERAISE                         0
                        1130    COPY                            3
                        1132    POP_EXCEPT                      
                        1134    RERAISE                         1
                        1136    PUSH_NULL                       
                        1138    LOAD_CONST                      14: '__pyarmor_exit_15623__'
                        1140    LOAD_CONST                      3: b'<COAddr>\x05\x00\x00\x1a:\x04\x00\x00\x00\x00\x00\x00\x00\x00\x00\x00\x00\x00\x00\x00'
                        1142    BUILD_TUPLE                     1
                        1144    CALL_FUNCTION_EX                0
                        1146    POP_TOP                         
                        1148    RETURN_VALUE                    
                    [Exception Table]
                        28 to 30 -> 1108 [0] 
                        32 to 438 -> 714 [0] 
                        460 to 642 -> 714 [0] 
                        662 to 688 -> 714 [0] 
                        708 to 714 -> 1108 [0] 
                        714 to 772 -> 1102 [1] lasti
                        772 to 776 -> 1108 [0] 
                        776 to 832 -> 1102 [1] lasti
                        832 to 836 -> 1108 [0] 
                        836 to 892 -> 1102 [1] lasti
                        892 to 896 -> 1108 [0] 
                        896 to 952 -> 1102 [1] lasti
                        952 to 956 -> 1108 [0] 
                        956 to 1012 -> 1102 [1] lasti
                        1012 to 1016 -> 1108 [0] 
                        1016 to 1050 -> 1102 [1] lasti
                        1050 to 1082 -> 1092 [1] lasti
                        1082 to 1092 -> 1108 [0] 
                        1092 to 1102 -> 1102 [1] lasti
                        1102 to 1108 -> 1108 [0] 
                        1108 to 1130 -> 1130 [1] lasti
                [Code]
                    File Name: <frozen program.modules.func.api.vaksms>
                    Object Name: set_status
                    Qualified Name: VakSMS.set_status
                    Arg Count: 3
                    Pos Only Arg Count: 0
                    KW Only Arg Count: 0
                    Stack Size: 6
                    Flags: 0x20000003 (CO_OPTIMIZED | CO_NEWLOCALS | CO_PYARMOR_OBFUSCATED)
                    [Names]
                        'stop_thread'
                        'is_set'
                        'StopProgram'
                        'apikey'
                        '_request'
                        'gate'
                        'json'
                        'loads'
                        'text'
                        'requests'
                        'exceptions'
                        'ConnectTimeout'
                        'ReadTimeout'
                        'ChunkedEncodingError'
                        'ConnectionError'
                        'RetryError'
                        'BaseException'
                        'logging'
                        '_wait'
                    [Locals+Names]
                        'self'
                        'regid'
                        'status'
                        '__assert_armored__'
                        '_var_var_5'
                        '_var_var_2'
                        '_var_var_6'
                        '_var_var_4'
                    [Constants]
                        None
                        '__pyarmor_assert_15624__'
                        '__pyarmor_enter_15625__'
                        b'<COAddr>\x07\x00\x00\x1a\x04\x03\x00\x00\x00\x00\x00\x00\x00\x00\x00\x00\x00\x00\x00\x00'
                        True
                        'apiKey'
                        'idNum'
                        'status'
                        'setStatus/'   # b'\x81\xf1\x1d\x07\x00\xee\xbf\xc6\x0e\xe9B'
                        'ready'
                        'update'
                        '__pyarmor_exit_15626__'
                        False
                        1
                    [Disassembly]
                        0       NOP                             
                        2       NOP                             
                        4       PUSH_NULL                       
                        6       LOAD_CONST                      2: '__pyarmor_enter_15625__'
                        8       LOAD_CONST                      3: b'<COAddr>\x07\x00\x00\x1a\x04\x03\x00\x00\x00\x00\x00\x00\x00\x00\x00\x00\x00\x00\x00\x00'
                        10      BUILD_TUPLE                     1
                        12      CALL_FUNCTION_EX                0
                        14      POP_TOP                         
                        16      RESUME                          0
                        18      NOP                             
                        20      NOP                             
                        22      NOP                             
                        24      NOP                             
                        26      NOP                             
                        28      NOP                             
                        30      NOP                             
                        32      LOAD_FAST                       0: self
                        34      LOAD_ATTR                       0: stop_thread
                        54      LOAD_ATTR                       3: is_set
                        74      CALL                            0
                        82      POP_JUMP_IF_FALSE               10 (to 104)
                        84      LOAD_GLOBAL                     5: NULL + StopProgram
                        94      CALL                            0
                        102     RAISE_VARARGS                   1
                        104     LOAD_CONST                      5: 'apiKey'
                        106     LOAD_FAST                       0: self
                        108     LOAD_ATTR                       6: apikey
                        128     BUILD_TUPLE                     2
                        130     LOAD_CONST                      6: 'idNum'
                        132     LOAD_FAST                       1: regid
                        134     BUILD_TUPLE                     2
                        136     LOAD_CONST                      7: 'status'
                        138     LOAD_FAST                       2: status
                        140     BUILD_TUPLE                     2
                        142     BUILD_TUPLE                     3
                        144     STORE_FAST                      4: _var_var_5
                        146     LOAD_FAST                       0: self
                        148     LOAD_ATTR                       9: _request
                        168     LOAD_FAST                       0: self
                        170     LOAD_ATTR                       10: gate
                        190     PUSH_NULL                       
                        192     LOAD_CONST                      1: '__pyarmor_assert_15624__'
                        194     LOAD_CONST                      8: 'setStatus/'   # b'\x81\xf1\x1d\x07\x00\xee\xbf\xc6\x0e\xe9B'
                        196     CALL                            1
                        204     BINARY_OP                       0 (+)
                        208     LOAD_FAST                       4: _var_var_5
                        210     CALL                            2
                        218     STORE_FAST                      5: _var_var_2
                        220     LOAD_GLOBAL                     13: NULL + json
                        230     LOAD_ATTR                       14: loads
                        250     LOAD_FAST                       5: _var_var_2
                        252     LOAD_ATTR                       16: text
                        272     CALL                            1
                        280     STORE_FAST                      6: _var_var_6
                        282     LOAD_CONST                      7: 'status'
                        284     LOAD_FAST                       6: _var_var_6
                        286     CONTAINS_OP                     0 (in)
                        288     POP_JUMP_IF_FALSE               38 (to 366)
                        290     LOAD_FAST                       6: _var_var_6
                        292     LOAD_CONST                      7: 'status'
                        294     BINARY_SUBSCR                   
                        298     LOAD_CONST                      9: 'ready'
                        300     COMPARE_OP                      40 (==)
                        304     POP_JUMP_IF_TRUE                8 (to 322)
                        306     LOAD_FAST                       6: _var_var_6
                        308     LOAD_CONST                      7: 'status'
                        310     BINARY_SUBSCR                   
                        314     LOAD_CONST                      10: 'update'
                        316     COMPARE_OP                      40 (==)
                        320     POP_JUMP_IF_FALSE               11 (to 344)
                        322     NOP                             
                        324     LOAD_CONST                      4: True
                        326     NOP                             
                        328     NOP                             
                        330     NOP                             
                        332     JUMP_FORWARD                    246 (to 826)
                        340     POP_TOP                         
                        342     RETURN_CONST                    4: True
                        344     NOP                             
                        346     LOAD_CONST                      12: False
                        348     NOP                             
                        350     NOP                             
                        352     NOP                             
                        354     JUMP_FORWARD                    235 (to 826)
                        362     POP_TOP                         
                        364     RETURN_CONST                    12: False
                        366     NOP                             
                        368     LOAD_FAST                       0: self
                        370     LOAD_ATTR                       37: _wait
                        390     LOAD_CONST                      13: 1
                        392     CALL                            1
                        400     POP_TOP                         
                        402     JUMP_BACKWARD                   187 (to 30)
                        404     PUSH_EXC_INFO                   
                        406     LOAD_GLOBAL                     18: requests
                        416     LOAD_ATTR                       20: exceptions
                        436     LOAD_ATTR                       22: ConnectTimeout
                        456     CHECK_EXC_MATCH                 
                        458     POP_JUMP_IF_FALSE               3 (to 466)
                        460     POP_TOP                         
                        462     POP_EXCEPT                      
                        464     JUMP_BACKWARD                   49 (to 368)
                        466     LOAD_GLOBAL                     18: requests
                        476     LOAD_ATTR                       20: exceptions
                        496     LOAD_ATTR                       24: ReadTimeout
                        516     CHECK_EXC_MATCH                 
                        518     POP_JUMP_IF_FALSE               3 (to 526)
                        520     POP_TOP                         
                        522     POP_EXCEPT                      
                        524     JUMP_BACKWARD                   79 (to 368)
                        526     LOAD_GLOBAL                     18: requests
                        536     LOAD_ATTR                       20: exceptions
                        556     LOAD_ATTR                       26: ChunkedEncodingError
                        576     CHECK_EXC_MATCH                 
                        578     POP_JUMP_IF_FALSE               3 (to 586)
                        580     POP_TOP                         
                        582     POP_EXCEPT                      
                        584     JUMP_BACKWARD                   109 (to 368)
                        586     LOAD_GLOBAL                     18: requests
                        596     LOAD_ATTR                       20: exceptions
                        616     LOAD_ATTR                       28: ConnectionError
                        636     CHECK_EXC_MATCH                 
                        638     POP_JUMP_IF_FALSE               3 (to 646)
                        640     POP_TOP                         
                        642     POP_EXCEPT                      
                        644     JUMP_BACKWARD                   139 (to 368)
                        646     LOAD_GLOBAL                     18: requests
                        656     LOAD_ATTR                       20: exceptions
                        676     LOAD_ATTR                       30: RetryError
                        696     CHECK_EXC_MATCH                 
                        698     POP_JUMP_IF_FALSE               3 (to 706)
                        700     POP_TOP                         
                        702     POP_EXCEPT                      
                        704     JUMP_BACKWARD                   169 (to 368)
                        706     LOAD_GLOBAL                     4: StopProgram
                        716     CHECK_EXC_MATCH                 
                        718     POP_JUMP_IF_FALSE               2 (to 724)
                        720     POP_TOP                         
                        722     RAISE_VARARGS                   0
                        724     LOAD_GLOBAL                     32: BaseException
                        734     CHECK_EXC_MATCH                 
                        736     POP_JUMP_IF_FALSE               26 (to 790)
                        738     STORE_FAST                      7: _var_var_4
                        740     PUSH_NULL                       
                        742     LOAD_GLOBAL                     35: NULL + logging
                        752     LOAD_FAST                       7: _var_var_4
                        754     CALL                            1
                        762     CALL                            0
                        770     POP_TOP                         
                        772     POP_EXCEPT                      
                        774     LOAD_CONST                      0: None
                        776     STORE_FAST                      7: _var_var_4
                        778     DELETE_FAST                     7: _var_var_4
                        780     JUMP_BACKWARD                   207 (to 368)
                        782     LOAD_CONST                      0: None
                        784     STORE_FAST                      7: _var_var_4
                        786     DELETE_FAST                     7: _var_var_4
                        788     RERAISE                         1
                        790     RERAISE                         0
                        792     COPY                            3
                        794     POP_EXCEPT                      
                        796     RERAISE                         1
                        798     PUSH_EXC_INFO                   
                        800     PUSH_NULL                       
                        802     LOAD_CONST                      11: '__pyarmor_exit_15626__'
                        804     NOP                             
                        806     LOAD_CONST                      3: b'<COAddr>\x07\x00\x00\x1a\x04\x03\x00\x00\x00\x00\x00\x00\x00\x00\x00\x00\x00\x00\x00\x00'
                        808     CALL                            1
                        816     POP_TOP                         
                        818     RERAISE                         0
                        820     COPY                            3
                        822     POP_EXCEPT                      
                        824     RERAISE                         1
                        826     PUSH_NULL                       
                        828     LOAD_CONST                      11: '__pyarmor_exit_15626__'
                        830     LOAD_CONST                      3: b'<COAddr>\x07\x00\x00\x1a\x04\x03\x00\x00\x00\x00\x00\x00\x00\x00\x00\x00\x00\x00\x00\x00'
                        832     BUILD_TUPLE                     1
                        834     CALL_FUNCTION_EX                0
                        836     POP_TOP                         
                        838     RETURN_VALUE                    
                    [Exception Table]
                        28 to 30 -> 798 [0] 
                        32 to 322 -> 404 [0] 
                        366 to 404 -> 798 [0] 
                        404 to 462 -> 792 [1] lasti
                        462 to 466 -> 798 [0] 
                        466 to 522 -> 792 [1] lasti
                        522 to 526 -> 798 [0] 
                        526 to 582 -> 792 [1] lasti
                        582 to 586 -> 798 [0] 
                        586 to 642 -> 792 [1] lasti
                        642 to 646 -> 798 [0] 
                        646 to 702 -> 792 [1] lasti
                        702 to 706 -> 798 [0] 
                        706 to 740 -> 792 [1] lasti
                        740 to 772 -> 782 [1] lasti
                        772 to 782 -> 798 [0] 
                        782 to 792 -> 792 [1] lasti
                        792 to 798 -> 798 [0] 
                        798 to 820 -> 820 [1] lasti
                '__pyarmor_exit_15596__'
                (
                    10
                )
                (
                    None
                )
                (
                    0
                )
            [Disassembly]
                0       NOP                             
                2       LOAD_NAME                       0: __name__
                4       STORE_NAME                      1: __module__
                6       LOAD_CONST                      0: 'VakSMS'
                8       STORE_NAME                      2: __qualname__
                10      NOP                             
                12      PUSH_NULL                       
                14      LOAD_CONST                      2: '__pyarmor_enter_15595__'
                16      LOAD_CONST                      3: b'<COAddr>\x05\x00\x00"f\x00\x00\x00\x00\x00\x00\x00\x00\x00\x00\x00\x00\x00\x00\x00'
                18      BUILD_TUPLE                     1
                20      CALL_FUNCTION_EX                0
                22      POP_TOP                         
                24      RESUME                          0
                26      NOP                             
                28      NOP                             
                30      NOP                             
                32      NOP                             
                34      NOP                             
                36      PUSH_NULL                       
                38      LOAD_NAME                       4: Event
                40      CALL                            0
                48      BUILD_TUPLE                     1
                50      LOAD_CONST                      4: <CODE> __init__
                52      MAKE_FUNCTION                   1
                54      STORE_NAME                      5: __init__
                56      LOAD_CONST                      5: <CODE> _request
                58      MAKE_FUNCTION                   0
                60      STORE_NAME                      6: _request
                62      LOAD_CONST                      16: (10,)
                64      LOAD_CONST                      6: <CODE> _wait
                66      MAKE_FUNCTION                   1
                68      STORE_NAME                      7: _wait
                70      LOAD_CONST                      7: <CODE> get_balance
                72      MAKE_FUNCTION                   0
                74      STORE_NAME                      8: get_balance
                76      LOAD_CONST                      8: <CODE> get_country
                78      MAKE_FUNCTION                   0
                80      STORE_NAME                      9: get_country
                82      LOAD_CONST                      9: <CODE> get_operators
                84      MAKE_FUNCTION                   0
                86      STORE_NAME                      10: get_operators
                88      LOAD_CONST                      10: <CODE> get_price
                90      MAKE_FUNCTION                   0
                92      STORE_NAME                      11: get_price
                94      LOAD_CONST                      17: (None,)
                96      LOAD_CONST                      12: <CODE> order_number
                98      MAKE_FUNCTION                   1
                100     STORE_NAME                      12: order_number
                102     LOAD_CONST                      18: (0,)
                104     LOAD_CONST                      13: <CODE> get_code
                106     MAKE_FUNCTION                   1
                108     STORE_NAME                      13: get_code
                110     LOAD_CONST                      14: <CODE> set_status
                112     MAKE_FUNCTION                   0
                114     STORE_NAME                      14: set_status
                116     LOAD_CONST                      11: None
                118     NOP                             
                120     NOP                             
                122     NOP                             
                124     JUMP_FORWARD                    19 (to 164)
                132     POP_TOP                         
                134     RETURN_CONST                    11: None
                136     PUSH_EXC_INFO                   
                138     PUSH_NULL                       
                140     LOAD_CONST                      15: '__pyarmor_exit_15596__'
                142     NOP                             
                144     LOAD_CONST                      3: b'<COAddr>\x05\x00\x00"f\x00\x00\x00\x00\x00\x00\x00\x00\x00\x00\x00\x00\x00\x00\x00'
                146     CALL                            1
                154     POP_TOP                         
                156     RERAISE                         0
                158     COPY                            3
                160     POP_EXCEPT                      
                162     RERAISE                         1
                164     PUSH_NULL                       
                166     LOAD_CONST                      15: '__pyarmor_exit_15596__'
                168     LOAD_CONST                      3: b'<COAddr>\x05\x00\x00"f\x00\x00\x00\x00\x00\x00\x00\x00\x00\x00\x00\x00\x00\x00\x00'
                170     BUILD_TUPLE                     1
                172     CALL_FUNCTION_EX                0
                174     POP_TOP                         
                176     RETURN_VALUE                    
            [Exception Table]
                36 to 116 -> 136 [0] 
                136 to 158 -> 158 [1] lasti
        'VakSMS'
        '__pyarmor_exit_15593__'
    [Disassembly]
        0       NOP                             
        2       NOP                             
        4       PUSH_NULL                       
        6       LOAD_CONST                      1: '__pyarmor_enter_15592__'
        8       LOAD_CONST                      2: b'<COAddr>\x05\x00\x00\x1a\x80\x00\x00\x00\x00\x00\x00\x00\x00\x00\x00\x00\x00\x00\x00\x00'
        10      BUILD_TUPLE                     1
        12      CALL_FUNCTION_EX                0
        14      POP_TOP                         
        16      RESUME                          0
        18      NOP                             
        20      NOP                             
        22      NOP                             
        24      NOP                             
        26      LOAD_CONST                      3: 0
        28      LOAD_CONST                      4: None
        30      IMPORT_NAME                     1: json
        32      STORE_NAME                      1: json
        34      LOAD_CONST                      3: 0
        36      LOAD_CONST                      4: None
        38      IMPORT_NAME                     2: time
        40      STORE_NAME                      2: time
        42      LOAD_CONST                      3: 0
        44      LOAD_CONST                      4: None
        46      IMPORT_NAME                     3: random
        48      STORE_NAME                      3: random
        50      LOAD_CONST                      3: 0
        52      LOAD_CONST                      4: None
        54      IMPORT_NAME                     4: requests
        56      STORE_NAME                      4: requests
        58      LOAD_CONST                      3: 0
        60      LOAD_CONST                      5: ('Event',)
        62      IMPORT_NAME                     5: threading
        64      IMPORT_FROM                     6: Event
        66      STORE_NAME                      6: Event
        68      POP_TOP                         
        70      LOAD_CONST                      3: 0
        72      LOAD_CONST                      6: ('StopProgram',)
        74      IMPORT_NAME                     7: multithon.errors
        76      IMPORT_FROM                     8: StopProgram
        78      STORE_NAME                      8: StopProgram
        80      POP_TOP                         
        82      LOAD_CONST                      3: 0
        84      LOAD_CONST                      7: ('HTTPAdapter', 'Retry')
        86      IMPORT_NAME                     9: requests.adapters
        88      IMPORT_FROM                     10: HTTPAdapter
        90      STORE_NAME                      10: HTTPAdapter
        92      IMPORT_FROM                     11: Retry
        94      STORE_NAME                      11: Retry
        96      POP_TOP                         
        98      LOAD_CONST                      3: 0
        100     LOAD_CONST                      8: ('Logs', 'logging')
        102     IMPORT_NAME                     12: program.static_classes
        104     IMPORT_FROM                     13: Logs
        106     STORE_NAME                      13: Logs
        108     IMPORT_FROM                     14: logging
        110     STORE_NAME                      14: logging
        112     POP_TOP                         
        114     PUSH_NULL                       
        116     LOAD_BUILD_CLASS                
        118     LOAD_CONST                      9: <CODE> VakSMS
        120     MAKE_FUNCTION                   0
        122     LOAD_CONST                      10: 'VakSMS'
        124     CALL                            2
        132     STORE_NAME                      15: VakSMS
        134     LOAD_CONST                      4: None
        136     NOP                             
        138     NOP                             
        140     NOP                             
        142     JUMP_FORWARD                    19 (to 182)
        150     POP_TOP                         
        152     RETURN_CONST                    4: None
        154     PUSH_EXC_INFO                   
        156     PUSH_NULL                       
        158     LOAD_CONST                      11: '__pyarmor_exit_15593__'
        160     NOP                             
        162     LOAD_CONST                      2: b'<COAddr>\x05\x00\x00\x1a\x80\x00\x00\x00\x00\x00\x00\x00\x00\x00\x00\x00\x00\x00\x00\x00'
        164     CALL                            1
        172     POP_TOP                         
        174     RERAISE                         0
        176     COPY                            3
        178     POP_EXCEPT                      
        180     RERAISE                         1
        182     PUSH_NULL                       
        184     LOAD_CONST                      11: '__pyarmor_exit_15593__'
        186     LOAD_CONST                      2: b'<COAddr>\x05\x00\x00\x1a\x80\x00\x00\x00\x00\x00\x00\x00\x00\x00\x00\x00\x00\x00\x00\x00'
        188     BUILD_TUPLE                     1
        190     CALL_FUNCTION_EX                0
        192     POP_TOP                         
        194     RETURN_VALUE                    
    [Exception Table]
        26 to 134 -> 154 [0] 
        154 to 176 -> 176 [1] lasti
