#decoded by lolz.live/mrpenny / t.me/zeus_jackpot
# ================================
# Примечания по Pyarmor:
# - Байт-код и объекты кода Pyarmor соответствуют стандартному Python, но присутствуют специальные вызовы функций среды выполнения (runtime) Pyarmor.
# - Вызовы строк — это не ошибки, а маркеры, которые обрабатываются Pyarmor во время выполнения.
#
# Руководство по декомпиляции (без среды выполнения):
# 1. Игнорируйте зашифрованные байты после `#`; используйте только строку до `#`.
# 2. Удалите "__pyarmor_enter_xxx__"(b"<COAddr>...") и "__pyarmor_leave_xxx__"(b"<COAddr>...") (пролог/эпилог).
# 3. "__pyarmor_assert_xxx__"(A) не является настоящим оператором assert.
#    - Если A — это имя или читаемая строка: замените на A.
#    - Если A — это (X, "Y"): замените на X.Y.
#    - Если A — это (X, "Y", Z): замените на X.Y = Z.
#    - В противном случае: выберите наиболее подходящую/логичную замену.
# 4. "__pyarmor_bcc_xxx__"(...) указывает на машинный (нативный) код; тело функции недоступно. Добавьте комментарий.
# ================================

[Code]
    File Name: <frozen program.static_classes.memory>
    Object Name: <module>
    Qualified Name: <module>
    Arg Count: 0
    Pos Only Arg Count: 0
    KW Only Arg Count: 0
    Stack Size: 5
    Flags: 0x20000000 (CO_PYARMOR_OBFUSCATED)
    [Names]
        '__assert_armored__'
        'time'
        'base64'
        'datetime'
        'Crypto.Cipher'
        'AES'
        'Crypto.Hash'
        'SHA256'
        'Crypto.Util.Padding'
        'pad'
        'unpad'
        'fingerprint'
        'get_fingerprint'
        'get_lic_key'
        'FileProtector'
        'memory_set_module'
        'int'
        'bool'
        'check_module'
        'memory_set_lang'
        'memory_get_lang'
        'memory_set_switcher'
        'memory_check_switcher'
        'memory_set_pid'
        'memory_check_pid'
        'memory_remove_pid'
        'list'
        'memory_set_ssl'
        'memory_get_ssl'
    [Locals+Names]
    [Constants]
        '__pyarmor_assert_15849__'
        '__pyarmor_enter_15850__'
        b'<COAddr>\x05\x00\x00\x1a\xe6\x00\x00\x00\x00\x00\x00\x00\x00\x00\x00\x00\x00\x00\x00\x00'
        0
        None
        (
            'AES'
        )
        (
            'SHA256'
        )
        (
            'pad'
            'unpad'
        )
        1
        (
            'get_fingerprint'
            'get_lic_key'
        )
        [Code]
            File Name: <frozen program.static_classes.memory>
            Object Name: FileProtector
            Qualified Name: FileProtector
            Arg Count: 0
            Pos Only Arg Count: 0
            KW Only Arg Count: 0
            Stack Size: 5
            Flags: 0x20000000 (CO_PYARMOR_OBFUSCATED)
            [Names]
                '__name__'
                '__module__'
                '__qualname__'
                '__assert_armored__'
                '__init__'
                '_key'
                'encrypt'
                'decrypt'
                '__del__'
            [Locals+Names]
            [Constants]
                'FileProtector'
                '__pyarmor_assert_15852__'
                '__pyarmor_enter_15853__'
                b'<COAddr>\x05\x00\x00"6\x00\x00\x00\x00\x00\x00\x00\x00\x00\x00\x00\x00\x00\x00\x00'
                [Code]
                    File Name: <frozen program.static_classes.memory>
                    Object Name: __init__
                    Qualified Name: FileProtector.__init__
                    Arg Count: 1
                    Pos Only Arg Count: 0
                    KW Only Arg Count: 0
                    Stack Size: 5
                    Flags: 0x20000003 (CO_OPTIMIZED | CO_NEWLOCALS | CO_PYARMOR_OBFUSCATED)
                    [Names]
                        'base64'
                        'b64decode'
                        'iv'
                        '_key'
                        'key'
                    [Locals+Names]
                        'self'
                        '__assert_armored__'
                    [Constants]
                        None
                        '__pyarmor_assert_15855__'
                        '__pyarmor_enter_15856__'
                        b'<COAddr>\x05\x00\x00\x1a\x80\x00\x00\x00\x00\x00\x00\x00\x00\x00\x00\x00\x00\x00\x00\x00'
                        'u1c0cnTGVCSG9evTP1DIjg=='   # b'\x81\xf7I\x10c\xf9\xb0\xe6<\xcc.\xf3K\xb5\xfd\x93;m\xea\x83\x83\xc1I\x91X'
                        '__pyarmor_exit_15857__'
                    [Disassembly]
                        0       NOP                             
                        2       NOP                             
                        4       PUSH_NULL                       
                        6       LOAD_CONST                      2: '__pyarmor_enter_15856__'
                        8       LOAD_CONST                      3: b'<COAddr>\x05\x00\x00\x1a\x80\x00\x00\x00\x00\x00\x00\x00\x00\x00\x00\x00\x00\x00\x00\x00'
                        10      BUILD_TUPLE                     1
                        12      CALL_FUNCTION_EX                0
                        14      POP_TOP                         
                        16      RESUME                          0
                        18      NOP                             
                        20      NOP                             
                        22      NOP                             
                        24      NOP                             
                        26      NOP                             
                        28      LOAD_GLOBAL                     1: NULL + base64
                        38      LOAD_ATTR                       2: b64decode
                        58      PUSH_NULL                       
                        60      LOAD_CONST                      1: '__pyarmor_assert_15855__'
                        62      LOAD_CONST                      4: 'u1c0cnTGVCSG9evTP1DIjg=='   # b'\x81\xf7I\x10c\xf9\xb0\xe6<\xcc.\xf3K\xb5\xfd\x93;m\xea\x83\x83\xc1I\x91X'
                        64      CALL                            1
                        72      CALL                            1
                        80      LOAD_FAST                       0: self
                        82      STORE_ATTR                      2: iv
                        92      LOAD_FAST                       0: self
                        94      LOAD_ATTR                       7: _key
                        114     CALL                            0
                        122     LOAD_FAST                       0: self
                        124     STORE_ATTR                      4: key
                        134     LOAD_CONST                      0: None
                        136     NOP                             
                        138     NOP                             
                        140     NOP                             
                        142     JUMP_FORWARD                    19 (to 182)
                        150     POP_TOP                         
                        152     RETURN_CONST                    0: None
                        154     PUSH_EXC_INFO                   
                        156     PUSH_NULL                       
                        158     LOAD_CONST                      5: '__pyarmor_exit_15857__'
                        160     NOP                             
                        162     LOAD_CONST                      3: b'<COAddr>\x05\x00\x00\x1a\x80\x00\x00\x00\x00\x00\x00\x00\x00\x00\x00\x00\x00\x00\x00\x00'
                        164     CALL                            1
                        172     POP_TOP                         
                        174     RERAISE                         0
                        176     COPY                            3
                        178     POP_EXCEPT                      
                        180     RERAISE                         1
                        182     PUSH_NULL                       
                        184     LOAD_CONST                      5: '__pyarmor_exit_15857__'
                        186     LOAD_CONST                      3: b'<COAddr>\x05\x00\x00\x1a\x80\x00\x00\x00\x00\x00\x00\x00\x00\x00\x00\x00\x00\x00\x00\x00'
                        188     BUILD_TUPLE                     1
                        190     CALL_FUNCTION_EX                0
                        192     POP_TOP                         
                        194     RETURN_VALUE                    
                    [Exception Table]
                        28 to 134 -> 154 [0] 
                        154 to 176 -> 176 [1] lasti
                [Code]
                    File Name: <frozen program.static_classes.memory>
                    Object Name: _key
                    Qualified Name: FileProtector._key
                    Arg Count: 1
                    Pos Only Arg Count: 0
                    KW Only Arg Count: 0
                    Stack Size: 5
                    Flags: 0x20000003 (CO_OPTIMIZED | CO_NEWLOCALS | CO_PYARMOR_OBFUSCATED)
                    [Names]
                        'get_lic_key'
                        'get_fingerprint'
                        'datetime'
                        'now'
                        'strftime'
                        'ValueError'
                        'SHA256'
                        'new'
                        'update'
                        'encode'
                        'digest'
                    [Locals+Names]
                        'self'
                        '__assert_armored__'
                        '_var_var_0'
                        '_var_var_1'
                        '_var_var_2'
                        '_var_var_3'
                        '_var_var_4'
                    [Constants]
                        None
                        '__pyarmor_assert_15858__'
                        '__pyarmor_enter_15859__'
                        b'<COAddr>\x07\x00\x00\x1a\x82\x01\x00\x00\x00\x00\x00\x00\x00\x00\x00\x00\x00\x00\x00\x00'
                        '%Y-%m-%U'
                        'key error'   # b'\x81\xe9\x1d\ns\xff\xac\xc0\x14\xe8'
                        'finger error'   # b'\x81\xe4\x11\x1d4\xff\xac\x92\x1e\xe8\x1f\xcf~'
                        '_'
                        'utf-8'
                        '__pyarmor_exit_15860__'
                    [Disassembly]
                        0       NOP                             
                        2       NOP                             
                        4       PUSH_NULL                       
                        6       LOAD_CONST                      2: '__pyarmor_enter_15859__'
                        8       LOAD_CONST                      3: b'<COAddr>\x07\x00\x00\x1a\x82\x01\x00\x00\x00\x00\x00\x00\x00\x00\x00\x00\x00\x00\x00\x00'
                        10      BUILD_TUPLE                     1
                        12      CALL_FUNCTION_EX                0
                        14      POP_TOP                         
                        16      RESUME                          0
                        18      NOP                             
                        20      NOP                             
                        22      NOP                             
                        24      NOP                             
                        26      NOP                             
                        28      LOAD_GLOBAL                     1: NULL + get_lic_key
                        38      CALL                            0
                        46      STORE_FAST                      2: _var_var_0
                        48      LOAD_GLOBAL                     3: NULL + get_fingerprint
                        58      CALL                            0
                        66      STORE_FAST                      3: _var_var_1
                        68      LOAD_GLOBAL                     4: datetime
                        78      LOAD_ATTR                       4: datetime
                        98      LOAD_ATTR                       7: now
                        118     CALL                            0
                        126     LOAD_ATTR                       9: strftime
                        146     LOAD_CONST                      4: '%Y-%m-%U'
                        148     CALL                            1
                        156     STORE_FAST                      4: _var_var_2
                        158     LOAD_FAST                       2: _var_var_0
                        160     POP_JUMP_IF_TRUE                17 (to 196)
                        162     LOAD_GLOBAL                     11: NULL + ValueError
                        172     PUSH_NULL                       
                        174     LOAD_CONST                      1: '__pyarmor_assert_15858__'
                        176     LOAD_CONST                      5: 'key error'   # b'\x81\xe9\x1d\ns\xff\xac\xc0\x14\xe8'
                        178     CALL                            1
                        186     CALL                            1
                        194     RAISE_VARARGS                   1
                        196     LOAD_FAST                       3: _var_var_1
                        198     POP_JUMP_IF_TRUE                17 (to 234)
                        200     LOAD_GLOBAL                     11: NULL + ValueError
                        210     PUSH_NULL                       
                        212     LOAD_CONST                      1: '__pyarmor_assert_15858__'
                        214     LOAD_CONST                      6: 'finger error'   # b'\x81\xe4\x11\x1d4\xff\xac\x92\x1e\xe8\x1f\xcf~'
                        216     CALL                            1
                        224     CALL                            1
                        232     RAISE_VARARGS                   1
                        234     LOAD_FAST                       4: _var_var_2
                        236     FORMAT_VALUE                    0 (FVC_NONE)
                        238     LOAD_CONST                      7: '_'
                        240     LOAD_FAST                       2: _var_var_0
                        242     FORMAT_VALUE                    0 (FVC_NONE)
                        244     LOAD_CONST                      7: '_'
                        246     LOAD_FAST                       3: _var_var_1
                        248     FORMAT_VALUE                    0 (FVC_NONE)
                        250     BUILD_STRING                    5
                        252     STORE_FAST                      5: _var_var_3
                        254     LOAD_GLOBAL                     13: NULL + SHA256
                        264     LOAD_ATTR                       14: new
                        284     CALL                            0
                        292     STORE_FAST                      6: _var_var_4
                        294     LOAD_FAST                       6: _var_var_4
                        296     LOAD_ATTR                       17: update
                        316     LOAD_FAST                       5: _var_var_3
                        318     LOAD_ATTR                       19: encode
                        338     LOAD_CONST                      8: 'utf-8'
                        340     CALL                            1
                        348     CALL                            1
                        356     POP_TOP                         
                        358     LOAD_FAST                       6: _var_var_4
                        360     LOAD_ATTR                       21: digest
                        380     CALL                            0
                        388     STORE_FAST                      2: _var_var_0
                        390     LOAD_FAST                       2: _var_var_0
                        392     NOP                             
                        394     NOP                             
                        396     NOP                             
                        398     JUMP_FORWARD                    20 (to 440)
                        400     CALL                            1
                        408     POP_TOP                         
                        410     RETURN_VALUE                    
                        412     PUSH_EXC_INFO                   
                        414     PUSH_NULL                       
                        416     LOAD_CONST                      9: '__pyarmor_exit_15860__'
                        418     NOP                             
                        420     LOAD_CONST                      3: b'<COAddr>\x07\x00\x00\x1a\x82\x01\x00\x00\x00\x00\x00\x00\x00\x00\x00\x00\x00\x00\x00\x00'
                        422     CALL                            1
                        430     POP_TOP                         
                        432     RERAISE                         0
                        434     COPY                            3
                        436     POP_EXCEPT                      
                        438     RERAISE                         1
                        440     PUSH_NULL                       
                        442     LOAD_CONST                      9: '__pyarmor_exit_15860__'
                        444     LOAD_CONST                      3: b'<COAddr>\x07\x00\x00\x1a\x82\x01\x00\x00\x00\x00\x00\x00\x00\x00\x00\x00\x00\x00\x00\x00'
                        446     BUILD_TUPLE                     1
                        448     CALL_FUNCTION_EX                0
                        450     POP_TOP                         
                        452     RETURN_VALUE                    
                    [Exception Table]
                        28 to 392 -> 412 [0] 
                        412 to 434 -> 434 [1] lasti
                [Code]
                    File Name: <frozen program.static_classes.memory>
                    Object Name: encrypt
                    Qualified Name: FileProtector.encrypt
                    Arg Count: 2
                    Pos Only Arg Count: 0
                    KW Only Arg Count: 0
                    Stack Size: 8
                    Flags: 0x20000003 (CO_OPTIMIZED | CO_NEWLOCALS | CO_PYARMOR_OBFUSCATED)
                    [Names]
                        'encode'
                        'AES'
                        'new'
                        'key'
                        'MODE_CBC'
                        'iv'
                        'base64'
                        'b64encode'
                        'encrypt'
                        'pad'
                        'block_size'
                        'decode'
                    [Locals+Names]
                        'self'
                        'data'
                        '__assert_armored__'
                        '_var_var_5'
                        '_var_var_6'
                    [Constants]
                        None
                        '__pyarmor_assert_15861__'
                        '__pyarmor_enter_15862__'
                        b'<COAddr>\x05\x00\x00\x1ad\x01\x00\x00\x00\x00\x00\x00\x00\x00\x00\x00\x00\x00\x00\x00'
                        'utf-8'
                        '__pyarmor_exit_15863__'
                        False
                    [Disassembly]
                        0       NOP                             
                        2       NOP                             
                        4       PUSH_NULL                       
                        6       LOAD_CONST                      2: '__pyarmor_enter_15862__'
                        8       LOAD_CONST                      3: b'<COAddr>\x05\x00\x00\x1ad\x01\x00\x00\x00\x00\x00\x00\x00\x00\x00\x00\x00\x00\x00\x00'
                        10      BUILD_TUPLE                     1
                        12      CALL_FUNCTION_EX                0
                        14      POP_TOP                         
                        16      RESUME                          0
                        18      NOP                             
                        20      NOP                             
                        22      NOP                             
                        24      NOP                             
                        26      NOP                             
                        28      NOP                             
                        30      LOAD_FAST                       1: data
                        32      LOAD_ATTR                       1: encode
                        52      LOAD_CONST                      4: 'utf-8'
                        54      CALL                            1
                        62      STORE_FAST                      1: data
                        64      LOAD_GLOBAL                     3: NULL + AES
                        74      LOAD_ATTR                       4: new
                        94      LOAD_FAST                       0: self
                        96      LOAD_ATTR                       6: key
                        116     LOAD_GLOBAL                     2: AES
                        126     LOAD_ATTR                       8: MODE_CBC
                        146     LOAD_FAST                       0: self
                        148     LOAD_ATTR                       10: iv
                        168     CALL                            3
                        176     STORE_FAST                      3: _var_var_5
                        178     LOAD_GLOBAL                     13: NULL + base64
                        188     LOAD_ATTR                       14: b64encode
                        208     LOAD_FAST                       3: _var_var_5
                        210     LOAD_ATTR                       17: encrypt
                        230     LOAD_GLOBAL                     19: NULL + pad
                        240     LOAD_FAST                       1: data
                        242     LOAD_GLOBAL                     2: AES
                        252     LOAD_ATTR                       20: block_size
                        272     CALL                            2
                        280     CALL                            1
                        288     CALL                            1
                        296     LOAD_ATTR                       23: decode
                        316     LOAD_CONST                      4: 'utf-8'
                        318     CALL                            1
                        326     STORE_FAST                      4: _var_var_6
                        328     LOAD_FAST                       4: _var_var_6
                        330     NOP                             
                        332     NOP                             
                        334     NOP                             
                        336     JUMP_FORWARD                    36 (to 410)
                        338     CALL                            1
                        346     POP_TOP                         
                        348     RETURN_VALUE                    
                        350     PUSH_EXC_INFO                   
                        352     POP_TOP                         
                        354     POP_EXCEPT                      
                        356     LOAD_CONST                      6: False
                        358     NOP                             
                        360     NOP                             
                        362     NOP                             
                        364     JUMP_FORWARD                    22 (to 410)
                        372     POP_TOP                         
                        374     RETURN_CONST                    6: False
                        376     COPY                            3
                        378     POP_EXCEPT                      
                        380     RERAISE                         1
                        382     PUSH_EXC_INFO                   
                        384     PUSH_NULL                       
                        386     LOAD_CONST                      5: '__pyarmor_exit_15863__'
                        388     NOP                             
                        390     LOAD_CONST                      3: b'<COAddr>\x05\x00\x00\x1ad\x01\x00\x00\x00\x00\x00\x00\x00\x00\x00\x00\x00\x00\x00\x00'
                        392     CALL                            1
                        400     POP_TOP                         
                        402     RERAISE                         0
                        404     COPY                            3
                        406     POP_EXCEPT                      
                        408     RERAISE                         1
                        410     PUSH_NULL                       
                        412     LOAD_CONST                      5: '__pyarmor_exit_15863__'
                        414     LOAD_CONST                      3: b'<COAddr>\x05\x00\x00\x1ad\x01\x00\x00\x00\x00\x00\x00\x00\x00\x00\x00\x00\x00\x00\x00'
                        416     BUILD_TUPLE                     1
                        418     CALL_FUNCTION_EX                0
                        420     POP_TOP                         
                        422     RETURN_VALUE                    
                    [Exception Table]
                        30 to 330 -> 350 [0] 
                        350 to 354 -> 376 [1] lasti
                        354 to 356 -> 382 [0] 
                        376 to 382 -> 382 [0] 
                        382 to 404 -> 404 [1] lasti
                [Code]
                    File Name: <frozen program.static_classes.memory>
                    Object Name: decrypt
                    Qualified Name: FileProtector.decrypt
                    Arg Count: 2
                    Pos Only Arg Count: 0
                    KW Only Arg Count: 0
                    Stack Size: 5
                    Flags: 0x20000003 (CO_OPTIMIZED | CO_NEWLOCALS | CO_PYARMOR_OBFUSCATED)
                    [Names]
                        'base64'
                        'b64decode'
                        'AES'
                        'new'
                        'key'
                        'MODE_CBC'
                        'iv'
                        'unpad'
                        'decrypt'
                        'block_size'
                        'decode'
                    [Locals+Names]
                        'self'
                        'data'
                        '__assert_armored__'
                        '_var_var_5'
                        '_var_var_7'
                    [Constants]
                        None
                        '__pyarmor_assert_15864__'
                        '__pyarmor_enter_15865__'
                        b'<COAddr>\x05\x00\x00\x1aF\x01\x00\x00\x00\x00\x00\x00\x00\x00\x00\x00\x00\x00\x00\x00'
                        'utf-8'
                        '__pyarmor_exit_15866__'
                        False
                    [Disassembly]
                        0       NOP                             
                        2       NOP                             
                        4       PUSH_NULL                       
                        6       LOAD_CONST                      2: '__pyarmor_enter_15865__'
                        8       LOAD_CONST                      3: b'<COAddr>\x05\x00\x00\x1aF\x01\x00\x00\x00\x00\x00\x00\x00\x00\x00\x00\x00\x00\x00\x00'
                        10      BUILD_TUPLE                     1
                        12      CALL_FUNCTION_EX                0
                        14      POP_TOP                         
                        16      RESUME                          0
                        18      NOP                             
                        20      NOP                             
                        22      NOP                             
                        24      NOP                             
                        26      NOP                             
                        28      NOP                             
                        30      LOAD_GLOBAL                     1: NULL + base64
                        40      LOAD_ATTR                       2: b64decode
                        60      LOAD_FAST                       1: data
                        62      CALL                            1
                        70      STORE_FAST                      1: data
                        72      LOAD_GLOBAL                     5: NULL + AES
                        82      LOAD_ATTR                       6: new
                        102     LOAD_FAST                       0: self
                        104     LOAD_ATTR                       8: key
                        124     LOAD_GLOBAL                     4: AES
                        134     LOAD_ATTR                       10: MODE_CBC
                        154     LOAD_FAST                       0: self
                        156     LOAD_ATTR                       12: iv
                        176     CALL                            3
                        184     STORE_FAST                      3: _var_var_5
                        186     LOAD_GLOBAL                     15: NULL + unpad
                        196     LOAD_FAST                       3: _var_var_5
                        198     LOAD_ATTR                       17: decrypt
                        218     LOAD_FAST                       1: data
                        220     CALL                            1
                        228     LOAD_GLOBAL                     4: AES
                        238     LOAD_ATTR                       18: block_size
                        258     CALL                            2
                        266     LOAD_ATTR                       21: decode
                        286     LOAD_CONST                      4: 'utf-8'
                        288     CALL                            1
                        296     STORE_FAST                      4: _var_var_7
                        298     LOAD_FAST                       4: _var_var_7
                        300     NOP                             
                        302     NOP                             
                        304     NOP                             
                        306     JUMP_FORWARD                    36 (to 380)
                        308     CALL                            1
                        316     POP_TOP                         
                        318     RETURN_VALUE                    
                        320     PUSH_EXC_INFO                   
                        322     POP_TOP                         
                        324     POP_EXCEPT                      
                        326     LOAD_CONST                      6: False
                        328     NOP                             
                        330     NOP                             
                        332     NOP                             
                        334     JUMP_FORWARD                    22 (to 380)
                        342     POP_TOP                         
                        344     RETURN_CONST                    6: False
                        346     COPY                            3
                        348     POP_EXCEPT                      
                        350     RERAISE                         1
                        352     PUSH_EXC_INFO                   
                        354     PUSH_NULL                       
                        356     LOAD_CONST                      5: '__pyarmor_exit_15866__'
                        358     NOP                             
                        360     LOAD_CONST                      3: b'<COAddr>\x05\x00\x00\x1aF\x01\x00\x00\x00\x00\x00\x00\x00\x00\x00\x00\x00\x00\x00\x00'
                        362     CALL                            1
                        370     POP_TOP                         
                        372     RERAISE                         0
                        374     COPY                            3
                        376     POP_EXCEPT                      
                        378     RERAISE                         1
                        380     PUSH_NULL                       
                        382     LOAD_CONST                      5: '__pyarmor_exit_15866__'
                        384     LOAD_CONST                      3: b'<COAddr>\x05\x00\x00\x1aF\x01\x00\x00\x00\x00\x00\x00\x00\x00\x00\x00\x00\x00\x00\x00'
                        386     BUILD_TUPLE                     1
                        388     CALL_FUNCTION_EX                0
                        390     POP_TOP                         
                        392     RETURN_VALUE                    
                    [Exception Table]
                        30 to 300 -> 320 [0] 
                        320 to 324 -> 346 [1] lasti
                        324 to 326 -> 352 [0] 
                        346 to 352 -> 352 [0] 
                        352 to 374 -> 374 [1] lasti
                None
                [Code]
                    File Name: <frozen program.static_classes.memory>
                    Object Name: __del__
                    Qualified Name: FileProtector.__del__
                    Arg Count: 1
                    Pos Only Arg Count: 0
                    KW Only Arg Count: 0
                    Stack Size: 5
                    Flags: 0x20000003 (CO_OPTIMIZED | CO_NEWLOCALS | CO_PYARMOR_OBFUSCATED)
                    [Names]
                        'iv'
                        'key'
                    [Locals+Names]
                        'self'
                        '__assert_armored__'
                    [Constants]
                        None
                        '__pyarmor_assert_15867__'
                        '__pyarmor_enter_15868__'
                        b'<COAddr>\x05\x00\x00\x1a\x1e\x00\x00\x00\x00\x00\x00\x00\x00\x00\x00\x00\x00\x00\x00\x00'
                        '__pyarmor_exit_15869__'
                    [Disassembly]
                        0       NOP                             
                        2       NOP                             
                        4       PUSH_NULL                       
                        6       LOAD_CONST                      2: '__pyarmor_enter_15868__'
                        8       LOAD_CONST                      3: b'<COAddr>\x05\x00\x00\x1a\x1e\x00\x00\x00\x00\x00\x00\x00\x00\x00\x00\x00\x00\x00\x00\x00'
                        10      BUILD_TUPLE                     1
                        12      CALL_FUNCTION_EX                0
                        14      POP_TOP                         
                        16      RESUME                          0
                        18      NOP                             
                        20      NOP                             
                        22      NOP                             
                        24      NOP                             
                        26      NOP                             
                        28      LOAD_FAST                       0: self
                        30      DELETE_ATTR                     0: iv
                        32      LOAD_FAST                       0: self
                        34      DELETE_ATTR                     1: key
                        36      LOAD_CONST                      0: None
                        38      NOP                             
                        40      NOP                             
                        42      NOP                             
                        44      JUMP_FORWARD                    19 (to 84)
                        52      POP_TOP                         
                        54      RETURN_CONST                    0: None
                        56      PUSH_EXC_INFO                   
                        58      PUSH_NULL                       
                        60      LOAD_CONST                      4: '__pyarmor_exit_15869__'
                        62      NOP                             
                        64      LOAD_CONST                      3: b'<COAddr>\x05\x00\x00\x1a\x1e\x00\x00\x00\x00\x00\x00\x00\x00\x00\x00\x00\x00\x00\x00\x00'
                        66      CALL                            1
                        74      POP_TOP                         
                        76      RERAISE                         0
                        78      COPY                            3
                        80      POP_EXCEPT                      
                        82      RERAISE                         1
                        84      PUSH_NULL                       
                        86      LOAD_CONST                      4: '__pyarmor_exit_15869__'
                        88      LOAD_CONST                      3: b'<COAddr>\x05\x00\x00\x1a\x1e\x00\x00\x00\x00\x00\x00\x00\x00\x00\x00\x00\x00\x00\x00\x00'
                        90      BUILD_TUPLE                     1
                        92      CALL_FUNCTION_EX                0
                        94      POP_TOP                         
                        96      RETURN_VALUE                    
                    [Exception Table]
                        28 to 36 -> 56 [0] 
                        56 to 78 -> 78 [1] lasti
                '__pyarmor_exit_15854__'
                (
                    'return'
                    None
                )
            [Disassembly]
                0       NOP                             
                2       LOAD_NAME                       0: __name__
                4       STORE_NAME                      1: __module__
                6       LOAD_CONST                      0: 'FileProtector'
                8       STORE_NAME                      2: __qualname__
                10      NOP                             
                12      PUSH_NULL                       
                14      LOAD_CONST                      2: '__pyarmor_enter_15853__'
                16      LOAD_CONST                      3: b'<COAddr>\x05\x00\x00"6\x00\x00\x00\x00\x00\x00\x00\x00\x00\x00\x00\x00\x00\x00\x00'
                18      BUILD_TUPLE                     1
                20      CALL_FUNCTION_EX                0
                22      POP_TOP                         
                24      RESUME                          0
                26      NOP                             
                28      NOP                             
                30      NOP                             
                32      NOP                             
                34      NOP                             
                36      LOAD_CONST                      4: <CODE> __init__
                38      MAKE_FUNCTION                   0
                40      STORE_NAME                      4: __init__
                42      LOAD_CONST                      5: <CODE> _key
                44      MAKE_FUNCTION                   0
                46      STORE_NAME                      5: _key
                48      LOAD_CONST                      6: <CODE> encrypt
                50      MAKE_FUNCTION                   0
                52      STORE_NAME                      6: encrypt
                54      LOAD_CONST                      7: <CODE> decrypt
                56      MAKE_FUNCTION                   0
                58      STORE_NAME                      7: decrypt
                60      LOAD_CONST                      11: ('return', None)
                62      LOAD_CONST                      9: <CODE> __del__
                64      MAKE_FUNCTION                   4
                66      STORE_NAME                      8: __del__
                68      LOAD_CONST                      8: None
                70      NOP                             
                72      NOP                             
                74      NOP                             
                76      JUMP_FORWARD                    19 (to 116)
                84      POP_TOP                         
                86      RETURN_CONST                    8: None
                88      PUSH_EXC_INFO                   
                90      PUSH_NULL                       
                92      LOAD_CONST                      10: '__pyarmor_exit_15854__'
                94      NOP                             
                96      LOAD_CONST                      3: b'<COAddr>\x05\x00\x00"6\x00\x00\x00\x00\x00\x00\x00\x00\x00\x00\x00\x00\x00\x00\x00'
                98      CALL                            1
                106     POP_TOP                         
                108     RERAISE                         0
                110     COPY                            3
                112     POP_EXCEPT                      
                114     RERAISE                         1
                116     PUSH_NULL                       
                118     LOAD_CONST                      10: '__pyarmor_exit_15854__'
                120     LOAD_CONST                      3: b'<COAddr>\x05\x00\x00"6\x00\x00\x00\x00\x00\x00\x00\x00\x00\x00\x00\x00\x00\x00\x00'
                122     BUILD_TUPLE                     1
                124     CALL_FUNCTION_EX                0
                126     POP_TOP                         
                128     RETURN_VALUE                    
            [Exception Table]
                36 to 68 -> 88 [0] 
                88 to 110 -> 110 [1] lasti
        'FileProtector'
        [Code]
            File Name: <frozen program.static_classes.memory>
            Object Name: memory_set_module
            Qualified Name: memory_set_module
            Arg Count: 1
            Pos Only Arg Count: 0
            KW Only Arg Count: 0
            Stack Size: 6
            Flags: 0x20000003 (CO_OPTIMIZED | CO_NEWLOCALS | CO_PYARMOR_OBFUSCATED)
            [Names]
                'open'
                'FileProtector'
                'encrypt'
                'write'
            [Locals+Names]
                'data'
                '__assert_armored__'
                '_var_var_8'
                '_var_var_9'
                '_var_var_10'
            [Constants]
                None
                '__pyarmor_assert_15870__'
                '__pyarmor_enter_15871__'
                b'<COAddr>\x05\x00\x00\x1a\\\x02\x00\x00\x00\x00\x00\x00\x00\x00\x00\x00\x00\x00\x00\x00'
                ''
                1
                'mod:registrator|'   # b'\x81\xef\x17\x17i\xe8\xbb\xd5\x12\xe9\x19\xd2m\xf8\xf7\x97\x13'
                2
                'mod:duplicator|'   # b'\x81\xef\x17\x17i\xfe\xab\xc2\x17\xf3\x0e\xc1x\xe3\xea\x99'
                3
                'mod:inviteadmin|'   # b'\x81\xef\x17\x17i\xf3\xb0\xc4\x12\xee\x08\xc1h\xe1\xf1\x8b\x13'
                4
                'mod:interceptor|'   # b'\x81\xef\x17\x17i\xf3\xb0\xc6\x1e\xe8\x0e\xc5|\xf8\xf7\x97\x13'
                5
                'mod:reporter|'   # b'\x81\xef\x17\x17i\xe8\xbb\xc2\x14\xe8\x19\xc5~\xf0'
                6
                'mod:chatcloner|'   # b'\x81\xef\x17\x17i\xf9\xb6\xd3\x0f\xf9\x01\xcfb\xe9\xea\x99'
                7
                'mod:channelcloner|'   # b'\x81\xef\x17\x17i\xf9\xb6\xd3\x15\xf4\x08\xcco\xe0\xf7\x8b\nO\xa7'
                8
                'mod:forwarder|'   # b'\x81\xef\x17\x17i\xfc\xb1\xc0\x0c\xfb\x1f\xc4i\xfe\xe4'
                9
                'mod:booster|'   # b'\x81\xef\x17\x17i\xf8\xb1\xdd\x08\xee\x08\xd2p'
                10
                'mod:converter|'   # b'\x81\xef\x17\x17i\xf9\xb1\xdc\r\xff\x1f\xd4i\xfe\xe4'
                11
                'mod:gpt|'
                12
                'mod:privatereg|'   # b'\x81\xef\x17\x17i\xea\xac\xdb\r\xfb\x19\xc5~\xe9\xff\x99'
                'temp/001.dat'   # b'\x81\xf6\x1d\x1e#\xb5\xee\x82J\xb4\t\xc1x'
                'w'
                'utf-8'
                'ignore'
                (
                    'encoding'
                    'errors'
                )
                '__pyarmor_exit_15872__'
                True
            [Disassembly]
                0       NOP                             
                2       NOP                             
                4       PUSH_NULL                       
                6       LOAD_CONST                      2: '__pyarmor_enter_15871__'
                8       LOAD_CONST                      3: b'<COAddr>\x05\x00\x00\x1a\\\x02\x00\x00\x00\x00\x00\x00\x00\x00\x00\x00\x00\x00\x00\x00'
                10      BUILD_TUPLE                     1
                12      CALL_FUNCTION_EX                0
                14      POP_TOP                         
                16      RESUME                          0
                18      NOP                             
                20      NOP                             
                22      NOP                             
                24      NOP                             
                26      NOP                             
                28      LOAD_CONST                      4: ''
                30      STORE_FAST                      2: _var_var_8
                32      LOAD_FAST                       0: data
                34      GET_ITER                        
                36      FOR_ITER                        189 (to 416)
                40      STORE_FAST                      3: _var_var_9
                42      LOAD_FAST                       3: _var_var_9
                44      LOAD_CONST                      5: 1
                46      COMPARE_OP                      40 (==)
                50      POP_JUMP_IF_FALSE               11 (to 74)
                52      LOAD_FAST                       2: _var_var_8
                54      PUSH_NULL                       
                56      LOAD_CONST                      1: '__pyarmor_assert_15870__'
                58      LOAD_CONST                      6: 'mod:registrator|'   # b'\x81\xef\x17\x17i\xe8\xbb\xd5\x12\xe9\x19\xd2m\xf8\xf7\x97\x13'
                60      CALL                            1
                68      BINARY_OP                       0 (+)
                72      STORE_FAST                      2: _var_var_8
                74      LOAD_FAST                       3: _var_var_9
                76      LOAD_CONST                      7: 2
                78      COMPARE_OP                      40 (==)
                82      POP_JUMP_IF_FALSE               11 (to 106)
                84      LOAD_FAST                       2: _var_var_8
                86      PUSH_NULL                       
                88      LOAD_CONST                      1: '__pyarmor_assert_15870__'
                90      LOAD_CONST                      8: 'mod:duplicator|'   # b'\x81\xef\x17\x17i\xfe\xab\xc2\x17\xf3\x0e\xc1x\xe3\xea\x99'
                92      CALL                            1
                100     BINARY_OP                       0 (+)
                104     STORE_FAST                      2: _var_var_8
                106     LOAD_FAST                       3: _var_var_9
                108     LOAD_CONST                      9: 3
                110     COMPARE_OP                      40 (==)
                114     POP_JUMP_IF_FALSE               11 (to 138)
                116     LOAD_FAST                       2: _var_var_8
                118     PUSH_NULL                       
                120     LOAD_CONST                      1: '__pyarmor_assert_15870__'
                122     LOAD_CONST                      10: 'mod:inviteadmin|'   # b'\x81\xef\x17\x17i\xf3\xb0\xc4\x12\xee\x08\xc1h\xe1\xf1\x8b\x13'
                124     CALL                            1
                132     BINARY_OP                       0 (+)
                136     STORE_FAST                      2: _var_var_8
                138     LOAD_FAST                       3: _var_var_9
                140     LOAD_CONST                      11: 4
                142     COMPARE_OP                      40 (==)
                146     POP_JUMP_IF_FALSE               11 (to 170)
                148     LOAD_FAST                       2: _var_var_8
                150     PUSH_NULL                       
                152     LOAD_CONST                      1: '__pyarmor_assert_15870__'
                154     LOAD_CONST                      12: 'mod:interceptor|'   # b'\x81\xef\x17\x17i\xf3\xb0\xc6\x1e\xe8\x0e\xc5|\xf8\xf7\x97\x13'
                156     CALL                            1
                164     BINARY_OP                       0 (+)
                168     STORE_FAST                      2: _var_var_8
                170     LOAD_FAST                       3: _var_var_9
                172     LOAD_CONST                      13: 5
                174     COMPARE_OP                      40 (==)
                178     POP_JUMP_IF_FALSE               11 (to 202)
                180     LOAD_FAST                       2: _var_var_8
                182     PUSH_NULL                       
                184     LOAD_CONST                      1: '__pyarmor_assert_15870__'
                186     LOAD_CONST                      14: 'mod:reporter|'   # b'\x81\xef\x17\x17i\xe8\xbb\xc2\x14\xe8\x19\xc5~\xf0'
                188     CALL                            1
                196     BINARY_OP                       0 (+)
                200     STORE_FAST                      2: _var_var_8
                202     LOAD_FAST                       3: _var_var_9
                204     LOAD_CONST                      15: 6
                206     COMPARE_OP                      40 (==)
                210     POP_JUMP_IF_FALSE               11 (to 234)
                212     LOAD_FAST                       2: _var_var_8
                214     PUSH_NULL                       
                216     LOAD_CONST                      1: '__pyarmor_assert_15870__'
                218     LOAD_CONST                      16: 'mod:chatcloner|'   # b'\x81\xef\x17\x17i\xf9\xb6\xd3\x0f\xf9\x01\xcfb\xe9\xea\x99'
                220     CALL                            1
                228     BINARY_OP                       0 (+)
                232     STORE_FAST                      2: _var_var_8
                234     LOAD_FAST                       3: _var_var_9
                236     LOAD_CONST                      17: 7
                238     COMPARE_OP                      40 (==)
                242     POP_JUMP_IF_FALSE               11 (to 266)
                244     LOAD_FAST                       2: _var_var_8
                246     PUSH_NULL                       
                248     LOAD_CONST                      1: '__pyarmor_assert_15870__'
                250     LOAD_CONST                      18: 'mod:channelcloner|'   # b'\x81\xef\x17\x17i\xf9\xb6\xd3\x15\xf4\x08\xcco\xe0\xf7\x8b\nO\xa7'
                252     CALL                            1
                260     BINARY_OP                       0 (+)
                264     STORE_FAST                      2: _var_var_8
                266     LOAD_FAST                       3: _var_var_9
                268     LOAD_CONST                      19: 8
                270     COMPARE_OP                      40 (==)
                274     POP_JUMP_IF_FALSE               11 (to 298)
                276     LOAD_FAST                       2: _var_var_8
                278     PUSH_NULL                       
                280     LOAD_CONST                      1: '__pyarmor_assert_15870__'
                282     LOAD_CONST                      20: 'mod:forwarder|'   # b'\x81\xef\x17\x17i\xfc\xb1\xc0\x0c\xfb\x1f\xc4i\xfe\xe4'
                284     CALL                            1
                292     BINARY_OP                       0 (+)
                296     STORE_FAST                      2: _var_var_8
                298     LOAD_FAST                       3: _var_var_9
                300     LOAD_CONST                      21: 9
                302     COMPARE_OP                      40 (==)
                306     POP_JUMP_IF_FALSE               11 (to 330)
                308     LOAD_FAST                       2: _var_var_8
                310     PUSH_NULL                       
                312     LOAD_CONST                      1: '__pyarmor_assert_15870__'
                314     LOAD_CONST                      22: 'mod:booster|'   # b'\x81\xef\x17\x17i\xf8\xb1\xdd\x08\xee\x08\xd2p'
                316     CALL                            1
                324     BINARY_OP                       0 (+)
                328     STORE_FAST                      2: _var_var_8
                330     LOAD_FAST                       3: _var_var_9
                332     LOAD_CONST                      23: 10
                334     COMPARE_OP                      40 (==)
                338     POP_JUMP_IF_FALSE               11 (to 362)
                340     LOAD_FAST                       2: _var_var_8
                342     PUSH_NULL                       
                344     LOAD_CONST                      1: '__pyarmor_assert_15870__'
                346     LOAD_CONST                      24: 'mod:converter|'   # b'\x81\xef\x17\x17i\xf9\xb1\xdc\r\xff\x1f\xd4i\xfe\xe4'
                348     CALL                            1
                356     BINARY_OP                       0 (+)
                360     STORE_FAST                      2: _var_var_8
                362     LOAD_FAST                       3: _var_var_9
                364     LOAD_CONST                      25: 11
                366     COMPARE_OP                      40 (==)
                370     POP_JUMP_IF_FALSE               5 (to 382)
                372     LOAD_FAST                       2: _var_var_8
                374     LOAD_CONST                      26: 'mod:gpt|'
                376     BINARY_OP                       0 (+)
                380     STORE_FAST                      2: _var_var_8
                382     LOAD_FAST                       3: _var_var_9
                384     LOAD_CONST                      27: 12
                386     COMPARE_OP                      40 (==)
                390     POP_JUMP_IF_TRUE                1 (to 394)
                392     JUMP_BACKWARD                   179 (to 36)
                394     LOAD_FAST                       2: _var_var_8
                396     PUSH_NULL                       
                398     LOAD_CONST                      1: '__pyarmor_assert_15870__'
                400     LOAD_CONST                      28: 'mod:privatereg|'   # b'\x81\xef\x17\x17i\xea\xac\xdb\r\xfb\x19\xc5~\xe9\xff\x99'
                402     CALL                            1
                410     BINARY_OP                       0 (+)
                414     STORE_FAST                      2: _var_var_8
                416     JUMP_BACKWARD                   191 (to 36)
                418     END_FOR                         
                420     LOAD_GLOBAL                     1: NULL + open
                430     PUSH_NULL                       
                432     LOAD_CONST                      1: '__pyarmor_assert_15870__'
                434     LOAD_CONST                      29: 'temp/001.dat'   # b'\x81\xf6\x1d\x1e#\xb5\xee\x82J\xb4\t\xc1x'
                436     CALL                            1
                444     LOAD_CONST                      30: 'w'
                446     LOAD_CONST                      31: 'utf-8'
                448     LOAD_CONST                      32: 'ignore'
                450     KW_NAMES                        33: ('encoding', 'errors')
                452     CALL                            4
                460     BEFORE_WITH                     
                462     STORE_FAST                      4: _var_var_10
                464     LOAD_GLOBAL                     3: NULL + FileProtector
                474     CALL                            0
                482     LOAD_ATTR                       5: encrypt
                502     LOAD_FAST                       2: _var_var_8
                504     CALL                            1
                512     STORE_FAST                      2: _var_var_8
                514     LOAD_FAST                       4: _var_var_10
                516     LOAD_ATTR                       7: write
                536     LOAD_FAST                       2: _var_var_8
                538     CALL                            1
                546     POP_TOP                         
                548     NOP                             
                550     LOAD_CONST                      0: None
                552     LOAD_CONST                      0: None
                554     LOAD_CONST                      0: None
                556     CALL                            2
                564     POP_TOP                         
                566     LOAD_CONST                      35: True
                568     NOP                             
                570     NOP                             
                572     NOP                             
                574     JUMP_FORWARD                    41 (to 658)
                582     POP_TOP                         
                584     RETURN_CONST                    35: True
                586     PUSH_EXC_INFO                   
                588     WITH_EXCEPT_START               
                590     POP_JUMP_IF_TRUE                1 (to 594)
                592     RERAISE                         2
                594     POP_TOP                         
                596     POP_EXCEPT                      
                598     POP_TOP                         
                600     POP_TOP                         
                602     JUMP_FORWARD                    3 (to 610)
                604     COPY                            3
                606     POP_EXCEPT                      
                608     RERAISE                         1
                610     LOAD_CONST                      0: None
                612     NOP                             
                614     NOP                             
                616     NOP                             
                618     JUMP_FORWARD                    19 (to 658)
                626     POP_TOP                         
                628     RETURN_CONST                    0: None
                630     PUSH_EXC_INFO                   
                632     PUSH_NULL                       
                634     LOAD_CONST                      34: '__pyarmor_exit_15872__'
                636     NOP                             
                638     LOAD_CONST                      3: b'<COAddr>\x05\x00\x00\x1a\\\x02\x00\x00\x00\x00\x00\x00\x00\x00\x00\x00\x00\x00\x00\x00'
                640     CALL                            1
                648     POP_TOP                         
                650     RERAISE                         0
                652     COPY                            3
                654     POP_EXCEPT                      
                656     RERAISE                         1
                658     PUSH_NULL                       
                660     LOAD_CONST                      34: '__pyarmor_exit_15872__'
                662     LOAD_CONST                      3: b'<COAddr>\x05\x00\x00\x1a\\\x02\x00\x00\x00\x00\x00\x00\x00\x00\x00\x00\x00\x00\x00\x00'
                664     BUILD_TUPLE                     1
                666     CALL_FUNCTION_EX                0
                668     POP_TOP                         
                670     RETURN_VALUE                    
            [Exception Table]
                28 to 392 -> 630 [0] 
                394 to 462 -> 630 [0] 
                462 to 550 -> 586 [1] lasti
                550 to 566 -> 630 [0] 
                586 to 596 -> 604 [3] lasti
                596 to 610 -> 630 [0] 
                630 to 652 -> 652 [1] lasti
        'ids'
        'return'
        [Code]
            File Name: <frozen program.static_classes.memory>
            Object Name: check_module
            Qualified Name: check_module
            Arg Count: 1
            Pos Only Arg Count: 0
            KW Only Arg Count: 0
            Stack Size: 6
            Flags: 0x20000003 (CO_OPTIMIZED | CO_NEWLOCALS | CO_PYARMOR_OBFUSCATED)
            [Names]
                'open'
                'read'
                'FileProtector'
                'decrypt'
            [Locals+Names]
                'ids'
                '__assert_armored__'
                '_var_var_10'
                '_var_var_3'
            [Constants]
                None
                '__pyarmor_assert_15873__'
                '__pyarmor_enter_15874__'
                b'<COAddr>\x05\x00\x00\x1a\xf0\x03\x00\x00\x00\x00\x00\x00\x00\x00\x00\x00\x00\x00\x00\x00'
                'temp/001.dat'   # b'\x81\xf6\x1d\x1e#\xb5\xee\x82J\xb4\t\xc1x'
                'r'
                'utf-8'
                'ignore'
                (
                    'encoding'
                    'errors'
                )
                1
                'mod:registrator'   # b'\x81\xef\x17\x17i\xe8\xbb\xd5\x12\xe9\x19\xd2m\xf8\xf7\x97'
                '__pyarmor_exit_15875__'
                True
                2
                'mod:duplicator'   # b'\x81\xef\x17\x17i\xfe\xab\xc2\x17\xf3\x0e\xc1x\xe3\xea'
                3
                'mod:inviteadmin'   # b'\x81\xef\x17\x17i\xf3\xb0\xc4\x12\xee\x08\xc1h\xe1\xf1\x8b'
                4
                'mod:interceptor'   # b'\x81\xef\x17\x17i\xf3\xb0\xc6\x1e\xe8\x0e\xc5|\xf8\xf7\x97'
                5
                'mod:reporter'   # b'\x81\xef\x17\x17i\xe8\xbb\xc2\x14\xe8\x19\xc5~'
                6
                'mod:chatcloner'   # b'\x81\xef\x17\x17i\xf9\xb6\xd3\x0f\xf9\x01\xcfb\xe9\xea'
                7
                'mod:channelcloner'   # b'\x81\xef\x17\x17i\xf9\xb6\xd3\x15\xf4\x08\xcco\xe0\xf7\x8b\nO'
                8
                'mod:forwarder'   # b'\x81\xef\x17\x17i\xfc\xb1\xc0\x0c\xfb\x1f\xc4i\xfe'
                9
                'mod:booster'   # b'\x81\xef\x17\x17i\xf8\xb1\xdd\x08\xee\x08\xd2'
                10
                'mod:converter'   # b'\x81\xef\x17\x17i\xf9\xb1\xdc\r\xff\x1f\xd4i\xfe'
                11
                'mod:gpt'
                12
                'mod:privatereg'   # b'\x81\xef\x17\x17i\xea\xac\xdb\r\xfb\x19\xc5~\xe9\xff'
                False
            [Disassembly]
                0       NOP                             
                2       NOP                             
                4       PUSH_NULL                       
                6       LOAD_CONST                      2: '__pyarmor_enter_15874__'
                8       LOAD_CONST                      3: b'<COAddr>\x05\x00\x00\x1a\xf0\x03\x00\x00\x00\x00\x00\x00\x00\x00\x00\x00\x00\x00\x00\x00'
                10      BUILD_TUPLE                     1
                12      CALL_FUNCTION_EX                0
                14      POP_TOP                         
                16      RESUME                          0
                18      NOP                             
                20      NOP                             
                22      NOP                             
                24      NOP                             
                26      NOP                             
                28      NOP                             
                30      LOAD_GLOBAL                     1: NULL + open
                40      PUSH_NULL                       
                42      LOAD_CONST                      1: '__pyarmor_assert_15873__'
                44      LOAD_CONST                      4: 'temp/001.dat'   # b'\x81\xf6\x1d\x1e#\xb5\xee\x82J\xb4\t\xc1x'
                46      CALL                            1
                54      LOAD_CONST                      5: 'r'
                56      LOAD_CONST                      6: 'utf-8'
                58      LOAD_CONST                      7: 'ignore'
                60      KW_NAMES                        8: ('encoding', 'errors')
                62      CALL                            4
                70      BEFORE_WITH                     
                72      STORE_FAST                      2: _var_var_10
                74      LOAD_FAST                       2: _var_var_10
                76      LOAD_ATTR                       3: read
                96      CALL                            0
                104     STORE_FAST                      3: _var_var_3
                106     LOAD_GLOBAL                     5: NULL + FileProtector
                116     CALL                            0
                124     LOAD_ATTR                       7: decrypt
                144     LOAD_FAST                       3: _var_var_3
                146     CALL                            1
                154     STORE_FAST                      3: _var_var_3
                156     LOAD_FAST                       0: ids
                158     LOAD_CONST                      9: 1
                160     COMPARE_OP                      40 (==)
                164     POP_JUMP_IF_FALSE               29 (to 224)
                166     PUSH_NULL                       
                168     LOAD_CONST                      1: '__pyarmor_assert_15873__'
                170     LOAD_CONST                      10: 'mod:registrator'   # b'\x81\xef\x17\x17i\xe8\xbb\xd5\x12\xe9\x19\xd2m\xf8\xf7\x97'
                172     CALL                            1
                180     LOAD_FAST                       3: _var_var_3
                182     CONTAINS_OP                     0 (in)
                184     POP_JUMP_IF_FALSE               19 (to 224)
                186     NOP                             
                188     LOAD_CONST                      0: None
                190     LOAD_CONST                      0: None
                192     LOAD_CONST                      0: None
                194     CALL                            2
                202     POP_TOP                         
                204     LOAD_CONST                      12: True
                206     NOP                             
                208     NOP                             
                210     JUMP_FORWARD                    424 (to 1062)
                220     POP_TOP                         
                222     RETURN_CONST                    12: True
                224     LOAD_FAST                       0: ids
                226     LOAD_CONST                      13: 2
                228     COMPARE_OP                      40 (==)
                232     POP_JUMP_IF_FALSE               29 (to 292)
                234     PUSH_NULL                       
                236     LOAD_CONST                      1: '__pyarmor_assert_15873__'
                238     LOAD_CONST                      14: 'mod:duplicator'   # b'\x81\xef\x17\x17i\xfe\xab\xc2\x17\xf3\x0e\xc1x\xe3\xea'
                240     CALL                            1
                248     LOAD_FAST                       3: _var_var_3
                250     CONTAINS_OP                     0 (in)
                252     POP_JUMP_IF_FALSE               19 (to 292)
                254     NOP                             
                256     LOAD_CONST                      0: None
                258     LOAD_CONST                      0: None
                260     LOAD_CONST                      0: None
                262     CALL                            2
                270     POP_TOP                         
                272     LOAD_CONST                      12: True
                274     NOP                             
                276     NOP                             
                278     JUMP_FORWARD                    390 (to 1062)
                288     POP_TOP                         
                290     RETURN_CONST                    12: True
                292     LOAD_FAST                       0: ids
                294     LOAD_CONST                      15: 3
                296     COMPARE_OP                      40 (==)
                300     POP_JUMP_IF_FALSE               29 (to 360)
                302     PUSH_NULL                       
                304     LOAD_CONST                      1: '__pyarmor_assert_15873__'
                306     LOAD_CONST                      16: 'mod:inviteadmin'   # b'\x81\xef\x17\x17i\xf3\xb0\xc4\x12\xee\x08\xc1h\xe1\xf1\x8b'
                308     CALL                            1
                316     LOAD_FAST                       3: _var_var_3
                318     CONTAINS_OP                     0 (in)
                320     POP_JUMP_IF_FALSE               19 (to 360)
                322     NOP                             
                324     LOAD_CONST                      0: None
                326     LOAD_CONST                      0: None
                328     LOAD_CONST                      0: None
                330     CALL                            2
                338     POP_TOP                         
                340     LOAD_CONST                      12: True
                342     NOP                             
                344     NOP                             
                346     JUMP_FORWARD                    356 (to 1062)
                356     POP_TOP                         
                358     RETURN_CONST                    12: True
                360     LOAD_FAST                       0: ids
                362     LOAD_CONST                      17: 4
                364     COMPARE_OP                      40 (==)
                368     POP_JUMP_IF_FALSE               29 (to 428)
                370     PUSH_NULL                       
                372     LOAD_CONST                      1: '__pyarmor_assert_15873__'
                374     LOAD_CONST                      18: 'mod:interceptor'   # b'\x81\xef\x17\x17i\xf3\xb0\xc6\x1e\xe8\x0e\xc5|\xf8\xf7\x97'
                376     CALL                            1
                384     LOAD_FAST                       3: _var_var_3
                386     CONTAINS_OP                     0 (in)
                388     POP_JUMP_IF_FALSE               19 (to 428)
                390     NOP                             
                392     LOAD_CONST                      0: None
                394     LOAD_CONST                      0: None
                396     LOAD_CONST                      0: None
                398     CALL                            2
                406     POP_TOP                         
                408     LOAD_CONST                      12: True
                410     NOP                             
                412     NOP                             
                414     JUMP_FORWARD                    322 (to 1062)
                424     POP_TOP                         
                426     RETURN_CONST                    12: True
                428     LOAD_FAST                       0: ids
                430     LOAD_CONST                      19: 5
                432     COMPARE_OP                      40 (==)
                436     POP_JUMP_IF_FALSE               29 (to 496)
                438     PUSH_NULL                       
                440     LOAD_CONST                      1: '__pyarmor_assert_15873__'
                442     LOAD_CONST                      20: 'mod:reporter'   # b'\x81\xef\x17\x17i\xe8\xbb\xc2\x14\xe8\x19\xc5~'
                444     CALL                            1
                452     LOAD_FAST                       3: _var_var_3
                454     CONTAINS_OP                     0 (in)
                456     POP_JUMP_IF_FALSE               19 (to 496)
                458     NOP                             
                460     LOAD_CONST                      0: None
                462     LOAD_CONST                      0: None
                464     LOAD_CONST                      0: None
                466     CALL                            2
                474     POP_TOP                         
                476     LOAD_CONST                      12: True
                478     NOP                             
                480     NOP                             
                482     JUMP_FORWARD                    288 (to 1062)
                492     POP_TOP                         
                494     RETURN_CONST                    12: True
                496     LOAD_FAST                       0: ids
                498     LOAD_CONST                      21: 6
                500     COMPARE_OP                      40 (==)
                504     POP_JUMP_IF_FALSE               29 (to 564)
                506     PUSH_NULL                       
                508     LOAD_CONST                      1: '__pyarmor_assert_15873__'
                510     LOAD_CONST                      22: 'mod:chatcloner'   # b'\x81\xef\x17\x17i\xf9\xb6\xd3\x0f\xf9\x01\xcfb\xe9\xea'
                512     CALL                            1
                520     LOAD_FAST                       3: _var_var_3
                522     CONTAINS_OP                     0 (in)
                524     POP_JUMP_IF_FALSE               19 (to 564)
                526     NOP                             
                528     LOAD_CONST                      0: None
                530     LOAD_CONST                      0: None
                532     LOAD_CONST                      0: None
                534     CALL                            2
                542     POP_TOP                         
                544     LOAD_CONST                      12: True
                546     NOP                             
                548     NOP                             
                550     NOP                             
                552     JUMP_FORWARD                    254 (to 1062)
                560     POP_TOP                         
                562     RETURN_CONST                    12: True
                564     LOAD_FAST                       0: ids
                566     LOAD_CONST                      23: 7
                568     COMPARE_OP                      40 (==)
                572     POP_JUMP_IF_FALSE               29 (to 632)
                574     PUSH_NULL                       
                576     LOAD_CONST                      1: '__pyarmor_assert_15873__'
                578     LOAD_CONST                      24: 'mod:channelcloner'   # b'\x81\xef\x17\x17i\xf9\xb6\xd3\x15\xf4\x08\xcco\xe0\xf7\x8b\nO'
                580     CALL                            1
                588     LOAD_FAST                       3: _var_var_3
                590     CONTAINS_OP                     0 (in)
                592     POP_JUMP_IF_FALSE               19 (to 632)
                594     NOP                             
                596     LOAD_CONST                      0: None
                598     LOAD_CONST                      0: None
                600     LOAD_CONST                      0: None
                602     CALL                            2
                610     POP_TOP                         
                612     LOAD_CONST                      12: True
                614     NOP                             
                616     NOP                             
                618     NOP                             
                620     JUMP_FORWARD                    220 (to 1062)
                628     POP_TOP                         
                630     RETURN_CONST                    12: True
                632     LOAD_FAST                       0: ids
                634     LOAD_CONST                      25: 8
                636     COMPARE_OP                      40 (==)
                640     POP_JUMP_IF_FALSE               29 (to 700)
                642     PUSH_NULL                       
                644     LOAD_CONST                      1: '__pyarmor_assert_15873__'
                646     LOAD_CONST                      26: 'mod:forwarder'   # b'\x81\xef\x17\x17i\xfc\xb1\xc0\x0c\xfb\x1f\xc4i\xfe'
                648     CALL                            1
                656     LOAD_FAST                       3: _var_var_3
                658     CONTAINS_OP                     0 (in)
                660     POP_JUMP_IF_FALSE               19 (to 700)
                662     NOP                             
                664     LOAD_CONST                      0: None
                666     LOAD_CONST                      0: None
                668     LOAD_CONST                      0: None
                670     CALL                            2
                678     POP_TOP                         
                680     LOAD_CONST                      12: True
                682     NOP                             
                684     NOP                             
                686     NOP                             
                688     JUMP_FORWARD                    186 (to 1062)
                696     POP_TOP                         
                698     RETURN_CONST                    12: True
                700     LOAD_FAST                       0: ids
                702     LOAD_CONST                      27: 9
                704     COMPARE_OP                      40 (==)
                708     POP_JUMP_IF_FALSE               29 (to 768)
                710     PUSH_NULL                       
                712     LOAD_CONST                      1: '__pyarmor_assert_15873__'
                714     LOAD_CONST                      28: 'mod:booster'   # b'\x81\xef\x17\x17i\xf8\xb1\xdd\x08\xee\x08\xd2'
                716     CALL                            1
                724     LOAD_FAST                       3: _var_var_3
                726     CONTAINS_OP                     0 (in)
                728     POP_JUMP_IF_FALSE               19 (to 768)
                730     NOP                             
                732     LOAD_CONST                      0: None
                734     LOAD_CONST                      0: None
                736     LOAD_CONST                      0: None
                738     CALL                            2
                746     POP_TOP                         
                748     LOAD_CONST                      12: True
                750     NOP                             
                752     NOP                             
                754     NOP                             
                756     JUMP_FORWARD                    152 (to 1062)
                764     POP_TOP                         
                766     RETURN_CONST                    12: True
                768     LOAD_FAST                       0: ids
                770     LOAD_CONST                      29: 10
                772     COMPARE_OP                      40 (==)
                776     POP_JUMP_IF_FALSE               29 (to 836)
                778     PUSH_NULL                       
                780     LOAD_CONST                      1: '__pyarmor_assert_15873__'
                782     LOAD_CONST                      30: 'mod:converter'   # b'\x81\xef\x17\x17i\xf9\xb1\xdc\r\xff\x1f\xd4i\xfe'
                784     CALL                            1
                792     LOAD_FAST                       3: _var_var_3
                794     CONTAINS_OP                     0 (in)
                796     POP_JUMP_IF_FALSE               19 (to 836)
                798     NOP                             
                800     LOAD_CONST                      0: None
                802     LOAD_CONST                      0: None
                804     LOAD_CONST                      0: None
                806     CALL                            2
                814     POP_TOP                         
                816     LOAD_CONST                      12: True
                818     NOP                             
                820     NOP                             
                822     NOP                             
                824     JUMP_FORWARD                    118 (to 1062)
                832     POP_TOP                         
                834     RETURN_CONST                    12: True
                836     LOAD_FAST                       0: ids
                838     LOAD_CONST                      31: 11
                840     COMPARE_OP                      40 (==)
                844     POP_JUMP_IF_FALSE               23 (to 892)
                846     LOAD_CONST                      32: 'mod:gpt'
                848     LOAD_FAST                       3: _var_var_3
                850     CONTAINS_OP                     0 (in)
                852     POP_JUMP_IF_FALSE               19 (to 892)
                854     NOP                             
                856     LOAD_CONST                      0: None
                858     LOAD_CONST                      0: None
                860     LOAD_CONST                      0: None
                862     CALL                            2
                870     POP_TOP                         
                872     LOAD_CONST                      12: True
                874     NOP                             
                876     NOP                             
                878     NOP                             
                880     JUMP_FORWARD                    90 (to 1062)
                888     POP_TOP                         
                890     RETURN_CONST                    12: True
                892     LOAD_FAST                       0: ids
                894     LOAD_CONST                      33: 12
                896     COMPARE_OP                      40 (==)
                900     POP_JUMP_IF_FALSE               29 (to 960)
                902     PUSH_NULL                       
                904     LOAD_CONST                      1: '__pyarmor_assert_15873__'
                906     LOAD_CONST                      34: 'mod:privatereg'   # b'\x81\xef\x17\x17i\xea\xac\xdb\r\xfb\x19\xc5~\xe9\xff'
                908     CALL                            1
                916     LOAD_FAST                       3: _var_var_3
                918     CONTAINS_OP                     0 (in)
                920     POP_JUMP_IF_FALSE               19 (to 960)
                922     NOP                             
                924     LOAD_CONST                      0: None
                926     LOAD_CONST                      0: None
                928     LOAD_CONST                      0: None
                930     CALL                            2
                938     POP_TOP                         
                940     LOAD_CONST                      12: True
                942     NOP                             
                944     NOP                             
                946     NOP                             
                948     JUMP_FORWARD                    56 (to 1062)
                956     POP_TOP                         
                958     RETURN_CONST                    12: True
                960     LOAD_CONST                      0: None
                962     LOAD_CONST                      0: None
                964     LOAD_CONST                      0: None
                966     CALL                            2
                974     POP_TOP                         
                976     LOAD_CONST                      35: False
                978     NOP                             
                980     NOP                             
                982     NOP                             
                984     JUMP_FORWARD                    38 (to 1062)
                992     POP_TOP                         
                994     RETURN_CONST                    35: False
                996     PUSH_EXC_INFO                   
                998     WITH_EXCEPT_START               
                1000    POP_JUMP_IF_TRUE                1 (to 1004)
                1002    RERAISE                         2
                1004    POP_TOP                         
                1006    POP_EXCEPT                      
                1008    POP_TOP                         
                1010    POP_TOP                         
                1012    JUMP_BACKWARD                   19 (to 976)
                1014    COPY                            3
                1016    POP_EXCEPT                      
                1018    RERAISE                         1
                1020    PUSH_EXC_INFO                   
                1022    POP_TOP                         
                1024    POP_EXCEPT                      
                1026    JUMP_BACKWARD                   26 (to 976)
                1028    COPY                            3
                1030    POP_EXCEPT                      
                1032    RERAISE                         1
                1034    PUSH_EXC_INFO                   
                1036    PUSH_NULL                       
                1038    LOAD_CONST                      11: '__pyarmor_exit_15875__'
                1040    NOP                             
                1042    LOAD_CONST                      3: b'<COAddr>\x05\x00\x00\x1a\xf0\x03\x00\x00\x00\x00\x00\x00\x00\x00\x00\x00\x00\x00\x00\x00'
                1044    CALL                            1
                1052    POP_TOP                         
                1054    RERAISE                         0
                1056    COPY                            3
                1058    POP_EXCEPT                      
                1060    RERAISE                         1
                1062    PUSH_NULL                       
                1064    LOAD_CONST                      11: '__pyarmor_exit_15875__'
                1066    LOAD_CONST                      3: b'<COAddr>\x05\x00\x00\x1a\xf0\x03\x00\x00\x00\x00\x00\x00\x00\x00\x00\x00\x00\x00\x00\x00'
                1068    BUILD_TUPLE                     1
                1070    CALL_FUNCTION_EX                0
                1072    POP_TOP                         
                1074    RETURN_VALUE                    
            [Exception Table]
                30 to 72 -> 1020 [0] 
                72 to 188 -> 996 [1] lasti
                188 to 204 -> 1020 [0] 
                224 to 256 -> 996 [1] lasti
                256 to 272 -> 1020 [0] 
                292 to 324 -> 996 [1] lasti
                324 to 340 -> 1020 [0] 
                360 to 392 -> 996 [1] lasti
                392 to 408 -> 1020 [0] 
                428 to 460 -> 996 [1] lasti
                460 to 476 -> 1020 [0] 
                496 to 528 -> 996 [1] lasti
                528 to 544 -> 1020 [0] 
                564 to 596 -> 996 [1] lasti
                596 to 612 -> 1020 [0] 
                632 to 664 -> 996 [1] lasti
                664 to 680 -> 1020 [0] 
                700 to 732 -> 996 [1] lasti
                732 to 748 -> 1020 [0] 
                768 to 800 -> 996 [1] lasti
                800 to 816 -> 1020 [0] 
                836 to 856 -> 996 [1] lasti
                856 to 872 -> 1020 [0] 
                892 to 924 -> 996 [1] lasti
                924 to 940 -> 1020 [0] 
                960 to 976 -> 1020 [0] 
                996 to 1006 -> 1014 [3] lasti
                1006 to 1020 -> 1020 [0] 
                1020 to 1024 -> 1028 [1] lasti
                1024 to 1034 -> 1034 [0] 
                1034 to 1056 -> 1056 [1] lasti
        [Code]
            File Name: <frozen program.static_classes.memory>
            Object Name: memory_set_lang
            Qualified Name: memory_set_lang
            Arg Count: 1
            Pos Only Arg Count: 0
            KW Only Arg Count: 0
            Stack Size: 6
            Flags: 0x20000003 (CO_OPTIMIZED | CO_NEWLOCALS | CO_PYARMOR_OBFUSCATED)
            [Names]
                'startswith'
                'open'
                'FileProtector'
                'encrypt'
                'write'
            [Locals+Names]
                'key'
                '__assert_armored__'
                '_var_var_11'
                '_var_var_10'
            [Constants]
                None
                '__pyarmor_assert_15876__'
                '__pyarmor_enter_15877__'
                b'<COAddr>\x07\x00\x00\x1a@\x01\x00\x00\x00\x00\x00\x00\x00\x00\x00\x00\x00\x00\x00\x00'
                'EXPERT-EN'   # b'\x81\xc7 #\x16\xc8\x8a\x9f>\xd4'
                'lang:en'
                'EXPERT-CN'   # b'\x81\xc7 #\x16\xc8\x8a\x9f8\xd4'
                'lang:cn'
                'lang:ru'
                'temp/002.dat'   # b'\x81\xf6\x1d\x1e#\xb5\xee\x82I\xb4\t\xc1x'
                'w'
                'utf-8'
                'ignore'
                (
                    'encoding'
                    'errors'
                )
                '__pyarmor_exit_15878__'
                True
                False
            [Disassembly]
                0       NOP                             
                2       NOP                             
                4       PUSH_NULL                       
                6       LOAD_CONST                      2: '__pyarmor_enter_15877__'
                8       LOAD_CONST                      3: b'<COAddr>\x07\x00\x00\x1a@\x01\x00\x00\x00\x00\x00\x00\x00\x00\x00\x00\x00\x00\x00\x00'
                10      BUILD_TUPLE                     1
                12      CALL_FUNCTION_EX                0
                14      POP_TOP                         
                16      RESUME                          0
                18      NOP                             
                20      NOP                             
                22      NOP                             
                24      NOP                             
                26      NOP                             
                28      LOAD_FAST                       0: key
                30      LOAD_ATTR                       1: startswith
                50      PUSH_NULL                       
                52      LOAD_CONST                      1: '__pyarmor_assert_15876__'
                54      LOAD_CONST                      4: 'EXPERT-EN'   # b'\x81\xc7 #\x16\xc8\x8a\x9f>\xd4'
                56      CALL                            1
                64      CALL                            1
                72      POP_JUMP_IF_FALSE               3 (to 80)
                74      LOAD_CONST                      5: 'lang:en'
                76      STORE_FAST                      2: _var_var_11
                78      JUMP_FORWARD                    28 (to 136)
                80      LOAD_FAST                       0: key
                82      LOAD_ATTR                       1: startswith
                102     PUSH_NULL                       
                104     LOAD_CONST                      1: '__pyarmor_assert_15876__'
                106     LOAD_CONST                      6: 'EXPERT-CN'   # b'\x81\xc7 #\x16\xc8\x8a\x9f8\xd4'
                108     CALL                            1
                116     CALL                            1
                124     POP_JUMP_IF_FALSE               3 (to 132)
                126     LOAD_CONST                      7: 'lang:cn'
                128     STORE_FAST                      2: _var_var_11
                130     JUMP_FORWARD                    2 (to 136)
                132     LOAD_CONST                      8: 'lang:ru'
                134     STORE_FAST                      2: _var_var_11
                136     LOAD_GLOBAL                     3: NULL + open
                146     PUSH_NULL                       
                148     LOAD_CONST                      1: '__pyarmor_assert_15876__'
                150     LOAD_CONST                      9: 'temp/002.dat'   # b'\x81\xf6\x1d\x1e#\xb5\xee\x82I\xb4\t\xc1x'
                152     CALL                            1
                160     LOAD_CONST                      10: 'w'
                162     LOAD_CONST                      11: 'utf-8'
                164     LOAD_CONST                      12: 'ignore'
                166     KW_NAMES                        13: ('encoding', 'errors')
                168     CALL                            4
                176     BEFORE_WITH                     
                178     STORE_FAST                      3: _var_var_10
                180     LOAD_GLOBAL                     5: NULL + FileProtector
                190     CALL                            0
                198     LOAD_ATTR                       7: encrypt
                218     LOAD_FAST                       2: _var_var_11
                220     CALL                            1
                228     STORE_FAST                      2: _var_var_11
                230     LOAD_FAST                       3: _var_var_10
                232     LOAD_ATTR                       9: write
                252     LOAD_FAST                       2: _var_var_11
                254     CALL                            1
                262     POP_TOP                         
                264     NOP                             
                266     LOAD_CONST                      0: None
                268     LOAD_CONST                      0: None
                270     LOAD_CONST                      0: None
                272     CALL                            2
                280     POP_TOP                         
                282     LOAD_CONST                      15: True
                284     NOP                             
                286     NOP                             
                288     NOP                             
                290     JUMP_FORWARD                    41 (to 374)
                298     POP_TOP                         
                300     RETURN_CONST                    15: True
                302     PUSH_EXC_INFO                   
                304     WITH_EXCEPT_START               
                306     POP_JUMP_IF_TRUE                1 (to 310)
                308     RERAISE                         2
                310     POP_TOP                         
                312     POP_EXCEPT                      
                314     POP_TOP                         
                316     POP_TOP                         
                318     JUMP_FORWARD                    3 (to 326)
                320     COPY                            3
                322     POP_EXCEPT                      
                324     RERAISE                         1
                326     LOAD_CONST                      16: False
                328     NOP                             
                330     NOP                             
                332     NOP                             
                334     JUMP_FORWARD                    19 (to 374)
                342     POP_TOP                         
                344     RETURN_CONST                    16: False
                346     PUSH_EXC_INFO                   
                348     PUSH_NULL                       
                350     LOAD_CONST                      14: '__pyarmor_exit_15878__'
                352     NOP                             
                354     LOAD_CONST                      3: b'<COAddr>\x07\x00\x00\x1a@\x01\x00\x00\x00\x00\x00\x00\x00\x00\x00\x00\x00\x00\x00\x00'
                356     CALL                            1
                364     POP_TOP                         
                366     RERAISE                         0
                368     COPY                            3
                370     POP_EXCEPT                      
                372     RERAISE                         1
                374     PUSH_NULL                       
                376     LOAD_CONST                      14: '__pyarmor_exit_15878__'
                378     LOAD_CONST                      3: b'<COAddr>\x07\x00\x00\x1a@\x01\x00\x00\x00\x00\x00\x00\x00\x00\x00\x00\x00\x00\x00\x00'
                380     BUILD_TUPLE                     1
                382     CALL_FUNCTION_EX                0
                384     POP_TOP                         
                386     RETURN_VALUE                    
            [Exception Table]
                28 to 178 -> 346 [0] 
                178 to 266 -> 302 [1] lasti
                266 to 282 -> 346 [0] 
                302 to 312 -> 320 [3] lasti
                312 to 326 -> 346 [0] 
                346 to 368 -> 368 [1] lasti
        [Code]
            File Name: <frozen program.static_classes.memory>
            Object Name: memory_get_lang
            Qualified Name: memory_get_lang
            Arg Count: 0
            Pos Only Arg Count: 0
            KW Only Arg Count: 0
            Stack Size: 6
            Flags: 0x20000003 (CO_OPTIMIZED | CO_NEWLOCALS | CO_PYARMOR_OBFUSCATED)
            [Names]
                'open'
                'read'
                'FileProtector'
                'decrypt'
            [Locals+Names]
                '__assert_armored__'
                '_var_var_10'
                '_var_var_3'
            [Constants]
                None
                '__pyarmor_assert_15879__'
                '__pyarmor_enter_15880__'
                b'<COAddr>\x05\x00\x00\x1aX\x01\x00\x00\x00\x00\x00\x00\x00\x00\x00\x00\x00\x00\x00\x00'
                'temp/002.dat'   # b'\x81\xf6\x1d\x1e#\xb5\xee\x82I\xb4\t\xc1x'
                'r'
                'utf-8'
                'ignore'
                (
                    'encoding'
                    'errors'
                )
                'lang:ru'
                '__pyarmor_exit_15881__'
                'ru'
                'lang:en'
                'en'
                'lang:cn'
                'cn'
                False
            [Disassembly]
                0       NOP                             
                2       NOP                             
                4       PUSH_NULL                       
                6       LOAD_CONST                      2: '__pyarmor_enter_15880__'
                8       LOAD_CONST                      3: b'<COAddr>\x05\x00\x00\x1aX\x01\x00\x00\x00\x00\x00\x00\x00\x00\x00\x00\x00\x00\x00\x00'
                10      BUILD_TUPLE                     1
                12      CALL_FUNCTION_EX                0
                14      POP_TOP                         
                16      RESUME                          0
                18      NOP                             
                20      NOP                             
                22      NOP                             
                24      NOP                             
                26      NOP                             
                28      NOP                             
                30      LOAD_GLOBAL                     1: NULL + open
                40      PUSH_NULL                       
                42      LOAD_CONST                      1: '__pyarmor_assert_15879__'
                44      LOAD_CONST                      4: 'temp/002.dat'   # b'\x81\xf6\x1d\x1e#\xb5\xee\x82I\xb4\t\xc1x'
                46      CALL                            1
                54      LOAD_CONST                      5: 'r'
                56      LOAD_CONST                      6: 'utf-8'
                58      LOAD_CONST                      7: 'ignore'
                60      KW_NAMES                        8: ('encoding', 'errors')
                62      CALL                            4
                70      BEFORE_WITH                     
                72      STORE_FAST                      1: _var_var_10
                74      LOAD_FAST                       1: _var_var_10
                76      LOAD_ATTR                       3: read
                96      CALL                            0
                104     STORE_FAST                      2: _var_var_3
                106     LOAD_GLOBAL                     5: NULL + FileProtector
                116     CALL                            0
                124     LOAD_ATTR                       7: decrypt
                144     LOAD_FAST                       2: _var_var_3
                146     CALL                            1
                154     STORE_FAST                      2: _var_var_3
                156     LOAD_CONST                      9: 'lang:ru'
                158     LOAD_FAST                       2: _var_var_3
                160     CONTAINS_OP                     0 (in)
                162     POP_JUMP_IF_FALSE               19 (to 202)
                164     NOP                             
                166     LOAD_CONST                      0: None
                168     LOAD_CONST                      0: None
                170     LOAD_CONST                      0: None
                172     CALL                            2
                180     POP_TOP                         
                182     LOAD_CONST                      11: 'ru'
                184     NOP                             
                186     NOP                             
                188     NOP                             
                190     JUMP_FORWARD                    103 (to 398)
                198     POP_TOP                         
                200     RETURN_CONST                    11: 'ru'
                202     LOAD_CONST                      12: 'lang:en'
                204     LOAD_FAST                       2: _var_var_3
                206     CONTAINS_OP                     0 (in)
                208     POP_JUMP_IF_FALSE               19 (to 248)
                210     NOP                             
                212     LOAD_CONST                      0: None
                214     LOAD_CONST                      0: None
                216     LOAD_CONST                      0: None
                218     CALL                            2
                226     POP_TOP                         
                228     LOAD_CONST                      13: 'en'
                230     NOP                             
                232     NOP                             
                234     NOP                             
                236     JUMP_FORWARD                    80 (to 398)
                244     POP_TOP                         
                246     RETURN_CONST                    13: 'en'
                248     LOAD_CONST                      14: 'lang:cn'
                250     LOAD_FAST                       2: _var_var_3
                252     CONTAINS_OP                     0 (in)
                254     POP_JUMP_IF_FALSE               19 (to 294)
                256     NOP                             
                258     LOAD_CONST                      0: None
                260     LOAD_CONST                      0: None
                262     LOAD_CONST                      0: None
                264     CALL                            2
                272     POP_TOP                         
                274     LOAD_CONST                      15: 'cn'
                276     NOP                             
                278     NOP                             
                280     NOP                             
                282     JUMP_FORWARD                    57 (to 398)
                290     POP_TOP                         
                292     RETURN_CONST                    15: 'cn'
                294     NOP                             
                296     LOAD_CONST                      0: None
                298     LOAD_CONST                      0: None
                300     LOAD_CONST                      0: None
                302     CALL                            2
                310     POP_TOP                         
                312     LOAD_CONST                      16: False
                314     NOP                             
                316     NOP                             
                318     NOP                             
                320     JUMP_FORWARD                    38 (to 398)
                328     POP_TOP                         
                330     RETURN_CONST                    16: False
                332     PUSH_EXC_INFO                   
                334     WITH_EXCEPT_START               
                336     POP_JUMP_IF_TRUE                1 (to 340)
                338     RERAISE                         2
                340     POP_TOP                         
                342     POP_EXCEPT                      
                344     POP_TOP                         
                346     POP_TOP                         
                348     JUMP_BACKWARD                   19 (to 312)
                350     COPY                            3
                352     POP_EXCEPT                      
                354     RERAISE                         1
                356     PUSH_EXC_INFO                   
                358     POP_TOP                         
                360     POP_EXCEPT                      
                362     JUMP_BACKWARD                   26 (to 312)
                364     COPY                            3
                366     POP_EXCEPT                      
                368     RERAISE                         1
                370     PUSH_EXC_INFO                   
                372     PUSH_NULL                       
                374     LOAD_CONST                      10: '__pyarmor_exit_15881__'
                376     NOP                             
                378     LOAD_CONST                      3: b'<COAddr>\x05\x00\x00\x1aX\x01\x00\x00\x00\x00\x00\x00\x00\x00\x00\x00\x00\x00\x00\x00'
                380     CALL                            1
                388     POP_TOP                         
                390     RERAISE                         0
                392     COPY                            3
                394     POP_EXCEPT                      
                396     RERAISE                         1
                398     PUSH_NULL                       
                400     LOAD_CONST                      10: '__pyarmor_exit_15881__'
                402     LOAD_CONST                      3: b'<COAddr>\x05\x00\x00\x1aX\x01\x00\x00\x00\x00\x00\x00\x00\x00\x00\x00\x00\x00\x00\x00'
                404     BUILD_TUPLE                     1
                406     CALL_FUNCTION_EX                0
                408     POP_TOP                         
                410     RETURN_VALUE                    
            [Exception Table]
                30 to 72 -> 356 [0] 
                72 to 166 -> 332 [1] lasti
                166 to 182 -> 356 [0] 
                202 to 212 -> 332 [1] lasti
                212 to 228 -> 356 [0] 
                248 to 258 -> 332 [1] lasti
                258 to 274 -> 356 [0] 
                296 to 312 -> 356 [0] 
                332 to 342 -> 350 [3] lasti
                342 to 356 -> 356 [0] 
                356 to 360 -> 364 [1] lasti
                360 to 370 -> 370 [0] 
                370 to 392 -> 392 [1] lasti
        [Code]
            File Name: <frozen program.static_classes.memory>
            Object Name: memory_set_switcher
            Qualified Name: memory_set_switcher
            Arg Count: 0
            Pos Only Arg Count: 0
            KW Only Arg Count: 0
            Stack Size: 6
            Flags: 0x20000003 (CO_OPTIMIZED | CO_NEWLOCALS | CO_PYARMOR_OBFUSCATED)
            [Names]
                'get_lic_key'
                'datetime'
                'now'
                'strftime'
                'SHA256'
                'new'
                'update'
                'encode'
                'hexdigest'
                'open'
                'FileProtector'
                'encrypt'
                'write'
            [Locals+Names]
                '__assert_armored__'
                '_var_var_0'
                '_var_var_2'
                '_var_var_3'
                '_var_var_4'
                '_var_var_10'
            [Constants]
                None
                '__pyarmor_assert_15882__'
                '__pyarmor_enter_15883__'
                b'<COAddr>\x07\x00\x00\x1a\xea\x01\x00\x00\x00\x00\x00\x00\x00\x00\x00\x00\x00\x00\x00\x00'
                '%Y-%m-%U'
                '_'
                'utf-8'
                'temp/003.dat'   # b'\x81\xf6\x1d\x1e#\xb5\xee\x82H\xb4\t\xc1x'
                'w'
                'ignore'
                (
                    'encoding'
                    'errors'
                )
                '__pyarmor_exit_15884__'
                True
                False
            [Disassembly]
                0       NOP                             
                2       NOP                             
                4       PUSH_NULL                       
                6       LOAD_CONST                      2: '__pyarmor_enter_15883__'
                8       LOAD_CONST                      3: b'<COAddr>\x07\x00\x00\x1a\xea\x01\x00\x00\x00\x00\x00\x00\x00\x00\x00\x00\x00\x00\x00\x00'
                10      BUILD_TUPLE                     1
                12      CALL_FUNCTION_EX                0
                14      POP_TOP                         
                16      RESUME                          0
                18      NOP                             
                20      NOP                             
                22      NOP                             
                24      NOP                             
                26      NOP                             
                28      NOP                             
                30      LOAD_GLOBAL                     1: NULL + get_lic_key
                40      CALL                            0
                48      STORE_FAST                      1: _var_var_0
                50      LOAD_GLOBAL                     2: datetime
                60      LOAD_ATTR                       2: datetime
                80      LOAD_ATTR                       5: now
                100     CALL                            0
                108     LOAD_ATTR                       7: strftime
                128     LOAD_CONST                      4: '%Y-%m-%U'
                130     CALL                            1
                138     STORE_FAST                      2: _var_var_2
                140     LOAD_FAST                       2: _var_var_2
                142     FORMAT_VALUE                    0 (FVC_NONE)
                144     LOAD_CONST                      5: '_'
                146     LOAD_FAST                       1: _var_var_0
                148     FORMAT_VALUE                    0 (FVC_NONE)
                150     BUILD_STRING                    3
                152     STORE_FAST                      3: _var_var_3
                154     LOAD_GLOBAL                     9: NULL + SHA256
                164     LOAD_ATTR                       10: new
                184     CALL                            0
                192     STORE_FAST                      4: _var_var_4
                194     LOAD_FAST                       4: _var_var_4
                196     LOAD_ATTR                       13: update
                216     LOAD_FAST                       3: _var_var_3
                218     LOAD_ATTR                       15: encode
                238     LOAD_CONST                      6: 'utf-8'
                240     CALL                            1
                248     CALL                            1
                256     POP_TOP                         
                258     LOAD_FAST                       4: _var_var_4
                260     LOAD_ATTR                       17: hexdigest
                280     CALL                            0
                288     STORE_FAST                      3: _var_var_3
                290     LOAD_GLOBAL                     19: NULL + open
                300     PUSH_NULL                       
                302     LOAD_CONST                      1: '__pyarmor_assert_15882__'
                304     LOAD_CONST                      7: 'temp/003.dat'   # b'\x81\xf6\x1d\x1e#\xb5\xee\x82H\xb4\t\xc1x'
                306     CALL                            1
                314     LOAD_CONST                      8: 'w'
                316     LOAD_CONST                      6: 'utf-8'
                318     LOAD_CONST                      9: 'ignore'
                320     KW_NAMES                        10: ('encoding', 'errors')
                322     CALL                            4
                330     BEFORE_WITH                     
                332     STORE_FAST                      5: _var_var_10
                334     LOAD_GLOBAL                     21: NULL + FileProtector
                344     CALL                            0
                352     LOAD_ATTR                       23: encrypt
                372     LOAD_FAST                       3: _var_var_3
                374     CALL                            1
                382     STORE_FAST                      3: _var_var_3
                384     LOAD_FAST                       5: _var_var_10
                386     LOAD_ATTR                       25: write
                406     LOAD_FAST                       3: _var_var_3
                408     CALL                            1
                416     POP_TOP                         
                418     NOP                             
                420     LOAD_CONST                      0: None
                422     LOAD_CONST                      0: None
                424     LOAD_CONST                      0: None
                426     CALL                            2
                434     POP_TOP                         
                436     LOAD_CONST                      12: True
                438     NOP                             
                440     NOP                             
                442     NOP                             
                444     JUMP_FORWARD                    49 (to 544)
                452     POP_TOP                         
                454     RETURN_CONST                    12: True
                456     PUSH_EXC_INFO                   
                458     WITH_EXCEPT_START               
                460     POP_JUMP_IF_TRUE                1 (to 464)
                462     RERAISE                         2
                464     POP_TOP                         
                466     POP_EXCEPT                      
                468     POP_TOP                         
                470     POP_TOP                         
                472     JUMP_FORWARD                    3 (to 480)
                474     COPY                            3
                476     POP_EXCEPT                      
                478     RERAISE                         1
                480     JUMP_FORWARD                    7 (to 496)
                482     PUSH_EXC_INFO                   
                484     POP_TOP                         
                486     POP_EXCEPT                      
                488     JUMP_FORWARD                    3 (to 496)
                490     COPY                            3
                492     POP_EXCEPT                      
                494     RERAISE                         1
                496     LOAD_CONST                      13: False
                498     NOP                             
                500     NOP                             
                502     NOP                             
                504     JUMP_FORWARD                    19 (to 544)
                512     POP_TOP                         
                514     RETURN_CONST                    13: False
                516     PUSH_EXC_INFO                   
                518     PUSH_NULL                       
                520     LOAD_CONST                      11: '__pyarmor_exit_15884__'
                522     NOP                             
                524     LOAD_CONST                      3: b'<COAddr>\x07\x00\x00\x1a\xea\x01\x00\x00\x00\x00\x00\x00\x00\x00\x00\x00\x00\x00\x00\x00'
                526     CALL                            1
                534     POP_TOP                         
                536     RERAISE                         0
                538     COPY                            3
                540     POP_EXCEPT                      
                542     RERAISE                         1
                544     PUSH_NULL                       
                546     LOAD_CONST                      11: '__pyarmor_exit_15884__'
                548     LOAD_CONST                      3: b'<COAddr>\x07\x00\x00\x1a\xea\x01\x00\x00\x00\x00\x00\x00\x00\x00\x00\x00\x00\x00\x00\x00'
                550     BUILD_TUPLE                     1
                552     CALL_FUNCTION_EX                0
                554     POP_TOP                         
                556     RETURN_VALUE                    
            [Exception Table]
                30 to 332 -> 482 [0] 
                332 to 420 -> 456 [1] lasti
                420 to 436 -> 482 [0] 
                456 to 466 -> 474 [3] lasti
                466 to 480 -> 482 [0] 
                480 to 482 -> 516 [0] 
                482 to 486 -> 490 [1] lasti
                486 to 496 -> 516 [0] 
                516 to 538 -> 538 [1] lasti
        [Code]
            File Name: <frozen program.static_classes.memory>
            Object Name: memory_check_switcher
            Qualified Name: memory_check_switcher
            Arg Count: 1
            Pos Only Arg Count: 0
            KW Only Arg Count: 0
            Stack Size: 6
            Flags: 0x20000003 (CO_OPTIMIZED | CO_NEWLOCALS | CO_PYARMOR_OBFUSCATED)
            [Names]
                'get_lic_key'
                'datetime'
                'now'
                'strftime'
                'SHA256'
                'new'
                'update'
                'encode'
                'hexdigest'
                'open'
                'read'
                'FileProtector'
                'decrypt'
            [Locals+Names]
                'ids'
                '__assert_armored__'
                '_var_var_0'
                '_var_var_2'
                '_var_var_3'
                '_var_var_4'
                '_var_var_12'
                '_var_var_10'
            [Constants]
                None
                '__pyarmor_assert_15885__'
                '__pyarmor_enter_15886__'
                b'<COAddr>\x07\x00\x00\x1a\x00\x02\x00\x00\x00\x00\x00\x00\x00\x00\x00\x00\x00\x00\x00\x00'
                '%Y-%m-%U'
                '_'
                'utf-8'
                'temp/003.dat'   # b'\x81\xf6\x1d\x1e#\xb5\xee\x82H\xb4\t\xc1x'
                'r'
                'ignore'
                (
                    'encoding'
                    'errors'
                )
                '__pyarmor_exit_15887__'
                True
                False
            [Disassembly]
                0       NOP                             
                2       NOP                             
                4       PUSH_NULL                       
                6       LOAD_CONST                      2: '__pyarmor_enter_15886__'
                8       LOAD_CONST                      3: b'<COAddr>\x07\x00\x00\x1a\x00\x02\x00\x00\x00\x00\x00\x00\x00\x00\x00\x00\x00\x00\x00\x00'
                10      BUILD_TUPLE                     1
                12      CALL_FUNCTION_EX                0
                14      POP_TOP                         
                16      RESUME                          0
                18      NOP                             
                20      NOP                             
                22      NOP                             
                24      NOP                             
                26      NOP                             
                28      NOP                             
                30      LOAD_GLOBAL                     1: NULL + get_lic_key
                40      CALL                            0
                48      STORE_FAST                      2: _var_var_0
                50      LOAD_GLOBAL                     2: datetime
                60      LOAD_ATTR                       2: datetime
                80      LOAD_ATTR                       5: now
                100     CALL                            0
                108     LOAD_ATTR                       7: strftime
                128     LOAD_CONST                      4: '%Y-%m-%U'
                130     CALL                            1
                138     STORE_FAST                      3: _var_var_2
                140     LOAD_FAST                       3: _var_var_2
                142     FORMAT_VALUE                    0 (FVC_NONE)
                144     LOAD_CONST                      5: '_'
                146     LOAD_FAST                       2: _var_var_0
                148     FORMAT_VALUE                    0 (FVC_NONE)
                150     BUILD_STRING                    3
                152     STORE_FAST                      4: _var_var_3
                154     LOAD_GLOBAL                     9: NULL + SHA256
                164     LOAD_ATTR                       10: new
                184     CALL                            0
                192     STORE_FAST                      5: _var_var_4
                194     LOAD_FAST                       5: _var_var_4
                196     LOAD_ATTR                       13: update
                216     LOAD_FAST                       4: _var_var_3
                218     LOAD_ATTR                       15: encode
                238     LOAD_CONST                      6: 'utf-8'
                240     CALL                            1
                248     CALL                            1
                256     POP_TOP                         
                258     LOAD_FAST                       5: _var_var_4
                260     LOAD_ATTR                       17: hexdigest
                280     CALL                            0
                288     STORE_FAST                      6: _var_var_12
                290     LOAD_GLOBAL                     19: NULL + open
                300     PUSH_NULL                       
                302     LOAD_CONST                      1: '__pyarmor_assert_15885__'
                304     LOAD_CONST                      7: 'temp/003.dat'   # b'\x81\xf6\x1d\x1e#\xb5\xee\x82H\xb4\t\xc1x'
                306     CALL                            1
                314     LOAD_CONST                      8: 'r'
                316     LOAD_CONST                      6: 'utf-8'
                318     LOAD_CONST                      9: 'ignore'
                320     KW_NAMES                        10: ('encoding', 'errors')
                322     CALL                            4
                330     BEFORE_WITH                     
                332     STORE_FAST                      7: _var_var_10
                334     LOAD_FAST                       7: _var_var_10
                336     LOAD_ATTR                       21: read
                356     CALL                            0
                364     STORE_FAST                      4: _var_var_3
                366     LOAD_GLOBAL                     23: NULL + FileProtector
                376     CALL                            0
                384     LOAD_ATTR                       25: decrypt
                404     LOAD_FAST                       4: _var_var_3
                406     CALL                            1
                414     STORE_FAST                      4: _var_var_3
                416     LOAD_FAST                       6: _var_var_12
                418     LOAD_FAST                       4: _var_var_3
                420     CONTAINS_OP                     0 (in)
                422     POP_JUMP_IF_FALSE               19 (to 462)
                424     NOP                             
                426     LOAD_CONST                      0: None
                428     LOAD_CONST                      0: None
                430     LOAD_CONST                      0: None
                432     CALL                            2
                440     POP_TOP                         
                442     LOAD_CONST                      12: True
                444     NOP                             
                446     NOP                             
                448     NOP                             
                450     JUMP_FORWARD                    57 (to 566)
                458     POP_TOP                         
                460     RETURN_CONST                    12: True
                462     NOP                             
                464     LOAD_CONST                      0: None
                466     LOAD_CONST                      0: None
                468     LOAD_CONST                      0: None
                470     CALL                            2
                478     POP_TOP                         
                480     LOAD_CONST                      13: False
                482     NOP                             
                484     NOP                             
                486     NOP                             
                488     JUMP_FORWARD                    38 (to 566)
                496     POP_TOP                         
                498     RETURN_CONST                    13: False
                500     PUSH_EXC_INFO                   
                502     WITH_EXCEPT_START               
                504     POP_JUMP_IF_TRUE                1 (to 508)
                506     RERAISE                         2
                508     POP_TOP                         
                510     POP_EXCEPT                      
                512     POP_TOP                         
                514     POP_TOP                         
                516     JUMP_BACKWARD                   19 (to 480)
                518     COPY                            3
                520     POP_EXCEPT                      
                522     RERAISE                         1
                524     PUSH_EXC_INFO                   
                526     POP_TOP                         
                528     POP_EXCEPT                      
                530     JUMP_BACKWARD                   26 (to 480)
                532     COPY                            3
                534     POP_EXCEPT                      
                536     RERAISE                         1
                538     PUSH_EXC_INFO                   
                540     PUSH_NULL                       
                542     LOAD_CONST                      11: '__pyarmor_exit_15887__'
                544     NOP                             
                546     LOAD_CONST                      3: b'<COAddr>\x07\x00\x00\x1a\x00\x02\x00\x00\x00\x00\x00\x00\x00\x00\x00\x00\x00\x00\x00\x00'
                548     CALL                            1
                556     POP_TOP                         
                558     RERAISE                         0
                560     COPY                            3
                562     POP_EXCEPT                      
                564     RERAISE                         1
                566     PUSH_NULL                       
                568     LOAD_CONST                      11: '__pyarmor_exit_15887__'
                570     LOAD_CONST                      3: b'<COAddr>\x07\x00\x00\x1a\x00\x02\x00\x00\x00\x00\x00\x00\x00\x00\x00\x00\x00\x00\x00\x00'
                572     BUILD_TUPLE                     1
                574     CALL_FUNCTION_EX                0
                576     POP_TOP                         
                578     RETURN_VALUE                    
            [Exception Table]
                30 to 332 -> 524 [0] 
                332 to 426 -> 500 [1] lasti
                426 to 442 -> 524 [0] 
                464 to 480 -> 524 [0] 
                500 to 510 -> 518 [3] lasti
                510 to 524 -> 524 [0] 
                524 to 528 -> 532 [1] lasti
                528 to 538 -> 538 [0] 
                538 to 560 -> 560 [1] lasti
        [Code]
            File Name: <frozen program.static_classes.memory>
            Object Name: memory_set_pid
            Qualified Name: memory_set_pid
            Arg Count: 0
            Pos Only Arg Count: 0
            KW Only Arg Count: 0
            Stack Size: 6
            Flags: 0x20000003 (CO_OPTIMIZED | CO_NEWLOCALS | CO_PYARMOR_OBFUSCATED)
            [Names]
                'int'
                'time'
                'open'
                'write'
            [Locals+Names]
                '__assert_armored__'
                '_var_var_13'
                '_var_var_10'
            [Constants]
                None
                '__pyarmor_assert_15888__'
                '__pyarmor_enter_15889__'
                b'<COAddr>\x05\x00\x00\x1a\xce\x00\x00\x00\x00\x00\x00\x00\x00\x00\x00\x00\x00\x00\x00\x00'
                'temp/process.dat'   # b'\x81\xf6\x1d\x1e#\xb5\xae\xc0\x14\xf9\x08\xd3\x7f\xa2\xfc\x84\x1b'
                'a'
                'utf-8'
                'ignore'
                (
                    'encoding'
                    'errors'
                )
                '|'
                '__pyarmor_exit_15890__'
            [Disassembly]
                0       NOP                             
                2       NOP                             
                4       PUSH_NULL                       
                6       LOAD_CONST                      2: '__pyarmor_enter_15889__'
                8       LOAD_CONST                      3: b'<COAddr>\x05\x00\x00\x1a\xce\x00\x00\x00\x00\x00\x00\x00\x00\x00\x00\x00\x00\x00\x00\x00'
                10      BUILD_TUPLE                     1
                12      CALL_FUNCTION_EX                0
                14      POP_TOP                         
                16      RESUME                          0
                18      NOP                             
                20      NOP                             
                22      NOP                             
                24      NOP                             
                26      NOP                             
                28      LOAD_GLOBAL                     1: NULL + int
                38      LOAD_GLOBAL                     3: NULL + time
                48      LOAD_ATTR                       2: time
                68      CALL                            0
                76      CALL                            1
                84      STORE_FAST                      1: _var_var_13
                86      LOAD_GLOBAL                     5: NULL + open
                96      PUSH_NULL                       
                98      LOAD_CONST                      1: '__pyarmor_assert_15888__'
                100     LOAD_CONST                      4: 'temp/process.dat'   # b'\x81\xf6\x1d\x1e#\xb5\xae\xc0\x14\xf9\x08\xd3\x7f\xa2\xfc\x84\x1b'
                102     CALL                            1
                110     LOAD_CONST                      5: 'a'
                112     LOAD_CONST                      6: 'utf-8'
                114     LOAD_CONST                      7: 'ignore'
                116     KW_NAMES                        8: ('encoding', 'errors')
                118     CALL                            4
                126     BEFORE_WITH                     
                128     STORE_FAST                      2: _var_var_10
                130     LOAD_FAST                       2: _var_var_10
                132     LOAD_ATTR                       7: write
                152     LOAD_FAST                       1: _var_var_13
                154     FORMAT_VALUE                    0 (FVC_NONE)
                156     LOAD_CONST                      9: '|'
                158     BUILD_STRING                    2
                160     CALL                            1
                168     POP_TOP                         
                170     LOAD_CONST                      0: None
                172     LOAD_CONST                      0: None
                174     LOAD_CONST                      0: None
                176     CALL                            2
                184     POP_TOP                         
                186     LOAD_FAST                       1: _var_var_13
                188     NOP                             
                190     NOP                             
                192     NOP                             
                194     JUMP_FORWARD                    32 (to 260)
                196     CALL                            1
                204     POP_TOP                         
                206     RETURN_VALUE                    
                208     PUSH_EXC_INFO                   
                210     WITH_EXCEPT_START               
                212     POP_JUMP_IF_TRUE                1 (to 216)
                214     RERAISE                         2
                216     POP_TOP                         
                218     POP_EXCEPT                      
                220     POP_TOP                         
                222     POP_TOP                         
                224     JUMP_BACKWARD                   20 (to 186)
                226     COPY                            3
                228     POP_EXCEPT                      
                230     RERAISE                         1
                232     PUSH_EXC_INFO                   
                234     PUSH_NULL                       
                236     LOAD_CONST                      10: '__pyarmor_exit_15890__'
                238     NOP                             
                240     LOAD_CONST                      3: b'<COAddr>\x05\x00\x00\x1a\xce\x00\x00\x00\x00\x00\x00\x00\x00\x00\x00\x00\x00\x00\x00\x00'
                242     CALL                            1
                250     POP_TOP                         
                252     RERAISE                         0
                254     COPY                            3
                256     POP_EXCEPT                      
                258     RERAISE                         1
                260     PUSH_NULL                       
                262     LOAD_CONST                      10: '__pyarmor_exit_15890__'
                264     LOAD_CONST                      3: b'<COAddr>\x05\x00\x00\x1a\xce\x00\x00\x00\x00\x00\x00\x00\x00\x00\x00\x00\x00\x00\x00\x00'
                266     BUILD_TUPLE                     1
                268     CALL_FUNCTION_EX                0
                270     POP_TOP                         
                272     RETURN_VALUE                    
            [Exception Table]
                28 to 128 -> 232 [0] 
                128 to 170 -> 208 [1] lasti
                170 to 188 -> 232 [0] 
                208 to 218 -> 226 [3] lasti
                218 to 232 -> 232 [0] 
                232 to 254 -> 254 [1] lasti
        [Code]
            File Name: <frozen program.static_classes.memory>
            Object Name: memory_check_pid
            Qualified Name: memory_check_pid
            Arg Count: 1
            Pos Only Arg Count: 0
            KW Only Arg Count: 0
            Stack Size: 6
            Flags: 0x20000003 (CO_OPTIMIZED | CO_NEWLOCALS | CO_PYARMOR_OBFUSCATED)
            [Names]
                'open'
                'read'
                'str'
            [Locals+Names]
                'pid'
                '__assert_armored__'
                '_var_var_10'
                '_var_var_3'
            [Constants]
                None
                '__pyarmor_assert_15891__'
                '__pyarmor_enter_15892__'
                b'<COAddr>\x07\x00\x00\x1a\xdc\x00\x00\x00\x00\x00\x00\x00\x00\x00\x00\x00\x00\x00\x00\x00'
                'temp/process.dat'   # b'\x81\xf6\x1d\x1e#\xb5\xae\xc0\x14\xf9\x08\xd3\x7f\xa2\xfc\x84\x1b'
                'r'
                'utf-8'
                'ignore'
                (
                    'encoding'
                    'errors'
                )
                '__pyarmor_exit_15893__'
                True
                False
            [Disassembly]
                0       NOP                             
                2       NOP                             
                4       PUSH_NULL                       
                6       LOAD_CONST                      2: '__pyarmor_enter_15892__'
                8       LOAD_CONST                      3: b'<COAddr>\x07\x00\x00\x1a\xdc\x00\x00\x00\x00\x00\x00\x00\x00\x00\x00\x00\x00\x00\x00\x00'
                10      BUILD_TUPLE                     1
                12      CALL_FUNCTION_EX                0
                14      POP_TOP                         
                16      RESUME                          0
                18      NOP                             
                20      NOP                             
                22      NOP                             
                24      NOP                             
                26      NOP                             
                28      NOP                             
                30      LOAD_GLOBAL                     1: NULL + open
                40      PUSH_NULL                       
                42      LOAD_CONST                      1: '__pyarmor_assert_15891__'
                44      LOAD_CONST                      4: 'temp/process.dat'   # b'\x81\xf6\x1d\x1e#\xb5\xae\xc0\x14\xf9\x08\xd3\x7f\xa2\xfc\x84\x1b'
                46      CALL                            1
                54      LOAD_CONST                      5: 'r'
                56      LOAD_CONST                      6: 'utf-8'
                58      LOAD_CONST                      7: 'ignore'
                60      KW_NAMES                        8: ('encoding', 'errors')
                62      CALL                            4
                70      BEFORE_WITH                     
                72      STORE_FAST                      2: _var_var_10
                74      LOAD_FAST                       2: _var_var_10
                76      LOAD_ATTR                       3: read
                96      CALL                            0
                104     STORE_FAST                      3: _var_var_3
                106     LOAD_GLOBAL                     5: NULL + str
                116     LOAD_FAST                       0: pid
                118     CALL                            1
                126     LOAD_FAST                       3: _var_var_3
                128     CONTAINS_OP                     0 (in)
                130     POP_JUMP_IF_FALSE               19 (to 170)
                132     NOP                             
                134     LOAD_CONST                      0: None
                136     LOAD_CONST                      0: None
                138     LOAD_CONST                      0: None
                140     CALL                            2
                148     POP_TOP                         
                150     LOAD_CONST                      10: True
                152     NOP                             
                154     NOP                             
                156     NOP                             
                158     JUMP_FORWARD                    57 (to 274)
                166     POP_TOP                         
                168     RETURN_CONST                    10: True
                170     NOP                             
                172     LOAD_CONST                      0: None
                174     LOAD_CONST                      0: None
                176     LOAD_CONST                      0: None
                178     CALL                            2
                186     POP_TOP                         
                188     LOAD_CONST                      11: False
                190     NOP                             
                192     NOP                             
                194     NOP                             
                196     JUMP_FORWARD                    38 (to 274)
                204     POP_TOP                         
                206     RETURN_CONST                    11: False
                208     PUSH_EXC_INFO                   
                210     WITH_EXCEPT_START               
                212     POP_JUMP_IF_TRUE                1 (to 216)
                214     RERAISE                         2
                216     POP_TOP                         
                218     POP_EXCEPT                      
                220     POP_TOP                         
                222     POP_TOP                         
                224     JUMP_BACKWARD                   19 (to 188)
                226     COPY                            3
                228     POP_EXCEPT                      
                230     RERAISE                         1
                232     PUSH_EXC_INFO                   
                234     POP_TOP                         
                236     POP_EXCEPT                      
                238     JUMP_BACKWARD                   26 (to 188)
                240     COPY                            3
                242     POP_EXCEPT                      
                244     RERAISE                         1
                246     PUSH_EXC_INFO                   
                248     PUSH_NULL                       
                250     LOAD_CONST                      9: '__pyarmor_exit_15893__'
                252     NOP                             
                254     LOAD_CONST                      3: b'<COAddr>\x07\x00\x00\x1a\xdc\x00\x00\x00\x00\x00\x00\x00\x00\x00\x00\x00\x00\x00\x00\x00'
                256     CALL                            1
                264     POP_TOP                         
                266     RERAISE                         0
                268     COPY                            3
                270     POP_EXCEPT                      
                272     RERAISE                         1
                274     PUSH_NULL                       
                276     LOAD_CONST                      9: '__pyarmor_exit_15893__'
                278     LOAD_CONST                      3: b'<COAddr>\x07\x00\x00\x1a\xdc\x00\x00\x00\x00\x00\x00\x00\x00\x00\x00\x00\x00\x00\x00\x00'
                280     BUILD_TUPLE                     1
                282     CALL_FUNCTION_EX                0
                284     POP_TOP                         
                286     RETURN_VALUE                    
            [Exception Table]
                30 to 72 -> 232 [0] 
                72 to 134 -> 208 [1] lasti
                134 to 150 -> 232 [0] 
                172 to 188 -> 232 [0] 
                208 to 218 -> 226 [3] lasti
                218 to 232 -> 232 [0] 
                232 to 236 -> 240 [1] lasti
                236 to 246 -> 246 [0] 
                246 to 268 -> 268 [1] lasti
        [Code]
            File Name: <frozen program.static_classes.memory>
            Object Name: memory_remove_pid
            Qualified Name: memory_remove_pid
            Arg Count: 1
            Pos Only Arg Count: 0
            KW Only Arg Count: 0
            Stack Size: 6
            Flags: 0x20000003 (CO_OPTIMIZED | CO_NEWLOCALS | CO_PYARMOR_OBFUSCATED)
            [Names]
                'open'
                'read'
                'replace'
                'write'
            [Locals+Names]
                'pid'
                '__assert_armored__'
                '_var_var_10'
                '_var_var_3'
            [Constants]
                None
                '__pyarmor_assert_15894__'
                '__pyarmor_enter_15895__'
                b'<COAddr>\x05\x00\x00\x1a4\x01\x00\x00\x00\x00\x00\x00\x00\x00\x00\x00\x00\x00\x00\x00'
                'temp/process.dat'   # b'\x81\xf6\x1d\x1e#\xb5\xae\xc0\x14\xf9\x08\xd3\x7f\xa2\xfc\x84\x1b'
                'r'
                'utf-8'
                'ignore'
                (
                    'encoding'
                    'errors'
                )
                '|'
                ''
                'w'
                '__pyarmor_exit_15896__'
            [Disassembly]
                0       NOP                             
                2       NOP                             
                4       PUSH_NULL                       
                6       LOAD_CONST                      2: '__pyarmor_enter_15895__'
                8       LOAD_CONST                      3: b'<COAddr>\x05\x00\x00\x1a4\x01\x00\x00\x00\x00\x00\x00\x00\x00\x00\x00\x00\x00\x00\x00'
                10      BUILD_TUPLE                     1
                12      CALL_FUNCTION_EX                0
                14      POP_TOP                         
                16      RESUME                          0
                18      NOP                             
                20      NOP                             
                22      NOP                             
                24      NOP                             
                26      NOP                             
                28      NOP                             
                30      LOAD_GLOBAL                     1: NULL + open
                40      PUSH_NULL                       
                42      LOAD_CONST                      1: '__pyarmor_assert_15894__'
                44      LOAD_CONST                      4: 'temp/process.dat'   # b'\x81\xf6\x1d\x1e#\xb5\xae\xc0\x14\xf9\x08\xd3\x7f\xa2\xfc\x84\x1b'
                46      CALL                            1
                54      LOAD_CONST                      5: 'r'
                56      LOAD_CONST                      6: 'utf-8'
                58      LOAD_CONST                      7: 'ignore'
                60      KW_NAMES                        8: ('encoding', 'errors')
                62      CALL                            4
                70      BEFORE_WITH                     
                72      STORE_FAST                      2: _var_var_10
                74      LOAD_FAST                       2: _var_var_10
                76      LOAD_ATTR                       3: read
                96      CALL                            0
                104     STORE_FAST                      3: _var_var_3
                106     LOAD_CONST                      0: None
                108     LOAD_CONST                      0: None
                110     LOAD_CONST                      0: None
                112     CALL                            2
                120     POP_TOP                         
                122     LOAD_FAST_CHECK                 3: _var_var_3
                124     LOAD_ATTR                       5: replace
                144     LOAD_FAST                       0: pid
                146     FORMAT_VALUE                    0 (FVC_NONE)
                148     LOAD_CONST                      9: '|'
                150     BUILD_STRING                    2
                152     LOAD_CONST                      10: ''
                154     CALL                            2
                162     STORE_FAST                      3: _var_var_3
                164     LOAD_GLOBAL                     1: NULL + open
                174     PUSH_NULL                       
                176     LOAD_CONST                      1: '__pyarmor_assert_15894__'
                178     LOAD_CONST                      4: 'temp/process.dat'   # b'\x81\xf6\x1d\x1e#\xb5\xae\xc0\x14\xf9\x08\xd3\x7f\xa2\xfc\x84\x1b'
                180     CALL                            1
                188     LOAD_CONST                      11: 'w'
                190     CALL                            2
                198     BEFORE_WITH                     
                200     STORE_FAST                      2: _var_var_10
                202     LOAD_FAST                       2: _var_var_10
                204     LOAD_ATTR                       7: write
                224     LOAD_FAST                       3: _var_var_3
                226     CALL                            1
                234     POP_TOP                         
                236     LOAD_CONST                      0: None
                238     LOAD_CONST                      0: None
                240     LOAD_CONST                      0: None
                242     CALL                            2
                250     POP_TOP                         
                252     LOAD_CONST                      0: None
                254     NOP                             
                256     NOP                             
                258     NOP                             
                260     JUMP_FORWARD                    50 (to 362)
                268     POP_TOP                         
                270     RETURN_CONST                    0: None
                272     PUSH_EXC_INFO                   
                274     WITH_EXCEPT_START               
                276     POP_JUMP_IF_TRUE                1 (to 280)
                278     RERAISE                         2
                280     POP_TOP                         
                282     POP_EXCEPT                      
                284     POP_TOP                         
                286     POP_TOP                         
                288     JUMP_BACKWARD                   84 (to 122)
                290     COPY                            3
                292     POP_EXCEPT                      
                294     RERAISE                         1
                296     PUSH_EXC_INFO                   
                298     WITH_EXCEPT_START               
                300     POP_JUMP_IF_TRUE                1 (to 304)
                302     RERAISE                         2
                304     POP_TOP                         
                306     POP_EXCEPT                      
                308     POP_TOP                         
                310     POP_TOP                         
                312     JUMP_BACKWARD                   31 (to 252)
                314     COPY                            3
                316     POP_EXCEPT                      
                318     RERAISE                         1
                320     PUSH_EXC_INFO                   
                322     POP_TOP                         
                324     POP_EXCEPT                      
                326     JUMP_BACKWARD                   38 (to 252)
                328     COPY                            3
                330     POP_EXCEPT                      
                332     RERAISE                         1
                334     PUSH_EXC_INFO                   
                336     PUSH_NULL                       
                338     LOAD_CONST                      12: '__pyarmor_exit_15896__'
                340     NOP                             
                342     LOAD_CONST                      3: b'<COAddr>\x05\x00\x00\x1a4\x01\x00\x00\x00\x00\x00\x00\x00\x00\x00\x00\x00\x00\x00\x00'
                344     CALL                            1
                352     POP_TOP                         
                354     RERAISE                         0
                356     COPY                            3
                358     POP_EXCEPT                      
                360     RERAISE                         1
                362     PUSH_NULL                       
                364     LOAD_CONST                      12: '__pyarmor_exit_15896__'
                366     LOAD_CONST                      3: b'<COAddr>\x05\x00\x00\x1a4\x01\x00\x00\x00\x00\x00\x00\x00\x00\x00\x00\x00\x00\x00\x00'
                368     BUILD_TUPLE                     1
                370     CALL_FUNCTION_EX                0
                372     POP_TOP                         
                374     RETURN_VALUE                    
            [Exception Table]
                30 to 72 -> 320 [0] 
                72 to 106 -> 272 [1] lasti
                106 to 200 -> 320 [0] 
                200 to 236 -> 296 [1] lasti
                236 to 252 -> 320 [0] 
                272 to 282 -> 290 [3] lasti
                282 to 296 -> 320 [0] 
                296 to 306 -> 314 [3] lasti
                306 to 320 -> 320 [0] 
                320 to 324 -> 328 [1] lasti
                324 to 334 -> 334 [0] 
                334 to 356 -> 356 [1] lasti
        'ssl'
        [Code]
            File Name: <frozen program.static_classes.memory>
            Object Name: memory_set_ssl
            Qualified Name: memory_set_ssl
            Arg Count: 1
            Pos Only Arg Count: 0
            KW Only Arg Count: 0
            Stack Size: 6
            Flags: 0x20000003 (CO_OPTIMIZED | CO_NEWLOCALS | CO_PYARMOR_OBFUSCATED)
            [Names]
                'open'
                'FileProtector'
                'encrypt'
                'write'
            [Locals+Names]
                'ssl'
                '__assert_armored__'
                '_var_var_8'
                '_var_var_14'
                '_var_var_10'
                '_var_var_15'
            [Constants]
                None
                '__pyarmor_assert_15897__'
                '__pyarmor_enter_15898__'
                b'<COAddr>\x07\x00\x00\x1a\xf6\x00\x00\x00\x00\x00\x00\x00\x00\x00\x00\x00\x00\x00\x00\x00'
                ''
                '|'
                'temp/004.dat'   # b'\x81\xf6\x1d\x1e#\xb5\xee\x82O\xb4\t\xc1x'
                'w'
                'utf-8'
                'ignore'
                (
                    'encoding'
                    'errors'
                )
                '__pyarmor_exit_15899__'
                True
                False
            [Disassembly]
                0       NOP                             
                2       NOP                             
                4       PUSH_NULL                       
                6       LOAD_CONST                      2: '__pyarmor_enter_15898__'
                8       LOAD_CONST                      3: b'<COAddr>\x07\x00\x00\x1a\xf6\x00\x00\x00\x00\x00\x00\x00\x00\x00\x00\x00\x00\x00\x00\x00'
                10      BUILD_TUPLE                     1
                12      CALL_FUNCTION_EX                0
                14      POP_TOP                         
                16      RESUME                          0
                18      NOP                             
                20      NOP                             
                22      NOP                             
                24      NOP                             
                26      NOP                             
                28      LOAD_CONST                      4: ''
                30      STORE_FAST                      2: _var_var_8
                32      LOAD_FAST                       0: ssl
                34      GET_ITER                        
                36      FOR_ITER                        10 (to 58)
                40      STORE_FAST                      3: _var_var_14
                42      LOAD_FAST                       2: _var_var_8
                44      LOAD_FAST                       3: _var_var_14
                46      FORMAT_VALUE                    0 (FVC_NONE)
                48      LOAD_CONST                      5: '|'
                50      BUILD_STRING                    2
                52      BINARY_OP                       13 (+=)
                56      STORE_FAST                      2: _var_var_8
                58      JUMP_BACKWARD                   12 (to 36)
                60      END_FOR                         
                62      LOAD_GLOBAL                     1: NULL + open
                72      PUSH_NULL                       
                74      LOAD_CONST                      1: '__pyarmor_assert_15897__'
                76      LOAD_CONST                      6: 'temp/004.dat'   # b'\x81\xf6\x1d\x1e#\xb5\xee\x82O\xb4\t\xc1x'
                78      CALL                            1
                86      LOAD_CONST                      7: 'w'
                88      LOAD_CONST                      8: 'utf-8'
                90      LOAD_CONST                      9: 'ignore'
                92      KW_NAMES                        10: ('encoding', 'errors')
                94      CALL                            4
                102     BEFORE_WITH                     
                104     STORE_FAST                      4: _var_var_10
                106     LOAD_GLOBAL                     3: NULL + FileProtector
                116     CALL                            0
                124     LOAD_ATTR                       5: encrypt
                144     LOAD_FAST                       2: _var_var_8
                146     CALL                            1
                154     STORE_FAST                      5: _var_var_15
                156     LOAD_FAST                       4: _var_var_10
                158     LOAD_ATTR                       7: write
                178     LOAD_FAST                       5: _var_var_15
                180     CALL                            1
                188     POP_TOP                         
                190     NOP                             
                192     LOAD_CONST                      0: None
                194     LOAD_CONST                      0: None
                196     LOAD_CONST                      0: None
                198     CALL                            2
                206     POP_TOP                         
                208     LOAD_CONST                      12: True
                210     NOP                             
                212     NOP                             
                214     NOP                             
                216     JUMP_FORWARD                    41 (to 300)
                224     POP_TOP                         
                226     RETURN_CONST                    12: True
                228     PUSH_EXC_INFO                   
                230     WITH_EXCEPT_START               
                232     POP_JUMP_IF_TRUE                1 (to 236)
                234     RERAISE                         2
                236     POP_TOP                         
                238     POP_EXCEPT                      
                240     POP_TOP                         
                242     POP_TOP                         
                244     JUMP_FORWARD                    3 (to 252)
                246     COPY                            3
                248     POP_EXCEPT                      
                250     RERAISE                         1
                252     LOAD_CONST                      13: False
                254     NOP                             
                256     NOP                             
                258     NOP                             
                260     JUMP_FORWARD                    19 (to 300)
                268     POP_TOP                         
                270     RETURN_CONST                    13: False
                272     PUSH_EXC_INFO                   
                274     PUSH_NULL                       
                276     LOAD_CONST                      11: '__pyarmor_exit_15899__'
                278     NOP                             
                280     LOAD_CONST                      3: b'<COAddr>\x07\x00\x00\x1a\xf6\x00\x00\x00\x00\x00\x00\x00\x00\x00\x00\x00\x00\x00\x00\x00'
                282     CALL                            1
                290     POP_TOP                         
                292     RERAISE                         0
                294     COPY                            3
                296     POP_EXCEPT                      
                298     RERAISE                         1
                300     PUSH_NULL                       
                302     LOAD_CONST                      11: '__pyarmor_exit_15899__'
                304     LOAD_CONST                      3: b'<COAddr>\x07\x00\x00\x1a\xf6\x00\x00\x00\x00\x00\x00\x00\x00\x00\x00\x00\x00\x00\x00\x00'
                306     BUILD_TUPLE                     1
                308     CALL_FUNCTION_EX                0
                310     POP_TOP                         
                312     RETURN_VALUE                    
            [Exception Table]
                28 to 104 -> 272 [0] 
                104 to 192 -> 228 [1] lasti
                192 to 208 -> 272 [0] 
                228 to 238 -> 246 [3] lasti
                238 to 252 -> 272 [0] 
                272 to 294 -> 294 [1] lasti
        [Code]
            File Name: <frozen program.static_classes.memory>
            Object Name: memory_get_ssl
            Qualified Name: memory_get_ssl
            Arg Count: 0
            Pos Only Arg Count: 0
            KW Only Arg Count: 0
            Stack Size: 6
            Flags: 0x20000003 (CO_OPTIMIZED | CO_NEWLOCALS | CO_PYARMOR_OBFUSCATED)
            [Names]
                'open'
                'FileProtector'
                'decrypt'
                'read'
                'split'
                'strip'
            [Locals+Names]
                '__assert_armored__'
                '_var_var_10'
                '_var_var_15'
                '_var_var_16'
                '_var_var_17'
            [Constants]
                None
                '__pyarmor_assert_15900__'
                '__pyarmor_enter_15901__'
                b'<COAddr>\x05\x00\x00\x1af\x01\x00\x00\x00\x00\x00\x00\x00\x00\x00\x00\x00\x00\x00\x00'
                'temp/004.dat'   # b'\x81\xf6\x1d\x1e#\xb5\xee\x82O\xb4\t\xc1x'
                'r'
                'utf-8'
                'ignore'
                (
                    'encoding'
                    'errors'
                )
                '|'
                '__pyarmor_exit_15902__'
                False
            [Disassembly]
                0       NOP                             
                2       NOP                             
                4       PUSH_NULL                       
                6       LOAD_CONST                      2: '__pyarmor_enter_15901__'
                8       LOAD_CONST                      3: b'<COAddr>\x05\x00\x00\x1af\x01\x00\x00\x00\x00\x00\x00\x00\x00\x00\x00\x00\x00\x00\x00'
                10      BUILD_TUPLE                     1
                12      CALL_FUNCTION_EX                0
                14      POP_TOP                         
                16      RESUME                          0
                18      NOP                             
                20      NOP                             
                22      NOP                             
                24      NOP                             
                26      NOP                             
                28      NOP                             
                30      LOAD_GLOBAL                     1: NULL + open
                40      PUSH_NULL                       
                42      LOAD_CONST                      1: '__pyarmor_assert_15900__'
                44      LOAD_CONST                      4: 'temp/004.dat'   # b'\x81\xf6\x1d\x1e#\xb5\xee\x82O\xb4\t\xc1x'
                46      CALL                            1
                54      LOAD_CONST                      5: 'r'
                56      LOAD_CONST                      6: 'utf-8'
                58      LOAD_CONST                      7: 'ignore'
                60      KW_NAMES                        8: ('encoding', 'errors')
                62      CALL                            4
                70      BEFORE_WITH                     
                72      STORE_FAST                      1: _var_var_10
                74      LOAD_GLOBAL                     3: NULL + FileProtector
                84      CALL                            0
                92      LOAD_ATTR                       5: decrypt
                112     LOAD_FAST                       1: _var_var_10
                114     LOAD_ATTR                       7: read
                134     CALL                            0
                142     CALL                            1
                150     STORE_FAST                      2: _var_var_15
                152     LOAD_FAST                       2: _var_var_15
                154     LOAD_ATTR                       9: split
                174     LOAD_CONST                      9: '|'
                176     CALL                            1
                184     GET_ITER                        
                186     LOAD_FAST_AND_CLEAR             3: _var_var_16
                188     SWAP                            2
                190     BUILD_LIST                      0
                192     SWAP                            2
                194     FOR_ITER                        35 (to 266)
                198     STORE_FAST                      3: _var_var_16
                200     LOAD_FAST                       3: _var_var_16
                202     LOAD_ATTR                       11: strip
                222     CALL                            0
                230     POP_JUMP_IF_TRUE                1 (to 234)
                232     JUMP_BACKWARD                   20 (to 194)
                234     LOAD_FAST                       3: _var_var_16
                236     LOAD_ATTR                       11: strip
                256     CALL                            0
                264     LIST_APPEND                     2
                266     JUMP_BACKWARD                   37 (to 194)
                268     END_FOR                         
                270     STORE_FAST                      4: _var_var_17
                272     STORE_FAST                      3: _var_var_16
                274     LOAD_FAST                       4: _var_var_17
                276     SWAP                            2
                278     LOAD_CONST                      0: None
                280     LOAD_CONST                      0: None
                282     LOAD_CONST                      0: None
                284     CALL                            2
                292     POP_TOP                         
                294     NOP                             
                296     NOP                             
                298     NOP                             
                300     JUMP_FORWARD                    55 (to 412)
                302     CALL                            1
                310     POP_TOP                         
                312     RETURN_VALUE                    
                314     SWAP                            2
                316     POP_TOP                         
                318     SWAP                            2
                320     STORE_FAST                      3: _var_var_16
                322     RERAISE                         0
                324     PUSH_EXC_INFO                   
                326     WITH_EXCEPT_START               
                328     POP_JUMP_IF_TRUE                1 (to 332)
                330     RERAISE                         2
                332     POP_TOP                         
                334     POP_EXCEPT                      
                336     POP_TOP                         
                338     POP_TOP                         
                340     JUMP_FORWARD                    3 (to 348)
                342     COPY                            3
                344     POP_EXCEPT                      
                346     RERAISE                         1
                348     JUMP_FORWARD                    7 (to 364)
                350     PUSH_EXC_INFO                   
                352     POP_TOP                         
                354     POP_EXCEPT                      
                356     JUMP_FORWARD                    3 (to 364)
                358     COPY                            3
                360     POP_EXCEPT                      
                362     RERAISE                         1
                364     LOAD_CONST                      11: False
                366     NOP                             
                368     NOP                             
                370     NOP                             
                372     JUMP_FORWARD                    19 (to 412)
                380     POP_TOP                         
                382     RETURN_CONST                    11: False
                384     PUSH_EXC_INFO                   
                386     PUSH_NULL                       
                388     LOAD_CONST                      10: '__pyarmor_exit_15902__'
                390     NOP                             
                392     LOAD_CONST                      3: b'<COAddr>\x05\x00\x00\x1af\x01\x00\x00\x00\x00\x00\x00\x00\x00\x00\x00\x00\x00\x00\x00'
                394     CALL                            1
                402     POP_TOP                         
                404     RERAISE                         0
                406     COPY                            3
                408     POP_EXCEPT                      
                410     RERAISE                         1
                412     PUSH_NULL                       
                414     LOAD_CONST                      10: '__pyarmor_exit_15902__'
                416     LOAD_CONST                      3: b'<COAddr>\x05\x00\x00\x1af\x01\x00\x00\x00\x00\x00\x00\x00\x00\x00\x00\x00\x00\x00\x00'
                418     BUILD_TUPLE                     1
                420     CALL_FUNCTION_EX                0
                422     POP_TOP                         
                424     RETURN_VALUE                    
            [Exception Table]
                30 to 72 -> 350 [0] 
                72 to 190 -> 324 [1] lasti
                190 to 232 -> 314 [3] 
                234 to 270 -> 314 [3] 
                270 to 276 -> 324 [1] lasti
                276 to 294 -> 350 [0] 
                314 to 324 -> 324 [1] lasti
                324 to 334 -> 342 [3] lasti
                334 to 348 -> 350 [0] 
                348 to 350 -> 384 [0] 
                350 to 354 -> 358 [1] lasti
                354 to 364 -> 384 [0] 
                384 to 406 -> 406 [1] lasti
        '__pyarmor_exit_15851__'
        (
            0
        )
    [Disassembly]
        0       NOP                             
        2       NOP                             
        4       PUSH_NULL                       
        6       LOAD_CONST                      1: '__pyarmor_enter_15850__'
        8       LOAD_CONST                      2: b'<COAddr>\x05\x00\x00\x1a\xe6\x00\x00\x00\x00\x00\x00\x00\x00\x00\x00\x00\x00\x00\x00\x00'
        10      BUILD_TUPLE                     1
        12      CALL_FUNCTION_EX                0
        14      POP_TOP                         
        16      RESUME                          0
        18      NOP                             
        20      NOP                             
        22      NOP                             
        24      NOP                             
        26      LOAD_CONST                      3: 0
        28      LOAD_CONST                      4: None
        30      IMPORT_NAME                     1: time
        32      STORE_NAME                      1: time
        34      LOAD_CONST                      3: 0
        36      LOAD_CONST                      4: None
        38      IMPORT_NAME                     2: base64
        40      STORE_NAME                      2: base64
        42      LOAD_CONST                      3: 0
        44      LOAD_CONST                      4: None
        46      IMPORT_NAME                     3: datetime
        48      STORE_NAME                      3: datetime
        50      LOAD_CONST                      3: 0
        52      LOAD_CONST                      5: ('AES',)
        54      IMPORT_NAME                     4: Crypto.Cipher
        56      IMPORT_FROM                     5: AES
        58      STORE_NAME                      5: AES
        60      POP_TOP                         
        62      LOAD_CONST                      3: 0
        64      LOAD_CONST                      6: ('SHA256',)
        66      IMPORT_NAME                     6: Crypto.Hash
        68      IMPORT_FROM                     7: SHA256
        70      STORE_NAME                      7: SHA256
        72      POP_TOP                         
        74      LOAD_CONST                      3: 0
        76      LOAD_CONST                      7: ('pad', 'unpad')
        78      IMPORT_NAME                     8: Crypto.Util.Padding
        80      IMPORT_FROM                     9: pad
        82      STORE_NAME                      9: pad
        84      IMPORT_FROM                     10: unpad
        86      STORE_NAME                      10: unpad
        88      POP_TOP                         
        90      LOAD_CONST                      8: 1
        92      LOAD_CONST                      9: ('get_fingerprint', 'get_lic_key')
        94      IMPORT_NAME                     11: fingerprint
        96      IMPORT_FROM                     12: get_fingerprint
        98      STORE_NAME                      12: get_fingerprint
        100     IMPORT_FROM                     13: get_lic_key
        102     STORE_NAME                      13: get_lic_key
        104     POP_TOP                         
        106     PUSH_NULL                       
        108     LOAD_BUILD_CLASS                
        110     LOAD_CONST                      10: <CODE> FileProtector
        112     MAKE_FUNCTION                   0
        114     LOAD_CONST                      11: 'FileProtector'
        116     CALL                            2
        124     STORE_NAME                      14: FileProtector
        126     LOAD_CONST                      12: <CODE> memory_set_module
        128     MAKE_FUNCTION                   0
        130     STORE_NAME                      15: memory_set_module
        132     LOAD_CONST                      13: 'ids'
        134     LOAD_NAME                       16: int
        136     LOAD_CONST                      14: 'return'
        138     LOAD_NAME                       17: bool
        140     BUILD_TUPLE                     4
        142     LOAD_CONST                      15: <CODE> check_module
        144     MAKE_FUNCTION                   4
        146     STORE_NAME                      18: check_module
        148     LOAD_CONST                      16: <CODE> memory_set_lang
        150     MAKE_FUNCTION                   0
        152     STORE_NAME                      19: memory_set_lang
        154     LOAD_CONST                      17: <CODE> memory_get_lang
        156     MAKE_FUNCTION                   0
        158     STORE_NAME                      20: memory_get_lang
        160     LOAD_CONST                      14: 'return'
        162     LOAD_NAME                       17: bool
        164     BUILD_TUPLE                     2
        166     LOAD_CONST                      18: <CODE> memory_set_switcher
        168     MAKE_FUNCTION                   4
        170     STORE_NAME                      21: memory_set_switcher
        172     LOAD_CONST                      27: (0,)
        174     LOAD_CONST                      13: 'ids'
        176     LOAD_NAME                       16: int
        178     LOAD_CONST                      14: 'return'
        180     LOAD_NAME                       17: bool
        182     BUILD_TUPLE                     4
        184     LOAD_CONST                      19: <CODE> memory_check_switcher
        186     MAKE_FUNCTION                   5
        188     STORE_NAME                      22: memory_check_switcher
        190     LOAD_CONST                      20: <CODE> memory_set_pid
        192     MAKE_FUNCTION                   0
        194     STORE_NAME                      23: memory_set_pid
        196     LOAD_CONST                      14: 'return'
        198     LOAD_NAME                       17: bool
        200     BUILD_TUPLE                     2
        202     LOAD_CONST                      21: <CODE> memory_check_pid
        204     MAKE_FUNCTION                   4
        206     STORE_NAME                      24: memory_check_pid
        208     LOAD_CONST                      22: <CODE> memory_remove_pid
        210     MAKE_FUNCTION                   0
        212     STORE_NAME                      25: memory_remove_pid
        214     LOAD_CONST                      23: 'ssl'
        216     LOAD_NAME                       26: list
        218     LOAD_CONST                      14: 'return'
        220     LOAD_NAME                       17: bool
        222     BUILD_TUPLE                     4
        224     LOAD_CONST                      24: <CODE> memory_set_ssl
        226     MAKE_FUNCTION                   4
        228     STORE_NAME                      27: memory_set_ssl
        230     LOAD_CONST                      25: <CODE> memory_get_ssl
        232     MAKE_FUNCTION                   0
        234     STORE_NAME                      28: memory_get_ssl
        236     LOAD_CONST                      4: None
        238     NOP                             
        240     NOP                             
        242     NOP                             
        244     JUMP_FORWARD                    19 (to 284)
        252     POP_TOP                         
        254     RETURN_CONST                    4: None
        256     PUSH_EXC_INFO                   
        258     PUSH_NULL                       
        260     LOAD_CONST                      26: '__pyarmor_exit_15851__'
        262     NOP                             
        264     LOAD_CONST                      2: b'<COAddr>\x05\x00\x00\x1a\xe6\x00\x00\x00\x00\x00\x00\x00\x00\x00\x00\x00\x00\x00\x00\x00'
        266     CALL                            1
        274     POP_TOP                         
        276     RERAISE                         0
        278     COPY                            3
        280     POP_EXCEPT                      
        282     RERAISE                         1
        284     PUSH_NULL                       
        286     LOAD_CONST                      26: '__pyarmor_exit_15851__'
        288     LOAD_CONST                      2: b'<COAddr>\x05\x00\x00\x1a\xe6\x00\x00\x00\x00\x00\x00\x00\x00\x00\x00\x00\x00\x00\x00\x00'
        290     BUILD_TUPLE                     1
        292     CALL_FUNCTION_EX                0
        294     POP_TOP                         
        296     RETURN_VALUE                    
    [Exception Table]
        26 to 236 -> 256 [0] 
        256 to 278 -> 278 [1] lasti
