#decoded by lolz.live/mrpenny / t.me/zeus_jackpot
# ================================
# Примечания по Pyarmor:
# - Байт-код и объекты кода Pyarmor соответствуют стандартному Python, но присутствуют специальные вызовы функций среды выполнения (runtime) Pyarmor.
# - Вызовы строк — это не ошибки, а маркеры, которые обрабатываются Pyarmor во время выполнения.
#
# Руководство по декомпиляции (без среды выполнения):
# 1. Игнорируйте зашифрованные байты после `#`; используйте только строку до `#`.
# 2. Удалите "__pyarmor_enter_xxx__"(b"<COAddr>...") и "__pyarmor_leave_xxx__"(b"<COAddr>...") (пролог/эпилог).
# 3. "__pyarmor_assert_xxx__"(A) не является настоящим оператором assert.
#    - Если A — это имя или читаемая строка: замените на A.
#    - Если A — это (X, "Y"): замените на X.Y.
#    - Если A — это (X, "Y", Z): замените на X.Y = Z.
#    - В противном случае: выберите наиболее подходящую/логичную замену.
# 4. "__pyarmor_bcc_xxx__"(...) указывает на машинный (нативный) код; тело функции недоступно. Добавьте комментарий.
# ================================

[Code]
    File Name: <frozen program.static_classes.stop>
    Object Name: <module>
    Qualified Name: <module>
    Arg Count: 0
    Pos Only Arg Count: 0
    KW Only Arg Count: 0
    Stack Size: 5
    Flags: 0x20000000 (CO_PYARMOR_OBFUSCATED)
    [Names]
        '__assert_armored__'
        'multithon.errors'
        'StopProgram'
        'Exception'
        'PeerFlood'
        'MaxFlood'
        'BanAccount'
        'StopAccount'
        'AutoStopCheck'
        'AutoStop'
    [Locals+Names]
    [Constants]
        '__pyarmor_assert_15978__'
        '__pyarmor_enter_15979__'
        b'<COAddr>\x07\x00\x00\x1a\xa2\x00\x00\x00\x00\x00\x00\x00\x00\x00\x00\x00\x00\x00\x00\x00'
        0
        (
            'StopProgram'
        )
        [Code]
            File Name: <frozen program.static_classes.stop>
            Object Name: PeerFlood
            Qualified Name: PeerFlood
            Arg Count: 0
            Pos Only Arg Count: 0
            KW Only Arg Count: 0
            Stack Size: 5
            Flags: 0x20000000 (CO_PYARMOR_OBFUSCATED)
            [Names]
                '__name__'
                '__module__'
                '__qualname__'
                '__assert_armored__'
                'str'
                '__init__'
            [Locals+Names]
            [Constants]
                'PeerFlood'
                '__pyarmor_assert_15981__'
                '__pyarmor_enter_15982__'
                b'<COAddr>\x05\x00\x00"8\x00\x00\x00\x00\x00\x00\x00\x00\x00\x00\x00\x00\x00\x00\x00'
                ''
                'Account is limited'   # b'\x81\xc3\x1b\x10<\xef\xb0\xc6[\xf3\x1e\x80`\xe5\xf5\x8c\x1bX\xbf'
                'account'
                'status'
                [Code]
                    File Name: <frozen program.static_classes.stop>
                    Object Name: __init__
                    Qualified Name: PeerFlood.__init__
                    Arg Count: 3
                    Pos Only Arg Count: 0
                    KW Only Arg Count: 0
                    Stack Size: 5
                    Flags: 0x20000003 (CO_OPTIMIZED | CO_NEWLOCALS | CO_PYARMOR_OBFUSCATED)
                    [Names]
                        'account'
                        'status'
                        'result'
                    [Locals+Names]
                        'self'
                        'account'
                        'status'
                        '__assert_armored__'
                    [Constants]
                        None
                        '__pyarmor_assert_15984__'
                        '__pyarmor_enter_15985__'
                        b'<COAddr>\x07\x00\x00\x1aF\x00\x00\x00\x00\x00\x00\x00\x00\x00\x00\x00\x00\x00\x00\x00'
                        (
                            'account'
                            'status'
                        )
                        '__pyarmor_exit_15986__'
                    [Disassembly]
                        0       NOP                             
                        2       NOP                             
                        4       PUSH_NULL                       
                        6       LOAD_CONST                      2: '__pyarmor_enter_15985__'
                        8       LOAD_CONST                      3: b'<COAddr>\x07\x00\x00\x1aF\x00\x00\x00\x00\x00\x00\x00\x00\x00\x00\x00\x00\x00\x00\x00'
                        10      BUILD_TUPLE                     1
                        12      CALL_FUNCTION_EX                0
                        14      POP_TOP                         
                        16      RESUME                          0
                        18      NOP                             
                        20      NOP                             
                        22      NOP                             
                        24      NOP                             
                        26      NOP                             
                        28      LOAD_FAST                       1: account
                        30      LOAD_FAST                       0: self
                        32      STORE_ATTR                      0: account
                        42      LOAD_FAST                       2: status
                        44      LOAD_FAST                       0: self
                        46      STORE_ATTR                      1: status
                        56      LOAD_FAST                       1: account
                        58      LOAD_FAST                       2: status
                        60      LOAD_CONST                      4: ('account', 'status')
                        62      BUILD_CONST_KEY_MAP             2
                        64      LOAD_FAST                       0: self
                        66      STORE_ATTR                      2: result
                        76      LOAD_CONST                      0: None
                        78      NOP                             
                        80      NOP                             
                        82      NOP                             
                        84      JUMP_FORWARD                    19 (to 124)
                        92      POP_TOP                         
                        94      RETURN_CONST                    0: None
                        96      PUSH_EXC_INFO                   
                        98      PUSH_NULL                       
                        100     LOAD_CONST                      5: '__pyarmor_exit_15986__'
                        102     NOP                             
                        104     LOAD_CONST                      3: b'<COAddr>\x07\x00\x00\x1aF\x00\x00\x00\x00\x00\x00\x00\x00\x00\x00\x00\x00\x00\x00\x00'
                        106     CALL                            1
                        114     POP_TOP                         
                        116     RERAISE                         0
                        118     COPY                            3
                        120     POP_EXCEPT                      
                        122     RERAISE                         1
                        124     PUSH_NULL                       
                        126     LOAD_CONST                      5: '__pyarmor_exit_15986__'
                        128     LOAD_CONST                      3: b'<COAddr>\x07\x00\x00\x1aF\x00\x00\x00\x00\x00\x00\x00\x00\x00\x00\x00\x00\x00\x00\x00'
                        130     BUILD_TUPLE                     1
                        132     CALL_FUNCTION_EX                0
                        134     POP_TOP                         
                        136     RETURN_VALUE                    
                    [Exception Table]
                        28 to 76 -> 96 [0] 
                        96 to 118 -> 118 [1] lasti
                '__pyarmor_exit_15983__'
                None
            [Disassembly]
                0       NOP                             
                2       LOAD_NAME                       0: __name__
                4       STORE_NAME                      1: __module__
                6       LOAD_CONST                      0: 'PeerFlood'
                8       STORE_NAME                      2: __qualname__
                10      NOP                             
                12      PUSH_NULL                       
                14      LOAD_CONST                      2: '__pyarmor_enter_15982__'
                16      LOAD_CONST                      3: b'<COAddr>\x05\x00\x00"8\x00\x00\x00\x00\x00\x00\x00\x00\x00\x00\x00\x00\x00\x00\x00'
                18      BUILD_TUPLE                     1
                20      CALL_FUNCTION_EX                0
                22      POP_TOP                         
                24      RESUME                          0
                26      NOP                             
                28      NOP                             
                30      NOP                             
                32      NOP                             
                34      NOP                             
                36      LOAD_CONST                      4: ''
                38      PUSH_NULL                       
                40      LOAD_CONST                      1: '__pyarmor_assert_15981__'
                42      LOAD_CONST                      5: 'Account is limited'   # b'\x81\xc3\x1b\x10<\xef\xb0\xc6[\xf3\x1e\x80`\xe5\xf5\x8c\x1bX\xbf'
                44      CALL                            1
                52      BUILD_TUPLE                     2
                54      LOAD_CONST                      6: 'account'
                56      LOAD_NAME                       4: str
                58      LOAD_CONST                      7: 'status'
                60      LOAD_NAME                       4: str
                62      BUILD_TUPLE                     4
                64      LOAD_CONST                      8: <CODE> __init__
                66      MAKE_FUNCTION                   5
                68      STORE_NAME                      5: __init__
                70      LOAD_CONST                      10: None
                72      NOP                             
                74      NOP                             
                76      NOP                             
                78      JUMP_FORWARD                    19 (to 118)
                86      POP_TOP                         
                88      RETURN_CONST                    10: None
                90      PUSH_EXC_INFO                   
                92      PUSH_NULL                       
                94      LOAD_CONST                      9: '__pyarmor_exit_15983__'
                96      NOP                             
                98      LOAD_CONST                      3: b'<COAddr>\x05\x00\x00"8\x00\x00\x00\x00\x00\x00\x00\x00\x00\x00\x00\x00\x00\x00\x00'
                100     CALL                            1
                108     POP_TOP                         
                110     RERAISE                         0
                112     COPY                            3
                114     POP_EXCEPT                      
                116     RERAISE                         1
                118     PUSH_NULL                       
                120     LOAD_CONST                      9: '__pyarmor_exit_15983__'
                122     LOAD_CONST                      3: b'<COAddr>\x05\x00\x00"8\x00\x00\x00\x00\x00\x00\x00\x00\x00\x00\x00\x00\x00\x00\x00'
                124     BUILD_TUPLE                     1
                126     CALL_FUNCTION_EX                0
                128     POP_TOP                         
                130     RETURN_VALUE                    
            [Exception Table]
                36 to 70 -> 90 [0] 
                90 to 112 -> 112 [1] lasti
        'PeerFlood'
        [Code]
            File Name: <frozen program.static_classes.stop>
            Object Name: MaxFlood
            Qualified Name: MaxFlood
            Arg Count: 0
            Pos Only Arg Count: 0
            KW Only Arg Count: 0
            Stack Size: 5
            Flags: 0x20000000 (CO_PYARMOR_OBFUSCATED)
            [Names]
                '__name__'
                '__module__'
                '__qualname__'
                '__assert_armored__'
                'str'
                '__init__'
            [Locals+Names]
            [Constants]
                'MaxFlood'
                '__pyarmor_assert_15987__'
                '__pyarmor_enter_15988__'
                b'<COAddr>\x05\x00\x00"8\x00\x00\x00\x00\x00\x00\x00\x00\x00\x00\x00\x00\x00\x00\x00'
                ''
                'Max flood wait'   # b'\x81\xcf\x19\x0bs\xfc\xb2\xdd\x14\xfeM\xd7m\xe5\xec'
                'account'
                'status'
                [Code]
                    File Name: <frozen program.static_classes.stop>
                    Object Name: __init__
                    Qualified Name: MaxFlood.__init__
                    Arg Count: 3
                    Pos Only Arg Count: 0
                    KW Only Arg Count: 0
                    Stack Size: 5
                    Flags: 0x20000003 (CO_OPTIMIZED | CO_NEWLOCALS | CO_PYARMOR_OBFUSCATED)
                    [Names]
                        'account'
                        'status'
                        'result'
                    [Locals+Names]
                        'self'
                        'account'
                        'status'
                        '__assert_armored__'
                    [Constants]
                        None
                        '__pyarmor_assert_15990__'
                        '__pyarmor_enter_15991__'
                        b'<COAddr>\x05\x00\x00\x1aF\x00\x00\x00\x00\x00\x00\x00\x00\x00\x00\x00\x00\x00\x00\x00'
                        (
                            'account'
                            'status'
                        )
                        '__pyarmor_exit_15992__'
                    [Disassembly]
                        0       NOP                             
                        2       NOP                             
                        4       PUSH_NULL                       
                        6       LOAD_CONST                      2: '__pyarmor_enter_15991__'
                        8       LOAD_CONST                      3: b'<COAddr>\x05\x00\x00\x1aF\x00\x00\x00\x00\x00\x00\x00\x00\x00\x00\x00\x00\x00\x00\x00'
                        10      BUILD_TUPLE                     1
                        12      CALL_FUNCTION_EX                0
                        14      POP_TOP                         
                        16      RESUME                          0
                        18      NOP                             
                        20      NOP                             
                        22      NOP                             
                        24      NOP                             
                        26      NOP                             
                        28      LOAD_FAST                       1: account
                        30      LOAD_FAST                       0: self
                        32      STORE_ATTR                      0: account
                        42      LOAD_FAST                       2: status
                        44      LOAD_FAST                       0: self
                        46      STORE_ATTR                      1: status
                        56      LOAD_FAST                       1: account
                        58      LOAD_FAST                       2: status
                        60      LOAD_CONST                      4: ('account', 'status')
                        62      BUILD_CONST_KEY_MAP             2
                        64      LOAD_FAST                       0: self
                        66      STORE_ATTR                      2: result
                        76      LOAD_CONST                      0: None
                        78      NOP                             
                        80      NOP                             
                        82      NOP                             
                        84      JUMP_FORWARD                    19 (to 124)
                        92      POP_TOP                         
                        94      RETURN_CONST                    0: None
                        96      PUSH_EXC_INFO                   
                        98      PUSH_NULL                       
                        100     LOAD_CONST                      5: '__pyarmor_exit_15992__'
                        102     NOP                             
                        104     LOAD_CONST                      3: b'<COAddr>\x05\x00\x00\x1aF\x00\x00\x00\x00\x00\x00\x00\x00\x00\x00\x00\x00\x00\x00\x00'
                        106     CALL                            1
                        114     POP_TOP                         
                        116     RERAISE                         0
                        118     COPY                            3
                        120     POP_EXCEPT                      
                        122     RERAISE                         1
                        124     PUSH_NULL                       
                        126     LOAD_CONST                      5: '__pyarmor_exit_15992__'
                        128     LOAD_CONST                      3: b'<COAddr>\x05\x00\x00\x1aF\x00\x00\x00\x00\x00\x00\x00\x00\x00\x00\x00\x00\x00\x00\x00'
                        130     BUILD_TUPLE                     1
                        132     CALL_FUNCTION_EX                0
                        134     POP_TOP                         
                        136     RETURN_VALUE                    
                    [Exception Table]
                        28 to 76 -> 96 [0] 
                        96 to 118 -> 118 [1] lasti
                '__pyarmor_exit_15989__'
                None
            [Disassembly]
                0       NOP                             
                2       LOAD_NAME                       0: __name__
                4       STORE_NAME                      1: __module__
                6       LOAD_CONST                      0: 'MaxFlood'
                8       STORE_NAME                      2: __qualname__
                10      NOP                             
                12      PUSH_NULL                       
                14      LOAD_CONST                      2: '__pyarmor_enter_15988__'
                16      LOAD_CONST                      3: b'<COAddr>\x05\x00\x00"8\x00\x00\x00\x00\x00\x00\x00\x00\x00\x00\x00\x00\x00\x00\x00'
                18      BUILD_TUPLE                     1
                20      CALL_FUNCTION_EX                0
                22      POP_TOP                         
                24      RESUME                          0
                26      NOP                             
                28      NOP                             
                30      NOP                             
                32      NOP                             
                34      NOP                             
                36      LOAD_CONST                      4: ''
                38      PUSH_NULL                       
                40      LOAD_CONST                      1: '__pyarmor_assert_15987__'
                42      LOAD_CONST                      5: 'Max flood wait'   # b'\x81\xcf\x19\x0bs\xfc\xb2\xdd\x14\xfeM\xd7m\xe5\xec'
                44      CALL                            1
                52      BUILD_TUPLE                     2
                54      LOAD_CONST                      6: 'account'
                56      LOAD_NAME                       4: str
                58      LOAD_CONST                      7: 'status'
                60      LOAD_NAME                       4: str
                62      BUILD_TUPLE                     4
                64      LOAD_CONST                      8: <CODE> __init__
                66      MAKE_FUNCTION                   5
                68      STORE_NAME                      5: __init__
                70      LOAD_CONST                      10: None
                72      NOP                             
                74      NOP                             
                76      NOP                             
                78      JUMP_FORWARD                    19 (to 118)
                86      POP_TOP                         
                88      RETURN_CONST                    10: None
                90      PUSH_EXC_INFO                   
                92      PUSH_NULL                       
                94      LOAD_CONST                      9: '__pyarmor_exit_15989__'
                96      NOP                             
                98      LOAD_CONST                      3: b'<COAddr>\x05\x00\x00"8\x00\x00\x00\x00\x00\x00\x00\x00\x00\x00\x00\x00\x00\x00\x00'
                100     CALL                            1
                108     POP_TOP                         
                110     RERAISE                         0
                112     COPY                            3
                114     POP_EXCEPT                      
                116     RERAISE                         1
                118     PUSH_NULL                       
                120     LOAD_CONST                      9: '__pyarmor_exit_15989__'
                122     LOAD_CONST                      3: b'<COAddr>\x05\x00\x00"8\x00\x00\x00\x00\x00\x00\x00\x00\x00\x00\x00\x00\x00\x00\x00'
                124     BUILD_TUPLE                     1
                126     CALL_FUNCTION_EX                0
                128     POP_TOP                         
                130     RETURN_VALUE                    
            [Exception Table]
                36 to 70 -> 90 [0] 
                90 to 112 -> 112 [1] lasti
        'MaxFlood'
        [Code]
            File Name: <frozen program.static_classes.stop>
            Object Name: BanAccount
            Qualified Name: BanAccount
            Arg Count: 0
            Pos Only Arg Count: 0
            KW Only Arg Count: 0
            Stack Size: 5
            Flags: 0x20000000 (CO_PYARMOR_OBFUSCATED)
            [Names]
                '__name__'
                '__module__'
                '__qualname__'
                '__assert_armored__'
                'str'
                '__init__'
            [Locals+Names]
            [Constants]
                'BanAccount'
                '__pyarmor_assert_15993__'
                '__pyarmor_enter_15994__'
                b'<COAddr>\x07\x00\x00"8\x00\x00\x00\x00\x00\x00\x00\x00\x00\x00\x00\x00\x00\x00\x00'
                ''
                'Account is banned'   # b'\x81\xc3\x1b\x10<\xef\xb0\xc6[\xf3\x1e\x80n\xed\xf6\x8b\nY'
                'account'
                'status'
                [Code]
                    File Name: <frozen program.static_classes.stop>
                    Object Name: __init__
                    Qualified Name: BanAccount.__init__
                    Arg Count: 3
                    Pos Only Arg Count: 0
                    KW Only Arg Count: 0
                    Stack Size: 5
                    Flags: 0x20000003 (CO_OPTIMIZED | CO_NEWLOCALS | CO_PYARMOR_OBFUSCATED)
                    [Names]
                        'account'
                        'status'
                        'result'
                    [Locals+Names]
                        'self'
                        'account'
                        'status'
                        '__assert_armored__'
                    [Constants]
                        None
                        '__pyarmor_assert_15996__'
                        '__pyarmor_enter_15997__'
                        b'<COAddr>\x07\x00\x00\x1aF\x00\x00\x00\x00\x00\x00\x00\x00\x00\x00\x00\x00\x00\x00\x00'
                        (
                            'account'
                            'status'
                        )
                        '__pyarmor_exit_15998__'
                    [Disassembly]
                        0       NOP                             
                        2       NOP                             
                        4       PUSH_NULL                       
                        6       LOAD_CONST                      2: '__pyarmor_enter_15997__'
                        8       LOAD_CONST                      3: b'<COAddr>\x07\x00\x00\x1aF\x00\x00\x00\x00\x00\x00\x00\x00\x00\x00\x00\x00\x00\x00\x00'
                        10      BUILD_TUPLE                     1
                        12      CALL_FUNCTION_EX                0
                        14      POP_TOP                         
                        16      RESUME                          0
                        18      NOP                             
                        20      NOP                             
                        22      NOP                             
                        24      NOP                             
                        26      NOP                             
                        28      LOAD_FAST                       1: account
                        30      LOAD_FAST                       0: self
                        32      STORE_ATTR                      0: account
                        42      LOAD_FAST                       2: status
                        44      LOAD_FAST                       0: self
                        46      STORE_ATTR                      1: status
                        56      LOAD_FAST                       1: account
                        58      LOAD_FAST                       2: status
                        60      LOAD_CONST                      4: ('account', 'status')
                        62      BUILD_CONST_KEY_MAP             2
                        64      LOAD_FAST                       0: self
                        66      STORE_ATTR                      2: result
                        76      LOAD_CONST                      0: None
                        78      NOP                             
                        80      NOP                             
                        82      NOP                             
                        84      JUMP_FORWARD                    19 (to 124)
                        92      POP_TOP                         
                        94      RETURN_CONST                    0: None
                        96      PUSH_EXC_INFO                   
                        98      PUSH_NULL                       
                        100     LOAD_CONST                      5: '__pyarmor_exit_15998__'
                        102     NOP                             
                        104     LOAD_CONST                      3: b'<COAddr>\x07\x00\x00\x1aF\x00\x00\x00\x00\x00\x00\x00\x00\x00\x00\x00\x00\x00\x00\x00'
                        106     CALL                            1
                        114     POP_TOP                         
                        116     RERAISE                         0
                        118     COPY                            3
                        120     POP_EXCEPT                      
                        122     RERAISE                         1
                        124     PUSH_NULL                       
                        126     LOAD_CONST                      5: '__pyarmor_exit_15998__'
                        128     LOAD_CONST                      3: b'<COAddr>\x07\x00\x00\x1aF\x00\x00\x00\x00\x00\x00\x00\x00\x00\x00\x00\x00\x00\x00\x00'
                        130     BUILD_TUPLE                     1
                        132     CALL_FUNCTION_EX                0
                        134     POP_TOP                         
                        136     RETURN_VALUE                    
                    [Exception Table]
                        28 to 76 -> 96 [0] 
                        96 to 118 -> 118 [1] lasti
                '__pyarmor_exit_15995__'
                None
            [Disassembly]
                0       NOP                             
                2       LOAD_NAME                       0: __name__
                4       STORE_NAME                      1: __module__
                6       LOAD_CONST                      0: 'BanAccount'
                8       STORE_NAME                      2: __qualname__
                10      NOP                             
                12      PUSH_NULL                       
                14      LOAD_CONST                      2: '__pyarmor_enter_15994__'
                16      LOAD_CONST                      3: b'<COAddr>\x07\x00\x00"8\x00\x00\x00\x00\x00\x00\x00\x00\x00\x00\x00\x00\x00\x00\x00'
                18      BUILD_TUPLE                     1
                20      CALL_FUNCTION_EX                0
                22      POP_TOP                         
                24      RESUME                          0
                26      NOP                             
                28      NOP                             
                30      NOP                             
                32      NOP                             
                34      NOP                             
                36      LOAD_CONST                      4: ''
                38      PUSH_NULL                       
                40      LOAD_CONST                      1: '__pyarmor_assert_15993__'
                42      LOAD_CONST                      5: 'Account is banned'   # b'\x81\xc3\x1b\x10<\xef\xb0\xc6[\xf3\x1e\x80n\xed\xf6\x8b\nY'
                44      CALL                            1
                52      BUILD_TUPLE                     2
                54      LOAD_CONST                      6: 'account'
                56      LOAD_NAME                       4: str
                58      LOAD_CONST                      7: 'status'
                60      LOAD_NAME                       4: str
                62      BUILD_TUPLE                     4
                64      LOAD_CONST                      8: <CODE> __init__
                66      MAKE_FUNCTION                   5
                68      STORE_NAME                      5: __init__
                70      LOAD_CONST                      10: None
                72      NOP                             
                74      NOP                             
                76      NOP                             
                78      JUMP_FORWARD                    19 (to 118)
                86      POP_TOP                         
                88      RETURN_CONST                    10: None
                90      PUSH_EXC_INFO                   
                92      PUSH_NULL                       
                94      LOAD_CONST                      9: '__pyarmor_exit_15995__'
                96      NOP                             
                98      LOAD_CONST                      3: b'<COAddr>\x07\x00\x00"8\x00\x00\x00\x00\x00\x00\x00\x00\x00\x00\x00\x00\x00\x00\x00'
                100     CALL                            1
                108     POP_TOP                         
                110     RERAISE                         0
                112     COPY                            3
                114     POP_EXCEPT                      
                116     RERAISE                         1
                118     PUSH_NULL                       
                120     LOAD_CONST                      9: '__pyarmor_exit_15995__'
                122     LOAD_CONST                      3: b'<COAddr>\x07\x00\x00"8\x00\x00\x00\x00\x00\x00\x00\x00\x00\x00\x00\x00\x00\x00\x00'
                124     BUILD_TUPLE                     1
                126     CALL_FUNCTION_EX                0
                128     POP_TOP                         
                130     RETURN_VALUE                    
            [Exception Table]
                36 to 70 -> 90 [0] 
                90 to 112 -> 112 [1] lasti
        'BanAccount'
        [Code]
            File Name: <frozen program.static_classes.stop>
            Object Name: StopAccount
            Qualified Name: StopAccount
            Arg Count: 0
            Pos Only Arg Count: 0
            KW Only Arg Count: 0
            Stack Size: 5
            Flags: 0x20000000 (CO_PYARMOR_OBFUSCATED)
            [Names]
                '__name__'
                '__module__'
                '__qualname__'
                '__assert_armored__'
                'str'
                '__init__'
            [Locals+Names]
            [Constants]
                'StopAccount'
                '__pyarmor_assert_15999__'
                '__pyarmor_enter_16000__'
                b'<COAddr>\x07\x00\x00"8\x00\x00\x00\x00\x00\x00\x00\x00\x00\x00\x00\x00\x00\x00\x00'
                ''
                'Account is stopped'   # b'\x81\xc3\x1b\x10<\xef\xb0\xc6[\xf3\x1e\x80\x7f\xf8\xf7\x95\x1fX\xbf'
                'account'
                'status'
                [Code]
                    File Name: <frozen program.static_classes.stop>
                    Object Name: __init__
                    Qualified Name: StopAccount.__init__
                    Arg Count: 3
                    Pos Only Arg Count: 0
                    KW Only Arg Count: 0
                    Stack Size: 5
                    Flags: 0x20000003 (CO_OPTIMIZED | CO_NEWLOCALS | CO_PYARMOR_OBFUSCATED)
                    [Names]
                        'account'
                        'status'
                        'result'
                    [Locals+Names]
                        'self'
                        'account'
                        'status'
                        '__assert_armored__'
                    [Constants]
                        None
                        '__pyarmor_assert_16002__'
                        '__pyarmor_enter_16003__'
                        b'<COAddr>\x07\x00\x00\x1aF\x00\x00\x00\x00\x00\x00\x00\x00\x00\x00\x00\x00\x00\x00\x00'
                        (
                            'account'
                            'status'
                        )
                        '__pyarmor_exit_16004__'
                    [Disassembly]
                        0       NOP                             
                        2       NOP                             
                        4       PUSH_NULL                       
                        6       LOAD_CONST                      2: '__pyarmor_enter_16003__'
                        8       LOAD_CONST                      3: b'<COAddr>\x07\x00\x00\x1aF\x00\x00\x00\x00\x00\x00\x00\x00\x00\x00\x00\x00\x00\x00\x00'
                        10      BUILD_TUPLE                     1
                        12      CALL_FUNCTION_EX                0
                        14      POP_TOP                         
                        16      RESUME                          0
                        18      NOP                             
                        20      NOP                             
                        22      NOP                             
                        24      NOP                             
                        26      NOP                             
                        28      LOAD_FAST                       1: account
                        30      LOAD_FAST                       0: self
                        32      STORE_ATTR                      0: account
                        42      LOAD_FAST                       2: status
                        44      LOAD_FAST                       0: self
                        46      STORE_ATTR                      1: status
                        56      LOAD_FAST                       1: account
                        58      LOAD_FAST                       2: status
                        60      LOAD_CONST                      4: ('account', 'status')
                        62      BUILD_CONST_KEY_MAP             2
                        64      LOAD_FAST                       0: self
                        66      STORE_ATTR                      2: result
                        76      LOAD_CONST                      0: None
                        78      NOP                             
                        80      NOP                             
                        82      NOP                             
                        84      JUMP_FORWARD                    19 (to 124)
                        92      POP_TOP                         
                        94      RETURN_CONST                    0: None
                        96      PUSH_EXC_INFO                   
                        98      PUSH_NULL                       
                        100     LOAD_CONST                      5: '__pyarmor_exit_16004__'
                        102     NOP                             
                        104     LOAD_CONST                      3: b'<COAddr>\x07\x00\x00\x1aF\x00\x00\x00\x00\x00\x00\x00\x00\x00\x00\x00\x00\x00\x00\x00'
                        106     CALL                            1
                        114     POP_TOP                         
                        116     RERAISE                         0
                        118     COPY                            3
                        120     POP_EXCEPT                      
                        122     RERAISE                         1
                        124     PUSH_NULL                       
                        126     LOAD_CONST                      5: '__pyarmor_exit_16004__'
                        128     LOAD_CONST                      3: b'<COAddr>\x07\x00\x00\x1aF\x00\x00\x00\x00\x00\x00\x00\x00\x00\x00\x00\x00\x00\x00\x00'
                        130     BUILD_TUPLE                     1
                        132     CALL_FUNCTION_EX                0
                        134     POP_TOP                         
                        136     RETURN_VALUE                    
                    [Exception Table]
                        28 to 76 -> 96 [0] 
                        96 to 118 -> 118 [1] lasti
                '__pyarmor_exit_16001__'
                None
            [Disassembly]
                0       NOP                             
                2       LOAD_NAME                       0: __name__
                4       STORE_NAME                      1: __module__
                6       LOAD_CONST                      0: 'StopAccount'
                8       STORE_NAME                      2: __qualname__
                10      NOP                             
                12      PUSH_NULL                       
                14      LOAD_CONST                      2: '__pyarmor_enter_16000__'
                16      LOAD_CONST                      3: b'<COAddr>\x07\x00\x00"8\x00\x00\x00\x00\x00\x00\x00\x00\x00\x00\x00\x00\x00\x00\x00'
                18      BUILD_TUPLE                     1
                20      CALL_FUNCTION_EX                0
                22      POP_TOP                         
                24      RESUME                          0
                26      NOP                             
                28      NOP                             
                30      NOP                             
                32      NOP                             
                34      NOP                             
                36      LOAD_CONST                      4: ''
                38      PUSH_NULL                       
                40      LOAD_CONST                      1: '__pyarmor_assert_15999__'
                42      LOAD_CONST                      5: 'Account is stopped'   # b'\x81\xc3\x1b\x10<\xef\xb0\xc6[\xf3\x1e\x80\x7f\xf8\xf7\x95\x1fX\xbf'
                44      CALL                            1
                52      BUILD_TUPLE                     2
                54      LOAD_CONST                      6: 'account'
                56      LOAD_NAME                       4: str
                58      LOAD_CONST                      7: 'status'
                60      LOAD_NAME                       4: str
                62      BUILD_TUPLE                     4
                64      LOAD_CONST                      8: <CODE> __init__
                66      MAKE_FUNCTION                   5
                68      STORE_NAME                      5: __init__
                70      LOAD_CONST                      10: None
                72      NOP                             
                74      NOP                             
                76      NOP                             
                78      JUMP_FORWARD                    19 (to 118)
                86      POP_TOP                         
                88      RETURN_CONST                    10: None
                90      PUSH_EXC_INFO                   
                92      PUSH_NULL                       
                94      LOAD_CONST                      9: '__pyarmor_exit_16001__'
                96      NOP                             
                98      LOAD_CONST                      3: b'<COAddr>\x07\x00\x00"8\x00\x00\x00\x00\x00\x00\x00\x00\x00\x00\x00\x00\x00\x00\x00'
                100     CALL                            1
                108     POP_TOP                         
                110     RERAISE                         0
                112     COPY                            3
                114     POP_EXCEPT                      
                116     RERAISE                         1
                118     PUSH_NULL                       
                120     LOAD_CONST                      9: '__pyarmor_exit_16001__'
                122     LOAD_CONST                      3: b'<COAddr>\x07\x00\x00"8\x00\x00\x00\x00\x00\x00\x00\x00\x00\x00\x00\x00\x00\x00\x00'
                124     BUILD_TUPLE                     1
                126     CALL_FUNCTION_EX                0
                128     POP_TOP                         
                130     RETURN_VALUE                    
            [Exception Table]
                36 to 70 -> 90 [0] 
                90 to 112 -> 112 [1] lasti
        'StopAccount'
        [Code]
            File Name: <frozen program.static_classes.stop>
            Object Name: AutoStopCheck
            Qualified Name: AutoStopCheck
            Arg Count: 0
            Pos Only Arg Count: 0
            KW Only Arg Count: 0
            Stack Size: 5
            Flags: 0x20000000 (CO_PYARMOR_OBFUSCATED)
            [Names]
                '__name__'
                '__module__'
                '__qualname__'
                '__assert_armored__'
                'str'
                '__init__'
                'start'
            [Locals+Names]
            [Constants]
                'AutoStopCheck'
                '__pyarmor_assert_16005__'
                '__pyarmor_enter_16006__'
                b'<COAddr>\x07\x00\x00".\x00\x00\x00\x00\x00\x00\x00\x00\x00\x00\x00\x00\x00\x00\x00'
                'account'
                'status'
                [Code]
                    File Name: <frozen program.static_classes.stop>
                    Object Name: __init__
                    Qualified Name: AutoStopCheck.__init__
                    Arg Count: 3
                    Pos Only Arg Count: 0
                    KW Only Arg Count: 0
                    Stack Size: 5
                    Flags: 0x20000003 (CO_OPTIMIZED | CO_NEWLOCALS | CO_PYARMOR_OBFUSCATED)
                    [Names]
                        'status'
                        'account'
                    [Locals+Names]
                        'self'
                        'account'
                        'status'
                        '__assert_armored__'
                    [Constants]
                        None
                        '__pyarmor_assert_16008__'
                        '__pyarmor_enter_16009__'
                        b'<COAddr>\x07\x00\x00\x1a2\x00\x00\x00\x00\x00\x00\x00\x00\x00\x00\x00\x00\x00\x00\x00'
                        '__pyarmor_exit_16010__'
                    [Disassembly]
                        0       NOP                             
                        2       NOP                             
                        4       PUSH_NULL                       
                        6       LOAD_CONST                      2: '__pyarmor_enter_16009__'
                        8       LOAD_CONST                      3: b'<COAddr>\x07\x00\x00\x1a2\x00\x00\x00\x00\x00\x00\x00\x00\x00\x00\x00\x00\x00\x00\x00'
                        10      BUILD_TUPLE                     1
                        12      CALL_FUNCTION_EX                0
                        14      POP_TOP                         
                        16      RESUME                          0
                        18      NOP                             
                        20      NOP                             
                        22      NOP                             
                        24      NOP                             
                        26      NOP                             
                        28      LOAD_FAST                       2: status
                        30      LOAD_FAST                       0: self
                        32      STORE_ATTR                      0: status
                        42      LOAD_FAST                       1: account
                        44      LOAD_FAST                       0: self
                        46      STORE_ATTR                      1: account
                        56      LOAD_CONST                      0: None
                        58      NOP                             
                        60      NOP                             
                        62      NOP                             
                        64      JUMP_FORWARD                    19 (to 104)
                        72      POP_TOP                         
                        74      RETURN_CONST                    0: None
                        76      PUSH_EXC_INFO                   
                        78      PUSH_NULL                       
                        80      LOAD_CONST                      4: '__pyarmor_exit_16010__'
                        82      NOP                             
                        84      LOAD_CONST                      3: b'<COAddr>\x07\x00\x00\x1a2\x00\x00\x00\x00\x00\x00\x00\x00\x00\x00\x00\x00\x00\x00\x00'
                        86      CALL                            1
                        94      POP_TOP                         
                        96      RERAISE                         0
                        98      COPY                            3
                        100     POP_EXCEPT                      
                        102     RERAISE                         1
                        104     PUSH_NULL                       
                        106     LOAD_CONST                      4: '__pyarmor_exit_16010__'
                        108     LOAD_CONST                      3: b'<COAddr>\x07\x00\x00\x1a2\x00\x00\x00\x00\x00\x00\x00\x00\x00\x00\x00\x00\x00\x00\x00'
                        110     BUILD_TUPLE                     1
                        112     CALL_FUNCTION_EX                0
                        114     POP_TOP                         
                        116     RETURN_VALUE                    
                    [Exception Table]
                        28 to 56 -> 76 [0] 
                        76 to 98 -> 98 [1] lasti
                [Code]
                    File Name: <frozen program.static_classes.stop>
                    Object Name: start
                    Qualified Name: AutoStopCheck.start
                    Arg Count: 1
                    Pos Only Arg Count: 0
                    KW Only Arg Count: 0
                    Stack Size: 6
                    Flags: 0x20000003 (CO_OPTIMIZED | CO_NEWLOCALS | CO_PYARMOR_OBFUSCATED)
                    [Names]
                        'status'
                        'MaxFlood'
                        'account'
                        'BanAccount'
                    [Locals+Names]
                        'self'
                        '__assert_armored__'
                    [Constants]
                        None
                        '__pyarmor_assert_16011__'
                        '__pyarmor_enter_16012__'
                        b'<COAddr>\x07\x00\x00\x1a\x1a\x03\x00\x00\x00\x00\x00\x00\x00\x00\x00\x00\x00\x00\x00\x00'
                        'FloodWaitError'   # b'\x81\xc4\x14\x1c<\xfe\x89\xd3\x12\xee(\xd2~\xe3\xea'
                        'MaxFlood'
                        'AuthKeyDuplicatedError'   # b'\x81\xc3\r\x07;\xd1\xbb\xcb?\xef\x1d\xcce\xef\xf9\x91\nY\x9e\xb5\xb8\xc4\\'
                        'BanAccount'   # b'\x81\xc0\x19\x1d\x12\xf9\xbd\xdd\x0e\xf4\x19'
                        'UserDeactivatedBanError'   # b'\x81\xd7\x0b\x16!\xde\xbb\xd3\x18\xee\x04\xd6m\xf8\xfd\x81-\\\xb5\x82\xb8\xd9A\xde'
                        'UserDeactivatedError'   # b'\x81\xd7\x0b\x16!\xde\xbb\xd3\x18\xee\x04\xd6m\xf8\xfd\x81*O\xa9\xa8\xb8'
                        'UnauthorizedError'   # b'\x81\xd7\x16\x12&\xee\xb6\xdd\t\xf3\x17\xc5h\xc9\xea\x97\x00O'
                        'SessionRevokedError'   # b'\x81\xd1\x1d\x00 \xf3\xb1\xdc)\xff\x1b\xcfg\xe9\xfc\xa0\x1dO\xb4\xb5'
                        'AuthKeyNotFound'   # b'\x81\xc3\r\x07;\xd1\xbb\xcb5\xf5\x19\xe6c\xf9\xf6\x81'
                        'AuthKeyUnregisteredError'   # b'\x81\xc3\r\x07;\xd1\xbb\xcb.\xf4\x1f\xc5k\xe5\xeb\x91\nO\xbe\xa3\x8f\xd9\\\xc3\x17'
                        '__pyarmor_exit_16013__'
                        False
                    [Disassembly]
                        0       NOP                             
                        2       NOP                             
                        4       PUSH_NULL                       
                        6       LOAD_CONST                      2: '__pyarmor_enter_16012__'
                        8       LOAD_CONST                      3: b'<COAddr>\x07\x00\x00\x1a\x1a\x03\x00\x00\x00\x00\x00\x00\x00\x00\x00\x00\x00\x00\x00\x00'
                        10      BUILD_TUPLE                     1
                        12      CALL_FUNCTION_EX                0
                        14      POP_TOP                         
                        16      RESUME                          0
                        18      NOP                             
                        20      NOP                             
                        22      NOP                             
                        24      NOP                             
                        26      NOP                             
                        28      LOAD_FAST                       0: self
                        30      LOAD_ATTR                       0: status
                        50      PUSH_NULL                       
                        52      LOAD_CONST                      1: '__pyarmor_assert_16011__'
                        54      LOAD_CONST                      4: 'FloodWaitError'   # b'\x81\xc4\x14\x1c<\xfe\x89\xd3\x12\xee(\xd2~\xe3\xea'
                        56      CALL                            1
                        64      COMPARE_OP                      40 (==)
                        68      POP_JUMP_IF_FALSE               22 (to 114)
                        70      LOAD_GLOBAL                     3: NULL + MaxFlood
                        80      LOAD_FAST                       0: self
                        82      LOAD_ATTR                       4: account
                        102     LOAD_CONST                      5: 'MaxFlood'
                        104     CALL                            2
                        112     RAISE_VARARGS                   1
                        114     LOAD_FAST                       0: self
                        116     LOAD_ATTR                       0: status
                        136     PUSH_NULL                       
                        138     LOAD_CONST                      1: '__pyarmor_assert_16011__'
                        140     LOAD_CONST                      6: 'AuthKeyDuplicatedError'   # b'\x81\xc3\r\x07;\xd1\xbb\xcb?\xef\x1d\xcce\xef\xf9\x91\nY\x9e\xb5\xb8\xc4\\'
                        142     CALL                            1
                        150     COMPARE_OP                      40 (==)
                        154     POP_JUMP_IF_FALSE               28 (to 212)
                        156     LOAD_GLOBAL                     7: NULL + BanAccount
                        166     LOAD_FAST                       0: self
                        168     LOAD_ATTR                       4: account
                        188     PUSH_NULL                       
                        190     LOAD_CONST                      1: '__pyarmor_assert_16011__'
                        192     LOAD_CONST                      7: 'BanAccount'   # b'\x81\xc0\x19\x1d\x12\xf9\xbd\xdd\x0e\xf4\x19'
                        194     CALL                            1
                        202     CALL                            2
                        210     RAISE_VARARGS                   1
                        212     LOAD_FAST                       0: self
                        214     LOAD_ATTR                       0: status
                        234     PUSH_NULL                       
                        236     LOAD_CONST                      1: '__pyarmor_assert_16011__'
                        238     LOAD_CONST                      8: 'UserDeactivatedBanError'   # b'\x81\xd7\x0b\x16!\xde\xbb\xd3\x18\xee\x04\xd6m\xf8\xfd\x81-\\\xb5\x82\xb8\xd9A\xde'
                        240     CALL                            1
                        248     COMPARE_OP                      40 (==)
                        252     POP_JUMP_IF_FALSE               28 (to 310)
                        254     LOAD_GLOBAL                     7: NULL + BanAccount
                        264     LOAD_FAST                       0: self
                        266     LOAD_ATTR                       4: account
                        286     PUSH_NULL                       
                        288     LOAD_CONST                      1: '__pyarmor_assert_16011__'
                        290     LOAD_CONST                      7: 'BanAccount'   # b'\x81\xc0\x19\x1d\x12\xf9\xbd\xdd\x0e\xf4\x19'
                        292     CALL                            1
                        300     CALL                            2
                        308     RAISE_VARARGS                   1
                        310     LOAD_FAST                       0: self
                        312     LOAD_ATTR                       0: status
                        332     PUSH_NULL                       
                        334     LOAD_CONST                      1: '__pyarmor_assert_16011__'
                        336     LOAD_CONST                      9: 'UserDeactivatedError'   # b'\x81\xd7\x0b\x16!\xde\xbb\xd3\x18\xee\x04\xd6m\xf8\xfd\x81*O\xa9\xa8\xb8'
                        338     CALL                            1
                        346     COMPARE_OP                      40 (==)
                        350     POP_JUMP_IF_FALSE               28 (to 408)
                        352     LOAD_GLOBAL                     7: NULL + BanAccount
                        362     LOAD_FAST                       0: self
                        364     LOAD_ATTR                       4: account
                        384     PUSH_NULL                       
                        386     LOAD_CONST                      1: '__pyarmor_assert_16011__'
                        388     LOAD_CONST                      7: 'BanAccount'   # b'\x81\xc0\x19\x1d\x12\xf9\xbd\xdd\x0e\xf4\x19'
                        390     CALL                            1
                        398     CALL                            2
                        406     RAISE_VARARGS                   1
                        408     LOAD_FAST                       0: self
                        410     LOAD_ATTR                       0: status
                        430     PUSH_NULL                       
                        432     LOAD_CONST                      1: '__pyarmor_assert_16011__'
                        434     LOAD_CONST                      10: 'UnauthorizedError'   # b'\x81\xd7\x16\x12&\xee\xb6\xdd\t\xf3\x17\xc5h\xc9\xea\x97\x00O'
                        436     CALL                            1
                        444     COMPARE_OP                      40 (==)
                        448     POP_JUMP_IF_FALSE               28 (to 506)
                        450     LOAD_GLOBAL                     7: NULL + BanAccount
                        460     LOAD_FAST                       0: self
                        462     LOAD_ATTR                       4: account
                        482     PUSH_NULL                       
                        484     LOAD_CONST                      1: '__pyarmor_assert_16011__'
                        486     LOAD_CONST                      7: 'BanAccount'   # b'\x81\xc0\x19\x1d\x12\xf9\xbd\xdd\x0e\xf4\x19'
                        488     CALL                            1
                        496     CALL                            2
                        504     RAISE_VARARGS                   1
                        506     LOAD_FAST                       0: self
                        508     LOAD_ATTR                       0: status
                        528     PUSH_NULL                       
                        530     LOAD_CONST                      1: '__pyarmor_assert_16011__'
                        532     LOAD_CONST                      11: 'SessionRevokedError'   # b'\x81\xd1\x1d\x00 \xf3\xb1\xdc)\xff\x1b\xcfg\xe9\xfc\xa0\x1dO\xb4\xb5'
                        534     CALL                            1
                        542     COMPARE_OP                      40 (==)
                        546     POP_JUMP_IF_FALSE               28 (to 604)
                        548     LOAD_GLOBAL                     7: NULL + BanAccount
                        558     LOAD_FAST                       0: self
                        560     LOAD_ATTR                       4: account
                        580     PUSH_NULL                       
                        582     LOAD_CONST                      1: '__pyarmor_assert_16011__'
                        584     LOAD_CONST                      7: 'BanAccount'   # b'\x81\xc0\x19\x1d\x12\xf9\xbd\xdd\x0e\xf4\x19'
                        586     CALL                            1
                        594     CALL                            2
                        602     RAISE_VARARGS                   1
                        604     LOAD_FAST                       0: self
                        606     LOAD_ATTR                       0: status
                        626     PUSH_NULL                       
                        628     LOAD_CONST                      1: '__pyarmor_assert_16011__'
                        630     LOAD_CONST                      12: 'AuthKeyNotFound'   # b'\x81\xc3\r\x07;\xd1\xbb\xcb5\xf5\x19\xe6c\xf9\xf6\x81'
                        632     CALL                            1
                        640     COMPARE_OP                      40 (==)
                        644     POP_JUMP_IF_FALSE               28 (to 702)
                        646     LOAD_GLOBAL                     7: NULL + BanAccount
                        656     LOAD_FAST                       0: self
                        658     LOAD_ATTR                       4: account
                        678     PUSH_NULL                       
                        680     LOAD_CONST                      1: '__pyarmor_assert_16011__'
                        682     LOAD_CONST                      7: 'BanAccount'   # b'\x81\xc0\x19\x1d\x12\xf9\xbd\xdd\x0e\xf4\x19'
                        684     CALL                            1
                        692     CALL                            2
                        700     RAISE_VARARGS                   1
                        702     LOAD_FAST                       0: self
                        704     LOAD_ATTR                       0: status
                        724     PUSH_NULL                       
                        726     LOAD_CONST                      1: '__pyarmor_assert_16011__'
                        728     LOAD_CONST                      13: 'AuthKeyUnregisteredError'   # b'\x81\xc3\r\x07;\xd1\xbb\xcb.\xf4\x1f\xc5k\xe5\xeb\x91\nO\xbe\xa3\x8f\xd9\\\xc3\x17'
                        730     CALL                            1
                        738     COMPARE_OP                      40 (==)
                        742     POP_JUMP_IF_FALSE               28 (to 800)
                        744     LOAD_GLOBAL                     7: NULL + BanAccount
                        754     LOAD_FAST                       0: self
                        756     LOAD_ATTR                       4: account
                        776     PUSH_NULL                       
                        778     LOAD_CONST                      1: '__pyarmor_assert_16011__'
                        780     LOAD_CONST                      7: 'BanAccount'   # b'\x81\xc0\x19\x1d\x12\xf9\xbd\xdd\x0e\xf4\x19'
                        782     CALL                            1
                        790     CALL                            2
                        798     RAISE_VARARGS                   1
                        800     LOAD_CONST                      15: False
                        802     NOP                             
                        804     NOP                             
                        806     NOP                             
                        808     JUMP_FORWARD                    19 (to 848)
                        816     POP_TOP                         
                        818     RETURN_CONST                    15: False
                        820     PUSH_EXC_INFO                   
                        822     PUSH_NULL                       
                        824     LOAD_CONST                      14: '__pyarmor_exit_16013__'
                        826     NOP                             
                        828     LOAD_CONST                      3: b'<COAddr>\x07\x00\x00\x1a\x1a\x03\x00\x00\x00\x00\x00\x00\x00\x00\x00\x00\x00\x00\x00\x00'
                        830     CALL                            1
                        838     POP_TOP                         
                        840     RERAISE                         0
                        842     COPY                            3
                        844     POP_EXCEPT                      
                        846     RERAISE                         1
                        848     PUSH_NULL                       
                        850     LOAD_CONST                      14: '__pyarmor_exit_16013__'
                        852     LOAD_CONST                      3: b'<COAddr>\x07\x00\x00\x1a\x1a\x03\x00\x00\x00\x00\x00\x00\x00\x00\x00\x00\x00\x00\x00\x00'
                        854     BUILD_TUPLE                     1
                        856     CALL_FUNCTION_EX                0
                        858     POP_TOP                         
                        860     RETURN_VALUE                    
                    [Exception Table]
                        28 to 800 -> 820 [0] 
                        820 to 842 -> 842 [1] lasti
                '__pyarmor_exit_16007__'
                None
                (
                    ''
                    ''
                )
            [Disassembly]
                0       NOP                             
                2       LOAD_NAME                       0: __name__
                4       STORE_NAME                      1: __module__
                6       LOAD_CONST                      0: 'AutoStopCheck'
                8       STORE_NAME                      2: __qualname__
                10      NOP                             
                12      PUSH_NULL                       
                14      LOAD_CONST                      2: '__pyarmor_enter_16006__'
                16      LOAD_CONST                      3: b'<COAddr>\x07\x00\x00".\x00\x00\x00\x00\x00\x00\x00\x00\x00\x00\x00\x00\x00\x00\x00'
                18      BUILD_TUPLE                     1
                20      CALL_FUNCTION_EX                0
                22      POP_TOP                         
                24      RESUME                          0
                26      NOP                             
                28      NOP                             
                30      NOP                             
                32      NOP                             
                34      NOP                             
                36      LOAD_CONST                      10: ('', '')
                38      LOAD_CONST                      4: 'account'
                40      LOAD_NAME                       4: str
                42      LOAD_CONST                      5: 'status'
                44      LOAD_NAME                       4: str
                46      BUILD_TUPLE                     4
                48      LOAD_CONST                      6: <CODE> __init__
                50      MAKE_FUNCTION                   5
                52      STORE_NAME                      5: __init__
                54      LOAD_CONST                      7: <CODE> start
                56      MAKE_FUNCTION                   0
                58      STORE_NAME                      6: start
                60      LOAD_CONST                      9: None
                62      NOP                             
                64      NOP                             
                66      NOP                             
                68      JUMP_FORWARD                    19 (to 108)
                76      POP_TOP                         
                78      RETURN_CONST                    9: None
                80      PUSH_EXC_INFO                   
                82      PUSH_NULL                       
                84      LOAD_CONST                      8: '__pyarmor_exit_16007__'
                86      NOP                             
                88      LOAD_CONST                      3: b'<COAddr>\x07\x00\x00".\x00\x00\x00\x00\x00\x00\x00\x00\x00\x00\x00\x00\x00\x00\x00'
                90      CALL                            1
                98      POP_TOP                         
                100     RERAISE                         0
                102     COPY                            3
                104     POP_EXCEPT                      
                106     RERAISE                         1
                108     PUSH_NULL                       
                110     LOAD_CONST                      8: '__pyarmor_exit_16007__'
                112     LOAD_CONST                      3: b'<COAddr>\x07\x00\x00".\x00\x00\x00\x00\x00\x00\x00\x00\x00\x00\x00\x00\x00\x00\x00'
                114     BUILD_TUPLE                     1
                116     CALL_FUNCTION_EX                0
                118     POP_TOP                         
                120     RETURN_VALUE                    
            [Exception Table]
                36 to 60 -> 80 [0] 
                80 to 102 -> 102 [1] lasti
        'AutoStopCheck'
        [Code]
            File Name: <frozen program.static_classes.stop>
            Object Name: AutoStop
            Qualified Name: AutoStop
            Arg Count: 0
            Pos Only Arg Count: 0
            KW Only Arg Count: 0
            Stack Size: 5
            Flags: 0x20000000 (CO_PYARMOR_OBFUSCATED)
            [Names]
                '__name__'
                '__module__'
                '__qualname__'
                '__assert_armored__'
                '__init__'
                'count_elements'
                'start'
                '_print'
            [Locals+Names]
            [Constants]
                'AutoStop'
                '__pyarmor_assert_16014__'
                '__pyarmor_enter_16015__'
                b'<COAddr>\x05\x00\x00"8\x00\x00\x00\x00\x00\x00\x00\x00\x00\x00\x00\x00\x00\x00\x00'
                None
                [Code]
                    File Name: <frozen program.static_classes.stop>
                    Object Name: __init__
                    Qualified Name: AutoStop.__init__
                    Arg Count: 5
                    Pos Only Arg Count: 0
                    KW Only Arg Count: 0
                    Stack Size: 7
                    Flags: 0x20000003 (CO_OPTIMIZED | CO_NEWLOCALS | CO_PYARMOR_OBFUSCATED)
                    [Names]
                        'result'
                        'get'
                        'autostop'
                        'int'
                        'ban'
                        'spamblock'
                        'flood'
                        'sequence'
                        'history'
                        'stop_thread'
                        '_ban'
                        '_flood'
                        '_spamblock'
                    [Locals+Names]
                        'self'
                        'result'
                        'history'
                        'data'
                        'stop_thread'
                        '__assert_armored__'
                    [Constants]
                        None
                        '__pyarmor_assert_16017__'
                        '__pyarmor_enter_16018__'
                        b'<COAddr>\x07\x00\x00\x1a\\\x02\x00\x00\x00\x00\x00\x00\x00\x00\x00\x00\x00\x00\x00\x00'
                        'Settings'
                        'autostop_rules'   # b'\x81\xe3\r\x07<\xe9\xaa\xdd\x0b\xc5\x1f\xd5`\xe9\xeb'
                        False
                        0
                        'autostop_ban'   # b'\x81\xe3\r\x07<\xe9\xaa\xdd\x0b\xc5\x0f\xc1b'
                        'autostop_spamblock'   # b'\x81\xe3\r\x07<\xe9\xaa\xdd\x0b\xc5\x1e\xd0m\xe1\xfa\x89\x00^\xb0'
                        'autostop_flood'   # b'\x81\xe3\r\x07<\xe9\xaa\xdd\x0b\xc5\x0b\xccc\xe3\xfc'
                        'autostop_sequential'   # b'\x81\xe3\r\x07<\xe9\xaa\xdd\x0b\xc5\x1e\xc5}\xf9\xfd\x8b\x1bT\xba\xab'
                        '__pyarmor_exit_16019__'
                    [Disassembly]
                        0       NOP                             
                        2       NOP                             
                        4       PUSH_NULL                       
                        6       LOAD_CONST                      2: '__pyarmor_enter_16018__'
                        8       LOAD_CONST                      3: b'<COAddr>\x07\x00\x00\x1a\\\x02\x00\x00\x00\x00\x00\x00\x00\x00\x00\x00\x00\x00\x00\x00'
                        10      BUILD_TUPLE                     1
                        12      CALL_FUNCTION_EX                0
                        14      POP_TOP                         
                        16      RESUME                          0
                        18      NOP                             
                        20      NOP                             
                        22      NOP                             
                        24      NOP                             
                        26      NOP                             
                        28      LOAD_FAST                       1: result
                        30      LOAD_FAST                       0: self
                        32      STORE_ATTR                      0: result
                        42      LOAD_FAST                       3: data
                        44      LOAD_ATTR                       3: get
                        64      LOAD_CONST                      4: 'Settings'
                        66      BUILD_LIST                      0
                        68      CALL                            2
                        76      LOAD_ATTR                       3: get
                        96      PUSH_NULL                       
                        98      LOAD_CONST                      1: '__pyarmor_assert_16017__'
                        100     LOAD_CONST                      5: 'autostop_rules'   # b'\x81\xe3\r\x07<\xe9\xaa\xdd\x0b\xc5\x1f\xd5`\xe9\xeb'
                        102     CALL                            1
                        110     LOAD_CONST                      6: False
                        112     CALL                            2
                        120     LOAD_FAST                       0: self
                        122     STORE_ATTR                      2: autostop
                        132     LOAD_GLOBAL                     7: NULL + int
                        142     LOAD_FAST                       3: data
                        144     LOAD_ATTR                       3: get
                        164     LOAD_CONST                      4: 'Settings'
                        166     LOAD_CONST                      7: 0
                        168     CALL                            2
                        176     LOAD_ATTR                       3: get
                        196     PUSH_NULL                       
                        198     LOAD_CONST                      1: '__pyarmor_assert_16017__'
                        200     LOAD_CONST                      8: 'autostop_ban'   # b'\x81\xe3\r\x07<\xe9\xaa\xdd\x0b\xc5\x0f\xc1b'
                        202     CALL                            1
                        210     CALL                            1
                        218     CALL                            1
                        226     LOAD_FAST                       0: self
                        228     STORE_ATTR                      4: ban
                        238     LOAD_GLOBAL                     7: NULL + int
                        248     LOAD_FAST                       3: data
                        250     LOAD_ATTR                       3: get
                        270     LOAD_CONST                      4: 'Settings'
                        272     LOAD_CONST                      7: 0
                        274     CALL                            2
                        282     LOAD_ATTR                       3: get
                        302     PUSH_NULL                       
                        304     LOAD_CONST                      1: '__pyarmor_assert_16017__'
                        306     LOAD_CONST                      9: 'autostop_spamblock'   # b'\x81\xe3\r\x07<\xe9\xaa\xdd\x0b\xc5\x1e\xd0m\xe1\xfa\x89\x00^\xb0'
                        308     CALL                            1
                        316     CALL                            1
                        324     CALL                            1
                        332     LOAD_FAST                       0: self
                        334     STORE_ATTR                      5: spamblock
                        344     LOAD_GLOBAL                     7: NULL + int
                        354     LOAD_FAST                       3: data
                        356     LOAD_ATTR                       3: get
                        376     LOAD_CONST                      4: 'Settings'
                        378     LOAD_CONST                      7: 0
                        380     CALL                            2
                        388     LOAD_ATTR                       3: get
                        408     PUSH_NULL                       
                        410     LOAD_CONST                      1: '__pyarmor_assert_16017__'
                        412     LOAD_CONST                      10: 'autostop_flood'   # b'\x81\xe3\r\x07<\xe9\xaa\xdd\x0b\xc5\x0b\xccc\xe3\xfc'
                        414     CALL                            1
                        422     CALL                            1
                        430     CALL                            1
                        438     LOAD_FAST                       0: self
                        440     STORE_ATTR                      6: flood
                        450     LOAD_FAST                       3: data
                        452     LOAD_ATTR                       3: get
                        472     LOAD_CONST                      4: 'Settings'
                        474     LOAD_CONST                      7: 0
                        476     CALL                            2
                        484     LOAD_ATTR                       3: get
                        504     PUSH_NULL                       
                        506     LOAD_CONST                      1: '__pyarmor_assert_16017__'
                        508     LOAD_CONST                      11: 'autostop_sequential'   # b'\x81\xe3\r\x07<\xe9\xaa\xdd\x0b\xc5\x1e\xc5}\xf9\xfd\x8b\x1bT\xba\xab'
                        510     CALL                            1
                        518     LOAD_CONST                      6: False
                        520     CALL                            2
                        528     LOAD_FAST                       0: self
                        530     STORE_ATTR                      7: sequence
                        540     LOAD_FAST                       2: history
                        542     LOAD_FAST                       0: self
                        544     STORE_ATTR                      8: history
                        554     LOAD_FAST                       4: stop_thread
                        556     LOAD_FAST                       0: self
                        558     STORE_ATTR                      9: stop_thread
                        568     LOAD_CONST                      7: 0
                        570     LOAD_FAST                       0: self
                        572     STORE_ATTR                      10: _ban
                        582     LOAD_CONST                      7: 0
                        584     LOAD_FAST                       0: self
                        586     STORE_ATTR                      11: _flood
                        596     LOAD_CONST                      7: 0
                        598     LOAD_FAST                       0: self
                        600     STORE_ATTR                      12: _spamblock
                        610     LOAD_CONST                      0: None
                        612     NOP                             
                        614     NOP                             
                        616     NOP                             
                        618     JUMP_FORWARD                    19 (to 658)
                        626     POP_TOP                         
                        628     RETURN_CONST                    0: None
                        630     PUSH_EXC_INFO                   
                        632     PUSH_NULL                       
                        634     LOAD_CONST                      12: '__pyarmor_exit_16019__'
                        636     NOP                             
                        638     LOAD_CONST                      3: b'<COAddr>\x07\x00\x00\x1a\\\x02\x00\x00\x00\x00\x00\x00\x00\x00\x00\x00\x00\x00\x00\x00'
                        640     CALL                            1
                        648     POP_TOP                         
                        650     RERAISE                         0
                        652     COPY                            3
                        654     POP_EXCEPT                      
                        656     RERAISE                         1
                        658     PUSH_NULL                       
                        660     LOAD_CONST                      12: '__pyarmor_exit_16019__'
                        662     LOAD_CONST                      3: b'<COAddr>\x07\x00\x00\x1a\\\x02\x00\x00\x00\x00\x00\x00\x00\x00\x00\x00\x00\x00\x00\x00'
                        664     BUILD_TUPLE                     1
                        666     CALL_FUNCTION_EX                0
                        668     POP_TOP                         
                        670     RETURN_VALUE                    
                    [Exception Table]
                        28 to 610 -> 630 [0] 
                        630 to 652 -> 652 [1] lasti
                [Code]
                    File Name: <frozen program.static_classes.stop>
                    Object Name: count_elements
                    Qualified Name: AutoStop.count_elements
                    Arg Count: 2
                    Pos Only Arg Count: 0
                    KW Only Arg Count: 0
                    Stack Size: 5
                    Flags: 0x20000003 (CO_OPTIMIZED | CO_NEWLOCALS | CO_PYARMOR_OBFUSCATED)
                    [Names]
                        'append'
                    [Locals+Names]
                        'self'
                        'lst'
                        '__assert_armored__'
                        '_var_var_0'
                        '_var_var_1'
                        '_var_var_2'
                        '_var_var_3'
                    [Constants]
                        None
                        '__pyarmor_assert_16020__'
                        '__pyarmor_enter_16021__'
                        b'<COAddr>\x05\x00\x00\x1a\x9c\x00\x00\x00\x00\x00\x00\x00\x00\x00\x00\x00\x00\x00\x00\x00'
                        0
                        1
                        '__pyarmor_exit_16022__'
                    [Disassembly]
                        0       NOP                             
                        2       NOP                             
                        4       PUSH_NULL                       
                        6       LOAD_CONST                      2: '__pyarmor_enter_16021__'
                        8       LOAD_CONST                      3: b'<COAddr>\x05\x00\x00\x1a\x9c\x00\x00\x00\x00\x00\x00\x00\x00\x00\x00\x00\x00\x00\x00\x00'
                        10      BUILD_TUPLE                     1
                        12      CALL_FUNCTION_EX                0
                        14      POP_TOP                         
                        16      RESUME                          0
                        18      NOP                             
                        20      NOP                             
                        22      NOP                             
                        24      NOP                             
                        26      NOP                             
                        28      LOAD_CONST                      4: 0
                        30      STORE_FAST                      3: _var_var_0
                        32      BUILD_LIST                      0
                        34      STORE_FAST                      4: _var_var_1
                        36      LOAD_CONST                      0: None
                        38      STORE_FAST                      5: _var_var_2
                        40      LOAD_FAST                       1: lst
                        42      GET_ITER                        
                        44      FOR_ITER                        55 (to 156)
                        48      STORE_FAST                      6: _var_var_3
                        50      LOAD_FAST                       6: _var_var_3
                        52      LOAD_FAST                       5: _var_var_2
                        54      COMPARE_OP                      40 (==)
                        58      POP_JUMP_IF_FALSE               25 (to 110)
                        60      LOAD_FAST                       3: _var_var_0
                        62      LOAD_CONST                      5: 1
                        64      BINARY_OP                       13 (+=)
                        68      STORE_FAST                      3: _var_var_0
                        70      LOAD_FAST                       4: _var_var_1
                        72      LOAD_ATTR                       1: append
                        92      LOAD_FAST                       6: _var_var_3
                        94      LOAD_FAST                       3: _var_var_0
                        96      BUILD_LIST                      2
                        98      CALL                            1
                        106     POP_TOP                         
                        108     JUMP_BACKWARD                   33 (to 44)
                        110     LOAD_FAST                       6: _var_var_3
                        112     STORE_FAST                      5: _var_var_2
                        114     LOAD_CONST                      5: 1
                        116     STORE_FAST                      3: _var_var_0
                        118     LOAD_FAST                       4: _var_var_1
                        120     LOAD_ATTR                       1: append
                        140     LOAD_FAST                       6: _var_var_3
                        142     LOAD_FAST                       3: _var_var_0
                        144     BUILD_LIST                      2
                        146     CALL                            1
                        154     POP_TOP                         
                        156     JUMP_BACKWARD                   57 (to 44)
                        158     END_FOR                         
                        160     LOAD_FAST                       4: _var_var_1
                        162     NOP                             
                        164     NOP                             
                        166     NOP                             
                        168     JUMP_FORWARD                    20 (to 210)
                        170     CALL                            1
                        178     POP_TOP                         
                        180     RETURN_VALUE                    
                        182     PUSH_EXC_INFO                   
                        184     PUSH_NULL                       
                        186     LOAD_CONST                      6: '__pyarmor_exit_16022__'
                        188     NOP                             
                        190     LOAD_CONST                      3: b'<COAddr>\x05\x00\x00\x1a\x9c\x00\x00\x00\x00\x00\x00\x00\x00\x00\x00\x00\x00\x00\x00\x00'
                        192     CALL                            1
                        200     POP_TOP                         
                        202     RERAISE                         0
                        204     COPY                            3
                        206     POP_EXCEPT                      
                        208     RERAISE                         1
                        210     PUSH_NULL                       
                        212     LOAD_CONST                      6: '__pyarmor_exit_16022__'
                        214     LOAD_CONST                      3: b'<COAddr>\x05\x00\x00\x1a\x9c\x00\x00\x00\x00\x00\x00\x00\x00\x00\x00\x00\x00\x00\x00\x00'
                        216     BUILD_TUPLE                     1
                        218     CALL_FUNCTION_EX                0
                        220     POP_TOP                         
                        222     RETURN_VALUE                    
                    [Exception Table]
                        28 to 162 -> 182 [0] 
                        182 to 204 -> 204 [1] lasti
                [Code]
                    File Name: <frozen program.static_classes.stop>
                    Object Name: start
                    Qualified Name: AutoStop.start
                    Arg Count: 1
                    Pos Only Arg Count: 0
                    KW Only Arg Count: 0
                    Stack Size: 9
                    Flags: 0x20000003 (CO_OPTIMIZED | CO_NEWLOCALS | CO_PYARMOR_OBFUSCATED)
                    [Names]
                        'autostop'
                        'history'
                        'result'
                        'get'
                        'append'
                        'sequence'
                        'count_elements'
                        'ban'
                        'flood'
                        'spamblock'
                        '_print'
                        'stop_thread'
                        'set'
                        'StopProgram'
                        '_ban'
                        '_flood'
                        '_spamblock'
                        'print'
                    [Locals+Names]
                        'self'
                        '__assert_armored__'
                        '_var_var_4'
                        '_var_var_3'
                        '_var_var_5'
                        '_var_var_6'
                        '_var_var_7'
                        '_var_var_8'
                    [Constants]
                        None
                        '__pyarmor_assert_16023__'
                        '__pyarmor_enter_16024__'
                        b'<COAddr>\x05\x00\x00\x1a"\x06\x00\x00\x00\x00\x00\x00\x00\x00\x00\x00\x00\x00\x00\x00'
                        '__pyarmor_exit_16025__'
                        'account'
                        '0'
                        'status'
                        'error'
                        (
                            'account'
                            'status'
                        )
                        False
                        0
                        'BanAccount'   # b'\x81\xc0\x19\x1d\x12\xf9\xbd\xdd\x0e\xf4\x19'
                        1
                        True
                        'MaxFlood'
                        'PeerFlood'   # b'\x81\xd2\x1d\x16!\xdc\xb2\xdd\x14\xfe'
                        ' BanAccount '   # b'\x81\xa2:\x12=\xdb\xbd\xd1\x14\xef\x03\xd4,'
                        '  MaxFlood '   # b'\x81\xa2X>2\xe2\x98\xde\x14\xf5\t\x80'
                        '  PeerFlood'   # b'\x81\xa2X#6\xff\xac\xf4\x17\xf5\x02\xc4'
                    [Disassembly]
                        0       NOP                             
                        2       NOP                             
                        4       PUSH_NULL                       
                        6       LOAD_CONST                      2: '__pyarmor_enter_16024__'
                        8       LOAD_CONST                      3: b'<COAddr>\x05\x00\x00\x1a"\x06\x00\x00\x00\x00\x00\x00\x00\x00\x00\x00\x00\x00\x00\x00'
                        10      BUILD_TUPLE                     1
                        12      CALL_FUNCTION_EX                0
                        14      POP_TOP                         
                        16      RESUME                          0
                        18      NOP                             
                        20      NOP                             
                        22      NOP                             
                        24      NOP                             
                        26      NOP                             
                        28      LOAD_FAST                       0: self
                        30      LOAD_ATTR                       0: autostop
                        50      POP_JUMP_IF_TRUE                21 (to 94)
                        52      LOAD_FAST                       0: self
                        54      LOAD_ATTR                       2: history
                        74      NOP                             
                        76      NOP                             
                        78      JUMP_FORWARD                    771 (to 1624)
                        82      CALL                            1
                        90      POP_TOP                         
                        92      RETURN_VALUE                    
                        94      LOAD_FAST                       0: self
                        96      LOAD_ATTR                       4: result
                        116     LOAD_ATTR                       7: get
                        136     LOAD_CONST                      5: 'account'
                        138     LOAD_CONST                      6: '0'
                        140     CALL                            2
                        148     STORE_FAST                      2: _var_var_4
                        150     LOAD_FAST                       0: self
                        152     LOAD_ATTR                       4: result
                        172     LOAD_ATTR                       7: get
                        192     LOAD_CONST                      7: 'status'
                        194     LOAD_CONST                      8: 'error'
                        196     CALL                            2
                        204     STORE_FAST                      3: _var_var_3
                        206     LOAD_FAST                       0: self
                        208     LOAD_ATTR                       2: history
                        228     LOAD_ATTR                       9: append
                        248     LOAD_FAST                       2: _var_var_4
                        250     LOAD_FAST                       3: _var_var_3
                        252     LOAD_CONST                      9: ('account', 'status')
                        254     BUILD_CONST_KEY_MAP             2
                        256     CALL                            1
                        264     POP_TOP                         
                        266     LOAD_FAST                       0: self
                        268     LOAD_ATTR                       10: sequence
                        288     POP_JUMP_IF_FALSE               264 (to 820)
                        292     BUILD_LIST                      0
                        294     STORE_FAST                      3: _var_var_3
                        296     LOAD_CONST                      10: False
                        298     STORE_FAST                      4: _var_var_5
                        300     LOAD_FAST                       0: self
                        302     LOAD_ATTR                       2: history
                        322     GET_ITER                        
                        324     FOR_ITER                        22 (to 370)
                        328     STORE_FAST                      5: _var_var_6
                        330     LOAD_FAST                       3: _var_var_3
                        332     LOAD_ATTR                       9: append
                        352     LOAD_FAST                       5: _var_var_6
                        354     LOAD_CONST                      7: 'status'
                        356     BINARY_SUBSCR                   
                        360     CALL                            1
                        368     POP_TOP                         
                        370     JUMP_BACKWARD                   24 (to 324)
                        372     END_FOR                         
                        374     LOAD_FAST                       0: self
                        376     LOAD_ATTR                       13: count_elements
                        396     LOAD_FAST                       3: _var_var_3
                        398     CALL                            1
                        406     STORE_FAST                      6: _var_var_7
                        408     LOAD_FAST                       6: _var_var_7
                        410     GET_ITER                        
                        412     FOR_ITER                        146 (to 706)
                        416     STORE_FAST                      7: _var_var_8
                        418     LOAD_FAST                       7: _var_var_8
                        420     LOAD_CONST                      11: 0
                        422     BINARY_SUBSCR                   
                        426     PUSH_NULL                       
                        428     LOAD_CONST                      1: '__pyarmor_assert_16023__'
                        430     LOAD_CONST                      12: 'BanAccount'   # b'\x81\xc0\x19\x1d\x12\xf9\xbd\xdd\x0e\xf4\x19'
                        432     CALL                            1
                        440     COMPARE_OP                      40 (==)
                        444     POP_JUMP_IF_FALSE               35 (to 516)
                        446     LOAD_FAST                       0: self
                        448     LOAD_ATTR                       14: ban
                        468     LOAD_CONST                      11: 0
                        470     COMPARE_OP                      55 (!=)
                        474     POP_JUMP_IF_FALSE               20 (to 516)
                        476     LOAD_FAST                       7: _var_var_8
                        478     LOAD_CONST                      13: 1
                        480     BINARY_SUBSCR                   
                        484     LOAD_FAST                       0: self
                        486     LOAD_ATTR                       14: ban
                        506     COMPARE_OP                      68 (>)
                        510     POP_JUMP_IF_FALSE               2 (to 516)
                        512     LOAD_CONST                      14: True
                        514     STORE_FAST                      4: _var_var_5
                        516     LOAD_FAST                       7: _var_var_8
                        518     LOAD_CONST                      11: 0
                        520     BINARY_SUBSCR                   
                        524     LOAD_CONST                      15: 'MaxFlood'
                        526     COMPARE_OP                      40 (==)
                        530     POP_JUMP_IF_FALSE               35 (to 602)
                        532     LOAD_FAST                       0: self
                        534     LOAD_ATTR                       16: flood
                        554     LOAD_CONST                      11: 0
                        556     COMPARE_OP                      55 (!=)
                        560     POP_JUMP_IF_FALSE               20 (to 602)
                        562     LOAD_FAST                       7: _var_var_8
                        564     LOAD_CONST                      13: 1
                        566     BINARY_SUBSCR                   
                        570     LOAD_FAST                       0: self
                        572     LOAD_ATTR                       16: flood
                        592     COMPARE_OP                      68 (>)
                        596     POP_JUMP_IF_FALSE               2 (to 602)
                        598     LOAD_CONST                      14: True
                        600     STORE_FAST                      4: _var_var_5
                        602     LOAD_FAST                       7: _var_var_8
                        604     LOAD_CONST                      11: 0
                        606     BINARY_SUBSCR                   
                        610     PUSH_NULL                       
                        612     LOAD_CONST                      1: '__pyarmor_assert_16023__'
                        614     LOAD_CONST                      16: 'PeerFlood'   # b'\x81\xd2\x1d\x16!\xdc\xb2\xdd\x14\xfe'
                        616     CALL                            1
                        624     COMPARE_OP                      40 (==)
                        628     POP_JUMP_IF_TRUE                1 (to 632)
                        630     JUMP_BACKWARD                   110 (to 412)
                        632     LOAD_FAST                       0: self
                        634     LOAD_ATTR                       18: spamblock
                        654     LOAD_CONST                      11: 0
                        656     COMPARE_OP                      55 (!=)
                        660     POP_JUMP_IF_TRUE                1 (to 664)
                        662     JUMP_BACKWARD                   126 (to 412)
                        664     LOAD_FAST                       7: _var_var_8
                        666     LOAD_CONST                      13: 1
                        668     BINARY_SUBSCR                   
                        672     LOAD_FAST                       0: self
                        674     LOAD_ATTR                       18: spamblock
                        694     COMPARE_OP                      68 (>)
                        698     POP_JUMP_IF_TRUE                1 (to 702)
                        700     JUMP_BACKWARD                   145 (to 412)
                        702     LOAD_CONST                      14: True
                        704     STORE_FAST                      4: _var_var_5
                        706     JUMP_BACKWARD                   148 (to 412)
                        708     END_FOR                         
                        710     LOAD_FAST                       4: _var_var_5
                        712     POP_JUMP_IF_FALSE               419 (to 1554)
                        716     LOAD_FAST                       0: self
                        718     LOAD_ATTR                       21: _print
                        738     CALL                            0
                        746     POP_TOP                         
                        748     LOAD_FAST                       0: self
                        750     LOAD_ATTR                       22: stop_thread
                        770     LOAD_ATTR                       25: set
                        790     CALL                            0
                        798     POP_TOP                         
                        800     LOAD_GLOBAL                     27: NULL + StopProgram
                        810     CALL                            0
                        818     RAISE_VARARGS                   1
                        820     LOAD_CONST                      10: False
                        822     STORE_FAST                      4: _var_var_5
                        824     LOAD_FAST                       0: self
                        826     LOAD_ATTR                       2: history
                        846     GET_ITER                        
                        848     FOR_ITER                        102 (to 1054)
                        852     STORE_FAST                      5: _var_var_6
                        854     LOAD_FAST                       5: _var_var_6
                        856     LOAD_CONST                      7: 'status'
                        858     BINARY_SUBSCR                   
                        862     PUSH_NULL                       
                        864     LOAD_CONST                      1: '__pyarmor_assert_16023__'
                        866     LOAD_CONST                      12: 'BanAccount'   # b'\x81\xc0\x19\x1d\x12\xf9\xbd\xdd\x0e\xf4\x19'
                        868     CALL                            1
                        876     COMPARE_OP                      40 (==)
                        880     POP_JUMP_IF_FALSE               21 (to 924)
                        882     LOAD_FAST                       0: self
                        884     COPY                            1
                        886     LOAD_ATTR                       28: _ban
                        906     LOAD_CONST                      13: 1
                        908     BINARY_OP                       13 (+=)
                        912     SWAP                            2
                        914     STORE_ATTR                      14: _ban
                        924     LOAD_FAST                       5: _var_var_6
                        926     LOAD_CONST                      7: 'status'
                        928     BINARY_SUBSCR                   
                        932     LOAD_CONST                      15: 'MaxFlood'
                        934     COMPARE_OP                      40 (==)
                        938     POP_JUMP_IF_FALSE               21 (to 982)
                        940     LOAD_FAST                       0: self
                        942     COPY                            1
                        944     LOAD_ATTR                       30: _flood
                        964     LOAD_CONST                      13: 1
                        966     BINARY_OP                       13 (+=)
                        970     SWAP                            2
                        972     STORE_ATTR                      15: _flood
                        982     LOAD_FAST                       5: _var_var_6
                        984     LOAD_CONST                      7: 'status'
                        986     BINARY_SUBSCR                   
                        990     PUSH_NULL                       
                        992     LOAD_CONST                      1: '__pyarmor_assert_16023__'
                        994     LOAD_CONST                      16: 'PeerFlood'   # b'\x81\xd2\x1d\x16!\xdc\xb2\xdd\x14\xfe'
                        996     CALL                            1
                        1004    COMPARE_OP                      40 (==)
                        1008    POP_JUMP_IF_TRUE                1 (to 1012)
                        1010    JUMP_BACKWARD                   82 (to 848)
                        1012    LOAD_FAST                       0: self
                        1014    COPY                            1
                        1016    LOAD_ATTR                       32: _spamblock
                        1036    LOAD_CONST                      13: 1
                        1038    BINARY_OP                       13 (+=)
                        1042    SWAP                            2
                        1044    STORE_ATTR                      16: _spamblock
                        1054    JUMP_BACKWARD                   104 (to 848)
                        1056    END_FOR                         
                        1058    LOAD_FAST                       0: self
                        1060    LOAD_ATTR                       28: _ban
                        1080    LOAD_FAST                       0: self
                        1082    LOAD_ATTR                       14: ban
                        1102    COMPARE_OP                      92 (>=)
                        1106    POP_JUMP_IF_FALSE               17 (to 1142)
                        1108    LOAD_FAST                       0: self
                        1110    LOAD_ATTR                       14: ban
                        1130    LOAD_CONST                      11: 0
                        1132    COMPARE_OP                      55 (!=)
                        1136    POP_JUMP_IF_FALSE               2 (to 1142)
                        1138    LOAD_CONST                      14: True
                        1140    STORE_FAST                      4: _var_var_5
                        1142    LOAD_FAST                       0: self
                        1144    LOAD_ATTR                       30: _flood
                        1164    LOAD_FAST                       0: self
                        1166    LOAD_ATTR                       16: flood
                        1186    COMPARE_OP                      92 (>=)
                        1190    POP_JUMP_IF_FALSE               17 (to 1226)
                        1192    LOAD_FAST                       0: self
                        1194    LOAD_ATTR                       16: flood
                        1214    LOAD_CONST                      11: 0
                        1216    COMPARE_OP                      55 (!=)
                        1220    POP_JUMP_IF_FALSE               2 (to 1226)
                        1222    LOAD_CONST                      14: True
                        1224    STORE_FAST                      4: _var_var_5
                        1226    LOAD_FAST                       0: self
                        1228    LOAD_ATTR                       32: _spamblock
                        1248    LOAD_FAST                       0: self
                        1250    LOAD_ATTR                       18: spamblock
                        1270    COMPARE_OP                      92 (>=)
                        1274    POP_JUMP_IF_FALSE               17 (to 1310)
                        1276    LOAD_FAST                       0: self
                        1278    LOAD_ATTR                       18: spamblock
                        1298    LOAD_CONST                      11: 0
                        1300    COMPARE_OP                      55 (!=)
                        1304    POP_JUMP_IF_FALSE               2 (to 1310)
                        1306    LOAD_CONST                      14: True
                        1308    STORE_FAST                      4: _var_var_5
                        1310    LOAD_FAST                       4: _var_var_5
                        1312    POP_JUMP_IF_FALSE               120 (to 1554)
                        1314    LOAD_GLOBAL                     35: NULL + print
                        1324    PUSH_NULL                       
                        1326    LOAD_CONST                      1: '__pyarmor_assert_16023__'
                        1328    LOAD_CONST                      17: ' BanAccount '   # b'\x81\xa2:\x12=\xdb\xbd\xd1\x14\xef\x03\xd4,'
                        1330    CALL                            1
                        1338    LOAD_FAST                       0: self
                        1340    LOAD_ATTR                       28: _ban
                        1360    FORMAT_VALUE                    0 (FVC_NONE)
                        1362    PUSH_NULL                       
                        1364    LOAD_CONST                      1: '__pyarmor_assert_16023__'
                        1366    LOAD_CONST                      18: '  MaxFlood '   # b'\x81\xa2X>2\xe2\x98\xde\x14\xf5\t\x80'
                        1368    CALL                            1
                        1376    LOAD_FAST                       0: self
                        1378    LOAD_ATTR                       30: _flood
                        1398    FORMAT_VALUE                    0 (FVC_NONE)
                        1400    PUSH_NULL                       
                        1402    LOAD_CONST                      1: '__pyarmor_assert_16023__'
                        1404    LOAD_CONST                      19: '  PeerFlood'   # b'\x81\xa2X#6\xff\xac\xf4\x17\xf5\x02\xc4'
                        1406    CALL                            1
                        1414    LOAD_FAST                       0: self
                        1416    LOAD_ATTR                       32: _spamblock
                        1436    FORMAT_VALUE                    0 (FVC_NONE)
                        1438    BUILD_STRING                    6
                        1440    CALL                            1
                        1448    POP_TOP                         
                        1450    LOAD_FAST                       0: self
                        1452    LOAD_ATTR                       21: _print
                        1472    CALL                            0
                        1480    POP_TOP                         
                        1482    LOAD_FAST                       0: self
                        1484    LOAD_ATTR                       22: stop_thread
                        1504    LOAD_ATTR                       25: set
                        1524    CALL                            0
                        1532    POP_TOP                         
                        1534    LOAD_GLOBAL                     27: NULL + StopProgram
                        1544    CALL                            0
                        1552    RAISE_VARARGS                   1
                        1554    LOAD_FAST                       0: self
                        1556    LOAD_ATTR                       2: history
                        1576    NOP                             
                        1578    NOP                             
                        1580    NOP                             
                        1582    JUMP_FORWARD                    20 (to 1624)
                        1584    CALL                            1
                        1592    POP_TOP                         
                        1594    RETURN_VALUE                    
                        1596    PUSH_EXC_INFO                   
                        1598    PUSH_NULL                       
                        1600    LOAD_CONST                      4: '__pyarmor_exit_16025__'
                        1602    NOP                             
                        1604    LOAD_CONST                      3: b'<COAddr>\x05\x00\x00\x1a"\x06\x00\x00\x00\x00\x00\x00\x00\x00\x00\x00\x00\x00\x00\x00'
                        1606    CALL                            1
                        1614    POP_TOP                         
                        1616    RERAISE                         0
                        1618    COPY                            3
                        1620    POP_EXCEPT                      
                        1622    RERAISE                         1
                        1624    PUSH_NULL                       
                        1626    LOAD_CONST                      4: '__pyarmor_exit_16025__'
                        1628    LOAD_CONST                      3: b'<COAddr>\x05\x00\x00\x1a"\x06\x00\x00\x00\x00\x00\x00\x00\x00\x00\x00\x00\x00\x00\x00'
                        1630    BUILD_TUPLE                     1
                        1632    CALL_FUNCTION_EX                0
                        1634    POP_TOP                         
                        1636    RETURN_VALUE                    
                    [Exception Table]
                        28 to 74 -> 1596 [0] 
                        94 to 630 -> 1596 [0] 
                        632 to 662 -> 1596 [0] 
                        664 to 700 -> 1596 [0] 
                        702 to 1010 -> 1596 [0] 
                        1012 to 1576 -> 1596 [0] 
                        1596 to 1618 -> 1618 [1] lasti
                [Code]
                    File Name: <frozen program.static_classes.stop>
                    Object Name: _print
                    Qualified Name: AutoStop._print
                    Arg Count: 1
                    Pos Only Arg Count: 0
                    KW Only Arg Count: 0
                    Stack Size: 5
                    Flags: 0x20000003 (CO_OPTIMIZED | CO_NEWLOCALS | CO_PYARMOR_OBFUSCATED)
                    [Names]
                        'print'
                        'history'
                    [Locals+Names]
                        'self'
                        '__assert_armored__'
                        '_var_var_8'
                    [Constants]
                        None
                        '__pyarmor_assert_16026__'
                        '__pyarmor_enter_16027__'
                        b'<COAddr>\x05\x00\x00\x1av\x00\x00\x00\x00\x00\x00\x00\x00\x00\x00\x00\x00\x00\x00\x00'
                        ' > Autostop is triggered, data for check:'   # b'\x81\xa2FS\x12\xef\xaa\xdd\x08\xee\x02\xd0,\xe5\xeb\xc5\x1bO\xb2\xa0\xad\xce\\\xc9\x01#\xe3X\x01\xa5\x1f\xa5<]2M\x9b\xc2\xb1-\x13\xb3'
                        ' > '
                        '__pyarmor_exit_16028__'
                    [Disassembly]
                        0       NOP                             
                        2       NOP                             
                        4       PUSH_NULL                       
                        6       LOAD_CONST                      2: '__pyarmor_enter_16027__'
                        8       LOAD_CONST                      3: b'<COAddr>\x05\x00\x00\x1av\x00\x00\x00\x00\x00\x00\x00\x00\x00\x00\x00\x00\x00\x00\x00'
                        10      BUILD_TUPLE                     1
                        12      CALL_FUNCTION_EX                0
                        14      POP_TOP                         
                        16      RESUME                          0
                        18      NOP                             
                        20      NOP                             
                        22      NOP                             
                        24      NOP                             
                        26      NOP                             
                        28      LOAD_GLOBAL                     1: NULL + print
                        38      PUSH_NULL                       
                        40      LOAD_CONST                      1: '__pyarmor_assert_16026__'
                        42      LOAD_CONST                      4: ' > Autostop is triggered, data for check:'   # b'\x81\xa2FS\x12\xef\xaa\xdd\x08\xee\x02\xd0,\xe5\xeb\xc5\x1bO\xb2\xa0\xad\xce\\\xc9\x01#\xe3X\x01\xa5\x1f\xa5<]2M\x9b\xc2\xb1-\x13\xb3'
                        44      CALL                            1
                        52      CALL                            1
                        60      POP_TOP                         
                        62      LOAD_FAST                       0: self
                        64      LOAD_ATTR                       2: history
                        84      GET_ITER                        
                        86      FOR_ITER                        16 (to 120)
                        90      STORE_FAST                      2: _var_var_8
                        92      LOAD_GLOBAL                     1: NULL + print
                        102     LOAD_CONST                      5: ' > '
                        104     LOAD_FAST                       2: _var_var_8
                        106     FORMAT_VALUE                    0 (FVC_NONE)
                        108     BUILD_STRING                    2
                        110     CALL                            1
                        118     POP_TOP                         
                        120     JUMP_BACKWARD                   18 (to 86)
                        122     END_FOR                         
                        124     LOAD_CONST                      0: None
                        126     NOP                             
                        128     NOP                             
                        130     NOP                             
                        132     JUMP_FORWARD                    19 (to 172)
                        140     POP_TOP                         
                        142     RETURN_CONST                    0: None
                        144     PUSH_EXC_INFO                   
                        146     PUSH_NULL                       
                        148     LOAD_CONST                      6: '__pyarmor_exit_16028__'
                        150     NOP                             
                        152     LOAD_CONST                      3: b'<COAddr>\x05\x00\x00\x1av\x00\x00\x00\x00\x00\x00\x00\x00\x00\x00\x00\x00\x00\x00\x00'
                        154     CALL                            1
                        162     POP_TOP                         
                        164     RERAISE                         0
                        166     COPY                            3
                        168     POP_EXCEPT                      
                        170     RERAISE                         1
                        172     PUSH_NULL                       
                        174     LOAD_CONST                      6: '__pyarmor_exit_16028__'
                        176     LOAD_CONST                      3: b'<COAddr>\x05\x00\x00\x1av\x00\x00\x00\x00\x00\x00\x00\x00\x00\x00\x00\x00\x00\x00\x00'
                        178     BUILD_TUPLE                     1
                        180     CALL_FUNCTION_EX                0
                        182     POP_TOP                         
                        184     RETURN_VALUE                    
                    [Exception Table]
                        28 to 124 -> 144 [0] 
                        144 to 166 -> 166 [1] lasti
                '__pyarmor_exit_16016__'
            [Disassembly]
                0       NOP                             
                2       LOAD_NAME                       0: __name__
                4       STORE_NAME                      1: __module__
                6       LOAD_CONST                      0: 'AutoStop'
                8       STORE_NAME                      2: __qualname__
                10      NOP                             
                12      PUSH_NULL                       
                14      LOAD_CONST                      2: '__pyarmor_enter_16015__'
                16      LOAD_CONST                      3: b'<COAddr>\x05\x00\x00"8\x00\x00\x00\x00\x00\x00\x00\x00\x00\x00\x00\x00\x00\x00\x00'
                18      BUILD_TUPLE                     1
                20      CALL_FUNCTION_EX                0
                22      POP_TOP                         
                24      RESUME                          0
                26      NOP                             
                28      NOP                             
                30      NOP                             
                32      NOP                             
                34      NOP                             
                36      LOAD_CONST                      4: None
                38      BUILD_LIST                      0
                40      LOAD_CONST                      4: None
                42      LOAD_CONST                      4: None
                44      BUILD_TUPLE                     4
                46      LOAD_CONST                      5: <CODE> __init__
                48      MAKE_FUNCTION                   1
                50      STORE_NAME                      4: __init__
                52      LOAD_CONST                      6: <CODE> count_elements
                54      MAKE_FUNCTION                   0
                56      STORE_NAME                      5: count_elements
                58      LOAD_CONST                      7: <CODE> start
                60      MAKE_FUNCTION                   0
                62      STORE_NAME                      6: start
                64      LOAD_CONST                      8: <CODE> _print
                66      MAKE_FUNCTION                   0
                68      STORE_NAME                      7: _print
                70      LOAD_CONST                      4: None
                72      NOP                             
                74      NOP                             
                76      NOP                             
                78      JUMP_FORWARD                    19 (to 118)
                86      POP_TOP                         
                88      RETURN_CONST                    4: None
                90      PUSH_EXC_INFO                   
                92      PUSH_NULL                       
                94      LOAD_CONST                      9: '__pyarmor_exit_16016__'
                96      NOP                             
                98      LOAD_CONST                      3: b'<COAddr>\x05\x00\x00"8\x00\x00\x00\x00\x00\x00\x00\x00\x00\x00\x00\x00\x00\x00\x00'
                100     CALL                            1
                108     POP_TOP                         
                110     RERAISE                         0
                112     COPY                            3
                114     POP_EXCEPT                      
                116     RERAISE                         1
                118     PUSH_NULL                       
                120     LOAD_CONST                      9: '__pyarmor_exit_16016__'
                122     LOAD_CONST                      3: b'<COAddr>\x05\x00\x00"8\x00\x00\x00\x00\x00\x00\x00\x00\x00\x00\x00\x00\x00\x00\x00'
                124     BUILD_TUPLE                     1
                126     CALL_FUNCTION_EX                0
                128     POP_TOP                         
                130     RETURN_VALUE                    
            [Exception Table]
                36 to 70 -> 90 [0] 
                90 to 112 -> 112 [1] lasti
        'AutoStop'
        '__pyarmor_exit_15980__'
        None
    [Disassembly]
        0       NOP                             
        2       NOP                             
        4       PUSH_NULL                       
        6       LOAD_CONST                      1: '__pyarmor_enter_15979__'
        8       LOAD_CONST                      2: b'<COAddr>\x07\x00\x00\x1a\xa2\x00\x00\x00\x00\x00\x00\x00\x00\x00\x00\x00\x00\x00\x00\x00'
        10      BUILD_TUPLE                     1
        12      CALL_FUNCTION_EX                0
        14      POP_TOP                         
        16      RESUME                          0
        18      NOP                             
        20      NOP                             
        22      NOP                             
        24      NOP                             
        26      NOP                             
        28      LOAD_CONST                      3: 0
        30      LOAD_CONST                      4: ('StopProgram',)
        32      IMPORT_NAME                     1: multithon.errors
        34      IMPORT_FROM                     2: StopProgram
        36      STORE_NAME                      2: StopProgram
        38      POP_TOP                         
        40      PUSH_NULL                       
        42      LOAD_BUILD_CLASS                
        44      LOAD_CONST                      5: <CODE> PeerFlood
        46      MAKE_FUNCTION                   0
        48      LOAD_CONST                      6: 'PeerFlood'
        50      LOAD_NAME                       3: Exception
        52      CALL                            3
        60      STORE_NAME                      4: PeerFlood
        62      PUSH_NULL                       
        64      LOAD_BUILD_CLASS                
        66      LOAD_CONST                      7: <CODE> MaxFlood
        68      MAKE_FUNCTION                   0
        70      LOAD_CONST                      8: 'MaxFlood'
        72      LOAD_NAME                       3: Exception
        74      CALL                            3
        82      STORE_NAME                      5: MaxFlood
        84      PUSH_NULL                       
        86      LOAD_BUILD_CLASS                
        88      LOAD_CONST                      9: <CODE> BanAccount
        90      MAKE_FUNCTION                   0
        92      LOAD_CONST                      10: 'BanAccount'
        94      LOAD_NAME                       3: Exception
        96      CALL                            3
        104     STORE_NAME                      6: BanAccount
        106     PUSH_NULL                       
        108     LOAD_BUILD_CLASS                
        110     LOAD_CONST                      11: <CODE> StopAccount
        112     MAKE_FUNCTION                   0
        114     LOAD_CONST                      12: 'StopAccount'
        116     LOAD_NAME                       3: Exception
        118     CALL                            3
        126     STORE_NAME                      7: StopAccount
        128     PUSH_NULL                       
        130     LOAD_BUILD_CLASS                
        132     LOAD_CONST                      13: <CODE> AutoStopCheck
        134     MAKE_FUNCTION                   0
        136     LOAD_CONST                      14: 'AutoStopCheck'
        138     CALL                            2
        146     STORE_NAME                      8: AutoStopCheck
        148     PUSH_NULL                       
        150     LOAD_BUILD_CLASS                
        152     LOAD_CONST                      15: <CODE> AutoStop
        154     MAKE_FUNCTION                   0
        156     LOAD_CONST                      16: 'AutoStop'
        158     CALL                            2
        166     STORE_NAME                      9: AutoStop
        168     LOAD_CONST                      18: None
        170     NOP                             
        172     NOP                             
        174     NOP                             
        176     JUMP_FORWARD                    19 (to 216)
        184     POP_TOP                         
        186     RETURN_CONST                    18: None
        188     PUSH_EXC_INFO                   
        190     PUSH_NULL                       
        192     LOAD_CONST                      17: '__pyarmor_exit_15980__'
        194     NOP                             
        196     LOAD_CONST                      2: b'<COAddr>\x07\x00\x00\x1a\xa2\x00\x00\x00\x00\x00\x00\x00\x00\x00\x00\x00\x00\x00\x00\x00'
        198     CALL                            1
        206     POP_TOP                         
        208     RERAISE                         0
        210     COPY                            3
        212     POP_EXCEPT                      
        214     RERAISE                         1
        216     PUSH_NULL                       
        218     LOAD_CONST                      17: '__pyarmor_exit_15980__'
        220     LOAD_CONST                      2: b'<COAddr>\x07\x00\x00\x1a\xa2\x00\x00\x00\x00\x00\x00\x00\x00\x00\x00\x00\x00\x00\x00\x00'
        222     BUILD_TUPLE                     1
        224     CALL_FUNCTION_EX                0
        226     POP_TOP                         
        228     RETURN_VALUE                    
    [Exception Table]
        28 to 168 -> 188 [0] 
        188 to 210 -> 210 [1] lasti
