#decoded by lolz.live/mrpenny / t.me/zeus_jackpot
# ================================
# Примечания по Pyarmor:
# - Байт-код и объекты кода Pyarmor соответствуют стандартному Python, но присутствуют специальные вызовы функций среды выполнения (runtime) Pyarmor.
# - Вызовы строк — это не ошибки, а маркеры, которые обрабатываются Pyarmor во время выполнения.
#
# Руководство по декомпиляции (без среды выполнения):
# 1. Игнорируйте зашифрованные байты после `#`; используйте только строку до `#`.
# 2. Удалите "__pyarmor_enter_xxx__"(b"<COAddr>...") и "__pyarmor_leave_xxx__"(b"<COAddr>...") (пролог/эпилог).
# 3. "__pyarmor_assert_xxx__"(A) не является настоящим оператором assert.
#    - Если A — это имя или читаемая строка: замените на A.
#    - Если A — это (X, "Y"): замените на X.Y.
#    - Если A — это (X, "Y", Z): замените на X.Y = Z.
#    - В противном случае: выберите наиболее подходящую/логичную замену.
# 4. "__pyarmor_bcc_xxx__"(...) указывает на машинный (нативный) код; тело функции недоступно. Добавьте комментарий.
# ================================

[Code]
    File Name: <frozen program.static_classes.version_control>
    Object Name: <module>
    Qualified Name: <module>
    Arg Count: 0
    Pos Only Arg Count: 0
    KW Only Arg Count: 0
    Stack Size: 5
    Flags: 0x20000000 (CO_PYARMOR_OBFUSCATED)
    [Names]
        '__assert_armored__'
        'program.static_classes'
        'Logs'
        'VersionControl'
    [Locals+Names]
    [Constants]
        '__pyarmor_assert_16029__'
        '__pyarmor_enter_16030__'
        b'<COAddr>\x05\x00\x00\x1a4\x00\x00\x00\x00\x00\x00\x00\x00\x00\x00\x00\x00\x00\x00\x00'
        0
        (
            'Logs'
        )
        [Code]
            File Name: <frozen program.static_classes.version_control>
            Object Name: VersionControl
            Qualified Name: VersionControl
            Arg Count: 0
            Pos Only Arg Count: 0
            KW Only Arg Count: 0
            Stack Size: 5
            Flags: 0x20000000 (CO_PYARMOR_OBFUSCATED)
            [Names]
                '__name__'
                '__module__'
                '__qualname__'
                '__assert_armored__'
                '__init__'
                'check'
            [Locals+Names]
            [Constants]
                'VersionControl'
                '__pyarmor_assert_16032__'
                '__pyarmor_enter_16033__'
                b'<COAddr>\x07\x00\x00"(\x00\x00\x00\x00\x00\x00\x00\x00\x00\x00\x00\x00\x00\x00\x00'
                None
                [Code]
                    File Name: <frozen program.static_classes.version_control>
                    Object Name: __init__
                    Qualified Name: VersionControl.__init__
                    Arg Count: 4
                    Pos Only Arg Count: 0
                    KW Only Arg Count: 0
                    Stack Size: 6
                    Flags: 0x20000003 (CO_OPTIMIZED | CO_NEWLOCALS | CO_PYARMOR_OBFUSCATED)
                    [Names]
                        'config'
                        'lang'
                        'log'
                        'account'
                        'app_id'
                        'version'
                        'android'
                        'android_x'
                        'desktop'
                    [Locals+Names]
                        'self'
                        'config'
                        'lang'
                        'log'
                        '__assert_armored__'
                    [Constants]
                        None
                        '__pyarmor_assert_16035__'
                        '__pyarmor_enter_16036__'
                        b'<COAddr>\x07\x00\x00\x1a\x1c\n\x00\x00\x00\x00\x00\x00\x00\x00\x00\x00\x00\x00\x00\x00'
                        '11.14.1 (61082)'   # b'\x81\xb3I]b\xae\xf0\x83[\xb2[\x91<\xb4\xaa\xcc'
                        '11.14.1 (61089)'   # b'\x81\xb3I]b\xae\xf0\x83[\xb2[\x91<\xb4\xa1\xcc'
                        '11.14.0 (61022)'   # b'\x81\xb3I]b\xae\xf0\x82[\xb2[\x91<\xbe\xaa\xcc'
                        '11.14.0 (61029)'   # b'\x81\xb3I]b\xae\xf0\x82[\xb2[\x91<\xbe\xa1\xcc'
                        '11.13.4 (60862)'   # b'\x81\xb3I]b\xa9\xf0\x86[\xb2[\x904\xba\xaa\xcc'
                        '11.13.4 (60869)'   # b'\x81\xb3I]b\xa9\xf0\x86[\xb2[\x904\xba\xa1\xcc'
                        '11.13.3 (60812)'   # b'\x81\xb3I]b\xa9\xf0\x81[\xb2[\x904\xbd\xaa\xcc'
                        '11.13.3 (60819)'   # b'\x81\xb3I]b\xa9\xf0\x81[\xb2[\x904\xbd\xa1\xcc'
                        '11.13.2 (60602)'   # b'\x81\xb3I]b\xa9\xf0\x80[\xb2[\x90:\xbc\xaa\xcc'
                        '11.13.2 (60609)'   # b'\x81\xb3I]b\xa9\xf0\x80[\xb2[\x90:\xbc\xa1\xcc'
                        '11.13.1 (60562)'   # b'\x81\xb3I]b\xa9\xf0\x83[\xb2[\x909\xba\xaa\xcc'
                        '11.13.1 (60569)'   # b'\x81\xb3I]b\xa9\xf0\x83[\xb2[\x909\xba\xa1\xcc'
                        '11.13.0 (60472)'   # b'\x81\xb3I]b\xa9\xf0\x82[\xb2[\x908\xbb\xaa\xcc'
                        '11.13.0 (60479)'   # b'\x81\xb3I]b\xa9\xf0\x82[\xb2[\x908\xbb\xa1\xcc'
                        '11.12.0 (59972)'   # b'\x81\xb3I]b\xa8\xf0\x82[\xb2X\x995\xbb\xaa\xcc'
                        '11.12.0 (59979)'   # b'\x81\xb3I]b\xa8\xf0\x82[\xb2X\x995\xbb\xa1\xcc'
                        '11.11.1 (59302)'   # b'\x81\xb3I]b\xab\xf0\x83[\xb2X\x99?\xbc\xaa\xcc'
                        '11.11.1 (59309)'   # b'\x81\xb3I]b\xab\xf0\x83[\xb2X\x99?\xbc\xa1\xcc'
                        '11.11.0 (59272)'   # b'\x81\xb3I]b\xab\xf0\x82[\xb2X\x99>\xbb\xaa\xcc'
                        '11.11.0 (59279)'   # b'\x81\xb3I]b\xab\xf0\x82[\xb2X\x99>\xbb\xa1\xcc'
                        '11.9.2 (59012)'   # b'\x81\xb3I]j\xb4\xec\x92S\xafT\x90=\xbe\xb1'
                        '11.9.2 (59019)'   # b'\x81\xb3I]j\xb4\xec\x92S\xafT\x90=\xb5\xb1'
                        '11.9.1 (59002)'   # b'\x81\xb3I]j\xb4\xef\x92S\xafT\x90<\xbe\xb1'
                        '11.9.1 (59009)'   # b'\x81\xb3I]j\xb4\xef\x92S\xafT\x90<\xb5\xb1'
                        '11.9.0 (58371)'   # b'\x81\xb3I]j\xb4\xee\x92S\xafU\x93;\xbd\xb1'
                        '11.9.0 (58372)'   # b'\x81\xb3I]j\xb4\xee\x92S\xafU\x93;\xbe\xb1'
                        '11.9.0 (58379)'   # b'\x81\xb3I]j\xb4\xee\x92S\xafU\x93;\xb5\xb1'
                        '11.8.3 (57992)'   # b'\x81\xb3I]k\xb4\xed\x92S\xafZ\x995\xbe\xb1'
                        '11.8.3 (57999)'   # b'\x81\xb3I]k\xb4\xed\x92S\xafZ\x995\xb5\xb1'
                        '11.8.2 (57841)'   # b'\x81\xb3I]k\xb4\xec\x92S\xafZ\x988\xbd\xb1'
                        '11.8.2 (57842)'   # b'\x81\xb3I]k\xb4\xec\x92S\xafZ\x988\xbe\xb1'
                        '11.8.2 (57849)'   # b'\x81\xb3I]k\xb4\xec\x92S\xafZ\x988\xb5\xb1'
                        '11.8.1 (57759)'   # b'\x81\xb3I]k\xb4\xef\x92S\xafZ\x979\xb5\xb1'
                        '11.8.0 (57731)'   # b'\x81\xb3I]k\xb4\xee\x92S\xafZ\x97?\xbd\xb1'
                        '11.8.0 (57732)'   # b'\x81\xb3I]k\xb4\xee\x92S\xafZ\x97?\xbe\xb1'
                        '11.8.0 (57719)'   # b'\x81\xb3I]k\xb4\xee\x92S\xafZ\x97=\xb5\xb1'
                        '11.7.4 (56982)'   # b'\x81\xb3I]d\xb4\xea\x92S\xaf[\x994\xbe\xb1'
                        '11.7.4 (56989)'   # b'\x81\xb3I]d\xb4\xea\x92S\xaf[\x994\xb5\xb1'
                        '11.7.3 (56962)'   # b'\x81\xb3I]d\xb4\xed\x92S\xaf[\x99:\xbe\xb1'
                        '11.7.3 (56969)'   # b'\x81\xb3I]d\xb4\xed\x92S\xaf[\x99:\xb5\xb1'
                        '11.7.0 (56631)'   # b'\x81\xb3I]d\xb4\xee\x92S\xaf[\x96?\xbd\xb1'
                        '11.7.0 (56632)'   # b'\x81\xb3I]d\xb4\xee\x92S\xaf[\x96?\xbe\xb1'
                        '11.7.0 (56639)'   # b'\x81\xb3I]d\xb4\xee\x92S\xaf[\x96?\xb5\xb1'
                        '11.6.2 (56151)'   # b'\x81\xb3I]e\xb4\xec\x92S\xaf[\x919\xbd\xb1'
                        '11.6.2 (56152)'   # b'\x81\xb3I]e\xb4\xec\x92S\xaf[\x919\xbe\xb1'
                        '11.6.2 (56159)'   # b'\x81\xb3I]e\xb4\xec\x92S\xaf[\x919\xb5\xb1'
                        '11.6.1 (55851)'   # b'\x81\xb3I]e\xb4\xef\x92S\xafX\x989\xbd\xb1'
                        '11.6.1 (55852)'   # b'\x81\xb3I]e\xb4\xef\x92S\xafX\x989\xbe\xb1'
                        '11.6.1 (55859)'   # b'\x81\xb3I]e\xb4\xef\x92S\xafX\x989\xb5\xb1'
                        '11.5.5 (55311)'   # b'\x81\xb3I]f\xb4\xeb\x92S\xafX\x93=\xbd\xb1'
                        '11.5.5 (55312)'   # b'\x81\xb3I]f\xb4\xeb\x92S\xafX\x93=\xbe\xb1'
                        '11.5.5 (55319)'   # b'\x81\xb3I]f\xb4\xeb\x92S\xafX\x93=\xb5\xb1'
                        '11.5.4 (55282)'   # b'\x81\xb3I]f\xb4\xea\x92S\xafX\x924\xbe\xb1'
                        '11.5.3 (55112)'   # b'\x81\xb3I]f\xb4\xed\x92S\xafX\x91=\xbe\xb1'
                        '11.5.3 (55119)'   # b'\x81\xb3I]f\xb4\xed\x92S\xafX\x91=\xb5\xb1'
                        '11.5.2 (55092)'   # b'\x81\xb3I]f\xb4\xec\x92S\xafX\x905\xbe\xb1'
                        '11.5.2 (55099)'   # b'\x81\xb3I]f\xb4\xec\x92S\xafX\x905\xb5\xb1'
                        '11.5.1 (55062)'   # b'\x81\xb3I]f\xb4\xef\x92S\xafX\x90:\xbe\xb1'
                        '11.5.1 (55069)'   # b'\x81\xb3I]f\xb4\xef\x92S\xafX\x90:\xb5\xb1'
                        '11.4.3 (54731)'   # b'\x81\xb3I]g\xb4\xed\x92S\xafY\x97?\xbd\xb1'
                        '11.4.3 (54732)'   # b'\x81\xb3I]g\xb4\xed\x92S\xafY\x97?\xbe\xb1'
                        '11.4.3 (54739)'   # b'\x81\xb3I]g\xb4\xed\x92S\xafY\x97?\xb5\xb1'
                        '11.4.2 (54691)'   # b'\x81\xb3I]g\xb4\xec\x92S\xafY\x965\xbd\xb1'
                        '11.4.2 (54692)'   # b'\x81\xb3I]g\xb4\xec\x92S\xafY\x965\xbe\xb1'
                        '11.4.2 (54699)'   # b'\x81\xb3I]g\xb4\xec\x92S\xafY\x965\xb5\xb1'
                        '11.4.1 (54591)'   # b'\x81\xb3I]g\xb4\xef\x92S\xafY\x955\xbd\xb1'
                        '11.4.1 (54592)'   # b'\x81\xb3I]g\xb4\xef\x92S\xafY\x955\xbe\xb1'
                        '11.4.1 (54599)'   # b'\x81\xb3I]g\xb4\xef\x92S\xafY\x955\xb5\xb1'
                        '11.4.0 (54451)'   # b'\x81\xb3I]g\xb4\xee\x92S\xafY\x949\xbd\xb1'
                        '11.4.0 (54452)'   # b'\x81\xb3I]g\xb4\xee\x92S\xafY\x949\xbe\xb1'
                        '11.4.0 (54459)'   # b'\x81\xb3I]g\xb4\xee\x92S\xafY\x949\xb5\xb1'
                        '11.3.4 (53971)'   # b'\x81\xb3I]`\xb4\xea\x92S\xaf^\x99;\xbd\xb1'
                        '11.3.4 (53972)'   # b'\x81\xb3I]`\xb4\xea\x92S\xaf^\x99;\xbe\xb1'
                        '11.3.4 (53979)'   # b'\x81\xb3I]`\xb4\xea\x92S\xaf^\x99;\xb5\xb1'
                        '11.3.3 (53961)'   # b'\x81\xb3I]`\xb4\xed\x92S\xaf^\x99:\xbd\xb1'
                        '11.3.3 (53962)'   # b'\x81\xb3I]`\xb4\xed\x92S\xaf^\x99:\xbe\xb1'
                        '11.3.2 (53931)'   # b'\x81\xb3I]`\xb4\xec\x92S\xaf^\x99?\xbd\xb1'
                        '11.3.2 (53932)'   # b'\x81\xb3I]`\xb4\xec\x92S\xaf^\x99?\xbe\xb1'
                        '11.3.2 (53939)'   # b'\x81\xb3I]`\xb4\xec\x92S\xaf^\x99?\xb5\xb1'
                        '11.3.1 (53911)'   # b'\x81\xb3I]`\xb4\xef\x92S\xaf^\x99=\xbd\xb1'
                        '11.3.1 (53912)'   # b'\x81\xb3I]`\xb4\xef\x92S\xaf^\x99=\xbe\xb1'
                        '11.3.1 (53919)'   # b'\x81\xb3I]`\xb4\xef\x92S\xaf^\x99=\xb5\xb1'
                        '11.3.0 (53861)'   # b'\x81\xb3I]`\xb4\xee\x92S\xaf^\x98:\xbd\xb1'
                        '11.3.0 (53862)'   # b'\x81\xb3I]`\xb4\xee\x92S\xaf^\x98:\xbe\xb1'
                        '11.3.0 (53869)'   # b'\x81\xb3I]`\xb4\xee\x92S\xaf^\x98:\xb5\xb1'
                        '11.2.3 (53351)'   # b'\x81\xb3I]a\xb4\xed\x92S\xaf^\x939\xbd\xb1'
                        '11.2.3 (53352)'   # b'\x81\xb3I]a\xb4\xed\x92S\xaf^\x939\xbe\xb1'
                        '11.2.3 (53359)'   # b'\x81\xb3I]a\xb4\xed\x92S\xaf^\x939\xb5\xb1'
                        '11.2.2 (53291)'   # b'\x81\xb3I]a\xb4\xec\x92S\xaf^\x925\xbd\xb1'
                        '11.2.2 (53292)'   # b'\x81\xb3I]a\xb4\xec\x92S\xaf^\x925\xbe\xb1'
                        '11.2.2 (53299)'   # b'\x81\xb3I]a\xb4\xec\x92S\xaf^\x925\xb5\xb1'
                        '11.2.1 (53159)'   # b'\x81\xb3I]a\xb4\xef\x92S\xaf^\x919\xb5\xb1'
                        '11.2.0 (52999)'   # b'\x81\xb3I]a\xb4\xee\x92S\xaf_\x995\xb5\xb1'
                        '11.2.0 (52992)'   # b'\x81\xb3I]a\xb4\xee\x92S\xaf_\x995\xbe\xb1'
                        '11.1.3 (52442)'   # b'\x81\xb3I]b\xb4\xed\x92S\xaf_\x948\xbe\xb1'
                        '11.1.1 (52352)'   # b'\x81\xb3I]b\xb4\xef\x92S\xaf_\x939\xbe\xb1'
                        '11.1.0 (52292)'   # b'\x81\xb3I]b\xb4\xee\x92S\xaf_\x925\xbe\xb1'
                        '11.0.1 (51762)'   # b'\x81\xb3I]c\xb4\xef\x92S\xaf\\\x97:\xbe\xb1'
                        '11.0.1 (51779)'   # b'\x81\xb3I]c\xb4\xef\x92S\xaf\\\x97;\xb5\xb1'
                        '11.0.0 (51431)'   # b'\x81\xb3I]c\xb4\xee\x92S\xaf\\\x94?\xbd\xb1'
                        '11.0.0 (51432)'   # b'\x81\xb3I]c\xb4\xee\x92S\xaf\\\x94?\xbe\xb1'
                        '11.0.0 (51439)'   # b'\x81\xb3I]c\xb4\xee\x92S\xaf\\\x94?\xb5\xb1'
                        '0.27.10.1752-arm64-v8a'   # b'\x81\xb2VAd\xb4\xef\x82U\xabZ\x95>\xa1\xf9\x97\x02\x0b\xef\xea\xbc\x93O'
                        '0.27.10.1752-armeabi-v7a'   # b'\x81\xb2VAd\xb4\xef\x82U\xabZ\x95>\xa1\xf9\x97\x02X\xba\xa5\xa3\x86X\x9b\x04'
                        '0.26.11.1734-arm64-v8a'   # b'\x81\xb2VAe\xb4\xef\x83U\xabZ\x938\xa1\xf9\x97\x02\x0b\xef\xea\xbc\x93O'
                        '0.26.11.1734-armeabi-v7a'   # b'\x81\xb2VAe\xb4\xef\x83U\xabZ\x938\xa1\xf9\x97\x02X\xba\xa5\xa3\x86X\x9b\x04'
                        '6.0.2 x64'   # b'\x81\xb4VC}\xa8\xfe\xcaM\xae'
                        '6.0.1 x64'   # b'\x81\xb4VC}\xab\xfe\xcaM\xae'
                        '6.0.0 x64'   # b'\x81\xb4VC}\xaa\xfe\xcaM\xae'
                        '5.16.6 x64'   # b'\x81\xb7VBe\xb4\xe8\x92\x03\xacY'
                        '5.16.5 x64'   # b'\x81\xb7VBe\xb4\xeb\x92\x03\xacY'
                        '5.16.4 x64'   # b'\x81\xb7VBe\xb4\xea\x92\x03\xacY'
                        '5.16.3 x64'   # b'\x81\xb7VBe\xb4\xed\x92\x03\xacY'
                        '5.16.2 x64'   # b'\x81\xb7VBe\xb4\xec\x92\x03\xacY'
                        '5.16.1 x64'   # b'\x81\xb7VBe\xb4\xef\x92\x03\xacY'
                        '5.16.0 x64'   # b'\x81\xb7VBe\xb4\xee\x92\x03\xacY'
                        '5.15.4 x64'   # b'\x81\xb7VBf\xb4\xea\x92\x03\xacY'
                        '5.15.3 x64'   # b'\x81\xb7VBf\xb4\xed\x92\x03\xacY'
                        '5.15.2 x64'   # b'\x81\xb7VBf\xb4\xec\x92\x03\xacY'
                        '5.15.1 x64'   # b'\x81\xb7VBf\xb4\xef\x92\x03\xacY'
                        '5.15.0 x64'   # b'\x81\xb7VBf\xb4\xee\x92\x03\xacY'
                        '5.14.3 x64'   # b'\x81\xb7VBg\xb4\xed\x92\x03\xacY'
                        '5.14.2 x64'   # b'\x81\xb7VBg\xb4\xec\x92\x03\xacY'
                        '5.14.1 x64'   # b'\x81\xb7VBg\xb4\xef\x92\x03\xacY'
                        '5.14.0 x64'   # b'\x81\xb7VBg\xb4\xee\x92\x03\xacY'
                        '5.13.1 x64'   # b'\x81\xb7VB`\xb4\xef\x92\x03\xacY'
                        '5.13.0 x64'   # b'\x81\xb7VB`\xb4\xee\x92\x03\xacY'
                        '5.12.3 x64'   # b'\x81\xb7VBa\xb4\xed\x92\x03\xacY'
                        '5.12.2 x64'   # b'\x81\xb7VBa\xb4\xec\x92\x03\xacY'
                        '5.12.1 x64'   # b'\x81\xb7VBa\xb4\xef\x92\x03\xacY'
                        '5.12.0 x64'   # b'\x81\xb7VBa\xb4\xee\x92\x03\xacY'
                        '5.11.1 x64'   # b'\x81\xb7VBb\xb4\xef\x92\x03\xacY'
                        '5.10.7 x64'   # b'\x81\xb7VBc\xb4\xe9\x92\x03\xacY'
                        '5.10.6 x64'   # b'\x81\xb7VBc\xb4\xe8\x92\x03\xacY'
                        '5.10.5 x64'   # b'\x81\xb7VBc\xb4\xeb\x92\x03\xacY'
                        '5.10.4 x64'   # b'\x81\xb7VBc\xb4\xea\x92\x03\xacY'
                        '5.10.3 x64'   # b'\x81\xb7VBc\xb4\xed\x92\x03\xacY'
                        '5.10.2 x64'   # b'\x81\xb7VBc\xb4\xec\x92\x03\xacY'
                        '5.10.1 x64'   # b'\x81\xb7VBc\xb4\xef\x92\x03\xacY'
                        '5.10.0 x64'   # b'\x81\xb7VBc\xb4\xee\x92\x03\xacY'
                        '5.9.0 x64'   # b'\x81\xb7VJ}\xaa\xfe\xcaM\xae'
                        '5.8.3 x64'   # b'\x81\xb7VK}\xa9\xfe\xcaM\xae'
                        '5.8.2 x64'   # b'\x81\xb7VK}\xa8\xfe\xcaM\xae'
                        '5.8.1 x64'   # b'\x81\xb7VK}\xab\xfe\xcaM\xae'
                        '5.8.0 x64'   # b'\x81\xb7VK}\xaa\xfe\xcaM\xae'
                        '5.7.2 x64'   # b'\x81\xb7VD}\xa8\xfe\xcaM\xae'
                        '5.7.1 x64'   # b'\x81\xb7VD}\xab\xfe\xcaM\xae'
                        '5.7.0 x64'   # b'\x81\xb7VD}\xaa\xfe\xcaM\xae'
                        '5.6.4 x64'   # b'\x81\xb7VE}\xae\xfe\xcaM\xae'
                        '5.6.3 x64'   # b'\x81\xb7VE}\xa9\xfe\xcaM\xae'
                        '5.6.2 x64'   # b'\x81\xb7VE}\xa8\xfe\xcaM\xae'
                        '5.6.1 x64'   # b'\x81\xb7VE}\xab\xfe\xcaM\xae'
                        '5.6.0 x64'   # b'\x81\xb7VE}\xaa\xfe\xcaM\xae'
                        '__pyarmor_exit_16037__'
                    [Disassembly]
                        0       NOP                             
                        2       NOP                             
                        4       PUSH_NULL                       
                        6       LOAD_CONST                      2: '__pyarmor_enter_16036__'
                        8       LOAD_CONST                      3: b'<COAddr>\x07\x00\x00\x1a\x1c\n\x00\x00\x00\x00\x00\x00\x00\x00\x00\x00\x00\x00\x00\x00'
                        10      BUILD_TUPLE                     1
                        12      CALL_FUNCTION_EX                0
                        14      POP_TOP                         
                        16      RESUME                          0
                        18      NOP                             
                        20      NOP                             
                        22      NOP                             
                        24      NOP                             
                        26      NOP                             
                        28      LOAD_FAST                       1: config
                        30      LOAD_FAST                       0: self
                        32      STORE_ATTR                      0: config
                        42      LOAD_FAST                       2: lang
                        44      LOAD_FAST                       0: self
                        46      STORE_ATTR                      1: lang
                        56      LOAD_FAST                       3: log
                        58      LOAD_FAST                       0: self
                        60      STORE_ATTR                      2: log
                        70      LOAD_CONST                      0: None
                        72      LOAD_FAST                       0: self
                        74      STORE_ATTR                      3: account
                        84      LOAD_CONST                      0: None
                        86      LOAD_FAST                       0: self
                        88      STORE_ATTR                      4: app_id
                        98      LOAD_CONST                      0: None
                        100     LOAD_FAST                       0: self
                        102     STORE_ATTR                      5: version
                        112     BUILD_LIST                      0
                        114     PUSH_NULL                       
                        116     LOAD_CONST                      1: '__pyarmor_assert_16035__'
                        118     LOAD_CONST                      4: '11.14.1 (61082)'   # b'\x81\xb3I]b\xae\xf0\x83[\xb2[\x91<\xb4\xaa\xcc'
                        120     CALL                            1
                        128     LIST_APPEND                     1
                        130     PUSH_NULL                       
                        132     LOAD_CONST                      1: '__pyarmor_assert_16035__'
                        134     LOAD_CONST                      5: '11.14.1 (61089)'   # b'\x81\xb3I]b\xae\xf0\x83[\xb2[\x91<\xb4\xa1\xcc'
                        136     CALL                            1
                        144     LIST_APPEND                     1
                        146     PUSH_NULL                       
                        148     LOAD_CONST                      1: '__pyarmor_assert_16035__'
                        150     LOAD_CONST                      6: '11.14.0 (61022)'   # b'\x81\xb3I]b\xae\xf0\x82[\xb2[\x91<\xbe\xaa\xcc'
                        152     CALL                            1
                        160     LIST_APPEND                     1
                        162     PUSH_NULL                       
                        164     LOAD_CONST                      1: '__pyarmor_assert_16035__'
                        166     LOAD_CONST                      7: '11.14.0 (61029)'   # b'\x81\xb3I]b\xae\xf0\x82[\xb2[\x91<\xbe\xa1\xcc'
                        168     CALL                            1
                        176     LIST_APPEND                     1
                        178     PUSH_NULL                       
                        180     LOAD_CONST                      1: '__pyarmor_assert_16035__'
                        182     LOAD_CONST                      8: '11.13.4 (60862)'   # b'\x81\xb3I]b\xa9\xf0\x86[\xb2[\x904\xba\xaa\xcc'
                        184     CALL                            1
                        192     LIST_APPEND                     1
                        194     PUSH_NULL                       
                        196     LOAD_CONST                      1: '__pyarmor_assert_16035__'
                        198     LOAD_CONST                      9: '11.13.4 (60869)'   # b'\x81\xb3I]b\xa9\xf0\x86[\xb2[\x904\xba\xa1\xcc'
                        200     CALL                            1
                        208     LIST_APPEND                     1
                        210     PUSH_NULL                       
                        212     LOAD_CONST                      1: '__pyarmor_assert_16035__'
                        214     LOAD_CONST                      10: '11.13.3 (60812)'   # b'\x81\xb3I]b\xa9\xf0\x81[\xb2[\x904\xbd\xaa\xcc'
                        216     CALL                            1
                        224     LIST_APPEND                     1
                        226     PUSH_NULL                       
                        228     LOAD_CONST                      1: '__pyarmor_assert_16035__'
                        230     LOAD_CONST                      11: '11.13.3 (60819)'   # b'\x81\xb3I]b\xa9\xf0\x81[\xb2[\x904\xbd\xa1\xcc'
                        232     CALL                            1
                        240     LIST_APPEND                     1
                        242     PUSH_NULL                       
                        244     LOAD_CONST                      1: '__pyarmor_assert_16035__'
                        246     LOAD_CONST                      12: '11.13.2 (60602)'   # b'\x81\xb3I]b\xa9\xf0\x80[\xb2[\x90:\xbc\xaa\xcc'
                        248     CALL                            1
                        256     LIST_APPEND                     1
                        258     PUSH_NULL                       
                        260     LOAD_CONST                      1: '__pyarmor_assert_16035__'
                        262     LOAD_CONST                      13: '11.13.2 (60609)'   # b'\x81\xb3I]b\xa9\xf0\x80[\xb2[\x90:\xbc\xa1\xcc'
                        264     CALL                            1
                        272     LIST_APPEND                     1
                        274     PUSH_NULL                       
                        276     LOAD_CONST                      1: '__pyarmor_assert_16035__'
                        278     LOAD_CONST                      14: '11.13.1 (60562)'   # b'\x81\xb3I]b\xa9\xf0\x83[\xb2[\x909\xba\xaa\xcc'
                        280     CALL                            1
                        288     LIST_APPEND                     1
                        290     PUSH_NULL                       
                        292     LOAD_CONST                      1: '__pyarmor_assert_16035__'
                        294     LOAD_CONST                      15: '11.13.1 (60569)'   # b'\x81\xb3I]b\xa9\xf0\x83[\xb2[\x909\xba\xa1\xcc'
                        296     CALL                            1
                        304     LIST_APPEND                     1
                        306     PUSH_NULL                       
                        308     LOAD_CONST                      1: '__pyarmor_assert_16035__'
                        310     LOAD_CONST                      16: '11.13.0 (60472)'   # b'\x81\xb3I]b\xa9\xf0\x82[\xb2[\x908\xbb\xaa\xcc'
                        312     CALL                            1
                        320     LIST_APPEND                     1
                        322     PUSH_NULL                       
                        324     LOAD_CONST                      1: '__pyarmor_assert_16035__'
                        326     LOAD_CONST                      17: '11.13.0 (60479)'   # b'\x81\xb3I]b\xa9\xf0\x82[\xb2[\x908\xbb\xa1\xcc'
                        328     CALL                            1
                        336     LIST_APPEND                     1
                        338     PUSH_NULL                       
                        340     LOAD_CONST                      1: '__pyarmor_assert_16035__'
                        342     LOAD_CONST                      18: '11.12.0 (59972)'   # b'\x81\xb3I]b\xa8\xf0\x82[\xb2X\x995\xbb\xaa\xcc'
                        344     CALL                            1
                        352     LIST_APPEND                     1
                        354     PUSH_NULL                       
                        356     LOAD_CONST                      1: '__pyarmor_assert_16035__'
                        358     LOAD_CONST                      19: '11.12.0 (59979)'   # b'\x81\xb3I]b\xa8\xf0\x82[\xb2X\x995\xbb\xa1\xcc'
                        360     CALL                            1
                        368     LIST_APPEND                     1
                        370     PUSH_NULL                       
                        372     LOAD_CONST                      1: '__pyarmor_assert_16035__'
                        374     LOAD_CONST                      20: '11.11.1 (59302)'   # b'\x81\xb3I]b\xab\xf0\x83[\xb2X\x99?\xbc\xaa\xcc'
                        376     CALL                            1
                        384     LIST_APPEND                     1
                        386     PUSH_NULL                       
                        388     LOAD_CONST                      1: '__pyarmor_assert_16035__'
                        390     LOAD_CONST                      21: '11.11.1 (59309)'   # b'\x81\xb3I]b\xab\xf0\x83[\xb2X\x99?\xbc\xa1\xcc'
                        392     CALL                            1
                        400     LIST_APPEND                     1
                        402     PUSH_NULL                       
                        404     LOAD_CONST                      1: '__pyarmor_assert_16035__'
                        406     LOAD_CONST                      22: '11.11.0 (59272)'   # b'\x81\xb3I]b\xab\xf0\x82[\xb2X\x99>\xbb\xaa\xcc'
                        408     CALL                            1
                        416     LIST_APPEND                     1
                        418     PUSH_NULL                       
                        420     LOAD_CONST                      1: '__pyarmor_assert_16035__'
                        422     LOAD_CONST                      23: '11.11.0 (59279)'   # b'\x81\xb3I]b\xab\xf0\x82[\xb2X\x99>\xbb\xa1\xcc'
                        424     CALL                            1
                        432     LIST_APPEND                     1
                        434     PUSH_NULL                       
                        436     LOAD_CONST                      1: '__pyarmor_assert_16035__'
                        438     LOAD_CONST                      24: '11.9.2 (59012)'   # b'\x81\xb3I]j\xb4\xec\x92S\xafT\x90=\xbe\xb1'
                        440     CALL                            1
                        448     LIST_APPEND                     1
                        450     PUSH_NULL                       
                        452     LOAD_CONST                      1: '__pyarmor_assert_16035__'
                        454     LOAD_CONST                      25: '11.9.2 (59019)'   # b'\x81\xb3I]j\xb4\xec\x92S\xafT\x90=\xb5\xb1'
                        456     CALL                            1
                        464     LIST_APPEND                     1
                        466     PUSH_NULL                       
                        468     LOAD_CONST                      1: '__pyarmor_assert_16035__'
                        470     LOAD_CONST                      26: '11.9.1 (59002)'   # b'\x81\xb3I]j\xb4\xef\x92S\xafT\x90<\xbe\xb1'
                        472     CALL                            1
                        480     LIST_APPEND                     1
                        482     PUSH_NULL                       
                        484     LOAD_CONST                      1: '__pyarmor_assert_16035__'
                        486     LOAD_CONST                      27: '11.9.1 (59009)'   # b'\x81\xb3I]j\xb4\xef\x92S\xafT\x90<\xb5\xb1'
                        488     CALL                            1
                        496     LIST_APPEND                     1
                        498     PUSH_NULL                       
                        500     LOAD_CONST                      1: '__pyarmor_assert_16035__'
                        502     LOAD_CONST                      28: '11.9.0 (58371)'   # b'\x81\xb3I]j\xb4\xee\x92S\xafU\x93;\xbd\xb1'
                        504     CALL                            1
                        512     LIST_APPEND                     1
                        514     PUSH_NULL                       
                        516     LOAD_CONST                      1: '__pyarmor_assert_16035__'
                        518     LOAD_CONST                      29: '11.9.0 (58372)'   # b'\x81\xb3I]j\xb4\xee\x92S\xafU\x93;\xbe\xb1'
                        520     CALL                            1
                        528     LIST_APPEND                     1
                        530     PUSH_NULL                       
                        532     LOAD_CONST                      1: '__pyarmor_assert_16035__'
                        534     LOAD_CONST                      30: '11.9.0 (58379)'   # b'\x81\xb3I]j\xb4\xee\x92S\xafU\x93;\xb5\xb1'
                        536     CALL                            1
                        544     LIST_APPEND                     1
                        546     PUSH_NULL                       
                        548     LOAD_CONST                      1: '__pyarmor_assert_16035__'
                        550     LOAD_CONST                      31: '11.8.3 (57992)'   # b'\x81\xb3I]k\xb4\xed\x92S\xafZ\x995\xbe\xb1'
                        552     CALL                            1
                        560     LIST_APPEND                     1
                        562     PUSH_NULL                       
                        564     LOAD_CONST                      1: '__pyarmor_assert_16035__'
                        566     LOAD_CONST                      32: '11.8.3 (57999)'   # b'\x81\xb3I]k\xb4\xed\x92S\xafZ\x995\xb5\xb1'
                        568     CALL                            1
                        576     LIST_APPEND                     1
                        578     PUSH_NULL                       
                        580     LOAD_CONST                      1: '__pyarmor_assert_16035__'
                        582     LOAD_CONST                      33: '11.8.2 (57841)'   # b'\x81\xb3I]k\xb4\xec\x92S\xafZ\x988\xbd\xb1'
                        584     CALL                            1
                        592     LIST_APPEND                     1
                        594     PUSH_NULL                       
                        596     LOAD_CONST                      1: '__pyarmor_assert_16035__'
                        598     LOAD_CONST                      34: '11.8.2 (57842)'   # b'\x81\xb3I]k\xb4\xec\x92S\xafZ\x988\xbe\xb1'
                        600     CALL                            1
                        608     LIST_APPEND                     1
                        610     PUSH_NULL                       
                        612     LOAD_CONST                      1: '__pyarmor_assert_16035__'
                        614     LOAD_CONST                      35: '11.8.2 (57849)'   # b'\x81\xb3I]k\xb4\xec\x92S\xafZ\x988\xb5\xb1'
                        616     CALL                            1
                        624     LIST_APPEND                     1
                        626     PUSH_NULL                       
                        628     LOAD_CONST                      1: '__pyarmor_assert_16035__'
                        630     LOAD_CONST                      36: '11.8.1 (57759)'   # b'\x81\xb3I]k\xb4\xef\x92S\xafZ\x979\xb5\xb1'
                        632     CALL                            1
                        640     LIST_APPEND                     1
                        642     PUSH_NULL                       
                        644     LOAD_CONST                      1: '__pyarmor_assert_16035__'
                        646     LOAD_CONST                      37: '11.8.0 (57731)'   # b'\x81\xb3I]k\xb4\xee\x92S\xafZ\x97?\xbd\xb1'
                        648     CALL                            1
                        656     LIST_APPEND                     1
                        658     PUSH_NULL                       
                        660     LOAD_CONST                      1: '__pyarmor_assert_16035__'
                        662     LOAD_CONST                      38: '11.8.0 (57732)'   # b'\x81\xb3I]k\xb4\xee\x92S\xafZ\x97?\xbe\xb1'
                        664     CALL                            1
                        672     LIST_APPEND                     1
                        674     PUSH_NULL                       
                        676     LOAD_CONST                      1: '__pyarmor_assert_16035__'
                        678     LOAD_CONST                      39: '11.8.0 (57719)'   # b'\x81\xb3I]k\xb4\xee\x92S\xafZ\x97=\xb5\xb1'
                        680     CALL                            1
                        688     LIST_APPEND                     1
                        690     PUSH_NULL                       
                        692     LOAD_CONST                      1: '__pyarmor_assert_16035__'
                        694     LOAD_CONST                      40: '11.7.4 (56982)'   # b'\x81\xb3I]d\xb4\xea\x92S\xaf[\x994\xbe\xb1'
                        696     CALL                            1
                        704     LIST_APPEND                     1
                        706     PUSH_NULL                       
                        708     LOAD_CONST                      1: '__pyarmor_assert_16035__'
                        710     LOAD_CONST                      41: '11.7.4 (56989)'   # b'\x81\xb3I]d\xb4\xea\x92S\xaf[\x994\xb5\xb1'
                        712     CALL                            1
                        720     LIST_APPEND                     1
                        722     PUSH_NULL                       
                        724     LOAD_CONST                      1: '__pyarmor_assert_16035__'
                        726     LOAD_CONST                      42: '11.7.3 (56962)'   # b'\x81\xb3I]d\xb4\xed\x92S\xaf[\x99:\xbe\xb1'
                        728     CALL                            1
                        736     LIST_APPEND                     1
                        738     PUSH_NULL                       
                        740     LOAD_CONST                      1: '__pyarmor_assert_16035__'
                        742     LOAD_CONST                      43: '11.7.3 (56969)'   # b'\x81\xb3I]d\xb4\xed\x92S\xaf[\x99:\xb5\xb1'
                        744     CALL                            1
                        752     LIST_APPEND                     1
                        754     PUSH_NULL                       
                        756     LOAD_CONST                      1: '__pyarmor_assert_16035__'
                        758     LOAD_CONST                      44: '11.7.0 (56631)'   # b'\x81\xb3I]d\xb4\xee\x92S\xaf[\x96?\xbd\xb1'
                        760     CALL                            1
                        768     LIST_APPEND                     1
                        770     PUSH_NULL                       
                        772     LOAD_CONST                      1: '__pyarmor_assert_16035__'
                        774     LOAD_CONST                      45: '11.7.0 (56632)'   # b'\x81\xb3I]d\xb4\xee\x92S\xaf[\x96?\xbe\xb1'
                        776     CALL                            1
                        784     LIST_APPEND                     1
                        786     PUSH_NULL                       
                        788     LOAD_CONST                      1: '__pyarmor_assert_16035__'
                        790     LOAD_CONST                      46: '11.7.0 (56639)'   # b'\x81\xb3I]d\xb4\xee\x92S\xaf[\x96?\xb5\xb1'
                        792     CALL                            1
                        800     LIST_APPEND                     1
                        802     PUSH_NULL                       
                        804     LOAD_CONST                      1: '__pyarmor_assert_16035__'
                        806     LOAD_CONST                      47: '11.6.2 (56151)'   # b'\x81\xb3I]e\xb4\xec\x92S\xaf[\x919\xbd\xb1'
                        808     CALL                            1
                        816     LIST_APPEND                     1
                        818     PUSH_NULL                       
                        820     LOAD_CONST                      1: '__pyarmor_assert_16035__'
                        822     LOAD_CONST                      48: '11.6.2 (56152)'   # b'\x81\xb3I]e\xb4\xec\x92S\xaf[\x919\xbe\xb1'
                        824     CALL                            1
                        832     LIST_APPEND                     1
                        834     PUSH_NULL                       
                        836     LOAD_CONST                      1: '__pyarmor_assert_16035__'
                        838     LOAD_CONST                      49: '11.6.2 (56159)'   # b'\x81\xb3I]e\xb4\xec\x92S\xaf[\x919\xb5\xb1'
                        840     CALL                            1
                        848     LIST_APPEND                     1
                        850     PUSH_NULL                       
                        852     LOAD_CONST                      1: '__pyarmor_assert_16035__'
                        854     LOAD_CONST                      50: '11.6.1 (55851)'   # b'\x81\xb3I]e\xb4\xef\x92S\xafX\x989\xbd\xb1'
                        856     CALL                            1
                        864     LIST_APPEND                     1
                        866     PUSH_NULL                       
                        868     LOAD_CONST                      1: '__pyarmor_assert_16035__'
                        870     LOAD_CONST                      51: '11.6.1 (55852)'   # b'\x81\xb3I]e\xb4\xef\x92S\xafX\x989\xbe\xb1'
                        872     CALL                            1
                        880     LIST_APPEND                     1
                        882     PUSH_NULL                       
                        884     LOAD_CONST                      1: '__pyarmor_assert_16035__'
                        886     LOAD_CONST                      52: '11.6.1 (55859)'   # b'\x81\xb3I]e\xb4\xef\x92S\xafX\x989\xb5\xb1'
                        888     CALL                            1
                        896     LIST_APPEND                     1
                        898     PUSH_NULL                       
                        900     LOAD_CONST                      1: '__pyarmor_assert_16035__'
                        902     LOAD_CONST                      53: '11.5.5 (55311)'   # b'\x81\xb3I]f\xb4\xeb\x92S\xafX\x93=\xbd\xb1'
                        904     CALL                            1
                        912     LIST_APPEND                     1
                        914     PUSH_NULL                       
                        916     LOAD_CONST                      1: '__pyarmor_assert_16035__'
                        918     LOAD_CONST                      54: '11.5.5 (55312)'   # b'\x81\xb3I]f\xb4\xeb\x92S\xafX\x93=\xbe\xb1'
                        920     CALL                            1
                        928     LIST_APPEND                     1
                        930     PUSH_NULL                       
                        932     LOAD_CONST                      1: '__pyarmor_assert_16035__'
                        934     LOAD_CONST                      55: '11.5.5 (55319)'   # b'\x81\xb3I]f\xb4\xeb\x92S\xafX\x93=\xb5\xb1'
                        936     CALL                            1
                        944     LIST_APPEND                     1
                        946     PUSH_NULL                       
                        948     LOAD_CONST                      1: '__pyarmor_assert_16035__'
                        950     LOAD_CONST                      56: '11.5.4 (55282)'   # b'\x81\xb3I]f\xb4\xea\x92S\xafX\x924\xbe\xb1'
                        952     CALL                            1
                        960     LIST_APPEND                     1
                        962     PUSH_NULL                       
                        964     LOAD_CONST                      1: '__pyarmor_assert_16035__'
                        966     LOAD_CONST                      57: '11.5.3 (55112)'   # b'\x81\xb3I]f\xb4\xed\x92S\xafX\x91=\xbe\xb1'
                        968     CALL                            1
                        976     LIST_APPEND                     1
                        978     PUSH_NULL                       
                        980     LOAD_CONST                      1: '__pyarmor_assert_16035__'
                        982     LOAD_CONST                      58: '11.5.3 (55119)'   # b'\x81\xb3I]f\xb4\xed\x92S\xafX\x91=\xb5\xb1'
                        984     CALL                            1
                        992     LIST_APPEND                     1
                        994     PUSH_NULL                       
                        996     LOAD_CONST                      1: '__pyarmor_assert_16035__'
                        998     LOAD_CONST                      59: '11.5.2 (55092)'   # b'\x81\xb3I]f\xb4\xec\x92S\xafX\x905\xbe\xb1'
                        1000    CALL                            1
                        1008    LIST_APPEND                     1
                        1010    PUSH_NULL                       
                        1012    LOAD_CONST                      1: '__pyarmor_assert_16035__'
                        1014    LOAD_CONST                      60: '11.5.2 (55099)'   # b'\x81\xb3I]f\xb4\xec\x92S\xafX\x905\xb5\xb1'
                        1016    CALL                            1
                        1024    LIST_APPEND                     1
                        1026    PUSH_NULL                       
                        1028    LOAD_CONST                      1: '__pyarmor_assert_16035__'
                        1030    LOAD_CONST                      61: '11.5.1 (55062)'   # b'\x81\xb3I]f\xb4\xef\x92S\xafX\x90:\xbe\xb1'
                        1032    CALL                            1
                        1040    LIST_APPEND                     1
                        1042    PUSH_NULL                       
                        1044    LOAD_CONST                      1: '__pyarmor_assert_16035__'
                        1046    LOAD_CONST                      62: '11.5.1 (55069)'   # b'\x81\xb3I]f\xb4\xef\x92S\xafX\x90:\xb5\xb1'
                        1048    CALL                            1
                        1056    LIST_APPEND                     1
                        1058    PUSH_NULL                       
                        1060    LOAD_CONST                      1: '__pyarmor_assert_16035__'
                        1062    LOAD_CONST                      63: '11.4.3 (54731)'   # b'\x81\xb3I]g\xb4\xed\x92S\xafY\x97?\xbd\xb1'
                        1064    CALL                            1
                        1072    LIST_APPEND                     1
                        1074    PUSH_NULL                       
                        1076    LOAD_CONST                      1: '__pyarmor_assert_16035__'
                        1078    LOAD_CONST                      64: '11.4.3 (54732)'   # b'\x81\xb3I]g\xb4\xed\x92S\xafY\x97?\xbe\xb1'
                        1080    CALL                            1
                        1088    LIST_APPEND                     1
                        1090    PUSH_NULL                       
                        1092    LOAD_CONST                      1: '__pyarmor_assert_16035__'
                        1094    LOAD_CONST                      65: '11.4.3 (54739)'   # b'\x81\xb3I]g\xb4\xed\x92S\xafY\x97?\xb5\xb1'
                        1096    CALL                            1
                        1104    LIST_APPEND                     1
                        1106    PUSH_NULL                       
                        1108    LOAD_CONST                      1: '__pyarmor_assert_16035__'
                        1110    LOAD_CONST                      66: '11.4.2 (54691)'   # b'\x81\xb3I]g\xb4\xec\x92S\xafY\x965\xbd\xb1'
                        1112    CALL                            1
                        1120    LIST_APPEND                     1
                        1122    PUSH_NULL                       
                        1124    LOAD_CONST                      1: '__pyarmor_assert_16035__'
                        1126    LOAD_CONST                      67: '11.4.2 (54692)'   # b'\x81\xb3I]g\xb4\xec\x92S\xafY\x965\xbe\xb1'
                        1128    CALL                            1
                        1136    LIST_APPEND                     1
                        1138    PUSH_NULL                       
                        1140    LOAD_CONST                      1: '__pyarmor_assert_16035__'
                        1142    LOAD_CONST                      68: '11.4.2 (54699)'   # b'\x81\xb3I]g\xb4\xec\x92S\xafY\x965\xb5\xb1'
                        1144    CALL                            1
                        1152    LIST_APPEND                     1
                        1154    PUSH_NULL                       
                        1156    LOAD_CONST                      1: '__pyarmor_assert_16035__'
                        1158    LOAD_CONST                      69: '11.4.1 (54591)'   # b'\x81\xb3I]g\xb4\xef\x92S\xafY\x955\xbd\xb1'
                        1160    CALL                            1
                        1168    LIST_APPEND                     1
                        1170    PUSH_NULL                       
                        1172    LOAD_CONST                      1: '__pyarmor_assert_16035__'
                        1174    LOAD_CONST                      70: '11.4.1 (54592)'   # b'\x81\xb3I]g\xb4\xef\x92S\xafY\x955\xbe\xb1'
                        1176    CALL                            1
                        1184    LIST_APPEND                     1
                        1186    PUSH_NULL                       
                        1188    LOAD_CONST                      1: '__pyarmor_assert_16035__'
                        1190    LOAD_CONST                      71: '11.4.1 (54599)'   # b'\x81\xb3I]g\xb4\xef\x92S\xafY\x955\xb5\xb1'
                        1192    CALL                            1
                        1200    LIST_APPEND                     1
                        1202    PUSH_NULL                       
                        1204    LOAD_CONST                      1: '__pyarmor_assert_16035__'
                        1206    LOAD_CONST                      72: '11.4.0 (54451)'   # b'\x81\xb3I]g\xb4\xee\x92S\xafY\x949\xbd\xb1'
                        1208    CALL                            1
                        1216    LIST_APPEND                     1
                        1218    PUSH_NULL                       
                        1220    LOAD_CONST                      1: '__pyarmor_assert_16035__'
                        1222    LOAD_CONST                      73: '11.4.0 (54452)'   # b'\x81\xb3I]g\xb4\xee\x92S\xafY\x949\xbe\xb1'
                        1224    CALL                            1
                        1232    LIST_APPEND                     1
                        1234    PUSH_NULL                       
                        1236    LOAD_CONST                      1: '__pyarmor_assert_16035__'
                        1238    LOAD_CONST                      74: '11.4.0 (54459)'   # b'\x81\xb3I]g\xb4\xee\x92S\xafY\x949\xb5\xb1'
                        1240    CALL                            1
                        1248    LIST_APPEND                     1
                        1250    PUSH_NULL                       
                        1252    LOAD_CONST                      1: '__pyarmor_assert_16035__'
                        1254    LOAD_CONST                      75: '11.3.4 (53971)'   # b'\x81\xb3I]`\xb4\xea\x92S\xaf^\x99;\xbd\xb1'
                        1256    CALL                            1
                        1264    LIST_APPEND                     1
                        1266    PUSH_NULL                       
                        1268    LOAD_CONST                      1: '__pyarmor_assert_16035__'
                        1270    LOAD_CONST                      76: '11.3.4 (53972)'   # b'\x81\xb3I]`\xb4\xea\x92S\xaf^\x99;\xbe\xb1'
                        1272    CALL                            1
                        1280    LIST_APPEND                     1
                        1282    PUSH_NULL                       
                        1284    LOAD_CONST                      1: '__pyarmor_assert_16035__'
                        1286    LOAD_CONST                      77: '11.3.4 (53979)'   # b'\x81\xb3I]`\xb4\xea\x92S\xaf^\x99;\xb5\xb1'
                        1288    CALL                            1
                        1296    LIST_APPEND                     1
                        1298    PUSH_NULL                       
                        1300    LOAD_CONST                      1: '__pyarmor_assert_16035__'
                        1302    LOAD_CONST                      78: '11.3.3 (53961)'   # b'\x81\xb3I]`\xb4\xed\x92S\xaf^\x99:\xbd\xb1'
                        1304    CALL                            1
                        1312    LIST_APPEND                     1
                        1314    PUSH_NULL                       
                        1316    LOAD_CONST                      1: '__pyarmor_assert_16035__'
                        1318    LOAD_CONST                      79: '11.3.3 (53962)'   # b'\x81\xb3I]`\xb4\xed\x92S\xaf^\x99:\xbe\xb1'
                        1320    CALL                            1
                        1328    LIST_APPEND                     1
                        1330    PUSH_NULL                       
                        1332    LOAD_CONST                      1: '__pyarmor_assert_16035__'
                        1334    LOAD_CONST                      80: '11.3.2 (53931)'   # b'\x81\xb3I]`\xb4\xec\x92S\xaf^\x99?\xbd\xb1'
                        1336    CALL                            1
                        1344    LIST_APPEND                     1
                        1346    PUSH_NULL                       
                        1348    LOAD_CONST                      1: '__pyarmor_assert_16035__'
                        1350    LOAD_CONST                      81: '11.3.2 (53932)'   # b'\x81\xb3I]`\xb4\xec\x92S\xaf^\x99?\xbe\xb1'
                        1352    CALL                            1
                        1360    LIST_APPEND                     1
                        1362    PUSH_NULL                       
                        1364    LOAD_CONST                      1: '__pyarmor_assert_16035__'
                        1366    LOAD_CONST                      82: '11.3.2 (53939)'   # b'\x81\xb3I]`\xb4\xec\x92S\xaf^\x99?\xb5\xb1'
                        1368    CALL                            1
                        1376    LIST_APPEND                     1
                        1378    PUSH_NULL                       
                        1380    LOAD_CONST                      1: '__pyarmor_assert_16035__'
                        1382    LOAD_CONST                      83: '11.3.1 (53911)'   # b'\x81\xb3I]`\xb4\xef\x92S\xaf^\x99=\xbd\xb1'
                        1384    CALL                            1
                        1392    LIST_APPEND                     1
                        1394    PUSH_NULL                       
                        1396    LOAD_CONST                      1: '__pyarmor_assert_16035__'
                        1398    LOAD_CONST                      84: '11.3.1 (53912)'   # b'\x81\xb3I]`\xb4\xef\x92S\xaf^\x99=\xbe\xb1'
                        1400    CALL                            1
                        1408    LIST_APPEND                     1
                        1410    PUSH_NULL                       
                        1412    LOAD_CONST                      1: '__pyarmor_assert_16035__'
                        1414    LOAD_CONST                      85: '11.3.1 (53919)'   # b'\x81\xb3I]`\xb4\xef\x92S\xaf^\x99=\xb5\xb1'
                        1416    CALL                            1
                        1424    LIST_APPEND                     1
                        1426    PUSH_NULL                       
                        1428    LOAD_CONST                      1: '__pyarmor_assert_16035__'
                        1430    LOAD_CONST                      86: '11.3.0 (53861)'   # b'\x81\xb3I]`\xb4\xee\x92S\xaf^\x98:\xbd\xb1'
                        1432    CALL                            1
                        1440    LIST_APPEND                     1
                        1442    PUSH_NULL                       
                        1444    LOAD_CONST                      1: '__pyarmor_assert_16035__'
                        1446    LOAD_CONST                      87: '11.3.0 (53862)'   # b'\x81\xb3I]`\xb4\xee\x92S\xaf^\x98:\xbe\xb1'
                        1448    CALL                            1
                        1456    LIST_APPEND                     1
                        1458    PUSH_NULL                       
                        1460    LOAD_CONST                      1: '__pyarmor_assert_16035__'
                        1462    LOAD_CONST                      88: '11.3.0 (53869)'   # b'\x81\xb3I]`\xb4\xee\x92S\xaf^\x98:\xb5\xb1'
                        1464    CALL                            1
                        1472    LIST_APPEND                     1
                        1474    PUSH_NULL                       
                        1476    LOAD_CONST                      1: '__pyarmor_assert_16035__'
                        1478    LOAD_CONST                      89: '11.2.3 (53351)'   # b'\x81\xb3I]a\xb4\xed\x92S\xaf^\x939\xbd\xb1'
                        1480    CALL                            1
                        1488    LIST_APPEND                     1
                        1490    PUSH_NULL                       
                        1492    LOAD_CONST                      1: '__pyarmor_assert_16035__'
                        1494    LOAD_CONST                      90: '11.2.3 (53352)'   # b'\x81\xb3I]a\xb4\xed\x92S\xaf^\x939\xbe\xb1'
                        1496    CALL                            1
                        1504    LIST_APPEND                     1
                        1506    PUSH_NULL                       
                        1508    LOAD_CONST                      1: '__pyarmor_assert_16035__'
                        1510    LOAD_CONST                      91: '11.2.3 (53359)'   # b'\x81\xb3I]a\xb4\xed\x92S\xaf^\x939\xb5\xb1'
                        1512    CALL                            1
                        1520    LIST_APPEND                     1
                        1522    PUSH_NULL                       
                        1524    LOAD_CONST                      1: '__pyarmor_assert_16035__'
                        1526    LOAD_CONST                      92: '11.2.2 (53291)'   # b'\x81\xb3I]a\xb4\xec\x92S\xaf^\x925\xbd\xb1'
                        1528    CALL                            1
                        1536    LIST_APPEND                     1
                        1538    PUSH_NULL                       
                        1540    LOAD_CONST                      1: '__pyarmor_assert_16035__'
                        1542    LOAD_CONST                      93: '11.2.2 (53292)'   # b'\x81\xb3I]a\xb4\xec\x92S\xaf^\x925\xbe\xb1'
                        1544    CALL                            1
                        1552    LIST_APPEND                     1
                        1554    PUSH_NULL                       
                        1556    LOAD_CONST                      1: '__pyarmor_assert_16035__'
                        1558    LOAD_CONST                      94: '11.2.2 (53299)'   # b'\x81\xb3I]a\xb4\xec\x92S\xaf^\x925\xb5\xb1'
                        1560    CALL                            1
                        1568    LIST_APPEND                     1
                        1570    PUSH_NULL                       
                        1572    LOAD_CONST                      1: '__pyarmor_assert_16035__'
                        1574    LOAD_CONST                      95: '11.2.1 (53159)'   # b'\x81\xb3I]a\xb4\xef\x92S\xaf^\x919\xb5\xb1'
                        1576    CALL                            1
                        1584    LIST_APPEND                     1
                        1586    PUSH_NULL                       
                        1588    LOAD_CONST                      1: '__pyarmor_assert_16035__'
                        1590    LOAD_CONST                      96: '11.2.0 (52999)'   # b'\x81\xb3I]a\xb4\xee\x92S\xaf_\x995\xb5\xb1'
                        1592    CALL                            1
                        1600    LIST_APPEND                     1
                        1602    PUSH_NULL                       
                        1604    LOAD_CONST                      1: '__pyarmor_assert_16035__'
                        1606    LOAD_CONST                      97: '11.2.0 (52992)'   # b'\x81\xb3I]a\xb4\xee\x92S\xaf_\x995\xbe\xb1'
                        1608    CALL                            1
                        1616    LIST_APPEND                     1
                        1618    PUSH_NULL                       
                        1620    LOAD_CONST                      1: '__pyarmor_assert_16035__'
                        1622    LOAD_CONST                      98: '11.1.3 (52442)'   # b'\x81\xb3I]b\xb4\xed\x92S\xaf_\x948\xbe\xb1'
                        1624    CALL                            1
                        1632    LIST_APPEND                     1
                        1634    PUSH_NULL                       
                        1636    LOAD_CONST                      1: '__pyarmor_assert_16035__'
                        1638    LOAD_CONST                      99: '11.1.1 (52352)'   # b'\x81\xb3I]b\xb4\xef\x92S\xaf_\x939\xbe\xb1'
                        1640    CALL                            1
                        1648    LIST_APPEND                     1
                        1650    PUSH_NULL                       
                        1652    LOAD_CONST                      1: '__pyarmor_assert_16035__'
                        1654    LOAD_CONST                      100: '11.1.0 (52292)'   # b'\x81\xb3I]b\xb4\xee\x92S\xaf_\x925\xbe\xb1'
                        1656    CALL                            1
                        1664    LIST_APPEND                     1
                        1666    PUSH_NULL                       
                        1668    LOAD_CONST                      1: '__pyarmor_assert_16035__'
                        1670    LOAD_CONST                      101: '11.0.1 (51762)'   # b'\x81\xb3I]c\xb4\xef\x92S\xaf\\\x97:\xbe\xb1'
                        1672    CALL                            1
                        1680    LIST_APPEND                     1
                        1682    PUSH_NULL                       
                        1684    LOAD_CONST                      1: '__pyarmor_assert_16035__'
                        1686    LOAD_CONST                      102: '11.0.1 (51779)'   # b'\x81\xb3I]c\xb4\xef\x92S\xaf\\\x97;\xb5\xb1'
                        1688    CALL                            1
                        1696    LIST_APPEND                     1
                        1698    PUSH_NULL                       
                        1700    LOAD_CONST                      1: '__pyarmor_assert_16035__'
                        1702    LOAD_CONST                      103: '11.0.0 (51431)'   # b'\x81\xb3I]c\xb4\xee\x92S\xaf\\\x94?\xbd\xb1'
                        1704    CALL                            1
                        1712    LIST_APPEND                     1
                        1714    PUSH_NULL                       
                        1716    LOAD_CONST                      1: '__pyarmor_assert_16035__'
                        1718    LOAD_CONST                      104: '11.0.0 (51432)'   # b'\x81\xb3I]c\xb4\xee\x92S\xaf\\\x94?\xbe\xb1'
                        1720    CALL                            1
                        1728    LIST_APPEND                     1
                        1730    PUSH_NULL                       
                        1732    LOAD_CONST                      1: '__pyarmor_assert_16035__'
                        1734    LOAD_CONST                      105: '11.0.0 (51439)'   # b'\x81\xb3I]c\xb4\xee\x92S\xaf\\\x94?\xb5\xb1'
                        1736    CALL                            1
                        1744    LIST_APPEND                     1
                        1746    LOAD_FAST                       0: self
                        1748    STORE_ATTR                      6: android
                        1758    PUSH_NULL                       
                        1760    LOAD_CONST                      1: '__pyarmor_assert_16035__'
                        1762    LOAD_CONST                      106: '0.27.10.1752-arm64-v8a'   # b'\x81\xb2VAd\xb4\xef\x82U\xabZ\x95>\xa1\xf9\x97\x02\x0b\xef\xea\xbc\x93O'
                        1764    CALL                            1
                        1772    PUSH_NULL                       
                        1774    LOAD_CONST                      1: '__pyarmor_assert_16035__'
                        1776    LOAD_CONST                      107: '0.27.10.1752-armeabi-v7a'   # b'\x81\xb2VAd\xb4\xef\x82U\xabZ\x95>\xa1\xf9\x97\x02X\xba\xa5\xa3\x86X\x9b\x04'
                        1778    CALL                            1
                        1786    PUSH_NULL                       
                        1788    LOAD_CONST                      1: '__pyarmor_assert_16035__'
                        1790    LOAD_CONST                      108: '0.26.11.1734-arm64-v8a'   # b'\x81\xb2VAe\xb4\xef\x83U\xabZ\x938\xa1\xf9\x97\x02\x0b\xef\xea\xbc\x93O'
                        1792    CALL                            1
                        1800    PUSH_NULL                       
                        1802    LOAD_CONST                      1: '__pyarmor_assert_16035__'
                        1804    LOAD_CONST                      109: '0.26.11.1734-armeabi-v7a'   # b'\x81\xb2VAe\xb4\xef\x83U\xabZ\x938\xa1\xf9\x97\x02X\xba\xa5\xa3\x86X\x9b\x04'
                        1806    CALL                            1
                        1814    BUILD_LIST                      4
                        1816    LOAD_FAST                       0: self
                        1818    STORE_ATTR                      7: android_x
                        1828    BUILD_LIST                      0
                        1830    PUSH_NULL                       
                        1832    LOAD_CONST                      1: '__pyarmor_assert_16035__'
                        1834    LOAD_CONST                      110: '6.0.2 x64'   # b'\x81\xb4VC}\xa8\xfe\xcaM\xae'
                        1836    CALL                            1
                        1844    LIST_APPEND                     1
                        1846    PUSH_NULL                       
                        1848    LOAD_CONST                      1: '__pyarmor_assert_16035__'
                        1850    LOAD_CONST                      111: '6.0.1 x64'   # b'\x81\xb4VC}\xab\xfe\xcaM\xae'
                        1852    CALL                            1
                        1860    LIST_APPEND                     1
                        1862    PUSH_NULL                       
                        1864    LOAD_CONST                      1: '__pyarmor_assert_16035__'
                        1866    LOAD_CONST                      112: '6.0.0 x64'   # b'\x81\xb4VC}\xaa\xfe\xcaM\xae'
                        1868    CALL                            1
                        1876    LIST_APPEND                     1
                        1878    PUSH_NULL                       
                        1880    LOAD_CONST                      1: '__pyarmor_assert_16035__'
                        1882    LOAD_CONST                      113: '5.16.6 x64'   # b'\x81\xb7VBe\xb4\xe8\x92\x03\xacY'
                        1884    CALL                            1
                        1892    LIST_APPEND                     1
                        1894    PUSH_NULL                       
                        1896    LOAD_CONST                      1: '__pyarmor_assert_16035__'
                        1898    LOAD_CONST                      114: '5.16.5 x64'   # b'\x81\xb7VBe\xb4\xeb\x92\x03\xacY'
                        1900    CALL                            1
                        1908    LIST_APPEND                     1
                        1910    PUSH_NULL                       
                        1912    LOAD_CONST                      1: '__pyarmor_assert_16035__'
                        1914    LOAD_CONST                      115: '5.16.4 x64'   # b'\x81\xb7VBe\xb4\xea\x92\x03\xacY'
                        1916    CALL                            1
                        1924    LIST_APPEND                     1
                        1926    PUSH_NULL                       
                        1928    LOAD_CONST                      1: '__pyarmor_assert_16035__'
                        1930    LOAD_CONST                      116: '5.16.3 x64'   # b'\x81\xb7VBe\xb4\xed\x92\x03\xacY'
                        1932    CALL                            1
                        1940    LIST_APPEND                     1
                        1942    PUSH_NULL                       
                        1944    LOAD_CONST                      1: '__pyarmor_assert_16035__'
                        1946    LOAD_CONST                      117: '5.16.2 x64'   # b'\x81\xb7VBe\xb4\xec\x92\x03\xacY'
                        1948    CALL                            1
                        1956    LIST_APPEND                     1
                        1958    PUSH_NULL                       
                        1960    LOAD_CONST                      1: '__pyarmor_assert_16035__'
                        1962    LOAD_CONST                      118: '5.16.1 x64'   # b'\x81\xb7VBe\xb4\xef\x92\x03\xacY'
                        1964    CALL                            1
                        1972    LIST_APPEND                     1
                        1974    PUSH_NULL                       
                        1976    LOAD_CONST                      1: '__pyarmor_assert_16035__'
                        1978    LOAD_CONST                      119: '5.16.0 x64'   # b'\x81\xb7VBe\xb4\xee\x92\x03\xacY'
                        1980    CALL                            1
                        1988    LIST_APPEND                     1
                        1990    PUSH_NULL                       
                        1992    LOAD_CONST                      1: '__pyarmor_assert_16035__'
                        1994    LOAD_CONST                      120: '5.15.4 x64'   # b'\x81\xb7VBf\xb4\xea\x92\x03\xacY'
                        1996    CALL                            1
                        2004    LIST_APPEND                     1
                        2006    PUSH_NULL                       
                        2008    LOAD_CONST                      1: '__pyarmor_assert_16035__'
                        2010    LOAD_CONST                      121: '5.15.3 x64'   # b'\x81\xb7VBf\xb4\xed\x92\x03\xacY'
                        2012    CALL                            1
                        2020    LIST_APPEND                     1
                        2022    PUSH_NULL                       
                        2024    LOAD_CONST                      1: '__pyarmor_assert_16035__'
                        2026    LOAD_CONST                      122: '5.15.2 x64'   # b'\x81\xb7VBf\xb4\xec\x92\x03\xacY'
                        2028    CALL                            1
                        2036    LIST_APPEND                     1
                        2038    PUSH_NULL                       
                        2040    LOAD_CONST                      1: '__pyarmor_assert_16035__'
                        2042    LOAD_CONST                      123: '5.15.1 x64'   # b'\x81\xb7VBf\xb4\xef\x92\x03\xacY'
                        2044    CALL                            1
                        2052    LIST_APPEND                     1
                        2054    PUSH_NULL                       
                        2056    LOAD_CONST                      1: '__pyarmor_assert_16035__'
                        2058    LOAD_CONST                      124: '5.15.0 x64'   # b'\x81\xb7VBf\xb4\xee\x92\x03\xacY'
                        2060    CALL                            1
                        2068    LIST_APPEND                     1
                        2070    PUSH_NULL                       
                        2072    LOAD_CONST                      1: '__pyarmor_assert_16035__'
                        2074    LOAD_CONST                      125: '5.14.3 x64'   # b'\x81\xb7VBg\xb4\xed\x92\x03\xacY'
                        2076    CALL                            1
                        2084    LIST_APPEND                     1
                        2086    PUSH_NULL                       
                        2088    LOAD_CONST                      1: '__pyarmor_assert_16035__'
                        2090    LOAD_CONST                      126: '5.14.2 x64'   # b'\x81\xb7VBg\xb4\xec\x92\x03\xacY'
                        2092    CALL                            1
                        2100    LIST_APPEND                     1
                        2102    PUSH_NULL                       
                        2104    LOAD_CONST                      1: '__pyarmor_assert_16035__'
                        2106    LOAD_CONST                      127: '5.14.1 x64'   # b'\x81\xb7VBg\xb4\xef\x92\x03\xacY'
                        2108    CALL                            1
                        2116    LIST_APPEND                     1
                        2118    PUSH_NULL                       
                        2120    LOAD_CONST                      1: '__pyarmor_assert_16035__'
                        2122    LOAD_CONST                      128: '5.14.0 x64'   # b'\x81\xb7VBg\xb4\xee\x92\x03\xacY'
                        2124    CALL                            1
                        2132    LIST_APPEND                     1
                        2134    PUSH_NULL                       
                        2136    LOAD_CONST                      1: '__pyarmor_assert_16035__'
                        2138    LOAD_CONST                      129: '5.13.1 x64'   # b'\x81\xb7VB`\xb4\xef\x92\x03\xacY'
                        2140    CALL                            1
                        2148    LIST_APPEND                     1
                        2150    PUSH_NULL                       
                        2152    LOAD_CONST                      1: '__pyarmor_assert_16035__'
                        2154    LOAD_CONST                      130: '5.13.0 x64'   # b'\x81\xb7VB`\xb4\xee\x92\x03\xacY'
                        2156    CALL                            1
                        2164    LIST_APPEND                     1
                        2166    PUSH_NULL                       
                        2168    LOAD_CONST                      1: '__pyarmor_assert_16035__'
                        2170    LOAD_CONST                      131: '5.12.3 x64'   # b'\x81\xb7VBa\xb4\xed\x92\x03\xacY'
                        2172    CALL                            1
                        2180    LIST_APPEND                     1
                        2182    PUSH_NULL                       
                        2184    LOAD_CONST                      1: '__pyarmor_assert_16035__'
                        2186    LOAD_CONST                      132: '5.12.2 x64'   # b'\x81\xb7VBa\xb4\xec\x92\x03\xacY'
                        2188    CALL                            1
                        2196    LIST_APPEND                     1
                        2198    PUSH_NULL                       
                        2200    LOAD_CONST                      1: '__pyarmor_assert_16035__'
                        2202    LOAD_CONST                      133: '5.12.1 x64'   # b'\x81\xb7VBa\xb4\xef\x92\x03\xacY'
                        2204    CALL                            1
                        2212    LIST_APPEND                     1
                        2214    PUSH_NULL                       
                        2216    LOAD_CONST                      1: '__pyarmor_assert_16035__'
                        2218    LOAD_CONST                      134: '5.12.0 x64'   # b'\x81\xb7VBa\xb4\xee\x92\x03\xacY'
                        2220    CALL                            1
                        2228    LIST_APPEND                     1
                        2230    PUSH_NULL                       
                        2232    LOAD_CONST                      1: '__pyarmor_assert_16035__'
                        2234    LOAD_CONST                      135: '5.11.1 x64'   # b'\x81\xb7VBb\xb4\xef\x92\x03\xacY'
                        2236    CALL                            1
                        2244    LIST_APPEND                     1
                        2246    PUSH_NULL                       
                        2248    LOAD_CONST                      1: '__pyarmor_assert_16035__'
                        2250    LOAD_CONST                      136: '5.10.7 x64'   # b'\x81\xb7VBc\xb4\xe9\x92\x03\xacY'
                        2252    CALL                            1
                        2260    LIST_APPEND                     1
                        2262    PUSH_NULL                       
                        2264    LOAD_CONST                      1: '__pyarmor_assert_16035__'
                        2266    LOAD_CONST                      137: '5.10.6 x64'   # b'\x81\xb7VBc\xb4\xe8\x92\x03\xacY'
                        2268    CALL                            1
                        2276    LIST_APPEND                     1
                        2278    PUSH_NULL                       
                        2280    LOAD_CONST                      1: '__pyarmor_assert_16035__'
                        2282    LOAD_CONST                      138: '5.10.5 x64'   # b'\x81\xb7VBc\xb4\xeb\x92\x03\xacY'
                        2284    CALL                            1
                        2292    LIST_APPEND                     1
                        2294    PUSH_NULL                       
                        2296    LOAD_CONST                      1: '__pyarmor_assert_16035__'
                        2298    LOAD_CONST                      139: '5.10.4 x64'   # b'\x81\xb7VBc\xb4\xea\x92\x03\xacY'
                        2300    CALL                            1
                        2308    LIST_APPEND                     1
                        2310    PUSH_NULL                       
                        2312    LOAD_CONST                      1: '__pyarmor_assert_16035__'
                        2314    LOAD_CONST                      140: '5.10.3 x64'   # b'\x81\xb7VBc\xb4\xed\x92\x03\xacY'
                        2316    CALL                            1
                        2324    LIST_APPEND                     1
                        2326    PUSH_NULL                       
                        2328    LOAD_CONST                      1: '__pyarmor_assert_16035__'
                        2330    LOAD_CONST                      141: '5.10.2 x64'   # b'\x81\xb7VBc\xb4\xec\x92\x03\xacY'
                        2332    CALL                            1
                        2340    LIST_APPEND                     1
                        2342    PUSH_NULL                       
                        2344    LOAD_CONST                      1: '__pyarmor_assert_16035__'
                        2346    LOAD_CONST                      142: '5.10.1 x64'   # b'\x81\xb7VBc\xb4\xef\x92\x03\xacY'
                        2348    CALL                            1
                        2356    LIST_APPEND                     1
                        2358    PUSH_NULL                       
                        2360    LOAD_CONST                      1: '__pyarmor_assert_16035__'
                        2362    LOAD_CONST                      143: '5.10.0 x64'   # b'\x81\xb7VBc\xb4\xee\x92\x03\xacY'
                        2364    CALL                            1
                        2372    LIST_APPEND                     1
                        2374    PUSH_NULL                       
                        2376    LOAD_CONST                      1: '__pyarmor_assert_16035__'
                        2378    LOAD_CONST                      144: '5.9.0 x64'   # b'\x81\xb7VJ}\xaa\xfe\xcaM\xae'
                        2380    CALL                            1
                        2388    LIST_APPEND                     1
                        2390    PUSH_NULL                       
                        2392    LOAD_CONST                      1: '__pyarmor_assert_16035__'
                        2394    LOAD_CONST                      145: '5.8.3 x64'   # b'\x81\xb7VK}\xa9\xfe\xcaM\xae'
                        2396    CALL                            1
                        2404    LIST_APPEND                     1
                        2406    PUSH_NULL                       
                        2408    LOAD_CONST                      1: '__pyarmor_assert_16035__'
                        2410    LOAD_CONST                      146: '5.8.2 x64'   # b'\x81\xb7VK}\xa8\xfe\xcaM\xae'
                        2412    CALL                            1
                        2420    LIST_APPEND                     1
                        2422    PUSH_NULL                       
                        2424    LOAD_CONST                      1: '__pyarmor_assert_16035__'
                        2426    LOAD_CONST                      147: '5.8.1 x64'   # b'\x81\xb7VK}\xab\xfe\xcaM\xae'
                        2428    CALL                            1
                        2436    LIST_APPEND                     1
                        2438    PUSH_NULL                       
                        2440    LOAD_CONST                      1: '__pyarmor_assert_16035__'
                        2442    LOAD_CONST                      148: '5.8.0 x64'   # b'\x81\xb7VK}\xaa\xfe\xcaM\xae'
                        2444    CALL                            1
                        2452    LIST_APPEND                     1
                        2454    PUSH_NULL                       
                        2456    LOAD_CONST                      1: '__pyarmor_assert_16035__'
                        2458    LOAD_CONST                      149: '5.7.2 x64'   # b'\x81\xb7VD}\xa8\xfe\xcaM\xae'
                        2460    CALL                            1
                        2468    LIST_APPEND                     1
                        2470    PUSH_NULL                       
                        2472    LOAD_CONST                      1: '__pyarmor_assert_16035__'
                        2474    LOAD_CONST                      150: '5.7.1 x64'   # b'\x81\xb7VD}\xab\xfe\xcaM\xae'
                        2476    CALL                            1
                        2484    LIST_APPEND                     1
                        2486    PUSH_NULL                       
                        2488    LOAD_CONST                      1: '__pyarmor_assert_16035__'
                        2490    LOAD_CONST                      151: '5.7.0 x64'   # b'\x81\xb7VD}\xaa\xfe\xcaM\xae'
                        2492    CALL                            1
                        2500    LIST_APPEND                     1
                        2502    PUSH_NULL                       
                        2504    LOAD_CONST                      1: '__pyarmor_assert_16035__'
                        2506    LOAD_CONST                      152: '5.6.4 x64'   # b'\x81\xb7VE}\xae\xfe\xcaM\xae'
                        2508    CALL                            1
                        2516    LIST_APPEND                     1
                        2518    PUSH_NULL                       
                        2520    LOAD_CONST                      1: '__pyarmor_assert_16035__'
                        2522    LOAD_CONST                      153: '5.6.3 x64'   # b'\x81\xb7VE}\xa9\xfe\xcaM\xae'
                        2524    CALL                            1
                        2532    LIST_APPEND                     1
                        2534    PUSH_NULL                       
                        2536    LOAD_CONST                      1: '__pyarmor_assert_16035__'
                        2538    LOAD_CONST                      154: '5.6.2 x64'   # b'\x81\xb7VE}\xa8\xfe\xcaM\xae'
                        2540    CALL                            1
                        2548    LIST_APPEND                     1
                        2550    PUSH_NULL                       
                        2552    LOAD_CONST                      1: '__pyarmor_assert_16035__'
                        2554    LOAD_CONST                      155: '5.6.1 x64'   # b'\x81\xb7VE}\xab\xfe\xcaM\xae'
                        2556    CALL                            1
                        2564    LIST_APPEND                     1
                        2566    PUSH_NULL                       
                        2568    LOAD_CONST                      1: '__pyarmor_assert_16035__'
                        2570    LOAD_CONST                      156: '5.6.0 x64'   # b'\x81\xb7VE}\xaa\xfe\xcaM\xae'
                        2572    CALL                            1
                        2580    LIST_APPEND                     1
                        2582    LOAD_FAST                       0: self
                        2584    STORE_ATTR                      8: desktop
                        2594    LOAD_CONST                      0: None
                        2596    NOP                             
                        2598    NOP                             
                        2600    NOP                             
                        2602    JUMP_FORWARD                    19 (to 2642)
                        2610    POP_TOP                         
                        2612    RETURN_CONST                    0: None
                        2614    PUSH_EXC_INFO                   
                        2616    PUSH_NULL                       
                        2618    LOAD_CONST                      157: '__pyarmor_exit_16037__'
                        2620    NOP                             
                        2622    LOAD_CONST                      3: b'<COAddr>\x07\x00\x00\x1a\x1c\n\x00\x00\x00\x00\x00\x00\x00\x00\x00\x00\x00\x00\x00\x00'
                        2624    CALL                            1
                        2632    POP_TOP                         
                        2634    RERAISE                         0
                        2636    COPY                            3
                        2638    POP_EXCEPT                      
                        2640    RERAISE                         1
                        2642    PUSH_NULL                       
                        2644    LOAD_CONST                      157: '__pyarmor_exit_16037__'
                        2646    LOAD_CONST                      3: b'<COAddr>\x07\x00\x00\x1a\x1c\n\x00\x00\x00\x00\x00\x00\x00\x00\x00\x00\x00\x00\x00\x00'
                        2648    BUILD_TUPLE                     1
                        2650    CALL_FUNCTION_EX                0
                        2652    POP_TOP                         
                        2654    RETURN_VALUE                    
                    [Exception Table]
                        28 to 2594 -> 2614 [0] 
                        2614 to 2636 -> 2636 [1] lasti
                [Code]
                    File Name: <frozen program.static_classes.version_control>
                    Object Name: check
                    Qualified Name: VersionControl.check
                    Arg Count: 4
                    Pos Only Arg Count: 0
                    KW Only Arg Count: 0
                    Stack Size: 8
                    Flags: 0x20000003 (CO_OPTIMIZED | CO_NEWLOCALS | CO_PYARMOR_OBFUSCATED)
                    [Names]
                        'account'
                        'int'
                        'app_id'
                        'str'
                        'version'
                        'config'
                        'android'
                        'log'
                        'Logs'
                        'PrintLog'
                        'lang'
                        'android_x'
                        'desktop'
                    [Locals+Names]
                        'self'
                        'account'
                        'app_id'
                        'version'
                        '__assert_armored__'
                    [Constants]
                        None
                        '__pyarmor_assert_16038__'
                        '__pyarmor_enter_16039__'
                        b'<COAddr>\x07\x00\x00\x1a\xc0\x0c\x00\x00\x00\x00\x00\x00\x00\x00\x00\x00\x00\x00\x00\x00'
                        4
                        6
                        'control_offical'   # b"\x81\xe1\x17\x1d'\xe8\xb1\xde$\xf5\x0b\xc6e\xef\xf9\x89"
                        '__pyarmor_exit_16040__'
                        True
                        'version_control_warning'   # b'\x81\xf4\x1d\x01 \xf3\xb1\xdc$\xf9\x02\xcex\xfe\xf7\x890J\xba\xb5\xa4\xc2@\xcb'
                        (
                            'config'
                            'account'
                            'message'
                        )
                        'version_control_work_android'   # b'\x81\xf4\x1d\x01 \xf3\xb1\xdc$\xf9\x02\xcex\xfe\xf7\x890J\xb4\xb5\xa1\xf4O\xc2\x01}\xacU\x04'
                        'version_control_json_correct'   # b'\x81\xf4\x1d\x01 \xf3\xb1\xdc$\xf9\x02\xcex\xfe\xf7\x890W\xa8\xa8\xa4\xf4M\xc3\x17}\xa6_\x14'
                        'version_control_go_panel'   # b'\x81\xf4\x1d\x01 \xf3\xb1\xdc$\xf9\x02\xcex\xfe\xf7\x890Z\xb4\x98\xba\xca@\xc9\t'
                        'version_control_or_off'   # b'\x81\xf4\x1d\x01 \xf3\xb1\xdc$\xf9\x02\xcex\xfe\xf7\x890R\xa9\x98\xa5\xcdH'
                        False
                        21724
                        'version_control_work_android_x'   # b'\x81\xf4\x1d\x01 \xf3\xb1\xdc$\xf9\x02\xcex\xfe\xf7\x890J\xb4\xb5\xa1\xf4O\xc2\x01}\xacU\x04\x8e\x06'
                        2040
                        'version_control_work_android_desktop'   # b'\x81\xf4\x1d\x01 \xf3\xb1\xdc$\xf9\x02\xcex\xfe\xf7\x890J\xb4\xb5\xa1\xf4O\xc2\x01}\xacU\x04\x8e\x1a\xe0)Y4\x02\x88'
                        'control_unoffical'   # b"\x81\xe1\x17\x1d'\xe8\xb1\xde$\xef\x03\xcfj\xea\xf1\x86\x0eQ"
                        'version_control_warning_unofficial'   # b'\x81\xf4\x1d\x01 \xf3\xb1\xdc$\xf9\x02\xcex\xfe\xf7\x890J\xba\xb5\xa4\xc2@\xcb:z\xadS\x06\xb7\x17\xe63S,'
                        'version_control_app_not_supported'   # b'\x81\xf4\x1d\x01 \xf3\xb1\xdc$\xf9\x02\xcex\xfe\xf7\x890\\\xab\xb7\x95\xc5A\xd8:|\xb6L\x10\xbe\x0c\xf1?V'
                        'version_control_go_settings'   # b'\x81\xf4\x1d\x01 \xf3\xb1\xdc$\xf9\x02\xcex\xfe\xf7\x890Z\xb4\x98\xb9\xceZ\xd8\x0ca\xa4O'
                        'version_control_make_test'   # b'\x81\xf4\x1d\x01 \xf3\xb1\xdc$\xf9\x02\xcex\xfe\xf7\x890P\xba\xac\xaf\xf4Z\xc9\x16{'
                    [Disassembly]
                        0       NOP                             
                        2       NOP                             
                        4       PUSH_NULL                       
                        6       LOAD_CONST                      2: '__pyarmor_enter_16039__'
                        8       LOAD_CONST                      3: b'<COAddr>\x07\x00\x00\x1a\xc0\x0c\x00\x00\x00\x00\x00\x00\x00\x00\x00\x00\x00\x00\x00\x00'
                        10      BUILD_TUPLE                     1
                        12      CALL_FUNCTION_EX                0
                        14      POP_TOP                         
                        16      RESUME                          0
                        18      NOP                             
                        20      NOP                             
                        22      NOP                             
                        24      NOP                             
                        26      NOP                             
                        28      LOAD_FAST                       1: account
                        30      LOAD_FAST                       0: self
                        32      STORE_ATTR                      0: account
                        42      LOAD_GLOBAL                     3: NULL + int
                        52      LOAD_FAST                       2: app_id
                        54      CALL                            1
                        62      LOAD_FAST                       0: self
                        64      STORE_ATTR                      2: app_id
                        74      LOAD_GLOBAL                     7: NULL + str
                        84      LOAD_FAST                       3: version
                        86      CALL                            1
                        94      LOAD_FAST                       0: self
                        96      STORE_ATTR                      4: version
                        106     LOAD_FAST                       0: self
                        108     LOAD_ATTR                       4: app_id
                        128     LOAD_CONST                      4: 4
                        130     COMPARE_OP                      40 (==)
                        134     POP_JUMP_IF_TRUE                16 (to 168)
                        136     LOAD_FAST                       0: self
                        138     LOAD_ATTR                       4: app_id
                        158     LOAD_CONST                      5: 6
                        160     COMPARE_OP                      40 (==)
                        164     POP_JUMP_IF_FALSE               407 (to 982)
                        168     LOAD_FAST                       0: self
                        170     LOAD_ATTR                       10: config
                        190     PUSH_NULL                       
                        192     LOAD_CONST                      1: '__pyarmor_assert_16038__'
                        194     LOAD_CONST                      6: 'control_offical'   # b"\x81\xe1\x17\x1d'\xe8\xb1\xde$\xf5\x0b\xc6e\xef\xf9\x89"
                        196     CALL                            1
                        204     BINARY_SUBSCR                   
                        208     POP_JUMP_IF_FALSE               374 (to 960)
                        212     LOAD_FAST                       0: self
                        214     LOAD_ATTR                       8: version
                        234     LOAD_FAST                       0: self
                        236     LOAD_ATTR                       12: android
                        256     CONTAINS_OP                     0 (in)
                        258     POP_JUMP_IF_FALSE               11 (to 282)
                        260     NOP                             
                        262     LOAD_CONST                      8: True
                        264     NOP                             
                        266     NOP                             
                        268     JUMP_FORWARD                    1523 (to 3318)
                        278     POP_TOP                         
                        280     RETURN_CONST                    8: True
                        282     LOAD_FAST                       0: self
                        284     LOAD_ATTR                       14: log
                        304     POP_JUMP_IF_FALSE               315 (to 938)
                        308     LOAD_GLOBAL                     17: NULL + Logs
                        318     LOAD_ATTR                       18: PrintLog
                        338     LOAD_FAST                       0: self
                        340     LOAD_ATTR                       10: config
                        360     LOAD_FAST                       0: self
                        362     LOAD_ATTR                       0: account
                        382     LOAD_FAST                       0: self
                        384     LOAD_ATTR                       20: lang
                        404     PUSH_NULL                       
                        406     LOAD_CONST                      1: '__pyarmor_assert_16038__'
                        408     LOAD_CONST                      9: 'version_control_warning'   # b'\x81\xf4\x1d\x01 \xf3\xb1\xdc$\xf9\x02\xcex\xfe\xf7\x890J\xba\xb5\xa4\xc2@\xcb'
                        410     CALL                            1
                        418     BINARY_SUBSCR                   
                        422     KW_NAMES                        10: ('config', 'account', 'message')
                        424     CALL                            3
                        432     POP_TOP                         
                        434     LOAD_GLOBAL                     17: NULL + Logs
                        444     LOAD_ATTR                       18: PrintLog
                        464     LOAD_FAST                       0: self
                        466     LOAD_ATTR                       10: config
                        486     LOAD_FAST                       0: self
                        488     LOAD_ATTR                       0: account
                        508     LOAD_FAST                       0: self
                        510     LOAD_ATTR                       20: lang
                        530     PUSH_NULL                       
                        532     LOAD_CONST                      1: '__pyarmor_assert_16038__'
                        534     LOAD_CONST                      11: 'version_control_work_android'   # b'\x81\xf4\x1d\x01 \xf3\xb1\xdc$\xf9\x02\xcex\xfe\xf7\x890J\xb4\xb5\xa1\xf4O\xc2\x01}\xacU\x04'
                        536     CALL                            1
                        544     BINARY_SUBSCR                   
                        548     KW_NAMES                        10: ('config', 'account', 'message')
                        550     CALL                            3
                        558     POP_TOP                         
                        560     LOAD_GLOBAL                     17: NULL + Logs
                        570     LOAD_ATTR                       18: PrintLog
                        590     LOAD_FAST                       0: self
                        592     LOAD_ATTR                       10: config
                        612     LOAD_FAST                       0: self
                        614     LOAD_ATTR                       0: account
                        634     LOAD_FAST                       0: self
                        636     LOAD_ATTR                       20: lang
                        656     PUSH_NULL                       
                        658     LOAD_CONST                      1: '__pyarmor_assert_16038__'
                        660     LOAD_CONST                      12: 'version_control_json_correct'   # b'\x81\xf4\x1d\x01 \xf3\xb1\xdc$\xf9\x02\xcex\xfe\xf7\x890W\xa8\xa8\xa4\xf4M\xc3\x17}\xa6_\x14'
                        662     CALL                            1
                        670     BINARY_SUBSCR                   
                        674     KW_NAMES                        10: ('config', 'account', 'message')
                        676     CALL                            3
                        684     POP_TOP                         
                        686     LOAD_GLOBAL                     17: NULL + Logs
                        696     LOAD_ATTR                       18: PrintLog
                        716     LOAD_FAST                       0: self
                        718     LOAD_ATTR                       10: config
                        738     LOAD_FAST                       0: self
                        740     LOAD_ATTR                       0: account
                        760     LOAD_FAST                       0: self
                        762     LOAD_ATTR                       20: lang
                        782     PUSH_NULL                       
                        784     LOAD_CONST                      1: '__pyarmor_assert_16038__'
                        786     LOAD_CONST                      13: 'version_control_go_panel'   # b'\x81\xf4\x1d\x01 \xf3\xb1\xdc$\xf9\x02\xcex\xfe\xf7\x890Z\xb4\x98\xba\xca@\xc9\t'
                        788     CALL                            1
                        796     BINARY_SUBSCR                   
                        800     KW_NAMES                        10: ('config', 'account', 'message')
                        802     CALL                            3
                        810     POP_TOP                         
                        812     LOAD_GLOBAL                     17: NULL + Logs
                        822     LOAD_ATTR                       18: PrintLog
                        842     LOAD_FAST                       0: self
                        844     LOAD_ATTR                       10: config
                        864     LOAD_FAST                       0: self
                        866     LOAD_ATTR                       0: account
                        886     LOAD_FAST                       0: self
                        888     LOAD_ATTR                       20: lang
                        908     PUSH_NULL                       
                        910     LOAD_CONST                      1: '__pyarmor_assert_16038__'
                        912     LOAD_CONST                      14: 'version_control_or_off'   # b'\x81\xf4\x1d\x01 \xf3\xb1\xdc$\xf9\x02\xcex\xfe\xf7\x890R\xa9\x98\xa5\xcdH'
                        914     CALL                            1
                        922     BINARY_SUBSCR                   
                        926     KW_NAMES                        10: ('config', 'account', 'message')
                        928     CALL                            3
                        936     POP_TOP                         
                        938     NOP                             
                        940     LOAD_CONST                      15: False
                        942     NOP                             
                        944     NOP                             
                        946     JUMP_FORWARD                    1184 (to 3318)
                        956     POP_TOP                         
                        958     RETURN_CONST                    15: False
                        960     NOP                             
                        962     LOAD_CONST                      8: True
                        964     NOP                             
                        966     NOP                             
                        968     JUMP_FORWARD                    1173 (to 3318)
                        978     POP_TOP                         
                        980     RETURN_CONST                    8: True
                        982     LOAD_FAST                       0: self
                        984     LOAD_ATTR                       4: app_id
                        1004    LOAD_CONST                      16: 21724
                        1006    COMPARE_OP                      40 (==)
                        1010    POP_JUMP_IF_FALSE               407 (to 1828)
                        1014    LOAD_FAST                       0: self
                        1016    LOAD_ATTR                       10: config
                        1036    PUSH_NULL                       
                        1038    LOAD_CONST                      1: '__pyarmor_assert_16038__'
                        1040    LOAD_CONST                      6: 'control_offical'   # b"\x81\xe1\x17\x1d'\xe8\xb1\xde$\xf5\x0b\xc6e\xef\xf9\x89"
                        1042    CALL                            1
                        1050    BINARY_SUBSCR                   
                        1054    POP_JUMP_IF_FALSE               374 (to 1806)
                        1058    LOAD_FAST                       0: self
                        1060    LOAD_ATTR                       8: version
                        1080    LOAD_FAST                       0: self
                        1082    LOAD_ATTR                       22: android_x
                        1102    CONTAINS_OP                     0 (in)
                        1104    POP_JUMP_IF_FALSE               11 (to 1128)
                        1106    NOP                             
                        1108    LOAD_CONST                      8: True
                        1110    NOP                             
                        1112    NOP                             
                        1114    JUMP_FORWARD                    1100 (to 3318)
                        1124    POP_TOP                         
                        1126    RETURN_CONST                    8: True
                        1128    LOAD_FAST                       0: self
                        1130    LOAD_ATTR                       14: log
                        1150    POP_JUMP_IF_FALSE               315 (to 1784)
                        1154    LOAD_GLOBAL                     17: NULL + Logs
                        1164    LOAD_ATTR                       18: PrintLog
                        1184    LOAD_FAST                       0: self
                        1186    LOAD_ATTR                       10: config
                        1206    LOAD_FAST                       0: self
                        1208    LOAD_ATTR                       0: account
                        1228    LOAD_FAST                       0: self
                        1230    LOAD_ATTR                       20: lang
                        1250    PUSH_NULL                       
                        1252    LOAD_CONST                      1: '__pyarmor_assert_16038__'
                        1254    LOAD_CONST                      9: 'version_control_warning'   # b'\x81\xf4\x1d\x01 \xf3\xb1\xdc$\xf9\x02\xcex\xfe\xf7\x890J\xba\xb5\xa4\xc2@\xcb'
                        1256    CALL                            1
                        1264    BINARY_SUBSCR                   
                        1268    KW_NAMES                        10: ('config', 'account', 'message')
                        1270    CALL                            3
                        1278    POP_TOP                         
                        1280    LOAD_GLOBAL                     17: NULL + Logs
                        1290    LOAD_ATTR                       18: PrintLog
                        1310    LOAD_FAST                       0: self
                        1312    LOAD_ATTR                       10: config
                        1332    LOAD_FAST                       0: self
                        1334    LOAD_ATTR                       0: account
                        1354    LOAD_FAST                       0: self
                        1356    LOAD_ATTR                       20: lang
                        1376    PUSH_NULL                       
                        1378    LOAD_CONST                      1: '__pyarmor_assert_16038__'
                        1380    LOAD_CONST                      17: 'version_control_work_android_x'   # b'\x81\xf4\x1d\x01 \xf3\xb1\xdc$\xf9\x02\xcex\xfe\xf7\x890J\xb4\xb5\xa1\xf4O\xc2\x01}\xacU\x04\x8e\x06'
                        1382    CALL                            1
                        1390    BINARY_SUBSCR                   
                        1394    KW_NAMES                        10: ('config', 'account', 'message')
                        1396    CALL                            3
                        1404    POP_TOP                         
                        1406    LOAD_GLOBAL                     17: NULL + Logs
                        1416    LOAD_ATTR                       18: PrintLog
                        1436    LOAD_FAST                       0: self
                        1438    LOAD_ATTR                       10: config
                        1458    LOAD_FAST                       0: self
                        1460    LOAD_ATTR                       0: account
                        1480    LOAD_FAST                       0: self
                        1482    LOAD_ATTR                       20: lang
                        1502    PUSH_NULL                       
                        1504    LOAD_CONST                      1: '__pyarmor_assert_16038__'
                        1506    LOAD_CONST                      12: 'version_control_json_correct'   # b'\x81\xf4\x1d\x01 \xf3\xb1\xdc$\xf9\x02\xcex\xfe\xf7\x890W\xa8\xa8\xa4\xf4M\xc3\x17}\xa6_\x14'
                        1508    CALL                            1
                        1516    BINARY_SUBSCR                   
                        1520    KW_NAMES                        10: ('config', 'account', 'message')
                        1522    CALL                            3
                        1530    POP_TOP                         
                        1532    LOAD_GLOBAL                     17: NULL + Logs
                        1542    LOAD_ATTR                       18: PrintLog
                        1562    LOAD_FAST                       0: self
                        1564    LOAD_ATTR                       10: config
                        1584    LOAD_FAST                       0: self
                        1586    LOAD_ATTR                       0: account
                        1606    LOAD_FAST                       0: self
                        1608    LOAD_ATTR                       20: lang
                        1628    PUSH_NULL                       
                        1630    LOAD_CONST                      1: '__pyarmor_assert_16038__'
                        1632    LOAD_CONST                      13: 'version_control_go_panel'   # b'\x81\xf4\x1d\x01 \xf3\xb1\xdc$\xf9\x02\xcex\xfe\xf7\x890Z\xb4\x98\xba\xca@\xc9\t'
                        1634    CALL                            1
                        1642    BINARY_SUBSCR                   
                        1646    KW_NAMES                        10: ('config', 'account', 'message')
                        1648    CALL                            3
                        1656    POP_TOP                         
                        1658    LOAD_GLOBAL                     17: NULL + Logs
                        1668    LOAD_ATTR                       18: PrintLog
                        1688    LOAD_FAST                       0: self
                        1690    LOAD_ATTR                       10: config
                        1710    LOAD_FAST                       0: self
                        1712    LOAD_ATTR                       0: account
                        1732    LOAD_FAST                       0: self
                        1734    LOAD_ATTR                       20: lang
                        1754    PUSH_NULL                       
                        1756    LOAD_CONST                      1: '__pyarmor_assert_16038__'
                        1758    LOAD_CONST                      14: 'version_control_or_off'   # b'\x81\xf4\x1d\x01 \xf3\xb1\xdc$\xf9\x02\xcex\xfe\xf7\x890R\xa9\x98\xa5\xcdH'
                        1760    CALL                            1
                        1768    BINARY_SUBSCR                   
                        1772    KW_NAMES                        10: ('config', 'account', 'message')
                        1774    CALL                            3
                        1782    POP_TOP                         
                        1784    NOP                             
                        1786    LOAD_CONST                      15: False
                        1788    NOP                             
                        1790    NOP                             
                        1792    JUMP_FORWARD                    761 (to 3318)
                        1802    POP_TOP                         
                        1804    RETURN_CONST                    15: False
                        1806    NOP                             
                        1808    LOAD_CONST                      8: True
                        1810    NOP                             
                        1812    NOP                             
                        1814    JUMP_FORWARD                    750 (to 3318)
                        1824    POP_TOP                         
                        1826    RETURN_CONST                    8: True
                        1828    LOAD_FAST                       0: self
                        1830    LOAD_ATTR                       4: app_id
                        1850    LOAD_CONST                      18: 2040
                        1852    COMPARE_OP                      40 (==)
                        1856    POP_JUMP_IF_FALSE               407 (to 2674)
                        1860    LOAD_FAST                       0: self
                        1862    LOAD_ATTR                       10: config
                        1882    PUSH_NULL                       
                        1884    LOAD_CONST                      1: '__pyarmor_assert_16038__'
                        1886    LOAD_CONST                      6: 'control_offical'   # b"\x81\xe1\x17\x1d'\xe8\xb1\xde$\xf5\x0b\xc6e\xef\xf9\x89"
                        1888    CALL                            1
                        1896    BINARY_SUBSCR                   
                        1900    POP_JUMP_IF_FALSE               374 (to 2652)
                        1904    LOAD_FAST                       0: self
                        1906    LOAD_ATTR                       8: version
                        1926    LOAD_FAST                       0: self
                        1928    LOAD_ATTR                       24: desktop
                        1948    CONTAINS_OP                     0 (in)
                        1950    POP_JUMP_IF_FALSE               11 (to 1974)
                        1952    NOP                             
                        1954    LOAD_CONST                      8: True
                        1956    NOP                             
                        1958    NOP                             
                        1960    JUMP_FORWARD                    677 (to 3318)
                        1970    POP_TOP                         
                        1972    RETURN_CONST                    8: True
                        1974    LOAD_FAST                       0: self
                        1976    LOAD_ATTR                       14: log
                        1996    POP_JUMP_IF_FALSE               315 (to 2630)
                        2000    LOAD_GLOBAL                     17: NULL + Logs
                        2010    LOAD_ATTR                       18: PrintLog
                        2030    LOAD_FAST                       0: self
                        2032    LOAD_ATTR                       10: config
                        2052    LOAD_FAST                       0: self
                        2054    LOAD_ATTR                       0: account
                        2074    LOAD_FAST                       0: self
                        2076    LOAD_ATTR                       20: lang
                        2096    PUSH_NULL                       
                        2098    LOAD_CONST                      1: '__pyarmor_assert_16038__'
                        2100    LOAD_CONST                      9: 'version_control_warning'   # b'\x81\xf4\x1d\x01 \xf3\xb1\xdc$\xf9\x02\xcex\xfe\xf7\x890J\xba\xb5\xa4\xc2@\xcb'
                        2102    CALL                            1
                        2110    BINARY_SUBSCR                   
                        2114    KW_NAMES                        10: ('config', 'account', 'message')
                        2116    CALL                            3
                        2124    POP_TOP                         
                        2126    LOAD_GLOBAL                     17: NULL + Logs
                        2136    LOAD_ATTR                       18: PrintLog
                        2156    LOAD_FAST                       0: self
                        2158    LOAD_ATTR                       10: config
                        2178    LOAD_FAST                       0: self
                        2180    LOAD_ATTR                       0: account
                        2200    LOAD_FAST                       0: self
                        2202    LOAD_ATTR                       20: lang
                        2222    PUSH_NULL                       
                        2224    LOAD_CONST                      1: '__pyarmor_assert_16038__'
                        2226    LOAD_CONST                      19: 'version_control_work_android_desktop'   # b'\x81\xf4\x1d\x01 \xf3\xb1\xdc$\xf9\x02\xcex\xfe\xf7\x890J\xb4\xb5\xa1\xf4O\xc2\x01}\xacU\x04\x8e\x1a\xe0)Y4\x02\x88'
                        2228    CALL                            1
                        2236    BINARY_SUBSCR                   
                        2240    KW_NAMES                        10: ('config', 'account', 'message')
                        2242    CALL                            3
                        2250    POP_TOP                         
                        2252    LOAD_GLOBAL                     17: NULL + Logs
                        2262    LOAD_ATTR                       18: PrintLog
                        2282    LOAD_FAST                       0: self
                        2284    LOAD_ATTR                       10: config
                        2304    LOAD_FAST                       0: self
                        2306    LOAD_ATTR                       0: account
                        2326    LOAD_FAST                       0: self
                        2328    LOAD_ATTR                       20: lang
                        2348    PUSH_NULL                       
                        2350    LOAD_CONST                      1: '__pyarmor_assert_16038__'
                        2352    LOAD_CONST                      12: 'version_control_json_correct'   # b'\x81\xf4\x1d\x01 \xf3\xb1\xdc$\xf9\x02\xcex\xfe\xf7\x890W\xa8\xa8\xa4\xf4M\xc3\x17}\xa6_\x14'
                        2354    CALL                            1
                        2362    BINARY_SUBSCR                   
                        2366    KW_NAMES                        10: ('config', 'account', 'message')
                        2368    CALL                            3
                        2376    POP_TOP                         
                        2378    LOAD_GLOBAL                     17: NULL + Logs
                        2388    LOAD_ATTR                       18: PrintLog
                        2408    LOAD_FAST                       0: self
                        2410    LOAD_ATTR                       10: config
                        2430    LOAD_FAST                       0: self
                        2432    LOAD_ATTR                       0: account
                        2452    LOAD_FAST                       0: self
                        2454    LOAD_ATTR                       20: lang
                        2474    PUSH_NULL                       
                        2476    LOAD_CONST                      1: '__pyarmor_assert_16038__'
                        2478    LOAD_CONST                      13: 'version_control_go_panel'   # b'\x81\xf4\x1d\x01 \xf3\xb1\xdc$\xf9\x02\xcex\xfe\xf7\x890Z\xb4\x98\xba\xca@\xc9\t'
                        2480    CALL                            1
                        2488    BINARY_SUBSCR                   
                        2492    KW_NAMES                        10: ('config', 'account', 'message')
                        2494    CALL                            3
                        2502    POP_TOP                         
                        2504    LOAD_GLOBAL                     17: NULL + Logs
                        2514    LOAD_ATTR                       18: PrintLog
                        2534    LOAD_FAST                       0: self
                        2536    LOAD_ATTR                       10: config
                        2556    LOAD_FAST                       0: self
                        2558    LOAD_ATTR                       0: account
                        2578    LOAD_FAST                       0: self
                        2580    LOAD_ATTR                       20: lang
                        2600    PUSH_NULL                       
                        2602    LOAD_CONST                      1: '__pyarmor_assert_16038__'
                        2604    LOAD_CONST                      14: 'version_control_or_off'   # b'\x81\xf4\x1d\x01 \xf3\xb1\xdc$\xf9\x02\xcex\xfe\xf7\x890R\xa9\x98\xa5\xcdH'
                        2606    CALL                            1
                        2614    BINARY_SUBSCR                   
                        2618    KW_NAMES                        10: ('config', 'account', 'message')
                        2620    CALL                            3
                        2628    POP_TOP                         
                        2630    NOP                             
                        2632    LOAD_CONST                      15: False
                        2634    NOP                             
                        2636    NOP                             
                        2638    JUMP_FORWARD                    338 (to 3318)
                        2648    POP_TOP                         
                        2650    RETURN_CONST                    15: False
                        2652    NOP                             
                        2654    LOAD_CONST                      8: True
                        2656    NOP                             
                        2658    NOP                             
                        2660    JUMP_FORWARD                    327 (to 3318)
                        2670    POP_TOP                         
                        2672    RETURN_CONST                    8: True
                        2674    LOAD_FAST                       0: self
                        2676    LOAD_ATTR                       10: config
                        2696    PUSH_NULL                       
                        2698    LOAD_CONST                      1: '__pyarmor_assert_16038__'
                        2700    LOAD_CONST                      20: 'control_unoffical'   # b"\x81\xe1\x17\x1d'\xe8\xb1\xde$\xef\x03\xcfj\xea\xf1\x86\x0eQ"
                        2702    CALL                            1
                        2710    BINARY_SUBSCR                   
                        2714    POP_JUMP_IF_FALSE               275 (to 3268)
                        2718    LOAD_FAST                       0: self
                        2720    LOAD_ATTR                       14: log
                        2740    POP_JUMP_IF_FALSE               252 (to 3246)
                        2742    LOAD_GLOBAL                     17: NULL + Logs
                        2752    LOAD_ATTR                       18: PrintLog
                        2772    LOAD_FAST                       0: self
                        2774    LOAD_ATTR                       10: config
                        2794    LOAD_FAST                       0: self
                        2796    LOAD_ATTR                       0: account
                        2816    LOAD_FAST                       0: self
                        2818    LOAD_ATTR                       20: lang
                        2838    PUSH_NULL                       
                        2840    LOAD_CONST                      1: '__pyarmor_assert_16038__'
                        2842    LOAD_CONST                      21: 'version_control_warning_unofficial'   # b'\x81\xf4\x1d\x01 \xf3\xb1\xdc$\xf9\x02\xcex\xfe\xf7\x890J\xba\xb5\xa4\xc2@\xcb:z\xadS\x06\xb7\x17\xe63S,'
                        2844    CALL                            1
                        2852    BINARY_SUBSCR                   
                        2856    KW_NAMES                        10: ('config', 'account', 'message')
                        2858    CALL                            3
                        2866    POP_TOP                         
                        2868    LOAD_GLOBAL                     17: NULL + Logs
                        2878    LOAD_ATTR                       18: PrintLog
                        2898    LOAD_FAST                       0: self
                        2900    LOAD_ATTR                       10: config
                        2920    LOAD_FAST                       0: self
                        2922    LOAD_ATTR                       0: account
                        2942    LOAD_FAST                       0: self
                        2944    LOAD_ATTR                       20: lang
                        2964    PUSH_NULL                       
                        2966    LOAD_CONST                      1: '__pyarmor_assert_16038__'
                        2968    LOAD_CONST                      22: 'version_control_app_not_supported'   # b'\x81\xf4\x1d\x01 \xf3\xb1\xdc$\xf9\x02\xcex\xfe\xf7\x890\\\xab\xb7\x95\xc5A\xd8:|\xb6L\x10\xbe\x0c\xf1?V'
                        2970    CALL                            1
                        2978    BINARY_SUBSCR                   
                        2982    KW_NAMES                        10: ('config', 'account', 'message')
                        2984    CALL                            3
                        2992    POP_TOP                         
                        2994    LOAD_GLOBAL                     17: NULL + Logs
                        3004    LOAD_ATTR                       18: PrintLog
                        3024    LOAD_FAST                       0: self
                        3026    LOAD_ATTR                       10: config
                        3046    LOAD_FAST                       0: self
                        3048    LOAD_ATTR                       0: account
                        3068    LOAD_FAST                       0: self
                        3070    LOAD_ATTR                       20: lang
                        3090    PUSH_NULL                       
                        3092    LOAD_CONST                      1: '__pyarmor_assert_16038__'
                        3094    LOAD_CONST                      23: 'version_control_go_settings'   # b'\x81\xf4\x1d\x01 \xf3\xb1\xdc$\xf9\x02\xcex\xfe\xf7\x890Z\xb4\x98\xb9\xceZ\xd8\x0ca\xa4O'
                        3096    CALL                            1
                        3104    BINARY_SUBSCR                   
                        3108    KW_NAMES                        10: ('config', 'account', 'message')
                        3110    CALL                            3
                        3118    POP_TOP                         
                        3120    LOAD_GLOBAL                     17: NULL + Logs
                        3130    LOAD_ATTR                       18: PrintLog
                        3150    LOAD_FAST                       0: self
                        3152    LOAD_ATTR                       10: config
                        3172    LOAD_FAST                       0: self
                        3174    LOAD_ATTR                       0: account
                        3194    LOAD_FAST                       0: self
                        3196    LOAD_ATTR                       20: lang
                        3216    PUSH_NULL                       
                        3218    LOAD_CONST                      1: '__pyarmor_assert_16038__'
                        3220    LOAD_CONST                      24: 'version_control_make_test'   # b'\x81\xf4\x1d\x01 \xf3\xb1\xdc$\xf9\x02\xcex\xfe\xf7\x890P\xba\xac\xaf\xf4Z\xc9\x16{'
                        3222    CALL                            1
                        3230    BINARY_SUBSCR                   
                        3234    KW_NAMES                        10: ('config', 'account', 'message')
                        3236    CALL                            3
                        3244    POP_TOP                         
                        3246    NOP                             
                        3248    LOAD_CONST                      15: False
                        3250    NOP                             
                        3252    NOP                             
                        3254    NOP                             
                        3256    JUMP_FORWARD                    30 (to 3318)
                        3264    POP_TOP                         
                        3266    RETURN_CONST                    15: False
                        3268    NOP                             
                        3270    LOAD_CONST                      8: True
                        3272    NOP                             
                        3274    NOP                             
                        3276    NOP                             
                        3278    JUMP_FORWARD                    19 (to 3318)
                        3286    POP_TOP                         
                        3288    RETURN_CONST                    8: True
                        3290    PUSH_EXC_INFO                   
                        3292    PUSH_NULL                       
                        3294    LOAD_CONST                      7: '__pyarmor_exit_16040__'
                        3296    NOP                             
                        3298    LOAD_CONST                      3: b'<COAddr>\x07\x00\x00\x1a\xc0\x0c\x00\x00\x00\x00\x00\x00\x00\x00\x00\x00\x00\x00\x00\x00'
                        3300    CALL                            1
                        3308    POP_TOP                         
                        3310    RERAISE                         0
                        3312    COPY                            3
                        3314    POP_EXCEPT                      
                        3316    RERAISE                         1
                        3318    PUSH_NULL                       
                        3320    LOAD_CONST                      7: '__pyarmor_exit_16040__'
                        3322    LOAD_CONST                      3: b'<COAddr>\x07\x00\x00\x1a\xc0\x0c\x00\x00\x00\x00\x00\x00\x00\x00\x00\x00\x00\x00\x00\x00'
                        3324    BUILD_TUPLE                     1
                        3326    CALL_FUNCTION_EX                0
                        3328    POP_TOP                         
                        3330    RETURN_VALUE                    
                    [Exception Table]
                        28 to 260 -> 3290 [0] 
                        282 to 938 -> 3290 [0] 
                        982 to 1106 -> 3290 [0] 
                        1128 to 1784 -> 3290 [0] 
                        1828 to 1952 -> 3290 [0] 
                        1974 to 2630 -> 3290 [0] 
                        2674 to 3246 -> 3290 [0] 
                        3290 to 3312 -> 3312 [1] lasti
                '__pyarmor_exit_16034__'
                (
                    None
                    None
                    True
                )
                (
                    'return'
                    None
                )
                (
                    ''
                    None
                    None
                )
            [Disassembly]
                0       NOP                             
                2       LOAD_NAME                       0: __name__
                4       STORE_NAME                      1: __module__
                6       LOAD_CONST                      0: 'VersionControl'
                8       STORE_NAME                      2: __qualname__
                10      NOP                             
                12      PUSH_NULL                       
                14      LOAD_CONST                      2: '__pyarmor_enter_16033__'
                16      LOAD_CONST                      3: b'<COAddr>\x07\x00\x00"(\x00\x00\x00\x00\x00\x00\x00\x00\x00\x00\x00\x00\x00\x00\x00'
                18      BUILD_TUPLE                     1
                20      CALL_FUNCTION_EX                0
                22      POP_TOP                         
                24      RESUME                          0
                26      NOP                             
                28      NOP                             
                30      NOP                             
                32      NOP                             
                34      NOP                             
                36      LOAD_CONST                      8: (None, None, True)
                38      LOAD_CONST                      9: ('return', None)
                40      LOAD_CONST                      5: <CODE> __init__
                42      MAKE_FUNCTION                   5
                44      STORE_NAME                      4: __init__
                46      LOAD_CONST                      10: ('', None, None)
                48      LOAD_CONST                      6: <CODE> check
                50      MAKE_FUNCTION                   1
                52      STORE_NAME                      5: check
                54      LOAD_CONST                      4: None
                56      NOP                             
                58      NOP                             
                60      NOP                             
                62      JUMP_FORWARD                    19 (to 102)
                70      POP_TOP                         
                72      RETURN_CONST                    4: None
                74      PUSH_EXC_INFO                   
                76      PUSH_NULL                       
                78      LOAD_CONST                      7: '__pyarmor_exit_16034__'
                80      NOP                             
                82      LOAD_CONST                      3: b'<COAddr>\x07\x00\x00"(\x00\x00\x00\x00\x00\x00\x00\x00\x00\x00\x00\x00\x00\x00\x00'
                84      CALL                            1
                92      POP_TOP                         
                94      RERAISE                         0
                96      COPY                            3
                98      POP_EXCEPT                      
                100     RERAISE                         1
                102     PUSH_NULL                       
                104     LOAD_CONST                      7: '__pyarmor_exit_16034__'
                106     LOAD_CONST                      3: b'<COAddr>\x07\x00\x00"(\x00\x00\x00\x00\x00\x00\x00\x00\x00\x00\x00\x00\x00\x00\x00'
                108     BUILD_TUPLE                     1
                110     CALL_FUNCTION_EX                0
                112     POP_TOP                         
                114     RETURN_VALUE                    
            [Exception Table]
                36 to 54 -> 74 [0] 
                74 to 96 -> 96 [1] lasti
        'VersionControl'
        '__pyarmor_exit_16031__'
        None
    [Disassembly]
        0       NOP                             
        2       NOP                             
        4       PUSH_NULL                       
        6       LOAD_CONST                      1: '__pyarmor_enter_16030__'
        8       LOAD_CONST                      2: b'<COAddr>\x05\x00\x00\x1a4\x00\x00\x00\x00\x00\x00\x00\x00\x00\x00\x00\x00\x00\x00\x00'
        10      BUILD_TUPLE                     1
        12      CALL_FUNCTION_EX                0
        14      POP_TOP                         
        16      RESUME                          0
        18      NOP                             
        20      NOP                             
        22      NOP                             
        24      NOP                             
        26      LOAD_CONST                      3: 0
        28      LOAD_CONST                      4: ('Logs',)
        30      IMPORT_NAME                     1: program.static_classes
        32      IMPORT_FROM                     2: Logs
        34      STORE_NAME                      2: Logs
        36      POP_TOP                         
        38      PUSH_NULL                       
        40      LOAD_BUILD_CLASS                
        42      LOAD_CONST                      5: <CODE> VersionControl
        44      MAKE_FUNCTION                   0
        46      LOAD_CONST                      6: 'VersionControl'
        48      CALL                            2
        56      STORE_NAME                      3: VersionControl
        58      LOAD_CONST                      8: None
        60      NOP                             
        62      NOP                             
        64      NOP                             
        66      JUMP_FORWARD                    19 (to 106)
        74      POP_TOP                         
        76      RETURN_CONST                    8: None
        78      PUSH_EXC_INFO                   
        80      PUSH_NULL                       
        82      LOAD_CONST                      7: '__pyarmor_exit_16031__'
        84      NOP                             
        86      LOAD_CONST                      2: b'<COAddr>\x05\x00\x00\x1a4\x00\x00\x00\x00\x00\x00\x00\x00\x00\x00\x00\x00\x00\x00\x00'
        88      CALL                            1
        96      POP_TOP                         
        98      RERAISE                         0
        100     COPY                            3
        102     POP_EXCEPT                      
        104     RERAISE                         1
        106     PUSH_NULL                       
        108     LOAD_CONST                      7: '__pyarmor_exit_16031__'
        110     LOAD_CONST                      2: b'<COAddr>\x05\x00\x00\x1a4\x00\x00\x00\x00\x00\x00\x00\x00\x00\x00\x00\x00\x00\x00\x00'
        112     BUILD_TUPLE                     1
        114     CALL_FUNCTION_EX                0
        116     POP_TOP                         
        118     RETURN_VALUE                    
    [Exception Table]
        26 to 58 -> 78 [0] 
        78 to 100 -> 100 [1] lasti
