#decoded by lolz.live/mrpenny / t.me/zeus_jackpot
# ================================
# Примечания по Pyarmor:
# - Байт-код и объекты кода Pyarmor соответствуют стандартному Python, но присутствуют специальные вызовы функций среды выполнения (runtime) Pyarmor.
# - Вызовы строк — это не ошибки, а маркеры, которые обрабатываются Pyarmor во время выполнения.
#
# Руководство по декомпиляции (без среды выполнения):
# 1. Игнорируйте зашифрованные байты после `#`; используйте только строку до `#`.
# 2. Удалите "__pyarmor_enter_xxx__"(b"<COAddr>...") и "__pyarmor_leave_xxx__"(b"<COAddr>...") (пролог/эпилог).
# 3. "__pyarmor_assert_xxx__"(A) не является настоящим оператором assert.
#    - Если A — это имя или читаемая строка: замените на A.
#    - Если A — это (X, "Y"): замените на X.Y.
#    - Если A — это (X, "Y", Z): замените на X.Y = Z.
#    - В противном случае: выберите наиболее подходящую/логичную замену.
# 4. "__pyarmor_bcc_xxx__"(...) указывает на машинный (нативный) код; тело функции недоступно. Добавьте комментарий.
# ================================

[Code]
    File Name: <frozen program.modules.func.android>
    Object Name: <module>
    Qualified Name: <module>
    Arg Count: 0
    Pos Only Arg Count: 0
    KW Only Arg Count: 0
    Stack Size: 5
    Flags: 0x20000000 (CO_PYARMOR_OBFUSCATED)
    [Names]
        '__assert_armored__'
        'time'
        'random'
        'string'
        'datetime'
        'multithon.sync'
        'functions'
        'types'
        'AndroidRequests'
    [Locals+Names]
    [Constants]
        '__pyarmor_assert_14874__'
        '__pyarmor_enter_14875__'
        b'<COAddr>\x07\x00\x00\x1aX\x00\x00\x00\x00\x00\x00\x00\x00\x00\x00\x00\x00\x00\x00\x00'
        0
        None
        (
            'functions'
            'types'
        )
        [Code]
            File Name: <frozen program.modules.func.android>
            Object Name: AndroidRequests
            Qualified Name: AndroidRequests
            Arg Count: 0
            Pos Only Arg Count: 0
            KW Only Arg Count: 0
            Stack Size: 5
            Flags: 0x20000000 (CO_PYARMOR_OBFUSCATED)
            [Names]
                '__name__'
                '__module__'
                '__qualname__'
                '__assert_armored__'
                '__init__'
                'staticmethod'
                'timer'
                '_random_search'
                'reg_start'
                'reg_middle'
                'reg_end'
                'check'
                'work'
            [Locals+Names]
            [Constants]
                'AndroidRequests'
                '__pyarmor_assert_14877__'
                '__pyarmor_enter_14878__'
                b'<COAddr>\x07\x00\x00"T\x00\x00\x00\x00\x00\x00\x00\x00\x00\x00\x00\x00\x00\x00\x00'
                None
                [Code]
                    File Name: <frozen program.modules.func.android>
                    Object Name: __init__
                    Qualified Name: AndroidRequests.__init__
                    Arg Count: 4
                    Pos Only Arg Count: 0
                    KW Only Arg Count: 0
                    Stack Size: 5
                    Flags: 0x20000003 (CO_OPTIMIZED | CO_NEWLOCALS | CO_PYARMOR_OBFUSCATED)
                    [Names]
                        'option_reg'
                        'option_work'
                        'option_check'
                        'client'
                        'int'
                        'app_id'
                        'lang_code'
                        'os'
                    [Locals+Names]
                        'self'
                        'client'
                        'app_id'
                        'lang_code'
                        '__assert_armored__'
                    [Constants]
                        None
                        '__pyarmor_assert_14880__'
                        '__pyarmor_enter_14881__'
                        b'<COAddr>\x07\x00\x00\x1a\xd6\x01\x00\x00\x00\x00\x00\x00\x00\x00\x00\x00\x00\x00\x00\x00'
                        True
                        False
                        4
                        6
                        'android'
                        1
                        8
                        'ios'
                        21724
                        'android_x'   # b'\x81\xe3\x16\x17!\xf5\xb7\xd6$\xe2'
                        2040
                        'tdesktop'
                        10840
                        2834
                        'macos'
                        '__pyarmor_exit_14882__'
                    [Disassembly]
                        0       NOP                             
                        2       NOP                             
                        4       PUSH_NULL                       
                        6       LOAD_CONST                      2: '__pyarmor_enter_14881__'
                        8       LOAD_CONST                      3: b'<COAddr>\x07\x00\x00\x1a\xd6\x01\x00\x00\x00\x00\x00\x00\x00\x00\x00\x00\x00\x00\x00\x00'
                        10      BUILD_TUPLE                     1
                        12      CALL_FUNCTION_EX                0
                        14      POP_TOP                         
                        16      RESUME                          0
                        18      NOP                             
                        20      NOP                             
                        22      NOP                             
                        24      NOP                             
                        26      NOP                             
                        28      LOAD_CONST                      4: True
                        30      LOAD_FAST                       0: self
                        32      STORE_ATTR                      0: option_reg
                        42      LOAD_CONST                      5: False
                        44      LOAD_FAST                       0: self
                        46      STORE_ATTR                      1: option_work
                        56      LOAD_CONST                      5: False
                        58      LOAD_FAST                       0: self
                        60      STORE_ATTR                      2: option_check
                        70      LOAD_FAST                       1: client
                        72      LOAD_FAST                       0: self
                        74      STORE_ATTR                      3: client
                        84      LOAD_GLOBAL                     9: NULL + int
                        94      LOAD_FAST                       2: app_id
                        96      CALL                            1
                        104     LOAD_FAST                       0: self
                        106     STORE_ATTR                      5: app_id
                        116     LOAD_FAST                       3: lang_code
                        118     LOAD_FAST                       0: self
                        120     STORE_ATTR                      6: lang_code
                        130     LOAD_FAST                       0: self
                        132     LOAD_ATTR                       10: app_id
                        152     LOAD_CONST                      6: 4
                        154     COMPARE_OP                      40 (==)
                        158     POP_JUMP_IF_TRUE                15 (to 190)
                        160     LOAD_FAST                       0: self
                        162     LOAD_ATTR                       10: app_id
                        182     LOAD_CONST                      7: 6
                        184     COMPARE_OP                      40 (==)
                        188     POP_JUMP_IF_FALSE               8 (to 206)
                        190     LOAD_CONST                      8: 'android'
                        192     LOAD_FAST                       0: self
                        194     STORE_ATTR                      7: os
                        204     JUMP_FORWARD                    135 (to 476)
                        206     LOAD_FAST                       0: self
                        208     LOAD_ATTR                       10: app_id
                        228     LOAD_CONST                      9: 1
                        230     COMPARE_OP                      40 (==)
                        234     POP_JUMP_IF_TRUE                15 (to 266)
                        236     LOAD_FAST                       0: self
                        238     LOAD_ATTR                       10: app_id
                        258     LOAD_CONST                      10: 8
                        260     COMPARE_OP                      40 (==)
                        264     POP_JUMP_IF_FALSE               8 (to 282)
                        266     LOAD_CONST                      11: 'ios'
                        268     LOAD_FAST                       0: self
                        270     STORE_ATTR                      7: os
                        280     JUMP_FORWARD                    97 (to 476)
                        282     LOAD_FAST                       0: self
                        284     LOAD_ATTR                       10: app_id
                        304     LOAD_CONST                      12: 21724
                        306     COMPARE_OP                      40 (==)
                        310     POP_JUMP_IF_FALSE               14 (to 340)
                        312     PUSH_NULL                       
                        314     LOAD_CONST                      1: '__pyarmor_assert_14880__'
                        316     LOAD_CONST                      13: 'android_x'   # b'\x81\xe3\x16\x17!\xf5\xb7\xd6$\xe2'
                        318     CALL                            1
                        326     LOAD_FAST                       0: self
                        328     STORE_ATTR                      7: os
                        338     JUMP_FORWARD                    68 (to 476)
                        340     LOAD_FAST                       0: self
                        342     LOAD_ATTR                       10: app_id
                        362     LOAD_CONST                      14: 2040
                        364     COMPARE_OP                      40 (==)
                        368     POP_JUMP_IF_FALSE               8 (to 386)
                        370     LOAD_CONST                      15: 'tdesktop'
                        372     LOAD_FAST                       0: self
                        374     STORE_ATTR                      7: os
                        384     JUMP_FORWARD                    45 (to 476)
                        386     LOAD_FAST                       0: self
                        388     LOAD_ATTR                       10: app_id
                        408     LOAD_CONST                      16: 10840
                        410     COMPARE_OP                      40 (==)
                        414     POP_JUMP_IF_TRUE                15 (to 446)
                        416     LOAD_FAST                       0: self
                        418     LOAD_ATTR                       10: app_id
                        438     LOAD_CONST                      17: 2834
                        440     COMPARE_OP                      40 (==)
                        444     POP_JUMP_IF_FALSE               8 (to 462)
                        446     LOAD_CONST                      18: 'macos'
                        448     LOAD_FAST                       0: self
                        450     STORE_ATTR                      7: os
                        460     JUMP_FORWARD                    7 (to 476)
                        462     LOAD_CONST                      8: 'android'
                        464     LOAD_FAST                       0: self
                        466     STORE_ATTR                      7: os
                        476     LOAD_CONST                      0: None
                        478     NOP                             
                        480     NOP                             
                        482     NOP                             
                        484     JUMP_FORWARD                    19 (to 524)
                        492     POP_TOP                         
                        494     RETURN_CONST                    0: None
                        496     PUSH_EXC_INFO                   
                        498     PUSH_NULL                       
                        500     LOAD_CONST                      19: '__pyarmor_exit_14882__'
                        502     NOP                             
                        504     LOAD_CONST                      3: b'<COAddr>\x07\x00\x00\x1a\xd6\x01\x00\x00\x00\x00\x00\x00\x00\x00\x00\x00\x00\x00\x00\x00'
                        506     CALL                            1
                        514     POP_TOP                         
                        516     RERAISE                         0
                        518     COPY                            3
                        520     POP_EXCEPT                      
                        522     RERAISE                         1
                        524     PUSH_NULL                       
                        526     LOAD_CONST                      19: '__pyarmor_exit_14882__'
                        528     LOAD_CONST                      3: b'<COAddr>\x07\x00\x00\x1a\xd6\x01\x00\x00\x00\x00\x00\x00\x00\x00\x00\x00\x00\x00\x00\x00'
                        530     BUILD_TUPLE                     1
                        532     CALL_FUNCTION_EX                0
                        534     POP_TOP                         
                        536     RETURN_VALUE                    
                    [Exception Table]
                        28 to 476 -> 496 [0] 
                        496 to 518 -> 518 [1] lasti
                [Code]
                    File Name: <frozen program.modules.func.android>
                    Object Name: timer
                    Qualified Name: AndroidRequests.timer
                    Arg Count: 1
                    Pos Only Arg Count: 0
                    KW Only Arg Count: 0
                    Stack Size: 5
                    Flags: 0x20000003 (CO_OPTIMIZED | CO_NEWLOCALS | CO_PYARMOR_OBFUSCATED)
                    [Names]
                    [Locals+Names]
                        'func'
                        '__assert_armored__'
                        '_var_var_0'
                    [Constants]
                        None
                        '__pyarmor_assert_14883__'
                        '__pyarmor_enter_14884__'
                        b'<COAddr>\x07\x00\x00\x1c"\x00\x00\x00\x00\x00\x00\x00\x00\x00\x00\x00\x00\x00\x00\x00'
                        [Code]
                            File Name: <frozen program.modules.func.android>
                            Object Name: wrapper
                            Qualified Name: AndroidRequests.timer.<locals>.wrapper
                            Arg Count: 0
                            Pos Only Arg Count: 0
                            KW Only Arg Count: 0
                            Stack Size: 5
                            Flags: 0x2000001F (CO_OPTIMIZED | CO_NEWLOCALS | CO_VARARGS | CO_VARKEYWORDS | CO_NESTED | CO_PYARMOR_OBFUSCATED)
                            [Names]
                                'time'
                                'print'
                            [Locals+Names]
                                'args'
                                'kwargs'
                                '__assert_armored__'
                                '_var_var_1'
                                '_var_var_2'
                                '_var_var_3'
                                '_var_var_4'
                                'func'
                            [Constants]
                                None
                                '__pyarmor_assert_14886__'
                                '__pyarmor_enter_14887__'
                                b'<COAddr>\x07\x00\x00\x1c\xac\x00\x00\x00\x00\x00\x00\x00\x00\x00\x00\x00\x00\x00\x00\x00'
                                'Функция выполнена за '   # b'\x81R\xdc\xa2\xd0Jcb\xc1K\xebp\xb4]\x17\xc5\xbf\x8f\nL\x1a\x14\xfe\x12\xb5\xb4\x13\x81\xb0d\xae8\x8a\x82`\xbdOzdn'
                                ' секунд'
                                '__pyarmor_exit_14888__'
                            [Disassembly]
                                0       COPY_FREE_VARS                  1
                                2       NOP                             
                                4       NOP                             
                                6       PUSH_NULL                       
                                8       LOAD_CONST                      2: '__pyarmor_enter_14887__'
                                10      LOAD_CONST                      3: b'<COAddr>\x07\x00\x00\x1c\xac\x00\x00\x00\x00\x00\x00\x00\x00\x00\x00\x00\x00\x00\x00\x00'
                                12      BUILD_TUPLE                     1
                                14      CALL_FUNCTION_EX                0
                                16      POP_TOP                         
                                18      RESUME                          0
                                20      NOP                             
                                22      NOP                             
                                24      NOP                             
                                26      NOP                             
                                28      NOP                             
                                30      LOAD_GLOBAL                     1: NULL + time
                                40      LOAD_ATTR                       0: time
                                60      CALL                            0
                                68      STORE_FAST                      3: _var_var_1
                                70      PUSH_NULL                       
                                72      LOAD_DEREF                      7: func
                                74      LOAD_FAST                       0: args
                                76      BUILD_MAP                       0
                                78      LOAD_FAST                       1: kwargs
                                80      DICT_MERGE                      1
                                82      CALL_FUNCTION_EX                1
                                84      STORE_FAST                      4: _var_var_2
                                86      LOAD_GLOBAL                     1: NULL + time
                                96      LOAD_ATTR                       0: time
                                116     CALL                            0
                                124     STORE_FAST                      5: _var_var_3
                                126     LOAD_FAST                       5: _var_var_3
                                128     LOAD_FAST                       3: _var_var_1
                                130     BINARY_OP                       10 (-)
                                134     STORE_FAST                      6: _var_var_4
                                136     LOAD_GLOBAL                     3: NULL + print
                                146     PUSH_NULL                       
                                148     LOAD_CONST                      1: '__pyarmor_assert_14886__'
                                150     LOAD_CONST                      4: 'Функция выполнена за '   # b'\x81R\xdc\xa2\xd0Jcb\xc1K\xebp\xb4]\x17\xc5\xbf\x8f\nL\x1a\x14\xfe\x12\xb5\xb4\x13\x81\xb0d\xae8\x8a\x82`\xbdOzdn'
                                152     CALL                            1
                                160     LOAD_FAST                       6: _var_var_4
                                162     FORMAT_VALUE                    0 (FVC_NONE)
                                164     LOAD_CONST                      5: ' секунд'
                                166     BUILD_STRING                    3
                                168     CALL                            1
                                176     POP_TOP                         
                                178     LOAD_FAST                       4: _var_var_2
                                180     NOP                             
                                182     NOP                             
                                184     NOP                             
                                186     JUMP_FORWARD                    20 (to 228)
                                188     CALL                            1
                                196     POP_TOP                         
                                198     RETURN_VALUE                    
                                200     PUSH_EXC_INFO                   
                                202     PUSH_NULL                       
                                204     LOAD_CONST                      6: '__pyarmor_exit_14888__'
                                206     NOP                             
                                208     LOAD_CONST                      3: b'<COAddr>\x07\x00\x00\x1c\xac\x00\x00\x00\x00\x00\x00\x00\x00\x00\x00\x00\x00\x00\x00\x00'
                                210     CALL                            1
                                218     POP_TOP                         
                                220     RERAISE                         0
                                222     COPY                            3
                                224     POP_EXCEPT                      
                                226     RERAISE                         1
                                228     PUSH_NULL                       
                                230     LOAD_CONST                      6: '__pyarmor_exit_14888__'
                                232     LOAD_CONST                      3: b'<COAddr>\x07\x00\x00\x1c\xac\x00\x00\x00\x00\x00\x00\x00\x00\x00\x00\x00\x00\x00\x00\x00'
                                234     BUILD_TUPLE                     1
                                236     CALL_FUNCTION_EX                0
                                238     POP_TOP                         
                                240     RETURN_VALUE                    
                            [Exception Table]
                                30 to 180 -> 200 [0] 
                                200 to 222 -> 222 [1] lasti
                        '__pyarmor_exit_14885__'
                    [Disassembly]
                        0       MAKE_CELL                       0: func
                        2       NOP                             
                        4       NOP                             
                        6       PUSH_NULL                       
                        8       LOAD_CONST                      2: '__pyarmor_enter_14884__'
                        10      LOAD_CONST                      3: b'<COAddr>\x07\x00\x00\x1c"\x00\x00\x00\x00\x00\x00\x00\x00\x00\x00\x00\x00\x00\x00\x00'
                        12      BUILD_TUPLE                     1
                        14      CALL_FUNCTION_EX                0
                        16      POP_TOP                         
                        18      RESUME                          0
                        20      NOP                             
                        22      NOP                             
                        24      NOP                             
                        26      NOP                             
                        28      NOP                             
                        30      LOAD_CLOSURE                    0: func
                        32      BUILD_TUPLE                     1
                        34      LOAD_CONST                      4: <CODE> wrapper
                        36      MAKE_FUNCTION                   8
                        38      STORE_FAST                      2: _var_var_0
                        40      LOAD_FAST                       2: _var_var_0
                        42      NOP                             
                        44      NOP                             
                        46      NOP                             
                        48      JUMP_FORWARD                    20 (to 90)
                        50      CALL                            1
                        58      POP_TOP                         
                        60      RETURN_VALUE                    
                        62      PUSH_EXC_INFO                   
                        64      PUSH_NULL                       
                        66      LOAD_CONST                      5: '__pyarmor_exit_14885__'
                        68      NOP                             
                        70      LOAD_CONST                      3: b'<COAddr>\x07\x00\x00\x1c"\x00\x00\x00\x00\x00\x00\x00\x00\x00\x00\x00\x00\x00\x00\x00'
                        72      CALL                            1
                        80      POP_TOP                         
                        82      RERAISE                         0
                        84      COPY                            3
                        86      POP_EXCEPT                      
                        88      RERAISE                         1
                        90      PUSH_NULL                       
                        92      LOAD_CONST                      5: '__pyarmor_exit_14885__'
                        94      LOAD_CONST                      3: b'<COAddr>\x07\x00\x00\x1c"\x00\x00\x00\x00\x00\x00\x00\x00\x00\x00\x00\x00\x00\x00\x00'
                        96      BUILD_TUPLE                     1
                        98      CALL_FUNCTION_EX                0
                        100     POP_TOP                         
                        102     RETURN_VALUE                    
                    [Exception Table]
                        30 to 42 -> 62 [0] 
                        62 to 84 -> 84 [1] lasti
                [Code]
                    File Name: <frozen program.modules.func.android>
                    Object Name: _random_search
                    Qualified Name: AndroidRequests._random_search
                    Arg Count: 1
                    Pos Only Arg Count: 0
                    KW Only Arg Count: 0
                    Stack Size: 14
                    Flags: 0x20000003 (CO_OPTIMIZED | CO_NEWLOCALS | CO_PYARMOR_OBFUSCATED)
                    [Names]
                        'random'
                        'randint'
                        'join'
                        'choices'
                        'string'
                        'ascii_lowercase'
                        'capitalize'
                        'functions'
                        'contacts'
                        'SearchRequest'
                        'messages'
                        'SearchGlobalRequest'
                        'types'
                        'InputMessagesFilterEmpty'
                        'InputPeerEmpty'
                        'client'
                        'time'
                        'sleep'
                        'Exception'
                    [Locals+Names]
                        'self'
                        '__assert_armored__'
                        '_var_var_5'
                        '_var_var_6'
                        '_var_var_7'
                        '_var_var_8'
                        '_var_var_9'
                        '_var_var_10'
                    [Constants]
                        None
                        '__pyarmor_assert_14889__'
                        '__pyarmor_enter_14890__'
                        b'<COAddr>\x05\x00\x00\x1a<\x02\x00\x00\x00\x00\x00\x00\x00\x00\x00\x00\x00\x00\x00\x00'
                        3
                        15
                        ''
                        (
                            'k'
                        )
                        20
                        (
                            'q'
                            'limit'
                        )
                        0
                        False
                        (
                            'q'
                            'filter'
                            'min_date'
                            'max_date'
                            'offset_rate'
                            'offset_peer'
                            'offset_id'
                            'limit'
                            'broadcasts_only'
                            'folder_id'
                        )
                        1
                        '__pyarmor_exit_14891__'
                    [Disassembly]
                        0       NOP                             
                        2       NOP                             
                        4       PUSH_NULL                       
                        6       LOAD_CONST                      2: '__pyarmor_enter_14890__'
                        8       LOAD_CONST                      3: b'<COAddr>\x05\x00\x00\x1a<\x02\x00\x00\x00\x00\x00\x00\x00\x00\x00\x00\x00\x00\x00\x00'
                        10      BUILD_TUPLE                     1
                        12      CALL_FUNCTION_EX                0
                        14      POP_TOP                         
                        16      RESUME                          0
                        18      NOP                             
                        20      NOP                             
                        22      NOP                             
                        24      NOP                             
                        26      NOP                             
                        28      LOAD_GLOBAL                     1: NULL + random
                        38      LOAD_ATTR                       2: randint
                        58      LOAD_CONST                      4: 3
                        60      LOAD_CONST                      5: 15
                        62      CALL                            2
                        70      STORE_FAST                      2: _var_var_5
                        72      LOAD_CONST                      6: ''
                        74      LOAD_ATTR                       5: join
                        94      LOAD_GLOBAL                     1: NULL + random
                        104     LOAD_ATTR                       6: choices
                        124     LOAD_GLOBAL                     8: string
                        134     LOAD_ATTR                       10: ascii_lowercase
                        154     LOAD_FAST                       2: _var_var_5
                        156     KW_NAMES                        7: ('k',)
                        158     CALL                            2
                        166     CALL                            1
                        174     STORE_FAST                      3: _var_var_6
                        176     LOAD_FAST                       3: _var_var_6
                        178     LOAD_ATTR                       13: capitalize
                        198     CALL                            0
                        206     STORE_FAST                      3: _var_var_6
                        208     LOAD_CONST                      6: ''
                        210     STORE_FAST                      4: _var_var_7
                        212     LOAD_FAST                       3: _var_var_6
                        214     GET_ITER                        
                        216     FOR_ITER                        156 (to 530)
                        220     STORE_FAST                      5: _var_var_8
                        222     NOP                             
                        224     LOAD_FAST                       4: _var_var_7
                        226     LOAD_FAST                       5: _var_var_8
                        228     BINARY_OP                       13 (+=)
                        232     STORE_FAST                      4: _var_var_7
                        234     LOAD_GLOBAL                     14: functions
                        244     LOAD_ATTR                       16: contacts
                        264     LOAD_ATTR                       19: SearchRequest
                        284     LOAD_FAST                       4: _var_var_7
                        286     LOAD_CONST                      8: 20
                        288     KW_NAMES                        9: ('q', 'limit')
                        290     CALL                            2
                        298     LOAD_GLOBAL                     14: functions
                        308     LOAD_ATTR                       20: messages
                        328     LOAD_ATTR                       23: SearchGlobalRequest
                        348     LOAD_FAST                       4: _var_var_7
                        350     LOAD_GLOBAL                     25: NULL + types
                        360     LOAD_ATTR                       26: InputMessagesFilterEmpty
                        380     CALL                            0
                        388     LOAD_CONST                      10: 0
                        390     LOAD_CONST                      10: 0
                        392     LOAD_CONST                      10: 0
                        394     LOAD_GLOBAL                     25: NULL + types
                        404     LOAD_ATTR                       28: InputPeerEmpty
                        424     CALL                            0
                        432     LOAD_CONST                      10: 0
                        434     LOAD_CONST                      8: 20
                        436     LOAD_CONST                      11: False
                        438     LOAD_CONST                      10: 0
                        440     KW_NAMES                        12: ('q', 'filter', 'min_date', 'max_date', 'offset_rate', 'offset_peer', 'offset_id', 'limit', 'broadcasts_only', 'folder_id')
                        442     CALL                            10
                        450     BUILD_LIST                      2
                        452     STORE_FAST                      6: _var_var_9
                        454     LOAD_FAST                       0: self
                        456     LOAD_ATTR                       31: client
                        476     LOAD_FAST                       6: _var_var_9
                        478     CALL                            1
                        486     POP_TOP                         
                        488     LOAD_GLOBAL                     33: NULL + time
                        498     LOAD_ATTR                       34: sleep
                        518     LOAD_CONST                      13: 1
                        520     CALL                            1
                        528     POP_TOP                         
                        530     JUMP_BACKWARD                   158 (to 216)
                        532     END_FOR                         
                        534     LOAD_CONST                      0: None
                        536     NOP                             
                        538     NOP                             
                        540     NOP                             
                        542     JUMP_FORWARD                    41 (to 626)
                        550     POP_TOP                         
                        552     RETURN_CONST                    0: None
                        554     PUSH_EXC_INFO                   
                        556     LOAD_GLOBAL                     36: Exception
                        566     CHECK_EXC_MATCH                 
                        568     POP_JUMP_IF_FALSE               10 (to 590)
                        570     STORE_FAST                      7: _var_var_10
                        572     POP_EXCEPT                      
                        574     LOAD_CONST                      0: None
                        576     STORE_FAST                      7: _var_var_10
                        578     DELETE_FAST                     7: _var_var_10
                        580     JUMP_BACKWARD                   183 (to 216)
                        582     LOAD_CONST                      0: None
                        584     STORE_FAST                      7: _var_var_10
                        586     DELETE_FAST                     7: _var_var_10
                        588     RERAISE                         1
                        590     RERAISE                         0
                        592     COPY                            3
                        594     POP_EXCEPT                      
                        596     RERAISE                         1
                        598     PUSH_EXC_INFO                   
                        600     PUSH_NULL                       
                        602     LOAD_CONST                      14: '__pyarmor_exit_14891__'
                        604     NOP                             
                        606     LOAD_CONST                      3: b'<COAddr>\x05\x00\x00\x1a<\x02\x00\x00\x00\x00\x00\x00\x00\x00\x00\x00\x00\x00\x00\x00'
                        608     CALL                            1
                        616     POP_TOP                         
                        618     RERAISE                         0
                        620     COPY                            3
                        622     POP_EXCEPT                      
                        624     RERAISE                         1
                        626     PUSH_NULL                       
                        628     LOAD_CONST                      14: '__pyarmor_exit_14891__'
                        630     LOAD_CONST                      3: b'<COAddr>\x05\x00\x00\x1a<\x02\x00\x00\x00\x00\x00\x00\x00\x00\x00\x00\x00\x00\x00\x00'
                        632     BUILD_TUPLE                     1
                        634     CALL_FUNCTION_EX                0
                        636     POP_TOP                         
                        638     RETURN_VALUE                    
                    [Exception Table]
                        28 to 222 -> 598 [0] 
                        224 to 530 -> 554 [1] 
                        530 to 534 -> 598 [0] 
                        554 to 572 -> 592 [2] lasti
                        572 to 582 -> 598 [0] 
                        582 to 592 -> 592 [2] lasti
                        592 to 598 -> 598 [0] 
                        598 to 620 -> 620 [1] lasti
                [Code]
                    File Name: <frozen program.modules.func.android>
                    Object Name: reg_start
                    Qualified Name: AndroidRequests.reg_start
                    Arg Count: 1
                    Pos Only Arg Count: 0
                    KW Only Arg Count: 0
                    Stack Size: 6
                    Flags: 0x20000003 (CO_OPTIMIZED | CO_NEWLOCALS | CO_PYARMOR_OBFUSCATED)
                    [Names]
                        'option_reg'
                        'app_id'
                        'functions'
                        'langpack'
                        'GetLanguagesRequest'
                        'help'
                        'GetNearestDcRequest'
                        'client'
                        'GetLanguages_tdlib_Request'
                        'GetCountriesListRequest'
                        'lang_code'
                    [Locals+Names]
                        'self'
                        '__assert_armored__'
                        '_var_var_9'
                    [Constants]
                        None
                        '__pyarmor_assert_14892__'
                        '__pyarmor_enter_14893__'
                        b'<COAddr>\x07\x00\x00\x1aR\x02\x00\x00\x00\x00\x00\x00\x00\x00\x00\x00\x00\x00\x00\x00'
                        '__pyarmor_exit_14894__'
                        4
                        6
                        21724
                        'android_x'   # b'\x81\xe3\x16\x17!\xf5\xb7\xd6$\xe2'
                        (
                            'lang_pack'
                        )
                        0
                        (
                            'lang_code'
                            'hash'
                        )
                    [Disassembly]
                        0       NOP                             
                        2       NOP                             
                        4       PUSH_NULL                       
                        6       LOAD_CONST                      2: '__pyarmor_enter_14893__'
                        8       LOAD_CONST                      3: b'<COAddr>\x07\x00\x00\x1aR\x02\x00\x00\x00\x00\x00\x00\x00\x00\x00\x00\x00\x00\x00\x00'
                        10      BUILD_TUPLE                     1
                        12      CALL_FUNCTION_EX                0
                        14      POP_TOP                         
                        16      RESUME                          0
                        18      NOP                             
                        20      NOP                             
                        22      NOP                             
                        24      NOP                             
                        26      NOP                             
                        28      LOAD_FAST                       0: self
                        30      LOAD_ATTR                       0: option_reg
                        50      POP_JUMP_IF_TRUE                11 (to 74)
                        52      NOP                             
                        54      LOAD_CONST                      0: None
                        56      NOP                             
                        58      NOP                             
                        60      JUMP_FORWARD                    292 (to 648)
                        70      POP_TOP                         
                        72      RETURN_CONST                    0: None
                        74      LOAD_FAST                       0: self
                        76      LOAD_ATTR                       2: app_id
                        96      LOAD_CONST                      5: 4
                        98      COMPARE_OP                      40 (==)
                        102     POP_JUMP_IF_TRUE                15 (to 134)
                        104     LOAD_FAST                       0: self
                        106     LOAD_ATTR                       2: app_id
                        126     LOAD_CONST                      6: 6
                        128     COMPARE_OP                      40 (==)
                        132     POP_JUMP_IF_FALSE               77 (to 288)
                        134     LOAD_GLOBAL                     4: functions
                        144     LOAD_ATTR                       6: langpack
                        164     LOAD_ATTR                       9: GetLanguagesRequest
                        184     CALL                            0
                        192     LOAD_GLOBAL                     4: functions
                        202     LOAD_ATTR                       10: help
                        222     LOAD_ATTR                       13: GetNearestDcRequest
                        242     CALL                            0
                        250     BUILD_LIST                      2
                        252     STORE_FAST                      2: _var_var_9
                        254     LOAD_FAST                       0: self
                        256     LOAD_ATTR                       15: client
                        276     LOAD_FAST                       2: _var_var_9
                        278     CALL                            1
                        286     POP_TOP                         
                        288     LOAD_FAST                       0: self
                        290     LOAD_ATTR                       2: app_id
                        310     LOAD_CONST                      7: 21724
                        312     COMPARE_OP                      40 (==)
                        316     POP_JUMP_IF_FALSE               127 (to 572)
                        318     LOAD_GLOBAL                     4: functions
                        328     LOAD_ATTR                       6: langpack
                        348     LOAD_ATTR                       17: GetLanguages_tdlib_Request
                        368     PUSH_NULL                       
                        370     LOAD_CONST                      1: '__pyarmor_assert_14892__'
                        372     LOAD_CONST                      8: 'android_x'   # b'\x81\xe3\x16\x17!\xf5\xb7\xd6$\xe2'
                        374     CALL                            1
                        382     KW_NAMES                        9: ('lang_pack',)
                        384     CALL                            1
                        392     LOAD_GLOBAL                     4: functions
                        402     LOAD_ATTR                       10: help
                        422     LOAD_ATTR                       13: GetNearestDcRequest
                        442     CALL                            0
                        450     LOAD_GLOBAL                     4: functions
                        460     LOAD_ATTR                       10: help
                        480     LOAD_ATTR                       19: GetCountriesListRequest
                        500     LOAD_FAST                       0: self
                        502     LOAD_ATTR                       20: lang_code
                        522     LOAD_CONST                      10: 0
                        524     KW_NAMES                        11: ('lang_code', 'hash')
                        526     CALL                            2
                        534     BUILD_LIST                      3
                        536     STORE_FAST                      2: _var_var_9
                        538     LOAD_FAST                       0: self
                        540     LOAD_ATTR                       15: client
                        560     LOAD_FAST                       2: _var_var_9
                        562     CALL                            1
                        570     POP_TOP                         
                        572     LOAD_CONST                      0: None
                        574     NOP                             
                        576     NOP                             
                        578     NOP                             
                        580     JUMP_FORWARD                    33 (to 648)
                        588     POP_TOP                         
                        590     RETURN_CONST                    0: None
                        592     PUSH_EXC_INFO                   
                        594     POP_TOP                         
                        596     POP_EXCEPT                      
                        598     JUMP_BACKWARD                   156 (to 288)
                        600     COPY                            3
                        602     POP_EXCEPT                      
                        604     RERAISE                         1
                        606     PUSH_EXC_INFO                   
                        608     POP_TOP                         
                        610     POP_EXCEPT                      
                        612     JUMP_BACKWARD                   21 (to 572)
                        614     COPY                            3
                        616     POP_EXCEPT                      
                        618     RERAISE                         1
                        620     PUSH_EXC_INFO                   
                        622     PUSH_NULL                       
                        624     LOAD_CONST                      4: '__pyarmor_exit_14894__'
                        626     NOP                             
                        628     LOAD_CONST                      3: b'<COAddr>\x07\x00\x00\x1aR\x02\x00\x00\x00\x00\x00\x00\x00\x00\x00\x00\x00\x00\x00\x00'
                        630     CALL                            1
                        638     POP_TOP                         
                        640     RERAISE                         0
                        642     COPY                            3
                        644     POP_EXCEPT                      
                        646     RERAISE                         1
                        648     PUSH_NULL                       
                        650     LOAD_CONST                      4: '__pyarmor_exit_14894__'
                        652     LOAD_CONST                      3: b'<COAddr>\x07\x00\x00\x1aR\x02\x00\x00\x00\x00\x00\x00\x00\x00\x00\x00\x00\x00\x00\x00'
                        654     BUILD_TUPLE                     1
                        656     CALL_FUNCTION_EX                0
                        658     POP_TOP                         
                        660     RETURN_VALUE                    
                    [Exception Table]
                        28 to 52 -> 620 [0] 
                        74 to 254 -> 620 [0] 
                        254 to 288 -> 592 [0] 
                        288 to 538 -> 620 [0] 
                        538 to 572 -> 606 [0] 
                        592 to 596 -> 600 [1] lasti
                        596 to 606 -> 620 [0] 
                        606 to 610 -> 614 [1] lasti
                        610 to 620 -> 620 [0] 
                        620 to 642 -> 642 [1] lasti
                [Code]
                    File Name: <frozen program.modules.func.android>
                    Object Name: reg_middle
                    Qualified Name: AndroidRequests.reg_middle
                    Arg Count: 1
                    Pos Only Arg Count: 0
                    KW Only Arg Count: 0
                    Stack Size: 7
                    Flags: 0x20000003 (CO_OPTIMIZED | CO_NEWLOCALS | CO_PYARMOR_OBFUSCATED)
                    [Names]
                        'option_reg'
                        'app_id'
                        'functions'
                        'langpack'
                        'GetLangPackRequest'
                        'lang_code'
                        'help'
                        'GetPromoDataRequest'
                        'GetLanguagesRequest'
                        'account'
                        'GetGlobalPrivacySettingsRequest'
                        'contacts'
                        'GetBirthdaysRequest'
                        'client'
                        'GetLangPack_tdlib_Request'
                        'GetLanguages_tdlib_Request'
                        'random'
                        'shuffle'
                    [Locals+Names]
                        'self'
                        '__assert_armored__'
                        '_var_var_9'
                    [Constants]
                        None
                        '__pyarmor_assert_14895__'
                        '__pyarmor_enter_14896__'
                        b'<COAddr>\x05\x00\x00\x1a\xfc\x03\x00\x00\x00\x00\x00\x00\x00\x00\x00\x00\x00\x00\x00\x00'
                        '__pyarmor_exit_14897__'
                        4
                        6
                        (
                            'lang_code'
                        )
                        21724
                        'android_x'   # b'\x81\xe3\x16\x17!\xf5\xb7\xd6$\xe2'
                    [Disassembly]
                        0       NOP                             
                        2       NOP                             
                        4       PUSH_NULL                       
                        6       LOAD_CONST                      2: '__pyarmor_enter_14896__'
                        8       LOAD_CONST                      3: b'<COAddr>\x05\x00\x00\x1a\xfc\x03\x00\x00\x00\x00\x00\x00\x00\x00\x00\x00\x00\x00\x00\x00'
                        10      BUILD_TUPLE                     1
                        12      CALL_FUNCTION_EX                0
                        14      POP_TOP                         
                        16      RESUME                          0
                        18      NOP                             
                        20      NOP                             
                        22      NOP                             
                        24      NOP                             
                        26      NOP                             
                        28      LOAD_FAST                       0: self
                        30      LOAD_ATTR                       0: option_reg
                        50      POP_JUMP_IF_TRUE                11 (to 74)
                        52      NOP                             
                        54      LOAD_CONST                      0: None
                        56      NOP                             
                        58      NOP                             
                        60      JUMP_FORWARD                    505 (to 1074)
                        70      POP_TOP                         
                        72      RETURN_CONST                    0: None
                        74      LOAD_FAST                       0: self
                        76      LOAD_ATTR                       2: app_id
                        96      LOAD_CONST                      5: 4
                        98      COMPARE_OP                      40 (==)
                        102     POP_JUMP_IF_TRUE                15 (to 134)
                        104     LOAD_FAST                       0: self
                        106     LOAD_ATTR                       2: app_id
                        126     LOAD_CONST                      6: 6
                        128     COMPARE_OP                      40 (==)
                        132     POP_JUMP_IF_FALSE               206 (to 546)
                        134     LOAD_GLOBAL                     4: functions
                        144     LOAD_ATTR                       6: langpack
                        164     LOAD_ATTR                       9: GetLangPackRequest
                        184     LOAD_FAST                       0: self
                        186     LOAD_ATTR                       10: lang_code
                        206     KW_NAMES                        7: ('lang_code',)
                        208     CALL                            1
                        216     LOAD_GLOBAL                     4: functions
                        226     LOAD_ATTR                       12: help
                        246     LOAD_ATTR                       15: GetPromoDataRequest
                        266     CALL                            0
                        274     LOAD_GLOBAL                     4: functions
                        284     LOAD_ATTR                       6: langpack
                        304     LOAD_ATTR                       17: GetLanguagesRequest
                        324     CALL                            0
                        332     LOAD_GLOBAL                     4: functions
                        342     LOAD_ATTR                       18: account
                        362     LOAD_ATTR                       21: GetGlobalPrivacySettingsRequest
                        382     CALL                            0
                        390     LOAD_GLOBAL                     4: functions
                        400     LOAD_ATTR                       22: contacts
                        420     LOAD_ATTR                       25: GetBirthdaysRequest
                        440     CALL                            0
                        448     LOAD_GLOBAL                     4: functions
                        458     LOAD_ATTR                       6: langpack
                        478     LOAD_ATTR                       17: GetLanguagesRequest
                        498     CALL                            0
                        506     BUILD_LIST                      6
                        508     STORE_FAST                      2: _var_var_9
                        510     NOP                             
                        512     LOAD_FAST                       0: self
                        514     LOAD_ATTR                       27: client
                        534     LOAD_FAST                       2: _var_var_9
                        536     CALL                            1
                        544     POP_TOP                         
                        546     LOAD_FAST                       0: self
                        548     LOAD_ATTR                       2: app_id
                        568     LOAD_CONST                      8: 21724
                        570     COMPARE_OP                      40 (==)
                        574     POP_JUMP_IF_FALSE               211 (to 998)
                        576     LOAD_GLOBAL                     4: functions
                        586     LOAD_ATTR                       6: langpack
                        606     LOAD_ATTR                       29: GetLangPack_tdlib_Request
                        626     PUSH_NULL                       
                        628     LOAD_CONST                      1: '__pyarmor_assert_14895__'
                        630     LOAD_CONST                      9: 'android_x'   # b'\x81\xe3\x16\x17!\xf5\xb7\xd6$\xe2'
                        632     CALL                            1
                        640     LOAD_FAST                       0: self
                        642     LOAD_ATTR                       10: lang_code
                        662     CALL                            2
                        670     LOAD_GLOBAL                     4: functions
                        680     LOAD_ATTR                       12: help
                        700     LOAD_ATTR                       15: GetPromoDataRequest
                        720     CALL                            0
                        728     LOAD_GLOBAL                     4: functions
                        738     LOAD_ATTR                       6: langpack
                        758     LOAD_ATTR                       31: GetLanguages_tdlib_Request
                        778     PUSH_NULL                       
                        780     LOAD_CONST                      1: '__pyarmor_assert_14895__'
                        782     LOAD_CONST                      9: 'android_x'   # b'\x81\xe3\x16\x17!\xf5\xb7\xd6$\xe2'
                        784     CALL                            1
                        792     CALL                            1
                        800     LOAD_GLOBAL                     4: functions
                        810     LOAD_ATTR                       18: account
                        830     LOAD_ATTR                       21: GetGlobalPrivacySettingsRequest
                        850     CALL                            0
                        858     LOAD_GLOBAL                     4: functions
                        868     LOAD_ATTR                       22: contacts
                        888     LOAD_ATTR                       25: GetBirthdaysRequest
                        908     CALL                            0
                        916     BUILD_LIST                      5
                        918     STORE_FAST                      2: _var_var_9
                        920     NOP                             
                        922     LOAD_GLOBAL                     33: NULL + random
                        932     LOAD_ATTR                       34: shuffle
                        952     LOAD_FAST                       2: _var_var_9
                        954     CALL                            1
                        962     POP_TOP                         
                        964     LOAD_FAST                       0: self
                        966     LOAD_ATTR                       27: client
                        986     LOAD_FAST                       2: _var_var_9
                        988     CALL                            1
                        996     POP_TOP                         
                        998     LOAD_CONST                      0: None
                        1000    NOP                             
                        1002    NOP                             
                        1004    NOP                             
                        1006    JUMP_FORWARD                    33 (to 1074)
                        1014    POP_TOP                         
                        1016    RETURN_CONST                    0: None
                        1018    PUSH_EXC_INFO                   
                        1020    POP_TOP                         
                        1022    POP_EXCEPT                      
                        1024    JUMP_BACKWARD                   240 (to 546)
                        1026    COPY                            3
                        1028    POP_EXCEPT                      
                        1030    RERAISE                         1
                        1032    PUSH_EXC_INFO                   
                        1034    POP_TOP                         
                        1036    POP_EXCEPT                      
                        1038    JUMP_BACKWARD                   21 (to 998)
                        1040    COPY                            3
                        1042    POP_EXCEPT                      
                        1044    RERAISE                         1
                        1046    PUSH_EXC_INFO                   
                        1048    PUSH_NULL                       
                        1050    LOAD_CONST                      4: '__pyarmor_exit_14897__'
                        1052    NOP                             
                        1054    LOAD_CONST                      3: b'<COAddr>\x05\x00\x00\x1a\xfc\x03\x00\x00\x00\x00\x00\x00\x00\x00\x00\x00\x00\x00\x00\x00'
                        1056    CALL                            1
                        1064    POP_TOP                         
                        1066    RERAISE                         0
                        1068    COPY                            3
                        1070    POP_EXCEPT                      
                        1072    RERAISE                         1
                        1074    PUSH_NULL                       
                        1076    LOAD_CONST                      4: '__pyarmor_exit_14897__'
                        1078    LOAD_CONST                      3: b'<COAddr>\x05\x00\x00\x1a\xfc\x03\x00\x00\x00\x00\x00\x00\x00\x00\x00\x00\x00\x00\x00\x00'
                        1080    BUILD_TUPLE                     1
                        1082    CALL_FUNCTION_EX                0
                        1084    POP_TOP                         
                        1086    RETURN_VALUE                    
                    [Exception Table]
                        28 to 52 -> 1046 [0] 
                        74 to 510 -> 1046 [0] 
                        512 to 546 -> 1018 [0] 
                        546 to 920 -> 1046 [0] 
                        922 to 998 -> 1032 [0] 
                        1018 to 1022 -> 1026 [1] lasti
                        1022 to 1032 -> 1046 [0] 
                        1032 to 1036 -> 1040 [1] lasti
                        1036 to 1046 -> 1046 [0] 
                        1046 to 1068 -> 1068 [1] lasti
                [Code]
                    File Name: <frozen program.modules.func.android>
                    Object Name: reg_end
                    Qualified Name: AndroidRequests.reg_end
                    Arg Count: 1
                    Pos Only Arg Count: 0
                    KW Only Arg Count: 0
                    Stack Size: 32
                    Flags: 0x20000003 (CO_OPTIMIZED | CO_NEWLOCALS | CO_PYARMOR_OBFUSCATED)
                    [Names]
                        'option_reg'
                        'app_id'
                        'functions'
                        'messages'
                        'GetStickerSetRequest'
                        'types'
                        'InputStickerSetShortName'
                        'account'
                        'GetThemesRequest'
                        'os'
                        'help'
                        'SaveAppLogRequest'
                        'InputAppEvent'
                        'datetime'
                        'now'
                        'timezone'
                        'utc'
                        'timestamp'
                        'JsonBool'
                        'client'
                        'GetPrivacyRequest'
                        'InputPrivacyKeyStatusTimestamp'
                        'InputPrivacyKeyChatInvite'
                        'InputPrivacyKeyPhoneCall'
                        'InputPrivacyKeyPhoneP2P'
                        'InputPrivacyKeyProfilePhoto'
                        'InputPrivacyKeyForwards'
                        'InputPrivacyKeyPhoneNumber'
                        'InputPrivacyKeyAddedByPhone'
                        'InputPrivacyKeyVoiceMessages'
                        'InputPrivacyKeyAbout'
                        'InputPrivacyKeyBirthday'
                        'GetMultiWallPapersRequest'
                        'InputWallPaperSlug'
                        'langpack'
                        'GetLangPack_tdlib_Request'
                        'lang_code'
                        'GetPromoDataRequest'
                        'GetLanguages_tdlib_Request'
                        'GetGlobalPrivacySettingsRequest'
                        'contacts'
                        'GetBirthdaysRequest'
                        'random'
                        'shuffle'
                    [Locals+Names]
                        'self'
                        '__assert_armored__'
                        '_var_var_9'
                    [Constants]
                        None
                        '__pyarmor_assert_14898__'
                        '__pyarmor_enter_14899__'
                        b'<COAddr>\x05\x00\x00\x1a\xa2\x0f\x00\x00\x00\x00\x00\x00\x00\x00\x00\x00\x00\x00\x00\x00'
                        '__pyarmor_exit_14900__'
                        4
                        6
                        'tg_placeholders_android'   # b'\x81\xf6\x1f,#\xf6\xbf\xd1\x1e\xf2\x02\xcch\xe9\xea\x960\\\xb5\xa3\xb8\xc4G\xc8'
                        (
                            'short_name'
                        )
                        0
                        (
                            'stickerset'
                            'hash'
                        )
                        (
                            'format'
                            'hash'
                        )
                        (
                            'tz'
                        )
                        'android_sdcard_exists'   # b'\x81\xe3\x16\x17!\xf5\xb7\xd6$\xe9\t\xc3m\xfe\xfc\xba\nE\xb2\xb4\xbe\xd8'
                        1
                        True
                        (
                            'time'
                            'type'
                            'peer'
                            'data'
                        )
                        (
                            'events'
                        )
                        (
                            'key'
                        )
                        'lp0prF8ISFAEAAAA_p385_CvG0w'   # b'\x81\xee\x08C#\xe8\x98\x8a2\xc9+\xe1I\xcd\xd9\xa4.b\xab\xf4\xf2\x9eq\xef\x13H\xf3K'
                        (
                            'slug'
                        )
                        'MIo6r0qGSFAFAAAAtL8TsDzNX60'   # b'\x81\xcf1\x1ce\xe8\xee\xc3<\xc9+\xe1J\xcd\xd9\xa4.I\x97\xff\x9e\xd8j\xd6+W\xf5\x0c'
                        'p-pXcflrmFIBAAAAvXYQk-mCwZU'   # b'\x81\xf2U\x03\x0b\xf9\xb8\xde\t\xf7+\xe9N\xcd\xd9\xa4.K\x83\x9e\x9b\xc0\x03\xc1&x\x99i'
                        'CJNyxPMgSVAEAAAAvW9sMwc51cw'   # b'\x81\xc12=*\xe2\x8e\xff\x1c\xc9;\xe1I\xcd\xd9\xa4.K\x8c\xfe\xb9\xe6Y\xcfP>\xa0K'
                        'mP3FG_iwSFAFAAAA2AklJO978pA'   # b'\x81\xef(@\x15\xdd\x81\xdb\x0c\xc9+\xe1J\xcd\xd9\xa4.\x0f\x9a\xac\xa6\xe1a\x95R7\xb3}'
                        'O-wmAfBPSFADAAAA4zINVfD_bro'   # b'\x81\xcdU\x04>\xdb\xb8\xf0+\xc9+\xe1H\xcd\xd9\xa4.\t\xa1\x8e\x84\xfdH\xe8:m\xb1S'
                        '-Xc-np9y2VMCAAAARKr0yNNPYW0'   # b'\x81\xaf \x10~\xf4\xae\x8b\x02\xa8;\xedO\xcd\xd9\xa4.o\x90\xb5\xfa\xd2`\xe25V\x94\x0c'
                        'kO4jyq55SFABAAAA0WEpcLfahXk'   # b'\x81\xe97G9\xe3\xaf\x87N\xc9+\xe1N\xcd\xd9\xa4.\r\x8c\x82\xba\xc8b\xca\x04g\x9bW'
                        'fqv01SQemVIBAAAApND8LDRUhRU'   # b'\x81\xe4\t\x05c\xab\x8d\xe3\x1e\xf7;\xe9N\xcd\xd9\xa4.M\x95\x83\xf2\xe7j\xfe0g\x91i'
                        'RepJ5uE_SVABAAAAr4d0YhgB850'   # b"\x81\xd0\x1d\x03\x19\xaf\xab\xf7$\xc9;\xe1N\xcd\xd9\xa4.O\xef\xa3\xfa\xf2F\xcb'7\xf6\x0c"
                        'JqSUrO0-mFIBAAAAWwTvLzoWGQI'   # b'\x81\xc8\t \x06\xe8\x91\x82V\xf7+\xe9N\xcd\xd9\xa4.j\xac\x93\xbc\xe7T\xc32H\x92u'
                        'dk_wwlghOFACAAAAfz9xrxi6euw'   # b'\x81\xe6\x13,$\xed\xb2\xd5\x13\xd5+\xe1O\xcd\xd9\xa4.[\xa1\xfe\xb2\xd9V\xc5Sj\xb6K'
                        'Ujx2TFcJSVACAAAARJ4vLa50MkM'   # b'\x81\xd7\x12\x0ba\xce\x98\xd11\xc9;\xe1O\xcd\xd9\xa4.o\x91\xf3\xbc\xe7O\x99UB\xa8q'
                        'dhf9pceaQVACAAAAbzdVo4SCiZA'   # b'\x81\xe6\x10\x15j\xea\xbd\xd7\x1a\xcb;\xe1O\xcd\xd9\xa4._\xa1\xa3\x9c\xc4\x1a\xff&f\x99}'
                        'PllZ-bf_SFAEAAAA8crRfwZiDNg'   # b'\x81\xd2\x14\x1f\t\xb7\xbc\xd4$\xc9+\xe1I\xcd\xd9\xa4.\x05\xb8\xb5\x98\xcdY\xf6\x0cK\x8d['
                        'heptcj-hSVACAAAAC9RrMzOa-cs'   # b'\x81\xea\x1d\x03\'\xf9\xb4\x9f\x13\xc9;\xe1O\xcd\xd9\xa4.~\xe2\x95\xb8\xe6T\xe3\x04"\xa0O'
                        '9LW_RcoOSVACAAAAFTk3DTyXN-M'   # b'\x81\xbb4$\x0c\xc8\xbd\xdd4\xc9;\xe1O\xcd\xd9\xa4.{\x8f\xac\xf9\xefz\xd5=A\xeeq'
                        '3rX-PaKbSFACAAAAEiHNvcEm6X4'   # b'\x81\xb1\n+~\xca\xbf\xf9\x19\xc9+\xe1O\xcd\xd9\xa4.x\xb2\x8f\x84\xddM\xe9\x089\x9b\x08'
                        '9ShF73d1MFIIAAAAjWnm8_ZMe8Q'   # b'\x81\xbb+\x1b\x15\xad\xed\xd6J\xd7+\xe9E\xcd\xd9\xa4.W\x8c\xa9\xa7\x93q\xf6(j\xfbm'
                        'F5oWoCs7QFACAAAAgf2bD_mg8Bw'   # b'\x81\xc4M\x1c\x04\xf5\x9d\xc1L\xcb+\xe1O\xcd\xd9\xa4.Z\xbd\xf5\xa8\xefq\xc1\x027\x81K'
                        '9GcNVISdSVADAAAAUcw5BYjELW4'   # b'\x81\xbb?\x10\x1d\xcc\x97\xe1\x1f\xc9;\xe1H\xcd\xd9\xa4.h\xb8\xb0\xff\xe9w\xc6 C\x94\x08'
                        '9iklpvIPQVABAAAAORQXKur_Eyc'   # b'\x81\xbb\x11\x18?\xea\xa8\xfb+\xcb;\xe1N\xcd\xd9\xa4.r\x89\x96\x92\xe0[\xde:J\xba_'
                        'ptuUd96JSFACAAAATobI23sPpz0'   # b'\x81\xf2\x0c\x06\x06\xfe\xe7\x841\xc9+\xe1O\xcd\xd9\xa4.i\xb4\xa5\x83\x99\x1d\xdf5\x7f\xb9\x0c'
                        'pgJfpFNRSFABAAAACDT8s5sEjfc'   # b'\x81\xf2\x1f95\xea\x98\xfc)\xc9+\xe1N\xcd\xd9\xa4.~\x9f\x93\xf2\xd8\x1b\xdf e\xa5_'
                        'YIxYGEALQVADAAAAA3QbEH0AowY'   # b'\x81\xdb1\x0b\n\xdd\x9b\xf37\xcb;\xe1H\xcd\xd9\xa4.|\xe8\x96\xa8\xeef\x9c$`\xb4e'
                        'Nl8Pg2rBQVACAAAA25Lxtb8SDp0'   # b'\x81\xcc\x14K\x03\xfd\xec\xc09\xcb;\xe1O\xcd\xd9\xa4.\x0f\xee\x8b\xb2\xdfL\x946K\xb3\x0c'
                        (
                            'wallpapers'
                        )
                        21724
                        'android_x'   # b'\x81\xe3\x16\x17!\xf5\xb7\xd6$\xe2'
                    [Disassembly]
                        0       NOP                             
                        2       NOP                             
                        4       PUSH_NULL                       
                        6       LOAD_CONST                      2: '__pyarmor_enter_14899__'
                        8       LOAD_CONST                      3: b'<COAddr>\x05\x00\x00\x1a\xa2\x0f\x00\x00\x00\x00\x00\x00\x00\x00\x00\x00\x00\x00\x00\x00'
                        10      BUILD_TUPLE                     1
                        12      CALL_FUNCTION_EX                0
                        14      POP_TOP                         
                        16      RESUME                          0
                        18      NOP                             
                        20      NOP                             
                        22      NOP                             
                        24      NOP                             
                        26      NOP                             
                        28      LOAD_FAST                       0: self
                        30      LOAD_ATTR                       0: option_reg
                        50      POP_JUMP_IF_TRUE                11 (to 74)
                        52      NOP                             
                        54      LOAD_CONST                      0: None
                        56      NOP                             
                        58      NOP                             
                        60      JUMP_FORWARD                    1996 (to 4056)
                        70      POP_TOP                         
                        72      RETURN_CONST                    0: None
                        74      LOAD_FAST                       0: self
                        76      LOAD_ATTR                       2: app_id
                        96      LOAD_CONST                      5: 4
                        98      COMPARE_OP                      40 (==)
                        102     POP_JUMP_IF_TRUE                16 (to 136)
                        104     LOAD_FAST                       0: self
                        106     LOAD_ATTR                       2: app_id
                        126     LOAD_CONST                      6: 6
                        128     COMPARE_OP                      40 (==)
                        132     POP_JUMP_IF_FALSE               1578 (to 3292)
                        136     LOAD_GLOBAL                     4: functions
                        146     LOAD_ATTR                       6: messages
                        166     LOAD_ATTR                       9: GetStickerSetRequest
                        186     LOAD_GLOBAL                     11: NULL + types
                        196     LOAD_ATTR                       12: InputStickerSetShortName
                        216     PUSH_NULL                       
                        218     LOAD_CONST                      1: '__pyarmor_assert_14898__'
                        220     LOAD_CONST                      7: 'tg_placeholders_android'   # b'\x81\xf6\x1f,#\xf6\xbf\xd1\x1e\xf2\x02\xcch\xe9\xea\x960\\\xb5\xa3\xb8\xc4G\xc8'
                        222     CALL                            1
                        230     KW_NAMES                        8: ('short_name',)
                        232     CALL                            1
                        240     LOAD_CONST                      9: 0
                        242     KW_NAMES                        10: ('stickerset', 'hash')
                        244     CALL                            2
                        252     LOAD_GLOBAL                     4: functions
                        262     LOAD_ATTR                       14: account
                        282     LOAD_ATTR                       17: GetThemesRequest
                        302     LOAD_FAST                       0: self
                        304     LOAD_ATTR                       18: os
                        324     LOAD_CONST                      9: 0
                        326     KW_NAMES                        11: ('format', 'hash')
                        328     CALL                            2
                        336     LOAD_GLOBAL                     4: functions
                        346     LOAD_ATTR                       20: help
                        366     LOAD_ATTR                       23: SaveAppLogRequest
                        386     LOAD_GLOBAL                     11: NULL + types
                        396     LOAD_ATTR                       24: InputAppEvent
                        416     LOAD_GLOBAL                     26: datetime
                        426     LOAD_ATTR                       26: datetime
                        446     LOAD_ATTR                       29: now
                        466     LOAD_GLOBAL                     26: datetime
                        476     LOAD_ATTR                       30: timezone
                        496     LOAD_ATTR                       32: utc
                        516     KW_NAMES                        12: ('tz',)
                        518     CALL                            1
                        526     LOAD_ATTR                       35: timestamp
                        546     CALL                            0
                        554     PUSH_NULL                       
                        556     LOAD_CONST                      1: '__pyarmor_assert_14898__'
                        558     LOAD_CONST                      13: 'android_sdcard_exists'   # b'\x81\xe3\x16\x17!\xf5\xb7\xd6$\xe9\t\xc3m\xfe\xfc\xba\nE\xb2\xb4\xbe\xd8'
                        560     CALL                            1
                        568     LOAD_CONST                      14: 1
                        570     LOAD_GLOBAL                     11: NULL + types
                        580     LOAD_ATTR                       36: JsonBool
                        600     LOAD_CONST                      15: True
                        602     CALL                            1
                        610     KW_NAMES                        16: ('time', 'type', 'peer', 'data')
                        612     CALL                            4
                        620     BUILD_LIST                      1
                        622     KW_NAMES                        17: ('events',)
                        624     CALL                            1
                        632     BUILD_LIST                      3
                        634     STORE_FAST                      2: _var_var_9
                        636     NOP                             
                        638     LOAD_FAST                       0: self
                        640     LOAD_ATTR                       39: client
                        660     LOAD_FAST                       2: _var_var_9
                        662     CALL                            1
                        670     POP_TOP                         
                        672     LOAD_GLOBAL                     4: functions
                        682     LOAD_ATTR                       14: account
                        702     LOAD_ATTR                       41: GetPrivacyRequest
                        722     LOAD_GLOBAL                     11: NULL + types
                        732     LOAD_ATTR                       42: InputPrivacyKeyStatusTimestamp
                        752     CALL                            0
                        760     KW_NAMES                        18: ('key',)
                        762     CALL                            1
                        770     LOAD_GLOBAL                     4: functions
                        780     LOAD_ATTR                       14: account
                        800     LOAD_ATTR                       41: GetPrivacyRequest
                        820     LOAD_GLOBAL                     11: NULL + types
                        830     LOAD_ATTR                       44: InputPrivacyKeyChatInvite
                        850     CALL                            0
                        858     KW_NAMES                        18: ('key',)
                        860     CALL                            1
                        868     LOAD_GLOBAL                     4: functions
                        878     LOAD_ATTR                       14: account
                        898     LOAD_ATTR                       41: GetPrivacyRequest
                        918     LOAD_GLOBAL                     11: NULL + types
                        928     LOAD_ATTR                       46: InputPrivacyKeyPhoneCall
                        948     CALL                            0
                        956     KW_NAMES                        18: ('key',)
                        958     CALL                            1
                        966     LOAD_GLOBAL                     4: functions
                        976     LOAD_ATTR                       14: account
                        996     LOAD_ATTR                       41: GetPrivacyRequest
                        1016    LOAD_GLOBAL                     11: NULL + types
                        1026    LOAD_ATTR                       48: InputPrivacyKeyPhoneP2P
                        1046    CALL                            0
                        1054    KW_NAMES                        18: ('key',)
                        1056    CALL                            1
                        1064    LOAD_GLOBAL                     4: functions
                        1074    LOAD_ATTR                       14: account
                        1094    LOAD_ATTR                       41: GetPrivacyRequest
                        1114    LOAD_GLOBAL                     11: NULL + types
                        1124    LOAD_ATTR                       50: InputPrivacyKeyProfilePhoto
                        1144    CALL                            0
                        1152    KW_NAMES                        18: ('key',)
                        1154    CALL                            1
                        1162    LOAD_GLOBAL                     4: functions
                        1172    LOAD_ATTR                       14: account
                        1192    LOAD_ATTR                       41: GetPrivacyRequest
                        1212    LOAD_GLOBAL                     11: NULL + types
                        1222    LOAD_ATTR                       52: InputPrivacyKeyForwards
                        1242    CALL                            0
                        1250    KW_NAMES                        18: ('key',)
                        1252    CALL                            1
                        1260    LOAD_GLOBAL                     4: functions
                        1270    LOAD_ATTR                       14: account
                        1290    LOAD_ATTR                       41: GetPrivacyRequest
                        1310    LOAD_GLOBAL                     11: NULL + types
                        1320    LOAD_ATTR                       54: InputPrivacyKeyPhoneNumber
                        1340    CALL                            0
                        1348    KW_NAMES                        18: ('key',)
                        1350    CALL                            1
                        1358    LOAD_GLOBAL                     4: functions
                        1368    LOAD_ATTR                       14: account
                        1388    LOAD_ATTR                       41: GetPrivacyRequest
                        1408    LOAD_GLOBAL                     11: NULL + types
                        1418    LOAD_ATTR                       56: InputPrivacyKeyAddedByPhone
                        1438    CALL                            0
                        1446    KW_NAMES                        18: ('key',)
                        1448    CALL                            1
                        1456    LOAD_GLOBAL                     4: functions
                        1466    LOAD_ATTR                       14: account
                        1486    LOAD_ATTR                       41: GetPrivacyRequest
                        1506    LOAD_GLOBAL                     11: NULL + types
                        1516    LOAD_ATTR                       58: InputPrivacyKeyVoiceMessages
                        1536    CALL                            0
                        1544    KW_NAMES                        18: ('key',)
                        1546    CALL                            1
                        1554    LOAD_GLOBAL                     4: functions
                        1564    LOAD_ATTR                       14: account
                        1584    LOAD_ATTR                       41: GetPrivacyRequest
                        1604    LOAD_GLOBAL                     11: NULL + types
                        1614    LOAD_ATTR                       60: InputPrivacyKeyAbout
                        1634    CALL                            0
                        1642    KW_NAMES                        18: ('key',)
                        1644    CALL                            1
                        1652    LOAD_GLOBAL                     4: functions
                        1662    LOAD_ATTR                       14: account
                        1682    LOAD_ATTR                       41: GetPrivacyRequest
                        1702    LOAD_GLOBAL                     11: NULL + types
                        1712    LOAD_ATTR                       62: InputPrivacyKeyBirthday
                        1732    CALL                            0
                        1740    KW_NAMES                        18: ('key',)
                        1742    CALL                            1
                        1750    BUILD_LIST                      11
                        1752    STORE_FAST                      2: _var_var_9
                        1754    LOAD_FAST                       0: self
                        1756    LOAD_ATTR                       39: client
                        1776    LOAD_FAST                       2: _var_var_9
                        1778    CALL                            1
                        1786    POP_TOP                         
                        1788    LOAD_GLOBAL                     4: functions
                        1798    LOAD_ATTR                       14: account
                        1818    LOAD_ATTR                       65: GetMultiWallPapersRequest
                        1838    LOAD_GLOBAL                     11: NULL + types
                        1848    LOAD_ATTR                       66: InputWallPaperSlug
                        1868    PUSH_NULL                       
                        1870    LOAD_CONST                      1: '__pyarmor_assert_14898__'
                        1872    LOAD_CONST                      19: 'lp0prF8ISFAEAAAA_p385_CvG0w'   # b'\x81\xee\x08C#\xe8\x98\x8a2\xc9+\xe1I\xcd\xd9\xa4.b\xab\xf4\xf2\x9eq\xef\x13H\xf3K'
                        1874    CALL                            1
                        1882    KW_NAMES                        20: ('slug',)
                        1884    CALL                            1
                        1892    LOAD_GLOBAL                     11: NULL + types
                        1902    LOAD_ATTR                       66: InputWallPaperSlug
                        1922    PUSH_NULL                       
                        1924    LOAD_CONST                      1: '__pyarmor_assert_14898__'
                        1926    LOAD_CONST                      21: 'MIo6r0qGSFAFAAAAtL8TsDzNX60'   # b'\x81\xcf1\x1ce\xe8\xee\xc3<\xc9+\xe1J\xcd\xd9\xa4.I\x97\xff\x9e\xd8j\xd6+W\xf5\x0c'
                        1928    CALL                            1
                        1936    KW_NAMES                        20: ('slug',)
                        1938    CALL                            1
                        1946    LOAD_GLOBAL                     11: NULL + types
                        1956    LOAD_ATTR                       66: InputWallPaperSlug
                        1976    PUSH_NULL                       
                        1978    LOAD_CONST                      1: '__pyarmor_assert_14898__'
                        1980    LOAD_CONST                      22: 'p-pXcflrmFIBAAAAvXYQk-mCwZU'   # b'\x81\xf2U\x03\x0b\xf9\xb8\xde\t\xf7+\xe9N\xcd\xd9\xa4.K\x83\x9e\x9b\xc0\x03\xc1&x\x99i'
                        1982    CALL                            1
                        1990    KW_NAMES                        20: ('slug',)
                        1992    CALL                            1
                        2000    LOAD_GLOBAL                     11: NULL + types
                        2010    LOAD_ATTR                       66: InputWallPaperSlug
                        2030    PUSH_NULL                       
                        2032    LOAD_CONST                      1: '__pyarmor_assert_14898__'
                        2034    LOAD_CONST                      23: 'CJNyxPMgSVAEAAAAvW9sMwc51cw'   # b'\x81\xc12=*\xe2\x8e\xff\x1c\xc9;\xe1I\xcd\xd9\xa4.K\x8c\xfe\xb9\xe6Y\xcfP>\xa0K'
                        2036    CALL                            1
                        2044    KW_NAMES                        20: ('slug',)
                        2046    CALL                            1
                        2054    LOAD_GLOBAL                     11: NULL + types
                        2064    LOAD_ATTR                       66: InputWallPaperSlug
                        2084    PUSH_NULL                       
                        2086    LOAD_CONST                      1: '__pyarmor_assert_14898__'
                        2088    LOAD_CONST                      24: 'mP3FG_iwSFAFAAAA2AklJO978pA'   # b'\x81\xef(@\x15\xdd\x81\xdb\x0c\xc9+\xe1J\xcd\xd9\xa4.\x0f\x9a\xac\xa6\xe1a\x95R7\xb3}'
                        2090    CALL                            1
                        2098    KW_NAMES                        20: ('slug',)
                        2100    CALL                            1
                        2108    LOAD_GLOBAL                     11: NULL + types
                        2118    LOAD_ATTR                       66: InputWallPaperSlug
                        2138    PUSH_NULL                       
                        2140    LOAD_CONST                      1: '__pyarmor_assert_14898__'
                        2142    LOAD_CONST                      25: 'O-wmAfBPSFADAAAA4zINVfD_bro'   # b'\x81\xcdU\x04>\xdb\xb8\xf0+\xc9+\xe1H\xcd\xd9\xa4.\t\xa1\x8e\x84\xfdH\xe8:m\xb1S'
                        2144    CALL                            1
                        2152    KW_NAMES                        20: ('slug',)
                        2154    CALL                            1
                        2162    LOAD_GLOBAL                     11: NULL + types
                        2172    LOAD_ATTR                       66: InputWallPaperSlug
                        2192    PUSH_NULL                       
                        2194    LOAD_CONST                      1: '__pyarmor_assert_14898__'
                        2196    LOAD_CONST                      26: '-Xc-np9y2VMCAAAARKr0yNNPYW0'   # b'\x81\xaf \x10~\xf4\xae\x8b\x02\xa8;\xedO\xcd\xd9\xa4.o\x90\xb5\xfa\xd2`\xe25V\x94\x0c'
                        2198    CALL                            1
                        2206    KW_NAMES                        20: ('slug',)
                        2208    CALL                            1
                        2216    LOAD_GLOBAL                     11: NULL + types
                        2226    LOAD_ATTR                       66: InputWallPaperSlug
                        2246    PUSH_NULL                       
                        2248    LOAD_CONST                      1: '__pyarmor_assert_14898__'
                        2250    LOAD_CONST                      27: 'kO4jyq55SFABAAAA0WEpcLfahXk'   # b'\x81\xe97G9\xe3\xaf\x87N\xc9+\xe1N\xcd\xd9\xa4.\r\x8c\x82\xba\xc8b\xca\x04g\x9bW'
                        2252    CALL                            1
                        2260    KW_NAMES                        20: ('slug',)
                        2262    CALL                            1
                        2270    LOAD_GLOBAL                     11: NULL + types
                        2280    LOAD_ATTR                       66: InputWallPaperSlug
                        2300    PUSH_NULL                       
                        2302    LOAD_CONST                      1: '__pyarmor_assert_14898__'
                        2304    LOAD_CONST                      28: 'fqv01SQemVIBAAAApND8LDRUhRU'   # b'\x81\xe4\t\x05c\xab\x8d\xe3\x1e\xf7;\xe9N\xcd\xd9\xa4.M\x95\x83\xf2\xe7j\xfe0g\x91i'
                        2306    CALL                            1
                        2314    KW_NAMES                        20: ('slug',)
                        2316    CALL                            1
                        2324    LOAD_GLOBAL                     11: NULL + types
                        2334    LOAD_ATTR                       66: InputWallPaperSlug
                        2354    PUSH_NULL                       
                        2356    LOAD_CONST                      1: '__pyarmor_assert_14898__'
                        2358    LOAD_CONST                      29: 'RepJ5uE_SVABAAAAr4d0YhgB850'   # b"\x81\xd0\x1d\x03\x19\xaf\xab\xf7$\xc9;\xe1N\xcd\xd9\xa4.O\xef\xa3\xfa\xf2F\xcb'7\xf6\x0c"
                        2360    CALL                            1
                        2368    KW_NAMES                        20: ('slug',)
                        2370    CALL                            1
                        2378    LOAD_GLOBAL                     11: NULL + types
                        2388    LOAD_ATTR                       66: InputWallPaperSlug
                        2408    PUSH_NULL                       
                        2410    LOAD_CONST                      1: '__pyarmor_assert_14898__'
                        2412    LOAD_CONST                      30: 'JqSUrO0-mFIBAAAAWwTvLzoWGQI'   # b'\x81\xc8\t \x06\xe8\x91\x82V\xf7+\xe9N\xcd\xd9\xa4.j\xac\x93\xbc\xe7T\xc32H\x92u'
                        2414    CALL                            1
                        2422    KW_NAMES                        20: ('slug',)
                        2424    CALL                            1
                        2432    LOAD_GLOBAL                     11: NULL + types
                        2442    LOAD_ATTR                       66: InputWallPaperSlug
                        2462    PUSH_NULL                       
                        2464    LOAD_CONST                      1: '__pyarmor_assert_14898__'
                        2466    LOAD_CONST                      31: 'dk_wwlghOFACAAAAfz9xrxi6euw'   # b'\x81\xe6\x13,$\xed\xb2\xd5\x13\xd5+\xe1O\xcd\xd9\xa4.[\xa1\xfe\xb2\xd9V\xc5Sj\xb6K'
                        2468    CALL                            1
                        2476    KW_NAMES                        20: ('slug',)
                        2478    CALL                            1
                        2486    LOAD_GLOBAL                     11: NULL + types
                        2496    LOAD_ATTR                       66: InputWallPaperSlug
                        2516    PUSH_NULL                       
                        2518    LOAD_CONST                      1: '__pyarmor_assert_14898__'
                        2520    LOAD_CONST                      32: 'Ujx2TFcJSVACAAAARJ4vLa50MkM'   # b'\x81\xd7\x12\x0ba\xce\x98\xd11\xc9;\xe1O\xcd\xd9\xa4.o\x91\xf3\xbc\xe7O\x99UB\xa8q'
                        2522    CALL                            1
                        2530    KW_NAMES                        20: ('slug',)
                        2532    CALL                            1
                        2540    LOAD_GLOBAL                     11: NULL + types
                        2550    LOAD_ATTR                       66: InputWallPaperSlug
                        2570    PUSH_NULL                       
                        2572    LOAD_CONST                      1: '__pyarmor_assert_14898__'
                        2574    LOAD_CONST                      33: 'dhf9pceaQVACAAAAbzdVo4SCiZA'   # b'\x81\xe6\x10\x15j\xea\xbd\xd7\x1a\xcb;\xe1O\xcd\xd9\xa4._\xa1\xa3\x9c\xc4\x1a\xff&f\x99}'
                        2576    CALL                            1
                        2584    KW_NAMES                        20: ('slug',)
                        2586    CALL                            1
                        2594    LOAD_GLOBAL                     11: NULL + types
                        2604    LOAD_ATTR                       66: InputWallPaperSlug
                        2624    PUSH_NULL                       
                        2626    LOAD_CONST                      1: '__pyarmor_assert_14898__'
                        2628    LOAD_CONST                      34: 'PllZ-bf_SFAEAAAA8crRfwZiDNg'   # b'\x81\xd2\x14\x1f\t\xb7\xbc\xd4$\xc9+\xe1I\xcd\xd9\xa4.\x05\xb8\xb5\x98\xcdY\xf6\x0cK\x8d['
                        2630    CALL                            1
                        2638    KW_NAMES                        20: ('slug',)
                        2640    CALL                            1
                        2648    LOAD_GLOBAL                     11: NULL + types
                        2658    LOAD_ATTR                       66: InputWallPaperSlug
                        2678    PUSH_NULL                       
                        2680    LOAD_CONST                      1: '__pyarmor_assert_14898__'
                        2682    LOAD_CONST                      35: 'heptcj-hSVACAAAAC9RrMzOa-cs'   # b'\x81\xea\x1d\x03\'\xf9\xb4\x9f\x13\xc9;\xe1O\xcd\xd9\xa4.~\xe2\x95\xb8\xe6T\xe3\x04"\xa0O'
                        2684    CALL                            1
                        2692    KW_NAMES                        20: ('slug',)
                        2694    CALL                            1
                        2702    LOAD_GLOBAL                     11: NULL + types
                        2712    LOAD_ATTR                       66: InputWallPaperSlug
                        2732    PUSH_NULL                       
                        2734    LOAD_CONST                      1: '__pyarmor_assert_14898__'
                        2736    LOAD_CONST                      36: '9LW_RcoOSVACAAAAFTk3DTyXN-M'   # b'\x81\xbb4$\x0c\xc8\xbd\xdd4\xc9;\xe1O\xcd\xd9\xa4.{\x8f\xac\xf9\xefz\xd5=A\xeeq'
                        2738    CALL                            1
                        2746    KW_NAMES                        20: ('slug',)
                        2748    CALL                            1
                        2756    LOAD_GLOBAL                     11: NULL + types
                        2766    LOAD_ATTR                       66: InputWallPaperSlug
                        2786    PUSH_NULL                       
                        2788    LOAD_CONST                      1: '__pyarmor_assert_14898__'
                        2790    LOAD_CONST                      37: '3rX-PaKbSFACAAAAEiHNvcEm6X4'   # b'\x81\xb1\n+~\xca\xbf\xf9\x19\xc9+\xe1O\xcd\xd9\xa4.x\xb2\x8f\x84\xddM\xe9\x089\x9b\x08'
                        2792    CALL                            1
                        2800    KW_NAMES                        20: ('slug',)
                        2802    CALL                            1
                        2810    LOAD_GLOBAL                     11: NULL + types
                        2820    LOAD_ATTR                       66: InputWallPaperSlug
                        2840    PUSH_NULL                       
                        2842    LOAD_CONST                      1: '__pyarmor_assert_14898__'
                        2844    LOAD_CONST                      38: '9ShF73d1MFIIAAAAjWnm8_ZMe8Q'   # b'\x81\xbb+\x1b\x15\xad\xed\xd6J\xd7+\xe9E\xcd\xd9\xa4.W\x8c\xa9\xa7\x93q\xf6(j\xfbm'
                        2846    CALL                            1
                        2854    KW_NAMES                        20: ('slug',)
                        2856    CALL                            1
                        2864    LOAD_GLOBAL                     11: NULL + types
                        2874    LOAD_ATTR                       66: InputWallPaperSlug
                        2894    PUSH_NULL                       
                        2896    LOAD_CONST                      1: '__pyarmor_assert_14898__'
                        2898    LOAD_CONST                      39: 'F5oWoCs7QFACAAAAgf2bD_mg8Bw'   # b'\x81\xc4M\x1c\x04\xf5\x9d\xc1L\xcb+\xe1O\xcd\xd9\xa4.Z\xbd\xf5\xa8\xefq\xc1\x027\x81K'
                        2900    CALL                            1
                        2908    KW_NAMES                        20: ('slug',)
                        2910    CALL                            1
                        2918    LOAD_GLOBAL                     11: NULL + types
                        2928    LOAD_ATTR                       66: InputWallPaperSlug
                        2948    PUSH_NULL                       
                        2950    LOAD_CONST                      1: '__pyarmor_assert_14898__'
                        2952    LOAD_CONST                      40: '9GcNVISdSVADAAAAUcw5BYjELW4'   # b'\x81\xbb?\x10\x1d\xcc\x97\xe1\x1f\xc9;\xe1H\xcd\xd9\xa4.h\xb8\xb0\xff\xe9w\xc6 C\x94\x08'
                        2954    CALL                            1
                        2962    KW_NAMES                        20: ('slug',)
                        2964    CALL                            1
                        2972    LOAD_GLOBAL                     11: NULL + types
                        2982    LOAD_ATTR                       66: InputWallPaperSlug
                        3002    PUSH_NULL                       
                        3004    LOAD_CONST                      1: '__pyarmor_assert_14898__'
                        3006    LOAD_CONST                      41: '9iklpvIPQVABAAAAORQXKur_Eyc'   # b'\x81\xbb\x11\x18?\xea\xa8\xfb+\xcb;\xe1N\xcd\xd9\xa4.r\x89\x96\x92\xe0[\xde:J\xba_'
                        3008    CALL                            1
                        3016    KW_NAMES                        20: ('slug',)
                        3018    CALL                            1
                        3026    LOAD_GLOBAL                     11: NULL + types
                        3036    LOAD_ATTR                       66: InputWallPaperSlug
                        3056    PUSH_NULL                       
                        3058    LOAD_CONST                      1: '__pyarmor_assert_14898__'
                        3060    LOAD_CONST                      42: 'ptuUd96JSFACAAAATobI23sPpz0'   # b'\x81\xf2\x0c\x06\x06\xfe\xe7\x841\xc9+\xe1O\xcd\xd9\xa4.i\xb4\xa5\x83\x99\x1d\xdf5\x7f\xb9\x0c'
                        3062    CALL                            1
                        3070    KW_NAMES                        20: ('slug',)
                        3072    CALL                            1
                        3080    LOAD_GLOBAL                     11: NULL + types
                        3090    LOAD_ATTR                       66: InputWallPaperSlug
                        3110    PUSH_NULL                       
                        3112    LOAD_CONST                      1: '__pyarmor_assert_14898__'
                        3114    LOAD_CONST                      43: 'pgJfpFNRSFABAAAACDT8s5sEjfc'   # b'\x81\xf2\x1f95\xea\x98\xfc)\xc9+\xe1N\xcd\xd9\xa4.~\x9f\x93\xf2\xd8\x1b\xdf e\xa5_'
                        3116    CALL                            1
                        3124    KW_NAMES                        20: ('slug',)
                        3126    CALL                            1
                        3134    LOAD_GLOBAL                     11: NULL + types
                        3144    LOAD_ATTR                       66: InputWallPaperSlug
                        3164    PUSH_NULL                       
                        3166    LOAD_CONST                      1: '__pyarmor_assert_14898__'
                        3168    LOAD_CONST                      44: 'YIxYGEALQVADAAAAA3QbEH0AowY'   # b'\x81\xdb1\x0b\n\xdd\x9b\xf37\xcb;\xe1H\xcd\xd9\xa4.|\xe8\x96\xa8\xeef\x9c$`\xb4e'
                        3170    CALL                            1
                        3178    KW_NAMES                        20: ('slug',)
                        3180    CALL                            1
                        3188    LOAD_GLOBAL                     11: NULL + types
                        3198    LOAD_ATTR                       66: InputWallPaperSlug
                        3218    PUSH_NULL                       
                        3220    LOAD_CONST                      1: '__pyarmor_assert_14898__'
                        3222    LOAD_CONST                      45: 'Nl8Pg2rBQVACAAAA25Lxtb8SDp0'   # b'\x81\xcc\x14K\x03\xfd\xec\xc09\xcb;\xe1O\xcd\xd9\xa4.\x0f\xee\x8b\xb2\xdfL\x946K\xb3\x0c'
                        3224    CALL                            1
                        3232    KW_NAMES                        20: ('slug',)
                        3234    CALL                            1
                        3242    BUILD_LIST                      26
                        3244    KW_NAMES                        46: ('wallpapers',)
                        3246    CALL                            1
                        3254    BUILD_LIST                      1
                        3256    STORE_FAST                      2: _var_var_9
                        3258    LOAD_FAST                       0: self
                        3260    LOAD_ATTR                       39: client
                        3280    LOAD_FAST                       2: _var_var_9
                        3282    CALL                            1
                        3290    POP_TOP                         
                        3292    LOAD_FAST                       0: self
                        3294    LOAD_ATTR                       2: app_id
                        3314    LOAD_CONST                      47: 21724
                        3316    COMPARE_OP                      40 (==)
                        3320    POP_JUMP_IF_FALSE               311 (to 3946)
                        3324    LOAD_GLOBAL                     4: functions
                        3334    LOAD_ATTR                       6: messages
                        3354    LOAD_ATTR                       9: GetStickerSetRequest
                        3374    LOAD_GLOBAL                     11: NULL + types
                        3384    LOAD_ATTR                       12: InputStickerSetShortName
                        3404    PUSH_NULL                       
                        3406    LOAD_CONST                      1: '__pyarmor_assert_14898__'
                        3408    LOAD_CONST                      7: 'tg_placeholders_android'   # b'\x81\xf6\x1f,#\xf6\xbf\xd1\x1e\xf2\x02\xcch\xe9\xea\x960\\\xb5\xa3\xb8\xc4G\xc8'
                        3410    CALL                            1
                        3418    KW_NAMES                        8: ('short_name',)
                        3420    CALL                            1
                        3428    LOAD_CONST                      9: 0
                        3430    KW_NAMES                        10: ('stickerset', 'hash')
                        3432    CALL                            2
                        3440    LOAD_GLOBAL                     4: functions
                        3450    LOAD_ATTR                       14: account
                        3470    LOAD_ATTR                       17: GetThemesRequest
                        3490    LOAD_FAST                       0: self
                        3492    LOAD_ATTR                       18: os
                        3512    LOAD_CONST                      9: 0
                        3514    KW_NAMES                        11: ('format', 'hash')
                        3516    CALL                            2
                        3524    LOAD_GLOBAL                     4: functions
                        3534    LOAD_ATTR                       68: langpack
                        3554    LOAD_ATTR                       71: GetLangPack_tdlib_Request
                        3574    PUSH_NULL                       
                        3576    LOAD_CONST                      1: '__pyarmor_assert_14898__'
                        3578    LOAD_CONST                      48: 'android_x'   # b'\x81\xe3\x16\x17!\xf5\xb7\xd6$\xe2'
                        3580    CALL                            1
                        3588    LOAD_FAST                       0: self
                        3590    LOAD_ATTR                       72: lang_code
                        3610    CALL                            2
                        3618    LOAD_GLOBAL                     4: functions
                        3628    LOAD_ATTR                       20: help
                        3648    LOAD_ATTR                       75: GetPromoDataRequest
                        3668    CALL                            0
                        3676    LOAD_GLOBAL                     4: functions
                        3686    LOAD_ATTR                       68: langpack
                        3706    LOAD_ATTR                       77: GetLanguages_tdlib_Request
                        3726    PUSH_NULL                       
                        3728    LOAD_CONST                      1: '__pyarmor_assert_14898__'
                        3730    LOAD_CONST                      48: 'android_x'   # b'\x81\xe3\x16\x17!\xf5\xb7\xd6$\xe2'
                        3732    CALL                            1
                        3740    CALL                            1
                        3748    LOAD_GLOBAL                     4: functions
                        3758    LOAD_ATTR                       14: account
                        3778    LOAD_ATTR                       79: GetGlobalPrivacySettingsRequest
                        3798    CALL                            0
                        3806    LOAD_GLOBAL                     4: functions
                        3816    LOAD_ATTR                       80: contacts
                        3836    LOAD_ATTR                       83: GetBirthdaysRequest
                        3856    CALL                            0
                        3864    BUILD_LIST                      7
                        3866    STORE_FAST                      2: _var_var_9
                        3868    NOP                             
                        3870    LOAD_GLOBAL                     85: NULL + random
                        3880    LOAD_ATTR                       86: shuffle
                        3900    LOAD_FAST                       2: _var_var_9
                        3902    CALL                            1
                        3910    POP_TOP                         
                        3912    LOAD_FAST                       0: self
                        3914    LOAD_ATTR                       39: client
                        3934    LOAD_FAST                       2: _var_var_9
                        3936    CALL                            1
                        3944    POP_TOP                         
                        3946    LOAD_CONST                      0: None
                        3948    NOP                             
                        3950    NOP                             
                        3952    NOP                             
                        3954    JUMP_FORWARD                    50 (to 4056)
                        3962    POP_TOP                         
                        3964    RETURN_CONST                    0: None
                        3966    PUSH_EXC_INFO                   
                        3968    POP_TOP                         
                        3970    POP_EXCEPT                      
                        3972    JUMP_BACKWARD                   1652 (to 672)
                        3976    COPY                            3
                        3978    POP_EXCEPT                      
                        3980    RERAISE                         1
                        3982    PUSH_EXC_INFO                   
                        3984    POP_TOP                         
                        3986    POP_EXCEPT                      
                        3988    JUMP_BACKWARD                   1102 (to 1788)
                        3992    COPY                            3
                        3994    POP_EXCEPT                      
                        3996    RERAISE                         1
                        3998    PUSH_EXC_INFO                   
                        4000    POP_TOP                         
                        4002    POP_EXCEPT                      
                        4004    JUMP_BACKWARD                   358 (to 3292)
                        4008    COPY                            3
                        4010    POP_EXCEPT                      
                        4012    RERAISE                         1
                        4014    PUSH_EXC_INFO                   
                        4016    POP_TOP                         
                        4018    POP_EXCEPT                      
                        4020    JUMP_BACKWARD                   38 (to 3946)
                        4022    COPY                            3
                        4024    POP_EXCEPT                      
                        4026    RERAISE                         1
                        4028    PUSH_EXC_INFO                   
                        4030    PUSH_NULL                       
                        4032    LOAD_CONST                      4: '__pyarmor_exit_14900__'
                        4034    NOP                             
                        4036    LOAD_CONST                      3: b'<COAddr>\x05\x00\x00\x1a\xa2\x0f\x00\x00\x00\x00\x00\x00\x00\x00\x00\x00\x00\x00\x00\x00'
                        4038    CALL                            1
                        4046    POP_TOP                         
                        4048    RERAISE                         0
                        4050    COPY                            3
                        4052    POP_EXCEPT                      
                        4054    RERAISE                         1
                        4056    PUSH_NULL                       
                        4058    LOAD_CONST                      4: '__pyarmor_exit_14900__'
                        4060    LOAD_CONST                      3: b'<COAddr>\x05\x00\x00\x1a\xa2\x0f\x00\x00\x00\x00\x00\x00\x00\x00\x00\x00\x00\x00\x00\x00'
                        4062    BUILD_TUPLE                     1
                        4064    CALL_FUNCTION_EX                0
                        4066    POP_TOP                         
                        4068    RETURN_VALUE                    
                    [Exception Table]
                        28 to 52 -> 4028 [0] 
                        74 to 636 -> 4028 [0] 
                        638 to 672 -> 3966 [0] 
                        672 to 1754 -> 4028 [0] 
                        1754 to 1788 -> 3982 [0] 
                        1788 to 3258 -> 4028 [0] 
                        3258 to 3292 -> 3998 [0] 
                        3292 to 3868 -> 4028 [0] 
                        3870 to 3946 -> 4014 [0] 
                        3966 to 3970 -> 3976 [1] lasti
                        3970 to 3982 -> 4028 [0] 
                        3982 to 3986 -> 3992 [1] lasti
                        3986 to 3998 -> 4028 [0] 
                        3998 to 4002 -> 4008 [1] lasti
                        4002 to 4014 -> 4028 [0] 
                        4014 to 4018 -> 4022 [1] lasti
                        4018 to 4028 -> 4028 [0] 
                        4028 to 4050 -> 4050 [1] lasti
                [Code]
                    File Name: <frozen program.modules.func.android>
                    Object Name: check
                    Qualified Name: AndroidRequests.check
                    Arg Count: 1
                    Pos Only Arg Count: 0
                    KW Only Arg Count: 0
                    Stack Size: 27
                    Flags: 0x20000003 (CO_OPTIMIZED | CO_NEWLOCALS | CO_PYARMOR_OBFUSCATED)
                    [Names]
                        'option_check'
                        'app_id'
                        'functions'
                        'account'
                        'GetDefaultProfilePhotoEmojisRequest'
                        'messages'
                        'GetTopReactionsRequest'
                        'GetGlobalPrivacySettingsRequest'
                        'GetRecentReactionsRequest'
                        'GetStickersRequest'
                        'contacts'
                        'GetContactsRequest'
                        'GetFavedStickersRequest'
                        'users'
                        'GetFullUserRequest'
                        'types'
                        'InputUserSelf'
                        'GetAttachMenuBotsRequest'
                        'GetFeaturedStickersRequest'
                        'GetFeaturedEmojiStickersRequest'
                        'GetAvailableReactionsRequest'
                        'GetStickerSetRequest'
                        'InputStickerSetEmojiGenericAnimations'
                        'help'
                        'GetAppConfigRequest'
                        'GetPromoDataRequest'
                        'GetPremiumPromoRequest'
                        'GetAutoDownloadSettingsRequest'
                        'SaveAppLogRequest'
                        'InputAppEvent'
                        'datetime'
                        'now'
                        'timezone'
                        'utc'
                        'timestamp'
                        'JsonBool'
                        'random'
                        'shuffle'
                        'client'
                        'Exception'
                        '_random_search'
                    [Locals+Names]
                        'self'
                        '__assert_armored__'
                        '_var_var_9'
                        '_var_var_10'
                    [Constants]
                        None
                        '__pyarmor_assert_14901__'
                        '__pyarmor_enter_14902__'
                        b'<COAddr>\x07\x00\x00\x1a\xa6\x06\x00\x00\x00\x00\x00\x00\x00\x00\x00\x00\x00\x00\x00\x00'
                        '__pyarmor_exit_14903__'
                        4
                        6
                        0
                        (
                            'hash'
                        )
                        100
                        (
                            'limit'
                            'hash'
                        )
                        50
                        '📂⭐'
                        (
                            'emoticon'
                            'hash'
                        )
                        (
                            'id'
                        )
                        (
                            'stickerset'
                            'hash'
                        )
                        (
                            'tz'
                        )
                        'android_sdcard_exists'   # b'\x81\xe3\x16\x17!\xf5\xb7\xd6$\xe9\t\xc3m\xfe\xfc\xba\nE\xb2\xb4\xbe\xd8'
                        1
                        True
                        (
                            'time'
                            'type'
                            'peer'
                            'data'
                        )
                        (
                            'events'
                        )
                    [Disassembly]
                        0       NOP                             
                        2       NOP                             
                        4       PUSH_NULL                       
                        6       LOAD_CONST                      2: '__pyarmor_enter_14902__'
                        8       LOAD_CONST                      3: b'<COAddr>\x07\x00\x00\x1a\xa6\x06\x00\x00\x00\x00\x00\x00\x00\x00\x00\x00\x00\x00\x00\x00'
                        10      BUILD_TUPLE                     1
                        12      CALL_FUNCTION_EX                0
                        14      POP_TOP                         
                        16      RESUME                          0
                        18      NOP                             
                        20      NOP                             
                        22      NOP                             
                        24      NOP                             
                        26      NOP                             
                        28      LOAD_FAST                       0: self
                        30      LOAD_ATTR                       0: option_check
                        50      POP_JUMP_IF_TRUE                11 (to 74)
                        52      NOP                             
                        54      LOAD_CONST                      0: None
                        56      NOP                             
                        58      NOP                             
                        60      JUMP_FORWARD                    846 (to 1756)
                        70      POP_TOP                         
                        72      RETURN_CONST                    0: None
                        74      LOAD_FAST                       0: self
                        76      LOAD_ATTR                       2: app_id
                        96      LOAD_CONST                      5: 4
                        98      COMPARE_OP                      40 (==)
                        102     POP_JUMP_IF_TRUE                16 (to 136)
                        104     LOAD_FAST                       0: self
                        106     LOAD_ATTR                       2: app_id
                        126     LOAD_CONST                      6: 6
                        128     COMPARE_OP                      40 (==)
                        132     POP_JUMP_IF_FALSE               748 (to 1632)
                        136     LOAD_GLOBAL                     4: functions
                        146     LOAD_ATTR                       6: account
                        166     LOAD_ATTR                       9: GetDefaultProfilePhotoEmojisRequest
                        186     LOAD_CONST                      7: 0
                        188     KW_NAMES                        8: ('hash',)
                        190     CALL                            1
                        198     LOAD_GLOBAL                     4: functions
                        208     LOAD_ATTR                       10: messages
                        228     LOAD_ATTR                       13: GetTopReactionsRequest
                        248     LOAD_CONST                      9: 100
                        250     LOAD_CONST                      7: 0
                        252     KW_NAMES                        10: ('limit', 'hash')
                        254     CALL                            2
                        262     LOAD_GLOBAL                     4: functions
                        272     LOAD_ATTR                       6: account
                        292     LOAD_ATTR                       15: GetGlobalPrivacySettingsRequest
                        312     CALL                            0
                        320     LOAD_GLOBAL                     4: functions
                        330     LOAD_ATTR                       10: messages
                        350     LOAD_ATTR                       17: GetRecentReactionsRequest
                        370     LOAD_CONST                      11: 50
                        372     LOAD_CONST                      7: 0
                        374     KW_NAMES                        10: ('limit', 'hash')
                        376     CALL                            2
                        384     LOAD_GLOBAL                     4: functions
                        394     LOAD_ATTR                       10: messages
                        414     LOAD_ATTR                       19: GetStickersRequest
                        434     LOAD_CONST                      12: '📂⭐'
                        436     LOAD_CONST                      7: 0
                        438     KW_NAMES                        13: ('emoticon', 'hash')
                        440     CALL                            2
                        448     LOAD_GLOBAL                     4: functions
                        458     LOAD_ATTR                       20: contacts
                        478     LOAD_ATTR                       23: GetContactsRequest
                        498     LOAD_CONST                      7: 0
                        500     KW_NAMES                        8: ('hash',)
                        502     CALL                            1
                        510     LOAD_GLOBAL                     4: functions
                        520     LOAD_ATTR                       10: messages
                        540     LOAD_ATTR                       25: GetFavedStickersRequest
                        560     LOAD_CONST                      7: 0
                        562     KW_NAMES                        8: ('hash',)
                        564     CALL                            1
                        572     LOAD_GLOBAL                     4: functions
                        582     LOAD_ATTR                       26: users
                        602     LOAD_ATTR                       29: GetFullUserRequest
                        622     LOAD_GLOBAL                     31: NULL + types
                        632     LOAD_ATTR                       32: InputUserSelf
                        652     CALL                            0
                        660     KW_NAMES                        14: ('id',)
                        662     CALL                            1
                        670     LOAD_GLOBAL                     4: functions
                        680     LOAD_ATTR                       10: messages
                        700     LOAD_ATTR                       35: GetAttachMenuBotsRequest
                        720     LOAD_CONST                      7: 0
                        722     KW_NAMES                        8: ('hash',)
                        724     CALL                            1
                        732     LOAD_GLOBAL                     4: functions
                        742     LOAD_ATTR                       10: messages
                        762     LOAD_ATTR                       37: GetFeaturedStickersRequest
                        782     LOAD_CONST                      7: 0
                        784     KW_NAMES                        8: ('hash',)
                        786     CALL                            1
                        794     LOAD_GLOBAL                     4: functions
                        804     LOAD_ATTR                       10: messages
                        824     LOAD_ATTR                       39: GetFeaturedEmojiStickersRequest
                        844     LOAD_CONST                      7: 0
                        846     KW_NAMES                        8: ('hash',)
                        848     CALL                            1
                        856     LOAD_GLOBAL                     4: functions
                        866     LOAD_ATTR                       10: messages
                        886     LOAD_ATTR                       41: GetAvailableReactionsRequest
                        906     LOAD_CONST                      7: 0
                        908     KW_NAMES                        8: ('hash',)
                        910     CALL                            1
                        918     LOAD_GLOBAL                     4: functions
                        928     LOAD_ATTR                       10: messages
                        948     LOAD_ATTR                       43: GetStickerSetRequest
                        968     LOAD_GLOBAL                     31: NULL + types
                        978     LOAD_ATTR                       44: InputStickerSetEmojiGenericAnimations
                        998     CALL                            0
                        1006    LOAD_CONST                      7: 0
                        1008    KW_NAMES                        15: ('stickerset', 'hash')
                        1010    CALL                            2
                        1018    LOAD_GLOBAL                     4: functions
                        1028    LOAD_ATTR                       46: help
                        1048    LOAD_ATTR                       49: GetAppConfigRequest
                        1068    LOAD_CONST                      7: 0
                        1070    KW_NAMES                        8: ('hash',)
                        1072    CALL                            1
                        1080    LOAD_GLOBAL                     4: functions
                        1090    LOAD_ATTR                       46: help
                        1110    LOAD_ATTR                       51: GetPromoDataRequest
                        1130    CALL                            0
                        1138    LOAD_GLOBAL                     4: functions
                        1148    LOAD_ATTR                       46: help
                        1168    LOAD_ATTR                       53: GetPremiumPromoRequest
                        1188    CALL                            0
                        1196    LOAD_GLOBAL                     4: functions
                        1206    LOAD_ATTR                       6: account
                        1226    LOAD_ATTR                       55: GetAutoDownloadSettingsRequest
                        1246    CALL                            0
                        1254    LOAD_GLOBAL                     4: functions
                        1264    LOAD_ATTR                       46: help
                        1284    LOAD_ATTR                       57: SaveAppLogRequest
                        1304    LOAD_GLOBAL                     31: NULL + types
                        1314    LOAD_ATTR                       58: InputAppEvent
                        1334    LOAD_GLOBAL                     60: datetime
                        1344    LOAD_ATTR                       60: datetime
                        1364    LOAD_ATTR                       63: now
                        1384    LOAD_GLOBAL                     60: datetime
                        1394    LOAD_ATTR                       64: timezone
                        1414    LOAD_ATTR                       66: utc
                        1434    KW_NAMES                        16: ('tz',)
                        1436    CALL                            1
                        1444    LOAD_ATTR                       69: timestamp
                        1464    CALL                            0
                        1472    PUSH_NULL                       
                        1474    LOAD_CONST                      1: '__pyarmor_assert_14901__'
                        1476    LOAD_CONST                      17: 'android_sdcard_exists'   # b'\x81\xe3\x16\x17!\xf5\xb7\xd6$\xe9\t\xc3m\xfe\xfc\xba\nE\xb2\xb4\xbe\xd8'
                        1478    CALL                            1
                        1486    LOAD_CONST                      18: 1
                        1488    LOAD_GLOBAL                     31: NULL + types
                        1498    LOAD_ATTR                       70: JsonBool
                        1518    LOAD_CONST                      19: True
                        1520    CALL                            1
                        1528    KW_NAMES                        20: ('time', 'type', 'peer', 'data')
                        1530    CALL                            4
                        1538    BUILD_LIST                      1
                        1540    KW_NAMES                        21: ('events',)
                        1542    CALL                            1
                        1550    BUILD_LIST                      18
                        1552    STORE_FAST                      2: _var_var_9
                        1554    NOP                             
                        1556    LOAD_GLOBAL                     73: NULL + random
                        1566    LOAD_ATTR                       74: shuffle
                        1586    LOAD_FAST                       2: _var_var_9
                        1588    CALL                            1
                        1596    POP_TOP                         
                        1598    LOAD_FAST                       0: self
                        1600    LOAD_ATTR                       77: client
                        1620    LOAD_FAST                       2: _var_var_9
                        1622    CALL                            1
                        1630    POP_TOP                         
                        1632    LOAD_FAST                       0: self
                        1634    LOAD_ATTR                       81: _random_search
                        1654    CALL                            0
                        1662    POP_TOP                         
                        1664    LOAD_CONST                      0: None
                        1666    NOP                             
                        1668    NOP                             
                        1670    NOP                             
                        1672    JUMP_FORWARD                    41 (to 1756)
                        1680    POP_TOP                         
                        1682    RETURN_CONST                    0: None
                        1684    PUSH_EXC_INFO                   
                        1686    LOAD_GLOBAL                     78: Exception
                        1696    CHECK_EXC_MATCH                 
                        1698    POP_JUMP_IF_FALSE               10 (to 1720)
                        1700    STORE_FAST                      3: _var_var_10
                        1702    POP_EXCEPT                      
                        1704    LOAD_CONST                      0: None
                        1706    STORE_FAST                      3: _var_var_10
                        1708    DELETE_FAST                     3: _var_var_10
                        1710    JUMP_BACKWARD                   40 (to 1632)
                        1712    LOAD_CONST                      0: None
                        1714    STORE_FAST                      3: _var_var_10
                        1716    DELETE_FAST                     3: _var_var_10
                        1718    RERAISE                         1
                        1720    RERAISE                         0
                        1722    COPY                            3
                        1724    POP_EXCEPT                      
                        1726    RERAISE                         1
                        1728    PUSH_EXC_INFO                   
                        1730    PUSH_NULL                       
                        1732    LOAD_CONST                      4: '__pyarmor_exit_14903__'
                        1734    NOP                             
                        1736    LOAD_CONST                      3: b'<COAddr>\x07\x00\x00\x1a\xa6\x06\x00\x00\x00\x00\x00\x00\x00\x00\x00\x00\x00\x00\x00\x00'
                        1738    CALL                            1
                        1746    POP_TOP                         
                        1748    RERAISE                         0
                        1750    COPY                            3
                        1752    POP_EXCEPT                      
                        1754    RERAISE                         1
                        1756    PUSH_NULL                       
                        1758    LOAD_CONST                      4: '__pyarmor_exit_14903__'
                        1760    LOAD_CONST                      3: b'<COAddr>\x07\x00\x00\x1a\xa6\x06\x00\x00\x00\x00\x00\x00\x00\x00\x00\x00\x00\x00\x00\x00'
                        1762    BUILD_TUPLE                     1
                        1764    CALL_FUNCTION_EX                0
                        1766    POP_TOP                         
                        1768    RETURN_VALUE                    
                    [Exception Table]
                        28 to 52 -> 1728 [0] 
                        74 to 1554 -> 1728 [0] 
                        1556 to 1632 -> 1684 [0] 
                        1632 to 1664 -> 1728 [0] 
                        1684 to 1702 -> 1722 [1] lasti
                        1702 to 1712 -> 1728 [0] 
                        1712 to 1722 -> 1722 [1] lasti
                        1722 to 1728 -> 1728 [0] 
                        1728 to 1750 -> 1750 [1] lasti
                [Code]
                    File Name: <frozen program.modules.func.android>
                    Object Name: work
                    Qualified Name: AndroidRequests.work
                    Arg Count: 1
                    Pos Only Arg Count: 0
                    KW Only Arg Count: 0
                    Stack Size: 27
                    Flags: 0x20000003 (CO_OPTIMIZED | CO_NEWLOCALS | CO_PYARMOR_OBFUSCATED)
                    [Names]
                        'option_work'
                        'app_id'
                        'functions'
                        'account'
                        'GetDefaultProfilePhotoEmojisRequest'
                        'messages'
                        'GetTopReactionsRequest'
                        'GetGlobalPrivacySettingsRequest'
                        'GetRecentReactionsRequest'
                        'GetStickersRequest'
                        'contacts'
                        'GetContactsRequest'
                        'GetFavedStickersRequest'
                        'users'
                        'GetFullUserRequest'
                        'types'
                        'InputUserSelf'
                        'GetAttachMenuBotsRequest'
                        'GetFeaturedStickersRequest'
                        'GetFeaturedEmojiStickersRequest'
                        'GetAvailableReactionsRequest'
                        'GetStickerSetRequest'
                        'InputStickerSetEmojiGenericAnimations'
                        'help'
                        'GetAppConfigRequest'
                        'GetPromoDataRequest'
                        'GetPremiumPromoRequest'
                        'GetAutoDownloadSettingsRequest'
                        'SaveAppLogRequest'
                        'InputAppEvent'
                        'datetime'
                        'now'
                        'timezone'
                        'utc'
                        'timestamp'
                        'JsonBool'
                        'random'
                        'shuffle'
                        'client'
                        '_random_search'
                    [Locals+Names]
                        'self'
                        '__assert_armored__'
                        '_var_var_9'
                    [Constants]
                        None
                        '__pyarmor_assert_14904__'
                        '__pyarmor_enter_14905__'
                        b'<COAddr>\x07\x00\x00\x1ah\x0b\x00\x00\x00\x00\x00\x00\x00\x00\x00\x00\x00\x00\x00\x00'
                        '__pyarmor_exit_14906__'
                        4
                        6
                        0
                        (
                            'hash'
                        )
                        100
                        (
                            'limit'
                            'hash'
                        )
                        50
                        '📂⭐'
                        (
                            'emoticon'
                            'hash'
                        )
                        (
                            'id'
                        )
                        (
                            'stickerset'
                            'hash'
                        )
                        (
                            'tz'
                        )
                        'android_sdcard_exists'   # b'\x81\xe3\x16\x17!\xf5\xb7\xd6$\xe9\t\xc3m\xfe\xfc\xba\nE\xb2\xb4\xbe\xd8'
                        1
                        True
                        (
                            'time'
                            'type'
                            'peer'
                            'data'
                        )
                        (
                            'events'
                        )
                        21724
                    [Disassembly]
                        0       NOP                             
                        2       NOP                             
                        4       PUSH_NULL                       
                        6       LOAD_CONST                      2: '__pyarmor_enter_14905__'
                        8       LOAD_CONST                      3: b'<COAddr>\x07\x00\x00\x1ah\x0b\x00\x00\x00\x00\x00\x00\x00\x00\x00\x00\x00\x00\x00\x00'
                        10      BUILD_TUPLE                     1
                        12      CALL_FUNCTION_EX                0
                        14      POP_TOP                         
                        16      RESUME                          0
                        18      NOP                             
                        20      NOP                             
                        22      NOP                             
                        24      NOP                             
                        26      NOP                             
                        28      LOAD_FAST                       0: self
                        30      LOAD_ATTR                       0: option_work
                        50      POP_JUMP_IF_TRUE                11 (to 74)
                        52      NOP                             
                        54      LOAD_CONST                      0: None
                        56      NOP                             
                        58      NOP                             
                        60      JUMP_FORWARD                    1455 (to 2974)
                        70      POP_TOP                         
                        72      RETURN_CONST                    0: None
                        74      LOAD_FAST                       0: self
                        76      LOAD_ATTR                       2: app_id
                        96      LOAD_CONST                      5: 4
                        98      COMPARE_OP                      40 (==)
                        102     POP_JUMP_IF_TRUE                16 (to 136)
                        104     LOAD_FAST                       0: self
                        106     LOAD_ATTR                       2: app_id
                        126     LOAD_CONST                      6: 6
                        128     COMPARE_OP                      40 (==)
                        132     POP_JUMP_IF_FALSE               748 (to 1632)
                        136     LOAD_GLOBAL                     4: functions
                        146     LOAD_ATTR                       6: account
                        166     LOAD_ATTR                       9: GetDefaultProfilePhotoEmojisRequest
                        186     LOAD_CONST                      7: 0
                        188     KW_NAMES                        8: ('hash',)
                        190     CALL                            1
                        198     LOAD_GLOBAL                     4: functions
                        208     LOAD_ATTR                       10: messages
                        228     LOAD_ATTR                       13: GetTopReactionsRequest
                        248     LOAD_CONST                      9: 100
                        250     LOAD_CONST                      7: 0
                        252     KW_NAMES                        10: ('limit', 'hash')
                        254     CALL                            2
                        262     LOAD_GLOBAL                     4: functions
                        272     LOAD_ATTR                       6: account
                        292     LOAD_ATTR                       15: GetGlobalPrivacySettingsRequest
                        312     CALL                            0
                        320     LOAD_GLOBAL                     4: functions
                        330     LOAD_ATTR                       10: messages
                        350     LOAD_ATTR                       17: GetRecentReactionsRequest
                        370     LOAD_CONST                      11: 50
                        372     LOAD_CONST                      7: 0
                        374     KW_NAMES                        10: ('limit', 'hash')
                        376     CALL                            2
                        384     LOAD_GLOBAL                     4: functions
                        394     LOAD_ATTR                       10: messages
                        414     LOAD_ATTR                       19: GetStickersRequest
                        434     LOAD_CONST                      12: '📂⭐'
                        436     LOAD_CONST                      7: 0
                        438     KW_NAMES                        13: ('emoticon', 'hash')
                        440     CALL                            2
                        448     LOAD_GLOBAL                     4: functions
                        458     LOAD_ATTR                       20: contacts
                        478     LOAD_ATTR                       23: GetContactsRequest
                        498     LOAD_CONST                      7: 0
                        500     KW_NAMES                        8: ('hash',)
                        502     CALL                            1
                        510     LOAD_GLOBAL                     4: functions
                        520     LOAD_ATTR                       10: messages
                        540     LOAD_ATTR                       25: GetFavedStickersRequest
                        560     LOAD_CONST                      7: 0
                        562     KW_NAMES                        8: ('hash',)
                        564     CALL                            1
                        572     LOAD_GLOBAL                     4: functions
                        582     LOAD_ATTR                       26: users
                        602     LOAD_ATTR                       29: GetFullUserRequest
                        622     LOAD_GLOBAL                     31: NULL + types
                        632     LOAD_ATTR                       32: InputUserSelf
                        652     CALL                            0
                        660     KW_NAMES                        14: ('id',)
                        662     CALL                            1
                        670     LOAD_GLOBAL                     4: functions
                        680     LOAD_ATTR                       10: messages
                        700     LOAD_ATTR                       35: GetAttachMenuBotsRequest
                        720     LOAD_CONST                      7: 0
                        722     KW_NAMES                        8: ('hash',)
                        724     CALL                            1
                        732     LOAD_GLOBAL                     4: functions
                        742     LOAD_ATTR                       10: messages
                        762     LOAD_ATTR                       37: GetFeaturedStickersRequest
                        782     LOAD_CONST                      7: 0
                        784     KW_NAMES                        8: ('hash',)
                        786     CALL                            1
                        794     LOAD_GLOBAL                     4: functions
                        804     LOAD_ATTR                       10: messages
                        824     LOAD_ATTR                       39: GetFeaturedEmojiStickersRequest
                        844     LOAD_CONST                      7: 0
                        846     KW_NAMES                        8: ('hash',)
                        848     CALL                            1
                        856     LOAD_GLOBAL                     4: functions
                        866     LOAD_ATTR                       10: messages
                        886     LOAD_ATTR                       41: GetAvailableReactionsRequest
                        906     LOAD_CONST                      7: 0
                        908     KW_NAMES                        8: ('hash',)
                        910     CALL                            1
                        918     LOAD_GLOBAL                     4: functions
                        928     LOAD_ATTR                       10: messages
                        948     LOAD_ATTR                       43: GetStickerSetRequest
                        968     LOAD_GLOBAL                     31: NULL + types
                        978     LOAD_ATTR                       44: InputStickerSetEmojiGenericAnimations
                        998     CALL                            0
                        1006    LOAD_CONST                      7: 0
                        1008    KW_NAMES                        15: ('stickerset', 'hash')
                        1010    CALL                            2
                        1018    LOAD_GLOBAL                     4: functions
                        1028    LOAD_ATTR                       46: help
                        1048    LOAD_ATTR                       49: GetAppConfigRequest
                        1068    LOAD_CONST                      7: 0
                        1070    KW_NAMES                        8: ('hash',)
                        1072    CALL                            1
                        1080    LOAD_GLOBAL                     4: functions
                        1090    LOAD_ATTR                       46: help
                        1110    LOAD_ATTR                       51: GetPromoDataRequest
                        1130    CALL                            0
                        1138    LOAD_GLOBAL                     4: functions
                        1148    LOAD_ATTR                       46: help
                        1168    LOAD_ATTR                       53: GetPremiumPromoRequest
                        1188    CALL                            0
                        1196    LOAD_GLOBAL                     4: functions
                        1206    LOAD_ATTR                       6: account
                        1226    LOAD_ATTR                       55: GetAutoDownloadSettingsRequest
                        1246    CALL                            0
                        1254    LOAD_GLOBAL                     4: functions
                        1264    LOAD_ATTR                       46: help
                        1284    LOAD_ATTR                       57: SaveAppLogRequest
                        1304    LOAD_GLOBAL                     31: NULL + types
                        1314    LOAD_ATTR                       58: InputAppEvent
                        1334    LOAD_GLOBAL                     60: datetime
                        1344    LOAD_ATTR                       60: datetime
                        1364    LOAD_ATTR                       63: now
                        1384    LOAD_GLOBAL                     60: datetime
                        1394    LOAD_ATTR                       64: timezone
                        1414    LOAD_ATTR                       66: utc
                        1434    KW_NAMES                        16: ('tz',)
                        1436    CALL                            1
                        1444    LOAD_ATTR                       69: timestamp
                        1464    CALL                            0
                        1472    PUSH_NULL                       
                        1474    LOAD_CONST                      1: '__pyarmor_assert_14904__'
                        1476    LOAD_CONST                      17: 'android_sdcard_exists'   # b'\x81\xe3\x16\x17!\xf5\xb7\xd6$\xe9\t\xc3m\xfe\xfc\xba\nE\xb2\xb4\xbe\xd8'
                        1478    CALL                            1
                        1486    LOAD_CONST                      18: 1
                        1488    LOAD_GLOBAL                     31: NULL + types
                        1498    LOAD_ATTR                       70: JsonBool
                        1518    LOAD_CONST                      19: True
                        1520    CALL                            1
                        1528    KW_NAMES                        20: ('time', 'type', 'peer', 'data')
                        1530    CALL                            4
                        1538    BUILD_LIST                      1
                        1540    KW_NAMES                        21: ('events',)
                        1542    CALL                            1
                        1550    BUILD_LIST                      18
                        1552    STORE_FAST                      2: _var_var_9
                        1554    NOP                             
                        1556    LOAD_GLOBAL                     73: NULL + random
                        1566    LOAD_ATTR                       74: shuffle
                        1586    LOAD_FAST                       2: _var_var_9
                        1588    CALL                            1
                        1596    POP_TOP                         
                        1598    LOAD_FAST                       0: self
                        1600    LOAD_ATTR                       77: client
                        1620    LOAD_FAST                       2: _var_var_9
                        1622    CALL                            1
                        1630    POP_TOP                         
                        1632    LOAD_FAST                       0: self
                        1634    LOAD_ATTR                       2: app_id
                        1654    LOAD_CONST                      22: 21724
                        1656    COMPARE_OP                      40 (==)
                        1660    POP_JUMP_IF_FALSE               600 (to 2864)
                        1664    LOAD_GLOBAL                     4: functions
                        1674    LOAD_ATTR                       6: account
                        1694    LOAD_ATTR                       9: GetDefaultProfilePhotoEmojisRequest
                        1714    LOAD_CONST                      7: 0
                        1716    KW_NAMES                        8: ('hash',)
                        1718    CALL                            1
                        1726    LOAD_GLOBAL                     4: functions
                        1736    LOAD_ATTR                       10: messages
                        1756    LOAD_ATTR                       13: GetTopReactionsRequest
                        1776    LOAD_CONST                      9: 100
                        1778    LOAD_CONST                      7: 0
                        1780    KW_NAMES                        10: ('limit', 'hash')
                        1782    CALL                            2
                        1790    LOAD_GLOBAL                     4: functions
                        1800    LOAD_ATTR                       6: account
                        1820    LOAD_ATTR                       15: GetGlobalPrivacySettingsRequest
                        1840    CALL                            0
                        1848    LOAD_GLOBAL                     4: functions
                        1858    LOAD_ATTR                       10: messages
                        1878    LOAD_ATTR                       17: GetRecentReactionsRequest
                        1898    LOAD_CONST                      11: 50
                        1900    LOAD_CONST                      7: 0
                        1902    KW_NAMES                        10: ('limit', 'hash')
                        1904    CALL                            2
                        1912    LOAD_GLOBAL                     4: functions
                        1922    LOAD_ATTR                       10: messages
                        1942    LOAD_ATTR                       19: GetStickersRequest
                        1962    LOAD_CONST                      12: '📂⭐'
                        1964    LOAD_CONST                      7: 0
                        1966    KW_NAMES                        13: ('emoticon', 'hash')
                        1968    CALL                            2
                        1976    LOAD_GLOBAL                     4: functions
                        1986    LOAD_ATTR                       20: contacts
                        2006    LOAD_ATTR                       23: GetContactsRequest
                        2026    LOAD_CONST                      7: 0
                        2028    KW_NAMES                        8: ('hash',)
                        2030    CALL                            1
                        2038    LOAD_GLOBAL                     4: functions
                        2048    LOAD_ATTR                       10: messages
                        2068    LOAD_ATTR                       25: GetFavedStickersRequest
                        2088    LOAD_CONST                      7: 0
                        2090    KW_NAMES                        8: ('hash',)
                        2092    CALL                            1
                        2100    LOAD_GLOBAL                     4: functions
                        2110    LOAD_ATTR                       26: users
                        2130    LOAD_ATTR                       29: GetFullUserRequest
                        2150    LOAD_GLOBAL                     31: NULL + types
                        2160    LOAD_ATTR                       32: InputUserSelf
                        2180    CALL                            0
                        2188    KW_NAMES                        14: ('id',)
                        2190    CALL                            1
                        2198    LOAD_GLOBAL                     4: functions
                        2208    LOAD_ATTR                       10: messages
                        2228    LOAD_ATTR                       35: GetAttachMenuBotsRequest
                        2248    LOAD_CONST                      7: 0
                        2250    KW_NAMES                        8: ('hash',)
                        2252    CALL                            1
                        2260    LOAD_GLOBAL                     4: functions
                        2270    LOAD_ATTR                       10: messages
                        2290    LOAD_ATTR                       37: GetFeaturedStickersRequest
                        2310    LOAD_CONST                      7: 0
                        2312    KW_NAMES                        8: ('hash',)
                        2314    CALL                            1
                        2322    LOAD_GLOBAL                     4: functions
                        2332    LOAD_ATTR                       10: messages
                        2352    LOAD_ATTR                       39: GetFeaturedEmojiStickersRequest
                        2372    LOAD_CONST                      7: 0
                        2374    KW_NAMES                        8: ('hash',)
                        2376    CALL                            1
                        2384    LOAD_GLOBAL                     4: functions
                        2394    LOAD_ATTR                       10: messages
                        2414    LOAD_ATTR                       41: GetAvailableReactionsRequest
                        2434    LOAD_CONST                      7: 0
                        2436    KW_NAMES                        8: ('hash',)
                        2438    CALL                            1
                        2446    LOAD_GLOBAL                     4: functions
                        2456    LOAD_ATTR                       10: messages
                        2476    LOAD_ATTR                       43: GetStickerSetRequest
                        2496    LOAD_GLOBAL                     31: NULL + types
                        2506    LOAD_ATTR                       44: InputStickerSetEmojiGenericAnimations
                        2526    CALL                            0
                        2534    LOAD_CONST                      7: 0
                        2536    KW_NAMES                        15: ('stickerset', 'hash')
                        2538    CALL                            2
                        2546    LOAD_GLOBAL                     4: functions
                        2556    LOAD_ATTR                       46: help
                        2576    LOAD_ATTR                       49: GetAppConfigRequest
                        2596    LOAD_CONST                      7: 0
                        2598    KW_NAMES                        8: ('hash',)
                        2600    CALL                            1
                        2608    LOAD_GLOBAL                     4: functions
                        2618    LOAD_ATTR                       46: help
                        2638    LOAD_ATTR                       51: GetPromoDataRequest
                        2658    CALL                            0
                        2666    LOAD_GLOBAL                     4: functions
                        2676    LOAD_ATTR                       46: help
                        2696    LOAD_ATTR                       53: GetPremiumPromoRequest
                        2716    CALL                            0
                        2724    LOAD_GLOBAL                     4: functions
                        2734    LOAD_ATTR                       6: account
                        2754    LOAD_ATTR                       55: GetAutoDownloadSettingsRequest
                        2774    CALL                            0
                        2782    BUILD_LIST                      17
                        2784    STORE_FAST                      2: _var_var_9
                        2786    NOP                             
                        2788    LOAD_GLOBAL                     73: NULL + random
                        2798    LOAD_ATTR                       74: shuffle
                        2818    LOAD_FAST                       2: _var_var_9
                        2820    CALL                            1
                        2828    POP_TOP                         
                        2830    LOAD_FAST                       0: self
                        2832    LOAD_ATTR                       77: client
                        2852    LOAD_FAST                       2: _var_var_9
                        2854    CALL                            1
                        2862    POP_TOP                         
                        2864    LOAD_FAST                       0: self
                        2866    LOAD_ATTR                       79: _random_search
                        2886    CALL                            0
                        2894    POP_TOP                         
                        2896    LOAD_CONST                      0: None
                        2898    NOP                             
                        2900    NOP                             
                        2902    NOP                             
                        2904    JUMP_FORWARD                    34 (to 2974)
                        2912    POP_TOP                         
                        2914    RETURN_CONST                    0: None
                        2916    PUSH_EXC_INFO                   
                        2918    POP_TOP                         
                        2920    POP_EXCEPT                      
                        2922    JUMP_BACKWARD                   647 (to 1632)
                        2926    COPY                            3
                        2928    POP_EXCEPT                      
                        2930    RERAISE                         1
                        2932    PUSH_EXC_INFO                   
                        2934    POP_TOP                         
                        2936    POP_EXCEPT                      
                        2938    JUMP_BACKWARD                   38 (to 2864)
                        2940    COPY                            3
                        2942    POP_EXCEPT                      
                        2944    RERAISE                         1
                        2946    PUSH_EXC_INFO                   
                        2948    PUSH_NULL                       
                        2950    LOAD_CONST                      4: '__pyarmor_exit_14906__'
                        2952    NOP                             
                        2954    LOAD_CONST                      3: b'<COAddr>\x07\x00\x00\x1ah\x0b\x00\x00\x00\x00\x00\x00\x00\x00\x00\x00\x00\x00\x00\x00'
                        2956    CALL                            1
                        2964    POP_TOP                         
                        2966    RERAISE                         0
                        2968    COPY                            3
                        2970    POP_EXCEPT                      
                        2972    RERAISE                         1
                        2974    PUSH_NULL                       
                        2976    LOAD_CONST                      4: '__pyarmor_exit_14906__'
                        2978    LOAD_CONST                      3: b'<COAddr>\x07\x00\x00\x1ah\x0b\x00\x00\x00\x00\x00\x00\x00\x00\x00\x00\x00\x00\x00\x00'
                        2980    BUILD_TUPLE                     1
                        2982    CALL_FUNCTION_EX                0
                        2984    POP_TOP                         
                        2986    RETURN_VALUE                    
                    [Exception Table]
                        28 to 52 -> 2946 [0] 
                        74 to 1554 -> 2946 [0] 
                        1556 to 1632 -> 2916 [0] 
                        1632 to 2786 -> 2946 [0] 
                        2788 to 2864 -> 2932 [0] 
                        2864 to 2896 -> 2946 [0] 
                        2916 to 2920 -> 2926 [1] lasti
                        2920 to 2932 -> 2946 [0] 
                        2932 to 2936 -> 2940 [1] lasti
                        2936 to 2946 -> 2946 [0] 
                        2946 to 2968 -> 2968 [1] lasti
                '__pyarmor_exit_14879__'
                (
                    4
                    'en'
                )
                (
                    'return'
                    None
                )
            [Disassembly]
                0       NOP                             
                2       LOAD_NAME                       0: __name__
                4       STORE_NAME                      1: __module__
                6       LOAD_CONST                      0: 'AndroidRequests'
                8       STORE_NAME                      2: __qualname__
                10      NOP                             
                12      PUSH_NULL                       
                14      LOAD_CONST                      2: '__pyarmor_enter_14878__'
                16      LOAD_CONST                      3: b'<COAddr>\x07\x00\x00"T\x00\x00\x00\x00\x00\x00\x00\x00\x00\x00\x00\x00\x00\x00\x00'
                18      BUILD_TUPLE                     1
                20      CALL_FUNCTION_EX                0
                22      POP_TOP                         
                24      RESUME                          0
                26      NOP                             
                28      NOP                             
                30      NOP                             
                32      NOP                             
                34      NOP                             
                36      LOAD_CONST                      14: (4, 'en')
                38      LOAD_CONST                      15: ('return', None)
                40      LOAD_CONST                      5: <CODE> __init__
                42      MAKE_FUNCTION                   5
                44      STORE_NAME                      4: __init__
                46      LOAD_NAME                       5: staticmethod
                48      LOAD_CONST                      6: <CODE> timer
                50      MAKE_FUNCTION                   0
                52      CALL                            0
                60      STORE_NAME                      6: timer
                62      LOAD_CONST                      7: <CODE> _random_search
                64      MAKE_FUNCTION                   0
                66      STORE_NAME                      7: _random_search
                68      LOAD_CONST                      8: <CODE> reg_start
                70      MAKE_FUNCTION                   0
                72      STORE_NAME                      8: reg_start
                74      LOAD_CONST                      9: <CODE> reg_middle
                76      MAKE_FUNCTION                   0
                78      STORE_NAME                      9: reg_middle
                80      LOAD_CONST                      10: <CODE> reg_end
                82      MAKE_FUNCTION                   0
                84      STORE_NAME                      10: reg_end
                86      LOAD_CONST                      11: <CODE> check
                88      MAKE_FUNCTION                   0
                90      STORE_NAME                      11: check
                92      LOAD_CONST                      12: <CODE> work
                94      MAKE_FUNCTION                   0
                96      STORE_NAME                      12: work
                98      LOAD_CONST                      4: None
                100     NOP                             
                102     NOP                             
                104     NOP                             
                106     JUMP_FORWARD                    19 (to 146)
                114     POP_TOP                         
                116     RETURN_CONST                    4: None
                118     PUSH_EXC_INFO                   
                120     PUSH_NULL                       
                122     LOAD_CONST                      13: '__pyarmor_exit_14879__'
                124     NOP                             
                126     LOAD_CONST                      3: b'<COAddr>\x07\x00\x00"T\x00\x00\x00\x00\x00\x00\x00\x00\x00\x00\x00\x00\x00\x00\x00'
                128     CALL                            1
                136     POP_TOP                         
                138     RERAISE                         0
                140     COPY                            3
                142     POP_EXCEPT                      
                144     RERAISE                         1
                146     PUSH_NULL                       
                148     LOAD_CONST                      13: '__pyarmor_exit_14879__'
                150     LOAD_CONST                      3: b'<COAddr>\x07\x00\x00"T\x00\x00\x00\x00\x00\x00\x00\x00\x00\x00\x00\x00\x00\x00\x00'
                152     BUILD_TUPLE                     1
                154     CALL_FUNCTION_EX                0
                156     POP_TOP                         
                158     RETURN_VALUE                    
            [Exception Table]
                36 to 98 -> 118 [0] 
                118 to 140 -> 140 [1] lasti
        'AndroidRequests'
        '__pyarmor_exit_14876__'
    [Disassembly]
        0       NOP                             
        2       NOP                             
        4       PUSH_NULL                       
        6       LOAD_CONST                      1: '__pyarmor_enter_14875__'
        8       LOAD_CONST                      2: b'<COAddr>\x07\x00\x00\x1aX\x00\x00\x00\x00\x00\x00\x00\x00\x00\x00\x00\x00\x00\x00\x00'
        10      BUILD_TUPLE                     1
        12      CALL_FUNCTION_EX                0
        14      POP_TOP                         
        16      RESUME                          0
        18      NOP                             
        20      NOP                             
        22      NOP                             
        24      NOP                             
        26      LOAD_CONST                      3: 0
        28      LOAD_CONST                      4: None
        30      IMPORT_NAME                     1: time
        32      STORE_NAME                      1: time
        34      LOAD_CONST                      3: 0
        36      LOAD_CONST                      4: None
        38      IMPORT_NAME                     2: random
        40      STORE_NAME                      2: random
        42      LOAD_CONST                      3: 0
        44      LOAD_CONST                      4: None
        46      IMPORT_NAME                     3: string
        48      STORE_NAME                      3: string
        50      LOAD_CONST                      3: 0
        52      LOAD_CONST                      4: None
        54      IMPORT_NAME                     4: datetime
        56      STORE_NAME                      4: datetime
        58      LOAD_CONST                      3: 0
        60      LOAD_CONST                      5: ('functions', 'types')
        62      IMPORT_NAME                     5: multithon.sync
        64      IMPORT_FROM                     6: functions
        66      STORE_NAME                      6: functions
        68      IMPORT_FROM                     7: types
        70      STORE_NAME                      7: types
        72      POP_TOP                         
        74      PUSH_NULL                       
        76      LOAD_BUILD_CLASS                
        78      LOAD_CONST                      6: <CODE> AndroidRequests
        80      MAKE_FUNCTION                   0
        82      LOAD_CONST                      7: 'AndroidRequests'
        84      CALL                            2
        92      STORE_NAME                      8: AndroidRequests
        94      LOAD_CONST                      4: None
        96      NOP                             
        98      NOP                             
        100     NOP                             
        102     JUMP_FORWARD                    19 (to 142)
        110     POP_TOP                         
        112     RETURN_CONST                    4: None
        114     PUSH_EXC_INFO                   
        116     PUSH_NULL                       
        118     LOAD_CONST                      8: '__pyarmor_exit_14876__'
        120     NOP                             
        122     LOAD_CONST                      2: b'<COAddr>\x07\x00\x00\x1aX\x00\x00\x00\x00\x00\x00\x00\x00\x00\x00\x00\x00\x00\x00\x00'
        124     CALL                            1
        132     POP_TOP                         
        134     RERAISE                         0
        136     COPY                            3
        138     POP_EXCEPT                      
        140     RERAISE                         1
        142     PUSH_NULL                       
        144     LOAD_CONST                      8: '__pyarmor_exit_14876__'
        146     LOAD_CONST                      2: b'<COAddr>\x07\x00\x00\x1aX\x00\x00\x00\x00\x00\x00\x00\x00\x00\x00\x00\x00\x00\x00\x00'
        148     BUILD_TUPLE                     1
        150     CALL_FUNCTION_EX                0
        152     POP_TOP                         
        154     RETURN_VALUE                    
    [Exception Table]
        26 to 94 -> 114 [0] 
        114 to 136 -> 136 [1] lasti
