#decoded by lolz.live/mrpenny / t.me/zeus_jackpot
# ================================
# Примечания по Pyarmor:
# - Байт-код и объекты кода Pyarmor соответствуют стандартному Python, но присутствуют специальные вызовы функций среды выполнения (runtime) Pyarmor.
# - Вызовы строк — это не ошибки, а маркеры, которые обрабатываются Pyarmor во время выполнения.
#
# Руководство по декомпиляции (без среды выполнения):
# 1. Игнорируйте зашифрованные байты после `#`; используйте только строку до `#`.
# 2. Удалите "__pyarmor_enter_xxx__"(b"<COAddr>...") и "__pyarmor_leave_xxx__"(b"<COAddr>...") (пролог/эпилог).
# 3. "__pyarmor_assert_xxx__"(A) не является настоящим оператором assert.
#    - Если A — это имя или читаемая строка: замените на A.
#    - Если A — это (X, "Y"): замените на X.Y.
#    - Если A — это (X, "Y", Z): замените на X.Y = Z.
#    - В противном случае: выберите наиболее подходящую/логичную замену.
# 4. "__pyarmor_bcc_xxx__"(...) указывает на машинный (нативный) код; тело функции недоступно. Добавьте комментарий.
# ================================

[Code]
    File Name: <frozen program.modules.func.gpt>
    Object Name: <module>
    Qualified Name: <module>
    Arg Count: 0
    Pos Only Arg Count: 0
    KW Only Arg Count: 0
    Stack Size: 5
    Flags: 0x20000000 (CO_PYARMOR_OBFUSCATED)
    [Names]
        '__assert_armored__'
        'warnings'
        'filterwarnings'
        'DeprecationWarning'
        'g4f'
        'random'
        'spintax'
        'threading'
        'Event'
        'program.static_classes'
        'Logs'
        'multithon.errors'
        'StopProgram'
        'queue'
        'Queue'
        'debug'
        'logging'
        'version_check'
        'GPT'
    [Locals+Names]
    [Constants]
        '__pyarmor_assert_15072__'
        '__pyarmor_enter_15073__'
        b'<COAddr>\x05\x00\x00\x1a\xfc\x00\x00\x00\x00\x00\x00\x00\x00\x00\x00\x00\x00\x00\x00\x00'
        0
        None
        'ignore'
        (
            'category'
        )
        (
            'Event'
        )
        (
            'Logs'
        )
        (
            'StopProgram'
        )
        (
            'Queue'
        )
        False
        [Code]
            File Name: <frozen program.modules.func.gpt>
            Object Name: GPT
            Qualified Name: GPT
            Arg Count: 0
            Pos Only Arg Count: 0
            KW Only Arg Count: 0
            Stack Size: 5
            Flags: 0x20000000 (CO_PYARMOR_OBFUSCATED)
            [Names]
                '__name__'
                '__module__'
                '__qualname__'
                '__assert_armored__'
                'Event'
                '__init__'
                'start'
                'clear'
            [Locals+Names]
            [Constants]
                'GPT'
                '__pyarmor_assert_15075__'
                '__pyarmor_enter_15076__'
                b'<COAddr>\x07\x00\x00"8\x00\x00\x00\x00\x00\x00\x00\x00\x00\x00\x00\x00\x00\x00\x00'
                [Code]
                    File Name: <frozen program.modules.func.gpt>
                    Object Name: __init__
                    Qualified Name: GPT.__init__
                    Arg Count: 6
                    Pos Only Arg Count: 0
                    KW Only Arg Count: 0
                    Stack Size: 5
                    Flags: 0x20000003 (CO_OPTIMIZED | CO_NEWLOCALS | CO_PYARMOR_OBFUSCATED)
                    [Names]
                        'config'
                        'lang'
                        'account'
                        'promt'
                        'stop_thread'
                        'ansfer'
                    [Locals+Names]
                        'self'
                        'config'
                        'lang'
                        'account'
                        'promt'
                        'stop_thread'
                        '__assert_armored__'
                    [Constants]
                        None
                        '__pyarmor_assert_15078__'
                        '__pyarmor_enter_15079__'
                        b'<COAddr>\x05\x00\x00\x1aj\x00\x00\x00\x00\x00\x00\x00\x00\x00\x00\x00\x00\x00\x00\x00'
                        ''
                        '__pyarmor_exit_15080__'
                    [Disassembly]
                        0       NOP                             
                        2       NOP                             
                        4       PUSH_NULL                       
                        6       LOAD_CONST                      2: '__pyarmor_enter_15079__'
                        8       LOAD_CONST                      3: b'<COAddr>\x05\x00\x00\x1aj\x00\x00\x00\x00\x00\x00\x00\x00\x00\x00\x00\x00\x00\x00\x00'
                        10      BUILD_TUPLE                     1
                        12      CALL_FUNCTION_EX                0
                        14      POP_TOP                         
                        16      RESUME                          0
                        18      NOP                             
                        20      NOP                             
                        22      NOP                             
                        24      NOP                             
                        26      NOP                             
                        28      LOAD_FAST                       1: config
                        30      LOAD_FAST                       0: self
                        32      STORE_ATTR                      0: config
                        42      LOAD_FAST                       2: lang
                        44      LOAD_FAST                       0: self
                        46      STORE_ATTR                      1: lang
                        56      LOAD_FAST                       3: account
                        58      LOAD_FAST                       0: self
                        60      STORE_ATTR                      2: account
                        70      LOAD_FAST                       4: promt
                        72      LOAD_FAST                       0: self
                        74      STORE_ATTR                      3: promt
                        84      LOAD_FAST                       5: stop_thread
                        86      LOAD_FAST                       0: self
                        88      STORE_ATTR                      4: stop_thread
                        98      LOAD_CONST                      4: ''
                        100     LOAD_FAST                       0: self
                        102     STORE_ATTR                      5: ansfer
                        112     LOAD_CONST                      0: None
                        114     NOP                             
                        116     NOP                             
                        118     NOP                             
                        120     JUMP_FORWARD                    19 (to 160)
                        128     POP_TOP                         
                        130     RETURN_CONST                    0: None
                        132     PUSH_EXC_INFO                   
                        134     PUSH_NULL                       
                        136     LOAD_CONST                      5: '__pyarmor_exit_15080__'
                        138     NOP                             
                        140     LOAD_CONST                      3: b'<COAddr>\x05\x00\x00\x1aj\x00\x00\x00\x00\x00\x00\x00\x00\x00\x00\x00\x00\x00\x00\x00'
                        142     CALL                            1
                        150     POP_TOP                         
                        152     RERAISE                         0
                        154     COPY                            3
                        156     POP_EXCEPT                      
                        158     RERAISE                         1
                        160     PUSH_NULL                       
                        162     LOAD_CONST                      5: '__pyarmor_exit_15080__'
                        164     LOAD_CONST                      3: b'<COAddr>\x05\x00\x00\x1aj\x00\x00\x00\x00\x00\x00\x00\x00\x00\x00\x00\x00\x00\x00\x00'
                        166     BUILD_TUPLE                     1
                        168     CALL_FUNCTION_EX                0
                        170     POP_TOP                         
                        172     RETURN_VALUE                    
                    [Exception Table]
                        28 to 112 -> 132 [0] 
                        132 to 154 -> 154 [1] lasti
                None
                [Code]
                    File Name: <frozen program.modules.func.gpt>
                    Object Name: start
                    Qualified Name: GPT.start
                    Arg Count: 2
                    Pos Only Arg Count: 0
                    KW Only Arg Count: 0
                    Stack Size: 9
                    Flags: 0x20000003 (CO_OPTIMIZED | CO_NEWLOCALS | CO_PYARMOR_OBFUSCATED)
                    [Names]
                        'stop_thread'
                        'is_set'
                        'StopProgram'
                        'Queue'
                        'Logs'
                        'PrintLog'
                        'config'
                        'account'
                        'lang'
                        'spintax'
                        'spin'
                        'promt'
                        'threading'
                        'Thread'
                        'start'
                        'join'
                        'get'
                        'clear'
                    [Locals+Names]
                        'self'
                        'replay'
                        '__assert_armored__'
                        '_var_var_0'
                        '_var_var_1'
                        '_var_var_2'
                        '_var_var_3'
                        '_var_var_4'
                    [Constants]
                        None
                        '__pyarmor_assert_15081__'
                        '__pyarmor_enter_15082__'
                        b'<COAddr>\x07\x00\x00\x1a\xae\x02\x00\x00\x00\x00\x00\x00\x00\x00\x00\x00\x00\x00\x00\x00'
                        [Code]
                            File Name: <frozen program.modules.func.gpt>
                            Object Name: hach
                            Qualified Name: GPT.start.<locals>.hach
                            Arg Count: 2
                            Pos Only Arg Count: 0
                            KW Only Arg Count: 0
                            Stack Size: 6
                            Flags: 0x20000013 (CO_OPTIMIZED | CO_NEWLOCALS | CO_NESTED | CO_PYARMOR_OBFUSCATED)
                            [Names]
                                'g4f'
                                'client'
                                'Client'
                                'chat'
                                'completions'
                                'create'
                                'choices'
                                'message'
                                'content'
                                'put'
                            [Locals+Names]
                                'queue'
                                'promt'
                                '__assert_armored__'
                                '_var_var_5'
                                '_var_var_6'
                                '_var_var_4'
                            [Constants]
                                None
                                '__pyarmor_assert_15084__'
                                '__pyarmor_enter_15085__'
                                b'<COAddr>\x07\x00\x00\x1a\x1e\x01\x00\x00\x00\x00\x00\x00\x00\x00\x00\x00\x00\x00\x00\x00'
                                'gpt-4o-mini'   # b'\x81\xe5\x08\x07~\xae\xb1\x9f\x16\xf3\x03\xc9'
                                'user'
                                (
                                    'role'
                                    'content'
                                )
                                False
                                (
                                    'model'
                                    'messages'
                                    'web_search'
                                )
                                0
                                '__pyarmor_exit_15086__'
                            [Disassembly]
                                0       NOP                             
                                2       NOP                             
                                4       PUSH_NULL                       
                                6       LOAD_CONST                      2: '__pyarmor_enter_15085__'
                                8       LOAD_CONST                      3: b'<COAddr>\x07\x00\x00\x1a\x1e\x01\x00\x00\x00\x00\x00\x00\x00\x00\x00\x00\x00\x00\x00\x00'
                                10      BUILD_TUPLE                     1
                                12      CALL_FUNCTION_EX                0
                                14      POP_TOP                         
                                16      RESUME                          0
                                18      NOP                             
                                20      NOP                             
                                22      NOP                             
                                24      NOP                             
                                26      NOP                             
                                28      LOAD_GLOBAL                     0: g4f
                                38      LOAD_ATTR                       2: client
                                58      LOAD_ATTR                       5: Client
                                78      CALL                            0
                                86      STORE_FAST                      3: _var_var_5
                                88      LOAD_FAST                       3: _var_var_5
                                90      LOAD_ATTR                       6: chat
                                110     LOAD_ATTR                       8: completions
                                130     LOAD_ATTR                       11: create
                                150     PUSH_NULL                       
                                152     LOAD_CONST                      1: '__pyarmor_assert_15084__'
                                154     LOAD_CONST                      4: 'gpt-4o-mini'   # b'\x81\xe5\x08\x07~\xae\xb1\x9f\x16\xf3\x03\xc9'
                                156     CALL                            1
                                164     LOAD_CONST                      5: 'user'
                                166     LOAD_FAST                       1: promt
                                168     LOAD_CONST                      6: ('role', 'content')
                                170     BUILD_CONST_KEY_MAP             2
                                172     BUILD_LIST                      1
                                174     LOAD_CONST                      7: False
                                176     KW_NAMES                        8: ('model', 'messages', 'web_search')
                                178     CALL                            3
                                186     STORE_FAST                      4: _var_var_6
                                188     LOAD_FAST                       4: _var_var_6
                                190     LOAD_ATTR                       12: choices
                                210     LOAD_CONST                      9: 0
                                212     BINARY_SUBSCR                   
                                216     LOAD_ATTR                       14: message
                                236     LOAD_ATTR                       16: content
                                256     STORE_FAST                      5: _var_var_4
                                258     LOAD_FAST                       0: queue
                                260     LOAD_ATTR                       19: put
                                280     LOAD_FAST                       5: _var_var_4
                                282     CALL                            1
                                290     POP_TOP                         
                                292     LOAD_CONST                      0: None
                                294     NOP                             
                                296     NOP                             
                                298     NOP                             
                                300     JUMP_FORWARD                    19 (to 340)
                                308     POP_TOP                         
                                310     RETURN_CONST                    0: None
                                312     PUSH_EXC_INFO                   
                                314     PUSH_NULL                       
                                316     LOAD_CONST                      10: '__pyarmor_exit_15086__'
                                318     NOP                             
                                320     LOAD_CONST                      3: b'<COAddr>\x07\x00\x00\x1a\x1e\x01\x00\x00\x00\x00\x00\x00\x00\x00\x00\x00\x00\x00\x00\x00'
                                322     CALL                            1
                                330     POP_TOP                         
                                332     RERAISE                         0
                                334     COPY                            3
                                336     POP_EXCEPT                      
                                338     RERAISE                         1
                                340     PUSH_NULL                       
                                342     LOAD_CONST                      10: '__pyarmor_exit_15086__'
                                344     LOAD_CONST                      3: b'<COAddr>\x07\x00\x00\x1a\x1e\x01\x00\x00\x00\x00\x00\x00\x00\x00\x00\x00\x00\x00\x00\x00'
                                346     BUILD_TUPLE                     1
                                348     CALL_FUNCTION_EX                0
                                350     POP_TOP                         
                                352     RETURN_VALUE                    
                            [Exception Table]
                                28 to 292 -> 312 [0] 
                                312 to 334 -> 334 [1] lasti
                        'gpt_ask'
                        (
                            'config'
                            'account'
                            'message'
                        )
                        " '''"
                        "'''"
                        (
                            'target'
                            'args'
                        )
                        '__pyarmor_exit_15083__'
                        'gpt_error'   # b'\x81\xe5\x08\x07\x0c\xff\xac\xc0\x14\xe8'
                    [Disassembly]
                        0       NOP                             
                        2       NOP                             
                        4       PUSH_NULL                       
                        6       LOAD_CONST                      2: '__pyarmor_enter_15082__'
                        8       LOAD_CONST                      3: b'<COAddr>\x07\x00\x00\x1a\xae\x02\x00\x00\x00\x00\x00\x00\x00\x00\x00\x00\x00\x00\x00\x00'
                        10      BUILD_TUPLE                     1
                        12      CALL_FUNCTION_EX                0
                        14      POP_TOP                         
                        16      RESUME                          0
                        18      NOP                             
                        20      NOP                             
                        22      NOP                             
                        24      NOP                             
                        26      NOP                             
                        28      LOAD_FAST                       0: self
                        30      LOAD_ATTR                       0: stop_thread
                        50      LOAD_ATTR                       3: is_set
                        70      CALL                            0
                        78      POP_JUMP_IF_FALSE               10 (to 100)
                        80      LOAD_GLOBAL                     5: NULL + StopProgram
                        90      CALL                            0
                        98      RAISE_VARARGS                   1
                        100     LOAD_CONST                      4: <CODE> hach
                        102     MAKE_FUNCTION                   0
                        104     STORE_FAST                      3: _var_var_0
                        106     LOAD_GLOBAL                     7: NULL + Queue
                        116     CALL                            0
                        124     STORE_FAST                      4: _var_var_1
                        126     NOP                             
                        128     LOAD_GLOBAL                     9: NULL + Logs
                        138     LOAD_ATTR                       10: PrintLog
                        158     LOAD_FAST                       0: self
                        160     LOAD_ATTR                       12: config
                        180     LOAD_FAST                       0: self
                        182     LOAD_ATTR                       14: account
                        202     LOAD_FAST                       0: self
                        204     LOAD_ATTR                       16: lang
                        224     LOAD_CONST                      5: 'gpt_ask'
                        226     BINARY_SUBSCR                   
                        230     KW_NAMES                        6: ('config', 'account', 'message')
                        232     CALL                            3
                        240     POP_TOP                         
                        242     LOAD_GLOBAL                     19: NULL + spintax
                        252     LOAD_ATTR                       20: spin
                        272     LOAD_FAST                       0: self
                        274     LOAD_ATTR                       22: promt
                        294     CALL                            1
                        302     STORE_FAST                      5: _var_var_2
                        304     LOAD_FAST                       1: replay
                        306     POP_JUMP_IF_NONE                8 (to 324)
                        308     LOAD_FAST                       5: _var_var_2
                        310     FORMAT_VALUE                    0 (FVC_NONE)
                        312     LOAD_CONST                      7: " '''"
                        314     LOAD_FAST                       1: replay
                        316     FORMAT_VALUE                    0 (FVC_NONE)
                        318     LOAD_CONST                      8: "'''"
                        320     BUILD_STRING                    4
                        322     STORE_FAST                      5: _var_var_2
                        324     LOAD_GLOBAL                     25: NULL + threading
                        334     LOAD_ATTR                       26: Thread
                        354     LOAD_FAST                       3: _var_var_0
                        356     LOAD_FAST                       4: _var_var_1
                        358     LOAD_FAST                       5: _var_var_2
                        360     BUILD_TUPLE                     2
                        362     KW_NAMES                        9: ('target', 'args')
                        364     CALL                            2
                        372     STORE_FAST                      6: _var_var_3
                        374     LOAD_FAST                       6: _var_var_3
                        376     LOAD_ATTR                       29: start
                        396     CALL                            0
                        404     POP_TOP                         
                        406     LOAD_FAST                       6: _var_var_3
                        408     LOAD_ATTR                       31: join
                        428     CALL                            0
                        436     POP_TOP                         
                        438     LOAD_FAST                       4: _var_var_1
                        440     LOAD_ATTR                       33: get
                        460     CALL                            0
                        468     STORE_FAST                      7: _var_var_4
                        470     LOAD_FAST                       0: self
                        472     LOAD_ATTR                       35: clear
                        492     LOAD_FAST                       7: _var_var_4
                        494     CALL                            1
                        502     NOP                             
                        504     NOP                             
                        506     NOP                             
                        508     JUMP_FORWARD                    115 (to 740)
                        510     CALL                            1
                        518     POP_TOP                         
                        520     RETURN_VALUE                    
                        522     PUSH_EXC_INFO                   
                        524     POP_TOP                         
                        526     LOAD_GLOBAL                     9: NULL + Logs
                        536     LOAD_ATTR                       10: PrintLog
                        556     LOAD_FAST                       0: self
                        558     LOAD_ATTR                       12: config
                        578     LOAD_FAST                       0: self
                        580     LOAD_ATTR                       14: account
                        600     LOAD_FAST                       0: self
                        602     LOAD_ATTR                       16: lang
                        622     PUSH_NULL                       
                        624     LOAD_CONST                      1: '__pyarmor_assert_15081__'
                        626     LOAD_CONST                      11: 'gpt_error'   # b'\x81\xe5\x08\x07\x0c\xff\xac\xc0\x14\xe8'
                        628     CALL                            1
                        636     BINARY_SUBSCR                   
                        640     KW_NAMES                        6: ('config', 'account', 'message')
                        642     CALL                            3
                        650     POP_TOP                         
                        652     LOAD_FAST                       0: self
                        654     LOAD_ATTR                       29: start
                        674     CALL                            0
                        682     SWAP                            2
                        684     POP_EXCEPT                      
                        686     NOP                             
                        688     NOP                             
                        690     NOP                             
                        692     JUMP_FORWARD                    23 (to 740)
                        694     CALL                            1
                        702     POP_TOP                         
                        704     RETURN_VALUE                    
                        706     COPY                            3
                        708     POP_EXCEPT                      
                        710     RERAISE                         1
                        712     PUSH_EXC_INFO                   
                        714     PUSH_NULL                       
                        716     LOAD_CONST                      10: '__pyarmor_exit_15083__'
                        718     NOP                             
                        720     LOAD_CONST                      3: b'<COAddr>\x07\x00\x00\x1a\xae\x02\x00\x00\x00\x00\x00\x00\x00\x00\x00\x00\x00\x00\x00\x00'
                        722     CALL                            1
                        730     POP_TOP                         
                        732     RERAISE                         0
                        734     COPY                            3
                        736     POP_EXCEPT                      
                        738     RERAISE                         1
                        740     PUSH_NULL                       
                        742     LOAD_CONST                      10: '__pyarmor_exit_15083__'
                        744     LOAD_CONST                      3: b'<COAddr>\x07\x00\x00\x1a\xae\x02\x00\x00\x00\x00\x00\x00\x00\x00\x00\x00\x00\x00\x00\x00'
                        746     BUILD_TUPLE                     1
                        748     CALL_FUNCTION_EX                0
                        750     POP_TOP                         
                        752     RETURN_VALUE                    
                    [Exception Table]
                        28 to 126 -> 712 [0] 
                        128 to 502 -> 522 [0] 
                        522 to 684 -> 706 [1] lasti
                        684 to 686 -> 712 [0] 
                        706 to 712 -> 712 [0] 
                        712 to 734 -> 734 [1] lasti
                [Code]
                    File Name: <frozen program.modules.func.gpt>
                    Object Name: clear
                    Qualified Name: GPT.clear
                    Arg Count: 2
                    Pos Only Arg Count: 0
                    KW Only Arg Count: 0
                    Stack Size: 8
                    Flags: 0x20000003 (CO_OPTIMIZED | CO_NEWLOCALS | CO_PYARMOR_OBFUSCATED)
                    [Names]
                        'startswith'
                        'endswith'
                        'Logs'
                        'PrintLog'
                        'config'
                        'account'
                        'lang'
                    [Locals+Names]
                        'self'
                        'text'
                        '__assert_armored__'
                    [Constants]
                        None
                        '__pyarmor_assert_15087__'
                        '__pyarmor_enter_15088__'
                        b'<COAddr>\x05\x00\x00\x1a6\x01\x00\x00\x00\x00\x00\x00\x00\x00\x00\x00\x00\x00\x00\x00'
                        '"'
                        1
                        -1
                        "'"
                        'gpt_ansfer'   # b'\x81\xe5\x08\x07\x0c\xfb\xb0\xc1\x1d\xff\x1f'
                        (
                            'config'
                            'account'
                            'message'
                            'end'
                        )
                        '__pyarmor_exit_15089__'
                    [Disassembly]
                        0       NOP                             
                        2       NOP                             
                        4       PUSH_NULL                       
                        6       LOAD_CONST                      2: '__pyarmor_enter_15088__'
                        8       LOAD_CONST                      3: b'<COAddr>\x05\x00\x00\x1a6\x01\x00\x00\x00\x00\x00\x00\x00\x00\x00\x00\x00\x00\x00\x00'
                        10      BUILD_TUPLE                     1
                        12      CALL_FUNCTION_EX                0
                        14      POP_TOP                         
                        16      RESUME                          0
                        18      NOP                             
                        20      NOP                             
                        22      NOP                             
                        24      NOP                             
                        26      NOP                             
                        28      LOAD_FAST                       1: text
                        30      LOAD_ATTR                       1: startswith
                        50      LOAD_CONST                      4: '"'
                        52      CALL                            1
                        60      POP_JUMP_IF_FALSE               23 (to 108)
                        62      LOAD_FAST                       1: text
                        64      LOAD_ATTR                       3: endswith
                        84      LOAD_CONST                      4: '"'
                        86      CALL                            1
                        94      POP_JUMP_IF_FALSE               6 (to 108)
                        96      LOAD_FAST                       1: text
                        98      LOAD_CONST                      5: 1
                        100     LOAD_CONST                      6: -1
                        102     BINARY_SLICE                    
                        104     STORE_FAST                      1: text
                        106     JUMP_FORWARD                    39 (to 186)
                        108     LOAD_FAST                       1: text
                        110     LOAD_ATTR                       1: startswith
                        130     LOAD_CONST                      7: "'"
                        132     CALL                            1
                        140     POP_JUMP_IF_FALSE               22 (to 186)
                        142     LOAD_FAST                       1: text
                        144     LOAD_ATTR                       3: endswith
                        164     LOAD_CONST                      7: "'"
                        166     CALL                            1
                        174     POP_JUMP_IF_FALSE               5 (to 186)
                        176     LOAD_FAST                       1: text
                        178     LOAD_CONST                      5: 1
                        180     LOAD_CONST                      6: -1
                        182     BINARY_SLICE                    
                        184     STORE_FAST                      1: text
                        186     LOAD_GLOBAL                     5: NULL + Logs
                        196     LOAD_ATTR                       6: PrintLog
                        216     LOAD_FAST                       0: self
                        218     LOAD_ATTR                       8: config
                        238     LOAD_FAST                       0: self
                        240     LOAD_ATTR                       10: account
                        260     LOAD_FAST                       0: self
                        262     LOAD_ATTR                       12: lang
                        282     PUSH_NULL                       
                        284     LOAD_CONST                      1: '__pyarmor_assert_15087__'
                        286     LOAD_CONST                      8: 'gpt_ansfer'   # b'\x81\xe5\x08\x07\x0c\xfb\xb0\xc1\x1d\xff\x1f'
                        288     CALL                            1
                        296     BINARY_SUBSCR                   
                        300     LOAD_FAST                       1: text
                        302     KW_NAMES                        9: ('config', 'account', 'message', 'end')
                        304     CALL                            4
                        312     POP_TOP                         
                        314     LOAD_FAST                       1: text
                        316     NOP                             
                        318     NOP                             
                        320     NOP                             
                        322     JUMP_FORWARD                    20 (to 364)
                        324     CALL                            1
                        332     POP_TOP                         
                        334     RETURN_VALUE                    
                        336     PUSH_EXC_INFO                   
                        338     PUSH_NULL                       
                        340     LOAD_CONST                      10: '__pyarmor_exit_15089__'
                        342     NOP                             
                        344     LOAD_CONST                      3: b'<COAddr>\x05\x00\x00\x1a6\x01\x00\x00\x00\x00\x00\x00\x00\x00\x00\x00\x00\x00\x00\x00'
                        346     CALL                            1
                        354     POP_TOP                         
                        356     RERAISE                         0
                        358     COPY                            3
                        360     POP_EXCEPT                      
                        362     RERAISE                         1
                        364     PUSH_NULL                       
                        366     LOAD_CONST                      10: '__pyarmor_exit_15089__'
                        368     LOAD_CONST                      3: b'<COAddr>\x05\x00\x00\x1a6\x01\x00\x00\x00\x00\x00\x00\x00\x00\x00\x00\x00\x00\x00\x00'
                        370     BUILD_TUPLE                     1
                        372     CALL_FUNCTION_EX                0
                        374     POP_TOP                         
                        376     RETURN_VALUE                    
                    [Exception Table]
                        28 to 316 -> 336 [0] 
                        336 to 358 -> 358 [1] lasti
                '__pyarmor_exit_15077__'
                (
                    None
                )
            [Disassembly]
                0       NOP                             
                2       LOAD_NAME                       0: __name__
                4       STORE_NAME                      1: __module__
                6       LOAD_CONST                      0: 'GPT'
                8       STORE_NAME                      2: __qualname__
                10      NOP                             
                12      PUSH_NULL                       
                14      LOAD_CONST                      2: '__pyarmor_enter_15076__'
                16      LOAD_CONST                      3: b'<COAddr>\x07\x00\x00"8\x00\x00\x00\x00\x00\x00\x00\x00\x00\x00\x00\x00\x00\x00\x00'
                18      BUILD_TUPLE                     1
                20      CALL_FUNCTION_EX                0
                22      POP_TOP                         
                24      RESUME                          0
                26      NOP                             
                28      NOP                             
                30      NOP                             
                32      NOP                             
                34      NOP                             
                36      PUSH_NULL                       
                38      LOAD_NAME                       4: Event
                40      CALL                            0
                48      BUILD_TUPLE                     1
                50      LOAD_CONST                      4: <CODE> __init__
                52      MAKE_FUNCTION                   1
                54      STORE_NAME                      5: __init__
                56      LOAD_CONST                      9: (None,)
                58      LOAD_CONST                      6: <CODE> start
                60      MAKE_FUNCTION                   1
                62      STORE_NAME                      6: start
                64      LOAD_CONST                      7: <CODE> clear
                66      MAKE_FUNCTION                   0
                68      STORE_NAME                      7: clear
                70      LOAD_CONST                      5: None
                72      NOP                             
                74      NOP                             
                76      NOP                             
                78      JUMP_FORWARD                    19 (to 118)
                86      POP_TOP                         
                88      RETURN_CONST                    5: None
                90      PUSH_EXC_INFO                   
                92      PUSH_NULL                       
                94      LOAD_CONST                      8: '__pyarmor_exit_15077__'
                96      NOP                             
                98      LOAD_CONST                      3: b'<COAddr>\x07\x00\x00"8\x00\x00\x00\x00\x00\x00\x00\x00\x00\x00\x00\x00\x00\x00\x00'
                100     CALL                            1
                108     POP_TOP                         
                110     RERAISE                         0
                112     COPY                            3
                114     POP_EXCEPT                      
                116     RERAISE                         1
                118     PUSH_NULL                       
                120     LOAD_CONST                      8: '__pyarmor_exit_15077__'
                122     LOAD_CONST                      3: b'<COAddr>\x07\x00\x00"8\x00\x00\x00\x00\x00\x00\x00\x00\x00\x00\x00\x00\x00\x00\x00'
                124     BUILD_TUPLE                     1
                126     CALL_FUNCTION_EX                0
                128     POP_TOP                         
                130     RETURN_VALUE                    
            [Exception Table]
                36 to 70 -> 90 [0] 
                90 to 112 -> 112 [1] lasti
        'GPT'
        '__pyarmor_exit_15074__'
    [Disassembly]
        0       NOP                             
        2       NOP                             
        4       PUSH_NULL                       
        6       LOAD_CONST                      1: '__pyarmor_enter_15073__'
        8       LOAD_CONST                      2: b'<COAddr>\x05\x00\x00\x1a\xfc\x00\x00\x00\x00\x00\x00\x00\x00\x00\x00\x00\x00\x00\x00\x00'
        10      BUILD_TUPLE                     1
        12      CALL_FUNCTION_EX                0
        14      POP_TOP                         
        16      RESUME                          0
        18      NOP                             
        20      NOP                             
        22      NOP                             
        24      NOP                             
        26      NOP                             
        28      LOAD_CONST                      3: 0
        30      LOAD_CONST                      4: None
        32      IMPORT_NAME                     1: warnings
        34      STORE_NAME                      1: warnings
        36      PUSH_NULL                       
        38      LOAD_NAME                       1: warnings
        40      LOAD_ATTR                       4: filterwarnings
        60      LOAD_CONST                      5: 'ignore'
        62      LOAD_NAME                       3: DeprecationWarning
        64      KW_NAMES                        6: ('category',)
        66      CALL                            2
        74      POP_TOP                         
        76      LOAD_CONST                      3: 0
        78      LOAD_CONST                      4: None
        80      IMPORT_NAME                     4: g4f
        82      STORE_NAME                      4: g4f
        84      LOAD_CONST                      3: 0
        86      LOAD_CONST                      4: None
        88      IMPORT_NAME                     5: random
        90      STORE_NAME                      5: random
        92      LOAD_CONST                      3: 0
        94      LOAD_CONST                      4: None
        96      IMPORT_NAME                     6: spintax
        98      STORE_NAME                      6: spintax
        100     LOAD_CONST                      3: 0
        102     LOAD_CONST                      7: ('Event',)
        104     IMPORT_NAME                     7: threading
        106     IMPORT_FROM                     8: Event
        108     STORE_NAME                      8: Event
        110     POP_TOP                         
        112     LOAD_CONST                      3: 0
        114     LOAD_CONST                      8: ('Logs',)
        116     IMPORT_NAME                     9: program.static_classes
        118     IMPORT_FROM                     10: Logs
        120     STORE_NAME                      10: Logs
        122     POP_TOP                         
        124     LOAD_CONST                      3: 0
        126     LOAD_CONST                      9: ('StopProgram',)
        128     IMPORT_NAME                     11: multithon.errors
        130     IMPORT_FROM                     12: StopProgram
        132     STORE_NAME                      12: StopProgram
        134     POP_TOP                         
        136     LOAD_CONST                      3: 0
        138     LOAD_CONST                      4: None
        140     IMPORT_NAME                     7: threading
        142     STORE_NAME                      7: threading
        144     LOAD_CONST                      3: 0
        146     LOAD_CONST                      10: ('Queue',)
        148     IMPORT_NAME                     13: queue
        150     IMPORT_FROM                     14: Queue
        152     STORE_NAME                      14: Queue
        154     POP_TOP                         
        156     LOAD_CONST                      11: False
        158     LOAD_NAME                       4: g4f
        160     LOAD_ATTR                       30: debug
        180     STORE_ATTR                      16: logging
        190     LOAD_CONST                      11: False
        192     LOAD_NAME                       4: g4f
        194     LOAD_ATTR                       30: debug
        214     STORE_ATTR                      17: version_check
        224     PUSH_NULL                       
        226     LOAD_BUILD_CLASS                
        228     LOAD_CONST                      12: <CODE> GPT
        230     MAKE_FUNCTION                   0
        232     LOAD_CONST                      13: 'GPT'
        234     CALL                            2
        242     STORE_NAME                      18: GPT
        244     LOAD_CONST                      4: None
        246     NOP                             
        248     NOP                             
        250     NOP                             
        252     JUMP_FORWARD                    26 (to 306)
        260     POP_TOP                         
        262     RETURN_CONST                    4: None
        264     PUSH_EXC_INFO                   
        266     POP_TOP                         
        268     POP_EXCEPT                      
        270     JUMP_BACKWARD                   98 (to 76)
        272     COPY                            3
        274     POP_EXCEPT                      
        276     RERAISE                         1
        278     PUSH_EXC_INFO                   
        280     PUSH_NULL                       
        282     LOAD_CONST                      14: '__pyarmor_exit_15074__'
        284     NOP                             
        286     LOAD_CONST                      2: b'<COAddr>\x05\x00\x00\x1a\xfc\x00\x00\x00\x00\x00\x00\x00\x00\x00\x00\x00\x00\x00\x00\x00'
        288     CALL                            1
        296     POP_TOP                         
        298     RERAISE                         0
        300     COPY                            3
        302     POP_EXCEPT                      
        304     RERAISE                         1
        306     PUSH_NULL                       
        308     LOAD_CONST                      14: '__pyarmor_exit_15074__'
        310     LOAD_CONST                      2: b'<COAddr>\x05\x00\x00\x1a\xfc\x00\x00\x00\x00\x00\x00\x00\x00\x00\x00\x00\x00\x00\x00\x00'
        312     BUILD_TUPLE                     1
        314     CALL_FUNCTION_EX                0
        316     POP_TOP                         
        318     RETURN_VALUE                    
    [Exception Table]
        28 to 76 -> 264 [0] 
        76 to 244 -> 278 [0] 
        264 to 268 -> 272 [1] lasti
        268 to 278 -> 278 [0] 
        278 to 300 -> 300 [1] lasti
