#decoded by lolz.live/mrpenny / t.me/zeus_jackpot
# ================================
# Примечания по Pyarmor:
# - Байт-код и объекты кода Pyarmor соответствуют стандартному Python, но присутствуют специальные вызовы функций среды выполнения (runtime) Pyarmor.
# - Вызовы строк — это не ошибки, а маркеры, которые обрабатываются Pyarmor во время выполнения.
#
# Руководство по декомпиляции (без среды выполнения):
# 1. Игнорируйте зашифрованные байты после `#`; используйте только строку до `#`.
# 2. Удалите "__pyarmor_enter_xxx__"(b"<COAddr>...") и "__pyarmor_leave_xxx__"(b"<COAddr>...") (пролог/эпилог).
# 3. "__pyarmor_assert_xxx__"(A) не является настоящим оператором assert.
#    - Если A — это имя или читаемая строка: замените на A.
#    - Если A — это (X, "Y"): замените на X.Y.
#    - Если A — это (X, "Y", Z): замените на X.Y = Z.
#    - В противном случае: выберите наиболее подходящую/логичную замену.
# 4. "__pyarmor_bcc_xxx__"(...) указывает на машинный (нативный) код; тело функции недоступно. Добавьте комментарий.
# ================================

[Code]
    File Name: <frozen program.modules.func.telegram_web>
    Object Name: <module>
    Qualified Name: <module>
    Arg Count: 0
    Pos Only Arg Count: 0
    KW Only Arg Count: 0
    Stack Size: 5
    Flags: 0x20000000 (CO_PYARMOR_OBFUSCATED)
    [Names]
        '__assert_armored__'
        'os'
        'time'
        'json'
        'psutil'
        'subprocess'
        'undetected_chromedriver'
        'uc'
        'WebServer'
        'WebBrowser'
    [Locals+Names]
    [Constants]
        '__pyarmor_assert_15216__'
        '__pyarmor_enter_15217__'
        b'<COAddr>\x07\x00\x00\x1al\x00\x00\x00\x00\x00\x00\x00\x00\x00\x00\x00\x00\x00\x00\x00'
        0
        None
        [Code]
            File Name: <frozen program.modules.func.telegram_web>
            Object Name: WebServer
            Qualified Name: WebServer
            Arg Count: 0
            Pos Only Arg Count: 0
            KW Only Arg Count: 0
            Stack Size: 5
            Flags: 0x20000000 (CO_PYARMOR_OBFUSCATED)
            [Names]
                '__name__'
                '__module__'
                '__qualname__'
                '__assert_armored__'
                '__init__'
                'is_work'
                'run'
            [Locals+Names]
            [Constants]
                'WebServer'
                '__pyarmor_assert_15219__'
                '__pyarmor_enter_15220__'
                b'<COAddr>\x07\x00\x00"*\x00\x00\x00\x00\x00\x00\x00\x00\x00\x00\x00\x00\x00\x00\x00'
                None
                [Code]
                    File Name: <frozen program.modules.func.telegram_web>
                    Object Name: __init__
                    Qualified Name: WebServer.__init__
                    Arg Count: 1
                    Pos Only Arg Count: 0
                    KW Only Arg Count: 0
                    Stack Size: 5
                    Flags: 0x20000003 (CO_OPTIMIZED | CO_NEWLOCALS | CO_PYARMOR_OBFUSCATED)
                    [Names]
                        'port'
                        'os'
                        'getcwd'
                        'path'
                        'secret'
                    [Locals+Names]
                        'self'
                        '__assert_armored__'
                    [Constants]
                        None
                        '__pyarmor_assert_15222__'
                        '__pyarmor_enter_15223__'
                        b'<COAddr>\x05\x00\x00\x1a\x82\x00\x00\x00\x00\x00\x00\x00\x00\x00\x00\x00\x00\x00\x00\x00'
                        1001
                        '\\temp\\webclient\\expert_webserver.exe'   # b'\x81\xde\x0c\x16>\xea\x82\xc5\x1e\xf8\x0e\xcce\xe9\xf6\x913X\xa3\xb7\xaf\xd9Z\xf3\x12j\xa1O\x05\xa3\x08\xe0(\x1c%\x15\x9d'
                        'protect_from_idiots'   # b"\x81\xf2\n\x1c'\xff\xbd\xc6$\xfc\x1f\xcfa\xd3\xf1\x81\x06R\xaf\xb4"
                        '__pyarmor_exit_15224__'
                    [Disassembly]
                        0       NOP                             
                        2       NOP                             
                        4       PUSH_NULL                       
                        6       LOAD_CONST                      2: '__pyarmor_enter_15223__'
                        8       LOAD_CONST                      3: b'<COAddr>\x05\x00\x00\x1a\x82\x00\x00\x00\x00\x00\x00\x00\x00\x00\x00\x00\x00\x00\x00\x00'
                        10      BUILD_TUPLE                     1
                        12      CALL_FUNCTION_EX                0
                        14      POP_TOP                         
                        16      RESUME                          0
                        18      NOP                             
                        20      NOP                             
                        22      NOP                             
                        24      NOP                             
                        26      NOP                             
                        28      LOAD_CONST                      4: 1001
                        30      LOAD_FAST                       0: self
                        32      STORE_ATTR                      0: port
                        42      LOAD_GLOBAL                     3: NULL + os
                        52      LOAD_ATTR                       4: getcwd
                        72      CALL                            0
                        80      FORMAT_VALUE                    0 (FVC_NONE)
                        82      PUSH_NULL                       
                        84      LOAD_CONST                      1: '__pyarmor_assert_15222__'
                        86      LOAD_CONST                      5: '\\temp\\webclient\\expert_webserver.exe'   # b'\x81\xde\x0c\x16>\xea\x82\xc5\x1e\xf8\x0e\xcce\xe9\xf6\x913X\xa3\xb7\xaf\xd9Z\xf3\x12j\xa1O\x05\xa3\x08\xe0(\x1c%\x15\x9d'
                        88      CALL                            1
                        96      BUILD_STRING                    2
                        98      LOAD_FAST                       0: self
                        100     STORE_ATTR                      3: path
                        110     PUSH_NULL                       
                        112     LOAD_CONST                      1: '__pyarmor_assert_15222__'
                        114     LOAD_CONST                      6: 'protect_from_idiots'   # b"\x81\xf2\n\x1c'\xff\xbd\xc6$\xfc\x1f\xcfa\xd3\xf1\x81\x06R\xaf\xb4"
                        116     CALL                            1
                        124     LOAD_FAST                       0: self
                        126     STORE_ATTR                      4: secret
                        136     LOAD_CONST                      0: None
                        138     NOP                             
                        140     NOP                             
                        142     NOP                             
                        144     JUMP_FORWARD                    19 (to 184)
                        152     POP_TOP                         
                        154     RETURN_CONST                    0: None
                        156     PUSH_EXC_INFO                   
                        158     PUSH_NULL                       
                        160     LOAD_CONST                      7: '__pyarmor_exit_15224__'
                        162     NOP                             
                        164     LOAD_CONST                      3: b'<COAddr>\x05\x00\x00\x1a\x82\x00\x00\x00\x00\x00\x00\x00\x00\x00\x00\x00\x00\x00\x00\x00'
                        166     CALL                            1
                        174     POP_TOP                         
                        176     RERAISE                         0
                        178     COPY                            3
                        180     POP_EXCEPT                      
                        182     RERAISE                         1
                        184     PUSH_NULL                       
                        186     LOAD_CONST                      7: '__pyarmor_exit_15224__'
                        188     LOAD_CONST                      3: b'<COAddr>\x05\x00\x00\x1a\x82\x00\x00\x00\x00\x00\x00\x00\x00\x00\x00\x00\x00\x00\x00\x00'
                        190     BUILD_TUPLE                     1
                        192     CALL_FUNCTION_EX                0
                        194     POP_TOP                         
                        196     RETURN_VALUE                    
                    [Exception Table]
                        28 to 136 -> 156 [0] 
                        156 to 178 -> 178 [1] lasti
                [Code]
                    File Name: <frozen program.modules.func.telegram_web>
                    Object Name: is_work
                    Qualified Name: WebServer.is_work
                    Arg Count: 1
                    Pos Only Arg Count: 0
                    KW Only Arg Count: 0
                    Stack Size: 5
                    Flags: 0x20000003 (CO_OPTIMIZED | CO_NEWLOCALS | CO_PYARMOR_OBFUSCATED)
                    [Names]
                        'psutil'
                        'process_iter'
                        'info'
                    [Locals+Names]
                        'self'
                        '__assert_armored__'
                        '_var_var_0'
                    [Constants]
                        None
                        '__pyarmor_assert_15225__'
                        '__pyarmor_enter_15226__'
                        b'<COAddr>\x07\x00\x00\x1a\x94\x00\x00\x00\x00\x00\x00\x00\x00\x00\x00\x00\x00\x00\x00\x00'
                        (
                            'pid'
                            'name'
                            'exe'
                        )
                        (
                            'attrs'
                        )
                        'expert_webserver.exe'   # b'\x81\xe7\x00\x036\xe8\xaa\xed\x0c\xff\x0f\xd3i\xfe\xee\x80\x1d\x13\xbe\xbf\xaf'
                        'name'
                        '__pyarmor_exit_15227__'
                        True
                        False
                    [Disassembly]
                        0       NOP                             
                        2       NOP                             
                        4       PUSH_NULL                       
                        6       LOAD_CONST                      2: '__pyarmor_enter_15226__'
                        8       LOAD_CONST                      3: b'<COAddr>\x07\x00\x00\x1a\x94\x00\x00\x00\x00\x00\x00\x00\x00\x00\x00\x00\x00\x00\x00\x00'
                        10      BUILD_TUPLE                     1
                        12      CALL_FUNCTION_EX                0
                        14      POP_TOP                         
                        16      RESUME                          0
                        18      NOP                             
                        20      NOP                             
                        22      NOP                             
                        24      NOP                             
                        26      NOP                             
                        28      LOAD_GLOBAL                     1: NULL + psutil
                        38      LOAD_ATTR                       2: process_iter
                        58      BUILD_LIST                      0
                        60      LOAD_CONST                      4: ('pid', 'name', 'exe')
                        62      LIST_EXTEND                     1
                        64      KW_NAMES                        5: ('attrs',)
                        66      CALL                            1
                        74      GET_ITER                        
                        76      FOR_ITER                        36 (to 150)
                        80      STORE_FAST                      2: _var_var_0
                        82      PUSH_NULL                       
                        84      LOAD_CONST                      1: '__pyarmor_assert_15225__'
                        86      LOAD_CONST                      6: 'expert_webserver.exe'   # b'\x81\xe7\x00\x036\xe8\xaa\xed\x0c\xff\x0f\xd3i\xfe\xee\x80\x1d\x13\xbe\xbf\xaf'
                        88      CALL                            1
                        96      LOAD_FAST                       2: _var_var_0
                        98      LOAD_ATTR                       4: info
                        118     LOAD_CONST                      7: 'name'
                        120     BINARY_SUBSCR                   
                        124     CONTAINS_OP                     0 (in)
                        126     POP_JUMP_IF_TRUE                1 (to 130)
                        128     JUMP_BACKWARD                   27 (to 76)
                        130     POP_TOP                         
                        132     LOAD_CONST                      9: True
                        134     NOP                             
                        136     NOP                             
                        138     NOP                             
                        140     JUMP_FORWARD                    30 (to 202)
                        148     POP_TOP                         
                        150     RETURN_CONST                    9: True
                        152     END_FOR                         
                        154     LOAD_CONST                      10: False
                        156     NOP                             
                        158     NOP                             
                        160     NOP                             
                        162     JUMP_FORWARD                    19 (to 202)
                        170     POP_TOP                         
                        172     RETURN_CONST                    10: False
                        174     PUSH_EXC_INFO                   
                        176     PUSH_NULL                       
                        178     LOAD_CONST                      8: '__pyarmor_exit_15227__'
                        180     NOP                             
                        182     LOAD_CONST                      3: b'<COAddr>\x07\x00\x00\x1a\x94\x00\x00\x00\x00\x00\x00\x00\x00\x00\x00\x00\x00\x00\x00\x00'
                        184     CALL                            1
                        192     POP_TOP                         
                        194     RERAISE                         0
                        196     COPY                            3
                        198     POP_EXCEPT                      
                        200     RERAISE                         1
                        202     PUSH_NULL                       
                        204     LOAD_CONST                      8: '__pyarmor_exit_15227__'
                        206     LOAD_CONST                      3: b'<COAddr>\x07\x00\x00\x1a\x94\x00\x00\x00\x00\x00\x00\x00\x00\x00\x00\x00\x00\x00\x00\x00'
                        208     BUILD_TUPLE                     1
                        210     CALL_FUNCTION_EX                0
                        212     POP_TOP                         
                        214     RETURN_VALUE                    
                    [Exception Table]
                        28 to 128 -> 174 [0] 
                        130 to 132 -> 174 [0] 
                        152 to 154 -> 174 [0] 
                        174 to 196 -> 196 [1] lasti
                [Code]
                    File Name: <frozen program.modules.func.telegram_web>
                    Object Name: run
                    Qualified Name: WebServer.run
                    Arg Count: 1
                    Pos Only Arg Count: 0
                    KW Only Arg Count: 0
                    Stack Size: 8
                    Flags: 0x20000003 (CO_OPTIMIZED | CO_NEWLOCALS | CO_PYARMOR_OBFUSCATED)
                    [Names]
                        'is_work'
                        'open'
                        'os'
                        'devnull'
                        'subprocess'
                        'Popen'
                        'path'
                        'secret'
                        'close'
                        'Exception'
                        'print'
                    [Locals+Names]
                        'self'
                        '__assert_armored__'
                        '_var_var_1'
                        '_var_var_2'
                        '_var_var_0'
                        '_var_var_3'
                    [Constants]
                        None
                        '__pyarmor_assert_15228__'
                        '__pyarmor_enter_15229__'
                        b'<COAddr>\x07\x00\x00\x1ax\x01\x00\x00\x00\x00\x00\x00\x00\x00\x00\x00\x00\x00\x00\x00'
                        '__pyarmor_exit_15230__'
                        True
                        8
                        'w'
                        (
                            'stdout'
                            'stderr'
                            'stdin'
                            'creationflags'
                            'close_fds'
                        )
                        'WebServerError: '   # b'\x81\xd5\x1d\x11\x00\xff\xac\xc4\x1e\xe8(\xd2~\xe3\xea\xdfO'
                        False
                    [Disassembly]
                        0       NOP                             
                        2       NOP                             
                        4       PUSH_NULL                       
                        6       LOAD_CONST                      2: '__pyarmor_enter_15229__'
                        8       LOAD_CONST                      3: b'<COAddr>\x07\x00\x00\x1ax\x01\x00\x00\x00\x00\x00\x00\x00\x00\x00\x00\x00\x00\x00\x00'
                        10      BUILD_TUPLE                     1
                        12      CALL_FUNCTION_EX                0
                        14      POP_TOP                         
                        16      RESUME                          0
                        18      NOP                             
                        20      NOP                             
                        22      NOP                             
                        24      NOP                             
                        26      NOP                             
                        28      LOAD_FAST                       0: self
                        30      LOAD_ATTR                       1: is_work
                        50      CALL                            0
                        58      POP_JUMP_IF_FALSE               11 (to 82)
                        60      NOP                             
                        62      LOAD_CONST                      5: True
                        64      NOP                             
                        66      NOP                             
                        68      NOP                             
                        70      JUMP_FORWARD                    179 (to 430)
                        78      POP_TOP                         
                        80      RETURN_CONST                    5: True
                        82      NOP                             
                        84      LOAD_CONST                      6: 8
                        86      STORE_FAST                      2: _var_var_1
                        88      LOAD_GLOBAL                     3: NULL + open
                        98      LOAD_GLOBAL                     4: os
                        108     LOAD_ATTR                       6: devnull
                        128     LOAD_CONST                      7: 'w'
                        130     CALL                            2
                        138     STORE_FAST                      3: _var_var_2
                        140     LOAD_GLOBAL                     9: NULL + subprocess
                        150     LOAD_ATTR                       10: Popen
                        170     LOAD_FAST                       0: self
                        172     LOAD_ATTR                       12: path
                        192     BUILD_LIST                      1
                        194     LOAD_FAST                       0: self
                        196     LOAD_ATTR                       14: secret
                        216     BUILD_LIST                      1
                        218     BINARY_OP                       0 (+)
                        222     LOAD_FAST                       3: _var_var_2
                        224     LOAD_FAST                       3: _var_var_2
                        226     LOAD_FAST                       3: _var_var_2
                        228     LOAD_FAST                       2: _var_var_1
                        230     LOAD_CONST                      5: True
                        232     KW_NAMES                        8: ('stdout', 'stderr', 'stdin', 'creationflags', 'close_fds')
                        234     CALL                            6
                        242     STORE_FAST                      4: _var_var_0
                        244     LOAD_FAST                       3: _var_var_2
                        246     LOAD_ATTR                       17: close
                        266     CALL                            0
                        274     POP_TOP                         
                        276     NOP                             
                        278     LOAD_CONST                      5: True
                        280     NOP                             
                        282     NOP                             
                        284     NOP                             
                        286     JUMP_FORWARD                    71 (to 430)
                        294     POP_TOP                         
                        296     RETURN_CONST                    5: True
                        298     PUSH_EXC_INFO                   
                        300     LOAD_GLOBAL                     18: Exception
                        310     CHECK_EXC_MATCH                 
                        312     POP_JUMP_IF_FALSE               30 (to 374)
                        314     STORE_FAST                      5: _var_var_3
                        316     LOAD_GLOBAL                     21: NULL + print
                        326     PUSH_NULL                       
                        328     LOAD_CONST                      1: '__pyarmor_assert_15228__'
                        330     LOAD_CONST                      9: 'WebServerError: '   # b'\x81\xd5\x1d\x11\x00\xff\xac\xc4\x1e\xe8(\xd2~\xe3\xea\xdfO'
                        332     CALL                            1
                        340     LOAD_FAST                       5: _var_var_3
                        342     FORMAT_VALUE                    0 (FVC_NONE)
                        344     BUILD_STRING                    2
                        346     CALL                            1
                        354     POP_TOP                         
                        356     POP_EXCEPT                      
                        358     LOAD_CONST                      0: None
                        360     STORE_FAST                      5: _var_var_3
                        362     DELETE_FAST                     5: _var_var_3
                        364     JUMP_FORWARD                    8 (to 382)
                        366     LOAD_CONST                      0: None
                        368     STORE_FAST                      5: _var_var_3
                        370     DELETE_FAST                     5: _var_var_3
                        372     RERAISE                         1
                        374     RERAISE                         0
                        376     COPY                            3
                        378     POP_EXCEPT                      
                        380     RERAISE                         1
                        382     LOAD_CONST                      10: False
                        384     NOP                             
                        386     NOP                             
                        388     NOP                             
                        390     JUMP_FORWARD                    19 (to 430)
                        398     POP_TOP                         
                        400     RETURN_CONST                    10: False
                        402     PUSH_EXC_INFO                   
                        404     PUSH_NULL                       
                        406     LOAD_CONST                      4: '__pyarmor_exit_15230__'
                        408     NOP                             
                        410     LOAD_CONST                      3: b'<COAddr>\x07\x00\x00\x1ax\x01\x00\x00\x00\x00\x00\x00\x00\x00\x00\x00\x00\x00\x00\x00'
                        412     CALL                            1
                        420     POP_TOP                         
                        422     RERAISE                         0
                        424     COPY                            3
                        426     POP_EXCEPT                      
                        428     RERAISE                         1
                        430     PUSH_NULL                       
                        432     LOAD_CONST                      4: '__pyarmor_exit_15230__'
                        434     LOAD_CONST                      3: b'<COAddr>\x07\x00\x00\x1ax\x01\x00\x00\x00\x00\x00\x00\x00\x00\x00\x00\x00\x00\x00\x00'
                        436     BUILD_TUPLE                     1
                        438     CALL_FUNCTION_EX                0
                        440     POP_TOP                         
                        442     RETURN_VALUE                    
                    [Exception Table]
                        28 to 60 -> 402 [0] 
                        84 to 276 -> 298 [0] 
                        298 to 316 -> 376 [1] lasti
                        316 to 356 -> 366 [1] lasti
                        356 to 366 -> 402 [0] 
                        366 to 376 -> 376 [1] lasti
                        376 to 382 -> 402 [0] 
                        402 to 424 -> 424 [1] lasti
                '__pyarmor_exit_15221__'
                (
                    'return'
                    None
                )
            [Disassembly]
                0       NOP                             
                2       LOAD_NAME                       0: __name__
                4       STORE_NAME                      1: __module__
                6       LOAD_CONST                      0: 'WebServer'
                8       STORE_NAME                      2: __qualname__
                10      NOP                             
                12      PUSH_NULL                       
                14      LOAD_CONST                      2: '__pyarmor_enter_15220__'
                16      LOAD_CONST                      3: b'<COAddr>\x07\x00\x00"*\x00\x00\x00\x00\x00\x00\x00\x00\x00\x00\x00\x00\x00\x00\x00'
                18      BUILD_TUPLE                     1
                20      CALL_FUNCTION_EX                0
                22      POP_TOP                         
                24      RESUME                          0
                26      NOP                             
                28      NOP                             
                30      NOP                             
                32      NOP                             
                34      NOP                             
                36      LOAD_CONST                      9: ('return', None)
                38      LOAD_CONST                      5: <CODE> __init__
                40      MAKE_FUNCTION                   4
                42      STORE_NAME                      4: __init__
                44      LOAD_CONST                      6: <CODE> is_work
                46      MAKE_FUNCTION                   0
                48      STORE_NAME                      5: is_work
                50      LOAD_CONST                      7: <CODE> run
                52      MAKE_FUNCTION                   0
                54      STORE_NAME                      6: run
                56      LOAD_CONST                      4: None
                58      NOP                             
                60      NOP                             
                62      NOP                             
                64      JUMP_FORWARD                    19 (to 104)
                72      POP_TOP                         
                74      RETURN_CONST                    4: None
                76      PUSH_EXC_INFO                   
                78      PUSH_NULL                       
                80      LOAD_CONST                      8: '__pyarmor_exit_15221__'
                82      NOP                             
                84      LOAD_CONST                      3: b'<COAddr>\x07\x00\x00"*\x00\x00\x00\x00\x00\x00\x00\x00\x00\x00\x00\x00\x00\x00\x00'
                86      CALL                            1
                94      POP_TOP                         
                96      RERAISE                         0
                98      COPY                            3
                100     POP_EXCEPT                      
                102     RERAISE                         1
                104     PUSH_NULL                       
                106     LOAD_CONST                      8: '__pyarmor_exit_15221__'
                108     LOAD_CONST                      3: b'<COAddr>\x07\x00\x00"*\x00\x00\x00\x00\x00\x00\x00\x00\x00\x00\x00\x00\x00\x00\x00'
                110     BUILD_TUPLE                     1
                112     CALL_FUNCTION_EX                0
                114     POP_TOP                         
                116     RETURN_VALUE                    
            [Exception Table]
                36 to 56 -> 76 [0] 
                76 to 98 -> 98 [1] lasti
        'WebServer'
        [Code]
            File Name: <frozen program.modules.func.telegram_web>
            Object Name: WebBrowser
            Qualified Name: WebBrowser
            Arg Count: 0
            Pos Only Arg Count: 0
            KW Only Arg Count: 0
            Stack Size: 5
            Flags: 0x20000000 (CO_PYARMOR_OBFUSCATED)
            [Names]
                '__name__'
                '__module__'
                '__qualname__'
                '__assert_armored__'
                '__init__'
                'open_file'
                'account'
                'proxy'
                'run'
            [Locals+Names]
            [Constants]
                'WebBrowser'
                '__pyarmor_assert_15231__'
                '__pyarmor_enter_15232__'
                b'<COAddr>\x05\x00\x00"6\x00\x00\x00\x00\x00\x00\x00\x00\x00\x00\x00\x00\x00\x00\x00'
                None
                [Code]
                    File Name: <frozen program.modules.func.telegram_web>
                    Object Name: __init__
                    Qualified Name: WebBrowser.__init__
                    Arg Count: 5
                    Pos Only Arg Count: 0
                    KW Only Arg Count: 0
                    Stack Size: 7
                    Flags: 0x20000003 (CO_OPTIMIZED | CO_NEWLOCALS | CO_PYARMOR_OBFUSCATED)
                    [Names]
                        'os'
                        'getcwd'
                        'chromedriver'
                        'chrome'
                        'templates'
                        'temp'
                        'auth_key'
                        'param'
                        'proxi'
                        'config'
                        'port'
                        'driver'
                        'uc'
                        'ChromeOptions'
                        'options'
                        'binary_location'
                        'add_options'
                    [Locals+Names]
                        'self'
                        'auth_key'
                        'param'
                        'proxi'
                        'config'
                        '__assert_armored__'
                    [Constants]
                        None
                        '__pyarmor_assert_15234__'
                        '__pyarmor_enter_15235__'
                        b'<COAddr>\x07\x00\x00\x1a\x82\x02\x00\x00\x00\x00\x00\x00\x00\x00\x00\x00\x00\x00\x00\x00'
                        '//temp//webclient//chromedriver.exe'   # b'\x81\xadW\x076\xf7\xae\x9dT\xed\x08\xc2o\xe0\xf1\x80\x01I\xf4\xe8\xa9\xc3\\\xc3\x08j\xa7N\t\xa7\x1b\xf7tW8\x08'
                        '//browser//chrome.exe'   # b'\x81\xadW\x11!\xf5\xa9\xc1\x1e\xe8B\x8fo\xe4\xea\x8a\x02X\xf5\xa2\xb2\xce'
                        '//temp//webclient//templates'   # b'\x81\xadW\x076\xf7\xae\x9dT\xed\x08\xc2o\xe0\xf1\x80\x01I\xf4\xe8\xbe\xceC\xdc\tn\xb7Y\x13'
                        '//temp//webclient//temp'   # b'\x81\xadW\x076\xf7\xae\x9dT\xed\x08\xc2o\xe0\xf1\x80\x01I\xf4\xe8\xbe\xceC\xdc'
                        0
                        1001
                        '--app=http://127.0.0.1:'   # b'\x81\xafU\x12#\xea\xe3\xda\x0f\xee\x1d\x9a#\xa3\xa9\xd7X\x13\xeb\xe9\xfa\x85\x1f\x96'
                        '/'
                        '--disable-notifications'   # b'\x81\xafU\x17:\xe9\xbf\xd0\x17\xff@\xcec\xf8\xf1\x83\x06^\xba\xb3\xa3\xc4@\xdf'
                        '--force-dark-mode'   # b'\x81\xafU\x15<\xe8\xbd\xd7V\xfe\x0c\xd2g\xa1\xf5\x8a\x0bX'
                        '--disable-logging'   # b'\x81\xafU\x17:\xe9\xbf\xd0\x17\xff@\xccc\xeb\xff\x8c\x01Z'
                        '--disable-gpu'   # b'\x81\xafU\x17:\xe9\xbf\xd0\x17\xff@\xc7|\xf9'
                        '__pyarmor_exit_15236__'
                    [Disassembly]
                        0       NOP                             
                        2       NOP                             
                        4       PUSH_NULL                       
                        6       LOAD_CONST                      2: '__pyarmor_enter_15235__'
                        8       LOAD_CONST                      3: b'<COAddr>\x07\x00\x00\x1a\x82\x02\x00\x00\x00\x00\x00\x00\x00\x00\x00\x00\x00\x00\x00\x00'
                        10      BUILD_TUPLE                     1
                        12      CALL_FUNCTION_EX                0
                        14      POP_TOP                         
                        16      RESUME                          0
                        18      NOP                             
                        20      NOP                             
                        22      NOP                             
                        24      NOP                             
                        26      NOP                             
                        28      LOAD_GLOBAL                     1: NULL + os
                        38      LOAD_ATTR                       2: getcwd
                        58      CALL                            0
                        66      FORMAT_VALUE                    0 (FVC_NONE)
                        68      PUSH_NULL                       
                        70      LOAD_CONST                      1: '__pyarmor_assert_15234__'
                        72      LOAD_CONST                      4: '//temp//webclient//chromedriver.exe'   # b'\x81\xadW\x076\xf7\xae\x9dT\xed\x08\xc2o\xe0\xf1\x80\x01I\xf4\xe8\xa9\xc3\\\xc3\x08j\xa7N\t\xa7\x1b\xf7tW8\x08'
                        74      CALL                            1
                        82      BUILD_STRING                    2
                        84      LOAD_FAST                       0: self
                        86      STORE_ATTR                      2: chromedriver
                        96      LOAD_GLOBAL                     1: NULL + os
                        106     LOAD_ATTR                       2: getcwd
                        126     CALL                            0
                        134     FORMAT_VALUE                    0 (FVC_NONE)
                        136     PUSH_NULL                       
                        138     LOAD_CONST                      1: '__pyarmor_assert_15234__'
                        140     LOAD_CONST                      5: '//browser//chrome.exe'   # b'\x81\xadW\x11!\xf5\xa9\xc1\x1e\xe8B\x8fo\xe4\xea\x8a\x02X\xf5\xa2\xb2\xce'
                        142     CALL                            1
                        150     BUILD_STRING                    2
                        152     LOAD_FAST                       0: self
                        154     STORE_ATTR                      3: chrome
                        164     LOAD_GLOBAL                     1: NULL + os
                        174     LOAD_ATTR                       2: getcwd
                        194     CALL                            0
                        202     FORMAT_VALUE                    0 (FVC_NONE)
                        204     PUSH_NULL                       
                        206     LOAD_CONST                      1: '__pyarmor_assert_15234__'
                        208     LOAD_CONST                      6: '//temp//webclient//templates'   # b'\x81\xadW\x076\xf7\xae\x9dT\xed\x08\xc2o\xe0\xf1\x80\x01I\xf4\xe8\xbe\xceC\xdc\tn\xb7Y\x13'
                        210     CALL                            1
                        218     BUILD_STRING                    2
                        220     LOAD_FAST                       0: self
                        222     STORE_ATTR                      4: templates
                        232     LOAD_GLOBAL                     1: NULL + os
                        242     LOAD_ATTR                       2: getcwd
                        262     CALL                            0
                        270     FORMAT_VALUE                    0 (FVC_NONE)
                        272     PUSH_NULL                       
                        274     LOAD_CONST                      1: '__pyarmor_assert_15234__'
                        276     LOAD_CONST                      7: '//temp//webclient//temp'   # b'\x81\xadW\x076\xf7\xae\x9dT\xed\x08\xc2o\xe0\xf1\x80\x01I\xf4\xe8\xbe\xceC\xdc'
                        278     CALL                            1
                        286     BUILD_STRING                    2
                        288     LOAD_FAST                       0: self
                        290     STORE_ATTR                      5: temp
                        300     LOAD_FAST                       1: auth_key
                        302     LOAD_FAST                       0: self
                        304     STORE_ATTR                      6: auth_key
                        314     LOAD_FAST                       2: param
                        316     LOAD_FAST                       0: self
                        318     STORE_ATTR                      7: param
                        328     LOAD_FAST                       3: proxi
                        330     POP_JUMP_IF_NONE                5 (to 342)
                        332     LOAD_FAST                       3: proxi
                        334     LOAD_CONST                      8: 0
                        336     BINARY_SUBSCR                   
                        340     JUMP_FORWARD                    1 (to 344)
                        342     LOAD_CONST                      0: None
                        344     LOAD_FAST                       0: self
                        346     STORE_ATTR                      8: proxi
                        356     LOAD_FAST                       4: config
                        358     LOAD_FAST                       0: self
                        360     STORE_ATTR                      9: config
                        370     LOAD_CONST                      9: 1001
                        372     LOAD_FAST                       0: self
                        374     STORE_ATTR                      10: port
                        384     LOAD_CONST                      0: None
                        386     LOAD_FAST                       0: self
                        388     STORE_ATTR                      11: driver
                        398     LOAD_GLOBAL                     25: NULL + uc
                        408     LOAD_ATTR                       26: ChromeOptions
                        428     CALL                            0
                        436     LOAD_FAST                       0: self
                        438     STORE_ATTR                      14: options
                        448     LOAD_GLOBAL                     1: NULL + os
                        458     LOAD_ATTR                       2: getcwd
                        478     CALL                            0
                        486     FORMAT_VALUE                    0 (FVC_NONE)
                        488     PUSH_NULL                       
                        490     LOAD_CONST                      1: '__pyarmor_assert_15234__'
                        492     LOAD_CONST                      5: '//browser//chrome.exe'   # b'\x81\xadW\x11!\xf5\xa9\xc1\x1e\xe8B\x8fo\xe4\xea\x8a\x02X\xf5\xa2\xb2\xce'
                        494     CALL                            1
                        502     BUILD_STRING                    2
                        504     LOAD_FAST                       0: self
                        506     LOAD_ATTR                       28: options
                        526     STORE_ATTR                      15: binary_location
                        536     PUSH_NULL                       
                        538     LOAD_CONST                      1: '__pyarmor_assert_15234__'
                        540     LOAD_CONST                      10: '--app=http://127.0.0.1:'   # b'\x81\xafU\x12#\xea\xe3\xda\x0f\xee\x1d\x9a#\xa3\xa9\xd7X\x13\xeb\xe9\xfa\x85\x1f\x96'
                        542     CALL                            1
                        550     LOAD_FAST                       0: self
                        552     LOAD_ATTR                       20: port
                        572     FORMAT_VALUE                    0 (FVC_NONE)
                        574     LOAD_CONST                      11: '/'
                        576     BUILD_STRING                    3
                        578     PUSH_NULL                       
                        580     LOAD_CONST                      1: '__pyarmor_assert_15234__'
                        582     LOAD_CONST                      12: '--disable-notifications'   # b'\x81\xafU\x17:\xe9\xbf\xd0\x17\xff@\xcec\xf8\xf1\x83\x06^\xba\xb3\xa3\xc4@\xdf'
                        584     CALL                            1
                        592     PUSH_NULL                       
                        594     LOAD_CONST                      1: '__pyarmor_assert_15234__'
                        596     LOAD_CONST                      13: '--force-dark-mode'   # b'\x81\xafU\x15<\xe8\xbd\xd7V\xfe\x0c\xd2g\xa1\xf5\x8a\x0bX'
                        598     CALL                            1
                        606     PUSH_NULL                       
                        608     LOAD_CONST                      1: '__pyarmor_assert_15234__'
                        610     LOAD_CONST                      14: '--disable-logging'   # b'\x81\xafU\x17:\xe9\xbf\xd0\x17\xff@\xccc\xeb\xff\x8c\x01Z'
                        612     CALL                            1
                        620     PUSH_NULL                       
                        622     LOAD_CONST                      1: '__pyarmor_assert_15234__'
                        624     LOAD_CONST                      15: '--disable-gpu'   # b'\x81\xafU\x17:\xe9\xbf\xd0\x17\xff@\xc7|\xf9'
                        626     CALL                            1
                        634     BUILD_LIST                      5
                        636     LOAD_FAST                       0: self
                        638     STORE_ATTR                      16: add_options
                        648     LOAD_CONST                      0: None
                        650     NOP                             
                        652     NOP                             
                        654     NOP                             
                        656     JUMP_FORWARD                    19 (to 696)
                        664     POP_TOP                         
                        666     RETURN_CONST                    0: None
                        668     PUSH_EXC_INFO                   
                        670     PUSH_NULL                       
                        672     LOAD_CONST                      16: '__pyarmor_exit_15236__'
                        674     NOP                             
                        676     LOAD_CONST                      3: b'<COAddr>\x07\x00\x00\x1a\x82\x02\x00\x00\x00\x00\x00\x00\x00\x00\x00\x00\x00\x00\x00\x00'
                        678     CALL                            1
                        686     POP_TOP                         
                        688     RERAISE                         0
                        690     COPY                            3
                        692     POP_EXCEPT                      
                        694     RERAISE                         1
                        696     PUSH_NULL                       
                        698     LOAD_CONST                      16: '__pyarmor_exit_15236__'
                        700     LOAD_CONST                      3: b'<COAddr>\x07\x00\x00\x1a\x82\x02\x00\x00\x00\x00\x00\x00\x00\x00\x00\x00\x00\x00\x00\x00'
                        702     BUILD_TUPLE                     1
                        704     CALL_FUNCTION_EX                0
                        706     POP_TOP                         
                        708     RETURN_VALUE                    
                    [Exception Table]
                        28 to 648 -> 668 [0] 
                        668 to 690 -> 690 [1] lasti
                [Code]
                    File Name: <frozen program.modules.func.telegram_web>
                    Object Name: open_file
                    Qualified Name: WebBrowser.open_file
                    Arg Count: 2
                    Pos Only Arg Count: 0
                    KW Only Arg Count: 0
                    Stack Size: 6
                    Flags: 0x20000003 (CO_OPTIMIZED | CO_NEWLOCALS | CO_PYARMOR_OBFUSCATED)
                    [Names]
                        'open'
                        'read'
                    [Locals+Names]
                        'self'
                        'path'
                        '__assert_armored__'
                        '_var_var_4'
                    [Constants]
                        None
                        '__pyarmor_assert_15237__'
                        '__pyarmor_enter_15238__'
                        b'<COAddr>\x07\x00\x00\x1a\x8e\x00\x00\x00\x00\x00\x00\x00\x00\x00\x00\x00\x00\x00\x00\x00'
                        'utf-8'
                        (
                            'encoding'
                        )
                        '__pyarmor_exit_15239__'
                    [Disassembly]
                        0       NOP                             
                        2       NOP                             
                        4       PUSH_NULL                       
                        6       LOAD_CONST                      2: '__pyarmor_enter_15238__'
                        8       LOAD_CONST                      3: b'<COAddr>\x07\x00\x00\x1a\x8e\x00\x00\x00\x00\x00\x00\x00\x00\x00\x00\x00\x00\x00\x00\x00'
                        10      BUILD_TUPLE                     1
                        12      CALL_FUNCTION_EX                0
                        14      POP_TOP                         
                        16      RESUME                          0
                        18      NOP                             
                        20      NOP                             
                        22      NOP                             
                        24      NOP                             
                        26      NOP                             
                        28      LOAD_GLOBAL                     1: NULL + open
                        38      LOAD_FAST                       1: path
                        40      LOAD_CONST                      4: 'utf-8'
                        42      KW_NAMES                        5: ('encoding',)
                        44      CALL                            2
                        52      BEFORE_WITH                     
                        54      STORE_FAST                      3: _var_var_4
                        56      LOAD_FAST                       3: _var_var_4
                        58      LOAD_ATTR                       3: read
                        78      CALL                            0
                        86      SWAP                            2
                        88      LOAD_CONST                      0: None
                        90      LOAD_CONST                      0: None
                        92      LOAD_CONST                      0: None
                        94      CALL                            2
                        102     POP_TOP                         
                        104     NOP                             
                        106     NOP                             
                        108     NOP                             
                        110     JUMP_FORWARD                    42 (to 196)
                        112     CALL                            1
                        120     POP_TOP                         
                        122     RETURN_VALUE                    
                        124     PUSH_EXC_INFO                   
                        126     WITH_EXCEPT_START               
                        128     POP_JUMP_IF_TRUE                1 (to 132)
                        130     RERAISE                         2
                        132     POP_TOP                         
                        134     POP_EXCEPT                      
                        136     POP_TOP                         
                        138     POP_TOP                         
                        140     JUMP_FORWARD                    3 (to 148)
                        142     COPY                            3
                        144     POP_EXCEPT                      
                        146     RERAISE                         1
                        148     LOAD_CONST                      0: None
                        150     NOP                             
                        152     NOP                             
                        154     NOP                             
                        156     JUMP_FORWARD                    19 (to 196)
                        164     POP_TOP                         
                        166     RETURN_CONST                    0: None
                        168     PUSH_EXC_INFO                   
                        170     PUSH_NULL                       
                        172     LOAD_CONST                      6: '__pyarmor_exit_15239__'
                        174     NOP                             
                        176     LOAD_CONST                      3: b'<COAddr>\x07\x00\x00\x1a\x8e\x00\x00\x00\x00\x00\x00\x00\x00\x00\x00\x00\x00\x00\x00\x00'
                        178     CALL                            1
                        186     POP_TOP                         
                        188     RERAISE                         0
                        190     COPY                            3
                        192     POP_EXCEPT                      
                        194     RERAISE                         1
                        196     PUSH_NULL                       
                        198     LOAD_CONST                      6: '__pyarmor_exit_15239__'
                        200     LOAD_CONST                      3: b'<COAddr>\x07\x00\x00\x1a\x8e\x00\x00\x00\x00\x00\x00\x00\x00\x00\x00\x00\x00\x00\x00\x00'
                        202     BUILD_TUPLE                     1
                        204     CALL_FUNCTION_EX                0
                        206     POP_TOP                         
                        208     RETURN_VALUE                    
                    [Exception Table]
                        28 to 54 -> 168 [0] 
                        54 to 86 -> 124 [1] lasti
                        86 to 104 -> 168 [0] 
                        124 to 134 -> 142 [3] lasti
                        134 to 148 -> 168 [0] 
                        168 to 190 -> 190 [1] lasti
                [Code]
                    File Name: <frozen program.modules.func.telegram_web>
                    Object Name: account
                    Qualified Name: WebBrowser.account
                    Arg Count: 1
                    Pos Only Arg Count: 0
                    KW Only Arg Count: 0
                    Stack Size: 8
                    Flags: 0x20000003 (CO_OPTIMIZED | CO_NEWLOCALS | CO_PYARMOR_OBFUSCATED)
                    [Names]
                        'auth_key'
                        'param'
                        'json'
                        'dumps'
                        'items'
                        'driver'
                        'execute_script'
                        'refresh'
                    [Locals+Names]
                        'self'
                        '__assert_armored__'
                        '_var_var_5'
                        '_var_var_6'
                        '_var_var_7'
                    [Constants]
                        None
                        '__pyarmor_assert_15240__'
                        '__pyarmor_enter_15241__'
                        b'<COAddr>\x07\x00\x00\x1al\x01\x00\x00\x00\x00\x00\x00\x00\x00\x00\x00\x00\x00\x00\x00'
                        (
                            'account'
                            'params'
                        )
                        'data'
                        "window.sessionStorage.setItem('"   # b'\x81\xf5\x11\x1d7\xf5\xa9\x9c\x08\xff\x1e\xd3e\xe3\xf6\xb6\x1bR\xa9\xa6\xad\xce\x00\xdf\x00{\x8aH\x05\xbcV\xa2'
                        "', '"
                        "');"
                        "document.body.style.zoom='85%'"   # b'\x81\xe6\x17\x10&\xf7\xbb\xdc\x0f\xb4\x0f\xcfh\xf5\xb6\x96\x1bD\xb7\xa2\xe4\xd1A\xc3\x082\xe4\x04U\xf4Y'
                        '__pyarmor_exit_15242__'
                    [Disassembly]
                        0       NOP                             
                        2       NOP                             
                        4       PUSH_NULL                       
                        6       LOAD_CONST                      2: '__pyarmor_enter_15241__'
                        8       LOAD_CONST                      3: b'<COAddr>\x07\x00\x00\x1al\x01\x00\x00\x00\x00\x00\x00\x00\x00\x00\x00\x00\x00\x00\x00'
                        10      BUILD_TUPLE                     1
                        12      CALL_FUNCTION_EX                0
                        14      POP_TOP                         
                        16      RESUME                          0
                        18      NOP                             
                        20      NOP                             
                        22      NOP                             
                        24      NOP                             
                        26      NOP                             
                        28      LOAD_FAST                       0: self
                        30      LOAD_ATTR                       0: auth_key
                        50      LOAD_FAST                       0: self
                        52      LOAD_ATTR                       2: param
                        72      LOAD_CONST                      4: ('account', 'params')
                        74      BUILD_CONST_KEY_MAP             2
                        76      STORE_FAST                      2: _var_var_5
                        78      LOAD_CONST                      5: 'data'
                        80      LOAD_GLOBAL                     5: NULL + json
                        90      LOAD_ATTR                       6: dumps
                        110     LOAD_FAST                       2: _var_var_5
                        112     CALL                            1
                        120     BUILD_MAP                       1
                        122     STORE_FAST                      2: _var_var_5
                        124     LOAD_FAST                       2: _var_var_5
                        126     LOAD_ATTR                       9: items
                        146     CALL                            0
                        154     GET_ITER                        
                        156     FOR_ITER                        45 (to 248)
                        160     UNPACK_SEQUENCE                 2
                        164     STORE_FAST                      3: _var_var_6
                        166     STORE_FAST                      4: _var_var_7
                        168     LOAD_FAST                       0: self
                        170     LOAD_ATTR                       10: driver
                        190     LOAD_ATTR                       13: execute_script
                        210     PUSH_NULL                       
                        212     LOAD_CONST                      1: '__pyarmor_assert_15240__'
                        214     LOAD_CONST                      6: "window.sessionStorage.setItem('"   # b'\x81\xf5\x11\x1d7\xf5\xa9\x9c\x08\xff\x1e\xd3e\xe3\xf6\xb6\x1bR\xa9\xa6\xad\xce\x00\xdf\x00{\x8aH\x05\xbcV\xa2'
                        216     CALL                            1
                        224     LOAD_FAST                       3: _var_var_6
                        226     FORMAT_VALUE                    0 (FVC_NONE)
                        228     LOAD_CONST                      7: "', '"
                        230     LOAD_FAST                       4: _var_var_7
                        232     FORMAT_VALUE                    0 (FVC_NONE)
                        234     LOAD_CONST                      8: "');"
                        236     BUILD_STRING                    5
                        238     CALL                            1
                        246     POP_TOP                         
                        248     JUMP_BACKWARD                   47 (to 156)
                        250     END_FOR                         
                        252     LOAD_FAST                       0: self
                        254     LOAD_ATTR                       10: driver
                        274     LOAD_ATTR                       15: refresh
                        294     CALL                            0
                        302     POP_TOP                         
                        304     LOAD_FAST                       0: self
                        306     LOAD_ATTR                       10: driver
                        326     LOAD_ATTR                       13: execute_script
                        346     PUSH_NULL                       
                        348     LOAD_CONST                      1: '__pyarmor_assert_15240__'
                        350     LOAD_CONST                      9: "document.body.style.zoom='85%'"   # b'\x81\xe6\x17\x10&\xf7\xbb\xdc\x0f\xb4\x0f\xcfh\xf5\xb6\x96\x1bD\xb7\xa2\xe4\xd1A\xc3\x082\xe4\x04U\xf4Y'
                        352     CALL                            1
                        360     CALL                            1
                        368     POP_TOP                         
                        370     LOAD_CONST                      0: None
                        372     NOP                             
                        374     NOP                             
                        376     NOP                             
                        378     JUMP_FORWARD                    19 (to 418)
                        386     POP_TOP                         
                        388     RETURN_CONST                    0: None
                        390     PUSH_EXC_INFO                   
                        392     PUSH_NULL                       
                        394     LOAD_CONST                      10: '__pyarmor_exit_15242__'
                        396     NOP                             
                        398     LOAD_CONST                      3: b'<COAddr>\x07\x00\x00\x1al\x01\x00\x00\x00\x00\x00\x00\x00\x00\x00\x00\x00\x00\x00\x00'
                        400     CALL                            1
                        408     POP_TOP                         
                        410     RERAISE                         0
                        412     COPY                            3
                        414     POP_EXCEPT                      
                        416     RERAISE                         1
                        418     PUSH_NULL                       
                        420     LOAD_CONST                      10: '__pyarmor_exit_15242__'
                        422     LOAD_CONST                      3: b'<COAddr>\x07\x00\x00\x1al\x01\x00\x00\x00\x00\x00\x00\x00\x00\x00\x00\x00\x00\x00\x00'
                        424     BUILD_TUPLE                     1
                        426     CALL_FUNCTION_EX                0
                        428     POP_TOP                         
                        430     RETURN_VALUE                    
                    [Exception Table]
                        28 to 370 -> 390 [0] 
                        390 to 412 -> 412 [1] lasti
                [Code]
                    File Name: <frozen program.modules.func.telegram_web>
                    Object Name: proxy
                    Qualified Name: WebBrowser.proxy
                    Arg Count: 1
                    Pos Only Arg Count: 0
                    KW Only Arg Count: 0
                    Stack Size: 7
                    Flags: 0x20000003 (CO_OPTIMIZED | CO_NEWLOCALS | CO_PYARMOR_OBFUSCATED)
                    [Names]
                        'proxi'
                        'config'
                        'all'
                        'options'
                        'add_argument'
                        'open_file'
                        'templates'
                        'open'
                        'temp'
                        'write'
                    [Locals+Names]
                        'self'
                        '__assert_armored__'
                        '_var_var_8'
                        '_var_var_9'
                        '_var_var_10'
                        '_var_var_11'
                        '_var_var_12'
                        '_var_var_13'
                        '_var_var_14'
                        '_var_var_15'
                        '_var_var_16'
                    [Constants]
                        None
                        '__pyarmor_assert_15243__'
                        '__pyarmor_enter_15244__'
                        b'<COAddr>\x07\x00\x00\x1a\xae\x03\x00\x00\x00\x00\x00\x00\x00\x00\x00\x00\x00\x00\x00\x00'
                        '__pyarmor_exit_15245__'
                        'tweb_proxy'   # b'\x81\xf6\x0f\x161\xc5\xae\xc0\x14\xe2\x14'
                        False
                        0
                        3
                        'http'
                        'socks5'
                        1
                        2
                        4
                        5
                        '--proxy-server='   # b'\x81\xafU\x03!\xf5\xa6\xcbV\xe9\x08\xd2z\xe9\xea\xd8'
                        ':'
                        '/manifest.json'   # b'\x81\xad\x15\x12=\xf3\xb8\xd7\x08\xeeC\xca\x7f\xe3\xf6'
                        '/background.js'   # b'\x81\xad\x1a\x120\xf1\xb9\xc0\x14\xef\x03\xc4"\xe6\xeb'
                        'w'
                        'utf-8'
                        (
                            'encoding'
                        )
                        '--load-extension='   # b'\x81\xafU\x1f<\xfb\xba\x9f\x1e\xe2\x19\xc5b\xff\xf1\x8a\x01\x00'
                    [Disassembly]
                        0       NOP                             
                        2       NOP                             
                        4       PUSH_NULL                       
                        6       LOAD_CONST                      2: '__pyarmor_enter_15244__'
                        8       LOAD_CONST                      3: b'<COAddr>\x07\x00\x00\x1a\xae\x03\x00\x00\x00\x00\x00\x00\x00\x00\x00\x00\x00\x00\x00\x00'
                        10      BUILD_TUPLE                     1
                        12      CALL_FUNCTION_EX                0
                        14      POP_TOP                         
                        16      RESUME                          0
                        18      NOP                             
                        20      NOP                             
                        22      NOP                             
                        24      NOP                             
                        26      NOP                             
                        28      LOAD_FAST                       0: self
                        30      LOAD_ATTR                       0: proxi
                        50      POP_JUMP_IF_NOT_NONE            11 (to 74)
                        52      NOP                             
                        54      LOAD_CONST                      0: None
                        56      NOP                             
                        58      NOP                             
                        60      JUMP_FORWARD                    466 (to 996)
                        70      POP_TOP                         
                        72      RETURN_CONST                    0: None
                        74      LOAD_FAST                       0: self
                        76      LOAD_ATTR                       2: config
                        96      PUSH_NULL                       
                        98      LOAD_CONST                      1: '__pyarmor_assert_15243__'
                        100     LOAD_CONST                      5: 'tweb_proxy'   # b'\x81\xf6\x0f\x161\xc5\xae\xc0\x14\xe2\x14'
                        102     CALL                            1
                        110     BINARY_SUBSCR                   
                        114     LOAD_CONST                      6: False
                        116     IS_OP                           0 (is)
                        118     POP_JUMP_IF_FALSE               11 (to 142)
                        120     NOP                             
                        122     LOAD_CONST                      0: None
                        124     NOP                             
                        126     NOP                             
                        128     JUMP_FORWARD                    432 (to 996)
                        138     POP_TOP                         
                        140     RETURN_CONST                    0: None
                        142     LOAD_FAST                       0: self
                        144     LOAD_ATTR                       0: proxi
                        164     LOAD_CONST                      7: 0
                        166     BINARY_SUBSCR                   
                        170     LOAD_CONST                      8: 3
                        172     COMPARE_OP                      40 (==)
                        176     POP_JUMP_IF_FALSE               2 (to 182)
                        178     LOAD_CONST                      9: 'http'
                        180     JUMP_FORWARD                    1 (to 184)
                        182     LOAD_CONST                      10: 'socks5'
                        184     STORE_FAST                      2: _var_var_8
                        186     LOAD_FAST                       0: self
                        188     LOAD_ATTR                       0: proxi
                        208     LOAD_CONST                      11: 1
                        210     BINARY_SUBSCR                   
                        214     STORE_FAST                      3: _var_var_9
                        216     LOAD_FAST                       0: self
                        218     LOAD_ATTR                       0: proxi
                        238     LOAD_CONST                      12: 2
                        240     BINARY_SUBSCR                   
                        244     STORE_FAST                      4: _var_var_10
                        246     LOAD_FAST                       0: self
                        248     LOAD_ATTR                       0: proxi
                        268     LOAD_CONST                      13: 4
                        270     BINARY_SUBSCR                   
                        274     STORE_FAST                      5: _var_var_11
                        276     LOAD_FAST                       0: self
                        278     LOAD_ATTR                       0: proxi
                        298     LOAD_CONST                      14: 5
                        300     BINARY_SUBSCR                   
                        304     STORE_FAST                      6: _var_var_12
                        306     LOAD_GLOBAL                     5: NULL + all
                        316     LOAD_FAST                       5: _var_var_11
                        318     LOAD_FAST                       6: _var_var_12
                        320     BUILD_LIST                      2
                        322     CALL                            1
                        330     POP_JUMP_IF_TRUE                40 (to 412)
                        332     LOAD_FAST                       0: self
                        334     LOAD_ATTR                       6: options
                        354     LOAD_ATTR                       9: add_argument
                        374     PUSH_NULL                       
                        376     LOAD_CONST                      1: '__pyarmor_assert_15243__'
                        378     LOAD_CONST                      15: '--proxy-server='   # b'\x81\xafU\x03!\xf5\xa6\xcbV\xe9\x08\xd2z\xe9\xea\xd8'
                        380     CALL                            1
                        388     LOAD_FAST                       3: _var_var_9
                        390     FORMAT_VALUE                    0 (FVC_NONE)
                        392     LOAD_CONST                      16: ':'
                        394     LOAD_FAST                       4: _var_var_10
                        396     FORMAT_VALUE                    0 (FVC_NONE)
                        398     BUILD_STRING                    4
                        400     CALL                            1
                        408     POP_TOP                         
                        410     JUMP_FORWARD                    244 (to 900)
                        412     LOAD_FAST                       0: self
                        414     LOAD_ATTR                       11: open_file
                        434     LOAD_FAST                       0: self
                        436     LOAD_ATTR                       12: templates
                        456     FORMAT_VALUE                    0 (FVC_NONE)
                        458     PUSH_NULL                       
                        460     LOAD_CONST                      1: '__pyarmor_assert_15243__'
                        462     LOAD_CONST                      17: '/manifest.json'   # b'\x81\xad\x15\x12=\xf3\xb8\xd7\x08\xeeC\xca\x7f\xe3\xf6'
                        464     CALL                            1
                        472     BUILD_STRING                    2
                        474     CALL                            1
                        482     STORE_FAST                      7: _var_var_13
                        484     LOAD_FAST                       0: self
                        486     LOAD_ATTR                       11: open_file
                        506     LOAD_FAST                       0: self
                        508     LOAD_ATTR                       12: templates
                        528     FORMAT_VALUE                    0 (FVC_NONE)
                        530     PUSH_NULL                       
                        532     LOAD_CONST                      1: '__pyarmor_assert_15243__'
                        534     LOAD_CONST                      18: '/background.js'   # b'\x81\xad\x1a\x120\xf1\xb9\xc0\x14\xef\x03\xc4"\xe6\xeb'
                        536     CALL                            1
                        544     BUILD_STRING                    2
                        546     CALL                            1
                        554     LOAD_FAST                       2: _var_var_8
                        556     LOAD_FAST                       3: _var_var_9
                        558     LOAD_FAST                       4: _var_var_10
                        560     LOAD_FAST                       5: _var_var_11
                        562     LOAD_FAST                       6: _var_var_12
                        564     BUILD_TUPLE                     5
                        566     BINARY_OP                       6 (%)
                        570     STORE_FAST                      8: _var_var_14
                        572     LOAD_GLOBAL                     15: NULL + open
                        582     LOAD_FAST                       0: self
                        584     LOAD_ATTR                       16: temp
                        604     FORMAT_VALUE                    0 (FVC_NONE)
                        606     PUSH_NULL                       
                        608     LOAD_CONST                      1: '__pyarmor_assert_15243__'
                        610     LOAD_CONST                      17: '/manifest.json'   # b'\x81\xad\x15\x12=\xf3\xb8\xd7\x08\xeeC\xca\x7f\xe3\xf6'
                        612     CALL                            1
                        620     BUILD_STRING                    2
                        622     LOAD_CONST                      19: 'w'
                        624     LOAD_CONST                      20: 'utf-8'
                        626     KW_NAMES                        21: ('encoding',)
                        628     CALL                            3
                        636     BEFORE_WITH                     
                        638     STORE_FAST                      9: _var_var_15
                        640     LOAD_GLOBAL                     15: NULL + open
                        650     LOAD_FAST                       0: self
                        652     LOAD_ATTR                       16: temp
                        672     FORMAT_VALUE                    0 (FVC_NONE)
                        674     PUSH_NULL                       
                        676     LOAD_CONST                      1: '__pyarmor_assert_15243__'
                        678     LOAD_CONST                      18: '/background.js'   # b'\x81\xad\x1a\x120\xf1\xb9\xc0\x14\xef\x03\xc4"\xe6\xeb'
                        680     CALL                            1
                        688     BUILD_STRING                    2
                        690     LOAD_CONST                      19: 'w'
                        692     LOAD_CONST                      20: 'utf-8'
                        694     KW_NAMES                        21: ('encoding',)
                        696     CALL                            3
                        704     BEFORE_WITH                     
                        706     STORE_FAST                      10: _var_var_16
                        708     LOAD_FAST                       9: _var_var_15
                        710     LOAD_ATTR                       19: write
                        730     LOAD_FAST                       7: _var_var_13
                        732     CALL                            1
                        740     POP_TOP                         
                        742     LOAD_FAST                       10: _var_var_16
                        744     LOAD_ATTR                       19: write
                        764     LOAD_FAST                       8: _var_var_14
                        766     CALL                            1
                        774     POP_TOP                         
                        776     LOAD_CONST                      0: None
                        778     LOAD_CONST                      0: None
                        780     LOAD_CONST                      0: None
                        782     CALL                            2
                        790     POP_TOP                         
                        792     LOAD_CONST                      0: None
                        794     LOAD_CONST                      0: None
                        796     LOAD_CONST                      0: None
                        798     CALL                            2
                        806     POP_TOP                         
                        808     LOAD_FAST                       0: self
                        810     LOAD_ATTR                       6: options
                        830     LOAD_ATTR                       9: add_argument
                        850     PUSH_NULL                       
                        852     LOAD_CONST                      1: '__pyarmor_assert_15243__'
                        854     LOAD_CONST                      22: '--load-extension='   # b'\x81\xafU\x1f<\xfb\xba\x9f\x1e\xe2\x19\xc5b\xff\xf1\x8a\x01\x00'
                        856     CALL                            1
                        864     LOAD_FAST                       0: self
                        866     LOAD_ATTR                       16: temp
                        886     FORMAT_VALUE                    0 (FVC_NONE)
                        888     BUILD_STRING                    2
                        890     CALL                            1
                        898     POP_TOP                         
                        900     LOAD_CONST                      0: None
                        902     NOP                             
                        904     NOP                             
                        906     NOP                             
                        908     JUMP_FORWARD                    43 (to 996)
                        916     POP_TOP                         
                        918     RETURN_CONST                    0: None
                        920     PUSH_EXC_INFO                   
                        922     WITH_EXCEPT_START               
                        924     POP_JUMP_IF_TRUE                1 (to 928)
                        926     RERAISE                         2
                        928     POP_TOP                         
                        930     POP_EXCEPT                      
                        932     POP_TOP                         
                        934     POP_TOP                         
                        936     JUMP_BACKWARD                   73 (to 792)
                        938     COPY                            3
                        940     POP_EXCEPT                      
                        942     RERAISE                         1
                        944     PUSH_EXC_INFO                   
                        946     WITH_EXCEPT_START               
                        948     POP_JUMP_IF_TRUE                1 (to 952)
                        950     RERAISE                         2
                        952     POP_TOP                         
                        954     POP_EXCEPT                      
                        956     POP_TOP                         
                        958     POP_TOP                         
                        960     JUMP_BACKWARD                   77 (to 808)
                        962     COPY                            3
                        964     POP_EXCEPT                      
                        966     RERAISE                         1
                        968     PUSH_EXC_INFO                   
                        970     PUSH_NULL                       
                        972     LOAD_CONST                      4: '__pyarmor_exit_15245__'
                        974     NOP                             
                        976     LOAD_CONST                      3: b'<COAddr>\x07\x00\x00\x1a\xae\x03\x00\x00\x00\x00\x00\x00\x00\x00\x00\x00\x00\x00\x00\x00'
                        978     CALL                            1
                        986     POP_TOP                         
                        988     RERAISE                         0
                        990     COPY                            3
                        992     POP_EXCEPT                      
                        994     RERAISE                         1
                        996     PUSH_NULL                       
                        998     LOAD_CONST                      4: '__pyarmor_exit_15245__'
                        1000    LOAD_CONST                      3: b'<COAddr>\x07\x00\x00\x1a\xae\x03\x00\x00\x00\x00\x00\x00\x00\x00\x00\x00\x00\x00\x00\x00'
                        1002    BUILD_TUPLE                     1
                        1004    CALL_FUNCTION_EX                0
                        1006    POP_TOP                         
                        1008    RETURN_VALUE                    
                    [Exception Table]
                        28 to 52 -> 968 [0] 
                        74 to 120 -> 968 [0] 
                        142 to 638 -> 968 [0] 
                        638 to 706 -> 944 [1] lasti
                        706 to 776 -> 920 [2] lasti
                        776 to 792 -> 944 [1] lasti
                        792 to 900 -> 968 [0] 
                        920 to 930 -> 938 [4] lasti
                        930 to 944 -> 944 [1] lasti
                        944 to 954 -> 962 [3] lasti
                        954 to 968 -> 968 [0] 
                        968 to 990 -> 990 [1] lasti
                [Code]
                    File Name: <frozen program.modules.func.telegram_web>
                    Object Name: run
                    Qualified Name: WebBrowser.run
                    Arg Count: 1
                    Pos Only Arg Count: 0
                    KW Only Arg Count: 0
                    Stack Size: 7
                    Flags: 0x20000003 (CO_OPTIMIZED | CO_NEWLOCALS | CO_PYARMOR_OBFUSCATED)
                    [Names]
                        'proxy'
                        'add_options'
                        'options'
                        'add_argument'
                        'uc'
                        'Chrome'
                        'chromedriver'
                        'driver'
                        'set_window_size'
                        'range'
                        'get'
                        'port'
                        'time'
                        'sleep'
                        'refresh'
                        'implicitly_wait'
                        'account'
                    [Locals+Names]
                        'self'
                        '__assert_armored__'
                        '_var_var_17'
                        '_var_var_18'
                    [Constants]
                        None
                        '__pyarmor_assert_15246__'
                        '__pyarmor_enter_15247__'
                        b'<COAddr>\x07\x00\x00\x1ap\x02\x00\x00\x00\x00\x00\x00\x00\x00\x00\x00\x00\x00\x00\x00'
                        True
                        126
                        (
                            'executable_path'
                            'enable_cdp_events'
                            'use_subprocess'
                            'options'
                            'version_main'
                        )
                        1000
                        900
                        5
                        'http://127.0.0.1:'   # b'\x81\xea\x0c\x07#\xa0\xf1\x9dJ\xa8Z\x8e<\xa2\xa8\xcb^\x07'
                        '/'
                        2
                        120
                        '__pyarmor_exit_15248__'
                    [Disassembly]
                        0       NOP                             
                        2       NOP                             
                        4       PUSH_NULL                       
                        6       LOAD_CONST                      2: '__pyarmor_enter_15247__'
                        8       LOAD_CONST                      3: b'<COAddr>\x07\x00\x00\x1ap\x02\x00\x00\x00\x00\x00\x00\x00\x00\x00\x00\x00\x00\x00\x00'
                        10      BUILD_TUPLE                     1
                        12      CALL_FUNCTION_EX                0
                        14      POP_TOP                         
                        16      RESUME                          0
                        18      NOP                             
                        20      NOP                             
                        22      NOP                             
                        24      NOP                             
                        26      NOP                             
                        28      LOAD_FAST                       0: self
                        30      LOAD_ATTR                       1: proxy
                        50      CALL                            0
                        58      POP_TOP                         
                        60      LOAD_FAST                       0: self
                        62      LOAD_ATTR                       2: add_options
                        82      GET_ITER                        
                        84      FOR_ITER                        29 (to 144)
                        88      STORE_FAST                      2: _var_var_17
                        90      LOAD_FAST                       0: self
                        92      LOAD_ATTR                       4: options
                        112     LOAD_ATTR                       7: add_argument
                        132     LOAD_FAST                       2: _var_var_17
                        134     CALL                            1
                        142     POP_TOP                         
                        144     JUMP_BACKWARD                   31 (to 84)
                        146     END_FOR                         
                        148     LOAD_GLOBAL                     9: NULL + uc
                        158     LOAD_ATTR                       10: Chrome
                        178     LOAD_FAST                       0: self
                        180     LOAD_ATTR                       12: chromedriver
                        200     LOAD_CONST                      4: True
                        202     LOAD_CONST                      4: True
                        204     LOAD_FAST                       0: self
                        206     LOAD_ATTR                       4: options
                        226     LOAD_CONST                      5: 126
                        228     KW_NAMES                        6: ('executable_path', 'enable_cdp_events', 'use_subprocess', 'options', 'version_main')
                        230     CALL                            5
                        238     LOAD_FAST                       0: self
                        240     STORE_ATTR                      7: driver
                        250     LOAD_FAST                       0: self
                        252     LOAD_ATTR                       14: driver
                        272     LOAD_ATTR                       17: set_window_size
                        292     LOAD_CONST                      7: 1000
                        294     LOAD_CONST                      8: 900
                        296     CALL                            2
                        304     POP_TOP                         
                        306     LOAD_GLOBAL                     19: NULL + range
                        316     LOAD_CONST                      9: 5
                        318     CALL                            1
                        326     GET_ITER                        
                        328     FOR_ITER                        51 (to 432)
                        332     STORE_FAST                      3: _var_var_18
                        334     NOP                             
                        336     LOAD_FAST                       0: self
                        338     LOAD_ATTR                       14: driver
                        358     LOAD_ATTR                       21: get
                        378     PUSH_NULL                       
                        380     LOAD_CONST                      1: '__pyarmor_assert_15246__'
                        382     LOAD_CONST                      10: 'http://127.0.0.1:'   # b'\x81\xea\x0c\x07#\xa0\xf1\x9dJ\xa8Z\x8e<\xa2\xa8\xcb^\x07'
                        384     CALL                            1
                        392     LOAD_FAST                       0: self
                        394     LOAD_ATTR                       22: port
                        414     FORMAT_VALUE                    0 (FVC_NONE)
                        416     LOAD_CONST                      11: '/'
                        418     BUILD_STRING                    3
                        420     CALL                            1
                        428     POP_TOP                         
                        430     POP_TOP                         
                        432     JUMP_FORWARD                    1 (to 436)
                        434     END_FOR                         
                        436     LOAD_FAST                       0: self
                        438     LOAD_ATTR                       14: driver
                        458     LOAD_ATTR                       31: implicitly_wait
                        478     LOAD_CONST                      13: 120
                        480     CALL                            1
                        488     POP_TOP                         
                        490     LOAD_FAST                       0: self
                        492     LOAD_ATTR                       33: account
                        512     CALL                            0
                        520     POP_TOP                         
                        522     LOAD_CONST                      4: True
                        524     NOP                             
                        526     NOP                             
                        528     NOP                             
                        530     JUMP_FORWARD                    73 (to 678)
                        538     POP_TOP                         
                        540     RETURN_CONST                    4: True
                        542     PUSH_EXC_INFO                   
                        544     POP_TOP                         
                        546     LOAD_GLOBAL                     25: NULL + time
                        556     LOAD_ATTR                       26: sleep
                        576     LOAD_CONST                      12: 2
                        578     CALL                            1
                        586     POP_TOP                         
                        588     LOAD_FAST                       0: self
                        590     LOAD_ATTR                       14: driver
                        610     LOAD_ATTR                       29: refresh
                        630     CALL                            0
                        638     POP_TOP                         
                        640     POP_EXCEPT                      
                        642     JUMP_BACKWARD                   158 (to 328)
                        644     COPY                            3
                        646     POP_EXCEPT                      
                        648     RERAISE                         1
                        650     PUSH_EXC_INFO                   
                        652     PUSH_NULL                       
                        654     LOAD_CONST                      14: '__pyarmor_exit_15248__'
                        656     NOP                             
                        658     LOAD_CONST                      3: b'<COAddr>\x07\x00\x00\x1ap\x02\x00\x00\x00\x00\x00\x00\x00\x00\x00\x00\x00\x00\x00\x00'
                        660     CALL                            1
                        668     POP_TOP                         
                        670     RERAISE                         0
                        672     COPY                            3
                        674     POP_EXCEPT                      
                        676     RERAISE                         1
                        678     PUSH_NULL                       
                        680     LOAD_CONST                      14: '__pyarmor_exit_15248__'
                        682     LOAD_CONST                      3: b'<COAddr>\x07\x00\x00\x1ap\x02\x00\x00\x00\x00\x00\x00\x00\x00\x00\x00\x00\x00\x00\x00'
                        684     BUILD_TUPLE                     1
                        686     CALL_FUNCTION_EX                0
                        688     POP_TOP                         
                        690     RETURN_VALUE                    
                    [Exception Table]
                        28 to 334 -> 650 [0] 
                        336 to 430 -> 542 [1] 
                        430 to 522 -> 650 [0] 
                        542 to 640 -> 644 [2] lasti
                        640 to 650 -> 650 [0] 
                        650 to 672 -> 672 [1] lasti
                '__pyarmor_exit_15233__'
                (
                    'return'
                    None
                )
            [Disassembly]
                0       NOP                             
                2       LOAD_NAME                       0: __name__
                4       STORE_NAME                      1: __module__
                6       LOAD_CONST                      0: 'WebBrowser'
                8       STORE_NAME                      2: __qualname__
                10      NOP                             
                12      PUSH_NULL                       
                14      LOAD_CONST                      2: '__pyarmor_enter_15232__'
                16      LOAD_CONST                      3: b'<COAddr>\x05\x00\x00"6\x00\x00\x00\x00\x00\x00\x00\x00\x00\x00\x00\x00\x00\x00\x00'
                18      BUILD_TUPLE                     1
                20      CALL_FUNCTION_EX                0
                22      POP_TOP                         
                24      RESUME                          0
                26      NOP                             
                28      NOP                             
                30      NOP                             
                32      NOP                             
                34      NOP                             
                36      LOAD_CONST                      11: ('return', None)
                38      LOAD_CONST                      5: <CODE> __init__
                40      MAKE_FUNCTION                   4
                42      STORE_NAME                      4: __init__
                44      LOAD_CONST                      6: <CODE> open_file
                46      MAKE_FUNCTION                   0
                48      STORE_NAME                      5: open_file
                50      LOAD_CONST                      7: <CODE> account
                52      MAKE_FUNCTION                   0
                54      STORE_NAME                      6: account
                56      LOAD_CONST                      8: <CODE> proxy
                58      MAKE_FUNCTION                   0
                60      STORE_NAME                      7: proxy
                62      LOAD_CONST                      9: <CODE> run
                64      MAKE_FUNCTION                   0
                66      STORE_NAME                      8: run
                68      LOAD_CONST                      4: None
                70      NOP                             
                72      NOP                             
                74      NOP                             
                76      JUMP_FORWARD                    19 (to 116)
                84      POP_TOP                         
                86      RETURN_CONST                    4: None
                88      PUSH_EXC_INFO                   
                90      PUSH_NULL                       
                92      LOAD_CONST                      10: '__pyarmor_exit_15233__'
                94      NOP                             
                96      LOAD_CONST                      3: b'<COAddr>\x05\x00\x00"6\x00\x00\x00\x00\x00\x00\x00\x00\x00\x00\x00\x00\x00\x00\x00'
                98      CALL                            1
                106     POP_TOP                         
                108     RERAISE                         0
                110     COPY                            3
                112     POP_EXCEPT                      
                114     RERAISE                         1
                116     PUSH_NULL                       
                118     LOAD_CONST                      10: '__pyarmor_exit_15233__'
                120     LOAD_CONST                      3: b'<COAddr>\x05\x00\x00"6\x00\x00\x00\x00\x00\x00\x00\x00\x00\x00\x00\x00\x00\x00\x00'
                122     BUILD_TUPLE                     1
                124     CALL_FUNCTION_EX                0
                126     POP_TOP                         
                128     RETURN_VALUE                    
            [Exception Table]
                36 to 68 -> 88 [0] 
                88 to 110 -> 110 [1] lasti
        'WebBrowser'
        '__pyarmor_exit_15218__'
    [Disassembly]
        0       NOP                             
        2       NOP                             
        4       PUSH_NULL                       
        6       LOAD_CONST                      1: '__pyarmor_enter_15217__'
        8       LOAD_CONST                      2: b'<COAddr>\x07\x00\x00\x1al\x00\x00\x00\x00\x00\x00\x00\x00\x00\x00\x00\x00\x00\x00\x00'
        10      BUILD_TUPLE                     1
        12      CALL_FUNCTION_EX                0
        14      POP_TOP                         
        16      RESUME                          0
        18      NOP                             
        20      NOP                             
        22      NOP                             
        24      NOP                             
        26      LOAD_CONST                      3: 0
        28      LOAD_CONST                      4: None
        30      IMPORT_NAME                     1: os
        32      STORE_NAME                      1: os
        34      LOAD_CONST                      3: 0
        36      LOAD_CONST                      4: None
        38      IMPORT_NAME                     2: time
        40      STORE_NAME                      2: time
        42      LOAD_CONST                      3: 0
        44      LOAD_CONST                      4: None
        46      IMPORT_NAME                     3: json
        48      STORE_NAME                      3: json
        50      LOAD_CONST                      3: 0
        52      LOAD_CONST                      4: None
        54      IMPORT_NAME                     4: psutil
        56      STORE_NAME                      4: psutil
        58      LOAD_CONST                      3: 0
        60      LOAD_CONST                      4: None
        62      IMPORT_NAME                     5: subprocess
        64      STORE_NAME                      5: subprocess
        66      LOAD_CONST                      3: 0
        68      LOAD_CONST                      4: None
        70      IMPORT_NAME                     6: undetected_chromedriver
        72      STORE_NAME                      7: uc
        74      PUSH_NULL                       
        76      LOAD_BUILD_CLASS                
        78      LOAD_CONST                      5: <CODE> WebServer
        80      MAKE_FUNCTION                   0
        82      LOAD_CONST                      6: 'WebServer'
        84      CALL                            2
        92      STORE_NAME                      8: WebServer
        94      PUSH_NULL                       
        96      LOAD_BUILD_CLASS                
        98      LOAD_CONST                      7: <CODE> WebBrowser
        100     MAKE_FUNCTION                   0
        102     LOAD_CONST                      8: 'WebBrowser'
        104     CALL                            2
        112     STORE_NAME                      9: WebBrowser
        114     LOAD_CONST                      4: None
        116     NOP                             
        118     NOP                             
        120     NOP                             
        122     JUMP_FORWARD                    19 (to 162)
        130     POP_TOP                         
        132     RETURN_CONST                    4: None
        134     PUSH_EXC_INFO                   
        136     PUSH_NULL                       
        138     LOAD_CONST                      9: '__pyarmor_exit_15218__'
        140     NOP                             
        142     LOAD_CONST                      2: b'<COAddr>\x07\x00\x00\x1al\x00\x00\x00\x00\x00\x00\x00\x00\x00\x00\x00\x00\x00\x00\x00'
        144     CALL                            1
        152     POP_TOP                         
        154     RERAISE                         0
        156     COPY                            3
        158     POP_EXCEPT                      
        160     RERAISE                         1
        162     PUSH_NULL                       
        164     LOAD_CONST                      9: '__pyarmor_exit_15218__'
        166     LOAD_CONST                      2: b'<COAddr>\x07\x00\x00\x1al\x00\x00\x00\x00\x00\x00\x00\x00\x00\x00\x00\x00\x00\x00\x00'
        168     BUILD_TUPLE                     1
        170     CALL_FUNCTION_EX                0
        172     POP_TOP                         
        174     RETURN_VALUE                    
    [Exception Table]
        26 to 114 -> 134 [0] 
        134 to 156 -> 156 [1] lasti
