#decoded by lolz.live/mrpenny / t.me/zeus_jackpot
# ================================
# Примечания по Pyarmor:
# - Байт-код и объекты кода Pyarmor соответствуют стандартному Python, но присутствуют специальные вызовы функций среды выполнения (runtime) Pyarmor.
# - Вызовы строк — это не ошибки, а маркеры, которые обрабатываются Pyarmor во время выполнения.
#
# Руководство по декомпиляции (без среды выполнения):
# 1. Игнорируйте зашифрованные байты после `#`; используйте только строку до `#`.
# 2. Удалите "__pyarmor_enter_xxx__"(b"<COAddr>...") и "__pyarmor_leave_xxx__"(b"<COAddr>...") (пролог/эпилог).
# 3. "__pyarmor_assert_xxx__"(A) не является настоящим оператором assert.
#    - Если A — это имя или читаемая строка: замените на A.
#    - Если A — это (X, "Y"): замените на X.Y.
#    - Если A — это (X, "Y", Z): замените на X.Y = Z.
#    - В противном случае: выберите наиболее подходящую/логичную замену.
# 4. "__pyarmor_bcc_xxx__"(...) указывает на машинный (нативный) код; тело функции недоступно. Добавьте комментарий.
# ================================

[Code]
    File Name: <frozen multithon.client.dialogs>
    Object Name: <module>
    Qualified Name: <module>
    Arg Count: 0
    Pos Only Arg Count: 0
    KW Only Arg Count: 0
    Stack Size: 5
    Flags: 0x20000000 (CO_PYARMOR_OBFUSCATED)
    [Names]
        '__assert_armored__'
        'asyncio'
        'inspect'
        'itertools'
        'typing'
        ''
        'helpers'
        'utils'
        'hints'
        'errors'
        'requestiter'
        'RequestIter'
        'tl'
        'types'
        'functions'
        'custom'
        '_MAX_CHUNK_SIZE'
        'TYPE_CHECKING'
        'telegramclient'
        'TelegramClient'
        '_dialog_message_key'
        '_DialogsIter'
        '_DraftsIter'
        'DialogMethods'
    [Locals+Names]
    [Constants]
        '__pyarmor_assert_16884__'
        '__pyarmor_enter_16885__'
        b'<COAddr>\x05\x00\x00\x1a\xda\x00\x00\x00\x00\x00\x00\x00\x00\x00\x00\x00\x00\x00\x00\x00'
        0
        None
        2
        (
            'helpers'
            'utils'
            'hints'
            'errors'
        )
        (
            'RequestIter'
        )
        (
            'types'
            'functions'
            'custom'
        )
        100
        1
        (
            'TelegramClient'
        )
        [Code]
            File Name: <frozen multithon.client.dialogs>
            Object Name: _dialog_message_key
            Qualified Name: _dialog_message_key
            Arg Count: 2
            Pos Only Arg Count: 0
            KW Only Arg Count: 0
            Stack Size: 5
            Flags: 0x20000003 (CO_OPTIMIZED | CO_NEWLOCALS | CO_PYARMOR_OBFUSCATED)
            [Names]
                'isinstance'
                'types'
                'PeerChannel'
                'channel_id'
            [Locals+Names]
                'peer'
                'message_id'
                '__assert_armored__'
            [Constants]
                '\n    Get the key to get messages from a dialog.\n\n    We cannot just use the message ID because channels share message IDs,\n    and the peer ID is required to distinguish between them. But it is not\n    necessary in small group chats and private chats.\n    '
                '__pyarmor_assert_16887__'
                '__pyarmor_enter_16888__'
                b'<COAddr>\x05\x00\x00\x1ah\x00\x00\x00\x00\x00\x00\x00\x00\x00\x00\x00\x00\x00\x00\x00'
                None
                '__pyarmor_exit_16889__'
            [Disassembly]
                0       NOP                             
                2       NOP                             
                4       PUSH_NULL                       
                6       LOAD_CONST                      2: '__pyarmor_enter_16888__'
                8       LOAD_CONST                      3: b'<COAddr>\x05\x00\x00\x1ah\x00\x00\x00\x00\x00\x00\x00\x00\x00\x00\x00\x00\x00\x00\x00'
                10      BUILD_TUPLE                     1
                12      CALL_FUNCTION_EX                0
                14      POP_TOP                         
                16      RESUME                          0
                18      NOP                             
                20      NOP                             
                22      NOP                             
                24      NOP                             
                26      NOP                             
                28      LOAD_GLOBAL                     1: NULL + isinstance
                38      LOAD_FAST                       0: peer
                40      LOAD_GLOBAL                     2: types
                50      LOAD_ATTR                       4: PeerChannel
                70      CALL                            2
                78      POP_JUMP_IF_FALSE               12 (to 104)
                80      LOAD_FAST                       0: peer
                82      LOAD_ATTR                       6: channel_id
                102     JUMP_FORWARD                    1 (to 106)
                104     LOAD_CONST                      4: None
                106     LOAD_FAST                       1: message_id
                108     BUILD_TUPLE                     2
                110     NOP                             
                112     NOP                             
                114     NOP                             
                116     JUMP_FORWARD                    20 (to 158)
                118     CALL                            1
                126     POP_TOP                         
                128     RETURN_VALUE                    
                130     PUSH_EXC_INFO                   
                132     PUSH_NULL                       
                134     LOAD_CONST                      5: '__pyarmor_exit_16889__'
                136     NOP                             
                138     LOAD_CONST                      3: b'<COAddr>\x05\x00\x00\x1ah\x00\x00\x00\x00\x00\x00\x00\x00\x00\x00\x00\x00\x00\x00\x00'
                140     CALL                            1
                148     POP_TOP                         
                150     RERAISE                         0
                152     COPY                            3
                154     POP_EXCEPT                      
                156     RERAISE                         1
                158     PUSH_NULL                       
                160     LOAD_CONST                      5: '__pyarmor_exit_16889__'
                162     LOAD_CONST                      3: b'<COAddr>\x05\x00\x00\x1ah\x00\x00\x00\x00\x00\x00\x00\x00\x00\x00\x00\x00\x00\x00\x00'
                164     BUILD_TUPLE                     1
                166     CALL_FUNCTION_EX                0
                168     POP_TOP                         
                170     RETURN_VALUE                    
            [Exception Table]
                28 to 110 -> 130 [0] 
                130 to 152 -> 152 [1] lasti
        [Code]
            File Name: <frozen multithon.client.dialogs>
            Object Name: _DialogsIter
            Qualified Name: _DialogsIter
            Arg Count: 0
            Pos Only Arg Count: 0
            KW Only Arg Count: 0
            Stack Size: 5
            Flags: 0x20000000 (CO_PYARMOR_OBFUSCATED)
            [Names]
                '__name__'
                '__module__'
                '__qualname__'
                '__assert_armored__'
                '_init'
                '_load_next_chunk'
            [Locals+Names]
            [Constants]
                '_DialogsIter'
                '__pyarmor_assert_16890__'
                '__pyarmor_enter_16891__'
                b'<COAddr>\x07\x00\x00""\x00\x00\x00\x00\x00\x00\x00\x00\x00\x00\x00\x00\x00\x00\x00'
                [Code]
                    File Name: <frozen multithon.client.dialogs>
                    Object Name: _init
                    Qualified Name: _DialogsIter._init
                    Arg Count: 7
                    Pos Only Arg Count: 0
                    KW Only Arg Count: 0
                    Stack Size: 9
                    Flags: 0x20000083 (CO_OPTIMIZED | CO_NEWLOCALS | CO_COROUTINE | CO_PYARMOR_OBFUSCATED)
                    [Names]
                        'functions'
                        'messages'
                        'GetDialogsRequest'
                        'request'
                        'limit'
                        'client'
                        'getattr'
                        'len'
                        'dialogs'
                        'total'
                        'StopAsyncIteration'
                        'set'
                        'seen'
                        'offset_date'
                        'ignore_migrated'
                    [Locals+Names]
                        'self'
                        'offset_date'
                        'offset_id'
                        'offset_peer'
                        'ignore_pinned'
                        'ignore_migrated'
                        'folder'
                        '__assert_armored__'
                        '_var_var_0'
                    [Constants]
                        None
                        '__pyarmor_assert_16893__'
                        '__pyarmor_enter_16894__'
                        b'<COAddr>\x05\x00\x00\x1ed\x01\x00\x00\x00\x00\x00\x00\x00\x00\x00\x00\x00\x00\x00\x00'
                        1
                        0
                        (
                            'offset_date'
                            'offset_id'
                            'offset_peer'
                            'limit'
                            'hash'
                            'exclude_pinned'
                            'folder_id'
                        )
                        'count'
                        '__pyarmor_exit_16895__'
                    [Disassembly]
                        0       RETURN_GENERATOR                
                        2       POP_TOP                         
                        4       NOP                             
                        6       NOP                             
                        8       PUSH_NULL                       
                        10      LOAD_CONST                      2: '__pyarmor_enter_16894__'
                        12      LOAD_CONST                      3: b'<COAddr>\x05\x00\x00\x1ed\x01\x00\x00\x00\x00\x00\x00\x00\x00\x00\x00\x00\x00\x00\x00'
                        14      BUILD_TUPLE                     1
                        16      CALL_FUNCTION_EX                0
                        18      POP_TOP                         
                        20      RESUME                          0
                        22      NOP                             
                        24      NOP                             
                        26      NOP                             
                        28      NOP                             
                        30      NOP                             
                        32      LOAD_GLOBAL                     0: functions
                        42      LOAD_ATTR                       2: messages
                        62      LOAD_ATTR                       5: GetDialogsRequest
                        82      LOAD_FAST                       1: offset_date
                        84      LOAD_FAST                       2: offset_id
                        86      LOAD_FAST                       3: offset_peer
                        88      LOAD_CONST                      4: 1
                        90      LOAD_CONST                      5: 0
                        92      LOAD_FAST                       4: ignore_pinned
                        94      LOAD_FAST                       6: folder
                        96      KW_NAMES                        6: ('offset_date', 'offset_id', 'offset_peer', 'limit', 'hash', 'exclude_pinned', 'folder_id')
                        98      CALL                            7
                        106     LOAD_FAST                       0: self
                        108     STORE_ATTR                      3: request
                        118     LOAD_FAST                       0: self
                        120     LOAD_ATTR                       8: limit
                        140     LOAD_CONST                      5: 0
                        142     COMPARE_OP                      26 (<=)
                        146     POP_JUMP_IF_FALSE               78 (to 304)
                        148     LOAD_FAST                       0: self
                        150     LOAD_ATTR                       11: client
                        170     LOAD_FAST                       0: self
                        172     LOAD_ATTR                       6: request
                        192     CALL                            1
                        200     GET_AWAITABLE                   0
                        202     LOAD_CONST                      0: None
                        204     SEND                            3 (to 212)
                        208     YIELD_VALUE                     3
                        210     RESUME                          3
                        212     JUMP_BACKWARD_NO_INTERRUPT      5 (to 204)
                        214     END_SEND                        
                        216     STORE_FAST                      8: _var_var_0
                        218     LOAD_GLOBAL                     13: NULL + getattr
                        228     LOAD_FAST                       8: _var_var_0
                        230     LOAD_CONST                      7: 'count'
                        232     LOAD_GLOBAL                     15: NULL + len
                        242     LOAD_FAST                       8: _var_var_0
                        244     LOAD_ATTR                       16: dialogs
                        264     CALL                            1
                        272     CALL                            3
                        280     LOAD_FAST                       0: self
                        282     STORE_ATTR                      9: total
                        292     LOAD_GLOBAL                     20: StopAsyncIteration
                        302     RAISE_VARARGS                   1
                        304     LOAD_GLOBAL                     23: NULL + set
                        314     CALL                            0
                        322     LOAD_FAST                       0: self
                        324     STORE_ATTR                      12: seen
                        334     LOAD_FAST                       1: offset_date
                        336     LOAD_FAST                       0: self
                        338     STORE_ATTR                      13: offset_date
                        348     LOAD_FAST                       5: ignore_migrated
                        350     LOAD_FAST                       0: self
                        352     STORE_ATTR                      14: ignore_migrated
                        362     LOAD_CONST                      0: None
                        364     NOP                             
                        366     NOP                             
                        368     NOP                             
                        370     JUMP_FORWARD                    23 (to 418)
                        378     POP_TOP                         
                        380     RETURN_CONST                    0: None
                        382     CLEANUP_THROW                   
                        384     JUMP_BACKWARD                   86 (to 214)
                        386     PUSH_EXC_INFO                   
                        388     PUSH_NULL                       
                        390     LOAD_CONST                      8: '__pyarmor_exit_16895__'
                        392     NOP                             
                        394     LOAD_CONST                      3: b'<COAddr>\x05\x00\x00\x1ed\x01\x00\x00\x00\x00\x00\x00\x00\x00\x00\x00\x00\x00\x00\x00'
                        396     CALL                            1
                        404     POP_TOP                         
                        406     RERAISE                         0
                        408     COPY                            3
                        410     POP_EXCEPT                      
                        412     RERAISE                         1
                        414     CALL_INTRINSIC_1                3 (INTRINSIC_STOPITERATION_ERROR)
                        416     RERAISE                         1
                        418     PUSH_NULL                       
                        420     LOAD_CONST                      8: '__pyarmor_exit_16895__'
                        422     LOAD_CONST                      3: b'<COAddr>\x05\x00\x00\x1ed\x01\x00\x00\x00\x00\x00\x00\x00\x00\x00\x00\x00\x00\x00\x00'
                        424     BUILD_TUPLE                     1
                        426     CALL_FUNCTION_EX                0
                        428     POP_TOP                         
                        430     RETURN_VALUE                    
                    [Exception Table]
                        4 to 30 -> 414 [0] lasti
                        32 to 208 -> 386 [0] 
                        208 to 210 -> 382 [2] 
                        210 to 362 -> 386 [0] 
                        362 to 382 -> 414 [0] lasti
                        382 to 384 -> 386 [0] 
                        386 to 408 -> 408 [1] lasti
                        408 to 414 -> 414 [0] lasti
                [Code]
                    File Name: <frozen multithon.client.dialogs>
                    Object Name: _load_next_chunk
                    Qualified Name: _DialogsIter._load_next_chunk
                    Arg Count: 1
                    Pos Only Arg Count: 0
                    KW Only Arg Count: 0
                    Stack Size: 9
                    Flags: 0x20000083 (CO_OPTIMIZED | CO_NEWLOCALS | CO_COROUTINE | CO_PYARMOR_OBFUSCATED)
                    [Names]
                        'min'
                        'left'
                        '_MAX_CHUNK_SIZE'
                        'request'
                        'limit'
                        'client'
                        'getattr'
                        'len'
                        'dialogs'
                        'total'
                        'itertools'
                        'chain'
                        'users'
                        'chats'
                        'isinstance'
                        'types'
                        'UserEmpty'
                        'ChatEmpty'
                        'utils'
                        'get_peer_id'
                        '_mb_entity_cache'
                        'extend'
                        'messages'
                        '_finish_init'
                        '_dialog_message_key'
                        'peer_id'
                        'id'
                        'get'
                        'peer'
                        'top_message'
                        'offset_date'
                        'timestamp'
                        'seen'
                        'add'
                        'custom'
                        'Dialog'
                        'dialog'
                        'pts'
                        '_message_box'
                        'try_set_channel_state'
                        'ignore_migrated'
                        'entity'
                        'buffer'
                        'append'
                        'DialogsSlice'
                        'next'
                        'filter'
                        'reversed'
                        'exclude_pinned'
                        'offset_id'
                        'date'
                        'input_entity'
                        'offset_peer'
                    [Locals+Names]
                        'self'
                        '__assert_armored__'
                        '_var_var_2'
                        '_var_var_3'
                        '_var_var_4'
                        '_var_var_5'
                        '_var_var_6'
                        '_var_var_7'
                        '_var_var_8'
                        '_var_var_9'
                        '_var_var_10'
                        '_var_var_11'
                        '_var_var_1'
                    [Constants]
                        None
                        '__pyarmor_assert_16896__'
                        '__pyarmor_enter_16897__'
                        b'<COAddr>\x07\x00\x00 \x8a\x08\x00\x00\x00\x00\x00\x00\x00\x00\x00\x00\x00\x00\x00\x00'
                        'count'
                        'date'
                        False
                        (
                            'add_mark'
                        )
                        'migrated_to'   # b'\x81\xef\x11\x14!\xfb\xaa\xd7\x1f\xc5\x19\xcf'
                        '__pyarmor_exit_16898__'
                        True
                        [Code]
                            File Name: <frozen multithon.client.dialogs>
                            Object Name: <genexpr>
                            Qualified Name: _DialogsIter._load_next_chunk.<locals>.<genexpr>
                            Arg Count: 1
                            Pos Only Arg Count: 0
                            KW Only Arg Count: 0
                            Stack Size: 7
                            Flags: 0x00000033 (CO_OPTIMIZED | CO_NEWLOCALS | CO_NESTED | CO_GENERATOR)
                            [Names]
                                'get'
                                '_dialog_message_key'
                                'peer'
                                'top_message'
                            [Locals+Names]
                                '.0'
                                '_var_var_6'
                                '_var_var_1'
                            [Constants]
                                None
                            [Disassembly]
                                0       COPY_FREE_VARS                  1
                                2       RETURN_GENERATOR                
                                4       POP_TOP                         
                                6       RESUME                          0
                                8       LOAD_FAST                       0: .0
                                10      FOR_ITER                        51 (to 114)
                                14      STORE_FAST                      1: _var_var_6
                                16      LOAD_DEREF                      2: _var_var_1
                                18      LOAD_ATTR                       1: get
                                38      LOAD_GLOBAL                     3: NULL + _dialog_message_key
                                48      LOAD_FAST                       1: _var_var_6
                                50      LOAD_ATTR                       4: peer
                                70      LOAD_FAST                       1: _var_var_6
                                72      LOAD_ATTR                       6: top_message
                                92      CALL                            2
                                100     CALL                            1
                                108     YIELD_VALUE                     1
                                110     RESUME                          1
                                112     POP_TOP                         
                                114     JUMP_BACKWARD                   53 (to 10)
                                116     END_FOR                         
                                118     RETURN_CONST                    0: None
                                120     CALL_INTRINSIC_1                3 (INTRINSIC_STOPITERATION_ERROR)
                                122     RERAISE                         1
                            [Exception Table]
                                6 to 120 -> 120 [0] lasti
                        0
                        -1
                    [Disassembly]
                        0       MAKE_CELL                       12: _var_var_1
                        2       RETURN_GENERATOR                
                        4       POP_TOP                         
                        6       NOP                             
                        8       NOP                             
                        10      PUSH_NULL                       
                        12      LOAD_CONST                      2: '__pyarmor_enter_16897__'
                        14      LOAD_CONST                      3: b'<COAddr>\x07\x00\x00 \x8a\x08\x00\x00\x00\x00\x00\x00\x00\x00\x00\x00\x00\x00\x00\x00'
                        16      BUILD_TUPLE                     1
                        18      CALL_FUNCTION_EX                0
                        20      POP_TOP                         
                        22      RESUME                          0
                        24      NOP                             
                        26      NOP                             
                        28      NOP                             
                        30      NOP                             
                        32      NOP                             
                        34      LOAD_GLOBAL                     1: NULL + min
                        44      LOAD_FAST                       0: self
                        46      LOAD_ATTR                       2: left
                        66      LOAD_GLOBAL                     4: _MAX_CHUNK_SIZE
                        76      CALL                            2
                        84      LOAD_FAST                       0: self
                        86      LOAD_ATTR                       6: request
                        106     STORE_ATTR                      4: limit
                        116     LOAD_FAST                       0: self
                        118     LOAD_ATTR                       11: client
                        138     LOAD_FAST                       0: self
                        140     LOAD_ATTR                       6: request
                        160     CALL                            1
                        168     GET_AWAITABLE                   0
                        170     LOAD_CONST                      0: None
                        172     SEND                            3 (to 180)
                        176     YIELD_VALUE                     3
                        178     RESUME                          3
                        180     JUMP_BACKWARD_NO_INTERRUPT      5 (to 172)
                        182     END_SEND                        
                        184     STORE_FAST                      2: _var_var_2
                        186     LOAD_GLOBAL                     13: NULL + getattr
                        196     LOAD_FAST                       2: _var_var_2
                        198     LOAD_CONST                      4: 'count'
                        200     LOAD_GLOBAL                     15: NULL + len
                        210     LOAD_FAST                       2: _var_var_2
                        212     LOAD_ATTR                       16: dialogs
                        232     CALL                            1
                        240     CALL                            3
                        248     LOAD_FAST                       0: self
                        250     STORE_ATTR                      9: total
                        260     LOAD_GLOBAL                     21: NULL + itertools
                        270     LOAD_ATTR                       22: chain
                        290     LOAD_FAST                       2: _var_var_2
                        292     LOAD_ATTR                       24: users
                        312     LOAD_FAST                       2: _var_var_2
                        314     LOAD_ATTR                       26: chats
                        334     CALL                            2
                        342     GET_ITER                        
                        344     LOAD_FAST_AND_CLEAR             3: _var_var_3
                        346     SWAP                            2
                        348     BUILD_MAP                       0
                        350     SWAP                            2
                        352     FOR_ITER                        66 (to 486)
                        356     STORE_FAST                      3: _var_var_3
                        358     LOAD_GLOBAL                     29: NULL + isinstance
                        368     LOAD_FAST                       3: _var_var_3
                        370     LOAD_GLOBAL                     30: types
                        380     LOAD_ATTR                       32: UserEmpty
                        400     LOAD_GLOBAL                     30: types
                        410     LOAD_ATTR                       34: ChatEmpty
                        430     BUILD_TUPLE                     2
                        432     CALL                            2
                        440     POP_JUMP_IF_TRUE                22 (to 486)
                        442     LOAD_GLOBAL                     37: NULL + utils
                        452     LOAD_ATTR                       38: get_peer_id
                        472     LOAD_FAST                       3: _var_var_3
                        474     CALL                            1
                        482     LOAD_FAST                       3: _var_var_3
                        484     MAP_ADD                         2
                        486     JUMP_BACKWARD                   68 (to 352)
                        488     END_FOR                         
                        490     STORE_FAST                      4: _var_var_4
                        492     STORE_FAST                      3: _var_var_3
                        494     LOAD_FAST                       0: self
                        496     LOAD_ATTR                       10: client
                        516     LOAD_ATTR                       40: _mb_entity_cache
                        536     LOAD_ATTR                       43: extend
                        556     LOAD_FAST                       2: _var_var_2
                        558     LOAD_ATTR                       24: users
                        578     LOAD_FAST                       2: _var_var_2
                        580     LOAD_ATTR                       26: chats
                        600     CALL                            2
                        608     POP_TOP                         
                        610     BUILD_MAP                       0
                        612     STORE_DEREF                     12: _var_var_1
                        614     LOAD_FAST                       2: _var_var_2
                        616     LOAD_ATTR                       44: messages
                        636     GET_ITER                        
                        638     FOR_ITER                        66 (to 772)
                        642     STORE_FAST                      5: _var_var_5
                        644     LOAD_FAST                       5: _var_var_5
                        646     LOAD_ATTR                       47: _finish_init
                        666     LOAD_FAST                       0: self
                        668     LOAD_ATTR                       10: client
                        688     LOAD_FAST                       4: _var_var_4
                        690     LOAD_CONST                      0: None
                        692     CALL                            3
                        700     POP_TOP                         
                        702     LOAD_FAST                       5: _var_var_5
                        704     LOAD_DEREF                      12: _var_var_1
                        706     LOAD_GLOBAL                     49: NULL + _dialog_message_key
                        716     LOAD_FAST                       5: _var_var_5
                        718     LOAD_ATTR                       50: peer_id
                        738     LOAD_FAST                       5: _var_var_5
                        740     LOAD_ATTR                       52: id
                        760     CALL                            2
                        768     STORE_SUBSCR                    
                        772     JUMP_BACKWARD                   68 (to 638)
                        774     END_FOR                         
                        776     LOAD_FAST                       2: _var_var_2
                        778     LOAD_ATTR                       16: dialogs
                        798     GET_ITER                        
                        800     FOR_ITER                        415 (to 1634)
                        806     STORE_FAST                      6: _var_var_6
                        808     LOAD_DEREF                      12: _var_var_1
                        810     LOAD_ATTR                       55: get
                        830     LOAD_GLOBAL                     49: NULL + _dialog_message_key
                        840     LOAD_FAST                       6: _var_var_6
                        842     LOAD_ATTR                       56: peer
                        862     LOAD_FAST                       6: _var_var_6
                        864     LOAD_ATTR                       58: top_message
                        884     CALL                            2
                        892     CALL                            1
                        900     STORE_FAST                      7: _var_var_7
                        902     LOAD_FAST                       0: self
                        904     LOAD_ATTR                       60: offset_date
                        924     POP_JUMP_IF_FALSE               59 (to 1044)
                        926     LOAD_GLOBAL                     13: NULL + getattr
                        936     LOAD_FAST                       7: _var_var_7
                        938     LOAD_CONST                      5: 'date'
                        940     LOAD_CONST                      0: None
                        942     CALL                            3
                        950     STORE_FAST                      8: _var_var_8
                        952     LOAD_FAST                       8: _var_var_8
                        954     POP_JUMP_IF_FALSE               43 (to 1042)
                        956     LOAD_FAST                       8: _var_var_8
                        958     LOAD_ATTR                       63: timestamp
                        978     CALL                            0
                        986     LOAD_FAST                       0: self
                        988     LOAD_ATTR                       60: offset_date
                        1008    LOAD_ATTR                       63: timestamp
                        1028    CALL                            0
                        1036    COMPARE_OP                      68 (>)
                        1040    POP_JUMP_IF_FALSE               1 (to 1044)
                        1042    JUMP_BACKWARD                   122 (to 800)
                        1044    LOAD_GLOBAL                     37: NULL + utils
                        1054    LOAD_ATTR                       38: get_peer_id
                        1074    LOAD_FAST                       6: _var_var_6
                        1076    LOAD_ATTR                       56: peer
                        1096    CALL                            1
                        1104    STORE_FAST                      9: _var_var_9
                        1106    LOAD_FAST                       9: _var_var_9
                        1108    LOAD_FAST                       0: self
                        1110    LOAD_ATTR                       64: seen
                        1130    CONTAINS_OP                     1 (not in)
                        1132    POP_JUMP_IF_TRUE                1 (to 1136)
                        1134    JUMP_BACKWARD                   168 (to 800)
                        1136    LOAD_FAST                       0: self
                        1138    LOAD_ATTR                       64: seen
                        1158    LOAD_ATTR                       67: add
                        1178    LOAD_FAST                       9: _var_var_9
                        1180    CALL                            1
                        1188    POP_TOP                         
                        1190    LOAD_FAST                       9: _var_var_9
                        1192    LOAD_FAST                       4: _var_var_4
                        1194    CONTAINS_OP                     1 (not in)
                        1196    POP_JUMP_IF_FALSE               1 (to 1200)
                        1198    JUMP_BACKWARD                   200 (to 800)
                        1200    LOAD_GLOBAL                     69: NULL + custom
                        1210    LOAD_ATTR                       70: Dialog
                        1230    LOAD_FAST                       0: self
                        1232    LOAD_ATTR                       10: client
                        1252    LOAD_FAST                       6: _var_var_6
                        1254    LOAD_FAST                       4: _var_var_4
                        1256    LOAD_FAST                       7: _var_var_7
                        1258    CALL                            4
                        1266    STORE_FAST                      10: _var_var_10
                        1268    LOAD_FAST                       10: _var_var_10
                        1270    LOAD_ATTR                       72: dialog
                        1290    LOAD_ATTR                       74: pts
                        1310    POP_JUMP_IF_FALSE               89 (to 1490)
                        1312    LOAD_FAST                       0: self
                        1314    LOAD_ATTR                       10: client
                        1334    LOAD_ATTR                       76: _message_box
                        1354    LOAD_ATTR                       79: try_set_channel_state
                        1374    LOAD_GLOBAL                     37: NULL + utils
                        1384    LOAD_ATTR                       38: get_peer_id
                        1404    LOAD_FAST                       6: _var_var_6
                        1406    LOAD_ATTR                       56: peer
                        1426    LOAD_CONST                      6: False
                        1428    KW_NAMES                        7: ('add_mark',)
                        1430    CALL                            2
                        1438    LOAD_FAST                       10: _var_var_10
                        1440    LOAD_ATTR                       72: dialog
                        1460    LOAD_ATTR                       74: pts
                        1480    CALL                            2
                        1488    POP_TOP                         
                        1490    LOAD_FAST                       0: self
                        1492    LOAD_ATTR                       80: ignore_migrated
                        1512    POP_JUMP_IF_FALSE               32 (to 1578)
                        1514    LOAD_GLOBAL                     13: NULL + getattr
                        1524    LOAD_FAST                       10: _var_var_10
                        1526    LOAD_ATTR                       82: entity
                        1546    PUSH_NULL                       
                        1548    LOAD_CONST                      1: '__pyarmor_assert_16896__'
                        1550    LOAD_CONST                      8: 'migrated_to'   # b'\x81\xef\x11\x14!\xfb\xaa\xd7\x1f\xc5\x19\xcf'
                        1552    CALL                            1
                        1560    LOAD_CONST                      0: None
                        1562    CALL                            3
                        1570    NOP                             
                        1572    POP_JUMP_IF_NONE                2 (to 1578)
                        1574    JUMP_BACKWARD                   389 (to 800)
                        1578    LOAD_FAST                       0: self
                        1580    LOAD_ATTR                       84: buffer
                        1600    LOAD_ATTR                       87: append
                        1620    LOAD_FAST                       10: _var_var_10
                        1622    CALL                            1
                        1630    POP_TOP                         
                        1632    JUMP_BACKWARD                   418 (to 800)
                        1636    END_FOR                         
                        1638    LOAD_FAST                       0: self
                        1640    LOAD_ATTR                       84: buffer
                        1660    POP_JUMP_IF_FALSE               80 (to 1822)
                        1662    LOAD_GLOBAL                     15: NULL + len
                        1672    LOAD_FAST                       2: _var_var_2
                        1674    LOAD_ATTR                       16: dialogs
                        1694    CALL                            1
                        1702    LOAD_FAST                       0: self
                        1704    LOAD_ATTR                       6: request
                        1724    LOAD_ATTR                       8: limit
                        1744    COMPARE_OP                      2 (<)
                        1748    POP_JUMP_IF_TRUE                36 (to 1822)
                        1750    LOAD_GLOBAL                     29: NULL + isinstance
                        1760    LOAD_FAST                       2: _var_var_2
                        1762    LOAD_GLOBAL                     30: types
                        1772    LOAD_ATTR                       44: messages
                        1792    LOAD_ATTR                       88: DialogsSlice
                        1812    CALL                            2
                        1820    POP_JUMP_IF_TRUE                11 (to 1844)
                        1822    NOP                             
                        1824    LOAD_CONST                      10: True
                        1826    NOP                             
                        1828    NOP                             
                        1830    NOP                             
                        1832    JUMP_FORWARD                    208 (to 2250)
                        1840    POP_TOP                         
                        1842    RETURN_CONST                    10: True
                        1844    LOAD_GLOBAL                     91: NULL + next
                        1854    LOAD_GLOBAL                     93: NULL + filter
                        1864    LOAD_CONST                      0: None
                        1866    LOAD_CLOSURE                    12: _var_var_1
                        1868    BUILD_TUPLE                     1
                        1870    LOAD_CONST                      11: <CODE> <genexpr>
                        1872    MAKE_FUNCTION                   8
                        1874    LOAD_GLOBAL                     95: NULL + reversed
                        1884    LOAD_FAST                       2: _var_var_2
                        1886    LOAD_ATTR                       16: dialogs
                        1906    CALL                            1
                        1914    GET_ITER                        
                        1916    CALL                            0
                        1924    CALL                            2
                        1932    LOAD_CONST                      0: None
                        1934    CALL                            2
                        1942    STORE_FAST                      11: _var_var_11
                        1944    LOAD_CONST                      10: True
                        1946    LOAD_FAST                       0: self
                        1948    LOAD_ATTR                       6: request
                        1968    STORE_ATTR                      48: exclude_pinned
                        1978    LOAD_FAST                       11: _var_var_11
                        1980    POP_JUMP_IF_FALSE               12 (to 2006)
                        1982    LOAD_FAST                       11: _var_var_11
                        1984    LOAD_ATTR                       52: id
                        2004    JUMP_FORWARD                    1 (to 2008)
                        2006    LOAD_CONST                      12: 0
                        2008    LOAD_FAST                       0: self
                        2010    LOAD_ATTR                       6: request
                        2030    STORE_ATTR                      49: offset_id
                        2040    LOAD_FAST                       11: _var_var_11
                        2042    POP_JUMP_IF_FALSE               12 (to 2068)
                        2044    LOAD_FAST                       11: _var_var_11
                        2046    LOAD_ATTR                       100: date
                        2066    JUMP_FORWARD                    1 (to 2070)
                        2068    LOAD_CONST                      0: None
                        2070    LOAD_FAST                       0: self
                        2072    LOAD_ATTR                       6: request
                        2092    STORE_ATTR                      30: offset_date
                        2102    LOAD_FAST                       0: self
                        2104    LOAD_ATTR                       84: buffer
                        2124    LOAD_CONST                      13: -1
                        2126    BINARY_SUBSCR                   
                        2130    LOAD_ATTR                       102: input_entity
                        2150    LOAD_FAST                       0: self
                        2152    LOAD_ATTR                       6: request
                        2172    STORE_ATTR                      52: offset_peer
                        2182    LOAD_CONST                      0: None
                        2184    NOP                             
                        2186    NOP                             
                        2188    NOP                             
                        2190    JUMP_FORWARD                    29 (to 2250)
                        2198    POP_TOP                         
                        2200    RETURN_CONST                    0: None
                        2202    CLEANUP_THROW                   
                        2204    JUMP_BACKWARD                   1013 (to 182)
                        2208    SWAP                            2
                        2210    POP_TOP                         
                        2212    SWAP                            2
                        2214    STORE_FAST                      3: _var_var_3
                        2216    RERAISE                         0
                        2218    PUSH_EXC_INFO                   
                        2220    PUSH_NULL                       
                        2222    LOAD_CONST                      9: '__pyarmor_exit_16898__'
                        2224    NOP                             
                        2226    LOAD_CONST                      3: b'<COAddr>\x07\x00\x00 \x8a\x08\x00\x00\x00\x00\x00\x00\x00\x00\x00\x00\x00\x00\x00\x00'
                        2228    CALL                            1
                        2236    POP_TOP                         
                        2238    RERAISE                         0
                        2240    COPY                            3
                        2242    POP_EXCEPT                      
                        2244    RERAISE                         1
                        2246    CALL_INTRINSIC_1                3 (INTRINSIC_STOPITERATION_ERROR)
                        2248    RERAISE                         1
                        2250    PUSH_NULL                       
                        2252    LOAD_CONST                      9: '__pyarmor_exit_16898__'
                        2254    LOAD_CONST                      3: b'<COAddr>\x07\x00\x00 \x8a\x08\x00\x00\x00\x00\x00\x00\x00\x00\x00\x00\x00\x00\x00\x00'
                        2256    BUILD_TUPLE                     1
                        2258    CALL_FUNCTION_EX                0
                        2260    POP_TOP                         
                        2262    RETURN_VALUE                    
                    [Exception Table]
                        6 to 32 -> 2246 [0] lasti
                        34 to 176 -> 2218 [0] 
                        176 to 178 -> 2202 [2] 
                        178 to 348 -> 2218 [0] 
                        348 to 490 -> 2208 [2] 
                        490 to 1134 -> 2218 [0] 
                        1136 to 1574 -> 2218 [0] 
                        1578 to 1822 -> 2218 [0] 
                        1824 to 1844 -> 2246 [0] lasti
                        1844 to 2182 -> 2218 [0] 
                        2182 to 2202 -> 2246 [0] lasti
                        2202 to 2204 -> 2218 [0] 
                        2208 to 2218 -> 2218 [0] 
                        2218 to 2240 -> 2240 [1] lasti
                        2240 to 2246 -> 2246 [0] lasti
                '__pyarmor_exit_16892__'
                None
            [Disassembly]
                0       NOP                             
                2       LOAD_NAME                       0: __name__
                4       STORE_NAME                      1: __module__
                6       LOAD_CONST                      0: '_DialogsIter'
                8       STORE_NAME                      2: __qualname__
                10      NOP                             
                12      PUSH_NULL                       
                14      LOAD_CONST                      2: '__pyarmor_enter_16891__'
                16      LOAD_CONST                      3: b'<COAddr>\x07\x00\x00""\x00\x00\x00\x00\x00\x00\x00\x00\x00\x00\x00\x00\x00\x00\x00'
                18      BUILD_TUPLE                     1
                20      CALL_FUNCTION_EX                0
                22      POP_TOP                         
                24      RESUME                          0
                26      NOP                             
                28      NOP                             
                30      NOP                             
                32      NOP                             
                34      NOP                             
                36      LOAD_CONST                      4: <CODE> _init
                38      MAKE_FUNCTION                   0
                40      STORE_NAME                      4: _init
                42      LOAD_CONST                      5: <CODE> _load_next_chunk
                44      MAKE_FUNCTION                   0
                46      STORE_NAME                      5: _load_next_chunk
                48      LOAD_CONST                      7: None
                50      NOP                             
                52      NOP                             
                54      NOP                             
                56      JUMP_FORWARD                    19 (to 96)
                64      POP_TOP                         
                66      RETURN_CONST                    7: None
                68      PUSH_EXC_INFO                   
                70      PUSH_NULL                       
                72      LOAD_CONST                      6: '__pyarmor_exit_16892__'
                74      NOP                             
                76      LOAD_CONST                      3: b'<COAddr>\x07\x00\x00""\x00\x00\x00\x00\x00\x00\x00\x00\x00\x00\x00\x00\x00\x00\x00'
                78      CALL                            1
                86      POP_TOP                         
                88      RERAISE                         0
                90      COPY                            3
                92      POP_EXCEPT                      
                94      RERAISE                         1
                96      PUSH_NULL                       
                98      LOAD_CONST                      6: '__pyarmor_exit_16892__'
                100     LOAD_CONST                      3: b'<COAddr>\x07\x00\x00""\x00\x00\x00\x00\x00\x00\x00\x00\x00\x00\x00\x00\x00\x00\x00'
                102     BUILD_TUPLE                     1
                104     CALL_FUNCTION_EX                0
                106     POP_TOP                         
                108     RETURN_VALUE                    
            [Exception Table]
                36 to 48 -> 68 [0] 
                68 to 90 -> 90 [1] lasti
        '_DialogsIter'
        [Code]
            File Name: <frozen multithon.client.dialogs>
            Object Name: _DraftsIter
            Qualified Name: _DraftsIter
            Arg Count: 0
            Pos Only Arg Count: 0
            KW Only Arg Count: 0
            Stack Size: 5
            Flags: 0x20000000 (CO_PYARMOR_OBFUSCATED)
            [Names]
                '__name__'
                '__module__'
                '__qualname__'
                '__assert_armored__'
                '_init'
                '_load_next_chunk'
            [Locals+Names]
            [Constants]
                '_DraftsIter'
                '__pyarmor_assert_16899__'
                '__pyarmor_enter_16900__'
                b'<COAddr>\x07\x00\x00""\x00\x00\x00\x00\x00\x00\x00\x00\x00\x00\x00\x00\x00\x00\x00'
                [Code]
                    File Name: <frozen multithon.client.dialogs>
                    Object Name: _init
                    Qualified Name: _DraftsIter._init
                    Arg Count: 2
                    Pos Only Arg Count: 0
                    KW Only Arg Count: 0
                    Stack Size: 8
                    Flags: 0x2000008B (CO_OPTIMIZED | CO_NEWLOCALS | CO_VARKEYWORDS | CO_COROUTINE | CO_PYARMOR_OBFUSCATED)
                    [Names]
                        'client'
                        'functions'
                        'messages'
                        'GetAllDraftsRequest'
                        'updates'
                        'append'
                        'types'
                        'InputDialogPeer'
                        'get_input_entity'
                        'GetPeerDialogsRequest'
                        'dialogs'
                        'itertools'
                        'chain'
                        'users'
                        'chats'
                        'utils'
                        'get_peer_id'
                        'buffer'
                        'extend'
                    [Locals+Names]
                        'self'
                        'entities'
                        'kwargs'
                        '__assert_armored__'
                        '_var_var_2'
                        '_var_var_12'
                        '_var_var_13'
                        '_var_var_14'
                        '_var_var_3'
                    [Constants]
                        None
                        '__pyarmor_assert_16902__'
                        '__pyarmor_enter_16903__'
                        b'<COAddr>\x05\x00\x00"\xb8\x02\x00\x00\x00\x00\x00\x00\x00\x00\x00\x00\x00\x00\x00\x00'
                        [Code]
                            File Name: <frozen multithon.client.dialogs>
                            Object Name: <genexpr>
                            Qualified Name: _DraftsIter._init.<locals>.<genexpr>
                            Arg Count: 1
                            Pos Only Arg Count: 0
                            KW Only Arg Count: 0
                            Stack Size: 8
                            Flags: 0x00000033 (CO_OPTIMIZED | CO_NEWLOCALS | CO_NESTED | CO_GENERATOR)
                            [Names]
                                'custom'
                                'Draft'
                                'client'
                                'utils'
                                'get_peer_id'
                                'peer'
                                'draft'
                            [Locals+Names]
                                '.0'
                                '_var_var_6'
                                'entities'
                                'self'
                            [Constants]
                                None
                            [Disassembly]
                                0       COPY_FREE_VARS                  2
                                2       RETURN_GENERATOR                
                                4       POP_TOP                         
                                6       RESUME                          0
                                8       LOAD_FAST                       0: .0
                                10      FOR_ITER                        79 (to 170)
                                14      STORE_FAST                      1: _var_var_6
                                16      LOAD_GLOBAL                     1: NULL + custom
                                26      LOAD_ATTR                       2: Draft
                                46      LOAD_DEREF                      3: self
                                48      LOAD_ATTR                       4: client
                                68      LOAD_DEREF                      2: entities
                                70      LOAD_GLOBAL                     7: NULL + utils
                                80      LOAD_ATTR                       8: get_peer_id
                                100     LOAD_FAST                       1: _var_var_6
                                102     LOAD_ATTR                       10: peer
                                122     CALL                            1
                                130     BINARY_SUBSCR                   
                                134     LOAD_FAST                       1: _var_var_6
                                136     LOAD_ATTR                       12: draft
                                156     CALL                            3
                                164     YIELD_VALUE                     1
                                166     RESUME                          1
                                168     POP_TOP                         
                                170     JUMP_BACKWARD                   81 (to 10)
                                172     END_FOR                         
                                174     RETURN_CONST                    0: None
                                176     CALL_INTRINSIC_1                3 (INTRINSIC_STOPITERATION_ERROR)
                                178     RERAISE                         1
                            [Exception Table]
                                6 to 176 -> 176 [0] lasti
                        '__pyarmor_exit_16904__'
                    [Disassembly]
                        0       MAKE_CELL                       0: self
                        2       MAKE_CELL                       1: entities
                        4       RETURN_GENERATOR                
                        6       POP_TOP                         
                        8       NOP                             
                        10      NOP                             
                        12      PUSH_NULL                       
                        14      LOAD_CONST                      2: '__pyarmor_enter_16903__'
                        16      LOAD_CONST                      3: b'<COAddr>\x05\x00\x00"\xb8\x02\x00\x00\x00\x00\x00\x00\x00\x00\x00\x00\x00\x00\x00\x00'
                        18      BUILD_TUPLE                     1
                        20      CALL_FUNCTION_EX                0
                        22      POP_TOP                         
                        24      RESUME                          0
                        26      NOP                             
                        28      NOP                             
                        30      NOP                             
                        32      NOP                             
                        34      NOP                             
                        36      LOAD_DEREF                      1: entities
                        38      POP_JUMP_IF_TRUE                66 (to 172)
                        40      LOAD_DEREF                      0: self
                        42      LOAD_ATTR                       1: client
                        62      LOAD_GLOBAL                     2: functions
                        72      LOAD_ATTR                       4: messages
                        92      LOAD_ATTR                       7: GetAllDraftsRequest
                        112     CALL                            0
                        120     CALL                            1
                        128     GET_AWAITABLE                   0
                        130     LOAD_CONST                      0: None
                        132     SEND                            3 (to 140)
                        136     YIELD_VALUE                     3
                        138     RESUME                          3
                        140     JUMP_BACKWARD_NO_INTERRUPT      5 (to 132)
                        142     END_SEND                        
                        144     STORE_FAST                      4: _var_var_2
                        146     LOAD_FAST                       4: _var_var_2
                        148     LOAD_ATTR                       8: updates
                        168     STORE_FAST                      5: _var_var_12
                        170     JUMP_FORWARD                    144 (to 460)
                        172     BUILD_LIST                      0
                        174     STORE_FAST                      6: _var_var_13
                        176     LOAD_DEREF                      1: entities
                        178     GET_ITER                        
                        180     FOR_ITER                        71 (to 324)
                        184     STORE_FAST                      7: _var_var_14
                        186     LOAD_FAST                       6: _var_var_13
                        188     LOAD_ATTR                       11: append
                        208     LOAD_GLOBAL                     13: NULL + types
                        218     LOAD_ATTR                       14: InputDialogPeer
                        238     LOAD_DEREF                      0: self
                        240     LOAD_ATTR                       0: client
                        260     LOAD_ATTR                       17: get_input_entity
                        280     LOAD_FAST                       7: _var_var_14
                        282     CALL                            1
                        290     GET_AWAITABLE                   0
                        292     LOAD_CONST                      0: None
                        294     SEND                            3 (to 302)
                        298     YIELD_VALUE                     3
                        300     RESUME                          3
                        302     JUMP_BACKWARD_NO_INTERRUPT      5 (to 294)
                        304     END_SEND                        
                        306     CALL                            1
                        314     CALL                            1
                        322     POP_TOP                         
                        324     JUMP_BACKWARD                   73 (to 180)
                        326     END_FOR                         
                        328     LOAD_DEREF                      0: self
                        330     LOAD_ATTR                       1: client
                        350     LOAD_GLOBAL                     2: functions
                        360     LOAD_ATTR                       4: messages
                        380     LOAD_ATTR                       19: GetPeerDialogsRequest
                        400     LOAD_FAST                       6: _var_var_13
                        402     CALL                            1
                        410     CALL                            1
                        418     GET_AWAITABLE                   0
                        420     LOAD_CONST                      0: None
                        422     SEND                            3 (to 430)
                        426     YIELD_VALUE                     3
                        428     RESUME                          3
                        430     JUMP_BACKWARD_NO_INTERRUPT      5 (to 422)
                        432     END_SEND                        
                        434     STORE_FAST                      4: _var_var_2
                        436     LOAD_FAST                       4: _var_var_2
                        438     LOAD_ATTR                       20: dialogs
                        458     STORE_FAST                      5: _var_var_12
                        460     LOAD_GLOBAL                     23: NULL + itertools
                        470     LOAD_ATTR                       24: chain
                        490     LOAD_FAST                       4: _var_var_2
                        492     LOAD_ATTR                       26: users
                        512     LOAD_FAST                       4: _var_var_2
                        514     LOAD_ATTR                       28: chats
                        534     CALL                            2
                        542     GET_ITER                        
                        544     LOAD_FAST_AND_CLEAR             8: _var_var_3
                        546     SWAP                            2
                        548     BUILD_MAP                       0
                        550     SWAP                            2
                        552     FOR_ITER                        24 (to 602)
                        556     STORE_FAST                      8: _var_var_3
                        558     LOAD_GLOBAL                     31: NULL + utils
                        568     LOAD_ATTR                       32: get_peer_id
                        588     LOAD_FAST                       8: _var_var_3
                        590     CALL                            1
                        598     LOAD_FAST                       8: _var_var_3
                        600     MAP_ADD                         2
                        602     JUMP_BACKWARD                   26 (to 552)
                        604     END_FOR                         
                        606     SWAP                            2
                        608     STORE_FAST                      8: _var_var_3
                        610     STORE_DEREF                     1: entities
                        612     LOAD_DEREF                      0: self
                        614     LOAD_ATTR                       34: buffer
                        634     LOAD_ATTR                       37: extend
                        654     LOAD_CLOSURE                    1: entities
                        656     LOAD_CLOSURE                    0: self
                        658     BUILD_TUPLE                     2
                        660     LOAD_CONST                      4: <CODE> <genexpr>
                        662     MAKE_FUNCTION                   8
                        664     LOAD_FAST                       5: _var_var_12
                        666     GET_ITER                        
                        668     CALL                            0
                        676     CALL                            1
                        684     POP_TOP                         
                        686     LOAD_CONST                      0: None
                        688     NOP                             
                        690     NOP                             
                        692     NOP                             
                        694     JUMP_FORWARD                    33 (to 762)
                        702     POP_TOP                         
                        704     RETURN_CONST                    0: None
                        706     CLEANUP_THROW                   
                        708     JUMP_BACKWARD                   285 (to 142)
                        712     CLEANUP_THROW                   
                        714     JUMP_BACKWARD                   206 (to 304)
                        716     CLEANUP_THROW                   
                        718     JUMP_BACKWARD                   144 (to 432)
                        720     SWAP                            2
                        722     POP_TOP                         
                        724     SWAP                            2
                        726     STORE_FAST                      8: _var_var_3
                        728     RERAISE                         0
                        730     PUSH_EXC_INFO                   
                        732     PUSH_NULL                       
                        734     LOAD_CONST                      5: '__pyarmor_exit_16904__'
                        736     NOP                             
                        738     LOAD_CONST                      3: b'<COAddr>\x05\x00\x00"\xb8\x02\x00\x00\x00\x00\x00\x00\x00\x00\x00\x00\x00\x00\x00\x00'
                        740     CALL                            1
                        748     POP_TOP                         
                        750     RERAISE                         0
                        752     COPY                            3
                        754     POP_EXCEPT                      
                        756     RERAISE                         1
                        758     CALL_INTRINSIC_1                3 (INTRINSIC_STOPITERATION_ERROR)
                        760     RERAISE                         1
                        762     PUSH_NULL                       
                        764     LOAD_CONST                      5: '__pyarmor_exit_16904__'
                        766     LOAD_CONST                      3: b'<COAddr>\x05\x00\x00"\xb8\x02\x00\x00\x00\x00\x00\x00\x00\x00\x00\x00\x00\x00\x00\x00'
                        768     BUILD_TUPLE                     1
                        770     CALL_FUNCTION_EX                0
                        772     POP_TOP                         
                        774     RETURN_VALUE                    
                    [Exception Table]
                        8 to 34 -> 758 [0] lasti
                        36 to 136 -> 730 [0] 
                        136 to 138 -> 706 [2] 
                        138 to 298 -> 730 [0] 
                        298 to 300 -> 712 [7] 
                        300 to 426 -> 730 [0] 
                        426 to 428 -> 716 [2] 
                        428 to 548 -> 730 [0] 
                        548 to 606 -> 720 [2] 
                        606 to 686 -> 730 [0] 
                        686 to 706 -> 758 [0] lasti
                        706 to 708 -> 730 [0] 
                        712 to 714 -> 730 [0] 
                        716 to 718 -> 730 [0] 
                        720 to 730 -> 730 [0] 
                        730 to 752 -> 752 [1] lasti
                        752 to 758 -> 758 [0] lasti
                [Code]
                    File Name: <frozen multithon.client.dialogs>
                    Object Name: _load_next_chunk
                    Qualified Name: _DraftsIter._load_next_chunk
                    Arg Count: 1
                    Pos Only Arg Count: 0
                    KW Only Arg Count: 0
                    Stack Size: 5
                    Flags: 0x20000083 (CO_OPTIMIZED | CO_NEWLOCALS | CO_COROUTINE | CO_PYARMOR_OBFUSCATED)
                    [Names]
                    [Locals+Names]
                        'self'
                        '__assert_armored__'
                    [Constants]
                        None
                        '__pyarmor_assert_16905__'
                        '__pyarmor_enter_16906__'
                        b'<COAddr>\x07\x00\x00\x1e\x18\x00\x00\x00\x00\x00\x00\x00\x00\x00\x00\x00\x00\x00\x00\x00'
                        '__pyarmor_exit_16907__'
                    [Disassembly]
                        0       RETURN_GENERATOR                
                        2       POP_TOP                         
                        4       NOP                             
                        6       NOP                             
                        8       PUSH_NULL                       
                        10      LOAD_CONST                      2: '__pyarmor_enter_16906__'
                        12      LOAD_CONST                      3: b'<COAddr>\x07\x00\x00\x1e\x18\x00\x00\x00\x00\x00\x00\x00\x00\x00\x00\x00\x00\x00\x00\x00'
                        14      BUILD_TUPLE                     1
                        16      CALL_FUNCTION_EX                0
                        18      POP_TOP                         
                        20      RESUME                          0
                        22      NOP                             
                        24      NOP                             
                        26      NOP                             
                        28      NOP                             
                        30      NOP                             
                        32      BUILD_LIST                      0
                        34      NOP                             
                        36      NOP                             
                        38      NOP                             
                        40      JUMP_FORWARD                    22 (to 86)
                        42      CALL                            1
                        50      POP_TOP                         
                        52      RETURN_VALUE                    
                        54      PUSH_EXC_INFO                   
                        56      PUSH_NULL                       
                        58      LOAD_CONST                      4: '__pyarmor_exit_16907__'
                        60      NOP                             
                        62      LOAD_CONST                      3: b'<COAddr>\x07\x00\x00\x1e\x18\x00\x00\x00\x00\x00\x00\x00\x00\x00\x00\x00\x00\x00\x00\x00'
                        64      CALL                            1
                        72      POP_TOP                         
                        74      RERAISE                         0
                        76      COPY                            3
                        78      POP_EXCEPT                      
                        80      RERAISE                         1
                        82      CALL_INTRINSIC_1                3 (INTRINSIC_STOPITERATION_ERROR)
                        84      RERAISE                         1
                        86      PUSH_NULL                       
                        88      LOAD_CONST                      4: '__pyarmor_exit_16907__'
                        90      LOAD_CONST                      3: b'<COAddr>\x07\x00\x00\x1e\x18\x00\x00\x00\x00\x00\x00\x00\x00\x00\x00\x00\x00\x00\x00\x00'
                        92      BUILD_TUPLE                     1
                        94      CALL_FUNCTION_EX                0
                        96      POP_TOP                         
                        98      RETURN_VALUE                    
                    [Exception Table]
                        4 to 30 -> 82 [0] lasti
                        32 to 34 -> 54 [0] 
                        34 to 54 -> 82 [0] lasti
                        54 to 76 -> 76 [1] lasti
                        76 to 82 -> 82 [0] lasti
                '__pyarmor_exit_16901__'
                None
            [Disassembly]
                0       NOP                             
                2       LOAD_NAME                       0: __name__
                4       STORE_NAME                      1: __module__
                6       LOAD_CONST                      0: '_DraftsIter'
                8       STORE_NAME                      2: __qualname__
                10      NOP                             
                12      PUSH_NULL                       
                14      LOAD_CONST                      2: '__pyarmor_enter_16900__'
                16      LOAD_CONST                      3: b'<COAddr>\x07\x00\x00""\x00\x00\x00\x00\x00\x00\x00\x00\x00\x00\x00\x00\x00\x00\x00'
                18      BUILD_TUPLE                     1
                20      CALL_FUNCTION_EX                0
                22      POP_TOP                         
                24      RESUME                          0
                26      NOP                             
                28      NOP                             
                30      NOP                             
                32      NOP                             
                34      NOP                             
                36      LOAD_CONST                      4: <CODE> _init
                38      MAKE_FUNCTION                   0
                40      STORE_NAME                      4: _init
                42      LOAD_CONST                      5: <CODE> _load_next_chunk
                44      MAKE_FUNCTION                   0
                46      STORE_NAME                      5: _load_next_chunk
                48      LOAD_CONST                      7: None
                50      NOP                             
                52      NOP                             
                54      NOP                             
                56      JUMP_FORWARD                    19 (to 96)
                64      POP_TOP                         
                66      RETURN_CONST                    7: None
                68      PUSH_EXC_INFO                   
                70      PUSH_NULL                       
                72      LOAD_CONST                      6: '__pyarmor_exit_16901__'
                74      NOP                             
                76      LOAD_CONST                      3: b'<COAddr>\x07\x00\x00""\x00\x00\x00\x00\x00\x00\x00\x00\x00\x00\x00\x00\x00\x00\x00'
                78      CALL                            1
                86      POP_TOP                         
                88      RERAISE                         0
                90      COPY                            3
                92      POP_EXCEPT                      
                94      RERAISE                         1
                96      PUSH_NULL                       
                98      LOAD_CONST                      6: '__pyarmor_exit_16901__'
                100     LOAD_CONST                      3: b'<COAddr>\x07\x00\x00""\x00\x00\x00\x00\x00\x00\x00\x00\x00\x00\x00\x00\x00\x00\x00'
                102     BUILD_TUPLE                     1
                104     CALL_FUNCTION_EX                0
                106     POP_TOP                         
                108     RETURN_VALUE                    
            [Exception Table]
                36 to 48 -> 68 [0] 
                68 to 90 -> 90 [1] lasti
        '_DraftsIter'
        [Code]
            File Name: <frozen multithon.client.dialogs>
            Object Name: DialogMethods
            Qualified Name: DialogMethods
            Arg Count: 0
            Pos Only Arg Count: 0
            KW Only Arg Count: 0
            Stack Size: 22
            Flags: 0x20000000 (CO_PYARMOR_OBFUSCATED)
            [Names]
                '__name__'
                '__module__'
                '__qualname__'
                '__assert_armored__'
                'types'
                'InputPeerEmpty'
                'float'
                'int'
                'bool'
                '_DialogsIter'
                'iter_dialogs'
                'get_dialogs'
                'inspect'
                'signature'
                '__signature__'
                '_DraftsIter'
                'iter_drafts'
                'get_drafts'
                'typing'
                'Union'
                'Sequence'
                'Updates'
                'edit_folder'
                'delete_dialog'
                'custom'
                'Conversation'
                'conversation'
            [Locals+Names]
            [Constants]
                'DialogMethods'
                '__pyarmor_assert_16908__'
                '__pyarmor_enter_16909__'
                b'<COAddr>\x07\x00\x00"|\x02\x00\x00\x00\x00\x00\x00\x00\x00\x00\x00\x00\x00\x00\x00'
                None
                0
                False
                (
                    'offset_date'
                    'offset_id'
                    'offset_peer'
                    'ignore_pinned'
                    'ignore_migrated'
                    'folder'
                    'archived'
                )
                'self'
                'TelegramClient'   # b'\x81\xd6\x1d\x1f6\xfd\xac\xd3\x16\xd9\x01\xc9i\xe2\xec'
                'limit'
                'offset_date'
                'hints.DateLike'   # b"\x81\xea\x11\x1d'\xe9\xf0\xf6\x1a\xee\x08\xece\xe7\xfd"
                'offset_id'
                'offset_peer'
                'hints.EntityLike'   # b"\x81\xea\x11\x1d'\xe9\xf0\xf7\x15\xee\x04\xd4u\xc0\xf1\x8e\n"
                'ignore_pinned'
                'ignore_migrated'
                'folder'
                'archived'
                'return'
                [Code]
                    File Name: <frozen multithon.client.dialogs>
                    Object Name: iter_dialogs
                    Qualified Name: DialogMethods.iter_dialogs
                    Arg Count: 2
                    Pos Only Arg Count: 0
                    KW Only Arg Count: 7
                    Stack Size: 10
                    Flags: 0x20000003 (CO_OPTIMIZED | CO_NEWLOCALS | CO_PYARMOR_OBFUSCATED)
                    [Names]
                        '_DialogsIter'
                    [Locals+Names]
                        'self'
                        'limit'
                        'offset_date'
                        'offset_id'
                        'offset_peer'
                        'ignore_pinned'
                        'ignore_migrated'
                        'folder'
                        'archived'
                        '__assert_armored__'
                    [Constants]
                        "\n        Iterator over the dialogs (open conversations/subscribed channels).\n\n        The order is the same as the one seen in official applications\n        (first pinned, them from those with the most recent message to\n        those with the oldest message).\n\n        Arguments\n            limit (`int` | `None`):\n                How many dialogs to be retrieved as maximum. Can be set to\n                `None` to retrieve all dialogs. Note that this may take\n                whole minutes if you have hundreds of dialogs, as Telegram\n                will tell the library to slow down through a\n                ``FloodWaitError``.\n\n            offset_date (`datetime`, optional):\n                The offset date to be used.\n\n            offset_id (`int`, optional):\n                The message ID to be used as an offset.\n\n            offset_peer (:tl:`InputPeer`, optional):\n                The peer to be used as an offset.\n\n            ignore_pinned (`bool`, optional):\n                Whether pinned dialogs should be ignored or not.\n                When set to `True`, these won't be yielded at all.\n\n            ignore_migrated (`bool`, optional):\n                Whether :tl:`Chat` that have ``migrated_to`` a :tl:`Channel`\n                should be included or not. By default all the chats in your\n                dialogs are returned, but setting this to `True` will ignore\n                (i.e. skip) them in the same way official applications do.\n\n            folder (`int`, optional):\n                The folder from which the dialogs should be retrieved.\n\n                If left unspecified, all dialogs (including those from\n                folders) will be returned.\n\n                If set to ``0``, all dialogs that don't belong to any\n                folder will be returned.\n\n                If set to a folder number like ``1``, only those from\n                said folder will be returned.\n\n                By default Telegram assigns the folder ID ``1`` to\n                archived chats, so you should use that if you need\n                to fetch the archived dialogs.\n\n            archived (`bool`, optional):\n                Alias for `folder`. If unspecified, all will be returned,\n                `False` implies ``folder=0`` and `True` implies ``folder=1``.\n        Yields\n            Instances of `Dialog <telethon.tl.custom.dialog.Dialog>`.\n\n        Example\n            .. code-block:: python\n\n                # Print all dialog IDs and the title, nicely formatted\n                async for dialog in client.iter_dialogs():\n                    print('{:>14}: {}'.format(dialog.id, dialog.title))\n        "
                        '__pyarmor_assert_16911__'
                        '__pyarmor_enter_16912__'
                        b'<COAddr>\x05\x00\x00\x1aJ\x00\x00\x00\x00\x00\x00\x00\x00\x00\x00\x00\x00\x00\x00\x00'
                        1
                        0
                        (
                            'offset_date'
                            'offset_id'
                            'offset_peer'
                            'ignore_pinned'
                            'ignore_migrated'
                            'folder'
                        )
                        '__pyarmor_exit_16913__'
                    [Disassembly]
                        0       NOP                             
                        2       NOP                             
                        4       PUSH_NULL                       
                        6       LOAD_CONST                      2: '__pyarmor_enter_16912__'
                        8       LOAD_CONST                      3: b'<COAddr>\x05\x00\x00\x1aJ\x00\x00\x00\x00\x00\x00\x00\x00\x00\x00\x00\x00\x00\x00\x00'
                        10      BUILD_TUPLE                     1
                        12      CALL_FUNCTION_EX                0
                        14      POP_TOP                         
                        16      RESUME                          0
                        18      NOP                             
                        20      NOP                             
                        22      NOP                             
                        24      NOP                             
                        26      NOP                             
                        28      LOAD_FAST                       8: archived
                        30      POP_JUMP_IF_NONE                6 (to 44)
                        32      LOAD_FAST                       8: archived
                        34      POP_JUMP_IF_FALSE               2 (to 40)
                        36      LOAD_CONST                      4: 1
                        38      JUMP_FORWARD                    1 (to 42)
                        40      LOAD_CONST                      5: 0
                        42      STORE_FAST                      7: folder
                        44      LOAD_GLOBAL                     1: NULL + _DialogsIter
                        54      LOAD_FAST                       0: self
                        56      LOAD_FAST                       1: limit
                        58      LOAD_FAST                       2: offset_date
                        60      LOAD_FAST                       3: offset_id
                        62      LOAD_FAST                       4: offset_peer
                        64      LOAD_FAST                       5: ignore_pinned
                        66      LOAD_FAST                       6: ignore_migrated
                        68      LOAD_FAST                       7: folder
                        70      KW_NAMES                        6: ('offset_date', 'offset_id', 'offset_peer', 'ignore_pinned', 'ignore_migrated', 'folder')
                        72      CALL                            8
                        80      NOP                             
                        82      NOP                             
                        84      NOP                             
                        86      JUMP_FORWARD                    20 (to 128)
                        88      CALL                            1
                        96      POP_TOP                         
                        98      RETURN_VALUE                    
                        100     PUSH_EXC_INFO                   
                        102     PUSH_NULL                       
                        104     LOAD_CONST                      7: '__pyarmor_exit_16913__'
                        106     NOP                             
                        108     LOAD_CONST                      3: b'<COAddr>\x05\x00\x00\x1aJ\x00\x00\x00\x00\x00\x00\x00\x00\x00\x00\x00\x00\x00\x00\x00'
                        110     CALL                            1
                        118     POP_TOP                         
                        120     RERAISE                         0
                        122     COPY                            3
                        124     POP_EXCEPT                      
                        126     RERAISE                         1
                        128     PUSH_NULL                       
                        130     LOAD_CONST                      7: '__pyarmor_exit_16913__'
                        132     LOAD_CONST                      3: b'<COAddr>\x05\x00\x00\x1aJ\x00\x00\x00\x00\x00\x00\x00\x00\x00\x00\x00\x00\x00\x00\x00'
                        134     BUILD_TUPLE                     1
                        136     CALL_FUNCTION_EX                0
                        138     POP_TOP                         
                        140     RETURN_VALUE                    
                    [Exception Table]
                        28 to 80 -> 100 [0] 
                        100 to 122 -> 122 [1] lasti
                'hints.TotalList'   # b"\x81\xea\x11\x1d'\xe9\xf0\xe6\x14\xee\x0c\xcc@\xe5\xeb\x91"
                [Code]
                    File Name: <frozen multithon.client.dialogs>
                    Object Name: get_dialogs
                    Qualified Name: DialogMethods.get_dialogs
                    Arg Count: 1
                    Pos Only Arg Count: 0
                    KW Only Arg Count: 0
                    Stack Size: 5
                    Flags: 0x2000008F (CO_OPTIMIZED | CO_NEWLOCALS | CO_VARARGS | CO_VARKEYWORDS | CO_COROUTINE | CO_PYARMOR_OBFUSCATED)
                    [Names]
                        'iter_dialogs'
                        'collect'
                    [Locals+Names]
                        'self'
                        'args'
                        'kwargs'
                        '__assert_armored__'
                    [Constants]
                        "\n        Same as `iter_dialogs()`, but returns a\n        `TotalList <telethon.helpers.TotalList>` instead.\n\n        Example\n            .. code-block:: python\n\n                # Get all open conversation, print the title of the first\n                dialogs = await client.get_dialogs()\n                first = dialogs[0]\n                print(first.title)\n\n                # Use the dialog somewhere else\n                await client.send_message(first, 'hi')\n\n                # Getting only non-archived dialogs (both equivalent)\n                non_archived = await client.get_dialogs(folder=0)\n                non_archived = await client.get_dialogs(archived=False)\n\n                # Getting only archived dialogs (both equivalent)\n                archived = await client.get_dialogs(folder=1)\n                archived = await client.get_dialogs(archived=True)\n        "
                        '__pyarmor_assert_16914__'
                        '__pyarmor_enter_16915__'
                        b'<COAddr>\x07\x00\x00\x1eh\x00\x00\x00\x00\x00\x00\x00\x00\x00\x00\x00\x00\x00\x00\x00'
                        None
                        '__pyarmor_exit_16916__'
                    [Disassembly]
                        0       RETURN_GENERATOR                
                        2       POP_TOP                         
                        4       NOP                             
                        6       NOP                             
                        8       PUSH_NULL                       
                        10      LOAD_CONST                      2: '__pyarmor_enter_16915__'
                        12      LOAD_CONST                      3: b'<COAddr>\x07\x00\x00\x1eh\x00\x00\x00\x00\x00\x00\x00\x00\x00\x00\x00\x00\x00\x00\x00'
                        14      BUILD_TUPLE                     1
                        16      CALL_FUNCTION_EX                0
                        18      POP_TOP                         
                        20      RESUME                          0
                        22      NOP                             
                        24      NOP                             
                        26      NOP                             
                        28      NOP                             
                        30      NOP                             
                        32      PUSH_NULL                       
                        34      LOAD_FAST                       0: self
                        36      LOAD_ATTR                       0: iter_dialogs
                        56      LOAD_FAST                       1: args
                        58      BUILD_MAP                       0
                        60      LOAD_FAST                       2: kwargs
                        62      DICT_MERGE                      1
                        64      CALL_FUNCTION_EX                1
                        66      LOAD_ATTR                       3: collect
                        86      CALL                            0
                        94      GET_AWAITABLE                   0
                        96      LOAD_CONST                      4: None
                        98      SEND                            3 (to 106)
                        102     YIELD_VALUE                     3
                        104     RESUME                          3
                        106     JUMP_BACKWARD_NO_INTERRUPT      5 (to 98)
                        108     END_SEND                        
                        110     NOP                             
                        112     NOP                             
                        114     NOP                             
                        116     JUMP_FORWARD                    24 (to 166)
                        118     CALL                            1
                        126     POP_TOP                         
                        128     RETURN_VALUE                    
                        130     CLEANUP_THROW                   
                        132     JUMP_BACKWARD                   13 (to 108)
                        134     PUSH_EXC_INFO                   
                        136     PUSH_NULL                       
                        138     LOAD_CONST                      5: '__pyarmor_exit_16916__'
                        140     NOP                             
                        142     LOAD_CONST                      3: b'<COAddr>\x07\x00\x00\x1eh\x00\x00\x00\x00\x00\x00\x00\x00\x00\x00\x00\x00\x00\x00\x00'
                        144     CALL                            1
                        152     POP_TOP                         
                        154     RERAISE                         0
                        156     COPY                            3
                        158     POP_EXCEPT                      
                        160     RERAISE                         1
                        162     CALL_INTRINSIC_1                3 (INTRINSIC_STOPITERATION_ERROR)
                        164     RERAISE                         1
                        166     PUSH_NULL                       
                        168     LOAD_CONST                      5: '__pyarmor_exit_16916__'
                        170     LOAD_CONST                      3: b'<COAddr>\x07\x00\x00\x1eh\x00\x00\x00\x00\x00\x00\x00\x00\x00\x00\x00\x00\x00\x00\x00'
                        172     BUILD_TUPLE                     1
                        174     CALL_FUNCTION_EX                0
                        176     POP_TOP                         
                        178     RETURN_VALUE                    
                    [Exception Table]
                        4 to 30 -> 162 [0] lasti
                        32 to 102 -> 134 [0] 
                        102 to 104 -> 130 [2] 
                        104 to 110 -> 134 [0] 
                        110 to 130 -> 162 [0] lasti
                        130 to 132 -> 134 [0] 
                        134 to 156 -> 156 [1] lasti
                        156 to 162 -> 162 [0] lasti
                'entity'
                'hints.EntitiesLike'   # b"\x81\xea\x11\x1d'\xe9\xf0\xf7\x15\xee\x04\xd4e\xe9\xeb\xa9\x06V\xbe"
                [Code]
                    File Name: <frozen multithon.client.dialogs>
                    Object Name: iter_drafts
                    Qualified Name: DialogMethods.iter_drafts
                    Arg Count: 2
                    Pos Only Arg Count: 0
                    KW Only Arg Count: 0
                    Stack Size: 5
                    Flags: 0x20000003 (CO_OPTIMIZED | CO_NEWLOCALS | CO_PYARMOR_OBFUSCATED)
                    [Names]
                        'utils'
                        'is_list_like'
                        '_DraftsIter'
                    [Locals+Names]
                        'self'
                        'entity'
                        '__assert_armored__'
                    [Constants]
                        "\n        Iterator over draft messages.\n\n        The order is unspecified.\n\n        Arguments\n            entity (`hints.EntitiesLike`, optional):\n                The entity or entities for which to fetch the draft messages.\n                If left unspecified, all draft messages will be returned.\n\n        Yields\n            Instances of `Draft <telethon.tl.custom.draft.Draft>`.\n\n        Example\n            .. code-block:: python\n\n                # Clear all drafts\n                async for draft in client.get_drafts():\n                    await draft.delete()\n\n                # Getting the drafts with 'bot1' and 'bot2'\n                async for draft in client.iter_drafts(['bot1', 'bot2']):\n                    print(draft.text)\n        "
                        '__pyarmor_assert_16917__'
                        '__pyarmor_enter_16918__'
                        b'<COAddr>\x05\x00\x00\x1ad\x00\x00\x00\x00\x00\x00\x00\x00\x00\x00\x00\x00\x00\x00\x00'
                        None
                        (
                            'entities'
                        )
                        '__pyarmor_exit_16919__'
                    [Disassembly]
                        0       NOP                             
                        2       NOP                             
                        4       PUSH_NULL                       
                        6       LOAD_CONST                      2: '__pyarmor_enter_16918__'
                        8       LOAD_CONST                      3: b'<COAddr>\x05\x00\x00\x1ad\x00\x00\x00\x00\x00\x00\x00\x00\x00\x00\x00\x00\x00\x00\x00'
                        10      BUILD_TUPLE                     1
                        12      CALL_FUNCTION_EX                0
                        14      POP_TOP                         
                        16      RESUME                          0
                        18      NOP                             
                        20      NOP                             
                        22      NOP                             
                        24      NOP                             
                        26      NOP                             
                        28      LOAD_FAST                       1: entity
                        30      POP_JUMP_IF_FALSE               24 (to 80)
                        32      LOAD_GLOBAL                     1: NULL + utils
                        42      LOAD_ATTR                       2: is_list_like
                        62      LOAD_FAST                       1: entity
                        64      CALL                            1
                        72      POP_JUMP_IF_TRUE                3 (to 80)
                        74      LOAD_FAST                       1: entity
                        76      BUILD_TUPLE                     1
                        78      STORE_FAST                      1: entity
                        80      LOAD_GLOBAL                     5: NULL + _DraftsIter
                        90      LOAD_FAST                       0: self
                        92      LOAD_CONST                      4: None
                        94      LOAD_FAST                       1: entity
                        96      KW_NAMES                        5: ('entities',)
                        98      CALL                            3
                        106     NOP                             
                        108     NOP                             
                        110     NOP                             
                        112     JUMP_FORWARD                    20 (to 154)
                        114     CALL                            1
                        122     POP_TOP                         
                        124     RETURN_VALUE                    
                        126     PUSH_EXC_INFO                   
                        128     PUSH_NULL                       
                        130     LOAD_CONST                      6: '__pyarmor_exit_16919__'
                        132     NOP                             
                        134     LOAD_CONST                      3: b'<COAddr>\x05\x00\x00\x1ad\x00\x00\x00\x00\x00\x00\x00\x00\x00\x00\x00\x00\x00\x00\x00'
                        136     CALL                            1
                        144     POP_TOP                         
                        146     RERAISE                         0
                        148     COPY                            3
                        150     POP_EXCEPT                      
                        152     RERAISE                         1
                        154     PUSH_NULL                       
                        156     LOAD_CONST                      6: '__pyarmor_exit_16919__'
                        158     LOAD_CONST                      3: b'<COAddr>\x05\x00\x00\x1ad\x00\x00\x00\x00\x00\x00\x00\x00\x00\x00\x00\x00\x00\x00\x00'
                        160     BUILD_TUPLE                     1
                        162     CALL_FUNCTION_EX                0
                        164     POP_TOP                         
                        166     RETURN_VALUE                    
                    [Exception Table]
                        28 to 106 -> 126 [0] 
                        126 to 148 -> 148 [1] lasti
                [Code]
                    File Name: <frozen multithon.client.dialogs>
                    Object Name: get_drafts
                    Qualified Name: DialogMethods.get_drafts
                    Arg Count: 2
                    Pos Only Arg Count: 0
                    KW Only Arg Count: 0
                    Stack Size: 5
                    Flags: 0x20000083 (CO_OPTIMIZED | CO_NEWLOCALS | CO_COROUTINE | CO_PYARMOR_OBFUSCATED)
                    [Names]
                        'iter_drafts'
                        'collect'
                        'utils'
                        'is_list_like'
                    [Locals+Names]
                        'self'
                        'entity'
                        '__assert_armored__'
                        '_var_var_12'
                    [Constants]
                        "\n        Same as `iter_drafts()`, but returns a list instead.\n\n        Example\n            .. code-block:: python\n\n                # Get drafts, print the text of the first\n                drafts = await client.get_drafts()\n                print(drafts[0].text)\n\n                # Get the draft in your chat\n                draft = await client.get_drafts('me')\n                print(drafts.text)\n        "
                        '__pyarmor_assert_16920__'
                        '__pyarmor_enter_16921__'
                        b'<COAddr>\x05\x00\x00\x1e\xb4\x00\x00\x00\x00\x00\x00\x00\x00\x00\x00\x00\x00\x00\x00\x00'
                        None
                        '__pyarmor_exit_16922__'
                        0
                    [Disassembly]
                        0       RETURN_GENERATOR                
                        2       POP_TOP                         
                        4       NOP                             
                        6       NOP                             
                        8       PUSH_NULL                       
                        10      LOAD_CONST                      2: '__pyarmor_enter_16921__'
                        12      LOAD_CONST                      3: b'<COAddr>\x05\x00\x00\x1e\xb4\x00\x00\x00\x00\x00\x00\x00\x00\x00\x00\x00\x00\x00\x00\x00'
                        14      BUILD_TUPLE                     1
                        16      CALL_FUNCTION_EX                0
                        18      POP_TOP                         
                        20      RESUME                          0
                        22      NOP                             
                        24      NOP                             
                        26      NOP                             
                        28      NOP                             
                        30      NOP                             
                        32      LOAD_FAST                       0: self
                        34      LOAD_ATTR                       1: iter_drafts
                        54      LOAD_FAST                       1: entity
                        56      CALL                            1
                        64      LOAD_ATTR                       3: collect
                        84      CALL                            0
                        92      GET_AWAITABLE                   0
                        94      LOAD_CONST                      4: None
                        96      SEND                            3 (to 104)
                        100     YIELD_VALUE                     3
                        102     RESUME                          3
                        104     JUMP_BACKWARD_NO_INTERRUPT      5 (to 96)
                        106     END_SEND                        
                        108     STORE_FAST                      3: _var_var_12
                        110     LOAD_FAST                       1: entity
                        112     POP_JUMP_IF_FALSE               21 (to 156)
                        114     LOAD_GLOBAL                     5: NULL + utils
                        124     LOAD_ATTR                       6: is_list_like
                        144     LOAD_FAST                       1: entity
                        146     CALL                            1
                        154     POP_JUMP_IF_FALSE               11 (to 178)
                        156     LOAD_FAST                       3: _var_var_12
                        158     NOP                             
                        160     NOP                             
                        162     NOP                             
                        164     JUMP_FORWARD                    38 (to 242)
                        166     CALL                            1
                        174     POP_TOP                         
                        176     RETURN_VALUE                    
                        178     LOAD_FAST                       3: _var_var_12
                        180     LOAD_CONST                      6: 0
                        182     BINARY_SUBSCR                   
                        186     NOP                             
                        188     NOP                             
                        190     NOP                             
                        192     JUMP_FORWARD                    24 (to 242)
                        194     CALL                            1
                        202     POP_TOP                         
                        204     RETURN_VALUE                    
                        206     CLEANUP_THROW                   
                        208     JUMP_BACKWARD                   52 (to 106)
                        210     PUSH_EXC_INFO                   
                        212     PUSH_NULL                       
                        214     LOAD_CONST                      5: '__pyarmor_exit_16922__'
                        216     NOP                             
                        218     LOAD_CONST                      3: b'<COAddr>\x05\x00\x00\x1e\xb4\x00\x00\x00\x00\x00\x00\x00\x00\x00\x00\x00\x00\x00\x00\x00'
                        220     CALL                            1
                        228     POP_TOP                         
                        230     RERAISE                         0
                        232     COPY                            3
                        234     POP_EXCEPT                      
                        236     RERAISE                         1
                        238     CALL_INTRINSIC_1                3 (INTRINSIC_STOPITERATION_ERROR)
                        240     RERAISE                         1
                        242     PUSH_NULL                       
                        244     LOAD_CONST                      5: '__pyarmor_exit_16922__'
                        246     LOAD_CONST                      3: b'<COAddr>\x05\x00\x00\x1e\xb4\x00\x00\x00\x00\x00\x00\x00\x00\x00\x00\x00\x00\x00\x00\x00'
                        248     BUILD_TUPLE                     1
                        250     CALL_FUNCTION_EX                0
                        252     POP_TOP                         
                        254     RETURN_VALUE                    
                    [Exception Table]
                        4 to 30 -> 238 [0] lasti
                        32 to 100 -> 210 [0] 
                        100 to 102 -> 206 [2] 
                        102 to 158 -> 210 [0] 
                        158 to 178 -> 238 [0] lasti
                        178 to 186 -> 210 [0] 
                        186 to 206 -> 238 [0] lasti
                        206 to 208 -> 210 [0] 
                        210 to 232 -> 232 [1] lasti
                        232 to 238 -> 238 [0] lasti
                (
                    'unpack'
                )
                [Code]
                    File Name: <frozen multithon.client.dialogs>
                    Object Name: edit_folder
                    Qualified Name: DialogMethods.edit_folder
                    Arg Count: 3
                    Pos Only Arg Count: 0
                    KW Only Arg Count: 1
                    Stack Size: 12
                    Flags: 0x20000083 (CO_OPTIMIZED | CO_NEWLOCALS | CO_COROUTINE | CO_PYARMOR_OBFUSCATED)
                    [Names]
                        'ValueError'
                        'functions'
                        'folders'
                        'DeleteFolderRequest'
                        'utils'
                        'is_list_like'
                        'get_input_entity'
                        'asyncio'
                        'gather'
                        'len'
                        'EditPeerFoldersRequest'
                        'zip'
                        'types'
                        'InputFolderPeer'
                    [Locals+Names]
                        'self'
                        'entity'
                        'folder'
                        'unpack'
                        '__assert_armored__'
                        '_var_var_4'
                        '_var_var_3'
                        '_var_var_15'
                    [Constants]
                        '\n        Edits the folder used by one or more dialogs to archive them.\n\n        Arguments\n            entity (entities):\n                The entity or list of entities to move to the desired\n                archive folder.\n\n            folder (`int`):\n                The folder to which the dialog should be archived to.\n\n                If you want to "archive" a dialog, use ``folder=1``.\n\n                If you want to "un-archive" it, use ``folder=0``.\n\n                You may also pass a list with the same length as\n                `entities` if you want to control where each entity\n                will go.\n\n            unpack (`int`, optional):\n                If you want to unpack an archived folder, set this\n                parameter to the folder number that you want to\n                delete.\n\n                When you unpack a folder, all the dialogs inside are\n                moved to the folder number 0.\n\n                You can only use this parameter if the other two\n                are not set.\n\n        Returns\n            The :tl:`Updates` object that the request produces.\n\n        Example\n            .. code-block:: python\n\n                # Archiving the first 5 dialogs\n                dialogs = await client.get_dialogs(5)\n                await client.edit_folder(dialogs, 1)\n\n                # Un-archiving the third dialog (archiving to folder 0)\n                await client.edit_folder(dialog[2], 0)\n\n                # Moving the first dialog to folder 0 and the second to 1\n                dialogs = await client.get_dialogs(2)\n                await client.edit_folder(dialogs, [0, 1])\n\n                # Un-archiving all dialogs\n                await client.edit_folder(unpack=1)\n        '
                        '__pyarmor_assert_16923__'
                        '__pyarmor_enter_16924__'
                        b'<COAddr>\x05\x00\x00 \xfc\x02\x00\x00\x00\x00\x00\x00\x00\x00\x00\x00\x00\x00\x00\x00'
                        None
                        'You can only set either entities or unpack, not both'   # b'\x81\xdb\x17\x06s\xf9\xbf\xdc[\xf5\x03\xccu\xac\xeb\x80\x1b\x1d\xbe\xae\xbe\xc3K\xdeEj\xadH\t\xa5\x17\xe0)\x12/\x1f\xd8\xdf\xba>\x19\xea\xf3\x11\x9d\xd6\x00Sw\xefY\xef\x8f'
                        (
                            'folder_id'
                        )
                        '__pyarmor_exit_16925__'
                        [Code]
                            File Name: <frozen multithon.client.dialogs>
                            Object Name: <genexpr>
                            Qualified Name: DialogMethods.edit_folder.<locals>.<genexpr>
                            Arg Count: 1
                            Pos Only Arg Count: 0
                            KW Only Arg Count: 0
                            Stack Size: 4
                            Flags: 0x00000033 (CO_OPTIMIZED | CO_NEWLOCALS | CO_NESTED | CO_GENERATOR)
                            [Names]
                                'get_input_entity'
                            [Locals+Names]
                                '.0'
                                '_var_var_3'
                                'self'
                            [Constants]
                                None
                            [Disassembly]
                                0       COPY_FREE_VARS                  1
                                2       RETURN_GENERATOR                
                                4       POP_TOP                         
                                6       RESUME                          0
                                8       LOAD_FAST                       0: .0
                                10      FOR_ITER                        21 (to 54)
                                14      STORE_FAST                      1: _var_var_3
                                16      LOAD_DEREF                      2: self
                                18      LOAD_ATTR                       1: get_input_entity
                                38      LOAD_FAST                       1: _var_var_3
                                40      CALL                            1
                                48      YIELD_VALUE                     1
                                50      RESUME                          1
                                52      POP_TOP                         
                                54      JUMP_BACKWARD                   23 (to 10)
                                56      END_FOR                         
                                58      RETURN_CONST                    0: None
                                60      CALL_INTRINSIC_1                3 (INTRINSIC_STOPITERATION_ERROR)
                                62      RERAISE                         1
                            [Exception Table]
                                6 to 60 -> 60 [0] lasti
                        'You must specify a folder'   # b'\x81\xdb\x17\x06s\xf7\xab\xc1\x0f\xba\x1e\xd0i\xef\xf1\x83\x16\x1d\xba\xe7\xac\xc4B\xc8\x00}'
                        'Number of folders does not match number of entities'   # b'\x81\xcc\r\x1e1\xff\xac\x92\x14\xfcM\xc6c\xe0\xfc\x80\x1dN\xfb\xa3\xa5\xce]\x8c\x0b`\xb7\x1c\r\xb0\n\xe62\x12.\x18\x95\xc8\xb1<X\xe6\xfe\x1d\xd8\xd6\x1bN#\xe4S\xe8'
                    [Disassembly]
                        0       MAKE_CELL                       0: self
                        2       RETURN_GENERATOR                
                        4       POP_TOP                         
                        6       NOP                             
                        8       NOP                             
                        10      PUSH_NULL                       
                        12      LOAD_CONST                      2: '__pyarmor_enter_16924__'
                        14      LOAD_CONST                      3: b'<COAddr>\x05\x00\x00 \xfc\x02\x00\x00\x00\x00\x00\x00\x00\x00\x00\x00\x00\x00\x00\x00'
                        16      BUILD_TUPLE                     1
                        18      CALL_FUNCTION_EX                0
                        20      POP_TOP                         
                        22      RESUME                          0
                        24      NOP                             
                        26      NOP                             
                        28      NOP                             
                        30      NOP                             
                        32      NOP                             
                        34      LOAD_FAST                       1: entity
                        36      LOAD_CONST                      4: None
                        38      IS_OP                           0 (is)
                        40      LOAD_FAST                       3: unpack
                        42      LOAD_CONST                      4: None
                        44      IS_OP                           0 (is)
                        46      COMPARE_OP                      40 (==)
                        50      POP_JUMP_IF_FALSE               17 (to 86)
                        52      LOAD_GLOBAL                     1: NULL + ValueError
                        62      PUSH_NULL                       
                        64      LOAD_CONST                      1: '__pyarmor_assert_16923__'
                        66      LOAD_CONST                      5: 'You can only set either entities or unpack, not both'   # b'\x81\xdb\x17\x06s\xf9\xbf\xdc[\xf5\x03\xccu\xac\xeb\x80\x1b\x1d\xbe\xae\xbe\xc3K\xdeEj\xadH\t\xa5\x17\xe0)\x12/\x1f\xd8\xdf\xba>\x19\xea\xf3\x11\x9d\xd6\x00Sw\xefY\xef\x8f'
                        68      CALL                            1
                        76      CALL                            1
                        84      RAISE_VARARGS                   1
                        86      LOAD_FAST                       3: unpack
                        88      POP_JUMP_IF_NONE                55 (to 200)
                        90      PUSH_NULL                       
                        92      LOAD_DEREF                      0: self
                        94      LOAD_GLOBAL                     2: functions
                        104     LOAD_ATTR                       4: folders
                        124     LOAD_ATTR                       7: DeleteFolderRequest
                        144     LOAD_FAST                       3: unpack
                        146     KW_NAMES                        6: ('folder_id',)
                        148     CALL                            1
                        156     CALL                            1
                        164     GET_AWAITABLE                   0
                        166     LOAD_CONST                      4: None
                        168     SEND                            3 (to 176)
                        172     YIELD_VALUE                     3
                        174     RESUME                          3
                        176     JUMP_BACKWARD_NO_INTERRUPT      5 (to 168)
                        178     END_SEND                        
                        180     NOP                             
                        182     NOP                             
                        184     JUMP_FORWARD                    320 (to 828)
                        188     CALL                            1
                        196     POP_TOP                         
                        198     RETURN_VALUE                    
                        200     LOAD_GLOBAL                     9: NULL + utils
                        210     LOAD_ATTR                       10: is_list_like
                        230     LOAD_FAST                       1: entity
                        232     CALL                            1
                        240     POP_JUMP_IF_TRUE                27 (to 296)
                        242     LOAD_DEREF                      0: self
                        244     LOAD_ATTR                       13: get_input_entity
                        264     LOAD_FAST                       1: entity
                        266     CALL                            1
                        274     GET_AWAITABLE                   0
                        276     LOAD_CONST                      4: None
                        278     SEND                            3 (to 286)
                        282     YIELD_VALUE                     3
                        284     RESUME                          3
                        286     JUMP_BACKWARD_NO_INTERRUPT      5 (to 278)
                        288     END_SEND                        
                        290     BUILD_LIST                      1
                        292     STORE_FAST                      5: _var_var_4
                        294     JUMP_FORWARD                    35 (to 366)
                        296     LOAD_GLOBAL                     15: NULL + asyncio
                        306     LOAD_ATTR                       16: gather
                        326     LOAD_CLOSURE                    0: self
                        328     BUILD_TUPLE                     1
                        330     LOAD_CONST                      8: <CODE> <genexpr>
                        332     MAKE_FUNCTION                   8
                        334     LOAD_FAST                       1: entity
                        336     GET_ITER                        
                        338     CALL                            0
                        346     CALL_FUNCTION_EX                0
                        348     GET_AWAITABLE                   0
                        350     LOAD_CONST                      4: None
                        352     SEND                            3 (to 360)
                        356     YIELD_VALUE                     3
                        358     RESUME                          3
                        360     JUMP_BACKWARD_NO_INTERRUPT      5 (to 352)
                        362     END_SEND                        
                        364     STORE_FAST                      5: _var_var_4
                        366     LOAD_FAST                       2: folder
                        368     POP_JUMP_IF_NOT_NONE            17 (to 404)
                        370     LOAD_GLOBAL                     1: NULL + ValueError
                        380     PUSH_NULL                       
                        382     LOAD_CONST                      1: '__pyarmor_assert_16923__'
                        384     LOAD_CONST                      9: 'You must specify a folder'   # b'\x81\xdb\x17\x06s\xf7\xab\xc1\x0f\xba\x1e\xd0i\xef\xf1\x83\x16\x1d\xba\xe7\xac\xc4B\xc8\x00}'
                        386     CALL                            1
                        394     CALL                            1
                        402     RAISE_VARARGS                   1
                        404     LOAD_GLOBAL                     9: NULL + utils
                        414     LOAD_ATTR                       10: is_list_like
                        434     LOAD_FAST                       2: folder
                        436     CALL                            1
                        444     POP_JUMP_IF_TRUE                16 (to 478)
                        446     LOAD_FAST                       2: folder
                        448     BUILD_LIST                      1
                        450     LOAD_GLOBAL                     19: NULL + len
                        460     LOAD_FAST                       5: _var_var_4
                        462     CALL                            1
                        470     BINARY_OP                       5 (*)
                        474     STORE_FAST                      2: folder
                        476     JUMP_FORWARD                    40 (to 558)
                        478     LOAD_GLOBAL                     19: NULL + len
                        488     LOAD_FAST                       5: _var_var_4
                        490     CALL                            1
                        498     LOAD_GLOBAL                     19: NULL + len
                        508     LOAD_FAST                       2: folder
                        510     CALL                            1
                        518     COMPARE_OP                      55 (!=)
                        522     POP_JUMP_IF_FALSE               17 (to 558)
                        524     LOAD_GLOBAL                     1: NULL + ValueError
                        534     PUSH_NULL                       
                        536     LOAD_CONST                      1: '__pyarmor_assert_16923__'
                        538     LOAD_CONST                      10: 'Number of folders does not match number of entities'   # b'\x81\xcc\r\x1e1\xff\xac\x92\x14\xfcM\xc6c\xe0\xfc\x80\x1dN\xfb\xa3\xa5\xce]\x8c\x0b`\xb7\x1c\r\xb0\n\xe62\x12.\x18\x95\xc8\xb1<X\xe6\xfe\x1d\xd8\xd6\x1bN#\xe4S\xe8'
                        540     CALL                            1
                        548     CALL                            1
                        556     RAISE_VARARGS                   1
                        558     PUSH_NULL                       
                        560     LOAD_DEREF                      0: self
                        562     LOAD_GLOBAL                     2: functions
                        572     LOAD_ATTR                       4: folders
                        592     LOAD_ATTR                       21: EditPeerFoldersRequest
                        612     LOAD_GLOBAL                     23: NULL + zip
                        622     LOAD_FAST                       5: _var_var_4
                        624     LOAD_FAST                       2: folder
                        626     CALL                            2
                        634     GET_ITER                        
                        636     LOAD_FAST_AND_CLEAR             6: _var_var_3
                        638     LOAD_FAST_AND_CLEAR             7: _var_var_15
                        640     SWAP                            3
                        642     BUILD_LIST                      0
                        644     SWAP                            2
                        646     FOR_ITER                        28 (to 704)
                        650     UNPACK_SEQUENCE                 2
                        654     STORE_FAST                      6: _var_var_3
                        656     STORE_FAST                      7: _var_var_15
                        658     LOAD_GLOBAL                     25: NULL + types
                        668     LOAD_ATTR                       26: InputFolderPeer
                        688     LOAD_FAST                       6: _var_var_3
                        690     LOAD_FAST                       7: _var_var_15
                        692     KW_NAMES                        6: ('folder_id',)
                        694     CALL                            2
                        702     LIST_APPEND                     2
                        704     JUMP_BACKWARD                   30 (to 646)
                        706     END_FOR                         
                        708     SWAP                            3
                        710     STORE_FAST                      7: _var_var_15
                        712     STORE_FAST                      6: _var_var_3
                        714     CALL                            1
                        722     CALL                            1
                        730     GET_AWAITABLE                   0
                        732     LOAD_CONST                      4: None
                        734     SEND                            3 (to 742)
                        738     YIELD_VALUE                     3
                        740     RESUME                          3
                        742     JUMP_BACKWARD_NO_INTERRUPT      5 (to 734)
                        744     END_SEND                        
                        746     NOP                             
                        748     NOP                             
                        750     NOP                             
                        752     JUMP_FORWARD                    37 (to 828)
                        754     CALL                            1
                        762     POP_TOP                         
                        764     RETURN_VALUE                    
                        766     CLEANUP_THROW                   
                        768     JUMP_BACKWARD                   297 (to 178)
                        772     CLEANUP_THROW                   
                        774     JUMP_BACKWARD                   244 (to 288)
                        776     CLEANUP_THROW                   
                        778     JUMP_BACKWARD                   209 (to 362)
                        780     SWAP                            2
                        782     POP_TOP                         
                        784     SWAP                            3
                        786     STORE_FAST                      7: _var_var_15
                        788     STORE_FAST                      6: _var_var_3
                        790     RERAISE                         0
                        792     CLEANUP_THROW                   
                        794     JUMP_BACKWARD                   26 (to 744)
                        796     PUSH_EXC_INFO                   
                        798     PUSH_NULL                       
                        800     LOAD_CONST                      7: '__pyarmor_exit_16925__'
                        802     NOP                             
                        804     LOAD_CONST                      3: b'<COAddr>\x05\x00\x00 \xfc\x02\x00\x00\x00\x00\x00\x00\x00\x00\x00\x00\x00\x00\x00\x00'
                        806     CALL                            1
                        814     POP_TOP                         
                        816     RERAISE                         0
                        818     COPY                            3
                        820     POP_EXCEPT                      
                        822     RERAISE                         1
                        824     CALL_INTRINSIC_1                3 (INTRINSIC_STOPITERATION_ERROR)
                        826     RERAISE                         1
                        828     PUSH_NULL                       
                        830     LOAD_CONST                      7: '__pyarmor_exit_16925__'
                        832     LOAD_CONST                      3: b'<COAddr>\x05\x00\x00 \xfc\x02\x00\x00\x00\x00\x00\x00\x00\x00\x00\x00\x00\x00\x00\x00'
                        834     BUILD_TUPLE                     1
                        836     CALL_FUNCTION_EX                0
                        838     POP_TOP                         
                        840     RETURN_VALUE                    
                    [Exception Table]
                        6 to 32 -> 824 [0] lasti
                        34 to 172 -> 796 [0] 
                        172 to 174 -> 766 [2] 
                        174 to 180 -> 796 [0] 
                        180 to 200 -> 824 [0] lasti
                        200 to 282 -> 796 [0] 
                        282 to 284 -> 772 [2] 
                        284 to 356 -> 796 [0] 
                        356 to 358 -> 776 [2] 
                        358 to 642 -> 796 [0] 
                        642 to 708 -> 780 [7] 
                        708 to 738 -> 796 [0] 
                        738 to 740 -> 792 [2] 
                        740 to 746 -> 796 [0] 
                        746 to 766 -> 824 [0] lasti
                        766 to 768 -> 796 [0] 
                        772 to 774 -> 796 [0] 
                        776 to 778 -> 796 [0] 
                        780 to 794 -> 796 [0] 
                        796 to 818 -> 818 [1] lasti
                        818 to 824 -> 824 [0] lasti
                (
                    'revoke'
                )
                'revoke'
                [Code]
                    File Name: <frozen multithon.client.dialogs>
                    Object Name: delete_dialog
                    Qualified Name: DialogMethods.delete_dialog
                    Arg Count: 2
                    Pos Only Arg Count: 0
                    KW Only Arg Count: 1
                    Stack Size: 7
                    Flags: 0x20000083 (CO_OPTIMIZED | CO_NEWLOCALS | CO_COROUTINE | CO_PYARMOR_OBFUSCATED)
                    [Names]
                        'isinstance'
                        'types'
                        'Chat'
                        'deactivated'
                        'get_input_entity'
                        'helpers'
                        '_entity_type'
                        '_EntityType'
                        'CHANNEL'
                        'functions'
                        'channels'
                        'LeaveChannelRequest'
                        'CHAT'
                        'messages'
                        'DeleteChatUserRequest'
                        'chat_id'
                        'InputUserSelf'
                        'errors'
                        'PeerIdInvalidError'
                        'is_bot'
                        'DeleteHistoryRequest'
                    [Locals+Names]
                        'self'
                        'entity'
                        'revoke'
                        '__assert_armored__'
                        '_var_var_16'
                        '_var_var_17'
                        '_var_var_18'
                    [Constants]
                        "\n        Deletes a dialog (leaves a chat or channel).\n\n        This method can be used as a user and as a bot. However,\n        bots will only be able to use it to leave groups and channels\n        (trying to delete a private conversation will do nothing).\n\n        See also `Dialog.delete() <telethon.tl.custom.dialog.Dialog.delete>`.\n\n        Arguments\n            entity (entities):\n                The entity of the dialog to delete. If it's a chat or\n                channel, you will leave it. Note that the chat itself\n                is not deleted, only the dialog, because you left it.\n\n            revoke (`bool`, optional):\n                On private chats, you may revoke the messages from\n                the other peer too. By default, it's `False`. Set\n                it to `True` to delete the history for both.\n\n                This makes no difference for bot accounts, who can\n                only leave groups and channels.\n\n        Returns\n            The :tl:`Updates` object that the request produces,\n            or nothing for private conversations.\n\n        Example\n            .. code-block:: python\n\n                # Deleting the first dialog\n                dialogs = await client.get_dialogs(5)\n                await client.delete_dialog(dialogs[0])\n\n                # Leaving a channel by username\n                await client.delete_dialog('username')\n        "
                        '__pyarmor_assert_16926__'
                        '__pyarmor_enter_16927__'
                        b'<COAddr>\x05\x00\x00\x1e&\x03\x00\x00\x00\x00\x00\x00\x00\x00\x00\x00\x00\x00\x00\x00'
                        False
                        None
                        '__pyarmor_exit_16928__'
                        (
                            'revoke_history'
                        )
                        0
                        (
                            'revoke'
                        )
                    [Disassembly]
                        0       RETURN_GENERATOR                
                        2       POP_TOP                         
                        4       NOP                             
                        6       NOP                             
                        8       PUSH_NULL                       
                        10      LOAD_CONST                      2: '__pyarmor_enter_16927__'
                        12      LOAD_CONST                      3: b'<COAddr>\x05\x00\x00\x1e&\x03\x00\x00\x00\x00\x00\x00\x00\x00\x00\x00\x00\x00\x00\x00'
                        14      BUILD_TUPLE                     1
                        16      CALL_FUNCTION_EX                0
                        18      POP_TOP                         
                        20      RESUME                          0
                        22      NOP                             
                        24      NOP                             
                        26      NOP                             
                        28      NOP                             
                        30      NOP                             
                        32      LOAD_GLOBAL                     1: NULL + isinstance
                        42      LOAD_FAST                       1: entity
                        44      LOAD_GLOBAL                     2: types
                        54      LOAD_ATTR                       4: Chat
                        74      CALL                            2
                        82      POP_JUMP_IF_FALSE               13 (to 110)
                        84      LOAD_FAST                       1: entity
                        86      LOAD_ATTR                       6: deactivated
                        106     STORE_FAST                      4: _var_var_16
                        108     JUMP_FORWARD                    2 (to 114)
                        110     LOAD_CONST                      4: False
                        112     STORE_FAST                      4: _var_var_16
                        114     LOAD_FAST                       0: self
                        116     LOAD_ATTR                       9: get_input_entity
                        136     LOAD_FAST                       1: entity
                        138     CALL                            1
                        146     GET_AWAITABLE                   0
                        148     LOAD_CONST                      5: None
                        150     SEND                            3 (to 158)
                        154     YIELD_VALUE                     3
                        156     RESUME                          3
                        158     JUMP_BACKWARD_NO_INTERRUPT      5 (to 150)
                        160     END_SEND                        
                        162     STORE_FAST                      1: entity
                        164     LOAD_GLOBAL                     11: NULL + helpers
                        174     LOAD_ATTR                       12: _entity_type
                        194     LOAD_FAST                       1: entity
                        196     CALL                            1
                        204     STORE_FAST                      5: _var_var_17
                        206     LOAD_FAST                       5: _var_var_17
                        208     LOAD_GLOBAL                     10: helpers
                        218     LOAD_ATTR                       14: _EntityType
                        238     LOAD_ATTR                       16: CHANNEL
                        258     COMPARE_OP                      40 (==)
                        262     POP_JUMP_IF_FALSE               54 (to 372)
                        264     PUSH_NULL                       
                        266     LOAD_FAST                       0: self
                        268     LOAD_GLOBAL                     18: functions
                        278     LOAD_ATTR                       20: channels
                        298     LOAD_ATTR                       23: LeaveChannelRequest
                        318     LOAD_FAST                       1: entity
                        320     CALL                            1
                        328     CALL                            1
                        336     GET_AWAITABLE                   0
                        338     LOAD_CONST                      5: None
                        340     SEND                            3 (to 348)
                        344     YIELD_VALUE                     3
                        346     RESUME                          3
                        348     JUMP_BACKWARD_NO_INTERRUPT      5 (to 340)
                        350     END_SEND                        
                        352     NOP                             
                        354     NOP                             
                        356     NOP                             
                        358     JUMP_FORWARD                    254 (to 868)
                        360     CALL                            1
                        368     POP_TOP                         
                        370     RETURN_VALUE                    
                        372     LOAD_FAST                       5: _var_var_17
                        374     LOAD_GLOBAL                     10: helpers
                        384     LOAD_ATTR                       14: _EntityType
                        404     LOAD_ATTR                       24: CHAT
                        424     COMPARE_OP                      40 (==)
                        428     POP_JUMP_IF_FALSE               80 (to 590)
                        430     LOAD_FAST                       4: _var_var_16
                        432     POP_JUMP_IF_TRUE                78 (to 590)
                        434     NOP                             
                        436     PUSH_NULL                       
                        438     LOAD_FAST                       0: self
                        440     LOAD_GLOBAL                     18: functions
                        450     LOAD_ATTR                       26: messages
                        470     LOAD_ATTR                       29: DeleteChatUserRequest
                        490     LOAD_FAST                       1: entity
                        492     LOAD_ATTR                       30: chat_id
                        512     LOAD_GLOBAL                     3: NULL + types
                        522     LOAD_ATTR                       32: InputUserSelf
                        542     CALL                            0
                        550     LOAD_FAST                       2: revoke
                        552     KW_NAMES                        7: ('revoke_history',)
                        554     CALL                            3
                        562     CALL                            1
                        570     GET_AWAITABLE                   0
                        572     LOAD_CONST                      5: None
                        574     SEND                            3 (to 582)
                        578     YIELD_VALUE                     4
                        580     RESUME                          3
                        582     JUMP_BACKWARD_NO_INTERRUPT      5 (to 574)
                        584     END_SEND                        
                        586     STORE_FAST                      6: _var_var_18
                        588     JUMP_FORWARD                    2 (to 594)
                        590     LOAD_CONST                      5: None
                        592     STORE_FAST                      6: _var_var_18
                        594     LOAD_FAST                       0: self
                        596     LOAD_ATTR                       39: is_bot
                        616     CALL                            0
                        624     GET_AWAITABLE                   0
                        626     LOAD_CONST                      5: None
                        628     SEND                            3 (to 636)
                        632     YIELD_VALUE                     3
                        634     RESUME                          3
                        636     JUMP_BACKWARD_NO_INTERRUPT      5 (to 628)
                        638     END_SEND                        
                        640     POP_JUMP_IF_TRUE                48 (to 738)
                        642     PUSH_NULL                       
                        644     LOAD_FAST                       0: self
                        646     LOAD_GLOBAL                     18: functions
                        656     LOAD_ATTR                       26: messages
                        676     LOAD_ATTR                       41: DeleteHistoryRequest
                        696     LOAD_FAST                       1: entity
                        698     LOAD_CONST                      8: 0
                        700     LOAD_FAST                       2: revoke
                        702     KW_NAMES                        9: ('revoke',)
                        704     CALL                            3
                        712     CALL                            1
                        720     GET_AWAITABLE                   0
                        722     LOAD_CONST                      5: None
                        724     SEND                            3 (to 732)
                        728     YIELD_VALUE                     3
                        730     RESUME                          3
                        732     JUMP_BACKWARD_NO_INTERRUPT      5 (to 724)
                        734     END_SEND                        
                        736     POP_TOP                         
                        738     LOAD_FAST                       6: _var_var_18
                        740     NOP                             
                        742     NOP                             
                        744     NOP                             
                        746     JUMP_FORWARD                    60 (to 868)
                        748     CALL                            1
                        756     POP_TOP                         
                        758     RETURN_VALUE                    
                        760     CLEANUP_THROW                   
                        762     JUMP_BACKWARD                   303 (to 160)
                        766     CLEANUP_THROW                   
                        768     JUMP_BACKWARD                   210 (to 350)
                        770     CLEANUP_THROW                   
                        772     JUMP_BACKWARD                   95 (to 584)
                        774     PUSH_EXC_INFO                   
                        776     LOAD_GLOBAL                     34: errors
                        786     LOAD_ATTR                       36: PeerIdInvalidError
                        806     CHECK_EXC_MATCH                 
                        808     POP_JUMP_IF_FALSE               5 (to 820)
                        810     POP_TOP                         
                        812     LOAD_CONST                      5: None
                        814     STORE_FAST                      6: _var_var_18
                        816     POP_EXCEPT                      
                        818     JUMP_BACKWARD                   113 (to 594)
                        820     RERAISE                         0
                        822     COPY                            3
                        824     POP_EXCEPT                      
                        826     RERAISE                         1
                        828     CLEANUP_THROW                   
                        830     JUMP_BACKWARD                   97 (to 638)
                        832     CLEANUP_THROW                   
                        834     JUMP_BACKWARD                   51 (to 734)
                        836     PUSH_EXC_INFO                   
                        838     PUSH_NULL                       
                        840     LOAD_CONST                      6: '__pyarmor_exit_16928__'
                        842     NOP                             
                        844     LOAD_CONST                      3: b'<COAddr>\x05\x00\x00\x1e&\x03\x00\x00\x00\x00\x00\x00\x00\x00\x00\x00\x00\x00\x00\x00'
                        846     CALL                            1
                        854     POP_TOP                         
                        856     RERAISE                         0
                        858     COPY                            3
                        860     POP_EXCEPT                      
                        862     RERAISE                         1
                        864     CALL_INTRINSIC_1                3 (INTRINSIC_STOPITERATION_ERROR)
                        866     RERAISE                         1
                        868     PUSH_NULL                       
                        870     LOAD_CONST                      6: '__pyarmor_exit_16928__'
                        872     LOAD_CONST                      3: b'<COAddr>\x05\x00\x00\x1e&\x03\x00\x00\x00\x00\x00\x00\x00\x00\x00\x00\x00\x00\x00\x00'
                        874     BUILD_TUPLE                     1
                        876     CALL_FUNCTION_EX                0
                        878     POP_TOP                         
                        880     RETURN_VALUE                    
                    [Exception Table]
                        4 to 30 -> 864 [0] lasti
                        32 to 154 -> 836 [0] 
                        154 to 156 -> 760 [2] 
                        156 to 344 -> 836 [0] 
                        344 to 346 -> 766 [2] 
                        346 to 352 -> 836 [0] 
                        352 to 372 -> 864 [0] lasti
                        372 to 434 -> 836 [0] 
                        436 to 578 -> 774 [0] 
                        578 to 580 -> 770 [2] 
                        580 to 588 -> 774 [0] 
                        588 to 632 -> 836 [0] 
                        632 to 634 -> 828 [2] 
                        634 to 728 -> 836 [0] 
                        728 to 730 -> 832 [2] 
                        730 to 740 -> 836 [0] 
                        740 to 760 -> 864 [0] lasti
                        760 to 762 -> 836 [0] 
                        766 to 768 -> 836 [0] 
                        770 to 772 -> 774 [0] 
                        774 to 816 -> 822 [1] lasti
                        816 to 820 -> 836 [0] 
                        820 to 822 -> 822 [1] lasti
                        822 to 830 -> 836 [0] 
                        832 to 834 -> 836 [0] 
                        836 to 858 -> 858 [1] lasti
                        858 to 864 -> 864 [0] lasti
                60
                100
                True
                (
                    'timeout'
                    'total_timeout'
                    'max_messages'
                    'exclusive'
                    'replies_are_responses'
                )
                'timeout'
                'total_timeout'
                'max_messages'
                'exclusive'
                'replies_are_responses'
                [Code]
                    File Name: <frozen multithon.client.dialogs>
                    Object Name: conversation
                    Qualified Name: DialogMethods.conversation
                    Arg Count: 2
                    Pos Only Arg Count: 0
                    KW Only Arg Count: 5
                    Stack Size: 9
                    Flags: 0x20000003 (CO_OPTIMIZED | CO_NEWLOCALS | CO_PYARMOR_OBFUSCATED)
                    [Names]
                        'custom'
                        'Conversation'
                    [Locals+Names]
                        'self'
                        'entity'
                        'timeout'
                        'total_timeout'
                        'max_messages'
                        'exclusive'
                        'replies_are_responses'
                        '__assert_armored__'
                    [Constants]
                        '\n        Creates a `Conversation <telethon.tl.custom.conversation.Conversation>`\n        with the given entity.\n\n        .. note::\n\n            This Conversation API has certain shortcomings, such as lacking\n            persistence, poor interaction with other event handlers, and\n            overcomplicated usage for anything beyond the simplest case.\n\n            If you plan to interact with a bot without handlers, this works\n            fine, but when running a bot yourself, you may instead prefer\n            to follow the advice from https://stackoverflow.com/a/62246569/.\n\n        This is not the same as just sending a message to create a "dialog"\n        with them, but rather a way to easily send messages and await for\n        responses or other reactions. Refer to its documentation for more.\n\n        Arguments\n            entity (`entity`):\n                The entity with which a new conversation should be opened.\n\n            timeout (`int` | `float`, optional):\n                The default timeout (in seconds) *per action* to be used. You\n                may also override this timeout on a per-method basis. By\n                default each action can take up to 60 seconds (the value of\n                this timeout).\n\n            total_timeout (`int` | `float`, optional):\n                The total timeout (in seconds) to use for the whole\n                conversation. This takes priority over per-action\n                timeouts. After these many seconds pass, subsequent\n                actions will result in ``asyncio.TimeoutError``.\n\n            max_messages (`int`, optional):\n                The maximum amount of messages this conversation will\n                remember. After these many messages arrive in the\n                specified chat, subsequent actions will result in\n                ``ValueError``.\n\n            exclusive (`bool`, optional):\n                By default, conversations are exclusive within a single\n                chat. That means that while a conversation is open in a\n                chat, you can\'t open another one in the same chat, unless\n                you disable this flag.\n\n                If you try opening an exclusive conversation for\n                a chat where it\'s already open, it will raise\n                ``AlreadyInConversationError``.\n\n            replies_are_responses (`bool`, optional):\n                Whether replies should be treated as responses or not.\n\n                If the setting is enabled, calls to `conv.get_response\n                <telethon.tl.custom.conversation.Conversation.get_response>`\n                and a subsequent call to `conv.get_reply\n                <telethon.tl.custom.conversation.Conversation.get_reply>`\n                will return different messages, otherwise they may return\n                the same message.\n\n                Consider the following scenario with one outgoing message,\n                1, and two incoming messages, the second one replying::\n\n                                        Hello! <1\n                    2> (reply to 1) Hi!\n                    3> (reply to 1) How are you?\n\n                And the following code:\n\n                .. code-block:: python\n\n                    async with client.conversation(chat) as conv:\n                        msg1 = await conv.send_message(\'Hello!\')\n                        msg2 = await conv.get_response()\n                        msg3 = await conv.get_reply()\n\n                With the setting enabled, ``msg2`` will be ``\'Hi!\'`` and\n                ``msg3`` be ``\'How are you?\'`` since replies are also\n                responses, and a response was already returned.\n\n                With the setting disabled, both ``msg2`` and ``msg3`` will\n                be ``\'Hi!\'`` since one is a response and also a reply.\n\n        Returns\n            A `Conversation <telethon.tl.custom.conversation.Conversation>`.\n\n        Example\n            .. code-block:: python\n\n                # <you> denotes outgoing messages you sent\n                # <usr> denotes incoming response messages\n                with bot.conversation(chat) as conv:\n                    # <you> Hi!\n                    conv.send_message(\'Hi!\')\n\n                    # <usr> Hello!\n                    hello = conv.get_response()\n\n                    # <you> Please tell me your name\n                    conv.send_message(\'Please tell me your name\')\n\n                    # <usr> ?\n                    name = conv.get_response().raw_text\n\n                    while not any(x.isalpha() for x in name):\n                        # <you> Your name didn\'t have any letters! Try again\n                        conv.send_message("Your name didn\'t have any letters! Try again")\n\n                        # <usr> Human\n                        name = conv.get_response().raw_text\n\n                    # <you> Thanks Human!\n                    conv.send_message(\'Thanks {}!\'.format(name))\n        '
                        '__pyarmor_assert_16929__'
                        '__pyarmor_enter_16930__'
                        b'<COAddr>\x07\x00\x00\x1aL\x00\x00\x00\x00\x00\x00\x00\x00\x00\x00\x00\x00\x00\x00\x00'
                        (
                            'timeout'
                            'total_timeout'
                            'max_messages'
                            'exclusive'
                            'replies_are_responses'
                        )
                        '__pyarmor_exit_16931__'
                    [Disassembly]
                        0       NOP                             
                        2       NOP                             
                        4       PUSH_NULL                       
                        6       LOAD_CONST                      2: '__pyarmor_enter_16930__'
                        8       LOAD_CONST                      3: b'<COAddr>\x07\x00\x00\x1aL\x00\x00\x00\x00\x00\x00\x00\x00\x00\x00\x00\x00\x00\x00\x00'
                        10      BUILD_TUPLE                     1
                        12      CALL_FUNCTION_EX                0
                        14      POP_TOP                         
                        16      RESUME                          0
                        18      NOP                             
                        20      NOP                             
                        22      NOP                             
                        24      NOP                             
                        26      NOP                             
                        28      LOAD_GLOBAL                     1: NULL + custom
                        38      LOAD_ATTR                       2: Conversation
                        58      LOAD_FAST                       0: self
                        60      LOAD_FAST                       1: entity
                        62      LOAD_FAST                       2: timeout
                        64      LOAD_FAST                       3: total_timeout
                        66      LOAD_FAST                       4: max_messages
                        68      LOAD_FAST                       5: exclusive
                        70      LOAD_FAST                       6: replies_are_responses
                        72      KW_NAMES                        4: ('timeout', 'total_timeout', 'max_messages', 'exclusive', 'replies_are_responses')
                        74      CALL                            7
                        82      NOP                             
                        84      NOP                             
                        86      NOP                             
                        88      JUMP_FORWARD                    20 (to 130)
                        90      CALL                            1
                        98      POP_TOP                         
                        100     RETURN_VALUE                    
                        102     PUSH_EXC_INFO                   
                        104     PUSH_NULL                       
                        106     LOAD_CONST                      5: '__pyarmor_exit_16931__'
                        108     NOP                             
                        110     LOAD_CONST                      3: b'<COAddr>\x07\x00\x00\x1aL\x00\x00\x00\x00\x00\x00\x00\x00\x00\x00\x00\x00\x00\x00\x00'
                        112     CALL                            1
                        120     POP_TOP                         
                        122     RERAISE                         0
                        124     COPY                            3
                        126     POP_EXCEPT                      
                        128     RERAISE                         1
                        130     PUSH_NULL                       
                        132     LOAD_CONST                      5: '__pyarmor_exit_16931__'
                        134     LOAD_CONST                      3: b'<COAddr>\x07\x00\x00\x1aL\x00\x00\x00\x00\x00\x00\x00\x00\x00\x00\x00\x00\x00\x00\x00'
                        136     BUILD_TUPLE                     1
                        138     CALL_FUNCTION_EX                0
                        140     POP_TOP                         
                        142     RETURN_VALUE                    
                    [Exception Table]
                        28 to 82 -> 102 [0] 
                        102 to 124 -> 124 [1] lasti
                '__pyarmor_exit_16910__'
                (
                    None
                )
                (
                    None
                    None
                )
            [Disassembly]
                0       NOP                             
                2       LOAD_NAME                       0: __name__
                4       STORE_NAME                      1: __module__
                6       LOAD_CONST                      0: 'DialogMethods'
                8       STORE_NAME                      2: __qualname__
                10      NOP                             
                12      PUSH_NULL                       
                14      LOAD_CONST                      2: '__pyarmor_enter_16909__'
                16      LOAD_CONST                      3: b'<COAddr>\x07\x00\x00"|\x02\x00\x00\x00\x00\x00\x00\x00\x00\x00\x00\x00\x00\x00\x00'
                18      BUILD_TUPLE                     1
                20      CALL_FUNCTION_EX                0
                22      POP_TOP                         
                24      RESUME                          0
                26      NOP                             
                28      NOP                             
                30      NOP                             
                32      NOP                             
                34      NOP                             
                36      NOP                             
                38      LOAD_CONST                      44: (None,)
                40      LOAD_CONST                      4: None
                42      LOAD_CONST                      5: 0
                44      PUSH_NULL                       
                46      LOAD_NAME                       4: types
                48      LOAD_ATTR                       10: InputPeerEmpty
                68      CALL                            0
                76      LOAD_CONST                      6: False
                78      LOAD_CONST                      6: False
                80      LOAD_CONST                      4: None
                82      LOAD_CONST                      4: None
                84      LOAD_CONST                      7: ('offset_date', 'offset_id', 'offset_peer', 'ignore_pinned', 'ignore_migrated', 'folder', 'archived')
                86      BUILD_CONST_KEY_MAP             7
                88      LOAD_CONST                      8: 'self'
                90      PUSH_NULL                       
                92      LOAD_CONST                      1: '__pyarmor_assert_16908__'
                94      LOAD_CONST                      9: 'TelegramClient'   # b'\x81\xd6\x1d\x1f6\xfd\xac\xd3\x16\xd9\x01\xc9i\xe2\xec'
                96      CALL                            1
                104     LOAD_CONST                      10: 'limit'
                106     LOAD_NAME                       6: float
                108     LOAD_CONST                      11: 'offset_date'
                110     PUSH_NULL                       
                112     LOAD_CONST                      1: '__pyarmor_assert_16908__'
                114     LOAD_CONST                      12: 'hints.DateLike'   # b"\x81\xea\x11\x1d'\xe9\xf0\xf6\x1a\xee\x08\xece\xe7\xfd"
                116     CALL                            1
                124     LOAD_CONST                      13: 'offset_id'
                126     LOAD_NAME                       7: int
                128     LOAD_CONST                      14: 'offset_peer'
                130     PUSH_NULL                       
                132     LOAD_CONST                      1: '__pyarmor_assert_16908__'
                134     LOAD_CONST                      15: 'hints.EntityLike'   # b"\x81\xea\x11\x1d'\xe9\xf0\xf7\x15\xee\x04\xd4u\xc0\xf1\x8e\n"
                136     CALL                            1
                144     LOAD_CONST                      16: 'ignore_pinned'
                146     LOAD_NAME                       8: bool
                148     LOAD_CONST                      17: 'ignore_migrated'
                150     LOAD_NAME                       8: bool
                152     LOAD_CONST                      18: 'folder'
                154     LOAD_NAME                       7: int
                156     LOAD_CONST                      19: 'archived'
                158     LOAD_NAME                       8: bool
                160     LOAD_CONST                      20: 'return'
                162     LOAD_NAME                       9: _DialogsIter
                164     BUILD_TUPLE                     20
                166     LOAD_CONST                      21: <CODE> iter_dialogs
                168     MAKE_FUNCTION                   7
                170     STORE_NAME                      10: iter_dialogs
                172     LOAD_CONST                      8: 'self'
                174     PUSH_NULL                       
                176     LOAD_CONST                      1: '__pyarmor_assert_16908__'
                178     LOAD_CONST                      9: 'TelegramClient'   # b'\x81\xd6\x1d\x1f6\xfd\xac\xd3\x16\xd9\x01\xc9i\xe2\xec'
                180     CALL                            1
                188     LOAD_CONST                      20: 'return'
                190     PUSH_NULL                       
                192     LOAD_CONST                      1: '__pyarmor_assert_16908__'
                194     LOAD_CONST                      22: 'hints.TotalList'   # b"\x81\xea\x11\x1d'\xe9\xf0\xe6\x14\xee\x0c\xcc@\xe5\xeb\x91"
                196     CALL                            1
                204     BUILD_TUPLE                     4
                206     LOAD_CONST                      23: <CODE> get_dialogs
                208     MAKE_FUNCTION                   4
                210     STORE_NAME                      11: get_dialogs
                212     PUSH_NULL                       
                214     LOAD_NAME                       12: inspect
                216     LOAD_ATTR                       26: signature
                236     LOAD_NAME                       10: iter_dialogs
                238     CALL                            1
                246     LOAD_NAME                       11: get_dialogs
                248     STORE_ATTR                      14: __signature__
                258     NOP                             
                260     LOAD_CONST                      44: (None,)
                262     LOAD_CONST                      8: 'self'
                264     PUSH_NULL                       
                266     LOAD_CONST                      1: '__pyarmor_assert_16908__'
                268     LOAD_CONST                      9: 'TelegramClient'   # b'\x81\xd6\x1d\x1f6\xfd\xac\xd3\x16\xd9\x01\xc9i\xe2\xec'
                270     CALL                            1
                278     LOAD_CONST                      24: 'entity'
                280     PUSH_NULL                       
                282     LOAD_CONST                      1: '__pyarmor_assert_16908__'
                284     LOAD_CONST                      25: 'hints.EntitiesLike'   # b"\x81\xea\x11\x1d'\xe9\xf0\xf7\x15\xee\x04\xd4e\xe9\xeb\xa9\x06V\xbe"
                286     CALL                            1
                294     LOAD_CONST                      20: 'return'
                296     LOAD_NAME                       15: _DraftsIter
                298     BUILD_TUPLE                     6
                300     LOAD_CONST                      26: <CODE> iter_drafts
                302     MAKE_FUNCTION                   5
                304     STORE_NAME                      16: iter_drafts
                306     NOP                             
                308     LOAD_CONST                      44: (None,)
                310     LOAD_CONST                      8: 'self'
                312     PUSH_NULL                       
                314     LOAD_CONST                      1: '__pyarmor_assert_16908__'
                316     LOAD_CONST                      9: 'TelegramClient'   # b'\x81\xd6\x1d\x1f6\xfd\xac\xd3\x16\xd9\x01\xc9i\xe2\xec'
                318     CALL                            1
                326     LOAD_CONST                      24: 'entity'
                328     PUSH_NULL                       
                330     LOAD_CONST                      1: '__pyarmor_assert_16908__'
                332     LOAD_CONST                      25: 'hints.EntitiesLike'   # b"\x81\xea\x11\x1d'\xe9\xf0\xf7\x15\xee\x04\xd4e\xe9\xeb\xa9\x06V\xbe"
                334     CALL                            1
                342     LOAD_CONST                      20: 'return'
                344     PUSH_NULL                       
                346     LOAD_CONST                      1: '__pyarmor_assert_16908__'
                348     LOAD_CONST                      22: 'hints.TotalList'   # b"\x81\xea\x11\x1d'\xe9\xf0\xe6\x14\xee\x0c\xcc@\xe5\xeb\x91"
                350     CALL                            1
                358     BUILD_TUPLE                     6
                360     LOAD_CONST                      27: <CODE> get_drafts
                362     MAKE_FUNCTION                   5
                364     STORE_NAME                      17: get_drafts
                366     NOP                             
                368     NOP                             
                370     LOAD_CONST                      45: (None, None)
                372     LOAD_CONST                      4: None
                374     LOAD_CONST                      28: ('unpack',)
                376     BUILD_CONST_KEY_MAP             1
                378     LOAD_CONST                      8: 'self'
                380     PUSH_NULL                       
                382     LOAD_CONST                      1: '__pyarmor_assert_16908__'
                384     LOAD_CONST                      9: 'TelegramClient'   # b'\x81\xd6\x1d\x1f6\xfd\xac\xd3\x16\xd9\x01\xc9i\xe2\xec'
                386     CALL                            1
                394     LOAD_CONST                      24: 'entity'
                396     PUSH_NULL                       
                398     LOAD_CONST                      1: '__pyarmor_assert_16908__'
                400     LOAD_CONST                      25: 'hints.EntitiesLike'   # b"\x81\xea\x11\x1d'\xe9\xf0\xf7\x15\xee\x04\xd4e\xe9\xeb\xa9\x06V\xbe"
                402     CALL                            1
                410     LOAD_CONST                      18: 'folder'
                412     LOAD_NAME                       18: typing
                414     LOAD_ATTR                       38: Union
                434     LOAD_NAME                       7: int
                436     LOAD_NAME                       18: typing
                438     LOAD_ATTR                       40: Sequence
                458     LOAD_NAME                       7: int
                460     BINARY_SUBSCR                   
                464     BUILD_TUPLE                     2
                466     BINARY_SUBSCR                   
                470     LOAD_CONST                      20: 'return'
                472     LOAD_NAME                       4: types
                474     LOAD_ATTR                       42: Updates
                494     BUILD_TUPLE                     8
                496     LOAD_CONST                      29: <CODE> edit_folder
                498     MAKE_FUNCTION                   7
                500     STORE_NAME                      22: edit_folder
                502     LOAD_CONST                      6: False
                504     LOAD_CONST                      30: ('revoke',)
                506     BUILD_CONST_KEY_MAP             1
                508     LOAD_CONST                      8: 'self'
                510     PUSH_NULL                       
                512     LOAD_CONST                      1: '__pyarmor_assert_16908__'
                514     LOAD_CONST                      9: 'TelegramClient'   # b'\x81\xd6\x1d\x1f6\xfd\xac\xd3\x16\xd9\x01\xc9i\xe2\xec'
                516     CALL                            1
                524     LOAD_CONST                      24: 'entity'
                526     PUSH_NULL                       
                528     LOAD_CONST                      1: '__pyarmor_assert_16908__'
                530     LOAD_CONST                      15: 'hints.EntityLike'   # b"\x81\xea\x11\x1d'\xe9\xf0\xf7\x15\xee\x04\xd4u\xc0\xf1\x8e\n"
                532     CALL                            1
                540     LOAD_CONST                      31: 'revoke'
                542     LOAD_NAME                       8: bool
                544     BUILD_TUPLE                     6
                546     LOAD_CONST                      32: <CODE> delete_dialog
                548     MAKE_FUNCTION                   6
                550     STORE_NAME                      23: delete_dialog
                552     LOAD_CONST                      33: 60
                554     LOAD_CONST                      4: None
                556     LOAD_CONST                      34: 100
                558     LOAD_CONST                      35: True
                560     LOAD_CONST                      35: True
                562     LOAD_CONST                      36: ('timeout', 'total_timeout', 'max_messages', 'exclusive', 'replies_are_responses')
                564     BUILD_CONST_KEY_MAP             5
                566     LOAD_CONST                      8: 'self'
                568     PUSH_NULL                       
                570     LOAD_CONST                      1: '__pyarmor_assert_16908__'
                572     LOAD_CONST                      9: 'TelegramClient'   # b'\x81\xd6\x1d\x1f6\xfd\xac\xd3\x16\xd9\x01\xc9i\xe2\xec'
                574     CALL                            1
                582     LOAD_CONST                      24: 'entity'
                584     PUSH_NULL                       
                586     LOAD_CONST                      1: '__pyarmor_assert_16908__'
                588     LOAD_CONST                      15: 'hints.EntityLike'   # b"\x81\xea\x11\x1d'\xe9\xf0\xf7\x15\xee\x04\xd4u\xc0\xf1\x8e\n"
                590     CALL                            1
                598     LOAD_CONST                      37: 'timeout'
                600     LOAD_NAME                       6: float
                602     LOAD_CONST                      38: 'total_timeout'
                604     LOAD_NAME                       6: float
                606     LOAD_CONST                      39: 'max_messages'
                608     LOAD_NAME                       7: int
                610     LOAD_CONST                      40: 'exclusive'
                612     LOAD_NAME                       8: bool
                614     LOAD_CONST                      41: 'replies_are_responses'
                616     LOAD_NAME                       8: bool
                618     LOAD_CONST                      20: 'return'
                620     LOAD_NAME                       24: custom
                622     LOAD_ATTR                       50: Conversation
                642     BUILD_TUPLE                     16
                644     LOAD_CONST                      42: <CODE> conversation
                646     MAKE_FUNCTION                   6
                648     STORE_NAME                      26: conversation
                650     LOAD_CONST                      4: None
                652     NOP                             
                654     NOP                             
                656     NOP                             
                658     JUMP_FORWARD                    19 (to 698)
                666     POP_TOP                         
                668     RETURN_CONST                    4: None
                670     PUSH_EXC_INFO                   
                672     PUSH_NULL                       
                674     LOAD_CONST                      43: '__pyarmor_exit_16910__'
                676     NOP                             
                678     LOAD_CONST                      3: b'<COAddr>\x07\x00\x00"|\x02\x00\x00\x00\x00\x00\x00\x00\x00\x00\x00\x00\x00\x00\x00'
                680     CALL                            1
                688     POP_TOP                         
                690     RERAISE                         0
                692     COPY                            3
                694     POP_EXCEPT                      
                696     RERAISE                         1
                698     PUSH_NULL                       
                700     LOAD_CONST                      43: '__pyarmor_exit_16910__'
                702     LOAD_CONST                      3: b'<COAddr>\x07\x00\x00"|\x02\x00\x00\x00\x00\x00\x00\x00\x00\x00\x00\x00\x00\x00\x00'
                704     BUILD_TUPLE                     1
                706     CALL_FUNCTION_EX                0
                708     POP_TOP                         
                710     RETURN_VALUE                    
            [Exception Table]
                36 to 650 -> 670 [0] 
                670 to 692 -> 692 [1] lasti
        'DialogMethods'
        '__pyarmor_exit_16886__'
    [Disassembly]
        0       NOP                             
        2       NOP                             
        4       PUSH_NULL                       
        6       LOAD_CONST                      1: '__pyarmor_enter_16885__'
        8       LOAD_CONST                      2: b'<COAddr>\x05\x00\x00\x1a\xda\x00\x00\x00\x00\x00\x00\x00\x00\x00\x00\x00\x00\x00\x00\x00'
        10      BUILD_TUPLE                     1
        12      CALL_FUNCTION_EX                0
        14      POP_TOP                         
        16      RESUME                          0
        18      NOP                             
        20      NOP                             
        22      NOP                             
        24      NOP                             
        26      LOAD_CONST                      3: 0
        28      LOAD_CONST                      4: None
        30      IMPORT_NAME                     1: asyncio
        32      STORE_NAME                      1: asyncio
        34      LOAD_CONST                      3: 0
        36      LOAD_CONST                      4: None
        38      IMPORT_NAME                     2: inspect
        40      STORE_NAME                      2: inspect
        42      LOAD_CONST                      3: 0
        44      LOAD_CONST                      4: None
        46      IMPORT_NAME                     3: itertools
        48      STORE_NAME                      3: itertools
        50      LOAD_CONST                      3: 0
        52      LOAD_CONST                      4: None
        54      IMPORT_NAME                     4: typing
        56      STORE_NAME                      4: typing
        58      LOAD_CONST                      5: 2
        60      LOAD_CONST                      6: ('helpers', 'utils', 'hints', 'errors')
        62      IMPORT_NAME                     5: 
        64      IMPORT_FROM                     6: helpers
        66      STORE_NAME                      6: helpers
        68      IMPORT_FROM                     7: utils
        70      STORE_NAME                      7: utils
        72      IMPORT_FROM                     8: hints
        74      STORE_NAME                      8: hints
        76      IMPORT_FROM                     9: errors
        78      STORE_NAME                      9: errors
        80      POP_TOP                         
        82      LOAD_CONST                      5: 2
        84      LOAD_CONST                      7: ('RequestIter',)
        86      IMPORT_NAME                     10: requestiter
        88      IMPORT_FROM                     11: RequestIter
        90      STORE_NAME                      11: RequestIter
        92      POP_TOP                         
        94      LOAD_CONST                      5: 2
        96      LOAD_CONST                      8: ('types', 'functions', 'custom')
        98      IMPORT_NAME                     12: tl
        100     IMPORT_FROM                     13: types
        102     STORE_NAME                      13: types
        104     IMPORT_FROM                     14: functions
        106     STORE_NAME                      14: functions
        108     IMPORT_FROM                     15: custom
        110     STORE_NAME                      15: custom
        112     POP_TOP                         
        114     LOAD_CONST                      9: 100
        116     STORE_NAME                      16: _MAX_CHUNK_SIZE
        118     LOAD_NAME                       4: typing
        120     LOAD_ATTR                       34: TYPE_CHECKING
        140     POP_JUMP_IF_FALSE               6 (to 154)
        142     LOAD_CONST                      10: 1
        144     LOAD_CONST                      11: ('TelegramClient',)
        146     IMPORT_NAME                     18: telegramclient
        148     IMPORT_FROM                     19: TelegramClient
        150     STORE_NAME                      19: TelegramClient
        152     POP_TOP                         
        154     LOAD_CONST                      12: <CODE> _dialog_message_key
        156     MAKE_FUNCTION                   0
        158     STORE_NAME                      20: _dialog_message_key
        160     PUSH_NULL                       
        162     LOAD_BUILD_CLASS                
        164     LOAD_CONST                      13: <CODE> _DialogsIter
        166     MAKE_FUNCTION                   0
        168     LOAD_CONST                      14: '_DialogsIter'
        170     LOAD_NAME                       11: RequestIter
        172     CALL                            3
        180     STORE_NAME                      21: _DialogsIter
        182     PUSH_NULL                       
        184     LOAD_BUILD_CLASS                
        186     LOAD_CONST                      15: <CODE> _DraftsIter
        188     MAKE_FUNCTION                   0
        190     LOAD_CONST                      16: '_DraftsIter'
        192     LOAD_NAME                       11: RequestIter
        194     CALL                            3
        202     STORE_NAME                      22: _DraftsIter
        204     PUSH_NULL                       
        206     LOAD_BUILD_CLASS                
        208     LOAD_CONST                      17: <CODE> DialogMethods
        210     MAKE_FUNCTION                   0
        212     LOAD_CONST                      18: 'DialogMethods'
        214     CALL                            2
        222     STORE_NAME                      23: DialogMethods
        224     LOAD_CONST                      4: None
        226     NOP                             
        228     NOP                             
        230     NOP                             
        232     JUMP_FORWARD                    19 (to 272)
        240     POP_TOP                         
        242     RETURN_CONST                    4: None
        244     PUSH_EXC_INFO                   
        246     PUSH_NULL                       
        248     LOAD_CONST                      19: '__pyarmor_exit_16886__'
        250     NOP                             
        252     LOAD_CONST                      2: b'<COAddr>\x05\x00\x00\x1a\xda\x00\x00\x00\x00\x00\x00\x00\x00\x00\x00\x00\x00\x00\x00\x00'
        254     CALL                            1
        262     POP_TOP                         
        264     RERAISE                         0
        266     COPY                            3
        268     POP_EXCEPT                      
        270     RERAISE                         1
        272     PUSH_NULL                       
        274     LOAD_CONST                      19: '__pyarmor_exit_16886__'
        276     LOAD_CONST                      2: b'<COAddr>\x05\x00\x00\x1a\xda\x00\x00\x00\x00\x00\x00\x00\x00\x00\x00\x00\x00\x00\x00\x00'
        278     BUILD_TUPLE                     1
        280     CALL_FUNCTION_EX                0
        282     POP_TOP                         
        284     RETURN_VALUE                    
    [Exception Table]
        26 to 224 -> 244 [0] 
        244 to 266 -> 266 [1] lasti
