#decoded by lolz.live/mrpenny / t.me/zeus_jackpot
# ================================
# Примечания по Pyarmor:
# - Байт-код и объекты кода Pyarmor соответствуют стандартному Python, но присутствуют специальные вызовы функций среды выполнения (runtime) Pyarmor.
# - Вызовы строк — это не ошибки, а маркеры, которые обрабатываются Pyarmor во время выполнения.
#
# Руководство по декомпиляции (без среды выполнения):
# 1. Игнорируйте зашифрованные байты после `#`; используйте только строку до `#`.
# 2. Удалите "__pyarmor_enter_xxx__"(b"<COAddr>...") и "__pyarmor_leave_xxx__"(b"<COAddr>...") (пролог/эпилог).
# 3. "__pyarmor_assert_xxx__"(A) не является настоящим оператором assert.
#    - Если A — это имя или читаемая строка: замените на A.
#    - Если A — это (X, "Y"): замените на X.Y.
#    - Если A — это (X, "Y", Z): замените на X.Y = Z.
#    - В противном случае: выберите наиболее подходящую/логичную замену.
# 4. "__pyarmor_bcc_xxx__"(...) указывает на машинный (нативный) код; тело функции недоступно. Добавьте комментарий.
# ================================

[Code]
    File Name: <frozen multithon.tl.functions.langpack>
    Object Name: <module>
    Qualified Name: <module>
    Arg Count: 0
    Pos Only Arg Count: 0
    KW Only Arg Count: 0
    Stack Size: 5
    Flags: 0x20000000 (CO_PYARMOR_OBFUSCATED)
    [Names]
        '__assert_armored__'
        'tl.tlobject'
        'TLObject'
        'TLRequest'
        'typing'
        'Optional'
        'List'
        'Union'
        'TYPE_CHECKING'
        'os'
        'struct'
        'datetime'
        'GetDifferenceRequest'
        'GetLangPackRequest'
        'GetLangPack_tdlib_Request'
        'GetLanguageRequest'
        'GetLanguagesRequest'
        'GetLanguages_tdlib_Request'
        'GetStringsRequest'
    [Locals+Names]
    [Constants]
        '__pyarmor_assert_29472__'
        '__pyarmor_enter_29473__'
        b'<COAddr>\x07\x00\x00\x1a\n\x01\x00\x00\x00\x00\x00\x00\x00\x00\x00\x00\x00\x00\x00\x00'
        "File generated by TLObjects' generator. All changes will be ERASED"   # b'\x81\xc4\x11\x1f6\xba\xb9\xd7\x15\xff\x1f\xc1x\xe9\xfc\xc5\rD\xfb\x93\x86\xe4L\xc6\x00l\xb7OG\xf1\x19\xe04W2\x0c\x8c\xc5\xa6`X\xc8\xf4Q\x9d\xdb\x07F9\xeaS\xe8\xc7g\x0f\xe1;\xab\x99\x18Xn\x03rdm!'
        3
        (
            'TLObject'
        )
        (
            'TLRequest'
        )
        0
        (
            'Optional'
            'List'
            'Union'
            'TYPE_CHECKING'
        )
        None
        (
            'datetime'
        )
        [Code]
            File Name: <frozen multithon.tl.functions.langpack>
            Object Name: GetDifferenceRequest
            Qualified Name: GetDifferenceRequest
            Arg Count: 0
            Pos Only Arg Count: 0
            KW Only Arg Count: 0
            Stack Size: 6
            Flags: 0x20000000 (CO_PYARMOR_OBFUSCATED)
            [Names]
                '__name__'
                '__module__'
                '__qualname__'
                '__assert_armored__'
                'CONSTRUCTOR_ID'
                'SUBCLASS_OF_ID'
                'str'
                'int'
                '__init__'
                'to_dict'
                '_bytes'
                'classmethod'
                'from_reader'
            [Locals+Names]
            [Constants]
                'GetDifferenceRequest'
                '__pyarmor_assert_29475__'
                '__pyarmor_enter_29476__'
                b'<COAddr>\x05\x00\x00"N\x00\x00\x00\x00\x00\x00\x00\x00\x00\x00\x00\x00\x00\x00\x00'
                0xCD984AA5
                1382427989
                'lang_pack'
                'lang_code'
                'from_version'
                [Code]
                    File Name: <frozen multithon.tl.functions.langpack>
                    Object Name: __init__
                    Qualified Name: GetDifferenceRequest.__init__
                    Arg Count: 4
                    Pos Only Arg Count: 0
                    KW Only Arg Count: 0
                    Stack Size: 5
                    Flags: 0x20000003 (CO_OPTIMIZED | CO_NEWLOCALS | CO_PYARMOR_OBFUSCATED)
                    [Names]
                        'lang_pack'
                        'lang_code'
                        'from_version'
                    [Locals+Names]
                        'self'
                        'lang_pack'
                        'lang_code'
                        'from_version'
                        '__assert_armored__'
                    [Constants]
                        '\n        :returns LangPackDifference: Instance of LangPackDifference.\n        '
                        '__pyarmor_assert_29478__'
                        '__pyarmor_enter_29479__'
                        b'<COAddr>\x07\x00\x00\x1a@\x00\x00\x00\x00\x00\x00\x00\x00\x00\x00\x00\x00\x00\x00\x00'
                        '__pyarmor_exit_29480__'
                        None
                    [Disassembly]
                        0       NOP                             
                        2       NOP                             
                        4       PUSH_NULL                       
                        6       LOAD_CONST                      2: '__pyarmor_enter_29479__'
                        8       LOAD_CONST                      3: b'<COAddr>\x07\x00\x00\x1a@\x00\x00\x00\x00\x00\x00\x00\x00\x00\x00\x00\x00\x00\x00\x00'
                        10      BUILD_TUPLE                     1
                        12      CALL_FUNCTION_EX                0
                        14      POP_TOP                         
                        16      RESUME                          0
                        18      NOP                             
                        20      NOP                             
                        22      NOP                             
                        24      NOP                             
                        26      NOP                             
                        28      LOAD_FAST                       1: lang_pack
                        30      LOAD_FAST                       0: self
                        32      STORE_ATTR                      0: lang_pack
                        42      LOAD_FAST                       2: lang_code
                        44      LOAD_FAST                       0: self
                        46      STORE_ATTR                      1: lang_code
                        56      LOAD_FAST                       3: from_version
                        58      LOAD_FAST                       0: self
                        60      STORE_ATTR                      2: from_version
                        70      LOAD_CONST                      5: None
                        72      NOP                             
                        74      NOP                             
                        76      NOP                             
                        78      JUMP_FORWARD                    19 (to 118)
                        86      POP_TOP                         
                        88      RETURN_CONST                    5: None
                        90      PUSH_EXC_INFO                   
                        92      PUSH_NULL                       
                        94      LOAD_CONST                      4: '__pyarmor_exit_29480__'
                        96      NOP                             
                        98      LOAD_CONST                      3: b'<COAddr>\x07\x00\x00\x1a@\x00\x00\x00\x00\x00\x00\x00\x00\x00\x00\x00\x00\x00\x00\x00'
                        100     CALL                            1
                        108     POP_TOP                         
                        110     RERAISE                         0
                        112     COPY                            3
                        114     POP_EXCEPT                      
                        116     RERAISE                         1
                        118     PUSH_NULL                       
                        120     LOAD_CONST                      4: '__pyarmor_exit_29480__'
                        122     LOAD_CONST                      3: b'<COAddr>\x07\x00\x00\x1a@\x00\x00\x00\x00\x00\x00\x00\x00\x00\x00\x00\x00\x00\x00\x00'
                        124     BUILD_TUPLE                     1
                        126     CALL_FUNCTION_EX                0
                        128     POP_TOP                         
                        130     RETURN_VALUE                    
                    [Exception Table]
                        28 to 70 -> 90 [0] 
                        90 to 112 -> 112 [1] lasti
                [Code]
                    File Name: <frozen multithon.tl.functions.langpack>
                    Object Name: to_dict
                    Qualified Name: GetDifferenceRequest.to_dict
                    Arg Count: 1
                    Pos Only Arg Count: 0
                    KW Only Arg Count: 0
                    Stack Size: 9
                    Flags: 0x20000003 (CO_OPTIMIZED | CO_NEWLOCALS | CO_PYARMOR_OBFUSCATED)
                    [Names]
                        'lang_pack'
                        'lang_code'
                        'from_version'
                    [Locals+Names]
                        'self'
                        '__assert_armored__'
                    [Constants]
                        None
                        '__pyarmor_assert_29481__'
                        '__pyarmor_enter_29482__'
                        b'<COAddr>\x07\x00\x00\x1a\x94\x00\x00\x00\x00\x00\x00\x00\x00\x00\x00\x00\x00\x00\x00\x00'
                        '_'
                        'GetDifferenceRequest'   # b'\x81\xc5\x1d\x07\x17\xf3\xb8\xd4\x1e\xe8\x08\xceo\xe9\xca\x80\x1eH\xbe\xb4\xbe'
                        'lang_pack'   # b'\x81\xee\x19\x1d4\xc5\xae\xd3\x18\xf1'
                        'lang_code'   # b'\x81\xee\x19\x1d4\xc5\xbd\xdd\x1f\xff'
                        'from_version'   # b'\x81\xe4\n\x1c>\xc5\xa8\xd7\t\xe9\x04\xcfb'
                        '__pyarmor_exit_29483__'
                    [Disassembly]
                        0       NOP                             
                        2       NOP                             
                        4       PUSH_NULL                       
                        6       LOAD_CONST                      2: '__pyarmor_enter_29482__'
                        8       LOAD_CONST                      3: b'<COAddr>\x07\x00\x00\x1a\x94\x00\x00\x00\x00\x00\x00\x00\x00\x00\x00\x00\x00\x00\x00\x00'
                        10      BUILD_TUPLE                     1
                        12      CALL_FUNCTION_EX                0
                        14      POP_TOP                         
                        16      RESUME                          0
                        18      NOP                             
                        20      NOP                             
                        22      NOP                             
                        24      NOP                             
                        26      NOP                             
                        28      LOAD_CONST                      4: '_'
                        30      PUSH_NULL                       
                        32      LOAD_CONST                      1: '__pyarmor_assert_29481__'
                        34      LOAD_CONST                      5: 'GetDifferenceRequest'   # b'\x81\xc5\x1d\x07\x17\xf3\xb8\xd4\x1e\xe8\x08\xceo\xe9\xca\x80\x1eH\xbe\xb4\xbe'
                        36      CALL                            1
                        44      PUSH_NULL                       
                        46      LOAD_CONST                      1: '__pyarmor_assert_29481__'
                        48      LOAD_CONST                      6: 'lang_pack'   # b'\x81\xee\x19\x1d4\xc5\xae\xd3\x18\xf1'
                        50      CALL                            1
                        58      LOAD_FAST                       0: self
                        60      LOAD_ATTR                       0: lang_pack
                        80      PUSH_NULL                       
                        82      LOAD_CONST                      1: '__pyarmor_assert_29481__'
                        84      LOAD_CONST                      7: 'lang_code'   # b'\x81\xee\x19\x1d4\xc5\xbd\xdd\x1f\xff'
                        86      CALL                            1
                        94      LOAD_FAST                       0: self
                        96      LOAD_ATTR                       2: lang_code
                        116     PUSH_NULL                       
                        118     LOAD_CONST                      1: '__pyarmor_assert_29481__'
                        120     LOAD_CONST                      8: 'from_version'   # b'\x81\xe4\n\x1c>\xc5\xa8\xd7\t\xe9\x04\xcfb'
                        122     CALL                            1
                        130     LOAD_FAST                       0: self
                        132     LOAD_ATTR                       4: from_version
                        152     BUILD_MAP                       4
                        154     NOP                             
                        156     NOP                             
                        158     NOP                             
                        160     JUMP_FORWARD                    20 (to 202)
                        162     CALL                            1
                        170     POP_TOP                         
                        172     RETURN_VALUE                    
                        174     PUSH_EXC_INFO                   
                        176     PUSH_NULL                       
                        178     LOAD_CONST                      9: '__pyarmor_exit_29483__'
                        180     NOP                             
                        182     LOAD_CONST                      3: b'<COAddr>\x07\x00\x00\x1a\x94\x00\x00\x00\x00\x00\x00\x00\x00\x00\x00\x00\x00\x00\x00\x00'
                        184     CALL                            1
                        192     POP_TOP                         
                        194     RERAISE                         0
                        196     COPY                            3
                        198     POP_EXCEPT                      
                        200     RERAISE                         1
                        202     PUSH_NULL                       
                        204     LOAD_CONST                      9: '__pyarmor_exit_29483__'
                        206     LOAD_CONST                      3: b'<COAddr>\x07\x00\x00\x1a\x94\x00\x00\x00\x00\x00\x00\x00\x00\x00\x00\x00\x00\x00\x00\x00'
                        208     BUILD_TUPLE                     1
                        210     CALL_FUNCTION_EX                0
                        212     POP_TOP                         
                        214     RETURN_VALUE                    
                    [Exception Table]
                        28 to 154 -> 174 [0] 
                        174 to 196 -> 196 [1] lasti
                [Code]
                    File Name: <frozen multithon.tl.functions.langpack>
                    Object Name: _bytes
                    Qualified Name: GetDifferenceRequest._bytes
                    Arg Count: 1
                    Pos Only Arg Count: 0
                    KW Only Arg Count: 0
                    Stack Size: 9
                    Flags: 0x20000003 (CO_OPTIMIZED | CO_NEWLOCALS | CO_PYARMOR_OBFUSCATED)
                    [Names]
                        'join'
                        'serialize_bytes'
                        'lang_pack'
                        'lang_code'
                        'struct'
                        'pack'
                        'from_version'
                    [Locals+Names]
                        'self'
                        '__assert_armored__'
                    [Constants]
                        None
                        '__pyarmor_assert_29484__'
                        '__pyarmor_enter_29485__'
                        b'<COAddr>\x07\x00\x00\x1a\xde\x00\x00\x00\x00\x00\x00\x00\x00\x00\x00\x00\x00\x00\x00\x00'
                        b''
                        b'\xa5J\x98\xcd'
                        '<i'
                        '__pyarmor_exit_29486__'
                    [Disassembly]
                        0       NOP                             
                        2       NOP                             
                        4       PUSH_NULL                       
                        6       LOAD_CONST                      2: '__pyarmor_enter_29485__'
                        8       LOAD_CONST                      3: b'<COAddr>\x07\x00\x00\x1a\xde\x00\x00\x00\x00\x00\x00\x00\x00\x00\x00\x00\x00\x00\x00\x00'
                        10      BUILD_TUPLE                     1
                        12      CALL_FUNCTION_EX                0
                        14      POP_TOP                         
                        16      RESUME                          0
                        18      NOP                             
                        20      NOP                             
                        22      NOP                             
                        24      NOP                             
                        26      NOP                             
                        28      LOAD_CONST                      4: b''
                        30      LOAD_ATTR                       1: join
                        50      LOAD_CONST                      5: b'\xa5J\x98\xcd'
                        52      LOAD_FAST                       0: self
                        54      LOAD_ATTR                       3: serialize_bytes
                        74      LOAD_FAST                       0: self
                        76      LOAD_ATTR                       4: lang_pack
                        96      CALL                            1
                        104     LOAD_FAST                       0: self
                        106     LOAD_ATTR                       3: serialize_bytes
                        126     LOAD_FAST                       0: self
                        128     LOAD_ATTR                       6: lang_code
                        148     CALL                            1
                        156     LOAD_GLOBAL                     9: NULL + struct
                        166     LOAD_ATTR                       10: pack
                        186     LOAD_CONST                      6: '<i'
                        188     LOAD_FAST                       0: self
                        190     LOAD_ATTR                       12: from_version
                        210     CALL                            2
                        218     BUILD_TUPLE                     4
                        220     CALL                            1
                        228     NOP                             
                        230     NOP                             
                        232     NOP                             
                        234     JUMP_FORWARD                    20 (to 276)
                        236     CALL                            1
                        244     POP_TOP                         
                        246     RETURN_VALUE                    
                        248     PUSH_EXC_INFO                   
                        250     PUSH_NULL                       
                        252     LOAD_CONST                      7: '__pyarmor_exit_29486__'
                        254     NOP                             
                        256     LOAD_CONST                      3: b'<COAddr>\x07\x00\x00\x1a\xde\x00\x00\x00\x00\x00\x00\x00\x00\x00\x00\x00\x00\x00\x00\x00'
                        258     CALL                            1
                        266     POP_TOP                         
                        268     RERAISE                         0
                        270     COPY                            3
                        272     POP_EXCEPT                      
                        274     RERAISE                         1
                        276     PUSH_NULL                       
                        278     LOAD_CONST                      7: '__pyarmor_exit_29486__'
                        280     LOAD_CONST                      3: b'<COAddr>\x07\x00\x00\x1a\xde\x00\x00\x00\x00\x00\x00\x00\x00\x00\x00\x00\x00\x00\x00\x00'
                        282     BUILD_TUPLE                     1
                        284     CALL_FUNCTION_EX                0
                        286     POP_TOP                         
                        288     RETURN_VALUE                    
                    [Exception Table]
                        28 to 228 -> 248 [0] 
                        248 to 270 -> 270 [1] lasti
                [Code]
                    File Name: <frozen multithon.tl.functions.langpack>
                    Object Name: from_reader
                    Qualified Name: GetDifferenceRequest.from_reader
                    Arg Count: 2
                    Pos Only Arg Count: 0
                    KW Only Arg Count: 0
                    Stack Size: 5
                    Flags: 0x20000003 (CO_OPTIMIZED | CO_NEWLOCALS | CO_PYARMOR_OBFUSCATED)
                    [Names]
                        'tgread_string'
                        'read_int'
                    [Locals+Names]
                        'cls'
                        'reader'
                        '__assert_armored__'
                        '_var_var_0'
                        '_var_var_1'
                        '_var_var_2'
                    [Constants]
                        None
                        '__pyarmor_assert_29487__'
                        '__pyarmor_enter_29488__'
                        b'<COAddr>\x05\x00\x00\x1a\x8a\x00\x00\x00\x00\x00\x00\x00\x00\x00\x00\x00\x00\x00\x00\x00'
                        (
                            'lang_pack'
                            'lang_code'
                            'from_version'
                        )
                        '__pyarmor_exit_29489__'
                    [Disassembly]
                        0       NOP                             
                        2       NOP                             
                        4       PUSH_NULL                       
                        6       LOAD_CONST                      2: '__pyarmor_enter_29488__'
                        8       LOAD_CONST                      3: b'<COAddr>\x05\x00\x00\x1a\x8a\x00\x00\x00\x00\x00\x00\x00\x00\x00\x00\x00\x00\x00\x00\x00'
                        10      BUILD_TUPLE                     1
                        12      CALL_FUNCTION_EX                0
                        14      POP_TOP                         
                        16      RESUME                          0
                        18      NOP                             
                        20      NOP                             
                        22      NOP                             
                        24      NOP                             
                        26      NOP                             
                        28      LOAD_FAST                       1: reader
                        30      LOAD_ATTR                       1: tgread_string
                        50      CALL                            0
                        58      STORE_FAST                      3: _var_var_0
                        60      LOAD_FAST                       1: reader
                        62      LOAD_ATTR                       1: tgread_string
                        82      CALL                            0
                        90      STORE_FAST                      4: _var_var_1
                        92      LOAD_FAST                       1: reader
                        94      LOAD_ATTR                       3: read_int
                        114     CALL                            0
                        122     STORE_FAST                      5: _var_var_2
                        124     PUSH_NULL                       
                        126     LOAD_FAST                       0: cls
                        128     LOAD_FAST                       3: _var_var_0
                        130     LOAD_FAST                       4: _var_var_1
                        132     LOAD_FAST                       5: _var_var_2
                        134     KW_NAMES                        4: ('lang_pack', 'lang_code', 'from_version')
                        136     CALL                            3
                        144     NOP                             
                        146     NOP                             
                        148     NOP                             
                        150     JUMP_FORWARD                    20 (to 192)
                        152     CALL                            1
                        160     POP_TOP                         
                        162     RETURN_VALUE                    
                        164     PUSH_EXC_INFO                   
                        166     PUSH_NULL                       
                        168     LOAD_CONST                      5: '__pyarmor_exit_29489__'
                        170     NOP                             
                        172     LOAD_CONST                      3: b'<COAddr>\x05\x00\x00\x1a\x8a\x00\x00\x00\x00\x00\x00\x00\x00\x00\x00\x00\x00\x00\x00\x00'
                        174     CALL                            1
                        182     POP_TOP                         
                        184     RERAISE                         0
                        186     COPY                            3
                        188     POP_EXCEPT                      
                        190     RERAISE                         1
                        192     PUSH_NULL                       
                        194     LOAD_CONST                      5: '__pyarmor_exit_29489__'
                        196     LOAD_CONST                      3: b'<COAddr>\x05\x00\x00\x1a\x8a\x00\x00\x00\x00\x00\x00\x00\x00\x00\x00\x00\x00\x00\x00\x00'
                        198     BUILD_TUPLE                     1
                        200     CALL_FUNCTION_EX                0
                        202     POP_TOP                         
                        204     RETURN_VALUE                    
                    [Exception Table]
                        28 to 144 -> 164 [0] 
                        164 to 186 -> 186 [1] lasti
                '__pyarmor_exit_29477__'
                None
            [Disassembly]
                0       NOP                             
                2       LOAD_NAME                       0: __name__
                4       STORE_NAME                      1: __module__
                6       LOAD_CONST                      0: 'GetDifferenceRequest'
                8       STORE_NAME                      2: __qualname__
                10      NOP                             
                12      PUSH_NULL                       
                14      LOAD_CONST                      2: '__pyarmor_enter_29476__'
                16      LOAD_CONST                      3: b'<COAddr>\x05\x00\x00"N\x00\x00\x00\x00\x00\x00\x00\x00\x00\x00\x00\x00\x00\x00\x00'
                18      BUILD_TUPLE                     1
                20      CALL_FUNCTION_EX                0
                22      POP_TOP                         
                24      RESUME                          0
                26      NOP                             
                28      NOP                             
                30      NOP                             
                32      NOP                             
                34      NOP                             
                36      LOAD_CONST                      4: 0xCD984AA5
                38      STORE_NAME                      4: CONSTRUCTOR_ID
                40      LOAD_CONST                      5: 1382427989
                42      STORE_NAME                      5: SUBCLASS_OF_ID
                44      LOAD_CONST                      6: 'lang_pack'
                46      LOAD_NAME                       6: str
                48      LOAD_CONST                      7: 'lang_code'
                50      LOAD_NAME                       6: str
                52      LOAD_CONST                      8: 'from_version'
                54      LOAD_NAME                       7: int
                56      BUILD_TUPLE                     6
                58      LOAD_CONST                      9: <CODE> __init__
                60      MAKE_FUNCTION                   4
                62      STORE_NAME                      8: __init__
                64      LOAD_CONST                      10: <CODE> to_dict
                66      MAKE_FUNCTION                   0
                68      STORE_NAME                      9: to_dict
                70      LOAD_CONST                      11: <CODE> _bytes
                72      MAKE_FUNCTION                   0
                74      STORE_NAME                      10: _bytes
                76      LOAD_NAME                       11: classmethod
                78      LOAD_CONST                      12: <CODE> from_reader
                80      MAKE_FUNCTION                   0
                82      CALL                            0
                90      STORE_NAME                      12: from_reader
                92      LOAD_CONST                      14: None
                94      NOP                             
                96      NOP                             
                98      NOP                             
                100     JUMP_FORWARD                    19 (to 140)
                108     POP_TOP                         
                110     RETURN_CONST                    14: None
                112     PUSH_EXC_INFO                   
                114     PUSH_NULL                       
                116     LOAD_CONST                      13: '__pyarmor_exit_29477__'
                118     NOP                             
                120     LOAD_CONST                      3: b'<COAddr>\x05\x00\x00"N\x00\x00\x00\x00\x00\x00\x00\x00\x00\x00\x00\x00\x00\x00\x00'
                122     CALL                            1
                130     POP_TOP                         
                132     RERAISE                         0
                134     COPY                            3
                136     POP_EXCEPT                      
                138     RERAISE                         1
                140     PUSH_NULL                       
                142     LOAD_CONST                      13: '__pyarmor_exit_29477__'
                144     LOAD_CONST                      3: b'<COAddr>\x05\x00\x00"N\x00\x00\x00\x00\x00\x00\x00\x00\x00\x00\x00\x00\x00\x00\x00'
                146     BUILD_TUPLE                     1
                148     CALL_FUNCTION_EX                0
                150     POP_TOP                         
                152     RETURN_VALUE                    
            [Exception Table]
                36 to 92 -> 112 [0] 
                112 to 134 -> 134 [1] lasti
        'GetDifferenceRequest'
        [Code]
            File Name: <frozen multithon.tl.functions.langpack>
            Object Name: GetLangPackRequest
            Qualified Name: GetLangPackRequest
            Arg Count: 0
            Pos Only Arg Count: 0
            KW Only Arg Count: 0
            Stack Size: 5
            Flags: 0x20000000 (CO_PYARMOR_OBFUSCATED)
            [Names]
                '__name__'
                '__module__'
                '__qualname__'
                '__assert_armored__'
                'CONSTRUCTOR_ID'
                'SUBCLASS_OF_ID'
                'str'
                '__init__'
                'to_dict'
                '_bytes'
                'classmethod'
                'from_reader'
            [Locals+Names]
            [Constants]
                'GetLangPackRequest'
                '__pyarmor_assert_29490__'
                '__pyarmor_enter_29491__'
                b'<COAddr>\x05\x00\x00"F\x00\x00\x00\x00\x00\x00\x00\x00\x00\x00\x00\x00\x00\x00\x00'
                0x9AB5C58E
                1382427989
                'lang_code'
                [Code]
                    File Name: <frozen multithon.tl.functions.langpack>
                    Object Name: __init__
                    Qualified Name: GetLangPackRequest.__init__
                    Arg Count: 2
                    Pos Only Arg Count: 0
                    KW Only Arg Count: 0
                    Stack Size: 5
                    Flags: 0x20000003 (CO_OPTIMIZED | CO_NEWLOCALS | CO_PYARMOR_OBFUSCATED)
                    [Names]
                        'lang_code'
                    [Locals+Names]
                        'self'
                        'lang_code'
                        '__assert_armored__'
                    [Constants]
                        '\n        :returns LangPackDifference: Instance of LangPackDifference.\n        '
                        '__pyarmor_assert_29493__'
                        '__pyarmor_enter_29494__'
                        b'<COAddr>\x07\x00\x00\x1a$\x00\x00\x00\x00\x00\x00\x00\x00\x00\x00\x00\x00\x00\x00\x00'
                        '__pyarmor_exit_29495__'
                        None
                    [Disassembly]
                        0       NOP                             
                        2       NOP                             
                        4       PUSH_NULL                       
                        6       LOAD_CONST                      2: '__pyarmor_enter_29494__'
                        8       LOAD_CONST                      3: b'<COAddr>\x07\x00\x00\x1a$\x00\x00\x00\x00\x00\x00\x00\x00\x00\x00\x00\x00\x00\x00\x00'
                        10      BUILD_TUPLE                     1
                        12      CALL_FUNCTION_EX                0
                        14      POP_TOP                         
                        16      RESUME                          0
                        18      NOP                             
                        20      NOP                             
                        22      NOP                             
                        24      NOP                             
                        26      NOP                             
                        28      LOAD_FAST                       1: lang_code
                        30      LOAD_FAST                       0: self
                        32      STORE_ATTR                      0: lang_code
                        42      LOAD_CONST                      5: None
                        44      NOP                             
                        46      NOP                             
                        48      NOP                             
                        50      JUMP_FORWARD                    19 (to 90)
                        58      POP_TOP                         
                        60      RETURN_CONST                    5: None
                        62      PUSH_EXC_INFO                   
                        64      PUSH_NULL                       
                        66      LOAD_CONST                      4: '__pyarmor_exit_29495__'
                        68      NOP                             
                        70      LOAD_CONST                      3: b'<COAddr>\x07\x00\x00\x1a$\x00\x00\x00\x00\x00\x00\x00\x00\x00\x00\x00\x00\x00\x00\x00'
                        72      CALL                            1
                        80      POP_TOP                         
                        82      RERAISE                         0
                        84      COPY                            3
                        86      POP_EXCEPT                      
                        88      RERAISE                         1
                        90      PUSH_NULL                       
                        92      LOAD_CONST                      4: '__pyarmor_exit_29495__'
                        94      LOAD_CONST                      3: b'<COAddr>\x07\x00\x00\x1a$\x00\x00\x00\x00\x00\x00\x00\x00\x00\x00\x00\x00\x00\x00\x00'
                        96      BUILD_TUPLE                     1
                        98      CALL_FUNCTION_EX                0
                        100     POP_TOP                         
                        102     RETURN_VALUE                    
                    [Exception Table]
                        28 to 42 -> 62 [0] 
                        62 to 84 -> 84 [1] lasti
                [Code]
                    File Name: <frozen multithon.tl.functions.langpack>
                    Object Name: to_dict
                    Qualified Name: GetLangPackRequest.to_dict
                    Arg Count: 1
                    Pos Only Arg Count: 0
                    KW Only Arg Count: 0
                    Stack Size: 5
                    Flags: 0x20000003 (CO_OPTIMIZED | CO_NEWLOCALS | CO_PYARMOR_OBFUSCATED)
                    [Names]
                        'lang_code'
                    [Locals+Names]
                        'self'
                        '__assert_armored__'
                    [Constants]
                        None
                        '__pyarmor_assert_29496__'
                        '__pyarmor_enter_29497__'
                        b'<COAddr>\x07\x00\x00\x1aL\x00\x00\x00\x00\x00\x00\x00\x00\x00\x00\x00\x00\x00\x00\x00'
                        '_'
                        'GetLangPackRequest'   # b'\x81\xc5\x1d\x07\x1f\xfb\xb0\xd5+\xfb\x0e\xcb^\xe9\xe9\x90\nN\xaf'
                        'lang_code'   # b'\x81\xee\x19\x1d4\xc5\xbd\xdd\x1f\xff'
                        '__pyarmor_exit_29498__'
                    [Disassembly]
                        0       NOP                             
                        2       NOP                             
                        4       PUSH_NULL                       
                        6       LOAD_CONST                      2: '__pyarmor_enter_29497__'
                        8       LOAD_CONST                      3: b'<COAddr>\x07\x00\x00\x1aL\x00\x00\x00\x00\x00\x00\x00\x00\x00\x00\x00\x00\x00\x00\x00'
                        10      BUILD_TUPLE                     1
                        12      CALL_FUNCTION_EX                0
                        14      POP_TOP                         
                        16      RESUME                          0
                        18      NOP                             
                        20      NOP                             
                        22      NOP                             
                        24      NOP                             
                        26      NOP                             
                        28      LOAD_CONST                      4: '_'
                        30      PUSH_NULL                       
                        32      LOAD_CONST                      1: '__pyarmor_assert_29496__'
                        34      LOAD_CONST                      5: 'GetLangPackRequest'   # b'\x81\xc5\x1d\x07\x1f\xfb\xb0\xd5+\xfb\x0e\xcb^\xe9\xe9\x90\nN\xaf'
                        36      CALL                            1
                        44      PUSH_NULL                       
                        46      LOAD_CONST                      1: '__pyarmor_assert_29496__'
                        48      LOAD_CONST                      6: 'lang_code'   # b'\x81\xee\x19\x1d4\xc5\xbd\xdd\x1f\xff'
                        50      CALL                            1
                        58      LOAD_FAST                       0: self
                        60      LOAD_ATTR                       0: lang_code
                        80      BUILD_MAP                       2
                        82      NOP                             
                        84      NOP                             
                        86      NOP                             
                        88      JUMP_FORWARD                    20 (to 130)
                        90      CALL                            1
                        98      POP_TOP                         
                        100     RETURN_VALUE                    
                        102     PUSH_EXC_INFO                   
                        104     PUSH_NULL                       
                        106     LOAD_CONST                      7: '__pyarmor_exit_29498__'
                        108     NOP                             
                        110     LOAD_CONST                      3: b'<COAddr>\x07\x00\x00\x1aL\x00\x00\x00\x00\x00\x00\x00\x00\x00\x00\x00\x00\x00\x00\x00'
                        112     CALL                            1
                        120     POP_TOP                         
                        122     RERAISE                         0
                        124     COPY                            3
                        126     POP_EXCEPT                      
                        128     RERAISE                         1
                        130     PUSH_NULL                       
                        132     LOAD_CONST                      7: '__pyarmor_exit_29498__'
                        134     LOAD_CONST                      3: b'<COAddr>\x07\x00\x00\x1aL\x00\x00\x00\x00\x00\x00\x00\x00\x00\x00\x00\x00\x00\x00\x00'
                        136     BUILD_TUPLE                     1
                        138     CALL_FUNCTION_EX                0
                        140     POP_TOP                         
                        142     RETURN_VALUE                    
                    [Exception Table]
                        28 to 82 -> 102 [0] 
                        102 to 124 -> 124 [1] lasti
                [Code]
                    File Name: <frozen multithon.tl.functions.langpack>
                    Object Name: _bytes
                    Qualified Name: GetLangPackRequest._bytes
                    Arg Count: 1
                    Pos Only Arg Count: 0
                    KW Only Arg Count: 0
                    Stack Size: 6
                    Flags: 0x20000003 (CO_OPTIMIZED | CO_NEWLOCALS | CO_PYARMOR_OBFUSCATED)
                    [Names]
                        'join'
                        'serialize_bytes'
                        'lang_code'
                    [Locals+Names]
                        'self'
                        '__assert_armored__'
                    [Constants]
                        None
                        '__pyarmor_assert_29499__'
                        '__pyarmor_enter_29500__'
                        b'<COAddr>\x07\x00\x00\x1al\x00\x00\x00\x00\x00\x00\x00\x00\x00\x00\x00\x00\x00\x00\x00'
                        b''
                        b'\x8e\xc5\xb5\x9a'
                        '__pyarmor_exit_29501__'
                    [Disassembly]
                        0       NOP                             
                        2       NOP                             
                        4       PUSH_NULL                       
                        6       LOAD_CONST                      2: '__pyarmor_enter_29500__'
                        8       LOAD_CONST                      3: b'<COAddr>\x07\x00\x00\x1al\x00\x00\x00\x00\x00\x00\x00\x00\x00\x00\x00\x00\x00\x00\x00'
                        10      BUILD_TUPLE                     1
                        12      CALL_FUNCTION_EX                0
                        14      POP_TOP                         
                        16      RESUME                          0
                        18      NOP                             
                        20      NOP                             
                        22      NOP                             
                        24      NOP                             
                        26      NOP                             
                        28      LOAD_CONST                      4: b''
                        30      LOAD_ATTR                       1: join
                        50      LOAD_CONST                      5: b'\x8e\xc5\xb5\x9a'
                        52      LOAD_FAST                       0: self
                        54      LOAD_ATTR                       3: serialize_bytes
                        74      LOAD_FAST                       0: self
                        76      LOAD_ATTR                       4: lang_code
                        96      CALL                            1
                        104     BUILD_TUPLE                     2
                        106     CALL                            1
                        114     NOP                             
                        116     NOP                             
                        118     NOP                             
                        120     JUMP_FORWARD                    20 (to 162)
                        122     CALL                            1
                        130     POP_TOP                         
                        132     RETURN_VALUE                    
                        134     PUSH_EXC_INFO                   
                        136     PUSH_NULL                       
                        138     LOAD_CONST                      6: '__pyarmor_exit_29501__'
                        140     NOP                             
                        142     LOAD_CONST                      3: b'<COAddr>\x07\x00\x00\x1al\x00\x00\x00\x00\x00\x00\x00\x00\x00\x00\x00\x00\x00\x00\x00'
                        144     CALL                            1
                        152     POP_TOP                         
                        154     RERAISE                         0
                        156     COPY                            3
                        158     POP_EXCEPT                      
                        160     RERAISE                         1
                        162     PUSH_NULL                       
                        164     LOAD_CONST                      6: '__pyarmor_exit_29501__'
                        166     LOAD_CONST                      3: b'<COAddr>\x07\x00\x00\x1al\x00\x00\x00\x00\x00\x00\x00\x00\x00\x00\x00\x00\x00\x00\x00'
                        168     BUILD_TUPLE                     1
                        170     CALL_FUNCTION_EX                0
                        172     POP_TOP                         
                        174     RETURN_VALUE                    
                    [Exception Table]
                        28 to 114 -> 134 [0] 
                        134 to 156 -> 156 [1] lasti
                [Code]
                    File Name: <frozen multithon.tl.functions.langpack>
                    Object Name: from_reader
                    Qualified Name: GetLangPackRequest.from_reader
                    Arg Count: 2
                    Pos Only Arg Count: 0
                    KW Only Arg Count: 0
                    Stack Size: 5
                    Flags: 0x20000003 (CO_OPTIMIZED | CO_NEWLOCALS | CO_PYARMOR_OBFUSCATED)
                    [Names]
                        'tgread_string'
                    [Locals+Names]
                        'cls'
                        'reader'
                        '__assert_armored__'
                        '_var_var_1'
                    [Constants]
                        None
                        '__pyarmor_assert_29502__'
                        '__pyarmor_enter_29503__'
                        b'<COAddr>\x05\x00\x00\x1aF\x00\x00\x00\x00\x00\x00\x00\x00\x00\x00\x00\x00\x00\x00\x00'
                        (
                            'lang_code'
                        )
                        '__pyarmor_exit_29504__'
                    [Disassembly]
                        0       NOP                             
                        2       NOP                             
                        4       PUSH_NULL                       
                        6       LOAD_CONST                      2: '__pyarmor_enter_29503__'
                        8       LOAD_CONST                      3: b'<COAddr>\x05\x00\x00\x1aF\x00\x00\x00\x00\x00\x00\x00\x00\x00\x00\x00\x00\x00\x00\x00'
                        10      BUILD_TUPLE                     1
                        12      CALL_FUNCTION_EX                0
                        14      POP_TOP                         
                        16      RESUME                          0
                        18      NOP                             
                        20      NOP                             
                        22      NOP                             
                        24      NOP                             
                        26      NOP                             
                        28      LOAD_FAST                       1: reader
                        30      LOAD_ATTR                       1: tgread_string
                        50      CALL                            0
                        58      STORE_FAST                      3: _var_var_1
                        60      PUSH_NULL                       
                        62      LOAD_FAST                       0: cls
                        64      LOAD_FAST                       3: _var_var_1
                        66      KW_NAMES                        4: ('lang_code',)
                        68      CALL                            1
                        76      NOP                             
                        78      NOP                             
                        80      NOP                             
                        82      JUMP_FORWARD                    20 (to 124)
                        84      CALL                            1
                        92      POP_TOP                         
                        94      RETURN_VALUE                    
                        96      PUSH_EXC_INFO                   
                        98      PUSH_NULL                       
                        100     LOAD_CONST                      5: '__pyarmor_exit_29504__'
                        102     NOP                             
                        104     LOAD_CONST                      3: b'<COAddr>\x05\x00\x00\x1aF\x00\x00\x00\x00\x00\x00\x00\x00\x00\x00\x00\x00\x00\x00\x00'
                        106     CALL                            1
                        114     POP_TOP                         
                        116     RERAISE                         0
                        118     COPY                            3
                        120     POP_EXCEPT                      
                        122     RERAISE                         1
                        124     PUSH_NULL                       
                        126     LOAD_CONST                      5: '__pyarmor_exit_29504__'
                        128     LOAD_CONST                      3: b'<COAddr>\x05\x00\x00\x1aF\x00\x00\x00\x00\x00\x00\x00\x00\x00\x00\x00\x00\x00\x00\x00'
                        130     BUILD_TUPLE                     1
                        132     CALL_FUNCTION_EX                0
                        134     POP_TOP                         
                        136     RETURN_VALUE                    
                    [Exception Table]
                        28 to 76 -> 96 [0] 
                        96 to 118 -> 118 [1] lasti
                '__pyarmor_exit_29492__'
                None
            [Disassembly]
                0       NOP                             
                2       LOAD_NAME                       0: __name__
                4       STORE_NAME                      1: __module__
                6       LOAD_CONST                      0: 'GetLangPackRequest'
                8       STORE_NAME                      2: __qualname__
                10      NOP                             
                12      PUSH_NULL                       
                14      LOAD_CONST                      2: '__pyarmor_enter_29491__'
                16      LOAD_CONST                      3: b'<COAddr>\x05\x00\x00"F\x00\x00\x00\x00\x00\x00\x00\x00\x00\x00\x00\x00\x00\x00\x00'
                18      BUILD_TUPLE                     1
                20      CALL_FUNCTION_EX                0
                22      POP_TOP                         
                24      RESUME                          0
                26      NOP                             
                28      NOP                             
                30      NOP                             
                32      NOP                             
                34      NOP                             
                36      LOAD_CONST                      4: 0x9AB5C58E
                38      STORE_NAME                      4: CONSTRUCTOR_ID
                40      LOAD_CONST                      5: 1382427989
                42      STORE_NAME                      5: SUBCLASS_OF_ID
                44      LOAD_CONST                      6: 'lang_code'
                46      LOAD_NAME                       6: str
                48      BUILD_TUPLE                     2
                50      LOAD_CONST                      7: <CODE> __init__
                52      MAKE_FUNCTION                   4
                54      STORE_NAME                      7: __init__
                56      LOAD_CONST                      8: <CODE> to_dict
                58      MAKE_FUNCTION                   0
                60      STORE_NAME                      8: to_dict
                62      LOAD_CONST                      9: <CODE> _bytes
                64      MAKE_FUNCTION                   0
                66      STORE_NAME                      9: _bytes
                68      LOAD_NAME                       10: classmethod
                70      LOAD_CONST                      10: <CODE> from_reader
                72      MAKE_FUNCTION                   0
                74      CALL                            0
                82      STORE_NAME                      11: from_reader
                84      LOAD_CONST                      12: None
                86      NOP                             
                88      NOP                             
                90      NOP                             
                92      JUMP_FORWARD                    19 (to 132)
                100     POP_TOP                         
                102     RETURN_CONST                    12: None
                104     PUSH_EXC_INFO                   
                106     PUSH_NULL                       
                108     LOAD_CONST                      11: '__pyarmor_exit_29492__'
                110     NOP                             
                112     LOAD_CONST                      3: b'<COAddr>\x05\x00\x00"F\x00\x00\x00\x00\x00\x00\x00\x00\x00\x00\x00\x00\x00\x00\x00'
                114     CALL                            1
                122     POP_TOP                         
                124     RERAISE                         0
                126     COPY                            3
                128     POP_EXCEPT                      
                130     RERAISE                         1
                132     PUSH_NULL                       
                134     LOAD_CONST                      11: '__pyarmor_exit_29492__'
                136     LOAD_CONST                      3: b'<COAddr>\x05\x00\x00"F\x00\x00\x00\x00\x00\x00\x00\x00\x00\x00\x00\x00\x00\x00\x00'
                138     BUILD_TUPLE                     1
                140     CALL_FUNCTION_EX                0
                142     POP_TOP                         
                144     RETURN_VALUE                    
            [Exception Table]
                36 to 84 -> 104 [0] 
                104 to 126 -> 126 [1] lasti
        'GetLangPackRequest'
        [Code]
            File Name: <frozen multithon.tl.functions.langpack>
            Object Name: GetLangPack_tdlib_Request
            Qualified Name: GetLangPack_tdlib_Request
            Arg Count: 0
            Pos Only Arg Count: 0
            KW Only Arg Count: 0
            Stack Size: 5
            Flags: 0x20000000 (CO_PYARMOR_OBFUSCATED)
            [Names]
                '__name__'
                '__module__'
                '__qualname__'
                '__assert_armored__'
                'CONSTRUCTOR_ID'
                'SUBCLASS_OF_ID'
                'str'
                '__init__'
                'to_dict'
                '_bytes'
                'classmethod'
                'from_reader'
            [Locals+Names]
            [Constants]
                'GetLangPack_tdlib_Request'
                '__pyarmor_assert_29505__'
                '__pyarmor_enter_29506__'
                b'<COAddr>\x05\x00\x00"J\x00\x00\x00\x00\x00\x00\x00\x00\x00\x00\x00\x00\x00\x00\x00'
                0xF2F2330A
                1382427989
                'lang_pack'
                'lang_code'
                [Code]
                    File Name: <frozen multithon.tl.functions.langpack>
                    Object Name: __init__
                    Qualified Name: GetLangPack_tdlib_Request.__init__
                    Arg Count: 3
                    Pos Only Arg Count: 0
                    KW Only Arg Count: 0
                    Stack Size: 5
                    Flags: 0x20000003 (CO_OPTIMIZED | CO_NEWLOCALS | CO_PYARMOR_OBFUSCATED)
                    [Names]
                        'lang_pack'
                        'lang_code'
                    [Locals+Names]
                        'self'
                        'lang_pack'
                        'lang_code'
                        '__assert_armored__'
                    [Constants]
                        '\n        :returns LangPackDifference: Instance of LangPackDifference.\n        '
                        '__pyarmor_assert_29508__'
                        '__pyarmor_enter_29509__'
                        b'<COAddr>\x05\x00\x00\x1a2\x00\x00\x00\x00\x00\x00\x00\x00\x00\x00\x00\x00\x00\x00\x00'
                        '__pyarmor_exit_29510__'
                        None
                    [Disassembly]
                        0       NOP                             
                        2       NOP                             
                        4       PUSH_NULL                       
                        6       LOAD_CONST                      2: '__pyarmor_enter_29509__'
                        8       LOAD_CONST                      3: b'<COAddr>\x05\x00\x00\x1a2\x00\x00\x00\x00\x00\x00\x00\x00\x00\x00\x00\x00\x00\x00\x00'
                        10      BUILD_TUPLE                     1
                        12      CALL_FUNCTION_EX                0
                        14      POP_TOP                         
                        16      RESUME                          0
                        18      NOP                             
                        20      NOP                             
                        22      NOP                             
                        24      NOP                             
                        26      NOP                             
                        28      LOAD_FAST                       1: lang_pack
                        30      LOAD_FAST                       0: self
                        32      STORE_ATTR                      0: lang_pack
                        42      LOAD_FAST                       2: lang_code
                        44      LOAD_FAST                       0: self
                        46      STORE_ATTR                      1: lang_code
                        56      LOAD_CONST                      5: None
                        58      NOP                             
                        60      NOP                             
                        62      NOP                             
                        64      JUMP_FORWARD                    19 (to 104)
                        72      POP_TOP                         
                        74      RETURN_CONST                    5: None
                        76      PUSH_EXC_INFO                   
                        78      PUSH_NULL                       
                        80      LOAD_CONST                      4: '__pyarmor_exit_29510__'
                        82      NOP                             
                        84      LOAD_CONST                      3: b'<COAddr>\x05\x00\x00\x1a2\x00\x00\x00\x00\x00\x00\x00\x00\x00\x00\x00\x00\x00\x00\x00'
                        86      CALL                            1
                        94      POP_TOP                         
                        96      RERAISE                         0
                        98      COPY                            3
                        100     POP_EXCEPT                      
                        102     RERAISE                         1
                        104     PUSH_NULL                       
                        106     LOAD_CONST                      4: '__pyarmor_exit_29510__'
                        108     LOAD_CONST                      3: b'<COAddr>\x05\x00\x00\x1a2\x00\x00\x00\x00\x00\x00\x00\x00\x00\x00\x00\x00\x00\x00\x00'
                        110     BUILD_TUPLE                     1
                        112     CALL_FUNCTION_EX                0
                        114     POP_TOP                         
                        116     RETURN_VALUE                    
                    [Exception Table]
                        28 to 56 -> 76 [0] 
                        76 to 98 -> 98 [1] lasti
                [Code]
                    File Name: <frozen multithon.tl.functions.langpack>
                    Object Name: to_dict
                    Qualified Name: GetLangPack_tdlib_Request.to_dict
                    Arg Count: 1
                    Pos Only Arg Count: 0
                    KW Only Arg Count: 0
                    Stack Size: 7
                    Flags: 0x20000003 (CO_OPTIMIZED | CO_NEWLOCALS | CO_PYARMOR_OBFUSCATED)
                    [Names]
                        'lang_pack'
                        'lang_code'
                    [Locals+Names]
                        'self'
                        '__assert_armored__'
                    [Constants]
                        None
                        '__pyarmor_assert_29511__'
                        '__pyarmor_enter_29512__'
                        b'<COAddr>\x05\x00\x00\x1ap\x00\x00\x00\x00\x00\x00\x00\x00\x00\x00\x00\x00\x00\x00\x00'
                        '_'
                        'GetLangPackRequest'   # b'\x81\xc5\x1d\x07\x1f\xfb\xb0\xd5+\xfb\x0e\xcb^\xe9\xe9\x90\nN\xaf'
                        'lang_pack'   # b'\x81\xee\x19\x1d4\xc5\xae\xd3\x18\xf1'
                        'lang_code'   # b'\x81\xee\x19\x1d4\xc5\xbd\xdd\x1f\xff'
                        '__pyarmor_exit_29513__'
                    [Disassembly]
                        0       NOP                             
                        2       NOP                             
                        4       PUSH_NULL                       
                        6       LOAD_CONST                      2: '__pyarmor_enter_29512__'
                        8       LOAD_CONST                      3: b'<COAddr>\x05\x00\x00\x1ap\x00\x00\x00\x00\x00\x00\x00\x00\x00\x00\x00\x00\x00\x00\x00'
                        10      BUILD_TUPLE                     1
                        12      CALL_FUNCTION_EX                0
                        14      POP_TOP                         
                        16      RESUME                          0
                        18      NOP                             
                        20      NOP                             
                        22      NOP                             
                        24      NOP                             
                        26      NOP                             
                        28      LOAD_CONST                      4: '_'
                        30      PUSH_NULL                       
                        32      LOAD_CONST                      1: '__pyarmor_assert_29511__'
                        34      LOAD_CONST                      5: 'GetLangPackRequest'   # b'\x81\xc5\x1d\x07\x1f\xfb\xb0\xd5+\xfb\x0e\xcb^\xe9\xe9\x90\nN\xaf'
                        36      CALL                            1
                        44      PUSH_NULL                       
                        46      LOAD_CONST                      1: '__pyarmor_assert_29511__'
                        48      LOAD_CONST                      6: 'lang_pack'   # b'\x81\xee\x19\x1d4\xc5\xae\xd3\x18\xf1'
                        50      CALL                            1
                        58      LOAD_FAST                       0: self
                        60      LOAD_ATTR                       0: lang_pack
                        80      PUSH_NULL                       
                        82      LOAD_CONST                      1: '__pyarmor_assert_29511__'
                        84      LOAD_CONST                      7: 'lang_code'   # b'\x81\xee\x19\x1d4\xc5\xbd\xdd\x1f\xff'
                        86      CALL                            1
                        94      LOAD_FAST                       0: self
                        96      LOAD_ATTR                       2: lang_code
                        116     BUILD_MAP                       3
                        118     NOP                             
                        120     NOP                             
                        122     NOP                             
                        124     JUMP_FORWARD                    20 (to 166)
                        126     CALL                            1
                        134     POP_TOP                         
                        136     RETURN_VALUE                    
                        138     PUSH_EXC_INFO                   
                        140     PUSH_NULL                       
                        142     LOAD_CONST                      8: '__pyarmor_exit_29513__'
                        144     NOP                             
                        146     LOAD_CONST                      3: b'<COAddr>\x05\x00\x00\x1ap\x00\x00\x00\x00\x00\x00\x00\x00\x00\x00\x00\x00\x00\x00\x00'
                        148     CALL                            1
                        156     POP_TOP                         
                        158     RERAISE                         0
                        160     COPY                            3
                        162     POP_EXCEPT                      
                        164     RERAISE                         1
                        166     PUSH_NULL                       
                        168     LOAD_CONST                      8: '__pyarmor_exit_29513__'
                        170     LOAD_CONST                      3: b'<COAddr>\x05\x00\x00\x1ap\x00\x00\x00\x00\x00\x00\x00\x00\x00\x00\x00\x00\x00\x00\x00'
                        172     BUILD_TUPLE                     1
                        174     CALL_FUNCTION_EX                0
                        176     POP_TOP                         
                        178     RETURN_VALUE                    
                    [Exception Table]
                        28 to 118 -> 138 [0] 
                        138 to 160 -> 160 [1] lasti
                [Code]
                    File Name: <frozen multithon.tl.functions.langpack>
                    Object Name: _bytes
                    Qualified Name: GetLangPack_tdlib_Request._bytes
                    Arg Count: 1
                    Pos Only Arg Count: 0
                    KW Only Arg Count: 0
                    Stack Size: 7
                    Flags: 0x20000003 (CO_OPTIMIZED | CO_NEWLOCALS | CO_PYARMOR_OBFUSCATED)
                    [Names]
                        'join'
                        'serialize_bytes'
                        'lang_pack'
                        'lang_code'
                    [Locals+Names]
                        'self'
                        '__assert_armored__'
                    [Constants]
                        None
                        '__pyarmor_assert_29514__'
                        '__pyarmor_enter_29515__'
                        b'<COAddr>\x05\x00\x00\x1a\xa0\x00\x00\x00\x00\x00\x00\x00\x00\x00\x00\x00\x00\x00\x00\x00'
                        b''
                        b'\n3\xf2\xf2'
                        '__pyarmor_exit_29516__'
                    [Disassembly]
                        0       NOP                             
                        2       NOP                             
                        4       PUSH_NULL                       
                        6       LOAD_CONST                      2: '__pyarmor_enter_29515__'
                        8       LOAD_CONST                      3: b'<COAddr>\x05\x00\x00\x1a\xa0\x00\x00\x00\x00\x00\x00\x00\x00\x00\x00\x00\x00\x00\x00\x00'
                        10      BUILD_TUPLE                     1
                        12      CALL_FUNCTION_EX                0
                        14      POP_TOP                         
                        16      RESUME                          0
                        18      NOP                             
                        20      NOP                             
                        22      NOP                             
                        24      NOP                             
                        26      NOP                             
                        28      LOAD_CONST                      4: b''
                        30      LOAD_ATTR                       1: join
                        50      LOAD_CONST                      5: b'\n3\xf2\xf2'
                        52      LOAD_FAST                       0: self
                        54      LOAD_ATTR                       3: serialize_bytes
                        74      LOAD_FAST                       0: self
                        76      LOAD_ATTR                       4: lang_pack
                        96      CALL                            1
                        104     LOAD_FAST                       0: self
                        106     LOAD_ATTR                       3: serialize_bytes
                        126     LOAD_FAST                       0: self
                        128     LOAD_ATTR                       6: lang_code
                        148     CALL                            1
                        156     BUILD_TUPLE                     3
                        158     CALL                            1
                        166     NOP                             
                        168     NOP                             
                        170     NOP                             
                        172     JUMP_FORWARD                    20 (to 214)
                        174     CALL                            1
                        182     POP_TOP                         
                        184     RETURN_VALUE                    
                        186     PUSH_EXC_INFO                   
                        188     PUSH_NULL                       
                        190     LOAD_CONST                      6: '__pyarmor_exit_29516__'
                        192     NOP                             
                        194     LOAD_CONST                      3: b'<COAddr>\x05\x00\x00\x1a\xa0\x00\x00\x00\x00\x00\x00\x00\x00\x00\x00\x00\x00\x00\x00\x00'
                        196     CALL                            1
                        204     POP_TOP                         
                        206     RERAISE                         0
                        208     COPY                            3
                        210     POP_EXCEPT                      
                        212     RERAISE                         1
                        214     PUSH_NULL                       
                        216     LOAD_CONST                      6: '__pyarmor_exit_29516__'
                        218     LOAD_CONST                      3: b'<COAddr>\x05\x00\x00\x1a\xa0\x00\x00\x00\x00\x00\x00\x00\x00\x00\x00\x00\x00\x00\x00\x00'
                        220     BUILD_TUPLE                     1
                        222     CALL_FUNCTION_EX                0
                        224     POP_TOP                         
                        226     RETURN_VALUE                    
                    [Exception Table]
                        28 to 166 -> 186 [0] 
                        186 to 208 -> 208 [1] lasti
                [Code]
                    File Name: <frozen multithon.tl.functions.langpack>
                    Object Name: from_reader
                    Qualified Name: GetLangPack_tdlib_Request.from_reader
                    Arg Count: 2
                    Pos Only Arg Count: 0
                    KW Only Arg Count: 0
                    Stack Size: 5
                    Flags: 0x20000003 (CO_OPTIMIZED | CO_NEWLOCALS | CO_PYARMOR_OBFUSCATED)
                    [Names]
                        'tgread_string'
                    [Locals+Names]
                        'cls'
                        'reader'
                        '__assert_armored__'
                        '_var_var_0'
                        '_var_var_1'
                    [Constants]
                        None
                        '__pyarmor_assert_29517__'
                        '__pyarmor_enter_29518__'
                        b'<COAddr>\x07\x00\x00\x1ah\x00\x00\x00\x00\x00\x00\x00\x00\x00\x00\x00\x00\x00\x00\x00'
                        (
                            'lang_pack'
                            'lang_code'
                        )
                        '__pyarmor_exit_29519__'
                    [Disassembly]
                        0       NOP                             
                        2       NOP                             
                        4       PUSH_NULL                       
                        6       LOAD_CONST                      2: '__pyarmor_enter_29518__'
                        8       LOAD_CONST                      3: b'<COAddr>\x07\x00\x00\x1ah\x00\x00\x00\x00\x00\x00\x00\x00\x00\x00\x00\x00\x00\x00\x00'
                        10      BUILD_TUPLE                     1
                        12      CALL_FUNCTION_EX                0
                        14      POP_TOP                         
                        16      RESUME                          0
                        18      NOP                             
                        20      NOP                             
                        22      NOP                             
                        24      NOP                             
                        26      NOP                             
                        28      LOAD_FAST                       1: reader
                        30      LOAD_ATTR                       1: tgread_string
                        50      CALL                            0
                        58      STORE_FAST                      3: _var_var_0
                        60      LOAD_FAST                       1: reader
                        62      LOAD_ATTR                       1: tgread_string
                        82      CALL                            0
                        90      STORE_FAST                      4: _var_var_1
                        92      PUSH_NULL                       
                        94      LOAD_FAST                       0: cls
                        96      LOAD_FAST                       3: _var_var_0
                        98      LOAD_FAST                       4: _var_var_1
                        100     KW_NAMES                        4: ('lang_pack', 'lang_code')
                        102     CALL                            2
                        110     NOP                             
                        112     NOP                             
                        114     NOP                             
                        116     JUMP_FORWARD                    20 (to 158)
                        118     CALL                            1
                        126     POP_TOP                         
                        128     RETURN_VALUE                    
                        130     PUSH_EXC_INFO                   
                        132     PUSH_NULL                       
                        134     LOAD_CONST                      5: '__pyarmor_exit_29519__'
                        136     NOP                             
                        138     LOAD_CONST                      3: b'<COAddr>\x07\x00\x00\x1ah\x00\x00\x00\x00\x00\x00\x00\x00\x00\x00\x00\x00\x00\x00\x00'
                        140     CALL                            1
                        148     POP_TOP                         
                        150     RERAISE                         0
                        152     COPY                            3
                        154     POP_EXCEPT                      
                        156     RERAISE                         1
                        158     PUSH_NULL                       
                        160     LOAD_CONST                      5: '__pyarmor_exit_29519__'
                        162     LOAD_CONST                      3: b'<COAddr>\x07\x00\x00\x1ah\x00\x00\x00\x00\x00\x00\x00\x00\x00\x00\x00\x00\x00\x00\x00'
                        164     BUILD_TUPLE                     1
                        166     CALL_FUNCTION_EX                0
                        168     POP_TOP                         
                        170     RETURN_VALUE                    
                    [Exception Table]
                        28 to 110 -> 130 [0] 
                        130 to 152 -> 152 [1] lasti
                '__pyarmor_exit_29507__'
                None
            [Disassembly]
                0       NOP                             
                2       LOAD_NAME                       0: __name__
                4       STORE_NAME                      1: __module__
                6       LOAD_CONST                      0: 'GetLangPack_tdlib_Request'
                8       STORE_NAME                      2: __qualname__
                10      NOP                             
                12      PUSH_NULL                       
                14      LOAD_CONST                      2: '__pyarmor_enter_29506__'
                16      LOAD_CONST                      3: b'<COAddr>\x05\x00\x00"J\x00\x00\x00\x00\x00\x00\x00\x00\x00\x00\x00\x00\x00\x00\x00'
                18      BUILD_TUPLE                     1
                20      CALL_FUNCTION_EX                0
                22      POP_TOP                         
                24      RESUME                          0
                26      NOP                             
                28      NOP                             
                30      NOP                             
                32      NOP                             
                34      NOP                             
                36      LOAD_CONST                      4: 0xF2F2330A
                38      STORE_NAME                      4: CONSTRUCTOR_ID
                40      LOAD_CONST                      5: 1382427989
                42      STORE_NAME                      5: SUBCLASS_OF_ID
                44      LOAD_CONST                      6: 'lang_pack'
                46      LOAD_NAME                       6: str
                48      LOAD_CONST                      7: 'lang_code'
                50      LOAD_NAME                       6: str
                52      BUILD_TUPLE                     4
                54      LOAD_CONST                      8: <CODE> __init__
                56      MAKE_FUNCTION                   4
                58      STORE_NAME                      7: __init__
                60      LOAD_CONST                      9: <CODE> to_dict
                62      MAKE_FUNCTION                   0
                64      STORE_NAME                      8: to_dict
                66      LOAD_CONST                      10: <CODE> _bytes
                68      MAKE_FUNCTION                   0
                70      STORE_NAME                      9: _bytes
                72      LOAD_NAME                       10: classmethod
                74      LOAD_CONST                      11: <CODE> from_reader
                76      MAKE_FUNCTION                   0
                78      CALL                            0
                86      STORE_NAME                      11: from_reader
                88      LOAD_CONST                      13: None
                90      NOP                             
                92      NOP                             
                94      NOP                             
                96      JUMP_FORWARD                    19 (to 136)
                104     POP_TOP                         
                106     RETURN_CONST                    13: None
                108     PUSH_EXC_INFO                   
                110     PUSH_NULL                       
                112     LOAD_CONST                      12: '__pyarmor_exit_29507__'
                114     NOP                             
                116     LOAD_CONST                      3: b'<COAddr>\x05\x00\x00"J\x00\x00\x00\x00\x00\x00\x00\x00\x00\x00\x00\x00\x00\x00\x00'
                118     CALL                            1
                126     POP_TOP                         
                128     RERAISE                         0
                130     COPY                            3
                132     POP_EXCEPT                      
                134     RERAISE                         1
                136     PUSH_NULL                       
                138     LOAD_CONST                      12: '__pyarmor_exit_29507__'
                140     LOAD_CONST                      3: b'<COAddr>\x05\x00\x00"J\x00\x00\x00\x00\x00\x00\x00\x00\x00\x00\x00\x00\x00\x00\x00'
                142     BUILD_TUPLE                     1
                144     CALL_FUNCTION_EX                0
                146     POP_TOP                         
                148     RETURN_VALUE                    
            [Exception Table]
                36 to 88 -> 108 [0] 
                108 to 130 -> 130 [1] lasti
        'GetLangPack_tdlib_Request'
        [Code]
            File Name: <frozen multithon.tl.functions.langpack>
            Object Name: GetLanguageRequest
            Qualified Name: GetLanguageRequest
            Arg Count: 0
            Pos Only Arg Count: 0
            KW Only Arg Count: 0
            Stack Size: 5
            Flags: 0x20000000 (CO_PYARMOR_OBFUSCATED)
            [Names]
                '__name__'
                '__module__'
                '__qualname__'
                '__assert_armored__'
                'CONSTRUCTOR_ID'
                'SUBCLASS_OF_ID'
                'str'
                '__init__'
                'to_dict'
                '_bytes'
                'classmethod'
                'from_reader'
            [Locals+Names]
            [Constants]
                'GetLanguageRequest'
                '__pyarmor_assert_29520__'
                '__pyarmor_enter_29521__'
                b'<COAddr>\x07\x00\x00"J\x00\x00\x00\x00\x00\x00\x00\x00\x00\x00\x00\x00\x00\x00\x00'
                1784243458
                0xABAC89B7
                'lang_pack'
                'lang_code'
                [Code]
                    File Name: <frozen multithon.tl.functions.langpack>
                    Object Name: __init__
                    Qualified Name: GetLanguageRequest.__init__
                    Arg Count: 3
                    Pos Only Arg Count: 0
                    KW Only Arg Count: 0
                    Stack Size: 5
                    Flags: 0x20000003 (CO_OPTIMIZED | CO_NEWLOCALS | CO_PYARMOR_OBFUSCATED)
                    [Names]
                        'lang_pack'
                        'lang_code'
                    [Locals+Names]
                        'self'
                        'lang_pack'
                        'lang_code'
                        '__assert_armored__'
                    [Constants]
                        '\n        :returns LangPackLanguage: Instance of LangPackLanguage.\n        '
                        '__pyarmor_assert_29523__'
                        '__pyarmor_enter_29524__'
                        b'<COAddr>\x05\x00\x00\x1a2\x00\x00\x00\x00\x00\x00\x00\x00\x00\x00\x00\x00\x00\x00\x00'
                        '__pyarmor_exit_29525__'
                        None
                    [Disassembly]
                        0       NOP                             
                        2       NOP                             
                        4       PUSH_NULL                       
                        6       LOAD_CONST                      2: '__pyarmor_enter_29524__'
                        8       LOAD_CONST                      3: b'<COAddr>\x05\x00\x00\x1a2\x00\x00\x00\x00\x00\x00\x00\x00\x00\x00\x00\x00\x00\x00\x00'
                        10      BUILD_TUPLE                     1
                        12      CALL_FUNCTION_EX                0
                        14      POP_TOP                         
                        16      RESUME                          0
                        18      NOP                             
                        20      NOP                             
                        22      NOP                             
                        24      NOP                             
                        26      NOP                             
                        28      LOAD_FAST                       1: lang_pack
                        30      LOAD_FAST                       0: self
                        32      STORE_ATTR                      0: lang_pack
                        42      LOAD_FAST                       2: lang_code
                        44      LOAD_FAST                       0: self
                        46      STORE_ATTR                      1: lang_code
                        56      LOAD_CONST                      5: None
                        58      NOP                             
                        60      NOP                             
                        62      NOP                             
                        64      JUMP_FORWARD                    19 (to 104)
                        72      POP_TOP                         
                        74      RETURN_CONST                    5: None
                        76      PUSH_EXC_INFO                   
                        78      PUSH_NULL                       
                        80      LOAD_CONST                      4: '__pyarmor_exit_29525__'
                        82      NOP                             
                        84      LOAD_CONST                      3: b'<COAddr>\x05\x00\x00\x1a2\x00\x00\x00\x00\x00\x00\x00\x00\x00\x00\x00\x00\x00\x00\x00'
                        86      CALL                            1
                        94      POP_TOP                         
                        96      RERAISE                         0
                        98      COPY                            3
                        100     POP_EXCEPT                      
                        102     RERAISE                         1
                        104     PUSH_NULL                       
                        106     LOAD_CONST                      4: '__pyarmor_exit_29525__'
                        108     LOAD_CONST                      3: b'<COAddr>\x05\x00\x00\x1a2\x00\x00\x00\x00\x00\x00\x00\x00\x00\x00\x00\x00\x00\x00\x00'
                        110     BUILD_TUPLE                     1
                        112     CALL_FUNCTION_EX                0
                        114     POP_TOP                         
                        116     RETURN_VALUE                    
                    [Exception Table]
                        28 to 56 -> 76 [0] 
                        76 to 98 -> 98 [1] lasti
                [Code]
                    File Name: <frozen multithon.tl.functions.langpack>
                    Object Name: to_dict
                    Qualified Name: GetLanguageRequest.to_dict
                    Arg Count: 1
                    Pos Only Arg Count: 0
                    KW Only Arg Count: 0
                    Stack Size: 7
                    Flags: 0x20000003 (CO_OPTIMIZED | CO_NEWLOCALS | CO_PYARMOR_OBFUSCATED)
                    [Names]
                        'lang_pack'
                        'lang_code'
                    [Locals+Names]
                        'self'
                        '__assert_armored__'
                    [Constants]
                        None
                        '__pyarmor_assert_29526__'
                        '__pyarmor_enter_29527__'
                        b'<COAddr>\x05\x00\x00\x1ap\x00\x00\x00\x00\x00\x00\x00\x00\x00\x00\x00\x00\x00\x00\x00'
                        '_'
                        'GetLanguageRequest'   # b'\x81\xc5\x1d\x07\x1f\xfb\xb0\xd5\x0e\xfb\n\xc5^\xe9\xe9\x90\nN\xaf'
                        'lang_pack'   # b'\x81\xee\x19\x1d4\xc5\xae\xd3\x18\xf1'
                        'lang_code'   # b'\x81\xee\x19\x1d4\xc5\xbd\xdd\x1f\xff'
                        '__pyarmor_exit_29528__'
                    [Disassembly]
                        0       NOP                             
                        2       NOP                             
                        4       PUSH_NULL                       
                        6       LOAD_CONST                      2: '__pyarmor_enter_29527__'
                        8       LOAD_CONST                      3: b'<COAddr>\x05\x00\x00\x1ap\x00\x00\x00\x00\x00\x00\x00\x00\x00\x00\x00\x00\x00\x00\x00'
                        10      BUILD_TUPLE                     1
                        12      CALL_FUNCTION_EX                0
                        14      POP_TOP                         
                        16      RESUME                          0
                        18      NOP                             
                        20      NOP                             
                        22      NOP                             
                        24      NOP                             
                        26      NOP                             
                        28      LOAD_CONST                      4: '_'
                        30      PUSH_NULL                       
                        32      LOAD_CONST                      1: '__pyarmor_assert_29526__'
                        34      LOAD_CONST                      5: 'GetLanguageRequest'   # b'\x81\xc5\x1d\x07\x1f\xfb\xb0\xd5\x0e\xfb\n\xc5^\xe9\xe9\x90\nN\xaf'
                        36      CALL                            1
                        44      PUSH_NULL                       
                        46      LOAD_CONST                      1: '__pyarmor_assert_29526__'
                        48      LOAD_CONST                      6: 'lang_pack'   # b'\x81\xee\x19\x1d4\xc5\xae\xd3\x18\xf1'
                        50      CALL                            1
                        58      LOAD_FAST                       0: self
                        60      LOAD_ATTR                       0: lang_pack
                        80      PUSH_NULL                       
                        82      LOAD_CONST                      1: '__pyarmor_assert_29526__'
                        84      LOAD_CONST                      7: 'lang_code'   # b'\x81\xee\x19\x1d4\xc5\xbd\xdd\x1f\xff'
                        86      CALL                            1
                        94      LOAD_FAST                       0: self
                        96      LOAD_ATTR                       2: lang_code
                        116     BUILD_MAP                       3
                        118     NOP                             
                        120     NOP                             
                        122     NOP                             
                        124     JUMP_FORWARD                    20 (to 166)
                        126     CALL                            1
                        134     POP_TOP                         
                        136     RETURN_VALUE                    
                        138     PUSH_EXC_INFO                   
                        140     PUSH_NULL                       
                        142     LOAD_CONST                      8: '__pyarmor_exit_29528__'
                        144     NOP                             
                        146     LOAD_CONST                      3: b'<COAddr>\x05\x00\x00\x1ap\x00\x00\x00\x00\x00\x00\x00\x00\x00\x00\x00\x00\x00\x00\x00'
                        148     CALL                            1
                        156     POP_TOP                         
                        158     RERAISE                         0
                        160     COPY                            3
                        162     POP_EXCEPT                      
                        164     RERAISE                         1
                        166     PUSH_NULL                       
                        168     LOAD_CONST                      8: '__pyarmor_exit_29528__'
                        170     LOAD_CONST                      3: b'<COAddr>\x05\x00\x00\x1ap\x00\x00\x00\x00\x00\x00\x00\x00\x00\x00\x00\x00\x00\x00\x00'
                        172     BUILD_TUPLE                     1
                        174     CALL_FUNCTION_EX                0
                        176     POP_TOP                         
                        178     RETURN_VALUE                    
                    [Exception Table]
                        28 to 118 -> 138 [0] 
                        138 to 160 -> 160 [1] lasti
                [Code]
                    File Name: <frozen multithon.tl.functions.langpack>
                    Object Name: _bytes
                    Qualified Name: GetLanguageRequest._bytes
                    Arg Count: 1
                    Pos Only Arg Count: 0
                    KW Only Arg Count: 0
                    Stack Size: 7
                    Flags: 0x20000003 (CO_OPTIMIZED | CO_NEWLOCALS | CO_PYARMOR_OBFUSCATED)
                    [Names]
                        'join'
                        'serialize_bytes'
                        'lang_pack'
                        'lang_code'
                    [Locals+Names]
                        'self'
                        '__assert_armored__'
                    [Constants]
                        None
                        '__pyarmor_assert_29529__'
                        '__pyarmor_enter_29530__'
                        b'<COAddr>\x07\x00\x00\x1a\xa0\x00\x00\x00\x00\x00\x00\x00\x00\x00\x00\x00\x00\x00\x00\x00'
                        b''
                        b'\x02eYj'
                        '__pyarmor_exit_29531__'
                    [Disassembly]
                        0       NOP                             
                        2       NOP                             
                        4       PUSH_NULL                       
                        6       LOAD_CONST                      2: '__pyarmor_enter_29530__'
                        8       LOAD_CONST                      3: b'<COAddr>\x07\x00\x00\x1a\xa0\x00\x00\x00\x00\x00\x00\x00\x00\x00\x00\x00\x00\x00\x00\x00'
                        10      BUILD_TUPLE                     1
                        12      CALL_FUNCTION_EX                0
                        14      POP_TOP                         
                        16      RESUME                          0
                        18      NOP                             
                        20      NOP                             
                        22      NOP                             
                        24      NOP                             
                        26      NOP                             
                        28      LOAD_CONST                      4: b''
                        30      LOAD_ATTR                       1: join
                        50      LOAD_CONST                      5: b'\x02eYj'
                        52      LOAD_FAST                       0: self
                        54      LOAD_ATTR                       3: serialize_bytes
                        74      LOAD_FAST                       0: self
                        76      LOAD_ATTR                       4: lang_pack
                        96      CALL                            1
                        104     LOAD_FAST                       0: self
                        106     LOAD_ATTR                       3: serialize_bytes
                        126     LOAD_FAST                       0: self
                        128     LOAD_ATTR                       6: lang_code
                        148     CALL                            1
                        156     BUILD_TUPLE                     3
                        158     CALL                            1
                        166     NOP                             
                        168     NOP                             
                        170     NOP                             
                        172     JUMP_FORWARD                    20 (to 214)
                        174     CALL                            1
                        182     POP_TOP                         
                        184     RETURN_VALUE                    
                        186     PUSH_EXC_INFO                   
                        188     PUSH_NULL                       
                        190     LOAD_CONST                      6: '__pyarmor_exit_29531__'
                        192     NOP                             
                        194     LOAD_CONST                      3: b'<COAddr>\x07\x00\x00\x1a\xa0\x00\x00\x00\x00\x00\x00\x00\x00\x00\x00\x00\x00\x00\x00\x00'
                        196     CALL                            1
                        204     POP_TOP                         
                        206     RERAISE                         0
                        208     COPY                            3
                        210     POP_EXCEPT                      
                        212     RERAISE                         1
                        214     PUSH_NULL                       
                        216     LOAD_CONST                      6: '__pyarmor_exit_29531__'
                        218     LOAD_CONST                      3: b'<COAddr>\x07\x00\x00\x1a\xa0\x00\x00\x00\x00\x00\x00\x00\x00\x00\x00\x00\x00\x00\x00\x00'
                        220     BUILD_TUPLE                     1
                        222     CALL_FUNCTION_EX                0
                        224     POP_TOP                         
                        226     RETURN_VALUE                    
                    [Exception Table]
                        28 to 166 -> 186 [0] 
                        186 to 208 -> 208 [1] lasti
                [Code]
                    File Name: <frozen multithon.tl.functions.langpack>
                    Object Name: from_reader
                    Qualified Name: GetLanguageRequest.from_reader
                    Arg Count: 2
                    Pos Only Arg Count: 0
                    KW Only Arg Count: 0
                    Stack Size: 5
                    Flags: 0x20000003 (CO_OPTIMIZED | CO_NEWLOCALS | CO_PYARMOR_OBFUSCATED)
                    [Names]
                        'tgread_string'
                    [Locals+Names]
                        'cls'
                        'reader'
                        '__assert_armored__'
                        '_var_var_0'
                        '_var_var_1'
                    [Constants]
                        None
                        '__pyarmor_assert_29532__'
                        '__pyarmor_enter_29533__'
                        b'<COAddr>\x07\x00\x00\x1ah\x00\x00\x00\x00\x00\x00\x00\x00\x00\x00\x00\x00\x00\x00\x00'
                        (
                            'lang_pack'
                            'lang_code'
                        )
                        '__pyarmor_exit_29534__'
                    [Disassembly]
                        0       NOP                             
                        2       NOP                             
                        4       PUSH_NULL                       
                        6       LOAD_CONST                      2: '__pyarmor_enter_29533__'
                        8       LOAD_CONST                      3: b'<COAddr>\x07\x00\x00\x1ah\x00\x00\x00\x00\x00\x00\x00\x00\x00\x00\x00\x00\x00\x00\x00'
                        10      BUILD_TUPLE                     1
                        12      CALL_FUNCTION_EX                0
                        14      POP_TOP                         
                        16      RESUME                          0
                        18      NOP                             
                        20      NOP                             
                        22      NOP                             
                        24      NOP                             
                        26      NOP                             
                        28      LOAD_FAST                       1: reader
                        30      LOAD_ATTR                       1: tgread_string
                        50      CALL                            0
                        58      STORE_FAST                      3: _var_var_0
                        60      LOAD_FAST                       1: reader
                        62      LOAD_ATTR                       1: tgread_string
                        82      CALL                            0
                        90      STORE_FAST                      4: _var_var_1
                        92      PUSH_NULL                       
                        94      LOAD_FAST                       0: cls
                        96      LOAD_FAST                       3: _var_var_0
                        98      LOAD_FAST                       4: _var_var_1
                        100     KW_NAMES                        4: ('lang_pack', 'lang_code')
                        102     CALL                            2
                        110     NOP                             
                        112     NOP                             
                        114     NOP                             
                        116     JUMP_FORWARD                    20 (to 158)
                        118     CALL                            1
                        126     POP_TOP                         
                        128     RETURN_VALUE                    
                        130     PUSH_EXC_INFO                   
                        132     PUSH_NULL                       
                        134     LOAD_CONST                      5: '__pyarmor_exit_29534__'
                        136     NOP                             
                        138     LOAD_CONST                      3: b'<COAddr>\x07\x00\x00\x1ah\x00\x00\x00\x00\x00\x00\x00\x00\x00\x00\x00\x00\x00\x00\x00'
                        140     CALL                            1
                        148     POP_TOP                         
                        150     RERAISE                         0
                        152     COPY                            3
                        154     POP_EXCEPT                      
                        156     RERAISE                         1
                        158     PUSH_NULL                       
                        160     LOAD_CONST                      5: '__pyarmor_exit_29534__'
                        162     LOAD_CONST                      3: b'<COAddr>\x07\x00\x00\x1ah\x00\x00\x00\x00\x00\x00\x00\x00\x00\x00\x00\x00\x00\x00\x00'
                        164     BUILD_TUPLE                     1
                        166     CALL_FUNCTION_EX                0
                        168     POP_TOP                         
                        170     RETURN_VALUE                    
                    [Exception Table]
                        28 to 110 -> 130 [0] 
                        130 to 152 -> 152 [1] lasti
                '__pyarmor_exit_29522__'
                None
            [Disassembly]
                0       NOP                             
                2       LOAD_NAME                       0: __name__
                4       STORE_NAME                      1: __module__
                6       LOAD_CONST                      0: 'GetLanguageRequest'
                8       STORE_NAME                      2: __qualname__
                10      NOP                             
                12      PUSH_NULL                       
                14      LOAD_CONST                      2: '__pyarmor_enter_29521__'
                16      LOAD_CONST                      3: b'<COAddr>\x07\x00\x00"J\x00\x00\x00\x00\x00\x00\x00\x00\x00\x00\x00\x00\x00\x00\x00'
                18      BUILD_TUPLE                     1
                20      CALL_FUNCTION_EX                0
                22      POP_TOP                         
                24      RESUME                          0
                26      NOP                             
                28      NOP                             
                30      NOP                             
                32      NOP                             
                34      NOP                             
                36      LOAD_CONST                      4: 1784243458
                38      STORE_NAME                      4: CONSTRUCTOR_ID
                40      LOAD_CONST                      5: 0xABAC89B7
                42      STORE_NAME                      5: SUBCLASS_OF_ID
                44      LOAD_CONST                      6: 'lang_pack'
                46      LOAD_NAME                       6: str
                48      LOAD_CONST                      7: 'lang_code'
                50      LOAD_NAME                       6: str
                52      BUILD_TUPLE                     4
                54      LOAD_CONST                      8: <CODE> __init__
                56      MAKE_FUNCTION                   4
                58      STORE_NAME                      7: __init__
                60      LOAD_CONST                      9: <CODE> to_dict
                62      MAKE_FUNCTION                   0
                64      STORE_NAME                      8: to_dict
                66      LOAD_CONST                      10: <CODE> _bytes
                68      MAKE_FUNCTION                   0
                70      STORE_NAME                      9: _bytes
                72      LOAD_NAME                       10: classmethod
                74      LOAD_CONST                      11: <CODE> from_reader
                76      MAKE_FUNCTION                   0
                78      CALL                            0
                86      STORE_NAME                      11: from_reader
                88      LOAD_CONST                      13: None
                90      NOP                             
                92      NOP                             
                94      NOP                             
                96      JUMP_FORWARD                    19 (to 136)
                104     POP_TOP                         
                106     RETURN_CONST                    13: None
                108     PUSH_EXC_INFO                   
                110     PUSH_NULL                       
                112     LOAD_CONST                      12: '__pyarmor_exit_29522__'
                114     NOP                             
                116     LOAD_CONST                      3: b'<COAddr>\x07\x00\x00"J\x00\x00\x00\x00\x00\x00\x00\x00\x00\x00\x00\x00\x00\x00\x00'
                118     CALL                            1
                126     POP_TOP                         
                128     RERAISE                         0
                130     COPY                            3
                132     POP_EXCEPT                      
                134     RERAISE                         1
                136     PUSH_NULL                       
                138     LOAD_CONST                      12: '__pyarmor_exit_29522__'
                140     LOAD_CONST                      3: b'<COAddr>\x07\x00\x00"J\x00\x00\x00\x00\x00\x00\x00\x00\x00\x00\x00\x00\x00\x00\x00'
                142     BUILD_TUPLE                     1
                144     CALL_FUNCTION_EX                0
                146     POP_TOP                         
                148     RETURN_VALUE                    
            [Exception Table]
                36 to 88 -> 108 [0] 
                108 to 130 -> 130 [1] lasti
        'GetLanguageRequest'
        [Code]
            File Name: <frozen multithon.tl.functions.langpack>
            Object Name: GetLanguagesRequest
            Qualified Name: GetLanguagesRequest
            Arg Count: 0
            Pos Only Arg Count: 0
            KW Only Arg Count: 0
            Stack Size: 5
            Flags: 0x20000000 (CO_PYARMOR_OBFUSCATED)
            [Names]
                '__name__'
                '__module__'
                '__qualname__'
                '__assert_armored__'
                'CONSTRUCTOR_ID'
                'SUBCLASS_OF_ID'
                '__init__'
                'to_dict'
                '_bytes'
                'classmethod'
                'from_reader'
            [Locals+Names]
            [Constants]
                'GetLanguagesRequest'
                '__pyarmor_assert_29535__'
                '__pyarmor_enter_29536__'
                b'<COAddr>\x07\x00\x00"@\x00\x00\x00\x00\x00\x00\x00\x00\x00\x00\x00\x00\x00\x00\x00'
                0x800FD57D
                671683273
                [Code]
                    File Name: <frozen multithon.tl.functions.langpack>
                    Object Name: __init__
                    Qualified Name: GetLanguagesRequest.__init__
                    Arg Count: 1
                    Pos Only Arg Count: 0
                    KW Only Arg Count: 0
                    Stack Size: 0
                    Flags: 0x00000003 (CO_OPTIMIZED | CO_NEWLOCALS)
                    [Names]
                    [Locals+Names]
                        'self'
                    [Constants]
                        '\n        :returns Vector<LangPackLanguage>: This type has no constructors.\n        '
                        None
                    [Disassembly]
                        0       RESUME                          0
                        2       RETURN_CONST                    1: None
                    [Exception Table]
                [Code]
                    File Name: <frozen multithon.tl.functions.langpack>
                    Object Name: to_dict
                    Qualified Name: GetLanguagesRequest.to_dict
                    Arg Count: 1
                    Pos Only Arg Count: 0
                    KW Only Arg Count: 0
                    Stack Size: 5
                    Flags: 0x20000003 (CO_OPTIMIZED | CO_NEWLOCALS | CO_PYARMOR_OBFUSCATED)
                    [Names]
                    [Locals+Names]
                        'self'
                        '__assert_armored__'
                    [Constants]
                        None
                        '__pyarmor_assert_29538__'
                        '__pyarmor_enter_29539__'
                        b'<COAddr>\x07\x00\x00\x1a(\x00\x00\x00\x00\x00\x00\x00\x00\x00\x00\x00\x00\x00\x00\x00'
                        '_'
                        'GetLanguagesRequest'   # b'\x81\xc5\x1d\x07\x1f\xfb\xb0\xd5\x0e\xfb\n\xc5\x7f\xde\xfd\x94\x1aX\xa8\xb3'
                        '__pyarmor_exit_29540__'
                    [Disassembly]
                        0       NOP                             
                        2       NOP                             
                        4       PUSH_NULL                       
                        6       LOAD_CONST                      2: '__pyarmor_enter_29539__'
                        8       LOAD_CONST                      3: b'<COAddr>\x07\x00\x00\x1a(\x00\x00\x00\x00\x00\x00\x00\x00\x00\x00\x00\x00\x00\x00\x00'
                        10      BUILD_TUPLE                     1
                        12      CALL_FUNCTION_EX                0
                        14      POP_TOP                         
                        16      RESUME                          0
                        18      NOP                             
                        20      NOP                             
                        22      NOP                             
                        24      NOP                             
                        26      NOP                             
                        28      LOAD_CONST                      4: '_'
                        30      PUSH_NULL                       
                        32      LOAD_CONST                      1: '__pyarmor_assert_29538__'
                        34      LOAD_CONST                      5: 'GetLanguagesRequest'   # b'\x81\xc5\x1d\x07\x1f\xfb\xb0\xd5\x0e\xfb\n\xc5\x7f\xde\xfd\x94\x1aX\xa8\xb3'
                        36      CALL                            1
                        44      BUILD_MAP                       1
                        46      NOP                             
                        48      NOP                             
                        50      NOP                             
                        52      JUMP_FORWARD                    20 (to 94)
                        54      CALL                            1
                        62      POP_TOP                         
                        64      RETURN_VALUE                    
                        66      PUSH_EXC_INFO                   
                        68      PUSH_NULL                       
                        70      LOAD_CONST                      6: '__pyarmor_exit_29540__'
                        72      NOP                             
                        74      LOAD_CONST                      3: b'<COAddr>\x07\x00\x00\x1a(\x00\x00\x00\x00\x00\x00\x00\x00\x00\x00\x00\x00\x00\x00\x00'
                        76      CALL                            1
                        84      POP_TOP                         
                        86      RERAISE                         0
                        88      COPY                            3
                        90      POP_EXCEPT                      
                        92      RERAISE                         1
                        94      PUSH_NULL                       
                        96      LOAD_CONST                      6: '__pyarmor_exit_29540__'
                        98      LOAD_CONST                      3: b'<COAddr>\x07\x00\x00\x1a(\x00\x00\x00\x00\x00\x00\x00\x00\x00\x00\x00\x00\x00\x00\x00'
                        100     BUILD_TUPLE                     1
                        102     CALL_FUNCTION_EX                0
                        104     POP_TOP                         
                        106     RETURN_VALUE                    
                    [Exception Table]
                        28 to 46 -> 66 [0] 
                        66 to 88 -> 88 [1] lasti
                [Code]
                    File Name: <frozen multithon.tl.functions.langpack>
                    Object Name: _bytes
                    Qualified Name: GetLanguagesRequest._bytes
                    Arg Count: 1
                    Pos Only Arg Count: 0
                    KW Only Arg Count: 0
                    Stack Size: 5
                    Flags: 0x20000003 (CO_OPTIMIZED | CO_NEWLOCALS | CO_PYARMOR_OBFUSCATED)
                    [Names]
                        'join'
                    [Locals+Names]
                        'self'
                        '__assert_armored__'
                    [Constants]
                        None
                        '__pyarmor_assert_29541__'
                        '__pyarmor_enter_29542__'
                        b'<COAddr>\x07\x00\x00\x1a6\x00\x00\x00\x00\x00\x00\x00\x00\x00\x00\x00\x00\x00\x00\x00'
                        b''
                        (
                            b'}\xd5\x0f\x80'
                        )
                        '__pyarmor_exit_29543__'
                    [Disassembly]
                        0       NOP                             
                        2       NOP                             
                        4       PUSH_NULL                       
                        6       LOAD_CONST                      2: '__pyarmor_enter_29542__'
                        8       LOAD_CONST                      3: b'<COAddr>\x07\x00\x00\x1a6\x00\x00\x00\x00\x00\x00\x00\x00\x00\x00\x00\x00\x00\x00\x00'
                        10      BUILD_TUPLE                     1
                        12      CALL_FUNCTION_EX                0
                        14      POP_TOP                         
                        16      RESUME                          0
                        18      NOP                             
                        20      NOP                             
                        22      NOP                             
                        24      NOP                             
                        26      NOP                             
                        28      LOAD_CONST                      4: b''
                        30      LOAD_ATTR                       1: join
                        50      LOAD_CONST                      5: (b'}\xd5\x0f\x80',)
                        52      CALL                            1
                        60      NOP                             
                        62      NOP                             
                        64      NOP                             
                        66      JUMP_FORWARD                    20 (to 108)
                        68      CALL                            1
                        76      POP_TOP                         
                        78      RETURN_VALUE                    
                        80      PUSH_EXC_INFO                   
                        82      PUSH_NULL                       
                        84      LOAD_CONST                      6: '__pyarmor_exit_29543__'
                        86      NOP                             
                        88      LOAD_CONST                      3: b'<COAddr>\x07\x00\x00\x1a6\x00\x00\x00\x00\x00\x00\x00\x00\x00\x00\x00\x00\x00\x00\x00'
                        90      CALL                            1
                        98      POP_TOP                         
                        100     RERAISE                         0
                        102     COPY                            3
                        104     POP_EXCEPT                      
                        106     RERAISE                         1
                        108     PUSH_NULL                       
                        110     LOAD_CONST                      6: '__pyarmor_exit_29543__'
                        112     LOAD_CONST                      3: b'<COAddr>\x07\x00\x00\x1a6\x00\x00\x00\x00\x00\x00\x00\x00\x00\x00\x00\x00\x00\x00\x00'
                        114     BUILD_TUPLE                     1
                        116     CALL_FUNCTION_EX                0
                        118     POP_TOP                         
                        120     RETURN_VALUE                    
                    [Exception Table]
                        28 to 60 -> 80 [0] 
                        80 to 102 -> 102 [1] lasti
                [Code]
                    File Name: <frozen multithon.tl.functions.langpack>
                    Object Name: from_reader
                    Qualified Name: GetLanguagesRequest.from_reader
                    Arg Count: 2
                    Pos Only Arg Count: 0
                    KW Only Arg Count: 0
                    Stack Size: 5
                    Flags: 0x20000003 (CO_OPTIMIZED | CO_NEWLOCALS | CO_PYARMOR_OBFUSCATED)
                    [Names]
                        'tgread_string'
                    [Locals+Names]
                        'cls'
                        'reader'
                        '__assert_armored__'
                        '_var_var_0'
                    [Constants]
                        None
                        '__pyarmor_assert_29544__'
                        '__pyarmor_enter_29545__'
                        b'<COAddr>\x07\x00\x00\x1aF\x00\x00\x00\x00\x00\x00\x00\x00\x00\x00\x00\x00\x00\x00\x00'
                        (
                            'lang_pack'
                        )
                        '__pyarmor_exit_29546__'
                    [Disassembly]
                        0       NOP                             
                        2       NOP                             
                        4       PUSH_NULL                       
                        6       LOAD_CONST                      2: '__pyarmor_enter_29545__'
                        8       LOAD_CONST                      3: b'<COAddr>\x07\x00\x00\x1aF\x00\x00\x00\x00\x00\x00\x00\x00\x00\x00\x00\x00\x00\x00\x00'
                        10      BUILD_TUPLE                     1
                        12      CALL_FUNCTION_EX                0
                        14      POP_TOP                         
                        16      RESUME                          0
                        18      NOP                             
                        20      NOP                             
                        22      NOP                             
                        24      NOP                             
                        26      NOP                             
                        28      LOAD_FAST                       1: reader
                        30      LOAD_ATTR                       1: tgread_string
                        50      CALL                            0
                        58      STORE_FAST                      3: _var_var_0
                        60      PUSH_NULL                       
                        62      LOAD_FAST                       0: cls
                        64      LOAD_FAST                       3: _var_var_0
                        66      KW_NAMES                        4: ('lang_pack',)
                        68      CALL                            1
                        76      NOP                             
                        78      NOP                             
                        80      NOP                             
                        82      JUMP_FORWARD                    20 (to 124)
                        84      CALL                            1
                        92      POP_TOP                         
                        94      RETURN_VALUE                    
                        96      PUSH_EXC_INFO                   
                        98      PUSH_NULL                       
                        100     LOAD_CONST                      5: '__pyarmor_exit_29546__'
                        102     NOP                             
                        104     LOAD_CONST                      3: b'<COAddr>\x07\x00\x00\x1aF\x00\x00\x00\x00\x00\x00\x00\x00\x00\x00\x00\x00\x00\x00\x00'
                        106     CALL                            1
                        114     POP_TOP                         
                        116     RERAISE                         0
                        118     COPY                            3
                        120     POP_EXCEPT                      
                        122     RERAISE                         1
                        124     PUSH_NULL                       
                        126     LOAD_CONST                      5: '__pyarmor_exit_29546__'
                        128     LOAD_CONST                      3: b'<COAddr>\x07\x00\x00\x1aF\x00\x00\x00\x00\x00\x00\x00\x00\x00\x00\x00\x00\x00\x00\x00'
                        130     BUILD_TUPLE                     1
                        132     CALL_FUNCTION_EX                0
                        134     POP_TOP                         
                        136     RETURN_VALUE                    
                    [Exception Table]
                        28 to 76 -> 96 [0] 
                        96 to 118 -> 118 [1] lasti
                '__pyarmor_exit_29537__'
                None
            [Disassembly]
                0       NOP                             
                2       LOAD_NAME                       0: __name__
                4       STORE_NAME                      1: __module__
                6       LOAD_CONST                      0: 'GetLanguagesRequest'
                8       STORE_NAME                      2: __qualname__
                10      NOP                             
                12      PUSH_NULL                       
                14      LOAD_CONST                      2: '__pyarmor_enter_29536__'
                16      LOAD_CONST                      3: b'<COAddr>\x07\x00\x00"@\x00\x00\x00\x00\x00\x00\x00\x00\x00\x00\x00\x00\x00\x00\x00'
                18      BUILD_TUPLE                     1
                20      CALL_FUNCTION_EX                0
                22      POP_TOP                         
                24      RESUME                          0
                26      NOP                             
                28      NOP                             
                30      NOP                             
                32      NOP                             
                34      NOP                             
                36      LOAD_CONST                      4: 0x800FD57D
                38      STORE_NAME                      4: CONSTRUCTOR_ID
                40      LOAD_CONST                      5: 671683273
                42      STORE_NAME                      5: SUBCLASS_OF_ID
                44      LOAD_CONST                      6: <CODE> __init__
                46      MAKE_FUNCTION                   0
                48      STORE_NAME                      6: __init__
                50      LOAD_CONST                      7: <CODE> to_dict
                52      MAKE_FUNCTION                   0
                54      STORE_NAME                      7: to_dict
                56      LOAD_CONST                      8: <CODE> _bytes
                58      MAKE_FUNCTION                   0
                60      STORE_NAME                      8: _bytes
                62      LOAD_NAME                       9: classmethod
                64      LOAD_CONST                      9: <CODE> from_reader
                66      MAKE_FUNCTION                   0
                68      CALL                            0
                76      STORE_NAME                      10: from_reader
                78      LOAD_CONST                      11: None
                80      NOP                             
                82      NOP                             
                84      NOP                             
                86      JUMP_FORWARD                    19 (to 126)
                94      POP_TOP                         
                96      RETURN_CONST                    11: None
                98      PUSH_EXC_INFO                   
                100     PUSH_NULL                       
                102     LOAD_CONST                      10: '__pyarmor_exit_29537__'
                104     NOP                             
                106     LOAD_CONST                      3: b'<COAddr>\x07\x00\x00"@\x00\x00\x00\x00\x00\x00\x00\x00\x00\x00\x00\x00\x00\x00\x00'
                108     CALL                            1
                116     POP_TOP                         
                118     RERAISE                         0
                120     COPY                            3
                122     POP_EXCEPT                      
                124     RERAISE                         1
                126     PUSH_NULL                       
                128     LOAD_CONST                      10: '__pyarmor_exit_29537__'
                130     LOAD_CONST                      3: b'<COAddr>\x07\x00\x00"@\x00\x00\x00\x00\x00\x00\x00\x00\x00\x00\x00\x00\x00\x00\x00'
                132     BUILD_TUPLE                     1
                134     CALL_FUNCTION_EX                0
                136     POP_TOP                         
                138     RETURN_VALUE                    
            [Exception Table]
                36 to 78 -> 98 [0] 
                98 to 120 -> 120 [1] lasti
        'GetLanguagesRequest'
        [Code]
            File Name: <frozen multithon.tl.functions.langpack>
            Object Name: GetLanguages_tdlib_Request
            Qualified Name: GetLanguages_tdlib_Request
            Arg Count: 0
            Pos Only Arg Count: 0
            KW Only Arg Count: 0
            Stack Size: 5
            Flags: 0x20000000 (CO_PYARMOR_OBFUSCATED)
            [Names]
                '__name__'
                '__module__'
                '__qualname__'
                '__assert_armored__'
                'CONSTRUCTOR_ID'
                'SUBCLASS_OF_ID'
                'str'
                '__init__'
                'to_dict'
                '_bytes'
                'classmethod'
                'from_reader'
            [Locals+Names]
            [Constants]
                'GetLanguages_tdlib_Request'
                '__pyarmor_assert_29547__'
                '__pyarmor_enter_29548__'
                b'<COAddr>\x05\x00\x00"F\x00\x00\x00\x00\x00\x00\x00\x00\x00\x00\x00\x00\x00\x00\x00'
                1120311183
                671683273
                'lang_pack'
                [Code]
                    File Name: <frozen multithon.tl.functions.langpack>
                    Object Name: __init__
                    Qualified Name: GetLanguages_tdlib_Request.__init__
                    Arg Count: 2
                    Pos Only Arg Count: 0
                    KW Only Arg Count: 0
                    Stack Size: 5
                    Flags: 0x20000003 (CO_OPTIMIZED | CO_NEWLOCALS | CO_PYARMOR_OBFUSCATED)
                    [Names]
                        'lang_pack'
                    [Locals+Names]
                        'self'
                        'lang_pack'
                        '__assert_armored__'
                    [Constants]
                        '\n        :returns Vector<LangPackLanguage>: This type has no constructors.\n        '
                        '__pyarmor_assert_29550__'
                        '__pyarmor_enter_29551__'
                        b'<COAddr>\x05\x00\x00\x1a$\x00\x00\x00\x00\x00\x00\x00\x00\x00\x00\x00\x00\x00\x00\x00'
                        '__pyarmor_exit_29552__'
                        None
                    [Disassembly]
                        0       NOP                             
                        2       NOP                             
                        4       PUSH_NULL                       
                        6       LOAD_CONST                      2: '__pyarmor_enter_29551__'
                        8       LOAD_CONST                      3: b'<COAddr>\x05\x00\x00\x1a$\x00\x00\x00\x00\x00\x00\x00\x00\x00\x00\x00\x00\x00\x00\x00'
                        10      BUILD_TUPLE                     1
                        12      CALL_FUNCTION_EX                0
                        14      POP_TOP                         
                        16      RESUME                          0
                        18      NOP                             
                        20      NOP                             
                        22      NOP                             
                        24      NOP                             
                        26      NOP                             
                        28      LOAD_FAST                       1: lang_pack
                        30      LOAD_FAST                       0: self
                        32      STORE_ATTR                      0: lang_pack
                        42      LOAD_CONST                      5: None
                        44      NOP                             
                        46      NOP                             
                        48      NOP                             
                        50      JUMP_FORWARD                    19 (to 90)
                        58      POP_TOP                         
                        60      RETURN_CONST                    5: None
                        62      PUSH_EXC_INFO                   
                        64      PUSH_NULL                       
                        66      LOAD_CONST                      4: '__pyarmor_exit_29552__'
                        68      NOP                             
                        70      LOAD_CONST                      3: b'<COAddr>\x05\x00\x00\x1a$\x00\x00\x00\x00\x00\x00\x00\x00\x00\x00\x00\x00\x00\x00\x00'
                        72      CALL                            1
                        80      POP_TOP                         
                        82      RERAISE                         0
                        84      COPY                            3
                        86      POP_EXCEPT                      
                        88      RERAISE                         1
                        90      PUSH_NULL                       
                        92      LOAD_CONST                      4: '__pyarmor_exit_29552__'
                        94      LOAD_CONST                      3: b'<COAddr>\x05\x00\x00\x1a$\x00\x00\x00\x00\x00\x00\x00\x00\x00\x00\x00\x00\x00\x00\x00'
                        96      BUILD_TUPLE                     1
                        98      CALL_FUNCTION_EX                0
                        100     POP_TOP                         
                        102     RETURN_VALUE                    
                    [Exception Table]
                        28 to 42 -> 62 [0] 
                        62 to 84 -> 84 [1] lasti
                [Code]
                    File Name: <frozen multithon.tl.functions.langpack>
                    Object Name: to_dict
                    Qualified Name: GetLanguages_tdlib_Request.to_dict
                    Arg Count: 1
                    Pos Only Arg Count: 0
                    KW Only Arg Count: 0
                    Stack Size: 5
                    Flags: 0x20000003 (CO_OPTIMIZED | CO_NEWLOCALS | CO_PYARMOR_OBFUSCATED)
                    [Names]
                        'lang_pack'
                    [Locals+Names]
                        'self'
                        '__assert_armored__'
                    [Constants]
                        None
                        '__pyarmor_assert_29553__'
                        '__pyarmor_enter_29554__'
                        b'<COAddr>\x07\x00\x00\x1aL\x00\x00\x00\x00\x00\x00\x00\x00\x00\x00\x00\x00\x00\x00\x00'
                        '_'
                        'GetLanguagesRequest'   # b'\x81\xc5\x1d\x07\x1f\xfb\xb0\xd5\x0e\xfb\n\xc5\x7f\xde\xfd\x94\x1aX\xa8\xb3'
                        'lang_pack'   # b'\x81\xee\x19\x1d4\xc5\xae\xd3\x18\xf1'
                        '__pyarmor_exit_29555__'
                    [Disassembly]
                        0       NOP                             
                        2       NOP                             
                        4       PUSH_NULL                       
                        6       LOAD_CONST                      2: '__pyarmor_enter_29554__'
                        8       LOAD_CONST                      3: b'<COAddr>\x07\x00\x00\x1aL\x00\x00\x00\x00\x00\x00\x00\x00\x00\x00\x00\x00\x00\x00\x00'
                        10      BUILD_TUPLE                     1
                        12      CALL_FUNCTION_EX                0
                        14      POP_TOP                         
                        16      RESUME                          0
                        18      NOP                             
                        20      NOP                             
                        22      NOP                             
                        24      NOP                             
                        26      NOP                             
                        28      LOAD_CONST                      4: '_'
                        30      PUSH_NULL                       
                        32      LOAD_CONST                      1: '__pyarmor_assert_29553__'
                        34      LOAD_CONST                      5: 'GetLanguagesRequest'   # b'\x81\xc5\x1d\x07\x1f\xfb\xb0\xd5\x0e\xfb\n\xc5\x7f\xde\xfd\x94\x1aX\xa8\xb3'
                        36      CALL                            1
                        44      PUSH_NULL                       
                        46      LOAD_CONST                      1: '__pyarmor_assert_29553__'
                        48      LOAD_CONST                      6: 'lang_pack'   # b'\x81\xee\x19\x1d4\xc5\xae\xd3\x18\xf1'
                        50      CALL                            1
                        58      LOAD_FAST                       0: self
                        60      LOAD_ATTR                       0: lang_pack
                        80      BUILD_MAP                       2
                        82      NOP                             
                        84      NOP                             
                        86      NOP                             
                        88      JUMP_FORWARD                    20 (to 130)
                        90      CALL                            1
                        98      POP_TOP                         
                        100     RETURN_VALUE                    
                        102     PUSH_EXC_INFO                   
                        104     PUSH_NULL                       
                        106     LOAD_CONST                      7: '__pyarmor_exit_29555__'
                        108     NOP                             
                        110     LOAD_CONST                      3: b'<COAddr>\x07\x00\x00\x1aL\x00\x00\x00\x00\x00\x00\x00\x00\x00\x00\x00\x00\x00\x00\x00'
                        112     CALL                            1
                        120     POP_TOP                         
                        122     RERAISE                         0
                        124     COPY                            3
                        126     POP_EXCEPT                      
                        128     RERAISE                         1
                        130     PUSH_NULL                       
                        132     LOAD_CONST                      7: '__pyarmor_exit_29555__'
                        134     LOAD_CONST                      3: b'<COAddr>\x07\x00\x00\x1aL\x00\x00\x00\x00\x00\x00\x00\x00\x00\x00\x00\x00\x00\x00\x00'
                        136     BUILD_TUPLE                     1
                        138     CALL_FUNCTION_EX                0
                        140     POP_TOP                         
                        142     RETURN_VALUE                    
                    [Exception Table]
                        28 to 82 -> 102 [0] 
                        102 to 124 -> 124 [1] lasti
                [Code]
                    File Name: <frozen multithon.tl.functions.langpack>
                    Object Name: _bytes
                    Qualified Name: GetLanguages_tdlib_Request._bytes
                    Arg Count: 1
                    Pos Only Arg Count: 0
                    KW Only Arg Count: 0
                    Stack Size: 6
                    Flags: 0x20000003 (CO_OPTIMIZED | CO_NEWLOCALS | CO_PYARMOR_OBFUSCATED)
                    [Names]
                        'join'
                        'serialize_bytes'
                        'lang_pack'
                    [Locals+Names]
                        'self'
                        '__assert_armored__'
                    [Constants]
                        None
                        '__pyarmor_assert_29556__'
                        '__pyarmor_enter_29557__'
                        b'<COAddr>\x07\x00\x00\x1al\x00\x00\x00\x00\x00\x00\x00\x00\x00\x00\x00\x00\x00\x00\x00'
                        b''
                        b'\x8f\x97\xc6B'
                        '__pyarmor_exit_29558__'
                    [Disassembly]
                        0       NOP                             
                        2       NOP                             
                        4       PUSH_NULL                       
                        6       LOAD_CONST                      2: '__pyarmor_enter_29557__'
                        8       LOAD_CONST                      3: b'<COAddr>\x07\x00\x00\x1al\x00\x00\x00\x00\x00\x00\x00\x00\x00\x00\x00\x00\x00\x00\x00'
                        10      BUILD_TUPLE                     1
                        12      CALL_FUNCTION_EX                0
                        14      POP_TOP                         
                        16      RESUME                          0
                        18      NOP                             
                        20      NOP                             
                        22      NOP                             
                        24      NOP                             
                        26      NOP                             
                        28      LOAD_CONST                      4: b''
                        30      LOAD_ATTR                       1: join
                        50      LOAD_CONST                      5: b'\x8f\x97\xc6B'
                        52      LOAD_FAST                       0: self
                        54      LOAD_ATTR                       3: serialize_bytes
                        74      LOAD_FAST                       0: self
                        76      LOAD_ATTR                       4: lang_pack
                        96      CALL                            1
                        104     BUILD_TUPLE                     2
                        106     CALL                            1
                        114     NOP                             
                        116     NOP                             
                        118     NOP                             
                        120     JUMP_FORWARD                    20 (to 162)
                        122     CALL                            1
                        130     POP_TOP                         
                        132     RETURN_VALUE                    
                        134     PUSH_EXC_INFO                   
                        136     PUSH_NULL                       
                        138     LOAD_CONST                      6: '__pyarmor_exit_29558__'
                        140     NOP                             
                        142     LOAD_CONST                      3: b'<COAddr>\x07\x00\x00\x1al\x00\x00\x00\x00\x00\x00\x00\x00\x00\x00\x00\x00\x00\x00\x00'
                        144     CALL                            1
                        152     POP_TOP                         
                        154     RERAISE                         0
                        156     COPY                            3
                        158     POP_EXCEPT                      
                        160     RERAISE                         1
                        162     PUSH_NULL                       
                        164     LOAD_CONST                      6: '__pyarmor_exit_29558__'
                        166     LOAD_CONST                      3: b'<COAddr>\x07\x00\x00\x1al\x00\x00\x00\x00\x00\x00\x00\x00\x00\x00\x00\x00\x00\x00\x00'
                        168     BUILD_TUPLE                     1
                        170     CALL_FUNCTION_EX                0
                        172     POP_TOP                         
                        174     RETURN_VALUE                    
                    [Exception Table]
                        28 to 114 -> 134 [0] 
                        134 to 156 -> 156 [1] lasti
                [Code]
                    File Name: <frozen multithon.tl.functions.langpack>
                    Object Name: from_reader
                    Qualified Name: GetLanguages_tdlib_Request.from_reader
                    Arg Count: 2
                    Pos Only Arg Count: 0
                    KW Only Arg Count: 0
                    Stack Size: 5
                    Flags: 0x20000003 (CO_OPTIMIZED | CO_NEWLOCALS | CO_PYARMOR_OBFUSCATED)
                    [Names]
                        'tgread_string'
                    [Locals+Names]
                        'cls'
                        'reader'
                        '__assert_armored__'
                        '_var_var_0'
                    [Constants]
                        None
                        '__pyarmor_assert_29559__'
                        '__pyarmor_enter_29560__'
                        b'<COAddr>\x07\x00\x00\x1aF\x00\x00\x00\x00\x00\x00\x00\x00\x00\x00\x00\x00\x00\x00\x00'
                        (
                            'lang_pack'
                        )
                        '__pyarmor_exit_29561__'
                    [Disassembly]
                        0       NOP                             
                        2       NOP                             
                        4       PUSH_NULL                       
                        6       LOAD_CONST                      2: '__pyarmor_enter_29560__'
                        8       LOAD_CONST                      3: b'<COAddr>\x07\x00\x00\x1aF\x00\x00\x00\x00\x00\x00\x00\x00\x00\x00\x00\x00\x00\x00\x00'
                        10      BUILD_TUPLE                     1
                        12      CALL_FUNCTION_EX                0
                        14      POP_TOP                         
                        16      RESUME                          0
                        18      NOP                             
                        20      NOP                             
                        22      NOP                             
                        24      NOP                             
                        26      NOP                             
                        28      LOAD_FAST                       1: reader
                        30      LOAD_ATTR                       1: tgread_string
                        50      CALL                            0
                        58      STORE_FAST                      3: _var_var_0
                        60      PUSH_NULL                       
                        62      LOAD_FAST                       0: cls
                        64      LOAD_FAST                       3: _var_var_0
                        66      KW_NAMES                        4: ('lang_pack',)
                        68      CALL                            1
                        76      NOP                             
                        78      NOP                             
                        80      NOP                             
                        82      JUMP_FORWARD                    20 (to 124)
                        84      CALL                            1
                        92      POP_TOP                         
                        94      RETURN_VALUE                    
                        96      PUSH_EXC_INFO                   
                        98      PUSH_NULL                       
                        100     LOAD_CONST                      5: '__pyarmor_exit_29561__'
                        102     NOP                             
                        104     LOAD_CONST                      3: b'<COAddr>\x07\x00\x00\x1aF\x00\x00\x00\x00\x00\x00\x00\x00\x00\x00\x00\x00\x00\x00\x00'
                        106     CALL                            1
                        114     POP_TOP                         
                        116     RERAISE                         0
                        118     COPY                            3
                        120     POP_EXCEPT                      
                        122     RERAISE                         1
                        124     PUSH_NULL                       
                        126     LOAD_CONST                      5: '__pyarmor_exit_29561__'
                        128     LOAD_CONST                      3: b'<COAddr>\x07\x00\x00\x1aF\x00\x00\x00\x00\x00\x00\x00\x00\x00\x00\x00\x00\x00\x00\x00'
                        130     BUILD_TUPLE                     1
                        132     CALL_FUNCTION_EX                0
                        134     POP_TOP                         
                        136     RETURN_VALUE                    
                    [Exception Table]
                        28 to 76 -> 96 [0] 
                        96 to 118 -> 118 [1] lasti
                '__pyarmor_exit_29549__'
                None
            [Disassembly]
                0       NOP                             
                2       LOAD_NAME                       0: __name__
                4       STORE_NAME                      1: __module__
                6       LOAD_CONST                      0: 'GetLanguages_tdlib_Request'
                8       STORE_NAME                      2: __qualname__
                10      NOP                             
                12      PUSH_NULL                       
                14      LOAD_CONST                      2: '__pyarmor_enter_29548__'
                16      LOAD_CONST                      3: b'<COAddr>\x05\x00\x00"F\x00\x00\x00\x00\x00\x00\x00\x00\x00\x00\x00\x00\x00\x00\x00'
                18      BUILD_TUPLE                     1
                20      CALL_FUNCTION_EX                0
                22      POP_TOP                         
                24      RESUME                          0
                26      NOP                             
                28      NOP                             
                30      NOP                             
                32      NOP                             
                34      NOP                             
                36      LOAD_CONST                      4: 1120311183
                38      STORE_NAME                      4: CONSTRUCTOR_ID
                40      LOAD_CONST                      5: 671683273
                42      STORE_NAME                      5: SUBCLASS_OF_ID
                44      LOAD_CONST                      6: 'lang_pack'
                46      LOAD_NAME                       6: str
                48      BUILD_TUPLE                     2
                50      LOAD_CONST                      7: <CODE> __init__
                52      MAKE_FUNCTION                   4
                54      STORE_NAME                      7: __init__
                56      LOAD_CONST                      8: <CODE> to_dict
                58      MAKE_FUNCTION                   0
                60      STORE_NAME                      8: to_dict
                62      LOAD_CONST                      9: <CODE> _bytes
                64      MAKE_FUNCTION                   0
                66      STORE_NAME                      9: _bytes
                68      LOAD_NAME                       10: classmethod
                70      LOAD_CONST                      10: <CODE> from_reader
                72      MAKE_FUNCTION                   0
                74      CALL                            0
                82      STORE_NAME                      11: from_reader
                84      LOAD_CONST                      12: None
                86      NOP                             
                88      NOP                             
                90      NOP                             
                92      JUMP_FORWARD                    19 (to 132)
                100     POP_TOP                         
                102     RETURN_CONST                    12: None
                104     PUSH_EXC_INFO                   
                106     PUSH_NULL                       
                108     LOAD_CONST                      11: '__pyarmor_exit_29549__'
                110     NOP                             
                112     LOAD_CONST                      3: b'<COAddr>\x05\x00\x00"F\x00\x00\x00\x00\x00\x00\x00\x00\x00\x00\x00\x00\x00\x00\x00'
                114     CALL                            1
                122     POP_TOP                         
                124     RERAISE                         0
                126     COPY                            3
                128     POP_EXCEPT                      
                130     RERAISE                         1
                132     PUSH_NULL                       
                134     LOAD_CONST                      11: '__pyarmor_exit_29549__'
                136     LOAD_CONST                      3: b'<COAddr>\x05\x00\x00"F\x00\x00\x00\x00\x00\x00\x00\x00\x00\x00\x00\x00\x00\x00\x00'
                138     BUILD_TUPLE                     1
                140     CALL_FUNCTION_EX                0
                142     POP_TOP                         
                144     RETURN_VALUE                    
            [Exception Table]
                36 to 84 -> 104 [0] 
                104 to 126 -> 126 [1] lasti
        'GetLanguages_tdlib_Request'
        [Code]
            File Name: <frozen multithon.tl.functions.langpack>
            Object Name: GetStringsRequest
            Qualified Name: GetStringsRequest
            Arg Count: 0
            Pos Only Arg Count: 0
            KW Only Arg Count: 0
            Stack Size: 7
            Flags: 0x20000000 (CO_PYARMOR_OBFUSCATED)
            [Names]
                '__name__'
                '__module__'
                '__qualname__'
                '__assert_armored__'
                'CONSTRUCTOR_ID'
                'SUBCLASS_OF_ID'
                'str'
                'List'
                '__init__'
                'to_dict'
                '_bytes'
                'classmethod'
                'from_reader'
            [Locals+Names]
            [Constants]
                'GetStringsRequest'
                '__pyarmor_assert_29562__'
                '__pyarmor_enter_29563__'
                b'<COAddr>\x07\x00\x00"T\x00\x00\x00\x00\x00\x00\x00\x00\x00\x00\x00\x00\x00\x00\x00'
                0xEFEA3803
                0xC7B7353D
                'lang_pack'
                'lang_code'
                'keys'
                [Code]
                    File Name: <frozen multithon.tl.functions.langpack>
                    Object Name: __init__
                    Qualified Name: GetStringsRequest.__init__
                    Arg Count: 4
                    Pos Only Arg Count: 0
                    KW Only Arg Count: 0
                    Stack Size: 5
                    Flags: 0x20000003 (CO_OPTIMIZED | CO_NEWLOCALS | CO_PYARMOR_OBFUSCATED)
                    [Names]
                        'lang_pack'
                        'lang_code'
                        'keys'
                    [Locals+Names]
                        'self'
                        'lang_pack'
                        'lang_code'
                        'keys'
                        '__assert_armored__'
                    [Constants]
                        '\n        :returns Vector<LangPackString>: This type has no constructors.\n        '
                        '__pyarmor_assert_29565__'
                        '__pyarmor_enter_29566__'
                        b'<COAddr>\x05\x00\x00\x1a@\x00\x00\x00\x00\x00\x00\x00\x00\x00\x00\x00\x00\x00\x00\x00'
                        '__pyarmor_exit_29567__'
                        None
                    [Disassembly]
                        0       NOP                             
                        2       NOP                             
                        4       PUSH_NULL                       
                        6       LOAD_CONST                      2: '__pyarmor_enter_29566__'
                        8       LOAD_CONST                      3: b'<COAddr>\x05\x00\x00\x1a@\x00\x00\x00\x00\x00\x00\x00\x00\x00\x00\x00\x00\x00\x00\x00'
                        10      BUILD_TUPLE                     1
                        12      CALL_FUNCTION_EX                0
                        14      POP_TOP                         
                        16      RESUME                          0
                        18      NOP                             
                        20      NOP                             
                        22      NOP                             
                        24      NOP                             
                        26      NOP                             
                        28      LOAD_FAST                       1: lang_pack
                        30      LOAD_FAST                       0: self
                        32      STORE_ATTR                      0: lang_pack
                        42      LOAD_FAST                       2: lang_code
                        44      LOAD_FAST                       0: self
                        46      STORE_ATTR                      1: lang_code
                        56      LOAD_FAST                       3: keys
                        58      LOAD_FAST                       0: self
                        60      STORE_ATTR                      2: keys
                        70      LOAD_CONST                      5: None
                        72      NOP                             
                        74      NOP                             
                        76      NOP                             
                        78      JUMP_FORWARD                    19 (to 118)
                        86      POP_TOP                         
                        88      RETURN_CONST                    5: None
                        90      PUSH_EXC_INFO                   
                        92      PUSH_NULL                       
                        94      LOAD_CONST                      4: '__pyarmor_exit_29567__'
                        96      NOP                             
                        98      LOAD_CONST                      3: b'<COAddr>\x05\x00\x00\x1a@\x00\x00\x00\x00\x00\x00\x00\x00\x00\x00\x00\x00\x00\x00\x00'
                        100     CALL                            1
                        108     POP_TOP                         
                        110     RERAISE                         0
                        112     COPY                            3
                        114     POP_EXCEPT                      
                        116     RERAISE                         1
                        118     PUSH_NULL                       
                        120     LOAD_CONST                      4: '__pyarmor_exit_29567__'
                        122     LOAD_CONST                      3: b'<COAddr>\x05\x00\x00\x1a@\x00\x00\x00\x00\x00\x00\x00\x00\x00\x00\x00\x00\x00\x00\x00'
                        124     BUILD_TUPLE                     1
                        126     CALL_FUNCTION_EX                0
                        128     POP_TOP                         
                        130     RETURN_VALUE                    
                    [Exception Table]
                        28 to 70 -> 90 [0] 
                        90 to 112 -> 112 [1] lasti
                [Code]
                    File Name: <frozen multithon.tl.functions.langpack>
                    Object Name: to_dict
                    Qualified Name: GetStringsRequest.to_dict
                    Arg Count: 1
                    Pos Only Arg Count: 0
                    KW Only Arg Count: 0
                    Stack Size: 10
                    Flags: 0x20000003 (CO_OPTIMIZED | CO_NEWLOCALS | CO_PYARMOR_OBFUSCATED)
                    [Names]
                        'lang_pack'
                        'lang_code'
                        'keys'
                    [Locals+Names]
                        'self'
                        '__assert_armored__'
                    [Constants]
                        None
                        '__pyarmor_assert_29568__'
                        '__pyarmor_enter_29569__'
                        b'<COAddr>\x07\x00\x00\x1a\xaa\x00\x00\x00\x00\x00\x00\x00\x00\x00\x00\x00\x00\x00\x00\x00'
                        '_'
                        'GetStringsRequest'   # b'\x81\xc5\x1d\x07\x00\xee\xac\xdb\x15\xfd\x1e\xf2i\xfd\xed\x80\x1cI'
                        'lang_pack'   # b'\x81\xee\x19\x1d4\xc5\xae\xd3\x18\xf1'
                        'lang_code'   # b'\x81\xee\x19\x1d4\xc5\xbd\xdd\x1f\xff'
                        'keys'
                        '__pyarmor_exit_29570__'
                    [Disassembly]
                        0       NOP                             
                        2       NOP                             
                        4       PUSH_NULL                       
                        6       LOAD_CONST                      2: '__pyarmor_enter_29569__'
                        8       LOAD_CONST                      3: b'<COAddr>\x07\x00\x00\x1a\xaa\x00\x00\x00\x00\x00\x00\x00\x00\x00\x00\x00\x00\x00\x00\x00'
                        10      BUILD_TUPLE                     1
                        12      CALL_FUNCTION_EX                0
                        14      POP_TOP                         
                        16      RESUME                          0
                        18      NOP                             
                        20      NOP                             
                        22      NOP                             
                        24      NOP                             
                        26      NOP                             
                        28      LOAD_CONST                      4: '_'
                        30      PUSH_NULL                       
                        32      LOAD_CONST                      1: '__pyarmor_assert_29568__'
                        34      LOAD_CONST                      5: 'GetStringsRequest'   # b'\x81\xc5\x1d\x07\x00\xee\xac\xdb\x15\xfd\x1e\xf2i\xfd\xed\x80\x1cI'
                        36      CALL                            1
                        44      PUSH_NULL                       
                        46      LOAD_CONST                      1: '__pyarmor_assert_29568__'
                        48      LOAD_CONST                      6: 'lang_pack'   # b'\x81\xee\x19\x1d4\xc5\xae\xd3\x18\xf1'
                        50      CALL                            1
                        58      LOAD_FAST                       0: self
                        60      LOAD_ATTR                       0: lang_pack
                        80      PUSH_NULL                       
                        82      LOAD_CONST                      1: '__pyarmor_assert_29568__'
                        84      LOAD_CONST                      7: 'lang_code'   # b'\x81\xee\x19\x1d4\xc5\xbd\xdd\x1f\xff'
                        86      CALL                            1
                        94      LOAD_FAST                       0: self
                        96      LOAD_ATTR                       2: lang_code
                        116     LOAD_CONST                      8: 'keys'
                        118     LOAD_FAST                       0: self
                        120     LOAD_ATTR                       4: keys
                        140     POP_JUMP_IF_NOT_NONE            2 (to 146)
                        142     BUILD_LIST                      0
                        144     JUMP_FORWARD                    14 (to 174)
                        146     LOAD_FAST                       0: self
                        148     LOAD_ATTR                       4: keys
                        168     LOAD_CONST                      0: None
                        170     LOAD_CONST                      0: None
                        172     BINARY_SLICE                    
                        174     BUILD_MAP                       4
                        176     NOP                             
                        178     NOP                             
                        180     NOP                             
                        182     JUMP_FORWARD                    20 (to 224)
                        184     CALL                            1
                        192     POP_TOP                         
                        194     RETURN_VALUE                    
                        196     PUSH_EXC_INFO                   
                        198     PUSH_NULL                       
                        200     LOAD_CONST                      9: '__pyarmor_exit_29570__'
                        202     NOP                             
                        204     LOAD_CONST                      3: b'<COAddr>\x07\x00\x00\x1a\xaa\x00\x00\x00\x00\x00\x00\x00\x00\x00\x00\x00\x00\x00\x00\x00'
                        206     CALL                            1
                        214     POP_TOP                         
                        216     RERAISE                         0
                        218     COPY                            3
                        220     POP_EXCEPT                      
                        222     RERAISE                         1
                        224     PUSH_NULL                       
                        226     LOAD_CONST                      9: '__pyarmor_exit_29570__'
                        228     LOAD_CONST                      3: b'<COAddr>\x07\x00\x00\x1a\xaa\x00\x00\x00\x00\x00\x00\x00\x00\x00\x00\x00\x00\x00\x00\x00'
                        230     BUILD_TUPLE                     1
                        232     CALL_FUNCTION_EX                0
                        234     POP_TOP                         
                        236     RETURN_VALUE                    
                    [Exception Table]
                        28 to 176 -> 196 [0] 
                        196 to 218 -> 218 [1] lasti
                [Code]
                    File Name: <frozen multithon.tl.functions.langpack>
                    Object Name: _bytes
                    Qualified Name: GetStringsRequest._bytes
                    Arg Count: 1
                    Pos Only Arg Count: 0
                    KW Only Arg Count: 0
                    Stack Size: 12
                    Flags: 0x20000003 (CO_OPTIMIZED | CO_NEWLOCALS | CO_PYARMOR_OBFUSCATED)
                    [Names]
                        'join'
                        'serialize_bytes'
                        'lang_pack'
                        'lang_code'
                        'struct'
                        'pack'
                        'len'
                        'keys'
                    [Locals+Names]
                        'self'
                        '__assert_armored__'
                    [Constants]
                        None
                        '__pyarmor_assert_29571__'
                        '__pyarmor_enter_29572__'
                        b'<COAddr>\x07\x00\x00\x1c8\x01\x00\x00\x00\x00\x00\x00\x00\x00\x00\x00\x00\x00\x00\x00'
                        b''
                        b'\x038\xea\xef'
                        b'\x15\xc4\xb5\x1c'
                        '<i'
                        [Code]
                            File Name: <frozen multithon.tl.functions.langpack>
                            Object Name: <genexpr>
                            Qualified Name: GetStringsRequest._bytes.<locals>.<genexpr>
                            Arg Count: 1
                            Pos Only Arg Count: 0
                            KW Only Arg Count: 0
                            Stack Size: 4
                            Flags: 0x00000033 (CO_OPTIMIZED | CO_NEWLOCALS | CO_NESTED | CO_GENERATOR)
                            [Names]
                                'serialize_bytes'
                            [Locals+Names]
                                '.0'
                                '_var_var_3'
                                'self'
                            [Constants]
                                None
                            [Disassembly]
                                0       COPY_FREE_VARS                  1
                                2       RETURN_GENERATOR                
                                4       POP_TOP                         
                                6       RESUME                          0
                                8       LOAD_FAST                       0: .0
                                10      FOR_ITER                        21 (to 54)
                                14      STORE_FAST                      1: _var_var_3
                                16      LOAD_DEREF                      2: self
                                18      LOAD_ATTR                       1: serialize_bytes
                                38      LOAD_FAST                       1: _var_var_3
                                40      CALL                            1
                                48      YIELD_VALUE                     1
                                50      RESUME                          1
                                52      POP_TOP                         
                                54      JUMP_BACKWARD                   23 (to 10)
                                56      END_FOR                         
                                58      RETURN_CONST                    0: None
                                60      CALL_INTRINSIC_1                3 (INTRINSIC_STOPITERATION_ERROR)
                                62      RERAISE                         1
                            [Exception Table]
                                6 to 60 -> 60 [0] lasti
                        '__pyarmor_exit_29573__'
                    [Disassembly]
                        0       MAKE_CELL                       0: self
                        2       NOP                             
                        4       NOP                             
                        6       PUSH_NULL                       
                        8       LOAD_CONST                      2: '__pyarmor_enter_29572__'
                        10      LOAD_CONST                      3: b'<COAddr>\x07\x00\x00\x1c8\x01\x00\x00\x00\x00\x00\x00\x00\x00\x00\x00\x00\x00\x00\x00'
                        12      BUILD_TUPLE                     1
                        14      CALL_FUNCTION_EX                0
                        16      POP_TOP                         
                        18      RESUME                          0
                        20      NOP                             
                        22      NOP                             
                        24      NOP                             
                        26      NOP                             
                        28      NOP                             
                        30      LOAD_CONST                      4: b''
                        32      LOAD_ATTR                       1: join
                        52      LOAD_CONST                      5: b'\x038\xea\xef'
                        54      LOAD_DEREF                      0: self
                        56      LOAD_ATTR                       3: serialize_bytes
                        76      LOAD_DEREF                      0: self
                        78      LOAD_ATTR                       4: lang_pack
                        98      CALL                            1
                        106     LOAD_DEREF                      0: self
                        108     LOAD_ATTR                       3: serialize_bytes
                        128     LOAD_DEREF                      0: self
                        130     LOAD_ATTR                       6: lang_code
                        150     CALL                            1
                        158     LOAD_CONST                      6: b'\x15\xc4\xb5\x1c'
                        160     LOAD_GLOBAL                     9: NULL + struct
                        170     LOAD_ATTR                       10: pack
                        190     LOAD_CONST                      7: '<i'
                        192     LOAD_GLOBAL                     13: NULL + len
                        202     LOAD_DEREF                      0: self
                        204     LOAD_ATTR                       14: keys
                        224     CALL                            1
                        232     CALL                            2
                        240     LOAD_CONST                      4: b''
                        242     LOAD_ATTR                       1: join
                        262     LOAD_CLOSURE                    0: self
                        264     BUILD_TUPLE                     1
                        266     LOAD_CONST                      8: <CODE> <genexpr>
                        268     MAKE_FUNCTION                   8
                        270     LOAD_DEREF                      0: self
                        272     LOAD_ATTR                       14: keys
                        292     GET_ITER                        
                        294     CALL                            0
                        302     CALL                            1
                        310     BUILD_TUPLE                     6
                        312     CALL                            1
                        320     NOP                             
                        322     NOP                             
                        324     NOP                             
                        326     JUMP_FORWARD                    20 (to 368)
                        328     CALL                            1
                        336     POP_TOP                         
                        338     RETURN_VALUE                    
                        340     PUSH_EXC_INFO                   
                        342     PUSH_NULL                       
                        344     LOAD_CONST                      9: '__pyarmor_exit_29573__'
                        346     NOP                             
                        348     LOAD_CONST                      3: b'<COAddr>\x07\x00\x00\x1c8\x01\x00\x00\x00\x00\x00\x00\x00\x00\x00\x00\x00\x00\x00\x00'
                        350     CALL                            1
                        358     POP_TOP                         
                        360     RERAISE                         0
                        362     COPY                            3
                        364     POP_EXCEPT                      
                        366     RERAISE                         1
                        368     PUSH_NULL                       
                        370     LOAD_CONST                      9: '__pyarmor_exit_29573__'
                        372     LOAD_CONST                      3: b'<COAddr>\x07\x00\x00\x1c8\x01\x00\x00\x00\x00\x00\x00\x00\x00\x00\x00\x00\x00\x00\x00'
                        374     BUILD_TUPLE                     1
                        376     CALL_FUNCTION_EX                0
                        378     POP_TOP                         
                        380     RETURN_VALUE                    
                    [Exception Table]
                        30 to 320 -> 340 [0] 
                        340 to 362 -> 362 [1] lasti
                [Code]
                    File Name: <frozen multithon.tl.functions.langpack>
                    Object Name: from_reader
                    Qualified Name: GetStringsRequest.from_reader
                    Arg Count: 2
                    Pos Only Arg Count: 0
                    KW Only Arg Count: 0
                    Stack Size: 5
                    Flags: 0x20000003 (CO_OPTIMIZED | CO_NEWLOCALS | CO_PYARMOR_OBFUSCATED)
                    [Names]
                        'tgread_string'
                        'read_int'
                        'range'
                        'append'
                    [Locals+Names]
                        'cls'
                        'reader'
                        '__assert_armored__'
                        '_var_var_0'
                        '_var_var_1'
                        '_var_var_4'
                        '_var_var_5'
                        '_var_var_6'
                    [Constants]
                        None
                        '__pyarmor_assert_29574__'
                        '__pyarmor_enter_29575__'
                        b'<COAddr>\x07\x00\x00\x1a\x0c\x01\x00\x00\x00\x00\x00\x00\x00\x00\x00\x00\x00\x00\x00\x00'
                        (
                            'lang_pack'
                            'lang_code'
                            'keys'
                        )
                        '__pyarmor_exit_29576__'
                    [Disassembly]
                        0       NOP                             
                        2       NOP                             
                        4       PUSH_NULL                       
                        6       LOAD_CONST                      2: '__pyarmor_enter_29575__'
                        8       LOAD_CONST                      3: b'<COAddr>\x07\x00\x00\x1a\x0c\x01\x00\x00\x00\x00\x00\x00\x00\x00\x00\x00\x00\x00\x00\x00'
                        10      BUILD_TUPLE                     1
                        12      CALL_FUNCTION_EX                0
                        14      POP_TOP                         
                        16      RESUME                          0
                        18      NOP                             
                        20      NOP                             
                        22      NOP                             
                        24      NOP                             
                        26      NOP                             
                        28      LOAD_FAST                       1: reader
                        30      LOAD_ATTR                       1: tgread_string
                        50      CALL                            0
                        58      STORE_FAST                      3: _var_var_0
                        60      LOAD_FAST                       1: reader
                        62      LOAD_ATTR                       1: tgread_string
                        82      CALL                            0
                        90      STORE_FAST                      4: _var_var_1
                        92      LOAD_FAST                       1: reader
                        94      LOAD_ATTR                       3: read_int
                        114     CALL                            0
                        122     POP_TOP                         
                        124     BUILD_LIST                      0
                        126     STORE_FAST                      5: _var_var_4
                        128     LOAD_GLOBAL                     5: NULL + range
                        138     LOAD_FAST                       1: reader
                        140     LOAD_ATTR                       3: read_int
                        160     CALL                            0
                        168     CALL                            1
                        176     GET_ITER                        
                        178     FOR_ITER                        35 (to 250)
                        182     STORE_FAST                      6: _var_var_5
                        184     LOAD_FAST                       1: reader
                        186     LOAD_ATTR                       1: tgread_string
                        206     CALL                            0
                        214     STORE_FAST                      7: _var_var_6
                        216     LOAD_FAST                       5: _var_var_4
                        218     LOAD_ATTR                       7: append
                        238     LOAD_FAST                       7: _var_var_6
                        240     CALL                            1
                        248     POP_TOP                         
                        250     JUMP_BACKWARD                   37 (to 178)
                        252     END_FOR                         
                        254     PUSH_NULL                       
                        256     LOAD_FAST                       0: cls
                        258     LOAD_FAST                       3: _var_var_0
                        260     LOAD_FAST                       4: _var_var_1
                        262     LOAD_FAST                       5: _var_var_4
                        264     KW_NAMES                        4: ('lang_pack', 'lang_code', 'keys')
                        266     CALL                            3
                        274     NOP                             
                        276     NOP                             
                        278     NOP                             
                        280     JUMP_FORWARD                    20 (to 322)
                        282     CALL                            1
                        290     POP_TOP                         
                        292     RETURN_VALUE                    
                        294     PUSH_EXC_INFO                   
                        296     PUSH_NULL                       
                        298     LOAD_CONST                      5: '__pyarmor_exit_29576__'
                        300     NOP                             
                        302     LOAD_CONST                      3: b'<COAddr>\x07\x00\x00\x1a\x0c\x01\x00\x00\x00\x00\x00\x00\x00\x00\x00\x00\x00\x00\x00\x00'
                        304     CALL                            1
                        312     POP_TOP                         
                        314     RERAISE                         0
                        316     COPY                            3
                        318     POP_EXCEPT                      
                        320     RERAISE                         1
                        322     PUSH_NULL                       
                        324     LOAD_CONST                      5: '__pyarmor_exit_29576__'
                        326     LOAD_CONST                      3: b'<COAddr>\x07\x00\x00\x1a\x0c\x01\x00\x00\x00\x00\x00\x00\x00\x00\x00\x00\x00\x00\x00\x00'
                        328     BUILD_TUPLE                     1
                        330     CALL_FUNCTION_EX                0
                        332     POP_TOP                         
                        334     RETURN_VALUE                    
                    [Exception Table]
                        28 to 274 -> 294 [0] 
                        294 to 316 -> 316 [1] lasti
                '__pyarmor_exit_29564__'
                None
            [Disassembly]
                0       NOP                             
                2       LOAD_NAME                       0: __name__
                4       STORE_NAME                      1: __module__
                6       LOAD_CONST                      0: 'GetStringsRequest'
                8       STORE_NAME                      2: __qualname__
                10      NOP                             
                12      PUSH_NULL                       
                14      LOAD_CONST                      2: '__pyarmor_enter_29563__'
                16      LOAD_CONST                      3: b'<COAddr>\x07\x00\x00"T\x00\x00\x00\x00\x00\x00\x00\x00\x00\x00\x00\x00\x00\x00\x00'
                18      BUILD_TUPLE                     1
                20      CALL_FUNCTION_EX                0
                22      POP_TOP                         
                24      RESUME                          0
                26      NOP                             
                28      NOP                             
                30      NOP                             
                32      NOP                             
                34      NOP                             
                36      LOAD_CONST                      4: 0xEFEA3803
                38      STORE_NAME                      4: CONSTRUCTOR_ID
                40      LOAD_CONST                      5: 0xC7B7353D
                42      STORE_NAME                      5: SUBCLASS_OF_ID
                44      LOAD_CONST                      6: 'lang_pack'
                46      LOAD_NAME                       6: str
                48      LOAD_CONST                      7: 'lang_code'
                50      LOAD_NAME                       6: str
                52      LOAD_CONST                      8: 'keys'
                54      LOAD_NAME                       7: List
                56      LOAD_NAME                       6: str
                58      BINARY_SUBSCR                   
                62      BUILD_TUPLE                     6
                64      LOAD_CONST                      9: <CODE> __init__
                66      MAKE_FUNCTION                   4
                68      STORE_NAME                      8: __init__
                70      LOAD_CONST                      10: <CODE> to_dict
                72      MAKE_FUNCTION                   0
                74      STORE_NAME                      9: to_dict
                76      LOAD_CONST                      11: <CODE> _bytes
                78      MAKE_FUNCTION                   0
                80      STORE_NAME                      10: _bytes
                82      LOAD_NAME                       11: classmethod
                84      LOAD_CONST                      12: <CODE> from_reader
                86      MAKE_FUNCTION                   0
                88      CALL                            0
                96      STORE_NAME                      12: from_reader
                98      LOAD_CONST                      14: None
                100     NOP                             
                102     NOP                             
                104     NOP                             
                106     JUMP_FORWARD                    19 (to 146)
                114     POP_TOP                         
                116     RETURN_CONST                    14: None
                118     PUSH_EXC_INFO                   
                120     PUSH_NULL                       
                122     LOAD_CONST                      13: '__pyarmor_exit_29564__'
                124     NOP                             
                126     LOAD_CONST                      3: b'<COAddr>\x07\x00\x00"T\x00\x00\x00\x00\x00\x00\x00\x00\x00\x00\x00\x00\x00\x00\x00'
                128     CALL                            1
                136     POP_TOP                         
                138     RERAISE                         0
                140     COPY                            3
                142     POP_EXCEPT                      
                144     RERAISE                         1
                146     PUSH_NULL                       
                148     LOAD_CONST                      13: '__pyarmor_exit_29564__'
                150     LOAD_CONST                      3: b'<COAddr>\x07\x00\x00"T\x00\x00\x00\x00\x00\x00\x00\x00\x00\x00\x00\x00\x00\x00\x00'
                152     BUILD_TUPLE                     1
                154     CALL_FUNCTION_EX                0
                156     POP_TOP                         
                158     RETURN_VALUE                    
            [Exception Table]
                36 to 98 -> 118 [0] 
                118 to 140 -> 140 [1] lasti
        'GetStringsRequest'
        '__pyarmor_exit_29474__'
    [Disassembly]
        0       NOP                             
        2       NOP                             
        4       PUSH_NULL                       
        6       LOAD_CONST                      1: '__pyarmor_enter_29473__'
        8       LOAD_CONST                      2: b'<COAddr>\x07\x00\x00\x1a\n\x01\x00\x00\x00\x00\x00\x00\x00\x00\x00\x00\x00\x00\x00\x00'
        10      BUILD_TUPLE                     1
        12      CALL_FUNCTION_EX                0
        14      POP_TOP                         
        16      RESUME                          0
        18      NOP                             
        20      NOP                             
        22      NOP                             
        24      NOP                             
        26      PUSH_NULL                       
        28      LOAD_CONST                      0: '__pyarmor_assert_29472__'
        30      LOAD_CONST                      3: "File generated by TLObjects' generator. All changes will be ERASED"   # b'\x81\xc4\x11\x1f6\xba\xb9\xd7\x15\xff\x1f\xc1x\xe9\xfc\xc5\rD\xfb\x93\x86\xe4L\xc6\x00l\xb7OG\xf1\x19\xe04W2\x0c\x8c\xc5\xa6`X\xc8\xf4Q\x9d\xdb\x07F9\xeaS\xe8\xc7g\x0f\xe1;\xab\x99\x18Xn\x03rdm!'
        32      CALL                            1
        40      POP_TOP                         
        42      LOAD_CONST                      4: 3
        44      LOAD_CONST                      5: ('TLObject',)
        46      IMPORT_NAME                     1: tl.tlobject
        48      IMPORT_FROM                     2: TLObject
        50      STORE_NAME                      2: TLObject
        52      POP_TOP                         
        54      LOAD_CONST                      4: 3
        56      LOAD_CONST                      6: ('TLRequest',)
        58      IMPORT_NAME                     1: tl.tlobject
        60      IMPORT_FROM                     3: TLRequest
        62      STORE_NAME                      3: TLRequest
        64      POP_TOP                         
        66      LOAD_CONST                      7: 0
        68      LOAD_CONST                      8: ('Optional', 'List', 'Union', 'TYPE_CHECKING')
        70      IMPORT_NAME                     4: typing
        72      IMPORT_FROM                     5: Optional
        74      STORE_NAME                      5: Optional
        76      IMPORT_FROM                     6: List
        78      STORE_NAME                      6: List
        80      IMPORT_FROM                     7: Union
        82      STORE_NAME                      7: Union
        84      IMPORT_FROM                     8: TYPE_CHECKING
        86      STORE_NAME                      8: TYPE_CHECKING
        88      POP_TOP                         
        90      LOAD_CONST                      7: 0
        92      LOAD_CONST                      9: None
        94      IMPORT_NAME                     9: os
        96      STORE_NAME                      9: os
        98      LOAD_CONST                      7: 0
        100     LOAD_CONST                      9: None
        102     IMPORT_NAME                     10: struct
        104     STORE_NAME                      10: struct
        106     LOAD_CONST                      7: 0
        108     LOAD_CONST                      10: ('datetime',)
        110     IMPORT_NAME                     11: datetime
        112     IMPORT_FROM                     11: datetime
        114     STORE_NAME                      11: datetime
        116     POP_TOP                         
        118     PUSH_NULL                       
        120     LOAD_BUILD_CLASS                
        122     LOAD_CONST                      11: <CODE> GetDifferenceRequest
        124     MAKE_FUNCTION                   0
        126     LOAD_CONST                      12: 'GetDifferenceRequest'
        128     LOAD_NAME                       3: TLRequest
        130     CALL                            3
        138     STORE_NAME                      12: GetDifferenceRequest
        140     PUSH_NULL                       
        142     LOAD_BUILD_CLASS                
        144     LOAD_CONST                      13: <CODE> GetLangPackRequest
        146     MAKE_FUNCTION                   0
        148     LOAD_CONST                      14: 'GetLangPackRequest'
        150     LOAD_NAME                       3: TLRequest
        152     CALL                            3
        160     STORE_NAME                      13: GetLangPackRequest
        162     PUSH_NULL                       
        164     LOAD_BUILD_CLASS                
        166     LOAD_CONST                      15: <CODE> GetLangPack_tdlib_Request
        168     MAKE_FUNCTION                   0
        170     LOAD_CONST                      16: 'GetLangPack_tdlib_Request'
        172     LOAD_NAME                       3: TLRequest
        174     CALL                            3
        182     STORE_NAME                      14: GetLangPack_tdlib_Request
        184     PUSH_NULL                       
        186     LOAD_BUILD_CLASS                
        188     LOAD_CONST                      17: <CODE> GetLanguageRequest
        190     MAKE_FUNCTION                   0
        192     LOAD_CONST                      18: 'GetLanguageRequest'
        194     LOAD_NAME                       3: TLRequest
        196     CALL                            3
        204     STORE_NAME                      15: GetLanguageRequest
        206     PUSH_NULL                       
        208     LOAD_BUILD_CLASS                
        210     LOAD_CONST                      19: <CODE> GetLanguagesRequest
        212     MAKE_FUNCTION                   0
        214     LOAD_CONST                      20: 'GetLanguagesRequest'
        216     LOAD_NAME                       3: TLRequest
        218     CALL                            3
        226     STORE_NAME                      16: GetLanguagesRequest
        228     PUSH_NULL                       
        230     LOAD_BUILD_CLASS                
        232     LOAD_CONST                      21: <CODE> GetLanguages_tdlib_Request
        234     MAKE_FUNCTION                   0
        236     LOAD_CONST                      22: 'GetLanguages_tdlib_Request'
        238     LOAD_NAME                       3: TLRequest
        240     CALL                            3
        248     STORE_NAME                      17: GetLanguages_tdlib_Request
        250     PUSH_NULL                       
        252     LOAD_BUILD_CLASS                
        254     LOAD_CONST                      23: <CODE> GetStringsRequest
        256     MAKE_FUNCTION                   0
        258     LOAD_CONST                      24: 'GetStringsRequest'
        260     LOAD_NAME                       3: TLRequest
        262     CALL                            3
        270     STORE_NAME                      18: GetStringsRequest
        272     LOAD_CONST                      9: None
        274     NOP                             
        276     NOP                             
        278     NOP                             
        280     JUMP_FORWARD                    19 (to 320)
        288     POP_TOP                         
        290     RETURN_CONST                    9: None
        292     PUSH_EXC_INFO                   
        294     PUSH_NULL                       
        296     LOAD_CONST                      25: '__pyarmor_exit_29474__'
        298     NOP                             
        300     LOAD_CONST                      2: b'<COAddr>\x07\x00\x00\x1a\n\x01\x00\x00\x00\x00\x00\x00\x00\x00\x00\x00\x00\x00\x00\x00'
        302     CALL                            1
        310     POP_TOP                         
        312     RERAISE                         0
        314     COPY                            3
        316     POP_EXCEPT                      
        318     RERAISE                         1
        320     PUSH_NULL                       
        322     LOAD_CONST                      25: '__pyarmor_exit_29474__'
        324     LOAD_CONST                      2: b'<COAddr>\x07\x00\x00\x1a\n\x01\x00\x00\x00\x00\x00\x00\x00\x00\x00\x00\x00\x00\x00\x00'
        326     BUILD_TUPLE                     1
        328     CALL_FUNCTION_EX                0
        330     POP_TOP                         
        332     RETURN_VALUE                    
    [Exception Table]
        26 to 272 -> 292 [0] 
        292 to 314 -> 314 [1] lasti
