#decoded by lolz.live/mrpenny / t.me/zeus_jackpot
# ================================
# Примечания по Pyarmor:
# - Байт-код и объекты кода Pyarmor соответствуют стандартному Python, но присутствуют специальные вызовы функций среды выполнения (runtime) Pyarmor.
# - Вызовы строк — это не ошибки, а маркеры, которые обрабатываются Pyarmor во время выполнения.
#
# Руководство по декомпиляции (без среды выполнения):
# 1. Игнорируйте зашифрованные байты после `#`; используйте только строку до `#`.
# 2. Удалите "__pyarmor_enter_xxx__"(b"<COAddr>...") и "__pyarmor_leave_xxx__"(b"<COAddr>...") (пролог/эпилог).
# 3. "__pyarmor_assert_xxx__"(A) не является настоящим оператором assert.
#    - Если A — это имя или читаемая строка: замените на A.
#    - Если A — это (X, "Y"): замените на X.Y.
#    - Если A — это (X, "Y", Z): замените на X.Y = Z.
#    - В противном случае: выберите наиболее подходящую/логичную замену.
# 4. "__pyarmor_bcc_xxx__"(...) указывает на машинный (нативный) код; тело функции недоступно. Добавьте комментарий.
# ================================

[Code]
    File Name: <frozen multithon.tl.functions.premium>
    Object Name: <module>
    Qualified Name: <module>
    Arg Count: 0
    Pos Only Arg Count: 0
    KW Only Arg Count: 0
    Stack Size: 5
    Flags: 0x20000000 (CO_PYARMOR_OBFUSCATED)
    [Names]
        '__assert_armored__'
        'tl.tlobject'
        'TLObject'
        'TLRequest'
        'typing'
        'Optional'
        'List'
        'Union'
        'TYPE_CHECKING'
        'os'
        'struct'
        'datetime'
        'tl.types'
        'TypeInputPeer'
        'TypeInputUser'
        'ApplyBoostRequest'
        'GetBoostsListRequest'
        'GetBoostsStatusRequest'
        'GetMyBoostsRequest'
        'GetUserBoostsRequest'
    [Locals+Names]
    [Constants]
        '__pyarmor_assert_35532__'
        '__pyarmor_enter_35533__'
        b'<COAddr>\x07\x00\x00\x1a\xf2\x00\x00\x00\x00\x00\x00\x00\x00\x00\x00\x00\x00\x00\x00\x00'
        "File generated by TLObjects' generator. All changes will be ERASED"   # b'\x81\xc4\x11\x1f6\xba\xb9\xd7\x15\xff\x1f\xc1x\xe9\xfc\xc5\rD\xfb\x93\x86\xe4L\xc6\x00l\xb7OG\xf1\x19\xe04W2\x0c\x8c\xc5\xa6`X\xc8\xf4Q\x9d\xdb\x07F9\xeaS\xe8\xc7g\x0f\xe1;\xab\x99\x18Xn\x03rdm!'
        3
        (
            'TLObject'
        )
        (
            'TLRequest'
        )
        0
        (
            'Optional'
            'List'
            'Union'
            'TYPE_CHECKING'
        )
        None
        (
            'datetime'
        )
        (
            'TypeInputPeer'
            'TypeInputUser'
        )
        [Code]
            File Name: <frozen multithon.tl.functions.premium>
            Object Name: ApplyBoostRequest
            Qualified Name: ApplyBoostRequest
            Arg Count: 0
            Pos Only Arg Count: 0
            KW Only Arg Count: 0
            Stack Size: 7
            Flags: 0x20000000 (CO_PYARMOR_OBFUSCATED)
            [Names]
                '__name__'
                '__module__'
                '__qualname__'
                '__assert_armored__'
                'CONSTRUCTOR_ID'
                'SUBCLASS_OF_ID'
                'Optional'
                'List'
                'int'
                '__init__'
                'resolve'
                'to_dict'
                '_bytes'
                'classmethod'
                'from_reader'
            [Locals+Names]
            [Constants]
                'ApplyBoostRequest'
                '__pyarmor_assert_35535__'
                '__pyarmor_enter_35536__'
                b'<COAddr>\x07\x00\x00"j\x00\x00\x00\x00\x00\x00\x00\x00\x00\x00\x00\x00\x00\x00\x00'
                1803396934
                0xAD3512DB
                None
                'peer'
                'TypeInputPeer'   # b'\x81\xd6\x01\x036\xd3\xb0\xc2\x0e\xee=\xc5i\xfe'
                'slots'
                [Code]
                    File Name: <frozen multithon.tl.functions.premium>
                    Object Name: __init__
                    Qualified Name: ApplyBoostRequest.__init__
                    Arg Count: 3
                    Pos Only Arg Count: 0
                    KW Only Arg Count: 0
                    Stack Size: 5
                    Flags: 0x20000003 (CO_OPTIMIZED | CO_NEWLOCALS | CO_PYARMOR_OBFUSCATED)
                    [Names]
                        'peer'
                        'slots'
                    [Locals+Names]
                        'self'
                        'peer'
                        'slots'
                        '__assert_armored__'
                    [Constants]
                        '\n        :returns premium.MyBoosts: Instance of MyBoosts.\n        '
                        '__pyarmor_assert_35538__'
                        '__pyarmor_enter_35539__'
                        b'<COAddr>\x05\x00\x00\x1a2\x00\x00\x00\x00\x00\x00\x00\x00\x00\x00\x00\x00\x00\x00\x00'
                        '__pyarmor_exit_35540__'
                        None
                    [Disassembly]
                        0       NOP                             
                        2       NOP                             
                        4       PUSH_NULL                       
                        6       LOAD_CONST                      2: '__pyarmor_enter_35539__'
                        8       LOAD_CONST                      3: b'<COAddr>\x05\x00\x00\x1a2\x00\x00\x00\x00\x00\x00\x00\x00\x00\x00\x00\x00\x00\x00\x00'
                        10      BUILD_TUPLE                     1
                        12      CALL_FUNCTION_EX                0
                        14      POP_TOP                         
                        16      RESUME                          0
                        18      NOP                             
                        20      NOP                             
                        22      NOP                             
                        24      NOP                             
                        26      NOP                             
                        28      LOAD_FAST                       1: peer
                        30      LOAD_FAST                       0: self
                        32      STORE_ATTR                      0: peer
                        42      LOAD_FAST                       2: slots
                        44      LOAD_FAST                       0: self
                        46      STORE_ATTR                      1: slots
                        56      LOAD_CONST                      5: None
                        58      NOP                             
                        60      NOP                             
                        62      NOP                             
                        64      JUMP_FORWARD                    19 (to 104)
                        72      POP_TOP                         
                        74      RETURN_CONST                    5: None
                        76      PUSH_EXC_INFO                   
                        78      PUSH_NULL                       
                        80      LOAD_CONST                      4: '__pyarmor_exit_35540__'
                        82      NOP                             
                        84      LOAD_CONST                      3: b'<COAddr>\x05\x00\x00\x1a2\x00\x00\x00\x00\x00\x00\x00\x00\x00\x00\x00\x00\x00\x00\x00'
                        86      CALL                            1
                        94      POP_TOP                         
                        96      RERAISE                         0
                        98      COPY                            3
                        100     POP_EXCEPT                      
                        102     RERAISE                         1
                        104     PUSH_NULL                       
                        106     LOAD_CONST                      4: '__pyarmor_exit_35540__'
                        108     LOAD_CONST                      3: b'<COAddr>\x05\x00\x00\x1a2\x00\x00\x00\x00\x00\x00\x00\x00\x00\x00\x00\x00\x00\x00\x00'
                        110     BUILD_TUPLE                     1
                        112     CALL_FUNCTION_EX                0
                        114     POP_TOP                         
                        116     RETURN_VALUE                    
                    [Exception Table]
                        28 to 56 -> 76 [0] 
                        76 to 98 -> 98 [1] lasti
                [Code]
                    File Name: <frozen multithon.tl.functions.premium>
                    Object Name: resolve
                    Qualified Name: ApplyBoostRequest.resolve
                    Arg Count: 3
                    Pos Only Arg Count: 0
                    KW Only Arg Count: 0
                    Stack Size: 5
                    Flags: 0x20000083 (CO_OPTIMIZED | CO_NEWLOCALS | CO_COROUTINE | CO_PYARMOR_OBFUSCATED)
                    [Names]
                        'get_input_peer'
                        'get_input_entity'
                        'peer'
                    [Locals+Names]
                        'self'
                        'client'
                        'utils'
                        '__assert_armored__'
                    [Constants]
                        None
                        '__pyarmor_assert_35541__'
                        '__pyarmor_enter_35542__'
                        b'<COAddr>\x05\x00\x00\x1e\x88\x00\x00\x00\x00\x00\x00\x00\x00\x00\x00\x00\x00\x00\x00\x00'
                        '__pyarmor_exit_35543__'
                    [Disassembly]
                        0       RETURN_GENERATOR                
                        2       POP_TOP                         
                        4       NOP                             
                        6       NOP                             
                        8       PUSH_NULL                       
                        10      LOAD_CONST                      2: '__pyarmor_enter_35542__'
                        12      LOAD_CONST                      3: b'<COAddr>\x05\x00\x00\x1e\x88\x00\x00\x00\x00\x00\x00\x00\x00\x00\x00\x00\x00\x00\x00\x00'
                        14      BUILD_TUPLE                     1
                        16      CALL_FUNCTION_EX                0
                        18      POP_TOP                         
                        20      RESUME                          0
                        22      NOP                             
                        24      NOP                             
                        26      NOP                             
                        28      NOP                             
                        30      NOP                             
                        32      LOAD_FAST                       2: utils
                        34      LOAD_ATTR                       1: get_input_peer
                        54      LOAD_FAST                       1: client
                        56      LOAD_ATTR                       3: get_input_entity
                        76      LOAD_FAST                       0: self
                        78      LOAD_ATTR                       4: peer
                        98      CALL                            1
                        106     GET_AWAITABLE                   0
                        108     LOAD_CONST                      0: None
                        110     SEND                            3 (to 118)
                        114     YIELD_VALUE                     3
                        116     RESUME                          3
                        118     JUMP_BACKWARD_NO_INTERRUPT      5 (to 110)
                        120     END_SEND                        
                        122     CALL                            1
                        130     LOAD_FAST                       0: self
                        132     STORE_ATTR                      2: peer
                        142     LOAD_CONST                      0: None
                        144     NOP                             
                        146     NOP                             
                        148     NOP                             
                        150     JUMP_FORWARD                    23 (to 198)
                        158     POP_TOP                         
                        160     RETURN_CONST                    0: None
                        162     CLEANUP_THROW                   
                        164     JUMP_BACKWARD                   23 (to 120)
                        166     PUSH_EXC_INFO                   
                        168     PUSH_NULL                       
                        170     LOAD_CONST                      4: '__pyarmor_exit_35543__'
                        172     NOP                             
                        174     LOAD_CONST                      3: b'<COAddr>\x05\x00\x00\x1e\x88\x00\x00\x00\x00\x00\x00\x00\x00\x00\x00\x00\x00\x00\x00\x00'
                        176     CALL                            1
                        184     POP_TOP                         
                        186     RERAISE                         0
                        188     COPY                            3
                        190     POP_EXCEPT                      
                        192     RERAISE                         1
                        194     CALL_INTRINSIC_1                3 (INTRINSIC_STOPITERATION_ERROR)
                        196     RERAISE                         1
                        198     PUSH_NULL                       
                        200     LOAD_CONST                      4: '__pyarmor_exit_35543__'
                        202     LOAD_CONST                      3: b'<COAddr>\x05\x00\x00\x1e\x88\x00\x00\x00\x00\x00\x00\x00\x00\x00\x00\x00\x00\x00\x00\x00'
                        204     BUILD_TUPLE                     1
                        206     CALL_FUNCTION_EX                0
                        208     POP_TOP                         
                        210     RETURN_VALUE                    
                    [Exception Table]
                        4 to 30 -> 194 [0] lasti
                        32 to 114 -> 166 [0] 
                        114 to 116 -> 162 [4] 
                        116 to 142 -> 166 [0] 
                        142 to 162 -> 194 [0] lasti
                        162 to 164 -> 166 [0] 
                        166 to 188 -> 188 [1] lasti
                        188 to 194 -> 194 [0] lasti
                [Code]
                    File Name: <frozen multithon.tl.functions.premium>
                    Object Name: to_dict
                    Qualified Name: ApplyBoostRequest.to_dict
                    Arg Count: 1
                    Pos Only Arg Count: 0
                    KW Only Arg Count: 0
                    Stack Size: 5
                    Flags: 0x20000003 (CO_OPTIMIZED | CO_NEWLOCALS | CO_PYARMOR_OBFUSCATED)
                    [Names]
                        'isinstance'
                        'peer'
                        'TLObject'
                        'to_dict'
                        'slots'
                    [Locals+Names]
                        'self'
                        '__assert_armored__'
                    [Constants]
                        None
                        '__pyarmor_assert_35544__'
                        '__pyarmor_enter_35545__'
                        b'<COAddr>\x07\x00\x00\x1a\xde\x00\x00\x00\x00\x00\x00\x00\x00\x00\x00\x00\x00\x00\x00\x00'
                        'ApplyBoostRequest'   # b'\x81\xc3\x08\x03?\xe3\x9c\xdd\x14\xe9\x19\xf2i\xfd\xed\x80\x1cI'
                        (
                            '_'
                            'peer'
                            'slots'
                        )
                        '__pyarmor_exit_35546__'
                    [Disassembly]
                        0       NOP                             
                        2       NOP                             
                        4       PUSH_NULL                       
                        6       LOAD_CONST                      2: '__pyarmor_enter_35545__'
                        8       LOAD_CONST                      3: b'<COAddr>\x07\x00\x00\x1a\xde\x00\x00\x00\x00\x00\x00\x00\x00\x00\x00\x00\x00\x00\x00\x00'
                        10      BUILD_TUPLE                     1
                        12      CALL_FUNCTION_EX                0
                        14      POP_TOP                         
                        16      RESUME                          0
                        18      NOP                             
                        20      NOP                             
                        22      NOP                             
                        24      NOP                             
                        26      NOP                             
                        28      PUSH_NULL                       
                        30      LOAD_CONST                      1: '__pyarmor_assert_35544__'
                        32      LOAD_CONST                      4: 'ApplyBoostRequest'   # b'\x81\xc3\x08\x03?\xe3\x9c\xdd\x14\xe9\x19\xf2i\xfd\xed\x80\x1cI'
                        34      CALL                            1
                        42      LOAD_GLOBAL                     1: NULL + isinstance
                        52      LOAD_FAST                       0: self
                        54      LOAD_ATTR                       2: peer
                        74      LOAD_GLOBAL                     4: TLObject
                        84      CALL                            2
                        92      POP_JUMP_IF_FALSE               26 (to 146)
                        94      LOAD_FAST                       0: self
                        96      LOAD_ATTR                       2: peer
                        116     LOAD_ATTR                       7: to_dict
                        136     CALL                            0
                        144     JUMP_FORWARD                    11 (to 168)
                        146     LOAD_FAST                       0: self
                        148     LOAD_ATTR                       2: peer
                        168     LOAD_FAST                       0: self
                        170     LOAD_ATTR                       8: slots
                        190     POP_JUMP_IF_NOT_NONE            2 (to 196)
                        192     BUILD_LIST                      0
                        194     JUMP_FORWARD                    14 (to 224)
                        196     LOAD_FAST                       0: self
                        198     LOAD_ATTR                       8: slots
                        218     LOAD_CONST                      0: None
                        220     LOAD_CONST                      0: None
                        222     BINARY_SLICE                    
                        224     LOAD_CONST                      5: ('_', 'peer', 'slots')
                        226     BUILD_CONST_KEY_MAP             3
                        228     NOP                             
                        230     NOP                             
                        232     NOP                             
                        234     JUMP_FORWARD                    20 (to 276)
                        236     CALL                            1
                        244     POP_TOP                         
                        246     RETURN_VALUE                    
                        248     PUSH_EXC_INFO                   
                        250     PUSH_NULL                       
                        252     LOAD_CONST                      6: '__pyarmor_exit_35546__'
                        254     NOP                             
                        256     LOAD_CONST                      3: b'<COAddr>\x07\x00\x00\x1a\xde\x00\x00\x00\x00\x00\x00\x00\x00\x00\x00\x00\x00\x00\x00\x00'
                        258     CALL                            1
                        266     POP_TOP                         
                        268     RERAISE                         0
                        270     COPY                            3
                        272     POP_EXCEPT                      
                        274     RERAISE                         1
                        276     PUSH_NULL                       
                        278     LOAD_CONST                      6: '__pyarmor_exit_35546__'
                        280     LOAD_CONST                      3: b'<COAddr>\x07\x00\x00\x1a\xde\x00\x00\x00\x00\x00\x00\x00\x00\x00\x00\x00\x00\x00\x00\x00'
                        282     BUILD_TUPLE                     1
                        284     CALL_FUNCTION_EX                0
                        286     POP_TOP                         
                        288     RETURN_VALUE                    
                    [Exception Table]
                        28 to 228 -> 248 [0] 
                        248 to 270 -> 270 [1] lasti
                [Code]
                    File Name: <frozen multithon.tl.functions.premium>
                    Object Name: _bytes
                    Qualified Name: ApplyBoostRequest._bytes
                    Arg Count: 1
                    Pos Only Arg Count: 0
                    KW Only Arg Count: 0
                    Stack Size: 13
                    Flags: 0x20000003 (CO_OPTIMIZED | CO_NEWLOCALS | CO_PYARMOR_OBFUSCATED)
                    [Names]
                        'join'
                        'struct'
                        'pack'
                        'slots'
                        'len'
                        'peer'
                        '_bytes'
                    [Locals+Names]
                        'self'
                        '__assert_armored__'
                    [Constants]
                        None
                        '__pyarmor_assert_35547__'
                        '__pyarmor_enter_35548__'
                        b'<COAddr>\x05\x00\x00\x1a\xb8\x01\x00\x00\x00\x00\x00\x00\x00\x00\x00\x00\x00\x00\x00\x00'
                        b''
                        b'F\xa7}k'
                        '<I'
                        False
                        0
                        1
                        b'\x15\xc4\xb5\x1c'
                        '<i'
                        [Code]
                            File Name: <frozen multithon.tl.functions.premium>
                            Object Name: <genexpr>
                            Qualified Name: ApplyBoostRequest._bytes.<locals>.<genexpr>
                            Arg Count: 1
                            Pos Only Arg Count: 0
                            KW Only Arg Count: 0
                            Stack Size: 5
                            Flags: 0x00000033 (CO_OPTIMIZED | CO_NEWLOCALS | CO_NESTED | CO_GENERATOR)
                            [Names]
                                'struct'
                                'pack'
                            [Locals+Names]
                                '.0'
                                '_var_var_0'
                            [Constants]
                                '<i'
                                None
                            [Disassembly]
                                0       RETURN_GENERATOR                
                                2       POP_TOP                         
                                4       RESUME                          0
                                6       LOAD_FAST                       0: .0
                                8       FOR_ITER                        26 (to 62)
                                12      STORE_FAST                      1: _var_var_0
                                14      LOAD_GLOBAL                     1: NULL + struct
                                24      LOAD_ATTR                       2: pack
                                44      LOAD_CONST                      0: '<i'
                                46      LOAD_FAST                       1: _var_var_0
                                48      CALL                            2
                                56      YIELD_VALUE                     1
                                58      RESUME                          1
                                60      POP_TOP                         
                                62      JUMP_BACKWARD                   28 (to 8)
                                64      END_FOR                         
                                66      RETURN_CONST                    1: None
                                68      CALL_INTRINSIC_1                3 (INTRINSIC_STOPITERATION_ERROR)
                                70      RERAISE                         1
                            [Exception Table]
                                4 to 68 -> 68 [0] lasti
                        '__pyarmor_exit_35549__'
                    [Disassembly]
                        0       NOP                             
                        2       NOP                             
                        4       PUSH_NULL                       
                        6       LOAD_CONST                      2: '__pyarmor_enter_35548__'
                        8       LOAD_CONST                      3: b'<COAddr>\x05\x00\x00\x1a\xb8\x01\x00\x00\x00\x00\x00\x00\x00\x00\x00\x00\x00\x00\x00\x00'
                        10      BUILD_TUPLE                     1
                        12      CALL_FUNCTION_EX                0
                        14      POP_TOP                         
                        16      RESUME                          0
                        18      NOP                             
                        20      NOP                             
                        22      NOP                             
                        24      NOP                             
                        26      NOP                             
                        28      LOAD_CONST                      4: b''
                        30      LOAD_ATTR                       1: join
                        50      LOAD_CONST                      5: b'F\xa7}k'
                        52      LOAD_GLOBAL                     3: NULL + struct
                        62      LOAD_ATTR                       4: pack
                        82      LOAD_CONST                      6: '<I'
                        84      LOAD_FAST                       0: self
                        86      LOAD_ATTR                       6: slots
                        106     POP_JUMP_IF_NONE                14 (to 136)
                        108     LOAD_FAST                       0: self
                        110     LOAD_ATTR                       6: slots
                        130     LOAD_CONST                      7: False
                        132     IS_OP                           0 (is)
                        134     POP_JUMP_IF_FALSE               2 (to 140)
                        136     LOAD_CONST                      8: 0
                        138     JUMP_FORWARD                    1 (to 142)
                        140     LOAD_CONST                      9: 1
                        142     CALL                            2
                        150     LOAD_FAST                       0: self
                        152     LOAD_ATTR                       6: slots
                        172     POP_JUMP_IF_NONE                14 (to 202)
                        174     LOAD_FAST                       0: self
                        176     LOAD_ATTR                       6: slots
                        196     LOAD_CONST                      7: False
                        198     IS_OP                           0 (is)
                        200     POP_JUMP_IF_FALSE               2 (to 206)
                        202     LOAD_CONST                      4: b''
                        204     JUMP_FORWARD                    90 (to 386)
                        206     LOAD_CONST                      4: b''
                        208     LOAD_ATTR                       1: join
                        228     LOAD_CONST                      10: b'\x15\xc4\xb5\x1c'
                        230     LOAD_GLOBAL                     3: NULL + struct
                        240     LOAD_ATTR                       4: pack
                        260     LOAD_CONST                      11: '<i'
                        262     LOAD_GLOBAL                     9: NULL + len
                        272     LOAD_FAST                       0: self
                        274     LOAD_ATTR                       6: slots
                        294     CALL                            1
                        302     CALL                            2
                        310     LOAD_CONST                      4: b''
                        312     LOAD_ATTR                       1: join
                        332     LOAD_CONST                      12: <CODE> <genexpr>
                        334     MAKE_FUNCTION                   0
                        336     LOAD_FAST                       0: self
                        338     LOAD_ATTR                       6: slots
                        358     GET_ITER                        
                        360     CALL                            0
                        368     CALL                            1
                        376     BUILD_TUPLE                     3
                        378     CALL                            1
                        386     LOAD_FAST                       0: self
                        388     LOAD_ATTR                       10: peer
                        408     LOAD_ATTR                       13: _bytes
                        428     CALL                            0
                        436     BUILD_TUPLE                     4
                        438     CALL                            1
                        446     NOP                             
                        448     NOP                             
                        450     NOP                             
                        452     JUMP_FORWARD                    20 (to 494)
                        454     CALL                            1
                        462     POP_TOP                         
                        464     RETURN_VALUE                    
                        466     PUSH_EXC_INFO                   
                        468     PUSH_NULL                       
                        470     LOAD_CONST                      13: '__pyarmor_exit_35549__'
                        472     NOP                             
                        474     LOAD_CONST                      3: b'<COAddr>\x05\x00\x00\x1a\xb8\x01\x00\x00\x00\x00\x00\x00\x00\x00\x00\x00\x00\x00\x00\x00'
                        476     CALL                            1
                        484     POP_TOP                         
                        486     RERAISE                         0
                        488     COPY                            3
                        490     POP_EXCEPT                      
                        492     RERAISE                         1
                        494     PUSH_NULL                       
                        496     LOAD_CONST                      13: '__pyarmor_exit_35549__'
                        498     LOAD_CONST                      3: b'<COAddr>\x05\x00\x00\x1a\xb8\x01\x00\x00\x00\x00\x00\x00\x00\x00\x00\x00\x00\x00\x00\x00'
                        500     BUILD_TUPLE                     1
                        502     CALL_FUNCTION_EX                0
                        504     POP_TOP                         
                        506     RETURN_VALUE                    
                    [Exception Table]
                        28 to 446 -> 466 [0] 
                        466 to 488 -> 488 [1] lasti
                [Code]
                    File Name: <frozen multithon.tl.functions.premium>
                    Object Name: from_reader
                    Qualified Name: ApplyBoostRequest.from_reader
                    Arg Count: 2
                    Pos Only Arg Count: 0
                    KW Only Arg Count: 0
                    Stack Size: 5
                    Flags: 0x20000003 (CO_OPTIMIZED | CO_NEWLOCALS | CO_PYARMOR_OBFUSCATED)
                    [Names]
                        'read_int'
                        'range'
                        'append'
                        'tgread_object'
                    [Locals+Names]
                        'cls'
                        'reader'
                        '__assert_armored__'
                        '_var_var_1'
                        '_var_var_2'
                        '_var_var_3'
                        '_var_var_4'
                        '_var_var_5'
                    [Constants]
                        None
                        '__pyarmor_assert_35550__'
                        '__pyarmor_enter_35551__'
                        b'<COAddr>\x05\x00\x00\x1a\x1a\x01\x00\x00\x00\x00\x00\x00\x00\x00\x00\x00\x00\x00\x00\x00'
                        1
                        (
                            'peer'
                            'slots'
                        )
                        '__pyarmor_exit_35552__'
                    [Disassembly]
                        0       NOP                             
                        2       NOP                             
                        4       PUSH_NULL                       
                        6       LOAD_CONST                      2: '__pyarmor_enter_35551__'
                        8       LOAD_CONST                      3: b'<COAddr>\x05\x00\x00\x1a\x1a\x01\x00\x00\x00\x00\x00\x00\x00\x00\x00\x00\x00\x00\x00\x00'
                        10      BUILD_TUPLE                     1
                        12      CALL_FUNCTION_EX                0
                        14      POP_TOP                         
                        16      RESUME                          0
                        18      NOP                             
                        20      NOP                             
                        22      NOP                             
                        24      NOP                             
                        26      NOP                             
                        28      LOAD_FAST                       1: reader
                        30      LOAD_ATTR                       1: read_int
                        50      CALL                            0
                        58      STORE_FAST                      3: _var_var_1
                        60      LOAD_FAST                       3: _var_var_1
                        62      LOAD_CONST                      4: 1
                        64      BINARY_OP                       1 (&)
                        68      POP_JUMP_IF_FALSE               82 (to 234)
                        70      LOAD_FAST                       1: reader
                        72      LOAD_ATTR                       1: read_int
                        92      CALL                            0
                        100     POP_TOP                         
                        102     BUILD_LIST                      0
                        104     STORE_FAST                      4: _var_var_2
                        106     LOAD_GLOBAL                     3: NULL + range
                        116     LOAD_FAST                       1: reader
                        118     LOAD_ATTR                       1: read_int
                        138     CALL                            0
                        146     CALL                            1
                        154     GET_ITER                        
                        156     FOR_ITER                        35 (to 228)
                        160     STORE_FAST                      5: _var_var_3
                        162     LOAD_FAST                       1: reader
                        164     LOAD_ATTR                       1: read_int
                        184     CALL                            0
                        192     STORE_FAST                      6: _var_var_4
                        194     LOAD_FAST                       4: _var_var_2
                        196     LOAD_ATTR                       5: append
                        216     LOAD_FAST                       6: _var_var_4
                        218     CALL                            1
                        226     POP_TOP                         
                        228     JUMP_BACKWARD                   37 (to 156)
                        230     END_FOR                         
                        232     JUMP_FORWARD                    2 (to 238)
                        234     LOAD_CONST                      0: None
                        236     STORE_FAST                      4: _var_var_2
                        238     LOAD_FAST                       1: reader
                        240     LOAD_ATTR                       7: tgread_object
                        260     CALL                            0
                        268     STORE_FAST                      7: _var_var_5
                        270     PUSH_NULL                       
                        272     LOAD_FAST                       0: cls
                        274     LOAD_FAST                       7: _var_var_5
                        276     LOAD_FAST                       4: _var_var_2
                        278     KW_NAMES                        5: ('peer', 'slots')
                        280     CALL                            2
                        288     NOP                             
                        290     NOP                             
                        292     NOP                             
                        294     JUMP_FORWARD                    20 (to 336)
                        296     CALL                            1
                        304     POP_TOP                         
                        306     RETURN_VALUE                    
                        308     PUSH_EXC_INFO                   
                        310     PUSH_NULL                       
                        312     LOAD_CONST                      6: '__pyarmor_exit_35552__'
                        314     NOP                             
                        316     LOAD_CONST                      3: b'<COAddr>\x05\x00\x00\x1a\x1a\x01\x00\x00\x00\x00\x00\x00\x00\x00\x00\x00\x00\x00\x00\x00'
                        318     CALL                            1
                        326     POP_TOP                         
                        328     RERAISE                         0
                        330     COPY                            3
                        332     POP_EXCEPT                      
                        334     RERAISE                         1
                        336     PUSH_NULL                       
                        338     LOAD_CONST                      6: '__pyarmor_exit_35552__'
                        340     LOAD_CONST                      3: b'<COAddr>\x05\x00\x00\x1a\x1a\x01\x00\x00\x00\x00\x00\x00\x00\x00\x00\x00\x00\x00\x00\x00'
                        342     BUILD_TUPLE                     1
                        344     CALL_FUNCTION_EX                0
                        346     POP_TOP                         
                        348     RETURN_VALUE                    
                    [Exception Table]
                        28 to 288 -> 308 [0] 
                        308 to 330 -> 330 [1] lasti
                '__pyarmor_exit_35537__'
                (
                    None
                )
            [Disassembly]
                0       NOP                             
                2       LOAD_NAME                       0: __name__
                4       STORE_NAME                      1: __module__
                6       LOAD_CONST                      0: 'ApplyBoostRequest'
                8       STORE_NAME                      2: __qualname__
                10      NOP                             
                12      PUSH_NULL                       
                14      LOAD_CONST                      2: '__pyarmor_enter_35536__'
                16      LOAD_CONST                      3: b'<COAddr>\x07\x00\x00"j\x00\x00\x00\x00\x00\x00\x00\x00\x00\x00\x00\x00\x00\x00\x00'
                18      BUILD_TUPLE                     1
                20      CALL_FUNCTION_EX                0
                22      POP_TOP                         
                24      RESUME                          0
                26      NOP                             
                28      NOP                             
                30      NOP                             
                32      NOP                             
                34      NOP                             
                36      LOAD_CONST                      4: 1803396934
                38      STORE_NAME                      4: CONSTRUCTOR_ID
                40      LOAD_CONST                      5: 0xAD3512DB
                42      STORE_NAME                      5: SUBCLASS_OF_ID
                44      LOAD_CONST                      16: (None,)
                46      LOAD_CONST                      7: 'peer'
                48      PUSH_NULL                       
                50      LOAD_CONST                      1: '__pyarmor_assert_35535__'
                52      LOAD_CONST                      8: 'TypeInputPeer'   # b'\x81\xd6\x01\x036\xd3\xb0\xc2\x0e\xee=\xc5i\xfe'
                54      CALL                            1
                62      LOAD_CONST                      9: 'slots'
                64      LOAD_NAME                       6: Optional
                66      LOAD_NAME                       7: List
                68      LOAD_NAME                       8: int
                70      BINARY_SUBSCR                   
                74      BINARY_SUBSCR                   
                78      BUILD_TUPLE                     4
                80      LOAD_CONST                      10: <CODE> __init__
                82      MAKE_FUNCTION                   5
                84      STORE_NAME                      9: __init__
                86      LOAD_CONST                      11: <CODE> resolve
                88      MAKE_FUNCTION                   0
                90      STORE_NAME                      10: resolve
                92      LOAD_CONST                      12: <CODE> to_dict
                94      MAKE_FUNCTION                   0
                96      STORE_NAME                      11: to_dict
                98      LOAD_CONST                      13: <CODE> _bytes
                100     MAKE_FUNCTION                   0
                102     STORE_NAME                      12: _bytes
                104     LOAD_NAME                       13: classmethod
                106     LOAD_CONST                      14: <CODE> from_reader
                108     MAKE_FUNCTION                   0
                110     CALL                            0
                118     STORE_NAME                      14: from_reader
                120     LOAD_CONST                      6: None
                122     NOP                             
                124     NOP                             
                126     NOP                             
                128     JUMP_FORWARD                    19 (to 168)
                136     POP_TOP                         
                138     RETURN_CONST                    6: None
                140     PUSH_EXC_INFO                   
                142     PUSH_NULL                       
                144     LOAD_CONST                      15: '__pyarmor_exit_35537__'
                146     NOP                             
                148     LOAD_CONST                      3: b'<COAddr>\x07\x00\x00"j\x00\x00\x00\x00\x00\x00\x00\x00\x00\x00\x00\x00\x00\x00\x00'
                150     CALL                            1
                158     POP_TOP                         
                160     RERAISE                         0
                162     COPY                            3
                164     POP_EXCEPT                      
                166     RERAISE                         1
                168     PUSH_NULL                       
                170     LOAD_CONST                      15: '__pyarmor_exit_35537__'
                172     LOAD_CONST                      3: b'<COAddr>\x07\x00\x00"j\x00\x00\x00\x00\x00\x00\x00\x00\x00\x00\x00\x00\x00\x00\x00'
                174     BUILD_TUPLE                     1
                176     CALL_FUNCTION_EX                0
                178     POP_TOP                         
                180     RETURN_VALUE                    
            [Exception Table]
                36 to 120 -> 140 [0] 
                140 to 162 -> 162 [1] lasti
        'ApplyBoostRequest'
        [Code]
            File Name: <frozen multithon.tl.functions.premium>
            Object Name: GetBoostsListRequest
            Qualified Name: GetBoostsListRequest
            Arg Count: 0
            Pos Only Arg Count: 0
            KW Only Arg Count: 0
            Stack Size: 10
            Flags: 0x20000000 (CO_PYARMOR_OBFUSCATED)
            [Names]
                '__name__'
                '__module__'
                '__qualname__'
                '__assert_armored__'
                'CONSTRUCTOR_ID'
                'SUBCLASS_OF_ID'
                'str'
                'int'
                'Optional'
                'bool'
                '__init__'
                'resolve'
                'to_dict'
                '_bytes'
                'classmethod'
                'from_reader'
            [Locals+Names]
            [Constants]
                'GetBoostsListRequest'
                '__pyarmor_assert_35553__'
                '__pyarmor_enter_35554__'
                b'<COAddr>\x05\x00\x00"l\x00\x00\x00\x00\x00\x00\x00\x00\x00\x00\x00\x00\x00\x00\x00'
                1626764896
                573941949
                None
                'peer'
                'TypeInputPeer'   # b'\x81\xd6\x01\x036\xd3\xb0\xc2\x0e\xee=\xc5i\xfe'
                'offset'
                'limit'
                'gifts'
                [Code]
                    File Name: <frozen multithon.tl.functions.premium>
                    Object Name: __init__
                    Qualified Name: GetBoostsListRequest.__init__
                    Arg Count: 5
                    Pos Only Arg Count: 0
                    KW Only Arg Count: 0
                    Stack Size: 5
                    Flags: 0x20000003 (CO_OPTIMIZED | CO_NEWLOCALS | CO_PYARMOR_OBFUSCATED)
                    [Names]
                        'peer'
                        'offset'
                        'limit'
                        'gifts'
                    [Locals+Names]
                        'self'
                        'peer'
                        'offset'
                        'limit'
                        'gifts'
                        '__assert_armored__'
                    [Constants]
                        '\n        :returns premium.BoostsList: Instance of BoostsList.\n        '
                        '__pyarmor_assert_35556__'
                        '__pyarmor_enter_35557__'
                        b'<COAddr>\x05\x00\x00\x1aN\x00\x00\x00\x00\x00\x00\x00\x00\x00\x00\x00\x00\x00\x00\x00'
                        '__pyarmor_exit_35558__'
                        None
                    [Disassembly]
                        0       NOP                             
                        2       NOP                             
                        4       PUSH_NULL                       
                        6       LOAD_CONST                      2: '__pyarmor_enter_35557__'
                        8       LOAD_CONST                      3: b'<COAddr>\x05\x00\x00\x1aN\x00\x00\x00\x00\x00\x00\x00\x00\x00\x00\x00\x00\x00\x00\x00'
                        10      BUILD_TUPLE                     1
                        12      CALL_FUNCTION_EX                0
                        14      POP_TOP                         
                        16      RESUME                          0
                        18      NOP                             
                        20      NOP                             
                        22      NOP                             
                        24      NOP                             
                        26      NOP                             
                        28      LOAD_FAST                       1: peer
                        30      LOAD_FAST                       0: self
                        32      STORE_ATTR                      0: peer
                        42      LOAD_FAST                       2: offset
                        44      LOAD_FAST                       0: self
                        46      STORE_ATTR                      1: offset
                        56      LOAD_FAST                       3: limit
                        58      LOAD_FAST                       0: self
                        60      STORE_ATTR                      2: limit
                        70      LOAD_FAST                       4: gifts
                        72      LOAD_FAST                       0: self
                        74      STORE_ATTR                      3: gifts
                        84      LOAD_CONST                      5: None
                        86      NOP                             
                        88      NOP                             
                        90      NOP                             
                        92      JUMP_FORWARD                    19 (to 132)
                        100     POP_TOP                         
                        102     RETURN_CONST                    5: None
                        104     PUSH_EXC_INFO                   
                        106     PUSH_NULL                       
                        108     LOAD_CONST                      4: '__pyarmor_exit_35558__'
                        110     NOP                             
                        112     LOAD_CONST                      3: b'<COAddr>\x05\x00\x00\x1aN\x00\x00\x00\x00\x00\x00\x00\x00\x00\x00\x00\x00\x00\x00\x00'
                        114     CALL                            1
                        122     POP_TOP                         
                        124     RERAISE                         0
                        126     COPY                            3
                        128     POP_EXCEPT                      
                        130     RERAISE                         1
                        132     PUSH_NULL                       
                        134     LOAD_CONST                      4: '__pyarmor_exit_35558__'
                        136     LOAD_CONST                      3: b'<COAddr>\x05\x00\x00\x1aN\x00\x00\x00\x00\x00\x00\x00\x00\x00\x00\x00\x00\x00\x00\x00'
                        138     BUILD_TUPLE                     1
                        140     CALL_FUNCTION_EX                0
                        142     POP_TOP                         
                        144     RETURN_VALUE                    
                    [Exception Table]
                        28 to 84 -> 104 [0] 
                        104 to 126 -> 126 [1] lasti
                [Code]
                    File Name: <frozen multithon.tl.functions.premium>
                    Object Name: resolve
                    Qualified Name: GetBoostsListRequest.resolve
                    Arg Count: 3
                    Pos Only Arg Count: 0
                    KW Only Arg Count: 0
                    Stack Size: 5
                    Flags: 0x20000083 (CO_OPTIMIZED | CO_NEWLOCALS | CO_COROUTINE | CO_PYARMOR_OBFUSCATED)
                    [Names]
                        'get_input_peer'
                        'get_input_entity'
                        'peer'
                    [Locals+Names]
                        'self'
                        'client'
                        'utils'
                        '__assert_armored__'
                    [Constants]
                        None
                        '__pyarmor_assert_35559__'
                        '__pyarmor_enter_35560__'
                        b'<COAddr>\x05\x00\x00\x1e\x88\x00\x00\x00\x00\x00\x00\x00\x00\x00\x00\x00\x00\x00\x00\x00'
                        '__pyarmor_exit_35561__'
                    [Disassembly]
                        0       RETURN_GENERATOR                
                        2       POP_TOP                         
                        4       NOP                             
                        6       NOP                             
                        8       PUSH_NULL                       
                        10      LOAD_CONST                      2: '__pyarmor_enter_35560__'
                        12      LOAD_CONST                      3: b'<COAddr>\x05\x00\x00\x1e\x88\x00\x00\x00\x00\x00\x00\x00\x00\x00\x00\x00\x00\x00\x00\x00'
                        14      BUILD_TUPLE                     1
                        16      CALL_FUNCTION_EX                0
                        18      POP_TOP                         
                        20      RESUME                          0
                        22      NOP                             
                        24      NOP                             
                        26      NOP                             
                        28      NOP                             
                        30      NOP                             
                        32      LOAD_FAST                       2: utils
                        34      LOAD_ATTR                       1: get_input_peer
                        54      LOAD_FAST                       1: client
                        56      LOAD_ATTR                       3: get_input_entity
                        76      LOAD_FAST                       0: self
                        78      LOAD_ATTR                       4: peer
                        98      CALL                            1
                        106     GET_AWAITABLE                   0
                        108     LOAD_CONST                      0: None
                        110     SEND                            3 (to 118)
                        114     YIELD_VALUE                     3
                        116     RESUME                          3
                        118     JUMP_BACKWARD_NO_INTERRUPT      5 (to 110)
                        120     END_SEND                        
                        122     CALL                            1
                        130     LOAD_FAST                       0: self
                        132     STORE_ATTR                      2: peer
                        142     LOAD_CONST                      0: None
                        144     NOP                             
                        146     NOP                             
                        148     NOP                             
                        150     JUMP_FORWARD                    23 (to 198)
                        158     POP_TOP                         
                        160     RETURN_CONST                    0: None
                        162     CLEANUP_THROW                   
                        164     JUMP_BACKWARD                   23 (to 120)
                        166     PUSH_EXC_INFO                   
                        168     PUSH_NULL                       
                        170     LOAD_CONST                      4: '__pyarmor_exit_35561__'
                        172     NOP                             
                        174     LOAD_CONST                      3: b'<COAddr>\x05\x00\x00\x1e\x88\x00\x00\x00\x00\x00\x00\x00\x00\x00\x00\x00\x00\x00\x00\x00'
                        176     CALL                            1
                        184     POP_TOP                         
                        186     RERAISE                         0
                        188     COPY                            3
                        190     POP_EXCEPT                      
                        192     RERAISE                         1
                        194     CALL_INTRINSIC_1                3 (INTRINSIC_STOPITERATION_ERROR)
                        196     RERAISE                         1
                        198     PUSH_NULL                       
                        200     LOAD_CONST                      4: '__pyarmor_exit_35561__'
                        202     LOAD_CONST                      3: b'<COAddr>\x05\x00\x00\x1e\x88\x00\x00\x00\x00\x00\x00\x00\x00\x00\x00\x00\x00\x00\x00\x00'
                        204     BUILD_TUPLE                     1
                        206     CALL_FUNCTION_EX                0
                        208     POP_TOP                         
                        210     RETURN_VALUE                    
                    [Exception Table]
                        4 to 30 -> 194 [0] lasti
                        32 to 114 -> 166 [0] 
                        114 to 116 -> 162 [4] 
                        116 to 142 -> 166 [0] 
                        142 to 162 -> 194 [0] lasti
                        162 to 164 -> 166 [0] 
                        166 to 188 -> 188 [1] lasti
                        188 to 194 -> 194 [0] lasti
                [Code]
                    File Name: <frozen multithon.tl.functions.premium>
                    Object Name: to_dict
                    Qualified Name: GetBoostsListRequest.to_dict
                    Arg Count: 1
                    Pos Only Arg Count: 0
                    KW Only Arg Count: 0
                    Stack Size: 6
                    Flags: 0x20000003 (CO_OPTIMIZED | CO_NEWLOCALS | CO_PYARMOR_OBFUSCATED)
                    [Names]
                        'isinstance'
                        'peer'
                        'TLObject'
                        'to_dict'
                        'offset'
                        'limit'
                        'gifts'
                    [Locals+Names]
                        'self'
                        '__assert_armored__'
                    [Constants]
                        None
                        '__pyarmor_assert_35562__'
                        '__pyarmor_enter_35563__'
                        b'<COAddr>\x05\x00\x00\x1a\xe8\x00\x00\x00\x00\x00\x00\x00\x00\x00\x00\x00\x00\x00\x00\x00'
                        'GetBoostsListRequest'   # b'\x81\xc5\x1d\x07\x11\xf5\xb1\xc1\x0f\xe9!\xc9\x7f\xf8\xca\x80\x1eH\xbe\xb4\xbe'
                        (
                            '_'
                            'peer'
                            'offset'
                            'limit'
                            'gifts'
                        )
                        '__pyarmor_exit_35564__'
                    [Disassembly]
                        0       NOP                             
                        2       NOP                             
                        4       PUSH_NULL                       
                        6       LOAD_CONST                      2: '__pyarmor_enter_35563__'
                        8       LOAD_CONST                      3: b'<COAddr>\x05\x00\x00\x1a\xe8\x00\x00\x00\x00\x00\x00\x00\x00\x00\x00\x00\x00\x00\x00\x00'
                        10      BUILD_TUPLE                     1
                        12      CALL_FUNCTION_EX                0
                        14      POP_TOP                         
                        16      RESUME                          0
                        18      NOP                             
                        20      NOP                             
                        22      NOP                             
                        24      NOP                             
                        26      NOP                             
                        28      PUSH_NULL                       
                        30      LOAD_CONST                      1: '__pyarmor_assert_35562__'
                        32      LOAD_CONST                      4: 'GetBoostsListRequest'   # b'\x81\xc5\x1d\x07\x11\xf5\xb1\xc1\x0f\xe9!\xc9\x7f\xf8\xca\x80\x1eH\xbe\xb4\xbe'
                        34      CALL                            1
                        42      LOAD_GLOBAL                     1: NULL + isinstance
                        52      LOAD_FAST                       0: self
                        54      LOAD_ATTR                       2: peer
                        74      LOAD_GLOBAL                     4: TLObject
                        84      CALL                            2
                        92      POP_JUMP_IF_FALSE               26 (to 146)
                        94      LOAD_FAST                       0: self
                        96      LOAD_ATTR                       2: peer
                        116     LOAD_ATTR                       7: to_dict
                        136     CALL                            0
                        144     JUMP_FORWARD                    11 (to 168)
                        146     LOAD_FAST                       0: self
                        148     LOAD_ATTR                       2: peer
                        168     LOAD_FAST                       0: self
                        170     LOAD_ATTR                       8: offset
                        190     LOAD_FAST                       0: self
                        192     LOAD_ATTR                       10: limit
                        212     LOAD_FAST                       0: self
                        214     LOAD_ATTR                       12: gifts
                        234     LOAD_CONST                      5: ('_', 'peer', 'offset', 'limit', 'gifts')
                        236     BUILD_CONST_KEY_MAP             5
                        238     NOP                             
                        240     NOP                             
                        242     NOP                             
                        244     JUMP_FORWARD                    20 (to 286)
                        246     CALL                            1
                        254     POP_TOP                         
                        256     RETURN_VALUE                    
                        258     PUSH_EXC_INFO                   
                        260     PUSH_NULL                       
                        262     LOAD_CONST                      6: '__pyarmor_exit_35564__'
                        264     NOP                             
                        266     LOAD_CONST                      3: b'<COAddr>\x05\x00\x00\x1a\xe8\x00\x00\x00\x00\x00\x00\x00\x00\x00\x00\x00\x00\x00\x00\x00'
                        268     CALL                            1
                        276     POP_TOP                         
                        278     RERAISE                         0
                        280     COPY                            3
                        282     POP_EXCEPT                      
                        284     RERAISE                         1
                        286     PUSH_NULL                       
                        288     LOAD_CONST                      6: '__pyarmor_exit_35564__'
                        290     LOAD_CONST                      3: b'<COAddr>\x05\x00\x00\x1a\xe8\x00\x00\x00\x00\x00\x00\x00\x00\x00\x00\x00\x00\x00\x00\x00'
                        292     BUILD_TUPLE                     1
                        294     CALL_FUNCTION_EX                0
                        296     POP_TOP                         
                        298     RETURN_VALUE                    
                    [Exception Table]
                        28 to 238 -> 258 [0] 
                        258 to 280 -> 280 [1] lasti
                [Code]
                    File Name: <frozen multithon.tl.functions.premium>
                    Object Name: _bytes
                    Qualified Name: GetBoostsListRequest._bytes
                    Arg Count: 1
                    Pos Only Arg Count: 0
                    KW Only Arg Count: 0
                    Stack Size: 10
                    Flags: 0x20000003 (CO_OPTIMIZED | CO_NEWLOCALS | CO_PYARMOR_OBFUSCATED)
                    [Names]
                        'join'
                        'struct'
                        'pack'
                        'gifts'
                        'peer'
                        '_bytes'
                        'serialize_bytes'
                        'offset'
                        'limit'
                    [Locals+Names]
                        'self'
                        '__assert_armored__'
                    [Constants]
                        None
                        '__pyarmor_assert_35565__'
                        '__pyarmor_enter_35566__'
                        b'<COAddr>\x07\x00\x00\x1a>\x01\x00\x00\x00\x00\x00\x00\x00\x00\x00\x00\x00\x00\x00\x00'
                        b''
                        b'`v\xf6`'
                        '<I'
                        False
                        0
                        1
                        '<i'
                        '__pyarmor_exit_35567__'
                    [Disassembly]
                        0       NOP                             
                        2       NOP                             
                        4       PUSH_NULL                       
                        6       LOAD_CONST                      2: '__pyarmor_enter_35566__'
                        8       LOAD_CONST                      3: b'<COAddr>\x07\x00\x00\x1a>\x01\x00\x00\x00\x00\x00\x00\x00\x00\x00\x00\x00\x00\x00\x00'
                        10      BUILD_TUPLE                     1
                        12      CALL_FUNCTION_EX                0
                        14      POP_TOP                         
                        16      RESUME                          0
                        18      NOP                             
                        20      NOP                             
                        22      NOP                             
                        24      NOP                             
                        26      NOP                             
                        28      LOAD_CONST                      4: b''
                        30      LOAD_ATTR                       1: join
                        50      LOAD_CONST                      5: b'`v\xf6`'
                        52      LOAD_GLOBAL                     3: NULL + struct
                        62      LOAD_ATTR                       4: pack
                        82      LOAD_CONST                      6: '<I'
                        84      LOAD_FAST                       0: self
                        86      LOAD_ATTR                       6: gifts
                        106     POP_JUMP_IF_NONE                14 (to 136)
                        108     LOAD_FAST                       0: self
                        110     LOAD_ATTR                       6: gifts
                        130     LOAD_CONST                      7: False
                        132     IS_OP                           0 (is)
                        134     POP_JUMP_IF_FALSE               2 (to 140)
                        136     LOAD_CONST                      8: 0
                        138     JUMP_FORWARD                    1 (to 142)
                        140     LOAD_CONST                      9: 1
                        142     CALL                            2
                        150     LOAD_FAST                       0: self
                        152     LOAD_ATTR                       8: peer
                        172     LOAD_ATTR                       11: _bytes
                        192     CALL                            0
                        200     LOAD_FAST                       0: self
                        202     LOAD_ATTR                       13: serialize_bytes
                        222     LOAD_FAST                       0: self
                        224     LOAD_ATTR                       14: offset
                        244     CALL                            1
                        252     LOAD_GLOBAL                     3: NULL + struct
                        262     LOAD_ATTR                       4: pack
                        282     LOAD_CONST                      10: '<i'
                        284     LOAD_FAST                       0: self
                        286     LOAD_ATTR                       16: limit
                        306     CALL                            2
                        314     BUILD_TUPLE                     5
                        316     CALL                            1
                        324     NOP                             
                        326     NOP                             
                        328     NOP                             
                        330     JUMP_FORWARD                    20 (to 372)
                        332     CALL                            1
                        340     POP_TOP                         
                        342     RETURN_VALUE                    
                        344     PUSH_EXC_INFO                   
                        346     PUSH_NULL                       
                        348     LOAD_CONST                      11: '__pyarmor_exit_35567__'
                        350     NOP                             
                        352     LOAD_CONST                      3: b'<COAddr>\x07\x00\x00\x1a>\x01\x00\x00\x00\x00\x00\x00\x00\x00\x00\x00\x00\x00\x00\x00'
                        354     CALL                            1
                        362     POP_TOP                         
                        364     RERAISE                         0
                        366     COPY                            3
                        368     POP_EXCEPT                      
                        370     RERAISE                         1
                        372     PUSH_NULL                       
                        374     LOAD_CONST                      11: '__pyarmor_exit_35567__'
                        376     LOAD_CONST                      3: b'<COAddr>\x07\x00\x00\x1a>\x01\x00\x00\x00\x00\x00\x00\x00\x00\x00\x00\x00\x00\x00\x00'
                        378     BUILD_TUPLE                     1
                        380     CALL_FUNCTION_EX                0
                        382     POP_TOP                         
                        384     RETURN_VALUE                    
                    [Exception Table]
                        28 to 324 -> 344 [0] 
                        344 to 366 -> 366 [1] lasti
                [Code]
                    File Name: <frozen multithon.tl.functions.premium>
                    Object Name: from_reader
                    Qualified Name: GetBoostsListRequest.from_reader
                    Arg Count: 2
                    Pos Only Arg Count: 0
                    KW Only Arg Count: 0
                    Stack Size: 6
                    Flags: 0x20000003 (CO_OPTIMIZED | CO_NEWLOCALS | CO_PYARMOR_OBFUSCATED)
                    [Names]
                        'read_int'
                        'bool'
                        'tgread_object'
                        'tgread_string'
                    [Locals+Names]
                        'cls'
                        'reader'
                        '__assert_armored__'
                        '_var_var_1'
                        '_var_var_6'
                        '_var_var_5'
                        '_var_var_7'
                        '_var_var_8'
                    [Constants]
                        None
                        '__pyarmor_assert_35568__'
                        '__pyarmor_enter_35569__'
                        b'<COAddr>\x05\x00\x00\x1a\xc8\x00\x00\x00\x00\x00\x00\x00\x00\x00\x00\x00\x00\x00\x00\x00'
                        1
                        (
                            'peer'
                            'offset'
                            'limit'
                            'gifts'
                        )
                        '__pyarmor_exit_35570__'
                    [Disassembly]
                        0       NOP                             
                        2       NOP                             
                        4       PUSH_NULL                       
                        6       LOAD_CONST                      2: '__pyarmor_enter_35569__'
                        8       LOAD_CONST                      3: b'<COAddr>\x05\x00\x00\x1a\xc8\x00\x00\x00\x00\x00\x00\x00\x00\x00\x00\x00\x00\x00\x00\x00'
                        10      BUILD_TUPLE                     1
                        12      CALL_FUNCTION_EX                0
                        14      POP_TOP                         
                        16      RESUME                          0
                        18      NOP                             
                        20      NOP                             
                        22      NOP                             
                        24      NOP                             
                        26      NOP                             
                        28      LOAD_FAST                       1: reader
                        30      LOAD_ATTR                       1: read_int
                        50      CALL                            0
                        58      STORE_FAST                      3: _var_var_1
                        60      LOAD_GLOBAL                     3: NULL + bool
                        70      LOAD_FAST                       3: _var_var_1
                        72      LOAD_CONST                      4: 1
                        74      BINARY_OP                       1 (&)
                        78      CALL                            1
                        86      STORE_FAST                      4: _var_var_6
                        88      LOAD_FAST                       1: reader
                        90      LOAD_ATTR                       5: tgread_object
                        110     CALL                            0
                        118     STORE_FAST                      5: _var_var_5
                        120     LOAD_FAST                       1: reader
                        122     LOAD_ATTR                       7: tgread_string
                        142     CALL                            0
                        150     STORE_FAST                      6: _var_var_7
                        152     LOAD_FAST                       1: reader
                        154     LOAD_ATTR                       1: read_int
                        174     CALL                            0
                        182     STORE_FAST                      7: _var_var_8
                        184     PUSH_NULL                       
                        186     LOAD_FAST                       0: cls
                        188     LOAD_FAST                       5: _var_var_5
                        190     LOAD_FAST                       6: _var_var_7
                        192     LOAD_FAST                       7: _var_var_8
                        194     LOAD_FAST                       4: _var_var_6
                        196     KW_NAMES                        5: ('peer', 'offset', 'limit', 'gifts')
                        198     CALL                            4
                        206     NOP                             
                        208     NOP                             
                        210     NOP                             
                        212     JUMP_FORWARD                    20 (to 254)
                        214     CALL                            1
                        222     POP_TOP                         
                        224     RETURN_VALUE                    
                        226     PUSH_EXC_INFO                   
                        228     PUSH_NULL                       
                        230     LOAD_CONST                      6: '__pyarmor_exit_35570__'
                        232     NOP                             
                        234     LOAD_CONST                      3: b'<COAddr>\x05\x00\x00\x1a\xc8\x00\x00\x00\x00\x00\x00\x00\x00\x00\x00\x00\x00\x00\x00\x00'
                        236     CALL                            1
                        244     POP_TOP                         
                        246     RERAISE                         0
                        248     COPY                            3
                        250     POP_EXCEPT                      
                        252     RERAISE                         1
                        254     PUSH_NULL                       
                        256     LOAD_CONST                      6: '__pyarmor_exit_35570__'
                        258     LOAD_CONST                      3: b'<COAddr>\x05\x00\x00\x1a\xc8\x00\x00\x00\x00\x00\x00\x00\x00\x00\x00\x00\x00\x00\x00\x00'
                        260     BUILD_TUPLE                     1
                        262     CALL_FUNCTION_EX                0
                        264     POP_TOP                         
                        266     RETURN_VALUE                    
                    [Exception Table]
                        28 to 206 -> 226 [0] 
                        226 to 248 -> 248 [1] lasti
                '__pyarmor_exit_35555__'
                (
                    None
                )
            [Disassembly]
                0       NOP                             
                2       LOAD_NAME                       0: __name__
                4       STORE_NAME                      1: __module__
                6       LOAD_CONST                      0: 'GetBoostsListRequest'
                8       STORE_NAME                      2: __qualname__
                10      NOP                             
                12      PUSH_NULL                       
                14      LOAD_CONST                      2: '__pyarmor_enter_35554__'
                16      LOAD_CONST                      3: b'<COAddr>\x05\x00\x00"l\x00\x00\x00\x00\x00\x00\x00\x00\x00\x00\x00\x00\x00\x00\x00'
                18      BUILD_TUPLE                     1
                20      CALL_FUNCTION_EX                0
                22      POP_TOP                         
                24      RESUME                          0
                26      NOP                             
                28      NOP                             
                30      NOP                             
                32      NOP                             
                34      NOP                             
                36      LOAD_CONST                      4: 1626764896
                38      STORE_NAME                      4: CONSTRUCTOR_ID
                40      LOAD_CONST                      5: 573941949
                42      STORE_NAME                      5: SUBCLASS_OF_ID
                44      LOAD_CONST                      18: (None,)
                46      LOAD_CONST                      7: 'peer'
                48      PUSH_NULL                       
                50      LOAD_CONST                      1: '__pyarmor_assert_35553__'
                52      LOAD_CONST                      8: 'TypeInputPeer'   # b'\x81\xd6\x01\x036\xd3\xb0\xc2\x0e\xee=\xc5i\xfe'
                54      CALL                            1
                62      LOAD_CONST                      9: 'offset'
                64      LOAD_NAME                       6: str
                66      LOAD_CONST                      10: 'limit'
                68      LOAD_NAME                       7: int
                70      LOAD_CONST                      11: 'gifts'
                72      LOAD_NAME                       8: Optional
                74      LOAD_NAME                       9: bool
                76      BINARY_SUBSCR                   
                80      BUILD_TUPLE                     8
                82      LOAD_CONST                      12: <CODE> __init__
                84      MAKE_FUNCTION                   5
                86      STORE_NAME                      10: __init__
                88      LOAD_CONST                      13: <CODE> resolve
                90      MAKE_FUNCTION                   0
                92      STORE_NAME                      11: resolve
                94      LOAD_CONST                      14: <CODE> to_dict
                96      MAKE_FUNCTION                   0
                98      STORE_NAME                      12: to_dict
                100     LOAD_CONST                      15: <CODE> _bytes
                102     MAKE_FUNCTION                   0
                104     STORE_NAME                      13: _bytes
                106     LOAD_NAME                       14: classmethod
                108     LOAD_CONST                      16: <CODE> from_reader
                110     MAKE_FUNCTION                   0
                112     CALL                            0
                120     STORE_NAME                      15: from_reader
                122     LOAD_CONST                      6: None
                124     NOP                             
                126     NOP                             
                128     NOP                             
                130     JUMP_FORWARD                    19 (to 170)
                138     POP_TOP                         
                140     RETURN_CONST                    6: None
                142     PUSH_EXC_INFO                   
                144     PUSH_NULL                       
                146     LOAD_CONST                      17: '__pyarmor_exit_35555__'
                148     NOP                             
                150     LOAD_CONST                      3: b'<COAddr>\x05\x00\x00"l\x00\x00\x00\x00\x00\x00\x00\x00\x00\x00\x00\x00\x00\x00\x00'
                152     CALL                            1
                160     POP_TOP                         
                162     RERAISE                         0
                164     COPY                            3
                166     POP_EXCEPT                      
                168     RERAISE                         1
                170     PUSH_NULL                       
                172     LOAD_CONST                      17: '__pyarmor_exit_35555__'
                174     LOAD_CONST                      3: b'<COAddr>\x05\x00\x00"l\x00\x00\x00\x00\x00\x00\x00\x00\x00\x00\x00\x00\x00\x00\x00'
                176     BUILD_TUPLE                     1
                178     CALL_FUNCTION_EX                0
                180     POP_TOP                         
                182     RETURN_VALUE                    
            [Exception Table]
                36 to 122 -> 142 [0] 
                142 to 164 -> 164 [1] lasti
        'GetBoostsListRequest'
        [Code]
            File Name: <frozen multithon.tl.functions.premium>
            Object Name: GetBoostsStatusRequest
            Qualified Name: GetBoostsStatusRequest
            Arg Count: 0
            Pos Only Arg Count: 0
            KW Only Arg Count: 0
            Stack Size: 5
            Flags: 0x20000000 (CO_PYARMOR_OBFUSCATED)
            [Names]
                '__name__'
                '__module__'
                '__qualname__'
                '__assert_armored__'
                'CONSTRUCTOR_ID'
                'SUBCLASS_OF_ID'
                '__init__'
                'resolve'
                'to_dict'
                '_bytes'
                'classmethod'
                'from_reader'
            [Locals+Names]
            [Constants]
                'GetBoostsStatusRequest'
                '__pyarmor_assert_35571__'
                '__pyarmor_enter_35572__'
                b'<COAddr>\x05\x00\x00"X\x00\x00\x00\x00\x00\x00\x00\x00\x00\x00\x00\x00\x00\x00\x00'
                70197089
                0xC31B1AB9
                'peer'
                'TypeInputPeer'   # b'\x81\xd6\x01\x036\xd3\xb0\xc2\x0e\xee=\xc5i\xfe'
                [Code]
                    File Name: <frozen multithon.tl.functions.premium>
                    Object Name: __init__
                    Qualified Name: GetBoostsStatusRequest.__init__
                    Arg Count: 2
                    Pos Only Arg Count: 0
                    KW Only Arg Count: 0
                    Stack Size: 5
                    Flags: 0x20000003 (CO_OPTIMIZED | CO_NEWLOCALS | CO_PYARMOR_OBFUSCATED)
                    [Names]
                        'peer'
                    [Locals+Names]
                        'self'
                        'peer'
                        '__assert_armored__'
                    [Constants]
                        '\n        :returns premium.BoostsStatus: Instance of BoostsStatus.\n        '
                        '__pyarmor_assert_35574__'
                        '__pyarmor_enter_35575__'
                        b'<COAddr>\x05\x00\x00\x1a$\x00\x00\x00\x00\x00\x00\x00\x00\x00\x00\x00\x00\x00\x00\x00'
                        '__pyarmor_exit_35576__'
                        None
                    [Disassembly]
                        0       NOP                             
                        2       NOP                             
                        4       PUSH_NULL                       
                        6       LOAD_CONST                      2: '__pyarmor_enter_35575__'
                        8       LOAD_CONST                      3: b'<COAddr>\x05\x00\x00\x1a$\x00\x00\x00\x00\x00\x00\x00\x00\x00\x00\x00\x00\x00\x00\x00'
                        10      BUILD_TUPLE                     1
                        12      CALL_FUNCTION_EX                0
                        14      POP_TOP                         
                        16      RESUME                          0
                        18      NOP                             
                        20      NOP                             
                        22      NOP                             
                        24      NOP                             
                        26      NOP                             
                        28      LOAD_FAST                       1: peer
                        30      LOAD_FAST                       0: self
                        32      STORE_ATTR                      0: peer
                        42      LOAD_CONST                      5: None
                        44      NOP                             
                        46      NOP                             
                        48      NOP                             
                        50      JUMP_FORWARD                    19 (to 90)
                        58      POP_TOP                         
                        60      RETURN_CONST                    5: None
                        62      PUSH_EXC_INFO                   
                        64      PUSH_NULL                       
                        66      LOAD_CONST                      4: '__pyarmor_exit_35576__'
                        68      NOP                             
                        70      LOAD_CONST                      3: b'<COAddr>\x05\x00\x00\x1a$\x00\x00\x00\x00\x00\x00\x00\x00\x00\x00\x00\x00\x00\x00\x00'
                        72      CALL                            1
                        80      POP_TOP                         
                        82      RERAISE                         0
                        84      COPY                            3
                        86      POP_EXCEPT                      
                        88      RERAISE                         1
                        90      PUSH_NULL                       
                        92      LOAD_CONST                      4: '__pyarmor_exit_35576__'
                        94      LOAD_CONST                      3: b'<COAddr>\x05\x00\x00\x1a$\x00\x00\x00\x00\x00\x00\x00\x00\x00\x00\x00\x00\x00\x00\x00'
                        96      BUILD_TUPLE                     1
                        98      CALL_FUNCTION_EX                0
                        100     POP_TOP                         
                        102     RETURN_VALUE                    
                    [Exception Table]
                        28 to 42 -> 62 [0] 
                        62 to 84 -> 84 [1] lasti
                [Code]
                    File Name: <frozen multithon.tl.functions.premium>
                    Object Name: resolve
                    Qualified Name: GetBoostsStatusRequest.resolve
                    Arg Count: 3
                    Pos Only Arg Count: 0
                    KW Only Arg Count: 0
                    Stack Size: 5
                    Flags: 0x20000083 (CO_OPTIMIZED | CO_NEWLOCALS | CO_COROUTINE | CO_PYARMOR_OBFUSCATED)
                    [Names]
                        'get_input_peer'
                        'get_input_entity'
                        'peer'
                    [Locals+Names]
                        'self'
                        'client'
                        'utils'
                        '__assert_armored__'
                    [Constants]
                        None
                        '__pyarmor_assert_35577__'
                        '__pyarmor_enter_35578__'
                        b'<COAddr>\x05\x00\x00\x1e\x88\x00\x00\x00\x00\x00\x00\x00\x00\x00\x00\x00\x00\x00\x00\x00'
                        '__pyarmor_exit_35579__'
                    [Disassembly]
                        0       RETURN_GENERATOR                
                        2       POP_TOP                         
                        4       NOP                             
                        6       NOP                             
                        8       PUSH_NULL                       
                        10      LOAD_CONST                      2: '__pyarmor_enter_35578__'
                        12      LOAD_CONST                      3: b'<COAddr>\x05\x00\x00\x1e\x88\x00\x00\x00\x00\x00\x00\x00\x00\x00\x00\x00\x00\x00\x00\x00'
                        14      BUILD_TUPLE                     1
                        16      CALL_FUNCTION_EX                0
                        18      POP_TOP                         
                        20      RESUME                          0
                        22      NOP                             
                        24      NOP                             
                        26      NOP                             
                        28      NOP                             
                        30      NOP                             
                        32      LOAD_FAST                       2: utils
                        34      LOAD_ATTR                       1: get_input_peer
                        54      LOAD_FAST                       1: client
                        56      LOAD_ATTR                       3: get_input_entity
                        76      LOAD_FAST                       0: self
                        78      LOAD_ATTR                       4: peer
                        98      CALL                            1
                        106     GET_AWAITABLE                   0
                        108     LOAD_CONST                      0: None
                        110     SEND                            3 (to 118)
                        114     YIELD_VALUE                     3
                        116     RESUME                          3
                        118     JUMP_BACKWARD_NO_INTERRUPT      5 (to 110)
                        120     END_SEND                        
                        122     CALL                            1
                        130     LOAD_FAST                       0: self
                        132     STORE_ATTR                      2: peer
                        142     LOAD_CONST                      0: None
                        144     NOP                             
                        146     NOP                             
                        148     NOP                             
                        150     JUMP_FORWARD                    23 (to 198)
                        158     POP_TOP                         
                        160     RETURN_CONST                    0: None
                        162     CLEANUP_THROW                   
                        164     JUMP_BACKWARD                   23 (to 120)
                        166     PUSH_EXC_INFO                   
                        168     PUSH_NULL                       
                        170     LOAD_CONST                      4: '__pyarmor_exit_35579__'
                        172     NOP                             
                        174     LOAD_CONST                      3: b'<COAddr>\x05\x00\x00\x1e\x88\x00\x00\x00\x00\x00\x00\x00\x00\x00\x00\x00\x00\x00\x00\x00'
                        176     CALL                            1
                        184     POP_TOP                         
                        186     RERAISE                         0
                        188     COPY                            3
                        190     POP_EXCEPT                      
                        192     RERAISE                         1
                        194     CALL_INTRINSIC_1                3 (INTRINSIC_STOPITERATION_ERROR)
                        196     RERAISE                         1
                        198     PUSH_NULL                       
                        200     LOAD_CONST                      4: '__pyarmor_exit_35579__'
                        202     LOAD_CONST                      3: b'<COAddr>\x05\x00\x00\x1e\x88\x00\x00\x00\x00\x00\x00\x00\x00\x00\x00\x00\x00\x00\x00\x00'
                        204     BUILD_TUPLE                     1
                        206     CALL_FUNCTION_EX                0
                        208     POP_TOP                         
                        210     RETURN_VALUE                    
                    [Exception Table]
                        4 to 30 -> 194 [0] lasti
                        32 to 114 -> 166 [0] 
                        114 to 116 -> 162 [4] 
                        116 to 142 -> 166 [0] 
                        142 to 162 -> 194 [0] lasti
                        162 to 164 -> 166 [0] 
                        166 to 188 -> 188 [1] lasti
                        188 to 194 -> 194 [0] lasti
                [Code]
                    File Name: <frozen multithon.tl.functions.premium>
                    Object Name: to_dict
                    Qualified Name: GetBoostsStatusRequest.to_dict
                    Arg Count: 1
                    Pos Only Arg Count: 0
                    KW Only Arg Count: 0
                    Stack Size: 5
                    Flags: 0x20000003 (CO_OPTIMIZED | CO_NEWLOCALS | CO_PYARMOR_OBFUSCATED)
                    [Names]
                        'isinstance'
                        'peer'
                        'TLObject'
                        'to_dict'
                    [Locals+Names]
                        'self'
                        '__assert_armored__'
                    [Constants]
                        None
                        '__pyarmor_assert_35580__'
                        '__pyarmor_enter_35581__'
                        b'<COAddr>\x07\x00\x00\x1a\xa6\x00\x00\x00\x00\x00\x00\x00\x00\x00\x00\x00\x00\x00\x00\x00'
                        'GetBoostsStatusRequest'   # b'\x81\xc5\x1d\x07\x11\xf5\xb1\xc1\x0f\xe9>\xd4m\xf8\xed\x96=X\xaa\xb2\xaf\xd8Z'
                        (
                            '_'
                            'peer'
                        )
                        '__pyarmor_exit_35582__'
                    [Disassembly]
                        0       NOP                             
                        2       NOP                             
                        4       PUSH_NULL                       
                        6       LOAD_CONST                      2: '__pyarmor_enter_35581__'
                        8       LOAD_CONST                      3: b'<COAddr>\x07\x00\x00\x1a\xa6\x00\x00\x00\x00\x00\x00\x00\x00\x00\x00\x00\x00\x00\x00\x00'
                        10      BUILD_TUPLE                     1
                        12      CALL_FUNCTION_EX                0
                        14      POP_TOP                         
                        16      RESUME                          0
                        18      NOP                             
                        20      NOP                             
                        22      NOP                             
                        24      NOP                             
                        26      NOP                             
                        28      PUSH_NULL                       
                        30      LOAD_CONST                      1: '__pyarmor_assert_35580__'
                        32      LOAD_CONST                      4: 'GetBoostsStatusRequest'   # b'\x81\xc5\x1d\x07\x11\xf5\xb1\xc1\x0f\xe9>\xd4m\xf8\xed\x96=X\xaa\xb2\xaf\xd8Z'
                        34      CALL                            1
                        42      LOAD_GLOBAL                     1: NULL + isinstance
                        52      LOAD_FAST                       0: self
                        54      LOAD_ATTR                       2: peer
                        74      LOAD_GLOBAL                     4: TLObject
                        84      CALL                            2
                        92      POP_JUMP_IF_FALSE               26 (to 146)
                        94      LOAD_FAST                       0: self
                        96      LOAD_ATTR                       2: peer
                        116     LOAD_ATTR                       7: to_dict
                        136     CALL                            0
                        144     JUMP_FORWARD                    11 (to 168)
                        146     LOAD_FAST                       0: self
                        148     LOAD_ATTR                       2: peer
                        168     LOAD_CONST                      5: ('_', 'peer')
                        170     BUILD_CONST_KEY_MAP             2
                        172     NOP                             
                        174     NOP                             
                        176     NOP                             
                        178     JUMP_FORWARD                    20 (to 220)
                        180     CALL                            1
                        188     POP_TOP                         
                        190     RETURN_VALUE                    
                        192     PUSH_EXC_INFO                   
                        194     PUSH_NULL                       
                        196     LOAD_CONST                      6: '__pyarmor_exit_35582__'
                        198     NOP                             
                        200     LOAD_CONST                      3: b'<COAddr>\x07\x00\x00\x1a\xa6\x00\x00\x00\x00\x00\x00\x00\x00\x00\x00\x00\x00\x00\x00\x00'
                        202     CALL                            1
                        210     POP_TOP                         
                        212     RERAISE                         0
                        214     COPY                            3
                        216     POP_EXCEPT                      
                        218     RERAISE                         1
                        220     PUSH_NULL                       
                        222     LOAD_CONST                      6: '__pyarmor_exit_35582__'
                        224     LOAD_CONST                      3: b'<COAddr>\x07\x00\x00\x1a\xa6\x00\x00\x00\x00\x00\x00\x00\x00\x00\x00\x00\x00\x00\x00\x00'
                        226     BUILD_TUPLE                     1
                        228     CALL_FUNCTION_EX                0
                        230     POP_TOP                         
                        232     RETURN_VALUE                    
                    [Exception Table]
                        28 to 172 -> 192 [0] 
                        192 to 214 -> 214 [1] lasti
                [Code]
                    File Name: <frozen multithon.tl.functions.premium>
                    Object Name: _bytes
                    Qualified Name: GetBoostsStatusRequest._bytes
                    Arg Count: 1
                    Pos Only Arg Count: 0
                    KW Only Arg Count: 0
                    Stack Size: 5
                    Flags: 0x20000003 (CO_OPTIMIZED | CO_NEWLOCALS | CO_PYARMOR_OBFUSCATED)
                    [Names]
                        'join'
                        'peer'
                        '_bytes'
                    [Locals+Names]
                        'self'
                        '__assert_armored__'
                    [Constants]
                        None
                        '__pyarmor_assert_35583__'
                        '__pyarmor_enter_35584__'
                        b'<COAddr>\x05\x00\x00\x1aj\x00\x00\x00\x00\x00\x00\x00\x00\x00\x00\x00\x00\x00\x00\x00'
                        b''
                        b'a\x1f/\x04'
                        '__pyarmor_exit_35585__'
                    [Disassembly]
                        0       NOP                             
                        2       NOP                             
                        4       PUSH_NULL                       
                        6       LOAD_CONST                      2: '__pyarmor_enter_35584__'
                        8       LOAD_CONST                      3: b'<COAddr>\x05\x00\x00\x1aj\x00\x00\x00\x00\x00\x00\x00\x00\x00\x00\x00\x00\x00\x00\x00'
                        10      BUILD_TUPLE                     1
                        12      CALL_FUNCTION_EX                0
                        14      POP_TOP                         
                        16      RESUME                          0
                        18      NOP                             
                        20      NOP                             
                        22      NOP                             
                        24      NOP                             
                        26      NOP                             
                        28      LOAD_CONST                      4: b''
                        30      LOAD_ATTR                       1: join
                        50      LOAD_CONST                      5: b'a\x1f/\x04'
                        52      LOAD_FAST                       0: self
                        54      LOAD_ATTR                       2: peer
                        74      LOAD_ATTR                       5: _bytes
                        94      CALL                            0
                        102     BUILD_TUPLE                     2
                        104     CALL                            1
                        112     NOP                             
                        114     NOP                             
                        116     NOP                             
                        118     JUMP_FORWARD                    20 (to 160)
                        120     CALL                            1
                        128     POP_TOP                         
                        130     RETURN_VALUE                    
                        132     PUSH_EXC_INFO                   
                        134     PUSH_NULL                       
                        136     LOAD_CONST                      6: '__pyarmor_exit_35585__'
                        138     NOP                             
                        140     LOAD_CONST                      3: b'<COAddr>\x05\x00\x00\x1aj\x00\x00\x00\x00\x00\x00\x00\x00\x00\x00\x00\x00\x00\x00\x00'
                        142     CALL                            1
                        150     POP_TOP                         
                        152     RERAISE                         0
                        154     COPY                            3
                        156     POP_EXCEPT                      
                        158     RERAISE                         1
                        160     PUSH_NULL                       
                        162     LOAD_CONST                      6: '__pyarmor_exit_35585__'
                        164     LOAD_CONST                      3: b'<COAddr>\x05\x00\x00\x1aj\x00\x00\x00\x00\x00\x00\x00\x00\x00\x00\x00\x00\x00\x00\x00'
                        166     BUILD_TUPLE                     1
                        168     CALL_FUNCTION_EX                0
                        170     POP_TOP                         
                        172     RETURN_VALUE                    
                    [Exception Table]
                        28 to 112 -> 132 [0] 
                        132 to 154 -> 154 [1] lasti
                [Code]
                    File Name: <frozen multithon.tl.functions.premium>
                    Object Name: from_reader
                    Qualified Name: GetBoostsStatusRequest.from_reader
                    Arg Count: 2
                    Pos Only Arg Count: 0
                    KW Only Arg Count: 0
                    Stack Size: 5
                    Flags: 0x20000003 (CO_OPTIMIZED | CO_NEWLOCALS | CO_PYARMOR_OBFUSCATED)
                    [Names]
                        'tgread_object'
                    [Locals+Names]
                        'cls'
                        'reader'
                        '__assert_armored__'
                        '_var_var_5'
                    [Constants]
                        None
                        '__pyarmor_assert_35586__'
                        '__pyarmor_enter_35587__'
                        b'<COAddr>\x05\x00\x00\x1aF\x00\x00\x00\x00\x00\x00\x00\x00\x00\x00\x00\x00\x00\x00\x00'
                        (
                            'peer'
                        )
                        '__pyarmor_exit_35588__'
                    [Disassembly]
                        0       NOP                             
                        2       NOP                             
                        4       PUSH_NULL                       
                        6       LOAD_CONST                      2: '__pyarmor_enter_35587__'
                        8       LOAD_CONST                      3: b'<COAddr>\x05\x00\x00\x1aF\x00\x00\x00\x00\x00\x00\x00\x00\x00\x00\x00\x00\x00\x00\x00'
                        10      BUILD_TUPLE                     1
                        12      CALL_FUNCTION_EX                0
                        14      POP_TOP                         
                        16      RESUME                          0
                        18      NOP                             
                        20      NOP                             
                        22      NOP                             
                        24      NOP                             
                        26      NOP                             
                        28      LOAD_FAST                       1: reader
                        30      LOAD_ATTR                       1: tgread_object
                        50      CALL                            0
                        58      STORE_FAST                      3: _var_var_5
                        60      PUSH_NULL                       
                        62      LOAD_FAST                       0: cls
                        64      LOAD_FAST                       3: _var_var_5
                        66      KW_NAMES                        4: ('peer',)
                        68      CALL                            1
                        76      NOP                             
                        78      NOP                             
                        80      NOP                             
                        82      JUMP_FORWARD                    20 (to 124)
                        84      CALL                            1
                        92      POP_TOP                         
                        94      RETURN_VALUE                    
                        96      PUSH_EXC_INFO                   
                        98      PUSH_NULL                       
                        100     LOAD_CONST                      5: '__pyarmor_exit_35588__'
                        102     NOP                             
                        104     LOAD_CONST                      3: b'<COAddr>\x05\x00\x00\x1aF\x00\x00\x00\x00\x00\x00\x00\x00\x00\x00\x00\x00\x00\x00\x00'
                        106     CALL                            1
                        114     POP_TOP                         
                        116     RERAISE                         0
                        118     COPY                            3
                        120     POP_EXCEPT                      
                        122     RERAISE                         1
                        124     PUSH_NULL                       
                        126     LOAD_CONST                      5: '__pyarmor_exit_35588__'
                        128     LOAD_CONST                      3: b'<COAddr>\x05\x00\x00\x1aF\x00\x00\x00\x00\x00\x00\x00\x00\x00\x00\x00\x00\x00\x00\x00'
                        130     BUILD_TUPLE                     1
                        132     CALL_FUNCTION_EX                0
                        134     POP_TOP                         
                        136     RETURN_VALUE                    
                    [Exception Table]
                        28 to 76 -> 96 [0] 
                        96 to 118 -> 118 [1] lasti
                '__pyarmor_exit_35573__'
                None
            [Disassembly]
                0       NOP                             
                2       LOAD_NAME                       0: __name__
                4       STORE_NAME                      1: __module__
                6       LOAD_CONST                      0: 'GetBoostsStatusRequest'
                8       STORE_NAME                      2: __qualname__
                10      NOP                             
                12      PUSH_NULL                       
                14      LOAD_CONST                      2: '__pyarmor_enter_35572__'
                16      LOAD_CONST                      3: b'<COAddr>\x05\x00\x00"X\x00\x00\x00\x00\x00\x00\x00\x00\x00\x00\x00\x00\x00\x00\x00'
                18      BUILD_TUPLE                     1
                20      CALL_FUNCTION_EX                0
                22      POP_TOP                         
                24      RESUME                          0
                26      NOP                             
                28      NOP                             
                30      NOP                             
                32      NOP                             
                34      NOP                             
                36      LOAD_CONST                      4: 70197089
                38      STORE_NAME                      4: CONSTRUCTOR_ID
                40      LOAD_CONST                      5: 0xC31B1AB9
                42      STORE_NAME                      5: SUBCLASS_OF_ID
                44      LOAD_CONST                      6: 'peer'
                46      PUSH_NULL                       
                48      LOAD_CONST                      1: '__pyarmor_assert_35571__'
                50      LOAD_CONST                      7: 'TypeInputPeer'   # b'\x81\xd6\x01\x036\xd3\xb0\xc2\x0e\xee=\xc5i\xfe'
                52      CALL                            1
                60      BUILD_TUPLE                     2
                62      LOAD_CONST                      8: <CODE> __init__
                64      MAKE_FUNCTION                   4
                66      STORE_NAME                      6: __init__
                68      LOAD_CONST                      9: <CODE> resolve
                70      MAKE_FUNCTION                   0
                72      STORE_NAME                      7: resolve
                74      LOAD_CONST                      10: <CODE> to_dict
                76      MAKE_FUNCTION                   0
                78      STORE_NAME                      8: to_dict
                80      LOAD_CONST                      11: <CODE> _bytes
                82      MAKE_FUNCTION                   0
                84      STORE_NAME                      9: _bytes
                86      LOAD_NAME                       10: classmethod
                88      LOAD_CONST                      12: <CODE> from_reader
                90      MAKE_FUNCTION                   0
                92      CALL                            0
                100     STORE_NAME                      11: from_reader
                102     LOAD_CONST                      14: None
                104     NOP                             
                106     NOP                             
                108     NOP                             
                110     JUMP_FORWARD                    19 (to 150)
                118     POP_TOP                         
                120     RETURN_CONST                    14: None
                122     PUSH_EXC_INFO                   
                124     PUSH_NULL                       
                126     LOAD_CONST                      13: '__pyarmor_exit_35573__'
                128     NOP                             
                130     LOAD_CONST                      3: b'<COAddr>\x05\x00\x00"X\x00\x00\x00\x00\x00\x00\x00\x00\x00\x00\x00\x00\x00\x00\x00'
                132     CALL                            1
                140     POP_TOP                         
                142     RERAISE                         0
                144     COPY                            3
                146     POP_EXCEPT                      
                148     RERAISE                         1
                150     PUSH_NULL                       
                152     LOAD_CONST                      13: '__pyarmor_exit_35573__'
                154     LOAD_CONST                      3: b'<COAddr>\x05\x00\x00"X\x00\x00\x00\x00\x00\x00\x00\x00\x00\x00\x00\x00\x00\x00\x00'
                156     BUILD_TUPLE                     1
                158     CALL_FUNCTION_EX                0
                160     POP_TOP                         
                162     RETURN_VALUE                    
            [Exception Table]
                36 to 102 -> 122 [0] 
                122 to 144 -> 144 [1] lasti
        'GetBoostsStatusRequest'
        [Code]
            File Name: <frozen multithon.tl.functions.premium>
            Object Name: GetMyBoostsRequest
            Qualified Name: GetMyBoostsRequest
            Arg Count: 0
            Pos Only Arg Count: 0
            KW Only Arg Count: 0
            Stack Size: 5
            Flags: 0x20000000 (CO_PYARMOR_OBFUSCATED)
            [Names]
                '__name__'
                '__module__'
                '__qualname__'
                '__assert_armored__'
                'CONSTRUCTOR_ID'
                'SUBCLASS_OF_ID'
                'to_dict'
                '_bytes'
                'classmethod'
                'from_reader'
            [Locals+Names]
            [Constants]
                'GetMyBoostsRequest'
                '__pyarmor_assert_35589__'
                '__pyarmor_enter_35590__'
                b'<COAddr>\x07\x00\x00":\x00\x00\x00\x00\x00\x00\x00\x00\x00\x00\x00\x00\x00\x00\x00'
                199719754
                0xAD3512DB
                [Code]
                    File Name: <frozen multithon.tl.functions.premium>
                    Object Name: to_dict
                    Qualified Name: GetMyBoostsRequest.to_dict
                    Arg Count: 1
                    Pos Only Arg Count: 0
                    KW Only Arg Count: 0
                    Stack Size: 5
                    Flags: 0x20000003 (CO_OPTIMIZED | CO_NEWLOCALS | CO_PYARMOR_OBFUSCATED)
                    [Names]
                    [Locals+Names]
                        'self'
                        '__assert_armored__'
                    [Constants]
                        None
                        '__pyarmor_assert_35592__'
                        '__pyarmor_enter_35593__'
                        b'<COAddr>\x05\x00\x00\x1a(\x00\x00\x00\x00\x00\x00\x00\x00\x00\x00\x00\x00\x00\x00\x00'
                        '_'
                        'GetMyBoostsRequest'   # b'\x81\xc5\x1d\x07\x1e\xe3\x9c\xdd\x14\xe9\x19\xd3^\xe9\xe9\x90\nN\xaf'
                        '__pyarmor_exit_35594__'
                    [Disassembly]
                        0       NOP                             
                        2       NOP                             
                        4       PUSH_NULL                       
                        6       LOAD_CONST                      2: '__pyarmor_enter_35593__'
                        8       LOAD_CONST                      3: b'<COAddr>\x05\x00\x00\x1a(\x00\x00\x00\x00\x00\x00\x00\x00\x00\x00\x00\x00\x00\x00\x00'
                        10      BUILD_TUPLE                     1
                        12      CALL_FUNCTION_EX                0
                        14      POP_TOP                         
                        16      RESUME                          0
                        18      NOP                             
                        20      NOP                             
                        22      NOP                             
                        24      NOP                             
                        26      NOP                             
                        28      LOAD_CONST                      4: '_'
                        30      PUSH_NULL                       
                        32      LOAD_CONST                      1: '__pyarmor_assert_35592__'
                        34      LOAD_CONST                      5: 'GetMyBoostsRequest'   # b'\x81\xc5\x1d\x07\x1e\xe3\x9c\xdd\x14\xe9\x19\xd3^\xe9\xe9\x90\nN\xaf'
                        36      CALL                            1
                        44      BUILD_MAP                       1
                        46      NOP                             
                        48      NOP                             
                        50      NOP                             
                        52      JUMP_FORWARD                    20 (to 94)
                        54      CALL                            1
                        62      POP_TOP                         
                        64      RETURN_VALUE                    
                        66      PUSH_EXC_INFO                   
                        68      PUSH_NULL                       
                        70      LOAD_CONST                      6: '__pyarmor_exit_35594__'
                        72      NOP                             
                        74      LOAD_CONST                      3: b'<COAddr>\x05\x00\x00\x1a(\x00\x00\x00\x00\x00\x00\x00\x00\x00\x00\x00\x00\x00\x00\x00'
                        76      CALL                            1
                        84      POP_TOP                         
                        86      RERAISE                         0
                        88      COPY                            3
                        90      POP_EXCEPT                      
                        92      RERAISE                         1
                        94      PUSH_NULL                       
                        96      LOAD_CONST                      6: '__pyarmor_exit_35594__'
                        98      LOAD_CONST                      3: b'<COAddr>\x05\x00\x00\x1a(\x00\x00\x00\x00\x00\x00\x00\x00\x00\x00\x00\x00\x00\x00\x00'
                        100     BUILD_TUPLE                     1
                        102     CALL_FUNCTION_EX                0
                        104     POP_TOP                         
                        106     RETURN_VALUE                    
                    [Exception Table]
                        28 to 46 -> 66 [0] 
                        66 to 88 -> 88 [1] lasti
                [Code]
                    File Name: <frozen multithon.tl.functions.premium>
                    Object Name: _bytes
                    Qualified Name: GetMyBoostsRequest._bytes
                    Arg Count: 1
                    Pos Only Arg Count: 0
                    KW Only Arg Count: 0
                    Stack Size: 5
                    Flags: 0x20000003 (CO_OPTIMIZED | CO_NEWLOCALS | CO_PYARMOR_OBFUSCATED)
                    [Names]
                        'join'
                    [Locals+Names]
                        'self'
                        '__assert_armored__'
                    [Constants]
                        None
                        '__pyarmor_assert_35595__'
                        '__pyarmor_enter_35596__'
                        b'<COAddr>\x07\x00\x00\x1a6\x00\x00\x00\x00\x00\x00\x00\x00\x00\x00\x00\x00\x00\x00\x00'
                        b''
                        (
                            b'J{\xe7\x0b'
                        )
                        '__pyarmor_exit_35597__'
                    [Disassembly]
                        0       NOP                             
                        2       NOP                             
                        4       PUSH_NULL                       
                        6       LOAD_CONST                      2: '__pyarmor_enter_35596__'
                        8       LOAD_CONST                      3: b'<COAddr>\x07\x00\x00\x1a6\x00\x00\x00\x00\x00\x00\x00\x00\x00\x00\x00\x00\x00\x00\x00'
                        10      BUILD_TUPLE                     1
                        12      CALL_FUNCTION_EX                0
                        14      POP_TOP                         
                        16      RESUME                          0
                        18      NOP                             
                        20      NOP                             
                        22      NOP                             
                        24      NOP                             
                        26      NOP                             
                        28      LOAD_CONST                      4: b''
                        30      LOAD_ATTR                       1: join
                        50      LOAD_CONST                      5: (b'J{\xe7\x0b',)
                        52      CALL                            1
                        60      NOP                             
                        62      NOP                             
                        64      NOP                             
                        66      JUMP_FORWARD                    20 (to 108)
                        68      CALL                            1
                        76      POP_TOP                         
                        78      RETURN_VALUE                    
                        80      PUSH_EXC_INFO                   
                        82      PUSH_NULL                       
                        84      LOAD_CONST                      6: '__pyarmor_exit_35597__'
                        86      NOP                             
                        88      LOAD_CONST                      3: b'<COAddr>\x07\x00\x00\x1a6\x00\x00\x00\x00\x00\x00\x00\x00\x00\x00\x00\x00\x00\x00\x00'
                        90      CALL                            1
                        98      POP_TOP                         
                        100     RERAISE                         0
                        102     COPY                            3
                        104     POP_EXCEPT                      
                        106     RERAISE                         1
                        108     PUSH_NULL                       
                        110     LOAD_CONST                      6: '__pyarmor_exit_35597__'
                        112     LOAD_CONST                      3: b'<COAddr>\x07\x00\x00\x1a6\x00\x00\x00\x00\x00\x00\x00\x00\x00\x00\x00\x00\x00\x00\x00'
                        114     BUILD_TUPLE                     1
                        116     CALL_FUNCTION_EX                0
                        118     POP_TOP                         
                        120     RETURN_VALUE                    
                    [Exception Table]
                        28 to 60 -> 80 [0] 
                        80 to 102 -> 102 [1] lasti
                [Code]
                    File Name: <frozen multithon.tl.functions.premium>
                    Object Name: from_reader
                    Qualified Name: GetMyBoostsRequest.from_reader
                    Arg Count: 2
                    Pos Only Arg Count: 0
                    KW Only Arg Count: 0
                    Stack Size: 5
                    Flags: 0x20000003 (CO_OPTIMIZED | CO_NEWLOCALS | CO_PYARMOR_OBFUSCATED)
                    [Names]
                    [Locals+Names]
                        'cls'
                        'reader'
                        '__assert_armored__'
                    [Constants]
                        None
                        '__pyarmor_assert_35598__'
                        '__pyarmor_enter_35599__'
                        b'<COAddr>\x07\x00\x00\x1a"\x00\x00\x00\x00\x00\x00\x00\x00\x00\x00\x00\x00\x00\x00\x00'
                        '__pyarmor_exit_35600__'
                    [Disassembly]
                        0       NOP                             
                        2       NOP                             
                        4       PUSH_NULL                       
                        6       LOAD_CONST                      2: '__pyarmor_enter_35599__'
                        8       LOAD_CONST                      3: b'<COAddr>\x07\x00\x00\x1a"\x00\x00\x00\x00\x00\x00\x00\x00\x00\x00\x00\x00\x00\x00\x00'
                        10      BUILD_TUPLE                     1
                        12      CALL_FUNCTION_EX                0
                        14      POP_TOP                         
                        16      RESUME                          0
                        18      NOP                             
                        20      NOP                             
                        22      NOP                             
                        24      NOP                             
                        26      NOP                             
                        28      PUSH_NULL                       
                        30      LOAD_FAST                       0: cls
                        32      CALL                            0
                        40      NOP                             
                        42      NOP                             
                        44      NOP                             
                        46      JUMP_FORWARD                    20 (to 88)
                        48      CALL                            1
                        56      POP_TOP                         
                        58      RETURN_VALUE                    
                        60      PUSH_EXC_INFO                   
                        62      PUSH_NULL                       
                        64      LOAD_CONST                      4: '__pyarmor_exit_35600__'
                        66      NOP                             
                        68      LOAD_CONST                      3: b'<COAddr>\x07\x00\x00\x1a"\x00\x00\x00\x00\x00\x00\x00\x00\x00\x00\x00\x00\x00\x00\x00'
                        70      CALL                            1
                        78      POP_TOP                         
                        80      RERAISE                         0
                        82      COPY                            3
                        84      POP_EXCEPT                      
                        86      RERAISE                         1
                        88      PUSH_NULL                       
                        90      LOAD_CONST                      4: '__pyarmor_exit_35600__'
                        92      LOAD_CONST                      3: b'<COAddr>\x07\x00\x00\x1a"\x00\x00\x00\x00\x00\x00\x00\x00\x00\x00\x00\x00\x00\x00\x00'
                        94      BUILD_TUPLE                     1
                        96      CALL_FUNCTION_EX                0
                        98      POP_TOP                         
                        100     RETURN_VALUE                    
                    [Exception Table]
                        28 to 40 -> 60 [0] 
                        60 to 82 -> 82 [1] lasti
                '__pyarmor_exit_35591__'
                None
            [Disassembly]
                0       NOP                             
                2       LOAD_NAME                       0: __name__
                4       STORE_NAME                      1: __module__
                6       LOAD_CONST                      0: 'GetMyBoostsRequest'
                8       STORE_NAME                      2: __qualname__
                10      NOP                             
                12      PUSH_NULL                       
                14      LOAD_CONST                      2: '__pyarmor_enter_35590__'
                16      LOAD_CONST                      3: b'<COAddr>\x07\x00\x00":\x00\x00\x00\x00\x00\x00\x00\x00\x00\x00\x00\x00\x00\x00\x00'
                18      BUILD_TUPLE                     1
                20      CALL_FUNCTION_EX                0
                22      POP_TOP                         
                24      RESUME                          0
                26      NOP                             
                28      NOP                             
                30      NOP                             
                32      NOP                             
                34      NOP                             
                36      LOAD_CONST                      4: 199719754
                38      STORE_NAME                      4: CONSTRUCTOR_ID
                40      LOAD_CONST                      5: 0xAD3512DB
                42      STORE_NAME                      5: SUBCLASS_OF_ID
                44      LOAD_CONST                      6: <CODE> to_dict
                46      MAKE_FUNCTION                   0
                48      STORE_NAME                      6: to_dict
                50      LOAD_CONST                      7: <CODE> _bytes
                52      MAKE_FUNCTION                   0
                54      STORE_NAME                      7: _bytes
                56      LOAD_NAME                       8: classmethod
                58      LOAD_CONST                      8: <CODE> from_reader
                60      MAKE_FUNCTION                   0
                62      CALL                            0
                70      STORE_NAME                      9: from_reader
                72      LOAD_CONST                      10: None
                74      NOP                             
                76      NOP                             
                78      NOP                             
                80      JUMP_FORWARD                    19 (to 120)
                88      POP_TOP                         
                90      RETURN_CONST                    10: None
                92      PUSH_EXC_INFO                   
                94      PUSH_NULL                       
                96      LOAD_CONST                      9: '__pyarmor_exit_35591__'
                98      NOP                             
                100     LOAD_CONST                      3: b'<COAddr>\x07\x00\x00":\x00\x00\x00\x00\x00\x00\x00\x00\x00\x00\x00\x00\x00\x00\x00'
                102     CALL                            1
                110     POP_TOP                         
                112     RERAISE                         0
                114     COPY                            3
                116     POP_EXCEPT                      
                118     RERAISE                         1
                120     PUSH_NULL                       
                122     LOAD_CONST                      9: '__pyarmor_exit_35591__'
                124     LOAD_CONST                      3: b'<COAddr>\x07\x00\x00":\x00\x00\x00\x00\x00\x00\x00\x00\x00\x00\x00\x00\x00\x00\x00'
                126     BUILD_TUPLE                     1
                128     CALL_FUNCTION_EX                0
                130     POP_TOP                         
                132     RETURN_VALUE                    
            [Exception Table]
                36 to 72 -> 92 [0] 
                92 to 114 -> 114 [1] lasti
        'GetMyBoostsRequest'
        [Code]
            File Name: <frozen multithon.tl.functions.premium>
            Object Name: GetUserBoostsRequest
            Qualified Name: GetUserBoostsRequest
            Arg Count: 0
            Pos Only Arg Count: 0
            KW Only Arg Count: 0
            Stack Size: 6
            Flags: 0x20000000 (CO_PYARMOR_OBFUSCATED)
            [Names]
                '__name__'
                '__module__'
                '__qualname__'
                '__assert_armored__'
                'CONSTRUCTOR_ID'
                'SUBCLASS_OF_ID'
                '__init__'
                'resolve'
                'to_dict'
                '_bytes'
                'classmethod'
                'from_reader'
            [Locals+Names]
            [Constants]
                'GetUserBoostsRequest'
                '__pyarmor_assert_35601__'
                '__pyarmor_enter_35602__'
                b'<COAddr>\x07\x00\x00"h\x00\x00\x00\x00\x00\x00\x00\x00\x00\x00\x00\x00\x00\x00\x00'
                965037343
                573941949
                'peer'
                'TypeInputPeer'   # b'\x81\xd6\x01\x036\xd3\xb0\xc2\x0e\xee=\xc5i\xfe'
                'user_id'
                'TypeInputUser'   # b'\x81\xd6\x01\x036\xd3\xb0\xc2\x0e\xee8\xd3i\xfe'
                [Code]
                    File Name: <frozen multithon.tl.functions.premium>
                    Object Name: __init__
                    Qualified Name: GetUserBoostsRequest.__init__
                    Arg Count: 3
                    Pos Only Arg Count: 0
                    KW Only Arg Count: 0
                    Stack Size: 5
                    Flags: 0x20000003 (CO_OPTIMIZED | CO_NEWLOCALS | CO_PYARMOR_OBFUSCATED)
                    [Names]
                        'peer'
                        'user_id'
                    [Locals+Names]
                        'self'
                        'peer'
                        'user_id'
                        '__assert_armored__'
                    [Constants]
                        '\n        :returns premium.BoostsList: Instance of BoostsList.\n        '
                        '__pyarmor_assert_35604__'
                        '__pyarmor_enter_35605__'
                        b'<COAddr>\x07\x00\x00\x1a2\x00\x00\x00\x00\x00\x00\x00\x00\x00\x00\x00\x00\x00\x00\x00'
                        '__pyarmor_exit_35606__'
                        None
                    [Disassembly]
                        0       NOP                             
                        2       NOP                             
                        4       PUSH_NULL                       
                        6       LOAD_CONST                      2: '__pyarmor_enter_35605__'
                        8       LOAD_CONST                      3: b'<COAddr>\x07\x00\x00\x1a2\x00\x00\x00\x00\x00\x00\x00\x00\x00\x00\x00\x00\x00\x00\x00'
                        10      BUILD_TUPLE                     1
                        12      CALL_FUNCTION_EX                0
                        14      POP_TOP                         
                        16      RESUME                          0
                        18      NOP                             
                        20      NOP                             
                        22      NOP                             
                        24      NOP                             
                        26      NOP                             
                        28      LOAD_FAST                       1: peer
                        30      LOAD_FAST                       0: self
                        32      STORE_ATTR                      0: peer
                        42      LOAD_FAST                       2: user_id
                        44      LOAD_FAST                       0: self
                        46      STORE_ATTR                      1: user_id
                        56      LOAD_CONST                      5: None
                        58      NOP                             
                        60      NOP                             
                        62      NOP                             
                        64      JUMP_FORWARD                    19 (to 104)
                        72      POP_TOP                         
                        74      RETURN_CONST                    5: None
                        76      PUSH_EXC_INFO                   
                        78      PUSH_NULL                       
                        80      LOAD_CONST                      4: '__pyarmor_exit_35606__'
                        82      NOP                             
                        84      LOAD_CONST                      3: b'<COAddr>\x07\x00\x00\x1a2\x00\x00\x00\x00\x00\x00\x00\x00\x00\x00\x00\x00\x00\x00\x00'
                        86      CALL                            1
                        94      POP_TOP                         
                        96      RERAISE                         0
                        98      COPY                            3
                        100     POP_EXCEPT                      
                        102     RERAISE                         1
                        104     PUSH_NULL                       
                        106     LOAD_CONST                      4: '__pyarmor_exit_35606__'
                        108     LOAD_CONST                      3: b'<COAddr>\x07\x00\x00\x1a2\x00\x00\x00\x00\x00\x00\x00\x00\x00\x00\x00\x00\x00\x00\x00'
                        110     BUILD_TUPLE                     1
                        112     CALL_FUNCTION_EX                0
                        114     POP_TOP                         
                        116     RETURN_VALUE                    
                    [Exception Table]
                        28 to 56 -> 76 [0] 
                        76 to 98 -> 98 [1] lasti
                [Code]
                    File Name: <frozen multithon.tl.functions.premium>
                    Object Name: resolve
                    Qualified Name: GetUserBoostsRequest.resolve
                    Arg Count: 3
                    Pos Only Arg Count: 0
                    KW Only Arg Count: 0
                    Stack Size: 5
                    Flags: 0x20000083 (CO_OPTIMIZED | CO_NEWLOCALS | CO_COROUTINE | CO_PYARMOR_OBFUSCATED)
                    [Names]
                        'get_input_peer'
                        'get_input_entity'
                        'peer'
                        'get_input_user'
                        'user_id'
                    [Locals+Names]
                        'self'
                        'client'
                        'utils'
                        '__assert_armored__'
                    [Constants]
                        None
                        '__pyarmor_assert_35607__'
                        '__pyarmor_enter_35608__'
                        b'<COAddr>\x07\x00\x00\x1e\xfa\x00\x00\x00\x00\x00\x00\x00\x00\x00\x00\x00\x00\x00\x00\x00'
                        '__pyarmor_exit_35609__'
                    [Disassembly]
                        0       RETURN_GENERATOR                
                        2       POP_TOP                         
                        4       NOP                             
                        6       NOP                             
                        8       PUSH_NULL                       
                        10      LOAD_CONST                      2: '__pyarmor_enter_35608__'
                        12      LOAD_CONST                      3: b'<COAddr>\x07\x00\x00\x1e\xfa\x00\x00\x00\x00\x00\x00\x00\x00\x00\x00\x00\x00\x00\x00\x00'
                        14      BUILD_TUPLE                     1
                        16      CALL_FUNCTION_EX                0
                        18      POP_TOP                         
                        20      RESUME                          0
                        22      NOP                             
                        24      NOP                             
                        26      NOP                             
                        28      NOP                             
                        30      NOP                             
                        32      LOAD_FAST                       2: utils
                        34      LOAD_ATTR                       1: get_input_peer
                        54      LOAD_FAST                       1: client
                        56      LOAD_ATTR                       3: get_input_entity
                        76      LOAD_FAST                       0: self
                        78      LOAD_ATTR                       4: peer
                        98      CALL                            1
                        106     GET_AWAITABLE                   0
                        108     LOAD_CONST                      0: None
                        110     SEND                            3 (to 118)
                        114     YIELD_VALUE                     3
                        116     RESUME                          3
                        118     JUMP_BACKWARD_NO_INTERRUPT      5 (to 110)
                        120     END_SEND                        
                        122     CALL                            1
                        130     LOAD_FAST                       0: self
                        132     STORE_ATTR                      2: peer
                        142     LOAD_FAST                       2: utils
                        144     LOAD_ATTR                       7: get_input_user
                        164     LOAD_FAST                       1: client
                        166     LOAD_ATTR                       3: get_input_entity
                        186     LOAD_FAST                       0: self
                        188     LOAD_ATTR                       8: user_id
                        208     CALL                            1
                        216     GET_AWAITABLE                   0
                        218     LOAD_CONST                      0: None
                        220     SEND                            3 (to 228)
                        224     YIELD_VALUE                     3
                        226     RESUME                          3
                        228     JUMP_BACKWARD_NO_INTERRUPT      5 (to 220)
                        230     END_SEND                        
                        232     CALL                            1
                        240     LOAD_FAST                       0: self
                        242     STORE_ATTR                      4: user_id
                        252     LOAD_CONST                      0: None
                        254     NOP                             
                        256     NOP                             
                        258     NOP                             
                        260     JUMP_FORWARD                    25 (to 312)
                        268     POP_TOP                         
                        270     RETURN_CONST                    0: None
                        272     CLEANUP_THROW                   
                        274     JUMP_BACKWARD                   78 (to 120)
                        276     CLEANUP_THROW                   
                        278     JUMP_BACKWARD                   25 (to 230)
                        280     PUSH_EXC_INFO                   
                        282     PUSH_NULL                       
                        284     LOAD_CONST                      4: '__pyarmor_exit_35609__'
                        286     NOP                             
                        288     LOAD_CONST                      3: b'<COAddr>\x07\x00\x00\x1e\xfa\x00\x00\x00\x00\x00\x00\x00\x00\x00\x00\x00\x00\x00\x00\x00'
                        290     CALL                            1
                        298     POP_TOP                         
                        300     RERAISE                         0
                        302     COPY                            3
                        304     POP_EXCEPT                      
                        306     RERAISE                         1
                        308     CALL_INTRINSIC_1                3 (INTRINSIC_STOPITERATION_ERROR)
                        310     RERAISE                         1
                        312     PUSH_NULL                       
                        314     LOAD_CONST                      4: '__pyarmor_exit_35609__'
                        316     LOAD_CONST                      3: b'<COAddr>\x07\x00\x00\x1e\xfa\x00\x00\x00\x00\x00\x00\x00\x00\x00\x00\x00\x00\x00\x00\x00'
                        318     BUILD_TUPLE                     1
                        320     CALL_FUNCTION_EX                0
                        322     POP_TOP                         
                        324     RETURN_VALUE                    
                    [Exception Table]
                        4 to 30 -> 308 [0] lasti
                        32 to 114 -> 280 [0] 
                        114 to 116 -> 272 [4] 
                        116 to 224 -> 280 [0] 
                        224 to 226 -> 276 [4] 
                        226 to 252 -> 280 [0] 
                        252 to 272 -> 308 [0] lasti
                        272 to 274 -> 280 [0] 
                        276 to 278 -> 280 [0] 
                        280 to 302 -> 302 [1] lasti
                        302 to 308 -> 308 [0] lasti
                [Code]
                    File Name: <frozen multithon.tl.functions.premium>
                    Object Name: to_dict
                    Qualified Name: GetUserBoostsRequest.to_dict
                    Arg Count: 1
                    Pos Only Arg Count: 0
                    KW Only Arg Count: 0
                    Stack Size: 6
                    Flags: 0x20000003 (CO_OPTIMIZED | CO_NEWLOCALS | CO_PYARMOR_OBFUSCATED)
                    [Names]
                        'isinstance'
                        'peer'
                        'TLObject'
                        'to_dict'
                        'user_id'
                    [Locals+Names]
                        'self'
                        '__assert_armored__'
                    [Constants]
                        None
                        '__pyarmor_assert_35610__'
                        '__pyarmor_enter_35611__'
                        b'<COAddr>\x05\x00\x00\x1a$\x01\x00\x00\x00\x00\x00\x00\x00\x00\x00\x00\x00\x00\x00\x00'
                        'GetUserBoostsRequest'   # b'\x81\xc5\x1d\x07\x06\xe9\xbb\xc09\xf5\x02\xd3x\xff\xca\x80\x1eH\xbe\xb4\xbe'
                        (
                            '_'
                            'peer'
                            'user_id'
                        )
                        '__pyarmor_exit_35612__'
                    [Disassembly]
                        0       NOP                             
                        2       NOP                             
                        4       PUSH_NULL                       
                        6       LOAD_CONST                      2: '__pyarmor_enter_35611__'
                        8       LOAD_CONST                      3: b'<COAddr>\x05\x00\x00\x1a$\x01\x00\x00\x00\x00\x00\x00\x00\x00\x00\x00\x00\x00\x00\x00'
                        10      BUILD_TUPLE                     1
                        12      CALL_FUNCTION_EX                0
                        14      POP_TOP                         
                        16      RESUME                          0
                        18      NOP                             
                        20      NOP                             
                        22      NOP                             
                        24      NOP                             
                        26      NOP                             
                        28      PUSH_NULL                       
                        30      LOAD_CONST                      1: '__pyarmor_assert_35610__'
                        32      LOAD_CONST                      4: 'GetUserBoostsRequest'   # b'\x81\xc5\x1d\x07\x06\xe9\xbb\xc09\xf5\x02\xd3x\xff\xca\x80\x1eH\xbe\xb4\xbe'
                        34      CALL                            1
                        42      LOAD_GLOBAL                     1: NULL + isinstance
                        52      LOAD_FAST                       0: self
                        54      LOAD_ATTR                       2: peer
                        74      LOAD_GLOBAL                     4: TLObject
                        84      CALL                            2
                        92      POP_JUMP_IF_FALSE               26 (to 146)
                        94      LOAD_FAST                       0: self
                        96      LOAD_ATTR                       2: peer
                        116     LOAD_ATTR                       7: to_dict
                        136     CALL                            0
                        144     JUMP_FORWARD                    11 (to 168)
                        146     LOAD_FAST                       0: self
                        148     LOAD_ATTR                       2: peer
                        168     LOAD_GLOBAL                     1: NULL + isinstance
                        178     LOAD_FAST                       0: self
                        180     LOAD_ATTR                       8: user_id
                        200     LOAD_GLOBAL                     4: TLObject
                        210     CALL                            2
                        218     POP_JUMP_IF_FALSE               26 (to 272)
                        220     LOAD_FAST                       0: self
                        222     LOAD_ATTR                       8: user_id
                        242     LOAD_ATTR                       7: to_dict
                        262     CALL                            0
                        270     JUMP_FORWARD                    11 (to 294)
                        272     LOAD_FAST                       0: self
                        274     LOAD_ATTR                       8: user_id
                        294     LOAD_CONST                      5: ('_', 'peer', 'user_id')
                        296     BUILD_CONST_KEY_MAP             3
                        298     NOP                             
                        300     NOP                             
                        302     NOP                             
                        304     JUMP_FORWARD                    20 (to 346)
                        306     CALL                            1
                        314     POP_TOP                         
                        316     RETURN_VALUE                    
                        318     PUSH_EXC_INFO                   
                        320     PUSH_NULL                       
                        322     LOAD_CONST                      6: '__pyarmor_exit_35612__'
                        324     NOP                             
                        326     LOAD_CONST                      3: b'<COAddr>\x05\x00\x00\x1a$\x01\x00\x00\x00\x00\x00\x00\x00\x00\x00\x00\x00\x00\x00\x00'
                        328     CALL                            1
                        336     POP_TOP                         
                        338     RERAISE                         0
                        340     COPY                            3
                        342     POP_EXCEPT                      
                        344     RERAISE                         1
                        346     PUSH_NULL                       
                        348     LOAD_CONST                      6: '__pyarmor_exit_35612__'
                        350     LOAD_CONST                      3: b'<COAddr>\x05\x00\x00\x1a$\x01\x00\x00\x00\x00\x00\x00\x00\x00\x00\x00\x00\x00\x00\x00'
                        352     BUILD_TUPLE                     1
                        354     CALL_FUNCTION_EX                0
                        356     POP_TOP                         
                        358     RETURN_VALUE                    
                    [Exception Table]
                        28 to 298 -> 318 [0] 
                        318 to 340 -> 340 [1] lasti
                [Code]
                    File Name: <frozen multithon.tl.functions.premium>
                    Object Name: _bytes
                    Qualified Name: GetUserBoostsRequest._bytes
                    Arg Count: 1
                    Pos Only Arg Count: 0
                    KW Only Arg Count: 0
                    Stack Size: 6
                    Flags: 0x20000003 (CO_OPTIMIZED | CO_NEWLOCALS | CO_PYARMOR_OBFUSCATED)
                    [Names]
                        'join'
                        'peer'
                        '_bytes'
                        'user_id'
                    [Locals+Names]
                        'self'
                        '__assert_armored__'
                    [Constants]
                        None
                        '__pyarmor_assert_35613__'
                        '__pyarmor_enter_35614__'
                        b'<COAddr>\x05\x00\x00\x1a\x9c\x00\x00\x00\x00\x00\x00\x00\x00\x00\x00\x00\x00\x00\x00\x00'
                        b''
                        b'\x1fM\x859'
                        '__pyarmor_exit_35615__'
                    [Disassembly]
                        0       NOP                             
                        2       NOP                             
                        4       PUSH_NULL                       
                        6       LOAD_CONST                      2: '__pyarmor_enter_35614__'
                        8       LOAD_CONST                      3: b'<COAddr>\x05\x00\x00\x1a\x9c\x00\x00\x00\x00\x00\x00\x00\x00\x00\x00\x00\x00\x00\x00\x00'
                        10      BUILD_TUPLE                     1
                        12      CALL_FUNCTION_EX                0
                        14      POP_TOP                         
                        16      RESUME                          0
                        18      NOP                             
                        20      NOP                             
                        22      NOP                             
                        24      NOP                             
                        26      NOP                             
                        28      LOAD_CONST                      4: b''
                        30      LOAD_ATTR                       1: join
                        50      LOAD_CONST                      5: b'\x1fM\x859'
                        52      LOAD_FAST                       0: self
                        54      LOAD_ATTR                       2: peer
                        74      LOAD_ATTR                       5: _bytes
                        94      CALL                            0
                        102     LOAD_FAST                       0: self
                        104     LOAD_ATTR                       6: user_id
                        124     LOAD_ATTR                       5: _bytes
                        144     CALL                            0
                        152     BUILD_TUPLE                     3
                        154     CALL                            1
                        162     NOP                             
                        164     NOP                             
                        166     NOP                             
                        168     JUMP_FORWARD                    20 (to 210)
                        170     CALL                            1
                        178     POP_TOP                         
                        180     RETURN_VALUE                    
                        182     PUSH_EXC_INFO                   
                        184     PUSH_NULL                       
                        186     LOAD_CONST                      6: '__pyarmor_exit_35615__'
                        188     NOP                             
                        190     LOAD_CONST                      3: b'<COAddr>\x05\x00\x00\x1a\x9c\x00\x00\x00\x00\x00\x00\x00\x00\x00\x00\x00\x00\x00\x00\x00'
                        192     CALL                            1
                        200     POP_TOP                         
                        202     RERAISE                         0
                        204     COPY                            3
                        206     POP_EXCEPT                      
                        208     RERAISE                         1
                        210     PUSH_NULL                       
                        212     LOAD_CONST                      6: '__pyarmor_exit_35615__'
                        214     LOAD_CONST                      3: b'<COAddr>\x05\x00\x00\x1a\x9c\x00\x00\x00\x00\x00\x00\x00\x00\x00\x00\x00\x00\x00\x00\x00'
                        216     BUILD_TUPLE                     1
                        218     CALL_FUNCTION_EX                0
                        220     POP_TOP                         
                        222     RETURN_VALUE                    
                    [Exception Table]
                        28 to 162 -> 182 [0] 
                        182 to 204 -> 204 [1] lasti
                [Code]
                    File Name: <frozen multithon.tl.functions.premium>
                    Object Name: from_reader
                    Qualified Name: GetUserBoostsRequest.from_reader
                    Arg Count: 2
                    Pos Only Arg Count: 0
                    KW Only Arg Count: 0
                    Stack Size: 5
                    Flags: 0x20000003 (CO_OPTIMIZED | CO_NEWLOCALS | CO_PYARMOR_OBFUSCATED)
                    [Names]
                        'tgread_object'
                    [Locals+Names]
                        'cls'
                        'reader'
                        '__assert_armored__'
                        '_var_var_5'
                        '_var_var_9'
                    [Constants]
                        None
                        '__pyarmor_assert_35616__'
                        '__pyarmor_enter_35617__'
                        b'<COAddr>\x07\x00\x00\x1ah\x00\x00\x00\x00\x00\x00\x00\x00\x00\x00\x00\x00\x00\x00\x00'
                        (
                            'peer'
                            'user_id'
                        )
                        '__pyarmor_exit_35618__'
                    [Disassembly]
                        0       NOP                             
                        2       NOP                             
                        4       PUSH_NULL                       
                        6       LOAD_CONST                      2: '__pyarmor_enter_35617__'
                        8       LOAD_CONST                      3: b'<COAddr>\x07\x00\x00\x1ah\x00\x00\x00\x00\x00\x00\x00\x00\x00\x00\x00\x00\x00\x00\x00'
                        10      BUILD_TUPLE                     1
                        12      CALL_FUNCTION_EX                0
                        14      POP_TOP                         
                        16      RESUME                          0
                        18      NOP                             
                        20      NOP                             
                        22      NOP                             
                        24      NOP                             
                        26      NOP                             
                        28      LOAD_FAST                       1: reader
                        30      LOAD_ATTR                       1: tgread_object
                        50      CALL                            0
                        58      STORE_FAST                      3: _var_var_5
                        60      LOAD_FAST                       1: reader
                        62      LOAD_ATTR                       1: tgread_object
                        82      CALL                            0
                        90      STORE_FAST                      4: _var_var_9
                        92      PUSH_NULL                       
                        94      LOAD_FAST                       0: cls
                        96      LOAD_FAST                       3: _var_var_5
                        98      LOAD_FAST                       4: _var_var_9
                        100     KW_NAMES                        4: ('peer', 'user_id')
                        102     CALL                            2
                        110     NOP                             
                        112     NOP                             
                        114     NOP                             
                        116     JUMP_FORWARD                    20 (to 158)
                        118     CALL                            1
                        126     POP_TOP                         
                        128     RETURN_VALUE                    
                        130     PUSH_EXC_INFO                   
                        132     PUSH_NULL                       
                        134     LOAD_CONST                      5: '__pyarmor_exit_35618__'
                        136     NOP                             
                        138     LOAD_CONST                      3: b'<COAddr>\x07\x00\x00\x1ah\x00\x00\x00\x00\x00\x00\x00\x00\x00\x00\x00\x00\x00\x00\x00'
                        140     CALL                            1
                        148     POP_TOP                         
                        150     RERAISE                         0
                        152     COPY                            3
                        154     POP_EXCEPT                      
                        156     RERAISE                         1
                        158     PUSH_NULL                       
                        160     LOAD_CONST                      5: '__pyarmor_exit_35618__'
                        162     LOAD_CONST                      3: b'<COAddr>\x07\x00\x00\x1ah\x00\x00\x00\x00\x00\x00\x00\x00\x00\x00\x00\x00\x00\x00\x00'
                        164     BUILD_TUPLE                     1
                        166     CALL_FUNCTION_EX                0
                        168     POP_TOP                         
                        170     RETURN_VALUE                    
                    [Exception Table]
                        28 to 110 -> 130 [0] 
                        130 to 152 -> 152 [1] lasti
                '__pyarmor_exit_35603__'
                None
            [Disassembly]
                0       NOP                             
                2       LOAD_NAME                       0: __name__
                4       STORE_NAME                      1: __module__
                6       LOAD_CONST                      0: 'GetUserBoostsRequest'
                8       STORE_NAME                      2: __qualname__
                10      NOP                             
                12      PUSH_NULL                       
                14      LOAD_CONST                      2: '__pyarmor_enter_35602__'
                16      LOAD_CONST                      3: b'<COAddr>\x07\x00\x00"h\x00\x00\x00\x00\x00\x00\x00\x00\x00\x00\x00\x00\x00\x00\x00'
                18      BUILD_TUPLE                     1
                20      CALL_FUNCTION_EX                0
                22      POP_TOP                         
                24      RESUME                          0
                26      NOP                             
                28      NOP                             
                30      NOP                             
                32      NOP                             
                34      NOP                             
                36      LOAD_CONST                      4: 965037343
                38      STORE_NAME                      4: CONSTRUCTOR_ID
                40      LOAD_CONST                      5: 573941949
                42      STORE_NAME                      5: SUBCLASS_OF_ID
                44      LOAD_CONST                      6: 'peer'
                46      PUSH_NULL                       
                48      LOAD_CONST                      1: '__pyarmor_assert_35601__'
                50      LOAD_CONST                      7: 'TypeInputPeer'   # b'\x81\xd6\x01\x036\xd3\xb0\xc2\x0e\xee=\xc5i\xfe'
                52      CALL                            1
                60      LOAD_CONST                      8: 'user_id'
                62      PUSH_NULL                       
                64      LOAD_CONST                      1: '__pyarmor_assert_35601__'
                66      LOAD_CONST                      9: 'TypeInputUser'   # b'\x81\xd6\x01\x036\xd3\xb0\xc2\x0e\xee8\xd3i\xfe'
                68      CALL                            1
                76      BUILD_TUPLE                     4
                78      LOAD_CONST                      10: <CODE> __init__
                80      MAKE_FUNCTION                   4
                82      STORE_NAME                      6: __init__
                84      LOAD_CONST                      11: <CODE> resolve
                86      MAKE_FUNCTION                   0
                88      STORE_NAME                      7: resolve
                90      LOAD_CONST                      12: <CODE> to_dict
                92      MAKE_FUNCTION                   0
                94      STORE_NAME                      8: to_dict
                96      LOAD_CONST                      13: <CODE> _bytes
                98      MAKE_FUNCTION                   0
                100     STORE_NAME                      9: _bytes
                102     LOAD_NAME                       10: classmethod
                104     LOAD_CONST                      14: <CODE> from_reader
                106     MAKE_FUNCTION                   0
                108     CALL                            0
                116     STORE_NAME                      11: from_reader
                118     LOAD_CONST                      16: None
                120     NOP                             
                122     NOP                             
                124     NOP                             
                126     JUMP_FORWARD                    19 (to 166)
                134     POP_TOP                         
                136     RETURN_CONST                    16: None
                138     PUSH_EXC_INFO                   
                140     PUSH_NULL                       
                142     LOAD_CONST                      15: '__pyarmor_exit_35603__'
                144     NOP                             
                146     LOAD_CONST                      3: b'<COAddr>\x07\x00\x00"h\x00\x00\x00\x00\x00\x00\x00\x00\x00\x00\x00\x00\x00\x00\x00'
                148     CALL                            1
                156     POP_TOP                         
                158     RERAISE                         0
                160     COPY                            3
                162     POP_EXCEPT                      
                164     RERAISE                         1
                166     PUSH_NULL                       
                168     LOAD_CONST                      15: '__pyarmor_exit_35603__'
                170     LOAD_CONST                      3: b'<COAddr>\x07\x00\x00"h\x00\x00\x00\x00\x00\x00\x00\x00\x00\x00\x00\x00\x00\x00\x00'
                172     BUILD_TUPLE                     1
                174     CALL_FUNCTION_EX                0
                176     POP_TOP                         
                178     RETURN_VALUE                    
            [Exception Table]
                36 to 118 -> 138 [0] 
                138 to 160 -> 160 [1] lasti
        'GetUserBoostsRequest'
        '__pyarmor_exit_35534__'
    [Disassembly]
        0       NOP                             
        2       NOP                             
        4       PUSH_NULL                       
        6       LOAD_CONST                      1: '__pyarmor_enter_35533__'
        8       LOAD_CONST                      2: b'<COAddr>\x07\x00\x00\x1a\xf2\x00\x00\x00\x00\x00\x00\x00\x00\x00\x00\x00\x00\x00\x00\x00'
        10      BUILD_TUPLE                     1
        12      CALL_FUNCTION_EX                0
        14      POP_TOP                         
        16      RESUME                          0
        18      NOP                             
        20      NOP                             
        22      NOP                             
        24      NOP                             
        26      PUSH_NULL                       
        28      LOAD_CONST                      0: '__pyarmor_assert_35532__'
        30      LOAD_CONST                      3: "File generated by TLObjects' generator. All changes will be ERASED"   # b'\x81\xc4\x11\x1f6\xba\xb9\xd7\x15\xff\x1f\xc1x\xe9\xfc\xc5\rD\xfb\x93\x86\xe4L\xc6\x00l\xb7OG\xf1\x19\xe04W2\x0c\x8c\xc5\xa6`X\xc8\xf4Q\x9d\xdb\x07F9\xeaS\xe8\xc7g\x0f\xe1;\xab\x99\x18Xn\x03rdm!'
        32      CALL                            1
        40      POP_TOP                         
        42      LOAD_CONST                      4: 3
        44      LOAD_CONST                      5: ('TLObject',)
        46      IMPORT_NAME                     1: tl.tlobject
        48      IMPORT_FROM                     2: TLObject
        50      STORE_NAME                      2: TLObject
        52      POP_TOP                         
        54      LOAD_CONST                      4: 3
        56      LOAD_CONST                      6: ('TLRequest',)
        58      IMPORT_NAME                     1: tl.tlobject
        60      IMPORT_FROM                     3: TLRequest
        62      STORE_NAME                      3: TLRequest
        64      POP_TOP                         
        66      LOAD_CONST                      7: 0
        68      LOAD_CONST                      8: ('Optional', 'List', 'Union', 'TYPE_CHECKING')
        70      IMPORT_NAME                     4: typing
        72      IMPORT_FROM                     5: Optional
        74      STORE_NAME                      5: Optional
        76      IMPORT_FROM                     6: List
        78      STORE_NAME                      6: List
        80      IMPORT_FROM                     7: Union
        82      STORE_NAME                      7: Union
        84      IMPORT_FROM                     8: TYPE_CHECKING
        86      STORE_NAME                      8: TYPE_CHECKING
        88      POP_TOP                         
        90      LOAD_CONST                      7: 0
        92      LOAD_CONST                      9: None
        94      IMPORT_NAME                     9: os
        96      STORE_NAME                      9: os
        98      LOAD_CONST                      7: 0
        100     LOAD_CONST                      9: None
        102     IMPORT_NAME                     10: struct
        104     STORE_NAME                      10: struct
        106     LOAD_CONST                      7: 0
        108     LOAD_CONST                      10: ('datetime',)
        110     IMPORT_NAME                     11: datetime
        112     IMPORT_FROM                     11: datetime
        114     STORE_NAME                      11: datetime
        116     POP_TOP                         
        118     LOAD_NAME                       8: TYPE_CHECKING
        120     POP_JUMP_IF_FALSE               8 (to 138)
        122     LOAD_CONST                      4: 3
        124     LOAD_CONST                      11: ('TypeInputPeer', 'TypeInputUser')
        126     IMPORT_NAME                     12: tl.types
        128     IMPORT_FROM                     13: TypeInputPeer
        130     STORE_NAME                      13: TypeInputPeer
        132     IMPORT_FROM                     14: TypeInputUser
        134     STORE_NAME                      14: TypeInputUser
        136     POP_TOP                         
        138     PUSH_NULL                       
        140     LOAD_BUILD_CLASS                
        142     LOAD_CONST                      12: <CODE> ApplyBoostRequest
        144     MAKE_FUNCTION                   0
        146     LOAD_CONST                      13: 'ApplyBoostRequest'
        148     LOAD_NAME                       3: TLRequest
        150     CALL                            3
        158     STORE_NAME                      15: ApplyBoostRequest
        160     PUSH_NULL                       
        162     LOAD_BUILD_CLASS                
        164     LOAD_CONST                      14: <CODE> GetBoostsListRequest
        166     MAKE_FUNCTION                   0
        168     LOAD_CONST                      15: 'GetBoostsListRequest'
        170     LOAD_NAME                       3: TLRequest
        172     CALL                            3
        180     STORE_NAME                      16: GetBoostsListRequest
        182     PUSH_NULL                       
        184     LOAD_BUILD_CLASS                
        186     LOAD_CONST                      16: <CODE> GetBoostsStatusRequest
        188     MAKE_FUNCTION                   0
        190     LOAD_CONST                      17: 'GetBoostsStatusRequest'
        192     LOAD_NAME                       3: TLRequest
        194     CALL                            3
        202     STORE_NAME                      17: GetBoostsStatusRequest
        204     PUSH_NULL                       
        206     LOAD_BUILD_CLASS                
        208     LOAD_CONST                      18: <CODE> GetMyBoostsRequest
        210     MAKE_FUNCTION                   0
        212     LOAD_CONST                      19: 'GetMyBoostsRequest'
        214     LOAD_NAME                       3: TLRequest
        216     CALL                            3
        224     STORE_NAME                      18: GetMyBoostsRequest
        226     PUSH_NULL                       
        228     LOAD_BUILD_CLASS                
        230     LOAD_CONST                      20: <CODE> GetUserBoostsRequest
        232     MAKE_FUNCTION                   0
        234     LOAD_CONST                      21: 'GetUserBoostsRequest'
        236     LOAD_NAME                       3: TLRequest
        238     CALL                            3
        246     STORE_NAME                      19: GetUserBoostsRequest
        248     LOAD_CONST                      9: None
        250     NOP                             
        252     NOP                             
        254     NOP                             
        256     JUMP_FORWARD                    19 (to 296)
        264     POP_TOP                         
        266     RETURN_CONST                    9: None
        268     PUSH_EXC_INFO                   
        270     PUSH_NULL                       
        272     LOAD_CONST                      22: '__pyarmor_exit_35534__'
        274     NOP                             
        276     LOAD_CONST                      2: b'<COAddr>\x07\x00\x00\x1a\xf2\x00\x00\x00\x00\x00\x00\x00\x00\x00\x00\x00\x00\x00\x00\x00'
        278     CALL                            1
        286     POP_TOP                         
        288     RERAISE                         0
        290     COPY                            3
        292     POP_EXCEPT                      
        294     RERAISE                         1
        296     PUSH_NULL                       
        298     LOAD_CONST                      22: '__pyarmor_exit_35534__'
        300     LOAD_CONST                      2: b'<COAddr>\x07\x00\x00\x1a\xf2\x00\x00\x00\x00\x00\x00\x00\x00\x00\x00\x00\x00\x00\x00\x00'
        302     BUILD_TUPLE                     1
        304     CALL_FUNCTION_EX                0
        306     POP_TOP                         
        308     RETURN_VALUE                    
    [Exception Table]
        26 to 248 -> 268 [0] 
        268 to 290 -> 290 [1] lasti
