#decoded by lolz.live/mrpenny / t.me/zeus_jackpot
# ================================
# Примечания по Pyarmor:
# - Байт-код и объекты кода Pyarmor соответствуют стандартному Python, но присутствуют специальные вызовы функций среды выполнения (runtime) Pyarmor.
# - Вызовы строк — это не ошибки, а маркеры, которые обрабатываются Pyarmor во время выполнения.
#
# Руководство по декомпиляции (без среды выполнения):
# 1. Игнорируйте зашифрованные байты после `#`; используйте только строку до `#`.
# 2. Удалите "__pyarmor_enter_xxx__"(b"<COAddr>...") и "__pyarmor_leave_xxx__"(b"<COAddr>...") (пролог/эпилог).
# 3. "__pyarmor_assert_xxx__"(A) не является настоящим оператором assert.
#    - Если A — это имя или читаемая строка: замените на A.
#    - Если A — это (X, "Y"): замените на X.Y.
#    - Если A — это (X, "Y", Z): замените на X.Y = Z.
#    - В противном случае: выберите наиболее подходящую/логичную замену.
# 4. "__pyarmor_bcc_xxx__"(...) указывает на машинный (нативный) код; тело функции недоступно. Добавьте комментарий.
# ================================

[Code]
    File Name: <frozen multithon.tl.functions.smsjobs>
    Object Name: <module>
    Qualified Name: <module>
    Arg Count: 0
    Pos Only Arg Count: 0
    KW Only Arg Count: 0
    Stack Size: 5
    Flags: 0x20000000 (CO_PYARMOR_OBFUSCATED)
    [Names]
        '__assert_armored__'
        'tl.tlobject'
        'TLObject'
        'TLRequest'
        'typing'
        'Optional'
        'List'
        'Union'
        'TYPE_CHECKING'
        'os'
        'struct'
        'datetime'
        'FinishJobRequest'
        'GetSmsJobRequest'
        'GetStatusRequest'
        'IsEligibleToJoinRequest'
        'JoinRequest'
        'LeaveRequest'
        'UpdateSettingsRequest'
    [Locals+Names]
    [Constants]
        '__pyarmor_assert_35619__'
        '__pyarmor_enter_35620__'
        b'<COAddr>\x05\x00\x00\x1a\n\x01\x00\x00\x00\x00\x00\x00\x00\x00\x00\x00\x00\x00\x00\x00'
        "File generated by TLObjects' generator. All changes will be ERASED"   # b'\x81\xc4\x11\x1f6\xba\xb9\xd7\x15\xff\x1f\xc1x\xe9\xfc\xc5\rD\xfb\x93\x86\xe4L\xc6\x00l\xb7OG\xf1\x19\xe04W2\x0c\x8c\xc5\xa6`X\xc8\xf4Q\x9d\xdb\x07F9\xeaS\xe8\xc7g\x0f\xe1;\xab\x99\x18Xn\x03rdm!'
        3
        (
            'TLObject'
        )
        (
            'TLRequest'
        )
        0
        (
            'Optional'
            'List'
            'Union'
            'TYPE_CHECKING'
        )
        None
        (
            'datetime'
        )
        [Code]
            File Name: <frozen multithon.tl.functions.smsjobs>
            Object Name: FinishJobRequest
            Qualified Name: FinishJobRequest
            Arg Count: 0
            Pos Only Arg Count: 0
            KW Only Arg Count: 0
            Stack Size: 6
            Flags: 0x20000000 (CO_PYARMOR_OBFUSCATED)
            [Names]
                '__name__'
                '__module__'
                '__qualname__'
                '__assert_armored__'
                'CONSTRUCTOR_ID'
                'SUBCLASS_OF_ID'
                'str'
                'Optional'
                '__init__'
                'to_dict'
                '_bytes'
                'classmethod'
                'from_reader'
            [Locals+Names]
            [Constants]
                'FinishJobRequest'
                '__pyarmor_assert_35622__'
                '__pyarmor_enter_35623__'
                b'<COAddr>\x05\x00\x00"R\x00\x00\x00\x00\x00\x00\x00\x00\x00\x00\x00\x00\x00\x00\x00'
                1327415076
                0xF5B399AC
                None
                'job_id'
                'error'
                [Code]
                    File Name: <frozen multithon.tl.functions.smsjobs>
                    Object Name: __init__
                    Qualified Name: FinishJobRequest.__init__
                    Arg Count: 3
                    Pos Only Arg Count: 0
                    KW Only Arg Count: 0
                    Stack Size: 5
                    Flags: 0x20000003 (CO_OPTIMIZED | CO_NEWLOCALS | CO_PYARMOR_OBFUSCATED)
                    [Names]
                        'job_id'
                        'error'
                    [Locals+Names]
                        'self'
                        'job_id'
                        'error'
                        '__assert_armored__'
                    [Constants]
                        '\n        :returns Bool: This type has no constructors.\n        '
                        '__pyarmor_assert_35625__'
                        '__pyarmor_enter_35626__'
                        b'<COAddr>\x05\x00\x00\x1a2\x00\x00\x00\x00\x00\x00\x00\x00\x00\x00\x00\x00\x00\x00\x00'
                        '__pyarmor_exit_35627__'
                        None
                    [Disassembly]
                        0       NOP                             
                        2       NOP                             
                        4       PUSH_NULL                       
                        6       LOAD_CONST                      2: '__pyarmor_enter_35626__'
                        8       LOAD_CONST                      3: b'<COAddr>\x05\x00\x00\x1a2\x00\x00\x00\x00\x00\x00\x00\x00\x00\x00\x00\x00\x00\x00\x00'
                        10      BUILD_TUPLE                     1
                        12      CALL_FUNCTION_EX                0
                        14      POP_TOP                         
                        16      RESUME                          0
                        18      NOP                             
                        20      NOP                             
                        22      NOP                             
                        24      NOP                             
                        26      NOP                             
                        28      LOAD_FAST                       1: job_id
                        30      LOAD_FAST                       0: self
                        32      STORE_ATTR                      0: job_id
                        42      LOAD_FAST                       2: error
                        44      LOAD_FAST                       0: self
                        46      STORE_ATTR                      1: error
                        56      LOAD_CONST                      5: None
                        58      NOP                             
                        60      NOP                             
                        62      NOP                             
                        64      JUMP_FORWARD                    19 (to 104)
                        72      POP_TOP                         
                        74      RETURN_CONST                    5: None
                        76      PUSH_EXC_INFO                   
                        78      PUSH_NULL                       
                        80      LOAD_CONST                      4: '__pyarmor_exit_35627__'
                        82      NOP                             
                        84      LOAD_CONST                      3: b'<COAddr>\x05\x00\x00\x1a2\x00\x00\x00\x00\x00\x00\x00\x00\x00\x00\x00\x00\x00\x00\x00'
                        86      CALL                            1
                        94      POP_TOP                         
                        96      RERAISE                         0
                        98      COPY                            3
                        100     POP_EXCEPT                      
                        102     RERAISE                         1
                        104     PUSH_NULL                       
                        106     LOAD_CONST                      4: '__pyarmor_exit_35627__'
                        108     LOAD_CONST                      3: b'<COAddr>\x05\x00\x00\x1a2\x00\x00\x00\x00\x00\x00\x00\x00\x00\x00\x00\x00\x00\x00\x00'
                        110     BUILD_TUPLE                     1
                        112     CALL_FUNCTION_EX                0
                        114     POP_TOP                         
                        116     RETURN_VALUE                    
                    [Exception Table]
                        28 to 56 -> 76 [0] 
                        76 to 98 -> 98 [1] lasti
                [Code]
                    File Name: <frozen multithon.tl.functions.smsjobs>
                    Object Name: to_dict
                    Qualified Name: FinishJobRequest.to_dict
                    Arg Count: 1
                    Pos Only Arg Count: 0
                    KW Only Arg Count: 0
                    Stack Size: 5
                    Flags: 0x20000003 (CO_OPTIMIZED | CO_NEWLOCALS | CO_PYARMOR_OBFUSCATED)
                    [Names]
                        'job_id'
                        'error'
                    [Locals+Names]
                        'self'
                        '__assert_armored__'
                    [Constants]
                        None
                        '__pyarmor_assert_35628__'
                        '__pyarmor_enter_35629__'
                        b'<COAddr>\x07\x00\x00\x1aT\x00\x00\x00\x00\x00\x00\x00\x00\x00\x00\x00\x00\x00\x00\x00'
                        'FinishJobRequest'   # b'\x81\xc4\x11\x1d:\xe9\xb6\xf8\x14\xf8?\xc5}\xf9\xfd\x96\x1b'
                        (
                            '_'
                            'job_id'
                            'error'
                        )
                        '__pyarmor_exit_35630__'
                    [Disassembly]
                        0       NOP                             
                        2       NOP                             
                        4       PUSH_NULL                       
                        6       LOAD_CONST                      2: '__pyarmor_enter_35629__'
                        8       LOAD_CONST                      3: b'<COAddr>\x07\x00\x00\x1aT\x00\x00\x00\x00\x00\x00\x00\x00\x00\x00\x00\x00\x00\x00\x00'
                        10      BUILD_TUPLE                     1
                        12      CALL_FUNCTION_EX                0
                        14      POP_TOP                         
                        16      RESUME                          0
                        18      NOP                             
                        20      NOP                             
                        22      NOP                             
                        24      NOP                             
                        26      NOP                             
                        28      PUSH_NULL                       
                        30      LOAD_CONST                      1: '__pyarmor_assert_35628__'
                        32      LOAD_CONST                      4: 'FinishJobRequest'   # b'\x81\xc4\x11\x1d:\xe9\xb6\xf8\x14\xf8?\xc5}\xf9\xfd\x96\x1b'
                        34      CALL                            1
                        42      LOAD_FAST                       0: self
                        44      LOAD_ATTR                       0: job_id
                        64      LOAD_FAST                       0: self
                        66      LOAD_ATTR                       2: error
                        86      LOAD_CONST                      5: ('_', 'job_id', 'error')
                        88      BUILD_CONST_KEY_MAP             3
                        90      NOP                             
                        92      NOP                             
                        94      NOP                             
                        96      JUMP_FORWARD                    20 (to 138)
                        98      CALL                            1
                        106     POP_TOP                         
                        108     RETURN_VALUE                    
                        110     PUSH_EXC_INFO                   
                        112     PUSH_NULL                       
                        114     LOAD_CONST                      6: '__pyarmor_exit_35630__'
                        116     NOP                             
                        118     LOAD_CONST                      3: b'<COAddr>\x07\x00\x00\x1aT\x00\x00\x00\x00\x00\x00\x00\x00\x00\x00\x00\x00\x00\x00\x00'
                        120     CALL                            1
                        128     POP_TOP                         
                        130     RERAISE                         0
                        132     COPY                            3
                        134     POP_EXCEPT                      
                        136     RERAISE                         1
                        138     PUSH_NULL                       
                        140     LOAD_CONST                      6: '__pyarmor_exit_35630__'
                        142     LOAD_CONST                      3: b'<COAddr>\x07\x00\x00\x1aT\x00\x00\x00\x00\x00\x00\x00\x00\x00\x00\x00\x00\x00\x00\x00'
                        144     BUILD_TUPLE                     1
                        146     CALL_FUNCTION_EX                0
                        148     POP_TOP                         
                        150     RETURN_VALUE                    
                    [Exception Table]
                        28 to 90 -> 110 [0] 
                        110 to 132 -> 132 [1] lasti
                [Code]
                    File Name: <frozen multithon.tl.functions.smsjobs>
                    Object Name: _bytes
                    Qualified Name: FinishJobRequest._bytes
                    Arg Count: 1
                    Pos Only Arg Count: 0
                    KW Only Arg Count: 0
                    Stack Size: 8
                    Flags: 0x20000003 (CO_OPTIMIZED | CO_NEWLOCALS | CO_PYARMOR_OBFUSCATED)
                    [Names]
                        'join'
                        'struct'
                        'pack'
                        'error'
                        'serialize_bytes'
                        'job_id'
                    [Locals+Names]
                        'self'
                        '__assert_armored__'
                    [Constants]
                        None
                        '__pyarmor_assert_35631__'
                        '__pyarmor_enter_35632__'
                        b'<COAddr>\x07\x00\x00\x1a:\x01\x00\x00\x00\x00\x00\x00\x00\x00\x00\x00\x00\x00\x00\x00'
                        b''
                        b'$\xbf\x1eO'
                        '<I'
                        False
                        0
                        1
                        '__pyarmor_exit_35633__'
                    [Disassembly]
                        0       NOP                             
                        2       NOP                             
                        4       PUSH_NULL                       
                        6       LOAD_CONST                      2: '__pyarmor_enter_35632__'
                        8       LOAD_CONST                      3: b'<COAddr>\x07\x00\x00\x1a:\x01\x00\x00\x00\x00\x00\x00\x00\x00\x00\x00\x00\x00\x00\x00'
                        10      BUILD_TUPLE                     1
                        12      CALL_FUNCTION_EX                0
                        14      POP_TOP                         
                        16      RESUME                          0
                        18      NOP                             
                        20      NOP                             
                        22      NOP                             
                        24      NOP                             
                        26      NOP                             
                        28      LOAD_CONST                      4: b''
                        30      LOAD_ATTR                       1: join
                        50      LOAD_CONST                      5: b'$\xbf\x1eO'
                        52      LOAD_GLOBAL                     3: NULL + struct
                        62      LOAD_ATTR                       4: pack
                        82      LOAD_CONST                      6: '<I'
                        84      LOAD_FAST                       0: self
                        86      LOAD_ATTR                       6: error
                        106     POP_JUMP_IF_NONE                14 (to 136)
                        108     LOAD_FAST                       0: self
                        110     LOAD_ATTR                       6: error
                        130     LOAD_CONST                      7: False
                        132     IS_OP                           0 (is)
                        134     POP_JUMP_IF_FALSE               2 (to 140)
                        136     LOAD_CONST                      8: 0
                        138     JUMP_FORWARD                    1 (to 142)
                        140     LOAD_CONST                      9: 1
                        142     CALL                            2
                        150     LOAD_FAST                       0: self
                        152     LOAD_ATTR                       9: serialize_bytes
                        172     LOAD_FAST                       0: self
                        174     LOAD_ATTR                       10: job_id
                        194     CALL                            1
                        202     LOAD_FAST                       0: self
                        204     LOAD_ATTR                       6: error
                        224     POP_JUMP_IF_NONE                14 (to 254)
                        226     LOAD_FAST                       0: self
                        228     LOAD_ATTR                       6: error
                        248     LOAD_CONST                      7: False
                        250     IS_OP                           0 (is)
                        252     POP_JUMP_IF_FALSE               2 (to 258)
                        254     LOAD_CONST                      4: b''
                        256     JUMP_FORWARD                    26 (to 310)
                        258     LOAD_FAST                       0: self
                        260     LOAD_ATTR                       9: serialize_bytes
                        280     LOAD_FAST                       0: self
                        282     LOAD_ATTR                       6: error
                        302     CALL                            1
                        310     BUILD_TUPLE                     4
                        312     CALL                            1
                        320     NOP                             
                        322     NOP                             
                        324     NOP                             
                        326     JUMP_FORWARD                    20 (to 368)
                        328     CALL                            1
                        336     POP_TOP                         
                        338     RETURN_VALUE                    
                        340     PUSH_EXC_INFO                   
                        342     PUSH_NULL                       
                        344     LOAD_CONST                      10: '__pyarmor_exit_35633__'
                        346     NOP                             
                        348     LOAD_CONST                      3: b'<COAddr>\x07\x00\x00\x1a:\x01\x00\x00\x00\x00\x00\x00\x00\x00\x00\x00\x00\x00\x00\x00'
                        350     CALL                            1
                        358     POP_TOP                         
                        360     RERAISE                         0
                        362     COPY                            3
                        364     POP_EXCEPT                      
                        366     RERAISE                         1
                        368     PUSH_NULL                       
                        370     LOAD_CONST                      10: '__pyarmor_exit_35633__'
                        372     LOAD_CONST                      3: b'<COAddr>\x07\x00\x00\x1a:\x01\x00\x00\x00\x00\x00\x00\x00\x00\x00\x00\x00\x00\x00\x00'
                        374     BUILD_TUPLE                     1
                        376     CALL_FUNCTION_EX                0
                        378     POP_TOP                         
                        380     RETURN_VALUE                    
                    [Exception Table]
                        28 to 320 -> 340 [0] 
                        340 to 362 -> 362 [1] lasti
                [Code]
                    File Name: <frozen multithon.tl.functions.smsjobs>
                    Object Name: from_reader
                    Qualified Name: FinishJobRequest.from_reader
                    Arg Count: 2
                    Pos Only Arg Count: 0
                    KW Only Arg Count: 0
                    Stack Size: 5
                    Flags: 0x20000003 (CO_OPTIMIZED | CO_NEWLOCALS | CO_PYARMOR_OBFUSCATED)
                    [Names]
                        'read_int'
                        'tgread_string'
                    [Locals+Names]
                        'cls'
                        'reader'
                        '__assert_armored__'
                        '_var_var_0'
                        '_var_var_1'
                        '_var_var_2'
                    [Constants]
                        None
                        '__pyarmor_assert_35634__'
                        '__pyarmor_enter_35635__'
                        b'<COAddr>\x07\x00\x00\x1a\x98\x00\x00\x00\x00\x00\x00\x00\x00\x00\x00\x00\x00\x00\x00\x00'
                        1
                        (
                            'job_id'
                            'error'
                        )
                        '__pyarmor_exit_35636__'
                    [Disassembly]
                        0       NOP                             
                        2       NOP                             
                        4       PUSH_NULL                       
                        6       LOAD_CONST                      2: '__pyarmor_enter_35635__'
                        8       LOAD_CONST                      3: b'<COAddr>\x07\x00\x00\x1a\x98\x00\x00\x00\x00\x00\x00\x00\x00\x00\x00\x00\x00\x00\x00\x00'
                        10      BUILD_TUPLE                     1
                        12      CALL_FUNCTION_EX                0
                        14      POP_TOP                         
                        16      RESUME                          0
                        18      NOP                             
                        20      NOP                             
                        22      NOP                             
                        24      NOP                             
                        26      NOP                             
                        28      LOAD_FAST                       1: reader
                        30      LOAD_ATTR                       1: read_int
                        50      CALL                            0
                        58      STORE_FAST                      3: _var_var_0
                        60      LOAD_FAST                       1: reader
                        62      LOAD_ATTR                       3: tgread_string
                        82      CALL                            0
                        90      STORE_FAST                      4: _var_var_1
                        92      LOAD_FAST                       3: _var_var_0
                        94      LOAD_CONST                      4: 1
                        96      BINARY_OP                       1 (&)
                        100     POP_JUMP_IF_FALSE               17 (to 136)
                        102     LOAD_FAST                       1: reader
                        104     LOAD_ATTR                       3: tgread_string
                        124     CALL                            0
                        132     STORE_FAST                      5: _var_var_2
                        134     JUMP_FORWARD                    2 (to 140)
                        136     LOAD_CONST                      0: None
                        138     STORE_FAST                      5: _var_var_2
                        140     PUSH_NULL                       
                        142     LOAD_FAST                       0: cls
                        144     LOAD_FAST                       4: _var_var_1
                        146     LOAD_FAST                       5: _var_var_2
                        148     KW_NAMES                        5: ('job_id', 'error')
                        150     CALL                            2
                        158     NOP                             
                        160     NOP                             
                        162     NOP                             
                        164     JUMP_FORWARD                    20 (to 206)
                        166     CALL                            1
                        174     POP_TOP                         
                        176     RETURN_VALUE                    
                        178     PUSH_EXC_INFO                   
                        180     PUSH_NULL                       
                        182     LOAD_CONST                      6: '__pyarmor_exit_35636__'
                        184     NOP                             
                        186     LOAD_CONST                      3: b'<COAddr>\x07\x00\x00\x1a\x98\x00\x00\x00\x00\x00\x00\x00\x00\x00\x00\x00\x00\x00\x00\x00'
                        188     CALL                            1
                        196     POP_TOP                         
                        198     RERAISE                         0
                        200     COPY                            3
                        202     POP_EXCEPT                      
                        204     RERAISE                         1
                        206     PUSH_NULL                       
                        208     LOAD_CONST                      6: '__pyarmor_exit_35636__'
                        210     LOAD_CONST                      3: b'<COAddr>\x07\x00\x00\x1a\x98\x00\x00\x00\x00\x00\x00\x00\x00\x00\x00\x00\x00\x00\x00\x00'
                        212     BUILD_TUPLE                     1
                        214     CALL_FUNCTION_EX                0
                        216     POP_TOP                         
                        218     RETURN_VALUE                    
                    [Exception Table]
                        28 to 158 -> 178 [0] 
                        178 to 200 -> 200 [1] lasti
                '__pyarmor_exit_35624__'
                (
                    None
                )
            [Disassembly]
                0       NOP                             
                2       LOAD_NAME                       0: __name__
                4       STORE_NAME                      1: __module__
                6       LOAD_CONST                      0: 'FinishJobRequest'
                8       STORE_NAME                      2: __qualname__
                10      NOP                             
                12      PUSH_NULL                       
                14      LOAD_CONST                      2: '__pyarmor_enter_35623__'
                16      LOAD_CONST                      3: b'<COAddr>\x05\x00\x00"R\x00\x00\x00\x00\x00\x00\x00\x00\x00\x00\x00\x00\x00\x00\x00'
                18      BUILD_TUPLE                     1
                20      CALL_FUNCTION_EX                0
                22      POP_TOP                         
                24      RESUME                          0
                26      NOP                             
                28      NOP                             
                30      NOP                             
                32      NOP                             
                34      NOP                             
                36      LOAD_CONST                      4: 1327415076
                38      STORE_NAME                      4: CONSTRUCTOR_ID
                40      LOAD_CONST                      5: 0xF5B399AC
                42      STORE_NAME                      5: SUBCLASS_OF_ID
                44      LOAD_CONST                      14: (None,)
                46      LOAD_CONST                      7: 'job_id'
                48      LOAD_NAME                       6: str
                50      LOAD_CONST                      8: 'error'
                52      LOAD_NAME                       7: Optional
                54      LOAD_NAME                       6: str
                56      BINARY_SUBSCR                   
                60      BUILD_TUPLE                     4
                62      LOAD_CONST                      9: <CODE> __init__
                64      MAKE_FUNCTION                   5
                66      STORE_NAME                      8: __init__
                68      LOAD_CONST                      10: <CODE> to_dict
                70      MAKE_FUNCTION                   0
                72      STORE_NAME                      9: to_dict
                74      LOAD_CONST                      11: <CODE> _bytes
                76      MAKE_FUNCTION                   0
                78      STORE_NAME                      10: _bytes
                80      LOAD_NAME                       11: classmethod
                82      LOAD_CONST                      12: <CODE> from_reader
                84      MAKE_FUNCTION                   0
                86      CALL                            0
                94      STORE_NAME                      12: from_reader
                96      LOAD_CONST                      6: None
                98      NOP                             
                100     NOP                             
                102     NOP                             
                104     JUMP_FORWARD                    19 (to 144)
                112     POP_TOP                         
                114     RETURN_CONST                    6: None
                116     PUSH_EXC_INFO                   
                118     PUSH_NULL                       
                120     LOAD_CONST                      13: '__pyarmor_exit_35624__'
                122     NOP                             
                124     LOAD_CONST                      3: b'<COAddr>\x05\x00\x00"R\x00\x00\x00\x00\x00\x00\x00\x00\x00\x00\x00\x00\x00\x00\x00'
                126     CALL                            1
                134     POP_TOP                         
                136     RERAISE                         0
                138     COPY                            3
                140     POP_EXCEPT                      
                142     RERAISE                         1
                144     PUSH_NULL                       
                146     LOAD_CONST                      13: '__pyarmor_exit_35624__'
                148     LOAD_CONST                      3: b'<COAddr>\x05\x00\x00"R\x00\x00\x00\x00\x00\x00\x00\x00\x00\x00\x00\x00\x00\x00\x00'
                150     BUILD_TUPLE                     1
                152     CALL_FUNCTION_EX                0
                154     POP_TOP                         
                156     RETURN_VALUE                    
            [Exception Table]
                36 to 96 -> 116 [0] 
                116 to 138 -> 138 [1] lasti
        'FinishJobRequest'
        [Code]
            File Name: <frozen multithon.tl.functions.smsjobs>
            Object Name: GetSmsJobRequest
            Qualified Name: GetSmsJobRequest
            Arg Count: 0
            Pos Only Arg Count: 0
            KW Only Arg Count: 0
            Stack Size: 5
            Flags: 0x20000000 (CO_PYARMOR_OBFUSCATED)
            [Names]
                '__name__'
                '__module__'
                '__qualname__'
                '__assert_armored__'
                'CONSTRUCTOR_ID'
                'SUBCLASS_OF_ID'
                'str'
                '__init__'
                'to_dict'
                '_bytes'
                'classmethod'
                'from_reader'
            [Locals+Names]
            [Constants]
                'GetSmsJobRequest'
                '__pyarmor_assert_35637__'
                '__pyarmor_enter_35638__'
                b'<COAddr>\x05\x00\x00"F\x00\x00\x00\x00\x00\x00\x00\x00\x00\x00\x00\x00\x00\x00\x00'
                2005766191
                522459262
                'job_id'
                [Code]
                    File Name: <frozen multithon.tl.functions.smsjobs>
                    Object Name: __init__
                    Qualified Name: GetSmsJobRequest.__init__
                    Arg Count: 2
                    Pos Only Arg Count: 0
                    KW Only Arg Count: 0
                    Stack Size: 5
                    Flags: 0x20000003 (CO_OPTIMIZED | CO_NEWLOCALS | CO_PYARMOR_OBFUSCATED)
                    [Names]
                        'job_id'
                    [Locals+Names]
                        'self'
                        'job_id'
                        '__assert_armored__'
                    [Constants]
                        '\n        :returns SmsJob: Instance of SmsJob.\n        '
                        '__pyarmor_assert_35640__'
                        '__pyarmor_enter_35641__'
                        b'<COAddr>\x05\x00\x00\x1a$\x00\x00\x00\x00\x00\x00\x00\x00\x00\x00\x00\x00\x00\x00\x00'
                        '__pyarmor_exit_35642__'
                        None
                    [Disassembly]
                        0       NOP                             
                        2       NOP                             
                        4       PUSH_NULL                       
                        6       LOAD_CONST                      2: '__pyarmor_enter_35641__'
                        8       LOAD_CONST                      3: b'<COAddr>\x05\x00\x00\x1a$\x00\x00\x00\x00\x00\x00\x00\x00\x00\x00\x00\x00\x00\x00\x00'
                        10      BUILD_TUPLE                     1
                        12      CALL_FUNCTION_EX                0
                        14      POP_TOP                         
                        16      RESUME                          0
                        18      NOP                             
                        20      NOP                             
                        22      NOP                             
                        24      NOP                             
                        26      NOP                             
                        28      LOAD_FAST                       1: job_id
                        30      LOAD_FAST                       0: self
                        32      STORE_ATTR                      0: job_id
                        42      LOAD_CONST                      5: None
                        44      NOP                             
                        46      NOP                             
                        48      NOP                             
                        50      JUMP_FORWARD                    19 (to 90)
                        58      POP_TOP                         
                        60      RETURN_CONST                    5: None
                        62      PUSH_EXC_INFO                   
                        64      PUSH_NULL                       
                        66      LOAD_CONST                      4: '__pyarmor_exit_35642__'
                        68      NOP                             
                        70      LOAD_CONST                      3: b'<COAddr>\x05\x00\x00\x1a$\x00\x00\x00\x00\x00\x00\x00\x00\x00\x00\x00\x00\x00\x00\x00'
                        72      CALL                            1
                        80      POP_TOP                         
                        82      RERAISE                         0
                        84      COPY                            3
                        86      POP_EXCEPT                      
                        88      RERAISE                         1
                        90      PUSH_NULL                       
                        92      LOAD_CONST                      4: '__pyarmor_exit_35642__'
                        94      LOAD_CONST                      3: b'<COAddr>\x05\x00\x00\x1a$\x00\x00\x00\x00\x00\x00\x00\x00\x00\x00\x00\x00\x00\x00\x00'
                        96      BUILD_TUPLE                     1
                        98      CALL_FUNCTION_EX                0
                        100     POP_TOP                         
                        102     RETURN_VALUE                    
                    [Exception Table]
                        28 to 42 -> 62 [0] 
                        62 to 84 -> 84 [1] lasti
                [Code]
                    File Name: <frozen multithon.tl.functions.smsjobs>
                    Object Name: to_dict
                    Qualified Name: GetSmsJobRequest.to_dict
                    Arg Count: 1
                    Pos Only Arg Count: 0
                    KW Only Arg Count: 0
                    Stack Size: 5
                    Flags: 0x20000003 (CO_OPTIMIZED | CO_NEWLOCALS | CO_PYARMOR_OBFUSCATED)
                    [Names]
                        'job_id'
                    [Locals+Names]
                        'self'
                        '__assert_armored__'
                    [Constants]
                        None
                        '__pyarmor_assert_35643__'
                        '__pyarmor_enter_35644__'
                        b'<COAddr>\x07\x00\x00\x1a>\x00\x00\x00\x00\x00\x00\x00\x00\x00\x00\x00\x00\x00\x00\x00'
                        'GetSmsJobRequest'   # b'\x81\xc5\x1d\x07\x00\xf7\xad\xf8\x14\xf8?\xc5}\xf9\xfd\x96\x1b'
                        (
                            '_'
                            'job_id'
                        )
                        '__pyarmor_exit_35645__'
                    [Disassembly]
                        0       NOP                             
                        2       NOP                             
                        4       PUSH_NULL                       
                        6       LOAD_CONST                      2: '__pyarmor_enter_35644__'
                        8       LOAD_CONST                      3: b'<COAddr>\x07\x00\x00\x1a>\x00\x00\x00\x00\x00\x00\x00\x00\x00\x00\x00\x00\x00\x00\x00'
                        10      BUILD_TUPLE                     1
                        12      CALL_FUNCTION_EX                0
                        14      POP_TOP                         
                        16      RESUME                          0
                        18      NOP                             
                        20      NOP                             
                        22      NOP                             
                        24      NOP                             
                        26      NOP                             
                        28      PUSH_NULL                       
                        30      LOAD_CONST                      1: '__pyarmor_assert_35643__'
                        32      LOAD_CONST                      4: 'GetSmsJobRequest'   # b'\x81\xc5\x1d\x07\x00\xf7\xad\xf8\x14\xf8?\xc5}\xf9\xfd\x96\x1b'
                        34      CALL                            1
                        42      LOAD_FAST                       0: self
                        44      LOAD_ATTR                       0: job_id
                        64      LOAD_CONST                      5: ('_', 'job_id')
                        66      BUILD_CONST_KEY_MAP             2
                        68      NOP                             
                        70      NOP                             
                        72      NOP                             
                        74      JUMP_FORWARD                    20 (to 116)
                        76      CALL                            1
                        84      POP_TOP                         
                        86      RETURN_VALUE                    
                        88      PUSH_EXC_INFO                   
                        90      PUSH_NULL                       
                        92      LOAD_CONST                      6: '__pyarmor_exit_35645__'
                        94      NOP                             
                        96      LOAD_CONST                      3: b'<COAddr>\x07\x00\x00\x1a>\x00\x00\x00\x00\x00\x00\x00\x00\x00\x00\x00\x00\x00\x00\x00'
                        98      CALL                            1
                        106     POP_TOP                         
                        108     RERAISE                         0
                        110     COPY                            3
                        112     POP_EXCEPT                      
                        114     RERAISE                         1
                        116     PUSH_NULL                       
                        118     LOAD_CONST                      6: '__pyarmor_exit_35645__'
                        120     LOAD_CONST                      3: b'<COAddr>\x07\x00\x00\x1a>\x00\x00\x00\x00\x00\x00\x00\x00\x00\x00\x00\x00\x00\x00\x00'
                        122     BUILD_TUPLE                     1
                        124     CALL_FUNCTION_EX                0
                        126     POP_TOP                         
                        128     RETURN_VALUE                    
                    [Exception Table]
                        28 to 68 -> 88 [0] 
                        88 to 110 -> 110 [1] lasti
                [Code]
                    File Name: <frozen multithon.tl.functions.smsjobs>
                    Object Name: _bytes
                    Qualified Name: GetSmsJobRequest._bytes
                    Arg Count: 1
                    Pos Only Arg Count: 0
                    KW Only Arg Count: 0
                    Stack Size: 6
                    Flags: 0x20000003 (CO_OPTIMIZED | CO_NEWLOCALS | CO_PYARMOR_OBFUSCATED)
                    [Names]
                        'join'
                        'serialize_bytes'
                        'job_id'
                    [Locals+Names]
                        'self'
                        '__assert_armored__'
                    [Constants]
                        None
                        '__pyarmor_assert_35646__'
                        '__pyarmor_enter_35647__'
                        b'<COAddr>\x05\x00\x00\x1al\x00\x00\x00\x00\x00\x00\x00\x00\x00\x00\x00\x00\x00\x00\x00'
                        b''
                        b'/\x90\x8dw'
                        '__pyarmor_exit_35648__'
                    [Disassembly]
                        0       NOP                             
                        2       NOP                             
                        4       PUSH_NULL                       
                        6       LOAD_CONST                      2: '__pyarmor_enter_35647__'
                        8       LOAD_CONST                      3: b'<COAddr>\x05\x00\x00\x1al\x00\x00\x00\x00\x00\x00\x00\x00\x00\x00\x00\x00\x00\x00\x00'
                        10      BUILD_TUPLE                     1
                        12      CALL_FUNCTION_EX                0
                        14      POP_TOP                         
                        16      RESUME                          0
                        18      NOP                             
                        20      NOP                             
                        22      NOP                             
                        24      NOP                             
                        26      NOP                             
                        28      LOAD_CONST                      4: b''
                        30      LOAD_ATTR                       1: join
                        50      LOAD_CONST                      5: b'/\x90\x8dw'
                        52      LOAD_FAST                       0: self
                        54      LOAD_ATTR                       3: serialize_bytes
                        74      LOAD_FAST                       0: self
                        76      LOAD_ATTR                       4: job_id
                        96      CALL                            1
                        104     BUILD_TUPLE                     2
                        106     CALL                            1
                        114     NOP                             
                        116     NOP                             
                        118     NOP                             
                        120     JUMP_FORWARD                    20 (to 162)
                        122     CALL                            1
                        130     POP_TOP                         
                        132     RETURN_VALUE                    
                        134     PUSH_EXC_INFO                   
                        136     PUSH_NULL                       
                        138     LOAD_CONST                      6: '__pyarmor_exit_35648__'
                        140     NOP                             
                        142     LOAD_CONST                      3: b'<COAddr>\x05\x00\x00\x1al\x00\x00\x00\x00\x00\x00\x00\x00\x00\x00\x00\x00\x00\x00\x00'
                        144     CALL                            1
                        152     POP_TOP                         
                        154     RERAISE                         0
                        156     COPY                            3
                        158     POP_EXCEPT                      
                        160     RERAISE                         1
                        162     PUSH_NULL                       
                        164     LOAD_CONST                      6: '__pyarmor_exit_35648__'
                        166     LOAD_CONST                      3: b'<COAddr>\x05\x00\x00\x1al\x00\x00\x00\x00\x00\x00\x00\x00\x00\x00\x00\x00\x00\x00\x00'
                        168     BUILD_TUPLE                     1
                        170     CALL_FUNCTION_EX                0
                        172     POP_TOP                         
                        174     RETURN_VALUE                    
                    [Exception Table]
                        28 to 114 -> 134 [0] 
                        134 to 156 -> 156 [1] lasti
                [Code]
                    File Name: <frozen multithon.tl.functions.smsjobs>
                    Object Name: from_reader
                    Qualified Name: GetSmsJobRequest.from_reader
                    Arg Count: 2
                    Pos Only Arg Count: 0
                    KW Only Arg Count: 0
                    Stack Size: 5
                    Flags: 0x20000003 (CO_OPTIMIZED | CO_NEWLOCALS | CO_PYARMOR_OBFUSCATED)
                    [Names]
                        'tgread_string'
                    [Locals+Names]
                        'cls'
                        'reader'
                        '__assert_armored__'
                        '_var_var_1'
                    [Constants]
                        None
                        '__pyarmor_assert_35649__'
                        '__pyarmor_enter_35650__'
                        b'<COAddr>\x07\x00\x00\x1aF\x00\x00\x00\x00\x00\x00\x00\x00\x00\x00\x00\x00\x00\x00\x00'
                        (
                            'job_id'
                        )
                        '__pyarmor_exit_35651__'
                    [Disassembly]
                        0       NOP                             
                        2       NOP                             
                        4       PUSH_NULL                       
                        6       LOAD_CONST                      2: '__pyarmor_enter_35650__'
                        8       LOAD_CONST                      3: b'<COAddr>\x07\x00\x00\x1aF\x00\x00\x00\x00\x00\x00\x00\x00\x00\x00\x00\x00\x00\x00\x00'
                        10      BUILD_TUPLE                     1
                        12      CALL_FUNCTION_EX                0
                        14      POP_TOP                         
                        16      RESUME                          0
                        18      NOP                             
                        20      NOP                             
                        22      NOP                             
                        24      NOP                             
                        26      NOP                             
                        28      LOAD_FAST                       1: reader
                        30      LOAD_ATTR                       1: tgread_string
                        50      CALL                            0
                        58      STORE_FAST                      3: _var_var_1
                        60      PUSH_NULL                       
                        62      LOAD_FAST                       0: cls
                        64      LOAD_FAST                       3: _var_var_1
                        66      KW_NAMES                        4: ('job_id',)
                        68      CALL                            1
                        76      NOP                             
                        78      NOP                             
                        80      NOP                             
                        82      JUMP_FORWARD                    20 (to 124)
                        84      CALL                            1
                        92      POP_TOP                         
                        94      RETURN_VALUE                    
                        96      PUSH_EXC_INFO                   
                        98      PUSH_NULL                       
                        100     LOAD_CONST                      5: '__pyarmor_exit_35651__'
                        102     NOP                             
                        104     LOAD_CONST                      3: b'<COAddr>\x07\x00\x00\x1aF\x00\x00\x00\x00\x00\x00\x00\x00\x00\x00\x00\x00\x00\x00\x00'
                        106     CALL                            1
                        114     POP_TOP                         
                        116     RERAISE                         0
                        118     COPY                            3
                        120     POP_EXCEPT                      
                        122     RERAISE                         1
                        124     PUSH_NULL                       
                        126     LOAD_CONST                      5: '__pyarmor_exit_35651__'
                        128     LOAD_CONST                      3: b'<COAddr>\x07\x00\x00\x1aF\x00\x00\x00\x00\x00\x00\x00\x00\x00\x00\x00\x00\x00\x00\x00'
                        130     BUILD_TUPLE                     1
                        132     CALL_FUNCTION_EX                0
                        134     POP_TOP                         
                        136     RETURN_VALUE                    
                    [Exception Table]
                        28 to 76 -> 96 [0] 
                        96 to 118 -> 118 [1] lasti
                '__pyarmor_exit_35639__'
                None
            [Disassembly]
                0       NOP                             
                2       LOAD_NAME                       0: __name__
                4       STORE_NAME                      1: __module__
                6       LOAD_CONST                      0: 'GetSmsJobRequest'
                8       STORE_NAME                      2: __qualname__
                10      NOP                             
                12      PUSH_NULL                       
                14      LOAD_CONST                      2: '__pyarmor_enter_35638__'
                16      LOAD_CONST                      3: b'<COAddr>\x05\x00\x00"F\x00\x00\x00\x00\x00\x00\x00\x00\x00\x00\x00\x00\x00\x00\x00'
                18      BUILD_TUPLE                     1
                20      CALL_FUNCTION_EX                0
                22      POP_TOP                         
                24      RESUME                          0
                26      NOP                             
                28      NOP                             
                30      NOP                             
                32      NOP                             
                34      NOP                             
                36      LOAD_CONST                      4: 2005766191
                38      STORE_NAME                      4: CONSTRUCTOR_ID
                40      LOAD_CONST                      5: 522459262
                42      STORE_NAME                      5: SUBCLASS_OF_ID
                44      LOAD_CONST                      6: 'job_id'
                46      LOAD_NAME                       6: str
                48      BUILD_TUPLE                     2
                50      LOAD_CONST                      7: <CODE> __init__
                52      MAKE_FUNCTION                   4
                54      STORE_NAME                      7: __init__
                56      LOAD_CONST                      8: <CODE> to_dict
                58      MAKE_FUNCTION                   0
                60      STORE_NAME                      8: to_dict
                62      LOAD_CONST                      9: <CODE> _bytes
                64      MAKE_FUNCTION                   0
                66      STORE_NAME                      9: _bytes
                68      LOAD_NAME                       10: classmethod
                70      LOAD_CONST                      10: <CODE> from_reader
                72      MAKE_FUNCTION                   0
                74      CALL                            0
                82      STORE_NAME                      11: from_reader
                84      LOAD_CONST                      12: None
                86      NOP                             
                88      NOP                             
                90      NOP                             
                92      JUMP_FORWARD                    19 (to 132)
                100     POP_TOP                         
                102     RETURN_CONST                    12: None
                104     PUSH_EXC_INFO                   
                106     PUSH_NULL                       
                108     LOAD_CONST                      11: '__pyarmor_exit_35639__'
                110     NOP                             
                112     LOAD_CONST                      3: b'<COAddr>\x05\x00\x00"F\x00\x00\x00\x00\x00\x00\x00\x00\x00\x00\x00\x00\x00\x00\x00'
                114     CALL                            1
                122     POP_TOP                         
                124     RERAISE                         0
                126     COPY                            3
                128     POP_EXCEPT                      
                130     RERAISE                         1
                132     PUSH_NULL                       
                134     LOAD_CONST                      11: '__pyarmor_exit_35639__'
                136     LOAD_CONST                      3: b'<COAddr>\x05\x00\x00"F\x00\x00\x00\x00\x00\x00\x00\x00\x00\x00\x00\x00\x00\x00\x00'
                138     BUILD_TUPLE                     1
                140     CALL_FUNCTION_EX                0
                142     POP_TOP                         
                144     RETURN_VALUE                    
            [Exception Table]
                36 to 84 -> 104 [0] 
                104 to 126 -> 126 [1] lasti
        'GetSmsJobRequest'
        [Code]
            File Name: <frozen multithon.tl.functions.smsjobs>
            Object Name: GetStatusRequest
            Qualified Name: GetStatusRequest
            Arg Count: 0
            Pos Only Arg Count: 0
            KW Only Arg Count: 0
            Stack Size: 5
            Flags: 0x20000000 (CO_PYARMOR_OBFUSCATED)
            [Names]
                '__name__'
                '__module__'
                '__qualname__'
                '__assert_armored__'
                'CONSTRUCTOR_ID'
                'SUBCLASS_OF_ID'
                'to_dict'
                '_bytes'
                'classmethod'
                'from_reader'
            [Locals+Names]
            [Constants]
                'GetStatusRequest'
                '__pyarmor_assert_35652__'
                '__pyarmor_enter_35653__'
                b'<COAddr>\x07\x00\x00":\x00\x00\x00\x00\x00\x00\x00\x00\x00\x00\x00\x00\x00\x00\x00'
                279353576
                0xCD8F2B25
                [Code]
                    File Name: <frozen multithon.tl.functions.smsjobs>
                    Object Name: to_dict
                    Qualified Name: GetStatusRequest.to_dict
                    Arg Count: 1
                    Pos Only Arg Count: 0
                    KW Only Arg Count: 0
                    Stack Size: 5
                    Flags: 0x20000003 (CO_OPTIMIZED | CO_NEWLOCALS | CO_PYARMOR_OBFUSCATED)
                    [Names]
                    [Locals+Names]
                        'self'
                        '__assert_armored__'
                    [Constants]
                        None
                        '__pyarmor_assert_35655__'
                        '__pyarmor_enter_35656__'
                        b'<COAddr>\x05\x00\x00\x1a(\x00\x00\x00\x00\x00\x00\x00\x00\x00\x00\x00\x00\x00\x00\x00'
                        '_'
                        'GetStatusRequest'   # b'\x81\xc5\x1d\x07\x00\xee\xbf\xc6\x0e\xe9?\xc5}\xf9\xfd\x96\x1b'
                        '__pyarmor_exit_35657__'
                    [Disassembly]
                        0       NOP                             
                        2       NOP                             
                        4       PUSH_NULL                       
                        6       LOAD_CONST                      2: '__pyarmor_enter_35656__'
                        8       LOAD_CONST                      3: b'<COAddr>\x05\x00\x00\x1a(\x00\x00\x00\x00\x00\x00\x00\x00\x00\x00\x00\x00\x00\x00\x00'
                        10      BUILD_TUPLE                     1
                        12      CALL_FUNCTION_EX                0
                        14      POP_TOP                         
                        16      RESUME                          0
                        18      NOP                             
                        20      NOP                             
                        22      NOP                             
                        24      NOP                             
                        26      NOP                             
                        28      LOAD_CONST                      4: '_'
                        30      PUSH_NULL                       
                        32      LOAD_CONST                      1: '__pyarmor_assert_35655__'
                        34      LOAD_CONST                      5: 'GetStatusRequest'   # b'\x81\xc5\x1d\x07\x00\xee\xbf\xc6\x0e\xe9?\xc5}\xf9\xfd\x96\x1b'
                        36      CALL                            1
                        44      BUILD_MAP                       1
                        46      NOP                             
                        48      NOP                             
                        50      NOP                             
                        52      JUMP_FORWARD                    20 (to 94)
                        54      CALL                            1
                        62      POP_TOP                         
                        64      RETURN_VALUE                    
                        66      PUSH_EXC_INFO                   
                        68      PUSH_NULL                       
                        70      LOAD_CONST                      6: '__pyarmor_exit_35657__'
                        72      NOP                             
                        74      LOAD_CONST                      3: b'<COAddr>\x05\x00\x00\x1a(\x00\x00\x00\x00\x00\x00\x00\x00\x00\x00\x00\x00\x00\x00\x00'
                        76      CALL                            1
                        84      POP_TOP                         
                        86      RERAISE                         0
                        88      COPY                            3
                        90      POP_EXCEPT                      
                        92      RERAISE                         1
                        94      PUSH_NULL                       
                        96      LOAD_CONST                      6: '__pyarmor_exit_35657__'
                        98      LOAD_CONST                      3: b'<COAddr>\x05\x00\x00\x1a(\x00\x00\x00\x00\x00\x00\x00\x00\x00\x00\x00\x00\x00\x00\x00'
                        100     BUILD_TUPLE                     1
                        102     CALL_FUNCTION_EX                0
                        104     POP_TOP                         
                        106     RETURN_VALUE                    
                    [Exception Table]
                        28 to 46 -> 66 [0] 
                        66 to 88 -> 88 [1] lasti
                [Code]
                    File Name: <frozen multithon.tl.functions.smsjobs>
                    Object Name: _bytes
                    Qualified Name: GetStatusRequest._bytes
                    Arg Count: 1
                    Pos Only Arg Count: 0
                    KW Only Arg Count: 0
                    Stack Size: 5
                    Flags: 0x20000003 (CO_OPTIMIZED | CO_NEWLOCALS | CO_PYARMOR_OBFUSCATED)
                    [Names]
                        'join'
                    [Locals+Names]
                        'self'
                        '__assert_armored__'
                    [Constants]
                        None
                        '__pyarmor_assert_35658__'
                        '__pyarmor_enter_35659__'
                        b'<COAddr>\x07\x00\x00\x1a6\x00\x00\x00\x00\x00\x00\x00\x00\x00\x00\x00\x00\x00\x00\x00'
                        b''
                        (
                            b'\xe8\x98\xa6\x10'
                        )
                        '__pyarmor_exit_35660__'
                    [Disassembly]
                        0       NOP                             
                        2       NOP                             
                        4       PUSH_NULL                       
                        6       LOAD_CONST                      2: '__pyarmor_enter_35659__'
                        8       LOAD_CONST                      3: b'<COAddr>\x07\x00\x00\x1a6\x00\x00\x00\x00\x00\x00\x00\x00\x00\x00\x00\x00\x00\x00\x00'
                        10      BUILD_TUPLE                     1
                        12      CALL_FUNCTION_EX                0
                        14      POP_TOP                         
                        16      RESUME                          0
                        18      NOP                             
                        20      NOP                             
                        22      NOP                             
                        24      NOP                             
                        26      NOP                             
                        28      LOAD_CONST                      4: b''
                        30      LOAD_ATTR                       1: join
                        50      LOAD_CONST                      5: (b'\xe8\x98\xa6\x10',)
                        52      CALL                            1
                        60      NOP                             
                        62      NOP                             
                        64      NOP                             
                        66      JUMP_FORWARD                    20 (to 108)
                        68      CALL                            1
                        76      POP_TOP                         
                        78      RETURN_VALUE                    
                        80      PUSH_EXC_INFO                   
                        82      PUSH_NULL                       
                        84      LOAD_CONST                      6: '__pyarmor_exit_35660__'
                        86      NOP                             
                        88      LOAD_CONST                      3: b'<COAddr>\x07\x00\x00\x1a6\x00\x00\x00\x00\x00\x00\x00\x00\x00\x00\x00\x00\x00\x00\x00'
                        90      CALL                            1
                        98      POP_TOP                         
                        100     RERAISE                         0
                        102     COPY                            3
                        104     POP_EXCEPT                      
                        106     RERAISE                         1
                        108     PUSH_NULL                       
                        110     LOAD_CONST                      6: '__pyarmor_exit_35660__'
                        112     LOAD_CONST                      3: b'<COAddr>\x07\x00\x00\x1a6\x00\x00\x00\x00\x00\x00\x00\x00\x00\x00\x00\x00\x00\x00\x00'
                        114     BUILD_TUPLE                     1
                        116     CALL_FUNCTION_EX                0
                        118     POP_TOP                         
                        120     RETURN_VALUE                    
                    [Exception Table]
                        28 to 60 -> 80 [0] 
                        80 to 102 -> 102 [1] lasti
                [Code]
                    File Name: <frozen multithon.tl.functions.smsjobs>
                    Object Name: from_reader
                    Qualified Name: GetStatusRequest.from_reader
                    Arg Count: 2
                    Pos Only Arg Count: 0
                    KW Only Arg Count: 0
                    Stack Size: 5
                    Flags: 0x20000003 (CO_OPTIMIZED | CO_NEWLOCALS | CO_PYARMOR_OBFUSCATED)
                    [Names]
                    [Locals+Names]
                        'cls'
                        'reader'
                        '__assert_armored__'
                    [Constants]
                        None
                        '__pyarmor_assert_35661__'
                        '__pyarmor_enter_35662__'
                        b'<COAddr>\x05\x00\x00\x1a"\x00\x00\x00\x00\x00\x00\x00\x00\x00\x00\x00\x00\x00\x00\x00'
                        '__pyarmor_exit_35663__'
                    [Disassembly]
                        0       NOP                             
                        2       NOP                             
                        4       PUSH_NULL                       
                        6       LOAD_CONST                      2: '__pyarmor_enter_35662__'
                        8       LOAD_CONST                      3: b'<COAddr>\x05\x00\x00\x1a"\x00\x00\x00\x00\x00\x00\x00\x00\x00\x00\x00\x00\x00\x00\x00'
                        10      BUILD_TUPLE                     1
                        12      CALL_FUNCTION_EX                0
                        14      POP_TOP                         
                        16      RESUME                          0
                        18      NOP                             
                        20      NOP                             
                        22      NOP                             
                        24      NOP                             
                        26      NOP                             
                        28      PUSH_NULL                       
                        30      LOAD_FAST                       0: cls
                        32      CALL                            0
                        40      NOP                             
                        42      NOP                             
                        44      NOP                             
                        46      JUMP_FORWARD                    20 (to 88)
                        48      CALL                            1
                        56      POP_TOP                         
                        58      RETURN_VALUE                    
                        60      PUSH_EXC_INFO                   
                        62      PUSH_NULL                       
                        64      LOAD_CONST                      4: '__pyarmor_exit_35663__'
                        66      NOP                             
                        68      LOAD_CONST                      3: b'<COAddr>\x05\x00\x00\x1a"\x00\x00\x00\x00\x00\x00\x00\x00\x00\x00\x00\x00\x00\x00\x00'
                        70      CALL                            1
                        78      POP_TOP                         
                        80      RERAISE                         0
                        82      COPY                            3
                        84      POP_EXCEPT                      
                        86      RERAISE                         1
                        88      PUSH_NULL                       
                        90      LOAD_CONST                      4: '__pyarmor_exit_35663__'
                        92      LOAD_CONST                      3: b'<COAddr>\x05\x00\x00\x1a"\x00\x00\x00\x00\x00\x00\x00\x00\x00\x00\x00\x00\x00\x00\x00'
                        94      BUILD_TUPLE                     1
                        96      CALL_FUNCTION_EX                0
                        98      POP_TOP                         
                        100     RETURN_VALUE                    
                    [Exception Table]
                        28 to 40 -> 60 [0] 
                        60 to 82 -> 82 [1] lasti
                '__pyarmor_exit_35654__'
                None
            [Disassembly]
                0       NOP                             
                2       LOAD_NAME                       0: __name__
                4       STORE_NAME                      1: __module__
                6       LOAD_CONST                      0: 'GetStatusRequest'
                8       STORE_NAME                      2: __qualname__
                10      NOP                             
                12      PUSH_NULL                       
                14      LOAD_CONST                      2: '__pyarmor_enter_35653__'
                16      LOAD_CONST                      3: b'<COAddr>\x07\x00\x00":\x00\x00\x00\x00\x00\x00\x00\x00\x00\x00\x00\x00\x00\x00\x00'
                18      BUILD_TUPLE                     1
                20      CALL_FUNCTION_EX                0
                22      POP_TOP                         
                24      RESUME                          0
                26      NOP                             
                28      NOP                             
                30      NOP                             
                32      NOP                             
                34      NOP                             
                36      LOAD_CONST                      4: 279353576
                38      STORE_NAME                      4: CONSTRUCTOR_ID
                40      LOAD_CONST                      5: 0xCD8F2B25
                42      STORE_NAME                      5: SUBCLASS_OF_ID
                44      LOAD_CONST                      6: <CODE> to_dict
                46      MAKE_FUNCTION                   0
                48      STORE_NAME                      6: to_dict
                50      LOAD_CONST                      7: <CODE> _bytes
                52      MAKE_FUNCTION                   0
                54      STORE_NAME                      7: _bytes
                56      LOAD_NAME                       8: classmethod
                58      LOAD_CONST                      8: <CODE> from_reader
                60      MAKE_FUNCTION                   0
                62      CALL                            0
                70      STORE_NAME                      9: from_reader
                72      LOAD_CONST                      10: None
                74      NOP                             
                76      NOP                             
                78      NOP                             
                80      JUMP_FORWARD                    19 (to 120)
                88      POP_TOP                         
                90      RETURN_CONST                    10: None
                92      PUSH_EXC_INFO                   
                94      PUSH_NULL                       
                96      LOAD_CONST                      9: '__pyarmor_exit_35654__'
                98      NOP                             
                100     LOAD_CONST                      3: b'<COAddr>\x07\x00\x00":\x00\x00\x00\x00\x00\x00\x00\x00\x00\x00\x00\x00\x00\x00\x00'
                102     CALL                            1
                110     POP_TOP                         
                112     RERAISE                         0
                114     COPY                            3
                116     POP_EXCEPT                      
                118     RERAISE                         1
                120     PUSH_NULL                       
                122     LOAD_CONST                      9: '__pyarmor_exit_35654__'
                124     LOAD_CONST                      3: b'<COAddr>\x07\x00\x00":\x00\x00\x00\x00\x00\x00\x00\x00\x00\x00\x00\x00\x00\x00\x00'
                126     BUILD_TUPLE                     1
                128     CALL_FUNCTION_EX                0
                130     POP_TOP                         
                132     RETURN_VALUE                    
            [Exception Table]
                36 to 72 -> 92 [0] 
                92 to 114 -> 114 [1] lasti
        'GetStatusRequest'
        [Code]
            File Name: <frozen multithon.tl.functions.smsjobs>
            Object Name: IsEligibleToJoinRequest
            Qualified Name: IsEligibleToJoinRequest
            Arg Count: 0
            Pos Only Arg Count: 0
            KW Only Arg Count: 0
            Stack Size: 5
            Flags: 0x20000000 (CO_PYARMOR_OBFUSCATED)
            [Names]
                '__name__'
                '__module__'
                '__qualname__'
                '__assert_armored__'
                'CONSTRUCTOR_ID'
                'SUBCLASS_OF_ID'
                'to_dict'
                '_bytes'
                'classmethod'
                'from_reader'
            [Locals+Names]
            [Constants]
                'IsEligibleToJoinRequest'
                '__pyarmor_assert_35664__'
                '__pyarmor_enter_35665__'
                b'<COAddr>\x05\x00\x00":\x00\x00\x00\x00\x00\x00\x00\x00\x00\x00\x00\x00\x00\x00\x00'
                249313744
                1589076134
                [Code]
                    File Name: <frozen multithon.tl.functions.smsjobs>
                    Object Name: to_dict
                    Qualified Name: IsEligibleToJoinRequest.to_dict
                    Arg Count: 1
                    Pos Only Arg Count: 0
                    KW Only Arg Count: 0
                    Stack Size: 5
                    Flags: 0x20000003 (CO_OPTIMIZED | CO_NEWLOCALS | CO_PYARMOR_OBFUSCATED)
                    [Names]
                    [Locals+Names]
                        'self'
                        '__assert_armored__'
                    [Constants]
                        None
                        '__pyarmor_assert_35667__'
                        '__pyarmor_enter_35668__'
                        b'<COAddr>\x05\x00\x00\x1a(\x00\x00\x00\x00\x00\x00\x00\x00\x00\x00\x00\x00\x00\x00\x00'
                        '_'
                        'IsEligibleToJoinRequest'   # b'\x81\xcb\x0b6?\xf3\xb9\xdb\x19\xf6\x08\xf4c\xc6\xf7\x8c\x01o\xbe\xb6\xbf\xce]\xd8'
                        '__pyarmor_exit_35669__'
                    [Disassembly]
                        0       NOP                             
                        2       NOP                             
                        4       PUSH_NULL                       
                        6       LOAD_CONST                      2: '__pyarmor_enter_35668__'
                        8       LOAD_CONST                      3: b'<COAddr>\x05\x00\x00\x1a(\x00\x00\x00\x00\x00\x00\x00\x00\x00\x00\x00\x00\x00\x00\x00'
                        10      BUILD_TUPLE                     1
                        12      CALL_FUNCTION_EX                0
                        14      POP_TOP                         
                        16      RESUME                          0
                        18      NOP                             
                        20      NOP                             
                        22      NOP                             
                        24      NOP                             
                        26      NOP                             
                        28      LOAD_CONST                      4: '_'
                        30      PUSH_NULL                       
                        32      LOAD_CONST                      1: '__pyarmor_assert_35667__'
                        34      LOAD_CONST                      5: 'IsEligibleToJoinRequest'   # b'\x81\xcb\x0b6?\xf3\xb9\xdb\x19\xf6\x08\xf4c\xc6\xf7\x8c\x01o\xbe\xb6\xbf\xce]\xd8'
                        36      CALL                            1
                        44      BUILD_MAP                       1
                        46      NOP                             
                        48      NOP                             
                        50      NOP                             
                        52      JUMP_FORWARD                    20 (to 94)
                        54      CALL                            1
                        62      POP_TOP                         
                        64      RETURN_VALUE                    
                        66      PUSH_EXC_INFO                   
                        68      PUSH_NULL                       
                        70      LOAD_CONST                      6: '__pyarmor_exit_35669__'
                        72      NOP                             
                        74      LOAD_CONST                      3: b'<COAddr>\x05\x00\x00\x1a(\x00\x00\x00\x00\x00\x00\x00\x00\x00\x00\x00\x00\x00\x00\x00'
                        76      CALL                            1
                        84      POP_TOP                         
                        86      RERAISE                         0
                        88      COPY                            3
                        90      POP_EXCEPT                      
                        92      RERAISE                         1
                        94      PUSH_NULL                       
                        96      LOAD_CONST                      6: '__pyarmor_exit_35669__'
                        98      LOAD_CONST                      3: b'<COAddr>\x05\x00\x00\x1a(\x00\x00\x00\x00\x00\x00\x00\x00\x00\x00\x00\x00\x00\x00\x00'
                        100     BUILD_TUPLE                     1
                        102     CALL_FUNCTION_EX                0
                        104     POP_TOP                         
                        106     RETURN_VALUE                    
                    [Exception Table]
                        28 to 46 -> 66 [0] 
                        66 to 88 -> 88 [1] lasti
                [Code]
                    File Name: <frozen multithon.tl.functions.smsjobs>
                    Object Name: _bytes
                    Qualified Name: IsEligibleToJoinRequest._bytes
                    Arg Count: 1
                    Pos Only Arg Count: 0
                    KW Only Arg Count: 0
                    Stack Size: 5
                    Flags: 0x20000003 (CO_OPTIMIZED | CO_NEWLOCALS | CO_PYARMOR_OBFUSCATED)
                    [Names]
                        'join'
                    [Locals+Names]
                        'self'
                        '__assert_armored__'
                    [Constants]
                        None
                        '__pyarmor_assert_35670__'
                        '__pyarmor_enter_35671__'
                        b'<COAddr>\x07\x00\x00\x1a6\x00\x00\x00\x00\x00\x00\x00\x00\x00\x00\x00\x00\x00\x00\x00'
                        b''
                        (
                            b'\xd09\xdc\x0e'
                        )
                        '__pyarmor_exit_35672__'
                    [Disassembly]
                        0       NOP                             
                        2       NOP                             
                        4       PUSH_NULL                       
                        6       LOAD_CONST                      2: '__pyarmor_enter_35671__'
                        8       LOAD_CONST                      3: b'<COAddr>\x07\x00\x00\x1a6\x00\x00\x00\x00\x00\x00\x00\x00\x00\x00\x00\x00\x00\x00\x00'
                        10      BUILD_TUPLE                     1
                        12      CALL_FUNCTION_EX                0
                        14      POP_TOP                         
                        16      RESUME                          0
                        18      NOP                             
                        20      NOP                             
                        22      NOP                             
                        24      NOP                             
                        26      NOP                             
                        28      LOAD_CONST                      4: b''
                        30      LOAD_ATTR                       1: join
                        50      LOAD_CONST                      5: (b'\xd09\xdc\x0e',)
                        52      CALL                            1
                        60      NOP                             
                        62      NOP                             
                        64      NOP                             
                        66      JUMP_FORWARD                    20 (to 108)
                        68      CALL                            1
                        76      POP_TOP                         
                        78      RETURN_VALUE                    
                        80      PUSH_EXC_INFO                   
                        82      PUSH_NULL                       
                        84      LOAD_CONST                      6: '__pyarmor_exit_35672__'
                        86      NOP                             
                        88      LOAD_CONST                      3: b'<COAddr>\x07\x00\x00\x1a6\x00\x00\x00\x00\x00\x00\x00\x00\x00\x00\x00\x00\x00\x00\x00'
                        90      CALL                            1
                        98      POP_TOP                         
                        100     RERAISE                         0
                        102     COPY                            3
                        104     POP_EXCEPT                      
                        106     RERAISE                         1
                        108     PUSH_NULL                       
                        110     LOAD_CONST                      6: '__pyarmor_exit_35672__'
                        112     LOAD_CONST                      3: b'<COAddr>\x07\x00\x00\x1a6\x00\x00\x00\x00\x00\x00\x00\x00\x00\x00\x00\x00\x00\x00\x00'
                        114     BUILD_TUPLE                     1
                        116     CALL_FUNCTION_EX                0
                        118     POP_TOP                         
                        120     RETURN_VALUE                    
                    [Exception Table]
                        28 to 60 -> 80 [0] 
                        80 to 102 -> 102 [1] lasti
                [Code]
                    File Name: <frozen multithon.tl.functions.smsjobs>
                    Object Name: from_reader
                    Qualified Name: IsEligibleToJoinRequest.from_reader
                    Arg Count: 2
                    Pos Only Arg Count: 0
                    KW Only Arg Count: 0
                    Stack Size: 5
                    Flags: 0x20000003 (CO_OPTIMIZED | CO_NEWLOCALS | CO_PYARMOR_OBFUSCATED)
                    [Names]
                    [Locals+Names]
                        'cls'
                        'reader'
                        '__assert_armored__'
                    [Constants]
                        None
                        '__pyarmor_assert_35673__'
                        '__pyarmor_enter_35674__'
                        b'<COAddr>\x07\x00\x00\x1a"\x00\x00\x00\x00\x00\x00\x00\x00\x00\x00\x00\x00\x00\x00\x00'
                        '__pyarmor_exit_35675__'
                    [Disassembly]
                        0       NOP                             
                        2       NOP                             
                        4       PUSH_NULL                       
                        6       LOAD_CONST                      2: '__pyarmor_enter_35674__'
                        8       LOAD_CONST                      3: b'<COAddr>\x07\x00\x00\x1a"\x00\x00\x00\x00\x00\x00\x00\x00\x00\x00\x00\x00\x00\x00\x00'
                        10      BUILD_TUPLE                     1
                        12      CALL_FUNCTION_EX                0
                        14      POP_TOP                         
                        16      RESUME                          0
                        18      NOP                             
                        20      NOP                             
                        22      NOP                             
                        24      NOP                             
                        26      NOP                             
                        28      PUSH_NULL                       
                        30      LOAD_FAST                       0: cls
                        32      CALL                            0
                        40      NOP                             
                        42      NOP                             
                        44      NOP                             
                        46      JUMP_FORWARD                    20 (to 88)
                        48      CALL                            1
                        56      POP_TOP                         
                        58      RETURN_VALUE                    
                        60      PUSH_EXC_INFO                   
                        62      PUSH_NULL                       
                        64      LOAD_CONST                      4: '__pyarmor_exit_35675__'
                        66      NOP                             
                        68      LOAD_CONST                      3: b'<COAddr>\x07\x00\x00\x1a"\x00\x00\x00\x00\x00\x00\x00\x00\x00\x00\x00\x00\x00\x00\x00'
                        70      CALL                            1
                        78      POP_TOP                         
                        80      RERAISE                         0
                        82      COPY                            3
                        84      POP_EXCEPT                      
                        86      RERAISE                         1
                        88      PUSH_NULL                       
                        90      LOAD_CONST                      4: '__pyarmor_exit_35675__'
                        92      LOAD_CONST                      3: b'<COAddr>\x07\x00\x00\x1a"\x00\x00\x00\x00\x00\x00\x00\x00\x00\x00\x00\x00\x00\x00\x00'
                        94      BUILD_TUPLE                     1
                        96      CALL_FUNCTION_EX                0
                        98      POP_TOP                         
                        100     RETURN_VALUE                    
                    [Exception Table]
                        28 to 40 -> 60 [0] 
                        60 to 82 -> 82 [1] lasti
                '__pyarmor_exit_35666__'
                None
            [Disassembly]
                0       NOP                             
                2       LOAD_NAME                       0: __name__
                4       STORE_NAME                      1: __module__
                6       LOAD_CONST                      0: 'IsEligibleToJoinRequest'
                8       STORE_NAME                      2: __qualname__
                10      NOP                             
                12      PUSH_NULL                       
                14      LOAD_CONST                      2: '__pyarmor_enter_35665__'
                16      LOAD_CONST                      3: b'<COAddr>\x05\x00\x00":\x00\x00\x00\x00\x00\x00\x00\x00\x00\x00\x00\x00\x00\x00\x00'
                18      BUILD_TUPLE                     1
                20      CALL_FUNCTION_EX                0
                22      POP_TOP                         
                24      RESUME                          0
                26      NOP                             
                28      NOP                             
                30      NOP                             
                32      NOP                             
                34      NOP                             
                36      LOAD_CONST                      4: 249313744
                38      STORE_NAME                      4: CONSTRUCTOR_ID
                40      LOAD_CONST                      5: 1589076134
                42      STORE_NAME                      5: SUBCLASS_OF_ID
                44      LOAD_CONST                      6: <CODE> to_dict
                46      MAKE_FUNCTION                   0
                48      STORE_NAME                      6: to_dict
                50      LOAD_CONST                      7: <CODE> _bytes
                52      MAKE_FUNCTION                   0
                54      STORE_NAME                      7: _bytes
                56      LOAD_NAME                       8: classmethod
                58      LOAD_CONST                      8: <CODE> from_reader
                60      MAKE_FUNCTION                   0
                62      CALL                            0
                70      STORE_NAME                      9: from_reader
                72      LOAD_CONST                      10: None
                74      NOP                             
                76      NOP                             
                78      NOP                             
                80      JUMP_FORWARD                    19 (to 120)
                88      POP_TOP                         
                90      RETURN_CONST                    10: None
                92      PUSH_EXC_INFO                   
                94      PUSH_NULL                       
                96      LOAD_CONST                      9: '__pyarmor_exit_35666__'
                98      NOP                             
                100     LOAD_CONST                      3: b'<COAddr>\x05\x00\x00":\x00\x00\x00\x00\x00\x00\x00\x00\x00\x00\x00\x00\x00\x00\x00'
                102     CALL                            1
                110     POP_TOP                         
                112     RERAISE                         0
                114     COPY                            3
                116     POP_EXCEPT                      
                118     RERAISE                         1
                120     PUSH_NULL                       
                122     LOAD_CONST                      9: '__pyarmor_exit_35666__'
                124     LOAD_CONST                      3: b'<COAddr>\x05\x00\x00":\x00\x00\x00\x00\x00\x00\x00\x00\x00\x00\x00\x00\x00\x00\x00'
                126     BUILD_TUPLE                     1
                128     CALL_FUNCTION_EX                0
                130     POP_TOP                         
                132     RETURN_VALUE                    
            [Exception Table]
                36 to 72 -> 92 [0] 
                92 to 114 -> 114 [1] lasti
        'IsEligibleToJoinRequest'
        [Code]
            File Name: <frozen multithon.tl.functions.smsjobs>
            Object Name: JoinRequest
            Qualified Name: JoinRequest
            Arg Count: 0
            Pos Only Arg Count: 0
            KW Only Arg Count: 0
            Stack Size: 5
            Flags: 0x20000000 (CO_PYARMOR_OBFUSCATED)
            [Names]
                '__name__'
                '__module__'
                '__qualname__'
                '__assert_armored__'
                'CONSTRUCTOR_ID'
                'SUBCLASS_OF_ID'
                'to_dict'
                '_bytes'
                'classmethod'
                'from_reader'
            [Locals+Names]
            [Constants]
                'JoinRequest'
                '__pyarmor_assert_35676__'
                '__pyarmor_enter_35677__'
                b'<COAddr>\x07\x00\x00":\x00\x00\x00\x00\x00\x00\x00\x00\x00\x00\x00\x00\x00\x00\x00'
                0xA74ECE2D
                0xF5B399AC
                [Code]
                    File Name: <frozen multithon.tl.functions.smsjobs>
                    Object Name: to_dict
                    Qualified Name: JoinRequest.to_dict
                    Arg Count: 1
                    Pos Only Arg Count: 0
                    KW Only Arg Count: 0
                    Stack Size: 5
                    Flags: 0x20000003 (CO_OPTIMIZED | CO_NEWLOCALS | CO_PYARMOR_OBFUSCATED)
                    [Names]
                    [Locals+Names]
                        'self'
                        '__assert_armored__'
                    [Constants]
                        None
                        '__pyarmor_assert_35679__'
                        '__pyarmor_enter_35680__'
                        b'<COAddr>\x05\x00\x00\x1a(\x00\x00\x00\x00\x00\x00\x00\x00\x00\x00\x00\x00\x00\x00\x00'
                        '_'
                        'JoinRequest'   # b'\x81\xc8\x17\x1a=\xc8\xbb\xc3\x0e\xff\x1e\xd4'
                        '__pyarmor_exit_35681__'
                    [Disassembly]
                        0       NOP                             
                        2       NOP                             
                        4       PUSH_NULL                       
                        6       LOAD_CONST                      2: '__pyarmor_enter_35680__'
                        8       LOAD_CONST                      3: b'<COAddr>\x05\x00\x00\x1a(\x00\x00\x00\x00\x00\x00\x00\x00\x00\x00\x00\x00\x00\x00\x00'
                        10      BUILD_TUPLE                     1
                        12      CALL_FUNCTION_EX                0
                        14      POP_TOP                         
                        16      RESUME                          0
                        18      NOP                             
                        20      NOP                             
                        22      NOP                             
                        24      NOP                             
                        26      NOP                             
                        28      LOAD_CONST                      4: '_'
                        30      PUSH_NULL                       
                        32      LOAD_CONST                      1: '__pyarmor_assert_35679__'
                        34      LOAD_CONST                      5: 'JoinRequest'   # b'\x81\xc8\x17\x1a=\xc8\xbb\xc3\x0e\xff\x1e\xd4'
                        36      CALL                            1
                        44      BUILD_MAP                       1
                        46      NOP                             
                        48      NOP                             
                        50      NOP                             
                        52      JUMP_FORWARD                    20 (to 94)
                        54      CALL                            1
                        62      POP_TOP                         
                        64      RETURN_VALUE                    
                        66      PUSH_EXC_INFO                   
                        68      PUSH_NULL                       
                        70      LOAD_CONST                      6: '__pyarmor_exit_35681__'
                        72      NOP                             
                        74      LOAD_CONST                      3: b'<COAddr>\x05\x00\x00\x1a(\x00\x00\x00\x00\x00\x00\x00\x00\x00\x00\x00\x00\x00\x00\x00'
                        76      CALL                            1
                        84      POP_TOP                         
                        86      RERAISE                         0
                        88      COPY                            3
                        90      POP_EXCEPT                      
                        92      RERAISE                         1
                        94      PUSH_NULL                       
                        96      LOAD_CONST                      6: '__pyarmor_exit_35681__'
                        98      LOAD_CONST                      3: b'<COAddr>\x05\x00\x00\x1a(\x00\x00\x00\x00\x00\x00\x00\x00\x00\x00\x00\x00\x00\x00\x00'
                        100     BUILD_TUPLE                     1
                        102     CALL_FUNCTION_EX                0
                        104     POP_TOP                         
                        106     RETURN_VALUE                    
                    [Exception Table]
                        28 to 46 -> 66 [0] 
                        66 to 88 -> 88 [1] lasti
                [Code]
                    File Name: <frozen multithon.tl.functions.smsjobs>
                    Object Name: _bytes
                    Qualified Name: JoinRequest._bytes
                    Arg Count: 1
                    Pos Only Arg Count: 0
                    KW Only Arg Count: 0
                    Stack Size: 5
                    Flags: 0x20000003 (CO_OPTIMIZED | CO_NEWLOCALS | CO_PYARMOR_OBFUSCATED)
                    [Names]
                        'join'
                    [Locals+Names]
                        'self'
                        '__assert_armored__'
                    [Constants]
                        None
                        '__pyarmor_assert_35682__'
                        '__pyarmor_enter_35683__'
                        b'<COAddr>\x05\x00\x00\x1a6\x00\x00\x00\x00\x00\x00\x00\x00\x00\x00\x00\x00\x00\x00\x00'
                        b''
                        (
                            b'-\xceN\xa7'
                        )
                        '__pyarmor_exit_35684__'
                    [Disassembly]
                        0       NOP                             
                        2       NOP                             
                        4       PUSH_NULL                       
                        6       LOAD_CONST                      2: '__pyarmor_enter_35683__'
                        8       LOAD_CONST                      3: b'<COAddr>\x05\x00\x00\x1a6\x00\x00\x00\x00\x00\x00\x00\x00\x00\x00\x00\x00\x00\x00\x00'
                        10      BUILD_TUPLE                     1
                        12      CALL_FUNCTION_EX                0
                        14      POP_TOP                         
                        16      RESUME                          0
                        18      NOP                             
                        20      NOP                             
                        22      NOP                             
                        24      NOP                             
                        26      NOP                             
                        28      LOAD_CONST                      4: b''
                        30      LOAD_ATTR                       1: join
                        50      LOAD_CONST                      5: (b'-\xceN\xa7',)
                        52      CALL                            1
                        60      NOP                             
                        62      NOP                             
                        64      NOP                             
                        66      JUMP_FORWARD                    20 (to 108)
                        68      CALL                            1
                        76      POP_TOP                         
                        78      RETURN_VALUE                    
                        80      PUSH_EXC_INFO                   
                        82      PUSH_NULL                       
                        84      LOAD_CONST                      6: '__pyarmor_exit_35684__'
                        86      NOP                             
                        88      LOAD_CONST                      3: b'<COAddr>\x05\x00\x00\x1a6\x00\x00\x00\x00\x00\x00\x00\x00\x00\x00\x00\x00\x00\x00\x00'
                        90      CALL                            1
                        98      POP_TOP                         
                        100     RERAISE                         0
                        102     COPY                            3
                        104     POP_EXCEPT                      
                        106     RERAISE                         1
                        108     PUSH_NULL                       
                        110     LOAD_CONST                      6: '__pyarmor_exit_35684__'
                        112     LOAD_CONST                      3: b'<COAddr>\x05\x00\x00\x1a6\x00\x00\x00\x00\x00\x00\x00\x00\x00\x00\x00\x00\x00\x00\x00'
                        114     BUILD_TUPLE                     1
                        116     CALL_FUNCTION_EX                0
                        118     POP_TOP                         
                        120     RETURN_VALUE                    
                    [Exception Table]
                        28 to 60 -> 80 [0] 
                        80 to 102 -> 102 [1] lasti
                [Code]
                    File Name: <frozen multithon.tl.functions.smsjobs>
                    Object Name: from_reader
                    Qualified Name: JoinRequest.from_reader
                    Arg Count: 2
                    Pos Only Arg Count: 0
                    KW Only Arg Count: 0
                    Stack Size: 5
                    Flags: 0x20000003 (CO_OPTIMIZED | CO_NEWLOCALS | CO_PYARMOR_OBFUSCATED)
                    [Names]
                    [Locals+Names]
                        'cls'
                        'reader'
                        '__assert_armored__'
                    [Constants]
                        None
                        '__pyarmor_assert_35685__'
                        '__pyarmor_enter_35686__'
                        b'<COAddr>\x05\x00\x00\x1a"\x00\x00\x00\x00\x00\x00\x00\x00\x00\x00\x00\x00\x00\x00\x00'
                        '__pyarmor_exit_35687__'
                    [Disassembly]
                        0       NOP                             
                        2       NOP                             
                        4       PUSH_NULL                       
                        6       LOAD_CONST                      2: '__pyarmor_enter_35686__'
                        8       LOAD_CONST                      3: b'<COAddr>\x05\x00\x00\x1a"\x00\x00\x00\x00\x00\x00\x00\x00\x00\x00\x00\x00\x00\x00\x00'
                        10      BUILD_TUPLE                     1
                        12      CALL_FUNCTION_EX                0
                        14      POP_TOP                         
                        16      RESUME                          0
                        18      NOP                             
                        20      NOP                             
                        22      NOP                             
                        24      NOP                             
                        26      NOP                             
                        28      PUSH_NULL                       
                        30      LOAD_FAST                       0: cls
                        32      CALL                            0
                        40      NOP                             
                        42      NOP                             
                        44      NOP                             
                        46      JUMP_FORWARD                    20 (to 88)
                        48      CALL                            1
                        56      POP_TOP                         
                        58      RETURN_VALUE                    
                        60      PUSH_EXC_INFO                   
                        62      PUSH_NULL                       
                        64      LOAD_CONST                      4: '__pyarmor_exit_35687__'
                        66      NOP                             
                        68      LOAD_CONST                      3: b'<COAddr>\x05\x00\x00\x1a"\x00\x00\x00\x00\x00\x00\x00\x00\x00\x00\x00\x00\x00\x00\x00'
                        70      CALL                            1
                        78      POP_TOP                         
                        80      RERAISE                         0
                        82      COPY                            3
                        84      POP_EXCEPT                      
                        86      RERAISE                         1
                        88      PUSH_NULL                       
                        90      LOAD_CONST                      4: '__pyarmor_exit_35687__'
                        92      LOAD_CONST                      3: b'<COAddr>\x05\x00\x00\x1a"\x00\x00\x00\x00\x00\x00\x00\x00\x00\x00\x00\x00\x00\x00\x00'
                        94      BUILD_TUPLE                     1
                        96      CALL_FUNCTION_EX                0
                        98      POP_TOP                         
                        100     RETURN_VALUE                    
                    [Exception Table]
                        28 to 40 -> 60 [0] 
                        60 to 82 -> 82 [1] lasti
                '__pyarmor_exit_35678__'
                None
            [Disassembly]
                0       NOP                             
                2       LOAD_NAME                       0: __name__
                4       STORE_NAME                      1: __module__
                6       LOAD_CONST                      0: 'JoinRequest'
                8       STORE_NAME                      2: __qualname__
                10      NOP                             
                12      PUSH_NULL                       
                14      LOAD_CONST                      2: '__pyarmor_enter_35677__'
                16      LOAD_CONST                      3: b'<COAddr>\x07\x00\x00":\x00\x00\x00\x00\x00\x00\x00\x00\x00\x00\x00\x00\x00\x00\x00'
                18      BUILD_TUPLE                     1
                20      CALL_FUNCTION_EX                0
                22      POP_TOP                         
                24      RESUME                          0
                26      NOP                             
                28      NOP                             
                30      NOP                             
                32      NOP                             
                34      NOP                             
                36      LOAD_CONST                      4: 0xA74ECE2D
                38      STORE_NAME                      4: CONSTRUCTOR_ID
                40      LOAD_CONST                      5: 0xF5B399AC
                42      STORE_NAME                      5: SUBCLASS_OF_ID
                44      LOAD_CONST                      6: <CODE> to_dict
                46      MAKE_FUNCTION                   0
                48      STORE_NAME                      6: to_dict
                50      LOAD_CONST                      7: <CODE> _bytes
                52      MAKE_FUNCTION                   0
                54      STORE_NAME                      7: _bytes
                56      LOAD_NAME                       8: classmethod
                58      LOAD_CONST                      8: <CODE> from_reader
                60      MAKE_FUNCTION                   0
                62      CALL                            0
                70      STORE_NAME                      9: from_reader
                72      LOAD_CONST                      10: None
                74      NOP                             
                76      NOP                             
                78      NOP                             
                80      JUMP_FORWARD                    19 (to 120)
                88      POP_TOP                         
                90      RETURN_CONST                    10: None
                92      PUSH_EXC_INFO                   
                94      PUSH_NULL                       
                96      LOAD_CONST                      9: '__pyarmor_exit_35678__'
                98      NOP                             
                100     LOAD_CONST                      3: b'<COAddr>\x07\x00\x00":\x00\x00\x00\x00\x00\x00\x00\x00\x00\x00\x00\x00\x00\x00\x00'
                102     CALL                            1
                110     POP_TOP                         
                112     RERAISE                         0
                114     COPY                            3
                116     POP_EXCEPT                      
                118     RERAISE                         1
                120     PUSH_NULL                       
                122     LOAD_CONST                      9: '__pyarmor_exit_35678__'
                124     LOAD_CONST                      3: b'<COAddr>\x07\x00\x00":\x00\x00\x00\x00\x00\x00\x00\x00\x00\x00\x00\x00\x00\x00\x00'
                126     BUILD_TUPLE                     1
                128     CALL_FUNCTION_EX                0
                130     POP_TOP                         
                132     RETURN_VALUE                    
            [Exception Table]
                36 to 72 -> 92 [0] 
                92 to 114 -> 114 [1] lasti
        'JoinRequest'
        [Code]
            File Name: <frozen multithon.tl.functions.smsjobs>
            Object Name: LeaveRequest
            Qualified Name: LeaveRequest
            Arg Count: 0
            Pos Only Arg Count: 0
            KW Only Arg Count: 0
            Stack Size: 5
            Flags: 0x20000000 (CO_PYARMOR_OBFUSCATED)
            [Names]
                '__name__'
                '__module__'
                '__qualname__'
                '__assert_armored__'
                'CONSTRUCTOR_ID'
                'SUBCLASS_OF_ID'
                'to_dict'
                '_bytes'
                'classmethod'
                'from_reader'
            [Locals+Names]
            [Constants]
                'LeaveRequest'
                '__pyarmor_assert_35688__'
                '__pyarmor_enter_35689__'
                b'<COAddr>\x07\x00\x00":\x00\x00\x00\x00\x00\x00\x00\x00\x00\x00\x00\x00\x00\x00\x00'
                0x9898AD73
                0xF5B399AC
                [Code]
                    File Name: <frozen multithon.tl.functions.smsjobs>
                    Object Name: to_dict
                    Qualified Name: LeaveRequest.to_dict
                    Arg Count: 1
                    Pos Only Arg Count: 0
                    KW Only Arg Count: 0
                    Stack Size: 5
                    Flags: 0x20000003 (CO_OPTIMIZED | CO_NEWLOCALS | CO_PYARMOR_OBFUSCATED)
                    [Names]
                    [Locals+Names]
                        'self'
                        '__assert_armored__'
                    [Constants]
                        None
                        '__pyarmor_assert_35691__'
                        '__pyarmor_enter_35692__'
                        b'<COAddr>\x07\x00\x00\x1a(\x00\x00\x00\x00\x00\x00\x00\x00\x00\x00\x00\x00\x00\x00\x00'
                        '_'
                        'LeaveRequest'   # b'\x81\xce\x1d\x12%\xff\x8c\xd7\n\xef\x08\xd3x'
                        '__pyarmor_exit_35693__'
                    [Disassembly]
                        0       NOP                             
                        2       NOP                             
                        4       PUSH_NULL                       
                        6       LOAD_CONST                      2: '__pyarmor_enter_35692__'
                        8       LOAD_CONST                      3: b'<COAddr>\x07\x00\x00\x1a(\x00\x00\x00\x00\x00\x00\x00\x00\x00\x00\x00\x00\x00\x00\x00'
                        10      BUILD_TUPLE                     1
                        12      CALL_FUNCTION_EX                0
                        14      POP_TOP                         
                        16      RESUME                          0
                        18      NOP                             
                        20      NOP                             
                        22      NOP                             
                        24      NOP                             
                        26      NOP                             
                        28      LOAD_CONST                      4: '_'
                        30      PUSH_NULL                       
                        32      LOAD_CONST                      1: '__pyarmor_assert_35691__'
                        34      LOAD_CONST                      5: 'LeaveRequest'   # b'\x81\xce\x1d\x12%\xff\x8c\xd7\n\xef\x08\xd3x'
                        36      CALL                            1
                        44      BUILD_MAP                       1
                        46      NOP                             
                        48      NOP                             
                        50      NOP                             
                        52      JUMP_FORWARD                    20 (to 94)
                        54      CALL                            1
                        62      POP_TOP                         
                        64      RETURN_VALUE                    
                        66      PUSH_EXC_INFO                   
                        68      PUSH_NULL                       
                        70      LOAD_CONST                      6: '__pyarmor_exit_35693__'
                        72      NOP                             
                        74      LOAD_CONST                      3: b'<COAddr>\x07\x00\x00\x1a(\x00\x00\x00\x00\x00\x00\x00\x00\x00\x00\x00\x00\x00\x00\x00'
                        76      CALL                            1
                        84      POP_TOP                         
                        86      RERAISE                         0
                        88      COPY                            3
                        90      POP_EXCEPT                      
                        92      RERAISE                         1
                        94      PUSH_NULL                       
                        96      LOAD_CONST                      6: '__pyarmor_exit_35693__'
                        98      LOAD_CONST                      3: b'<COAddr>\x07\x00\x00\x1a(\x00\x00\x00\x00\x00\x00\x00\x00\x00\x00\x00\x00\x00\x00\x00'
                        100     BUILD_TUPLE                     1
                        102     CALL_FUNCTION_EX                0
                        104     POP_TOP                         
                        106     RETURN_VALUE                    
                    [Exception Table]
                        28 to 46 -> 66 [0] 
                        66 to 88 -> 88 [1] lasti
                [Code]
                    File Name: <frozen multithon.tl.functions.smsjobs>
                    Object Name: _bytes
                    Qualified Name: LeaveRequest._bytes
                    Arg Count: 1
                    Pos Only Arg Count: 0
                    KW Only Arg Count: 0
                    Stack Size: 5
                    Flags: 0x20000003 (CO_OPTIMIZED | CO_NEWLOCALS | CO_PYARMOR_OBFUSCATED)
                    [Names]
                        'join'
                    [Locals+Names]
                        'self'
                        '__assert_armored__'
                    [Constants]
                        None
                        '__pyarmor_assert_35694__'
                        '__pyarmor_enter_35695__'
                        b'<COAddr>\x05\x00\x00\x1a6\x00\x00\x00\x00\x00\x00\x00\x00\x00\x00\x00\x00\x00\x00\x00'
                        b''
                        (
                            b's\xad\x98\x98'
                        )
                        '__pyarmor_exit_35696__'
                    [Disassembly]
                        0       NOP                             
                        2       NOP                             
                        4       PUSH_NULL                       
                        6       LOAD_CONST                      2: '__pyarmor_enter_35695__'
                        8       LOAD_CONST                      3: b'<COAddr>\x05\x00\x00\x1a6\x00\x00\x00\x00\x00\x00\x00\x00\x00\x00\x00\x00\x00\x00\x00'
                        10      BUILD_TUPLE                     1
                        12      CALL_FUNCTION_EX                0
                        14      POP_TOP                         
                        16      RESUME                          0
                        18      NOP                             
                        20      NOP                             
                        22      NOP                             
                        24      NOP                             
                        26      NOP                             
                        28      LOAD_CONST                      4: b''
                        30      LOAD_ATTR                       1: join
                        50      LOAD_CONST                      5: (b's\xad\x98\x98',)
                        52      CALL                            1
                        60      NOP                             
                        62      NOP                             
                        64      NOP                             
                        66      JUMP_FORWARD                    20 (to 108)
                        68      CALL                            1
                        76      POP_TOP                         
                        78      RETURN_VALUE                    
                        80      PUSH_EXC_INFO                   
                        82      PUSH_NULL                       
                        84      LOAD_CONST                      6: '__pyarmor_exit_35696__'
                        86      NOP                             
                        88      LOAD_CONST                      3: b'<COAddr>\x05\x00\x00\x1a6\x00\x00\x00\x00\x00\x00\x00\x00\x00\x00\x00\x00\x00\x00\x00'
                        90      CALL                            1
                        98      POP_TOP                         
                        100     RERAISE                         0
                        102     COPY                            3
                        104     POP_EXCEPT                      
                        106     RERAISE                         1
                        108     PUSH_NULL                       
                        110     LOAD_CONST                      6: '__pyarmor_exit_35696__'
                        112     LOAD_CONST                      3: b'<COAddr>\x05\x00\x00\x1a6\x00\x00\x00\x00\x00\x00\x00\x00\x00\x00\x00\x00\x00\x00\x00'
                        114     BUILD_TUPLE                     1
                        116     CALL_FUNCTION_EX                0
                        118     POP_TOP                         
                        120     RETURN_VALUE                    
                    [Exception Table]
                        28 to 60 -> 80 [0] 
                        80 to 102 -> 102 [1] lasti
                [Code]
                    File Name: <frozen multithon.tl.functions.smsjobs>
                    Object Name: from_reader
                    Qualified Name: LeaveRequest.from_reader
                    Arg Count: 2
                    Pos Only Arg Count: 0
                    KW Only Arg Count: 0
                    Stack Size: 5
                    Flags: 0x20000003 (CO_OPTIMIZED | CO_NEWLOCALS | CO_PYARMOR_OBFUSCATED)
                    [Names]
                    [Locals+Names]
                        'cls'
                        'reader'
                        '__assert_armored__'
                    [Constants]
                        None
                        '__pyarmor_assert_35697__'
                        '__pyarmor_enter_35698__'
                        b'<COAddr>\x07\x00\x00\x1a"\x00\x00\x00\x00\x00\x00\x00\x00\x00\x00\x00\x00\x00\x00\x00'
                        '__pyarmor_exit_35699__'
                    [Disassembly]
                        0       NOP                             
                        2       NOP                             
                        4       PUSH_NULL                       
                        6       LOAD_CONST                      2: '__pyarmor_enter_35698__'
                        8       LOAD_CONST                      3: b'<COAddr>\x07\x00\x00\x1a"\x00\x00\x00\x00\x00\x00\x00\x00\x00\x00\x00\x00\x00\x00\x00'
                        10      BUILD_TUPLE                     1
                        12      CALL_FUNCTION_EX                0
                        14      POP_TOP                         
                        16      RESUME                          0
                        18      NOP                             
                        20      NOP                             
                        22      NOP                             
                        24      NOP                             
                        26      NOP                             
                        28      PUSH_NULL                       
                        30      LOAD_FAST                       0: cls
                        32      CALL                            0
                        40      NOP                             
                        42      NOP                             
                        44      NOP                             
                        46      JUMP_FORWARD                    20 (to 88)
                        48      CALL                            1
                        56      POP_TOP                         
                        58      RETURN_VALUE                    
                        60      PUSH_EXC_INFO                   
                        62      PUSH_NULL                       
                        64      LOAD_CONST                      4: '__pyarmor_exit_35699__'
                        66      NOP                             
                        68      LOAD_CONST                      3: b'<COAddr>\x07\x00\x00\x1a"\x00\x00\x00\x00\x00\x00\x00\x00\x00\x00\x00\x00\x00\x00\x00'
                        70      CALL                            1
                        78      POP_TOP                         
                        80      RERAISE                         0
                        82      COPY                            3
                        84      POP_EXCEPT                      
                        86      RERAISE                         1
                        88      PUSH_NULL                       
                        90      LOAD_CONST                      4: '__pyarmor_exit_35699__'
                        92      LOAD_CONST                      3: b'<COAddr>\x07\x00\x00\x1a"\x00\x00\x00\x00\x00\x00\x00\x00\x00\x00\x00\x00\x00\x00\x00'
                        94      BUILD_TUPLE                     1
                        96      CALL_FUNCTION_EX                0
                        98      POP_TOP                         
                        100     RETURN_VALUE                    
                    [Exception Table]
                        28 to 40 -> 60 [0] 
                        60 to 82 -> 82 [1] lasti
                '__pyarmor_exit_35690__'
                None
            [Disassembly]
                0       NOP                             
                2       LOAD_NAME                       0: __name__
                4       STORE_NAME                      1: __module__
                6       LOAD_CONST                      0: 'LeaveRequest'
                8       STORE_NAME                      2: __qualname__
                10      NOP                             
                12      PUSH_NULL                       
                14      LOAD_CONST                      2: '__pyarmor_enter_35689__'
                16      LOAD_CONST                      3: b'<COAddr>\x07\x00\x00":\x00\x00\x00\x00\x00\x00\x00\x00\x00\x00\x00\x00\x00\x00\x00'
                18      BUILD_TUPLE                     1
                20      CALL_FUNCTION_EX                0
                22      POP_TOP                         
                24      RESUME                          0
                26      NOP                             
                28      NOP                             
                30      NOP                             
                32      NOP                             
                34      NOP                             
                36      LOAD_CONST                      4: 0x9898AD73
                38      STORE_NAME                      4: CONSTRUCTOR_ID
                40      LOAD_CONST                      5: 0xF5B399AC
                42      STORE_NAME                      5: SUBCLASS_OF_ID
                44      LOAD_CONST                      6: <CODE> to_dict
                46      MAKE_FUNCTION                   0
                48      STORE_NAME                      6: to_dict
                50      LOAD_CONST                      7: <CODE> _bytes
                52      MAKE_FUNCTION                   0
                54      STORE_NAME                      7: _bytes
                56      LOAD_NAME                       8: classmethod
                58      LOAD_CONST                      8: <CODE> from_reader
                60      MAKE_FUNCTION                   0
                62      CALL                            0
                70      STORE_NAME                      9: from_reader
                72      LOAD_CONST                      10: None
                74      NOP                             
                76      NOP                             
                78      NOP                             
                80      JUMP_FORWARD                    19 (to 120)
                88      POP_TOP                         
                90      RETURN_CONST                    10: None
                92      PUSH_EXC_INFO                   
                94      PUSH_NULL                       
                96      LOAD_CONST                      9: '__pyarmor_exit_35690__'
                98      NOP                             
                100     LOAD_CONST                      3: b'<COAddr>\x07\x00\x00":\x00\x00\x00\x00\x00\x00\x00\x00\x00\x00\x00\x00\x00\x00\x00'
                102     CALL                            1
                110     POP_TOP                         
                112     RERAISE                         0
                114     COPY                            3
                116     POP_EXCEPT                      
                118     RERAISE                         1
                120     PUSH_NULL                       
                122     LOAD_CONST                      9: '__pyarmor_exit_35690__'
                124     LOAD_CONST                      3: b'<COAddr>\x07\x00\x00":\x00\x00\x00\x00\x00\x00\x00\x00\x00\x00\x00\x00\x00\x00\x00'
                126     BUILD_TUPLE                     1
                128     CALL_FUNCTION_EX                0
                130     POP_TOP                         
                132     RETURN_VALUE                    
            [Exception Table]
                36 to 72 -> 92 [0] 
                92 to 114 -> 114 [1] lasti
        'LeaveRequest'
        [Code]
            File Name: <frozen multithon.tl.functions.smsjobs>
            Object Name: UpdateSettingsRequest
            Qualified Name: UpdateSettingsRequest
            Arg Count: 0
            Pos Only Arg Count: 0
            KW Only Arg Count: 0
            Stack Size: 5
            Flags: 0x20000000 (CO_PYARMOR_OBFUSCATED)
            [Names]
                '__name__'
                '__module__'
                '__qualname__'
                '__assert_armored__'
                'CONSTRUCTOR_ID'
                'SUBCLASS_OF_ID'
                'Optional'
                'bool'
                '__init__'
                'to_dict'
                '_bytes'
                'classmethod'
                'from_reader'
            [Locals+Names]
            [Constants]
                'UpdateSettingsRequest'
                '__pyarmor_assert_35700__'
                '__pyarmor_enter_35701__'
                b'<COAddr>\x07\x00\x00"N\x00\x00\x00\x00\x00\x00\x00\x00\x00\x00\x00\x00\x00\x00\x00'
                155164863
                0xF5B399AC
                None
                'allow_international'
                [Code]
                    File Name: <frozen multithon.tl.functions.smsjobs>
                    Object Name: __init__
                    Qualified Name: UpdateSettingsRequest.__init__
                    Arg Count: 2
                    Pos Only Arg Count: 0
                    KW Only Arg Count: 0
                    Stack Size: 5
                    Flags: 0x20000003 (CO_OPTIMIZED | CO_NEWLOCALS | CO_PYARMOR_OBFUSCATED)
                    [Names]
                        'allow_international'
                    [Locals+Names]
                        'self'
                        'allow_international'
                        '__assert_armored__'
                    [Constants]
                        '\n        :returns Bool: This type has no constructors.\n        '
                        '__pyarmor_assert_35703__'
                        '__pyarmor_enter_35704__'
                        b'<COAddr>\x07\x00\x00\x1a$\x00\x00\x00\x00\x00\x00\x00\x00\x00\x00\x00\x00\x00\x00\x00'
                        '__pyarmor_exit_35705__'
                        None
                    [Disassembly]
                        0       NOP                             
                        2       NOP                             
                        4       PUSH_NULL                       
                        6       LOAD_CONST                      2: '__pyarmor_enter_35704__'
                        8       LOAD_CONST                      3: b'<COAddr>\x07\x00\x00\x1a$\x00\x00\x00\x00\x00\x00\x00\x00\x00\x00\x00\x00\x00\x00\x00'
                        10      BUILD_TUPLE                     1
                        12      CALL_FUNCTION_EX                0
                        14      POP_TOP                         
                        16      RESUME                          0
                        18      NOP                             
                        20      NOP                             
                        22      NOP                             
                        24      NOP                             
                        26      NOP                             
                        28      LOAD_FAST                       1: allow_international
                        30      LOAD_FAST                       0: self
                        32      STORE_ATTR                      0: allow_international
                        42      LOAD_CONST                      5: None
                        44      NOP                             
                        46      NOP                             
                        48      NOP                             
                        50      JUMP_FORWARD                    19 (to 90)
                        58      POP_TOP                         
                        60      RETURN_CONST                    5: None
                        62      PUSH_EXC_INFO                   
                        64      PUSH_NULL                       
                        66      LOAD_CONST                      4: '__pyarmor_exit_35705__'
                        68      NOP                             
                        70      LOAD_CONST                      3: b'<COAddr>\x07\x00\x00\x1a$\x00\x00\x00\x00\x00\x00\x00\x00\x00\x00\x00\x00\x00\x00\x00'
                        72      CALL                            1
                        80      POP_TOP                         
                        82      RERAISE                         0
                        84      COPY                            3
                        86      POP_EXCEPT                      
                        88      RERAISE                         1
                        90      PUSH_NULL                       
                        92      LOAD_CONST                      4: '__pyarmor_exit_35705__'
                        94      LOAD_CONST                      3: b'<COAddr>\x07\x00\x00\x1a$\x00\x00\x00\x00\x00\x00\x00\x00\x00\x00\x00\x00\x00\x00\x00'
                        96      BUILD_TUPLE                     1
                        98      CALL_FUNCTION_EX                0
                        100     POP_TOP                         
                        102     RETURN_VALUE                    
                    [Exception Table]
                        28 to 42 -> 62 [0] 
                        62 to 84 -> 84 [1] lasti
                [Code]
                    File Name: <frozen multithon.tl.functions.smsjobs>
                    Object Name: to_dict
                    Qualified Name: UpdateSettingsRequest.to_dict
                    Arg Count: 1
                    Pos Only Arg Count: 0
                    KW Only Arg Count: 0
                    Stack Size: 5
                    Flags: 0x20000003 (CO_OPTIMIZED | CO_NEWLOCALS | CO_PYARMOR_OBFUSCATED)
                    [Names]
                        'allow_international'
                    [Locals+Names]
                        'self'
                        '__assert_armored__'
                    [Constants]
                        None
                        '__pyarmor_assert_35706__'
                        '__pyarmor_enter_35707__'
                        b'<COAddr>\x07\x00\x00\x1aL\x00\x00\x00\x00\x00\x00\x00\x00\x00\x00\x00\x00\x00\x00\x00'
                        '_'
                        'UpdateSettingsRequest'   # b'\x81\xd7\x08\x172\xee\xbb\xe1\x1e\xee\x19\xc9b\xeb\xeb\xb7\nL\xae\xa2\xb9\xdf'
                        'allow_international'   # b'\x81\xe3\x14\x1f<\xed\x81\xdb\x15\xee\x08\xd2b\xed\xec\x8c\x00S\xba\xab'
                        '__pyarmor_exit_35708__'
                    [Disassembly]
                        0       NOP                             
                        2       NOP                             
                        4       PUSH_NULL                       
                        6       LOAD_CONST                      2: '__pyarmor_enter_35707__'
                        8       LOAD_CONST                      3: b'<COAddr>\x07\x00\x00\x1aL\x00\x00\x00\x00\x00\x00\x00\x00\x00\x00\x00\x00\x00\x00\x00'
                        10      BUILD_TUPLE                     1
                        12      CALL_FUNCTION_EX                0
                        14      POP_TOP                         
                        16      RESUME                          0
                        18      NOP                             
                        20      NOP                             
                        22      NOP                             
                        24      NOP                             
                        26      NOP                             
                        28      LOAD_CONST                      4: '_'
                        30      PUSH_NULL                       
                        32      LOAD_CONST                      1: '__pyarmor_assert_35706__'
                        34      LOAD_CONST                      5: 'UpdateSettingsRequest'   # b'\x81\xd7\x08\x172\xee\xbb\xe1\x1e\xee\x19\xc9b\xeb\xeb\xb7\nL\xae\xa2\xb9\xdf'
                        36      CALL                            1
                        44      PUSH_NULL                       
                        46      LOAD_CONST                      1: '__pyarmor_assert_35706__'
                        48      LOAD_CONST                      6: 'allow_international'   # b'\x81\xe3\x14\x1f<\xed\x81\xdb\x15\xee\x08\xd2b\xed\xec\x8c\x00S\xba\xab'
                        50      CALL                            1
                        58      LOAD_FAST                       0: self
                        60      LOAD_ATTR                       0: allow_international
                        80      BUILD_MAP                       2
                        82      NOP                             
                        84      NOP                             
                        86      NOP                             
                        88      JUMP_FORWARD                    20 (to 130)
                        90      CALL                            1
                        98      POP_TOP                         
                        100     RETURN_VALUE                    
                        102     PUSH_EXC_INFO                   
                        104     PUSH_NULL                       
                        106     LOAD_CONST                      7: '__pyarmor_exit_35708__'
                        108     NOP                             
                        110     LOAD_CONST                      3: b'<COAddr>\x07\x00\x00\x1aL\x00\x00\x00\x00\x00\x00\x00\x00\x00\x00\x00\x00\x00\x00\x00'
                        112     CALL                            1
                        120     POP_TOP                         
                        122     RERAISE                         0
                        124     COPY                            3
                        126     POP_EXCEPT                      
                        128     RERAISE                         1
                        130     PUSH_NULL                       
                        132     LOAD_CONST                      7: '__pyarmor_exit_35708__'
                        134     LOAD_CONST                      3: b'<COAddr>\x07\x00\x00\x1aL\x00\x00\x00\x00\x00\x00\x00\x00\x00\x00\x00\x00\x00\x00\x00'
                        136     BUILD_TUPLE                     1
                        138     CALL_FUNCTION_EX                0
                        140     POP_TOP                         
                        142     RETURN_VALUE                    
                    [Exception Table]
                        28 to 82 -> 102 [0] 
                        102 to 124 -> 124 [1] lasti
                [Code]
                    File Name: <frozen multithon.tl.functions.smsjobs>
                    Object Name: _bytes
                    Qualified Name: UpdateSettingsRequest._bytes
                    Arg Count: 1
                    Pos Only Arg Count: 0
                    KW Only Arg Count: 0
                    Stack Size: 8
                    Flags: 0x20000003 (CO_OPTIMIZED | CO_NEWLOCALS | CO_PYARMOR_OBFUSCATED)
                    [Names]
                        'join'
                        'struct'
                        'pack'
                        'allow_international'
                    [Locals+Names]
                        'self'
                        '__assert_armored__'
                    [Constants]
                        None
                        '__pyarmor_assert_35709__'
                        '__pyarmor_enter_35710__'
                        b'<COAddr>\x07\x00\x00\x1a\x9a\x00\x00\x00\x00\x00\x00\x00\x00\x00\x00\x00\x00\x00\x00\x00'
                        b''
                        b'\xbf\xa0?\t'
                        '<I'
                        False
                        0
                        1
                        '__pyarmor_exit_35711__'
                    [Disassembly]
                        0       NOP                             
                        2       NOP                             
                        4       PUSH_NULL                       
                        6       LOAD_CONST                      2: '__pyarmor_enter_35710__'
                        8       LOAD_CONST                      3: b'<COAddr>\x07\x00\x00\x1a\x9a\x00\x00\x00\x00\x00\x00\x00\x00\x00\x00\x00\x00\x00\x00\x00'
                        10      BUILD_TUPLE                     1
                        12      CALL_FUNCTION_EX                0
                        14      POP_TOP                         
                        16      RESUME                          0
                        18      NOP                             
                        20      NOP                             
                        22      NOP                             
                        24      NOP                             
                        26      NOP                             
                        28      LOAD_CONST                      4: b''
                        30      LOAD_ATTR                       1: join
                        50      LOAD_CONST                      5: b'\xbf\xa0?\t'
                        52      LOAD_GLOBAL                     3: NULL + struct
                        62      LOAD_ATTR                       4: pack
                        82      LOAD_CONST                      6: '<I'
                        84      LOAD_FAST                       0: self
                        86      LOAD_ATTR                       6: allow_international
                        106     POP_JUMP_IF_NONE                14 (to 136)
                        108     LOAD_FAST                       0: self
                        110     LOAD_ATTR                       6: allow_international
                        130     LOAD_CONST                      7: False
                        132     IS_OP                           0 (is)
                        134     POP_JUMP_IF_FALSE               2 (to 140)
                        136     LOAD_CONST                      8: 0
                        138     JUMP_FORWARD                    1 (to 142)
                        140     LOAD_CONST                      9: 1
                        142     CALL                            2
                        150     BUILD_TUPLE                     2
                        152     CALL                            1
                        160     NOP                             
                        162     NOP                             
                        164     NOP                             
                        166     JUMP_FORWARD                    20 (to 208)
                        168     CALL                            1
                        176     POP_TOP                         
                        178     RETURN_VALUE                    
                        180     PUSH_EXC_INFO                   
                        182     PUSH_NULL                       
                        184     LOAD_CONST                      10: '__pyarmor_exit_35711__'
                        186     NOP                             
                        188     LOAD_CONST                      3: b'<COAddr>\x07\x00\x00\x1a\x9a\x00\x00\x00\x00\x00\x00\x00\x00\x00\x00\x00\x00\x00\x00\x00'
                        190     CALL                            1
                        198     POP_TOP                         
                        200     RERAISE                         0
                        202     COPY                            3
                        204     POP_EXCEPT                      
                        206     RERAISE                         1
                        208     PUSH_NULL                       
                        210     LOAD_CONST                      10: '__pyarmor_exit_35711__'
                        212     LOAD_CONST                      3: b'<COAddr>\x07\x00\x00\x1a\x9a\x00\x00\x00\x00\x00\x00\x00\x00\x00\x00\x00\x00\x00\x00\x00'
                        214     BUILD_TUPLE                     1
                        216     CALL_FUNCTION_EX                0
                        218     POP_TOP                         
                        220     RETURN_VALUE                    
                    [Exception Table]
                        28 to 160 -> 180 [0] 
                        180 to 202 -> 202 [1] lasti
                [Code]
                    File Name: <frozen multithon.tl.functions.smsjobs>
                    Object Name: from_reader
                    Qualified Name: UpdateSettingsRequest.from_reader
                    Arg Count: 2
                    Pos Only Arg Count: 0
                    KW Only Arg Count: 0
                    Stack Size: 5
                    Flags: 0x20000003 (CO_OPTIMIZED | CO_NEWLOCALS | CO_PYARMOR_OBFUSCATED)
                    [Names]
                        'read_int'
                        'bool'
                    [Locals+Names]
                        'cls'
                        'reader'
                        '__assert_armored__'
                        '_var_var_0'
                        '_var_var_3'
                    [Constants]
                        None
                        '__pyarmor_assert_35712__'
                        '__pyarmor_enter_35713__'
                        b'<COAddr>\x05\x00\x00\x1ab\x00\x00\x00\x00\x00\x00\x00\x00\x00\x00\x00\x00\x00\x00\x00'
                        1
                        (
                            'allow_international'
                        )
                        '__pyarmor_exit_35714__'
                    [Disassembly]
                        0       NOP                             
                        2       NOP                             
                        4       PUSH_NULL                       
                        6       LOAD_CONST                      2: '__pyarmor_enter_35713__'
                        8       LOAD_CONST                      3: b'<COAddr>\x05\x00\x00\x1ab\x00\x00\x00\x00\x00\x00\x00\x00\x00\x00\x00\x00\x00\x00\x00'
                        10      BUILD_TUPLE                     1
                        12      CALL_FUNCTION_EX                0
                        14      POP_TOP                         
                        16      RESUME                          0
                        18      NOP                             
                        20      NOP                             
                        22      NOP                             
                        24      NOP                             
                        26      NOP                             
                        28      LOAD_FAST                       1: reader
                        30      LOAD_ATTR                       1: read_int
                        50      CALL                            0
                        58      STORE_FAST                      3: _var_var_0
                        60      LOAD_GLOBAL                     3: NULL + bool
                        70      LOAD_FAST                       3: _var_var_0
                        72      LOAD_CONST                      4: 1
                        74      BINARY_OP                       1 (&)
                        78      CALL                            1
                        86      STORE_FAST                      4: _var_var_3
                        88      PUSH_NULL                       
                        90      LOAD_FAST                       0: cls
                        92      LOAD_FAST                       4: _var_var_3
                        94      KW_NAMES                        5: ('allow_international',)
                        96      CALL                            1
                        104     NOP                             
                        106     NOP                             
                        108     NOP                             
                        110     JUMP_FORWARD                    20 (to 152)
                        112     CALL                            1
                        120     POP_TOP                         
                        122     RETURN_VALUE                    
                        124     PUSH_EXC_INFO                   
                        126     PUSH_NULL                       
                        128     LOAD_CONST                      6: '__pyarmor_exit_35714__'
                        130     NOP                             
                        132     LOAD_CONST                      3: b'<COAddr>\x05\x00\x00\x1ab\x00\x00\x00\x00\x00\x00\x00\x00\x00\x00\x00\x00\x00\x00\x00'
                        134     CALL                            1
                        142     POP_TOP                         
                        144     RERAISE                         0
                        146     COPY                            3
                        148     POP_EXCEPT                      
                        150     RERAISE                         1
                        152     PUSH_NULL                       
                        154     LOAD_CONST                      6: '__pyarmor_exit_35714__'
                        156     LOAD_CONST                      3: b'<COAddr>\x05\x00\x00\x1ab\x00\x00\x00\x00\x00\x00\x00\x00\x00\x00\x00\x00\x00\x00\x00'
                        158     BUILD_TUPLE                     1
                        160     CALL_FUNCTION_EX                0
                        162     POP_TOP                         
                        164     RETURN_VALUE                    
                    [Exception Table]
                        28 to 104 -> 124 [0] 
                        124 to 146 -> 146 [1] lasti
                '__pyarmor_exit_35702__'
                (
                    None
                )
            [Disassembly]
                0       NOP                             
                2       LOAD_NAME                       0: __name__
                4       STORE_NAME                      1: __module__
                6       LOAD_CONST                      0: 'UpdateSettingsRequest'
                8       STORE_NAME                      2: __qualname__
                10      NOP                             
                12      PUSH_NULL                       
                14      LOAD_CONST                      2: '__pyarmor_enter_35701__'
                16      LOAD_CONST                      3: b'<COAddr>\x07\x00\x00"N\x00\x00\x00\x00\x00\x00\x00\x00\x00\x00\x00\x00\x00\x00\x00'
                18      BUILD_TUPLE                     1
                20      CALL_FUNCTION_EX                0
                22      POP_TOP                         
                24      RESUME                          0
                26      NOP                             
                28      NOP                             
                30      NOP                             
                32      NOP                             
                34      NOP                             
                36      LOAD_CONST                      4: 155164863
                38      STORE_NAME                      4: CONSTRUCTOR_ID
                40      LOAD_CONST                      5: 0xF5B399AC
                42      STORE_NAME                      5: SUBCLASS_OF_ID
                44      LOAD_CONST                      13: (None,)
                46      LOAD_CONST                      7: 'allow_international'
                48      LOAD_NAME                       6: Optional
                50      LOAD_NAME                       7: bool
                52      BINARY_SUBSCR                   
                56      BUILD_TUPLE                     2
                58      LOAD_CONST                      8: <CODE> __init__
                60      MAKE_FUNCTION                   5
                62      STORE_NAME                      8: __init__
                64      LOAD_CONST                      9: <CODE> to_dict
                66      MAKE_FUNCTION                   0
                68      STORE_NAME                      9: to_dict
                70      LOAD_CONST                      10: <CODE> _bytes
                72      MAKE_FUNCTION                   0
                74      STORE_NAME                      10: _bytes
                76      LOAD_NAME                       11: classmethod
                78      LOAD_CONST                      11: <CODE> from_reader
                80      MAKE_FUNCTION                   0
                82      CALL                            0
                90      STORE_NAME                      12: from_reader
                92      LOAD_CONST                      6: None
                94      NOP                             
                96      NOP                             
                98      NOP                             
                100     JUMP_FORWARD                    19 (to 140)
                108     POP_TOP                         
                110     RETURN_CONST                    6: None
                112     PUSH_EXC_INFO                   
                114     PUSH_NULL                       
                116     LOAD_CONST                      12: '__pyarmor_exit_35702__'
                118     NOP                             
                120     LOAD_CONST                      3: b'<COAddr>\x07\x00\x00"N\x00\x00\x00\x00\x00\x00\x00\x00\x00\x00\x00\x00\x00\x00\x00'
                122     CALL                            1
                130     POP_TOP                         
                132     RERAISE                         0
                134     COPY                            3
                136     POP_EXCEPT                      
                138     RERAISE                         1
                140     PUSH_NULL                       
                142     LOAD_CONST                      12: '__pyarmor_exit_35702__'
                144     LOAD_CONST                      3: b'<COAddr>\x07\x00\x00"N\x00\x00\x00\x00\x00\x00\x00\x00\x00\x00\x00\x00\x00\x00\x00'
                146     BUILD_TUPLE                     1
                148     CALL_FUNCTION_EX                0
                150     POP_TOP                         
                152     RETURN_VALUE                    
            [Exception Table]
                36 to 92 -> 112 [0] 
                112 to 134 -> 134 [1] lasti
        'UpdateSettingsRequest'
        '__pyarmor_exit_35621__'
    [Disassembly]
        0       NOP                             
        2       NOP                             
        4       PUSH_NULL                       
        6       LOAD_CONST                      1: '__pyarmor_enter_35620__'
        8       LOAD_CONST                      2: b'<COAddr>\x05\x00\x00\x1a\n\x01\x00\x00\x00\x00\x00\x00\x00\x00\x00\x00\x00\x00\x00\x00'
        10      BUILD_TUPLE                     1
        12      CALL_FUNCTION_EX                0
        14      POP_TOP                         
        16      RESUME                          0
        18      NOP                             
        20      NOP                             
        22      NOP                             
        24      NOP                             
        26      PUSH_NULL                       
        28      LOAD_CONST                      0: '__pyarmor_assert_35619__'
        30      LOAD_CONST                      3: "File generated by TLObjects' generator. All changes will be ERASED"   # b'\x81\xc4\x11\x1f6\xba\xb9\xd7\x15\xff\x1f\xc1x\xe9\xfc\xc5\rD\xfb\x93\x86\xe4L\xc6\x00l\xb7OG\xf1\x19\xe04W2\x0c\x8c\xc5\xa6`X\xc8\xf4Q\x9d\xdb\x07F9\xeaS\xe8\xc7g\x0f\xe1;\xab\x99\x18Xn\x03rdm!'
        32      CALL                            1
        40      POP_TOP                         
        42      LOAD_CONST                      4: 3
        44      LOAD_CONST                      5: ('TLObject',)
        46      IMPORT_NAME                     1: tl.tlobject
        48      IMPORT_FROM                     2: TLObject
        50      STORE_NAME                      2: TLObject
        52      POP_TOP                         
        54      LOAD_CONST                      4: 3
        56      LOAD_CONST                      6: ('TLRequest',)
        58      IMPORT_NAME                     1: tl.tlobject
        60      IMPORT_FROM                     3: TLRequest
        62      STORE_NAME                      3: TLRequest
        64      POP_TOP                         
        66      LOAD_CONST                      7: 0
        68      LOAD_CONST                      8: ('Optional', 'List', 'Union', 'TYPE_CHECKING')
        70      IMPORT_NAME                     4: typing
        72      IMPORT_FROM                     5: Optional
        74      STORE_NAME                      5: Optional
        76      IMPORT_FROM                     6: List
        78      STORE_NAME                      6: List
        80      IMPORT_FROM                     7: Union
        82      STORE_NAME                      7: Union
        84      IMPORT_FROM                     8: TYPE_CHECKING
        86      STORE_NAME                      8: TYPE_CHECKING
        88      POP_TOP                         
        90      LOAD_CONST                      7: 0
        92      LOAD_CONST                      9: None
        94      IMPORT_NAME                     9: os
        96      STORE_NAME                      9: os
        98      LOAD_CONST                      7: 0
        100     LOAD_CONST                      9: None
        102     IMPORT_NAME                     10: struct
        104     STORE_NAME                      10: struct
        106     LOAD_CONST                      7: 0
        108     LOAD_CONST                      10: ('datetime',)
        110     IMPORT_NAME                     11: datetime
        112     IMPORT_FROM                     11: datetime
        114     STORE_NAME                      11: datetime
        116     POP_TOP                         
        118     PUSH_NULL                       
        120     LOAD_BUILD_CLASS                
        122     LOAD_CONST                      11: <CODE> FinishJobRequest
        124     MAKE_FUNCTION                   0
        126     LOAD_CONST                      12: 'FinishJobRequest'
        128     LOAD_NAME                       3: TLRequest
        130     CALL                            3
        138     STORE_NAME                      12: FinishJobRequest
        140     PUSH_NULL                       
        142     LOAD_BUILD_CLASS                
        144     LOAD_CONST                      13: <CODE> GetSmsJobRequest
        146     MAKE_FUNCTION                   0
        148     LOAD_CONST                      14: 'GetSmsJobRequest'
        150     LOAD_NAME                       3: TLRequest
        152     CALL                            3
        160     STORE_NAME                      13: GetSmsJobRequest
        162     PUSH_NULL                       
        164     LOAD_BUILD_CLASS                
        166     LOAD_CONST                      15: <CODE> GetStatusRequest
        168     MAKE_FUNCTION                   0
        170     LOAD_CONST                      16: 'GetStatusRequest'
        172     LOAD_NAME                       3: TLRequest
        174     CALL                            3
        182     STORE_NAME                      14: GetStatusRequest
        184     PUSH_NULL                       
        186     LOAD_BUILD_CLASS                
        188     LOAD_CONST                      17: <CODE> IsEligibleToJoinRequest
        190     MAKE_FUNCTION                   0
        192     LOAD_CONST                      18: 'IsEligibleToJoinRequest'
        194     LOAD_NAME                       3: TLRequest
        196     CALL                            3
        204     STORE_NAME                      15: IsEligibleToJoinRequest
        206     PUSH_NULL                       
        208     LOAD_BUILD_CLASS                
        210     LOAD_CONST                      19: <CODE> JoinRequest
        212     MAKE_FUNCTION                   0
        214     LOAD_CONST                      20: 'JoinRequest'
        216     LOAD_NAME                       3: TLRequest
        218     CALL                            3
        226     STORE_NAME                      16: JoinRequest
        228     PUSH_NULL                       
        230     LOAD_BUILD_CLASS                
        232     LOAD_CONST                      21: <CODE> LeaveRequest
        234     MAKE_FUNCTION                   0
        236     LOAD_CONST                      22: 'LeaveRequest'
        238     LOAD_NAME                       3: TLRequest
        240     CALL                            3
        248     STORE_NAME                      17: LeaveRequest
        250     PUSH_NULL                       
        252     LOAD_BUILD_CLASS                
        254     LOAD_CONST                      23: <CODE> UpdateSettingsRequest
        256     MAKE_FUNCTION                   0
        258     LOAD_CONST                      24: 'UpdateSettingsRequest'
        260     LOAD_NAME                       3: TLRequest
        262     CALL                            3
        270     STORE_NAME                      18: UpdateSettingsRequest
        272     LOAD_CONST                      9: None
        274     NOP                             
        276     NOP                             
        278     NOP                             
        280     JUMP_FORWARD                    19 (to 320)
        288     POP_TOP                         
        290     RETURN_CONST                    9: None
        292     PUSH_EXC_INFO                   
        294     PUSH_NULL                       
        296     LOAD_CONST                      25: '__pyarmor_exit_35621__'
        298     NOP                             
        300     LOAD_CONST                      2: b'<COAddr>\x05\x00\x00\x1a\n\x01\x00\x00\x00\x00\x00\x00\x00\x00\x00\x00\x00\x00\x00\x00'
        302     CALL                            1
        310     POP_TOP                         
        312     RERAISE                         0
        314     COPY                            3
        316     POP_EXCEPT                      
        318     RERAISE                         1
        320     PUSH_NULL                       
        322     LOAD_CONST                      25: '__pyarmor_exit_35621__'
        324     LOAD_CONST                      2: b'<COAddr>\x05\x00\x00\x1a\n\x01\x00\x00\x00\x00\x00\x00\x00\x00\x00\x00\x00\x00\x00\x00'
        326     BUILD_TUPLE                     1
        328     CALL_FUNCTION_EX                0
        330     POP_TOP                         
        332     RETURN_VALUE                    
    [Exception Table]
        26 to 272 -> 292 [0] 
        292 to 314 -> 314 [1] lasti
