#decoded by lolz.live/mrpenny / t.me/zeus_jackpot
# ================================
# Примечания по Pyarmor:
# - Байт-код и объекты кода Pyarmor соответствуют стандартному Python, но присутствуют специальные вызовы функций среды выполнения (runtime) Pyarmor.
# - Вызовы строк — это не ошибки, а маркеры, которые обрабатываются Pyarmor во время выполнения.
#
# Руководство по декомпиляции (без среды выполнения):
# 1. Игнорируйте зашифрованные байты после `#`; используйте только строку до `#`.
# 2. Удалите "__pyarmor_enter_xxx__"(b"<COAddr>...") и "__pyarmor_leave_xxx__"(b"<COAddr>...") (пролог/эпилог).
# 3. "__pyarmor_assert_xxx__"(A) не является настоящим оператором assert.
#    - Если A — это имя или читаемая строка: замените на A.
#    - Если A — это (X, "Y"): замените на X.Y.
#    - Если A — это (X, "Y", Z): замените на X.Y = Z.
#    - В противном случае: выберите наиболее подходящую/логичную замену.
# 4. "__pyarmor_bcc_xxx__"(...) указывает на машинный (нативный) код; тело функции недоступно. Добавьте комментарий.
# ================================

[Code]
    File Name: <frozen multithon.tl.functions.updates>
    Object Name: <module>
    Qualified Name: <module>
    Arg Count: 0
    Pos Only Arg Count: 0
    KW Only Arg Count: 0
    Stack Size: 5
    Flags: 0x20000000 (CO_PYARMOR_OBFUSCATED)
    [Names]
        '__assert_armored__'
        'tl.tlobject'
        'TLObject'
        'TLRequest'
        'typing'
        'Optional'
        'List'
        'Union'
        'TYPE_CHECKING'
        'os'
        'struct'
        'datetime'
        'tl.types'
        'TypeChannelMessagesFilter'
        'TypeInputChannel'
        'GetChannelDifferenceRequest'
        'GetDifferenceRequest'
        'GetDifference_tdlib_Request'
        'GetStateRequest'
    [Locals+Names]
    [Constants]
        '__pyarmor_assert_36687__'
        '__pyarmor_enter_36688__'
        b'<COAddr>\x05\x00\x00\x1a\xdc\x00\x00\x00\x00\x00\x00\x00\x00\x00\x00\x00\x00\x00\x00\x00'
        "File generated by TLObjects' generator. All changes will be ERASED"   # b'\x81\xc4\x11\x1f6\xba\xb9\xd7\x15\xff\x1f\xc1x\xe9\xfc\xc5\rD\xfb\x93\x86\xe4L\xc6\x00l\xb7OG\xf1\x19\xe04W2\x0c\x8c\xc5\xa6`X\xc8\xf4Q\x9d\xdb\x07F9\xeaS\xe8\xc7g\x0f\xe1;\xab\x99\x18Xn\x03rdm!'
        3
        (
            'TLObject'
        )
        (
            'TLRequest'
        )
        0
        (
            'Optional'
            'List'
            'Union'
            'TYPE_CHECKING'
        )
        None
        (
            'datetime'
        )
        (
            'TypeChannelMessagesFilter'
            'TypeInputChannel'
        )
        [Code]
            File Name: <frozen multithon.tl.functions.updates>
            Object Name: GetChannelDifferenceRequest
            Qualified Name: GetChannelDifferenceRequest
            Arg Count: 0
            Pos Only Arg Count: 0
            KW Only Arg Count: 0
            Stack Size: 12
            Flags: 0x20000000 (CO_PYARMOR_OBFUSCATED)
            [Names]
                '__name__'
                '__module__'
                '__qualname__'
                '__assert_armored__'
                'CONSTRUCTOR_ID'
                'SUBCLASS_OF_ID'
                'int'
                'Optional'
                'bool'
                '__init__'
                'resolve'
                'to_dict'
                '_bytes'
                'classmethod'
                'from_reader'
            [Locals+Names]
            [Constants]
                'GetChannelDifferenceRequest'
                '__pyarmor_assert_36690__'
                '__pyarmor_enter_36691__'
                b'<COAddr>\x07\x00\x00"|\x00\x00\x00\x00\x00\x00\x00\x00\x00\x00\x00\x00\x00\x00\x00'
                51854712
                696872797
                None
                'channel'
                'TypeInputChannel'   # b'\x81\xd6\x01\x036\xd3\xb0\xc2\x0e\xee.\xc8m\xe2\xf6\x80\x03'
                'filter'
                'TypeChannelMessagesFilter'   # b'\x81\xd6\x01\x036\xd9\xb6\xd3\x15\xf4\x08\xccA\xe9\xeb\x96\x0eZ\xbe\xb4\x8c\xc2B\xd8\x00}'
                'pts'
                'limit'
                'force'
                [Code]
                    File Name: <frozen multithon.tl.functions.updates>
                    Object Name: __init__
                    Qualified Name: GetChannelDifferenceRequest.__init__
                    Arg Count: 6
                    Pos Only Arg Count: 0
                    KW Only Arg Count: 0
                    Stack Size: 5
                    Flags: 0x20000003 (CO_OPTIMIZED | CO_NEWLOCALS | CO_PYARMOR_OBFUSCATED)
                    [Names]
                        'channel'
                        'filter'
                        'pts'
                        'limit'
                        'force'
                    [Locals+Names]
                        'self'
                        'channel'
                        'filter'
                        'pts'
                        'limit'
                        'force'
                        '__assert_armored__'
                    [Constants]
                        '\n        :returns updates.ChannelDifference: Instance of either ChannelDifferenceEmpty, ChannelDifferenceTooLong, ChannelDifference.\n        '
                        '__pyarmor_assert_36693__'
                        '__pyarmor_enter_36694__'
                        b'<COAddr>\x07\x00\x00\x1a\\\x00\x00\x00\x00\x00\x00\x00\x00\x00\x00\x00\x00\x00\x00\x00'
                        '__pyarmor_exit_36695__'
                        None
                    [Disassembly]
                        0       NOP                             
                        2       NOP                             
                        4       PUSH_NULL                       
                        6       LOAD_CONST                      2: '__pyarmor_enter_36694__'
                        8       LOAD_CONST                      3: b'<COAddr>\x07\x00\x00\x1a\\\x00\x00\x00\x00\x00\x00\x00\x00\x00\x00\x00\x00\x00\x00\x00'
                        10      BUILD_TUPLE                     1
                        12      CALL_FUNCTION_EX                0
                        14      POP_TOP                         
                        16      RESUME                          0
                        18      NOP                             
                        20      NOP                             
                        22      NOP                             
                        24      NOP                             
                        26      NOP                             
                        28      LOAD_FAST                       1: channel
                        30      LOAD_FAST                       0: self
                        32      STORE_ATTR                      0: channel
                        42      LOAD_FAST                       2: filter
                        44      LOAD_FAST                       0: self
                        46      STORE_ATTR                      1: filter
                        56      LOAD_FAST                       3: pts
                        58      LOAD_FAST                       0: self
                        60      STORE_ATTR                      2: pts
                        70      LOAD_FAST                       4: limit
                        72      LOAD_FAST                       0: self
                        74      STORE_ATTR                      3: limit
                        84      LOAD_FAST                       5: force
                        86      LOAD_FAST                       0: self
                        88      STORE_ATTR                      4: force
                        98      LOAD_CONST                      5: None
                        100     NOP                             
                        102     NOP                             
                        104     NOP                             
                        106     JUMP_FORWARD                    19 (to 146)
                        114     POP_TOP                         
                        116     RETURN_CONST                    5: None
                        118     PUSH_EXC_INFO                   
                        120     PUSH_NULL                       
                        122     LOAD_CONST                      4: '__pyarmor_exit_36695__'
                        124     NOP                             
                        126     LOAD_CONST                      3: b'<COAddr>\x07\x00\x00\x1a\\\x00\x00\x00\x00\x00\x00\x00\x00\x00\x00\x00\x00\x00\x00\x00'
                        128     CALL                            1
                        136     POP_TOP                         
                        138     RERAISE                         0
                        140     COPY                            3
                        142     POP_EXCEPT                      
                        144     RERAISE                         1
                        146     PUSH_NULL                       
                        148     LOAD_CONST                      4: '__pyarmor_exit_36695__'
                        150     LOAD_CONST                      3: b'<COAddr>\x07\x00\x00\x1a\\\x00\x00\x00\x00\x00\x00\x00\x00\x00\x00\x00\x00\x00\x00\x00'
                        152     BUILD_TUPLE                     1
                        154     CALL_FUNCTION_EX                0
                        156     POP_TOP                         
                        158     RETURN_VALUE                    
                    [Exception Table]
                        28 to 98 -> 118 [0] 
                        118 to 140 -> 140 [1] lasti
                [Code]
                    File Name: <frozen multithon.tl.functions.updates>
                    Object Name: resolve
                    Qualified Name: GetChannelDifferenceRequest.resolve
                    Arg Count: 3
                    Pos Only Arg Count: 0
                    KW Only Arg Count: 0
                    Stack Size: 5
                    Flags: 0x20000083 (CO_OPTIMIZED | CO_NEWLOCALS | CO_COROUTINE | CO_PYARMOR_OBFUSCATED)
                    [Names]
                        'get_input_channel'
                        'get_input_entity'
                        'channel'
                    [Locals+Names]
                        'self'
                        'client'
                        'utils'
                        '__assert_armored__'
                    [Constants]
                        None
                        '__pyarmor_assert_36696__'
                        '__pyarmor_enter_36697__'
                        b'<COAddr>\x07\x00\x00\x1e\x88\x00\x00\x00\x00\x00\x00\x00\x00\x00\x00\x00\x00\x00\x00\x00'
                        '__pyarmor_exit_36698__'
                    [Disassembly]
                        0       RETURN_GENERATOR                
                        2       POP_TOP                         
                        4       NOP                             
                        6       NOP                             
                        8       PUSH_NULL                       
                        10      LOAD_CONST                      2: '__pyarmor_enter_36697__'
                        12      LOAD_CONST                      3: b'<COAddr>\x07\x00\x00\x1e\x88\x00\x00\x00\x00\x00\x00\x00\x00\x00\x00\x00\x00\x00\x00\x00'
                        14      BUILD_TUPLE                     1
                        16      CALL_FUNCTION_EX                0
                        18      POP_TOP                         
                        20      RESUME                          0
                        22      NOP                             
                        24      NOP                             
                        26      NOP                             
                        28      NOP                             
                        30      NOP                             
                        32      LOAD_FAST                       2: utils
                        34      LOAD_ATTR                       1: get_input_channel
                        54      LOAD_FAST                       1: client
                        56      LOAD_ATTR                       3: get_input_entity
                        76      LOAD_FAST                       0: self
                        78      LOAD_ATTR                       4: channel
                        98      CALL                            1
                        106     GET_AWAITABLE                   0
                        108     LOAD_CONST                      0: None
                        110     SEND                            3 (to 118)
                        114     YIELD_VALUE                     3
                        116     RESUME                          3
                        118     JUMP_BACKWARD_NO_INTERRUPT      5 (to 110)
                        120     END_SEND                        
                        122     CALL                            1
                        130     LOAD_FAST                       0: self
                        132     STORE_ATTR                      2: channel
                        142     LOAD_CONST                      0: None
                        144     NOP                             
                        146     NOP                             
                        148     NOP                             
                        150     JUMP_FORWARD                    23 (to 198)
                        158     POP_TOP                         
                        160     RETURN_CONST                    0: None
                        162     CLEANUP_THROW                   
                        164     JUMP_BACKWARD                   23 (to 120)
                        166     PUSH_EXC_INFO                   
                        168     PUSH_NULL                       
                        170     LOAD_CONST                      4: '__pyarmor_exit_36698__'
                        172     NOP                             
                        174     LOAD_CONST                      3: b'<COAddr>\x07\x00\x00\x1e\x88\x00\x00\x00\x00\x00\x00\x00\x00\x00\x00\x00\x00\x00\x00\x00'
                        176     CALL                            1
                        184     POP_TOP                         
                        186     RERAISE                         0
                        188     COPY                            3
                        190     POP_EXCEPT                      
                        192     RERAISE                         1
                        194     CALL_INTRINSIC_1                3 (INTRINSIC_STOPITERATION_ERROR)
                        196     RERAISE                         1
                        198     PUSH_NULL                       
                        200     LOAD_CONST                      4: '__pyarmor_exit_36698__'
                        202     LOAD_CONST                      3: b'<COAddr>\x07\x00\x00\x1e\x88\x00\x00\x00\x00\x00\x00\x00\x00\x00\x00\x00\x00\x00\x00\x00'
                        204     BUILD_TUPLE                     1
                        206     CALL_FUNCTION_EX                0
                        208     POP_TOP                         
                        210     RETURN_VALUE                    
                    [Exception Table]
                        4 to 30 -> 194 [0] lasti
                        32 to 114 -> 166 [0] 
                        114 to 116 -> 162 [4] 
                        116 to 142 -> 166 [0] 
                        142 to 162 -> 194 [0] lasti
                        162 to 164 -> 166 [0] 
                        166 to 188 -> 188 [1] lasti
                        188 to 194 -> 194 [0] lasti
                [Code]
                    File Name: <frozen multithon.tl.functions.updates>
                    Object Name: to_dict
                    Qualified Name: GetChannelDifferenceRequest.to_dict
                    Arg Count: 1
                    Pos Only Arg Count: 0
                    KW Only Arg Count: 0
                    Stack Size: 7
                    Flags: 0x20000003 (CO_OPTIMIZED | CO_NEWLOCALS | CO_PYARMOR_OBFUSCATED)
                    [Names]
                        'isinstance'
                        'channel'
                        'TLObject'
                        'to_dict'
                        'filter'
                        'pts'
                        'limit'
                        'force'
                    [Locals+Names]
                        'self'
                        '__assert_armored__'
                    [Constants]
                        None
                        '__pyarmor_assert_36699__'
                        '__pyarmor_enter_36700__'
                        b'<COAddr>\x05\x00\x00\x1af\x01\x00\x00\x00\x00\x00\x00\x00\x00\x00\x00\x00\x00\x00\x00'
                        'GetChannelDifferenceRequest'   # b'\x81\xc5\x1d\x07\x10\xf2\xbf\xdc\x15\xff\x01\xe4e\xea\xfe\x80\x1dX\xb5\xa4\xaf\xf9K\xdd\x10j\xb0H'
                        (
                            '_'
                            'channel'
                            'filter'
                            'pts'
                            'limit'
                            'force'
                        )
                        '__pyarmor_exit_36701__'
                    [Disassembly]
                        0       NOP                             
                        2       NOP                             
                        4       PUSH_NULL                       
                        6       LOAD_CONST                      2: '__pyarmor_enter_36700__'
                        8       LOAD_CONST                      3: b'<COAddr>\x05\x00\x00\x1af\x01\x00\x00\x00\x00\x00\x00\x00\x00\x00\x00\x00\x00\x00\x00'
                        10      BUILD_TUPLE                     1
                        12      CALL_FUNCTION_EX                0
                        14      POP_TOP                         
                        16      RESUME                          0
                        18      NOP                             
                        20      NOP                             
                        22      NOP                             
                        24      NOP                             
                        26      NOP                             
                        28      PUSH_NULL                       
                        30      LOAD_CONST                      1: '__pyarmor_assert_36699__'
                        32      LOAD_CONST                      4: 'GetChannelDifferenceRequest'   # b'\x81\xc5\x1d\x07\x10\xf2\xbf\xdc\x15\xff\x01\xe4e\xea\xfe\x80\x1dX\xb5\xa4\xaf\xf9K\xdd\x10j\xb0H'
                        34      CALL                            1
                        42      LOAD_GLOBAL                     1: NULL + isinstance
                        52      LOAD_FAST                       0: self
                        54      LOAD_ATTR                       2: channel
                        74      LOAD_GLOBAL                     4: TLObject
                        84      CALL                            2
                        92      POP_JUMP_IF_FALSE               26 (to 146)
                        94      LOAD_FAST                       0: self
                        96      LOAD_ATTR                       2: channel
                        116     LOAD_ATTR                       7: to_dict
                        136     CALL                            0
                        144     JUMP_FORWARD                    11 (to 168)
                        146     LOAD_FAST                       0: self
                        148     LOAD_ATTR                       2: channel
                        168     LOAD_GLOBAL                     1: NULL + isinstance
                        178     LOAD_FAST                       0: self
                        180     LOAD_ATTR                       8: filter
                        200     LOAD_GLOBAL                     4: TLObject
                        210     CALL                            2
                        218     POP_JUMP_IF_FALSE               26 (to 272)
                        220     LOAD_FAST                       0: self
                        222     LOAD_ATTR                       8: filter
                        242     LOAD_ATTR                       7: to_dict
                        262     CALL                            0
                        270     JUMP_FORWARD                    11 (to 294)
                        272     LOAD_FAST                       0: self
                        274     LOAD_ATTR                       8: filter
                        294     LOAD_FAST                       0: self
                        296     LOAD_ATTR                       10: pts
                        316     LOAD_FAST                       0: self
                        318     LOAD_ATTR                       12: limit
                        338     LOAD_FAST                       0: self
                        340     LOAD_ATTR                       14: force
                        360     LOAD_CONST                      5: ('_', 'channel', 'filter', 'pts', 'limit', 'force')
                        362     BUILD_CONST_KEY_MAP             6
                        364     NOP                             
                        366     NOP                             
                        368     NOP                             
                        370     JUMP_FORWARD                    20 (to 412)
                        372     CALL                            1
                        380     POP_TOP                         
                        382     RETURN_VALUE                    
                        384     PUSH_EXC_INFO                   
                        386     PUSH_NULL                       
                        388     LOAD_CONST                      6: '__pyarmor_exit_36701__'
                        390     NOP                             
                        392     LOAD_CONST                      3: b'<COAddr>\x05\x00\x00\x1af\x01\x00\x00\x00\x00\x00\x00\x00\x00\x00\x00\x00\x00\x00\x00'
                        394     CALL                            1
                        402     POP_TOP                         
                        404     RERAISE                         0
                        406     COPY                            3
                        408     POP_EXCEPT                      
                        410     RERAISE                         1
                        412     PUSH_NULL                       
                        414     LOAD_CONST                      6: '__pyarmor_exit_36701__'
                        416     LOAD_CONST                      3: b'<COAddr>\x05\x00\x00\x1af\x01\x00\x00\x00\x00\x00\x00\x00\x00\x00\x00\x00\x00\x00\x00'
                        418     BUILD_TUPLE                     1
                        420     CALL_FUNCTION_EX                0
                        422     POP_TOP                         
                        424     RETURN_VALUE                    
                    [Exception Table]
                        28 to 364 -> 384 [0] 
                        384 to 406 -> 406 [1] lasti
                [Code]
                    File Name: <frozen multithon.tl.functions.updates>
                    Object Name: _bytes
                    Qualified Name: GetChannelDifferenceRequest._bytes
                    Arg Count: 1
                    Pos Only Arg Count: 0
                    KW Only Arg Count: 0
                    Stack Size: 11
                    Flags: 0x20000003 (CO_OPTIMIZED | CO_NEWLOCALS | CO_PYARMOR_OBFUSCATED)
                    [Names]
                        'join'
                        'struct'
                        'pack'
                        'force'
                        'channel'
                        '_bytes'
                        'filter'
                        'pts'
                        'limit'
                    [Locals+Names]
                        'self'
                        '__assert_armored__'
                    [Constants]
                        None
                        '__pyarmor_assert_36702__'
                        '__pyarmor_enter_36703__'
                        b'<COAddr>\x05\x00\x00\x1az\x01\x00\x00\x00\x00\x00\x00\x00\x00\x00\x00\x00\x00\x00\x00'
                        b''
                        b'x=\x17\x03'
                        '<I'
                        False
                        0
                        1
                        '<i'
                        '__pyarmor_exit_36704__'
                    [Disassembly]
                        0       NOP                             
                        2       NOP                             
                        4       PUSH_NULL                       
                        6       LOAD_CONST                      2: '__pyarmor_enter_36703__'
                        8       LOAD_CONST                      3: b'<COAddr>\x05\x00\x00\x1az\x01\x00\x00\x00\x00\x00\x00\x00\x00\x00\x00\x00\x00\x00\x00'
                        10      BUILD_TUPLE                     1
                        12      CALL_FUNCTION_EX                0
                        14      POP_TOP                         
                        16      RESUME                          0
                        18      NOP                             
                        20      NOP                             
                        22      NOP                             
                        24      NOP                             
                        26      NOP                             
                        28      LOAD_CONST                      4: b''
                        30      LOAD_ATTR                       1: join
                        50      LOAD_CONST                      5: b'x=\x17\x03'
                        52      LOAD_GLOBAL                     3: NULL + struct
                        62      LOAD_ATTR                       4: pack
                        82      LOAD_CONST                      6: '<I'
                        84      LOAD_FAST                       0: self
                        86      LOAD_ATTR                       6: force
                        106     POP_JUMP_IF_NONE                14 (to 136)
                        108     LOAD_FAST                       0: self
                        110     LOAD_ATTR                       6: force
                        130     LOAD_CONST                      7: False
                        132     IS_OP                           0 (is)
                        134     POP_JUMP_IF_FALSE               2 (to 140)
                        136     LOAD_CONST                      8: 0
                        138     JUMP_FORWARD                    1 (to 142)
                        140     LOAD_CONST                      9: 1
                        142     CALL                            2
                        150     LOAD_FAST                       0: self
                        152     LOAD_ATTR                       8: channel
                        172     LOAD_ATTR                       11: _bytes
                        192     CALL                            0
                        200     LOAD_FAST                       0: self
                        202     LOAD_ATTR                       12: filter
                        222     LOAD_ATTR                       11: _bytes
                        242     CALL                            0
                        250     LOAD_GLOBAL                     3: NULL + struct
                        260     LOAD_ATTR                       4: pack
                        280     LOAD_CONST                      10: '<i'
                        282     LOAD_FAST                       0: self
                        284     LOAD_ATTR                       14: pts
                        304     CALL                            2
                        312     LOAD_GLOBAL                     3: NULL + struct
                        322     LOAD_ATTR                       4: pack
                        342     LOAD_CONST                      10: '<i'
                        344     LOAD_FAST                       0: self
                        346     LOAD_ATTR                       16: limit
                        366     CALL                            2
                        374     BUILD_TUPLE                     6
                        376     CALL                            1
                        384     NOP                             
                        386     NOP                             
                        388     NOP                             
                        390     JUMP_FORWARD                    20 (to 432)
                        392     CALL                            1
                        400     POP_TOP                         
                        402     RETURN_VALUE                    
                        404     PUSH_EXC_INFO                   
                        406     PUSH_NULL                       
                        408     LOAD_CONST                      11: '__pyarmor_exit_36704__'
                        410     NOP                             
                        412     LOAD_CONST                      3: b'<COAddr>\x05\x00\x00\x1az\x01\x00\x00\x00\x00\x00\x00\x00\x00\x00\x00\x00\x00\x00\x00'
                        414     CALL                            1
                        422     POP_TOP                         
                        424     RERAISE                         0
                        426     COPY                            3
                        428     POP_EXCEPT                      
                        430     RERAISE                         1
                        432     PUSH_NULL                       
                        434     LOAD_CONST                      11: '__pyarmor_exit_36704__'
                        436     LOAD_CONST                      3: b'<COAddr>\x05\x00\x00\x1az\x01\x00\x00\x00\x00\x00\x00\x00\x00\x00\x00\x00\x00\x00\x00'
                        438     BUILD_TUPLE                     1
                        440     CALL_FUNCTION_EX                0
                        442     POP_TOP                         
                        444     RETURN_VALUE                    
                    [Exception Table]
                        28 to 384 -> 404 [0] 
                        404 to 426 -> 426 [1] lasti
                [Code]
                    File Name: <frozen multithon.tl.functions.updates>
                    Object Name: from_reader
                    Qualified Name: GetChannelDifferenceRequest.from_reader
                    Arg Count: 2
                    Pos Only Arg Count: 0
                    KW Only Arg Count: 0
                    Stack Size: 7
                    Flags: 0x20000003 (CO_OPTIMIZED | CO_NEWLOCALS | CO_PYARMOR_OBFUSCATED)
                    [Names]
                        'read_int'
                        'bool'
                        'tgread_object'
                    [Locals+Names]
                        'cls'
                        'reader'
                        '__assert_armored__'
                        '_var_var_0'
                        '_var_var_1'
                        '_var_var_2'
                        '_var_var_3'
                        '_var_var_4'
                        '_var_var_5'
                    [Constants]
                        None
                        '__pyarmor_assert_36705__'
                        '__pyarmor_enter_36706__'
                        b'<COAddr>\x07\x00\x00\x1a\xea\x00\x00\x00\x00\x00\x00\x00\x00\x00\x00\x00\x00\x00\x00\x00'
                        1
                        (
                            'channel'
                            'filter'
                            'pts'
                            'limit'
                            'force'
                        )
                        '__pyarmor_exit_36707__'
                    [Disassembly]
                        0       NOP                             
                        2       NOP                             
                        4       PUSH_NULL                       
                        6       LOAD_CONST                      2: '__pyarmor_enter_36706__'
                        8       LOAD_CONST                      3: b'<COAddr>\x07\x00\x00\x1a\xea\x00\x00\x00\x00\x00\x00\x00\x00\x00\x00\x00\x00\x00\x00\x00'
                        10      BUILD_TUPLE                     1
                        12      CALL_FUNCTION_EX                0
                        14      POP_TOP                         
                        16      RESUME                          0
                        18      NOP                             
                        20      NOP                             
                        22      NOP                             
                        24      NOP                             
                        26      NOP                             
                        28      LOAD_FAST                       1: reader
                        30      LOAD_ATTR                       1: read_int
                        50      CALL                            0
                        58      STORE_FAST                      3: _var_var_0
                        60      LOAD_GLOBAL                     3: NULL + bool
                        70      LOAD_FAST                       3: _var_var_0
                        72      LOAD_CONST                      4: 1
                        74      BINARY_OP                       1 (&)
                        78      CALL                            1
                        86      STORE_FAST                      4: _var_var_1
                        88      LOAD_FAST                       1: reader
                        90      LOAD_ATTR                       5: tgread_object
                        110     CALL                            0
                        118     STORE_FAST                      5: _var_var_2
                        120     LOAD_FAST                       1: reader
                        122     LOAD_ATTR                       5: tgread_object
                        142     CALL                            0
                        150     STORE_FAST                      6: _var_var_3
                        152     LOAD_FAST                       1: reader
                        154     LOAD_ATTR                       1: read_int
                        174     CALL                            0
                        182     STORE_FAST                      7: _var_var_4
                        184     LOAD_FAST                       1: reader
                        186     LOAD_ATTR                       1: read_int
                        206     CALL                            0
                        214     STORE_FAST                      8: _var_var_5
                        216     PUSH_NULL                       
                        218     LOAD_FAST                       0: cls
                        220     LOAD_FAST                       5: _var_var_2
                        222     LOAD_FAST                       6: _var_var_3
                        224     LOAD_FAST                       7: _var_var_4
                        226     LOAD_FAST                       8: _var_var_5
                        228     LOAD_FAST                       4: _var_var_1
                        230     KW_NAMES                        5: ('channel', 'filter', 'pts', 'limit', 'force')
                        232     CALL                            5
                        240     NOP                             
                        242     NOP                             
                        244     NOP                             
                        246     JUMP_FORWARD                    20 (to 288)
                        248     CALL                            1
                        256     POP_TOP                         
                        258     RETURN_VALUE                    
                        260     PUSH_EXC_INFO                   
                        262     PUSH_NULL                       
                        264     LOAD_CONST                      6: '__pyarmor_exit_36707__'
                        266     NOP                             
                        268     LOAD_CONST                      3: b'<COAddr>\x07\x00\x00\x1a\xea\x00\x00\x00\x00\x00\x00\x00\x00\x00\x00\x00\x00\x00\x00\x00'
                        270     CALL                            1
                        278     POP_TOP                         
                        280     RERAISE                         0
                        282     COPY                            3
                        284     POP_EXCEPT                      
                        286     RERAISE                         1
                        288     PUSH_NULL                       
                        290     LOAD_CONST                      6: '__pyarmor_exit_36707__'
                        292     LOAD_CONST                      3: b'<COAddr>\x07\x00\x00\x1a\xea\x00\x00\x00\x00\x00\x00\x00\x00\x00\x00\x00\x00\x00\x00\x00'
                        294     BUILD_TUPLE                     1
                        296     CALL_FUNCTION_EX                0
                        298     POP_TOP                         
                        300     RETURN_VALUE                    
                    [Exception Table]
                        28 to 240 -> 260 [0] 
                        260 to 282 -> 282 [1] lasti
                '__pyarmor_exit_36692__'
                (
                    None
                )
            [Disassembly]
                0       NOP                             
                2       LOAD_NAME                       0: __name__
                4       STORE_NAME                      1: __module__
                6       LOAD_CONST                      0: 'GetChannelDifferenceRequest'
                8       STORE_NAME                      2: __qualname__
                10      NOP                             
                12      PUSH_NULL                       
                14      LOAD_CONST                      2: '__pyarmor_enter_36691__'
                16      LOAD_CONST                      3: b'<COAddr>\x07\x00\x00"|\x00\x00\x00\x00\x00\x00\x00\x00\x00\x00\x00\x00\x00\x00\x00'
                18      BUILD_TUPLE                     1
                20      CALL_FUNCTION_EX                0
                22      POP_TOP                         
                24      RESUME                          0
                26      NOP                             
                28      NOP                             
                30      NOP                             
                32      NOP                             
                34      NOP                             
                36      LOAD_CONST                      4: 51854712
                38      STORE_NAME                      4: CONSTRUCTOR_ID
                40      LOAD_CONST                      5: 696872797
                42      STORE_NAME                      5: SUBCLASS_OF_ID
                44      LOAD_CONST                      20: (None,)
                46      LOAD_CONST                      7: 'channel'
                48      PUSH_NULL                       
                50      LOAD_CONST                      1: '__pyarmor_assert_36690__'
                52      LOAD_CONST                      8: 'TypeInputChannel'   # b'\x81\xd6\x01\x036\xd3\xb0\xc2\x0e\xee.\xc8m\xe2\xf6\x80\x03'
                54      CALL                            1
                62      LOAD_CONST                      9: 'filter'
                64      PUSH_NULL                       
                66      LOAD_CONST                      1: '__pyarmor_assert_36690__'
                68      LOAD_CONST                      10: 'TypeChannelMessagesFilter'   # b'\x81\xd6\x01\x036\xd9\xb6\xd3\x15\xf4\x08\xccA\xe9\xeb\x96\x0eZ\xbe\xb4\x8c\xc2B\xd8\x00}'
                70      CALL                            1
                78      LOAD_CONST                      11: 'pts'
                80      LOAD_NAME                       6: int
                82      LOAD_CONST                      12: 'limit'
                84      LOAD_NAME                       6: int
                86      LOAD_CONST                      13: 'force'
                88      LOAD_NAME                       7: Optional
                90      LOAD_NAME                       8: bool
                92      BINARY_SUBSCR                   
                96      BUILD_TUPLE                     10
                98      LOAD_CONST                      14: <CODE> __init__
                100     MAKE_FUNCTION                   5
                102     STORE_NAME                      9: __init__
                104     LOAD_CONST                      15: <CODE> resolve
                106     MAKE_FUNCTION                   0
                108     STORE_NAME                      10: resolve
                110     LOAD_CONST                      16: <CODE> to_dict
                112     MAKE_FUNCTION                   0
                114     STORE_NAME                      11: to_dict
                116     LOAD_CONST                      17: <CODE> _bytes
                118     MAKE_FUNCTION                   0
                120     STORE_NAME                      12: _bytes
                122     LOAD_NAME                       13: classmethod
                124     LOAD_CONST                      18: <CODE> from_reader
                126     MAKE_FUNCTION                   0
                128     CALL                            0
                136     STORE_NAME                      14: from_reader
                138     LOAD_CONST                      6: None
                140     NOP                             
                142     NOP                             
                144     NOP                             
                146     JUMP_FORWARD                    19 (to 186)
                154     POP_TOP                         
                156     RETURN_CONST                    6: None
                158     PUSH_EXC_INFO                   
                160     PUSH_NULL                       
                162     LOAD_CONST                      19: '__pyarmor_exit_36692__'
                164     NOP                             
                166     LOAD_CONST                      3: b'<COAddr>\x07\x00\x00"|\x00\x00\x00\x00\x00\x00\x00\x00\x00\x00\x00\x00\x00\x00\x00'
                168     CALL                            1
                176     POP_TOP                         
                178     RERAISE                         0
                180     COPY                            3
                182     POP_EXCEPT                      
                184     RERAISE                         1
                186     PUSH_NULL                       
                188     LOAD_CONST                      19: '__pyarmor_exit_36692__'
                190     LOAD_CONST                      3: b'<COAddr>\x07\x00\x00"|\x00\x00\x00\x00\x00\x00\x00\x00\x00\x00\x00\x00\x00\x00\x00'
                192     BUILD_TUPLE                     1
                194     CALL_FUNCTION_EX                0
                196     POP_TOP                         
                198     RETURN_VALUE                    
            [Exception Table]
                36 to 138 -> 158 [0] 
                158 to 180 -> 180 [1] lasti
        'GetChannelDifferenceRequest'
        [Code]
            File Name: <frozen multithon.tl.functions.updates>
            Object Name: GetDifferenceRequest
            Qualified Name: GetDifferenceRequest
            Arg Count: 0
            Pos Only Arg Count: 0
            KW Only Arg Count: 0
            Stack Size: 14
            Flags: 0x20000000 (CO_PYARMOR_OBFUSCATED)
            [Names]
                '__name__'
                '__module__'
                '__qualname__'
                '__assert_armored__'
                'CONSTRUCTOR_ID'
                'SUBCLASS_OF_ID'
                'int'
                'Optional'
                'datetime'
                '__init__'
                'to_dict'
                '_bytes'
                'classmethod'
                'from_reader'
            [Locals+Names]
            [Constants]
                'GetDifferenceRequest'
                '__pyarmor_assert_36708__'
                '__pyarmor_enter_36709__'
                b'<COAddr>\x05\x00\x00"t\x00\x00\x00\x00\x00\x00\x00\x00\x00\x00\x00\x00\x00\x00\x00'
                630429265
                541599860
                None
                'pts'
                'date'
                'qts'
                'pts_limit'
                'pts_total_limit'
                'qts_limit'
                [Code]
                    File Name: <frozen multithon.tl.functions.updates>
                    Object Name: __init__
                    Qualified Name: GetDifferenceRequest.__init__
                    Arg Count: 7
                    Pos Only Arg Count: 0
                    KW Only Arg Count: 0
                    Stack Size: 5
                    Flags: 0x20000003 (CO_OPTIMIZED | CO_NEWLOCALS | CO_PYARMOR_OBFUSCATED)
                    [Names]
                        'pts'
                        'date'
                        'qts'
                        'pts_limit'
                        'pts_total_limit'
                        'qts_limit'
                    [Locals+Names]
                        'self'
                        'pts'
                        'date'
                        'qts'
                        'pts_limit'
                        'pts_total_limit'
                        'qts_limit'
                        '__assert_armored__'
                    [Constants]
                        '\n        :returns updates.Difference: Instance of either DifferenceEmpty, Difference, DifferenceSlice, DifferenceTooLong.\n        '
                        '__pyarmor_assert_36711__'
                        '__pyarmor_enter_36712__'
                        b'<COAddr>\x05\x00\x00\x1aj\x00\x00\x00\x00\x00\x00\x00\x00\x00\x00\x00\x00\x00\x00\x00'
                        '__pyarmor_exit_36713__'
                        None
                    [Disassembly]
                        0       NOP                             
                        2       NOP                             
                        4       PUSH_NULL                       
                        6       LOAD_CONST                      2: '__pyarmor_enter_36712__'
                        8       LOAD_CONST                      3: b'<COAddr>\x05\x00\x00\x1aj\x00\x00\x00\x00\x00\x00\x00\x00\x00\x00\x00\x00\x00\x00\x00'
                        10      BUILD_TUPLE                     1
                        12      CALL_FUNCTION_EX                0
                        14      POP_TOP                         
                        16      RESUME                          0
                        18      NOP                             
                        20      NOP                             
                        22      NOP                             
                        24      NOP                             
                        26      NOP                             
                        28      LOAD_FAST                       1: pts
                        30      LOAD_FAST                       0: self
                        32      STORE_ATTR                      0: pts
                        42      LOAD_FAST                       2: date
                        44      LOAD_FAST                       0: self
                        46      STORE_ATTR                      1: date
                        56      LOAD_FAST                       3: qts
                        58      LOAD_FAST                       0: self
                        60      STORE_ATTR                      2: qts
                        70      LOAD_FAST                       4: pts_limit
                        72      LOAD_FAST                       0: self
                        74      STORE_ATTR                      3: pts_limit
                        84      LOAD_FAST                       5: pts_total_limit
                        86      LOAD_FAST                       0: self
                        88      STORE_ATTR                      4: pts_total_limit
                        98      LOAD_FAST                       6: qts_limit
                        100     LOAD_FAST                       0: self
                        102     STORE_ATTR                      5: qts_limit
                        112     LOAD_CONST                      5: None
                        114     NOP                             
                        116     NOP                             
                        118     NOP                             
                        120     JUMP_FORWARD                    19 (to 160)
                        128     POP_TOP                         
                        130     RETURN_CONST                    5: None
                        132     PUSH_EXC_INFO                   
                        134     PUSH_NULL                       
                        136     LOAD_CONST                      4: '__pyarmor_exit_36713__'
                        138     NOP                             
                        140     LOAD_CONST                      3: b'<COAddr>\x05\x00\x00\x1aj\x00\x00\x00\x00\x00\x00\x00\x00\x00\x00\x00\x00\x00\x00\x00'
                        142     CALL                            1
                        150     POP_TOP                         
                        152     RERAISE                         0
                        154     COPY                            3
                        156     POP_EXCEPT                      
                        158     RERAISE                         1
                        160     PUSH_NULL                       
                        162     LOAD_CONST                      4: '__pyarmor_exit_36713__'
                        164     LOAD_CONST                      3: b'<COAddr>\x05\x00\x00\x1aj\x00\x00\x00\x00\x00\x00\x00\x00\x00\x00\x00\x00\x00\x00\x00'
                        166     BUILD_TUPLE                     1
                        168     CALL_FUNCTION_EX                0
                        170     POP_TOP                         
                        172     RETURN_VALUE                    
                    [Exception Table]
                        28 to 112 -> 132 [0] 
                        132 to 154 -> 154 [1] lasti
                [Code]
                    File Name: <frozen multithon.tl.functions.updates>
                    Object Name: to_dict
                    Qualified Name: GetDifferenceRequest.to_dict
                    Arg Count: 1
                    Pos Only Arg Count: 0
                    KW Only Arg Count: 0
                    Stack Size: 15
                    Flags: 0x20000003 (CO_OPTIMIZED | CO_NEWLOCALS | CO_PYARMOR_OBFUSCATED)
                    [Names]
                        'pts'
                        'date'
                        'qts'
                        'pts_limit'
                        'pts_total_limit'
                        'qts_limit'
                    [Locals+Names]
                        'self'
                        '__assert_armored__'
                    [Constants]
                        None
                        '__pyarmor_assert_36714__'
                        '__pyarmor_enter_36715__'
                        b'<COAddr>\x05\x00\x00\x1a\xdc\x00\x00\x00\x00\x00\x00\x00\x00\x00\x00\x00\x00\x00\x00\x00'
                        '_'
                        'GetDifferenceRequest'   # b'\x81\xc5\x1d\x07\x17\xf3\xb8\xd4\x1e\xe8\x08\xceo\xe9\xca\x80\x1eH\xbe\xb4\xbe'
                        'pts'
                        'date'
                        'qts'
                        'pts_limit'   # b'\x81\xf2\x0c\x00\x0c\xf6\xb7\xdf\x12\xee'
                        'pts_total_limit'   # b'\x81\xf2\x0c\x00\x0c\xee\xb1\xc6\x1a\xf62\xcce\xe1\xf1\x91'
                        'qts_limit'   # b'\x81\xf3\x0c\x00\x0c\xf6\xb7\xdf\x12\xee'
                        '__pyarmor_exit_36716__'
                    [Disassembly]
                        0       NOP                             
                        2       NOP                             
                        4       PUSH_NULL                       
                        6       LOAD_CONST                      2: '__pyarmor_enter_36715__'
                        8       LOAD_CONST                      3: b'<COAddr>\x05\x00\x00\x1a\xdc\x00\x00\x00\x00\x00\x00\x00\x00\x00\x00\x00\x00\x00\x00\x00'
                        10      BUILD_TUPLE                     1
                        12      CALL_FUNCTION_EX                0
                        14      POP_TOP                         
                        16      RESUME                          0
                        18      NOP                             
                        20      NOP                             
                        22      NOP                             
                        24      NOP                             
                        26      NOP                             
                        28      LOAD_CONST                      4: '_'
                        30      PUSH_NULL                       
                        32      LOAD_CONST                      1: '__pyarmor_assert_36714__'
                        34      LOAD_CONST                      5: 'GetDifferenceRequest'   # b'\x81\xc5\x1d\x07\x17\xf3\xb8\xd4\x1e\xe8\x08\xceo\xe9\xca\x80\x1eH\xbe\xb4\xbe'
                        36      CALL                            1
                        44      LOAD_CONST                      6: 'pts'
                        46      LOAD_FAST                       0: self
                        48      LOAD_ATTR                       0: pts
                        68      LOAD_CONST                      7: 'date'
                        70      LOAD_FAST                       0: self
                        72      LOAD_ATTR                       2: date
                        92      LOAD_CONST                      8: 'qts'
                        94      LOAD_FAST                       0: self
                        96      LOAD_ATTR                       4: qts
                        116     PUSH_NULL                       
                        118     LOAD_CONST                      1: '__pyarmor_assert_36714__'
                        120     LOAD_CONST                      9: 'pts_limit'   # b'\x81\xf2\x0c\x00\x0c\xf6\xb7\xdf\x12\xee'
                        122     CALL                            1
                        130     LOAD_FAST                       0: self
                        132     LOAD_ATTR                       6: pts_limit
                        152     PUSH_NULL                       
                        154     LOAD_CONST                      1: '__pyarmor_assert_36714__'
                        156     LOAD_CONST                      10: 'pts_total_limit'   # b'\x81\xf2\x0c\x00\x0c\xee\xb1\xc6\x1a\xf62\xcce\xe1\xf1\x91'
                        158     CALL                            1
                        166     LOAD_FAST                       0: self
                        168     LOAD_ATTR                       8: pts_total_limit
                        188     PUSH_NULL                       
                        190     LOAD_CONST                      1: '__pyarmor_assert_36714__'
                        192     LOAD_CONST                      11: 'qts_limit'   # b'\x81\xf3\x0c\x00\x0c\xf6\xb7\xdf\x12\xee'
                        194     CALL                            1
                        202     LOAD_FAST                       0: self
                        204     LOAD_ATTR                       10: qts_limit
                        224     BUILD_MAP                       7
                        226     NOP                             
                        228     NOP                             
                        230     NOP                             
                        232     JUMP_FORWARD                    20 (to 274)
                        234     CALL                            1
                        242     POP_TOP                         
                        244     RETURN_VALUE                    
                        246     PUSH_EXC_INFO                   
                        248     PUSH_NULL                       
                        250     LOAD_CONST                      12: '__pyarmor_exit_36716__'
                        252     NOP                             
                        254     LOAD_CONST                      3: b'<COAddr>\x05\x00\x00\x1a\xdc\x00\x00\x00\x00\x00\x00\x00\x00\x00\x00\x00\x00\x00\x00\x00'
                        256     CALL                            1
                        264     POP_TOP                         
                        266     RERAISE                         0
                        268     COPY                            3
                        270     POP_EXCEPT                      
                        272     RERAISE                         1
                        274     PUSH_NULL                       
                        276     LOAD_CONST                      12: '__pyarmor_exit_36716__'
                        278     LOAD_CONST                      3: b'<COAddr>\x05\x00\x00\x1a\xdc\x00\x00\x00\x00\x00\x00\x00\x00\x00\x00\x00\x00\x00\x00\x00'
                        280     BUILD_TUPLE                     1
                        282     CALL_FUNCTION_EX                0
                        284     POP_TOP                         
                        286     RETURN_VALUE                    
                    [Exception Table]
                        28 to 226 -> 246 [0] 
                        246 to 268 -> 268 [1] lasti
                [Code]
                    File Name: <frozen multithon.tl.functions.updates>
                    Object Name: _bytes
                    Qualified Name: GetDifferenceRequest._bytes
                    Arg Count: 1
                    Pos Only Arg Count: 0
                    KW Only Arg Count: 0
                    Stack Size: 13
                    Flags: 0x20000003 (CO_OPTIMIZED | CO_NEWLOCALS | CO_PYARMOR_OBFUSCATED)
                    [Names]
                        'join'
                        'struct'
                        'pack'
                        'pts_limit'
                        'pts_total_limit'
                        'qts_limit'
                        'pts'
                        'serialize_datetime'
                        'date'
                        'qts'
                    [Locals+Names]
                        'self'
                        '__assert_armored__'
                    [Constants]
                        None
                        '__pyarmor_assert_36717__'
                        '__pyarmor_enter_36718__'
                        b'<COAddr>\x07\x00\x00\x1a(\x03\x00\x00\x00\x00\x00\x00\x00\x00\x00\x00\x00\x00\x00\x00'
                        b''
                        b'Q\x96\x93%'
                        '<I'
                        False
                        0
                        2
                        1
                        4
                        '<i'
                        '__pyarmor_exit_36719__'
                    [Disassembly]
                        0       NOP                             
                        2       NOP                             
                        4       PUSH_NULL                       
                        6       LOAD_CONST                      2: '__pyarmor_enter_36718__'
                        8       LOAD_CONST                      3: b'<COAddr>\x07\x00\x00\x1a(\x03\x00\x00\x00\x00\x00\x00\x00\x00\x00\x00\x00\x00\x00\x00'
                        10      BUILD_TUPLE                     1
                        12      CALL_FUNCTION_EX                0
                        14      POP_TOP                         
                        16      RESUME                          0
                        18      NOP                             
                        20      NOP                             
                        22      NOP                             
                        24      NOP                             
                        26      NOP                             
                        28      LOAD_CONST                      4: b''
                        30      LOAD_ATTR                       1: join
                        50      LOAD_CONST                      5: b'Q\x96\x93%'
                        52      LOAD_GLOBAL                     3: NULL + struct
                        62      LOAD_ATTR                       4: pack
                        82      LOAD_CONST                      6: '<I'
                        84      LOAD_FAST                       0: self
                        86      LOAD_ATTR                       6: pts_limit
                        106     POP_JUMP_IF_NONE                14 (to 136)
                        108     LOAD_FAST                       0: self
                        110     LOAD_ATTR                       6: pts_limit
                        130     LOAD_CONST                      7: False
                        132     IS_OP                           0 (is)
                        134     POP_JUMP_IF_FALSE               2 (to 140)
                        136     LOAD_CONST                      8: 0
                        138     JUMP_FORWARD                    1 (to 142)
                        140     LOAD_CONST                      9: 2
                        142     LOAD_FAST                       0: self
                        144     LOAD_ATTR                       8: pts_total_limit
                        164     POP_JUMP_IF_NONE                14 (to 194)
                        166     LOAD_FAST                       0: self
                        168     LOAD_ATTR                       8: pts_total_limit
                        188     LOAD_CONST                      7: False
                        190     IS_OP                           0 (is)
                        192     POP_JUMP_IF_FALSE               2 (to 198)
                        194     LOAD_CONST                      8: 0
                        196     JUMP_FORWARD                    1 (to 200)
                        198     LOAD_CONST                      10: 1
                        200     BINARY_OP                       7 (|)
                        204     LOAD_FAST                       0: self
                        206     LOAD_ATTR                       10: qts_limit
                        226     POP_JUMP_IF_NONE                14 (to 256)
                        228     LOAD_FAST                       0: self
                        230     LOAD_ATTR                       10: qts_limit
                        250     LOAD_CONST                      7: False
                        252     IS_OP                           0 (is)
                        254     POP_JUMP_IF_FALSE               2 (to 260)
                        256     LOAD_CONST                      8: 0
                        258     JUMP_FORWARD                    1 (to 262)
                        260     LOAD_CONST                      11: 4
                        262     BINARY_OP                       7 (|)
                        266     CALL                            2
                        274     LOAD_GLOBAL                     3: NULL + struct
                        284     LOAD_ATTR                       4: pack
                        304     LOAD_CONST                      12: '<i'
                        306     LOAD_FAST                       0: self
                        308     LOAD_ATTR                       12: pts
                        328     CALL                            2
                        336     LOAD_FAST                       0: self
                        338     LOAD_ATTR                       6: pts_limit
                        358     POP_JUMP_IF_NONE                14 (to 388)
                        360     LOAD_FAST                       0: self
                        362     LOAD_ATTR                       6: pts_limit
                        382     LOAD_CONST                      7: False
                        384     IS_OP                           0 (is)
                        386     POP_JUMP_IF_FALSE               2 (to 392)
                        388     LOAD_CONST                      4: b''
                        390     JUMP_FORWARD                    31 (to 454)
                        392     LOAD_GLOBAL                     3: NULL + struct
                        402     LOAD_ATTR                       4: pack
                        422     LOAD_CONST                      12: '<i'
                        424     LOAD_FAST                       0: self
                        426     LOAD_ATTR                       6: pts_limit
                        446     CALL                            2
                        454     LOAD_FAST                       0: self
                        456     LOAD_ATTR                       8: pts_total_limit
                        476     POP_JUMP_IF_NONE                14 (to 506)
                        478     LOAD_FAST                       0: self
                        480     LOAD_ATTR                       8: pts_total_limit
                        500     LOAD_CONST                      7: False
                        502     IS_OP                           0 (is)
                        504     POP_JUMP_IF_FALSE               2 (to 510)
                        506     LOAD_CONST                      4: b''
                        508     JUMP_FORWARD                    31 (to 572)
                        510     LOAD_GLOBAL                     3: NULL + struct
                        520     LOAD_ATTR                       4: pack
                        540     LOAD_CONST                      12: '<i'
                        542     LOAD_FAST                       0: self
                        544     LOAD_ATTR                       8: pts_total_limit
                        564     CALL                            2
                        572     LOAD_FAST                       0: self
                        574     LOAD_ATTR                       15: serialize_datetime
                        594     LOAD_FAST                       0: self
                        596     LOAD_ATTR                       16: date
                        616     CALL                            1
                        624     LOAD_GLOBAL                     3: NULL + struct
                        634     LOAD_ATTR                       4: pack
                        654     LOAD_CONST                      12: '<i'
                        656     LOAD_FAST                       0: self
                        658     LOAD_ATTR                       18: qts
                        678     CALL                            2
                        686     LOAD_FAST                       0: self
                        688     LOAD_ATTR                       10: qts_limit
                        708     POP_JUMP_IF_NONE                14 (to 738)
                        710     LOAD_FAST                       0: self
                        712     LOAD_ATTR                       10: qts_limit
                        732     LOAD_CONST                      7: False
                        734     IS_OP                           0 (is)
                        736     POP_JUMP_IF_FALSE               2 (to 742)
                        738     LOAD_CONST                      4: b''
                        740     JUMP_FORWARD                    31 (to 804)
                        742     LOAD_GLOBAL                     3: NULL + struct
                        752     LOAD_ATTR                       4: pack
                        772     LOAD_CONST                      12: '<i'
                        774     LOAD_FAST                       0: self
                        776     LOAD_ATTR                       10: qts_limit
                        796     CALL                            2
                        804     BUILD_TUPLE                     8
                        806     CALL                            1
                        814     NOP                             
                        816     NOP                             
                        818     NOP                             
                        820     JUMP_FORWARD                    20 (to 862)
                        822     CALL                            1
                        830     POP_TOP                         
                        832     RETURN_VALUE                    
                        834     PUSH_EXC_INFO                   
                        836     PUSH_NULL                       
                        838     LOAD_CONST                      13: '__pyarmor_exit_36719__'
                        840     NOP                             
                        842     LOAD_CONST                      3: b'<COAddr>\x07\x00\x00\x1a(\x03\x00\x00\x00\x00\x00\x00\x00\x00\x00\x00\x00\x00\x00\x00'
                        844     CALL                            1
                        852     POP_TOP                         
                        854     RERAISE                         0
                        856     COPY                            3
                        858     POP_EXCEPT                      
                        860     RERAISE                         1
                        862     PUSH_NULL                       
                        864     LOAD_CONST                      13: '__pyarmor_exit_36719__'
                        866     LOAD_CONST                      3: b'<COAddr>\x07\x00\x00\x1a(\x03\x00\x00\x00\x00\x00\x00\x00\x00\x00\x00\x00\x00\x00\x00'
                        868     BUILD_TUPLE                     1
                        870     CALL_FUNCTION_EX                0
                        872     POP_TOP                         
                        874     RETURN_VALUE                    
                    [Exception Table]
                        28 to 814 -> 834 [0] 
                        834 to 856 -> 856 [1] lasti
                [Code]
                    File Name: <frozen multithon.tl.functions.updates>
                    Object Name: from_reader
                    Qualified Name: GetDifferenceRequest.from_reader
                    Arg Count: 2
                    Pos Only Arg Count: 0
                    KW Only Arg Count: 0
                    Stack Size: 8
                    Flags: 0x20000003 (CO_OPTIMIZED | CO_NEWLOCALS | CO_PYARMOR_OBFUSCATED)
                    [Names]
                        'read_int'
                        'tgread_date'
                    [Locals+Names]
                        'cls'
                        'reader'
                        '__assert_armored__'
                        '_var_var_0'
                        '_var_var_4'
                        '_var_var_6'
                        '_var_var_7'
                        '_var_var_8'
                        '_var_var_9'
                        '_var_var_10'
                    [Constants]
                        None
                        '__pyarmor_assert_36720__'
                        '__pyarmor_enter_36721__'
                        b'<COAddr>\x05\x00\x00\x1a@\x01\x00\x00\x00\x00\x00\x00\x00\x00\x00\x00\x00\x00\x00\x00'
                        2
                        1
                        4
                        (
                            'pts'
                            'date'
                            'qts'
                            'pts_limit'
                            'pts_total_limit'
                            'qts_limit'
                        )
                        '__pyarmor_exit_36722__'
                    [Disassembly]
                        0       NOP                             
                        2       NOP                             
                        4       PUSH_NULL                       
                        6       LOAD_CONST                      2: '__pyarmor_enter_36721__'
                        8       LOAD_CONST                      3: b'<COAddr>\x05\x00\x00\x1a@\x01\x00\x00\x00\x00\x00\x00\x00\x00\x00\x00\x00\x00\x00\x00'
                        10      BUILD_TUPLE                     1
                        12      CALL_FUNCTION_EX                0
                        14      POP_TOP                         
                        16      RESUME                          0
                        18      NOP                             
                        20      NOP                             
                        22      NOP                             
                        24      NOP                             
                        26      NOP                             
                        28      LOAD_FAST                       1: reader
                        30      LOAD_ATTR                       1: read_int
                        50      CALL                            0
                        58      STORE_FAST                      3: _var_var_0
                        60      LOAD_FAST                       1: reader
                        62      LOAD_ATTR                       1: read_int
                        82      CALL                            0
                        90      STORE_FAST                      4: _var_var_4
                        92      LOAD_FAST                       3: _var_var_0
                        94      LOAD_CONST                      4: 2
                        96      BINARY_OP                       1 (&)
                        100     POP_JUMP_IF_FALSE               17 (to 136)
                        102     LOAD_FAST                       1: reader
                        104     LOAD_ATTR                       1: read_int
                        124     CALL                            0
                        132     STORE_FAST                      5: _var_var_6
                        134     JUMP_FORWARD                    2 (to 140)
                        136     LOAD_CONST                      0: None
                        138     STORE_FAST                      5: _var_var_6
                        140     LOAD_FAST                       3: _var_var_0
                        142     LOAD_CONST                      5: 1
                        144     BINARY_OP                       1 (&)
                        148     POP_JUMP_IF_FALSE               17 (to 184)
                        150     LOAD_FAST                       1: reader
                        152     LOAD_ATTR                       1: read_int
                        172     CALL                            0
                        180     STORE_FAST                      6: _var_var_7
                        182     JUMP_FORWARD                    2 (to 188)
                        184     LOAD_CONST                      0: None
                        186     STORE_FAST                      6: _var_var_7
                        188     LOAD_FAST                       1: reader
                        190     LOAD_ATTR                       3: tgread_date
                        210     CALL                            0
                        218     STORE_FAST                      7: _var_var_8
                        220     LOAD_FAST                       1: reader
                        222     LOAD_ATTR                       1: read_int
                        242     CALL                            0
                        250     STORE_FAST                      8: _var_var_9
                        252     LOAD_FAST                       3: _var_var_0
                        254     LOAD_CONST                      6: 4
                        256     BINARY_OP                       1 (&)
                        260     POP_JUMP_IF_FALSE               17 (to 296)
                        262     LOAD_FAST                       1: reader
                        264     LOAD_ATTR                       1: read_int
                        284     CALL                            0
                        292     STORE_FAST                      9: _var_var_10
                        294     JUMP_FORWARD                    2 (to 300)
                        296     LOAD_CONST                      0: None
                        298     STORE_FAST                      9: _var_var_10
                        300     PUSH_NULL                       
                        302     LOAD_FAST                       0: cls
                        304     LOAD_FAST                       4: _var_var_4
                        306     LOAD_FAST                       7: _var_var_8
                        308     LOAD_FAST                       8: _var_var_9
                        310     LOAD_FAST                       5: _var_var_6
                        312     LOAD_FAST                       6: _var_var_7
                        314     LOAD_FAST                       9: _var_var_10
                        316     KW_NAMES                        7: ('pts', 'date', 'qts', 'pts_limit', 'pts_total_limit', 'qts_limit')
                        318     CALL                            6
                        326     NOP                             
                        328     NOP                             
                        330     NOP                             
                        332     JUMP_FORWARD                    20 (to 374)
                        334     CALL                            1
                        342     POP_TOP                         
                        344     RETURN_VALUE                    
                        346     PUSH_EXC_INFO                   
                        348     PUSH_NULL                       
                        350     LOAD_CONST                      8: '__pyarmor_exit_36722__'
                        352     NOP                             
                        354     LOAD_CONST                      3: b'<COAddr>\x05\x00\x00\x1a@\x01\x00\x00\x00\x00\x00\x00\x00\x00\x00\x00\x00\x00\x00\x00'
                        356     CALL                            1
                        364     POP_TOP                         
                        366     RERAISE                         0
                        368     COPY                            3
                        370     POP_EXCEPT                      
                        372     RERAISE                         1
                        374     PUSH_NULL                       
                        376     LOAD_CONST                      8: '__pyarmor_exit_36722__'
                        378     LOAD_CONST                      3: b'<COAddr>\x05\x00\x00\x1a@\x01\x00\x00\x00\x00\x00\x00\x00\x00\x00\x00\x00\x00\x00\x00'
                        380     BUILD_TUPLE                     1
                        382     CALL_FUNCTION_EX                0
                        384     POP_TOP                         
                        386     RETURN_VALUE                    
                    [Exception Table]
                        28 to 326 -> 346 [0] 
                        346 to 368 -> 368 [1] lasti
                '__pyarmor_exit_36710__'
                (
                    None
                    None
                    None
                )
            [Disassembly]
                0       NOP                             
                2       LOAD_NAME                       0: __name__
                4       STORE_NAME                      1: __module__
                6       LOAD_CONST                      0: 'GetDifferenceRequest'
                8       STORE_NAME                      2: __qualname__
                10      NOP                             
                12      PUSH_NULL                       
                14      LOAD_CONST                      2: '__pyarmor_enter_36709__'
                16      LOAD_CONST                      3: b'<COAddr>\x05\x00\x00"t\x00\x00\x00\x00\x00\x00\x00\x00\x00\x00\x00\x00\x00\x00\x00'
                18      BUILD_TUPLE                     1
                20      CALL_FUNCTION_EX                0
                22      POP_TOP                         
                24      RESUME                          0
                26      NOP                             
                28      NOP                             
                30      NOP                             
                32      NOP                             
                34      NOP                             
                36      LOAD_CONST                      4: 630429265
                38      STORE_NAME                      4: CONSTRUCTOR_ID
                40      LOAD_CONST                      5: 541599860
                42      STORE_NAME                      5: SUBCLASS_OF_ID
                44      LOAD_CONST                      18: (None, None, None)
                46      LOAD_CONST                      7: 'pts'
                48      LOAD_NAME                       6: int
                50      LOAD_CONST                      8: 'date'
                52      LOAD_NAME                       7: Optional
                54      LOAD_NAME                       8: datetime
                56      BINARY_SUBSCR                   
                60      LOAD_CONST                      9: 'qts'
                62      LOAD_NAME                       6: int
                64      LOAD_CONST                      10: 'pts_limit'
                66      LOAD_NAME                       7: Optional
                68      LOAD_NAME                       6: int
                70      BINARY_SUBSCR                   
                74      LOAD_CONST                      11: 'pts_total_limit'
                76      LOAD_NAME                       7: Optional
                78      LOAD_NAME                       6: int
                80      BINARY_SUBSCR                   
                84      LOAD_CONST                      12: 'qts_limit'
                86      LOAD_NAME                       7: Optional
                88      LOAD_NAME                       6: int
                90      BINARY_SUBSCR                   
                94      BUILD_TUPLE                     12
                96      LOAD_CONST                      13: <CODE> __init__
                98      MAKE_FUNCTION                   5
                100     STORE_NAME                      9: __init__
                102     LOAD_CONST                      14: <CODE> to_dict
                104     MAKE_FUNCTION                   0
                106     STORE_NAME                      10: to_dict
                108     LOAD_CONST                      15: <CODE> _bytes
                110     MAKE_FUNCTION                   0
                112     STORE_NAME                      11: _bytes
                114     LOAD_NAME                       12: classmethod
                116     LOAD_CONST                      16: <CODE> from_reader
                118     MAKE_FUNCTION                   0
                120     CALL                            0
                128     STORE_NAME                      13: from_reader
                130     LOAD_CONST                      6: None
                132     NOP                             
                134     NOP                             
                136     NOP                             
                138     JUMP_FORWARD                    19 (to 178)
                146     POP_TOP                         
                148     RETURN_CONST                    6: None
                150     PUSH_EXC_INFO                   
                152     PUSH_NULL                       
                154     LOAD_CONST                      17: '__pyarmor_exit_36710__'
                156     NOP                             
                158     LOAD_CONST                      3: b'<COAddr>\x05\x00\x00"t\x00\x00\x00\x00\x00\x00\x00\x00\x00\x00\x00\x00\x00\x00\x00'
                160     CALL                            1
                168     POP_TOP                         
                170     RERAISE                         0
                172     COPY                            3
                174     POP_EXCEPT                      
                176     RERAISE                         1
                178     PUSH_NULL                       
                180     LOAD_CONST                      17: '__pyarmor_exit_36710__'
                182     LOAD_CONST                      3: b'<COAddr>\x05\x00\x00"t\x00\x00\x00\x00\x00\x00\x00\x00\x00\x00\x00\x00\x00\x00\x00'
                184     BUILD_TUPLE                     1
                186     CALL_FUNCTION_EX                0
                188     POP_TOP                         
                190     RETURN_VALUE                    
            [Exception Table]
                36 to 130 -> 150 [0] 
                150 to 172 -> 172 [1] lasti
        'GetDifferenceRequest'
        [Code]
            File Name: <frozen multithon.tl.functions.updates>
            Object Name: GetDifference_tdlib_Request
            Qualified Name: GetDifference_tdlib_Request
            Arg Count: 0
            Pos Only Arg Count: 0
            KW Only Arg Count: 0
            Stack Size: 14
            Flags: 0x20000000 (CO_PYARMOR_OBFUSCATED)
            [Names]
                '__name__'
                '__module__'
                '__qualname__'
                '__assert_armored__'
                'CONSTRUCTOR_ID'
                'SUBCLASS_OF_ID'
                'int'
                'Optional'
                'datetime'
                '__init__'
                'to_dict'
                '_bytes'
                'classmethod'
                'from_reader'
            [Locals+Names]
            [Constants]
                'GetDifference_tdlib_Request'
                '__pyarmor_assert_36723__'
                '__pyarmor_enter_36724__'
                b'<COAddr>\x05\x00\x00"t\x00\x00\x00\x00\x00\x00\x00\x00\x00\x00\x00\x00\x00\x00\x00'
                432207715
                541599860
                None
                'pts'
                'date'
                'qts'
                'pts_limit'
                'pts_total_limit'
                'qts_limit'
                [Code]
                    File Name: <frozen multithon.tl.functions.updates>
                    Object Name: __init__
                    Qualified Name: GetDifference_tdlib_Request.__init__
                    Arg Count: 7
                    Pos Only Arg Count: 0
                    KW Only Arg Count: 0
                    Stack Size: 5
                    Flags: 0x20000003 (CO_OPTIMIZED | CO_NEWLOCALS | CO_PYARMOR_OBFUSCATED)
                    [Names]
                        'pts'
                        'date'
                        'qts'
                        'pts_limit'
                        'pts_total_limit'
                        'qts_limit'
                    [Locals+Names]
                        'self'
                        'pts'
                        'date'
                        'qts'
                        'pts_limit'
                        'pts_total_limit'
                        'qts_limit'
                        '__assert_armored__'
                    [Constants]
                        '\n        :returns updates.Difference: Instance of either DifferenceEmpty, Difference, DifferenceSlice, DifferenceTooLong.\n        '
                        '__pyarmor_assert_36726__'
                        '__pyarmor_enter_36727__'
                        b'<COAddr>\x07\x00\x00\x1aj\x00\x00\x00\x00\x00\x00\x00\x00\x00\x00\x00\x00\x00\x00\x00'
                        '__pyarmor_exit_36728__'
                        None
                    [Disassembly]
                        0       NOP                             
                        2       NOP                             
                        4       PUSH_NULL                       
                        6       LOAD_CONST                      2: '__pyarmor_enter_36727__'
                        8       LOAD_CONST                      3: b'<COAddr>\x07\x00\x00\x1aj\x00\x00\x00\x00\x00\x00\x00\x00\x00\x00\x00\x00\x00\x00\x00'
                        10      BUILD_TUPLE                     1
                        12      CALL_FUNCTION_EX                0
                        14      POP_TOP                         
                        16      RESUME                          0
                        18      NOP                             
                        20      NOP                             
                        22      NOP                             
                        24      NOP                             
                        26      NOP                             
                        28      LOAD_FAST                       1: pts
                        30      LOAD_FAST                       0: self
                        32      STORE_ATTR                      0: pts
                        42      LOAD_FAST                       2: date
                        44      LOAD_FAST                       0: self
                        46      STORE_ATTR                      1: date
                        56      LOAD_FAST                       3: qts
                        58      LOAD_FAST                       0: self
                        60      STORE_ATTR                      2: qts
                        70      LOAD_FAST                       4: pts_limit
                        72      LOAD_FAST                       0: self
                        74      STORE_ATTR                      3: pts_limit
                        84      LOAD_FAST                       5: pts_total_limit
                        86      LOAD_FAST                       0: self
                        88      STORE_ATTR                      4: pts_total_limit
                        98      LOAD_FAST                       6: qts_limit
                        100     LOAD_FAST                       0: self
                        102     STORE_ATTR                      5: qts_limit
                        112     LOAD_CONST                      5: None
                        114     NOP                             
                        116     NOP                             
                        118     NOP                             
                        120     JUMP_FORWARD                    19 (to 160)
                        128     POP_TOP                         
                        130     RETURN_CONST                    5: None
                        132     PUSH_EXC_INFO                   
                        134     PUSH_NULL                       
                        136     LOAD_CONST                      4: '__pyarmor_exit_36728__'
                        138     NOP                             
                        140     LOAD_CONST                      3: b'<COAddr>\x07\x00\x00\x1aj\x00\x00\x00\x00\x00\x00\x00\x00\x00\x00\x00\x00\x00\x00\x00'
                        142     CALL                            1
                        150     POP_TOP                         
                        152     RERAISE                         0
                        154     COPY                            3
                        156     POP_EXCEPT                      
                        158     RERAISE                         1
                        160     PUSH_NULL                       
                        162     LOAD_CONST                      4: '__pyarmor_exit_36728__'
                        164     LOAD_CONST                      3: b'<COAddr>\x07\x00\x00\x1aj\x00\x00\x00\x00\x00\x00\x00\x00\x00\x00\x00\x00\x00\x00\x00'
                        166     BUILD_TUPLE                     1
                        168     CALL_FUNCTION_EX                0
                        170     POP_TOP                         
                        172     RETURN_VALUE                    
                    [Exception Table]
                        28 to 112 -> 132 [0] 
                        132 to 154 -> 154 [1] lasti
                [Code]
                    File Name: <frozen multithon.tl.functions.updates>
                    Object Name: to_dict
                    Qualified Name: GetDifference_tdlib_Request.to_dict
                    Arg Count: 1
                    Pos Only Arg Count: 0
                    KW Only Arg Count: 0
                    Stack Size: 15
                    Flags: 0x20000003 (CO_OPTIMIZED | CO_NEWLOCALS | CO_PYARMOR_OBFUSCATED)
                    [Names]
                        'pts'
                        'date'
                        'qts'
                        'pts_limit'
                        'pts_total_limit'
                        'qts_limit'
                    [Locals+Names]
                        'self'
                        '__assert_armored__'
                    [Constants]
                        None
                        '__pyarmor_assert_36729__'
                        '__pyarmor_enter_36730__'
                        b'<COAddr>\x07\x00\x00\x1a\xdc\x00\x00\x00\x00\x00\x00\x00\x00\x00\x00\x00\x00\x00\x00\x00'
                        '_'
                        'GetDifferenceRequest'   # b'\x81\xc5\x1d\x07\x17\xf3\xb8\xd4\x1e\xe8\x08\xceo\xe9\xca\x80\x1eH\xbe\xb4\xbe'
                        'pts'
                        'date'
                        'qts'
                        'pts_limit'   # b'\x81\xf2\x0c\x00\x0c\xf6\xb7\xdf\x12\xee'
                        'pts_total_limit'   # b'\x81\xf2\x0c\x00\x0c\xee\xb1\xc6\x1a\xf62\xcce\xe1\xf1\x91'
                        'qts_limit'   # b'\x81\xf3\x0c\x00\x0c\xf6\xb7\xdf\x12\xee'
                        '__pyarmor_exit_36731__'
                    [Disassembly]
                        0       NOP                             
                        2       NOP                             
                        4       PUSH_NULL                       
                        6       LOAD_CONST                      2: '__pyarmor_enter_36730__'
                        8       LOAD_CONST                      3: b'<COAddr>\x07\x00\x00\x1a\xdc\x00\x00\x00\x00\x00\x00\x00\x00\x00\x00\x00\x00\x00\x00\x00'
                        10      BUILD_TUPLE                     1
                        12      CALL_FUNCTION_EX                0
                        14      POP_TOP                         
                        16      RESUME                          0
                        18      NOP                             
                        20      NOP                             
                        22      NOP                             
                        24      NOP                             
                        26      NOP                             
                        28      LOAD_CONST                      4: '_'
                        30      PUSH_NULL                       
                        32      LOAD_CONST                      1: '__pyarmor_assert_36729__'
                        34      LOAD_CONST                      5: 'GetDifferenceRequest'   # b'\x81\xc5\x1d\x07\x17\xf3\xb8\xd4\x1e\xe8\x08\xceo\xe9\xca\x80\x1eH\xbe\xb4\xbe'
                        36      CALL                            1
                        44      LOAD_CONST                      6: 'pts'
                        46      LOAD_FAST                       0: self
                        48      LOAD_ATTR                       0: pts
                        68      LOAD_CONST                      7: 'date'
                        70      LOAD_FAST                       0: self
                        72      LOAD_ATTR                       2: date
                        92      LOAD_CONST                      8: 'qts'
                        94      LOAD_FAST                       0: self
                        96      LOAD_ATTR                       4: qts
                        116     PUSH_NULL                       
                        118     LOAD_CONST                      1: '__pyarmor_assert_36729__'
                        120     LOAD_CONST                      9: 'pts_limit'   # b'\x81\xf2\x0c\x00\x0c\xf6\xb7\xdf\x12\xee'
                        122     CALL                            1
                        130     LOAD_FAST                       0: self
                        132     LOAD_ATTR                       6: pts_limit
                        152     PUSH_NULL                       
                        154     LOAD_CONST                      1: '__pyarmor_assert_36729__'
                        156     LOAD_CONST                      10: 'pts_total_limit'   # b'\x81\xf2\x0c\x00\x0c\xee\xb1\xc6\x1a\xf62\xcce\xe1\xf1\x91'
                        158     CALL                            1
                        166     LOAD_FAST                       0: self
                        168     LOAD_ATTR                       8: pts_total_limit
                        188     PUSH_NULL                       
                        190     LOAD_CONST                      1: '__pyarmor_assert_36729__'
                        192     LOAD_CONST                      11: 'qts_limit'   # b'\x81\xf3\x0c\x00\x0c\xf6\xb7\xdf\x12\xee'
                        194     CALL                            1
                        202     LOAD_FAST                       0: self
                        204     LOAD_ATTR                       10: qts_limit
                        224     BUILD_MAP                       7
                        226     NOP                             
                        228     NOP                             
                        230     NOP                             
                        232     JUMP_FORWARD                    20 (to 274)
                        234     CALL                            1
                        242     POP_TOP                         
                        244     RETURN_VALUE                    
                        246     PUSH_EXC_INFO                   
                        248     PUSH_NULL                       
                        250     LOAD_CONST                      12: '__pyarmor_exit_36731__'
                        252     NOP                             
                        254     LOAD_CONST                      3: b'<COAddr>\x07\x00\x00\x1a\xdc\x00\x00\x00\x00\x00\x00\x00\x00\x00\x00\x00\x00\x00\x00\x00'
                        256     CALL                            1
                        264     POP_TOP                         
                        266     RERAISE                         0
                        268     COPY                            3
                        270     POP_EXCEPT                      
                        272     RERAISE                         1
                        274     PUSH_NULL                       
                        276     LOAD_CONST                      12: '__pyarmor_exit_36731__'
                        278     LOAD_CONST                      3: b'<COAddr>\x07\x00\x00\x1a\xdc\x00\x00\x00\x00\x00\x00\x00\x00\x00\x00\x00\x00\x00\x00\x00'
                        280     BUILD_TUPLE                     1
                        282     CALL_FUNCTION_EX                0
                        284     POP_TOP                         
                        286     RETURN_VALUE                    
                    [Exception Table]
                        28 to 226 -> 246 [0] 
                        246 to 268 -> 268 [1] lasti
                [Code]
                    File Name: <frozen multithon.tl.functions.updates>
                    Object Name: _bytes
                    Qualified Name: GetDifference_tdlib_Request._bytes
                    Arg Count: 1
                    Pos Only Arg Count: 0
                    KW Only Arg Count: 0
                    Stack Size: 13
                    Flags: 0x20000003 (CO_OPTIMIZED | CO_NEWLOCALS | CO_PYARMOR_OBFUSCATED)
                    [Names]
                        'join'
                        'struct'
                        'pack'
                        'pts_limit'
                        'pts_total_limit'
                        'qts_limit'
                        'pts'
                        'serialize_datetime'
                        'date'
                        'qts'
                    [Locals+Names]
                        'self'
                        '__assert_armored__'
                    [Constants]
                        None
                        '__pyarmor_assert_36732__'
                        '__pyarmor_enter_36733__'
                        b'<COAddr>\x07\x00\x00\x1a(\x03\x00\x00\x00\x00\x00\x00\x00\x00\x00\x00\x00\x00\x00\x00'
                        b''
                        b'c\xf7\xc2\x19'
                        '<I'
                        False
                        0
                        2
                        1
                        4
                        '<i'
                        '__pyarmor_exit_36734__'
                    [Disassembly]
                        0       NOP                             
                        2       NOP                             
                        4       PUSH_NULL                       
                        6       LOAD_CONST                      2: '__pyarmor_enter_36733__'
                        8       LOAD_CONST                      3: b'<COAddr>\x07\x00\x00\x1a(\x03\x00\x00\x00\x00\x00\x00\x00\x00\x00\x00\x00\x00\x00\x00'
                        10      BUILD_TUPLE                     1
                        12      CALL_FUNCTION_EX                0
                        14      POP_TOP                         
                        16      RESUME                          0
                        18      NOP                             
                        20      NOP                             
                        22      NOP                             
                        24      NOP                             
                        26      NOP                             
                        28      LOAD_CONST                      4: b''
                        30      LOAD_ATTR                       1: join
                        50      LOAD_CONST                      5: b'c\xf7\xc2\x19'
                        52      LOAD_GLOBAL                     3: NULL + struct
                        62      LOAD_ATTR                       4: pack
                        82      LOAD_CONST                      6: '<I'
                        84      LOAD_FAST                       0: self
                        86      LOAD_ATTR                       6: pts_limit
                        106     POP_JUMP_IF_NONE                14 (to 136)
                        108     LOAD_FAST                       0: self
                        110     LOAD_ATTR                       6: pts_limit
                        130     LOAD_CONST                      7: False
                        132     IS_OP                           0 (is)
                        134     POP_JUMP_IF_FALSE               2 (to 140)
                        136     LOAD_CONST                      8: 0
                        138     JUMP_FORWARD                    1 (to 142)
                        140     LOAD_CONST                      9: 2
                        142     LOAD_FAST                       0: self
                        144     LOAD_ATTR                       8: pts_total_limit
                        164     POP_JUMP_IF_NONE                14 (to 194)
                        166     LOAD_FAST                       0: self
                        168     LOAD_ATTR                       8: pts_total_limit
                        188     LOAD_CONST                      7: False
                        190     IS_OP                           0 (is)
                        192     POP_JUMP_IF_FALSE               2 (to 198)
                        194     LOAD_CONST                      8: 0
                        196     JUMP_FORWARD                    1 (to 200)
                        198     LOAD_CONST                      10: 1
                        200     BINARY_OP                       7 (|)
                        204     LOAD_FAST                       0: self
                        206     LOAD_ATTR                       10: qts_limit
                        226     POP_JUMP_IF_NONE                14 (to 256)
                        228     LOAD_FAST                       0: self
                        230     LOAD_ATTR                       10: qts_limit
                        250     LOAD_CONST                      7: False
                        252     IS_OP                           0 (is)
                        254     POP_JUMP_IF_FALSE               2 (to 260)
                        256     LOAD_CONST                      8: 0
                        258     JUMP_FORWARD                    1 (to 262)
                        260     LOAD_CONST                      11: 4
                        262     BINARY_OP                       7 (|)
                        266     CALL                            2
                        274     LOAD_GLOBAL                     3: NULL + struct
                        284     LOAD_ATTR                       4: pack
                        304     LOAD_CONST                      12: '<i'
                        306     LOAD_FAST                       0: self
                        308     LOAD_ATTR                       12: pts
                        328     CALL                            2
                        336     LOAD_FAST                       0: self
                        338     LOAD_ATTR                       6: pts_limit
                        358     POP_JUMP_IF_NONE                14 (to 388)
                        360     LOAD_FAST                       0: self
                        362     LOAD_ATTR                       6: pts_limit
                        382     LOAD_CONST                      7: False
                        384     IS_OP                           0 (is)
                        386     POP_JUMP_IF_FALSE               2 (to 392)
                        388     LOAD_CONST                      4: b''
                        390     JUMP_FORWARD                    31 (to 454)
                        392     LOAD_GLOBAL                     3: NULL + struct
                        402     LOAD_ATTR                       4: pack
                        422     LOAD_CONST                      12: '<i'
                        424     LOAD_FAST                       0: self
                        426     LOAD_ATTR                       6: pts_limit
                        446     CALL                            2
                        454     LOAD_FAST                       0: self
                        456     LOAD_ATTR                       8: pts_total_limit
                        476     POP_JUMP_IF_NONE                14 (to 506)
                        478     LOAD_FAST                       0: self
                        480     LOAD_ATTR                       8: pts_total_limit
                        500     LOAD_CONST                      7: False
                        502     IS_OP                           0 (is)
                        504     POP_JUMP_IF_FALSE               2 (to 510)
                        506     LOAD_CONST                      4: b''
                        508     JUMP_FORWARD                    31 (to 572)
                        510     LOAD_GLOBAL                     3: NULL + struct
                        520     LOAD_ATTR                       4: pack
                        540     LOAD_CONST                      12: '<i'
                        542     LOAD_FAST                       0: self
                        544     LOAD_ATTR                       8: pts_total_limit
                        564     CALL                            2
                        572     LOAD_FAST                       0: self
                        574     LOAD_ATTR                       15: serialize_datetime
                        594     LOAD_FAST                       0: self
                        596     LOAD_ATTR                       16: date
                        616     CALL                            1
                        624     LOAD_GLOBAL                     3: NULL + struct
                        634     LOAD_ATTR                       4: pack
                        654     LOAD_CONST                      12: '<i'
                        656     LOAD_FAST                       0: self
                        658     LOAD_ATTR                       18: qts
                        678     CALL                            2
                        686     LOAD_FAST                       0: self
                        688     LOAD_ATTR                       10: qts_limit
                        708     POP_JUMP_IF_NONE                14 (to 738)
                        710     LOAD_FAST                       0: self
                        712     LOAD_ATTR                       10: qts_limit
                        732     LOAD_CONST                      7: False
                        734     IS_OP                           0 (is)
                        736     POP_JUMP_IF_FALSE               2 (to 742)
                        738     LOAD_CONST                      4: b''
                        740     JUMP_FORWARD                    31 (to 804)
                        742     LOAD_GLOBAL                     3: NULL + struct
                        752     LOAD_ATTR                       4: pack
                        772     LOAD_CONST                      12: '<i'
                        774     LOAD_FAST                       0: self
                        776     LOAD_ATTR                       10: qts_limit
                        796     CALL                            2
                        804     BUILD_TUPLE                     8
                        806     CALL                            1
                        814     NOP                             
                        816     NOP                             
                        818     NOP                             
                        820     JUMP_FORWARD                    20 (to 862)
                        822     CALL                            1
                        830     POP_TOP                         
                        832     RETURN_VALUE                    
                        834     PUSH_EXC_INFO                   
                        836     PUSH_NULL                       
                        838     LOAD_CONST                      13: '__pyarmor_exit_36734__'
                        840     NOP                             
                        842     LOAD_CONST                      3: b'<COAddr>\x07\x00\x00\x1a(\x03\x00\x00\x00\x00\x00\x00\x00\x00\x00\x00\x00\x00\x00\x00'
                        844     CALL                            1
                        852     POP_TOP                         
                        854     RERAISE                         0
                        856     COPY                            3
                        858     POP_EXCEPT                      
                        860     RERAISE                         1
                        862     PUSH_NULL                       
                        864     LOAD_CONST                      13: '__pyarmor_exit_36734__'
                        866     LOAD_CONST                      3: b'<COAddr>\x07\x00\x00\x1a(\x03\x00\x00\x00\x00\x00\x00\x00\x00\x00\x00\x00\x00\x00\x00'
                        868     BUILD_TUPLE                     1
                        870     CALL_FUNCTION_EX                0
                        872     POP_TOP                         
                        874     RETURN_VALUE                    
                    [Exception Table]
                        28 to 814 -> 834 [0] 
                        834 to 856 -> 856 [1] lasti
                [Code]
                    File Name: <frozen multithon.tl.functions.updates>
                    Object Name: from_reader
                    Qualified Name: GetDifference_tdlib_Request.from_reader
                    Arg Count: 2
                    Pos Only Arg Count: 0
                    KW Only Arg Count: 0
                    Stack Size: 8
                    Flags: 0x20000003 (CO_OPTIMIZED | CO_NEWLOCALS | CO_PYARMOR_OBFUSCATED)
                    [Names]
                        'read_int'
                        'tgread_date'
                    [Locals+Names]
                        'cls'
                        'reader'
                        '__assert_armored__'
                        '_var_var_0'
                        '_var_var_4'
                        '_var_var_6'
                        '_var_var_7'
                        '_var_var_8'
                        '_var_var_9'
                        '_var_var_10'
                    [Constants]
                        None
                        '__pyarmor_assert_36735__'
                        '__pyarmor_enter_36736__'
                        b'<COAddr>\x07\x00\x00\x1a@\x01\x00\x00\x00\x00\x00\x00\x00\x00\x00\x00\x00\x00\x00\x00'
                        2
                        1
                        4
                        (
                            'pts'
                            'date'
                            'qts'
                            'pts_limit'
                            'pts_total_limit'
                            'qts_limit'
                        )
                        '__pyarmor_exit_36737__'
                    [Disassembly]
                        0       NOP                             
                        2       NOP                             
                        4       PUSH_NULL                       
                        6       LOAD_CONST                      2: '__pyarmor_enter_36736__'
                        8       LOAD_CONST                      3: b'<COAddr>\x07\x00\x00\x1a@\x01\x00\x00\x00\x00\x00\x00\x00\x00\x00\x00\x00\x00\x00\x00'
                        10      BUILD_TUPLE                     1
                        12      CALL_FUNCTION_EX                0
                        14      POP_TOP                         
                        16      RESUME                          0
                        18      NOP                             
                        20      NOP                             
                        22      NOP                             
                        24      NOP                             
                        26      NOP                             
                        28      LOAD_FAST                       1: reader
                        30      LOAD_ATTR                       1: read_int
                        50      CALL                            0
                        58      STORE_FAST                      3: _var_var_0
                        60      LOAD_FAST                       1: reader
                        62      LOAD_ATTR                       1: read_int
                        82      CALL                            0
                        90      STORE_FAST                      4: _var_var_4
                        92      LOAD_FAST                       3: _var_var_0
                        94      LOAD_CONST                      4: 2
                        96      BINARY_OP                       1 (&)
                        100     POP_JUMP_IF_FALSE               17 (to 136)
                        102     LOAD_FAST                       1: reader
                        104     LOAD_ATTR                       1: read_int
                        124     CALL                            0
                        132     STORE_FAST                      5: _var_var_6
                        134     JUMP_FORWARD                    2 (to 140)
                        136     LOAD_CONST                      0: None
                        138     STORE_FAST                      5: _var_var_6
                        140     LOAD_FAST                       3: _var_var_0
                        142     LOAD_CONST                      5: 1
                        144     BINARY_OP                       1 (&)
                        148     POP_JUMP_IF_FALSE               17 (to 184)
                        150     LOAD_FAST                       1: reader
                        152     LOAD_ATTR                       1: read_int
                        172     CALL                            0
                        180     STORE_FAST                      6: _var_var_7
                        182     JUMP_FORWARD                    2 (to 188)
                        184     LOAD_CONST                      0: None
                        186     STORE_FAST                      6: _var_var_7
                        188     LOAD_FAST                       1: reader
                        190     LOAD_ATTR                       3: tgread_date
                        210     CALL                            0
                        218     STORE_FAST                      7: _var_var_8
                        220     LOAD_FAST                       1: reader
                        222     LOAD_ATTR                       1: read_int
                        242     CALL                            0
                        250     STORE_FAST                      8: _var_var_9
                        252     LOAD_FAST                       3: _var_var_0
                        254     LOAD_CONST                      6: 4
                        256     BINARY_OP                       1 (&)
                        260     POP_JUMP_IF_FALSE               17 (to 296)
                        262     LOAD_FAST                       1: reader
                        264     LOAD_ATTR                       1: read_int
                        284     CALL                            0
                        292     STORE_FAST                      9: _var_var_10
                        294     JUMP_FORWARD                    2 (to 300)
                        296     LOAD_CONST                      0: None
                        298     STORE_FAST                      9: _var_var_10
                        300     PUSH_NULL                       
                        302     LOAD_FAST                       0: cls
                        304     LOAD_FAST                       4: _var_var_4
                        306     LOAD_FAST                       7: _var_var_8
                        308     LOAD_FAST                       8: _var_var_9
                        310     LOAD_FAST                       5: _var_var_6
                        312     LOAD_FAST                       6: _var_var_7
                        314     LOAD_FAST                       9: _var_var_10
                        316     KW_NAMES                        7: ('pts', 'date', 'qts', 'pts_limit', 'pts_total_limit', 'qts_limit')
                        318     CALL                            6
                        326     NOP                             
                        328     NOP                             
                        330     NOP                             
                        332     JUMP_FORWARD                    20 (to 374)
                        334     CALL                            1
                        342     POP_TOP                         
                        344     RETURN_VALUE                    
                        346     PUSH_EXC_INFO                   
                        348     PUSH_NULL                       
                        350     LOAD_CONST                      8: '__pyarmor_exit_36737__'
                        352     NOP                             
                        354     LOAD_CONST                      3: b'<COAddr>\x07\x00\x00\x1a@\x01\x00\x00\x00\x00\x00\x00\x00\x00\x00\x00\x00\x00\x00\x00'
                        356     CALL                            1
                        364     POP_TOP                         
                        366     RERAISE                         0
                        368     COPY                            3
                        370     POP_EXCEPT                      
                        372     RERAISE                         1
                        374     PUSH_NULL                       
                        376     LOAD_CONST                      8: '__pyarmor_exit_36737__'
                        378     LOAD_CONST                      3: b'<COAddr>\x07\x00\x00\x1a@\x01\x00\x00\x00\x00\x00\x00\x00\x00\x00\x00\x00\x00\x00\x00'
                        380     BUILD_TUPLE                     1
                        382     CALL_FUNCTION_EX                0
                        384     POP_TOP                         
                        386     RETURN_VALUE                    
                    [Exception Table]
                        28 to 326 -> 346 [0] 
                        346 to 368 -> 368 [1] lasti
                '__pyarmor_exit_36725__'
                (
                    None
                    None
                    None
                )
            [Disassembly]
                0       NOP                             
                2       LOAD_NAME                       0: __name__
                4       STORE_NAME                      1: __module__
                6       LOAD_CONST                      0: 'GetDifference_tdlib_Request'
                8       STORE_NAME                      2: __qualname__
                10      NOP                             
                12      PUSH_NULL                       
                14      LOAD_CONST                      2: '__pyarmor_enter_36724__'
                16      LOAD_CONST                      3: b'<COAddr>\x05\x00\x00"t\x00\x00\x00\x00\x00\x00\x00\x00\x00\x00\x00\x00\x00\x00\x00'
                18      BUILD_TUPLE                     1
                20      CALL_FUNCTION_EX                0
                22      POP_TOP                         
                24      RESUME                          0
                26      NOP                             
                28      NOP                             
                30      NOP                             
                32      NOP                             
                34      NOP                             
                36      LOAD_CONST                      4: 432207715
                38      STORE_NAME                      4: CONSTRUCTOR_ID
                40      LOAD_CONST                      5: 541599860
                42      STORE_NAME                      5: SUBCLASS_OF_ID
                44      LOAD_CONST                      18: (None, None, None)
                46      LOAD_CONST                      7: 'pts'
                48      LOAD_NAME                       6: int
                50      LOAD_CONST                      8: 'date'
                52      LOAD_NAME                       7: Optional
                54      LOAD_NAME                       8: datetime
                56      BINARY_SUBSCR                   
                60      LOAD_CONST                      9: 'qts'
                62      LOAD_NAME                       6: int
                64      LOAD_CONST                      10: 'pts_limit'
                66      LOAD_NAME                       7: Optional
                68      LOAD_NAME                       6: int
                70      BINARY_SUBSCR                   
                74      LOAD_CONST                      11: 'pts_total_limit'
                76      LOAD_NAME                       7: Optional
                78      LOAD_NAME                       6: int
                80      BINARY_SUBSCR                   
                84      LOAD_CONST                      12: 'qts_limit'
                86      LOAD_NAME                       7: Optional
                88      LOAD_NAME                       6: int
                90      BINARY_SUBSCR                   
                94      BUILD_TUPLE                     12
                96      LOAD_CONST                      13: <CODE> __init__
                98      MAKE_FUNCTION                   5
                100     STORE_NAME                      9: __init__
                102     LOAD_CONST                      14: <CODE> to_dict
                104     MAKE_FUNCTION                   0
                106     STORE_NAME                      10: to_dict
                108     LOAD_CONST                      15: <CODE> _bytes
                110     MAKE_FUNCTION                   0
                112     STORE_NAME                      11: _bytes
                114     LOAD_NAME                       12: classmethod
                116     LOAD_CONST                      16: <CODE> from_reader
                118     MAKE_FUNCTION                   0
                120     CALL                            0
                128     STORE_NAME                      13: from_reader
                130     LOAD_CONST                      6: None
                132     NOP                             
                134     NOP                             
                136     NOP                             
                138     JUMP_FORWARD                    19 (to 178)
                146     POP_TOP                         
                148     RETURN_CONST                    6: None
                150     PUSH_EXC_INFO                   
                152     PUSH_NULL                       
                154     LOAD_CONST                      17: '__pyarmor_exit_36725__'
                156     NOP                             
                158     LOAD_CONST                      3: b'<COAddr>\x05\x00\x00"t\x00\x00\x00\x00\x00\x00\x00\x00\x00\x00\x00\x00\x00\x00\x00'
                160     CALL                            1
                168     POP_TOP                         
                170     RERAISE                         0
                172     COPY                            3
                174     POP_EXCEPT                      
                176     RERAISE                         1
                178     PUSH_NULL                       
                180     LOAD_CONST                      17: '__pyarmor_exit_36725__'
                182     LOAD_CONST                      3: b'<COAddr>\x05\x00\x00"t\x00\x00\x00\x00\x00\x00\x00\x00\x00\x00\x00\x00\x00\x00\x00'
                184     BUILD_TUPLE                     1
                186     CALL_FUNCTION_EX                0
                188     POP_TOP                         
                190     RETURN_VALUE                    
            [Exception Table]
                36 to 130 -> 150 [0] 
                150 to 172 -> 172 [1] lasti
        'GetDifference_tdlib_Request'
        [Code]
            File Name: <frozen multithon.tl.functions.updates>
            Object Name: GetStateRequest
            Qualified Name: GetStateRequest
            Arg Count: 0
            Pos Only Arg Count: 0
            KW Only Arg Count: 0
            Stack Size: 5
            Flags: 0x20000000 (CO_PYARMOR_OBFUSCATED)
            [Names]
                '__name__'
                '__module__'
                '__qualname__'
                '__assert_armored__'
                'CONSTRUCTOR_ID'
                'SUBCLASS_OF_ID'
                'to_dict'
                '_bytes'
                'classmethod'
                'from_reader'
            [Locals+Names]
            [Constants]
                'GetStateRequest'
                '__pyarmor_assert_36738__'
                '__pyarmor_enter_36739__'
                b'<COAddr>\x05\x00\x00":\x00\x00\x00\x00\x00\x00\x00\x00\x00\x00\x00\x00\x00\x00\x00'
                0xEDD4882A
                601823745
                [Code]
                    File Name: <frozen multithon.tl.functions.updates>
                    Object Name: to_dict
                    Qualified Name: GetStateRequest.to_dict
                    Arg Count: 1
                    Pos Only Arg Count: 0
                    KW Only Arg Count: 0
                    Stack Size: 5
                    Flags: 0x20000003 (CO_OPTIMIZED | CO_NEWLOCALS | CO_PYARMOR_OBFUSCATED)
                    [Names]
                    [Locals+Names]
                        'self'
                        '__assert_armored__'
                    [Constants]
                        None
                        '__pyarmor_assert_36741__'
                        '__pyarmor_enter_36742__'
                        b'<COAddr>\x05\x00\x00\x1a(\x00\x00\x00\x00\x00\x00\x00\x00\x00\x00\x00\x00\x00\x00\x00'
                        '_'
                        'GetStateRequest'   # b'\x81\xc5\x1d\x07\x00\xee\xbf\xc6\x1e\xc8\x08\xd1y\xe9\xeb\x91'
                        '__pyarmor_exit_36743__'
                    [Disassembly]
                        0       NOP                             
                        2       NOP                             
                        4       PUSH_NULL                       
                        6       LOAD_CONST                      2: '__pyarmor_enter_36742__'
                        8       LOAD_CONST                      3: b'<COAddr>\x05\x00\x00\x1a(\x00\x00\x00\x00\x00\x00\x00\x00\x00\x00\x00\x00\x00\x00\x00'
                        10      BUILD_TUPLE                     1
                        12      CALL_FUNCTION_EX                0
                        14      POP_TOP                         
                        16      RESUME                          0
                        18      NOP                             
                        20      NOP                             
                        22      NOP                             
                        24      NOP                             
                        26      NOP                             
                        28      LOAD_CONST                      4: '_'
                        30      PUSH_NULL                       
                        32      LOAD_CONST                      1: '__pyarmor_assert_36741__'
                        34      LOAD_CONST                      5: 'GetStateRequest'   # b'\x81\xc5\x1d\x07\x00\xee\xbf\xc6\x1e\xc8\x08\xd1y\xe9\xeb\x91'
                        36      CALL                            1
                        44      BUILD_MAP                       1
                        46      NOP                             
                        48      NOP                             
                        50      NOP                             
                        52      JUMP_FORWARD                    20 (to 94)
                        54      CALL                            1
                        62      POP_TOP                         
                        64      RETURN_VALUE                    
                        66      PUSH_EXC_INFO                   
                        68      PUSH_NULL                       
                        70      LOAD_CONST                      6: '__pyarmor_exit_36743__'
                        72      NOP                             
                        74      LOAD_CONST                      3: b'<COAddr>\x05\x00\x00\x1a(\x00\x00\x00\x00\x00\x00\x00\x00\x00\x00\x00\x00\x00\x00\x00'
                        76      CALL                            1
                        84      POP_TOP                         
                        86      RERAISE                         0
                        88      COPY                            3
                        90      POP_EXCEPT                      
                        92      RERAISE                         1
                        94      PUSH_NULL                       
                        96      LOAD_CONST                      6: '__pyarmor_exit_36743__'
                        98      LOAD_CONST                      3: b'<COAddr>\x05\x00\x00\x1a(\x00\x00\x00\x00\x00\x00\x00\x00\x00\x00\x00\x00\x00\x00\x00'
                        100     BUILD_TUPLE                     1
                        102     CALL_FUNCTION_EX                0
                        104     POP_TOP                         
                        106     RETURN_VALUE                    
                    [Exception Table]
                        28 to 46 -> 66 [0] 
                        66 to 88 -> 88 [1] lasti
                [Code]
                    File Name: <frozen multithon.tl.functions.updates>
                    Object Name: _bytes
                    Qualified Name: GetStateRequest._bytes
                    Arg Count: 1
                    Pos Only Arg Count: 0
                    KW Only Arg Count: 0
                    Stack Size: 5
                    Flags: 0x20000003 (CO_OPTIMIZED | CO_NEWLOCALS | CO_PYARMOR_OBFUSCATED)
                    [Names]
                        'join'
                    [Locals+Names]
                        'self'
                        '__assert_armored__'
                    [Constants]
                        None
                        '__pyarmor_assert_36744__'
                        '__pyarmor_enter_36745__'
                        b'<COAddr>\x05\x00\x00\x1a6\x00\x00\x00\x00\x00\x00\x00\x00\x00\x00\x00\x00\x00\x00\x00'
                        b''
                        (
                            b'*\x88\xd4\xed'
                        )
                        '__pyarmor_exit_36746__'
                    [Disassembly]
                        0       NOP                             
                        2       NOP                             
                        4       PUSH_NULL                       
                        6       LOAD_CONST                      2: '__pyarmor_enter_36745__'
                        8       LOAD_CONST                      3: b'<COAddr>\x05\x00\x00\x1a6\x00\x00\x00\x00\x00\x00\x00\x00\x00\x00\x00\x00\x00\x00\x00'
                        10      BUILD_TUPLE                     1
                        12      CALL_FUNCTION_EX                0
                        14      POP_TOP                         
                        16      RESUME                          0
                        18      NOP                             
                        20      NOP                             
                        22      NOP                             
                        24      NOP                             
                        26      NOP                             
                        28      LOAD_CONST                      4: b''
                        30      LOAD_ATTR                       1: join
                        50      LOAD_CONST                      5: (b'*\x88\xd4\xed',)
                        52      CALL                            1
                        60      NOP                             
                        62      NOP                             
                        64      NOP                             
                        66      JUMP_FORWARD                    20 (to 108)
                        68      CALL                            1
                        76      POP_TOP                         
                        78      RETURN_VALUE                    
                        80      PUSH_EXC_INFO                   
                        82      PUSH_NULL                       
                        84      LOAD_CONST                      6: '__pyarmor_exit_36746__'
                        86      NOP                             
                        88      LOAD_CONST                      3: b'<COAddr>\x05\x00\x00\x1a6\x00\x00\x00\x00\x00\x00\x00\x00\x00\x00\x00\x00\x00\x00\x00'
                        90      CALL                            1
                        98      POP_TOP                         
                        100     RERAISE                         0
                        102     COPY                            3
                        104     POP_EXCEPT                      
                        106     RERAISE                         1
                        108     PUSH_NULL                       
                        110     LOAD_CONST                      6: '__pyarmor_exit_36746__'
                        112     LOAD_CONST                      3: b'<COAddr>\x05\x00\x00\x1a6\x00\x00\x00\x00\x00\x00\x00\x00\x00\x00\x00\x00\x00\x00\x00'
                        114     BUILD_TUPLE                     1
                        116     CALL_FUNCTION_EX                0
                        118     POP_TOP                         
                        120     RETURN_VALUE                    
                    [Exception Table]
                        28 to 60 -> 80 [0] 
                        80 to 102 -> 102 [1] lasti
                [Code]
                    File Name: <frozen multithon.tl.functions.updates>
                    Object Name: from_reader
                    Qualified Name: GetStateRequest.from_reader
                    Arg Count: 2
                    Pos Only Arg Count: 0
                    KW Only Arg Count: 0
                    Stack Size: 5
                    Flags: 0x20000003 (CO_OPTIMIZED | CO_NEWLOCALS | CO_PYARMOR_OBFUSCATED)
                    [Names]
                    [Locals+Names]
                        'cls'
                        'reader'
                        '__assert_armored__'
                    [Constants]
                        None
                        '__pyarmor_assert_36747__'
                        '__pyarmor_enter_36748__'
                        b'<COAddr>\x05\x00\x00\x1a"\x00\x00\x00\x00\x00\x00\x00\x00\x00\x00\x00\x00\x00\x00\x00'
                        '__pyarmor_exit_36749__'
                    [Disassembly]
                        0       NOP                             
                        2       NOP                             
                        4       PUSH_NULL                       
                        6       LOAD_CONST                      2: '__pyarmor_enter_36748__'
                        8       LOAD_CONST                      3: b'<COAddr>\x05\x00\x00\x1a"\x00\x00\x00\x00\x00\x00\x00\x00\x00\x00\x00\x00\x00\x00\x00'
                        10      BUILD_TUPLE                     1
                        12      CALL_FUNCTION_EX                0
                        14      POP_TOP                         
                        16      RESUME                          0
                        18      NOP                             
                        20      NOP                             
                        22      NOP                             
                        24      NOP                             
                        26      NOP                             
                        28      PUSH_NULL                       
                        30      LOAD_FAST                       0: cls
                        32      CALL                            0
                        40      NOP                             
                        42      NOP                             
                        44      NOP                             
                        46      JUMP_FORWARD                    20 (to 88)
                        48      CALL                            1
                        56      POP_TOP                         
                        58      RETURN_VALUE                    
                        60      PUSH_EXC_INFO                   
                        62      PUSH_NULL                       
                        64      LOAD_CONST                      4: '__pyarmor_exit_36749__'
                        66      NOP                             
                        68      LOAD_CONST                      3: b'<COAddr>\x05\x00\x00\x1a"\x00\x00\x00\x00\x00\x00\x00\x00\x00\x00\x00\x00\x00\x00\x00'
                        70      CALL                            1
                        78      POP_TOP                         
                        80      RERAISE                         0
                        82      COPY                            3
                        84      POP_EXCEPT                      
                        86      RERAISE                         1
                        88      PUSH_NULL                       
                        90      LOAD_CONST                      4: '__pyarmor_exit_36749__'
                        92      LOAD_CONST                      3: b'<COAddr>\x05\x00\x00\x1a"\x00\x00\x00\x00\x00\x00\x00\x00\x00\x00\x00\x00\x00\x00\x00'
                        94      BUILD_TUPLE                     1
                        96      CALL_FUNCTION_EX                0
                        98      POP_TOP                         
                        100     RETURN_VALUE                    
                    [Exception Table]
                        28 to 40 -> 60 [0] 
                        60 to 82 -> 82 [1] lasti
                '__pyarmor_exit_36740__'
                None
            [Disassembly]
                0       NOP                             
                2       LOAD_NAME                       0: __name__
                4       STORE_NAME                      1: __module__
                6       LOAD_CONST                      0: 'GetStateRequest'
                8       STORE_NAME                      2: __qualname__
                10      NOP                             
                12      PUSH_NULL                       
                14      LOAD_CONST                      2: '__pyarmor_enter_36739__'
                16      LOAD_CONST                      3: b'<COAddr>\x05\x00\x00":\x00\x00\x00\x00\x00\x00\x00\x00\x00\x00\x00\x00\x00\x00\x00'
                18      BUILD_TUPLE                     1
                20      CALL_FUNCTION_EX                0
                22      POP_TOP                         
                24      RESUME                          0
                26      NOP                             
                28      NOP                             
                30      NOP                             
                32      NOP                             
                34      NOP                             
                36      LOAD_CONST                      4: 0xEDD4882A
                38      STORE_NAME                      4: CONSTRUCTOR_ID
                40      LOAD_CONST                      5: 601823745
                42      STORE_NAME                      5: SUBCLASS_OF_ID
                44      LOAD_CONST                      6: <CODE> to_dict
                46      MAKE_FUNCTION                   0
                48      STORE_NAME                      6: to_dict
                50      LOAD_CONST                      7: <CODE> _bytes
                52      MAKE_FUNCTION                   0
                54      STORE_NAME                      7: _bytes
                56      LOAD_NAME                       8: classmethod
                58      LOAD_CONST                      8: <CODE> from_reader
                60      MAKE_FUNCTION                   0
                62      CALL                            0
                70      STORE_NAME                      9: from_reader
                72      LOAD_CONST                      10: None
                74      NOP                             
                76      NOP                             
                78      NOP                             
                80      JUMP_FORWARD                    19 (to 120)
                88      POP_TOP                         
                90      RETURN_CONST                    10: None
                92      PUSH_EXC_INFO                   
                94      PUSH_NULL                       
                96      LOAD_CONST                      9: '__pyarmor_exit_36740__'
                98      NOP                             
                100     LOAD_CONST                      3: b'<COAddr>\x05\x00\x00":\x00\x00\x00\x00\x00\x00\x00\x00\x00\x00\x00\x00\x00\x00\x00'
                102     CALL                            1
                110     POP_TOP                         
                112     RERAISE                         0
                114     COPY                            3
                116     POP_EXCEPT                      
                118     RERAISE                         1
                120     PUSH_NULL                       
                122     LOAD_CONST                      9: '__pyarmor_exit_36740__'
                124     LOAD_CONST                      3: b'<COAddr>\x05\x00\x00":\x00\x00\x00\x00\x00\x00\x00\x00\x00\x00\x00\x00\x00\x00\x00'
                126     BUILD_TUPLE                     1
                128     CALL_FUNCTION_EX                0
                130     POP_TOP                         
                132     RETURN_VALUE                    
            [Exception Table]
                36 to 72 -> 92 [0] 
                92 to 114 -> 114 [1] lasti
        'GetStateRequest'
        '__pyarmor_exit_36689__'
    [Disassembly]
        0       NOP                             
        2       NOP                             
        4       PUSH_NULL                       
        6       LOAD_CONST                      1: '__pyarmor_enter_36688__'
        8       LOAD_CONST                      2: b'<COAddr>\x05\x00\x00\x1a\xdc\x00\x00\x00\x00\x00\x00\x00\x00\x00\x00\x00\x00\x00\x00\x00'
        10      BUILD_TUPLE                     1
        12      CALL_FUNCTION_EX                0
        14      POP_TOP                         
        16      RESUME                          0
        18      NOP                             
        20      NOP                             
        22      NOP                             
        24      NOP                             
        26      PUSH_NULL                       
        28      LOAD_CONST                      0: '__pyarmor_assert_36687__'
        30      LOAD_CONST                      3: "File generated by TLObjects' generator. All changes will be ERASED"   # b'\x81\xc4\x11\x1f6\xba\xb9\xd7\x15\xff\x1f\xc1x\xe9\xfc\xc5\rD\xfb\x93\x86\xe4L\xc6\x00l\xb7OG\xf1\x19\xe04W2\x0c\x8c\xc5\xa6`X\xc8\xf4Q\x9d\xdb\x07F9\xeaS\xe8\xc7g\x0f\xe1;\xab\x99\x18Xn\x03rdm!'
        32      CALL                            1
        40      POP_TOP                         
        42      LOAD_CONST                      4: 3
        44      LOAD_CONST                      5: ('TLObject',)
        46      IMPORT_NAME                     1: tl.tlobject
        48      IMPORT_FROM                     2: TLObject
        50      STORE_NAME                      2: TLObject
        52      POP_TOP                         
        54      LOAD_CONST                      4: 3
        56      LOAD_CONST                      6: ('TLRequest',)
        58      IMPORT_NAME                     1: tl.tlobject
        60      IMPORT_FROM                     3: TLRequest
        62      STORE_NAME                      3: TLRequest
        64      POP_TOP                         
        66      LOAD_CONST                      7: 0
        68      LOAD_CONST                      8: ('Optional', 'List', 'Union', 'TYPE_CHECKING')
        70      IMPORT_NAME                     4: typing
        72      IMPORT_FROM                     5: Optional
        74      STORE_NAME                      5: Optional
        76      IMPORT_FROM                     6: List
        78      STORE_NAME                      6: List
        80      IMPORT_FROM                     7: Union
        82      STORE_NAME                      7: Union
        84      IMPORT_FROM                     8: TYPE_CHECKING
        86      STORE_NAME                      8: TYPE_CHECKING
        88      POP_TOP                         
        90      LOAD_CONST                      7: 0
        92      LOAD_CONST                      9: None
        94      IMPORT_NAME                     9: os
        96      STORE_NAME                      9: os
        98      LOAD_CONST                      7: 0
        100     LOAD_CONST                      9: None
        102     IMPORT_NAME                     10: struct
        104     STORE_NAME                      10: struct
        106     LOAD_CONST                      7: 0
        108     LOAD_CONST                      10: ('datetime',)
        110     IMPORT_NAME                     11: datetime
        112     IMPORT_FROM                     11: datetime
        114     STORE_NAME                      11: datetime
        116     POP_TOP                         
        118     LOAD_NAME                       8: TYPE_CHECKING
        120     POP_JUMP_IF_FALSE               8 (to 138)
        122     LOAD_CONST                      4: 3
        124     LOAD_CONST                      11: ('TypeChannelMessagesFilter', 'TypeInputChannel')
        126     IMPORT_NAME                     12: tl.types
        128     IMPORT_FROM                     13: TypeChannelMessagesFilter
        130     STORE_NAME                      13: TypeChannelMessagesFilter
        132     IMPORT_FROM                     14: TypeInputChannel
        134     STORE_NAME                      14: TypeInputChannel
        136     POP_TOP                         
        138     PUSH_NULL                       
        140     LOAD_BUILD_CLASS                
        142     LOAD_CONST                      12: <CODE> GetChannelDifferenceRequest
        144     MAKE_FUNCTION                   0
        146     LOAD_CONST                      13: 'GetChannelDifferenceRequest'
        148     LOAD_NAME                       3: TLRequest
        150     CALL                            3
        158     STORE_NAME                      15: GetChannelDifferenceRequest
        160     PUSH_NULL                       
        162     LOAD_BUILD_CLASS                
        164     LOAD_CONST                      14: <CODE> GetDifferenceRequest
        166     MAKE_FUNCTION                   0
        168     LOAD_CONST                      15: 'GetDifferenceRequest'
        170     LOAD_NAME                       3: TLRequest
        172     CALL                            3
        180     STORE_NAME                      16: GetDifferenceRequest
        182     PUSH_NULL                       
        184     LOAD_BUILD_CLASS                
        186     LOAD_CONST                      16: <CODE> GetDifference_tdlib_Request
        188     MAKE_FUNCTION                   0
        190     LOAD_CONST                      17: 'GetDifference_tdlib_Request'
        192     LOAD_NAME                       3: TLRequest
        194     CALL                            3
        202     STORE_NAME                      17: GetDifference_tdlib_Request
        204     PUSH_NULL                       
        206     LOAD_BUILD_CLASS                
        208     LOAD_CONST                      18: <CODE> GetStateRequest
        210     MAKE_FUNCTION                   0
        212     LOAD_CONST                      19: 'GetStateRequest'
        214     LOAD_NAME                       3: TLRequest
        216     CALL                            3
        224     STORE_NAME                      18: GetStateRequest
        226     LOAD_CONST                      9: None
        228     NOP                             
        230     NOP                             
        232     NOP                             
        234     JUMP_FORWARD                    19 (to 274)
        242     POP_TOP                         
        244     RETURN_CONST                    9: None
        246     PUSH_EXC_INFO                   
        248     PUSH_NULL                       
        250     LOAD_CONST                      20: '__pyarmor_exit_36689__'
        252     NOP                             
        254     LOAD_CONST                      2: b'<COAddr>\x05\x00\x00\x1a\xdc\x00\x00\x00\x00\x00\x00\x00\x00\x00\x00\x00\x00\x00\x00\x00'
        256     CALL                            1
        264     POP_TOP                         
        266     RERAISE                         0
        268     COPY                            3
        270     POP_EXCEPT                      
        272     RERAISE                         1
        274     PUSH_NULL                       
        276     LOAD_CONST                      20: '__pyarmor_exit_36689__'
        278     LOAD_CONST                      2: b'<COAddr>\x05\x00\x00\x1a\xdc\x00\x00\x00\x00\x00\x00\x00\x00\x00\x00\x00\x00\x00\x00\x00'
        280     BUILD_TUPLE                     1
        282     CALL_FUNCTION_EX                0
        284     POP_TOP                         
        286     RETURN_VALUE                    
    [Exception Table]
        26 to 226 -> 246 [0] 
        246 to 268 -> 268 [1] lasti
