#decoded by lolz.live/mrpenny / t.me/zeus_jackpot
# ================================
# Примечания по Pyarmor:
# - Байт-код и объекты кода Pyarmor соответствуют стандартному Python, но присутствуют специальные вызовы функций среды выполнения (runtime) Pyarmor.
# - Вызовы строк — это не ошибки, а маркеры, которые обрабатываются Pyarmor во время выполнения.
#
# Руководство по декомпиляции (без среды выполнения):
# 1. Игнорируйте зашифрованные байты после `#`; используйте только строку до `#`.
# 2. Удалите "__pyarmor_enter_xxx__"(b"<COAddr>...") и "__pyarmor_leave_xxx__"(b"<COAddr>...") (пролог/эпилог).
# 3. "__pyarmor_assert_xxx__"(A) не является настоящим оператором assert.
#    - Если A — это имя или читаемая строка: замените на A.
#    - Если A — это (X, "Y"): замените на X.Y.
#    - Если A — это (X, "Y", Z): замените на X.Y = Z.
#    - В противном случае: выберите наиболее подходящую/логичную замену.
# 4. "__pyarmor_bcc_xxx__"(...) указывает на машинный (нативный) код; тело функции недоступно. Добавьте комментарий.
# ================================

[Code]
    File Name: <frozen multithon.tl.functions.upload>
    Object Name: <module>
    Qualified Name: <module>
    Arg Count: 0
    Pos Only Arg Count: 0
    KW Only Arg Count: 0
    Stack Size: 5
    Flags: 0x20000000 (CO_PYARMOR_OBFUSCATED)
    [Names]
        '__assert_armored__'
        'tl.tlobject'
        'TLObject'
        'TLRequest'
        'typing'
        'Optional'
        'List'
        'Union'
        'TYPE_CHECKING'
        'os'
        'struct'
        'datetime'
        'tl.types'
        'TypeInputFileLocation'
        'TypeInputWebFileLocation'
        'GetCdnFileRequest'
        'GetCdnFileHashesRequest'
        'GetFileRequest'
        'GetFileHashesRequest'
        'GetWebFileRequest'
        'ReuploadCdnFileRequest'
        'SaveBigFilePartRequest'
        'SaveFilePartRequest'
    [Locals+Names]
    [Constants]
        '__pyarmor_assert_36750__'
        '__pyarmor_enter_36751__'
        b'<COAddr>\x07\x00\x00\x1a4\x01\x00\x00\x00\x00\x00\x00\x00\x00\x00\x00\x00\x00\x00\x00'
        "File generated by TLObjects' generator. All changes will be ERASED"   # b'\x81\xc4\x11\x1f6\xba\xb9\xd7\x15\xff\x1f\xc1x\xe9\xfc\xc5\rD\xfb\x93\x86\xe4L\xc6\x00l\xb7OG\xf1\x19\xe04W2\x0c\x8c\xc5\xa6`X\xc8\xf4Q\x9d\xdb\x07F9\xeaS\xe8\xc7g\x0f\xe1;\xab\x99\x18Xn\x03rdm!'
        3
        (
            'TLObject'
        )
        (
            'TLRequest'
        )
        0
        (
            'Optional'
            'List'
            'Union'
            'TYPE_CHECKING'
        )
        None
        (
            'datetime'
        )
        (
            'TypeInputFileLocation'
            'TypeInputWebFileLocation'
        )
        [Code]
            File Name: <frozen multithon.tl.functions.upload>
            Object Name: GetCdnFileRequest
            Qualified Name: GetCdnFileRequest
            Arg Count: 0
            Pos Only Arg Count: 0
            KW Only Arg Count: 0
            Stack Size: 6
            Flags: 0x20000000 (CO_PYARMOR_OBFUSCATED)
            [Names]
                '__name__'
                '__module__'
                '__qualname__'
                '__assert_armored__'
                'CONSTRUCTOR_ID'
                'SUBCLASS_OF_ID'
                'bytes'
                'int'
                '__init__'
                'to_dict'
                '_bytes'
                'classmethod'
                'from_reader'
            [Locals+Names]
            [Constants]
                'GetCdnFileRequest'
                '__pyarmor_assert_36753__'
                '__pyarmor_enter_36754__'
                b'<COAddr>\x07\x00\x00"N\x00\x00\x00\x00\x00\x00\x00\x00\x00\x00\x00\x00\x00\x00\x00'
                962554330
                0xF5CCF928
                'file_token'
                'offset'
                'limit'
                [Code]
                    File Name: <frozen multithon.tl.functions.upload>
                    Object Name: __init__
                    Qualified Name: GetCdnFileRequest.__init__
                    Arg Count: 4
                    Pos Only Arg Count: 0
                    KW Only Arg Count: 0
                    Stack Size: 5
                    Flags: 0x20000003 (CO_OPTIMIZED | CO_NEWLOCALS | CO_PYARMOR_OBFUSCATED)
                    [Names]
                        'file_token'
                        'offset'
                        'limit'
                    [Locals+Names]
                        'self'
                        'file_token'
                        'offset'
                        'limit'
                        '__assert_armored__'
                    [Constants]
                        '\n        :returns upload.CdnFile: Instance of either CdnFileReuploadNeeded, CdnFile.\n        '
                        '__pyarmor_assert_36756__'
                        '__pyarmor_enter_36757__'
                        b'<COAddr>\x05\x00\x00\x1a@\x00\x00\x00\x00\x00\x00\x00\x00\x00\x00\x00\x00\x00\x00\x00'
                        '__pyarmor_exit_36758__'
                        None
                    [Disassembly]
                        0       NOP                             
                        2       NOP                             
                        4       PUSH_NULL                       
                        6       LOAD_CONST                      2: '__pyarmor_enter_36757__'
                        8       LOAD_CONST                      3: b'<COAddr>\x05\x00\x00\x1a@\x00\x00\x00\x00\x00\x00\x00\x00\x00\x00\x00\x00\x00\x00\x00'
                        10      BUILD_TUPLE                     1
                        12      CALL_FUNCTION_EX                0
                        14      POP_TOP                         
                        16      RESUME                          0
                        18      NOP                             
                        20      NOP                             
                        22      NOP                             
                        24      NOP                             
                        26      NOP                             
                        28      LOAD_FAST                       1: file_token
                        30      LOAD_FAST                       0: self
                        32      STORE_ATTR                      0: file_token
                        42      LOAD_FAST                       2: offset
                        44      LOAD_FAST                       0: self
                        46      STORE_ATTR                      1: offset
                        56      LOAD_FAST                       3: limit
                        58      LOAD_FAST                       0: self
                        60      STORE_ATTR                      2: limit
                        70      LOAD_CONST                      5: None
                        72      NOP                             
                        74      NOP                             
                        76      NOP                             
                        78      JUMP_FORWARD                    19 (to 118)
                        86      POP_TOP                         
                        88      RETURN_CONST                    5: None
                        90      PUSH_EXC_INFO                   
                        92      PUSH_NULL                       
                        94      LOAD_CONST                      4: '__pyarmor_exit_36758__'
                        96      NOP                             
                        98      LOAD_CONST                      3: b'<COAddr>\x05\x00\x00\x1a@\x00\x00\x00\x00\x00\x00\x00\x00\x00\x00\x00\x00\x00\x00\x00'
                        100     CALL                            1
                        108     POP_TOP                         
                        110     RERAISE                         0
                        112     COPY                            3
                        114     POP_EXCEPT                      
                        116     RERAISE                         1
                        118     PUSH_NULL                       
                        120     LOAD_CONST                      4: '__pyarmor_exit_36758__'
                        122     LOAD_CONST                      3: b'<COAddr>\x05\x00\x00\x1a@\x00\x00\x00\x00\x00\x00\x00\x00\x00\x00\x00\x00\x00\x00\x00'
                        124     BUILD_TUPLE                     1
                        126     CALL_FUNCTION_EX                0
                        128     POP_TOP                         
                        130     RETURN_VALUE                    
                    [Exception Table]
                        28 to 70 -> 90 [0] 
                        90 to 112 -> 112 [1] lasti
                [Code]
                    File Name: <frozen multithon.tl.functions.upload>
                    Object Name: to_dict
                    Qualified Name: GetCdnFileRequest.to_dict
                    Arg Count: 1
                    Pos Only Arg Count: 0
                    KW Only Arg Count: 0
                    Stack Size: 8
                    Flags: 0x20000003 (CO_OPTIMIZED | CO_NEWLOCALS | CO_PYARMOR_OBFUSCATED)
                    [Names]
                        'file_token'
                        'offset'
                        'limit'
                    [Locals+Names]
                        'self'
                        '__assert_armored__'
                    [Constants]
                        None
                        '__pyarmor_assert_36759__'
                        '__pyarmor_enter_36760__'
                        b'<COAddr>\x07\x00\x00\x1a|\x00\x00\x00\x00\x00\x00\x00\x00\x00\x00\x00\x00\x00\x00\x00'
                        '_'
                        'GetCdnFileRequest'   # b'\x81\xc5\x1d\x07\x10\xfe\xb0\xf4\x12\xf6\x08\xf2i\xfd\xed\x80\x1cI'
                        'file_token'   # b'\x81\xe4\x11\x1f6\xc5\xaa\xdd\x10\xff\x03'
                        'offset'
                        'limit'
                        '__pyarmor_exit_36761__'
                    [Disassembly]
                        0       NOP                             
                        2       NOP                             
                        4       PUSH_NULL                       
                        6       LOAD_CONST                      2: '__pyarmor_enter_36760__'
                        8       LOAD_CONST                      3: b'<COAddr>\x07\x00\x00\x1a|\x00\x00\x00\x00\x00\x00\x00\x00\x00\x00\x00\x00\x00\x00\x00'
                        10      BUILD_TUPLE                     1
                        12      CALL_FUNCTION_EX                0
                        14      POP_TOP                         
                        16      RESUME                          0
                        18      NOP                             
                        20      NOP                             
                        22      NOP                             
                        24      NOP                             
                        26      NOP                             
                        28      LOAD_CONST                      4: '_'
                        30      PUSH_NULL                       
                        32      LOAD_CONST                      1: '__pyarmor_assert_36759__'
                        34      LOAD_CONST                      5: 'GetCdnFileRequest'   # b'\x81\xc5\x1d\x07\x10\xfe\xb0\xf4\x12\xf6\x08\xf2i\xfd\xed\x80\x1cI'
                        36      CALL                            1
                        44      PUSH_NULL                       
                        46      LOAD_CONST                      1: '__pyarmor_assert_36759__'
                        48      LOAD_CONST                      6: 'file_token'   # b'\x81\xe4\x11\x1f6\xc5\xaa\xdd\x10\xff\x03'
                        50      CALL                            1
                        58      LOAD_FAST                       0: self
                        60      LOAD_ATTR                       0: file_token
                        80      LOAD_CONST                      7: 'offset'
                        82      LOAD_FAST                       0: self
                        84      LOAD_ATTR                       2: offset
                        104     LOAD_CONST                      8: 'limit'
                        106     LOAD_FAST                       0: self
                        108     LOAD_ATTR                       4: limit
                        128     BUILD_MAP                       4
                        130     NOP                             
                        132     NOP                             
                        134     NOP                             
                        136     JUMP_FORWARD                    20 (to 178)
                        138     CALL                            1
                        146     POP_TOP                         
                        148     RETURN_VALUE                    
                        150     PUSH_EXC_INFO                   
                        152     PUSH_NULL                       
                        154     LOAD_CONST                      9: '__pyarmor_exit_36761__'
                        156     NOP                             
                        158     LOAD_CONST                      3: b'<COAddr>\x07\x00\x00\x1a|\x00\x00\x00\x00\x00\x00\x00\x00\x00\x00\x00\x00\x00\x00\x00'
                        160     CALL                            1
                        168     POP_TOP                         
                        170     RERAISE                         0
                        172     COPY                            3
                        174     POP_EXCEPT                      
                        176     RERAISE                         1
                        178     PUSH_NULL                       
                        180     LOAD_CONST                      9: '__pyarmor_exit_36761__'
                        182     LOAD_CONST                      3: b'<COAddr>\x07\x00\x00\x1a|\x00\x00\x00\x00\x00\x00\x00\x00\x00\x00\x00\x00\x00\x00\x00'
                        184     BUILD_TUPLE                     1
                        186     CALL_FUNCTION_EX                0
                        188     POP_TOP                         
                        190     RETURN_VALUE                    
                    [Exception Table]
                        28 to 130 -> 150 [0] 
                        150 to 172 -> 172 [1] lasti
                [Code]
                    File Name: <frozen multithon.tl.functions.upload>
                    Object Name: _bytes
                    Qualified Name: GetCdnFileRequest._bytes
                    Arg Count: 1
                    Pos Only Arg Count: 0
                    KW Only Arg Count: 0
                    Stack Size: 9
                    Flags: 0x20000003 (CO_OPTIMIZED | CO_NEWLOCALS | CO_PYARMOR_OBFUSCATED)
                    [Names]
                        'join'
                        'serialize_bytes'
                        'file_token'
                        'struct'
                        'pack'
                        'offset'
                        'limit'
                    [Locals+Names]
                        'self'
                        '__assert_armored__'
                    [Constants]
                        None
                        '__pyarmor_assert_36762__'
                        '__pyarmor_enter_36763__'
                        b'<COAddr>\x07\x00\x00\x1a\xe8\x00\x00\x00\x00\x00\x00\x00\x00\x00\x00\x00\x00\x00\x00\x00'
                        b''
                        b'\xdai_9'
                        '<q'
                        '<i'
                        '__pyarmor_exit_36764__'
                    [Disassembly]
                        0       NOP                             
                        2       NOP                             
                        4       PUSH_NULL                       
                        6       LOAD_CONST                      2: '__pyarmor_enter_36763__'
                        8       LOAD_CONST                      3: b'<COAddr>\x07\x00\x00\x1a\xe8\x00\x00\x00\x00\x00\x00\x00\x00\x00\x00\x00\x00\x00\x00\x00'
                        10      BUILD_TUPLE                     1
                        12      CALL_FUNCTION_EX                0
                        14      POP_TOP                         
                        16      RESUME                          0
                        18      NOP                             
                        20      NOP                             
                        22      NOP                             
                        24      NOP                             
                        26      NOP                             
                        28      LOAD_CONST                      4: b''
                        30      LOAD_ATTR                       1: join
                        50      LOAD_CONST                      5: b'\xdai_9'
                        52      LOAD_FAST                       0: self
                        54      LOAD_ATTR                       3: serialize_bytes
                        74      LOAD_FAST                       0: self
                        76      LOAD_ATTR                       4: file_token
                        96      CALL                            1
                        104     LOAD_GLOBAL                     7: NULL + struct
                        114     LOAD_ATTR                       8: pack
                        134     LOAD_CONST                      6: '<q'
                        136     LOAD_FAST                       0: self
                        138     LOAD_ATTR                       10: offset
                        158     CALL                            2
                        166     LOAD_GLOBAL                     7: NULL + struct
                        176     LOAD_ATTR                       8: pack
                        196     LOAD_CONST                      7: '<i'
                        198     LOAD_FAST                       0: self
                        200     LOAD_ATTR                       12: limit
                        220     CALL                            2
                        228     BUILD_TUPLE                     4
                        230     CALL                            1
                        238     NOP                             
                        240     NOP                             
                        242     NOP                             
                        244     JUMP_FORWARD                    20 (to 286)
                        246     CALL                            1
                        254     POP_TOP                         
                        256     RETURN_VALUE                    
                        258     PUSH_EXC_INFO                   
                        260     PUSH_NULL                       
                        262     LOAD_CONST                      8: '__pyarmor_exit_36764__'
                        264     NOP                             
                        266     LOAD_CONST                      3: b'<COAddr>\x07\x00\x00\x1a\xe8\x00\x00\x00\x00\x00\x00\x00\x00\x00\x00\x00\x00\x00\x00\x00'
                        268     CALL                            1
                        276     POP_TOP                         
                        278     RERAISE                         0
                        280     COPY                            3
                        282     POP_EXCEPT                      
                        284     RERAISE                         1
                        286     PUSH_NULL                       
                        288     LOAD_CONST                      8: '__pyarmor_exit_36764__'
                        290     LOAD_CONST                      3: b'<COAddr>\x07\x00\x00\x1a\xe8\x00\x00\x00\x00\x00\x00\x00\x00\x00\x00\x00\x00\x00\x00\x00'
                        292     BUILD_TUPLE                     1
                        294     CALL_FUNCTION_EX                0
                        296     POP_TOP                         
                        298     RETURN_VALUE                    
                    [Exception Table]
                        28 to 238 -> 258 [0] 
                        258 to 280 -> 280 [1] lasti
                [Code]
                    File Name: <frozen multithon.tl.functions.upload>
                    Object Name: from_reader
                    Qualified Name: GetCdnFileRequest.from_reader
                    Arg Count: 2
                    Pos Only Arg Count: 0
                    KW Only Arg Count: 0
                    Stack Size: 5
                    Flags: 0x20000003 (CO_OPTIMIZED | CO_NEWLOCALS | CO_PYARMOR_OBFUSCATED)
                    [Names]
                        'tgread_bytes'
                        'read_long'
                        'read_int'
                    [Locals+Names]
                        'cls'
                        'reader'
                        '__assert_armored__'
                        '_var_var_0'
                        '_var_var_1'
                        '_var_var_2'
                    [Constants]
                        None
                        '__pyarmor_assert_36765__'
                        '__pyarmor_enter_36766__'
                        b'<COAddr>\x05\x00\x00\x1a\x8a\x00\x00\x00\x00\x00\x00\x00\x00\x00\x00\x00\x00\x00\x00\x00'
                        (
                            'file_token'
                            'offset'
                            'limit'
                        )
                        '__pyarmor_exit_36767__'
                    [Disassembly]
                        0       NOP                             
                        2       NOP                             
                        4       PUSH_NULL                       
                        6       LOAD_CONST                      2: '__pyarmor_enter_36766__'
                        8       LOAD_CONST                      3: b'<COAddr>\x05\x00\x00\x1a\x8a\x00\x00\x00\x00\x00\x00\x00\x00\x00\x00\x00\x00\x00\x00\x00'
                        10      BUILD_TUPLE                     1
                        12      CALL_FUNCTION_EX                0
                        14      POP_TOP                         
                        16      RESUME                          0
                        18      NOP                             
                        20      NOP                             
                        22      NOP                             
                        24      NOP                             
                        26      NOP                             
                        28      LOAD_FAST                       1: reader
                        30      LOAD_ATTR                       1: tgread_bytes
                        50      CALL                            0
                        58      STORE_FAST                      3: _var_var_0
                        60      LOAD_FAST                       1: reader
                        62      LOAD_ATTR                       3: read_long
                        82      CALL                            0
                        90      STORE_FAST                      4: _var_var_1
                        92      LOAD_FAST                       1: reader
                        94      LOAD_ATTR                       5: read_int
                        114     CALL                            0
                        122     STORE_FAST                      5: _var_var_2
                        124     PUSH_NULL                       
                        126     LOAD_FAST                       0: cls
                        128     LOAD_FAST                       3: _var_var_0
                        130     LOAD_FAST                       4: _var_var_1
                        132     LOAD_FAST                       5: _var_var_2
                        134     KW_NAMES                        4: ('file_token', 'offset', 'limit')
                        136     CALL                            3
                        144     NOP                             
                        146     NOP                             
                        148     NOP                             
                        150     JUMP_FORWARD                    20 (to 192)
                        152     CALL                            1
                        160     POP_TOP                         
                        162     RETURN_VALUE                    
                        164     PUSH_EXC_INFO                   
                        166     PUSH_NULL                       
                        168     LOAD_CONST                      5: '__pyarmor_exit_36767__'
                        170     NOP                             
                        172     LOAD_CONST                      3: b'<COAddr>\x05\x00\x00\x1a\x8a\x00\x00\x00\x00\x00\x00\x00\x00\x00\x00\x00\x00\x00\x00\x00'
                        174     CALL                            1
                        182     POP_TOP                         
                        184     RERAISE                         0
                        186     COPY                            3
                        188     POP_EXCEPT                      
                        190     RERAISE                         1
                        192     PUSH_NULL                       
                        194     LOAD_CONST                      5: '__pyarmor_exit_36767__'
                        196     LOAD_CONST                      3: b'<COAddr>\x05\x00\x00\x1a\x8a\x00\x00\x00\x00\x00\x00\x00\x00\x00\x00\x00\x00\x00\x00\x00'
                        198     BUILD_TUPLE                     1
                        200     CALL_FUNCTION_EX                0
                        202     POP_TOP                         
                        204     RETURN_VALUE                    
                    [Exception Table]
                        28 to 144 -> 164 [0] 
                        164 to 186 -> 186 [1] lasti
                '__pyarmor_exit_36755__'
                None
            [Disassembly]
                0       NOP                             
                2       LOAD_NAME                       0: __name__
                4       STORE_NAME                      1: __module__
                6       LOAD_CONST                      0: 'GetCdnFileRequest'
                8       STORE_NAME                      2: __qualname__
                10      NOP                             
                12      PUSH_NULL                       
                14      LOAD_CONST                      2: '__pyarmor_enter_36754__'
                16      LOAD_CONST                      3: b'<COAddr>\x07\x00\x00"N\x00\x00\x00\x00\x00\x00\x00\x00\x00\x00\x00\x00\x00\x00\x00'
                18      BUILD_TUPLE                     1
                20      CALL_FUNCTION_EX                0
                22      POP_TOP                         
                24      RESUME                          0
                26      NOP                             
                28      NOP                             
                30      NOP                             
                32      NOP                             
                34      NOP                             
                36      LOAD_CONST                      4: 962554330
                38      STORE_NAME                      4: CONSTRUCTOR_ID
                40      LOAD_CONST                      5: 0xF5CCF928
                42      STORE_NAME                      5: SUBCLASS_OF_ID
                44      LOAD_CONST                      6: 'file_token'
                46      LOAD_NAME                       6: bytes
                48      LOAD_CONST                      7: 'offset'
                50      LOAD_NAME                       7: int
                52      LOAD_CONST                      8: 'limit'
                54      LOAD_NAME                       7: int
                56      BUILD_TUPLE                     6
                58      LOAD_CONST                      9: <CODE> __init__
                60      MAKE_FUNCTION                   4
                62      STORE_NAME                      8: __init__
                64      LOAD_CONST                      10: <CODE> to_dict
                66      MAKE_FUNCTION                   0
                68      STORE_NAME                      9: to_dict
                70      LOAD_CONST                      11: <CODE> _bytes
                72      MAKE_FUNCTION                   0
                74      STORE_NAME                      10: _bytes
                76      LOAD_NAME                       11: classmethod
                78      LOAD_CONST                      12: <CODE> from_reader
                80      MAKE_FUNCTION                   0
                82      CALL                            0
                90      STORE_NAME                      12: from_reader
                92      LOAD_CONST                      14: None
                94      NOP                             
                96      NOP                             
                98      NOP                             
                100     JUMP_FORWARD                    19 (to 140)
                108     POP_TOP                         
                110     RETURN_CONST                    14: None
                112     PUSH_EXC_INFO                   
                114     PUSH_NULL                       
                116     LOAD_CONST                      13: '__pyarmor_exit_36755__'
                118     NOP                             
                120     LOAD_CONST                      3: b'<COAddr>\x07\x00\x00"N\x00\x00\x00\x00\x00\x00\x00\x00\x00\x00\x00\x00\x00\x00\x00'
                122     CALL                            1
                130     POP_TOP                         
                132     RERAISE                         0
                134     COPY                            3
                136     POP_EXCEPT                      
                138     RERAISE                         1
                140     PUSH_NULL                       
                142     LOAD_CONST                      13: '__pyarmor_exit_36755__'
                144     LOAD_CONST                      3: b'<COAddr>\x07\x00\x00"N\x00\x00\x00\x00\x00\x00\x00\x00\x00\x00\x00\x00\x00\x00\x00'
                146     BUILD_TUPLE                     1
                148     CALL_FUNCTION_EX                0
                150     POP_TOP                         
                152     RETURN_VALUE                    
            [Exception Table]
                36 to 92 -> 112 [0] 
                112 to 134 -> 134 [1] lasti
        'GetCdnFileRequest'
        [Code]
            File Name: <frozen multithon.tl.functions.upload>
            Object Name: GetCdnFileHashesRequest
            Qualified Name: GetCdnFileHashesRequest
            Arg Count: 0
            Pos Only Arg Count: 0
            KW Only Arg Count: 0
            Stack Size: 5
            Flags: 0x20000000 (CO_PYARMOR_OBFUSCATED)
            [Names]
                '__name__'
                '__module__'
                '__qualname__'
                '__assert_armored__'
                'CONSTRUCTOR_ID'
                'SUBCLASS_OF_ID'
                'bytes'
                'int'
                '__init__'
                'to_dict'
                '_bytes'
                'classmethod'
                'from_reader'
            [Locals+Names]
            [Constants]
                'GetCdnFileHashesRequest'
                '__pyarmor_assert_36768__'
                '__pyarmor_enter_36769__'
                b'<COAddr>\x07\x00\x00"J\x00\x00\x00\x00\x00\x00\x00\x00\x00\x00\x00\x00\x00\x00\x00'
                0x91DC3F31
                0xA5940726
                'file_token'
                'offset'
                [Code]
                    File Name: <frozen multithon.tl.functions.upload>
                    Object Name: __init__
                    Qualified Name: GetCdnFileHashesRequest.__init__
                    Arg Count: 3
                    Pos Only Arg Count: 0
                    KW Only Arg Count: 0
                    Stack Size: 5
                    Flags: 0x20000003 (CO_OPTIMIZED | CO_NEWLOCALS | CO_PYARMOR_OBFUSCATED)
                    [Names]
                        'file_token'
                        'offset'
                    [Locals+Names]
                        'self'
                        'file_token'
                        'offset'
                        '__assert_armored__'
                    [Constants]
                        '\n        :returns Vector<FileHash>: This type has no constructors.\n        '
                        '__pyarmor_assert_36771__'
                        '__pyarmor_enter_36772__'
                        b'<COAddr>\x07\x00\x00\x1a2\x00\x00\x00\x00\x00\x00\x00\x00\x00\x00\x00\x00\x00\x00\x00'
                        '__pyarmor_exit_36773__'
                        None
                    [Disassembly]
                        0       NOP                             
                        2       NOP                             
                        4       PUSH_NULL                       
                        6       LOAD_CONST                      2: '__pyarmor_enter_36772__'
                        8       LOAD_CONST                      3: b'<COAddr>\x07\x00\x00\x1a2\x00\x00\x00\x00\x00\x00\x00\x00\x00\x00\x00\x00\x00\x00\x00'
                        10      BUILD_TUPLE                     1
                        12      CALL_FUNCTION_EX                0
                        14      POP_TOP                         
                        16      RESUME                          0
                        18      NOP                             
                        20      NOP                             
                        22      NOP                             
                        24      NOP                             
                        26      NOP                             
                        28      LOAD_FAST                       1: file_token
                        30      LOAD_FAST                       0: self
                        32      STORE_ATTR                      0: file_token
                        42      LOAD_FAST                       2: offset
                        44      LOAD_FAST                       0: self
                        46      STORE_ATTR                      1: offset
                        56      LOAD_CONST                      5: None
                        58      NOP                             
                        60      NOP                             
                        62      NOP                             
                        64      JUMP_FORWARD                    19 (to 104)
                        72      POP_TOP                         
                        74      RETURN_CONST                    5: None
                        76      PUSH_EXC_INFO                   
                        78      PUSH_NULL                       
                        80      LOAD_CONST                      4: '__pyarmor_exit_36773__'
                        82      NOP                             
                        84      LOAD_CONST                      3: b'<COAddr>\x07\x00\x00\x1a2\x00\x00\x00\x00\x00\x00\x00\x00\x00\x00\x00\x00\x00\x00\x00'
                        86      CALL                            1
                        94      POP_TOP                         
                        96      RERAISE                         0
                        98      COPY                            3
                        100     POP_EXCEPT                      
                        102     RERAISE                         1
                        104     PUSH_NULL                       
                        106     LOAD_CONST                      4: '__pyarmor_exit_36773__'
                        108     LOAD_CONST                      3: b'<COAddr>\x07\x00\x00\x1a2\x00\x00\x00\x00\x00\x00\x00\x00\x00\x00\x00\x00\x00\x00\x00'
                        110     BUILD_TUPLE                     1
                        112     CALL_FUNCTION_EX                0
                        114     POP_TOP                         
                        116     RETURN_VALUE                    
                    [Exception Table]
                        28 to 56 -> 76 [0] 
                        76 to 98 -> 98 [1] lasti
                [Code]
                    File Name: <frozen multithon.tl.functions.upload>
                    Object Name: to_dict
                    Qualified Name: GetCdnFileHashesRequest.to_dict
                    Arg Count: 1
                    Pos Only Arg Count: 0
                    KW Only Arg Count: 0
                    Stack Size: 6
                    Flags: 0x20000003 (CO_OPTIMIZED | CO_NEWLOCALS | CO_PYARMOR_OBFUSCATED)
                    [Names]
                        'file_token'
                        'offset'
                    [Locals+Names]
                        'self'
                        '__assert_armored__'
                    [Constants]
                        None
                        '__pyarmor_assert_36774__'
                        '__pyarmor_enter_36775__'
                        b'<COAddr>\x05\x00\x00\x1ad\x00\x00\x00\x00\x00\x00\x00\x00\x00\x00\x00\x00\x00\x00\x00'
                        '_'
                        'GetCdnFileHashesRequest'   # b'\x81\xc5\x1d\x07\x10\xfe\xb0\xf4\x12\xf6\x08\xe8m\xff\xf0\x80\x1co\xbe\xb6\xbf\xce]\xd8'
                        'file_token'   # b'\x81\xe4\x11\x1f6\xc5\xaa\xdd\x10\xff\x03'
                        'offset'
                        '__pyarmor_exit_36776__'
                    [Disassembly]
                        0       NOP                             
                        2       NOP                             
                        4       PUSH_NULL                       
                        6       LOAD_CONST                      2: '__pyarmor_enter_36775__'
                        8       LOAD_CONST                      3: b'<COAddr>\x05\x00\x00\x1ad\x00\x00\x00\x00\x00\x00\x00\x00\x00\x00\x00\x00\x00\x00\x00'
                        10      BUILD_TUPLE                     1
                        12      CALL_FUNCTION_EX                0
                        14      POP_TOP                         
                        16      RESUME                          0
                        18      NOP                             
                        20      NOP                             
                        22      NOP                             
                        24      NOP                             
                        26      NOP                             
                        28      LOAD_CONST                      4: '_'
                        30      PUSH_NULL                       
                        32      LOAD_CONST                      1: '__pyarmor_assert_36774__'
                        34      LOAD_CONST                      5: 'GetCdnFileHashesRequest'   # b'\x81\xc5\x1d\x07\x10\xfe\xb0\xf4\x12\xf6\x08\xe8m\xff\xf0\x80\x1co\xbe\xb6\xbf\xce]\xd8'
                        36      CALL                            1
                        44      PUSH_NULL                       
                        46      LOAD_CONST                      1: '__pyarmor_assert_36774__'
                        48      LOAD_CONST                      6: 'file_token'   # b'\x81\xe4\x11\x1f6\xc5\xaa\xdd\x10\xff\x03'
                        50      CALL                            1
                        58      LOAD_FAST                       0: self
                        60      LOAD_ATTR                       0: file_token
                        80      LOAD_CONST                      7: 'offset'
                        82      LOAD_FAST                       0: self
                        84      LOAD_ATTR                       2: offset
                        104     BUILD_MAP                       3
                        106     NOP                             
                        108     NOP                             
                        110     NOP                             
                        112     JUMP_FORWARD                    20 (to 154)
                        114     CALL                            1
                        122     POP_TOP                         
                        124     RETURN_VALUE                    
                        126     PUSH_EXC_INFO                   
                        128     PUSH_NULL                       
                        130     LOAD_CONST                      8: '__pyarmor_exit_36776__'
                        132     NOP                             
                        134     LOAD_CONST                      3: b'<COAddr>\x05\x00\x00\x1ad\x00\x00\x00\x00\x00\x00\x00\x00\x00\x00\x00\x00\x00\x00\x00'
                        136     CALL                            1
                        144     POP_TOP                         
                        146     RERAISE                         0
                        148     COPY                            3
                        150     POP_EXCEPT                      
                        152     RERAISE                         1
                        154     PUSH_NULL                       
                        156     LOAD_CONST                      8: '__pyarmor_exit_36776__'
                        158     LOAD_CONST                      3: b'<COAddr>\x05\x00\x00\x1ad\x00\x00\x00\x00\x00\x00\x00\x00\x00\x00\x00\x00\x00\x00\x00'
                        160     BUILD_TUPLE                     1
                        162     CALL_FUNCTION_EX                0
                        164     POP_TOP                         
                        166     RETURN_VALUE                    
                    [Exception Table]
                        28 to 106 -> 126 [0] 
                        126 to 148 -> 148 [1] lasti
                [Code]
                    File Name: <frozen multithon.tl.functions.upload>
                    Object Name: _bytes
                    Qualified Name: GetCdnFileHashesRequest._bytes
                    Arg Count: 1
                    Pos Only Arg Count: 0
                    KW Only Arg Count: 0
                    Stack Size: 8
                    Flags: 0x20000003 (CO_OPTIMIZED | CO_NEWLOCALS | CO_PYARMOR_OBFUSCATED)
                    [Names]
                        'join'
                        'serialize_bytes'
                        'file_token'
                        'struct'
                        'pack'
                        'offset'
                    [Locals+Names]
                        'self'
                        '__assert_armored__'
                    [Constants]
                        None
                        '__pyarmor_assert_36777__'
                        '__pyarmor_enter_36778__'
                        b'<COAddr>\x07\x00\x00\x1a\xaa\x00\x00\x00\x00\x00\x00\x00\x00\x00\x00\x00\x00\x00\x00\x00'
                        b''
                        b'1?\xdc\x91'
                        '<q'
                        '__pyarmor_exit_36779__'
                    [Disassembly]
                        0       NOP                             
                        2       NOP                             
                        4       PUSH_NULL                       
                        6       LOAD_CONST                      2: '__pyarmor_enter_36778__'
                        8       LOAD_CONST                      3: b'<COAddr>\x07\x00\x00\x1a\xaa\x00\x00\x00\x00\x00\x00\x00\x00\x00\x00\x00\x00\x00\x00\x00'
                        10      BUILD_TUPLE                     1
                        12      CALL_FUNCTION_EX                0
                        14      POP_TOP                         
                        16      RESUME                          0
                        18      NOP                             
                        20      NOP                             
                        22      NOP                             
                        24      NOP                             
                        26      NOP                             
                        28      LOAD_CONST                      4: b''
                        30      LOAD_ATTR                       1: join
                        50      LOAD_CONST                      5: b'1?\xdc\x91'
                        52      LOAD_FAST                       0: self
                        54      LOAD_ATTR                       3: serialize_bytes
                        74      LOAD_FAST                       0: self
                        76      LOAD_ATTR                       4: file_token
                        96      CALL                            1
                        104     LOAD_GLOBAL                     7: NULL + struct
                        114     LOAD_ATTR                       8: pack
                        134     LOAD_CONST                      6: '<q'
                        136     LOAD_FAST                       0: self
                        138     LOAD_ATTR                       10: offset
                        158     CALL                            2
                        166     BUILD_TUPLE                     3
                        168     CALL                            1
                        176     NOP                             
                        178     NOP                             
                        180     NOP                             
                        182     JUMP_FORWARD                    20 (to 224)
                        184     CALL                            1
                        192     POP_TOP                         
                        194     RETURN_VALUE                    
                        196     PUSH_EXC_INFO                   
                        198     PUSH_NULL                       
                        200     LOAD_CONST                      7: '__pyarmor_exit_36779__'
                        202     NOP                             
                        204     LOAD_CONST                      3: b'<COAddr>\x07\x00\x00\x1a\xaa\x00\x00\x00\x00\x00\x00\x00\x00\x00\x00\x00\x00\x00\x00\x00'
                        206     CALL                            1
                        214     POP_TOP                         
                        216     RERAISE                         0
                        218     COPY                            3
                        220     POP_EXCEPT                      
                        222     RERAISE                         1
                        224     PUSH_NULL                       
                        226     LOAD_CONST                      7: '__pyarmor_exit_36779__'
                        228     LOAD_CONST                      3: b'<COAddr>\x07\x00\x00\x1a\xaa\x00\x00\x00\x00\x00\x00\x00\x00\x00\x00\x00\x00\x00\x00\x00'
                        230     BUILD_TUPLE                     1
                        232     CALL_FUNCTION_EX                0
                        234     POP_TOP                         
                        236     RETURN_VALUE                    
                    [Exception Table]
                        28 to 176 -> 196 [0] 
                        196 to 218 -> 218 [1] lasti
                [Code]
                    File Name: <frozen multithon.tl.functions.upload>
                    Object Name: from_reader
                    Qualified Name: GetCdnFileHashesRequest.from_reader
                    Arg Count: 2
                    Pos Only Arg Count: 0
                    KW Only Arg Count: 0
                    Stack Size: 5
                    Flags: 0x20000003 (CO_OPTIMIZED | CO_NEWLOCALS | CO_PYARMOR_OBFUSCATED)
                    [Names]
                        'tgread_bytes'
                        'read_long'
                    [Locals+Names]
                        'cls'
                        'reader'
                        '__assert_armored__'
                        '_var_var_0'
                        '_var_var_1'
                    [Constants]
                        None
                        '__pyarmor_assert_36780__'
                        '__pyarmor_enter_36781__'
                        b'<COAddr>\x05\x00\x00\x1ah\x00\x00\x00\x00\x00\x00\x00\x00\x00\x00\x00\x00\x00\x00\x00'
                        (
                            'file_token'
                            'offset'
                        )
                        '__pyarmor_exit_36782__'
                    [Disassembly]
                        0       NOP                             
                        2       NOP                             
                        4       PUSH_NULL                       
                        6       LOAD_CONST                      2: '__pyarmor_enter_36781__'
                        8       LOAD_CONST                      3: b'<COAddr>\x05\x00\x00\x1ah\x00\x00\x00\x00\x00\x00\x00\x00\x00\x00\x00\x00\x00\x00\x00'
                        10      BUILD_TUPLE                     1
                        12      CALL_FUNCTION_EX                0
                        14      POP_TOP                         
                        16      RESUME                          0
                        18      NOP                             
                        20      NOP                             
                        22      NOP                             
                        24      NOP                             
                        26      NOP                             
                        28      LOAD_FAST                       1: reader
                        30      LOAD_ATTR                       1: tgread_bytes
                        50      CALL                            0
                        58      STORE_FAST                      3: _var_var_0
                        60      LOAD_FAST                       1: reader
                        62      LOAD_ATTR                       3: read_long
                        82      CALL                            0
                        90      STORE_FAST                      4: _var_var_1
                        92      PUSH_NULL                       
                        94      LOAD_FAST                       0: cls
                        96      LOAD_FAST                       3: _var_var_0
                        98      LOAD_FAST                       4: _var_var_1
                        100     KW_NAMES                        4: ('file_token', 'offset')
                        102     CALL                            2
                        110     NOP                             
                        112     NOP                             
                        114     NOP                             
                        116     JUMP_FORWARD                    20 (to 158)
                        118     CALL                            1
                        126     POP_TOP                         
                        128     RETURN_VALUE                    
                        130     PUSH_EXC_INFO                   
                        132     PUSH_NULL                       
                        134     LOAD_CONST                      5: '__pyarmor_exit_36782__'
                        136     NOP                             
                        138     LOAD_CONST                      3: b'<COAddr>\x05\x00\x00\x1ah\x00\x00\x00\x00\x00\x00\x00\x00\x00\x00\x00\x00\x00\x00\x00'
                        140     CALL                            1
                        148     POP_TOP                         
                        150     RERAISE                         0
                        152     COPY                            3
                        154     POP_EXCEPT                      
                        156     RERAISE                         1
                        158     PUSH_NULL                       
                        160     LOAD_CONST                      5: '__pyarmor_exit_36782__'
                        162     LOAD_CONST                      3: b'<COAddr>\x05\x00\x00\x1ah\x00\x00\x00\x00\x00\x00\x00\x00\x00\x00\x00\x00\x00\x00\x00'
                        164     BUILD_TUPLE                     1
                        166     CALL_FUNCTION_EX                0
                        168     POP_TOP                         
                        170     RETURN_VALUE                    
                    [Exception Table]
                        28 to 110 -> 130 [0] 
                        130 to 152 -> 152 [1] lasti
                '__pyarmor_exit_36770__'
                None
            [Disassembly]
                0       NOP                             
                2       LOAD_NAME                       0: __name__
                4       STORE_NAME                      1: __module__
                6       LOAD_CONST                      0: 'GetCdnFileHashesRequest'
                8       STORE_NAME                      2: __qualname__
                10      NOP                             
                12      PUSH_NULL                       
                14      LOAD_CONST                      2: '__pyarmor_enter_36769__'
                16      LOAD_CONST                      3: b'<COAddr>\x07\x00\x00"J\x00\x00\x00\x00\x00\x00\x00\x00\x00\x00\x00\x00\x00\x00\x00'
                18      BUILD_TUPLE                     1
                20      CALL_FUNCTION_EX                0
                22      POP_TOP                         
                24      RESUME                          0
                26      NOP                             
                28      NOP                             
                30      NOP                             
                32      NOP                             
                34      NOP                             
                36      LOAD_CONST                      4: 0x91DC3F31
                38      STORE_NAME                      4: CONSTRUCTOR_ID
                40      LOAD_CONST                      5: 0xA5940726
                42      STORE_NAME                      5: SUBCLASS_OF_ID
                44      LOAD_CONST                      6: 'file_token'
                46      LOAD_NAME                       6: bytes
                48      LOAD_CONST                      7: 'offset'
                50      LOAD_NAME                       7: int
                52      BUILD_TUPLE                     4
                54      LOAD_CONST                      8: <CODE> __init__
                56      MAKE_FUNCTION                   4
                58      STORE_NAME                      8: __init__
                60      LOAD_CONST                      9: <CODE> to_dict
                62      MAKE_FUNCTION                   0
                64      STORE_NAME                      9: to_dict
                66      LOAD_CONST                      10: <CODE> _bytes
                68      MAKE_FUNCTION                   0
                70      STORE_NAME                      10: _bytes
                72      LOAD_NAME                       11: classmethod
                74      LOAD_CONST                      11: <CODE> from_reader
                76      MAKE_FUNCTION                   0
                78      CALL                            0
                86      STORE_NAME                      12: from_reader
                88      LOAD_CONST                      13: None
                90      NOP                             
                92      NOP                             
                94      NOP                             
                96      JUMP_FORWARD                    19 (to 136)
                104     POP_TOP                         
                106     RETURN_CONST                    13: None
                108     PUSH_EXC_INFO                   
                110     PUSH_NULL                       
                112     LOAD_CONST                      12: '__pyarmor_exit_36770__'
                114     NOP                             
                116     LOAD_CONST                      3: b'<COAddr>\x07\x00\x00"J\x00\x00\x00\x00\x00\x00\x00\x00\x00\x00\x00\x00\x00\x00\x00'
                118     CALL                            1
                126     POP_TOP                         
                128     RERAISE                         0
                130     COPY                            3
                132     POP_EXCEPT                      
                134     RERAISE                         1
                136     PUSH_NULL                       
                138     LOAD_CONST                      12: '__pyarmor_exit_36770__'
                140     LOAD_CONST                      3: b'<COAddr>\x07\x00\x00"J\x00\x00\x00\x00\x00\x00\x00\x00\x00\x00\x00\x00\x00\x00\x00'
                142     BUILD_TUPLE                     1
                144     CALL_FUNCTION_EX                0
                146     POP_TOP                         
                148     RETURN_VALUE                    
            [Exception Table]
                36 to 88 -> 108 [0] 
                108 to 130 -> 130 [1] lasti
        'GetCdnFileHashesRequest'
        [Code]
            File Name: <frozen multithon.tl.functions.upload>
            Object Name: GetFileRequest
            Qualified Name: GetFileRequest
            Arg Count: 0
            Pos Only Arg Count: 0
            KW Only Arg Count: 0
            Stack Size: 12
            Flags: 0x20000000 (CO_PYARMOR_OBFUSCATED)
            [Names]
                '__name__'
                '__module__'
                '__qualname__'
                '__assert_armored__'
                'CONSTRUCTOR_ID'
                'SUBCLASS_OF_ID'
                'int'
                'Optional'
                'bool'
                '__init__'
                'to_dict'
                '_bytes'
                'classmethod'
                'from_reader'
            [Locals+Names]
            [Constants]
                'GetFileRequest'
                '__pyarmor_assert_36783__'
                '__pyarmor_enter_36784__'
                b'<COAddr>\x05\x00\x00"p\x00\x00\x00\x00\x00\x00\x00\x00\x00\x00\x00\x00\x00\x00\x00'
                0xBE5335BE
                1822152488
                None
                'location'
                'TypeInputFileLocation'   # b'\x81\xd6\x01\x036\xd3\xb0\xc2\x0e\xee+\xc9`\xe9\xd4\x8a\x0c\\\xaf\xae\xa5\xc5'
                'offset'
                'limit'
                'precise'
                'cdn_supported'
                [Code]
                    File Name: <frozen multithon.tl.functions.upload>
                    Object Name: __init__
                    Qualified Name: GetFileRequest.__init__
                    Arg Count: 6
                    Pos Only Arg Count: 0
                    KW Only Arg Count: 0
                    Stack Size: 5
                    Flags: 0x20000003 (CO_OPTIMIZED | CO_NEWLOCALS | CO_PYARMOR_OBFUSCATED)
                    [Names]
                        'location'
                        'offset'
                        'limit'
                        'precise'
                        'cdn_supported'
                    [Locals+Names]
                        'self'
                        'location'
                        'offset'
                        'limit'
                        'precise'
                        'cdn_supported'
                        '__assert_armored__'
                    [Constants]
                        '\n        :returns upload.File: Instance of either File, FileCdnRedirect.\n        '
                        '__pyarmor_assert_36786__'
                        '__pyarmor_enter_36787__'
                        b'<COAddr>\x07\x00\x00\x1a\\\x00\x00\x00\x00\x00\x00\x00\x00\x00\x00\x00\x00\x00\x00\x00'
                        '__pyarmor_exit_36788__'
                        None
                    [Disassembly]
                        0       NOP                             
                        2       NOP                             
                        4       PUSH_NULL                       
                        6       LOAD_CONST                      2: '__pyarmor_enter_36787__'
                        8       LOAD_CONST                      3: b'<COAddr>\x07\x00\x00\x1a\\\x00\x00\x00\x00\x00\x00\x00\x00\x00\x00\x00\x00\x00\x00\x00'
                        10      BUILD_TUPLE                     1
                        12      CALL_FUNCTION_EX                0
                        14      POP_TOP                         
                        16      RESUME                          0
                        18      NOP                             
                        20      NOP                             
                        22      NOP                             
                        24      NOP                             
                        26      NOP                             
                        28      LOAD_FAST                       1: location
                        30      LOAD_FAST                       0: self
                        32      STORE_ATTR                      0: location
                        42      LOAD_FAST                       2: offset
                        44      LOAD_FAST                       0: self
                        46      STORE_ATTR                      1: offset
                        56      LOAD_FAST                       3: limit
                        58      LOAD_FAST                       0: self
                        60      STORE_ATTR                      2: limit
                        70      LOAD_FAST                       4: precise
                        72      LOAD_FAST                       0: self
                        74      STORE_ATTR                      3: precise
                        84      LOAD_FAST                       5: cdn_supported
                        86      LOAD_FAST                       0: self
                        88      STORE_ATTR                      4: cdn_supported
                        98      LOAD_CONST                      5: None
                        100     NOP                             
                        102     NOP                             
                        104     NOP                             
                        106     JUMP_FORWARD                    19 (to 146)
                        114     POP_TOP                         
                        116     RETURN_CONST                    5: None
                        118     PUSH_EXC_INFO                   
                        120     PUSH_NULL                       
                        122     LOAD_CONST                      4: '__pyarmor_exit_36788__'
                        124     NOP                             
                        126     LOAD_CONST                      3: b'<COAddr>\x07\x00\x00\x1a\\\x00\x00\x00\x00\x00\x00\x00\x00\x00\x00\x00\x00\x00\x00\x00'
                        128     CALL                            1
                        136     POP_TOP                         
                        138     RERAISE                         0
                        140     COPY                            3
                        142     POP_EXCEPT                      
                        144     RERAISE                         1
                        146     PUSH_NULL                       
                        148     LOAD_CONST                      4: '__pyarmor_exit_36788__'
                        150     LOAD_CONST                      3: b'<COAddr>\x07\x00\x00\x1a\\\x00\x00\x00\x00\x00\x00\x00\x00\x00\x00\x00\x00\x00\x00\x00'
                        152     BUILD_TUPLE                     1
                        154     CALL_FUNCTION_EX                0
                        156     POP_TOP                         
                        158     RETURN_VALUE                    
                    [Exception Table]
                        28 to 98 -> 118 [0] 
                        118 to 140 -> 140 [1] lasti
                [Code]
                    File Name: <frozen multithon.tl.functions.upload>
                    Object Name: to_dict
                    Qualified Name: GetFileRequest.to_dict
                    Arg Count: 1
                    Pos Only Arg Count: 0
                    KW Only Arg Count: 0
                    Stack Size: 13
                    Flags: 0x20000003 (CO_OPTIMIZED | CO_NEWLOCALS | CO_PYARMOR_OBFUSCATED)
                    [Names]
                        'isinstance'
                        'location'
                        'TLObject'
                        'to_dict'
                        'offset'
                        'limit'
                        'precise'
                        'cdn_supported'
                    [Locals+Names]
                        'self'
                        '__assert_armored__'
                    [Constants]
                        None
                        '__pyarmor_assert_36789__'
                        '__pyarmor_enter_36790__'
                        b'<COAddr>\x07\x00\x00\x1a\x14\x01\x00\x00\x00\x00\x00\x00\x00\x00\x00\x00\x00\x00\x00\x00'
                        '_'
                        'GetFileRequest'   # b'\x81\xc5\x1d\x07\x15\xf3\xb2\xd7)\xff\x1c\xd5i\xff\xec'
                        'location'
                        'offset'
                        'limit'
                        'precise'
                        'cdn_supported'   # b'\x81\xe1\x1c\x1d\x0c\xe9\xab\xc2\x0b\xf5\x1f\xd4i\xe8'
                        '__pyarmor_exit_36791__'
                    [Disassembly]
                        0       NOP                             
                        2       NOP                             
                        4       PUSH_NULL                       
                        6       LOAD_CONST                      2: '__pyarmor_enter_36790__'
                        8       LOAD_CONST                      3: b'<COAddr>\x07\x00\x00\x1a\x14\x01\x00\x00\x00\x00\x00\x00\x00\x00\x00\x00\x00\x00\x00\x00'
                        10      BUILD_TUPLE                     1
                        12      CALL_FUNCTION_EX                0
                        14      POP_TOP                         
                        16      RESUME                          0
                        18      NOP                             
                        20      NOP                             
                        22      NOP                             
                        24      NOP                             
                        26      NOP                             
                        28      LOAD_CONST                      4: '_'
                        30      PUSH_NULL                       
                        32      LOAD_CONST                      1: '__pyarmor_assert_36789__'
                        34      LOAD_CONST                      5: 'GetFileRequest'   # b'\x81\xc5\x1d\x07\x15\xf3\xb2\xd7)\xff\x1c\xd5i\xff\xec'
                        36      CALL                            1
                        44      LOAD_CONST                      6: 'location'
                        46      LOAD_GLOBAL                     1: NULL + isinstance
                        56      LOAD_FAST                       0: self
                        58      LOAD_ATTR                       2: location
                        78      LOAD_GLOBAL                     4: TLObject
                        88      CALL                            2
                        96      POP_JUMP_IF_FALSE               26 (to 150)
                        98      LOAD_FAST                       0: self
                        100     LOAD_ATTR                       2: location
                        120     LOAD_ATTR                       7: to_dict
                        140     CALL                            0
                        148     JUMP_FORWARD                    11 (to 172)
                        150     LOAD_FAST                       0: self
                        152     LOAD_ATTR                       2: location
                        172     LOAD_CONST                      7: 'offset'
                        174     LOAD_FAST                       0: self
                        176     LOAD_ATTR                       8: offset
                        196     LOAD_CONST                      8: 'limit'
                        198     LOAD_FAST                       0: self
                        200     LOAD_ATTR                       10: limit
                        220     LOAD_CONST                      9: 'precise'
                        222     LOAD_FAST                       0: self
                        224     LOAD_ATTR                       12: precise
                        244     PUSH_NULL                       
                        246     LOAD_CONST                      1: '__pyarmor_assert_36789__'
                        248     LOAD_CONST                      10: 'cdn_supported'   # b'\x81\xe1\x1c\x1d\x0c\xe9\xab\xc2\x0b\xf5\x1f\xd4i\xe8'
                        250     CALL                            1
                        258     LOAD_FAST                       0: self
                        260     LOAD_ATTR                       14: cdn_supported
                        280     BUILD_MAP                       6
                        282     NOP                             
                        284     NOP                             
                        286     NOP                             
                        288     JUMP_FORWARD                    20 (to 330)
                        290     CALL                            1
                        298     POP_TOP                         
                        300     RETURN_VALUE                    
                        302     PUSH_EXC_INFO                   
                        304     PUSH_NULL                       
                        306     LOAD_CONST                      11: '__pyarmor_exit_36791__'
                        308     NOP                             
                        310     LOAD_CONST                      3: b'<COAddr>\x07\x00\x00\x1a\x14\x01\x00\x00\x00\x00\x00\x00\x00\x00\x00\x00\x00\x00\x00\x00'
                        312     CALL                            1
                        320     POP_TOP                         
                        322     RERAISE                         0
                        324     COPY                            3
                        326     POP_EXCEPT                      
                        328     RERAISE                         1
                        330     PUSH_NULL                       
                        332     LOAD_CONST                      11: '__pyarmor_exit_36791__'
                        334     LOAD_CONST                      3: b'<COAddr>\x07\x00\x00\x1a\x14\x01\x00\x00\x00\x00\x00\x00\x00\x00\x00\x00\x00\x00\x00\x00'
                        336     BUILD_TUPLE                     1
                        338     CALL_FUNCTION_EX                0
                        340     POP_TOP                         
                        342     RETURN_VALUE                    
                    [Exception Table]
                        28 to 282 -> 302 [0] 
                        302 to 324 -> 324 [1] lasti
                [Code]
                    File Name: <frozen multithon.tl.functions.upload>
                    Object Name: _bytes
                    Qualified Name: GetFileRequest._bytes
                    Arg Count: 1
                    Pos Only Arg Count: 0
                    KW Only Arg Count: 0
                    Stack Size: 10
                    Flags: 0x20000003 (CO_OPTIMIZED | CO_NEWLOCALS | CO_PYARMOR_OBFUSCATED)
                    [Names]
                        'join'
                        'struct'
                        'pack'
                        'precise'
                        'cdn_supported'
                        'location'
                        '_bytes'
                        'offset'
                        'limit'
                    [Locals+Names]
                        'self'
                        '__assert_armored__'
                    [Constants]
                        None
                        '__pyarmor_assert_36792__'
                        '__pyarmor_enter_36793__'
                        b'<COAddr>\x05\x00\x00\x1a\x86\x01\x00\x00\x00\x00\x00\x00\x00\x00\x00\x00\x00\x00\x00\x00'
                        b''
                        b'\xbe5S\xbe'
                        '<I'
                        False
                        0
                        1
                        2
                        '<q'
                        '<i'
                        '__pyarmor_exit_36794__'
                    [Disassembly]
                        0       NOP                             
                        2       NOP                             
                        4       PUSH_NULL                       
                        6       LOAD_CONST                      2: '__pyarmor_enter_36793__'
                        8       LOAD_CONST                      3: b'<COAddr>\x05\x00\x00\x1a\x86\x01\x00\x00\x00\x00\x00\x00\x00\x00\x00\x00\x00\x00\x00\x00'
                        10      BUILD_TUPLE                     1
                        12      CALL_FUNCTION_EX                0
                        14      POP_TOP                         
                        16      RESUME                          0
                        18      NOP                             
                        20      NOP                             
                        22      NOP                             
                        24      NOP                             
                        26      NOP                             
                        28      LOAD_CONST                      4: b''
                        30      LOAD_ATTR                       1: join
                        50      LOAD_CONST                      5: b'\xbe5S\xbe'
                        52      LOAD_GLOBAL                     3: NULL + struct
                        62      LOAD_ATTR                       4: pack
                        82      LOAD_CONST                      6: '<I'
                        84      LOAD_FAST                       0: self
                        86      LOAD_ATTR                       6: precise
                        106     POP_JUMP_IF_NONE                14 (to 136)
                        108     LOAD_FAST                       0: self
                        110     LOAD_ATTR                       6: precise
                        130     LOAD_CONST                      7: False
                        132     IS_OP                           0 (is)
                        134     POP_JUMP_IF_FALSE               2 (to 140)
                        136     LOAD_CONST                      8: 0
                        138     JUMP_FORWARD                    1 (to 142)
                        140     LOAD_CONST                      9: 1
                        142     LOAD_FAST                       0: self
                        144     LOAD_ATTR                       8: cdn_supported
                        164     POP_JUMP_IF_NONE                14 (to 194)
                        166     LOAD_FAST                       0: self
                        168     LOAD_ATTR                       8: cdn_supported
                        188     LOAD_CONST                      7: False
                        190     IS_OP                           0 (is)
                        192     POP_JUMP_IF_FALSE               2 (to 198)
                        194     LOAD_CONST                      8: 0
                        196     JUMP_FORWARD                    1 (to 200)
                        198     LOAD_CONST                      10: 2
                        200     BINARY_OP                       7 (|)
                        204     CALL                            2
                        212     LOAD_FAST                       0: self
                        214     LOAD_ATTR                       10: location
                        234     LOAD_ATTR                       13: _bytes
                        254     CALL                            0
                        262     LOAD_GLOBAL                     3: NULL + struct
                        272     LOAD_ATTR                       4: pack
                        292     LOAD_CONST                      11: '<q'
                        294     LOAD_FAST                       0: self
                        296     LOAD_ATTR                       14: offset
                        316     CALL                            2
                        324     LOAD_GLOBAL                     3: NULL + struct
                        334     LOAD_ATTR                       4: pack
                        354     LOAD_CONST                      12: '<i'
                        356     LOAD_FAST                       0: self
                        358     LOAD_ATTR                       16: limit
                        378     CALL                            2
                        386     BUILD_TUPLE                     5
                        388     CALL                            1
                        396     NOP                             
                        398     NOP                             
                        400     NOP                             
                        402     JUMP_FORWARD                    20 (to 444)
                        404     CALL                            1
                        412     POP_TOP                         
                        414     RETURN_VALUE                    
                        416     PUSH_EXC_INFO                   
                        418     PUSH_NULL                       
                        420     LOAD_CONST                      13: '__pyarmor_exit_36794__'
                        422     NOP                             
                        424     LOAD_CONST                      3: b'<COAddr>\x05\x00\x00\x1a\x86\x01\x00\x00\x00\x00\x00\x00\x00\x00\x00\x00\x00\x00\x00\x00'
                        426     CALL                            1
                        434     POP_TOP                         
                        436     RERAISE                         0
                        438     COPY                            3
                        440     POP_EXCEPT                      
                        442     RERAISE                         1
                        444     PUSH_NULL                       
                        446     LOAD_CONST                      13: '__pyarmor_exit_36794__'
                        448     LOAD_CONST                      3: b'<COAddr>\x05\x00\x00\x1a\x86\x01\x00\x00\x00\x00\x00\x00\x00\x00\x00\x00\x00\x00\x00\x00'
                        450     BUILD_TUPLE                     1
                        452     CALL_FUNCTION_EX                0
                        454     POP_TOP                         
                        456     RETURN_VALUE                    
                    [Exception Table]
                        28 to 396 -> 416 [0] 
                        416 to 438 -> 438 [1] lasti
                [Code]
                    File Name: <frozen multithon.tl.functions.upload>
                    Object Name: from_reader
                    Qualified Name: GetFileRequest.from_reader
                    Arg Count: 2
                    Pos Only Arg Count: 0
                    KW Only Arg Count: 0
                    Stack Size: 7
                    Flags: 0x20000003 (CO_OPTIMIZED | CO_NEWLOCALS | CO_PYARMOR_OBFUSCATED)
                    [Names]
                        'read_int'
                        'bool'
                        'tgread_object'
                        'read_long'
                    [Locals+Names]
                        'cls'
                        'reader'
                        '__assert_armored__'
                        '_var_var_3'
                        '_var_var_4'
                        '_var_var_5'
                        '_var_var_6'
                        '_var_var_1'
                        '_var_var_2'
                    [Constants]
                        None
                        '__pyarmor_assert_36795__'
                        '__pyarmor_enter_36796__'
                        b'<COAddr>\x07\x00\x00\x1a\xe6\x00\x00\x00\x00\x00\x00\x00\x00\x00\x00\x00\x00\x00\x00\x00'
                        1
                        2
                        (
                            'location'
                            'offset'
                            'limit'
                            'precise'
                            'cdn_supported'
                        )
                        '__pyarmor_exit_36797__'
                    [Disassembly]
                        0       NOP                             
                        2       NOP                             
                        4       PUSH_NULL                       
                        6       LOAD_CONST                      2: '__pyarmor_enter_36796__'
                        8       LOAD_CONST                      3: b'<COAddr>\x07\x00\x00\x1a\xe6\x00\x00\x00\x00\x00\x00\x00\x00\x00\x00\x00\x00\x00\x00\x00'
                        10      BUILD_TUPLE                     1
                        12      CALL_FUNCTION_EX                0
                        14      POP_TOP                         
                        16      RESUME                          0
                        18      NOP                             
                        20      NOP                             
                        22      NOP                             
                        24      NOP                             
                        26      NOP                             
                        28      LOAD_FAST                       1: reader
                        30      LOAD_ATTR                       1: read_int
                        50      CALL                            0
                        58      STORE_FAST                      3: _var_var_3
                        60      LOAD_GLOBAL                     3: NULL + bool
                        70      LOAD_FAST                       3: _var_var_3
                        72      LOAD_CONST                      4: 1
                        74      BINARY_OP                       1 (&)
                        78      CALL                            1
                        86      STORE_FAST                      4: _var_var_4
                        88      LOAD_GLOBAL                     3: NULL + bool
                        98      LOAD_FAST                       3: _var_var_3
                        100     LOAD_CONST                      5: 2
                        102     BINARY_OP                       1 (&)
                        106     CALL                            1
                        114     STORE_FAST                      5: _var_var_5
                        116     LOAD_FAST                       1: reader
                        118     LOAD_ATTR                       5: tgread_object
                        138     CALL                            0
                        146     STORE_FAST                      6: _var_var_6
                        148     LOAD_FAST                       1: reader
                        150     LOAD_ATTR                       7: read_long
                        170     CALL                            0
                        178     STORE_FAST                      7: _var_var_1
                        180     LOAD_FAST                       1: reader
                        182     LOAD_ATTR                       1: read_int
                        202     CALL                            0
                        210     STORE_FAST                      8: _var_var_2
                        212     PUSH_NULL                       
                        214     LOAD_FAST                       0: cls
                        216     LOAD_FAST                       6: _var_var_6
                        218     LOAD_FAST                       7: _var_var_1
                        220     LOAD_FAST                       8: _var_var_2
                        222     LOAD_FAST                       4: _var_var_4
                        224     LOAD_FAST                       5: _var_var_5
                        226     KW_NAMES                        6: ('location', 'offset', 'limit', 'precise', 'cdn_supported')
                        228     CALL                            5
                        236     NOP                             
                        238     NOP                             
                        240     NOP                             
                        242     JUMP_FORWARD                    20 (to 284)
                        244     CALL                            1
                        252     POP_TOP                         
                        254     RETURN_VALUE                    
                        256     PUSH_EXC_INFO                   
                        258     PUSH_NULL                       
                        260     LOAD_CONST                      7: '__pyarmor_exit_36797__'
                        262     NOP                             
                        264     LOAD_CONST                      3: b'<COAddr>\x07\x00\x00\x1a\xe6\x00\x00\x00\x00\x00\x00\x00\x00\x00\x00\x00\x00\x00\x00\x00'
                        266     CALL                            1
                        274     POP_TOP                         
                        276     RERAISE                         0
                        278     COPY                            3
                        280     POP_EXCEPT                      
                        282     RERAISE                         1
                        284     PUSH_NULL                       
                        286     LOAD_CONST                      7: '__pyarmor_exit_36797__'
                        288     LOAD_CONST                      3: b'<COAddr>\x07\x00\x00\x1a\xe6\x00\x00\x00\x00\x00\x00\x00\x00\x00\x00\x00\x00\x00\x00\x00'
                        290     BUILD_TUPLE                     1
                        292     CALL_FUNCTION_EX                0
                        294     POP_TOP                         
                        296     RETURN_VALUE                    
                    [Exception Table]
                        28 to 236 -> 256 [0] 
                        256 to 278 -> 278 [1] lasti
                '__pyarmor_exit_36785__'
                (
                    None
                    None
                )
            [Disassembly]
                0       NOP                             
                2       LOAD_NAME                       0: __name__
                4       STORE_NAME                      1: __module__
                6       LOAD_CONST                      0: 'GetFileRequest'
                8       STORE_NAME                      2: __qualname__
                10      NOP                             
                12      PUSH_NULL                       
                14      LOAD_CONST                      2: '__pyarmor_enter_36784__'
                16      LOAD_CONST                      3: b'<COAddr>\x05\x00\x00"p\x00\x00\x00\x00\x00\x00\x00\x00\x00\x00\x00\x00\x00\x00\x00'
                18      BUILD_TUPLE                     1
                20      CALL_FUNCTION_EX                0
                22      POP_TOP                         
                24      RESUME                          0
                26      NOP                             
                28      NOP                             
                30      NOP                             
                32      NOP                             
                34      NOP                             
                36      LOAD_CONST                      4: 0xBE5335BE
                38      STORE_NAME                      4: CONSTRUCTOR_ID
                40      LOAD_CONST                      5: 1822152488
                42      STORE_NAME                      5: SUBCLASS_OF_ID
                44      LOAD_CONST                      18: (None, None)
                46      LOAD_CONST                      7: 'location'
                48      PUSH_NULL                       
                50      LOAD_CONST                      1: '__pyarmor_assert_36783__'
                52      LOAD_CONST                      8: 'TypeInputFileLocation'   # b'\x81\xd6\x01\x036\xd3\xb0\xc2\x0e\xee+\xc9`\xe9\xd4\x8a\x0c\\\xaf\xae\xa5\xc5'
                54      CALL                            1
                62      LOAD_CONST                      9: 'offset'
                64      LOAD_NAME                       6: int
                66      LOAD_CONST                      10: 'limit'
                68      LOAD_NAME                       6: int
                70      LOAD_CONST                      11: 'precise'
                72      LOAD_NAME                       7: Optional
                74      LOAD_NAME                       8: bool
                76      BINARY_SUBSCR                   
                80      LOAD_CONST                      12: 'cdn_supported'
                82      LOAD_NAME                       7: Optional
                84      LOAD_NAME                       8: bool
                86      BINARY_SUBSCR                   
                90      BUILD_TUPLE                     10
                92      LOAD_CONST                      13: <CODE> __init__
                94      MAKE_FUNCTION                   5
                96      STORE_NAME                      9: __init__
                98      LOAD_CONST                      14: <CODE> to_dict
                100     MAKE_FUNCTION                   0
                102     STORE_NAME                      10: to_dict
                104     LOAD_CONST                      15: <CODE> _bytes
                106     MAKE_FUNCTION                   0
                108     STORE_NAME                      11: _bytes
                110     LOAD_NAME                       12: classmethod
                112     LOAD_CONST                      16: <CODE> from_reader
                114     MAKE_FUNCTION                   0
                116     CALL                            0
                124     STORE_NAME                      13: from_reader
                126     LOAD_CONST                      6: None
                128     NOP                             
                130     NOP                             
                132     NOP                             
                134     JUMP_FORWARD                    19 (to 174)
                142     POP_TOP                         
                144     RETURN_CONST                    6: None
                146     PUSH_EXC_INFO                   
                148     PUSH_NULL                       
                150     LOAD_CONST                      17: '__pyarmor_exit_36785__'
                152     NOP                             
                154     LOAD_CONST                      3: b'<COAddr>\x05\x00\x00"p\x00\x00\x00\x00\x00\x00\x00\x00\x00\x00\x00\x00\x00\x00\x00'
                156     CALL                            1
                164     POP_TOP                         
                166     RERAISE                         0
                168     COPY                            3
                170     POP_EXCEPT                      
                172     RERAISE                         1
                174     PUSH_NULL                       
                176     LOAD_CONST                      17: '__pyarmor_exit_36785__'
                178     LOAD_CONST                      3: b'<COAddr>\x05\x00\x00"p\x00\x00\x00\x00\x00\x00\x00\x00\x00\x00\x00\x00\x00\x00\x00'
                180     BUILD_TUPLE                     1
                182     CALL_FUNCTION_EX                0
                184     POP_TOP                         
                186     RETURN_VALUE                    
            [Exception Table]
                36 to 126 -> 146 [0] 
                146 to 168 -> 168 [1] lasti
        'GetFileRequest'
        [Code]
            File Name: <frozen multithon.tl.functions.upload>
            Object Name: GetFileHashesRequest
            Qualified Name: GetFileHashesRequest
            Arg Count: 0
            Pos Only Arg Count: 0
            KW Only Arg Count: 0
            Stack Size: 5
            Flags: 0x20000000 (CO_PYARMOR_OBFUSCATED)
            [Names]
                '__name__'
                '__module__'
                '__qualname__'
                '__assert_armored__'
                'CONSTRUCTOR_ID'
                'SUBCLASS_OF_ID'
                'int'
                '__init__'
                'to_dict'
                '_bytes'
                'classmethod'
                'from_reader'
            [Locals+Names]
            [Constants]
                'GetFileHashesRequest'
                '__pyarmor_assert_36798__'
                '__pyarmor_enter_36799__'
                b'<COAddr>\x05\x00\x00"V\x00\x00\x00\x00\x00\x00\x00\x00\x00\x00\x00\x00\x00\x00\x00'
                0x9156982A
                0xA5940726
                'location'
                'TypeInputFileLocation'   # b'\x81\xd6\x01\x036\xd3\xb0\xc2\x0e\xee+\xc9`\xe9\xd4\x8a\x0c\\\xaf\xae\xa5\xc5'
                'offset'
                [Code]
                    File Name: <frozen multithon.tl.functions.upload>
                    Object Name: __init__
                    Qualified Name: GetFileHashesRequest.__init__
                    Arg Count: 3
                    Pos Only Arg Count: 0
                    KW Only Arg Count: 0
                    Stack Size: 5
                    Flags: 0x20000003 (CO_OPTIMIZED | CO_NEWLOCALS | CO_PYARMOR_OBFUSCATED)
                    [Names]
                        'location'
                        'offset'
                    [Locals+Names]
                        'self'
                        'location'
                        'offset'
                        '__assert_armored__'
                    [Constants]
                        '\n        :returns Vector<FileHash>: This type has no constructors.\n        '
                        '__pyarmor_assert_36801__'
                        '__pyarmor_enter_36802__'
                        b'<COAddr>\x05\x00\x00\x1a2\x00\x00\x00\x00\x00\x00\x00\x00\x00\x00\x00\x00\x00\x00\x00'
                        '__pyarmor_exit_36803__'
                        None
                    [Disassembly]
                        0       NOP                             
                        2       NOP                             
                        4       PUSH_NULL                       
                        6       LOAD_CONST                      2: '__pyarmor_enter_36802__'
                        8       LOAD_CONST                      3: b'<COAddr>\x05\x00\x00\x1a2\x00\x00\x00\x00\x00\x00\x00\x00\x00\x00\x00\x00\x00\x00\x00'
                        10      BUILD_TUPLE                     1
                        12      CALL_FUNCTION_EX                0
                        14      POP_TOP                         
                        16      RESUME                          0
                        18      NOP                             
                        20      NOP                             
                        22      NOP                             
                        24      NOP                             
                        26      NOP                             
                        28      LOAD_FAST                       1: location
                        30      LOAD_FAST                       0: self
                        32      STORE_ATTR                      0: location
                        42      LOAD_FAST                       2: offset
                        44      LOAD_FAST                       0: self
                        46      STORE_ATTR                      1: offset
                        56      LOAD_CONST                      5: None
                        58      NOP                             
                        60      NOP                             
                        62      NOP                             
                        64      JUMP_FORWARD                    19 (to 104)
                        72      POP_TOP                         
                        74      RETURN_CONST                    5: None
                        76      PUSH_EXC_INFO                   
                        78      PUSH_NULL                       
                        80      LOAD_CONST                      4: '__pyarmor_exit_36803__'
                        82      NOP                             
                        84      LOAD_CONST                      3: b'<COAddr>\x05\x00\x00\x1a2\x00\x00\x00\x00\x00\x00\x00\x00\x00\x00\x00\x00\x00\x00\x00'
                        86      CALL                            1
                        94      POP_TOP                         
                        96      RERAISE                         0
                        98      COPY                            3
                        100     POP_EXCEPT                      
                        102     RERAISE                         1
                        104     PUSH_NULL                       
                        106     LOAD_CONST                      4: '__pyarmor_exit_36803__'
                        108     LOAD_CONST                      3: b'<COAddr>\x05\x00\x00\x1a2\x00\x00\x00\x00\x00\x00\x00\x00\x00\x00\x00\x00\x00\x00\x00'
                        110     BUILD_TUPLE                     1
                        112     CALL_FUNCTION_EX                0
                        114     POP_TOP                         
                        116     RETURN_VALUE                    
                    [Exception Table]
                        28 to 56 -> 76 [0] 
                        76 to 98 -> 98 [1] lasti
                [Code]
                    File Name: <frozen multithon.tl.functions.upload>
                    Object Name: to_dict
                    Qualified Name: GetFileHashesRequest.to_dict
                    Arg Count: 1
                    Pos Only Arg Count: 0
                    KW Only Arg Count: 0
                    Stack Size: 5
                    Flags: 0x20000003 (CO_OPTIMIZED | CO_NEWLOCALS | CO_PYARMOR_OBFUSCATED)
                    [Names]
                        'isinstance'
                        'location'
                        'TLObject'
                        'to_dict'
                        'offset'
                    [Locals+Names]
                        'self'
                        '__assert_armored__'
                    [Constants]
                        None
                        '__pyarmor_assert_36804__'
                        '__pyarmor_enter_36805__'
                        b'<COAddr>\x05\x00\x00\x1a\xbc\x00\x00\x00\x00\x00\x00\x00\x00\x00\x00\x00\x00\x00\x00\x00'
                        'GetFileHashesRequest'   # b'\x81\xc5\x1d\x07\x15\xf3\xb2\xd73\xfb\x1e\xc8i\xff\xca\x80\x1eH\xbe\xb4\xbe'
                        (
                            '_'
                            'location'
                            'offset'
                        )
                        '__pyarmor_exit_36806__'
                    [Disassembly]
                        0       NOP                             
                        2       NOP                             
                        4       PUSH_NULL                       
                        6       LOAD_CONST                      2: '__pyarmor_enter_36805__'
                        8       LOAD_CONST                      3: b'<COAddr>\x05\x00\x00\x1a\xbc\x00\x00\x00\x00\x00\x00\x00\x00\x00\x00\x00\x00\x00\x00\x00'
                        10      BUILD_TUPLE                     1
                        12      CALL_FUNCTION_EX                0
                        14      POP_TOP                         
                        16      RESUME                          0
                        18      NOP                             
                        20      NOP                             
                        22      NOP                             
                        24      NOP                             
                        26      NOP                             
                        28      PUSH_NULL                       
                        30      LOAD_CONST                      1: '__pyarmor_assert_36804__'
                        32      LOAD_CONST                      4: 'GetFileHashesRequest'   # b'\x81\xc5\x1d\x07\x15\xf3\xb2\xd73\xfb\x1e\xc8i\xff\xca\x80\x1eH\xbe\xb4\xbe'
                        34      CALL                            1
                        42      LOAD_GLOBAL                     1: NULL + isinstance
                        52      LOAD_FAST                       0: self
                        54      LOAD_ATTR                       2: location
                        74      LOAD_GLOBAL                     4: TLObject
                        84      CALL                            2
                        92      POP_JUMP_IF_FALSE               26 (to 146)
                        94      LOAD_FAST                       0: self
                        96      LOAD_ATTR                       2: location
                        116     LOAD_ATTR                       7: to_dict
                        136     CALL                            0
                        144     JUMP_FORWARD                    11 (to 168)
                        146     LOAD_FAST                       0: self
                        148     LOAD_ATTR                       2: location
                        168     LOAD_FAST                       0: self
                        170     LOAD_ATTR                       8: offset
                        190     LOAD_CONST                      5: ('_', 'location', 'offset')
                        192     BUILD_CONST_KEY_MAP             3
                        194     NOP                             
                        196     NOP                             
                        198     NOP                             
                        200     JUMP_FORWARD                    20 (to 242)
                        202     CALL                            1
                        210     POP_TOP                         
                        212     RETURN_VALUE                    
                        214     PUSH_EXC_INFO                   
                        216     PUSH_NULL                       
                        218     LOAD_CONST                      6: '__pyarmor_exit_36806__'
                        220     NOP                             
                        222     LOAD_CONST                      3: b'<COAddr>\x05\x00\x00\x1a\xbc\x00\x00\x00\x00\x00\x00\x00\x00\x00\x00\x00\x00\x00\x00\x00'
                        224     CALL                            1
                        232     POP_TOP                         
                        234     RERAISE                         0
                        236     COPY                            3
                        238     POP_EXCEPT                      
                        240     RERAISE                         1
                        242     PUSH_NULL                       
                        244     LOAD_CONST                      6: '__pyarmor_exit_36806__'
                        246     LOAD_CONST                      3: b'<COAddr>\x05\x00\x00\x1a\xbc\x00\x00\x00\x00\x00\x00\x00\x00\x00\x00\x00\x00\x00\x00\x00'
                        248     BUILD_TUPLE                     1
                        250     CALL_FUNCTION_EX                0
                        252     POP_TOP                         
                        254     RETURN_VALUE                    
                    [Exception Table]
                        28 to 194 -> 214 [0] 
                        214 to 236 -> 236 [1] lasti
                [Code]
                    File Name: <frozen multithon.tl.functions.upload>
                    Object Name: _bytes
                    Qualified Name: GetFileHashesRequest._bytes
                    Arg Count: 1
                    Pos Only Arg Count: 0
                    KW Only Arg Count: 0
                    Stack Size: 8
                    Flags: 0x20000003 (CO_OPTIMIZED | CO_NEWLOCALS | CO_PYARMOR_OBFUSCATED)
                    [Names]
                        'join'
                        'location'
                        '_bytes'
                        'struct'
                        'pack'
                        'offset'
                    [Locals+Names]
                        'self'
                        '__assert_armored__'
                    [Constants]
                        None
                        '__pyarmor_assert_36807__'
                        '__pyarmor_enter_36808__'
                        b'<COAddr>\x05\x00\x00\x1a\xa8\x00\x00\x00\x00\x00\x00\x00\x00\x00\x00\x00\x00\x00\x00\x00'
                        b''
                        b'*\x98V\x91'
                        '<q'
                        '__pyarmor_exit_36809__'
                    [Disassembly]
                        0       NOP                             
                        2       NOP                             
                        4       PUSH_NULL                       
                        6       LOAD_CONST                      2: '__pyarmor_enter_36808__'
                        8       LOAD_CONST                      3: b'<COAddr>\x05\x00\x00\x1a\xa8\x00\x00\x00\x00\x00\x00\x00\x00\x00\x00\x00\x00\x00\x00\x00'
                        10      BUILD_TUPLE                     1
                        12      CALL_FUNCTION_EX                0
                        14      POP_TOP                         
                        16      RESUME                          0
                        18      NOP                             
                        20      NOP                             
                        22      NOP                             
                        24      NOP                             
                        26      NOP                             
                        28      LOAD_CONST                      4: b''
                        30      LOAD_ATTR                       1: join
                        50      LOAD_CONST                      5: b'*\x98V\x91'
                        52      LOAD_FAST                       0: self
                        54      LOAD_ATTR                       2: location
                        74      LOAD_ATTR                       5: _bytes
                        94      CALL                            0
                        102     LOAD_GLOBAL                     7: NULL + struct
                        112     LOAD_ATTR                       8: pack
                        132     LOAD_CONST                      6: '<q'
                        134     LOAD_FAST                       0: self
                        136     LOAD_ATTR                       10: offset
                        156     CALL                            2
                        164     BUILD_TUPLE                     3
                        166     CALL                            1
                        174     NOP                             
                        176     NOP                             
                        178     NOP                             
                        180     JUMP_FORWARD                    20 (to 222)
                        182     CALL                            1
                        190     POP_TOP                         
                        192     RETURN_VALUE                    
                        194     PUSH_EXC_INFO                   
                        196     PUSH_NULL                       
                        198     LOAD_CONST                      7: '__pyarmor_exit_36809__'
                        200     NOP                             
                        202     LOAD_CONST                      3: b'<COAddr>\x05\x00\x00\x1a\xa8\x00\x00\x00\x00\x00\x00\x00\x00\x00\x00\x00\x00\x00\x00\x00'
                        204     CALL                            1
                        212     POP_TOP                         
                        214     RERAISE                         0
                        216     COPY                            3
                        218     POP_EXCEPT                      
                        220     RERAISE                         1
                        222     PUSH_NULL                       
                        224     LOAD_CONST                      7: '__pyarmor_exit_36809__'
                        226     LOAD_CONST                      3: b'<COAddr>\x05\x00\x00\x1a\xa8\x00\x00\x00\x00\x00\x00\x00\x00\x00\x00\x00\x00\x00\x00\x00'
                        228     BUILD_TUPLE                     1
                        230     CALL_FUNCTION_EX                0
                        232     POP_TOP                         
                        234     RETURN_VALUE                    
                    [Exception Table]
                        28 to 174 -> 194 [0] 
                        194 to 216 -> 216 [1] lasti
                [Code]
                    File Name: <frozen multithon.tl.functions.upload>
                    Object Name: from_reader
                    Qualified Name: GetFileHashesRequest.from_reader
                    Arg Count: 2
                    Pos Only Arg Count: 0
                    KW Only Arg Count: 0
                    Stack Size: 5
                    Flags: 0x20000003 (CO_OPTIMIZED | CO_NEWLOCALS | CO_PYARMOR_OBFUSCATED)
                    [Names]
                        'tgread_object'
                        'read_long'
                    [Locals+Names]
                        'cls'
                        'reader'
                        '__assert_armored__'
                        '_var_var_6'
                        '_var_var_1'
                    [Constants]
                        None
                        '__pyarmor_assert_36810__'
                        '__pyarmor_enter_36811__'
                        b'<COAddr>\x07\x00\x00\x1ah\x00\x00\x00\x00\x00\x00\x00\x00\x00\x00\x00\x00\x00\x00\x00'
                        (
                            'location'
                            'offset'
                        )
                        '__pyarmor_exit_36812__'
                    [Disassembly]
                        0       NOP                             
                        2       NOP                             
                        4       PUSH_NULL                       
                        6       LOAD_CONST                      2: '__pyarmor_enter_36811__'
                        8       LOAD_CONST                      3: b'<COAddr>\x07\x00\x00\x1ah\x00\x00\x00\x00\x00\x00\x00\x00\x00\x00\x00\x00\x00\x00\x00'
                        10      BUILD_TUPLE                     1
                        12      CALL_FUNCTION_EX                0
                        14      POP_TOP                         
                        16      RESUME                          0
                        18      NOP                             
                        20      NOP                             
                        22      NOP                             
                        24      NOP                             
                        26      NOP                             
                        28      LOAD_FAST                       1: reader
                        30      LOAD_ATTR                       1: tgread_object
                        50      CALL                            0
                        58      STORE_FAST                      3: _var_var_6
                        60      LOAD_FAST                       1: reader
                        62      LOAD_ATTR                       3: read_long
                        82      CALL                            0
                        90      STORE_FAST                      4: _var_var_1
                        92      PUSH_NULL                       
                        94      LOAD_FAST                       0: cls
                        96      LOAD_FAST                       3: _var_var_6
                        98      LOAD_FAST                       4: _var_var_1
                        100     KW_NAMES                        4: ('location', 'offset')
                        102     CALL                            2
                        110     NOP                             
                        112     NOP                             
                        114     NOP                             
                        116     JUMP_FORWARD                    20 (to 158)
                        118     CALL                            1
                        126     POP_TOP                         
                        128     RETURN_VALUE                    
                        130     PUSH_EXC_INFO                   
                        132     PUSH_NULL                       
                        134     LOAD_CONST                      5: '__pyarmor_exit_36812__'
                        136     NOP                             
                        138     LOAD_CONST                      3: b'<COAddr>\x07\x00\x00\x1ah\x00\x00\x00\x00\x00\x00\x00\x00\x00\x00\x00\x00\x00\x00\x00'
                        140     CALL                            1
                        148     POP_TOP                         
                        150     RERAISE                         0
                        152     COPY                            3
                        154     POP_EXCEPT                      
                        156     RERAISE                         1
                        158     PUSH_NULL                       
                        160     LOAD_CONST                      5: '__pyarmor_exit_36812__'
                        162     LOAD_CONST                      3: b'<COAddr>\x07\x00\x00\x1ah\x00\x00\x00\x00\x00\x00\x00\x00\x00\x00\x00\x00\x00\x00\x00'
                        164     BUILD_TUPLE                     1
                        166     CALL_FUNCTION_EX                0
                        168     POP_TOP                         
                        170     RETURN_VALUE                    
                    [Exception Table]
                        28 to 110 -> 130 [0] 
                        130 to 152 -> 152 [1] lasti
                '__pyarmor_exit_36800__'
                None
            [Disassembly]
                0       NOP                             
                2       LOAD_NAME                       0: __name__
                4       STORE_NAME                      1: __module__
                6       LOAD_CONST                      0: 'GetFileHashesRequest'
                8       STORE_NAME                      2: __qualname__
                10      NOP                             
                12      PUSH_NULL                       
                14      LOAD_CONST                      2: '__pyarmor_enter_36799__'
                16      LOAD_CONST                      3: b'<COAddr>\x05\x00\x00"V\x00\x00\x00\x00\x00\x00\x00\x00\x00\x00\x00\x00\x00\x00\x00'
                18      BUILD_TUPLE                     1
                20      CALL_FUNCTION_EX                0
                22      POP_TOP                         
                24      RESUME                          0
                26      NOP                             
                28      NOP                             
                30      NOP                             
                32      NOP                             
                34      NOP                             
                36      LOAD_CONST                      4: 0x9156982A
                38      STORE_NAME                      4: CONSTRUCTOR_ID
                40      LOAD_CONST                      5: 0xA5940726
                42      STORE_NAME                      5: SUBCLASS_OF_ID
                44      LOAD_CONST                      6: 'location'
                46      PUSH_NULL                       
                48      LOAD_CONST                      1: '__pyarmor_assert_36798__'
                50      LOAD_CONST                      7: 'TypeInputFileLocation'   # b'\x81\xd6\x01\x036\xd3\xb0\xc2\x0e\xee+\xc9`\xe9\xd4\x8a\x0c\\\xaf\xae\xa5\xc5'
                52      CALL                            1
                60      LOAD_CONST                      8: 'offset'
                62      LOAD_NAME                       6: int
                64      BUILD_TUPLE                     4
                66      LOAD_CONST                      9: <CODE> __init__
                68      MAKE_FUNCTION                   4
                70      STORE_NAME                      7: __init__
                72      LOAD_CONST                      10: <CODE> to_dict
                74      MAKE_FUNCTION                   0
                76      STORE_NAME                      8: to_dict
                78      LOAD_CONST                      11: <CODE> _bytes
                80      MAKE_FUNCTION                   0
                82      STORE_NAME                      9: _bytes
                84      LOAD_NAME                       10: classmethod
                86      LOAD_CONST                      12: <CODE> from_reader
                88      MAKE_FUNCTION                   0
                90      CALL                            0
                98      STORE_NAME                      11: from_reader
                100     LOAD_CONST                      14: None
                102     NOP                             
                104     NOP                             
                106     NOP                             
                108     JUMP_FORWARD                    19 (to 148)
                116     POP_TOP                         
                118     RETURN_CONST                    14: None
                120     PUSH_EXC_INFO                   
                122     PUSH_NULL                       
                124     LOAD_CONST                      13: '__pyarmor_exit_36800__'
                126     NOP                             
                128     LOAD_CONST                      3: b'<COAddr>\x05\x00\x00"V\x00\x00\x00\x00\x00\x00\x00\x00\x00\x00\x00\x00\x00\x00\x00'
                130     CALL                            1
                138     POP_TOP                         
                140     RERAISE                         0
                142     COPY                            3
                144     POP_EXCEPT                      
                146     RERAISE                         1
                148     PUSH_NULL                       
                150     LOAD_CONST                      13: '__pyarmor_exit_36800__'
                152     LOAD_CONST                      3: b'<COAddr>\x05\x00\x00"V\x00\x00\x00\x00\x00\x00\x00\x00\x00\x00\x00\x00\x00\x00\x00'
                154     BUILD_TUPLE                     1
                156     CALL_FUNCTION_EX                0
                158     POP_TOP                         
                160     RETURN_VALUE                    
            [Exception Table]
                36 to 100 -> 120 [0] 
                120 to 142 -> 142 [1] lasti
        'GetFileHashesRequest'
        [Code]
            File Name: <frozen multithon.tl.functions.upload>
            Object Name: GetWebFileRequest
            Qualified Name: GetWebFileRequest
            Arg Count: 0
            Pos Only Arg Count: 0
            KW Only Arg Count: 0
            Stack Size: 6
            Flags: 0x20000000 (CO_PYARMOR_OBFUSCATED)
            [Names]
                '__name__'
                '__module__'
                '__qualname__'
                '__assert_armored__'
                'CONSTRUCTOR_ID'
                'SUBCLASS_OF_ID'
                'int'
                '__init__'
                'to_dict'
                '_bytes'
                'classmethod'
                'from_reader'
            [Locals+Names]
            [Constants]
                'GetWebFileRequest'
                '__pyarmor_assert_36813__'
                '__pyarmor_enter_36814__'
                b'<COAddr>\x05\x00\x00"Z\x00\x00\x00\x00\x00\x00\x00\x00\x00\x00\x00\x00\x00\x00\x00'
                619086221
                1760657233
                'location'
                'TypeInputWebFileLocation'   # b'\x81\xd6\x01\x036\xd3\xb0\xc2\x0e\xee:\xc5n\xca\xf1\x89\nq\xb4\xa4\xab\xdfG\xc3\x0b'
                'offset'
                'limit'
                [Code]
                    File Name: <frozen multithon.tl.functions.upload>
                    Object Name: __init__
                    Qualified Name: GetWebFileRequest.__init__
                    Arg Count: 4
                    Pos Only Arg Count: 0
                    KW Only Arg Count: 0
                    Stack Size: 5
                    Flags: 0x20000003 (CO_OPTIMIZED | CO_NEWLOCALS | CO_PYARMOR_OBFUSCATED)
                    [Names]
                        'location'
                        'offset'
                        'limit'
                    [Locals+Names]
                        'self'
                        'location'
                        'offset'
                        'limit'
                        '__assert_armored__'
                    [Constants]
                        '\n        :returns upload.WebFile: Instance of WebFile.\n        '
                        '__pyarmor_assert_36816__'
                        '__pyarmor_enter_36817__'
                        b'<COAddr>\x07\x00\x00\x1a@\x00\x00\x00\x00\x00\x00\x00\x00\x00\x00\x00\x00\x00\x00\x00'
                        '__pyarmor_exit_36818__'
                        None
                    [Disassembly]
                        0       NOP                             
                        2       NOP                             
                        4       PUSH_NULL                       
                        6       LOAD_CONST                      2: '__pyarmor_enter_36817__'
                        8       LOAD_CONST                      3: b'<COAddr>\x07\x00\x00\x1a@\x00\x00\x00\x00\x00\x00\x00\x00\x00\x00\x00\x00\x00\x00\x00'
                        10      BUILD_TUPLE                     1
                        12      CALL_FUNCTION_EX                0
                        14      POP_TOP                         
                        16      RESUME                          0
                        18      NOP                             
                        20      NOP                             
                        22      NOP                             
                        24      NOP                             
                        26      NOP                             
                        28      LOAD_FAST                       1: location
                        30      LOAD_FAST                       0: self
                        32      STORE_ATTR                      0: location
                        42      LOAD_FAST                       2: offset
                        44      LOAD_FAST                       0: self
                        46      STORE_ATTR                      1: offset
                        56      LOAD_FAST                       3: limit
                        58      LOAD_FAST                       0: self
                        60      STORE_ATTR                      2: limit
                        70      LOAD_CONST                      5: None
                        72      NOP                             
                        74      NOP                             
                        76      NOP                             
                        78      JUMP_FORWARD                    19 (to 118)
                        86      POP_TOP                         
                        88      RETURN_CONST                    5: None
                        90      PUSH_EXC_INFO                   
                        92      PUSH_NULL                       
                        94      LOAD_CONST                      4: '__pyarmor_exit_36818__'
                        96      NOP                             
                        98      LOAD_CONST                      3: b'<COAddr>\x07\x00\x00\x1a@\x00\x00\x00\x00\x00\x00\x00\x00\x00\x00\x00\x00\x00\x00\x00'
                        100     CALL                            1
                        108     POP_TOP                         
                        110     RERAISE                         0
                        112     COPY                            3
                        114     POP_EXCEPT                      
                        116     RERAISE                         1
                        118     PUSH_NULL                       
                        120     LOAD_CONST                      4: '__pyarmor_exit_36818__'
                        122     LOAD_CONST                      3: b'<COAddr>\x07\x00\x00\x1a@\x00\x00\x00\x00\x00\x00\x00\x00\x00\x00\x00\x00\x00\x00\x00'
                        124     BUILD_TUPLE                     1
                        126     CALL_FUNCTION_EX                0
                        128     POP_TOP                         
                        130     RETURN_VALUE                    
                    [Exception Table]
                        28 to 70 -> 90 [0] 
                        90 to 112 -> 112 [1] lasti
                [Code]
                    File Name: <frozen multithon.tl.functions.upload>
                    Object Name: to_dict
                    Qualified Name: GetWebFileRequest.to_dict
                    Arg Count: 1
                    Pos Only Arg Count: 0
                    KW Only Arg Count: 0
                    Stack Size: 5
                    Flags: 0x20000003 (CO_OPTIMIZED | CO_NEWLOCALS | CO_PYARMOR_OBFUSCATED)
                    [Names]
                        'isinstance'
                        'location'
                        'TLObject'
                        'to_dict'
                        'offset'
                        'limit'
                    [Locals+Names]
                        'self'
                        '__assert_armored__'
                    [Constants]
                        None
                        '__pyarmor_assert_36819__'
                        '__pyarmor_enter_36820__'
                        b'<COAddr>\x07\x00\x00\x1a\xd2\x00\x00\x00\x00\x00\x00\x00\x00\x00\x00\x00\x00\x00\x00\x00'
                        'GetWebFileRequest'   # b'\x81\xc5\x1d\x07\x04\xff\xbc\xf4\x12\xf6\x08\xf2i\xfd\xed\x80\x1cI'
                        (
                            '_'
                            'location'
                            'offset'
                            'limit'
                        )
                        '__pyarmor_exit_36821__'
                    [Disassembly]
                        0       NOP                             
                        2       NOP                             
                        4       PUSH_NULL                       
                        6       LOAD_CONST                      2: '__pyarmor_enter_36820__'
                        8       LOAD_CONST                      3: b'<COAddr>\x07\x00\x00\x1a\xd2\x00\x00\x00\x00\x00\x00\x00\x00\x00\x00\x00\x00\x00\x00\x00'
                        10      BUILD_TUPLE                     1
                        12      CALL_FUNCTION_EX                0
                        14      POP_TOP                         
                        16      RESUME                          0
                        18      NOP                             
                        20      NOP                             
                        22      NOP                             
                        24      NOP                             
                        26      NOP                             
                        28      PUSH_NULL                       
                        30      LOAD_CONST                      1: '__pyarmor_assert_36819__'
                        32      LOAD_CONST                      4: 'GetWebFileRequest'   # b'\x81\xc5\x1d\x07\x04\xff\xbc\xf4\x12\xf6\x08\xf2i\xfd\xed\x80\x1cI'
                        34      CALL                            1
                        42      LOAD_GLOBAL                     1: NULL + isinstance
                        52      LOAD_FAST                       0: self
                        54      LOAD_ATTR                       2: location
                        74      LOAD_GLOBAL                     4: TLObject
                        84      CALL                            2
                        92      POP_JUMP_IF_FALSE               26 (to 146)
                        94      LOAD_FAST                       0: self
                        96      LOAD_ATTR                       2: location
                        116     LOAD_ATTR                       7: to_dict
                        136     CALL                            0
                        144     JUMP_FORWARD                    11 (to 168)
                        146     LOAD_FAST                       0: self
                        148     LOAD_ATTR                       2: location
                        168     LOAD_FAST                       0: self
                        170     LOAD_ATTR                       8: offset
                        190     LOAD_FAST                       0: self
                        192     LOAD_ATTR                       10: limit
                        212     LOAD_CONST                      5: ('_', 'location', 'offset', 'limit')
                        214     BUILD_CONST_KEY_MAP             4
                        216     NOP                             
                        218     NOP                             
                        220     NOP                             
                        222     JUMP_FORWARD                    20 (to 264)
                        224     CALL                            1
                        232     POP_TOP                         
                        234     RETURN_VALUE                    
                        236     PUSH_EXC_INFO                   
                        238     PUSH_NULL                       
                        240     LOAD_CONST                      6: '__pyarmor_exit_36821__'
                        242     NOP                             
                        244     LOAD_CONST                      3: b'<COAddr>\x07\x00\x00\x1a\xd2\x00\x00\x00\x00\x00\x00\x00\x00\x00\x00\x00\x00\x00\x00\x00'
                        246     CALL                            1
                        254     POP_TOP                         
                        256     RERAISE                         0
                        258     COPY                            3
                        260     POP_EXCEPT                      
                        262     RERAISE                         1
                        264     PUSH_NULL                       
                        266     LOAD_CONST                      6: '__pyarmor_exit_36821__'
                        268     LOAD_CONST                      3: b'<COAddr>\x07\x00\x00\x1a\xd2\x00\x00\x00\x00\x00\x00\x00\x00\x00\x00\x00\x00\x00\x00\x00'
                        270     BUILD_TUPLE                     1
                        272     CALL_FUNCTION_EX                0
                        274     POP_TOP                         
                        276     RETURN_VALUE                    
                    [Exception Table]
                        28 to 216 -> 236 [0] 
                        236 to 258 -> 258 [1] lasti
                [Code]
                    File Name: <frozen multithon.tl.functions.upload>
                    Object Name: _bytes
                    Qualified Name: GetWebFileRequest._bytes
                    Arg Count: 1
                    Pos Only Arg Count: 0
                    KW Only Arg Count: 0
                    Stack Size: 9
                    Flags: 0x20000003 (CO_OPTIMIZED | CO_NEWLOCALS | CO_PYARMOR_OBFUSCATED)
                    [Names]
                        'join'
                        'location'
                        '_bytes'
                        'struct'
                        'pack'
                        'offset'
                        'limit'
                    [Locals+Names]
                        'self'
                        '__assert_armored__'
                    [Constants]
                        None
                        '__pyarmor_assert_36822__'
                        '__pyarmor_enter_36823__'
                        b'<COAddr>\x07\x00\x00\x1a\xe6\x00\x00\x00\x00\x00\x00\x00\x00\x00\x00\x00\x00\x00\x00\x00'
                        b''
                        b'\x8d\x81\xe6$'
                        '<i'
                        '__pyarmor_exit_36824__'
                    [Disassembly]
                        0       NOP                             
                        2       NOP                             
                        4       PUSH_NULL                       
                        6       LOAD_CONST                      2: '__pyarmor_enter_36823__'
                        8       LOAD_CONST                      3: b'<COAddr>\x07\x00\x00\x1a\xe6\x00\x00\x00\x00\x00\x00\x00\x00\x00\x00\x00\x00\x00\x00\x00'
                        10      BUILD_TUPLE                     1
                        12      CALL_FUNCTION_EX                0
                        14      POP_TOP                         
                        16      RESUME                          0
                        18      NOP                             
                        20      NOP                             
                        22      NOP                             
                        24      NOP                             
                        26      NOP                             
                        28      LOAD_CONST                      4: b''
                        30      LOAD_ATTR                       1: join
                        50      LOAD_CONST                      5: b'\x8d\x81\xe6$'
                        52      LOAD_FAST                       0: self
                        54      LOAD_ATTR                       2: location
                        74      LOAD_ATTR                       5: _bytes
                        94      CALL                            0
                        102     LOAD_GLOBAL                     7: NULL + struct
                        112     LOAD_ATTR                       8: pack
                        132     LOAD_CONST                      6: '<i'
                        134     LOAD_FAST                       0: self
                        136     LOAD_ATTR                       10: offset
                        156     CALL                            2
                        164     LOAD_GLOBAL                     7: NULL + struct
                        174     LOAD_ATTR                       8: pack
                        194     LOAD_CONST                      6: '<i'
                        196     LOAD_FAST                       0: self
                        198     LOAD_ATTR                       12: limit
                        218     CALL                            2
                        226     BUILD_TUPLE                     4
                        228     CALL                            1
                        236     NOP                             
                        238     NOP                             
                        240     NOP                             
                        242     JUMP_FORWARD                    20 (to 284)
                        244     CALL                            1
                        252     POP_TOP                         
                        254     RETURN_VALUE                    
                        256     PUSH_EXC_INFO                   
                        258     PUSH_NULL                       
                        260     LOAD_CONST                      7: '__pyarmor_exit_36824__'
                        262     NOP                             
                        264     LOAD_CONST                      3: b'<COAddr>\x07\x00\x00\x1a\xe6\x00\x00\x00\x00\x00\x00\x00\x00\x00\x00\x00\x00\x00\x00\x00'
                        266     CALL                            1
                        274     POP_TOP                         
                        276     RERAISE                         0
                        278     COPY                            3
                        280     POP_EXCEPT                      
                        282     RERAISE                         1
                        284     PUSH_NULL                       
                        286     LOAD_CONST                      7: '__pyarmor_exit_36824__'
                        288     LOAD_CONST                      3: b'<COAddr>\x07\x00\x00\x1a\xe6\x00\x00\x00\x00\x00\x00\x00\x00\x00\x00\x00\x00\x00\x00\x00'
                        290     BUILD_TUPLE                     1
                        292     CALL_FUNCTION_EX                0
                        294     POP_TOP                         
                        296     RETURN_VALUE                    
                    [Exception Table]
                        28 to 236 -> 256 [0] 
                        256 to 278 -> 278 [1] lasti
                [Code]
                    File Name: <frozen multithon.tl.functions.upload>
                    Object Name: from_reader
                    Qualified Name: GetWebFileRequest.from_reader
                    Arg Count: 2
                    Pos Only Arg Count: 0
                    KW Only Arg Count: 0
                    Stack Size: 5
                    Flags: 0x20000003 (CO_OPTIMIZED | CO_NEWLOCALS | CO_PYARMOR_OBFUSCATED)
                    [Names]
                        'tgread_object'
                        'read_int'
                    [Locals+Names]
                        'cls'
                        'reader'
                        '__assert_armored__'
                        '_var_var_6'
                        '_var_var_1'
                        '_var_var_2'
                    [Constants]
                        None
                        '__pyarmor_assert_36825__'
                        '__pyarmor_enter_36826__'
                        b'<COAddr>\x07\x00\x00\x1a\x8a\x00\x00\x00\x00\x00\x00\x00\x00\x00\x00\x00\x00\x00\x00\x00'
                        (
                            'location'
                            'offset'
                            'limit'
                        )
                        '__pyarmor_exit_36827__'
                    [Disassembly]
                        0       NOP                             
                        2       NOP                             
                        4       PUSH_NULL                       
                        6       LOAD_CONST                      2: '__pyarmor_enter_36826__'
                        8       LOAD_CONST                      3: b'<COAddr>\x07\x00\x00\x1a\x8a\x00\x00\x00\x00\x00\x00\x00\x00\x00\x00\x00\x00\x00\x00\x00'
                        10      BUILD_TUPLE                     1
                        12      CALL_FUNCTION_EX                0
                        14      POP_TOP                         
                        16      RESUME                          0
                        18      NOP                             
                        20      NOP                             
                        22      NOP                             
                        24      NOP                             
                        26      NOP                             
                        28      LOAD_FAST                       1: reader
                        30      LOAD_ATTR                       1: tgread_object
                        50      CALL                            0
                        58      STORE_FAST                      3: _var_var_6
                        60      LOAD_FAST                       1: reader
                        62      LOAD_ATTR                       3: read_int
                        82      CALL                            0
                        90      STORE_FAST                      4: _var_var_1
                        92      LOAD_FAST                       1: reader
                        94      LOAD_ATTR                       3: read_int
                        114     CALL                            0
                        122     STORE_FAST                      5: _var_var_2
                        124     PUSH_NULL                       
                        126     LOAD_FAST                       0: cls
                        128     LOAD_FAST                       3: _var_var_6
                        130     LOAD_FAST                       4: _var_var_1
                        132     LOAD_FAST                       5: _var_var_2
                        134     KW_NAMES                        4: ('location', 'offset', 'limit')
                        136     CALL                            3
                        144     NOP                             
                        146     NOP                             
                        148     NOP                             
                        150     JUMP_FORWARD                    20 (to 192)
                        152     CALL                            1
                        160     POP_TOP                         
                        162     RETURN_VALUE                    
                        164     PUSH_EXC_INFO                   
                        166     PUSH_NULL                       
                        168     LOAD_CONST                      5: '__pyarmor_exit_36827__'
                        170     NOP                             
                        172     LOAD_CONST                      3: b'<COAddr>\x07\x00\x00\x1a\x8a\x00\x00\x00\x00\x00\x00\x00\x00\x00\x00\x00\x00\x00\x00\x00'
                        174     CALL                            1
                        182     POP_TOP                         
                        184     RERAISE                         0
                        186     COPY                            3
                        188     POP_EXCEPT                      
                        190     RERAISE                         1
                        192     PUSH_NULL                       
                        194     LOAD_CONST                      5: '__pyarmor_exit_36827__'
                        196     LOAD_CONST                      3: b'<COAddr>\x07\x00\x00\x1a\x8a\x00\x00\x00\x00\x00\x00\x00\x00\x00\x00\x00\x00\x00\x00\x00'
                        198     BUILD_TUPLE                     1
                        200     CALL_FUNCTION_EX                0
                        202     POP_TOP                         
                        204     RETURN_VALUE                    
                    [Exception Table]
                        28 to 144 -> 164 [0] 
                        164 to 186 -> 186 [1] lasti
                '__pyarmor_exit_36815__'
                None
            [Disassembly]
                0       NOP                             
                2       LOAD_NAME                       0: __name__
                4       STORE_NAME                      1: __module__
                6       LOAD_CONST                      0: 'GetWebFileRequest'
                8       STORE_NAME                      2: __qualname__
                10      NOP                             
                12      PUSH_NULL                       
                14      LOAD_CONST                      2: '__pyarmor_enter_36814__'
                16      LOAD_CONST                      3: b'<COAddr>\x05\x00\x00"Z\x00\x00\x00\x00\x00\x00\x00\x00\x00\x00\x00\x00\x00\x00\x00'
                18      BUILD_TUPLE                     1
                20      CALL_FUNCTION_EX                0
                22      POP_TOP                         
                24      RESUME                          0
                26      NOP                             
                28      NOP                             
                30      NOP                             
                32      NOP                             
                34      NOP                             
                36      LOAD_CONST                      4: 619086221
                38      STORE_NAME                      4: CONSTRUCTOR_ID
                40      LOAD_CONST                      5: 1760657233
                42      STORE_NAME                      5: SUBCLASS_OF_ID
                44      LOAD_CONST                      6: 'location'
                46      PUSH_NULL                       
                48      LOAD_CONST                      1: '__pyarmor_assert_36813__'
                50      LOAD_CONST                      7: 'TypeInputWebFileLocation'   # b'\x81\xd6\x01\x036\xd3\xb0\xc2\x0e\xee:\xc5n\xca\xf1\x89\nq\xb4\xa4\xab\xdfG\xc3\x0b'
                52      CALL                            1
                60      LOAD_CONST                      8: 'offset'
                62      LOAD_NAME                       6: int
                64      LOAD_CONST                      9: 'limit'
                66      LOAD_NAME                       6: int
                68      BUILD_TUPLE                     6
                70      LOAD_CONST                      10: <CODE> __init__
                72      MAKE_FUNCTION                   4
                74      STORE_NAME                      7: __init__
                76      LOAD_CONST                      11: <CODE> to_dict
                78      MAKE_FUNCTION                   0
                80      STORE_NAME                      8: to_dict
                82      LOAD_CONST                      12: <CODE> _bytes
                84      MAKE_FUNCTION                   0
                86      STORE_NAME                      9: _bytes
                88      LOAD_NAME                       10: classmethod
                90      LOAD_CONST                      13: <CODE> from_reader
                92      MAKE_FUNCTION                   0
                94      CALL                            0
                102     STORE_NAME                      11: from_reader
                104     LOAD_CONST                      15: None
                106     NOP                             
                108     NOP                             
                110     NOP                             
                112     JUMP_FORWARD                    19 (to 152)
                120     POP_TOP                         
                122     RETURN_CONST                    15: None
                124     PUSH_EXC_INFO                   
                126     PUSH_NULL                       
                128     LOAD_CONST                      14: '__pyarmor_exit_36815__'
                130     NOP                             
                132     LOAD_CONST                      3: b'<COAddr>\x05\x00\x00"Z\x00\x00\x00\x00\x00\x00\x00\x00\x00\x00\x00\x00\x00\x00\x00'
                134     CALL                            1
                142     POP_TOP                         
                144     RERAISE                         0
                146     COPY                            3
                148     POP_EXCEPT                      
                150     RERAISE                         1
                152     PUSH_NULL                       
                154     LOAD_CONST                      14: '__pyarmor_exit_36815__'
                156     LOAD_CONST                      3: b'<COAddr>\x05\x00\x00"Z\x00\x00\x00\x00\x00\x00\x00\x00\x00\x00\x00\x00\x00\x00\x00'
                158     BUILD_TUPLE                     1
                160     CALL_FUNCTION_EX                0
                162     POP_TOP                         
                164     RETURN_VALUE                    
            [Exception Table]
                36 to 104 -> 124 [0] 
                124 to 146 -> 146 [1] lasti
        'GetWebFileRequest'
        [Code]
            File Name: <frozen multithon.tl.functions.upload>
            Object Name: ReuploadCdnFileRequest
            Qualified Name: ReuploadCdnFileRequest
            Arg Count: 0
            Pos Only Arg Count: 0
            KW Only Arg Count: 0
            Stack Size: 5
            Flags: 0x20000000 (CO_PYARMOR_OBFUSCATED)
            [Names]
                '__name__'
                '__module__'
                '__qualname__'
                '__assert_armored__'
                'CONSTRUCTOR_ID'
                'SUBCLASS_OF_ID'
                'bytes'
                '__init__'
                'to_dict'
                '_bytes'
                'classmethod'
                'from_reader'
            [Locals+Names]
            [Constants]
                'ReuploadCdnFileRequest'
                '__pyarmor_assert_36828__'
                '__pyarmor_enter_36829__'
                b'<COAddr>\x05\x00\x00"J\x00\x00\x00\x00\x00\x00\x00\x00\x00\x00\x00\x00\x00\x00\x00'
                0x9B2754A8
                0xA5940726
                'file_token'
                'request_token'
                [Code]
                    File Name: <frozen multithon.tl.functions.upload>
                    Object Name: __init__
                    Qualified Name: ReuploadCdnFileRequest.__init__
                    Arg Count: 3
                    Pos Only Arg Count: 0
                    KW Only Arg Count: 0
                    Stack Size: 5
                    Flags: 0x20000003 (CO_OPTIMIZED | CO_NEWLOCALS | CO_PYARMOR_OBFUSCATED)
                    [Names]
                        'file_token'
                        'request_token'
                    [Locals+Names]
                        'self'
                        'file_token'
                        'request_token'
                        '__assert_armored__'
                    [Constants]
                        '\n        :returns Vector<FileHash>: This type has no constructors.\n        '
                        '__pyarmor_assert_36831__'
                        '__pyarmor_enter_36832__'
                        b'<COAddr>\x07\x00\x00\x1a2\x00\x00\x00\x00\x00\x00\x00\x00\x00\x00\x00\x00\x00\x00\x00'
                        '__pyarmor_exit_36833__'
                        None
                    [Disassembly]
                        0       NOP                             
                        2       NOP                             
                        4       PUSH_NULL                       
                        6       LOAD_CONST                      2: '__pyarmor_enter_36832__'
                        8       LOAD_CONST                      3: b'<COAddr>\x07\x00\x00\x1a2\x00\x00\x00\x00\x00\x00\x00\x00\x00\x00\x00\x00\x00\x00\x00'
                        10      BUILD_TUPLE                     1
                        12      CALL_FUNCTION_EX                0
                        14      POP_TOP                         
                        16      RESUME                          0
                        18      NOP                             
                        20      NOP                             
                        22      NOP                             
                        24      NOP                             
                        26      NOP                             
                        28      LOAD_FAST                       1: file_token
                        30      LOAD_FAST                       0: self
                        32      STORE_ATTR                      0: file_token
                        42      LOAD_FAST                       2: request_token
                        44      LOAD_FAST                       0: self
                        46      STORE_ATTR                      1: request_token
                        56      LOAD_CONST                      5: None
                        58      NOP                             
                        60      NOP                             
                        62      NOP                             
                        64      JUMP_FORWARD                    19 (to 104)
                        72      POP_TOP                         
                        74      RETURN_CONST                    5: None
                        76      PUSH_EXC_INFO                   
                        78      PUSH_NULL                       
                        80      LOAD_CONST                      4: '__pyarmor_exit_36833__'
                        82      NOP                             
                        84      LOAD_CONST                      3: b'<COAddr>\x07\x00\x00\x1a2\x00\x00\x00\x00\x00\x00\x00\x00\x00\x00\x00\x00\x00\x00\x00'
                        86      CALL                            1
                        94      POP_TOP                         
                        96      RERAISE                         0
                        98      COPY                            3
                        100     POP_EXCEPT                      
                        102     RERAISE                         1
                        104     PUSH_NULL                       
                        106     LOAD_CONST                      4: '__pyarmor_exit_36833__'
                        108     LOAD_CONST                      3: b'<COAddr>\x07\x00\x00\x1a2\x00\x00\x00\x00\x00\x00\x00\x00\x00\x00\x00\x00\x00\x00\x00'
                        110     BUILD_TUPLE                     1
                        112     CALL_FUNCTION_EX                0
                        114     POP_TOP                         
                        116     RETURN_VALUE                    
                    [Exception Table]
                        28 to 56 -> 76 [0] 
                        76 to 98 -> 98 [1] lasti
                [Code]
                    File Name: <frozen multithon.tl.functions.upload>
                    Object Name: to_dict
                    Qualified Name: ReuploadCdnFileRequest.to_dict
                    Arg Count: 1
                    Pos Only Arg Count: 0
                    KW Only Arg Count: 0
                    Stack Size: 7
                    Flags: 0x20000003 (CO_OPTIMIZED | CO_NEWLOCALS | CO_PYARMOR_OBFUSCATED)
                    [Names]
                        'file_token'
                        'request_token'
                    [Locals+Names]
                        'self'
                        '__assert_armored__'
                    [Constants]
                        None
                        '__pyarmor_assert_36834__'
                        '__pyarmor_enter_36835__'
                        b'<COAddr>\x07\x00\x00\x1ap\x00\x00\x00\x00\x00\x00\x00\x00\x00\x00\x00\x00\x00\x00\x00'
                        '_'
                        'ReuploadCdnFileRequest'   # b'\x81\xd0\x1d\x06#\xf6\xb1\xd3\x1f\xd9\t\xceJ\xe5\xf4\x80=X\xaa\xb2\xaf\xd8Z'
                        'file_token'   # b'\x81\xe4\x11\x1f6\xc5\xaa\xdd\x10\xff\x03'
                        'request_token'   # b'\x81\xf0\x1d\x02&\xff\xad\xc6$\xee\x02\xcbi\xe2'
                        '__pyarmor_exit_36836__'
                    [Disassembly]
                        0       NOP                             
                        2       NOP                             
                        4       PUSH_NULL                       
                        6       LOAD_CONST                      2: '__pyarmor_enter_36835__'
                        8       LOAD_CONST                      3: b'<COAddr>\x07\x00\x00\x1ap\x00\x00\x00\x00\x00\x00\x00\x00\x00\x00\x00\x00\x00\x00\x00'
                        10      BUILD_TUPLE                     1
                        12      CALL_FUNCTION_EX                0
                        14      POP_TOP                         
                        16      RESUME                          0
                        18      NOP                             
                        20      NOP                             
                        22      NOP                             
                        24      NOP                             
                        26      NOP                             
                        28      LOAD_CONST                      4: '_'
                        30      PUSH_NULL                       
                        32      LOAD_CONST                      1: '__pyarmor_assert_36834__'
                        34      LOAD_CONST                      5: 'ReuploadCdnFileRequest'   # b'\x81\xd0\x1d\x06#\xf6\xb1\xd3\x1f\xd9\t\xceJ\xe5\xf4\x80=X\xaa\xb2\xaf\xd8Z'
                        36      CALL                            1
                        44      PUSH_NULL                       
                        46      LOAD_CONST                      1: '__pyarmor_assert_36834__'
                        48      LOAD_CONST                      6: 'file_token'   # b'\x81\xe4\x11\x1f6\xc5\xaa\xdd\x10\xff\x03'
                        50      CALL                            1
                        58      LOAD_FAST                       0: self
                        60      LOAD_ATTR                       0: file_token
                        80      PUSH_NULL                       
                        82      LOAD_CONST                      1: '__pyarmor_assert_36834__'
                        84      LOAD_CONST                      7: 'request_token'   # b'\x81\xf0\x1d\x02&\xff\xad\xc6$\xee\x02\xcbi\xe2'
                        86      CALL                            1
                        94      LOAD_FAST                       0: self
                        96      LOAD_ATTR                       2: request_token
                        116     BUILD_MAP                       3
                        118     NOP                             
                        120     NOP                             
                        122     NOP                             
                        124     JUMP_FORWARD                    20 (to 166)
                        126     CALL                            1
                        134     POP_TOP                         
                        136     RETURN_VALUE                    
                        138     PUSH_EXC_INFO                   
                        140     PUSH_NULL                       
                        142     LOAD_CONST                      8: '__pyarmor_exit_36836__'
                        144     NOP                             
                        146     LOAD_CONST                      3: b'<COAddr>\x07\x00\x00\x1ap\x00\x00\x00\x00\x00\x00\x00\x00\x00\x00\x00\x00\x00\x00\x00'
                        148     CALL                            1
                        156     POP_TOP                         
                        158     RERAISE                         0
                        160     COPY                            3
                        162     POP_EXCEPT                      
                        164     RERAISE                         1
                        166     PUSH_NULL                       
                        168     LOAD_CONST                      8: '__pyarmor_exit_36836__'
                        170     LOAD_CONST                      3: b'<COAddr>\x07\x00\x00\x1ap\x00\x00\x00\x00\x00\x00\x00\x00\x00\x00\x00\x00\x00\x00\x00'
                        172     BUILD_TUPLE                     1
                        174     CALL_FUNCTION_EX                0
                        176     POP_TOP                         
                        178     RETURN_VALUE                    
                    [Exception Table]
                        28 to 118 -> 138 [0] 
                        138 to 160 -> 160 [1] lasti
                [Code]
                    File Name: <frozen multithon.tl.functions.upload>
                    Object Name: _bytes
                    Qualified Name: ReuploadCdnFileRequest._bytes
                    Arg Count: 1
                    Pos Only Arg Count: 0
                    KW Only Arg Count: 0
                    Stack Size: 7
                    Flags: 0x20000003 (CO_OPTIMIZED | CO_NEWLOCALS | CO_PYARMOR_OBFUSCATED)
                    [Names]
                        'join'
                        'serialize_bytes'
                        'file_token'
                        'request_token'
                    [Locals+Names]
                        'self'
                        '__assert_armored__'
                    [Constants]
                        None
                        '__pyarmor_assert_36837__'
                        '__pyarmor_enter_36838__'
                        b'<COAddr>\x07\x00\x00\x1a\xa0\x00\x00\x00\x00\x00\x00\x00\x00\x00\x00\x00\x00\x00\x00\x00'
                        b''
                        b"\xa8T'\x9b"
                        '__pyarmor_exit_36839__'
                    [Disassembly]
                        0       NOP                             
                        2       NOP                             
                        4       PUSH_NULL                       
                        6       LOAD_CONST                      2: '__pyarmor_enter_36838__'
                        8       LOAD_CONST                      3: b'<COAddr>\x07\x00\x00\x1a\xa0\x00\x00\x00\x00\x00\x00\x00\x00\x00\x00\x00\x00\x00\x00\x00'
                        10      BUILD_TUPLE                     1
                        12      CALL_FUNCTION_EX                0
                        14      POP_TOP                         
                        16      RESUME                          0
                        18      NOP                             
                        20      NOP                             
                        22      NOP                             
                        24      NOP                             
                        26      NOP                             
                        28      LOAD_CONST                      4: b''
                        30      LOAD_ATTR                       1: join
                        50      LOAD_CONST                      5: b"\xa8T'\x9b"
                        52      LOAD_FAST                       0: self
                        54      LOAD_ATTR                       3: serialize_bytes
                        74      LOAD_FAST                       0: self
                        76      LOAD_ATTR                       4: file_token
                        96      CALL                            1
                        104     LOAD_FAST                       0: self
                        106     LOAD_ATTR                       3: serialize_bytes
                        126     LOAD_FAST                       0: self
                        128     LOAD_ATTR                       6: request_token
                        148     CALL                            1
                        156     BUILD_TUPLE                     3
                        158     CALL                            1
                        166     NOP                             
                        168     NOP                             
                        170     NOP                             
                        172     JUMP_FORWARD                    20 (to 214)
                        174     CALL                            1
                        182     POP_TOP                         
                        184     RETURN_VALUE                    
                        186     PUSH_EXC_INFO                   
                        188     PUSH_NULL                       
                        190     LOAD_CONST                      6: '__pyarmor_exit_36839__'
                        192     NOP                             
                        194     LOAD_CONST                      3: b'<COAddr>\x07\x00\x00\x1a\xa0\x00\x00\x00\x00\x00\x00\x00\x00\x00\x00\x00\x00\x00\x00\x00'
                        196     CALL                            1
                        204     POP_TOP                         
                        206     RERAISE                         0
                        208     COPY                            3
                        210     POP_EXCEPT                      
                        212     RERAISE                         1
                        214     PUSH_NULL                       
                        216     LOAD_CONST                      6: '__pyarmor_exit_36839__'
                        218     LOAD_CONST                      3: b'<COAddr>\x07\x00\x00\x1a\xa0\x00\x00\x00\x00\x00\x00\x00\x00\x00\x00\x00\x00\x00\x00\x00'
                        220     BUILD_TUPLE                     1
                        222     CALL_FUNCTION_EX                0
                        224     POP_TOP                         
                        226     RETURN_VALUE                    
                    [Exception Table]
                        28 to 166 -> 186 [0] 
                        186 to 208 -> 208 [1] lasti
                [Code]
                    File Name: <frozen multithon.tl.functions.upload>
                    Object Name: from_reader
                    Qualified Name: ReuploadCdnFileRequest.from_reader
                    Arg Count: 2
                    Pos Only Arg Count: 0
                    KW Only Arg Count: 0
                    Stack Size: 5
                    Flags: 0x20000003 (CO_OPTIMIZED | CO_NEWLOCALS | CO_PYARMOR_OBFUSCATED)
                    [Names]
                        'tgread_bytes'
                    [Locals+Names]
                        'cls'
                        'reader'
                        '__assert_armored__'
                        '_var_var_0'
                        '_var_var_7'
                    [Constants]
                        None
                        '__pyarmor_assert_36840__'
                        '__pyarmor_enter_36841__'
                        b'<COAddr>\x05\x00\x00\x1ah\x00\x00\x00\x00\x00\x00\x00\x00\x00\x00\x00\x00\x00\x00\x00'
                        (
                            'file_token'
                            'request_token'
                        )
                        '__pyarmor_exit_36842__'
                    [Disassembly]
                        0       NOP                             
                        2       NOP                             
                        4       PUSH_NULL                       
                        6       LOAD_CONST                      2: '__pyarmor_enter_36841__'
                        8       LOAD_CONST                      3: b'<COAddr>\x05\x00\x00\x1ah\x00\x00\x00\x00\x00\x00\x00\x00\x00\x00\x00\x00\x00\x00\x00'
                        10      BUILD_TUPLE                     1
                        12      CALL_FUNCTION_EX                0
                        14      POP_TOP                         
                        16      RESUME                          0
                        18      NOP                             
                        20      NOP                             
                        22      NOP                             
                        24      NOP                             
                        26      NOP                             
                        28      LOAD_FAST                       1: reader
                        30      LOAD_ATTR                       1: tgread_bytes
                        50      CALL                            0
                        58      STORE_FAST                      3: _var_var_0
                        60      LOAD_FAST                       1: reader
                        62      LOAD_ATTR                       1: tgread_bytes
                        82      CALL                            0
                        90      STORE_FAST                      4: _var_var_7
                        92      PUSH_NULL                       
                        94      LOAD_FAST                       0: cls
                        96      LOAD_FAST                       3: _var_var_0
                        98      LOAD_FAST                       4: _var_var_7
                        100     KW_NAMES                        4: ('file_token', 'request_token')
                        102     CALL                            2
                        110     NOP                             
                        112     NOP                             
                        114     NOP                             
                        116     JUMP_FORWARD                    20 (to 158)
                        118     CALL                            1
                        126     POP_TOP                         
                        128     RETURN_VALUE                    
                        130     PUSH_EXC_INFO                   
                        132     PUSH_NULL                       
                        134     LOAD_CONST                      5: '__pyarmor_exit_36842__'
                        136     NOP                             
                        138     LOAD_CONST                      3: b'<COAddr>\x05\x00\x00\x1ah\x00\x00\x00\x00\x00\x00\x00\x00\x00\x00\x00\x00\x00\x00\x00'
                        140     CALL                            1
                        148     POP_TOP                         
                        150     RERAISE                         0
                        152     COPY                            3
                        154     POP_EXCEPT                      
                        156     RERAISE                         1
                        158     PUSH_NULL                       
                        160     LOAD_CONST                      5: '__pyarmor_exit_36842__'
                        162     LOAD_CONST                      3: b'<COAddr>\x05\x00\x00\x1ah\x00\x00\x00\x00\x00\x00\x00\x00\x00\x00\x00\x00\x00\x00\x00'
                        164     BUILD_TUPLE                     1
                        166     CALL_FUNCTION_EX                0
                        168     POP_TOP                         
                        170     RETURN_VALUE                    
                    [Exception Table]
                        28 to 110 -> 130 [0] 
                        130 to 152 -> 152 [1] lasti
                '__pyarmor_exit_36830__'
                None
            [Disassembly]
                0       NOP                             
                2       LOAD_NAME                       0: __name__
                4       STORE_NAME                      1: __module__
                6       LOAD_CONST                      0: 'ReuploadCdnFileRequest'
                8       STORE_NAME                      2: __qualname__
                10      NOP                             
                12      PUSH_NULL                       
                14      LOAD_CONST                      2: '__pyarmor_enter_36829__'
                16      LOAD_CONST                      3: b'<COAddr>\x05\x00\x00"J\x00\x00\x00\x00\x00\x00\x00\x00\x00\x00\x00\x00\x00\x00\x00'
                18      BUILD_TUPLE                     1
                20      CALL_FUNCTION_EX                0
                22      POP_TOP                         
                24      RESUME                          0
                26      NOP                             
                28      NOP                             
                30      NOP                             
                32      NOP                             
                34      NOP                             
                36      LOAD_CONST                      4: 0x9B2754A8
                38      STORE_NAME                      4: CONSTRUCTOR_ID
                40      LOAD_CONST                      5: 0xA5940726
                42      STORE_NAME                      5: SUBCLASS_OF_ID
                44      LOAD_CONST                      6: 'file_token'
                46      LOAD_NAME                       6: bytes
                48      LOAD_CONST                      7: 'request_token'
                50      LOAD_NAME                       6: bytes
                52      BUILD_TUPLE                     4
                54      LOAD_CONST                      8: <CODE> __init__
                56      MAKE_FUNCTION                   4
                58      STORE_NAME                      7: __init__
                60      LOAD_CONST                      9: <CODE> to_dict
                62      MAKE_FUNCTION                   0
                64      STORE_NAME                      8: to_dict
                66      LOAD_CONST                      10: <CODE> _bytes
                68      MAKE_FUNCTION                   0
                70      STORE_NAME                      9: _bytes
                72      LOAD_NAME                       10: classmethod
                74      LOAD_CONST                      11: <CODE> from_reader
                76      MAKE_FUNCTION                   0
                78      CALL                            0
                86      STORE_NAME                      11: from_reader
                88      LOAD_CONST                      13: None
                90      NOP                             
                92      NOP                             
                94      NOP                             
                96      JUMP_FORWARD                    19 (to 136)
                104     POP_TOP                         
                106     RETURN_CONST                    13: None
                108     PUSH_EXC_INFO                   
                110     PUSH_NULL                       
                112     LOAD_CONST                      12: '__pyarmor_exit_36830__'
                114     NOP                             
                116     LOAD_CONST                      3: b'<COAddr>\x05\x00\x00"J\x00\x00\x00\x00\x00\x00\x00\x00\x00\x00\x00\x00\x00\x00\x00'
                118     CALL                            1
                126     POP_TOP                         
                128     RERAISE                         0
                130     COPY                            3
                132     POP_EXCEPT                      
                134     RERAISE                         1
                136     PUSH_NULL                       
                138     LOAD_CONST                      12: '__pyarmor_exit_36830__'
                140     LOAD_CONST                      3: b'<COAddr>\x05\x00\x00"J\x00\x00\x00\x00\x00\x00\x00\x00\x00\x00\x00\x00\x00\x00\x00'
                142     BUILD_TUPLE                     1
                144     CALL_FUNCTION_EX                0
                146     POP_TOP                         
                148     RETURN_VALUE                    
            [Exception Table]
                36 to 88 -> 108 [0] 
                108 to 130 -> 130 [1] lasti
        'ReuploadCdnFileRequest'
        [Code]
            File Name: <frozen multithon.tl.functions.upload>
            Object Name: SaveBigFilePartRequest
            Qualified Name: SaveBigFilePartRequest
            Arg Count: 0
            Pos Only Arg Count: 0
            KW Only Arg Count: 0
            Stack Size: 8
            Flags: 0x20000000 (CO_PYARMOR_OBFUSCATED)
            [Names]
                '__name__'
                '__module__'
                '__qualname__'
                '__assert_armored__'
                'CONSTRUCTOR_ID'
                'SUBCLASS_OF_ID'
                'int'
                'bytes'
                '__init__'
                'to_dict'
                '_bytes'
                'classmethod'
                'from_reader'
            [Locals+Names]
            [Constants]
                'SaveBigFilePartRequest'
                '__pyarmor_assert_36843__'
                '__pyarmor_enter_36844__'
                b'<COAddr>\x05\x00\x00"R\x00\x00\x00\x00\x00\x00\x00\x00\x00\x00\x00\x00\x00\x00\x00'
                0xDE7B673D
                0xF5B399AC
                'file_id'
                'file_part'
                'file_total_parts'
                'bytes'
                [Code]
                    File Name: <frozen multithon.tl.functions.upload>
                    Object Name: __init__
                    Qualified Name: SaveBigFilePartRequest.__init__
                    Arg Count: 5
                    Pos Only Arg Count: 0
                    KW Only Arg Count: 0
                    Stack Size: 5
                    Flags: 0x20000003 (CO_OPTIMIZED | CO_NEWLOCALS | CO_PYARMOR_OBFUSCATED)
                    [Names]
                        'file_id'
                        'file_part'
                        'file_total_parts'
                        'bytes'
                    [Locals+Names]
                        'self'
                        'file_id'
                        'file_part'
                        'file_total_parts'
                        'bytes'
                        '__assert_armored__'
                    [Constants]
                        '\n        :returns Bool: This type has no constructors.\n        '
                        '__pyarmor_assert_36846__'
                        '__pyarmor_enter_36847__'
                        b'<COAddr>\x05\x00\x00\x1aN\x00\x00\x00\x00\x00\x00\x00\x00\x00\x00\x00\x00\x00\x00\x00'
                        '__pyarmor_exit_36848__'
                        None
                    [Disassembly]
                        0       NOP                             
                        2       NOP                             
                        4       PUSH_NULL                       
                        6       LOAD_CONST                      2: '__pyarmor_enter_36847__'
                        8       LOAD_CONST                      3: b'<COAddr>\x05\x00\x00\x1aN\x00\x00\x00\x00\x00\x00\x00\x00\x00\x00\x00\x00\x00\x00\x00'
                        10      BUILD_TUPLE                     1
                        12      CALL_FUNCTION_EX                0
                        14      POP_TOP                         
                        16      RESUME                          0
                        18      NOP                             
                        20      NOP                             
                        22      NOP                             
                        24      NOP                             
                        26      NOP                             
                        28      LOAD_FAST                       1: file_id
                        30      LOAD_FAST                       0: self
                        32      STORE_ATTR                      0: file_id
                        42      LOAD_FAST                       2: file_part
                        44      LOAD_FAST                       0: self
                        46      STORE_ATTR                      1: file_part
                        56      LOAD_FAST                       3: file_total_parts
                        58      LOAD_FAST                       0: self
                        60      STORE_ATTR                      2: file_total_parts
                        70      LOAD_FAST                       4: bytes
                        72      LOAD_FAST                       0: self
                        74      STORE_ATTR                      3: bytes
                        84      LOAD_CONST                      5: None
                        86      NOP                             
                        88      NOP                             
                        90      NOP                             
                        92      JUMP_FORWARD                    19 (to 132)
                        100     POP_TOP                         
                        102     RETURN_CONST                    5: None
                        104     PUSH_EXC_INFO                   
                        106     PUSH_NULL                       
                        108     LOAD_CONST                      4: '__pyarmor_exit_36848__'
                        110     NOP                             
                        112     LOAD_CONST                      3: b'<COAddr>\x05\x00\x00\x1aN\x00\x00\x00\x00\x00\x00\x00\x00\x00\x00\x00\x00\x00\x00\x00'
                        114     CALL                            1
                        122     POP_TOP                         
                        124     RERAISE                         0
                        126     COPY                            3
                        128     POP_EXCEPT                      
                        130     RERAISE                         1
                        132     PUSH_NULL                       
                        134     LOAD_CONST                      4: '__pyarmor_exit_36848__'
                        136     LOAD_CONST                      3: b'<COAddr>\x05\x00\x00\x1aN\x00\x00\x00\x00\x00\x00\x00\x00\x00\x00\x00\x00\x00\x00\x00'
                        138     BUILD_TUPLE                     1
                        140     CALL_FUNCTION_EX                0
                        142     POP_TOP                         
                        144     RETURN_VALUE                    
                    [Exception Table]
                        28 to 84 -> 104 [0] 
                        104 to 126 -> 126 [1] lasti
                [Code]
                    File Name: <frozen multithon.tl.functions.upload>
                    Object Name: to_dict
                    Qualified Name: SaveBigFilePartRequest.to_dict
                    Arg Count: 1
                    Pos Only Arg Count: 0
                    KW Only Arg Count: 0
                    Stack Size: 10
                    Flags: 0x20000003 (CO_OPTIMIZED | CO_NEWLOCALS | CO_PYARMOR_OBFUSCATED)
                    [Names]
                        'file_id'
                        'file_part'
                        'file_total_parts'
                        'bytes'
                    [Locals+Names]
                        'self'
                        '__assert_armored__'
                    [Constants]
                        None
                        '__pyarmor_assert_36849__'
                        '__pyarmor_enter_36850__'
                        b'<COAddr>\x05\x00\x00\x1a\xa0\x00\x00\x00\x00\x00\x00\x00\x00\x00\x00\x00\x00\x00\x00\x00'
                        '_'
                        'SaveBigFilePartRequest'   # b'\x81\xd1\x19\x056\xd8\xb7\xd5=\xf3\x01\xc5\\\xed\xea\x91=X\xaa\xb2\xaf\xd8Z'
                        'file_id'
                        'file_part'   # b'\x81\xe4\x11\x1f6\xc5\xae\xd3\t\xee'
                        'file_total_parts'   # b'\x81\xe4\x11\x1f6\xc5\xaa\xdd\x0f\xfb\x01\xff|\xed\xea\x91\x1c'
                        'bytes'
                        '__pyarmor_exit_36851__'
                    [Disassembly]
                        0       NOP                             
                        2       NOP                             
                        4       PUSH_NULL                       
                        6       LOAD_CONST                      2: '__pyarmor_enter_36850__'
                        8       LOAD_CONST                      3: b'<COAddr>\x05\x00\x00\x1a\xa0\x00\x00\x00\x00\x00\x00\x00\x00\x00\x00\x00\x00\x00\x00\x00'
                        10      BUILD_TUPLE                     1
                        12      CALL_FUNCTION_EX                0
                        14      POP_TOP                         
                        16      RESUME                          0
                        18      NOP                             
                        20      NOP                             
                        22      NOP                             
                        24      NOP                             
                        26      NOP                             
                        28      LOAD_CONST                      4: '_'
                        30      PUSH_NULL                       
                        32      LOAD_CONST                      1: '__pyarmor_assert_36849__'
                        34      LOAD_CONST                      5: 'SaveBigFilePartRequest'   # b'\x81\xd1\x19\x056\xd8\xb7\xd5=\xf3\x01\xc5\\\xed\xea\x91=X\xaa\xb2\xaf\xd8Z'
                        36      CALL                            1
                        44      LOAD_CONST                      6: 'file_id'
                        46      LOAD_FAST                       0: self
                        48      LOAD_ATTR                       0: file_id
                        68      PUSH_NULL                       
                        70      LOAD_CONST                      1: '__pyarmor_assert_36849__'
                        72      LOAD_CONST                      7: 'file_part'   # b'\x81\xe4\x11\x1f6\xc5\xae\xd3\t\xee'
                        74      CALL                            1
                        82      LOAD_FAST                       0: self
                        84      LOAD_ATTR                       2: file_part
                        104     PUSH_NULL                       
                        106     LOAD_CONST                      1: '__pyarmor_assert_36849__'
                        108     LOAD_CONST                      8: 'file_total_parts'   # b'\x81\xe4\x11\x1f6\xc5\xaa\xdd\x0f\xfb\x01\xff|\xed\xea\x91\x1c'
                        110     CALL                            1
                        118     LOAD_FAST                       0: self
                        120     LOAD_ATTR                       4: file_total_parts
                        140     LOAD_CONST                      9: 'bytes'
                        142     LOAD_FAST                       0: self
                        144     LOAD_ATTR                       6: bytes
                        164     BUILD_MAP                       5
                        166     NOP                             
                        168     NOP                             
                        170     NOP                             
                        172     JUMP_FORWARD                    20 (to 214)
                        174     CALL                            1
                        182     POP_TOP                         
                        184     RETURN_VALUE                    
                        186     PUSH_EXC_INFO                   
                        188     PUSH_NULL                       
                        190     LOAD_CONST                      10: '__pyarmor_exit_36851__'
                        192     NOP                             
                        194     LOAD_CONST                      3: b'<COAddr>\x05\x00\x00\x1a\xa0\x00\x00\x00\x00\x00\x00\x00\x00\x00\x00\x00\x00\x00\x00\x00'
                        196     CALL                            1
                        204     POP_TOP                         
                        206     RERAISE                         0
                        208     COPY                            3
                        210     POP_EXCEPT                      
                        212     RERAISE                         1
                        214     PUSH_NULL                       
                        216     LOAD_CONST                      10: '__pyarmor_exit_36851__'
                        218     LOAD_CONST                      3: b'<COAddr>\x05\x00\x00\x1a\xa0\x00\x00\x00\x00\x00\x00\x00\x00\x00\x00\x00\x00\x00\x00\x00'
                        220     BUILD_TUPLE                     1
                        222     CALL_FUNCTION_EX                0
                        224     POP_TOP                         
                        226     RETURN_VALUE                    
                    [Exception Table]
                        28 to 166 -> 186 [0] 
                        186 to 208 -> 208 [1] lasti
                [Code]
                    File Name: <frozen multithon.tl.functions.upload>
                    Object Name: _bytes
                    Qualified Name: SaveBigFilePartRequest._bytes
                    Arg Count: 1
                    Pos Only Arg Count: 0
                    KW Only Arg Count: 0
                    Stack Size: 9
                    Flags: 0x20000003 (CO_OPTIMIZED | CO_NEWLOCALS | CO_PYARMOR_OBFUSCATED)
                    [Names]
                        'join'
                        'struct'
                        'pack'
                        'file_id'
                        'file_part'
                        'file_total_parts'
                        'serialize_bytes'
                        'bytes'
                    [Locals+Names]
                        'self'
                        '__assert_armored__'
                    [Constants]
                        None
                        '__pyarmor_assert_36852__'
                        '__pyarmor_enter_36853__'
                        b'<COAddr>\x05\x00\x00\x1a&\x01\x00\x00\x00\x00\x00\x00\x00\x00\x00\x00\x00\x00\x00\x00'
                        b''
                        b'=g{\xde'
                        '<q'
                        '<i'
                        '__pyarmor_exit_36854__'
                    [Disassembly]
                        0       NOP                             
                        2       NOP                             
                        4       PUSH_NULL                       
                        6       LOAD_CONST                      2: '__pyarmor_enter_36853__'
                        8       LOAD_CONST                      3: b'<COAddr>\x05\x00\x00\x1a&\x01\x00\x00\x00\x00\x00\x00\x00\x00\x00\x00\x00\x00\x00\x00'
                        10      BUILD_TUPLE                     1
                        12      CALL_FUNCTION_EX                0
                        14      POP_TOP                         
                        16      RESUME                          0
                        18      NOP                             
                        20      NOP                             
                        22      NOP                             
                        24      NOP                             
                        26      NOP                             
                        28      LOAD_CONST                      4: b''
                        30      LOAD_ATTR                       1: join
                        50      LOAD_CONST                      5: b'=g{\xde'
                        52      LOAD_GLOBAL                     3: NULL + struct
                        62      LOAD_ATTR                       4: pack
                        82      LOAD_CONST                      6: '<q'
                        84      LOAD_FAST                       0: self
                        86      LOAD_ATTR                       6: file_id
                        106     CALL                            2
                        114     LOAD_GLOBAL                     3: NULL + struct
                        124     LOAD_ATTR                       4: pack
                        144     LOAD_CONST                      7: '<i'
                        146     LOAD_FAST                       0: self
                        148     LOAD_ATTR                       8: file_part
                        168     CALL                            2
                        176     LOAD_GLOBAL                     3: NULL + struct
                        186     LOAD_ATTR                       4: pack
                        206     LOAD_CONST                      7: '<i'
                        208     LOAD_FAST                       0: self
                        210     LOAD_ATTR                       10: file_total_parts
                        230     CALL                            2
                        238     LOAD_FAST                       0: self
                        240     LOAD_ATTR                       13: serialize_bytes
                        260     LOAD_FAST                       0: self
                        262     LOAD_ATTR                       14: bytes
                        282     CALL                            1
                        290     BUILD_TUPLE                     5
                        292     CALL                            1
                        300     NOP                             
                        302     NOP                             
                        304     NOP                             
                        306     JUMP_FORWARD                    20 (to 348)
                        308     CALL                            1
                        316     POP_TOP                         
                        318     RETURN_VALUE                    
                        320     PUSH_EXC_INFO                   
                        322     PUSH_NULL                       
                        324     LOAD_CONST                      8: '__pyarmor_exit_36854__'
                        326     NOP                             
                        328     LOAD_CONST                      3: b'<COAddr>\x05\x00\x00\x1a&\x01\x00\x00\x00\x00\x00\x00\x00\x00\x00\x00\x00\x00\x00\x00'
                        330     CALL                            1
                        338     POP_TOP                         
                        340     RERAISE                         0
                        342     COPY                            3
                        344     POP_EXCEPT                      
                        346     RERAISE                         1
                        348     PUSH_NULL                       
                        350     LOAD_CONST                      8: '__pyarmor_exit_36854__'
                        352     LOAD_CONST                      3: b'<COAddr>\x05\x00\x00\x1a&\x01\x00\x00\x00\x00\x00\x00\x00\x00\x00\x00\x00\x00\x00\x00'
                        354     BUILD_TUPLE                     1
                        356     CALL_FUNCTION_EX                0
                        358     POP_TOP                         
                        360     RETURN_VALUE                    
                    [Exception Table]
                        28 to 300 -> 320 [0] 
                        320 to 342 -> 342 [1] lasti
                [Code]
                    File Name: <frozen multithon.tl.functions.upload>
                    Object Name: from_reader
                    Qualified Name: SaveBigFilePartRequest.from_reader
                    Arg Count: 2
                    Pos Only Arg Count: 0
                    KW Only Arg Count: 0
                    Stack Size: 6
                    Flags: 0x20000003 (CO_OPTIMIZED | CO_NEWLOCALS | CO_PYARMOR_OBFUSCATED)
                    [Names]
                        'read_long'
                        'read_int'
                        'tgread_bytes'
                    [Locals+Names]
                        'cls'
                        'reader'
                        '__assert_armored__'
                        '_var_var_8'
                        '_var_var_9'
                        '_var_var_10'
                        '_var_var_11'
                    [Constants]
                        None
                        '__pyarmor_assert_36855__'
                        '__pyarmor_enter_36856__'
                        b'<COAddr>\x07\x00\x00\x1a\xac\x00\x00\x00\x00\x00\x00\x00\x00\x00\x00\x00\x00\x00\x00\x00'
                        (
                            'file_id'
                            'file_part'
                            'file_total_parts'
                            'bytes'
                        )
                        '__pyarmor_exit_36857__'
                    [Disassembly]
                        0       NOP                             
                        2       NOP                             
                        4       PUSH_NULL                       
                        6       LOAD_CONST                      2: '__pyarmor_enter_36856__'
                        8       LOAD_CONST                      3: b'<COAddr>\x07\x00\x00\x1a\xac\x00\x00\x00\x00\x00\x00\x00\x00\x00\x00\x00\x00\x00\x00\x00'
                        10      BUILD_TUPLE                     1
                        12      CALL_FUNCTION_EX                0
                        14      POP_TOP                         
                        16      RESUME                          0
                        18      NOP                             
                        20      NOP                             
                        22      NOP                             
                        24      NOP                             
                        26      NOP                             
                        28      LOAD_FAST                       1: reader
                        30      LOAD_ATTR                       1: read_long
                        50      CALL                            0
                        58      STORE_FAST                      3: _var_var_8
                        60      LOAD_FAST                       1: reader
                        62      LOAD_ATTR                       3: read_int
                        82      CALL                            0
                        90      STORE_FAST                      4: _var_var_9
                        92      LOAD_FAST                       1: reader
                        94      LOAD_ATTR                       3: read_int
                        114     CALL                            0
                        122     STORE_FAST                      5: _var_var_10
                        124     LOAD_FAST                       1: reader
                        126     LOAD_ATTR                       5: tgread_bytes
                        146     CALL                            0
                        154     STORE_FAST                      6: _var_var_11
                        156     PUSH_NULL                       
                        158     LOAD_FAST                       0: cls
                        160     LOAD_FAST                       3: _var_var_8
                        162     LOAD_FAST                       4: _var_var_9
                        164     LOAD_FAST                       5: _var_var_10
                        166     LOAD_FAST                       6: _var_var_11
                        168     KW_NAMES                        4: ('file_id', 'file_part', 'file_total_parts', 'bytes')
                        170     CALL                            4
                        178     NOP                             
                        180     NOP                             
                        182     NOP                             
                        184     JUMP_FORWARD                    20 (to 226)
                        186     CALL                            1
                        194     POP_TOP                         
                        196     RETURN_VALUE                    
                        198     PUSH_EXC_INFO                   
                        200     PUSH_NULL                       
                        202     LOAD_CONST                      5: '__pyarmor_exit_36857__'
                        204     NOP                             
                        206     LOAD_CONST                      3: b'<COAddr>\x07\x00\x00\x1a\xac\x00\x00\x00\x00\x00\x00\x00\x00\x00\x00\x00\x00\x00\x00\x00'
                        208     CALL                            1
                        216     POP_TOP                         
                        218     RERAISE                         0
                        220     COPY                            3
                        222     POP_EXCEPT                      
                        224     RERAISE                         1
                        226     PUSH_NULL                       
                        228     LOAD_CONST                      5: '__pyarmor_exit_36857__'
                        230     LOAD_CONST                      3: b'<COAddr>\x07\x00\x00\x1a\xac\x00\x00\x00\x00\x00\x00\x00\x00\x00\x00\x00\x00\x00\x00\x00'
                        232     BUILD_TUPLE                     1
                        234     CALL_FUNCTION_EX                0
                        236     POP_TOP                         
                        238     RETURN_VALUE                    
                    [Exception Table]
                        28 to 178 -> 198 [0] 
                        198 to 220 -> 220 [1] lasti
                '__pyarmor_exit_36845__'
                None
            [Disassembly]
                0       NOP                             
                2       LOAD_NAME                       0: __name__
                4       STORE_NAME                      1: __module__
                6       LOAD_CONST                      0: 'SaveBigFilePartRequest'
                8       STORE_NAME                      2: __qualname__
                10      NOP                             
                12      PUSH_NULL                       
                14      LOAD_CONST                      2: '__pyarmor_enter_36844__'
                16      LOAD_CONST                      3: b'<COAddr>\x05\x00\x00"R\x00\x00\x00\x00\x00\x00\x00\x00\x00\x00\x00\x00\x00\x00\x00'
                18      BUILD_TUPLE                     1
                20      CALL_FUNCTION_EX                0
                22      POP_TOP                         
                24      RESUME                          0
                26      NOP                             
                28      NOP                             
                30      NOP                             
                32      NOP                             
                34      NOP                             
                36      LOAD_CONST                      4: 0xDE7B673D
                38      STORE_NAME                      4: CONSTRUCTOR_ID
                40      LOAD_CONST                      5: 0xF5B399AC
                42      STORE_NAME                      5: SUBCLASS_OF_ID
                44      LOAD_CONST                      6: 'file_id'
                46      LOAD_NAME                       6: int
                48      LOAD_CONST                      7: 'file_part'
                50      LOAD_NAME                       6: int
                52      LOAD_CONST                      8: 'file_total_parts'
                54      LOAD_NAME                       6: int
                56      LOAD_CONST                      9: 'bytes'
                58      LOAD_NAME                       7: bytes
                60      BUILD_TUPLE                     8
                62      LOAD_CONST                      10: <CODE> __init__
                64      MAKE_FUNCTION                   4
                66      STORE_NAME                      8: __init__
                68      LOAD_CONST                      11: <CODE> to_dict
                70      MAKE_FUNCTION                   0
                72      STORE_NAME                      9: to_dict
                74      LOAD_CONST                      12: <CODE> _bytes
                76      MAKE_FUNCTION                   0
                78      STORE_NAME                      10: _bytes
                80      LOAD_NAME                       11: classmethod
                82      LOAD_CONST                      13: <CODE> from_reader
                84      MAKE_FUNCTION                   0
                86      CALL                            0
                94      STORE_NAME                      12: from_reader
                96      LOAD_CONST                      15: None
                98      NOP                             
                100     NOP                             
                102     NOP                             
                104     JUMP_FORWARD                    19 (to 144)
                112     POP_TOP                         
                114     RETURN_CONST                    15: None
                116     PUSH_EXC_INFO                   
                118     PUSH_NULL                       
                120     LOAD_CONST                      14: '__pyarmor_exit_36845__'
                122     NOP                             
                124     LOAD_CONST                      3: b'<COAddr>\x05\x00\x00"R\x00\x00\x00\x00\x00\x00\x00\x00\x00\x00\x00\x00\x00\x00\x00'
                126     CALL                            1
                134     POP_TOP                         
                136     RERAISE                         0
                138     COPY                            3
                140     POP_EXCEPT                      
                142     RERAISE                         1
                144     PUSH_NULL                       
                146     LOAD_CONST                      14: '__pyarmor_exit_36845__'
                148     LOAD_CONST                      3: b'<COAddr>\x05\x00\x00"R\x00\x00\x00\x00\x00\x00\x00\x00\x00\x00\x00\x00\x00\x00\x00'
                150     BUILD_TUPLE                     1
                152     CALL_FUNCTION_EX                0
                154     POP_TOP                         
                156     RETURN_VALUE                    
            [Exception Table]
                36 to 96 -> 116 [0] 
                116 to 138 -> 138 [1] lasti
        'SaveBigFilePartRequest'
        [Code]
            File Name: <frozen multithon.tl.functions.upload>
            Object Name: SaveFilePartRequest
            Qualified Name: SaveFilePartRequest
            Arg Count: 0
            Pos Only Arg Count: 0
            KW Only Arg Count: 0
            Stack Size: 6
            Flags: 0x20000000 (CO_PYARMOR_OBFUSCATED)
            [Names]
                '__name__'
                '__module__'
                '__qualname__'
                '__assert_armored__'
                'CONSTRUCTOR_ID'
                'SUBCLASS_OF_ID'
                'int'
                'bytes'
                '__init__'
                'to_dict'
                '_bytes'
                'classmethod'
                'from_reader'
            [Locals+Names]
            [Constants]
                'SaveFilePartRequest'
                '__pyarmor_assert_36858__'
                '__pyarmor_enter_36859__'
                b'<COAddr>\x07\x00\x00"N\x00\x00\x00\x00\x00\x00\x00\x00\x00\x00\x00\x00\x00\x00\x00'
                0xB304A621
                0xF5B399AC
                'file_id'
                'file_part'
                'bytes'
                [Code]
                    File Name: <frozen multithon.tl.functions.upload>
                    Object Name: __init__
                    Qualified Name: SaveFilePartRequest.__init__
                    Arg Count: 4
                    Pos Only Arg Count: 0
                    KW Only Arg Count: 0
                    Stack Size: 5
                    Flags: 0x20000003 (CO_OPTIMIZED | CO_NEWLOCALS | CO_PYARMOR_OBFUSCATED)
                    [Names]
                        'file_id'
                        'file_part'
                        'bytes'
                    [Locals+Names]
                        'self'
                        'file_id'
                        'file_part'
                        'bytes'
                        '__assert_armored__'
                    [Constants]
                        '\n        :returns Bool: This type has no constructors.\n        '
                        '__pyarmor_assert_36861__'
                        '__pyarmor_enter_36862__'
                        b'<COAddr>\x05\x00\x00\x1a@\x00\x00\x00\x00\x00\x00\x00\x00\x00\x00\x00\x00\x00\x00\x00'
                        '__pyarmor_exit_36863__'
                        None
                    [Disassembly]
                        0       NOP                             
                        2       NOP                             
                        4       PUSH_NULL                       
                        6       LOAD_CONST                      2: '__pyarmor_enter_36862__'
                        8       LOAD_CONST                      3: b'<COAddr>\x05\x00\x00\x1a@\x00\x00\x00\x00\x00\x00\x00\x00\x00\x00\x00\x00\x00\x00\x00'
                        10      BUILD_TUPLE                     1
                        12      CALL_FUNCTION_EX                0
                        14      POP_TOP                         
                        16      RESUME                          0
                        18      NOP                             
                        20      NOP                             
                        22      NOP                             
                        24      NOP                             
                        26      NOP                             
                        28      LOAD_FAST                       1: file_id
                        30      LOAD_FAST                       0: self
                        32      STORE_ATTR                      0: file_id
                        42      LOAD_FAST                       2: file_part
                        44      LOAD_FAST                       0: self
                        46      STORE_ATTR                      1: file_part
                        56      LOAD_FAST                       3: bytes
                        58      LOAD_FAST                       0: self
                        60      STORE_ATTR                      2: bytes
                        70      LOAD_CONST                      5: None
                        72      NOP                             
                        74      NOP                             
                        76      NOP                             
                        78      JUMP_FORWARD                    19 (to 118)
                        86      POP_TOP                         
                        88      RETURN_CONST                    5: None
                        90      PUSH_EXC_INFO                   
                        92      PUSH_NULL                       
                        94      LOAD_CONST                      4: '__pyarmor_exit_36863__'
                        96      NOP                             
                        98      LOAD_CONST                      3: b'<COAddr>\x05\x00\x00\x1a@\x00\x00\x00\x00\x00\x00\x00\x00\x00\x00\x00\x00\x00\x00\x00'
                        100     CALL                            1
                        108     POP_TOP                         
                        110     RERAISE                         0
                        112     COPY                            3
                        114     POP_EXCEPT                      
                        116     RERAISE                         1
                        118     PUSH_NULL                       
                        120     LOAD_CONST                      4: '__pyarmor_exit_36863__'
                        122     LOAD_CONST                      3: b'<COAddr>\x05\x00\x00\x1a@\x00\x00\x00\x00\x00\x00\x00\x00\x00\x00\x00\x00\x00\x00\x00'
                        124     BUILD_TUPLE                     1
                        126     CALL_FUNCTION_EX                0
                        128     POP_TOP                         
                        130     RETURN_VALUE                    
                    [Exception Table]
                        28 to 70 -> 90 [0] 
                        90 to 112 -> 112 [1] lasti
                [Code]
                    File Name: <frozen multithon.tl.functions.upload>
                    Object Name: to_dict
                    Qualified Name: SaveFilePartRequest.to_dict
                    Arg Count: 1
                    Pos Only Arg Count: 0
                    KW Only Arg Count: 0
                    Stack Size: 8
                    Flags: 0x20000003 (CO_OPTIMIZED | CO_NEWLOCALS | CO_PYARMOR_OBFUSCATED)
                    [Names]
                        'file_id'
                        'file_part'
                        'bytes'
                    [Locals+Names]
                        'self'
                        '__assert_armored__'
                    [Constants]
                        None
                        '__pyarmor_assert_36864__'
                        '__pyarmor_enter_36865__'
                        b'<COAddr>\x05\x00\x00\x1a|\x00\x00\x00\x00\x00\x00\x00\x00\x00\x00\x00\x00\x00\x00\x00'
                        '_'
                        'SaveFilePartRequest'   # b'\x81\xd1\x19\x056\xdc\xb7\xde\x1e\xca\x0c\xd2x\xde\xfd\x94\x1aX\xa8\xb3'
                        'file_id'
                        'file_part'   # b'\x81\xe4\x11\x1f6\xc5\xae\xd3\t\xee'
                        'bytes'
                        '__pyarmor_exit_36866__'
                    [Disassembly]
                        0       NOP                             
                        2       NOP                             
                        4       PUSH_NULL                       
                        6       LOAD_CONST                      2: '__pyarmor_enter_36865__'
                        8       LOAD_CONST                      3: b'<COAddr>\x05\x00\x00\x1a|\x00\x00\x00\x00\x00\x00\x00\x00\x00\x00\x00\x00\x00\x00\x00'
                        10      BUILD_TUPLE                     1
                        12      CALL_FUNCTION_EX                0
                        14      POP_TOP                         
                        16      RESUME                          0
                        18      NOP                             
                        20      NOP                             
                        22      NOP                             
                        24      NOP                             
                        26      NOP                             
                        28      LOAD_CONST                      4: '_'
                        30      PUSH_NULL                       
                        32      LOAD_CONST                      1: '__pyarmor_assert_36864__'
                        34      LOAD_CONST                      5: 'SaveFilePartRequest'   # b'\x81\xd1\x19\x056\xdc\xb7\xde\x1e\xca\x0c\xd2x\xde\xfd\x94\x1aX\xa8\xb3'
                        36      CALL                            1
                        44      LOAD_CONST                      6: 'file_id'
                        46      LOAD_FAST                       0: self
                        48      LOAD_ATTR                       0: file_id
                        68      PUSH_NULL                       
                        70      LOAD_CONST                      1: '__pyarmor_assert_36864__'
                        72      LOAD_CONST                      7: 'file_part'   # b'\x81\xe4\x11\x1f6\xc5\xae\xd3\t\xee'
                        74      CALL                            1
                        82      LOAD_FAST                       0: self
                        84      LOAD_ATTR                       2: file_part
                        104     LOAD_CONST                      8: 'bytes'
                        106     LOAD_FAST                       0: self
                        108     LOAD_ATTR                       4: bytes
                        128     BUILD_MAP                       4
                        130     NOP                             
                        132     NOP                             
                        134     NOP                             
                        136     JUMP_FORWARD                    20 (to 178)
                        138     CALL                            1
                        146     POP_TOP                         
                        148     RETURN_VALUE                    
                        150     PUSH_EXC_INFO                   
                        152     PUSH_NULL                       
                        154     LOAD_CONST                      9: '__pyarmor_exit_36866__'
                        156     NOP                             
                        158     LOAD_CONST                      3: b'<COAddr>\x05\x00\x00\x1a|\x00\x00\x00\x00\x00\x00\x00\x00\x00\x00\x00\x00\x00\x00\x00'
                        160     CALL                            1
                        168     POP_TOP                         
                        170     RERAISE                         0
                        172     COPY                            3
                        174     POP_EXCEPT                      
                        176     RERAISE                         1
                        178     PUSH_NULL                       
                        180     LOAD_CONST                      9: '__pyarmor_exit_36866__'
                        182     LOAD_CONST                      3: b'<COAddr>\x05\x00\x00\x1a|\x00\x00\x00\x00\x00\x00\x00\x00\x00\x00\x00\x00\x00\x00\x00'
                        184     BUILD_TUPLE                     1
                        186     CALL_FUNCTION_EX                0
                        188     POP_TOP                         
                        190     RETURN_VALUE                    
                    [Exception Table]
                        28 to 130 -> 150 [0] 
                        150 to 172 -> 172 [1] lasti
                [Code]
                    File Name: <frozen multithon.tl.functions.upload>
                    Object Name: _bytes
                    Qualified Name: SaveFilePartRequest._bytes
                    Arg Count: 1
                    Pos Only Arg Count: 0
                    KW Only Arg Count: 0
                    Stack Size: 8
                    Flags: 0x20000003 (CO_OPTIMIZED | CO_NEWLOCALS | CO_PYARMOR_OBFUSCATED)
                    [Names]
                        'join'
                        'struct'
                        'pack'
                        'file_id'
                        'file_part'
                        'serialize_bytes'
                        'bytes'
                    [Locals+Names]
                        'self'
                        '__assert_armored__'
                    [Constants]
                        None
                        '__pyarmor_assert_36867__'
                        '__pyarmor_enter_36868__'
                        b'<COAddr>\x07\x00\x00\x1a\xe8\x00\x00\x00\x00\x00\x00\x00\x00\x00\x00\x00\x00\x00\x00\x00'
                        b''
                        b'!\xa6\x04\xb3'
                        '<q'
                        '<i'
                        '__pyarmor_exit_36869__'
                    [Disassembly]
                        0       NOP                             
                        2       NOP                             
                        4       PUSH_NULL                       
                        6       LOAD_CONST                      2: '__pyarmor_enter_36868__'
                        8       LOAD_CONST                      3: b'<COAddr>\x07\x00\x00\x1a\xe8\x00\x00\x00\x00\x00\x00\x00\x00\x00\x00\x00\x00\x00\x00\x00'
                        10      BUILD_TUPLE                     1
                        12      CALL_FUNCTION_EX                0
                        14      POP_TOP                         
                        16      RESUME                          0
                        18      NOP                             
                        20      NOP                             
                        22      NOP                             
                        24      NOP                             
                        26      NOP                             
                        28      LOAD_CONST                      4: b''
                        30      LOAD_ATTR                       1: join
                        50      LOAD_CONST                      5: b'!\xa6\x04\xb3'
                        52      LOAD_GLOBAL                     3: NULL + struct
                        62      LOAD_ATTR                       4: pack
                        82      LOAD_CONST                      6: '<q'
                        84      LOAD_FAST                       0: self
                        86      LOAD_ATTR                       6: file_id
                        106     CALL                            2
                        114     LOAD_GLOBAL                     3: NULL + struct
                        124     LOAD_ATTR                       4: pack
                        144     LOAD_CONST                      7: '<i'
                        146     LOAD_FAST                       0: self
                        148     LOAD_ATTR                       8: file_part
                        168     CALL                            2
                        176     LOAD_FAST                       0: self
                        178     LOAD_ATTR                       11: serialize_bytes
                        198     LOAD_FAST                       0: self
                        200     LOAD_ATTR                       12: bytes
                        220     CALL                            1
                        228     BUILD_TUPLE                     4
                        230     CALL                            1
                        238     NOP                             
                        240     NOP                             
                        242     NOP                             
                        244     JUMP_FORWARD                    20 (to 286)
                        246     CALL                            1
                        254     POP_TOP                         
                        256     RETURN_VALUE                    
                        258     PUSH_EXC_INFO                   
                        260     PUSH_NULL                       
                        262     LOAD_CONST                      8: '__pyarmor_exit_36869__'
                        264     NOP                             
                        266     LOAD_CONST                      3: b'<COAddr>\x07\x00\x00\x1a\xe8\x00\x00\x00\x00\x00\x00\x00\x00\x00\x00\x00\x00\x00\x00\x00'
                        268     CALL                            1
                        276     POP_TOP                         
                        278     RERAISE                         0
                        280     COPY                            3
                        282     POP_EXCEPT                      
                        284     RERAISE                         1
                        286     PUSH_NULL                       
                        288     LOAD_CONST                      8: '__pyarmor_exit_36869__'
                        290     LOAD_CONST                      3: b'<COAddr>\x07\x00\x00\x1a\xe8\x00\x00\x00\x00\x00\x00\x00\x00\x00\x00\x00\x00\x00\x00\x00'
                        292     BUILD_TUPLE                     1
                        294     CALL_FUNCTION_EX                0
                        296     POP_TOP                         
                        298     RETURN_VALUE                    
                    [Exception Table]
                        28 to 238 -> 258 [0] 
                        258 to 280 -> 280 [1] lasti
                [Code]
                    File Name: <frozen multithon.tl.functions.upload>
                    Object Name: from_reader
                    Qualified Name: SaveFilePartRequest.from_reader
                    Arg Count: 2
                    Pos Only Arg Count: 0
                    KW Only Arg Count: 0
                    Stack Size: 5
                    Flags: 0x20000003 (CO_OPTIMIZED | CO_NEWLOCALS | CO_PYARMOR_OBFUSCATED)
                    [Names]
                        'read_long'
                        'read_int'
                        'tgread_bytes'
                    [Locals+Names]
                        'cls'
                        'reader'
                        '__assert_armored__'
                        '_var_var_8'
                        '_var_var_9'
                        '_var_var_11'
                    [Constants]
                        None
                        '__pyarmor_assert_36870__'
                        '__pyarmor_enter_36871__'
                        b'<COAddr>\x07\x00\x00\x1a\x8a\x00\x00\x00\x00\x00\x00\x00\x00\x00\x00\x00\x00\x00\x00\x00'
                        (
                            'file_id'
                            'file_part'
                            'bytes'
                        )
                        '__pyarmor_exit_36872__'
                    [Disassembly]
                        0       NOP                             
                        2       NOP                             
                        4       PUSH_NULL                       
                        6       LOAD_CONST                      2: '__pyarmor_enter_36871__'
                        8       LOAD_CONST                      3: b'<COAddr>\x07\x00\x00\x1a\x8a\x00\x00\x00\x00\x00\x00\x00\x00\x00\x00\x00\x00\x00\x00\x00'
                        10      BUILD_TUPLE                     1
                        12      CALL_FUNCTION_EX                0
                        14      POP_TOP                         
                        16      RESUME                          0
                        18      NOP                             
                        20      NOP                             
                        22      NOP                             
                        24      NOP                             
                        26      NOP                             
                        28      LOAD_FAST                       1: reader
                        30      LOAD_ATTR                       1: read_long
                        50      CALL                            0
                        58      STORE_FAST                      3: _var_var_8
                        60      LOAD_FAST                       1: reader
                        62      LOAD_ATTR                       3: read_int
                        82      CALL                            0
                        90      STORE_FAST                      4: _var_var_9
                        92      LOAD_FAST                       1: reader
                        94      LOAD_ATTR                       5: tgread_bytes
                        114     CALL                            0
                        122     STORE_FAST                      5: _var_var_11
                        124     PUSH_NULL                       
                        126     LOAD_FAST                       0: cls
                        128     LOAD_FAST                       3: _var_var_8
                        130     LOAD_FAST                       4: _var_var_9
                        132     LOAD_FAST                       5: _var_var_11
                        134     KW_NAMES                        4: ('file_id', 'file_part', 'bytes')
                        136     CALL                            3
                        144     NOP                             
                        146     NOP                             
                        148     NOP                             
                        150     JUMP_FORWARD                    20 (to 192)
                        152     CALL                            1
                        160     POP_TOP                         
                        162     RETURN_VALUE                    
                        164     PUSH_EXC_INFO                   
                        166     PUSH_NULL                       
                        168     LOAD_CONST                      5: '__pyarmor_exit_36872__'
                        170     NOP                             
                        172     LOAD_CONST                      3: b'<COAddr>\x07\x00\x00\x1a\x8a\x00\x00\x00\x00\x00\x00\x00\x00\x00\x00\x00\x00\x00\x00\x00'
                        174     CALL                            1
                        182     POP_TOP                         
                        184     RERAISE                         0
                        186     COPY                            3
                        188     POP_EXCEPT                      
                        190     RERAISE                         1
                        192     PUSH_NULL                       
                        194     LOAD_CONST                      5: '__pyarmor_exit_36872__'
                        196     LOAD_CONST                      3: b'<COAddr>\x07\x00\x00\x1a\x8a\x00\x00\x00\x00\x00\x00\x00\x00\x00\x00\x00\x00\x00\x00\x00'
                        198     BUILD_TUPLE                     1
                        200     CALL_FUNCTION_EX                0
                        202     POP_TOP                         
                        204     RETURN_VALUE                    
                    [Exception Table]
                        28 to 144 -> 164 [0] 
                        164 to 186 -> 186 [1] lasti
                '__pyarmor_exit_36860__'
                None
            [Disassembly]
                0       NOP                             
                2       LOAD_NAME                       0: __name__
                4       STORE_NAME                      1: __module__
                6       LOAD_CONST                      0: 'SaveFilePartRequest'
                8       STORE_NAME                      2: __qualname__
                10      NOP                             
                12      PUSH_NULL                       
                14      LOAD_CONST                      2: '__pyarmor_enter_36859__'
                16      LOAD_CONST                      3: b'<COAddr>\x07\x00\x00"N\x00\x00\x00\x00\x00\x00\x00\x00\x00\x00\x00\x00\x00\x00\x00'
                18      BUILD_TUPLE                     1
                20      CALL_FUNCTION_EX                0
                22      POP_TOP                         
                24      RESUME                          0
                26      NOP                             
                28      NOP                             
                30      NOP                             
                32      NOP                             
                34      NOP                             
                36      LOAD_CONST                      4: 0xB304A621
                38      STORE_NAME                      4: CONSTRUCTOR_ID
                40      LOAD_CONST                      5: 0xF5B399AC
                42      STORE_NAME                      5: SUBCLASS_OF_ID
                44      LOAD_CONST                      6: 'file_id'
                46      LOAD_NAME                       6: int
                48      LOAD_CONST                      7: 'file_part'
                50      LOAD_NAME                       6: int
                52      LOAD_CONST                      8: 'bytes'
                54      LOAD_NAME                       7: bytes
                56      BUILD_TUPLE                     6
                58      LOAD_CONST                      9: <CODE> __init__
                60      MAKE_FUNCTION                   4
                62      STORE_NAME                      8: __init__
                64      LOAD_CONST                      10: <CODE> to_dict
                66      MAKE_FUNCTION                   0
                68      STORE_NAME                      9: to_dict
                70      LOAD_CONST                      11: <CODE> _bytes
                72      MAKE_FUNCTION                   0
                74      STORE_NAME                      10: _bytes
                76      LOAD_NAME                       11: classmethod
                78      LOAD_CONST                      12: <CODE> from_reader
                80      MAKE_FUNCTION                   0
                82      CALL                            0
                90      STORE_NAME                      12: from_reader
                92      LOAD_CONST                      14: None
                94      NOP                             
                96      NOP                             
                98      NOP                             
                100     JUMP_FORWARD                    19 (to 140)
                108     POP_TOP                         
                110     RETURN_CONST                    14: None
                112     PUSH_EXC_INFO                   
                114     PUSH_NULL                       
                116     LOAD_CONST                      13: '__pyarmor_exit_36860__'
                118     NOP                             
                120     LOAD_CONST                      3: b'<COAddr>\x07\x00\x00"N\x00\x00\x00\x00\x00\x00\x00\x00\x00\x00\x00\x00\x00\x00\x00'
                122     CALL                            1
                130     POP_TOP                         
                132     RERAISE                         0
                134     COPY                            3
                136     POP_EXCEPT                      
                138     RERAISE                         1
                140     PUSH_NULL                       
                142     LOAD_CONST                      13: '__pyarmor_exit_36860__'
                144     LOAD_CONST                      3: b'<COAddr>\x07\x00\x00"N\x00\x00\x00\x00\x00\x00\x00\x00\x00\x00\x00\x00\x00\x00\x00'
                146     BUILD_TUPLE                     1
                148     CALL_FUNCTION_EX                0
                150     POP_TOP                         
                152     RETURN_VALUE                    
            [Exception Table]
                36 to 92 -> 112 [0] 
                112 to 134 -> 134 [1] lasti
        'SaveFilePartRequest'
        '__pyarmor_exit_36752__'
    [Disassembly]
        0       NOP                             
        2       NOP                             
        4       PUSH_NULL                       
        6       LOAD_CONST                      1: '__pyarmor_enter_36751__'
        8       LOAD_CONST                      2: b'<COAddr>\x07\x00\x00\x1a4\x01\x00\x00\x00\x00\x00\x00\x00\x00\x00\x00\x00\x00\x00\x00'
        10      BUILD_TUPLE                     1
        12      CALL_FUNCTION_EX                0
        14      POP_TOP                         
        16      RESUME                          0
        18      NOP                             
        20      NOP                             
        22      NOP                             
        24      NOP                             
        26      PUSH_NULL                       
        28      LOAD_CONST                      0: '__pyarmor_assert_36750__'
        30      LOAD_CONST                      3: "File generated by TLObjects' generator. All changes will be ERASED"   # b'\x81\xc4\x11\x1f6\xba\xb9\xd7\x15\xff\x1f\xc1x\xe9\xfc\xc5\rD\xfb\x93\x86\xe4L\xc6\x00l\xb7OG\xf1\x19\xe04W2\x0c\x8c\xc5\xa6`X\xc8\xf4Q\x9d\xdb\x07F9\xeaS\xe8\xc7g\x0f\xe1;\xab\x99\x18Xn\x03rdm!'
        32      CALL                            1
        40      POP_TOP                         
        42      LOAD_CONST                      4: 3
        44      LOAD_CONST                      5: ('TLObject',)
        46      IMPORT_NAME                     1: tl.tlobject
        48      IMPORT_FROM                     2: TLObject
        50      STORE_NAME                      2: TLObject
        52      POP_TOP                         
        54      LOAD_CONST                      4: 3
        56      LOAD_CONST                      6: ('TLRequest',)
        58      IMPORT_NAME                     1: tl.tlobject
        60      IMPORT_FROM                     3: TLRequest
        62      STORE_NAME                      3: TLRequest
        64      POP_TOP                         
        66      LOAD_CONST                      7: 0
        68      LOAD_CONST                      8: ('Optional', 'List', 'Union', 'TYPE_CHECKING')
        70      IMPORT_NAME                     4: typing
        72      IMPORT_FROM                     5: Optional
        74      STORE_NAME                      5: Optional
        76      IMPORT_FROM                     6: List
        78      STORE_NAME                      6: List
        80      IMPORT_FROM                     7: Union
        82      STORE_NAME                      7: Union
        84      IMPORT_FROM                     8: TYPE_CHECKING
        86      STORE_NAME                      8: TYPE_CHECKING
        88      POP_TOP                         
        90      LOAD_CONST                      7: 0
        92      LOAD_CONST                      9: None
        94      IMPORT_NAME                     9: os
        96      STORE_NAME                      9: os
        98      LOAD_CONST                      7: 0
        100     LOAD_CONST                      9: None
        102     IMPORT_NAME                     10: struct
        104     STORE_NAME                      10: struct
        106     LOAD_CONST                      7: 0
        108     LOAD_CONST                      10: ('datetime',)
        110     IMPORT_NAME                     11: datetime
        112     IMPORT_FROM                     11: datetime
        114     STORE_NAME                      11: datetime
        116     POP_TOP                         
        118     LOAD_NAME                       8: TYPE_CHECKING
        120     POP_JUMP_IF_FALSE               8 (to 138)
        122     LOAD_CONST                      4: 3
        124     LOAD_CONST                      11: ('TypeInputFileLocation', 'TypeInputWebFileLocation')
        126     IMPORT_NAME                     12: tl.types
        128     IMPORT_FROM                     13: TypeInputFileLocation
        130     STORE_NAME                      13: TypeInputFileLocation
        132     IMPORT_FROM                     14: TypeInputWebFileLocation
        134     STORE_NAME                      14: TypeInputWebFileLocation
        136     POP_TOP                         
        138     PUSH_NULL                       
        140     LOAD_BUILD_CLASS                
        142     LOAD_CONST                      12: <CODE> GetCdnFileRequest
        144     MAKE_FUNCTION                   0
        146     LOAD_CONST                      13: 'GetCdnFileRequest'
        148     LOAD_NAME                       3: TLRequest
        150     CALL                            3
        158     STORE_NAME                      15: GetCdnFileRequest
        160     PUSH_NULL                       
        162     LOAD_BUILD_CLASS                
        164     LOAD_CONST                      14: <CODE> GetCdnFileHashesRequest
        166     MAKE_FUNCTION                   0
        168     LOAD_CONST                      15: 'GetCdnFileHashesRequest'
        170     LOAD_NAME                       3: TLRequest
        172     CALL                            3
        180     STORE_NAME                      16: GetCdnFileHashesRequest
        182     PUSH_NULL                       
        184     LOAD_BUILD_CLASS                
        186     LOAD_CONST                      16: <CODE> GetFileRequest
        188     MAKE_FUNCTION                   0
        190     LOAD_CONST                      17: 'GetFileRequest'
        192     LOAD_NAME                       3: TLRequest
        194     CALL                            3
        202     STORE_NAME                      17: GetFileRequest
        204     PUSH_NULL                       
        206     LOAD_BUILD_CLASS                
        208     LOAD_CONST                      18: <CODE> GetFileHashesRequest
        210     MAKE_FUNCTION                   0
        212     LOAD_CONST                      19: 'GetFileHashesRequest'
        214     LOAD_NAME                       3: TLRequest
        216     CALL                            3
        224     STORE_NAME                      18: GetFileHashesRequest
        226     PUSH_NULL                       
        228     LOAD_BUILD_CLASS                
        230     LOAD_CONST                      20: <CODE> GetWebFileRequest
        232     MAKE_FUNCTION                   0
        234     LOAD_CONST                      21: 'GetWebFileRequest'
        236     LOAD_NAME                       3: TLRequest
        238     CALL                            3
        246     STORE_NAME                      19: GetWebFileRequest
        248     PUSH_NULL                       
        250     LOAD_BUILD_CLASS                
        252     LOAD_CONST                      22: <CODE> ReuploadCdnFileRequest
        254     MAKE_FUNCTION                   0
        256     LOAD_CONST                      23: 'ReuploadCdnFileRequest'
        258     LOAD_NAME                       3: TLRequest
        260     CALL                            3
        268     STORE_NAME                      20: ReuploadCdnFileRequest
        270     PUSH_NULL                       
        272     LOAD_BUILD_CLASS                
        274     LOAD_CONST                      24: <CODE> SaveBigFilePartRequest
        276     MAKE_FUNCTION                   0
        278     LOAD_CONST                      25: 'SaveBigFilePartRequest'
        280     LOAD_NAME                       3: TLRequest
        282     CALL                            3
        290     STORE_NAME                      21: SaveBigFilePartRequest
        292     PUSH_NULL                       
        294     LOAD_BUILD_CLASS                
        296     LOAD_CONST                      26: <CODE> SaveFilePartRequest
        298     MAKE_FUNCTION                   0
        300     LOAD_CONST                      27: 'SaveFilePartRequest'
        302     LOAD_NAME                       3: TLRequest
        304     CALL                            3
        312     STORE_NAME                      22: SaveFilePartRequest
        314     LOAD_CONST                      9: None
        316     NOP                             
        318     NOP                             
        320     NOP                             
        322     JUMP_FORWARD                    19 (to 362)
        330     POP_TOP                         
        332     RETURN_CONST                    9: None
        334     PUSH_EXC_INFO                   
        336     PUSH_NULL                       
        338     LOAD_CONST                      28: '__pyarmor_exit_36752__'
        340     NOP                             
        342     LOAD_CONST                      2: b'<COAddr>\x07\x00\x00\x1a4\x01\x00\x00\x00\x00\x00\x00\x00\x00\x00\x00\x00\x00\x00\x00'
        344     CALL                            1
        352     POP_TOP                         
        354     RERAISE                         0
        356     COPY                            3
        358     POP_EXCEPT                      
        360     RERAISE                         1
        362     PUSH_NULL                       
        364     LOAD_CONST                      28: '__pyarmor_exit_36752__'
        366     LOAD_CONST                      2: b'<COAddr>\x07\x00\x00\x1a4\x01\x00\x00\x00\x00\x00\x00\x00\x00\x00\x00\x00\x00\x00\x00'
        368     BUILD_TUPLE                     1
        370     CALL_FUNCTION_EX                0
        372     POP_TOP                         
        374     RETURN_VALUE                    
    [Exception Table]
        26 to 314 -> 334 [0] 
        334 to 356 -> 356 [1] lasti
