#decoded by lolz.live/mrpenny / t.me/zeus_jackpot
# ================================
# Примечания по Pyarmor:
# - Байт-код и объекты кода Pyarmor соответствуют стандартному Python, но присутствуют специальные вызовы функций среды выполнения (runtime) Pyarmor.
# - Вызовы строк — это не ошибки, а маркеры, которые обрабатываются Pyarmor во время выполнения.
#
# Руководство по декомпиляции (без среды выполнения):
# 1. Игнорируйте зашифрованные байты после `#`; используйте только строку до `#`.
# 2. Удалите "__pyarmor_enter_xxx__"(b"<COAddr>...") и "__pyarmor_leave_xxx__"(b"<COAddr>...") (пролог/эпилог).
# 3. "__pyarmor_assert_xxx__"(A) не является настоящим оператором assert.
#    - Если A — это имя или читаемая строка: замените на A.
#    - Если A — это (X, "Y"): замените на X.Y.
#    - Если A — это (X, "Y", Z): замените на X.Y = Z.
#    - В противном случае: выберите наиболее подходящую/логичную замену.
# 4. "__pyarmor_bcc_xxx__"(...) указывает на машинный (нативный) код; тело функции недоступно. Добавьте комментарий.
# ================================

[Code]
    File Name: <frozen multithon.tl.functions.users>
    Object Name: <module>
    Qualified Name: <module>
    Arg Count: 0
    Pos Only Arg Count: 0
    KW Only Arg Count: 0
    Stack Size: 5
    Flags: 0x20000000 (CO_PYARMOR_OBFUSCATED)
    [Names]
        '__assert_armored__'
        'tl.tlobject'
        'TLObject'
        'TLRequest'
        'typing'
        'Optional'
        'List'
        'Union'
        'TYPE_CHECKING'
        'os'
        'struct'
        'datetime'
        'tl.types'
        'TypeInputUser'
        'TypeSecureValueError'
        'GetFullUserRequest'
        'GetRequirementsToContactRequest'
        'GetIsPremiumRequiredToContactRequest'
        'GetUsersRequest'
        'SetSecureValueErrorsRequest'
    [Locals+Names]
    [Constants]
        '__pyarmor_assert_36873__'
        '__pyarmor_enter_36874__'
        b'<COAddr>\x05\x00\x00\x1a\xf2\x00\x00\x00\x00\x00\x00\x00\x00\x00\x00\x00\x00\x00\x00\x00'
        "File generated by TLObjects' generator. All changes will be ERASED"   # b'\x81\xc4\x11\x1f6\xba\xb9\xd7\x15\xff\x1f\xc1x\xe9\xfc\xc5\rD\xfb\x93\x86\xe4L\xc6\x00l\xb7OG\xf1\x19\xe04W2\x0c\x8c\xc5\xa6`X\xc8\xf4Q\x9d\xdb\x07F9\xeaS\xe8\xc7g\x0f\xe1;\xab\x99\x18Xn\x03rdm!'
        3
        (
            'TLObject'
        )
        (
            'TLRequest'
        )
        0
        (
            'Optional'
            'List'
            'Union'
            'TYPE_CHECKING'
        )
        None
        (
            'datetime'
        )
        (
            'TypeInputUser'
            'TypeSecureValueError'
        )
        [Code]
            File Name: <frozen multithon.tl.functions.users>
            Object Name: GetFullUserRequest
            Qualified Name: GetFullUserRequest
            Arg Count: 0
            Pos Only Arg Count: 0
            KW Only Arg Count: 0
            Stack Size: 5
            Flags: 0x20000000 (CO_PYARMOR_OBFUSCATED)
            [Names]
                '__name__'
                '__module__'
                '__qualname__'
                '__assert_armored__'
                'CONSTRUCTOR_ID'
                'SUBCLASS_OF_ID'
                '__init__'
                'resolve'
                'to_dict'
                '_bytes'
                'classmethod'
                'from_reader'
            [Locals+Names]
            [Constants]
                'GetFullUserRequest'
                '__pyarmor_assert_36876__'
                '__pyarmor_enter_36877__'
                b'<COAddr>\x07\x00\x00"X\x00\x00\x00\x00\x00\x00\x00\x00\x00\x00\x00\x00\x00\x00\x00'
                0xB60F5918
                0x83DF9DF5
                'id'
                'TypeInputUser'   # b'\x81\xd6\x01\x036\xd3\xb0\xc2\x0e\xee8\xd3i\xfe'
                [Code]
                    File Name: <frozen multithon.tl.functions.users>
                    Object Name: __init__
                    Qualified Name: GetFullUserRequest.__init__
                    Arg Count: 2
                    Pos Only Arg Count: 0
                    KW Only Arg Count: 0
                    Stack Size: 5
                    Flags: 0x20000003 (CO_OPTIMIZED | CO_NEWLOCALS | CO_PYARMOR_OBFUSCATED)
                    [Names]
                        'id'
                    [Locals+Names]
                        'self'
                        'id'
                        '__assert_armored__'
                    [Constants]
                        '\n        :returns users.UserFull: Instance of UserFull.\n        '
                        '__pyarmor_assert_36879__'
                        '__pyarmor_enter_36880__'
                        b'<COAddr>\x05\x00\x00\x1a$\x00\x00\x00\x00\x00\x00\x00\x00\x00\x00\x00\x00\x00\x00\x00'
                        '__pyarmor_exit_36881__'
                        None
                    [Disassembly]
                        0       NOP                             
                        2       NOP                             
                        4       PUSH_NULL                       
                        6       LOAD_CONST                      2: '__pyarmor_enter_36880__'
                        8       LOAD_CONST                      3: b'<COAddr>\x05\x00\x00\x1a$\x00\x00\x00\x00\x00\x00\x00\x00\x00\x00\x00\x00\x00\x00\x00'
                        10      BUILD_TUPLE                     1
                        12      CALL_FUNCTION_EX                0
                        14      POP_TOP                         
                        16      RESUME                          0
                        18      NOP                             
                        20      NOP                             
                        22      NOP                             
                        24      NOP                             
                        26      NOP                             
                        28      LOAD_FAST                       1: id
                        30      LOAD_FAST                       0: self
                        32      STORE_ATTR                      0: id
                        42      LOAD_CONST                      5: None
                        44      NOP                             
                        46      NOP                             
                        48      NOP                             
                        50      JUMP_FORWARD                    19 (to 90)
                        58      POP_TOP                         
                        60      RETURN_CONST                    5: None
                        62      PUSH_EXC_INFO                   
                        64      PUSH_NULL                       
                        66      LOAD_CONST                      4: '__pyarmor_exit_36881__'
                        68      NOP                             
                        70      LOAD_CONST                      3: b'<COAddr>\x05\x00\x00\x1a$\x00\x00\x00\x00\x00\x00\x00\x00\x00\x00\x00\x00\x00\x00\x00'
                        72      CALL                            1
                        80      POP_TOP                         
                        82      RERAISE                         0
                        84      COPY                            3
                        86      POP_EXCEPT                      
                        88      RERAISE                         1
                        90      PUSH_NULL                       
                        92      LOAD_CONST                      4: '__pyarmor_exit_36881__'
                        94      LOAD_CONST                      3: b'<COAddr>\x05\x00\x00\x1a$\x00\x00\x00\x00\x00\x00\x00\x00\x00\x00\x00\x00\x00\x00\x00'
                        96      BUILD_TUPLE                     1
                        98      CALL_FUNCTION_EX                0
                        100     POP_TOP                         
                        102     RETURN_VALUE                    
                    [Exception Table]
                        28 to 42 -> 62 [0] 
                        62 to 84 -> 84 [1] lasti
                [Code]
                    File Name: <frozen multithon.tl.functions.users>
                    Object Name: resolve
                    Qualified Name: GetFullUserRequest.resolve
                    Arg Count: 3
                    Pos Only Arg Count: 0
                    KW Only Arg Count: 0
                    Stack Size: 5
                    Flags: 0x20000083 (CO_OPTIMIZED | CO_NEWLOCALS | CO_COROUTINE | CO_PYARMOR_OBFUSCATED)
                    [Names]
                        'get_input_user'
                        'get_input_entity'
                        'id'
                    [Locals+Names]
                        'self'
                        'client'
                        'utils'
                        '__assert_armored__'
                    [Constants]
                        None
                        '__pyarmor_assert_36882__'
                        '__pyarmor_enter_36883__'
                        b'<COAddr>\x05\x00\x00\x1e\x88\x00\x00\x00\x00\x00\x00\x00\x00\x00\x00\x00\x00\x00\x00\x00'
                        '__pyarmor_exit_36884__'
                    [Disassembly]
                        0       RETURN_GENERATOR                
                        2       POP_TOP                         
                        4       NOP                             
                        6       NOP                             
                        8       PUSH_NULL                       
                        10      LOAD_CONST                      2: '__pyarmor_enter_36883__'
                        12      LOAD_CONST                      3: b'<COAddr>\x05\x00\x00\x1e\x88\x00\x00\x00\x00\x00\x00\x00\x00\x00\x00\x00\x00\x00\x00\x00'
                        14      BUILD_TUPLE                     1
                        16      CALL_FUNCTION_EX                0
                        18      POP_TOP                         
                        20      RESUME                          0
                        22      NOP                             
                        24      NOP                             
                        26      NOP                             
                        28      NOP                             
                        30      NOP                             
                        32      LOAD_FAST                       2: utils
                        34      LOAD_ATTR                       1: get_input_user
                        54      LOAD_FAST                       1: client
                        56      LOAD_ATTR                       3: get_input_entity
                        76      LOAD_FAST                       0: self
                        78      LOAD_ATTR                       4: id
                        98      CALL                            1
                        106     GET_AWAITABLE                   0
                        108     LOAD_CONST                      0: None
                        110     SEND                            3 (to 118)
                        114     YIELD_VALUE                     3
                        116     RESUME                          3
                        118     JUMP_BACKWARD_NO_INTERRUPT      5 (to 110)
                        120     END_SEND                        
                        122     CALL                            1
                        130     LOAD_FAST                       0: self
                        132     STORE_ATTR                      2: id
                        142     LOAD_CONST                      0: None
                        144     NOP                             
                        146     NOP                             
                        148     NOP                             
                        150     JUMP_FORWARD                    23 (to 198)
                        158     POP_TOP                         
                        160     RETURN_CONST                    0: None
                        162     CLEANUP_THROW                   
                        164     JUMP_BACKWARD                   23 (to 120)
                        166     PUSH_EXC_INFO                   
                        168     PUSH_NULL                       
                        170     LOAD_CONST                      4: '__pyarmor_exit_36884__'
                        172     NOP                             
                        174     LOAD_CONST                      3: b'<COAddr>\x05\x00\x00\x1e\x88\x00\x00\x00\x00\x00\x00\x00\x00\x00\x00\x00\x00\x00\x00\x00'
                        176     CALL                            1
                        184     POP_TOP                         
                        186     RERAISE                         0
                        188     COPY                            3
                        190     POP_EXCEPT                      
                        192     RERAISE                         1
                        194     CALL_INTRINSIC_1                3 (INTRINSIC_STOPITERATION_ERROR)
                        196     RERAISE                         1
                        198     PUSH_NULL                       
                        200     LOAD_CONST                      4: '__pyarmor_exit_36884__'
                        202     LOAD_CONST                      3: b'<COAddr>\x05\x00\x00\x1e\x88\x00\x00\x00\x00\x00\x00\x00\x00\x00\x00\x00\x00\x00\x00\x00'
                        204     BUILD_TUPLE                     1
                        206     CALL_FUNCTION_EX                0
                        208     POP_TOP                         
                        210     RETURN_VALUE                    
                    [Exception Table]
                        4 to 30 -> 194 [0] lasti
                        32 to 114 -> 166 [0] 
                        114 to 116 -> 162 [4] 
                        116 to 142 -> 166 [0] 
                        142 to 162 -> 194 [0] lasti
                        162 to 164 -> 166 [0] 
                        166 to 188 -> 188 [1] lasti
                        188 to 194 -> 194 [0] lasti
                [Code]
                    File Name: <frozen multithon.tl.functions.users>
                    Object Name: to_dict
                    Qualified Name: GetFullUserRequest.to_dict
                    Arg Count: 1
                    Pos Only Arg Count: 0
                    KW Only Arg Count: 0
                    Stack Size: 5
                    Flags: 0x20000003 (CO_OPTIMIZED | CO_NEWLOCALS | CO_PYARMOR_OBFUSCATED)
                    [Names]
                        'isinstance'
                        'id'
                        'TLObject'
                        'to_dict'
                    [Locals+Names]
                        'self'
                        '__assert_armored__'
                    [Constants]
                        None
                        '__pyarmor_assert_36885__'
                        '__pyarmor_enter_36886__'
                        b'<COAddr>\x05\x00\x00\x1a\xa6\x00\x00\x00\x00\x00\x00\x00\x00\x00\x00\x00\x00\x00\x00\x00'
                        'GetFullUserRequest'   # b'\x81\xc5\x1d\x07\x15\xef\xb2\xde.\xe9\x08\xd2^\xe9\xe9\x90\nN\xaf'
                        (
                            '_'
                            'id'
                        )
                        '__pyarmor_exit_36887__'
                    [Disassembly]
                        0       NOP                             
                        2       NOP                             
                        4       PUSH_NULL                       
                        6       LOAD_CONST                      2: '__pyarmor_enter_36886__'
                        8       LOAD_CONST                      3: b'<COAddr>\x05\x00\x00\x1a\xa6\x00\x00\x00\x00\x00\x00\x00\x00\x00\x00\x00\x00\x00\x00\x00'
                        10      BUILD_TUPLE                     1
                        12      CALL_FUNCTION_EX                0
                        14      POP_TOP                         
                        16      RESUME                          0
                        18      NOP                             
                        20      NOP                             
                        22      NOP                             
                        24      NOP                             
                        26      NOP                             
                        28      PUSH_NULL                       
                        30      LOAD_CONST                      1: '__pyarmor_assert_36885__'
                        32      LOAD_CONST                      4: 'GetFullUserRequest'   # b'\x81\xc5\x1d\x07\x15\xef\xb2\xde.\xe9\x08\xd2^\xe9\xe9\x90\nN\xaf'
                        34      CALL                            1
                        42      LOAD_GLOBAL                     1: NULL + isinstance
                        52      LOAD_FAST                       0: self
                        54      LOAD_ATTR                       2: id
                        74      LOAD_GLOBAL                     4: TLObject
                        84      CALL                            2
                        92      POP_JUMP_IF_FALSE               26 (to 146)
                        94      LOAD_FAST                       0: self
                        96      LOAD_ATTR                       2: id
                        116     LOAD_ATTR                       7: to_dict
                        136     CALL                            0
                        144     JUMP_FORWARD                    11 (to 168)
                        146     LOAD_FAST                       0: self
                        148     LOAD_ATTR                       2: id
                        168     LOAD_CONST                      5: ('_', 'id')
                        170     BUILD_CONST_KEY_MAP             2
                        172     NOP                             
                        174     NOP                             
                        176     NOP                             
                        178     JUMP_FORWARD                    20 (to 220)
                        180     CALL                            1
                        188     POP_TOP                         
                        190     RETURN_VALUE                    
                        192     PUSH_EXC_INFO                   
                        194     PUSH_NULL                       
                        196     LOAD_CONST                      6: '__pyarmor_exit_36887__'
                        198     NOP                             
                        200     LOAD_CONST                      3: b'<COAddr>\x05\x00\x00\x1a\xa6\x00\x00\x00\x00\x00\x00\x00\x00\x00\x00\x00\x00\x00\x00\x00'
                        202     CALL                            1
                        210     POP_TOP                         
                        212     RERAISE                         0
                        214     COPY                            3
                        216     POP_EXCEPT                      
                        218     RERAISE                         1
                        220     PUSH_NULL                       
                        222     LOAD_CONST                      6: '__pyarmor_exit_36887__'
                        224     LOAD_CONST                      3: b'<COAddr>\x05\x00\x00\x1a\xa6\x00\x00\x00\x00\x00\x00\x00\x00\x00\x00\x00\x00\x00\x00\x00'
                        226     BUILD_TUPLE                     1
                        228     CALL_FUNCTION_EX                0
                        230     POP_TOP                         
                        232     RETURN_VALUE                    
                    [Exception Table]
                        28 to 172 -> 192 [0] 
                        192 to 214 -> 214 [1] lasti
                [Code]
                    File Name: <frozen multithon.tl.functions.users>
                    Object Name: _bytes
                    Qualified Name: GetFullUserRequest._bytes
                    Arg Count: 1
                    Pos Only Arg Count: 0
                    KW Only Arg Count: 0
                    Stack Size: 5
                    Flags: 0x20000003 (CO_OPTIMIZED | CO_NEWLOCALS | CO_PYARMOR_OBFUSCATED)
                    [Names]
                        'join'
                        'id'
                        '_bytes'
                    [Locals+Names]
                        'self'
                        '__assert_armored__'
                    [Constants]
                        None
                        '__pyarmor_assert_36888__'
                        '__pyarmor_enter_36889__'
                        b'<COAddr>\x07\x00\x00\x1aj\x00\x00\x00\x00\x00\x00\x00\x00\x00\x00\x00\x00\x00\x00\x00'
                        b''
                        b'\x18Y\x0f\xb6'
                        '__pyarmor_exit_36890__'
                    [Disassembly]
                        0       NOP                             
                        2       NOP                             
                        4       PUSH_NULL                       
                        6       LOAD_CONST                      2: '__pyarmor_enter_36889__'
                        8       LOAD_CONST                      3: b'<COAddr>\x07\x00\x00\x1aj\x00\x00\x00\x00\x00\x00\x00\x00\x00\x00\x00\x00\x00\x00\x00'
                        10      BUILD_TUPLE                     1
                        12      CALL_FUNCTION_EX                0
                        14      POP_TOP                         
                        16      RESUME                          0
                        18      NOP                             
                        20      NOP                             
                        22      NOP                             
                        24      NOP                             
                        26      NOP                             
                        28      LOAD_CONST                      4: b''
                        30      LOAD_ATTR                       1: join
                        50      LOAD_CONST                      5: b'\x18Y\x0f\xb6'
                        52      LOAD_FAST                       0: self
                        54      LOAD_ATTR                       2: id
                        74      LOAD_ATTR                       5: _bytes
                        94      CALL                            0
                        102     BUILD_TUPLE                     2
                        104     CALL                            1
                        112     NOP                             
                        114     NOP                             
                        116     NOP                             
                        118     JUMP_FORWARD                    20 (to 160)
                        120     CALL                            1
                        128     POP_TOP                         
                        130     RETURN_VALUE                    
                        132     PUSH_EXC_INFO                   
                        134     PUSH_NULL                       
                        136     LOAD_CONST                      6: '__pyarmor_exit_36890__'
                        138     NOP                             
                        140     LOAD_CONST                      3: b'<COAddr>\x07\x00\x00\x1aj\x00\x00\x00\x00\x00\x00\x00\x00\x00\x00\x00\x00\x00\x00\x00'
                        142     CALL                            1
                        150     POP_TOP                         
                        152     RERAISE                         0
                        154     COPY                            3
                        156     POP_EXCEPT                      
                        158     RERAISE                         1
                        160     PUSH_NULL                       
                        162     LOAD_CONST                      6: '__pyarmor_exit_36890__'
                        164     LOAD_CONST                      3: b'<COAddr>\x07\x00\x00\x1aj\x00\x00\x00\x00\x00\x00\x00\x00\x00\x00\x00\x00\x00\x00\x00'
                        166     BUILD_TUPLE                     1
                        168     CALL_FUNCTION_EX                0
                        170     POP_TOP                         
                        172     RETURN_VALUE                    
                    [Exception Table]
                        28 to 112 -> 132 [0] 
                        132 to 154 -> 154 [1] lasti
                [Code]
                    File Name: <frozen multithon.tl.functions.users>
                    Object Name: from_reader
                    Qualified Name: GetFullUserRequest.from_reader
                    Arg Count: 2
                    Pos Only Arg Count: 0
                    KW Only Arg Count: 0
                    Stack Size: 5
                    Flags: 0x20000003 (CO_OPTIMIZED | CO_NEWLOCALS | CO_PYARMOR_OBFUSCATED)
                    [Names]
                        'tgread_object'
                    [Locals+Names]
                        'cls'
                        'reader'
                        '__assert_armored__'
                        '_var_var_0'
                    [Constants]
                        None
                        '__pyarmor_assert_36891__'
                        '__pyarmor_enter_36892__'
                        b'<COAddr>\x05\x00\x00\x1aF\x00\x00\x00\x00\x00\x00\x00\x00\x00\x00\x00\x00\x00\x00\x00'
                        (
                            'id'
                        )
                        '__pyarmor_exit_36893__'
                    [Disassembly]
                        0       NOP                             
                        2       NOP                             
                        4       PUSH_NULL                       
                        6       LOAD_CONST                      2: '__pyarmor_enter_36892__'
                        8       LOAD_CONST                      3: b'<COAddr>\x05\x00\x00\x1aF\x00\x00\x00\x00\x00\x00\x00\x00\x00\x00\x00\x00\x00\x00\x00'
                        10      BUILD_TUPLE                     1
                        12      CALL_FUNCTION_EX                0
                        14      POP_TOP                         
                        16      RESUME                          0
                        18      NOP                             
                        20      NOP                             
                        22      NOP                             
                        24      NOP                             
                        26      NOP                             
                        28      LOAD_FAST                       1: reader
                        30      LOAD_ATTR                       1: tgread_object
                        50      CALL                            0
                        58      STORE_FAST                      3: _var_var_0
                        60      PUSH_NULL                       
                        62      LOAD_FAST                       0: cls
                        64      LOAD_FAST                       3: _var_var_0
                        66      KW_NAMES                        4: ('id',)
                        68      CALL                            1
                        76      NOP                             
                        78      NOP                             
                        80      NOP                             
                        82      JUMP_FORWARD                    20 (to 124)
                        84      CALL                            1
                        92      POP_TOP                         
                        94      RETURN_VALUE                    
                        96      PUSH_EXC_INFO                   
                        98      PUSH_NULL                       
                        100     LOAD_CONST                      5: '__pyarmor_exit_36893__'
                        102     NOP                             
                        104     LOAD_CONST                      3: b'<COAddr>\x05\x00\x00\x1aF\x00\x00\x00\x00\x00\x00\x00\x00\x00\x00\x00\x00\x00\x00\x00'
                        106     CALL                            1
                        114     POP_TOP                         
                        116     RERAISE                         0
                        118     COPY                            3
                        120     POP_EXCEPT                      
                        122     RERAISE                         1
                        124     PUSH_NULL                       
                        126     LOAD_CONST                      5: '__pyarmor_exit_36893__'
                        128     LOAD_CONST                      3: b'<COAddr>\x05\x00\x00\x1aF\x00\x00\x00\x00\x00\x00\x00\x00\x00\x00\x00\x00\x00\x00\x00'
                        130     BUILD_TUPLE                     1
                        132     CALL_FUNCTION_EX                0
                        134     POP_TOP                         
                        136     RETURN_VALUE                    
                    [Exception Table]
                        28 to 76 -> 96 [0] 
                        96 to 118 -> 118 [1] lasti
                '__pyarmor_exit_36878__'
                None
            [Disassembly]
                0       NOP                             
                2       LOAD_NAME                       0: __name__
                4       STORE_NAME                      1: __module__
                6       LOAD_CONST                      0: 'GetFullUserRequest'
                8       STORE_NAME                      2: __qualname__
                10      NOP                             
                12      PUSH_NULL                       
                14      LOAD_CONST                      2: '__pyarmor_enter_36877__'
                16      LOAD_CONST                      3: b'<COAddr>\x07\x00\x00"X\x00\x00\x00\x00\x00\x00\x00\x00\x00\x00\x00\x00\x00\x00\x00'
                18      BUILD_TUPLE                     1
                20      CALL_FUNCTION_EX                0
                22      POP_TOP                         
                24      RESUME                          0
                26      NOP                             
                28      NOP                             
                30      NOP                             
                32      NOP                             
                34      NOP                             
                36      LOAD_CONST                      4: 0xB60F5918
                38      STORE_NAME                      4: CONSTRUCTOR_ID
                40      LOAD_CONST                      5: 0x83DF9DF5
                42      STORE_NAME                      5: SUBCLASS_OF_ID
                44      LOAD_CONST                      6: 'id'
                46      PUSH_NULL                       
                48      LOAD_CONST                      1: '__pyarmor_assert_36876__'
                50      LOAD_CONST                      7: 'TypeInputUser'   # b'\x81\xd6\x01\x036\xd3\xb0\xc2\x0e\xee8\xd3i\xfe'
                52      CALL                            1
                60      BUILD_TUPLE                     2
                62      LOAD_CONST                      8: <CODE> __init__
                64      MAKE_FUNCTION                   4
                66      STORE_NAME                      6: __init__
                68      LOAD_CONST                      9: <CODE> resolve
                70      MAKE_FUNCTION                   0
                72      STORE_NAME                      7: resolve
                74      LOAD_CONST                      10: <CODE> to_dict
                76      MAKE_FUNCTION                   0
                78      STORE_NAME                      8: to_dict
                80      LOAD_CONST                      11: <CODE> _bytes
                82      MAKE_FUNCTION                   0
                84      STORE_NAME                      9: _bytes
                86      LOAD_NAME                       10: classmethod
                88      LOAD_CONST                      12: <CODE> from_reader
                90      MAKE_FUNCTION                   0
                92      CALL                            0
                100     STORE_NAME                      11: from_reader
                102     LOAD_CONST                      14: None
                104     NOP                             
                106     NOP                             
                108     NOP                             
                110     JUMP_FORWARD                    19 (to 150)
                118     POP_TOP                         
                120     RETURN_CONST                    14: None
                122     PUSH_EXC_INFO                   
                124     PUSH_NULL                       
                126     LOAD_CONST                      13: '__pyarmor_exit_36878__'
                128     NOP                             
                130     LOAD_CONST                      3: b'<COAddr>\x07\x00\x00"X\x00\x00\x00\x00\x00\x00\x00\x00\x00\x00\x00\x00\x00\x00\x00'
                132     CALL                            1
                140     POP_TOP                         
                142     RERAISE                         0
                144     COPY                            3
                146     POP_EXCEPT                      
                148     RERAISE                         1
                150     PUSH_NULL                       
                152     LOAD_CONST                      13: '__pyarmor_exit_36878__'
                154     LOAD_CONST                      3: b'<COAddr>\x07\x00\x00"X\x00\x00\x00\x00\x00\x00\x00\x00\x00\x00\x00\x00\x00\x00\x00'
                156     BUILD_TUPLE                     1
                158     CALL_FUNCTION_EX                0
                160     POP_TOP                         
                162     RETURN_VALUE                    
            [Exception Table]
                36 to 102 -> 122 [0] 
                122 to 144 -> 144 [1] lasti
        'GetFullUserRequest'
        [Code]
            File Name: <frozen multithon.tl.functions.users>
            Object Name: GetRequirementsToContactRequest
            Qualified Name: GetRequirementsToContactRequest
            Arg Count: 0
            Pos Only Arg Count: 0
            KW Only Arg Count: 0
            Stack Size: 5
            Flags: 0x20000000 (CO_PYARMOR_OBFUSCATED)
            [Names]
                '__name__'
                '__module__'
                '__qualname__'
                '__assert_armored__'
                'CONSTRUCTOR_ID'
                'SUBCLASS_OF_ID'
                'List'
                '__init__'
                'resolve'
                'to_dict'
                '_bytes'
                'classmethod'
                'from_reader'
            [Locals+Names]
            [Constants]
                'GetRequirementsToContactRequest'
                '__pyarmor_assert_36894__'
                '__pyarmor_enter_36895__'
                b'<COAddr>\x05\x00\x00"^\x00\x00\x00\x00\x00\x00\x00\x00\x00\x00\x00\x00\x00\x00\x00'
                0xD89A83A3
                841360323
                'id'
                'TypeInputUser'   # b'\x81\xd6\x01\x036\xd3\xb0\xc2\x0e\xee8\xd3i\xfe'
                [Code]
                    File Name: <frozen multithon.tl.functions.users>
                    Object Name: __init__
                    Qualified Name: GetRequirementsToContactRequest.__init__
                    Arg Count: 2
                    Pos Only Arg Count: 0
                    KW Only Arg Count: 0
                    Stack Size: 5
                    Flags: 0x20000003 (CO_OPTIMIZED | CO_NEWLOCALS | CO_PYARMOR_OBFUSCATED)
                    [Names]
                        'id'
                    [Locals+Names]
                        'self'
                        'id'
                        '__assert_armored__'
                    [Constants]
                        '\n        :returns Vector<RequirementToContact>: This type has no constructors.\n        '
                        '__pyarmor_assert_36897__'
                        '__pyarmor_enter_36898__'
                        b'<COAddr>\x07\x00\x00\x1a$\x00\x00\x00\x00\x00\x00\x00\x00\x00\x00\x00\x00\x00\x00\x00'
                        '__pyarmor_exit_36899__'
                        None
                    [Disassembly]
                        0       NOP                             
                        2       NOP                             
                        4       PUSH_NULL                       
                        6       LOAD_CONST                      2: '__pyarmor_enter_36898__'
                        8       LOAD_CONST                      3: b'<COAddr>\x07\x00\x00\x1a$\x00\x00\x00\x00\x00\x00\x00\x00\x00\x00\x00\x00\x00\x00\x00'
                        10      BUILD_TUPLE                     1
                        12      CALL_FUNCTION_EX                0
                        14      POP_TOP                         
                        16      RESUME                          0
                        18      NOP                             
                        20      NOP                             
                        22      NOP                             
                        24      NOP                             
                        26      NOP                             
                        28      LOAD_FAST                       1: id
                        30      LOAD_FAST                       0: self
                        32      STORE_ATTR                      0: id
                        42      LOAD_CONST                      5: None
                        44      NOP                             
                        46      NOP                             
                        48      NOP                             
                        50      JUMP_FORWARD                    19 (to 90)
                        58      POP_TOP                         
                        60      RETURN_CONST                    5: None
                        62      PUSH_EXC_INFO                   
                        64      PUSH_NULL                       
                        66      LOAD_CONST                      4: '__pyarmor_exit_36899__'
                        68      NOP                             
                        70      LOAD_CONST                      3: b'<COAddr>\x07\x00\x00\x1a$\x00\x00\x00\x00\x00\x00\x00\x00\x00\x00\x00\x00\x00\x00\x00'
                        72      CALL                            1
                        80      POP_TOP                         
                        82      RERAISE                         0
                        84      COPY                            3
                        86      POP_EXCEPT                      
                        88      RERAISE                         1
                        90      PUSH_NULL                       
                        92      LOAD_CONST                      4: '__pyarmor_exit_36899__'
                        94      LOAD_CONST                      3: b'<COAddr>\x07\x00\x00\x1a$\x00\x00\x00\x00\x00\x00\x00\x00\x00\x00\x00\x00\x00\x00\x00'
                        96      BUILD_TUPLE                     1
                        98      CALL_FUNCTION_EX                0
                        100     POP_TOP                         
                        102     RETURN_VALUE                    
                    [Exception Table]
                        28 to 42 -> 62 [0] 
                        62 to 84 -> 84 [1] lasti
                [Code]
                    File Name: <frozen multithon.tl.functions.users>
                    Object Name: resolve
                    Qualified Name: GetRequirementsToContactRequest.resolve
                    Arg Count: 3
                    Pos Only Arg Count: 0
                    KW Only Arg Count: 0
                    Stack Size: 8
                    Flags: 0x20000083 (CO_OPTIMIZED | CO_NEWLOCALS | CO_COROUTINE | CO_PYARMOR_OBFUSCATED)
                    [Names]
                        'id'
                        'append'
                        'get_input_user'
                        'get_input_entity'
                    [Locals+Names]
                        'self'
                        'client'
                        'utils'
                        '__assert_armored__'
                        '_var_var_1'
                        '_var_var_2'
                    [Constants]
                        None
                        '__pyarmor_assert_36900__'
                        '__pyarmor_enter_36901__'
                        b'<COAddr>\x05\x00\x00\x1e\xbc\x00\x00\x00\x00\x00\x00\x00\x00\x00\x00\x00\x00\x00\x00\x00'
                        '__pyarmor_exit_36902__'
                    [Disassembly]
                        0       RETURN_GENERATOR                
                        2       POP_TOP                         
                        4       NOP                             
                        6       NOP                             
                        8       PUSH_NULL                       
                        10      LOAD_CONST                      2: '__pyarmor_enter_36901__'
                        12      LOAD_CONST                      3: b'<COAddr>\x05\x00\x00\x1e\xbc\x00\x00\x00\x00\x00\x00\x00\x00\x00\x00\x00\x00\x00\x00\x00'
                        14      BUILD_TUPLE                     1
                        16      CALL_FUNCTION_EX                0
                        18      POP_TOP                         
                        20      RESUME                          0
                        22      NOP                             
                        24      NOP                             
                        26      NOP                             
                        28      NOP                             
                        30      NOP                             
                        32      BUILD_LIST                      0
                        34      STORE_FAST                      4: _var_var_1
                        36      LOAD_FAST                       0: self
                        38      LOAD_ATTR                       0: id
                        58      GET_ITER                        
                        60      FOR_ITER                        57 (to 176)
                        64      STORE_FAST                      5: _var_var_2
                        66      LOAD_FAST                       4: _var_var_1
                        68      LOAD_ATTR                       3: append
                        88      LOAD_FAST                       2: utils
                        90      LOAD_ATTR                       5: get_input_user
                        110     LOAD_FAST                       1: client
                        112     LOAD_ATTR                       7: get_input_entity
                        132     LOAD_FAST                       5: _var_var_2
                        134     CALL                            1
                        142     GET_AWAITABLE                   0
                        144     LOAD_CONST                      0: None
                        146     SEND                            3 (to 154)
                        150     YIELD_VALUE                     3
                        152     RESUME                          3
                        154     JUMP_BACKWARD_NO_INTERRUPT      5 (to 146)
                        156     END_SEND                        
                        158     CALL                            1
                        166     CALL                            1
                        174     POP_TOP                         
                        176     JUMP_BACKWARD                   59 (to 60)
                        178     END_FOR                         
                        180     LOAD_FAST                       4: _var_var_1
                        182     LOAD_FAST                       0: self
                        184     STORE_ATTR                      0: id
                        194     LOAD_CONST                      0: None
                        196     NOP                             
                        198     NOP                             
                        200     NOP                             
                        202     JUMP_FORWARD                    23 (to 250)
                        210     POP_TOP                         
                        212     RETURN_CONST                    0: None
                        214     CLEANUP_THROW                   
                        216     JUMP_BACKWARD                   31 (to 156)
                        218     PUSH_EXC_INFO                   
                        220     PUSH_NULL                       
                        222     LOAD_CONST                      4: '__pyarmor_exit_36902__'
                        224     NOP                             
                        226     LOAD_CONST                      3: b'<COAddr>\x05\x00\x00\x1e\xbc\x00\x00\x00\x00\x00\x00\x00\x00\x00\x00\x00\x00\x00\x00\x00'
                        228     CALL                            1
                        236     POP_TOP                         
                        238     RERAISE                         0
                        240     COPY                            3
                        242     POP_EXCEPT                      
                        244     RERAISE                         1
                        246     CALL_INTRINSIC_1                3 (INTRINSIC_STOPITERATION_ERROR)
                        248     RERAISE                         1
                        250     PUSH_NULL                       
                        252     LOAD_CONST                      4: '__pyarmor_exit_36902__'
                        254     LOAD_CONST                      3: b'<COAddr>\x05\x00\x00\x1e\xbc\x00\x00\x00\x00\x00\x00\x00\x00\x00\x00\x00\x00\x00\x00\x00'
                        256     BUILD_TUPLE                     1
                        258     CALL_FUNCTION_EX                0
                        260     POP_TOP                         
                        262     RETURN_VALUE                    
                    [Exception Table]
                        4 to 30 -> 246 [0] lasti
                        32 to 150 -> 218 [0] 
                        150 to 152 -> 214 [7] 
                        152 to 194 -> 218 [0] 
                        194 to 214 -> 246 [0] lasti
                        214 to 216 -> 218 [0] 
                        218 to 240 -> 240 [1] lasti
                        240 to 246 -> 246 [0] lasti
                [Code]
                    File Name: <frozen multithon.tl.functions.users>
                    Object Name: to_dict
                    Qualified Name: GetRequirementsToContactRequest.to_dict
                    Arg Count: 1
                    Pos Only Arg Count: 0
                    KW Only Arg Count: 0
                    Stack Size: 8
                    Flags: 0x20000003 (CO_OPTIMIZED | CO_NEWLOCALS | CO_PYARMOR_OBFUSCATED)
                    [Names]
                        'id'
                        'isinstance'
                        'TLObject'
                        'to_dict'
                    [Locals+Names]
                        'self'
                        '__assert_armored__'
                        '_var_var_3'
                    [Constants]
                        None
                        '__pyarmor_assert_36903__'
                        '__pyarmor_enter_36904__'
                        b'<COAddr>\x07\x00\x00\x1a\xc0\x00\x00\x00\x00\x00\x00\x00\x00\x00\x00\x00\x00\x00\x00\x00'
                        'GetRequirementsToContactRequest'   # b'\x81\xc5\x1d\x07\x01\xff\xaf\xc7\x12\xe8\x08\xcdi\xe2\xec\x96;R\x98\xa8\xa4\xdfO\xcf\x11]\xa6M\x15\xb4\r\xf1'
                        (
                            '_'
                            'id'
                        )
                        '__pyarmor_exit_36905__'
                    [Disassembly]
                        0       NOP                             
                        2       NOP                             
                        4       PUSH_NULL                       
                        6       LOAD_CONST                      2: '__pyarmor_enter_36904__'
                        8       LOAD_CONST                      3: b'<COAddr>\x07\x00\x00\x1a\xc0\x00\x00\x00\x00\x00\x00\x00\x00\x00\x00\x00\x00\x00\x00\x00'
                        10      BUILD_TUPLE                     1
                        12      CALL_FUNCTION_EX                0
                        14      POP_TOP                         
                        16      RESUME                          0
                        18      NOP                             
                        20      NOP                             
                        22      NOP                             
                        24      NOP                             
                        26      NOP                             
                        28      PUSH_NULL                       
                        30      LOAD_CONST                      1: '__pyarmor_assert_36903__'
                        32      LOAD_CONST                      4: 'GetRequirementsToContactRequest'   # b'\x81\xc5\x1d\x07\x01\xff\xaf\xc7\x12\xe8\x08\xcdi\xe2\xec\x96;R\x98\xa8\xa4\xdfO\xcf\x11]\xa6M\x15\xb4\r\xf1'
                        34      CALL                            1
                        42      LOAD_FAST                       0: self
                        44      LOAD_ATTR                       0: id
                        64      POP_JUMP_IF_NOT_NONE            2 (to 70)
                        66      BUILD_LIST                      0
                        68      JUMP_FORWARD                    57 (to 184)
                        70      LOAD_FAST                       0: self
                        72      LOAD_ATTR                       0: id
                        92      GET_ITER                        
                        94      LOAD_FAST_AND_CLEAR             2: _var_var_3
                        96      SWAP                            2
                        98      BUILD_LIST                      0
                        100     SWAP                            2
                        102     FOR_ITER                        36 (to 176)
                        106     STORE_FAST                      2: _var_var_3
                        108     LOAD_GLOBAL                     3: NULL + isinstance
                        118     LOAD_FAST                       2: _var_var_3
                        120     LOAD_GLOBAL                     4: TLObject
                        130     CALL                            2
                        138     POP_JUMP_IF_FALSE               16 (to 172)
                        140     LOAD_FAST                       2: _var_var_3
                        142     LOAD_ATTR                       7: to_dict
                        162     CALL                            0
                        170     JUMP_FORWARD                    1 (to 174)
                        172     LOAD_FAST                       2: _var_var_3
                        174     LIST_APPEND                     2
                        176     JUMP_BACKWARD                   38 (to 102)
                        178     END_FOR                         
                        180     SWAP                            2
                        182     STORE_FAST                      2: _var_var_3
                        184     LOAD_CONST                      5: ('_', 'id')
                        186     BUILD_CONST_KEY_MAP             2
                        188     NOP                             
                        190     NOP                             
                        192     NOP                             
                        194     JUMP_FORWARD                    25 (to 246)
                        196     CALL                            1
                        204     POP_TOP                         
                        206     RETURN_VALUE                    
                        208     SWAP                            2
                        210     POP_TOP                         
                        212     SWAP                            2
                        214     STORE_FAST                      2: _var_var_3
                        216     RERAISE                         0
                        218     PUSH_EXC_INFO                   
                        220     PUSH_NULL                       
                        222     LOAD_CONST                      6: '__pyarmor_exit_36905__'
                        224     NOP                             
                        226     LOAD_CONST                      3: b'<COAddr>\x07\x00\x00\x1a\xc0\x00\x00\x00\x00\x00\x00\x00\x00\x00\x00\x00\x00\x00\x00\x00'
                        228     CALL                            1
                        236     POP_TOP                         
                        238     RERAISE                         0
                        240     COPY                            3
                        242     POP_EXCEPT                      
                        244     RERAISE                         1
                        246     PUSH_NULL                       
                        248     LOAD_CONST                      6: '__pyarmor_exit_36905__'
                        250     LOAD_CONST                      3: b'<COAddr>\x07\x00\x00\x1a\xc0\x00\x00\x00\x00\x00\x00\x00\x00\x00\x00\x00\x00\x00\x00\x00'
                        252     BUILD_TUPLE                     1
                        254     CALL_FUNCTION_EX                0
                        256     POP_TOP                         
                        258     RETURN_VALUE                    
                    [Exception Table]
                        28 to 98 -> 218 [0] 
                        98 to 180 -> 208 [3] 
                        180 to 188 -> 218 [0] 
                        208 to 218 -> 218 [0] 
                        218 to 240 -> 240 [1] lasti
                [Code]
                    File Name: <frozen multithon.tl.functions.users>
                    Object Name: _bytes
                    Qualified Name: GetRequirementsToContactRequest._bytes
                    Arg Count: 1
                    Pos Only Arg Count: 0
                    KW Only Arg Count: 0
                    Stack Size: 10
                    Flags: 0x20000003 (CO_OPTIMIZED | CO_NEWLOCALS | CO_PYARMOR_OBFUSCATED)
                    [Names]
                        'join'
                        'struct'
                        'pack'
                        'len'
                        'id'
                    [Locals+Names]
                        'self'
                        '__assert_armored__'
                    [Constants]
                        None
                        '__pyarmor_assert_36906__'
                        '__pyarmor_enter_36907__'
                        b'<COAddr>\x05\x00\x00\x1a\xcc\x00\x00\x00\x00\x00\x00\x00\x00\x00\x00\x00\x00\x00\x00\x00'
                        b''
                        b'\xa3\x83\x9a\xd8'
                        b'\x15\xc4\xb5\x1c'
                        '<i'
                        [Code]
                            File Name: <frozen multithon.tl.functions.users>
                            Object Name: <genexpr>
                            Qualified Name: GetRequirementsToContactRequest._bytes.<locals>.<genexpr>
                            Arg Count: 1
                            Pos Only Arg Count: 0
                            KW Only Arg Count: 0
                            Stack Size: 3
                            Flags: 0x00000033 (CO_OPTIMIZED | CO_NEWLOCALS | CO_NESTED | CO_GENERATOR)
                            [Names]
                                '_bytes'
                            [Locals+Names]
                                '.0'
                                '_var_var_3'
                            [Constants]
                                None
                            [Disassembly]
                                0       RETURN_GENERATOR                
                                2       POP_TOP                         
                                4       RESUME                          0
                                6       LOAD_FAST                       0: .0
                                8       FOR_ITER                        20 (to 50)
                                12      STORE_FAST                      1: _var_var_3
                                14      LOAD_FAST                       1: _var_var_3
                                16      LOAD_ATTR                       1: _bytes
                                36      CALL                            0
                                44      YIELD_VALUE                     1
                                46      RESUME                          1
                                48      POP_TOP                         
                                50      JUMP_BACKWARD                   22 (to 8)
                                52      END_FOR                         
                                54      RETURN_CONST                    0: None
                                56      CALL_INTRINSIC_1                3 (INTRINSIC_STOPITERATION_ERROR)
                                58      RERAISE                         1
                            [Exception Table]
                                4 to 56 -> 56 [0] lasti
                        '__pyarmor_exit_36908__'
                    [Disassembly]
                        0       NOP                             
                        2       NOP                             
                        4       PUSH_NULL                       
                        6       LOAD_CONST                      2: '__pyarmor_enter_36907__'
                        8       LOAD_CONST                      3: b'<COAddr>\x05\x00\x00\x1a\xcc\x00\x00\x00\x00\x00\x00\x00\x00\x00\x00\x00\x00\x00\x00\x00'
                        10      BUILD_TUPLE                     1
                        12      CALL_FUNCTION_EX                0
                        14      POP_TOP                         
                        16      RESUME                          0
                        18      NOP                             
                        20      NOP                             
                        22      NOP                             
                        24      NOP                             
                        26      NOP                             
                        28      LOAD_CONST                      4: b''
                        30      LOAD_ATTR                       1: join
                        50      LOAD_CONST                      5: b'\xa3\x83\x9a\xd8'
                        52      LOAD_CONST                      6: b'\x15\xc4\xb5\x1c'
                        54      LOAD_GLOBAL                     3: NULL + struct
                        64      LOAD_ATTR                       4: pack
                        84      LOAD_CONST                      7: '<i'
                        86      LOAD_GLOBAL                     7: NULL + len
                        96      LOAD_FAST                       0: self
                        98      LOAD_ATTR                       8: id
                        118     CALL                            1
                        126     CALL                            2
                        134     LOAD_CONST                      4: b''
                        136     LOAD_ATTR                       1: join
                        156     LOAD_CONST                      8: <CODE> <genexpr>
                        158     MAKE_FUNCTION                   0
                        160     LOAD_FAST                       0: self
                        162     LOAD_ATTR                       8: id
                        182     GET_ITER                        
                        184     CALL                            0
                        192     CALL                            1
                        200     BUILD_TUPLE                     4
                        202     CALL                            1
                        210     NOP                             
                        212     NOP                             
                        214     NOP                             
                        216     JUMP_FORWARD                    20 (to 258)
                        218     CALL                            1
                        226     POP_TOP                         
                        228     RETURN_VALUE                    
                        230     PUSH_EXC_INFO                   
                        232     PUSH_NULL                       
                        234     LOAD_CONST                      9: '__pyarmor_exit_36908__'
                        236     NOP                             
                        238     LOAD_CONST                      3: b'<COAddr>\x05\x00\x00\x1a\xcc\x00\x00\x00\x00\x00\x00\x00\x00\x00\x00\x00\x00\x00\x00\x00'
                        240     CALL                            1
                        248     POP_TOP                         
                        250     RERAISE                         0
                        252     COPY                            3
                        254     POP_EXCEPT                      
                        256     RERAISE                         1
                        258     PUSH_NULL                       
                        260     LOAD_CONST                      9: '__pyarmor_exit_36908__'
                        262     LOAD_CONST                      3: b'<COAddr>\x05\x00\x00\x1a\xcc\x00\x00\x00\x00\x00\x00\x00\x00\x00\x00\x00\x00\x00\x00\x00'
                        264     BUILD_TUPLE                     1
                        266     CALL_FUNCTION_EX                0
                        268     POP_TOP                         
                        270     RETURN_VALUE                    
                    [Exception Table]
                        28 to 210 -> 230 [0] 
                        230 to 252 -> 252 [1] lasti
                [Code]
                    File Name: <frozen multithon.tl.functions.users>
                    Object Name: from_reader
                    Qualified Name: GetRequirementsToContactRequest.from_reader
                    Arg Count: 2
                    Pos Only Arg Count: 0
                    KW Only Arg Count: 0
                    Stack Size: 5
                    Flags: 0x20000003 (CO_OPTIMIZED | CO_NEWLOCALS | CO_PYARMOR_OBFUSCATED)
                    [Names]
                        'read_int'
                        'range'
                        'tgread_object'
                        'append'
                    [Locals+Names]
                        'cls'
                        'reader'
                        '__assert_armored__'
                        '_var_var_0'
                        '_var_var_4'
                        '_var_var_2'
                    [Constants]
                        None
                        '__pyarmor_assert_36909__'
                        '__pyarmor_enter_36910__'
                        b'<COAddr>\x07\x00\x00\x1a\xc8\x00\x00\x00\x00\x00\x00\x00\x00\x00\x00\x00\x00\x00\x00\x00'
                        (
                            'id'
                        )
                        '__pyarmor_exit_36911__'
                    [Disassembly]
                        0       NOP                             
                        2       NOP                             
                        4       PUSH_NULL                       
                        6       LOAD_CONST                      2: '__pyarmor_enter_36910__'
                        8       LOAD_CONST                      3: b'<COAddr>\x07\x00\x00\x1a\xc8\x00\x00\x00\x00\x00\x00\x00\x00\x00\x00\x00\x00\x00\x00\x00'
                        10      BUILD_TUPLE                     1
                        12      CALL_FUNCTION_EX                0
                        14      POP_TOP                         
                        16      RESUME                          0
                        18      NOP                             
                        20      NOP                             
                        22      NOP                             
                        24      NOP                             
                        26      NOP                             
                        28      LOAD_FAST                       1: reader
                        30      LOAD_ATTR                       1: read_int
                        50      CALL                            0
                        58      POP_TOP                         
                        60      BUILD_LIST                      0
                        62      STORE_FAST                      3: _var_var_0
                        64      LOAD_GLOBAL                     3: NULL + range
                        74      LOAD_FAST                       1: reader
                        76      LOAD_ATTR                       1: read_int
                        96      CALL                            0
                        104     CALL                            1
                        112     GET_ITER                        
                        114     FOR_ITER                        35 (to 186)
                        118     STORE_FAST                      4: _var_var_4
                        120     LOAD_FAST                       1: reader
                        122     LOAD_ATTR                       5: tgread_object
                        142     CALL                            0
                        150     STORE_FAST                      5: _var_var_2
                        152     LOAD_FAST                       3: _var_var_0
                        154     LOAD_ATTR                       7: append
                        174     LOAD_FAST                       5: _var_var_2
                        176     CALL                            1
                        184     POP_TOP                         
                        186     JUMP_BACKWARD                   37 (to 114)
                        188     END_FOR                         
                        190     PUSH_NULL                       
                        192     LOAD_FAST                       0: cls
                        194     LOAD_FAST                       3: _var_var_0
                        196     KW_NAMES                        4: ('id',)
                        198     CALL                            1
                        206     NOP                             
                        208     NOP                             
                        210     NOP                             
                        212     JUMP_FORWARD                    20 (to 254)
                        214     CALL                            1
                        222     POP_TOP                         
                        224     RETURN_VALUE                    
                        226     PUSH_EXC_INFO                   
                        228     PUSH_NULL                       
                        230     LOAD_CONST                      5: '__pyarmor_exit_36911__'
                        232     NOP                             
                        234     LOAD_CONST                      3: b'<COAddr>\x07\x00\x00\x1a\xc8\x00\x00\x00\x00\x00\x00\x00\x00\x00\x00\x00\x00\x00\x00\x00'
                        236     CALL                            1
                        244     POP_TOP                         
                        246     RERAISE                         0
                        248     COPY                            3
                        250     POP_EXCEPT                      
                        252     RERAISE                         1
                        254     PUSH_NULL                       
                        256     LOAD_CONST                      5: '__pyarmor_exit_36911__'
                        258     LOAD_CONST                      3: b'<COAddr>\x07\x00\x00\x1a\xc8\x00\x00\x00\x00\x00\x00\x00\x00\x00\x00\x00\x00\x00\x00\x00'
                        260     BUILD_TUPLE                     1
                        262     CALL_FUNCTION_EX                0
                        264     POP_TOP                         
                        266     RETURN_VALUE                    
                    [Exception Table]
                        28 to 206 -> 226 [0] 
                        226 to 248 -> 248 [1] lasti
                '__pyarmor_exit_36896__'
                None
            [Disassembly]
                0       NOP                             
                2       LOAD_NAME                       0: __name__
                4       STORE_NAME                      1: __module__
                6       LOAD_CONST                      0: 'GetRequirementsToContactRequest'
                8       STORE_NAME                      2: __qualname__
                10      NOP                             
                12      PUSH_NULL                       
                14      LOAD_CONST                      2: '__pyarmor_enter_36895__'
                16      LOAD_CONST                      3: b'<COAddr>\x05\x00\x00"^\x00\x00\x00\x00\x00\x00\x00\x00\x00\x00\x00\x00\x00\x00\x00'
                18      BUILD_TUPLE                     1
                20      CALL_FUNCTION_EX                0
                22      POP_TOP                         
                24      RESUME                          0
                26      NOP                             
                28      NOP                             
                30      NOP                             
                32      NOP                             
                34      NOP                             
                36      LOAD_CONST                      4: 0xD89A83A3
                38      STORE_NAME                      4: CONSTRUCTOR_ID
                40      LOAD_CONST                      5: 841360323
                42      STORE_NAME                      5: SUBCLASS_OF_ID
                44      LOAD_CONST                      6: 'id'
                46      LOAD_NAME                       6: List
                48      PUSH_NULL                       
                50      LOAD_CONST                      1: '__pyarmor_assert_36894__'
                52      LOAD_CONST                      7: 'TypeInputUser'   # b'\x81\xd6\x01\x036\xd3\xb0\xc2\x0e\xee8\xd3i\xfe'
                54      CALL                            1
                62      BINARY_SUBSCR                   
                66      BUILD_TUPLE                     2
                68      LOAD_CONST                      8: <CODE> __init__
                70      MAKE_FUNCTION                   4
                72      STORE_NAME                      7: __init__
                74      LOAD_CONST                      9: <CODE> resolve
                76      MAKE_FUNCTION                   0
                78      STORE_NAME                      8: resolve
                80      LOAD_CONST                      10: <CODE> to_dict
                82      MAKE_FUNCTION                   0
                84      STORE_NAME                      9: to_dict
                86      LOAD_CONST                      11: <CODE> _bytes
                88      MAKE_FUNCTION                   0
                90      STORE_NAME                      10: _bytes
                92      LOAD_NAME                       11: classmethod
                94      LOAD_CONST                      12: <CODE> from_reader
                96      MAKE_FUNCTION                   0
                98      CALL                            0
                106     STORE_NAME                      12: from_reader
                108     LOAD_CONST                      14: None
                110     NOP                             
                112     NOP                             
                114     NOP                             
                116     JUMP_FORWARD                    19 (to 156)
                124     POP_TOP                         
                126     RETURN_CONST                    14: None
                128     PUSH_EXC_INFO                   
                130     PUSH_NULL                       
                132     LOAD_CONST                      13: '__pyarmor_exit_36896__'
                134     NOP                             
                136     LOAD_CONST                      3: b'<COAddr>\x05\x00\x00"^\x00\x00\x00\x00\x00\x00\x00\x00\x00\x00\x00\x00\x00\x00\x00'
                138     CALL                            1
                146     POP_TOP                         
                148     RERAISE                         0
                150     COPY                            3
                152     POP_EXCEPT                      
                154     RERAISE                         1
                156     PUSH_NULL                       
                158     LOAD_CONST                      13: '__pyarmor_exit_36896__'
                160     LOAD_CONST                      3: b'<COAddr>\x05\x00\x00"^\x00\x00\x00\x00\x00\x00\x00\x00\x00\x00\x00\x00\x00\x00\x00'
                162     BUILD_TUPLE                     1
                164     CALL_FUNCTION_EX                0
                166     POP_TOP                         
                168     RETURN_VALUE                    
            [Exception Table]
                36 to 108 -> 128 [0] 
                128 to 150 -> 150 [1] lasti
        'GetRequirementsToContactRequest'
        [Code]
            File Name: <frozen multithon.tl.functions.users>
            Object Name: GetIsPremiumRequiredToContactRequest
            Qualified Name: GetIsPremiumRequiredToContactRequest
            Arg Count: 0
            Pos Only Arg Count: 0
            KW Only Arg Count: 0
            Stack Size: 5
            Flags: 0x20000000 (CO_PYARMOR_OBFUSCATED)
            [Names]
                '__name__'
                '__module__'
                '__qualname__'
                '__assert_armored__'
                'CONSTRUCTOR_ID'
                'SUBCLASS_OF_ID'
                'List'
                '__init__'
                'resolve'
                'to_dict'
                '_bytes'
                'classmethod'
                'from_reader'
            [Locals+Names]
            [Constants]
                'GetIsPremiumRequiredToContactRequest'
                '__pyarmor_assert_36912__'
                '__pyarmor_enter_36913__'
                b'<COAddr>\x07\x00\x00"^\x00\x00\x00\x00\x00\x00\x00\x00\x00\x00\x00\x00\x00\x00\x00'
                0xA622AA10
                366986225
                'id'
                'TypeInputUser'   # b'\x81\xd6\x01\x036\xd3\xb0\xc2\x0e\xee8\xd3i\xfe'
                [Code]
                    File Name: <frozen multithon.tl.functions.users>
                    Object Name: __init__
                    Qualified Name: GetIsPremiumRequiredToContactRequest.__init__
                    Arg Count: 2
                    Pos Only Arg Count: 0
                    KW Only Arg Count: 0
                    Stack Size: 5
                    Flags: 0x20000003 (CO_OPTIMIZED | CO_NEWLOCALS | CO_PYARMOR_OBFUSCATED)
                    [Names]
                        'id'
                    [Locals+Names]
                        'self'
                        'id'
                        '__assert_armored__'
                    [Constants]
                        '\n        :returns Vector<Bool>: This type has no constructors.\n        '
                        '__pyarmor_assert_36915__'
                        '__pyarmor_enter_36916__'
                        b'<COAddr>\x07\x00\x00\x1a$\x00\x00\x00\x00\x00\x00\x00\x00\x00\x00\x00\x00\x00\x00\x00'
                        '__pyarmor_exit_36917__'
                        None
                    [Disassembly]
                        0       NOP                             
                        2       NOP                             
                        4       PUSH_NULL                       
                        6       LOAD_CONST                      2: '__pyarmor_enter_36916__'
                        8       LOAD_CONST                      3: b'<COAddr>\x07\x00\x00\x1a$\x00\x00\x00\x00\x00\x00\x00\x00\x00\x00\x00\x00\x00\x00\x00'
                        10      BUILD_TUPLE                     1
                        12      CALL_FUNCTION_EX                0
                        14      POP_TOP                         
                        16      RESUME                          0
                        18      NOP                             
                        20      NOP                             
                        22      NOP                             
                        24      NOP                             
                        26      NOP                             
                        28      LOAD_FAST                       1: id
                        30      LOAD_FAST                       0: self
                        32      STORE_ATTR                      0: id
                        42      LOAD_CONST                      5: None
                        44      NOP                             
                        46      NOP                             
                        48      NOP                             
                        50      JUMP_FORWARD                    19 (to 90)
                        58      POP_TOP                         
                        60      RETURN_CONST                    5: None
                        62      PUSH_EXC_INFO                   
                        64      PUSH_NULL                       
                        66      LOAD_CONST                      4: '__pyarmor_exit_36917__'
                        68      NOP                             
                        70      LOAD_CONST                      3: b'<COAddr>\x07\x00\x00\x1a$\x00\x00\x00\x00\x00\x00\x00\x00\x00\x00\x00\x00\x00\x00\x00'
                        72      CALL                            1
                        80      POP_TOP                         
                        82      RERAISE                         0
                        84      COPY                            3
                        86      POP_EXCEPT                      
                        88      RERAISE                         1
                        90      PUSH_NULL                       
                        92      LOAD_CONST                      4: '__pyarmor_exit_36917__'
                        94      LOAD_CONST                      3: b'<COAddr>\x07\x00\x00\x1a$\x00\x00\x00\x00\x00\x00\x00\x00\x00\x00\x00\x00\x00\x00\x00'
                        96      BUILD_TUPLE                     1
                        98      CALL_FUNCTION_EX                0
                        100     POP_TOP                         
                        102     RETURN_VALUE                    
                    [Exception Table]
                        28 to 42 -> 62 [0] 
                        62 to 84 -> 84 [1] lasti
                [Code]
                    File Name: <frozen multithon.tl.functions.users>
                    Object Name: resolve
                    Qualified Name: GetIsPremiumRequiredToContactRequest.resolve
                    Arg Count: 3
                    Pos Only Arg Count: 0
                    KW Only Arg Count: 0
                    Stack Size: 8
                    Flags: 0x20000083 (CO_OPTIMIZED | CO_NEWLOCALS | CO_COROUTINE | CO_PYARMOR_OBFUSCATED)
                    [Names]
                        'id'
                        'append'
                        'get_input_user'
                        'get_input_entity'
                    [Locals+Names]
                        'self'
                        'client'
                        'utils'
                        '__assert_armored__'
                        '_var_var_1'
                        '_var_var_2'
                    [Constants]
                        None
                        '__pyarmor_assert_36918__'
                        '__pyarmor_enter_36919__'
                        b'<COAddr>\x05\x00\x00\x1e\xbc\x00\x00\x00\x00\x00\x00\x00\x00\x00\x00\x00\x00\x00\x00\x00'
                        '__pyarmor_exit_36920__'
                    [Disassembly]
                        0       RETURN_GENERATOR                
                        2       POP_TOP                         
                        4       NOP                             
                        6       NOP                             
                        8       PUSH_NULL                       
                        10      LOAD_CONST                      2: '__pyarmor_enter_36919__'
                        12      LOAD_CONST                      3: b'<COAddr>\x05\x00\x00\x1e\xbc\x00\x00\x00\x00\x00\x00\x00\x00\x00\x00\x00\x00\x00\x00\x00'
                        14      BUILD_TUPLE                     1
                        16      CALL_FUNCTION_EX                0
                        18      POP_TOP                         
                        20      RESUME                          0
                        22      NOP                             
                        24      NOP                             
                        26      NOP                             
                        28      NOP                             
                        30      NOP                             
                        32      BUILD_LIST                      0
                        34      STORE_FAST                      4: _var_var_1
                        36      LOAD_FAST                       0: self
                        38      LOAD_ATTR                       0: id
                        58      GET_ITER                        
                        60      FOR_ITER                        57 (to 176)
                        64      STORE_FAST                      5: _var_var_2
                        66      LOAD_FAST                       4: _var_var_1
                        68      LOAD_ATTR                       3: append
                        88      LOAD_FAST                       2: utils
                        90      LOAD_ATTR                       5: get_input_user
                        110     LOAD_FAST                       1: client
                        112     LOAD_ATTR                       7: get_input_entity
                        132     LOAD_FAST                       5: _var_var_2
                        134     CALL                            1
                        142     GET_AWAITABLE                   0
                        144     LOAD_CONST                      0: None
                        146     SEND                            3 (to 154)
                        150     YIELD_VALUE                     3
                        152     RESUME                          3
                        154     JUMP_BACKWARD_NO_INTERRUPT      5 (to 146)
                        156     END_SEND                        
                        158     CALL                            1
                        166     CALL                            1
                        174     POP_TOP                         
                        176     JUMP_BACKWARD                   59 (to 60)
                        178     END_FOR                         
                        180     LOAD_FAST                       4: _var_var_1
                        182     LOAD_FAST                       0: self
                        184     STORE_ATTR                      0: id
                        194     LOAD_CONST                      0: None
                        196     NOP                             
                        198     NOP                             
                        200     NOP                             
                        202     JUMP_FORWARD                    23 (to 250)
                        210     POP_TOP                         
                        212     RETURN_CONST                    0: None
                        214     CLEANUP_THROW                   
                        216     JUMP_BACKWARD                   31 (to 156)
                        218     PUSH_EXC_INFO                   
                        220     PUSH_NULL                       
                        222     LOAD_CONST                      4: '__pyarmor_exit_36920__'
                        224     NOP                             
                        226     LOAD_CONST                      3: b'<COAddr>\x05\x00\x00\x1e\xbc\x00\x00\x00\x00\x00\x00\x00\x00\x00\x00\x00\x00\x00\x00\x00'
                        228     CALL                            1
                        236     POP_TOP                         
                        238     RERAISE                         0
                        240     COPY                            3
                        242     POP_EXCEPT                      
                        244     RERAISE                         1
                        246     CALL_INTRINSIC_1                3 (INTRINSIC_STOPITERATION_ERROR)
                        248     RERAISE                         1
                        250     PUSH_NULL                       
                        252     LOAD_CONST                      4: '__pyarmor_exit_36920__'
                        254     LOAD_CONST                      3: b'<COAddr>\x05\x00\x00\x1e\xbc\x00\x00\x00\x00\x00\x00\x00\x00\x00\x00\x00\x00\x00\x00\x00'
                        256     BUILD_TUPLE                     1
                        258     CALL_FUNCTION_EX                0
                        260     POP_TOP                         
                        262     RETURN_VALUE                    
                    [Exception Table]
                        4 to 30 -> 246 [0] lasti
                        32 to 150 -> 218 [0] 
                        150 to 152 -> 214 [7] 
                        152 to 194 -> 218 [0] 
                        194 to 214 -> 246 [0] lasti
                        214 to 216 -> 218 [0] 
                        218 to 240 -> 240 [1] lasti
                        240 to 246 -> 246 [0] lasti
                [Code]
                    File Name: <frozen multithon.tl.functions.users>
                    Object Name: to_dict
                    Qualified Name: GetIsPremiumRequiredToContactRequest.to_dict
                    Arg Count: 1
                    Pos Only Arg Count: 0
                    KW Only Arg Count: 0
                    Stack Size: 8
                    Flags: 0x20000003 (CO_OPTIMIZED | CO_NEWLOCALS | CO_PYARMOR_OBFUSCATED)
                    [Names]
                        'id'
                        'isinstance'
                        'TLObject'
                        'to_dict'
                    [Locals+Names]
                        'self'
                        '__assert_armored__'
                        '_var_var_3'
                    [Constants]
                        None
                        '__pyarmor_assert_36921__'
                        '__pyarmor_enter_36922__'
                        b'<COAddr>\x05\x00\x00\x1a\xc0\x00\x00\x00\x00\x00\x00\x00\x00\x00\x00\x00\x00\x00\x00\x00'
                        'GetIsPremiumRequiredToContactRequest'   # b'\x81\xc5\x1d\x07\x1a\xe9\x8e\xc0\x1e\xf7\x04\xd5a\xde\xfd\x94\x1aT\xa9\xa2\xae\xffA\xef\na\xb7]\x03\xa5,\xe0+G%\x1e\x8c'
                        (
                            '_'
                            'id'
                        )
                        '__pyarmor_exit_36923__'
                    [Disassembly]
                        0       NOP                             
                        2       NOP                             
                        4       PUSH_NULL                       
                        6       LOAD_CONST                      2: '__pyarmor_enter_36922__'
                        8       LOAD_CONST                      3: b'<COAddr>\x05\x00\x00\x1a\xc0\x00\x00\x00\x00\x00\x00\x00\x00\x00\x00\x00\x00\x00\x00\x00'
                        10      BUILD_TUPLE                     1
                        12      CALL_FUNCTION_EX                0
                        14      POP_TOP                         
                        16      RESUME                          0
                        18      NOP                             
                        20      NOP                             
                        22      NOP                             
                        24      NOP                             
                        26      NOP                             
                        28      PUSH_NULL                       
                        30      LOAD_CONST                      1: '__pyarmor_assert_36921__'
                        32      LOAD_CONST                      4: 'GetIsPremiumRequiredToContactRequest'   # b'\x81\xc5\x1d\x07\x1a\xe9\x8e\xc0\x1e\xf7\x04\xd5a\xde\xfd\x94\x1aT\xa9\xa2\xae\xffA\xef\na\xb7]\x03\xa5,\xe0+G%\x1e\x8c'
                        34      CALL                            1
                        42      LOAD_FAST                       0: self
                        44      LOAD_ATTR                       0: id
                        64      POP_JUMP_IF_NOT_NONE            2 (to 70)
                        66      BUILD_LIST                      0
                        68      JUMP_FORWARD                    57 (to 184)
                        70      LOAD_FAST                       0: self
                        72      LOAD_ATTR                       0: id
                        92      GET_ITER                        
                        94      LOAD_FAST_AND_CLEAR             2: _var_var_3
                        96      SWAP                            2
                        98      BUILD_LIST                      0
                        100     SWAP                            2
                        102     FOR_ITER                        36 (to 176)
                        106     STORE_FAST                      2: _var_var_3
                        108     LOAD_GLOBAL                     3: NULL + isinstance
                        118     LOAD_FAST                       2: _var_var_3
                        120     LOAD_GLOBAL                     4: TLObject
                        130     CALL                            2
                        138     POP_JUMP_IF_FALSE               16 (to 172)
                        140     LOAD_FAST                       2: _var_var_3
                        142     LOAD_ATTR                       7: to_dict
                        162     CALL                            0
                        170     JUMP_FORWARD                    1 (to 174)
                        172     LOAD_FAST                       2: _var_var_3
                        174     LIST_APPEND                     2
                        176     JUMP_BACKWARD                   38 (to 102)
                        178     END_FOR                         
                        180     SWAP                            2
                        182     STORE_FAST                      2: _var_var_3
                        184     LOAD_CONST                      5: ('_', 'id')
                        186     BUILD_CONST_KEY_MAP             2
                        188     NOP                             
                        190     NOP                             
                        192     NOP                             
                        194     JUMP_FORWARD                    25 (to 246)
                        196     CALL                            1
                        204     POP_TOP                         
                        206     RETURN_VALUE                    
                        208     SWAP                            2
                        210     POP_TOP                         
                        212     SWAP                            2
                        214     STORE_FAST                      2: _var_var_3
                        216     RERAISE                         0
                        218     PUSH_EXC_INFO                   
                        220     PUSH_NULL                       
                        222     LOAD_CONST                      6: '__pyarmor_exit_36923__'
                        224     NOP                             
                        226     LOAD_CONST                      3: b'<COAddr>\x05\x00\x00\x1a\xc0\x00\x00\x00\x00\x00\x00\x00\x00\x00\x00\x00\x00\x00\x00\x00'
                        228     CALL                            1
                        236     POP_TOP                         
                        238     RERAISE                         0
                        240     COPY                            3
                        242     POP_EXCEPT                      
                        244     RERAISE                         1
                        246     PUSH_NULL                       
                        248     LOAD_CONST                      6: '__pyarmor_exit_36923__'
                        250     LOAD_CONST                      3: b'<COAddr>\x05\x00\x00\x1a\xc0\x00\x00\x00\x00\x00\x00\x00\x00\x00\x00\x00\x00\x00\x00\x00'
                        252     BUILD_TUPLE                     1
                        254     CALL_FUNCTION_EX                0
                        256     POP_TOP                         
                        258     RETURN_VALUE                    
                    [Exception Table]
                        28 to 98 -> 218 [0] 
                        98 to 180 -> 208 [3] 
                        180 to 188 -> 218 [0] 
                        208 to 218 -> 218 [0] 
                        218 to 240 -> 240 [1] lasti
                [Code]
                    File Name: <frozen multithon.tl.functions.users>
                    Object Name: _bytes
                    Qualified Name: GetIsPremiumRequiredToContactRequest._bytes
                    Arg Count: 1
                    Pos Only Arg Count: 0
                    KW Only Arg Count: 0
                    Stack Size: 10
                    Flags: 0x20000003 (CO_OPTIMIZED | CO_NEWLOCALS | CO_PYARMOR_OBFUSCATED)
                    [Names]
                        'join'
                        'struct'
                        'pack'
                        'len'
                        'id'
                    [Locals+Names]
                        'self'
                        '__assert_armored__'
                    [Constants]
                        None
                        '__pyarmor_assert_36924__'
                        '__pyarmor_enter_36925__'
                        b'<COAddr>\x05\x00\x00\x1a\xcc\x00\x00\x00\x00\x00\x00\x00\x00\x00\x00\x00\x00\x00\x00\x00'
                        b''
                        b'\x10\xaa"\xa6'
                        b'\x15\xc4\xb5\x1c'
                        '<i'
                        [Code]
                            File Name: <frozen multithon.tl.functions.users>
                            Object Name: <genexpr>
                            Qualified Name: GetIsPremiumRequiredToContactRequest._bytes.<locals>.<genexpr>
                            Arg Count: 1
                            Pos Only Arg Count: 0
                            KW Only Arg Count: 0
                            Stack Size: 3
                            Flags: 0x00000033 (CO_OPTIMIZED | CO_NEWLOCALS | CO_NESTED | CO_GENERATOR)
                            [Names]
                                '_bytes'
                            [Locals+Names]
                                '.0'
                                '_var_var_3'
                            [Constants]
                                None
                            [Disassembly]
                                0       RETURN_GENERATOR                
                                2       POP_TOP                         
                                4       RESUME                          0
                                6       LOAD_FAST                       0: .0
                                8       FOR_ITER                        20 (to 50)
                                12      STORE_FAST                      1: _var_var_3
                                14      LOAD_FAST                       1: _var_var_3
                                16      LOAD_ATTR                       1: _bytes
                                36      CALL                            0
                                44      YIELD_VALUE                     1
                                46      RESUME                          1
                                48      POP_TOP                         
                                50      JUMP_BACKWARD                   22 (to 8)
                                52      END_FOR                         
                                54      RETURN_CONST                    0: None
                                56      CALL_INTRINSIC_1                3 (INTRINSIC_STOPITERATION_ERROR)
                                58      RERAISE                         1
                            [Exception Table]
                                4 to 56 -> 56 [0] lasti
                        '__pyarmor_exit_36926__'
                    [Disassembly]
                        0       NOP                             
                        2       NOP                             
                        4       PUSH_NULL                       
                        6       LOAD_CONST                      2: '__pyarmor_enter_36925__'
                        8       LOAD_CONST                      3: b'<COAddr>\x05\x00\x00\x1a\xcc\x00\x00\x00\x00\x00\x00\x00\x00\x00\x00\x00\x00\x00\x00\x00'
                        10      BUILD_TUPLE                     1
                        12      CALL_FUNCTION_EX                0
                        14      POP_TOP                         
                        16      RESUME                          0
                        18      NOP                             
                        20      NOP                             
                        22      NOP                             
                        24      NOP                             
                        26      NOP                             
                        28      LOAD_CONST                      4: b''
                        30      LOAD_ATTR                       1: join
                        50      LOAD_CONST                      5: b'\x10\xaa"\xa6'
                        52      LOAD_CONST                      6: b'\x15\xc4\xb5\x1c'
                        54      LOAD_GLOBAL                     3: NULL + struct
                        64      LOAD_ATTR                       4: pack
                        84      LOAD_CONST                      7: '<i'
                        86      LOAD_GLOBAL                     7: NULL + len
                        96      LOAD_FAST                       0: self
                        98      LOAD_ATTR                       8: id
                        118     CALL                            1
                        126     CALL                            2
                        134     LOAD_CONST                      4: b''
                        136     LOAD_ATTR                       1: join
                        156     LOAD_CONST                      8: <CODE> <genexpr>
                        158     MAKE_FUNCTION                   0
                        160     LOAD_FAST                       0: self
                        162     LOAD_ATTR                       8: id
                        182     GET_ITER                        
                        184     CALL                            0
                        192     CALL                            1
                        200     BUILD_TUPLE                     4
                        202     CALL                            1
                        210     NOP                             
                        212     NOP                             
                        214     NOP                             
                        216     JUMP_FORWARD                    20 (to 258)
                        218     CALL                            1
                        226     POP_TOP                         
                        228     RETURN_VALUE                    
                        230     PUSH_EXC_INFO                   
                        232     PUSH_NULL                       
                        234     LOAD_CONST                      9: '__pyarmor_exit_36926__'
                        236     NOP                             
                        238     LOAD_CONST                      3: b'<COAddr>\x05\x00\x00\x1a\xcc\x00\x00\x00\x00\x00\x00\x00\x00\x00\x00\x00\x00\x00\x00\x00'
                        240     CALL                            1
                        248     POP_TOP                         
                        250     RERAISE                         0
                        252     COPY                            3
                        254     POP_EXCEPT                      
                        256     RERAISE                         1
                        258     PUSH_NULL                       
                        260     LOAD_CONST                      9: '__pyarmor_exit_36926__'
                        262     LOAD_CONST                      3: b'<COAddr>\x05\x00\x00\x1a\xcc\x00\x00\x00\x00\x00\x00\x00\x00\x00\x00\x00\x00\x00\x00\x00'
                        264     BUILD_TUPLE                     1
                        266     CALL_FUNCTION_EX                0
                        268     POP_TOP                         
                        270     RETURN_VALUE                    
                    [Exception Table]
                        28 to 210 -> 230 [0] 
                        230 to 252 -> 252 [1] lasti
                [Code]
                    File Name: <frozen multithon.tl.functions.users>
                    Object Name: from_reader
                    Qualified Name: GetIsPremiumRequiredToContactRequest.from_reader
                    Arg Count: 2
                    Pos Only Arg Count: 0
                    KW Only Arg Count: 0
                    Stack Size: 5
                    Flags: 0x20000003 (CO_OPTIMIZED | CO_NEWLOCALS | CO_PYARMOR_OBFUSCATED)
                    [Names]
                        'read_int'
                        'range'
                        'tgread_object'
                        'append'
                    [Locals+Names]
                        'cls'
                        'reader'
                        '__assert_armored__'
                        '_var_var_0'
                        '_var_var_4'
                        '_var_var_2'
                    [Constants]
                        None
                        '__pyarmor_assert_36927__'
                        '__pyarmor_enter_36928__'
                        b'<COAddr>\x05\x00\x00\x1a\xc8\x00\x00\x00\x00\x00\x00\x00\x00\x00\x00\x00\x00\x00\x00\x00'
                        (
                            'id'
                        )
                        '__pyarmor_exit_36929__'
                    [Disassembly]
                        0       NOP                             
                        2       NOP                             
                        4       PUSH_NULL                       
                        6       LOAD_CONST                      2: '__pyarmor_enter_36928__'
                        8       LOAD_CONST                      3: b'<COAddr>\x05\x00\x00\x1a\xc8\x00\x00\x00\x00\x00\x00\x00\x00\x00\x00\x00\x00\x00\x00\x00'
                        10      BUILD_TUPLE                     1
                        12      CALL_FUNCTION_EX                0
                        14      POP_TOP                         
                        16      RESUME                          0
                        18      NOP                             
                        20      NOP                             
                        22      NOP                             
                        24      NOP                             
                        26      NOP                             
                        28      LOAD_FAST                       1: reader
                        30      LOAD_ATTR                       1: read_int
                        50      CALL                            0
                        58      POP_TOP                         
                        60      BUILD_LIST                      0
                        62      STORE_FAST                      3: _var_var_0
                        64      LOAD_GLOBAL                     3: NULL + range
                        74      LOAD_FAST                       1: reader
                        76      LOAD_ATTR                       1: read_int
                        96      CALL                            0
                        104     CALL                            1
                        112     GET_ITER                        
                        114     FOR_ITER                        35 (to 186)
                        118     STORE_FAST                      4: _var_var_4
                        120     LOAD_FAST                       1: reader
                        122     LOAD_ATTR                       5: tgread_object
                        142     CALL                            0
                        150     STORE_FAST                      5: _var_var_2
                        152     LOAD_FAST                       3: _var_var_0
                        154     LOAD_ATTR                       7: append
                        174     LOAD_FAST                       5: _var_var_2
                        176     CALL                            1
                        184     POP_TOP                         
                        186     JUMP_BACKWARD                   37 (to 114)
                        188     END_FOR                         
                        190     PUSH_NULL                       
                        192     LOAD_FAST                       0: cls
                        194     LOAD_FAST                       3: _var_var_0
                        196     KW_NAMES                        4: ('id',)
                        198     CALL                            1
                        206     NOP                             
                        208     NOP                             
                        210     NOP                             
                        212     JUMP_FORWARD                    20 (to 254)
                        214     CALL                            1
                        222     POP_TOP                         
                        224     RETURN_VALUE                    
                        226     PUSH_EXC_INFO                   
                        228     PUSH_NULL                       
                        230     LOAD_CONST                      5: '__pyarmor_exit_36929__'
                        232     NOP                             
                        234     LOAD_CONST                      3: b'<COAddr>\x05\x00\x00\x1a\xc8\x00\x00\x00\x00\x00\x00\x00\x00\x00\x00\x00\x00\x00\x00\x00'
                        236     CALL                            1
                        244     POP_TOP                         
                        246     RERAISE                         0
                        248     COPY                            3
                        250     POP_EXCEPT                      
                        252     RERAISE                         1
                        254     PUSH_NULL                       
                        256     LOAD_CONST                      5: '__pyarmor_exit_36929__'
                        258     LOAD_CONST                      3: b'<COAddr>\x05\x00\x00\x1a\xc8\x00\x00\x00\x00\x00\x00\x00\x00\x00\x00\x00\x00\x00\x00\x00'
                        260     BUILD_TUPLE                     1
                        262     CALL_FUNCTION_EX                0
                        264     POP_TOP                         
                        266     RETURN_VALUE                    
                    [Exception Table]
                        28 to 206 -> 226 [0] 
                        226 to 248 -> 248 [1] lasti
                '__pyarmor_exit_36914__'
                None
            [Disassembly]
                0       NOP                             
                2       LOAD_NAME                       0: __name__
                4       STORE_NAME                      1: __module__
                6       LOAD_CONST                      0: 'GetIsPremiumRequiredToContactRequest'
                8       STORE_NAME                      2: __qualname__
                10      NOP                             
                12      PUSH_NULL                       
                14      LOAD_CONST                      2: '__pyarmor_enter_36913__'
                16      LOAD_CONST                      3: b'<COAddr>\x07\x00\x00"^\x00\x00\x00\x00\x00\x00\x00\x00\x00\x00\x00\x00\x00\x00\x00'
                18      BUILD_TUPLE                     1
                20      CALL_FUNCTION_EX                0
                22      POP_TOP                         
                24      RESUME                          0
                26      NOP                             
                28      NOP                             
                30      NOP                             
                32      NOP                             
                34      NOP                             
                36      LOAD_CONST                      4: 0xA622AA10
                38      STORE_NAME                      4: CONSTRUCTOR_ID
                40      LOAD_CONST                      5: 366986225
                42      STORE_NAME                      5: SUBCLASS_OF_ID
                44      LOAD_CONST                      6: 'id'
                46      LOAD_NAME                       6: List
                48      PUSH_NULL                       
                50      LOAD_CONST                      1: '__pyarmor_assert_36912__'
                52      LOAD_CONST                      7: 'TypeInputUser'   # b'\x81\xd6\x01\x036\xd3\xb0\xc2\x0e\xee8\xd3i\xfe'
                54      CALL                            1
                62      BINARY_SUBSCR                   
                66      BUILD_TUPLE                     2
                68      LOAD_CONST                      8: <CODE> __init__
                70      MAKE_FUNCTION                   4
                72      STORE_NAME                      7: __init__
                74      LOAD_CONST                      9: <CODE> resolve
                76      MAKE_FUNCTION                   0
                78      STORE_NAME                      8: resolve
                80      LOAD_CONST                      10: <CODE> to_dict
                82      MAKE_FUNCTION                   0
                84      STORE_NAME                      9: to_dict
                86      LOAD_CONST                      11: <CODE> _bytes
                88      MAKE_FUNCTION                   0
                90      STORE_NAME                      10: _bytes
                92      LOAD_NAME                       11: classmethod
                94      LOAD_CONST                      12: <CODE> from_reader
                96      MAKE_FUNCTION                   0
                98      CALL                            0
                106     STORE_NAME                      12: from_reader
                108     LOAD_CONST                      14: None
                110     NOP                             
                112     NOP                             
                114     NOP                             
                116     JUMP_FORWARD                    19 (to 156)
                124     POP_TOP                         
                126     RETURN_CONST                    14: None
                128     PUSH_EXC_INFO                   
                130     PUSH_NULL                       
                132     LOAD_CONST                      13: '__pyarmor_exit_36914__'
                134     NOP                             
                136     LOAD_CONST                      3: b'<COAddr>\x07\x00\x00"^\x00\x00\x00\x00\x00\x00\x00\x00\x00\x00\x00\x00\x00\x00\x00'
                138     CALL                            1
                146     POP_TOP                         
                148     RERAISE                         0
                150     COPY                            3
                152     POP_EXCEPT                      
                154     RERAISE                         1
                156     PUSH_NULL                       
                158     LOAD_CONST                      13: '__pyarmor_exit_36914__'
                160     LOAD_CONST                      3: b'<COAddr>\x07\x00\x00"^\x00\x00\x00\x00\x00\x00\x00\x00\x00\x00\x00\x00\x00\x00\x00'
                162     BUILD_TUPLE                     1
                164     CALL_FUNCTION_EX                0
                166     POP_TOP                         
                168     RETURN_VALUE                    
            [Exception Table]
                36 to 108 -> 128 [0] 
                128 to 150 -> 150 [1] lasti
        'GetIsPremiumRequiredToContactRequest'
        [Code]
            File Name: <frozen multithon.tl.functions.users>
            Object Name: GetUsersRequest
            Qualified Name: GetUsersRequest
            Arg Count: 0
            Pos Only Arg Count: 0
            KW Only Arg Count: 0
            Stack Size: 5
            Flags: 0x20000000 (CO_PYARMOR_OBFUSCATED)
            [Names]
                '__name__'
                '__module__'
                '__qualname__'
                '__assert_armored__'
                'CONSTRUCTOR_ID'
                'SUBCLASS_OF_ID'
                'List'
                '__init__'
                'resolve'
                'to_dict'
                '_bytes'
                'classmethod'
                'from_reader'
            [Locals+Names]
            [Constants]
                'GetUsersRequest'
                '__pyarmor_assert_36930__'
                '__pyarmor_enter_36931__'
                b'<COAddr>\x07\x00\x00"^\x00\x00\x00\x00\x00\x00\x00\x00\x00\x00\x00\x00\x00\x00\x00'
                227648840
                67557965
                'id'
                'TypeInputUser'   # b'\x81\xd6\x01\x036\xd3\xb0\xc2\x0e\xee8\xd3i\xfe'
                [Code]
                    File Name: <frozen multithon.tl.functions.users>
                    Object Name: __init__
                    Qualified Name: GetUsersRequest.__init__
                    Arg Count: 2
                    Pos Only Arg Count: 0
                    KW Only Arg Count: 0
                    Stack Size: 5
                    Flags: 0x20000003 (CO_OPTIMIZED | CO_NEWLOCALS | CO_PYARMOR_OBFUSCATED)
                    [Names]
                        'id'
                    [Locals+Names]
                        'self'
                        'id'
                        '__assert_armored__'
                    [Constants]
                        '\n        :returns Vector<User>: This type has no constructors.\n        '
                        '__pyarmor_assert_36933__'
                        '__pyarmor_enter_36934__'
                        b'<COAddr>\x07\x00\x00\x1a$\x00\x00\x00\x00\x00\x00\x00\x00\x00\x00\x00\x00\x00\x00\x00'
                        '__pyarmor_exit_36935__'
                        None
                    [Disassembly]
                        0       NOP                             
                        2       NOP                             
                        4       PUSH_NULL                       
                        6       LOAD_CONST                      2: '__pyarmor_enter_36934__'
                        8       LOAD_CONST                      3: b'<COAddr>\x07\x00\x00\x1a$\x00\x00\x00\x00\x00\x00\x00\x00\x00\x00\x00\x00\x00\x00\x00'
                        10      BUILD_TUPLE                     1
                        12      CALL_FUNCTION_EX                0
                        14      POP_TOP                         
                        16      RESUME                          0
                        18      NOP                             
                        20      NOP                             
                        22      NOP                             
                        24      NOP                             
                        26      NOP                             
                        28      LOAD_FAST                       1: id
                        30      LOAD_FAST                       0: self
                        32      STORE_ATTR                      0: id
                        42      LOAD_CONST                      5: None
                        44      NOP                             
                        46      NOP                             
                        48      NOP                             
                        50      JUMP_FORWARD                    19 (to 90)
                        58      POP_TOP                         
                        60      RETURN_CONST                    5: None
                        62      PUSH_EXC_INFO                   
                        64      PUSH_NULL                       
                        66      LOAD_CONST                      4: '__pyarmor_exit_36935__'
                        68      NOP                             
                        70      LOAD_CONST                      3: b'<COAddr>\x07\x00\x00\x1a$\x00\x00\x00\x00\x00\x00\x00\x00\x00\x00\x00\x00\x00\x00\x00'
                        72      CALL                            1
                        80      POP_TOP                         
                        82      RERAISE                         0
                        84      COPY                            3
                        86      POP_EXCEPT                      
                        88      RERAISE                         1
                        90      PUSH_NULL                       
                        92      LOAD_CONST                      4: '__pyarmor_exit_36935__'
                        94      LOAD_CONST                      3: b'<COAddr>\x07\x00\x00\x1a$\x00\x00\x00\x00\x00\x00\x00\x00\x00\x00\x00\x00\x00\x00\x00'
                        96      BUILD_TUPLE                     1
                        98      CALL_FUNCTION_EX                0
                        100     POP_TOP                         
                        102     RETURN_VALUE                    
                    [Exception Table]
                        28 to 42 -> 62 [0] 
                        62 to 84 -> 84 [1] lasti
                [Code]
                    File Name: <frozen multithon.tl.functions.users>
                    Object Name: resolve
                    Qualified Name: GetUsersRequest.resolve
                    Arg Count: 3
                    Pos Only Arg Count: 0
                    KW Only Arg Count: 0
                    Stack Size: 8
                    Flags: 0x20000083 (CO_OPTIMIZED | CO_NEWLOCALS | CO_COROUTINE | CO_PYARMOR_OBFUSCATED)
                    [Names]
                        'id'
                        'append'
                        'get_input_user'
                        'get_input_entity'
                    [Locals+Names]
                        'self'
                        'client'
                        'utils'
                        '__assert_armored__'
                        '_var_var_1'
                        '_var_var_2'
                    [Constants]
                        None
                        '__pyarmor_assert_36936__'
                        '__pyarmor_enter_36937__'
                        b'<COAddr>\x05\x00\x00\x1e\xbc\x00\x00\x00\x00\x00\x00\x00\x00\x00\x00\x00\x00\x00\x00\x00'
                        '__pyarmor_exit_36938__'
                    [Disassembly]
                        0       RETURN_GENERATOR                
                        2       POP_TOP                         
                        4       NOP                             
                        6       NOP                             
                        8       PUSH_NULL                       
                        10      LOAD_CONST                      2: '__pyarmor_enter_36937__'
                        12      LOAD_CONST                      3: b'<COAddr>\x05\x00\x00\x1e\xbc\x00\x00\x00\x00\x00\x00\x00\x00\x00\x00\x00\x00\x00\x00\x00'
                        14      BUILD_TUPLE                     1
                        16      CALL_FUNCTION_EX                0
                        18      POP_TOP                         
                        20      RESUME                          0
                        22      NOP                             
                        24      NOP                             
                        26      NOP                             
                        28      NOP                             
                        30      NOP                             
                        32      BUILD_LIST                      0
                        34      STORE_FAST                      4: _var_var_1
                        36      LOAD_FAST                       0: self
                        38      LOAD_ATTR                       0: id
                        58      GET_ITER                        
                        60      FOR_ITER                        57 (to 176)
                        64      STORE_FAST                      5: _var_var_2
                        66      LOAD_FAST                       4: _var_var_1
                        68      LOAD_ATTR                       3: append
                        88      LOAD_FAST                       2: utils
                        90      LOAD_ATTR                       5: get_input_user
                        110     LOAD_FAST                       1: client
                        112     LOAD_ATTR                       7: get_input_entity
                        132     LOAD_FAST                       5: _var_var_2
                        134     CALL                            1
                        142     GET_AWAITABLE                   0
                        144     LOAD_CONST                      0: None
                        146     SEND                            3 (to 154)
                        150     YIELD_VALUE                     3
                        152     RESUME                          3
                        154     JUMP_BACKWARD_NO_INTERRUPT      5 (to 146)
                        156     END_SEND                        
                        158     CALL                            1
                        166     CALL                            1
                        174     POP_TOP                         
                        176     JUMP_BACKWARD                   59 (to 60)
                        178     END_FOR                         
                        180     LOAD_FAST                       4: _var_var_1
                        182     LOAD_FAST                       0: self
                        184     STORE_ATTR                      0: id
                        194     LOAD_CONST                      0: None
                        196     NOP                             
                        198     NOP                             
                        200     NOP                             
                        202     JUMP_FORWARD                    23 (to 250)
                        210     POP_TOP                         
                        212     RETURN_CONST                    0: None
                        214     CLEANUP_THROW                   
                        216     JUMP_BACKWARD                   31 (to 156)
                        218     PUSH_EXC_INFO                   
                        220     PUSH_NULL                       
                        222     LOAD_CONST                      4: '__pyarmor_exit_36938__'
                        224     NOP                             
                        226     LOAD_CONST                      3: b'<COAddr>\x05\x00\x00\x1e\xbc\x00\x00\x00\x00\x00\x00\x00\x00\x00\x00\x00\x00\x00\x00\x00'
                        228     CALL                            1
                        236     POP_TOP                         
                        238     RERAISE                         0
                        240     COPY                            3
                        242     POP_EXCEPT                      
                        244     RERAISE                         1
                        246     CALL_INTRINSIC_1                3 (INTRINSIC_STOPITERATION_ERROR)
                        248     RERAISE                         1
                        250     PUSH_NULL                       
                        252     LOAD_CONST                      4: '__pyarmor_exit_36938__'
                        254     LOAD_CONST                      3: b'<COAddr>\x05\x00\x00\x1e\xbc\x00\x00\x00\x00\x00\x00\x00\x00\x00\x00\x00\x00\x00\x00\x00'
                        256     BUILD_TUPLE                     1
                        258     CALL_FUNCTION_EX                0
                        260     POP_TOP                         
                        262     RETURN_VALUE                    
                    [Exception Table]
                        4 to 30 -> 246 [0] lasti
                        32 to 150 -> 218 [0] 
                        150 to 152 -> 214 [7] 
                        152 to 194 -> 218 [0] 
                        194 to 214 -> 246 [0] lasti
                        214 to 216 -> 218 [0] 
                        218 to 240 -> 240 [1] lasti
                        240 to 246 -> 246 [0] lasti
                [Code]
                    File Name: <frozen multithon.tl.functions.users>
                    Object Name: to_dict
                    Qualified Name: GetUsersRequest.to_dict
                    Arg Count: 1
                    Pos Only Arg Count: 0
                    KW Only Arg Count: 0
                    Stack Size: 8
                    Flags: 0x20000003 (CO_OPTIMIZED | CO_NEWLOCALS | CO_PYARMOR_OBFUSCATED)
                    [Names]
                        'id'
                        'isinstance'
                        'TLObject'
                        'to_dict'
                    [Locals+Names]
                        'self'
                        '__assert_armored__'
                        '_var_var_3'
                    [Constants]
                        None
                        '__pyarmor_assert_36939__'
                        '__pyarmor_enter_36940__'
                        b'<COAddr>\x07\x00\x00\x1a\xc0\x00\x00\x00\x00\x00\x00\x00\x00\x00\x00\x00\x00\x00\x00\x00'
                        'GetUsersRequest'   # b'\x81\xc5\x1d\x07\x06\xe9\xbb\xc0\x08\xc8\x08\xd1y\xe9\xeb\x91'
                        (
                            '_'
                            'id'
                        )
                        '__pyarmor_exit_36941__'
                    [Disassembly]
                        0       NOP                             
                        2       NOP                             
                        4       PUSH_NULL                       
                        6       LOAD_CONST                      2: '__pyarmor_enter_36940__'
                        8       LOAD_CONST                      3: b'<COAddr>\x07\x00\x00\x1a\xc0\x00\x00\x00\x00\x00\x00\x00\x00\x00\x00\x00\x00\x00\x00\x00'
                        10      BUILD_TUPLE                     1
                        12      CALL_FUNCTION_EX                0
                        14      POP_TOP                         
                        16      RESUME                          0
                        18      NOP                             
                        20      NOP                             
                        22      NOP                             
                        24      NOP                             
                        26      NOP                             
                        28      PUSH_NULL                       
                        30      LOAD_CONST                      1: '__pyarmor_assert_36939__'
                        32      LOAD_CONST                      4: 'GetUsersRequest'   # b'\x81\xc5\x1d\x07\x06\xe9\xbb\xc0\x08\xc8\x08\xd1y\xe9\xeb\x91'
                        34      CALL                            1
                        42      LOAD_FAST                       0: self
                        44      LOAD_ATTR                       0: id
                        64      POP_JUMP_IF_NOT_NONE            2 (to 70)
                        66      BUILD_LIST                      0
                        68      JUMP_FORWARD                    57 (to 184)
                        70      LOAD_FAST                       0: self
                        72      LOAD_ATTR                       0: id
                        92      GET_ITER                        
                        94      LOAD_FAST_AND_CLEAR             2: _var_var_3
                        96      SWAP                            2
                        98      BUILD_LIST                      0
                        100     SWAP                            2
                        102     FOR_ITER                        36 (to 176)
                        106     STORE_FAST                      2: _var_var_3
                        108     LOAD_GLOBAL                     3: NULL + isinstance
                        118     LOAD_FAST                       2: _var_var_3
                        120     LOAD_GLOBAL                     4: TLObject
                        130     CALL                            2
                        138     POP_JUMP_IF_FALSE               16 (to 172)
                        140     LOAD_FAST                       2: _var_var_3
                        142     LOAD_ATTR                       7: to_dict
                        162     CALL                            0
                        170     JUMP_FORWARD                    1 (to 174)
                        172     LOAD_FAST                       2: _var_var_3
                        174     LIST_APPEND                     2
                        176     JUMP_BACKWARD                   38 (to 102)
                        178     END_FOR                         
                        180     SWAP                            2
                        182     STORE_FAST                      2: _var_var_3
                        184     LOAD_CONST                      5: ('_', 'id')
                        186     BUILD_CONST_KEY_MAP             2
                        188     NOP                             
                        190     NOP                             
                        192     NOP                             
                        194     JUMP_FORWARD                    25 (to 246)
                        196     CALL                            1
                        204     POP_TOP                         
                        206     RETURN_VALUE                    
                        208     SWAP                            2
                        210     POP_TOP                         
                        212     SWAP                            2
                        214     STORE_FAST                      2: _var_var_3
                        216     RERAISE                         0
                        218     PUSH_EXC_INFO                   
                        220     PUSH_NULL                       
                        222     LOAD_CONST                      6: '__pyarmor_exit_36941__'
                        224     NOP                             
                        226     LOAD_CONST                      3: b'<COAddr>\x07\x00\x00\x1a\xc0\x00\x00\x00\x00\x00\x00\x00\x00\x00\x00\x00\x00\x00\x00\x00'
                        228     CALL                            1
                        236     POP_TOP                         
                        238     RERAISE                         0
                        240     COPY                            3
                        242     POP_EXCEPT                      
                        244     RERAISE                         1
                        246     PUSH_NULL                       
                        248     LOAD_CONST                      6: '__pyarmor_exit_36941__'
                        250     LOAD_CONST                      3: b'<COAddr>\x07\x00\x00\x1a\xc0\x00\x00\x00\x00\x00\x00\x00\x00\x00\x00\x00\x00\x00\x00\x00'
                        252     BUILD_TUPLE                     1
                        254     CALL_FUNCTION_EX                0
                        256     POP_TOP                         
                        258     RETURN_VALUE                    
                    [Exception Table]
                        28 to 98 -> 218 [0] 
                        98 to 180 -> 208 [3] 
                        180 to 188 -> 218 [0] 
                        208 to 218 -> 218 [0] 
                        218 to 240 -> 240 [1] lasti
                [Code]
                    File Name: <frozen multithon.tl.functions.users>
                    Object Name: _bytes
                    Qualified Name: GetUsersRequest._bytes
                    Arg Count: 1
                    Pos Only Arg Count: 0
                    KW Only Arg Count: 0
                    Stack Size: 10
                    Flags: 0x20000003 (CO_OPTIMIZED | CO_NEWLOCALS | CO_PYARMOR_OBFUSCATED)
                    [Names]
                        'join'
                        'struct'
                        'pack'
                        'len'
                        'id'
                    [Locals+Names]
                        'self'
                        '__assert_armored__'
                    [Constants]
                        None
                        '__pyarmor_assert_36942__'
                        '__pyarmor_enter_36943__'
                        b'<COAddr>\x05\x00\x00\x1a\xcc\x00\x00\x00\x00\x00\x00\x00\x00\x00\x00\x00\x00\x00\x00\x00'
                        b''
                        b'H\xa5\x91\r'
                        b'\x15\xc4\xb5\x1c'
                        '<i'
                        [Code]
                            File Name: <frozen multithon.tl.functions.users>
                            Object Name: <genexpr>
                            Qualified Name: GetUsersRequest._bytes.<locals>.<genexpr>
                            Arg Count: 1
                            Pos Only Arg Count: 0
                            KW Only Arg Count: 0
                            Stack Size: 3
                            Flags: 0x00000033 (CO_OPTIMIZED | CO_NEWLOCALS | CO_NESTED | CO_GENERATOR)
                            [Names]
                                '_bytes'
                            [Locals+Names]
                                '.0'
                                '_var_var_3'
                            [Constants]
                                None
                            [Disassembly]
                                0       RETURN_GENERATOR                
                                2       POP_TOP                         
                                4       RESUME                          0
                                6       LOAD_FAST                       0: .0
                                8       FOR_ITER                        20 (to 50)
                                12      STORE_FAST                      1: _var_var_3
                                14      LOAD_FAST                       1: _var_var_3
                                16      LOAD_ATTR                       1: _bytes
                                36      CALL                            0
                                44      YIELD_VALUE                     1
                                46      RESUME                          1
                                48      POP_TOP                         
                                50      JUMP_BACKWARD                   22 (to 8)
                                52      END_FOR                         
                                54      RETURN_CONST                    0: None
                                56      CALL_INTRINSIC_1                3 (INTRINSIC_STOPITERATION_ERROR)
                                58      RERAISE                         1
                            [Exception Table]
                                4 to 56 -> 56 [0] lasti
                        '__pyarmor_exit_36944__'
                    [Disassembly]
                        0       NOP                             
                        2       NOP                             
                        4       PUSH_NULL                       
                        6       LOAD_CONST                      2: '__pyarmor_enter_36943__'
                        8       LOAD_CONST                      3: b'<COAddr>\x05\x00\x00\x1a\xcc\x00\x00\x00\x00\x00\x00\x00\x00\x00\x00\x00\x00\x00\x00\x00'
                        10      BUILD_TUPLE                     1
                        12      CALL_FUNCTION_EX                0
                        14      POP_TOP                         
                        16      RESUME                          0
                        18      NOP                             
                        20      NOP                             
                        22      NOP                             
                        24      NOP                             
                        26      NOP                             
                        28      LOAD_CONST                      4: b''
                        30      LOAD_ATTR                       1: join
                        50      LOAD_CONST                      5: b'H\xa5\x91\r'
                        52      LOAD_CONST                      6: b'\x15\xc4\xb5\x1c'
                        54      LOAD_GLOBAL                     3: NULL + struct
                        64      LOAD_ATTR                       4: pack
                        84      LOAD_CONST                      7: '<i'
                        86      LOAD_GLOBAL                     7: NULL + len
                        96      LOAD_FAST                       0: self
                        98      LOAD_ATTR                       8: id
                        118     CALL                            1
                        126     CALL                            2
                        134     LOAD_CONST                      4: b''
                        136     LOAD_ATTR                       1: join
                        156     LOAD_CONST                      8: <CODE> <genexpr>
                        158     MAKE_FUNCTION                   0
                        160     LOAD_FAST                       0: self
                        162     LOAD_ATTR                       8: id
                        182     GET_ITER                        
                        184     CALL                            0
                        192     CALL                            1
                        200     BUILD_TUPLE                     4
                        202     CALL                            1
                        210     NOP                             
                        212     NOP                             
                        214     NOP                             
                        216     JUMP_FORWARD                    20 (to 258)
                        218     CALL                            1
                        226     POP_TOP                         
                        228     RETURN_VALUE                    
                        230     PUSH_EXC_INFO                   
                        232     PUSH_NULL                       
                        234     LOAD_CONST                      9: '__pyarmor_exit_36944__'
                        236     NOP                             
                        238     LOAD_CONST                      3: b'<COAddr>\x05\x00\x00\x1a\xcc\x00\x00\x00\x00\x00\x00\x00\x00\x00\x00\x00\x00\x00\x00\x00'
                        240     CALL                            1
                        248     POP_TOP                         
                        250     RERAISE                         0
                        252     COPY                            3
                        254     POP_EXCEPT                      
                        256     RERAISE                         1
                        258     PUSH_NULL                       
                        260     LOAD_CONST                      9: '__pyarmor_exit_36944__'
                        262     LOAD_CONST                      3: b'<COAddr>\x05\x00\x00\x1a\xcc\x00\x00\x00\x00\x00\x00\x00\x00\x00\x00\x00\x00\x00\x00\x00'
                        264     BUILD_TUPLE                     1
                        266     CALL_FUNCTION_EX                0
                        268     POP_TOP                         
                        270     RETURN_VALUE                    
                    [Exception Table]
                        28 to 210 -> 230 [0] 
                        230 to 252 -> 252 [1] lasti
                [Code]
                    File Name: <frozen multithon.tl.functions.users>
                    Object Name: from_reader
                    Qualified Name: GetUsersRequest.from_reader
                    Arg Count: 2
                    Pos Only Arg Count: 0
                    KW Only Arg Count: 0
                    Stack Size: 5
                    Flags: 0x20000003 (CO_OPTIMIZED | CO_NEWLOCALS | CO_PYARMOR_OBFUSCATED)
                    [Names]
                        'read_int'
                        'range'
                        'tgread_object'
                        'append'
                    [Locals+Names]
                        'cls'
                        'reader'
                        '__assert_armored__'
                        '_var_var_0'
                        '_var_var_4'
                        '_var_var_2'
                    [Constants]
                        None
                        '__pyarmor_assert_36945__'
                        '__pyarmor_enter_36946__'
                        b'<COAddr>\x05\x00\x00\x1a\xc8\x00\x00\x00\x00\x00\x00\x00\x00\x00\x00\x00\x00\x00\x00\x00'
                        (
                            'id'
                        )
                        '__pyarmor_exit_36947__'
                    [Disassembly]
                        0       NOP                             
                        2       NOP                             
                        4       PUSH_NULL                       
                        6       LOAD_CONST                      2: '__pyarmor_enter_36946__'
                        8       LOAD_CONST                      3: b'<COAddr>\x05\x00\x00\x1a\xc8\x00\x00\x00\x00\x00\x00\x00\x00\x00\x00\x00\x00\x00\x00\x00'
                        10      BUILD_TUPLE                     1
                        12      CALL_FUNCTION_EX                0
                        14      POP_TOP                         
                        16      RESUME                          0
                        18      NOP                             
                        20      NOP                             
                        22      NOP                             
                        24      NOP                             
                        26      NOP                             
                        28      LOAD_FAST                       1: reader
                        30      LOAD_ATTR                       1: read_int
                        50      CALL                            0
                        58      POP_TOP                         
                        60      BUILD_LIST                      0
                        62      STORE_FAST                      3: _var_var_0
                        64      LOAD_GLOBAL                     3: NULL + range
                        74      LOAD_FAST                       1: reader
                        76      LOAD_ATTR                       1: read_int
                        96      CALL                            0
                        104     CALL                            1
                        112     GET_ITER                        
                        114     FOR_ITER                        35 (to 186)
                        118     STORE_FAST                      4: _var_var_4
                        120     LOAD_FAST                       1: reader
                        122     LOAD_ATTR                       5: tgread_object
                        142     CALL                            0
                        150     STORE_FAST                      5: _var_var_2
                        152     LOAD_FAST                       3: _var_var_0
                        154     LOAD_ATTR                       7: append
                        174     LOAD_FAST                       5: _var_var_2
                        176     CALL                            1
                        184     POP_TOP                         
                        186     JUMP_BACKWARD                   37 (to 114)
                        188     END_FOR                         
                        190     PUSH_NULL                       
                        192     LOAD_FAST                       0: cls
                        194     LOAD_FAST                       3: _var_var_0
                        196     KW_NAMES                        4: ('id',)
                        198     CALL                            1
                        206     NOP                             
                        208     NOP                             
                        210     NOP                             
                        212     JUMP_FORWARD                    20 (to 254)
                        214     CALL                            1
                        222     POP_TOP                         
                        224     RETURN_VALUE                    
                        226     PUSH_EXC_INFO                   
                        228     PUSH_NULL                       
                        230     LOAD_CONST                      5: '__pyarmor_exit_36947__'
                        232     NOP                             
                        234     LOAD_CONST                      3: b'<COAddr>\x05\x00\x00\x1a\xc8\x00\x00\x00\x00\x00\x00\x00\x00\x00\x00\x00\x00\x00\x00\x00'
                        236     CALL                            1
                        244     POP_TOP                         
                        246     RERAISE                         0
                        248     COPY                            3
                        250     POP_EXCEPT                      
                        252     RERAISE                         1
                        254     PUSH_NULL                       
                        256     LOAD_CONST                      5: '__pyarmor_exit_36947__'
                        258     LOAD_CONST                      3: b'<COAddr>\x05\x00\x00\x1a\xc8\x00\x00\x00\x00\x00\x00\x00\x00\x00\x00\x00\x00\x00\x00\x00'
                        260     BUILD_TUPLE                     1
                        262     CALL_FUNCTION_EX                0
                        264     POP_TOP                         
                        266     RETURN_VALUE                    
                    [Exception Table]
                        28 to 206 -> 226 [0] 
                        226 to 248 -> 248 [1] lasti
                '__pyarmor_exit_36932__'
                None
            [Disassembly]
                0       NOP                             
                2       LOAD_NAME                       0: __name__
                4       STORE_NAME                      1: __module__
                6       LOAD_CONST                      0: 'GetUsersRequest'
                8       STORE_NAME                      2: __qualname__
                10      NOP                             
                12      PUSH_NULL                       
                14      LOAD_CONST                      2: '__pyarmor_enter_36931__'
                16      LOAD_CONST                      3: b'<COAddr>\x07\x00\x00"^\x00\x00\x00\x00\x00\x00\x00\x00\x00\x00\x00\x00\x00\x00\x00'
                18      BUILD_TUPLE                     1
                20      CALL_FUNCTION_EX                0
                22      POP_TOP                         
                24      RESUME                          0
                26      NOP                             
                28      NOP                             
                30      NOP                             
                32      NOP                             
                34      NOP                             
                36      LOAD_CONST                      4: 227648840
                38      STORE_NAME                      4: CONSTRUCTOR_ID
                40      LOAD_CONST                      5: 67557965
                42      STORE_NAME                      5: SUBCLASS_OF_ID
                44      LOAD_CONST                      6: 'id'
                46      LOAD_NAME                       6: List
                48      PUSH_NULL                       
                50      LOAD_CONST                      1: '__pyarmor_assert_36930__'
                52      LOAD_CONST                      7: 'TypeInputUser'   # b'\x81\xd6\x01\x036\xd3\xb0\xc2\x0e\xee8\xd3i\xfe'
                54      CALL                            1
                62      BINARY_SUBSCR                   
                66      BUILD_TUPLE                     2
                68      LOAD_CONST                      8: <CODE> __init__
                70      MAKE_FUNCTION                   4
                72      STORE_NAME                      7: __init__
                74      LOAD_CONST                      9: <CODE> resolve
                76      MAKE_FUNCTION                   0
                78      STORE_NAME                      8: resolve
                80      LOAD_CONST                      10: <CODE> to_dict
                82      MAKE_FUNCTION                   0
                84      STORE_NAME                      9: to_dict
                86      LOAD_CONST                      11: <CODE> _bytes
                88      MAKE_FUNCTION                   0
                90      STORE_NAME                      10: _bytes
                92      LOAD_NAME                       11: classmethod
                94      LOAD_CONST                      12: <CODE> from_reader
                96      MAKE_FUNCTION                   0
                98      CALL                            0
                106     STORE_NAME                      12: from_reader
                108     LOAD_CONST                      14: None
                110     NOP                             
                112     NOP                             
                114     NOP                             
                116     JUMP_FORWARD                    19 (to 156)
                124     POP_TOP                         
                126     RETURN_CONST                    14: None
                128     PUSH_EXC_INFO                   
                130     PUSH_NULL                       
                132     LOAD_CONST                      13: '__pyarmor_exit_36932__'
                134     NOP                             
                136     LOAD_CONST                      3: b'<COAddr>\x07\x00\x00"^\x00\x00\x00\x00\x00\x00\x00\x00\x00\x00\x00\x00\x00\x00\x00'
                138     CALL                            1
                146     POP_TOP                         
                148     RERAISE                         0
                150     COPY                            3
                152     POP_EXCEPT                      
                154     RERAISE                         1
                156     PUSH_NULL                       
                158     LOAD_CONST                      13: '__pyarmor_exit_36932__'
                160     LOAD_CONST                      3: b'<COAddr>\x07\x00\x00"^\x00\x00\x00\x00\x00\x00\x00\x00\x00\x00\x00\x00\x00\x00\x00'
                162     BUILD_TUPLE                     1
                164     CALL_FUNCTION_EX                0
                166     POP_TOP                         
                168     RETURN_VALUE                    
            [Exception Table]
                36 to 108 -> 128 [0] 
                128 to 150 -> 150 [1] lasti
        'GetUsersRequest'
        [Code]
            File Name: <frozen multithon.tl.functions.users>
            Object Name: SetSecureValueErrorsRequest
            Qualified Name: SetSecureValueErrorsRequest
            Arg Count: 0
            Pos Only Arg Count: 0
            KW Only Arg Count: 0
            Stack Size: 7
            Flags: 0x20000000 (CO_PYARMOR_OBFUSCATED)
            [Names]
                '__name__'
                '__module__'
                '__qualname__'
                '__assert_armored__'
                'CONSTRUCTOR_ID'
                'SUBCLASS_OF_ID'
                'List'
                '__init__'
                'resolve'
                'to_dict'
                '_bytes'
                'classmethod'
                'from_reader'
            [Locals+Names]
            [Constants]
                'SetSecureValueErrorsRequest'
                '__pyarmor_assert_36948__'
                '__pyarmor_enter_36949__'
                b'<COAddr>\x07\x00\x00"n\x00\x00\x00\x00\x00\x00\x00\x00\x00\x00\x00\x00\x00\x00\x00'
                0x90C894B5
                0xF5B399AC
                'id'
                'TypeInputUser'   # b'\x81\xd6\x01\x036\xd3\xb0\xc2\x0e\xee8\xd3i\xfe'
                'errors'
                'TypeSecureValueError'   # b'\x81\xd6\x01\x036\xc9\xbb\xd1\x0e\xe8\x08\xf6m\xe0\xed\x80*O\xa9\xa8\xb8'
                [Code]
                    File Name: <frozen multithon.tl.functions.users>
                    Object Name: __init__
                    Qualified Name: SetSecureValueErrorsRequest.__init__
                    Arg Count: 3
                    Pos Only Arg Count: 0
                    KW Only Arg Count: 0
                    Stack Size: 5
                    Flags: 0x20000003 (CO_OPTIMIZED | CO_NEWLOCALS | CO_PYARMOR_OBFUSCATED)
                    [Names]
                        'id'
                        'errors'
                    [Locals+Names]
                        'self'
                        'id'
                        'errors'
                        '__assert_armored__'
                    [Constants]
                        '\n        :returns Bool: This type has no constructors.\n        '
                        '__pyarmor_assert_36951__'
                        '__pyarmor_enter_36952__'
                        b'<COAddr>\x05\x00\x00\x1a2\x00\x00\x00\x00\x00\x00\x00\x00\x00\x00\x00\x00\x00\x00\x00'
                        '__pyarmor_exit_36953__'
                        None
                    [Disassembly]
                        0       NOP                             
                        2       NOP                             
                        4       PUSH_NULL                       
                        6       LOAD_CONST                      2: '__pyarmor_enter_36952__'
                        8       LOAD_CONST                      3: b'<COAddr>\x05\x00\x00\x1a2\x00\x00\x00\x00\x00\x00\x00\x00\x00\x00\x00\x00\x00\x00\x00'
                        10      BUILD_TUPLE                     1
                        12      CALL_FUNCTION_EX                0
                        14      POP_TOP                         
                        16      RESUME                          0
                        18      NOP                             
                        20      NOP                             
                        22      NOP                             
                        24      NOP                             
                        26      NOP                             
                        28      LOAD_FAST                       1: id
                        30      LOAD_FAST                       0: self
                        32      STORE_ATTR                      0: id
                        42      LOAD_FAST                       2: errors
                        44      LOAD_FAST                       0: self
                        46      STORE_ATTR                      1: errors
                        56      LOAD_CONST                      5: None
                        58      NOP                             
                        60      NOP                             
                        62      NOP                             
                        64      JUMP_FORWARD                    19 (to 104)
                        72      POP_TOP                         
                        74      RETURN_CONST                    5: None
                        76      PUSH_EXC_INFO                   
                        78      PUSH_NULL                       
                        80      LOAD_CONST                      4: '__pyarmor_exit_36953__'
                        82      NOP                             
                        84      LOAD_CONST                      3: b'<COAddr>\x05\x00\x00\x1a2\x00\x00\x00\x00\x00\x00\x00\x00\x00\x00\x00\x00\x00\x00\x00'
                        86      CALL                            1
                        94      POP_TOP                         
                        96      RERAISE                         0
                        98      COPY                            3
                        100     POP_EXCEPT                      
                        102     RERAISE                         1
                        104     PUSH_NULL                       
                        106     LOAD_CONST                      4: '__pyarmor_exit_36953__'
                        108     LOAD_CONST                      3: b'<COAddr>\x05\x00\x00\x1a2\x00\x00\x00\x00\x00\x00\x00\x00\x00\x00\x00\x00\x00\x00\x00'
                        110     BUILD_TUPLE                     1
                        112     CALL_FUNCTION_EX                0
                        114     POP_TOP                         
                        116     RETURN_VALUE                    
                    [Exception Table]
                        28 to 56 -> 76 [0] 
                        76 to 98 -> 98 [1] lasti
                [Code]
                    File Name: <frozen multithon.tl.functions.users>
                    Object Name: resolve
                    Qualified Name: SetSecureValueErrorsRequest.resolve
                    Arg Count: 3
                    Pos Only Arg Count: 0
                    KW Only Arg Count: 0
                    Stack Size: 5
                    Flags: 0x20000083 (CO_OPTIMIZED | CO_NEWLOCALS | CO_COROUTINE | CO_PYARMOR_OBFUSCATED)
                    [Names]
                        'get_input_user'
                        'get_input_entity'
                        'id'
                    [Locals+Names]
                        'self'
                        'client'
                        'utils'
                        '__assert_armored__'
                    [Constants]
                        None
                        '__pyarmor_assert_36954__'
                        '__pyarmor_enter_36955__'
                        b'<COAddr>\x05\x00\x00\x1e\x88\x00\x00\x00\x00\x00\x00\x00\x00\x00\x00\x00\x00\x00\x00\x00'
                        '__pyarmor_exit_36956__'
                    [Disassembly]
                        0       RETURN_GENERATOR                
                        2       POP_TOP                         
                        4       NOP                             
                        6       NOP                             
                        8       PUSH_NULL                       
                        10      LOAD_CONST                      2: '__pyarmor_enter_36955__'
                        12      LOAD_CONST                      3: b'<COAddr>\x05\x00\x00\x1e\x88\x00\x00\x00\x00\x00\x00\x00\x00\x00\x00\x00\x00\x00\x00\x00'
                        14      BUILD_TUPLE                     1
                        16      CALL_FUNCTION_EX                0
                        18      POP_TOP                         
                        20      RESUME                          0
                        22      NOP                             
                        24      NOP                             
                        26      NOP                             
                        28      NOP                             
                        30      NOP                             
                        32      LOAD_FAST                       2: utils
                        34      LOAD_ATTR                       1: get_input_user
                        54      LOAD_FAST                       1: client
                        56      LOAD_ATTR                       3: get_input_entity
                        76      LOAD_FAST                       0: self
                        78      LOAD_ATTR                       4: id
                        98      CALL                            1
                        106     GET_AWAITABLE                   0
                        108     LOAD_CONST                      0: None
                        110     SEND                            3 (to 118)
                        114     YIELD_VALUE                     3
                        116     RESUME                          3
                        118     JUMP_BACKWARD_NO_INTERRUPT      5 (to 110)
                        120     END_SEND                        
                        122     CALL                            1
                        130     LOAD_FAST                       0: self
                        132     STORE_ATTR                      2: id
                        142     LOAD_CONST                      0: None
                        144     NOP                             
                        146     NOP                             
                        148     NOP                             
                        150     JUMP_FORWARD                    23 (to 198)
                        158     POP_TOP                         
                        160     RETURN_CONST                    0: None
                        162     CLEANUP_THROW                   
                        164     JUMP_BACKWARD                   23 (to 120)
                        166     PUSH_EXC_INFO                   
                        168     PUSH_NULL                       
                        170     LOAD_CONST                      4: '__pyarmor_exit_36956__'
                        172     NOP                             
                        174     LOAD_CONST                      3: b'<COAddr>\x05\x00\x00\x1e\x88\x00\x00\x00\x00\x00\x00\x00\x00\x00\x00\x00\x00\x00\x00\x00'
                        176     CALL                            1
                        184     POP_TOP                         
                        186     RERAISE                         0
                        188     COPY                            3
                        190     POP_EXCEPT                      
                        192     RERAISE                         1
                        194     CALL_INTRINSIC_1                3 (INTRINSIC_STOPITERATION_ERROR)
                        196     RERAISE                         1
                        198     PUSH_NULL                       
                        200     LOAD_CONST                      4: '__pyarmor_exit_36956__'
                        202     LOAD_CONST                      3: b'<COAddr>\x05\x00\x00\x1e\x88\x00\x00\x00\x00\x00\x00\x00\x00\x00\x00\x00\x00\x00\x00\x00'
                        204     BUILD_TUPLE                     1
                        206     CALL_FUNCTION_EX                0
                        208     POP_TOP                         
                        210     RETURN_VALUE                    
                    [Exception Table]
                        4 to 30 -> 194 [0] lasti
                        32 to 114 -> 166 [0] 
                        114 to 116 -> 162 [4] 
                        116 to 142 -> 166 [0] 
                        142 to 162 -> 194 [0] lasti
                        162 to 164 -> 166 [0] 
                        166 to 188 -> 188 [1] lasti
                        188 to 194 -> 194 [0] lasti
                [Code]
                    File Name: <frozen multithon.tl.functions.users>
                    Object Name: to_dict
                    Qualified Name: SetSecureValueErrorsRequest.to_dict
                    Arg Count: 1
                    Pos Only Arg Count: 0
                    KW Only Arg Count: 0
                    Stack Size: 9
                    Flags: 0x20000003 (CO_OPTIMIZED | CO_NEWLOCALS | CO_PYARMOR_OBFUSCATED)
                    [Names]
                        'isinstance'
                        'id'
                        'TLObject'
                        'to_dict'
                        'errors'
                    [Locals+Names]
                        'self'
                        '__assert_armored__'
                        '_var_var_3'
                    [Constants]
                        None
                        '__pyarmor_assert_36957__'
                        '__pyarmor_enter_36958__'
                        b'<COAddr>\x05\x00\x00\x1a>\x01\x00\x00\x00\x00\x00\x00\x00\x00\x00\x00\x00\x00\x00\x00'
                        'SetSecureValueErrorsRequest'   # b'\x81\xd1\x1d\x07\x00\xff\xbd\xc7\t\xff;\xc1`\xf9\xfd\xa0\x1dO\xb4\xb5\xb9\xf9K\xdd\x10j\xb0H'
                        (
                            '_'
                            'id'
                            'errors'
                        )
                        '__pyarmor_exit_36959__'
                    [Disassembly]
                        0       NOP                             
                        2       NOP                             
                        4       PUSH_NULL                       
                        6       LOAD_CONST                      2: '__pyarmor_enter_36958__'
                        8       LOAD_CONST                      3: b'<COAddr>\x05\x00\x00\x1a>\x01\x00\x00\x00\x00\x00\x00\x00\x00\x00\x00\x00\x00\x00\x00'
                        10      BUILD_TUPLE                     1
                        12      CALL_FUNCTION_EX                0
                        14      POP_TOP                         
                        16      RESUME                          0
                        18      NOP                             
                        20      NOP                             
                        22      NOP                             
                        24      NOP                             
                        26      NOP                             
                        28      PUSH_NULL                       
                        30      LOAD_CONST                      1: '__pyarmor_assert_36957__'
                        32      LOAD_CONST                      4: 'SetSecureValueErrorsRequest'   # b'\x81\xd1\x1d\x07\x00\xff\xbd\xc7\t\xff;\xc1`\xf9\xfd\xa0\x1dO\xb4\xb5\xb9\xf9K\xdd\x10j\xb0H'
                        34      CALL                            1
                        42      LOAD_GLOBAL                     1: NULL + isinstance
                        52      LOAD_FAST                       0: self
                        54      LOAD_ATTR                       2: id
                        74      LOAD_GLOBAL                     4: TLObject
                        84      CALL                            2
                        92      POP_JUMP_IF_FALSE               26 (to 146)
                        94      LOAD_FAST                       0: self
                        96      LOAD_ATTR                       2: id
                        116     LOAD_ATTR                       7: to_dict
                        136     CALL                            0
                        144     JUMP_FORWARD                    11 (to 168)
                        146     LOAD_FAST                       0: self
                        148     LOAD_ATTR                       2: id
                        168     LOAD_FAST                       0: self
                        170     LOAD_ATTR                       8: errors
                        190     POP_JUMP_IF_NOT_NONE            2 (to 196)
                        192     BUILD_LIST                      0
                        194     JUMP_FORWARD                    57 (to 310)
                        196     LOAD_FAST                       0: self
                        198     LOAD_ATTR                       8: errors
                        218     GET_ITER                        
                        220     LOAD_FAST_AND_CLEAR             2: _var_var_3
                        222     SWAP                            2
                        224     BUILD_LIST                      0
                        226     SWAP                            2
                        228     FOR_ITER                        36 (to 302)
                        232     STORE_FAST                      2: _var_var_3
                        234     LOAD_GLOBAL                     1: NULL + isinstance
                        244     LOAD_FAST                       2: _var_var_3
                        246     LOAD_GLOBAL                     4: TLObject
                        256     CALL                            2
                        264     POP_JUMP_IF_FALSE               16 (to 298)
                        266     LOAD_FAST                       2: _var_var_3
                        268     LOAD_ATTR                       7: to_dict
                        288     CALL                            0
                        296     JUMP_FORWARD                    1 (to 300)
                        298     LOAD_FAST                       2: _var_var_3
                        300     LIST_APPEND                     2
                        302     JUMP_BACKWARD                   38 (to 228)
                        304     END_FOR                         
                        306     SWAP                            2
                        308     STORE_FAST                      2: _var_var_3
                        310     LOAD_CONST                      5: ('_', 'id', 'errors')
                        312     BUILD_CONST_KEY_MAP             3
                        314     NOP                             
                        316     NOP                             
                        318     NOP                             
                        320     JUMP_FORWARD                    25 (to 372)
                        322     CALL                            1
                        330     POP_TOP                         
                        332     RETURN_VALUE                    
                        334     SWAP                            2
                        336     POP_TOP                         
                        338     SWAP                            2
                        340     STORE_FAST                      2: _var_var_3
                        342     RERAISE                         0
                        344     PUSH_EXC_INFO                   
                        346     PUSH_NULL                       
                        348     LOAD_CONST                      6: '__pyarmor_exit_36959__'
                        350     NOP                             
                        352     LOAD_CONST                      3: b'<COAddr>\x05\x00\x00\x1a>\x01\x00\x00\x00\x00\x00\x00\x00\x00\x00\x00\x00\x00\x00\x00'
                        354     CALL                            1
                        362     POP_TOP                         
                        364     RERAISE                         0
                        366     COPY                            3
                        368     POP_EXCEPT                      
                        370     RERAISE                         1
                        372     PUSH_NULL                       
                        374     LOAD_CONST                      6: '__pyarmor_exit_36959__'
                        376     LOAD_CONST                      3: b'<COAddr>\x05\x00\x00\x1a>\x01\x00\x00\x00\x00\x00\x00\x00\x00\x00\x00\x00\x00\x00\x00'
                        378     BUILD_TUPLE                     1
                        380     CALL_FUNCTION_EX                0
                        382     POP_TOP                         
                        384     RETURN_VALUE                    
                    [Exception Table]
                        28 to 224 -> 344 [0] 
                        224 to 306 -> 334 [4] 
                        306 to 314 -> 344 [0] 
                        334 to 344 -> 344 [0] 
                        344 to 366 -> 366 [1] lasti
                [Code]
                    File Name: <frozen multithon.tl.functions.users>
                    Object Name: _bytes
                    Qualified Name: SetSecureValueErrorsRequest._bytes
                    Arg Count: 1
                    Pos Only Arg Count: 0
                    KW Only Arg Count: 0
                    Stack Size: 11
                    Flags: 0x20000003 (CO_OPTIMIZED | CO_NEWLOCALS | CO_PYARMOR_OBFUSCATED)
                    [Names]
                        'join'
                        'id'
                        '_bytes'
                        'struct'
                        'pack'
                        'len'
                        'errors'
                    [Locals+Names]
                        'self'
                        '__assert_armored__'
                    [Constants]
                        None
                        '__pyarmor_assert_36960__'
                        '__pyarmor_enter_36961__'
                        b'<COAddr>\x07\x00\x00\x1a\xfe\x00\x00\x00\x00\x00\x00\x00\x00\x00\x00\x00\x00\x00\x00\x00'
                        b''
                        b'\xb5\x94\xc8\x90'
                        b'\x15\xc4\xb5\x1c'
                        '<i'
                        [Code]
                            File Name: <frozen multithon.tl.functions.users>
                            Object Name: <genexpr>
                            Qualified Name: SetSecureValueErrorsRequest._bytes.<locals>.<genexpr>
                            Arg Count: 1
                            Pos Only Arg Count: 0
                            KW Only Arg Count: 0
                            Stack Size: 3
                            Flags: 0x00000033 (CO_OPTIMIZED | CO_NEWLOCALS | CO_NESTED | CO_GENERATOR)
                            [Names]
                                '_bytes'
                            [Locals+Names]
                                '.0'
                                '_var_var_3'
                            [Constants]
                                None
                            [Disassembly]
                                0       RETURN_GENERATOR                
                                2       POP_TOP                         
                                4       RESUME                          0
                                6       LOAD_FAST                       0: .0
                                8       FOR_ITER                        20 (to 50)
                                12      STORE_FAST                      1: _var_var_3
                                14      LOAD_FAST                       1: _var_var_3
                                16      LOAD_ATTR                       1: _bytes
                                36      CALL                            0
                                44      YIELD_VALUE                     1
                                46      RESUME                          1
                                48      POP_TOP                         
                                50      JUMP_BACKWARD                   22 (to 8)
                                52      END_FOR                         
                                54      RETURN_CONST                    0: None
                                56      CALL_INTRINSIC_1                3 (INTRINSIC_STOPITERATION_ERROR)
                                58      RERAISE                         1
                            [Exception Table]
                                4 to 56 -> 56 [0] lasti
                        '__pyarmor_exit_36962__'
                    [Disassembly]
                        0       NOP                             
                        2       NOP                             
                        4       PUSH_NULL                       
                        6       LOAD_CONST                      2: '__pyarmor_enter_36961__'
                        8       LOAD_CONST                      3: b'<COAddr>\x07\x00\x00\x1a\xfe\x00\x00\x00\x00\x00\x00\x00\x00\x00\x00\x00\x00\x00\x00\x00'
                        10      BUILD_TUPLE                     1
                        12      CALL_FUNCTION_EX                0
                        14      POP_TOP                         
                        16      RESUME                          0
                        18      NOP                             
                        20      NOP                             
                        22      NOP                             
                        24      NOP                             
                        26      NOP                             
                        28      LOAD_CONST                      4: b''
                        30      LOAD_ATTR                       1: join
                        50      LOAD_CONST                      5: b'\xb5\x94\xc8\x90'
                        52      LOAD_FAST                       0: self
                        54      LOAD_ATTR                       2: id
                        74      LOAD_ATTR                       5: _bytes
                        94      CALL                            0
                        102     LOAD_CONST                      6: b'\x15\xc4\xb5\x1c'
                        104     LOAD_GLOBAL                     7: NULL + struct
                        114     LOAD_ATTR                       8: pack
                        134     LOAD_CONST                      7: '<i'
                        136     LOAD_GLOBAL                     11: NULL + len
                        146     LOAD_FAST                       0: self
                        148     LOAD_ATTR                       12: errors
                        168     CALL                            1
                        176     CALL                            2
                        184     LOAD_CONST                      4: b''
                        186     LOAD_ATTR                       1: join
                        206     LOAD_CONST                      8: <CODE> <genexpr>
                        208     MAKE_FUNCTION                   0
                        210     LOAD_FAST                       0: self
                        212     LOAD_ATTR                       12: errors
                        232     GET_ITER                        
                        234     CALL                            0
                        242     CALL                            1
                        250     BUILD_TUPLE                     5
                        252     CALL                            1
                        260     NOP                             
                        262     NOP                             
                        264     NOP                             
                        266     JUMP_FORWARD                    20 (to 308)
                        268     CALL                            1
                        276     POP_TOP                         
                        278     RETURN_VALUE                    
                        280     PUSH_EXC_INFO                   
                        282     PUSH_NULL                       
                        284     LOAD_CONST                      9: '__pyarmor_exit_36962__'
                        286     NOP                             
                        288     LOAD_CONST                      3: b'<COAddr>\x07\x00\x00\x1a\xfe\x00\x00\x00\x00\x00\x00\x00\x00\x00\x00\x00\x00\x00\x00\x00'
                        290     CALL                            1
                        298     POP_TOP                         
                        300     RERAISE                         0
                        302     COPY                            3
                        304     POP_EXCEPT                      
                        306     RERAISE                         1
                        308     PUSH_NULL                       
                        310     LOAD_CONST                      9: '__pyarmor_exit_36962__'
                        312     LOAD_CONST                      3: b'<COAddr>\x07\x00\x00\x1a\xfe\x00\x00\x00\x00\x00\x00\x00\x00\x00\x00\x00\x00\x00\x00\x00'
                        314     BUILD_TUPLE                     1
                        316     CALL_FUNCTION_EX                0
                        318     POP_TOP                         
                        320     RETURN_VALUE                    
                    [Exception Table]
                        28 to 260 -> 280 [0] 
                        280 to 302 -> 302 [1] lasti
                [Code]
                    File Name: <frozen multithon.tl.functions.users>
                    Object Name: from_reader
                    Qualified Name: SetSecureValueErrorsRequest.from_reader
                    Arg Count: 2
                    Pos Only Arg Count: 0
                    KW Only Arg Count: 0
                    Stack Size: 5
                    Flags: 0x20000003 (CO_OPTIMIZED | CO_NEWLOCALS | CO_PYARMOR_OBFUSCATED)
                    [Names]
                        'tgread_object'
                        'read_int'
                        'range'
                        'append'
                    [Locals+Names]
                        'cls'
                        'reader'
                        '__assert_armored__'
                        '_var_var_0'
                        '_var_var_5'
                        '_var_var_4'
                        '_var_var_2'
                    [Constants]
                        None
                        '__pyarmor_assert_36963__'
                        '__pyarmor_enter_36964__'
                        b'<COAddr>\x07\x00\x00\x1a\xea\x00\x00\x00\x00\x00\x00\x00\x00\x00\x00\x00\x00\x00\x00\x00'
                        (
                            'id'
                            'errors'
                        )
                        '__pyarmor_exit_36965__'
                    [Disassembly]
                        0       NOP                             
                        2       NOP                             
                        4       PUSH_NULL                       
                        6       LOAD_CONST                      2: '__pyarmor_enter_36964__'
                        8       LOAD_CONST                      3: b'<COAddr>\x07\x00\x00\x1a\xea\x00\x00\x00\x00\x00\x00\x00\x00\x00\x00\x00\x00\x00\x00\x00'
                        10      BUILD_TUPLE                     1
                        12      CALL_FUNCTION_EX                0
                        14      POP_TOP                         
                        16      RESUME                          0
                        18      NOP                             
                        20      NOP                             
                        22      NOP                             
                        24      NOP                             
                        26      NOP                             
                        28      LOAD_FAST                       1: reader
                        30      LOAD_ATTR                       1: tgread_object
                        50      CALL                            0
                        58      STORE_FAST                      3: _var_var_0
                        60      LOAD_FAST                       1: reader
                        62      LOAD_ATTR                       3: read_int
                        82      CALL                            0
                        90      POP_TOP                         
                        92      BUILD_LIST                      0
                        94      STORE_FAST                      4: _var_var_5
                        96      LOAD_GLOBAL                     5: NULL + range
                        106     LOAD_FAST                       1: reader
                        108     LOAD_ATTR                       3: read_int
                        128     CALL                            0
                        136     CALL                            1
                        144     GET_ITER                        
                        146     FOR_ITER                        35 (to 218)
                        150     STORE_FAST                      5: _var_var_4
                        152     LOAD_FAST                       1: reader
                        154     LOAD_ATTR                       1: tgread_object
                        174     CALL                            0
                        182     STORE_FAST                      6: _var_var_2
                        184     LOAD_FAST                       4: _var_var_5
                        186     LOAD_ATTR                       7: append
                        206     LOAD_FAST                       6: _var_var_2
                        208     CALL                            1
                        216     POP_TOP                         
                        218     JUMP_BACKWARD                   37 (to 146)
                        220     END_FOR                         
                        222     PUSH_NULL                       
                        224     LOAD_FAST                       0: cls
                        226     LOAD_FAST                       3: _var_var_0
                        228     LOAD_FAST                       4: _var_var_5
                        230     KW_NAMES                        4: ('id', 'errors')
                        232     CALL                            2
                        240     NOP                             
                        242     NOP                             
                        244     NOP                             
                        246     JUMP_FORWARD                    20 (to 288)
                        248     CALL                            1
                        256     POP_TOP                         
                        258     RETURN_VALUE                    
                        260     PUSH_EXC_INFO                   
                        262     PUSH_NULL                       
                        264     LOAD_CONST                      5: '__pyarmor_exit_36965__'
                        266     NOP                             
                        268     LOAD_CONST                      3: b'<COAddr>\x07\x00\x00\x1a\xea\x00\x00\x00\x00\x00\x00\x00\x00\x00\x00\x00\x00\x00\x00\x00'
                        270     CALL                            1
                        278     POP_TOP                         
                        280     RERAISE                         0
                        282     COPY                            3
                        284     POP_EXCEPT                      
                        286     RERAISE                         1
                        288     PUSH_NULL                       
                        290     LOAD_CONST                      5: '__pyarmor_exit_36965__'
                        292     LOAD_CONST                      3: b'<COAddr>\x07\x00\x00\x1a\xea\x00\x00\x00\x00\x00\x00\x00\x00\x00\x00\x00\x00\x00\x00\x00'
                        294     BUILD_TUPLE                     1
                        296     CALL_FUNCTION_EX                0
                        298     POP_TOP                         
                        300     RETURN_VALUE                    
                    [Exception Table]
                        28 to 240 -> 260 [0] 
                        260 to 282 -> 282 [1] lasti
                '__pyarmor_exit_36950__'
                None
            [Disassembly]
                0       NOP                             
                2       LOAD_NAME                       0: __name__
                4       STORE_NAME                      1: __module__
                6       LOAD_CONST                      0: 'SetSecureValueErrorsRequest'
                8       STORE_NAME                      2: __qualname__
                10      NOP                             
                12      PUSH_NULL                       
                14      LOAD_CONST                      2: '__pyarmor_enter_36949__'
                16      LOAD_CONST                      3: b'<COAddr>\x07\x00\x00"n\x00\x00\x00\x00\x00\x00\x00\x00\x00\x00\x00\x00\x00\x00\x00'
                18      BUILD_TUPLE                     1
                20      CALL_FUNCTION_EX                0
                22      POP_TOP                         
                24      RESUME                          0
                26      NOP                             
                28      NOP                             
                30      NOP                             
                32      NOP                             
                34      NOP                             
                36      LOAD_CONST                      4: 0x90C894B5
                38      STORE_NAME                      4: CONSTRUCTOR_ID
                40      LOAD_CONST                      5: 0xF5B399AC
                42      STORE_NAME                      5: SUBCLASS_OF_ID
                44      LOAD_CONST                      6: 'id'
                46      PUSH_NULL                       
                48      LOAD_CONST                      1: '__pyarmor_assert_36948__'
                50      LOAD_CONST                      7: 'TypeInputUser'   # b'\x81\xd6\x01\x036\xd3\xb0\xc2\x0e\xee8\xd3i\xfe'
                52      CALL                            1
                60      LOAD_CONST                      8: 'errors'
                62      LOAD_NAME                       6: List
                64      PUSH_NULL                       
                66      LOAD_CONST                      1: '__pyarmor_assert_36948__'
                68      LOAD_CONST                      9: 'TypeSecureValueError'   # b'\x81\xd6\x01\x036\xc9\xbb\xd1\x0e\xe8\x08\xf6m\xe0\xed\x80*O\xa9\xa8\xb8'
                70      CALL                            1
                78      BINARY_SUBSCR                   
                82      BUILD_TUPLE                     4
                84      LOAD_CONST                      10: <CODE> __init__
                86      MAKE_FUNCTION                   4
                88      STORE_NAME                      7: __init__
                90      LOAD_CONST                      11: <CODE> resolve
                92      MAKE_FUNCTION                   0
                94      STORE_NAME                      8: resolve
                96      LOAD_CONST                      12: <CODE> to_dict
                98      MAKE_FUNCTION                   0
                100     STORE_NAME                      9: to_dict
                102     LOAD_CONST                      13: <CODE> _bytes
                104     MAKE_FUNCTION                   0
                106     STORE_NAME                      10: _bytes
                108     LOAD_NAME                       11: classmethod
                110     LOAD_CONST                      14: <CODE> from_reader
                112     MAKE_FUNCTION                   0
                114     CALL                            0
                122     STORE_NAME                      12: from_reader
                124     LOAD_CONST                      16: None
                126     NOP                             
                128     NOP                             
                130     NOP                             
                132     JUMP_FORWARD                    19 (to 172)
                140     POP_TOP                         
                142     RETURN_CONST                    16: None
                144     PUSH_EXC_INFO                   
                146     PUSH_NULL                       
                148     LOAD_CONST                      15: '__pyarmor_exit_36950__'
                150     NOP                             
                152     LOAD_CONST                      3: b'<COAddr>\x07\x00\x00"n\x00\x00\x00\x00\x00\x00\x00\x00\x00\x00\x00\x00\x00\x00\x00'
                154     CALL                            1
                162     POP_TOP                         
                164     RERAISE                         0
                166     COPY                            3
                168     POP_EXCEPT                      
                170     RERAISE                         1
                172     PUSH_NULL                       
                174     LOAD_CONST                      15: '__pyarmor_exit_36950__'
                176     LOAD_CONST                      3: b'<COAddr>\x07\x00\x00"n\x00\x00\x00\x00\x00\x00\x00\x00\x00\x00\x00\x00\x00\x00\x00'
                178     BUILD_TUPLE                     1
                180     CALL_FUNCTION_EX                0
                182     POP_TOP                         
                184     RETURN_VALUE                    
            [Exception Table]
                36 to 124 -> 144 [0] 
                144 to 166 -> 166 [1] lasti
        'SetSecureValueErrorsRequest'
        '__pyarmor_exit_36875__'
    [Disassembly]
        0       NOP                             
        2       NOP                             
        4       PUSH_NULL                       
        6       LOAD_CONST                      1: '__pyarmor_enter_36874__'
        8       LOAD_CONST                      2: b'<COAddr>\x05\x00\x00\x1a\xf2\x00\x00\x00\x00\x00\x00\x00\x00\x00\x00\x00\x00\x00\x00\x00'
        10      BUILD_TUPLE                     1
        12      CALL_FUNCTION_EX                0
        14      POP_TOP                         
        16      RESUME                          0
        18      NOP                             
        20      NOP                             
        22      NOP                             
        24      NOP                             
        26      PUSH_NULL                       
        28      LOAD_CONST                      0: '__pyarmor_assert_36873__'
        30      LOAD_CONST                      3: "File generated by TLObjects' generator. All changes will be ERASED"   # b'\x81\xc4\x11\x1f6\xba\xb9\xd7\x15\xff\x1f\xc1x\xe9\xfc\xc5\rD\xfb\x93\x86\xe4L\xc6\x00l\xb7OG\xf1\x19\xe04W2\x0c\x8c\xc5\xa6`X\xc8\xf4Q\x9d\xdb\x07F9\xeaS\xe8\xc7g\x0f\xe1;\xab\x99\x18Xn\x03rdm!'
        32      CALL                            1
        40      POP_TOP                         
        42      LOAD_CONST                      4: 3
        44      LOAD_CONST                      5: ('TLObject',)
        46      IMPORT_NAME                     1: tl.tlobject
        48      IMPORT_FROM                     2: TLObject
        50      STORE_NAME                      2: TLObject
        52      POP_TOP                         
        54      LOAD_CONST                      4: 3
        56      LOAD_CONST                      6: ('TLRequest',)
        58      IMPORT_NAME                     1: tl.tlobject
        60      IMPORT_FROM                     3: TLRequest
        62      STORE_NAME                      3: TLRequest
        64      POP_TOP                         
        66      LOAD_CONST                      7: 0
        68      LOAD_CONST                      8: ('Optional', 'List', 'Union', 'TYPE_CHECKING')
        70      IMPORT_NAME                     4: typing
        72      IMPORT_FROM                     5: Optional
        74      STORE_NAME                      5: Optional
        76      IMPORT_FROM                     6: List
        78      STORE_NAME                      6: List
        80      IMPORT_FROM                     7: Union
        82      STORE_NAME                      7: Union
        84      IMPORT_FROM                     8: TYPE_CHECKING
        86      STORE_NAME                      8: TYPE_CHECKING
        88      POP_TOP                         
        90      LOAD_CONST                      7: 0
        92      LOAD_CONST                      9: None
        94      IMPORT_NAME                     9: os
        96      STORE_NAME                      9: os
        98      LOAD_CONST                      7: 0
        100     LOAD_CONST                      9: None
        102     IMPORT_NAME                     10: struct
        104     STORE_NAME                      10: struct
        106     LOAD_CONST                      7: 0
        108     LOAD_CONST                      10: ('datetime',)
        110     IMPORT_NAME                     11: datetime
        112     IMPORT_FROM                     11: datetime
        114     STORE_NAME                      11: datetime
        116     POP_TOP                         
        118     LOAD_NAME                       8: TYPE_CHECKING
        120     POP_JUMP_IF_FALSE               8 (to 138)
        122     LOAD_CONST                      4: 3
        124     LOAD_CONST                      11: ('TypeInputUser', 'TypeSecureValueError')
        126     IMPORT_NAME                     12: tl.types
        128     IMPORT_FROM                     13: TypeInputUser
        130     STORE_NAME                      13: TypeInputUser
        132     IMPORT_FROM                     14: TypeSecureValueError
        134     STORE_NAME                      14: TypeSecureValueError
        136     POP_TOP                         
        138     PUSH_NULL                       
        140     LOAD_BUILD_CLASS                
        142     LOAD_CONST                      12: <CODE> GetFullUserRequest
        144     MAKE_FUNCTION                   0
        146     LOAD_CONST                      13: 'GetFullUserRequest'
        148     LOAD_NAME                       3: TLRequest
        150     CALL                            3
        158     STORE_NAME                      15: GetFullUserRequest
        160     PUSH_NULL                       
        162     LOAD_BUILD_CLASS                
        164     LOAD_CONST                      14: <CODE> GetRequirementsToContactRequest
        166     MAKE_FUNCTION                   0
        168     LOAD_CONST                      15: 'GetRequirementsToContactRequest'
        170     LOAD_NAME                       3: TLRequest
        172     CALL                            3
        180     STORE_NAME                      16: GetRequirementsToContactRequest
        182     PUSH_NULL                       
        184     LOAD_BUILD_CLASS                
        186     LOAD_CONST                      16: <CODE> GetIsPremiumRequiredToContactRequest
        188     MAKE_FUNCTION                   0
        190     LOAD_CONST                      17: 'GetIsPremiumRequiredToContactRequest'
        192     LOAD_NAME                       3: TLRequest
        194     CALL                            3
        202     STORE_NAME                      17: GetIsPremiumRequiredToContactRequest
        204     PUSH_NULL                       
        206     LOAD_BUILD_CLASS                
        208     LOAD_CONST                      18: <CODE> GetUsersRequest
        210     MAKE_FUNCTION                   0
        212     LOAD_CONST                      19: 'GetUsersRequest'
        214     LOAD_NAME                       3: TLRequest
        216     CALL                            3
        224     STORE_NAME                      18: GetUsersRequest
        226     PUSH_NULL                       
        228     LOAD_BUILD_CLASS                
        230     LOAD_CONST                      20: <CODE> SetSecureValueErrorsRequest
        232     MAKE_FUNCTION                   0
        234     LOAD_CONST                      21: 'SetSecureValueErrorsRequest'
        236     LOAD_NAME                       3: TLRequest
        238     CALL                            3
        246     STORE_NAME                      19: SetSecureValueErrorsRequest
        248     LOAD_CONST                      9: None
        250     NOP                             
        252     NOP                             
        254     NOP                             
        256     JUMP_FORWARD                    19 (to 296)
        264     POP_TOP                         
        266     RETURN_CONST                    9: None
        268     PUSH_EXC_INFO                   
        270     PUSH_NULL                       
        272     LOAD_CONST                      22: '__pyarmor_exit_36875__'
        274     NOP                             
        276     LOAD_CONST                      2: b'<COAddr>\x05\x00\x00\x1a\xf2\x00\x00\x00\x00\x00\x00\x00\x00\x00\x00\x00\x00\x00\x00\x00'
        278     CALL                            1
        286     POP_TOP                         
        288     RERAISE                         0
        290     COPY                            3
        292     POP_EXCEPT                      
        294     RERAISE                         1
        296     PUSH_NULL                       
        298     LOAD_CONST                      22: '__pyarmor_exit_36875__'
        300     LOAD_CONST                      2: b'<COAddr>\x05\x00\x00\x1a\xf2\x00\x00\x00\x00\x00\x00\x00\x00\x00\x00\x00\x00\x00\x00\x00'
        302     BUILD_TUPLE                     1
        304     CALL_FUNCTION_EX                0
        306     POP_TOP                         
        308     RETURN_VALUE                    
    [Exception Table]
        26 to 248 -> 268 [0] 
        268 to 290 -> 290 [1] lasti
