#decoded by lolz.live/mrpenny / t.me/zeus_jackpot
# ================================
# Примечания по Pyarmor:
# - Байт-код и объекты кода Pyarmor соответствуют стандартному Python, но присутствуют специальные вызовы функций среды выполнения (runtime) Pyarmor.
# - Вызовы строк — это не ошибки, а маркеры, которые обрабатываются Pyarmor во время выполнения.
#
# Руководство по декомпиляции (без среды выполнения):
# 1. Игнорируйте зашифрованные байты после `#`; используйте только строку до `#`.
# 2. Удалите "__pyarmor_enter_xxx__"(b"<COAddr>...") и "__pyarmor_leave_xxx__"(b"<COAddr>...") (пролог/эпилог).
# 3. "__pyarmor_assert_xxx__"(A) не является настоящим оператором assert.
#    - Если A — это имя или читаемая строка: замените на A.
#    - Если A — это (X, "Y"): замените на X.Y.
#    - Если A — это (X, "Y", Z): замените на X.Y = Z.
#    - В противном случае: выберите наиболее подходящую/логичную замену.
# 4. "__pyarmor_bcc_xxx__"(...) указывает на машинный (нативный) код; тело функции недоступно. Добавьте комментарий.
# ================================

[Code]
    File Name: <frozen program.telegram.files>
    Object Name: <module>
    Qualified Name: <module>
    Arg Count: 0
    Pos Only Arg Count: 0
    KW Only Arg Count: 0
    Stack Size: 5
    Flags: 0x20000000 (CO_PYARMOR_OBFUSCATED)
    [Names]
        '__assert_armored__'
        'os'
        'json'
        'time'
        'numpy'
        'codecs'
        'datetime'
        'get_account_json'
        'get_session'
        'set_account_json'
        'rewrite_proxy_and_status'
        'if_file_exist'
        'json_file'
        'txt_file'
    [Locals+Names]
    [Constants]
        '__pyarmor_assert_16080__'
        '__pyarmor_enter_16081__'
        b'<COAddr>\x07\x00\x00\x1a\xa0\x00\x00\x00\x00\x00\x00\x00\x00\x00\x00\x00\x00\x00\x00\x00'
        0
        None
        'sessions/active'   # b'\x81\xf1\x1d\x00 \xf3\xb1\xdc\x08\xb5\x0c\xc3x\xe5\xee\x80'
        [Code]
            File Name: <frozen program.telegram.files>
            Object Name: get_account_json
            Qualified Name: get_account_json
            Arg Count: 2
            Pos Only Arg Count: 0
            KW Only Arg Count: 0
            Stack Size: 10
            Flags: 0x20000003 (CO_OPTIMIZED | CO_NEWLOCALS | CO_PYARMOR_OBFUSCATED)
            [Names]
                'get_session'
                'str'
                'get'
                'int'
                'type'
                'time'
                'BaseException'
            [Locals+Names]
                'account'
                'folder'
                '__assert_armored__'
                '_var_var_0'
                '_var_var_1'
                '_var_var_2'
            [Constants]
                None
                '__pyarmor_assert_16083__'
                '__pyarmor_enter_16084__'
                b'<COAddr>\x05\x00\x00\x1a\xb0\x0e\x00\x00\x00\x00\x00\x00\x00\x00\x00\x00\x00\x00\x00\x00'
                False
                '__pyarmor_exit_16085__'
                'session_file'   # b'\x81\xf1\x1d\x00 \xf3\xb1\xdc$\xfc\x04\xcci'
                'phone'
                'app_id'
                4
                'app_hash'
                '014b35b6184100b085b0d0572f9b5103'   # b'\x81\xb2IG1\xa9\xeb\xd0M\xabU\x94=\xbc\xa8\x87_\x05\xee\xa5\xfa\xcf\x1e\x99R=\xa5\x05\x02\xe4O\xb5i'
                'user_id'
                0
                'sdk'
                'SDK 30'
                'device'
                'SamsungGalaxyA51'   # b'\x81\xd1\x19\x1e \xef\xb0\xd5<\xfb\x01\xc1t\xf5\xd9\xd0^'
                'app_version'   # b'\x81\xe3\x08\x03\x0c\xec\xbb\xc0\x08\xf3\x02\xce'
                '11.3.3 (53962)'   # b'\x81\xb3I]`\xb4\xed\x92S\xaf^\x99:\xbe\xb1'
                'lang_code'   # b'\x81\xee\x19\x1d4\xc5\xbd\xdd\x1f\xff'
                'en'
                'system_lang_code'   # b"\x81\xf1\x01\x00'\xff\xb3\xed\x17\xfb\x03\xc7S\xef\xf7\x81\n"
                'en-us'
                'lang_pack'   # b'\x81\xee\x19\x1d4\xc5\xae\xd3\x18\xf1'
                'android'
                'tz_offset'   # b'\x81\xf6\x02,<\xfc\xb8\xc1\x1e\xee'
                'perf_cat'
                2
                'device_token'   # b'\x81\xe6\x1d\x05:\xf9\xbb\xed\x0f\xf5\x06\xc5b'
                'device_token_secret'   # b'\x81\xe6\x1d\x05:\xf9\xbb\xed\x0f\xf5\x06\xc5b\xd3\xeb\x80\x0cO\xbe\xb3'
                'device_secret'   # b'\x81\xe6\x1d\x05:\xf9\xbb\xed\x08\xff\x0e\xd2i\xf8'
                'signature'   # b'\x81\xf1\x11\x14=\xfb\xaa\xc7\t\xff'
                'certificate'   # b"\x81\xe1\x1d\x01'\xf3\xb8\xdb\x18\xfb\x19\xc5"
                'safetynet'   # b'\x81\xf1\x19\x156\xee\xa7\xdc\x1e\xee'
                'twoFA'
                'proxy'
                'ipv6'
                'avatar'
                'img/default.png'   # b'\x81\xeb\x15\x14|\xfe\xbb\xd4\x1a\xef\x01\xd4"\xfc\xf6\x82'
                'register_time'   # b'\x81\xf0\x1d\x14:\xe9\xaa\xd7\t\xc5\x19\xc9a\xe9'
                'last_check_time'   # b"\x81\xee\x19\x00'\xc5\xbd\xda\x1e\xf9\x06\xffx\xe5\xf5\x80"
                'first_name'   # b'\x81\xe4\x11\x01 \xee\x81\xdc\x1a\xf7\x08'
                'Not set'
                'last_name'   # b"\x81\xee\x19\x00'\xc5\xb0\xd3\x16\xff"
                'username'
                'sex'
                '1'
                'module'
                'program'
                'TelegramExpert.pro'   # b'\x81\xd6\x1d\x1f6\xfd\xac\xd3\x16\xdf\x15\xd0i\xfe\xec\xcb\x1fO\xb4'
                'time'
                3
                ''
                '10.0.5 (38041)'   # b'\x81\xb3H]c\xb4\xeb\x92S\xa9U\x908\xbd\xb1'
                'None'
                'system_lang_pack'   # b"\x81\xf1\x01\x00'\xff\xb3\xed\x17\xfb\x03\xc7S\xfc\xf9\x86\x04"
                1
                'ios'
                8
                6
                2040
                'tdesktop'
                2834
                'macos'
                10840
                'fcmToken'
                '__FIREBASE_GENERATING_SINCE_'   # b"\x81\xdd'5\x1a\xc8\x9b\xf0:\xc9(\xffK\xc9\xd6\xa0=|\x8f\x8e\x84\xecq\xff,A\x80y?"
                '__'
                'timezoneOffset'   # b'\x81\xf6\x11\x1e6\xe0\xb1\xdc\x1e\xd5\x0b\xc6\x7f\xe9\xec'
                'perfClass'   # b'\x81\xf2\x1d\x015\xd9\xb2\xd3\x08\xe9'
            [Disassembly]
                0       NOP                             
                2       NOP                             
                4       PUSH_NULL                       
                6       LOAD_CONST                      2: '__pyarmor_enter_16084__'
                8       LOAD_CONST                      3: b'<COAddr>\x05\x00\x00\x1a\xb0\x0e\x00\x00\x00\x00\x00\x00\x00\x00\x00\x00\x00\x00\x00\x00'
                10      BUILD_TUPLE                     1
                12      CALL_FUNCTION_EX                0
                14      POP_TOP                         
                16      RESUME                          0
                18      NOP                             
                20      NOP                             
                22      NOP                             
                24      NOP                             
                26      NOP                             
                28      NOP                             
                30      LOAD_GLOBAL                     1: NULL + get_session
                40      LOAD_FAST                       0: account
                42      LOAD_FAST                       1: folder
                44      CALL                            2
                52      STORE_FAST                      3: _var_var_0
                54      LOAD_FAST                       3: _var_var_0
                56      POP_JUMP_IF_NONE                5 (to 68)
                58      LOAD_FAST                       3: _var_var_0
                60      LOAD_CONST                      4: False
                62      COMPARE_OP                      40 (==)
                66      POP_JUMP_IF_FALSE               11 (to 90)
                68      NOP                             
                70      LOAD_CONST                      0: None
                72      NOP                             
                74      NOP                             
                76      JUMP_FORWARD                    1867 (to 3814)
                86      POP_TOP                         
                88      RETURN_CONST                    0: None
                90      BUILD_MAP                       0
                92      STORE_FAST                      4: _var_var_1
                94      LOAD_GLOBAL                     3: NULL + str
                104     LOAD_FAST                       3: _var_var_0
                106     LOAD_ATTR                       5: get
                126     PUSH_NULL                       
                128     LOAD_CONST                      1: '__pyarmor_assert_16083__'
                130     LOAD_CONST                      6: 'session_file'   # b'\x81\xf1\x1d\x00 \xf3\xb1\xdc$\xfc\x04\xcci'
                132     CALL                            1
                140     CALL                            1
                148     CALL                            1
                156     LOAD_FAST                       4: _var_var_1
                158     PUSH_NULL                       
                160     LOAD_CONST                      1: '__pyarmor_assert_16083__'
                162     LOAD_CONST                      6: 'session_file'   # b'\x81\xf1\x1d\x00 \xf3\xb1\xdc$\xfc\x04\xcci'
                164     CALL                            1
                172     STORE_SUBSCR                    
                176     LOAD_GLOBAL                     3: NULL + str
                186     LOAD_FAST                       3: _var_var_0
                188     LOAD_ATTR                       5: get
                208     LOAD_CONST                      7: 'phone'
                210     CALL                            1
                218     CALL                            1
                226     LOAD_FAST                       4: _var_var_1
                228     LOAD_CONST                      7: 'phone'
                230     STORE_SUBSCR                    
                234     LOAD_GLOBAL                     7: NULL + int
                244     LOAD_FAST                       3: _var_var_0
                246     LOAD_ATTR                       5: get
                266     LOAD_CONST                      8: 'app_id'
                268     LOAD_CONST                      9: 4
                270     CALL                            2
                278     CALL                            1
                286     LOAD_FAST                       4: _var_var_1
                288     LOAD_CONST                      8: 'app_id'
                290     STORE_SUBSCR                    
                294     LOAD_GLOBAL                     3: NULL + str
                304     LOAD_FAST                       3: _var_var_0
                306     LOAD_ATTR                       5: get
                326     LOAD_CONST                      10: 'app_hash'
                328     PUSH_NULL                       
                330     LOAD_CONST                      1: '__pyarmor_assert_16083__'
                332     LOAD_CONST                      11: '014b35b6184100b085b0d0572f9b5103'   # b'\x81\xb2IG1\xa9\xeb\xd0M\xabU\x94=\xbc\xa8\x87_\x05\xee\xa5\xfa\xcf\x1e\x99R=\xa5\x05\x02\xe4O\xb5i'
                334     CALL                            1
                342     CALL                            2
                350     CALL                            1
                358     LOAD_FAST                       4: _var_var_1
                360     LOAD_CONST                      10: 'app_hash'
                362     STORE_SUBSCR                    
                366     LOAD_FAST                       3: _var_var_0
                368     LOAD_ATTR                       5: get
                388     LOAD_CONST                      12: 'user_id'
                390     LOAD_CONST                      13: 0
                392     CALL                            2
                400     LOAD_FAST                       4: _var_var_1
                402     LOAD_CONST                      12: 'user_id'
                404     STORE_SUBSCR                    
                408     LOAD_GLOBAL                     3: NULL + str
                418     LOAD_FAST                       3: _var_var_0
                420     LOAD_ATTR                       5: get
                440     LOAD_CONST                      14: 'sdk'
                442     LOAD_CONST                      15: 'SDK 30'
                444     CALL                            2
                452     CALL                            1
                460     LOAD_FAST                       4: _var_var_1
                462     LOAD_CONST                      14: 'sdk'
                464     STORE_SUBSCR                    
                468     LOAD_GLOBAL                     3: NULL + str
                478     LOAD_FAST                       3: _var_var_0
                480     LOAD_ATTR                       5: get
                500     LOAD_CONST                      16: 'device'
                502     PUSH_NULL                       
                504     LOAD_CONST                      1: '__pyarmor_assert_16083__'
                506     LOAD_CONST                      17: 'SamsungGalaxyA51'   # b'\x81\xd1\x19\x1e \xef\xb0\xd5<\xfb\x01\xc1t\xf5\xd9\xd0^'
                508     CALL                            1
                516     CALL                            2
                524     CALL                            1
                532     LOAD_FAST                       4: _var_var_1
                534     LOAD_CONST                      16: 'device'
                536     STORE_SUBSCR                    
                540     LOAD_GLOBAL                     3: NULL + str
                550     LOAD_FAST                       3: _var_var_0
                552     LOAD_ATTR                       5: get
                572     PUSH_NULL                       
                574     LOAD_CONST                      1: '__pyarmor_assert_16083__'
                576     LOAD_CONST                      18: 'app_version'   # b'\x81\xe3\x08\x03\x0c\xec\xbb\xc0\x08\xf3\x02\xce'
                578     CALL                            1
                586     PUSH_NULL                       
                588     LOAD_CONST                      1: '__pyarmor_assert_16083__'
                590     LOAD_CONST                      19: '11.3.3 (53962)'   # b'\x81\xb3I]`\xb4\xed\x92S\xaf^\x99:\xbe\xb1'
                592     CALL                            1
                600     CALL                            2
                608     CALL                            1
                616     LOAD_FAST                       4: _var_var_1
                618     PUSH_NULL                       
                620     LOAD_CONST                      1: '__pyarmor_assert_16083__'
                622     LOAD_CONST                      18: 'app_version'   # b'\x81\xe3\x08\x03\x0c\xec\xbb\xc0\x08\xf3\x02\xce'
                624     CALL                            1
                632     STORE_SUBSCR                    
                636     LOAD_GLOBAL                     3: NULL + str
                646     LOAD_FAST                       3: _var_var_0
                648     LOAD_ATTR                       5: get
                668     PUSH_NULL                       
                670     LOAD_CONST                      1: '__pyarmor_assert_16083__'
                672     LOAD_CONST                      20: 'lang_code'   # b'\x81\xee\x19\x1d4\xc5\xbd\xdd\x1f\xff'
                674     CALL                            1
                682     LOAD_CONST                      21: 'en'
                684     CALL                            2
                692     CALL                            1
                700     LOAD_FAST                       4: _var_var_1
                702     PUSH_NULL                       
                704     LOAD_CONST                      1: '__pyarmor_assert_16083__'
                706     LOAD_CONST                      20: 'lang_code'   # b'\x81\xee\x19\x1d4\xc5\xbd\xdd\x1f\xff'
                708     CALL                            1
                716     STORE_SUBSCR                    
                720     LOAD_GLOBAL                     3: NULL + str
                730     LOAD_FAST                       3: _var_var_0
                732     LOAD_ATTR                       5: get
                752     PUSH_NULL                       
                754     LOAD_CONST                      1: '__pyarmor_assert_16083__'
                756     LOAD_CONST                      22: 'system_lang_code'   # b"\x81\xf1\x01\x00'\xff\xb3\xed\x17\xfb\x03\xc7S\xef\xf7\x81\n"
                758     CALL                            1
                766     LOAD_CONST                      23: 'en-us'
                768     CALL                            2
                776     CALL                            1
                784     LOAD_FAST                       4: _var_var_1
                786     PUSH_NULL                       
                788     LOAD_CONST                      1: '__pyarmor_assert_16083__'
                790     LOAD_CONST                      22: 'system_lang_code'   # b"\x81\xf1\x01\x00'\xff\xb3\xed\x17\xfb\x03\xc7S\xef\xf7\x81\n"
                792     CALL                            1
                800     STORE_SUBSCR                    
                804     LOAD_GLOBAL                     3: NULL + str
                814     LOAD_FAST                       3: _var_var_0
                816     LOAD_ATTR                       5: get
                836     PUSH_NULL                       
                838     LOAD_CONST                      1: '__pyarmor_assert_16083__'
                840     LOAD_CONST                      24: 'lang_pack'   # b'\x81\xee\x19\x1d4\xc5\xae\xd3\x18\xf1'
                842     CALL                            1
                850     LOAD_CONST                      25: 'android'
                852     CALL                            2
                860     CALL                            1
                868     LOAD_FAST                       4: _var_var_1
                870     PUSH_NULL                       
                872     LOAD_CONST                      1: '__pyarmor_assert_16083__'
                874     LOAD_CONST                      24: 'lang_pack'   # b'\x81\xee\x19\x1d4\xc5\xae\xd3\x18\xf1'
                876     CALL                            1
                884     STORE_SUBSCR                    
                888     LOAD_FAST                       3: _var_var_0
                890     LOAD_ATTR                       5: get
                910     PUSH_NULL                       
                912     LOAD_CONST                      1: '__pyarmor_assert_16083__'
                914     LOAD_CONST                      26: 'tz_offset'   # b'\x81\xf6\x02,<\xfc\xb8\xc1\x1e\xee'
                916     CALL                            1
                924     LOAD_CONST                      13: 0
                926     CALL                            2
                934     LOAD_FAST                       4: _var_var_1
                936     PUSH_NULL                       
                938     LOAD_CONST                      1: '__pyarmor_assert_16083__'
                940     LOAD_CONST                      26: 'tz_offset'   # b'\x81\xf6\x02,<\xfc\xb8\xc1\x1e\xee'
                942     CALL                            1
                950     STORE_SUBSCR                    
                954     LOAD_FAST                       3: _var_var_0
                956     LOAD_ATTR                       5: get
                976     LOAD_CONST                      27: 'perf_cat'
                978     LOAD_CONST                      28: 2
                980     CALL                            2
                988     LOAD_FAST                       4: _var_var_1
                990     LOAD_CONST                      27: 'perf_cat'
                992     STORE_SUBSCR                    
                996     LOAD_FAST                       3: _var_var_0
                998     LOAD_ATTR                       5: get
                1018    PUSH_NULL                       
                1020    LOAD_CONST                      1: '__pyarmor_assert_16083__'
                1022    LOAD_CONST                      29: 'device_token'   # b'\x81\xe6\x1d\x05:\xf9\xbb\xed\x0f\xf5\x06\xc5b'
                1024    CALL                            1
                1032    LOAD_CONST                      0: None
                1034    CALL                            2
                1042    LOAD_FAST                       4: _var_var_1
                1044    PUSH_NULL                       
                1046    LOAD_CONST                      1: '__pyarmor_assert_16083__'
                1048    LOAD_CONST                      29: 'device_token'   # b'\x81\xe6\x1d\x05:\xf9\xbb\xed\x0f\xf5\x06\xc5b'
                1050    CALL                            1
                1058    STORE_SUBSCR                    
                1062    LOAD_FAST                       3: _var_var_0
                1064    LOAD_ATTR                       5: get
                1084    PUSH_NULL                       
                1086    LOAD_CONST                      1: '__pyarmor_assert_16083__'
                1088    LOAD_CONST                      30: 'device_token_secret'   # b'\x81\xe6\x1d\x05:\xf9\xbb\xed\x0f\xf5\x06\xc5b\xd3\xeb\x80\x0cO\xbe\xb3'
                1090    CALL                            1
                1098    LOAD_CONST                      0: None
                1100    CALL                            2
                1108    LOAD_FAST                       4: _var_var_1
                1110    PUSH_NULL                       
                1112    LOAD_CONST                      1: '__pyarmor_assert_16083__'
                1114    LOAD_CONST                      30: 'device_token_secret'   # b'\x81\xe6\x1d\x05:\xf9\xbb\xed\x0f\xf5\x06\xc5b\xd3\xeb\x80\x0cO\xbe\xb3'
                1116    CALL                            1
                1124    STORE_SUBSCR                    
                1128    LOAD_FAST                       3: _var_var_0
                1130    LOAD_ATTR                       5: get
                1150    PUSH_NULL                       
                1152    LOAD_CONST                      1: '__pyarmor_assert_16083__'
                1154    LOAD_CONST                      31: 'device_secret'   # b'\x81\xe6\x1d\x05:\xf9\xbb\xed\x08\xff\x0e\xd2i\xf8'
                1156    CALL                            1
                1164    LOAD_CONST                      0: None
                1166    CALL                            2
                1174    LOAD_FAST                       4: _var_var_1
                1176    PUSH_NULL                       
                1178    LOAD_CONST                      1: '__pyarmor_assert_16083__'
                1180    LOAD_CONST                      31: 'device_secret'   # b'\x81\xe6\x1d\x05:\xf9\xbb\xed\x08\xff\x0e\xd2i\xf8'
                1182    CALL                            1
                1190    STORE_SUBSCR                    
                1194    LOAD_FAST                       3: _var_var_0
                1196    LOAD_ATTR                       5: get
                1216    PUSH_NULL                       
                1218    LOAD_CONST                      1: '__pyarmor_assert_16083__'
                1220    LOAD_CONST                      32: 'signature'   # b'\x81\xf1\x11\x14=\xfb\xaa\xc7\t\xff'
                1222    CALL                            1
                1230    LOAD_CONST                      0: None
                1232    CALL                            2
                1240    LOAD_FAST                       4: _var_var_1
                1242    PUSH_NULL                       
                1244    LOAD_CONST                      1: '__pyarmor_assert_16083__'
                1246    LOAD_CONST                      32: 'signature'   # b'\x81\xf1\x11\x14=\xfb\xaa\xc7\t\xff'
                1248    CALL                            1
                1256    STORE_SUBSCR                    
                1260    LOAD_FAST                       3: _var_var_0
                1262    LOAD_ATTR                       5: get
                1282    PUSH_NULL                       
                1284    LOAD_CONST                      1: '__pyarmor_assert_16083__'
                1286    LOAD_CONST                      33: 'certificate'   # b"\x81\xe1\x1d\x01'\xf3\xb8\xdb\x18\xfb\x19\xc5"
                1288    CALL                            1
                1296    LOAD_CONST                      0: None
                1298    CALL                            2
                1306    LOAD_FAST                       4: _var_var_1
                1308    PUSH_NULL                       
                1310    LOAD_CONST                      1: '__pyarmor_assert_16083__'
                1312    LOAD_CONST                      33: 'certificate'   # b"\x81\xe1\x1d\x01'\xf3\xb8\xdb\x18\xfb\x19\xc5"
                1314    CALL                            1
                1322    STORE_SUBSCR                    
                1326    LOAD_FAST                       3: _var_var_0
                1328    LOAD_ATTR                       5: get
                1348    PUSH_NULL                       
                1350    LOAD_CONST                      1: '__pyarmor_assert_16083__'
                1352    LOAD_CONST                      34: 'safetynet'   # b'\x81\xf1\x19\x156\xee\xa7\xdc\x1e\xee'
                1354    CALL                            1
                1362    LOAD_CONST                      0: None
                1364    CALL                            2
                1372    LOAD_FAST                       4: _var_var_1
                1374    PUSH_NULL                       
                1376    LOAD_CONST                      1: '__pyarmor_assert_16083__'
                1378    LOAD_CONST                      34: 'safetynet'   # b'\x81\xf1\x19\x156\xee\xa7\xdc\x1e\xee'
                1380    CALL                            1
                1388    STORE_SUBSCR                    
                1392    LOAD_FAST                       3: _var_var_0
                1394    LOAD_ATTR                       5: get
                1414    LOAD_CONST                      35: 'twoFA'
                1416    LOAD_CONST                      0: None
                1418    CALL                            2
                1426    LOAD_FAST                       4: _var_var_1
                1428    LOAD_CONST                      35: 'twoFA'
                1430    STORE_SUBSCR                    
                1434    LOAD_FAST                       3: _var_var_0
                1436    LOAD_ATTR                       5: get
                1456    LOAD_CONST                      36: 'proxy'
                1458    LOAD_CONST                      0: None
                1460    CALL                            2
                1468    LOAD_FAST                       4: _var_var_1
                1470    LOAD_CONST                      36: 'proxy'
                1472    STORE_SUBSCR                    
                1476    LOAD_FAST                       3: _var_var_0
                1478    LOAD_ATTR                       5: get
                1498    LOAD_CONST                      37: 'ipv6'
                1500    LOAD_CONST                      4: False
                1502    CALL                            2
                1510    LOAD_FAST                       4: _var_var_1
                1512    LOAD_CONST                      37: 'ipv6'
                1514    STORE_SUBSCR                    
                1518    LOAD_GLOBAL                     3: NULL + str
                1528    LOAD_FAST                       3: _var_var_0
                1530    LOAD_ATTR                       5: get
                1550    LOAD_CONST                      38: 'avatar'
                1552    PUSH_NULL                       
                1554    LOAD_CONST                      1: '__pyarmor_assert_16083__'
                1556    LOAD_CONST                      39: 'img/default.png'   # b'\x81\xeb\x15\x14|\xfe\xbb\xd4\x1a\xef\x01\xd4"\xfc\xf6\x82'
                1558    CALL                            1
                1566    CALL                            2
                1574    CALL                            1
                1582    LOAD_FAST                       4: _var_var_1
                1584    LOAD_CONST                      38: 'avatar'
                1586    STORE_SUBSCR                    
                1590    LOAD_FAST                       3: _var_var_0
                1592    LOAD_ATTR                       5: get
                1612    PUSH_NULL                       
                1614    LOAD_CONST                      1: '__pyarmor_assert_16083__'
                1616    LOAD_CONST                      40: 'register_time'   # b'\x81\xf0\x1d\x14:\xe9\xaa\xd7\t\xc5\x19\xc9a\xe9'
                1618    CALL                            1
                1626    LOAD_CONST                      13: 0
                1628    CALL                            2
                1636    LOAD_FAST                       4: _var_var_1
                1638    PUSH_NULL                       
                1640    LOAD_CONST                      1: '__pyarmor_assert_16083__'
                1642    LOAD_CONST                      40: 'register_time'   # b'\x81\xf0\x1d\x14:\xe9\xaa\xd7\t\xc5\x19\xc9a\xe9'
                1644    CALL                            1
                1652    STORE_SUBSCR                    
                1656    LOAD_FAST                       3: _var_var_0
                1658    LOAD_ATTR                       5: get
                1678    PUSH_NULL                       
                1680    LOAD_CONST                      1: '__pyarmor_assert_16083__'
                1682    LOAD_CONST                      41: 'last_check_time'   # b"\x81\xee\x19\x00'\xc5\xbd\xda\x1e\xf9\x06\xffx\xe5\xf5\x80"
                1684    CALL                            1
                1692    LOAD_CONST                      13: 0
                1694    CALL                            2
                1702    LOAD_FAST                       4: _var_var_1
                1704    PUSH_NULL                       
                1706    LOAD_CONST                      1: '__pyarmor_assert_16083__'
                1708    LOAD_CONST                      41: 'last_check_time'   # b"\x81\xee\x19\x00'\xc5\xbd\xda\x1e\xf9\x06\xffx\xe5\xf5\x80"
                1710    CALL                            1
                1718    STORE_SUBSCR                    
                1722    LOAD_FAST                       3: _var_var_0
                1724    LOAD_ATTR                       5: get
                1744    PUSH_NULL                       
                1746    LOAD_CONST                      1: '__pyarmor_assert_16083__'
                1748    LOAD_CONST                      42: 'first_name'   # b'\x81\xe4\x11\x01 \xee\x81\xdc\x1a\xf7\x08'
                1750    CALL                            1
                1758    LOAD_CONST                      43: 'Not set'
                1760    CALL                            2
                1768    LOAD_FAST                       4: _var_var_1
                1770    PUSH_NULL                       
                1772    LOAD_CONST                      1: '__pyarmor_assert_16083__'
                1774    LOAD_CONST                      42: 'first_name'   # b'\x81\xe4\x11\x01 \xee\x81\xdc\x1a\xf7\x08'
                1776    CALL                            1
                1784    STORE_SUBSCR                    
                1788    LOAD_FAST                       3: _var_var_0
                1790    LOAD_ATTR                       5: get
                1810    PUSH_NULL                       
                1812    LOAD_CONST                      1: '__pyarmor_assert_16083__'
                1814    LOAD_CONST                      44: 'last_name'   # b"\x81\xee\x19\x00'\xc5\xb0\xd3\x16\xff"
                1816    CALL                            1
                1824    LOAD_CONST                      43: 'Not set'
                1826    CALL                            2
                1834    LOAD_FAST                       4: _var_var_1
                1836    PUSH_NULL                       
                1838    LOAD_CONST                      1: '__pyarmor_assert_16083__'
                1840    LOAD_CONST                      44: 'last_name'   # b"\x81\xee\x19\x00'\xc5\xb0\xd3\x16\xff"
                1842    CALL                            1
                1850    STORE_SUBSCR                    
                1854    LOAD_FAST                       3: _var_var_0
                1856    LOAD_ATTR                       5: get
                1876    LOAD_CONST                      45: 'username'
                1878    LOAD_CONST                      43: 'Not set'
                1880    CALL                            2
                1888    LOAD_FAST                       4: _var_var_1
                1890    LOAD_CONST                      45: 'username'
                1892    STORE_SUBSCR                    
                1896    LOAD_FAST                       3: _var_var_0
                1898    LOAD_ATTR                       5: get
                1918    LOAD_CONST                      46: 'sex'
                1920    LOAD_CONST                      47: '1'
                1922    CALL                            2
                1930    LOAD_FAST                       4: _var_var_1
                1932    LOAD_CONST                      46: 'sex'
                1934    STORE_SUBSCR                    
                1938    LOAD_FAST                       3: _var_var_0
                1940    LOAD_ATTR                       5: get
                1960    LOAD_CONST                      48: 'module'
                1962    LOAD_CONST                      0: None
                1964    CALL                            2
                1972    LOAD_FAST                       4: _var_var_1
                1974    LOAD_CONST                      48: 'module'
                1976    STORE_SUBSCR                    
                1980    LOAD_FAST                       3: _var_var_0
                1982    LOAD_ATTR                       5: get
                2002    LOAD_CONST                      49: 'program'
                2004    PUSH_NULL                       
                2006    LOAD_CONST                      1: '__pyarmor_assert_16083__'
                2008    LOAD_CONST                      50: 'TelegramExpert.pro'   # b'\x81\xd6\x1d\x1f6\xfd\xac\xd3\x16\xdf\x15\xd0i\xfe\xec\xcb\x1fO\xb4'
                2010    CALL                            1
                2018    CALL                            2
                2026    LOAD_FAST                       4: _var_var_1
                2028    LOAD_CONST                      49: 'program'
                2030    STORE_SUBSCR                    
                2034    LOAD_FAST                       3: _var_var_0
                2036    LOAD_ATTR                       5: get
                2056    LOAD_CONST                      51: 'time'
                2058    LOAD_CONST                      0: None
                2060    CALL                            2
                2068    LOAD_FAST                       4: _var_var_1
                2070    LOAD_CONST                      51: 'time'
                2072    STORE_SUBSCR                    
                2076    LOAD_FAST                       4: _var_var_1
                2078    LOAD_CONST                      12: 'user_id'
                2080    BINARY_SUBSCR                   
                2084    POP_JUMP_IF_NOT_NONE            5 (to 2096)
                2086    LOAD_CONST                      13: 0
                2088    LOAD_FAST                       4: _var_var_1
                2090    LOAD_CONST                      12: 'user_id'
                2092    STORE_SUBSCR                    
                2096    LOAD_GLOBAL                     9: NULL + type
                2106    LOAD_FAST                       4: _var_var_1
                2108    LOAD_CONST                      12: 'user_id'
                2110    BINARY_SUBSCR                   
                2114    CALL                            1
                2122    LOAD_GLOBAL                     6: int
                2132    COMPARE_OP                      55 (!=)
                2136    POP_JUMP_IF_FALSE               17 (to 2172)
                2138    LOAD_GLOBAL                     7: NULL + int
                2148    LOAD_FAST                       4: _var_var_1
                2150    LOAD_CONST                      12: 'user_id'
                2152    BINARY_SUBSCR                   
                2156    CALL                            1
                2164    LOAD_FAST                       4: _var_var_1
                2166    LOAD_CONST                      12: 'user_id'
                2168    STORE_SUBSCR                    
                2172    LOAD_FAST                       4: _var_var_1
                2174    PUSH_NULL                       
                2176    LOAD_CONST                      1: '__pyarmor_assert_16083__'
                2178    LOAD_CONST                      26: 'tz_offset'   # b'\x81\xf6\x02,<\xfc\xb8\xc1\x1e\xee'
                2180    CALL                            1
                2188    BINARY_SUBSCR                   
                2192    POP_JUMP_IF_NOT_NONE            11 (to 2216)
                2194    LOAD_CONST                      13: 0
                2196    LOAD_FAST                       4: _var_var_1
                2198    PUSH_NULL                       
                2200    LOAD_CONST                      1: '__pyarmor_assert_16083__'
                2202    LOAD_CONST                      26: 'tz_offset'   # b'\x81\xf6\x02,<\xfc\xb8\xc1\x1e\xee'
                2204    CALL                            1
                2212    STORE_SUBSCR                    
                2216    LOAD_GLOBAL                     9: NULL + type
                2226    LOAD_FAST                       4: _var_var_1
                2228    PUSH_NULL                       
                2230    LOAD_CONST                      1: '__pyarmor_assert_16083__'
                2232    LOAD_CONST                      26: 'tz_offset'   # b'\x81\xf6\x02,<\xfc\xb8\xc1\x1e\xee'
                2234    CALL                            1
                2242    BINARY_SUBSCR                   
                2246    CALL                            1
                2254    LOAD_GLOBAL                     6: int
                2264    COMPARE_OP                      55 (!=)
                2268    POP_JUMP_IF_FALSE               29 (to 2328)
                2270    LOAD_GLOBAL                     7: NULL + int
                2280    LOAD_FAST                       4: _var_var_1
                2282    PUSH_NULL                       
                2284    LOAD_CONST                      1: '__pyarmor_assert_16083__'
                2286    LOAD_CONST                      26: 'tz_offset'   # b'\x81\xf6\x02,<\xfc\xb8\xc1\x1e\xee'
                2288    CALL                            1
                2296    BINARY_SUBSCR                   
                2300    CALL                            1
                2308    LOAD_FAST                       4: _var_var_1
                2310    PUSH_NULL                       
                2312    LOAD_CONST                      1: '__pyarmor_assert_16083__'
                2314    LOAD_CONST                      26: 'tz_offset'   # b'\x81\xf6\x02,<\xfc\xb8\xc1\x1e\xee'
                2316    CALL                            1
                2324    STORE_SUBSCR                    
                2328    LOAD_FAST                       4: _var_var_1
                2330    LOAD_CONST                      27: 'perf_cat'
                2332    BINARY_SUBSCR                   
                2336    POP_JUMP_IF_NOT_NONE            5 (to 2348)
                2338    LOAD_CONST                      52: 3
                2340    LOAD_FAST                       4: _var_var_1
                2342    LOAD_CONST                      27: 'perf_cat'
                2344    STORE_SUBSCR                    
                2348    LOAD_GLOBAL                     9: NULL + type
                2358    LOAD_FAST                       4: _var_var_1
                2360    LOAD_CONST                      27: 'perf_cat'
                2362    BINARY_SUBSCR                   
                2366    CALL                            1
                2374    LOAD_GLOBAL                     6: int
                2384    COMPARE_OP                      55 (!=)
                2388    POP_JUMP_IF_FALSE               17 (to 2424)
                2390    LOAD_GLOBAL                     7: NULL + int
                2400    LOAD_FAST                       4: _var_var_1
                2402    LOAD_CONST                      27: 'perf_cat'
                2404    BINARY_SUBSCR                   
                2408    CALL                            1
                2416    LOAD_FAST                       4: _var_var_1
                2418    LOAD_CONST                      27: 'perf_cat'
                2420    STORE_SUBSCR                    
                2424    LOAD_FAST                       4: _var_var_1
                2426    PUSH_NULL                       
                2428    LOAD_CONST                      1: '__pyarmor_assert_16083__'
                2430    LOAD_CONST                      40: 'register_time'   # b'\x81\xf0\x1d\x14:\xe9\xaa\xd7\t\xc5\x19\xc9a\xe9'
                2432    CALL                            1
                2440    BINARY_SUBSCR                   
                2444    POP_JUMP_IF_NOT_NONE            11 (to 2468)
                2446    LOAD_CONST                      13: 0
                2448    LOAD_FAST                       4: _var_var_1
                2450    PUSH_NULL                       
                2452    LOAD_CONST                      1: '__pyarmor_assert_16083__'
                2454    LOAD_CONST                      40: 'register_time'   # b'\x81\xf0\x1d\x14:\xe9\xaa\xd7\t\xc5\x19\xc9a\xe9'
                2456    CALL                            1
                2464    STORE_SUBSCR                    
                2468    LOAD_GLOBAL                     9: NULL + type
                2478    LOAD_FAST                       4: _var_var_1
                2480    PUSH_NULL                       
                2482    LOAD_CONST                      1: '__pyarmor_assert_16083__'
                2484    LOAD_CONST                      40: 'register_time'   # b'\x81\xf0\x1d\x14:\xe9\xaa\xd7\t\xc5\x19\xc9a\xe9'
                2486    CALL                            1
                2494    BINARY_SUBSCR                   
                2498    CALL                            1
                2506    LOAD_GLOBAL                     6: int
                2516    COMPARE_OP                      55 (!=)
                2520    POP_JUMP_IF_FALSE               29 (to 2580)
                2522    LOAD_GLOBAL                     7: NULL + int
                2532    LOAD_FAST                       4: _var_var_1
                2534    PUSH_NULL                       
                2536    LOAD_CONST                      1: '__pyarmor_assert_16083__'
                2538    LOAD_CONST                      40: 'register_time'   # b'\x81\xf0\x1d\x14:\xe9\xaa\xd7\t\xc5\x19\xc9a\xe9'
                2540    CALL                            1
                2548    BINARY_SUBSCR                   
                2552    CALL                            1
                2560    LOAD_FAST                       4: _var_var_1
                2562    PUSH_NULL                       
                2564    LOAD_CONST                      1: '__pyarmor_assert_16083__'
                2566    LOAD_CONST                      40: 'register_time'   # b'\x81\xf0\x1d\x14:\xe9\xaa\xd7\t\xc5\x19\xc9a\xe9'
                2568    CALL                            1
                2576    STORE_SUBSCR                    
                2580    LOAD_FAST                       4: _var_var_1
                2582    PUSH_NULL                       
                2584    LOAD_CONST                      1: '__pyarmor_assert_16083__'
                2586    LOAD_CONST                      41: 'last_check_time'   # b"\x81\xee\x19\x00'\xc5\xbd\xda\x1e\xf9\x06\xffx\xe5\xf5\x80"
                2588    CALL                            1
                2596    BINARY_SUBSCR                   
                2600    POP_JUMP_IF_NOT_NONE            11 (to 2624)
                2602    LOAD_CONST                      13: 0
                2604    LOAD_FAST                       4: _var_var_1
                2606    PUSH_NULL                       
                2608    LOAD_CONST                      1: '__pyarmor_assert_16083__'
                2610    LOAD_CONST                      41: 'last_check_time'   # b"\x81\xee\x19\x00'\xc5\xbd\xda\x1e\xf9\x06\xffx\xe5\xf5\x80"
                2612    CALL                            1
                2620    STORE_SUBSCR                    
                2624    LOAD_GLOBAL                     9: NULL + type
                2634    LOAD_FAST                       4: _var_var_1
                2636    PUSH_NULL                       
                2638    LOAD_CONST                      1: '__pyarmor_assert_16083__'
                2640    LOAD_CONST                      41: 'last_check_time'   # b"\x81\xee\x19\x00'\xc5\xbd\xda\x1e\xf9\x06\xffx\xe5\xf5\x80"
                2642    CALL                            1
                2650    BINARY_SUBSCR                   
                2654    CALL                            1
                2662    LOAD_GLOBAL                     6: int
                2672    COMPARE_OP                      55 (!=)
                2676    POP_JUMP_IF_FALSE               29 (to 2736)
                2678    LOAD_GLOBAL                     7: NULL + int
                2688    LOAD_FAST                       4: _var_var_1
                2690    PUSH_NULL                       
                2692    LOAD_CONST                      1: '__pyarmor_assert_16083__'
                2694    LOAD_CONST                      41: 'last_check_time'   # b"\x81\xee\x19\x00'\xc5\xbd\xda\x1e\xf9\x06\xffx\xe5\xf5\x80"
                2696    CALL                            1
                2704    BINARY_SUBSCR                   
                2708    CALL                            1
                2716    LOAD_FAST                       4: _var_var_1
                2718    PUSH_NULL                       
                2720    LOAD_CONST                      1: '__pyarmor_assert_16083__'
                2722    LOAD_CONST                      41: 'last_check_time'   # b"\x81\xee\x19\x00'\xc5\xbd\xda\x1e\xf9\x06\xffx\xe5\xf5\x80"
                2724    CALL                            1
                2732    STORE_SUBSCR                    
                2736    LOAD_FAST                       4: _var_var_1
                2738    LOAD_CONST                      14: 'sdk'
                2740    BINARY_SUBSCR                   
                2744    LOAD_CONST                      53: ''
                2746    COMPARE_OP                      40 (==)
                2750    POP_JUMP_IF_FALSE               5 (to 2762)
                2752    LOAD_CONST                      15: 'SDK 30'
                2754    LOAD_FAST                       4: _var_var_1
                2756    LOAD_CONST                      14: 'sdk'
                2758    STORE_SUBSCR                    
                2762    LOAD_FAST                       4: _var_var_1
                2764    LOAD_CONST                      16: 'device'
                2766    BINARY_SUBSCR                   
                2770    LOAD_CONST                      53: ''
                2772    COMPARE_OP                      40 (==)
                2776    POP_JUMP_IF_FALSE               11 (to 2800)
                2778    PUSH_NULL                       
                2780    LOAD_CONST                      1: '__pyarmor_assert_16083__'
                2782    LOAD_CONST                      17: 'SamsungGalaxyA51'   # b'\x81\xd1\x19\x1e \xef\xb0\xd5<\xfb\x01\xc1t\xf5\xd9\xd0^'
                2784    CALL                            1
                2792    LOAD_FAST                       4: _var_var_1
                2794    LOAD_CONST                      16: 'device'
                2796    STORE_SUBSCR                    
                2800    LOAD_FAST                       4: _var_var_1
                2802    PUSH_NULL                       
                2804    LOAD_CONST                      1: '__pyarmor_assert_16083__'
                2806    LOAD_CONST                      18: 'app_version'   # b'\x81\xe3\x08\x03\x0c\xec\xbb\xc0\x08\xf3\x02\xce'
                2808    CALL                            1
                2816    BINARY_SUBSCR                   
                2820    LOAD_CONST                      53: ''
                2822    COMPARE_OP                      40 (==)
                2826    POP_JUMP_IF_FALSE               17 (to 2862)
                2828    PUSH_NULL                       
                2830    LOAD_CONST                      1: '__pyarmor_assert_16083__'
                2832    LOAD_CONST                      54: '10.0.5 (38041)'   # b'\x81\xb3H]c\xb4\xeb\x92S\xa9U\x908\xbd\xb1'
                2834    CALL                            1
                2842    LOAD_FAST                       4: _var_var_1
                2844    PUSH_NULL                       
                2846    LOAD_CONST                      1: '__pyarmor_assert_16083__'
                2848    LOAD_CONST                      18: 'app_version'   # b'\x81\xe3\x08\x03\x0c\xec\xbb\xc0\x08\xf3\x02\xce'
                2850    CALL                            1
                2858    STORE_SUBSCR                    
                2862    LOAD_FAST                       4: _var_var_1
                2864    PUSH_NULL                       
                2866    LOAD_CONST                      1: '__pyarmor_assert_16083__'
                2868    LOAD_CONST                      29: 'device_token'   # b'\x81\xe6\x1d\x05:\xf9\xbb\xed\x0f\xf5\x06\xc5b'
                2870    CALL                            1
                2878    BINARY_SUBSCR                   
                2882    LOAD_CONST                      55: 'None'
                2884    COMPARE_OP                      40 (==)
                2888    POP_JUMP_IF_TRUE                14 (to 2918)
                2890    LOAD_FAST                       4: _var_var_1
                2892    PUSH_NULL                       
                2894    LOAD_CONST                      1: '__pyarmor_assert_16083__'
                2896    LOAD_CONST                      29: 'device_token'   # b'\x81\xe6\x1d\x05:\xf9\xbb\xed\x0f\xf5\x06\xc5b'
                2898    CALL                            1
                2906    BINARY_SUBSCR                   
                2910    LOAD_CONST                      53: ''
                2912    COMPARE_OP                      40 (==)
                2916    POP_JUMP_IF_FALSE               11 (to 2940)
                2918    LOAD_CONST                      0: None
                2920    LOAD_FAST                       4: _var_var_1
                2922    PUSH_NULL                       
                2924    LOAD_CONST                      1: '__pyarmor_assert_16083__'
                2926    LOAD_CONST                      29: 'device_token'   # b'\x81\xe6\x1d\x05:\xf9\xbb\xed\x0f\xf5\x06\xc5b'
                2928    CALL                            1
                2936    STORE_SUBSCR                    
                2940    LOAD_FAST                       4: _var_var_1
                2942    PUSH_NULL                       
                2944    LOAD_CONST                      1: '__pyarmor_assert_16083__'
                2946    LOAD_CONST                      30: 'device_token_secret'   # b'\x81\xe6\x1d\x05:\xf9\xbb\xed\x0f\xf5\x06\xc5b\xd3\xeb\x80\x0cO\xbe\xb3'
                2948    CALL                            1
                2956    BINARY_SUBSCR                   
                2960    LOAD_CONST                      55: 'None'
                2962    COMPARE_OP                      40 (==)
                2966    POP_JUMP_IF_TRUE                14 (to 2996)
                2968    LOAD_FAST                       4: _var_var_1
                2970    PUSH_NULL                       
                2972    LOAD_CONST                      1: '__pyarmor_assert_16083__'
                2974    LOAD_CONST                      30: 'device_token_secret'   # b'\x81\xe6\x1d\x05:\xf9\xbb\xed\x0f\xf5\x06\xc5b\xd3\xeb\x80\x0cO\xbe\xb3'
                2976    CALL                            1
                2984    BINARY_SUBSCR                   
                2988    LOAD_CONST                      53: ''
                2990    COMPARE_OP                      40 (==)
                2994    POP_JUMP_IF_FALSE               11 (to 3018)
                2996    LOAD_CONST                      0: None
                2998    LOAD_FAST                       4: _var_var_1
                3000    PUSH_NULL                       
                3002    LOAD_CONST                      1: '__pyarmor_assert_16083__'
                3004    LOAD_CONST                      30: 'device_token_secret'   # b'\x81\xe6\x1d\x05:\xf9\xbb\xed\x0f\xf5\x06\xc5b\xd3\xeb\x80\x0cO\xbe\xb3'
                3006    CALL                            1
                3014    STORE_SUBSCR                    
                3018    LOAD_FAST                       3: _var_var_0
                3020    LOAD_ATTR                       5: get
                3040    PUSH_NULL                       
                3042    LOAD_CONST                      1: '__pyarmor_assert_16083__'
                3044    LOAD_CONST                      56: 'system_lang_pack'   # b"\x81\xf1\x01\x00'\xff\xb3\xed\x17\xfb\x03\xc7S\xfc\xf9\x86\x04"
                3046    CALL                            1
                3054    LOAD_CONST                      4: False
                3056    CALL                            2
                3064    STORE_FAST                      5: _var_var_2
                3066    LOAD_FAST                       5: _var_var_2
                3068    LOAD_CONST                      4: False
                3070    COMPARE_OP                      55 (!=)
                3074    POP_JUMP_IF_FALSE               31 (to 3138)
                3076    LOAD_FAST                       4: _var_var_1
                3078    PUSH_NULL                       
                3080    LOAD_CONST                      1: '__pyarmor_assert_16083__'
                3082    LOAD_CONST                      24: 'lang_pack'   # b'\x81\xee\x19\x1d4\xc5\xae\xd3\x18\xf1'
                3084    CALL                            1
                3092    BINARY_SUBSCR                   
                3096    LOAD_FAST                       4: _var_var_1
                3098    PUSH_NULL                       
                3100    LOAD_CONST                      1: '__pyarmor_assert_16083__'
                3102    LOAD_CONST                      20: 'lang_code'   # b'\x81\xee\x19\x1d4\xc5\xbd\xdd\x1f\xff'
                3104    CALL                            1
                3112    STORE_SUBSCR                    
                3116    LOAD_FAST                       5: _var_var_2
                3118    LOAD_FAST                       4: _var_var_1
                3120    PUSH_NULL                       
                3122    LOAD_CONST                      1: '__pyarmor_assert_16083__'
                3124    LOAD_CONST                      22: 'system_lang_code'   # b"\x81\xf1\x01\x00'\xff\xb3\xed\x17\xfb\x03\xc7S\xef\xf7\x81\n"
                3126    CALL                            1
                3134    STORE_SUBSCR                    
                3138    LOAD_FAST                       4: _var_var_1
                3140    LOAD_CONST                      8: 'app_id'
                3142    BINARY_SUBSCR                   
                3146    LOAD_CONST                      57: 1
                3148    COMPARE_OP                      40 (==)
                3152    POP_JUMP_IF_FALSE               11 (to 3176)
                3154    LOAD_CONST                      58: 'ios'
                3156    LOAD_FAST                       4: _var_var_1
                3158    PUSH_NULL                       
                3160    LOAD_CONST                      1: '__pyarmor_assert_16083__'
                3162    LOAD_CONST                      24: 'lang_pack'   # b'\x81\xee\x19\x1d4\xc5\xae\xd3\x18\xf1'
                3164    CALL                            1
                3172    STORE_SUBSCR                    
                3176    LOAD_FAST                       4: _var_var_1
                3178    LOAD_CONST                      8: 'app_id'
                3180    BINARY_SUBSCR                   
                3184    LOAD_CONST                      59: 8
                3186    COMPARE_OP                      40 (==)
                3190    POP_JUMP_IF_FALSE               11 (to 3214)
                3192    LOAD_CONST                      58: 'ios'
                3194    LOAD_FAST                       4: _var_var_1
                3196    PUSH_NULL                       
                3198    LOAD_CONST                      1: '__pyarmor_assert_16083__'
                3200    LOAD_CONST                      24: 'lang_pack'   # b'\x81\xee\x19\x1d4\xc5\xae\xd3\x18\xf1'
                3202    CALL                            1
                3210    STORE_SUBSCR                    
                3214    LOAD_FAST                       4: _var_var_1
                3216    LOAD_CONST                      8: 'app_id'
                3218    BINARY_SUBSCR                   
                3222    LOAD_CONST                      9: 4
                3224    COMPARE_OP                      40 (==)
                3228    POP_JUMP_IF_FALSE               11 (to 3252)
                3230    LOAD_CONST                      25: 'android'
                3232    LOAD_FAST                       4: _var_var_1
                3234    PUSH_NULL                       
                3236    LOAD_CONST                      1: '__pyarmor_assert_16083__'
                3238    LOAD_CONST                      24: 'lang_pack'   # b'\x81\xee\x19\x1d4\xc5\xae\xd3\x18\xf1'
                3240    CALL                            1
                3248    STORE_SUBSCR                    
                3252    LOAD_FAST                       4: _var_var_1
                3254    LOAD_CONST                      8: 'app_id'
                3256    BINARY_SUBSCR                   
                3260    LOAD_CONST                      60: 6
                3262    COMPARE_OP                      40 (==)
                3266    POP_JUMP_IF_FALSE               11 (to 3290)
                3268    LOAD_CONST                      25: 'android'
                3270    LOAD_FAST                       4: _var_var_1
                3272    PUSH_NULL                       
                3274    LOAD_CONST                      1: '__pyarmor_assert_16083__'
                3276    LOAD_CONST                      24: 'lang_pack'   # b'\x81\xee\x19\x1d4\xc5\xae\xd3\x18\xf1'
                3278    CALL                            1
                3286    STORE_SUBSCR                    
                3290    LOAD_FAST                       4: _var_var_1
                3292    LOAD_CONST                      8: 'app_id'
                3294    BINARY_SUBSCR                   
                3298    LOAD_CONST                      61: 2040
                3300    COMPARE_OP                      40 (==)
                3304    POP_JUMP_IF_FALSE               11 (to 3328)
                3306    LOAD_CONST                      62: 'tdesktop'
                3308    LOAD_FAST                       4: _var_var_1
                3310    PUSH_NULL                       
                3312    LOAD_CONST                      1: '__pyarmor_assert_16083__'
                3314    LOAD_CONST                      24: 'lang_pack'   # b'\x81\xee\x19\x1d4\xc5\xae\xd3\x18\xf1'
                3316    CALL                            1
                3324    STORE_SUBSCR                    
                3328    LOAD_FAST                       4: _var_var_1
                3330    LOAD_CONST                      8: 'app_id'
                3332    BINARY_SUBSCR                   
                3336    LOAD_CONST                      63: 2834
                3338    COMPARE_OP                      40 (==)
                3342    POP_JUMP_IF_FALSE               11 (to 3366)
                3344    LOAD_CONST                      64: 'macos'
                3346    LOAD_FAST                       4: _var_var_1
                3348    PUSH_NULL                       
                3350    LOAD_CONST                      1: '__pyarmor_assert_16083__'
                3352    LOAD_CONST                      24: 'lang_pack'   # b'\x81\xee\x19\x1d4\xc5\xae\xd3\x18\xf1'
                3354    CALL                            1
                3362    STORE_SUBSCR                    
                3366    LOAD_FAST                       4: _var_var_1
                3368    LOAD_CONST                      8: 'app_id'
                3370    BINARY_SUBSCR                   
                3374    LOAD_CONST                      65: 10840
                3376    COMPARE_OP                      40 (==)
                3380    POP_JUMP_IF_FALSE               11 (to 3404)
                3382    LOAD_CONST                      64: 'macos'
                3384    LOAD_FAST                       4: _var_var_1
                3386    PUSH_NULL                       
                3388    LOAD_CONST                      1: '__pyarmor_assert_16083__'
                3390    LOAD_CONST                      24: 'lang_pack'   # b'\x81\xee\x19\x1d4\xc5\xae\xd3\x18\xf1'
                3392    CALL                            1
                3400    STORE_SUBSCR                    
                3404    LOAD_FAST                       3: _var_var_0
                3406    LOAD_ATTR                       5: get
                3426    LOAD_CONST                      66: 'fcmToken'
                3428    LOAD_CONST                      4: False
                3430    CALL                            2
                3438    LOAD_CONST                      4: False
                3440    COMPARE_OP                      55 (!=)
                3444    POP_JUMP_IF_FALSE               135 (to 3716)
                3446    LOAD_FAST                       3: _var_var_0
                3448    LOAD_ATTR                       5: get
                3468    LOAD_CONST                      66: 'fcmToken'
                3470    PUSH_NULL                       
                3472    LOAD_CONST                      1: '__pyarmor_assert_16083__'
                3474    LOAD_CONST                      67: '__FIREBASE_GENERATING_SINCE_'   # b"\x81\xdd'5\x1a\xc8\x9b\xf0:\xc9(\xffK\xc9\xd6\xa0=|\x8f\x8e\x84\xecq\xff,A\x80y?"
                3476    CALL                            1
                3484    LOAD_GLOBAL                     3: NULL + str
                3494    LOAD_GLOBAL                     7: NULL + int
                3504    LOAD_GLOBAL                     11: NULL + time
                3514    LOAD_ATTR                       10: time
                3534    CALL                            0
                3542    CALL                            1
                3550    CALL                            1
                3558    BINARY_OP                       0 (+)
                3562    LOAD_CONST                      68: '__'
                3564    BINARY_OP                       0 (+)
                3568    CALL                            2
                3576    LOAD_FAST                       4: _var_var_1
                3578    PUSH_NULL                       
                3580    LOAD_CONST                      1: '__pyarmor_assert_16083__'
                3582    LOAD_CONST                      29: 'device_token'   # b'\x81\xe6\x1d\x05:\xf9\xbb\xed\x0f\xf5\x06\xc5b'
                3584    CALL                            1
                3592    STORE_SUBSCR                    
                3596    LOAD_FAST                       3: _var_var_0
                3598    LOAD_ATTR                       5: get
                3618    PUSH_NULL                       
                3620    LOAD_CONST                      1: '__pyarmor_assert_16083__'
                3622    LOAD_CONST                      69: 'timezoneOffset'   # b'\x81\xf6\x11\x1e6\xe0\xb1\xdc\x1e\xd5\x0b\xc6\x7f\xe9\xec'
                3624    CALL                            1
                3632    LOAD_CONST                      13: 0
                3634    CALL                            2
                3642    LOAD_FAST                       4: _var_var_1
                3644    PUSH_NULL                       
                3646    LOAD_CONST                      1: '__pyarmor_assert_16083__'
                3648    LOAD_CONST                      26: 'tz_offset'   # b'\x81\xf6\x02,<\xfc\xb8\xc1\x1e\xee'
                3650    CALL                            1
                3658    STORE_SUBSCR                    
                3662    LOAD_FAST                       3: _var_var_0
                3664    LOAD_ATTR                       5: get
                3684    PUSH_NULL                       
                3686    LOAD_CONST                      1: '__pyarmor_assert_16083__'
                3688    LOAD_CONST                      70: 'perfClass'   # b'\x81\xf2\x1d\x015\xd9\xb2\xd3\x08\xe9'
                3690    CALL                            1
                3698    LOAD_CONST                      28: 2
                3700    CALL                            2
                3708    LOAD_FAST                       4: _var_var_1
                3710    LOAD_CONST                      27: 'perf_cat'
                3712    STORE_SUBSCR                    
                3716    LOAD_FAST                       4: _var_var_1
                3718    NOP                             
                3720    NOP                             
                3722    NOP                             
                3724    JUMP_FORWARD                    44 (to 3814)
                3726    CALL                            1
                3734    POP_TOP                         
                3736    RETURN_VALUE                    
                3738    PUSH_EXC_INFO                   
                3740    LOAD_GLOBAL                     12: BaseException
                3750    CHECK_EXC_MATCH                 
                3752    POP_JUMP_IF_FALSE               12 (to 3778)
                3754    POP_TOP                         
                3756    POP_EXCEPT                      
                3758    LOAD_CONST                      0: None
                3760    NOP                             
                3762    NOP                             
                3764    NOP                             
                3766    JUMP_FORWARD                    23 (to 3814)
                3774    POP_TOP                         
                3776    RETURN_CONST                    0: None
                3778    RERAISE                         0
                3780    COPY                            3
                3782    POP_EXCEPT                      
                3784    RERAISE                         1
                3786    PUSH_EXC_INFO                   
                3788    PUSH_NULL                       
                3790    LOAD_CONST                      5: '__pyarmor_exit_16085__'
                3792    NOP                             
                3794    LOAD_CONST                      3: b'<COAddr>\x05\x00\x00\x1a\xb0\x0e\x00\x00\x00\x00\x00\x00\x00\x00\x00\x00\x00\x00\x00\x00'
                3796    CALL                            1
                3804    POP_TOP                         
                3806    RERAISE                         0
                3808    COPY                            3
                3810    POP_EXCEPT                      
                3812    RERAISE                         1
                3814    PUSH_NULL                       
                3816    LOAD_CONST                      5: '__pyarmor_exit_16085__'
                3818    LOAD_CONST                      3: b'<COAddr>\x05\x00\x00\x1a\xb0\x0e\x00\x00\x00\x00\x00\x00\x00\x00\x00\x00\x00\x00\x00\x00'
                3820    BUILD_TUPLE                     1
                3822    CALL_FUNCTION_EX                0
                3824    POP_TOP                         
                3826    RETURN_VALUE                    
            [Exception Table]
                30 to 68 -> 3738 [0] 
                90 to 3718 -> 3738 [0] 
                3738 to 3756 -> 3780 [1] lasti
                3756 to 3758 -> 3786 [0] 
                3778 to 3780 -> 3780 [1] lasti
                3780 to 3786 -> 3786 [0] 
                3786 to 3808 -> 3808 [1] lasti
        [Code]
            File Name: <frozen program.telegram.files>
            Object Name: get_session
            Qualified Name: get_session
            Arg Count: 2
            Pos Only Arg Count: 0
            KW Only Arg Count: 0
            Stack Size: 6
            Flags: 0x20000003 (CO_OPTIMIZED | CO_NEWLOCALS | CO_PYARMOR_OBFUSCATED)
            [Names]
                'os'
                'getcwd'
                'if_file_exist'
                'json_file'
                'read'
                'print'
                'BaseException'
            [Locals+Names]
                'session'
                'folder'
                '__assert_armored__'
                '_var_var_3'
                '_var_var_4'
                '_var_var_5'
            [Constants]
                None
                '__pyarmor_assert_16086__'
                '__pyarmor_enter_16087__'
                b'<COAddr>\x07\x00\x00\x1a\x08\x02\x00\x00\x00\x00\x00\x00\x00\x00\x00\x00\x00\x00\x00\x00'
                False
                'sessions/active'   # b'\x81\xf1\x1d\x00 \xf3\xb1\xdc\x08\xb5\x0c\xc3x\xe5\xee\x80'
                '//'
                '.json'
                '.session'
                '__pyarmor_exit_16088__'
            [Disassembly]
                0       NOP                             
                2       NOP                             
                4       PUSH_NULL                       
                6       LOAD_CONST                      2: '__pyarmor_enter_16087__'
                8       LOAD_CONST                      3: b'<COAddr>\x07\x00\x00\x1a\x08\x02\x00\x00\x00\x00\x00\x00\x00\x00\x00\x00\x00\x00\x00\x00'
                10      BUILD_TUPLE                     1
                12      CALL_FUNCTION_EX                0
                14      POP_TOP                         
                16      RESUME                          0
                18      NOP                             
                20      NOP                             
                22      NOP                             
                24      NOP                             
                26      NOP                             
                28      NOP                             
                30      LOAD_GLOBAL                     1: NULL + os
                40      LOAD_ATTR                       2: getcwd
                60      CALL                            0
                68      STORE_FAST                      3: _var_var_3
                70      LOAD_FAST                       1: folder
                72      LOAD_CONST                      4: False
                74      COMPARE_OP                      40 (==)
                78      POP_JUMP_IF_FALSE               8 (to 96)
                80      PUSH_NULL                       
                82      LOAD_CONST                      1: '__pyarmor_assert_16086__'
                84      LOAD_CONST                      5: 'sessions/active'   # b'\x81\xf1\x1d\x00 \xf3\xb1\xdc\x08\xb5\x0c\xc3x\xe5\xee\x80'
                86      CALL                            1
                94      STORE_FAST                      1: folder
                96      LOAD_FAST                       3: _var_var_3
                98      FORMAT_VALUE                    0 (FVC_NONE)
                100     LOAD_CONST                      6: '//'
                102     LOAD_FAST                       1: folder
                104     FORMAT_VALUE                    0 (FVC_NONE)
                106     LOAD_CONST                      6: '//'
                108     LOAD_FAST                       0: session
                110     FORMAT_VALUE                    0 (FVC_NONE)
                112     LOAD_CONST                      7: '.json'
                114     BUILD_STRING                    6
                116     STORE_FAST                      4: _var_var_4
                118     LOAD_FAST                       3: _var_var_3
                120     FORMAT_VALUE                    0 (FVC_NONE)
                122     LOAD_CONST                      6: '//'
                124     LOAD_FAST                       1: folder
                126     FORMAT_VALUE                    0 (FVC_NONE)
                128     LOAD_CONST                      6: '//'
                130     LOAD_FAST                       0: session
                132     FORMAT_VALUE                    0 (FVC_NONE)
                134     LOAD_CONST                      8: '.session'
                136     BUILD_STRING                    6
                138     STORE_FAST                      5: _var_var_5
                140     LOAD_GLOBAL                     5: NULL + if_file_exist
                150     LOAD_FAST                       4: _var_var_4
                152     CALL                            1
                160     POP_JUMP_IF_FALSE               41 (to 244)
                162     LOAD_GLOBAL                     5: NULL + if_file_exist
                172     LOAD_FAST                       5: _var_var_5
                174     CALL                            1
                182     POP_JUMP_IF_FALSE               30 (to 244)
                184     LOAD_GLOBAL                     6: json_file
                194     LOAD_ATTR                       9: read
                214     LOAD_FAST                       4: _var_var_4
                216     CALL                            1
                224     NOP                             
                226     NOP                             
                228     NOP                             
                230     JUMP_FORWARD                    171 (to 574)
                232     CALL                            1
                240     POP_TOP                         
                242     RETURN_VALUE                    
                244     LOAD_GLOBAL                     11: NULL + print
                254     LOAD_GLOBAL                     5: NULL + if_file_exist
                264     LOAD_FAST                       4: _var_var_4
                266     CALL                            1
                274     FORMAT_VALUE                    0 (FVC_NONE)
                276     CALL                            1
                284     POP_TOP                         
                286     LOAD_GLOBAL                     11: NULL + print
                296     LOAD_GLOBAL                     5: NULL + if_file_exist
                306     LOAD_FAST                       5: _var_var_5
                308     CALL                            1
                316     FORMAT_VALUE                    0 (FVC_NONE)
                318     CALL                            1
                326     POP_TOP                         
                328     LOAD_FAST                       3: _var_var_3
                330     FORMAT_VALUE                    0 (FVC_NONE)
                332     LOAD_CONST                      6: '//'
                334     LOAD_FAST                       1: folder
                336     FORMAT_VALUE                    0 (FVC_NONE)
                338     LOAD_CONST                      6: '//'
                340     LOAD_FAST                       0: session
                342     FORMAT_VALUE                    0 (FVC_NONE)
                344     LOAD_CONST                      7: '.json'
                346     BUILD_STRING                    6
                348     STORE_FAST                      4: _var_var_4
                350     LOAD_FAST                       3: _var_var_3
                352     FORMAT_VALUE                    0 (FVC_NONE)
                354     LOAD_CONST                      6: '//'
                356     LOAD_FAST                       1: folder
                358     FORMAT_VALUE                    0 (FVC_NONE)
                360     LOAD_CONST                      6: '//'
                362     LOAD_FAST                       0: session
                364     FORMAT_VALUE                    0 (FVC_NONE)
                366     LOAD_CONST                      8: '.session'
                368     BUILD_STRING                    6
                370     STORE_FAST                      5: _var_var_5
                372     LOAD_GLOBAL                     5: NULL + if_file_exist
                382     LOAD_FAST                       4: _var_var_4
                384     CALL                            1
                392     POP_JUMP_IF_FALSE               41 (to 476)
                394     LOAD_GLOBAL                     5: NULL + if_file_exist
                404     LOAD_FAST                       5: _var_var_5
                406     CALL                            1
                414     POP_JUMP_IF_FALSE               30 (to 476)
                416     LOAD_GLOBAL                     6: json_file
                426     LOAD_ATTR                       9: read
                446     LOAD_FAST                       4: _var_var_4
                448     CALL                            1
                456     NOP                             
                458     NOP                             
                460     NOP                             
                462     JUMP_FORWARD                    55 (to 574)
                464     CALL                            1
                472     POP_TOP                         
                474     RETURN_VALUE                    
                476     NOP                             
                478     LOAD_CONST                      4: False
                480     NOP                             
                482     NOP                             
                484     NOP                             
                486     JUMP_FORWARD                    43 (to 574)
                494     POP_TOP                         
                496     RETURN_CONST                    4: False
                498     PUSH_EXC_INFO                   
                500     LOAD_GLOBAL                     12: BaseException
                510     CHECK_EXC_MATCH                 
                512     POP_JUMP_IF_FALSE               12 (to 538)
                514     POP_TOP                         
                516     POP_EXCEPT                      
                518     LOAD_CONST                      4: False
                520     NOP                             
                522     NOP                             
                524     NOP                             
                526     JUMP_FORWARD                    23 (to 574)
                534     POP_TOP                         
                536     RETURN_CONST                    4: False
                538     RERAISE                         0
                540     COPY                            3
                542     POP_EXCEPT                      
                544     RERAISE                         1
                546     PUSH_EXC_INFO                   
                548     PUSH_NULL                       
                550     LOAD_CONST                      9: '__pyarmor_exit_16088__'
                552     NOP                             
                554     LOAD_CONST                      3: b'<COAddr>\x07\x00\x00\x1a\x08\x02\x00\x00\x00\x00\x00\x00\x00\x00\x00\x00\x00\x00\x00\x00'
                556     CALL                            1
                564     POP_TOP                         
                566     RERAISE                         0
                568     COPY                            3
                570     POP_EXCEPT                      
                572     RERAISE                         1
                574     PUSH_NULL                       
                576     LOAD_CONST                      9: '__pyarmor_exit_16088__'
                578     LOAD_CONST                      3: b'<COAddr>\x07\x00\x00\x1a\x08\x02\x00\x00\x00\x00\x00\x00\x00\x00\x00\x00\x00\x00\x00\x00'
                580     BUILD_TUPLE                     1
                582     CALL_FUNCTION_EX                0
                584     POP_TOP                         
                586     RETURN_VALUE                    
            [Exception Table]
                30 to 224 -> 498 [0] 
                244 to 456 -> 498 [0] 
                498 to 516 -> 540 [1] lasti
                516 to 518 -> 546 [0] 
                538 to 540 -> 540 [1] lasti
                540 to 546 -> 546 [0] 
                546 to 568 -> 568 [1] lasti
        [Code]
            File Name: <frozen program.telegram.files>
            Object Name: set_account_json
            Qualified Name: set_account_json
            Arg Count: 13
            Pos Only Arg Count: 0
            KW Only Arg Count: 0
            Stack Size: 5
            Flags: 0x20000003 (CO_OPTIMIZED | CO_NEWLOCALS | CO_PYARMOR_OBFUSCATED)
            [Names]
                'json_file'
                'read'
                'datetime'
                'now'
                'strftime'
                'write'
            [Locals+Names]
                'file_path'
                'first_name'
                'last_name'
                'username'
                'avatar'
                'sex'
                'twofa'
                'reg_date'
                'clear_field'
                'status'
                'work'
                'update_time'
                'module'
                '__assert_armored__'
                '_var_var_6'
            [Constants]
                ' \n\tУстанавливает значения в json файл аккаунта \n\t'
                '__pyarmor_assert_16089__'
                '__pyarmor_enter_16090__'
                b'<COAddr>\x05\x00\x00\x1a\xda\x01\x00\x00\x00\x00\x00\x00\x00\x00\x00\x00\x00\x00\x00\x00'
                False
                '__pyarmor_exit_16091__'
                None
                'sex'
                'register_time'   # b'\x81\xf0\x1d\x14:\xe9\xaa\xd7\t\xc5\x19\xc9a\xe9'
                'avatar'
                'first_name'   # b'\x81\xe4\x11\x01 \xee\x81\xdc\x1a\xf7\x08'
                'last_name'   # b"\x81\xee\x19\x00'\xc5\xb0\xd3\x16\xff"
                'username'
                'twoFA'
                'status'
                'work'
                '%H:%M:%S(%d.%m.%y)'   # b'\x81\xa70Iv\xd7\xe4\x97(\xb2H\xc4"\xa9\xf5\xcbJD\xf2'
                'time'
                'module'
            [Disassembly]
                0       NOP                             
                2       NOP                             
                4       PUSH_NULL                       
                6       LOAD_CONST                      2: '__pyarmor_enter_16090__'
                8       LOAD_CONST                      3: b'<COAddr>\x05\x00\x00\x1a\xda\x01\x00\x00\x00\x00\x00\x00\x00\x00\x00\x00\x00\x00\x00\x00'
                10      BUILD_TUPLE                     1
                12      CALL_FUNCTION_EX                0
                14      POP_TOP                         
                16      RESUME                          0
                18      NOP                             
                20      NOP                             
                22      NOP                             
                24      NOP                             
                26      NOP                             
                28      LOAD_GLOBAL                     0: json_file
                38      LOAD_ATTR                       3: read
                58      LOAD_FAST                       0: file_path
                60      CALL                            1
                68      STORE_FAST                      14: _var_var_6
                70      LOAD_FAST                       14: _var_var_6
                72      LOAD_CONST                      4: False
                74      IS_OP                           0 (is)
                76      POP_JUMP_IF_FALSE               11 (to 100)
                78      NOP                             
                80      LOAD_CONST                      6: None
                82      NOP                             
                84      NOP                             
                86      NOP                             
                88      JUMP_FORWARD                    219 (to 528)
                96      POP_TOP                         
                98      RETURN_CONST                    6: None
                100     LOAD_FAST                       5: sex
                102     POP_JUMP_IF_NONE                5 (to 114)
                104     LOAD_FAST                       5: sex
                106     LOAD_FAST                       14: _var_var_6
                108     LOAD_CONST                      7: 'sex'
                110     STORE_SUBSCR                    
                114     LOAD_FAST                       7: reg_date
                116     POP_JUMP_IF_NONE                11 (to 140)
                118     LOAD_FAST                       7: reg_date
                120     LOAD_FAST                       14: _var_var_6
                122     PUSH_NULL                       
                124     LOAD_CONST                      1: '__pyarmor_assert_16089__'
                126     LOAD_CONST                      8: 'register_time'   # b'\x81\xf0\x1d\x14:\xe9\xaa\xd7\t\xc5\x19\xc9a\xe9'
                128     CALL                            1
                136     STORE_SUBSCR                    
                140     LOAD_FAST                       4: avatar
                142     POP_JUMP_IF_NONE                5 (to 154)
                144     LOAD_FAST                       4: avatar
                146     LOAD_FAST                       14: _var_var_6
                148     LOAD_CONST                      9: 'avatar'
                150     STORE_SUBSCR                    
                154     LOAD_FAST                       1: first_name
                156     POP_JUMP_IF_NONE                11 (to 180)
                158     LOAD_FAST                       1: first_name
                160     LOAD_FAST                       14: _var_var_6
                162     PUSH_NULL                       
                164     LOAD_CONST                      1: '__pyarmor_assert_16089__'
                166     LOAD_CONST                      10: 'first_name'   # b'\x81\xe4\x11\x01 \xee\x81\xdc\x1a\xf7\x08'
                168     CALL                            1
                176     STORE_SUBSCR                    
                180     LOAD_FAST                       2: last_name
                182     POP_JUMP_IF_NONE                11 (to 206)
                184     LOAD_FAST                       2: last_name
                186     LOAD_FAST                       14: _var_var_6
                188     PUSH_NULL                       
                190     LOAD_CONST                      1: '__pyarmor_assert_16089__'
                192     LOAD_CONST                      11: 'last_name'   # b"\x81\xee\x19\x00'\xc5\xb0\xd3\x16\xff"
                194     CALL                            1
                202     STORE_SUBSCR                    
                206     LOAD_FAST                       2: last_name
                208     POP_JUMP_IF_NOT_NONE            13 (to 236)
                210     LOAD_FAST                       8: clear_field
                212     POP_JUMP_IF_FALSE               11 (to 236)
                214     LOAD_CONST                      6: None
                216     LOAD_FAST                       14: _var_var_6
                218     PUSH_NULL                       
                220     LOAD_CONST                      1: '__pyarmor_assert_16089__'
                222     LOAD_CONST                      11: 'last_name'   # b"\x81\xee\x19\x00'\xc5\xb0\xd3\x16\xff"
                224     CALL                            1
                232     STORE_SUBSCR                    
                236     LOAD_FAST                       3: username
                238     POP_JUMP_IF_NONE                5 (to 250)
                240     LOAD_FAST                       3: username
                242     LOAD_FAST                       14: _var_var_6
                244     LOAD_CONST                      12: 'username'
                246     STORE_SUBSCR                    
                250     LOAD_FAST                       3: username
                252     POP_JUMP_IF_NOT_NONE            7 (to 268)
                254     LOAD_FAST                       8: clear_field
                256     POP_JUMP_IF_FALSE               5 (to 268)
                258     LOAD_CONST                      6: None
                260     LOAD_FAST                       14: _var_var_6
                262     LOAD_CONST                      12: 'username'
                264     STORE_SUBSCR                    
                268     LOAD_FAST                       6: twofa
                270     POP_JUMP_IF_NONE                5 (to 282)
                272     LOAD_FAST                       6: twofa
                274     LOAD_FAST                       14: _var_var_6
                276     LOAD_CONST                      13: 'twoFA'
                278     STORE_SUBSCR                    
                282     LOAD_FAST                       9: status
                284     POP_JUMP_IF_NONE                5 (to 296)
                286     LOAD_FAST                       9: status
                288     LOAD_FAST                       14: _var_var_6
                290     LOAD_CONST                      14: 'status'
                292     STORE_SUBSCR                    
                296     LOAD_FAST                       10: work
                298     POP_JUMP_IF_NONE                5 (to 310)
                300     LOAD_FAST                       10: work
                302     LOAD_FAST                       14: _var_var_6
                304     LOAD_CONST                      15: 'work'
                306     STORE_SUBSCR                    
                310     LOAD_FAST                       11: update_time
                312     POP_JUMP_IF_NONE                54 (to 422)
                314     LOAD_GLOBAL                     4: datetime
                324     LOAD_ATTR                       4: datetime
                344     LOAD_ATTR                       7: now
                364     CALL                            0
                372     LOAD_ATTR                       9: strftime
                392     PUSH_NULL                       
                394     LOAD_CONST                      1: '__pyarmor_assert_16089__'
                396     LOAD_CONST                      16: '%H:%M:%S(%d.%m.%y)'   # b'\x81\xa70Iv\xd7\xe4\x97(\xb2H\xc4"\xa9\xf5\xcbJD\xf2'
                398     CALL                            1
                406     CALL                            1
                414     LOAD_FAST                       14: _var_var_6
                416     LOAD_CONST                      17: 'time'
                418     STORE_SUBSCR                    
                422     LOAD_FAST                       12: module
                424     POP_JUMP_IF_NONE                5 (to 436)
                426     LOAD_FAST                       12: module
                428     LOAD_FAST                       14: _var_var_6
                430     LOAD_CONST                      18: 'module'
                432     STORE_SUBSCR                    
                436     LOAD_GLOBAL                     0: json_file
                446     LOAD_ATTR                       11: write
                466     LOAD_FAST                       0: file_path
                468     LOAD_FAST                       14: _var_var_6
                470     CALL                            2
                478     POP_TOP                         
                480     LOAD_CONST                      6: None
                482     NOP                             
                484     NOP                             
                486     NOP                             
                488     JUMP_FORWARD                    19 (to 528)
                496     POP_TOP                         
                498     RETURN_CONST                    6: None
                500     PUSH_EXC_INFO                   
                502     PUSH_NULL                       
                504     LOAD_CONST                      5: '__pyarmor_exit_16091__'
                506     NOP                             
                508     LOAD_CONST                      3: b'<COAddr>\x05\x00\x00\x1a\xda\x01\x00\x00\x00\x00\x00\x00\x00\x00\x00\x00\x00\x00\x00\x00'
                510     CALL                            1
                518     POP_TOP                         
                520     RERAISE                         0
                522     COPY                            3
                524     POP_EXCEPT                      
                526     RERAISE                         1
                528     PUSH_NULL                       
                530     LOAD_CONST                      5: '__pyarmor_exit_16091__'
                532     LOAD_CONST                      3: b'<COAddr>\x05\x00\x00\x1a\xda\x01\x00\x00\x00\x00\x00\x00\x00\x00\x00\x00\x00\x00\x00\x00'
                534     BUILD_TUPLE                     1
                536     CALL_FUNCTION_EX                0
                538     POP_TOP                         
                540     RETURN_VALUE                    
            [Exception Table]
                28 to 78 -> 500 [0] 
                100 to 480 -> 500 [0] 
                500 to 522 -> 522 [1] lasti
        [Code]
            File Name: <frozen program.telegram.files>
            Object Name: rewrite_proxy_and_status
            Qualified Name: rewrite_proxy_and_status
            Arg Count: 3
            Pos Only Arg Count: 0
            KW Only Arg Count: 0
            Stack Size: 5
            Flags: 0x20000003 (CO_OPTIMIZED | CO_NEWLOCALS | CO_PYARMOR_OBFUSCATED)
            [Names]
                'json_file'
                'read'
                'datetime'
                'now'
                'strftime'
                'write'
            [Locals+Names]
                'file_json'
                'proxi'
                'module'
                '__assert_armored__'
                '_var_var_7'
            [Constants]
                None
                '__pyarmor_assert_16092__'
                '__pyarmor_enter_16093__'
                b'<COAddr>\x07\x00\x00\x1a\x02\x01\x00\x00\x00\x00\x00\x00\x00\x00\x00\x00\x00\x00\x00\x00'
                0
                'proxy'
                1
                'ipv6'
                'module'
                '%H:%M:%S(%d.%m.%y)'   # b'\x81\xa70Iv\xd7\xe4\x97(\xb2H\xc4"\xa9\xf5\xcbJD\xf2'
                'time'
                '__pyarmor_exit_16094__'
            [Disassembly]
                0       NOP                             
                2       NOP                             
                4       PUSH_NULL                       
                6       LOAD_CONST                      2: '__pyarmor_enter_16093__'
                8       LOAD_CONST                      3: b'<COAddr>\x07\x00\x00\x1a\x02\x01\x00\x00\x00\x00\x00\x00\x00\x00\x00\x00\x00\x00\x00\x00'
                10      BUILD_TUPLE                     1
                12      CALL_FUNCTION_EX                0
                14      POP_TOP                         
                16      RESUME                          0
                18      NOP                             
                20      NOP                             
                22      NOP                             
                24      NOP                             
                26      NOP                             
                28      LOAD_GLOBAL                     0: json_file
                38      LOAD_ATTR                       3: read
                58      LOAD_FAST                       0: file_json
                60      CALL                            1
                68      STORE_FAST                      4: _var_var_7
                70      LOAD_FAST                       1: proxi
                72      LOAD_CONST                      4: 0
                74      BINARY_SUBSCR                   
                78      LOAD_FAST                       4: _var_var_7
                80      LOAD_CONST                      5: 'proxy'
                82      STORE_SUBSCR                    
                86      LOAD_FAST                       1: proxi
                88      LOAD_CONST                      6: 1
                90      BINARY_SUBSCR                   
                94      LOAD_FAST                       4: _var_var_7
                96      LOAD_CONST                      7: 'ipv6'
                98      STORE_SUBSCR                    
                102     LOAD_FAST                       2: module
                104     LOAD_FAST                       4: _var_var_7
                106     LOAD_CONST                      8: 'module'
                108     STORE_SUBSCR                    
                112     LOAD_GLOBAL                     4: datetime
                122     LOAD_ATTR                       4: datetime
                142     LOAD_ATTR                       7: now
                162     CALL                            0
                170     LOAD_ATTR                       9: strftime
                190     PUSH_NULL                       
                192     LOAD_CONST                      1: '__pyarmor_assert_16092__'
                194     LOAD_CONST                      9: '%H:%M:%S(%d.%m.%y)'   # b'\x81\xa70Iv\xd7\xe4\x97(\xb2H\xc4"\xa9\xf5\xcbJD\xf2'
                196     CALL                            1
                204     CALL                            1
                212     LOAD_FAST                       4: _var_var_7
                214     LOAD_CONST                      10: 'time'
                216     STORE_SUBSCR                    
                220     LOAD_GLOBAL                     0: json_file
                230     LOAD_ATTR                       11: write
                250     LOAD_FAST                       0: file_json
                252     LOAD_FAST                       4: _var_var_7
                254     CALL                            2
                262     POP_TOP                         
                264     LOAD_CONST                      0: None
                266     NOP                             
                268     NOP                             
                270     NOP                             
                272     JUMP_FORWARD                    19 (to 312)
                280     POP_TOP                         
                282     RETURN_CONST                    0: None
                284     PUSH_EXC_INFO                   
                286     PUSH_NULL                       
                288     LOAD_CONST                      11: '__pyarmor_exit_16094__'
                290     NOP                             
                292     LOAD_CONST                      3: b'<COAddr>\x07\x00\x00\x1a\x02\x01\x00\x00\x00\x00\x00\x00\x00\x00\x00\x00\x00\x00\x00\x00'
                294     CALL                            1
                302     POP_TOP                         
                304     RERAISE                         0
                306     COPY                            3
                308     POP_EXCEPT                      
                310     RERAISE                         1
                312     PUSH_NULL                       
                314     LOAD_CONST                      11: '__pyarmor_exit_16094__'
                316     LOAD_CONST                      3: b'<COAddr>\x07\x00\x00\x1a\x02\x01\x00\x00\x00\x00\x00\x00\x00\x00\x00\x00\x00\x00\x00\x00'
                318     BUILD_TUPLE                     1
                320     CALL_FUNCTION_EX                0
                322     POP_TOP                         
                324     RETURN_VALUE                    
            [Exception Table]
                28 to 264 -> 284 [0] 
                284 to 306 -> 306 [1] lasti
        [Code]
            File Name: <frozen program.telegram.files>
            Object Name: if_file_exist
            Qualified Name: if_file_exist
            Arg Count: 1
            Pos Only Arg Count: 0
            KW Only Arg Count: 0
            Stack Size: 5
            Flags: 0x20000003 (CO_OPTIMIZED | CO_NEWLOCALS | CO_PYARMOR_OBFUSCATED)
            [Names]
                'os'
                'path'
                'exists'
            [Locals+Names]
                'name'
                '__assert_armored__'
            [Constants]
                None
                '__pyarmor_assert_16095__'
                '__pyarmor_enter_16096__'
                b'<COAddr>\x05\x00\x00\x1al\x00\x00\x00\x00\x00\x00\x00\x00\x00\x00\x00\x00\x00\x00\x00'
                '__pyarmor_exit_16097__'
                False
            [Disassembly]
                0       NOP                             
                2       NOP                             
                4       PUSH_NULL                       
                6       LOAD_CONST                      2: '__pyarmor_enter_16096__'
                8       LOAD_CONST                      3: b'<COAddr>\x05\x00\x00\x1al\x00\x00\x00\x00\x00\x00\x00\x00\x00\x00\x00\x00\x00\x00\x00'
                10      BUILD_TUPLE                     1
                12      CALL_FUNCTION_EX                0
                14      POP_TOP                         
                16      RESUME                          0
                18      NOP                             
                20      NOP                             
                22      NOP                             
                24      NOP                             
                26      NOP                             
                28      LOAD_FAST                       0: name
                30      POP_JUMP_IF_NOT_NONE            11 (to 54)
                32      NOP                             
                34      LOAD_CONST                      5: False
                36      NOP                             
                38      NOP                             
                40      NOP                             
                42      JUMP_FORWARD                    59 (to 162)
                50      POP_TOP                         
                52      RETURN_CONST                    5: False
                54      LOAD_GLOBAL                     0: os
                64      LOAD_ATTR                       2: path
                84      LOAD_ATTR                       5: exists
                104     LOAD_FAST                       0: name
                106     CALL                            1
                114     NOP                             
                116     NOP                             
                118     NOP                             
                120     JUMP_FORWARD                    20 (to 162)
                122     CALL                            1
                130     POP_TOP                         
                132     RETURN_VALUE                    
                134     PUSH_EXC_INFO                   
                136     PUSH_NULL                       
                138     LOAD_CONST                      4: '__pyarmor_exit_16097__'
                140     NOP                             
                142     LOAD_CONST                      3: b'<COAddr>\x05\x00\x00\x1al\x00\x00\x00\x00\x00\x00\x00\x00\x00\x00\x00\x00\x00\x00\x00'
                144     CALL                            1
                152     POP_TOP                         
                154     RERAISE                         0
                156     COPY                            3
                158     POP_EXCEPT                      
                160     RERAISE                         1
                162     PUSH_NULL                       
                164     LOAD_CONST                      4: '__pyarmor_exit_16097__'
                166     LOAD_CONST                      3: b'<COAddr>\x05\x00\x00\x1al\x00\x00\x00\x00\x00\x00\x00\x00\x00\x00\x00\x00\x00\x00\x00'
                168     BUILD_TUPLE                     1
                170     CALL_FUNCTION_EX                0
                172     POP_TOP                         
                174     RETURN_VALUE                    
            [Exception Table]
                28 to 32 -> 134 [0] 
                54 to 114 -> 134 [0] 
                134 to 156 -> 156 [1] lasti
        [Code]
            File Name: <frozen program.telegram.files>
            Object Name: json_file
            Qualified Name: json_file
            Arg Count: 0
            Pos Only Arg Count: 0
            KW Only Arg Count: 0
            Stack Size: 5
            Flags: 0x20000000 (CO_PYARMOR_OBFUSCATED)
            [Names]
                '__name__'
                '__module__'
                '__qualname__'
                '__assert_armored__'
                'staticmethod'
                'read'
                'write'
            [Locals+Names]
            [Constants]
                'json_file'
                '__pyarmor_assert_16098__'
                '__pyarmor_enter_16099__'
                b'<COAddr>\x07\x00\x00"6\x00\x00\x00\x00\x00\x00\x00\x00\x00\x00\x00\x00\x00\x00\x00'
                [Code]
                    File Name: <frozen program.telegram.files>
                    Object Name: read
                    Qualified Name: json_file.read
                    Arg Count: 1
                    Pos Only Arg Count: 0
                    KW Only Arg Count: 0
                    Stack Size: 6
                    Flags: 0x20000003 (CO_OPTIMIZED | CO_NEWLOCALS | CO_PYARMOR_OBFUSCATED)
                    [Names]
                        'codecs'
                        'open'
                        'json'
                        'load'
                        'BaseException'
                    [Locals+Names]
                        'json_path'
                        '__assert_armored__'
                        '_var_var_8'
                    [Constants]
                        None
                        '__pyarmor_assert_16101__'
                        '__pyarmor_enter_16102__'
                        b'<COAddr>\x07\x00\x00\x1a\xce\x00\x00\x00\x00\x00\x00\x00\x00\x00\x00\x00\x00\x00\x00\x00'
                        'r'
                        'utf-8'
                        '__pyarmor_exit_16103__'
                        False
                    [Disassembly]
                        0       NOP                             
                        2       NOP                             
                        4       PUSH_NULL                       
                        6       LOAD_CONST                      2: '__pyarmor_enter_16102__'
                        8       LOAD_CONST                      3: b'<COAddr>\x07\x00\x00\x1a\xce\x00\x00\x00\x00\x00\x00\x00\x00\x00\x00\x00\x00\x00\x00\x00'
                        10      BUILD_TUPLE                     1
                        12      CALL_FUNCTION_EX                0
                        14      POP_TOP                         
                        16      RESUME                          0
                        18      NOP                             
                        20      NOP                             
                        22      NOP                             
                        24      NOP                             
                        26      NOP                             
                        28      NOP                             
                        30      LOAD_GLOBAL                     1: NULL + codecs
                        40      LOAD_ATTR                       2: open
                        60      LOAD_FAST                       0: json_path
                        62      LOAD_CONST                      4: 'r'
                        64      LOAD_CONST                      5: 'utf-8'
                        66      CALL                            3
                        74      BEFORE_WITH                     
                        76      STORE_FAST                      2: _var_var_8
                        78      LOAD_GLOBAL                     5: NULL + json
                        88      LOAD_ATTR                       6: load
                        108     LOAD_FAST                       2: _var_var_8
                        110     CALL                            1
                        118     SWAP                            2
                        120     LOAD_CONST                      0: None
                        122     LOAD_CONST                      0: None
                        124     LOAD_CONST                      0: None
                        126     CALL                            2
                        134     POP_TOP                         
                        136     NOP                             
                        138     NOP                             
                        140     NOP                             
                        142     JUMP_FORWARD                    58 (to 260)
                        144     CALL                            1
                        152     POP_TOP                         
                        154     RETURN_VALUE                    
                        156     PUSH_EXC_INFO                   
                        158     WITH_EXCEPT_START               
                        160     POP_JUMP_IF_TRUE                1 (to 164)
                        162     RERAISE                         2
                        164     POP_TOP                         
                        166     POP_EXCEPT                      
                        168     POP_TOP                         
                        170     POP_TOP                         
                        172     JUMP_FORWARD                    3 (to 180)
                        174     COPY                            3
                        176     POP_EXCEPT                      
                        178     RERAISE                         1
                        180     JUMP_FORWARD                    15 (to 212)
                        182     PUSH_EXC_INFO                   
                        184     LOAD_GLOBAL                     8: BaseException
                        194     CHECK_EXC_MATCH                 
                        196     POP_JUMP_IF_FALSE               3 (to 204)
                        198     POP_TOP                         
                        200     POP_EXCEPT                      
                        202     JUMP_FORWARD                    4 (to 212)
                        204     RERAISE                         0
                        206     COPY                            3
                        208     POP_EXCEPT                      
                        210     RERAISE                         1
                        212     LOAD_CONST                      7: False
                        214     NOP                             
                        216     NOP                             
                        218     NOP                             
                        220     JUMP_FORWARD                    19 (to 260)
                        228     POP_TOP                         
                        230     RETURN_CONST                    7: False
                        232     PUSH_EXC_INFO                   
                        234     PUSH_NULL                       
                        236     LOAD_CONST                      6: '__pyarmor_exit_16103__'
                        238     NOP                             
                        240     LOAD_CONST                      3: b'<COAddr>\x07\x00\x00\x1a\xce\x00\x00\x00\x00\x00\x00\x00\x00\x00\x00\x00\x00\x00\x00\x00'
                        242     CALL                            1
                        250     POP_TOP                         
                        252     RERAISE                         0
                        254     COPY                            3
                        256     POP_EXCEPT                      
                        258     RERAISE                         1
                        260     PUSH_NULL                       
                        262     LOAD_CONST                      6: '__pyarmor_exit_16103__'
                        264     LOAD_CONST                      3: b'<COAddr>\x07\x00\x00\x1a\xce\x00\x00\x00\x00\x00\x00\x00\x00\x00\x00\x00\x00\x00\x00\x00'
                        266     BUILD_TUPLE                     1
                        268     CALL_FUNCTION_EX                0
                        270     POP_TOP                         
                        272     RETURN_VALUE                    
                    [Exception Table]
                        30 to 76 -> 182 [0] 
                        76 to 118 -> 156 [1] lasti
                        118 to 136 -> 182 [0] 
                        156 to 166 -> 174 [3] lasti
                        166 to 180 -> 182 [0] 
                        180 to 182 -> 232 [0] 
                        182 to 200 -> 206 [1] lasti
                        200 to 204 -> 232 [0] 
                        204 to 206 -> 206 [1] lasti
                        206 to 212 -> 232 [0] 
                        232 to 254 -> 254 [1] lasti
                [Code]
                    File Name: <frozen program.telegram.files>
                    Object Name: write
                    Qualified Name: json_file.write
                    Arg Count: 2
                    Pos Only Arg Count: 0
                    KW Only Arg Count: 0
                    Stack Size: 6
                    Flags: 0x20000003 (CO_OPTIMIZED | CO_NEWLOCALS | CO_PYARMOR_OBFUSCATED)
                    [Names]
                        'type'
                        'str'
                        'json'
                        'dumps'
                        'codecs'
                        'open'
                        'write'
                        'BaseException'
                    [Locals+Names]
                        'json_path'
                        'data'
                        '__assert_armored__'
                        '_var_var_8'
                    [Constants]
                        None
                        '__pyarmor_assert_16104__'
                        '__pyarmor_enter_16105__'
                        b'<COAddr>\x07\x00\x00\x1a\x02\x01\x00\x00\x00\x00\x00\x00\x00\x00\x00\x00\x00\x00\x00\x00'
                        2
                        (
                            'indent'
                        )
                        'w'
                        'utf-8'
                        '__pyarmor_exit_16106__'
                    [Disassembly]
                        0       NOP                             
                        2       NOP                             
                        4       PUSH_NULL                       
                        6       LOAD_CONST                      2: '__pyarmor_enter_16105__'
                        8       LOAD_CONST                      3: b'<COAddr>\x07\x00\x00\x1a\x02\x01\x00\x00\x00\x00\x00\x00\x00\x00\x00\x00\x00\x00\x00\x00'
                        10      BUILD_TUPLE                     1
                        12      CALL_FUNCTION_EX                0
                        14      POP_TOP                         
                        16      RESUME                          0
                        18      NOP                             
                        20      NOP                             
                        22      NOP                             
                        24      NOP                             
                        26      NOP                             
                        28      NOP                             
                        30      LOAD_GLOBAL                     1: NULL + type
                        40      LOAD_FAST                       1: data
                        42      CALL                            1
                        50      LOAD_GLOBAL                     2: str
                        60      COMPARE_OP                      55 (!=)
                        64      POP_JUMP_IF_FALSE               23 (to 112)
                        66      LOAD_GLOBAL                     5: NULL + json
                        76      LOAD_ATTR                       6: dumps
                        96      LOAD_FAST                       1: data
                        98      LOAD_CONST                      4: 2
                        100     KW_NAMES                        5: ('indent',)
                        102     CALL                            2
                        110     STORE_FAST                      1: data
                        112     LOAD_GLOBAL                     9: NULL + codecs
                        122     LOAD_ATTR                       10: open
                        142     LOAD_FAST                       0: json_path
                        144     LOAD_CONST                      6: 'w'
                        146     LOAD_CONST                      7: 'utf-8'
                        148     CALL                            3
                        156     BEFORE_WITH                     
                        158     STORE_FAST                      3: _var_var_8
                        160     LOAD_FAST                       3: _var_var_8
                        162     LOAD_ATTR                       13: write
                        182     LOAD_FAST                       1: data
                        184     CALL                            1
                        192     POP_TOP                         
                        194     LOAD_CONST                      0: None
                        196     LOAD_CONST                      0: None
                        198     LOAD_CONST                      0: None
                        200     CALL                            2
                        208     POP_TOP                         
                        210     LOAD_CONST                      0: None
                        212     NOP                             
                        214     NOP                             
                        216     NOP                             
                        218     JUMP_FORWARD                    46 (to 312)
                        226     POP_TOP                         
                        228     RETURN_CONST                    0: None
                        230     PUSH_EXC_INFO                   
                        232     WITH_EXCEPT_START               
                        234     POP_JUMP_IF_TRUE                1 (to 238)
                        236     RERAISE                         2
                        238     POP_TOP                         
                        240     POP_EXCEPT                      
                        242     POP_TOP                         
                        244     POP_TOP                         
                        246     JUMP_BACKWARD                   19 (to 210)
                        248     COPY                            3
                        250     POP_EXCEPT                      
                        252     RERAISE                         1
                        254     PUSH_EXC_INFO                   
                        256     LOAD_GLOBAL                     14: BaseException
                        266     CHECK_EXC_MATCH                 
                        268     POP_JUMP_IF_FALSE               3 (to 276)
                        270     POP_TOP                         
                        272     POP_EXCEPT                      
                        274     JUMP_BACKWARD                   33 (to 210)
                        276     RERAISE                         0
                        278     COPY                            3
                        280     POP_EXCEPT                      
                        282     RERAISE                         1
                        284     PUSH_EXC_INFO                   
                        286     PUSH_NULL                       
                        288     LOAD_CONST                      8: '__pyarmor_exit_16106__'
                        290     NOP                             
                        292     LOAD_CONST                      3: b'<COAddr>\x07\x00\x00\x1a\x02\x01\x00\x00\x00\x00\x00\x00\x00\x00\x00\x00\x00\x00\x00\x00'
                        294     CALL                            1
                        302     POP_TOP                         
                        304     RERAISE                         0
                        306     COPY                            3
                        308     POP_EXCEPT                      
                        310     RERAISE                         1
                        312     PUSH_NULL                       
                        314     LOAD_CONST                      8: '__pyarmor_exit_16106__'
                        316     LOAD_CONST                      3: b'<COAddr>\x07\x00\x00\x1a\x02\x01\x00\x00\x00\x00\x00\x00\x00\x00\x00\x00\x00\x00\x00\x00'
                        318     BUILD_TUPLE                     1
                        320     CALL_FUNCTION_EX                0
                        322     POP_TOP                         
                        324     RETURN_VALUE                    
                    [Exception Table]
                        30 to 158 -> 254 [0] 
                        158 to 194 -> 230 [1] lasti
                        194 to 210 -> 254 [0] 
                        230 to 240 -> 248 [3] lasti
                        240 to 254 -> 254 [0] 
                        254 to 272 -> 278 [1] lasti
                        272 to 276 -> 284 [0] 
                        276 to 278 -> 278 [1] lasti
                        278 to 284 -> 284 [0] 
                        284 to 306 -> 306 [1] lasti
                '__pyarmor_exit_16100__'
                None
            [Disassembly]
                0       NOP                             
                2       LOAD_NAME                       0: __name__
                4       STORE_NAME                      1: __module__
                6       LOAD_CONST                      0: 'json_file'
                8       STORE_NAME                      2: __qualname__
                10      NOP                             
                12      PUSH_NULL                       
                14      LOAD_CONST                      2: '__pyarmor_enter_16099__'
                16      LOAD_CONST                      3: b'<COAddr>\x07\x00\x00"6\x00\x00\x00\x00\x00\x00\x00\x00\x00\x00\x00\x00\x00\x00\x00'
                18      BUILD_TUPLE                     1
                20      CALL_FUNCTION_EX                0
                22      POP_TOP                         
                24      RESUME                          0
                26      NOP                             
                28      NOP                             
                30      NOP                             
                32      NOP                             
                34      NOP                             
                36      LOAD_NAME                       4: staticmethod
                38      LOAD_CONST                      4: <CODE> read
                40      MAKE_FUNCTION                   0
                42      CALL                            0
                50      STORE_NAME                      5: read
                52      LOAD_NAME                       4: staticmethod
                54      LOAD_CONST                      5: <CODE> write
                56      MAKE_FUNCTION                   0
                58      CALL                            0
                66      STORE_NAME                      6: write
                68      LOAD_CONST                      7: None
                70      NOP                             
                72      NOP                             
                74      NOP                             
                76      JUMP_FORWARD                    19 (to 116)
                84      POP_TOP                         
                86      RETURN_CONST                    7: None
                88      PUSH_EXC_INFO                   
                90      PUSH_NULL                       
                92      LOAD_CONST                      6: '__pyarmor_exit_16100__'
                94      NOP                             
                96      LOAD_CONST                      3: b'<COAddr>\x07\x00\x00"6\x00\x00\x00\x00\x00\x00\x00\x00\x00\x00\x00\x00\x00\x00\x00'
                98      CALL                            1
                106     POP_TOP                         
                108     RERAISE                         0
                110     COPY                            3
                112     POP_EXCEPT                      
                114     RERAISE                         1
                116     PUSH_NULL                       
                118     LOAD_CONST                      6: '__pyarmor_exit_16100__'
                120     LOAD_CONST                      3: b'<COAddr>\x07\x00\x00"6\x00\x00\x00\x00\x00\x00\x00\x00\x00\x00\x00\x00\x00\x00\x00'
                122     BUILD_TUPLE                     1
                124     CALL_FUNCTION_EX                0
                126     POP_TOP                         
                128     RETURN_VALUE                    
            [Exception Table]
                36 to 68 -> 88 [0] 
                88 to 110 -> 110 [1] lasti
        'json_file'
        [Code]
            File Name: <frozen program.telegram.files>
            Object Name: txt_file
            Qualified Name: txt_file
            Arg Count: 0
            Pos Only Arg Count: 0
            KW Only Arg Count: 0
            Stack Size: 5
            Flags: 0x20000000 (CO_PYARMOR_OBFUSCATED)
            [Names]
                '__name__'
                '__module__'
                '__qualname__'
                '__assert_armored__'
                'staticmethod'
                'unic'
            [Locals+Names]
            [Constants]
                'txt_file'
                '__pyarmor_assert_16107__'
                '__pyarmor_enter_16108__'
                b'<COAddr>\x07\x00\x00"&\x00\x00\x00\x00\x00\x00\x00\x00\x00\x00\x00\x00\x00\x00\x00'
                [Code]
                    File Name: <frozen program.telegram.files>
                    Object Name: unic
                    Qualified Name: txt_file.unic
                    Arg Count: 1
                    Pos Only Arg Count: 0
                    KW Only Arg Count: 0
                    Stack Size: 5
                    Flags: 0x20000003 (CO_OPTIMIZED | CO_NEWLOCALS | CO_PYARMOR_OBFUSCATED)
                    [Names]
                        'numpy'
                        'loadtxt'
                        'str'
                        'unique'
                        'size'
                        'savetxt'
                    [Locals+Names]
                        'path'
                        '__assert_armored__'
                        '_var_var_9'
                        '_var_var_10'
                        '_var_var_11'
                        '_var_var_12'
                    [Constants]
                        None
                        '__pyarmor_assert_16110__'
                        '__pyarmor_enter_16111__'
                        b'<COAddr>\x05\x00\x00\x1a\xda\x00\x00\x00\x00\x00\x00\x00\x00\x00\x00\x00\x00\x00\x00\x00'
                        '%s'
                        (
                            'total'
                            'unic'
                        )
                        '__pyarmor_exit_16112__'
                    [Disassembly]
                        0       NOP                             
                        2       NOP                             
                        4       PUSH_NULL                       
                        6       LOAD_CONST                      2: '__pyarmor_enter_16111__'
                        8       LOAD_CONST                      3: b'<COAddr>\x05\x00\x00\x1a\xda\x00\x00\x00\x00\x00\x00\x00\x00\x00\x00\x00\x00\x00\x00\x00'
                        10      BUILD_TUPLE                     1
                        12      CALL_FUNCTION_EX                0
                        14      POP_TOP                         
                        16      RESUME                          0
                        18      NOP                             
                        20      NOP                             
                        22      NOP                             
                        24      NOP                             
                        26      NOP                             
                        28      LOAD_GLOBAL                     1: NULL + numpy
                        38      LOAD_ATTR                       2: loadtxt
                        58      LOAD_FAST                       0: path
                        60      LOAD_GLOBAL                     4: str
                        70      CALL                            2
                        78      STORE_FAST                      2: _var_var_9
                        80      LOAD_GLOBAL                     1: NULL + numpy
                        90      LOAD_ATTR                       6: unique
                        110     LOAD_FAST                       2: _var_var_9
                        112     CALL                            1
                        120     STORE_FAST                      3: _var_var_10
                        122     LOAD_FAST                       2: _var_var_9
                        124     LOAD_ATTR                       8: size
                        144     STORE_FAST                      4: _var_var_11
                        146     LOAD_FAST                       3: _var_var_10
                        148     LOAD_ATTR                       8: size
                        168     STORE_FAST                      5: _var_var_12
                        170     LOAD_GLOBAL                     1: NULL + numpy
                        180     LOAD_ATTR                       10: savetxt
                        200     LOAD_FAST                       0: path
                        202     LOAD_FAST                       3: _var_var_10
                        204     LOAD_CONST                      4: '%s'
                        206     CALL                            3
                        214     POP_TOP                         
                        216     LOAD_FAST                       4: _var_var_11
                        218     LOAD_FAST                       5: _var_var_12
                        220     LOAD_CONST                      5: ('total', 'unic')
                        222     BUILD_CONST_KEY_MAP             2
                        224     NOP                             
                        226     NOP                             
                        228     NOP                             
                        230     JUMP_FORWARD                    20 (to 272)
                        232     CALL                            1
                        240     POP_TOP                         
                        242     RETURN_VALUE                    
                        244     PUSH_EXC_INFO                   
                        246     PUSH_NULL                       
                        248     LOAD_CONST                      6: '__pyarmor_exit_16112__'
                        250     NOP                             
                        252     LOAD_CONST                      3: b'<COAddr>\x05\x00\x00\x1a\xda\x00\x00\x00\x00\x00\x00\x00\x00\x00\x00\x00\x00\x00\x00\x00'
                        254     CALL                            1
                        262     POP_TOP                         
                        264     RERAISE                         0
                        266     COPY                            3
                        268     POP_EXCEPT                      
                        270     RERAISE                         1
                        272     PUSH_NULL                       
                        274     LOAD_CONST                      6: '__pyarmor_exit_16112__'
                        276     LOAD_CONST                      3: b'<COAddr>\x05\x00\x00\x1a\xda\x00\x00\x00\x00\x00\x00\x00\x00\x00\x00\x00\x00\x00\x00\x00'
                        278     BUILD_TUPLE                     1
                        280     CALL_FUNCTION_EX                0
                        282     POP_TOP                         
                        284     RETURN_VALUE                    
                    [Exception Table]
                        28 to 224 -> 244 [0] 
                        244 to 266 -> 266 [1] lasti
                '__pyarmor_exit_16109__'
                None
            [Disassembly]
                0       NOP                             
                2       LOAD_NAME                       0: __name__
                4       STORE_NAME                      1: __module__
                6       LOAD_CONST                      0: 'txt_file'
                8       STORE_NAME                      2: __qualname__
                10      NOP                             
                12      PUSH_NULL                       
                14      LOAD_CONST                      2: '__pyarmor_enter_16108__'
                16      LOAD_CONST                      3: b'<COAddr>\x07\x00\x00"&\x00\x00\x00\x00\x00\x00\x00\x00\x00\x00\x00\x00\x00\x00\x00'
                18      BUILD_TUPLE                     1
                20      CALL_FUNCTION_EX                0
                22      POP_TOP                         
                24      RESUME                          0
                26      NOP                             
                28      NOP                             
                30      NOP                             
                32      NOP                             
                34      NOP                             
                36      LOAD_NAME                       4: staticmethod
                38      LOAD_CONST                      4: <CODE> unic
                40      MAKE_FUNCTION                   0
                42      CALL                            0
                50      STORE_NAME                      5: unic
                52      LOAD_CONST                      6: None
                54      NOP                             
                56      NOP                             
                58      NOP                             
                60      JUMP_FORWARD                    19 (to 100)
                68      POP_TOP                         
                70      RETURN_CONST                    6: None
                72      PUSH_EXC_INFO                   
                74      PUSH_NULL                       
                76      LOAD_CONST                      5: '__pyarmor_exit_16109__'
                78      NOP                             
                80      LOAD_CONST                      3: b'<COAddr>\x07\x00\x00"&\x00\x00\x00\x00\x00\x00\x00\x00\x00\x00\x00\x00\x00\x00\x00'
                82      CALL                            1
                90      POP_TOP                         
                92      RERAISE                         0
                94      COPY                            3
                96      POP_EXCEPT                      
                98      RERAISE                         1
                100     PUSH_NULL                       
                102     LOAD_CONST                      5: '__pyarmor_exit_16109__'
                104     LOAD_CONST                      3: b'<COAddr>\x07\x00\x00"&\x00\x00\x00\x00\x00\x00\x00\x00\x00\x00\x00\x00\x00\x00\x00'
                106     BUILD_TUPLE                     1
                108     CALL_FUNCTION_EX                0
                110     POP_TOP                         
                112     RETURN_VALUE                    
            [Exception Table]
                36 to 52 -> 72 [0] 
                72 to 94 -> 94 [1] lasti
        'txt_file'
        '__pyarmor_exit_16082__'
        (
            False
        )
        (
            None
            None
            None
            None
            None
            None
            None
            False
            None
            None
            None
            None
        )
        (
            'main'
        )
    [Disassembly]
        0       NOP                             
        2       NOP                             
        4       PUSH_NULL                       
        6       LOAD_CONST                      1: '__pyarmor_enter_16081__'
        8       LOAD_CONST                      2: b'<COAddr>\x07\x00\x00\x1a\xa0\x00\x00\x00\x00\x00\x00\x00\x00\x00\x00\x00\x00\x00\x00\x00'
        10      BUILD_TUPLE                     1
        12      CALL_FUNCTION_EX                0
        14      POP_TOP                         
        16      RESUME                          0
        18      NOP                             
        20      NOP                             
        22      NOP                             
        24      NOP                             
        26      LOAD_CONST                      3: 0
        28      LOAD_CONST                      4: None
        30      IMPORT_NAME                     1: os
        32      STORE_NAME                      1: os
        34      LOAD_CONST                      3: 0
        36      LOAD_CONST                      4: None
        38      IMPORT_NAME                     2: json
        40      STORE_NAME                      2: json
        42      LOAD_CONST                      3: 0
        44      LOAD_CONST                      4: None
        46      IMPORT_NAME                     3: time
        48      STORE_NAME                      3: time
        50      LOAD_CONST                      3: 0
        52      LOAD_CONST                      4: None
        54      IMPORT_NAME                     4: numpy
        56      STORE_NAME                      4: numpy
        58      LOAD_CONST                      3: 0
        60      LOAD_CONST                      4: None
        62      IMPORT_NAME                     5: codecs
        64      STORE_NAME                      5: codecs
        66      LOAD_CONST                      3: 0
        68      LOAD_CONST                      4: None
        70      IMPORT_NAME                     6: datetime
        72      STORE_NAME                      6: datetime
        74      PUSH_NULL                       
        76      LOAD_CONST                      0: '__pyarmor_assert_16080__'
        78      LOAD_CONST                      5: 'sessions/active'   # b'\x81\xf1\x1d\x00 \xf3\xb1\xdc\x08\xb5\x0c\xc3x\xe5\xee\x80'
        80      CALL                            1
        88      BUILD_TUPLE                     1
        90      LOAD_CONST                      6: <CODE> get_account_json
        92      MAKE_FUNCTION                   1
        94      STORE_NAME                      7: get_account_json
        96      LOAD_CONST                      16: (False,)
        98      LOAD_CONST                      7: <CODE> get_session
        100     MAKE_FUNCTION                   1
        102     STORE_NAME                      8: get_session
        104     LOAD_CONST                      17: (None, None, None, None, None, None, None, False, None, None, None, None)
        106     LOAD_CONST                      8: <CODE> set_account_json
        108     MAKE_FUNCTION                   1
        110     STORE_NAME                      9: set_account_json
        112     LOAD_CONST                      18: ('main',)
        114     LOAD_CONST                      9: <CODE> rewrite_proxy_and_status
        116     MAKE_FUNCTION                   1
        118     STORE_NAME                      10: rewrite_proxy_and_status
        120     LOAD_CONST                      10: <CODE> if_file_exist
        122     MAKE_FUNCTION                   0
        124     STORE_NAME                      11: if_file_exist
        126     PUSH_NULL                       
        128     LOAD_BUILD_CLASS                
        130     LOAD_CONST                      11: <CODE> json_file
        132     MAKE_FUNCTION                   0
        134     LOAD_CONST                      12: 'json_file'
        136     CALL                            2
        144     STORE_NAME                      12: json_file
        146     PUSH_NULL                       
        148     LOAD_BUILD_CLASS                
        150     LOAD_CONST                      13: <CODE> txt_file
        152     MAKE_FUNCTION                   0
        154     LOAD_CONST                      14: 'txt_file'
        156     CALL                            2
        164     STORE_NAME                      13: txt_file
        166     LOAD_CONST                      4: None
        168     NOP                             
        170     NOP                             
        172     NOP                             
        174     JUMP_FORWARD                    19 (to 214)
        182     POP_TOP                         
        184     RETURN_CONST                    4: None
        186     PUSH_EXC_INFO                   
        188     PUSH_NULL                       
        190     LOAD_CONST                      15: '__pyarmor_exit_16082__'
        192     NOP                             
        194     LOAD_CONST                      2: b'<COAddr>\x07\x00\x00\x1a\xa0\x00\x00\x00\x00\x00\x00\x00\x00\x00\x00\x00\x00\x00\x00\x00'
        196     CALL                            1
        204     POP_TOP                         
        206     RERAISE                         0
        208     COPY                            3
        210     POP_EXCEPT                      
        212     RERAISE                         1
        214     PUSH_NULL                       
        216     LOAD_CONST                      15: '__pyarmor_exit_16082__'
        218     LOAD_CONST                      2: b'<COAddr>\x07\x00\x00\x1a\xa0\x00\x00\x00\x00\x00\x00\x00\x00\x00\x00\x00\x00\x00\x00\x00'
        220     BUILD_TUPLE                     1
        222     CALL_FUNCTION_EX                0
        224     POP_TOP                         
        226     RETURN_VALUE                    
    [Exception Table]
        26 to 166 -> 186 [0] 
        186 to 208 -> 208 [1] lasti
