#decoded by lolz.live/mrpenny / t.me/zeus_jackpot
# ================================
# Примечания по Pyarmor:
# - Байт-код и объекты кода Pyarmor соответствуют стандартному Python, но присутствуют специальные вызовы функций среды выполнения (runtime) Pyarmor.
# - Вызовы строк — это не ошибки, а маркеры, которые обрабатываются Pyarmor во время выполнения.
#
# Руководство по декомпиляции (без среды выполнения):
# 1. Игнорируйте зашифрованные байты после `#`; используйте только строку до `#`.
# 2. Удалите "__pyarmor_enter_xxx__"(b"<COAddr>...") и "__pyarmor_leave_xxx__"(b"<COAddr>...") (пролог/эпилог).
# 3. "__pyarmor_assert_xxx__"(A) не является настоящим оператором assert.
#    - Если A — это имя или читаемая строка: замените на A.
#    - Если A — это (X, "Y"): замените на X.Y.
#    - Если A — это (X, "Y", Z): замените на X.Y = Z.
#    - В противном случае: выберите наиболее подходящую/логичную замену.
# 4. "__pyarmor_bcc_xxx__"(...) указывает на машинный (нативный) код; тело функции недоступно. Добавьте комментарий.
# ================================

[Code]
    File Name: <frozen program.telegram.links>
    Object Name: <module>
    Qualified Name: <module>
    Arg Count: 0
    Pos Only Arg Count: 0
    KW Only Arg Count: 0
    Stack Size: 5
    Flags: 0x20000000 (CO_PYARMOR_OBFUSCATED)
    [Names]
        '__assert_armored__'
        'tg_links'
    [Locals+Names]
    [Constants]
        '__pyarmor_assert_16239__'
        '__pyarmor_enter_16240__'
        b'<COAddr>\x07\x00\x00\x1a(\x00\x00\x00\x00\x00\x00\x00\x00\x00\x00\x00\x00\x00\x00\x00'
        [Code]
            File Name: <frozen program.telegram.links>
            Object Name: tg_links
            Qualified Name: tg_links
            Arg Count: 0
            Pos Only Arg Count: 0
            KW Only Arg Count: 0
            Stack Size: 5
            Flags: 0x20000000 (CO_PYARMOR_OBFUSCATED)
            [Names]
                '__name__'
                '__module__'
                '__qualname__'
                '__assert_armored__'
                '__init__'
                'staticmethod'
                'get_hash'
                '_correct'
                '_correct_private'
                'str'
                'message_link_id_username'
                'get_data'
                'standart'
                'phones'
                'contacts_phone_or_username'
                'clear_username'
            [Locals+Names]
            [Constants]
                'tg_links'
                '__pyarmor_assert_16242__'
                '__pyarmor_enter_16243__'
                b'<COAddr>\x05\x00\x00"\xd0\x00\x00\x00\x00\x00\x00\x00\x00\x00\x00\x00\x00\x00\x00\x00'
                [Code]
                    File Name: <frozen program.telegram.links>
                    Object Name: __init__
                    Qualified Name: tg_links.__init__
                    Arg Count: 1
                    Pos Only Arg Count: 0
                    KW Only Arg Count: 0
                    Stack Size: 5
                    Flags: 0x20000003 (CO_OPTIMIZED | CO_NEWLOCALS | CO_PYARMOR_OBFUSCATED)
                    [Names]
                    [Locals+Names]
                        'self'
                        '__assert_armored__'
                    [Constants]
                        None
                        '__pyarmor_assert_16245__'
                        '__pyarmor_enter_16246__'
                        b'<COAddr>\x07\x00\x00\x1a\x16\x00\x00\x00\x00\x00\x00\x00\x00\x00\x00\x00\x00\x00\x00\x00'
                        '__pyarmor_exit_16247__'
                    [Disassembly]
                        0       NOP                             
                        2       NOP                             
                        4       PUSH_NULL                       
                        6       LOAD_CONST                      2: '__pyarmor_enter_16246__'
                        8       LOAD_CONST                      3: b'<COAddr>\x07\x00\x00\x1a\x16\x00\x00\x00\x00\x00\x00\x00\x00\x00\x00\x00\x00\x00\x00\x00'
                        10      BUILD_TUPLE                     1
                        12      CALL_FUNCTION_EX                0
                        14      POP_TOP                         
                        16      RESUME                          0
                        18      NOP                             
                        20      NOP                             
                        22      NOP                             
                        24      NOP                             
                        26      NOP                             
                        28      LOAD_CONST                      0: None
                        30      NOP                             
                        32      NOP                             
                        34      NOP                             
                        36      JUMP_FORWARD                    19 (to 76)
                        44      POP_TOP                         
                        46      RETURN_CONST                    0: None
                        48      PUSH_EXC_INFO                   
                        50      PUSH_NULL                       
                        52      LOAD_CONST                      4: '__pyarmor_exit_16247__'
                        54      NOP                             
                        56      LOAD_CONST                      3: b'<COAddr>\x07\x00\x00\x1a\x16\x00\x00\x00\x00\x00\x00\x00\x00\x00\x00\x00\x00\x00\x00\x00'
                        58      CALL                            1
                        66      POP_TOP                         
                        68      RERAISE                         0
                        70      COPY                            3
                        72      POP_EXCEPT                      
                        74      RERAISE                         1
                        76      PUSH_NULL                       
                        78      LOAD_CONST                      4: '__pyarmor_exit_16247__'
                        80      LOAD_CONST                      3: b'<COAddr>\x07\x00\x00\x1a\x16\x00\x00\x00\x00\x00\x00\x00\x00\x00\x00\x00\x00\x00\x00\x00'
                        82      BUILD_TUPLE                     1
                        84      CALL_FUNCTION_EX                0
                        86      POP_TOP                         
                        88      RETURN_VALUE                    
                    [Exception Table]
                        48 to 70 -> 70 [1] lasti
                [Code]
                    File Name: <frozen program.telegram.links>
                    Object Name: get_hash
                    Qualified Name: tg_links.get_hash
                    Arg Count: 1
                    Pos Only Arg Count: 0
                    KW Only Arg Count: 0
                    Stack Size: 5
                    Flags: 0x20000003 (CO_OPTIMIZED | CO_NEWLOCALS | CO_PYARMOR_OBFUSCATED)
                    [Names]
                        'replace'
                        'strip'
                    [Locals+Names]
                        'link'
                        '__assert_armored__'
                    [Constants]
                        None
                        '__pyarmor_assert_16248__'
                        '__pyarmor_enter_16249__'
                        b'<COAddr>\x05\x00\x00\x1a*\x01\x00\x00\x00\x00\x00\x00\x00\x00\x00\x00\x00\x00\x00\x00'
                        '__pyarmor_exit_16250__'
                        ''
                        'https://t.me/joinchat'   # b'\x81\xea\x0c\x07#\xe9\xe4\x9dT\xeeC\xcdi\xa3\xf2\x8a\x06S\xb8\xaf\xab\xdf'
                        'https://t.me/'   # b'\x81\xea\x0c\x07#\xe9\xe4\x9dT\xeeC\xcdi\xa3'
                        '+'
                        '/'
                        ':'
                        '@'
                    [Disassembly]
                        0       NOP                             
                        2       NOP                             
                        4       PUSH_NULL                       
                        6       LOAD_CONST                      2: '__pyarmor_enter_16249__'
                        8       LOAD_CONST                      3: b'<COAddr>\x05\x00\x00\x1a*\x01\x00\x00\x00\x00\x00\x00\x00\x00\x00\x00\x00\x00\x00\x00'
                        10      BUILD_TUPLE                     1
                        12      CALL_FUNCTION_EX                0
                        14      POP_TOP                         
                        16      RESUME                          0
                        18      NOP                             
                        20      NOP                             
                        22      NOP                             
                        24      NOP                             
                        26      NOP                             
                        28      LOAD_FAST                       0: link
                        30      POP_JUMP_IF_NOT_NONE            11 (to 54)
                        32      NOP                             
                        34      LOAD_CONST                      5: ''
                        36      NOP                             
                        38      NOP                             
                        40      NOP                             
                        42      JUMP_FORWARD                    154 (to 352)
                        50      POP_TOP                         
                        52      RETURN_CONST                    5: ''
                        54      LOAD_FAST                       0: link
                        56      LOAD_ATTR                       1: replace
                        76      PUSH_NULL                       
                        78      LOAD_CONST                      1: '__pyarmor_assert_16248__'
                        80      LOAD_CONST                      6: 'https://t.me/joinchat'   # b'\x81\xea\x0c\x07#\xe9\xe4\x9dT\xeeC\xcdi\xa3\xf2\x8a\x06S\xb8\xaf\xab\xdf'
                        82      CALL                            1
                        90      LOAD_CONST                      5: ''
                        92      CALL                            2
                        100     LOAD_ATTR                       1: replace
                        120     PUSH_NULL                       
                        122     LOAD_CONST                      1: '__pyarmor_assert_16248__'
                        124     LOAD_CONST                      7: 'https://t.me/'   # b'\x81\xea\x0c\x07#\xe9\xe4\x9dT\xeeC\xcdi\xa3'
                        126     CALL                            1
                        134     LOAD_CONST                      5: ''
                        136     CALL                            2
                        144     LOAD_ATTR                       1: replace
                        164     LOAD_CONST                      8: '+'
                        166     LOAD_CONST                      5: ''
                        168     CALL                            2
                        176     LOAD_ATTR                       1: replace
                        196     LOAD_CONST                      9: '/'
                        198     LOAD_CONST                      5: ''
                        200     CALL                            2
                        208     LOAD_ATTR                       1: replace
                        228     LOAD_CONST                      10: ':'
                        230     LOAD_CONST                      5: ''
                        232     CALL                            2
                        240     LOAD_ATTR                       1: replace
                        260     LOAD_CONST                      11: '@'
                        262     LOAD_CONST                      5: ''
                        264     CALL                            2
                        272     STORE_FAST                      0: link
                        274     LOAD_FAST                       0: link
                        276     LOAD_ATTR                       3: strip
                        296     CALL                            0
                        304     NOP                             
                        306     NOP                             
                        308     NOP                             
                        310     JUMP_FORWARD                    20 (to 352)
                        312     CALL                            1
                        320     POP_TOP                         
                        322     RETURN_VALUE                    
                        324     PUSH_EXC_INFO                   
                        326     PUSH_NULL                       
                        328     LOAD_CONST                      4: '__pyarmor_exit_16250__'
                        330     NOP                             
                        332     LOAD_CONST                      3: b'<COAddr>\x05\x00\x00\x1a*\x01\x00\x00\x00\x00\x00\x00\x00\x00\x00\x00\x00\x00\x00\x00'
                        334     CALL                            1
                        342     POP_TOP                         
                        344     RERAISE                         0
                        346     COPY                            3
                        348     POP_EXCEPT                      
                        350     RERAISE                         1
                        352     PUSH_NULL                       
                        354     LOAD_CONST                      4: '__pyarmor_exit_16250__'
                        356     LOAD_CONST                      3: b'<COAddr>\x05\x00\x00\x1a*\x01\x00\x00\x00\x00\x00\x00\x00\x00\x00\x00\x00\x00\x00\x00'
                        358     BUILD_TUPLE                     1
                        360     CALL_FUNCTION_EX                0
                        362     POP_TOP                         
                        364     RETURN_VALUE                    
                    [Exception Table]
                        28 to 32 -> 324 [0] 
                        54 to 304 -> 324 [0] 
                        324 to 346 -> 346 [1] lasti
                [Code]
                    File Name: <frozen program.telegram.links>
                    Object Name: _correct
                    Qualified Name: tg_links._correct
                    Arg Count: 1
                    Pos Only Arg Count: 0
                    KW Only Arg Count: 0
                    Stack Size: 6
                    Flags: 0x20000003 (CO_OPTIMIZED | CO_NEWLOCALS | CO_PYARMOR_OBFUSCATED)
                    [Names]
                        'replace'
                        'strip'
                    [Locals+Names]
                        'link'
                        '__assert_armored__'
                    [Constants]
                        None
                        '__pyarmor_assert_16251__'
                        '__pyarmor_enter_16252__'
                        b'<COAddr>\x07\x00\x00\x1a\xa2\x00\x00\x00\x00\x00\x00\x00\x00\x00\x00\x00\x00\x00\x00\x00'
                        '__pyarmor_exit_16253__'
                        ''
                        '+'
                        'joinchat/'   # b'\x81\xe8\x17\x1a=\xf9\xb6\xd3\x0f\xb5'
                        '@'
                    [Disassembly]
                        0       NOP                             
                        2       NOP                             
                        4       PUSH_NULL                       
                        6       LOAD_CONST                      2: '__pyarmor_enter_16252__'
                        8       LOAD_CONST                      3: b'<COAddr>\x07\x00\x00\x1a\xa2\x00\x00\x00\x00\x00\x00\x00\x00\x00\x00\x00\x00\x00\x00\x00'
                        10      BUILD_TUPLE                     1
                        12      CALL_FUNCTION_EX                0
                        14      POP_TOP                         
                        16      RESUME                          0
                        18      NOP                             
                        20      NOP                             
                        22      NOP                             
                        24      NOP                             
                        26      NOP                             
                        28      LOAD_FAST                       0: link
                        30      POP_JUMP_IF_NOT_NONE            11 (to 54)
                        32      NOP                             
                        34      LOAD_CONST                      5: ''
                        36      NOP                             
                        38      NOP                             
                        40      NOP                             
                        42      JUMP_FORWARD                    86 (to 216)
                        50      POP_TOP                         
                        52      RETURN_CONST                    5: ''
                        54      LOAD_FAST                       0: link
                        56      LOAD_ATTR                       1: replace
                        76      LOAD_CONST                      6: '+'
                        78      PUSH_NULL                       
                        80      LOAD_CONST                      1: '__pyarmor_assert_16251__'
                        82      LOAD_CONST                      7: 'joinchat/'   # b'\x81\xe8\x17\x1a=\xf9\xb6\xd3\x0f\xb5'
                        84      CALL                            1
                        92      CALL                            2
                        100     LOAD_ATTR                       1: replace
                        120     LOAD_CONST                      8: '@'
                        122     LOAD_CONST                      5: ''
                        124     CALL                            2
                        132     STORE_FAST                      0: link
                        134     LOAD_FAST                       0: link
                        136     LOAD_ATTR                       3: strip
                        156     CALL                            0
                        164     STORE_FAST                      0: link
                        166     LOAD_FAST                       0: link
                        168     NOP                             
                        170     NOP                             
                        172     NOP                             
                        174     JUMP_FORWARD                    20 (to 216)
                        176     CALL                            1
                        184     POP_TOP                         
                        186     RETURN_VALUE                    
                        188     PUSH_EXC_INFO                   
                        190     PUSH_NULL                       
                        192     LOAD_CONST                      4: '__pyarmor_exit_16253__'
                        194     NOP                             
                        196     LOAD_CONST                      3: b'<COAddr>\x07\x00\x00\x1a\xa2\x00\x00\x00\x00\x00\x00\x00\x00\x00\x00\x00\x00\x00\x00\x00'
                        198     CALL                            1
                        206     POP_TOP                         
                        208     RERAISE                         0
                        210     COPY                            3
                        212     POP_EXCEPT                      
                        214     RERAISE                         1
                        216     PUSH_NULL                       
                        218     LOAD_CONST                      4: '__pyarmor_exit_16253__'
                        220     LOAD_CONST                      3: b'<COAddr>\x07\x00\x00\x1a\xa2\x00\x00\x00\x00\x00\x00\x00\x00\x00\x00\x00\x00\x00\x00\x00'
                        222     BUILD_TUPLE                     1
                        224     CALL_FUNCTION_EX                0
                        226     POP_TOP                         
                        228     RETURN_VALUE                    
                    [Exception Table]
                        28 to 32 -> 188 [0] 
                        54 to 168 -> 188 [0] 
                        188 to 210 -> 210 [1] lasti
                [Code]
                    File Name: <frozen program.telegram.links>
                    Object Name: _correct_private
                    Qualified Name: tg_links._correct_private
                    Arg Count: 1
                    Pos Only Arg Count: 0
                    KW Only Arg Count: 0
                    Stack Size: 6
                    Flags: 0x20000003 (CO_OPTIMIZED | CO_NEWLOCALS | CO_PYARMOR_OBFUSCATED)
                    [Names]
                        'replace'
                        'strip'
                    [Locals+Names]
                        'link'
                        '__assert_armored__'
                    [Constants]
                        None
                        '__pyarmor_assert_16254__'
                        '__pyarmor_enter_16255__'
                        b'<COAddr>\x05\x00\x00\x1a~\x01\x00\x00\x00\x00\x00\x00\x00\x00\x00\x00\x00\x00\x00\x00'
                        '__pyarmor_exit_16256__'
                        ''
                        'https://t.me/joinchat'   # b'\x81\xea\x0c\x07#\xe9\xe4\x9dT\xeeC\xcdi\xa3\xf2\x8a\x06S\xb8\xaf\xab\xdf'
                        ' '
                        'https://t.me/+'   # b'\x81\xea\x0c\x07#\xe9\xe4\x9dT\xeeC\xcdi\xa3\xb3'
                        'https://t.me/joinchat/'   # b'\x81\xea\x0c\x07#\xe9\xe4\x9dT\xeeC\xcdi\xa3\xf2\x8a\x06S\xb8\xaf\xab\xdf\x01'
                        'https://t.me/'   # b'\x81\xea\x0c\x07#\xe9\xe4\x9dT\xeeC\xcdi\xa3'
                        '@'
                    [Disassembly]
                        0       NOP                             
                        2       NOP                             
                        4       PUSH_NULL                       
                        6       LOAD_CONST                      2: '__pyarmor_enter_16255__'
                        8       LOAD_CONST                      3: b'<COAddr>\x05\x00\x00\x1a~\x01\x00\x00\x00\x00\x00\x00\x00\x00\x00\x00\x00\x00\x00\x00'
                        10      BUILD_TUPLE                     1
                        12      CALL_FUNCTION_EX                0
                        14      POP_TOP                         
                        16      RESUME                          0
                        18      NOP                             
                        20      NOP                             
                        22      NOP                             
                        24      NOP                             
                        26      NOP                             
                        28      LOAD_FAST                       0: link
                        30      POP_JUMP_IF_NOT_NONE            11 (to 54)
                        32      NOP                             
                        34      LOAD_CONST                      5: ''
                        36      NOP                             
                        38      NOP                             
                        40      NOP                             
                        42      JUMP_FORWARD                    196 (to 436)
                        50      POP_TOP                         
                        52      RETURN_CONST                    5: ''
                        54      PUSH_NULL                       
                        56      LOAD_CONST                      1: '__pyarmor_assert_16254__'
                        58      LOAD_CONST                      6: 'https://t.me/joinchat'   # b'\x81\xea\x0c\x07#\xe9\xe4\x9dT\xeeC\xcdi\xa3\xf2\x8a\x06S\xb8\xaf\xab\xdf'
                        60      CALL                            1
                        68      LOAD_FAST                       0: link
                        70      CONTAINS_OP                     0 (in)
                        72      POP_JUMP_IF_FALSE               41 (to 156)
                        74      LOAD_FAST                       0: link
                        76      LOAD_ATTR                       1: replace
                        96      LOAD_CONST                      7: ' '
                        98      LOAD_CONST                      5: ''
                        100     CALL                            2
                        108     LOAD_ATTR                       3: strip
                        128     CALL                            0
                        136     NOP                             
                        138     NOP                             
                        140     NOP                             
                        142     JUMP_FORWARD                    146 (to 436)
                        144     CALL                            1
                        152     POP_TOP                         
                        154     RETURN_VALUE                    
                        156     PUSH_NULL                       
                        158     LOAD_CONST                      1: '__pyarmor_assert_16254__'
                        160     LOAD_CONST                      8: 'https://t.me/+'   # b'\x81\xea\x0c\x07#\xe9\xe4\x9dT\xeeC\xcdi\xa3\xb3'
                        162     CALL                            1
                        170     LOAD_FAST                       0: link
                        172     CONTAINS_OP                     0 (in)
                        174     POP_JUMP_IF_FALSE               53 (to 282)
                        176     LOAD_FAST                       0: link
                        178     LOAD_ATTR                       1: replace
                        198     PUSH_NULL                       
                        200     LOAD_CONST                      1: '__pyarmor_assert_16254__'
                        202     LOAD_CONST                      8: 'https://t.me/+'   # b'\x81\xea\x0c\x07#\xe9\xe4\x9dT\xeeC\xcdi\xa3\xb3'
                        204     CALL                            1
                        212     PUSH_NULL                       
                        214     LOAD_CONST                      1: '__pyarmor_assert_16254__'
                        216     LOAD_CONST                      9: 'https://t.me/joinchat/'   # b'\x81\xea\x0c\x07#\xe9\xe4\x9dT\xeeC\xcdi\xa3\xf2\x8a\x06S\xb8\xaf\xab\xdf\x01'
                        218     CALL                            1
                        226     CALL                            2
                        234     LOAD_ATTR                       3: strip
                        254     CALL                            0
                        262     NOP                             
                        264     NOP                             
                        266     NOP                             
                        268     JUMP_FORWARD                    83 (to 436)
                        270     CALL                            1
                        278     POP_TOP                         
                        280     RETURN_VALUE                    
                        282     LOAD_FAST                       0: link
                        284     LOAD_ATTR                       1: replace
                        304     PUSH_NULL                       
                        306     LOAD_CONST                      1: '__pyarmor_assert_16254__'
                        308     LOAD_CONST                      10: 'https://t.me/'   # b'\x81\xea\x0c\x07#\xe9\xe4\x9dT\xeeC\xcdi\xa3'
                        310     CALL                            1
                        318     LOAD_CONST                      5: ''
                        320     CALL                            2
                        328     LOAD_ATTR                       1: replace
                        348     LOAD_CONST                      11: '@'
                        350     LOAD_CONST                      5: ''
                        352     CALL                            2
                        360     LOAD_ATTR                       3: strip
                        380     CALL                            0
                        388     NOP                             
                        390     NOP                             
                        392     NOP                             
                        394     JUMP_FORWARD                    20 (to 436)
                        396     CALL                            1
                        404     POP_TOP                         
                        406     RETURN_VALUE                    
                        408     PUSH_EXC_INFO                   
                        410     PUSH_NULL                       
                        412     LOAD_CONST                      4: '__pyarmor_exit_16256__'
                        414     NOP                             
                        416     LOAD_CONST                      3: b'<COAddr>\x05\x00\x00\x1a~\x01\x00\x00\x00\x00\x00\x00\x00\x00\x00\x00\x00\x00\x00\x00'
                        418     CALL                            1
                        426     POP_TOP                         
                        428     RERAISE                         0
                        430     COPY                            3
                        432     POP_EXCEPT                      
                        434     RERAISE                         1
                        436     PUSH_NULL                       
                        438     LOAD_CONST                      4: '__pyarmor_exit_16256__'
                        440     LOAD_CONST                      3: b'<COAddr>\x05\x00\x00\x1a~\x01\x00\x00\x00\x00\x00\x00\x00\x00\x00\x00\x00\x00\x00\x00'
                        442     BUILD_TUPLE                     1
                        444     CALL_FUNCTION_EX                0
                        446     POP_TOP                         
                        448     RETURN_VALUE                    
                    [Exception Table]
                        28 to 32 -> 408 [0] 
                        54 to 136 -> 408 [0] 
                        156 to 262 -> 408 [0] 
                        282 to 388 -> 408 [0] 
                        408 to 430 -> 430 [1] lasti
                'link'
                [Code]
                    File Name: <frozen program.telegram.links>
                    Object Name: message_link_id_username
                    Qualified Name: tg_links.message_link_id_username
                    Arg Count: 1
                    Pos Only Arg Count: 0
                    KW Only Arg Count: 0
                    Stack Size: 6
                    Flags: 0x20000003 (CO_OPTIMIZED | CO_NEWLOCALS | CO_PYARMOR_OBFUSCATED)
                    [Names]
                        'replace'
                        'split'
                        'int'
                        'Exception'
                        'print'
                    [Locals+Names]
                        'link'
                        '__assert_armored__'
                        '_var_var_0'
                    [Constants]
                        None
                        '__pyarmor_assert_16257__'
                        '__pyarmor_enter_16258__'
                        b'<COAddr>\x07\x00\x00\x1a\xdc\x01\x00\x00\x00\x00\x00\x00\x00\x00\x00\x00\x00\x00\x00\x00'
                        'https://t.me/'   # b'\x81\xea\x0c\x07#\xe9\xe4\x9dT\xeeC\xcdi\xa3'
                        ''
                        'http://t.me/'   # b'\x81\xea\x0c\x07#\xa0\xf1\x9d\x0f\xb4\x00\xc5#'
                        'https://telegram.me/'   # b'\x81\xea\x0c\x07#\xe9\xe4\x9dT\xee\x08\xcci\xeb\xea\x84\x02\x13\xb6\xa2\xe5'
                        'http://telegram.me/'   # b'\x81\xea\x0c\x07#\xa0\xf1\x9d\x0f\xff\x01\xc5k\xfe\xf9\x88AP\xbe\xe8'
                        '/'
                        0
                        'c'
                        1
                        2
                        (
                            'group_id'
                            'username'
                            'mess_id'
                        )
                        '__pyarmor_exit_16259__'
                        'message_link_id_username: '   # b'\x81\xef\x1d\x00 \xfb\xb9\xd7$\xf6\x04\xceg\xd3\xf1\x810H\xa8\xa2\xb8\xc5O\xc1\x005\xe3'
                        False
                    [Disassembly]
                        0       NOP                             
                        2       NOP                             
                        4       PUSH_NULL                       
                        6       LOAD_CONST                      2: '__pyarmor_enter_16258__'
                        8       LOAD_CONST                      3: b'<COAddr>\x07\x00\x00\x1a\xdc\x01\x00\x00\x00\x00\x00\x00\x00\x00\x00\x00\x00\x00\x00\x00'
                        10      BUILD_TUPLE                     1
                        12      CALL_FUNCTION_EX                0
                        14      POP_TOP                         
                        16      RESUME                          0
                        18      NOP                             
                        20      NOP                             
                        22      NOP                             
                        24      NOP                             
                        26      NOP                             
                        28      NOP                             
                        30      LOAD_FAST                       0: link
                        32      LOAD_ATTR                       1: replace
                        52      PUSH_NULL                       
                        54      LOAD_CONST                      1: '__pyarmor_assert_16257__'
                        56      LOAD_CONST                      4: 'https://t.me/'   # b'\x81\xea\x0c\x07#\xe9\xe4\x9dT\xeeC\xcdi\xa3'
                        58      CALL                            1
                        66      LOAD_CONST                      5: ''
                        68      CALL                            2
                        76      LOAD_ATTR                       1: replace
                        96      PUSH_NULL                       
                        98      LOAD_CONST                      1: '__pyarmor_assert_16257__'
                        100     LOAD_CONST                      6: 'http://t.me/'   # b'\x81\xea\x0c\x07#\xa0\xf1\x9d\x0f\xb4\x00\xc5#'
                        102     CALL                            1
                        110     LOAD_CONST                      5: ''
                        112     CALL                            2
                        120     LOAD_ATTR                       1: replace
                        140     PUSH_NULL                       
                        142     LOAD_CONST                      1: '__pyarmor_assert_16257__'
                        144     LOAD_CONST                      7: 'https://telegram.me/'   # b'\x81\xea\x0c\x07#\xe9\xe4\x9dT\xee\x08\xcci\xeb\xea\x84\x02\x13\xb6\xa2\xe5'
                        146     CALL                            1
                        154     LOAD_CONST                      5: ''
                        156     CALL                            2
                        164     LOAD_ATTR                       1: replace
                        184     PUSH_NULL                       
                        186     LOAD_CONST                      1: '__pyarmor_assert_16257__'
                        188     LOAD_CONST                      8: 'http://telegram.me/'   # b'\x81\xea\x0c\x07#\xa0\xf1\x9d\x0f\xff\x01\xc5k\xfe\xf9\x88AP\xbe\xe8'
                        190     CALL                            1
                        198     LOAD_CONST                      5: ''
                        200     CALL                            2
                        208     STORE_FAST                      0: link
                        210     LOAD_FAST                       0: link
                        212     LOAD_ATTR                       3: split
                        232     LOAD_CONST                      9: '/'
                        234     CALL                            1
                        242     STORE_FAST                      0: link
                        244     LOAD_FAST                       0: link
                        246     LOAD_CONST                      10: 0
                        248     BINARY_SUBSCR                   
                        252     LOAD_CONST                      11: 'c'
                        254     COMPARE_OP                      40 (==)
                        258     POP_JUMP_IF_FALSE               39 (to 338)
                        260     LOAD_GLOBAL                     5: NULL + int
                        270     LOAD_FAST                       0: link
                        272     LOAD_CONST                      12: 1
                        274     BINARY_SUBSCR                   
                        278     CALL                            1
                        286     LOAD_CONST                      0: None
                        288     LOAD_GLOBAL                     5: NULL + int
                        298     LOAD_FAST                       0: link
                        300     LOAD_CONST                      13: 2
                        302     BINARY_SUBSCR                   
                        306     CALL                            1
                        314     LOAD_CONST                      14: ('group_id', 'username', 'mess_id')
                        316     BUILD_CONST_KEY_MAP             3
                        318     NOP                             
                        320     NOP                             
                        322     NOP                             
                        324     JUMP_FORWARD                    102 (to 530)
                        326     CALL                            1
                        334     POP_TOP                         
                        336     RETURN_VALUE                    
                        338     LOAD_CONST                      10: 0
                        340     LOAD_FAST                       0: link
                        342     LOAD_CONST                      10: 0
                        344     BINARY_SUBSCR                   
                        348     LOAD_GLOBAL                     5: NULL + int
                        358     LOAD_FAST                       0: link
                        360     LOAD_CONST                      12: 1
                        362     BINARY_SUBSCR                   
                        366     CALL                            1
                        374     LOAD_CONST                      14: ('group_id', 'username', 'mess_id')
                        376     BUILD_CONST_KEY_MAP             3
                        378     NOP                             
                        380     NOP                             
                        382     NOP                             
                        384     JUMP_FORWARD                    72 (to 530)
                        386     CALL                            1
                        394     POP_TOP                         
                        396     RETURN_VALUE                    
                        398     PUSH_EXC_INFO                   
                        400     LOAD_GLOBAL                     6: Exception
                        410     CHECK_EXC_MATCH                 
                        412     POP_JUMP_IF_FALSE               30 (to 474)
                        414     STORE_FAST                      2: _var_var_0
                        416     LOAD_GLOBAL                     9: NULL + print
                        426     PUSH_NULL                       
                        428     LOAD_CONST                      1: '__pyarmor_assert_16257__'
                        430     LOAD_CONST                      16: 'message_link_id_username: '   # b'\x81\xef\x1d\x00 \xfb\xb9\xd7$\xf6\x04\xceg\xd3\xf1\x810H\xa8\xa2\xb8\xc5O\xc1\x005\xe3'
                        432     CALL                            1
                        440     LOAD_FAST                       2: _var_var_0
                        442     FORMAT_VALUE                    0 (FVC_NONE)
                        444     BUILD_STRING                    2
                        446     CALL                            1
                        454     POP_TOP                         
                        456     POP_EXCEPT                      
                        458     LOAD_CONST                      0: None
                        460     STORE_FAST                      2: _var_var_0
                        462     DELETE_FAST                     2: _var_var_0
                        464     JUMP_FORWARD                    8 (to 482)
                        466     LOAD_CONST                      0: None
                        468     STORE_FAST                      2: _var_var_0
                        470     DELETE_FAST                     2: _var_var_0
                        472     RERAISE                         1
                        474     RERAISE                         0
                        476     COPY                            3
                        478     POP_EXCEPT                      
                        480     RERAISE                         1
                        482     LOAD_CONST                      17: False
                        484     NOP                             
                        486     NOP                             
                        488     NOP                             
                        490     JUMP_FORWARD                    19 (to 530)
                        498     POP_TOP                         
                        500     RETURN_CONST                    17: False
                        502     PUSH_EXC_INFO                   
                        504     PUSH_NULL                       
                        506     LOAD_CONST                      15: '__pyarmor_exit_16259__'
                        508     NOP                             
                        510     LOAD_CONST                      3: b'<COAddr>\x07\x00\x00\x1a\xdc\x01\x00\x00\x00\x00\x00\x00\x00\x00\x00\x00\x00\x00\x00\x00'
                        512     CALL                            1
                        520     POP_TOP                         
                        522     RERAISE                         0
                        524     COPY                            3
                        526     POP_EXCEPT                      
                        528     RERAISE                         1
                        530     PUSH_NULL                       
                        532     LOAD_CONST                      15: '__pyarmor_exit_16259__'
                        534     LOAD_CONST                      3: b'<COAddr>\x07\x00\x00\x1a\xdc\x01\x00\x00\x00\x00\x00\x00\x00\x00\x00\x00\x00\x00\x00\x00'
                        536     BUILD_TUPLE                     1
                        538     CALL_FUNCTION_EX                0
                        540     POP_TOP                         
                        542     RETURN_VALUE                    
                    [Exception Table]
                        30 to 318 -> 398 [0] 
                        338 to 378 -> 398 [0] 
                        398 to 416 -> 476 [1] lasti
                        416 to 456 -> 466 [1] lasti
                        456 to 466 -> 502 [0] 
                        466 to 476 -> 476 [1] lasti
                        476 to 482 -> 502 [0] 
                        502 to 524 -> 524 [1] lasti
                [Code]
                    File Name: <frozen program.telegram.links>
                    Object Name: get_data
                    Qualified Name: tg_links.get_data
                    Arg Count: 1
                    Pos Only Arg Count: 0
                    KW Only Arg Count: 0
                    Stack Size: 6
                    Flags: 0x20000003 (CO_OPTIMIZED | CO_NEWLOCALS | CO_PYARMOR_OBFUSCATED)
                    [Names]
                        'replace'
                        'split'
                        'int'
                        'len'
                        'Exception'
                        'print'
                    [Locals+Names]
                        'link'
                        '__assert_armored__'
                        '_var_var_0'
                    [Constants]
                        None
                        '__pyarmor_assert_16260__'
                        '__pyarmor_enter_16261__'
                        b'<COAddr>\x05\x00\x00\x1a(\x02\x00\x00\x00\x00\x00\x00\x00\x00\x00\x00\x00\x00\x00\x00'
                        'https://t.me/'   # b'\x81\xea\x0c\x07#\xe9\xe4\x9dT\xeeC\xcdi\xa3'
                        ''
                        'http://t.me/'   # b'\x81\xea\x0c\x07#\xa0\xf1\x9d\x0f\xb4\x00\xc5#'
                        'https://telegram.me/'   # b'\x81\xea\x0c\x07#\xe9\xe4\x9dT\xee\x08\xcci\xeb\xea\x84\x02\x13\xb6\xa2\xe5'
                        'http://telegram.me/'   # b'\x81\xea\x0c\x07#\xa0\xf1\x9d\x0f\xff\x01\xc5k\xfe\xf9\x88AP\xbe\xe8'
                        '/'
                        0
                        'c'
                        1
                        2
                        (
                            'id'
                            'username'
                            'mess_id'
                        )
                        '__pyarmor_exit_16262__'
                        'get_data: '   # b'\x81\xe5\x1d\x07\x0c\xfe\xbf\xc6\x1a\xa0M'
                        False
                    [Disassembly]
                        0       NOP                             
                        2       NOP                             
                        4       PUSH_NULL                       
                        6       LOAD_CONST                      2: '__pyarmor_enter_16261__'
                        8       LOAD_CONST                      3: b'<COAddr>\x05\x00\x00\x1a(\x02\x00\x00\x00\x00\x00\x00\x00\x00\x00\x00\x00\x00\x00\x00'
                        10      BUILD_TUPLE                     1
                        12      CALL_FUNCTION_EX                0
                        14      POP_TOP                         
                        16      RESUME                          0
                        18      NOP                             
                        20      NOP                             
                        22      NOP                             
                        24      NOP                             
                        26      NOP                             
                        28      NOP                             
                        30      LOAD_FAST                       0: link
                        32      LOAD_ATTR                       1: replace
                        52      PUSH_NULL                       
                        54      LOAD_CONST                      1: '__pyarmor_assert_16260__'
                        56      LOAD_CONST                      4: 'https://t.me/'   # b'\x81\xea\x0c\x07#\xe9\xe4\x9dT\xeeC\xcdi\xa3'
                        58      CALL                            1
                        66      LOAD_CONST                      5: ''
                        68      CALL                            2
                        76      LOAD_ATTR                       1: replace
                        96      PUSH_NULL                       
                        98      LOAD_CONST                      1: '__pyarmor_assert_16260__'
                        100     LOAD_CONST                      6: 'http://t.me/'   # b'\x81\xea\x0c\x07#\xa0\xf1\x9d\x0f\xb4\x00\xc5#'
                        102     CALL                            1
                        110     LOAD_CONST                      5: ''
                        112     CALL                            2
                        120     LOAD_ATTR                       1: replace
                        140     PUSH_NULL                       
                        142     LOAD_CONST                      1: '__pyarmor_assert_16260__'
                        144     LOAD_CONST                      7: 'https://telegram.me/'   # b'\x81\xea\x0c\x07#\xe9\xe4\x9dT\xee\x08\xcci\xeb\xea\x84\x02\x13\xb6\xa2\xe5'
                        146     CALL                            1
                        154     LOAD_CONST                      5: ''
                        156     CALL                            2
                        164     LOAD_ATTR                       1: replace
                        184     PUSH_NULL                       
                        186     LOAD_CONST                      1: '__pyarmor_assert_16260__'
                        188     LOAD_CONST                      8: 'http://telegram.me/'   # b'\x81\xea\x0c\x07#\xa0\xf1\x9d\x0f\xff\x01\xc5k\xfe\xf9\x88AP\xbe\xe8'
                        190     CALL                            1
                        198     LOAD_CONST                      5: ''
                        200     CALL                            2
                        208     LOAD_ATTR                       3: split
                        228     LOAD_CONST                      9: '/'
                        230     CALL                            1
                        238     STORE_FAST                      0: link
                        240     LOAD_FAST                       0: link
                        242     LOAD_CONST                      10: 0
                        244     BINARY_SUBSCR                   
                        248     LOAD_CONST                      11: 'c'
                        250     COMPARE_OP                      40 (==)
                        254     POP_JUMP_IF_FALSE               39 (to 334)
                        256     LOAD_GLOBAL                     5: NULL + int
                        266     LOAD_FAST                       0: link
                        268     LOAD_CONST                      12: 1
                        270     BINARY_SUBSCR                   
                        274     CALL                            1
                        282     LOAD_CONST                      0: None
                        284     LOAD_GLOBAL                     5: NULL + int
                        294     LOAD_FAST                       0: link
                        296     LOAD_CONST                      13: 2
                        298     BINARY_SUBSCR                   
                        302     CALL                            1
                        310     LOAD_CONST                      14: ('id', 'username', 'mess_id')
                        312     BUILD_CONST_KEY_MAP             3
                        314     NOP                             
                        316     NOP                             
                        318     NOP                             
                        320     JUMP_FORWARD                    142 (to 606)
                        322     CALL                            1
                        330     POP_TOP                         
                        332     RETURN_VALUE                    
                        334     LOAD_GLOBAL                     7: NULL + len
                        344     LOAD_FAST                       0: link
                        346     CALL                            1
                        354     LOAD_CONST                      13: 2
                        356     COMPARE_OP                      40 (==)
                        360     POP_JUMP_IF_FALSE               38 (to 438)
                        362     LOAD_FAST                       0: link
                        364     LOAD_CONST                      12: 1
                        366     BINARY_SUBSCR                   
                        370     LOAD_CONST                      5: ''
                        372     COMPARE_OP                      55 (!=)
                        376     POP_JUMP_IF_FALSE               30 (to 438)
                        378     LOAD_CONST                      0: None
                        380     LOAD_FAST                       0: link
                        382     LOAD_CONST                      10: 0
                        384     BINARY_SUBSCR                   
                        388     LOAD_GLOBAL                     5: NULL + int
                        398     LOAD_FAST                       0: link
                        400     LOAD_CONST                      12: 1
                        402     BINARY_SUBSCR                   
                        406     CALL                            1
                        414     LOAD_CONST                      14: ('id', 'username', 'mess_id')
                        416     BUILD_CONST_KEY_MAP             3
                        418     NOP                             
                        420     NOP                             
                        422     NOP                             
                        424     JUMP_FORWARD                    90 (to 606)
                        426     CALL                            1
                        434     POP_TOP                         
                        436     RETURN_VALUE                    
                        438     LOAD_CONST                      0: None
                        440     LOAD_FAST                       0: link
                        442     LOAD_CONST                      10: 0
                        444     BINARY_SUBSCR                   
                        448     LOAD_CONST                      0: None
                        450     LOAD_CONST                      14: ('id', 'username', 'mess_id')
                        452     BUILD_CONST_KEY_MAP             3
                        454     NOP                             
                        456     NOP                             
                        458     NOP                             
                        460     JUMP_FORWARD                    72 (to 606)
                        462     CALL                            1
                        470     POP_TOP                         
                        472     RETURN_VALUE                    
                        474     PUSH_EXC_INFO                   
                        476     LOAD_GLOBAL                     8: Exception
                        486     CHECK_EXC_MATCH                 
                        488     POP_JUMP_IF_FALSE               30 (to 550)
                        490     STORE_FAST                      2: _var_var_0
                        492     LOAD_GLOBAL                     11: NULL + print
                        502     PUSH_NULL                       
                        504     LOAD_CONST                      1: '__pyarmor_assert_16260__'
                        506     LOAD_CONST                      16: 'get_data: '   # b'\x81\xe5\x1d\x07\x0c\xfe\xbf\xc6\x1a\xa0M'
                        508     CALL                            1
                        516     LOAD_FAST                       2: _var_var_0
                        518     FORMAT_VALUE                    0 (FVC_NONE)
                        520     BUILD_STRING                    2
                        522     CALL                            1
                        530     POP_TOP                         
                        532     POP_EXCEPT                      
                        534     LOAD_CONST                      0: None
                        536     STORE_FAST                      2: _var_var_0
                        538     DELETE_FAST                     2: _var_var_0
                        540     JUMP_FORWARD                    8 (to 558)
                        542     LOAD_CONST                      0: None
                        544     STORE_FAST                      2: _var_var_0
                        546     DELETE_FAST                     2: _var_var_0
                        548     RERAISE                         1
                        550     RERAISE                         0
                        552     COPY                            3
                        554     POP_EXCEPT                      
                        556     RERAISE                         1
                        558     LOAD_CONST                      17: False
                        560     NOP                             
                        562     NOP                             
                        564     NOP                             
                        566     JUMP_FORWARD                    19 (to 606)
                        574     POP_TOP                         
                        576     RETURN_CONST                    17: False
                        578     PUSH_EXC_INFO                   
                        580     PUSH_NULL                       
                        582     LOAD_CONST                      15: '__pyarmor_exit_16262__'
                        584     NOP                             
                        586     LOAD_CONST                      3: b'<COAddr>\x05\x00\x00\x1a(\x02\x00\x00\x00\x00\x00\x00\x00\x00\x00\x00\x00\x00\x00\x00'
                        588     CALL                            1
                        596     POP_TOP                         
                        598     RERAISE                         0
                        600     COPY                            3
                        602     POP_EXCEPT                      
                        604     RERAISE                         1
                        606     PUSH_NULL                       
                        608     LOAD_CONST                      15: '__pyarmor_exit_16262__'
                        610     LOAD_CONST                      3: b'<COAddr>\x05\x00\x00\x1a(\x02\x00\x00\x00\x00\x00\x00\x00\x00\x00\x00\x00\x00\x00\x00'
                        612     BUILD_TUPLE                     1
                        614     CALL_FUNCTION_EX                0
                        616     POP_TOP                         
                        618     RETURN_VALUE                    
                    [Exception Table]
                        30 to 314 -> 474 [0] 
                        334 to 418 -> 474 [0] 
                        438 to 454 -> 474 [0] 
                        474 to 492 -> 552 [1] lasti
                        492 to 532 -> 542 [1] lasti
                        532 to 542 -> 578 [0] 
                        542 to 552 -> 552 [1] lasti
                        552 to 558 -> 578 [0] 
                        578 to 600 -> 600 [1] lasti
                [Code]
                    File Name: <frozen program.telegram.links>
                    Object Name: standart
                    Qualified Name: tg_links.standart
                    Arg Count: 1
                    Pos Only Arg Count: 0
                    KW Only Arg Count: 0
                    Stack Size: 6
                    Flags: 0x20000003 (CO_OPTIMIZED | CO_NEWLOCALS | CO_PYARMOR_OBFUSCATED)
                    [Names]
                        'strip'
                        'replace'
                    [Locals+Names]
                        'link'
                        '__assert_armored__'
                    [Constants]
                        None
                        '__pyarmor_assert_16263__'
                        '__pyarmor_enter_16264__'
                        b'<COAddr>\x07\x00\x00\x1a,\x01\x00\x00\x00\x00\x00\x00\x00\x00\x00\x00\x00\x00\x00\x00'
                        'http:'
                        'https:'
                        'joinchat'
                        '+'
                        'https://t.me/+'   # b'\x81\xea\x0c\x07#\xe9\xe4\x9dT\xeeC\xcdi\xa3\xb3'
                        'https://t.me/joinchat/'   # b'\x81\xea\x0c\x07#\xe9\xe4\x9dT\xeeC\xcdi\xa3\xf2\x8a\x06S\xb8\xaf\xab\xdf\x01'
                        '__pyarmor_exit_16265__'
                        '@'
                        'https://t.me/'   # b'\x81\xea\x0c\x07#\xe9\xe4\x9dT\xeeC\xcdi\xa3'
                        'telegram.me'   # b'\x81\xf6\x1d\x1f6\xfd\xac\xd3\x16\xb4\x00\xc5'
                        't.me'
                    [Disassembly]
                        0       NOP                             
                        2       NOP                             
                        4       PUSH_NULL                       
                        6       LOAD_CONST                      2: '__pyarmor_enter_16264__'
                        8       LOAD_CONST                      3: b'<COAddr>\x07\x00\x00\x1a,\x01\x00\x00\x00\x00\x00\x00\x00\x00\x00\x00\x00\x00\x00\x00'
                        10      BUILD_TUPLE                     1
                        12      CALL_FUNCTION_EX                0
                        14      POP_TOP                         
                        16      RESUME                          0
                        18      NOP                             
                        20      NOP                             
                        22      NOP                             
                        24      NOP                             
                        26      NOP                             
                        28      LOAD_FAST                       0: link
                        30      LOAD_ATTR                       1: strip
                        50      CALL                            0
                        58      LOAD_ATTR                       3: replace
                        78      LOAD_CONST                      4: 'http:'
                        80      LOAD_CONST                      5: 'https:'
                        82      CALL                            2
                        90      STORE_FAST                      0: link
                        92      LOAD_CONST                      6: 'joinchat'
                        94      LOAD_FAST                       0: link
                        96      CONTAINS_OP                     0 (in)
                        98      POP_JUMP_IF_TRUE                4 (to 108)
                        100     LOAD_CONST                      7: '+'
                        102     LOAD_FAST                       0: link
                        104     CONTAINS_OP                     0 (in)
                        106     POP_JUMP_IF_FALSE               39 (to 186)
                        108     LOAD_FAST                       0: link
                        110     LOAD_ATTR                       3: replace
                        130     PUSH_NULL                       
                        132     LOAD_CONST                      1: '__pyarmor_assert_16263__'
                        134     LOAD_CONST                      8: 'https://t.me/+'   # b'\x81\xea\x0c\x07#\xe9\xe4\x9dT\xeeC\xcdi\xa3\xb3'
                        136     CALL                            1
                        144     PUSH_NULL                       
                        146     LOAD_CONST                      1: '__pyarmor_assert_16263__'
                        148     LOAD_CONST                      9: 'https://t.me/joinchat/'   # b'\x81\xea\x0c\x07#\xe9\xe4\x9dT\xeeC\xcdi\xa3\xf2\x8a\x06S\xb8\xaf\xab\xdf\x01'
                        150     CALL                            1
                        158     CALL                            2
                        166     NOP                             
                        168     NOP                             
                        170     NOP                             
                        172     JUMP_FORWARD                    90 (to 354)
                        174     CALL                            1
                        182     POP_TOP                         
                        184     RETURN_VALUE                    
                        186     LOAD_CONST                      11: '@'
                        188     LOAD_FAST                       0: link
                        190     CONTAINS_OP                     0 (in)
                        192     POP_JUMP_IF_FALSE               33 (to 260)
                        194     LOAD_FAST                       0: link
                        196     LOAD_ATTR                       3: replace
                        216     LOAD_CONST                      11: '@'
                        218     PUSH_NULL                       
                        220     LOAD_CONST                      1: '__pyarmor_assert_16263__'
                        222     LOAD_CONST                      12: 'https://t.me/'   # b'\x81\xea\x0c\x07#\xe9\xe4\x9dT\xeeC\xcdi\xa3'
                        224     CALL                            1
                        232     CALL                            2
                        240     NOP                             
                        242     NOP                             
                        244     NOP                             
                        246     JUMP_FORWARD                    53 (to 354)
                        248     CALL                            1
                        256     POP_TOP                         
                        258     RETURN_VALUE                    
                        260     LOAD_FAST                       0: link
                        262     LOAD_ATTR                       3: replace
                        282     PUSH_NULL                       
                        284     LOAD_CONST                      1: '__pyarmor_assert_16263__'
                        286     LOAD_CONST                      13: 'telegram.me'   # b'\x81\xf6\x1d\x1f6\xfd\xac\xd3\x16\xb4\x00\xc5'
                        288     CALL                            1
                        296     LOAD_CONST                      14: 't.me'
                        298     CALL                            2
                        306     NOP                             
                        308     NOP                             
                        310     NOP                             
                        312     JUMP_FORWARD                    20 (to 354)
                        314     CALL                            1
                        322     POP_TOP                         
                        324     RETURN_VALUE                    
                        326     PUSH_EXC_INFO                   
                        328     PUSH_NULL                       
                        330     LOAD_CONST                      10: '__pyarmor_exit_16265__'
                        332     NOP                             
                        334     LOAD_CONST                      3: b'<COAddr>\x07\x00\x00\x1a,\x01\x00\x00\x00\x00\x00\x00\x00\x00\x00\x00\x00\x00\x00\x00'
                        336     CALL                            1
                        344     POP_TOP                         
                        346     RERAISE                         0
                        348     COPY                            3
                        350     POP_EXCEPT                      
                        352     RERAISE                         1
                        354     PUSH_NULL                       
                        356     LOAD_CONST                      10: '__pyarmor_exit_16265__'
                        358     LOAD_CONST                      3: b'<COAddr>\x07\x00\x00\x1a,\x01\x00\x00\x00\x00\x00\x00\x00\x00\x00\x00\x00\x00\x00\x00'
                        360     BUILD_TUPLE                     1
                        362     CALL_FUNCTION_EX                0
                        364     POP_TOP                         
                        366     RETURN_VALUE                    
                    [Exception Table]
                        28 to 166 -> 326 [0] 
                        186 to 240 -> 326 [0] 
                        260 to 306 -> 326 [0] 
                        326 to 348 -> 348 [1] lasti
                'phone'
                [Code]
                    File Name: <frozen program.telegram.links>
                    Object Name: phones
                    Qualified Name: tg_links.phones
                    Arg Count: 1
                    Pos Only Arg Count: 0
                    KW Only Arg Count: 0
                    Stack Size: 5
                    Flags: 0x20000003 (CO_OPTIMIZED | CO_NEWLOCALS | CO_PYARMOR_OBFUSCATED)
                    [Names]
                        'replace'
                    [Locals+Names]
                        'phone'
                        '__assert_armored__'
                    [Constants]
                        None
                        '__pyarmor_assert_16266__'
                        '__pyarmor_enter_16267__'
                        b'<COAddr>\x07\x00\x00\x1a\xfc\x00\x00\x00\x00\x00\x00\x00\x00\x00\x00\x00\x00\x00\x00\x00'
                        ' '
                        ''
                        '+'
                        '-'
                        '.'
                        ','
                        '('
                        ')'
                        '__pyarmor_exit_16268__'
                    [Disassembly]
                        0       NOP                             
                        2       NOP                             
                        4       PUSH_NULL                       
                        6       LOAD_CONST                      2: '__pyarmor_enter_16267__'
                        8       LOAD_CONST                      3: b'<COAddr>\x07\x00\x00\x1a\xfc\x00\x00\x00\x00\x00\x00\x00\x00\x00\x00\x00\x00\x00\x00\x00'
                        10      BUILD_TUPLE                     1
                        12      CALL_FUNCTION_EX                0
                        14      POP_TOP                         
                        16      RESUME                          0
                        18      NOP                             
                        20      NOP                             
                        22      NOP                             
                        24      NOP                             
                        26      NOP                             
                        28      LOAD_FAST                       0: phone
                        30      LOAD_ATTR                       1: replace
                        50      LOAD_CONST                      4: ' '
                        52      LOAD_CONST                      5: ''
                        54      CALL                            2
                        62      LOAD_ATTR                       1: replace
                        82      LOAD_CONST                      6: '+'
                        84      LOAD_CONST                      5: ''
                        86      CALL                            2
                        94      LOAD_ATTR                       1: replace
                        114     LOAD_CONST                      7: '-'
                        116     LOAD_CONST                      5: ''
                        118     CALL                            2
                        126     LOAD_ATTR                       1: replace
                        146     LOAD_CONST                      8: '.'
                        148     LOAD_CONST                      5: ''
                        150     CALL                            2
                        158     LOAD_ATTR                       1: replace
                        178     LOAD_CONST                      9: ','
                        180     LOAD_CONST                      5: ''
                        182     CALL                            2
                        190     LOAD_ATTR                       1: replace
                        210     LOAD_CONST                      10: '('
                        212     LOAD_CONST                      5: ''
                        214     CALL                            2
                        222     LOAD_ATTR                       1: replace
                        242     LOAD_CONST                      11: ')'
                        244     LOAD_CONST                      5: ''
                        246     CALL                            2
                        254     STORE_FAST                      0: phone
                        256     LOAD_FAST                       0: phone
                        258     NOP                             
                        260     NOP                             
                        262     NOP                             
                        264     JUMP_FORWARD                    20 (to 306)
                        266     CALL                            1
                        274     POP_TOP                         
                        276     RETURN_VALUE                    
                        278     PUSH_EXC_INFO                   
                        280     PUSH_NULL                       
                        282     LOAD_CONST                      12: '__pyarmor_exit_16268__'
                        284     NOP                             
                        286     LOAD_CONST                      3: b'<COAddr>\x07\x00\x00\x1a\xfc\x00\x00\x00\x00\x00\x00\x00\x00\x00\x00\x00\x00\x00\x00\x00'
                        288     CALL                            1
                        296     POP_TOP                         
                        298     RERAISE                         0
                        300     COPY                            3
                        302     POP_EXCEPT                      
                        304     RERAISE                         1
                        306     PUSH_NULL                       
                        308     LOAD_CONST                      12: '__pyarmor_exit_16268__'
                        310     LOAD_CONST                      3: b'<COAddr>\x07\x00\x00\x1a\xfc\x00\x00\x00\x00\x00\x00\x00\x00\x00\x00\x00\x00\x00\x00\x00'
                        312     BUILD_TUPLE                     1
                        314     CALL_FUNCTION_EX                0
                        316     POP_TOP                         
                        318     RETURN_VALUE                    
                    [Exception Table]
                        28 to 258 -> 278 [0] 
                        278 to 300 -> 300 [1] lasti
                'data'
                [Code]
                    File Name: <frozen program.telegram.links>
                    Object Name: contacts_phone_or_username
                    Qualified Name: tg_links.contacts_phone_or_username
                    Arg Count: 1
                    Pos Only Arg Count: 0
                    KW Only Arg Count: 0
                    Stack Size: 14
                    Flags: 0x20000003 (CO_OPTIMIZED | CO_NEWLOCALS | CO_PYARMOR_OBFUSCATED)
                    [Names]
                        'replace'
                        'isdigit'
                        'int'
                    [Locals+Names]
                        'data'
                        '__assert_armored__'
                        '_var_var_1'
                        '_var_var_2'
                    [Constants]
                        None
                        '__pyarmor_assert_16269__'
                        '__pyarmor_enter_16270__'
                        b'<COAddr>\x05\x00\x00\x1a\xee\x00\x00\x00\x00\x00\x00\x00\x00\x00\x00\x00\x00\x00\x00\x00'
                        'https://t.me/'   # b'\x81\xea\x0c\x07#\xe9\xe4\x9dT\xeeC\xcdi\xa3'
                        'http://t.me/'   # b'\x81\xea\x0c\x07#\xa0\xf1\x9d\x0f\xb4\x00\xc5#'
                        'https://telegram.me/'   # b'\x81\xea\x0c\x07#\xe9\xe4\x9dT\xee\x08\xcci\xeb\xea\x84\x02\x13\xb6\xa2\xe5'
                        'http://telegram.me/'   # b'\x81\xea\x0c\x07#\xa0\xf1\x9d\x0f\xff\x01\xc5k\xfe\xf9\x88AP\xbe\xe8'
                        '@'
                        '+'
                        '-'
                        '.'
                        ','
                        '('
                        ')'
                        '/'
                        ':'
                        ' '
                        ''
                        (
                            'phone'
                            'username'
                        )
                        '__pyarmor_exit_16271__'
                    [Disassembly]
                        0       NOP                             
                        2       NOP                             
                        4       PUSH_NULL                       
                        6       LOAD_CONST                      2: '__pyarmor_enter_16270__'
                        8       LOAD_CONST                      3: b'<COAddr>\x05\x00\x00\x1a\xee\x00\x00\x00\x00\x00\x00\x00\x00\x00\x00\x00\x00\x00\x00\x00'
                        10      BUILD_TUPLE                     1
                        12      CALL_FUNCTION_EX                0
                        14      POP_TOP                         
                        16      RESUME                          0
                        18      NOP                             
                        20      NOP                             
                        22      NOP                             
                        24      NOP                             
                        26      NOP                             
                        28      PUSH_NULL                       
                        30      LOAD_CONST                      1: '__pyarmor_assert_16269__'
                        32      LOAD_CONST                      4: 'https://t.me/'   # b'\x81\xea\x0c\x07#\xe9\xe4\x9dT\xeeC\xcdi\xa3'
                        34      CALL                            1
                        42      PUSH_NULL                       
                        44      LOAD_CONST                      1: '__pyarmor_assert_16269__'
                        46      LOAD_CONST                      5: 'http://t.me/'   # b'\x81\xea\x0c\x07#\xa0\xf1\x9d\x0f\xb4\x00\xc5#'
                        48      CALL                            1
                        56      PUSH_NULL                       
                        58      LOAD_CONST                      1: '__pyarmor_assert_16269__'
                        60      LOAD_CONST                      6: 'https://telegram.me/'   # b'\x81\xea\x0c\x07#\xe9\xe4\x9dT\xee\x08\xcci\xeb\xea\x84\x02\x13\xb6\xa2\xe5'
                        62      CALL                            1
                        70      PUSH_NULL                       
                        72      LOAD_CONST                      1: '__pyarmor_assert_16269__'
                        74      LOAD_CONST                      7: 'http://telegram.me/'   # b'\x81\xea\x0c\x07#\xa0\xf1\x9d\x0f\xff\x01\xc5k\xfe\xf9\x88AP\xbe\xe8'
                        76      CALL                            1
                        84      LOAD_CONST                      8: '@'
                        86      LOAD_CONST                      9: '+'
                        88      LOAD_CONST                      10: '-'
                        90      LOAD_CONST                      11: '.'
                        92      LOAD_CONST                      12: ','
                        94      LOAD_CONST                      13: '('
                        96      LOAD_CONST                      14: ')'
                        98      LOAD_CONST                      15: '/'
                        100     LOAD_CONST                      16: ':'
                        102     LOAD_CONST                      17: ' '
                        104     BUILD_LIST                      14
                        106     STORE_FAST                      2: _var_var_1
                        108     LOAD_FAST                       2: _var_var_1
                        110     GET_ITER                        
                        112     FOR_ITER                        20 (to 154)
                        116     STORE_FAST                      3: _var_var_2
                        118     LOAD_FAST                       0: data
                        120     LOAD_ATTR                       1: replace
                        140     LOAD_FAST                       3: _var_var_2
                        142     LOAD_CONST                      18: ''
                        144     CALL                            2
                        152     STORE_FAST                      0: data
                        154     JUMP_BACKWARD                   22 (to 112)
                        156     END_FOR                         
                        158     LOAD_FAST                       0: data
                        160     LOAD_ATTR                       3: isdigit
                        180     CALL                            0
                        188     POP_JUMP_IF_FALSE               23 (to 236)
                        190     LOAD_GLOBAL                     5: NULL + int
                        200     LOAD_FAST                       0: data
                        202     CALL                            1
                        210     LOAD_CONST                      0: None
                        212     LOAD_CONST                      19: ('phone', 'username')
                        214     BUILD_CONST_KEY_MAP             2
                        216     NOP                             
                        218     NOP                             
                        220     NOP                             
                        222     JUMP_FORWARD                    34 (to 292)
                        224     CALL                            1
                        232     POP_TOP                         
                        234     RETURN_VALUE                    
                        236     LOAD_CONST                      0: None
                        238     LOAD_FAST                       0: data
                        240     LOAD_CONST                      19: ('phone', 'username')
                        242     BUILD_CONST_KEY_MAP             2
                        244     NOP                             
                        246     NOP                             
                        248     NOP                             
                        250     JUMP_FORWARD                    20 (to 292)
                        252     CALL                            1
                        260     POP_TOP                         
                        262     RETURN_VALUE                    
                        264     PUSH_EXC_INFO                   
                        266     PUSH_NULL                       
                        268     LOAD_CONST                      20: '__pyarmor_exit_16271__'
                        270     NOP                             
                        272     LOAD_CONST                      3: b'<COAddr>\x05\x00\x00\x1a\xee\x00\x00\x00\x00\x00\x00\x00\x00\x00\x00\x00\x00\x00\x00\x00'
                        274     CALL                            1
                        282     POP_TOP                         
                        284     RERAISE                         0
                        286     COPY                            3
                        288     POP_EXCEPT                      
                        290     RERAISE                         1
                        292     PUSH_NULL                       
                        294     LOAD_CONST                      20: '__pyarmor_exit_16271__'
                        296     LOAD_CONST                      3: b'<COAddr>\x05\x00\x00\x1a\xee\x00\x00\x00\x00\x00\x00\x00\x00\x00\x00\x00\x00\x00\x00\x00'
                        298     BUILD_TUPLE                     1
                        300     CALL_FUNCTION_EX                0
                        302     POP_TOP                         
                        304     RETURN_VALUE                    
                    [Exception Table]
                        28 to 216 -> 264 [0] 
                        236 to 244 -> 264 [0] 
                        264 to 286 -> 286 [1] lasti
                [Code]
                    File Name: <frozen program.telegram.links>
                    Object Name: clear_username
                    Qualified Name: tg_links.clear_username
                    Arg Count: 1
                    Pos Only Arg Count: 0
                    KW Only Arg Count: 0
                    Stack Size: 13
                    Flags: 0x20000003 (CO_OPTIMIZED | CO_NEWLOCALS | CO_PYARMOR_OBFUSCATED)
                    [Names]
                        'replace'
                    [Locals+Names]
                        'data'
                        '__assert_armored__'
                        '_var_var_1'
                        '_var_var_2'
                    [Constants]
                        None
                        '__pyarmor_assert_16272__'
                        '__pyarmor_enter_16273__'
                        b'<COAddr>\x05\x00\x00\x1a\x98\x00\x00\x00\x00\x00\x00\x00\x00\x00\x00\x00\x00\x00\x00\x00'
                        'https://t.me/'   # b'\x81\xea\x0c\x07#\xe9\xe4\x9dT\xeeC\xcdi\xa3'
                        'http://t.me/'   # b'\x81\xea\x0c\x07#\xa0\xf1\x9d\x0f\xb4\x00\xc5#'
                        'https://telegram.me/'   # b'\x81\xea\x0c\x07#\xe9\xe4\x9dT\xee\x08\xcci\xeb\xea\x84\x02\x13\xb6\xa2\xe5'
                        'http://telegram.me/'   # b'\x81\xea\x0c\x07#\xa0\xf1\x9d\x0f\xff\x01\xc5k\xfe\xf9\x88AP\xbe\xe8'
                        '@'
                        '-'
                        '.'
                        ','
                        '('
                        ')'
                        '/'
                        ':'
                        ' '
                        ''
                        '__pyarmor_exit_16274__'
                    [Disassembly]
                        0       NOP                             
                        2       NOP                             
                        4       PUSH_NULL                       
                        6       LOAD_CONST                      2: '__pyarmor_enter_16273__'
                        8       LOAD_CONST                      3: b'<COAddr>\x05\x00\x00\x1a\x98\x00\x00\x00\x00\x00\x00\x00\x00\x00\x00\x00\x00\x00\x00\x00'
                        10      BUILD_TUPLE                     1
                        12      CALL_FUNCTION_EX                0
                        14      POP_TOP                         
                        16      RESUME                          0
                        18      NOP                             
                        20      NOP                             
                        22      NOP                             
                        24      NOP                             
                        26      NOP                             
                        28      PUSH_NULL                       
                        30      LOAD_CONST                      1: '__pyarmor_assert_16272__'
                        32      LOAD_CONST                      4: 'https://t.me/'   # b'\x81\xea\x0c\x07#\xe9\xe4\x9dT\xeeC\xcdi\xa3'
                        34      CALL                            1
                        42      PUSH_NULL                       
                        44      LOAD_CONST                      1: '__pyarmor_assert_16272__'
                        46      LOAD_CONST                      5: 'http://t.me/'   # b'\x81\xea\x0c\x07#\xa0\xf1\x9d\x0f\xb4\x00\xc5#'
                        48      CALL                            1
                        56      PUSH_NULL                       
                        58      LOAD_CONST                      1: '__pyarmor_assert_16272__'
                        60      LOAD_CONST                      6: 'https://telegram.me/'   # b'\x81\xea\x0c\x07#\xe9\xe4\x9dT\xee\x08\xcci\xeb\xea\x84\x02\x13\xb6\xa2\xe5'
                        62      CALL                            1
                        70      PUSH_NULL                       
                        72      LOAD_CONST                      1: '__pyarmor_assert_16272__'
                        74      LOAD_CONST                      7: 'http://telegram.me/'   # b'\x81\xea\x0c\x07#\xa0\xf1\x9d\x0f\xff\x01\xc5k\xfe\xf9\x88AP\xbe\xe8'
                        76      CALL                            1
                        84      LOAD_CONST                      8: '@'
                        86      LOAD_CONST                      9: '-'
                        88      LOAD_CONST                      10: '.'
                        90      LOAD_CONST                      11: ','
                        92      LOAD_CONST                      12: '('
                        94      LOAD_CONST                      13: ')'
                        96      LOAD_CONST                      14: '/'
                        98      LOAD_CONST                      15: ':'
                        100     LOAD_CONST                      16: ' '
                        102     BUILD_LIST                      13
                        104     STORE_FAST                      2: _var_var_1
                        106     LOAD_FAST                       2: _var_var_1
                        108     GET_ITER                        
                        110     FOR_ITER                        20 (to 152)
                        114     STORE_FAST                      3: _var_var_2
                        116     LOAD_FAST                       0: data
                        118     LOAD_ATTR                       1: replace
                        138     LOAD_FAST                       3: _var_var_2
                        140     LOAD_CONST                      17: ''
                        142     CALL                            2
                        150     STORE_FAST                      0: data
                        152     JUMP_BACKWARD                   22 (to 110)
                        154     END_FOR                         
                        156     LOAD_FAST                       0: data
                        158     NOP                             
                        160     NOP                             
                        162     NOP                             
                        164     JUMP_FORWARD                    20 (to 206)
                        166     CALL                            1
                        174     POP_TOP                         
                        176     RETURN_VALUE                    
                        178     PUSH_EXC_INFO                   
                        180     PUSH_NULL                       
                        182     LOAD_CONST                      18: '__pyarmor_exit_16274__'
                        184     NOP                             
                        186     LOAD_CONST                      3: b'<COAddr>\x05\x00\x00\x1a\x98\x00\x00\x00\x00\x00\x00\x00\x00\x00\x00\x00\x00\x00\x00\x00'
                        188     CALL                            1
                        196     POP_TOP                         
                        198     RERAISE                         0
                        200     COPY                            3
                        202     POP_EXCEPT                      
                        204     RERAISE                         1
                        206     PUSH_NULL                       
                        208     LOAD_CONST                      18: '__pyarmor_exit_16274__'
                        210     LOAD_CONST                      3: b'<COAddr>\x05\x00\x00\x1a\x98\x00\x00\x00\x00\x00\x00\x00\x00\x00\x00\x00\x00\x00\x00\x00'
                        212     BUILD_TUPLE                     1
                        214     CALL_FUNCTION_EX                0
                        216     POP_TOP                         
                        218     RETURN_VALUE                    
                    [Exception Table]
                        28 to 158 -> 178 [0] 
                        178 to 200 -> 200 [1] lasti
                '__pyarmor_exit_16244__'
                None
            [Disassembly]
                0       NOP                             
                2       LOAD_NAME                       0: __name__
                4       STORE_NAME                      1: __module__
                6       LOAD_CONST                      0: 'tg_links'
                8       STORE_NAME                      2: __qualname__
                10      NOP                             
                12      PUSH_NULL                       
                14      LOAD_CONST                      2: '__pyarmor_enter_16243__'
                16      LOAD_CONST                      3: b'<COAddr>\x05\x00\x00"\xd0\x00\x00\x00\x00\x00\x00\x00\x00\x00\x00\x00\x00\x00\x00\x00'
                18      BUILD_TUPLE                     1
                20      CALL_FUNCTION_EX                0
                22      POP_TOP                         
                24      RESUME                          0
                26      NOP                             
                28      NOP                             
                30      NOP                             
                32      NOP                             
                34      NOP                             
                36      LOAD_CONST                      4: <CODE> __init__
                38      MAKE_FUNCTION                   0
                40      STORE_NAME                      4: __init__
                42      LOAD_NAME                       5: staticmethod
                44      LOAD_CONST                      5: <CODE> get_hash
                46      MAKE_FUNCTION                   0
                48      CALL                            0
                56      STORE_NAME                      6: get_hash
                58      LOAD_NAME                       5: staticmethod
                60      LOAD_CONST                      6: <CODE> _correct
                62      MAKE_FUNCTION                   0
                64      CALL                            0
                72      STORE_NAME                      7: _correct
                74      LOAD_NAME                       5: staticmethod
                76      LOAD_CONST                      7: <CODE> _correct_private
                78      MAKE_FUNCTION                   0
                80      CALL                            0
                88      STORE_NAME                      8: _correct_private
                90      LOAD_NAME                       5: staticmethod
                92      LOAD_CONST                      8: 'link'
                94      LOAD_NAME                       9: str
                96      BUILD_TUPLE                     2
                98      LOAD_CONST                      9: <CODE> message_link_id_username
                100     MAKE_FUNCTION                   4
                102     CALL                            0
                110     STORE_NAME                      10: message_link_id_username
                112     LOAD_NAME                       5: staticmethod
                114     LOAD_CONST                      8: 'link'
                116     LOAD_NAME                       9: str
                118     BUILD_TUPLE                     2
                120     LOAD_CONST                      10: <CODE> get_data
                122     MAKE_FUNCTION                   4
                124     CALL                            0
                132     STORE_NAME                      11: get_data
                134     LOAD_NAME                       5: staticmethod
                136     LOAD_CONST                      8: 'link'
                138     LOAD_NAME                       9: str
                140     BUILD_TUPLE                     2
                142     LOAD_CONST                      11: <CODE> standart
                144     MAKE_FUNCTION                   4
                146     CALL                            0
                154     STORE_NAME                      12: standart
                156     LOAD_NAME                       5: staticmethod
                158     LOAD_CONST                      12: 'phone'
                160     LOAD_NAME                       9: str
                162     BUILD_TUPLE                     2
                164     LOAD_CONST                      13: <CODE> phones
                166     MAKE_FUNCTION                   4
                168     CALL                            0
                176     STORE_NAME                      13: phones
                178     LOAD_NAME                       5: staticmethod
                180     LOAD_CONST                      14: 'data'
                182     LOAD_NAME                       9: str
                184     BUILD_TUPLE                     2
                186     LOAD_CONST                      15: <CODE> contacts_phone_or_username
                188     MAKE_FUNCTION                   4
                190     CALL                            0
                198     STORE_NAME                      14: contacts_phone_or_username
                200     LOAD_NAME                       5: staticmethod
                202     LOAD_CONST                      14: 'data'
                204     LOAD_NAME                       9: str
                206     BUILD_TUPLE                     2
                208     LOAD_CONST                      16: <CODE> clear_username
                210     MAKE_FUNCTION                   4
                212     CALL                            0
                220     STORE_NAME                      15: clear_username
                222     LOAD_CONST                      18: None
                224     NOP                             
                226     NOP                             
                228     NOP                             
                230     JUMP_FORWARD                    19 (to 270)
                238     POP_TOP                         
                240     RETURN_CONST                    18: None
                242     PUSH_EXC_INFO                   
                244     PUSH_NULL                       
                246     LOAD_CONST                      17: '__pyarmor_exit_16244__'
                248     NOP                             
                250     LOAD_CONST                      3: b'<COAddr>\x05\x00\x00"\xd0\x00\x00\x00\x00\x00\x00\x00\x00\x00\x00\x00\x00\x00\x00\x00'
                252     CALL                            1
                260     POP_TOP                         
                262     RERAISE                         0
                264     COPY                            3
                266     POP_EXCEPT                      
                268     RERAISE                         1
                270     PUSH_NULL                       
                272     LOAD_CONST                      17: '__pyarmor_exit_16244__'
                274     LOAD_CONST                      3: b'<COAddr>\x05\x00\x00"\xd0\x00\x00\x00\x00\x00\x00\x00\x00\x00\x00\x00\x00\x00\x00\x00'
                276     BUILD_TUPLE                     1
                278     CALL_FUNCTION_EX                0
                280     POP_TOP                         
                282     RETURN_VALUE                    
            [Exception Table]
                36 to 222 -> 242 [0] 
                242 to 264 -> 264 [1] lasti
        'tg_links'
        '__pyarmor_exit_16241__'
        None
    [Disassembly]
        0       NOP                             
        2       NOP                             
        4       PUSH_NULL                       
        6       LOAD_CONST                      1: '__pyarmor_enter_16240__'
        8       LOAD_CONST                      2: b'<COAddr>\x07\x00\x00\x1a(\x00\x00\x00\x00\x00\x00\x00\x00\x00\x00\x00\x00\x00\x00\x00'
        10      BUILD_TUPLE                     1
        12      CALL_FUNCTION_EX                0
        14      POP_TOP                         
        16      RESUME                          0
        18      NOP                             
        20      NOP                             
        22      NOP                             
        24      NOP                             
        26      PUSH_NULL                       
        28      LOAD_BUILD_CLASS                
        30      LOAD_CONST                      3: <CODE> tg_links
        32      MAKE_FUNCTION                   0
        34      LOAD_CONST                      4: 'tg_links'
        36      CALL                            2
        44      STORE_NAME                      1: tg_links
        46      LOAD_CONST                      6: None
        48      NOP                             
        50      NOP                             
        52      NOP                             
        54      JUMP_FORWARD                    19 (to 94)
        62      POP_TOP                         
        64      RETURN_CONST                    6: None
        66      PUSH_EXC_INFO                   
        68      PUSH_NULL                       
        70      LOAD_CONST                      5: '__pyarmor_exit_16241__'
        72      NOP                             
        74      LOAD_CONST                      2: b'<COAddr>\x07\x00\x00\x1a(\x00\x00\x00\x00\x00\x00\x00\x00\x00\x00\x00\x00\x00\x00\x00'
        76      CALL                            1
        84      POP_TOP                         
        86      RERAISE                         0
        88      COPY                            3
        90      POP_EXCEPT                      
        92      RERAISE                         1
        94      PUSH_NULL                       
        96      LOAD_CONST                      5: '__pyarmor_exit_16241__'
        98      LOAD_CONST                      2: b'<COAddr>\x07\x00\x00\x1a(\x00\x00\x00\x00\x00\x00\x00\x00\x00\x00\x00\x00\x00\x00\x00'
        100     BUILD_TUPLE                     1
        102     CALL_FUNCTION_EX                0
        104     POP_TOP                         
        106     RETURN_VALUE                    
    [Exception Table]
        26 to 46 -> 66 [0] 
        66 to 88 -> 88 [1] lasti
