#decoded by lolz.live/mrpenny / t.me/zeus_jackpot
# ================================
# Примечания по Pyarmor:
# - Байт-код и объекты кода Pyarmor соответствуют стандартному Python, но присутствуют специальные вызовы функций среды выполнения (runtime) Pyarmor.
# - Вызовы строк — это не ошибки, а маркеры, которые обрабатываются Pyarmor во время выполнения.
#
# Руководство по декомпиляции (без среды выполнения):
# 1. Игнорируйте зашифрованные байты после `#`; используйте только строку до `#`.
# 2. Удалите "__pyarmor_enter_xxx__"(b"<COAddr>...") и "__pyarmor_leave_xxx__"(b"<COAddr>...") (пролог/эпилог).
# 3. "__pyarmor_assert_xxx__"(A) не является настоящим оператором assert.
#    - Если A — это имя или читаемая строка: замените на A.
#    - Если A — это (X, "Y"): замените на X.Y.
#    - Если A — это (X, "Y", Z): замените на X.Y = Z.
#    - В противном случае: выберите наиболее подходящую/логичную замену.
# 4. "__pyarmor_bcc_xxx__"(...) указывает на машинный (нативный) код; тело функции недоступно. Добавьте комментарий.
# ================================

[Code]
    File Name: <frozen multithon.sessions.memory>
    Object Name: <module>
    Qualified Name: <module>
    Arg Count: 0
    Pos Only Arg Count: 0
    KW Only Arg Count: 0
    Stack Size: 5
    Flags: 0x20000000 (CO_PYARMOR_OBFUSCATED)
    [Names]
        '__assert_armored__'
        'enum'
        'Enum'
        'abstract'
        'Session'
        ''
        'utils'
        'tl'
        'TLObject'
        'tl.types'
        'PeerUser'
        'PeerChat'
        'PeerChannel'
        'InputPeerUser'
        'InputPeerChat'
        'InputPeerChannel'
        'InputPhoto'
        'InputDocument'
        '_SentFileType'
        'MemorySession'
    [Locals+Names]
    [Constants]
        '__pyarmor_assert_23520__'
        '__pyarmor_enter_23521__'
        b'<COAddr>\x07\x00\x00\x1a\x98\x00\x00\x00\x00\x00\x00\x00\x00\x00\x00\x00\x00\x00\x00\x00'
        0
        (
            'Enum'
        )
        1
        (
            'Session'
        )
        2
        (
            'utils'
        )
        (
            'TLObject'
        )
        (
            'PeerUser'
            'PeerChat'
            'PeerChannel'
            'InputPeerUser'
            'InputPeerChat'
            'InputPeerChannel'
            'InputPhoto'
            'InputDocument'
        )
        [Code]
            File Name: <frozen multithon.sessions.memory>
            Object Name: _SentFileType
            Qualified Name: _SentFileType
            Arg Count: 0
            Pos Only Arg Count: 0
            KW Only Arg Count: 0
            Stack Size: 5
            Flags: 0x20000000 (CO_PYARMOR_OBFUSCATED)
            [Names]
                '__name__'
                '__module__'
                '__qualname__'
                '__assert_armored__'
                'DOCUMENT'
                'PHOTO'
                'staticmethod'
                'from_type'
            [Locals+Names]
            [Constants]
                '_SentFileType'
                '__pyarmor_assert_23523__'
                '__pyarmor_enter_23524__'
                b'<COAddr>\x05\x00\x00".\x00\x00\x00\x00\x00\x00\x00\x00\x00\x00\x00\x00\x00\x00\x00'
                0
                1
                [Code]
                    File Name: <frozen multithon.sessions.memory>
                    Object Name: from_type
                    Qualified Name: _SentFileType.from_type
                    Arg Count: 1
                    Pos Only Arg Count: 0
                    KW Only Arg Count: 0
                    Stack Size: 5
                    Flags: 0x20000003 (CO_OPTIMIZED | CO_NEWLOCALS | CO_PYARMOR_OBFUSCATED)
                    [Names]
                        'InputDocument'
                        '_SentFileType'
                        'DOCUMENT'
                        'InputPhoto'
                        'PHOTO'
                        'ValueError'
                    [Locals+Names]
                        'cls'
                        '__assert_armored__'
                    [Constants]
                        None
                        '__pyarmor_assert_23526__'
                        '__pyarmor_enter_23527__'
                        b'<COAddr>\x07\x00\x00\x1a\xac\x00\x00\x00\x00\x00\x00\x00\x00\x00\x00\x00\x00\x00\x00\x00'
                        '__pyarmor_exit_23528__'
                        'The cls must be either InputDocument/InputPhoto'   # b'\x81\xd6\x10\x16s\xf9\xb2\xc1[\xf7\x18\xd3x\xac\xfa\x80OX\xb2\xb3\xa2\xce\\\x8c,a\xb3I\x14\x95\x11\xe6/_%\x03\x8c\x85\x9d \x08\xfc\xecm\xd5\xd7\x1bH'
                    [Disassembly]
                        0       NOP                             
                        2       NOP                             
                        4       PUSH_NULL                       
                        6       LOAD_CONST                      2: '__pyarmor_enter_23527__'
                        8       LOAD_CONST                      3: b'<COAddr>\x07\x00\x00\x1a\xac\x00\x00\x00\x00\x00\x00\x00\x00\x00\x00\x00\x00\x00\x00\x00'
                        10      BUILD_TUPLE                     1
                        12      CALL_FUNCTION_EX                0
                        14      POP_TOP                         
                        16      RESUME                          0
                        18      NOP                             
                        20      NOP                             
                        22      NOP                             
                        24      NOP                             
                        26      NOP                             
                        28      LOAD_FAST                       0: cls
                        30      LOAD_GLOBAL                     0: InputDocument
                        40      COMPARE_OP                      40 (==)
                        44      POP_JUMP_IF_FALSE               25 (to 96)
                        46      LOAD_GLOBAL                     2: _SentFileType
                        56      LOAD_ATTR                       4: DOCUMENT
                        76      NOP                             
                        78      NOP                             
                        80      NOP                             
                        82      JUMP_FORWARD                    71 (to 226)
                        84      CALL                            1
                        92      POP_TOP                         
                        94      RETURN_VALUE                    
                        96      LOAD_FAST                       0: cls
                        98      LOAD_GLOBAL                     6: InputPhoto
                        108     COMPARE_OP                      40 (==)
                        112     POP_JUMP_IF_FALSE               25 (to 164)
                        114     LOAD_GLOBAL                     2: _SentFileType
                        124     LOAD_ATTR                       8: PHOTO
                        144     NOP                             
                        146     NOP                             
                        148     NOP                             
                        150     JUMP_FORWARD                    37 (to 226)
                        152     CALL                            1
                        160     POP_TOP                         
                        162     RETURN_VALUE                    
                        164     LOAD_GLOBAL                     11: NULL + ValueError
                        174     PUSH_NULL                       
                        176     LOAD_CONST                      1: '__pyarmor_assert_23526__'
                        178     LOAD_CONST                      5: 'The cls must be either InputDocument/InputPhoto'   # b'\x81\xd6\x10\x16s\xf9\xb2\xc1[\xf7\x18\xd3x\xac\xfa\x80OX\xb2\xb3\xa2\xce\\\x8c,a\xb3I\x14\x95\x11\xe6/_%\x03\x8c\x85\x9d \x08\xfc\xecm\xd5\xd7\x1bH'
                        180     CALL                            1
                        188     CALL                            1
                        196     RAISE_VARARGS                   1
                        198     PUSH_EXC_INFO                   
                        200     PUSH_NULL                       
                        202     LOAD_CONST                      4: '__pyarmor_exit_23528__'
                        204     NOP                             
                        206     LOAD_CONST                      3: b'<COAddr>\x07\x00\x00\x1a\xac\x00\x00\x00\x00\x00\x00\x00\x00\x00\x00\x00\x00\x00\x00\x00'
                        208     CALL                            1
                        216     POP_TOP                         
                        218     RERAISE                         0
                        220     COPY                            3
                        222     POP_EXCEPT                      
                        224     RERAISE                         1
                        226     PUSH_NULL                       
                        228     LOAD_CONST                      4: '__pyarmor_exit_23528__'
                        230     LOAD_CONST                      3: b'<COAddr>\x07\x00\x00\x1a\xac\x00\x00\x00\x00\x00\x00\x00\x00\x00\x00\x00\x00\x00\x00\x00'
                        232     BUILD_TUPLE                     1
                        234     CALL_FUNCTION_EX                0
                        236     POP_TOP                         
                        238     RETURN_VALUE                    
                    [Exception Table]
                        28 to 76 -> 198 [0] 
                        96 to 144 -> 198 [0] 
                        164 to 198 -> 198 [0] 
                        198 to 220 -> 220 [1] lasti
                '__pyarmor_exit_23525__'
                None
            [Disassembly]
                0       NOP                             
                2       LOAD_NAME                       0: __name__
                4       STORE_NAME                      1: __module__
                6       LOAD_CONST                      0: '_SentFileType'
                8       STORE_NAME                      2: __qualname__
                10      NOP                             
                12      PUSH_NULL                       
                14      LOAD_CONST                      2: '__pyarmor_enter_23524__'
                16      LOAD_CONST                      3: b'<COAddr>\x05\x00\x00".\x00\x00\x00\x00\x00\x00\x00\x00\x00\x00\x00\x00\x00\x00\x00'
                18      BUILD_TUPLE                     1
                20      CALL_FUNCTION_EX                0
                22      POP_TOP                         
                24      RESUME                          0
                26      NOP                             
                28      NOP                             
                30      NOP                             
                32      NOP                             
                34      NOP                             
                36      LOAD_CONST                      4: 0
                38      STORE_NAME                      4: DOCUMENT
                40      LOAD_CONST                      5: 1
                42      STORE_NAME                      5: PHOTO
                44      LOAD_NAME                       6: staticmethod
                46      LOAD_CONST                      6: <CODE> from_type
                48      MAKE_FUNCTION                   0
                50      CALL                            0
                58      STORE_NAME                      7: from_type
                60      LOAD_CONST                      8: None
                62      NOP                             
                64      NOP                             
                66      NOP                             
                68      JUMP_FORWARD                    19 (to 108)
                76      POP_TOP                         
                78      RETURN_CONST                    8: None
                80      PUSH_EXC_INFO                   
                82      PUSH_NULL                       
                84      LOAD_CONST                      7: '__pyarmor_exit_23525__'
                86      NOP                             
                88      LOAD_CONST                      3: b'<COAddr>\x05\x00\x00".\x00\x00\x00\x00\x00\x00\x00\x00\x00\x00\x00\x00\x00\x00\x00'
                90      CALL                            1
                98      POP_TOP                         
                100     RERAISE                         0
                102     COPY                            3
                104     POP_EXCEPT                      
                106     RERAISE                         1
                108     PUSH_NULL                       
                110     LOAD_CONST                      7: '__pyarmor_exit_23525__'
                112     LOAD_CONST                      3: b'<COAddr>\x05\x00\x00".\x00\x00\x00\x00\x00\x00\x00\x00\x00\x00\x00\x00\x00\x00\x00'
                114     BUILD_TUPLE                     1
                116     CALL_FUNCTION_EX                0
                118     POP_TOP                         
                120     RETURN_VALUE                    
            [Exception Table]
                36 to 60 -> 80 [0] 
                80 to 102 -> 102 [1] lasti
        '_SentFileType'
        [Code]
            File Name: <frozen multithon.sessions.memory>
            Object Name: MemorySession
            Qualified Name: MemorySession
            Arg Count: 0
            Pos Only Arg Count: 0
            KW Only Arg Count: 0
            Stack Size: 5
            Flags: 0x20000000 (CO_PYARMOR_OBFUSCATED)
            [Names]
                '__name__'
                '__module__'
                '__qualname__'
                '__assert_armored__'
                '__init__'
                'set_dc'
                'property'
                'dc_id'
                'server_address'
                'port'
                'auth_key'
                'setter'
                'takeout_id'
                'get_update_state'
                'set_update_state'
                'get_update_states'
                'close'
                'save'
                'delete'
                'staticmethod'
                '_entity_values_to_row'
                '_entity_to_row'
                '_entities_to_rows'
                'process_entities'
                'get_entity_rows_by_phone'
                'get_entity_rows_by_username'
                'get_entity_rows_by_name'
                'get_entity_rows_by_id'
                'get_input_entity'
                'cache_file'
                'get_file'
                '__classcell__'
            [Locals+Names]
                '__class__'
            [Constants]
                'MemorySession'
                '__pyarmor_assert_23529__'
                '__pyarmor_enter_23530__'
                b'<COAddr>\x05\x00\x00$6\x01\x00\x00\x00\x00\x00\x00\x00\x00\x00\x00\x00\x00\x00\x00'
                [Code]
                    File Name: <frozen multithon.sessions.memory>
                    Object Name: __init__
                    Qualified Name: MemorySession.__init__
                    Arg Count: 1
                    Pos Only Arg Count: 0
                    KW Only Arg Count: 0
                    Stack Size: 5
                    Flags: 0x20000003 (CO_OPTIMIZED | CO_NEWLOCALS | CO_PYARMOR_OBFUSCATED)
                    [Names]
                        'super'
                        '__init__'
                        '_dc_id'
                        '_server_address'
                        '_port'
                        '_auth_key'
                        '_takeout_id'
                        '_files'
                        'set'
                        '_entities'
                        '_update_states'
                    [Locals+Names]
                        'self'
                        '__assert_armored__'
                        '__class__'
                    [Constants]
                        None
                        '__pyarmor_assert_23532__'
                        '__pyarmor_enter_23533__'
                        b'<COAddr>\x05\x00\x00\x1c\xb2\x00\x00\x00\x00\x00\x00\x00\x00\x00\x00\x00\x00\x00\x00\x00'
                        0
                        '__pyarmor_exit_23534__'
                    [Disassembly]
                        0       COPY_FREE_VARS                  1
                        2       NOP                             
                        4       NOP                             
                        6       PUSH_NULL                       
                        8       LOAD_CONST                      2: '__pyarmor_enter_23533__'
                        10      LOAD_CONST                      3: b'<COAddr>\x05\x00\x00\x1c\xb2\x00\x00\x00\x00\x00\x00\x00\x00\x00\x00\x00\x00\x00\x00\x00'
                        12      BUILD_TUPLE                     1
                        14      CALL_FUNCTION_EX                0
                        16      POP_TOP                         
                        18      RESUME                          0
                        20      NOP                             
                        22      NOP                             
                        24      NOP                             
                        26      NOP                             
                        28      NOP                             
                        30      LOAD_GLOBAL                     0: super
                        40      LOAD_DEREF                      2: __class__
                        42      LOAD_FAST                       0: self
                        44      LOAD_SUPER_ATTR                 5: __init__
                        48      CALL                            0
                        56      POP_TOP                         
                        58      LOAD_CONST                      4: 0
                        60      LOAD_FAST                       0: self
                        62      STORE_ATTR                      2: _dc_id
                        72      LOAD_CONST                      0: None
                        74      LOAD_FAST                       0: self
                        76      STORE_ATTR                      3: _server_address
                        86      LOAD_CONST                      0: None
                        88      LOAD_FAST                       0: self
                        90      STORE_ATTR                      4: _port
                        100     LOAD_CONST                      0: None
                        102     LOAD_FAST                       0: self
                        104     STORE_ATTR                      5: _auth_key
                        114     LOAD_CONST                      0: None
                        116     LOAD_FAST                       0: self
                        118     STORE_ATTR                      6: _takeout_id
                        128     BUILD_MAP                       0
                        130     LOAD_FAST                       0: self
                        132     STORE_ATTR                      7: _files
                        142     LOAD_GLOBAL                     17: NULL + set
                        152     CALL                            0
                        160     LOAD_FAST                       0: self
                        162     STORE_ATTR                      9: _entities
                        172     BUILD_MAP                       0
                        174     LOAD_FAST                       0: self
                        176     STORE_ATTR                      10: _update_states
                        186     LOAD_CONST                      0: None
                        188     NOP                             
                        190     NOP                             
                        192     NOP                             
                        194     JUMP_FORWARD                    19 (to 234)
                        202     POP_TOP                         
                        204     RETURN_CONST                    0: None
                        206     PUSH_EXC_INFO                   
                        208     PUSH_NULL                       
                        210     LOAD_CONST                      5: '__pyarmor_exit_23534__'
                        212     NOP                             
                        214     LOAD_CONST                      3: b'<COAddr>\x05\x00\x00\x1c\xb2\x00\x00\x00\x00\x00\x00\x00\x00\x00\x00\x00\x00\x00\x00\x00'
                        216     CALL                            1
                        224     POP_TOP                         
                        226     RERAISE                         0
                        228     COPY                            3
                        230     POP_EXCEPT                      
                        232     RERAISE                         1
                        234     PUSH_NULL                       
                        236     LOAD_CONST                      5: '__pyarmor_exit_23534__'
                        238     LOAD_CONST                      3: b'<COAddr>\x05\x00\x00\x1c\xb2\x00\x00\x00\x00\x00\x00\x00\x00\x00\x00\x00\x00\x00\x00\x00'
                        240     BUILD_TUPLE                     1
                        242     CALL_FUNCTION_EX                0
                        244     POP_TOP                         
                        246     RETURN_VALUE                    
                    [Exception Table]
                        30 to 186 -> 206 [0] 
                        206 to 228 -> 228 [1] lasti
                [Code]
                    File Name: <frozen multithon.sessions.memory>
                    Object Name: set_dc
                    Qualified Name: MemorySession.set_dc
                    Arg Count: 4
                    Pos Only Arg Count: 0
                    KW Only Arg Count: 0
                    Stack Size: 5
                    Flags: 0x20000003 (CO_OPTIMIZED | CO_NEWLOCALS | CO_PYARMOR_OBFUSCATED)
                    [Names]
                        '_dc_id'
                        '_server_address'
                        '_port'
                    [Locals+Names]
                        'self'
                        'dc_id'
                        'server_address'
                        'port'
                        '__assert_armored__'
                    [Constants]
                        None
                        '__pyarmor_assert_23535__'
                        '__pyarmor_enter_23536__'
                        b'<COAddr>\x05\x00\x00\x1aH\x00\x00\x00\x00\x00\x00\x00\x00\x00\x00\x00\x00\x00\x00\x00'
                        0
                        '__pyarmor_exit_23537__'
                    [Disassembly]
                        0       NOP                             
                        2       NOP                             
                        4       PUSH_NULL                       
                        6       LOAD_CONST                      2: '__pyarmor_enter_23536__'
                        8       LOAD_CONST                      3: b'<COAddr>\x05\x00\x00\x1aH\x00\x00\x00\x00\x00\x00\x00\x00\x00\x00\x00\x00\x00\x00\x00'
                        10      BUILD_TUPLE                     1
                        12      CALL_FUNCTION_EX                0
                        14      POP_TOP                         
                        16      RESUME                          0
                        18      NOP                             
                        20      NOP                             
                        22      NOP                             
                        24      NOP                             
                        26      NOP                             
                        28      LOAD_FAST                       1: dc_id
                        30      COPY                            1
                        32      POP_JUMP_IF_TRUE                2 (to 38)
                        34      POP_TOP                         
                        36      LOAD_CONST                      4: 0
                        38      LOAD_FAST                       0: self
                        40      STORE_ATTR                      0: _dc_id
                        50      LOAD_FAST                       2: server_address
                        52      LOAD_FAST                       0: self
                        54      STORE_ATTR                      1: _server_address
                        64      LOAD_FAST                       3: port
                        66      LOAD_FAST                       0: self
                        68      STORE_ATTR                      2: _port
                        78      LOAD_CONST                      0: None
                        80      NOP                             
                        82      NOP                             
                        84      NOP                             
                        86      JUMP_FORWARD                    19 (to 126)
                        94      POP_TOP                         
                        96      RETURN_CONST                    0: None
                        98      PUSH_EXC_INFO                   
                        100     PUSH_NULL                       
                        102     LOAD_CONST                      5: '__pyarmor_exit_23537__'
                        104     NOP                             
                        106     LOAD_CONST                      3: b'<COAddr>\x05\x00\x00\x1aH\x00\x00\x00\x00\x00\x00\x00\x00\x00\x00\x00\x00\x00\x00\x00'
                        108     CALL                            1
                        116     POP_TOP                         
                        118     RERAISE                         0
                        120     COPY                            3
                        122     POP_EXCEPT                      
                        124     RERAISE                         1
                        126     PUSH_NULL                       
                        128     LOAD_CONST                      5: '__pyarmor_exit_23537__'
                        130     LOAD_CONST                      3: b'<COAddr>\x05\x00\x00\x1aH\x00\x00\x00\x00\x00\x00\x00\x00\x00\x00\x00\x00\x00\x00\x00'
                        132     BUILD_TUPLE                     1
                        134     CALL_FUNCTION_EX                0
                        136     POP_TOP                         
                        138     RETURN_VALUE                    
                    [Exception Table]
                        28 to 78 -> 98 [0] 
                        98 to 120 -> 120 [1] lasti
                [Code]
                    File Name: <frozen multithon.sessions.memory>
                    Object Name: dc_id
                    Qualified Name: MemorySession.dc_id
                    Arg Count: 1
                    Pos Only Arg Count: 0
                    KW Only Arg Count: 0
                    Stack Size: 5
                    Flags: 0x20000003 (CO_OPTIMIZED | CO_NEWLOCALS | CO_PYARMOR_OBFUSCATED)
                    [Names]
                        '_dc_id'
                    [Locals+Names]
                        'self'
                        '__assert_armored__'
                    [Constants]
                        None
                        '__pyarmor_assert_23538__'
                        '__pyarmor_enter_23539__'
                        b'<COAddr>\x05\x00\x00\x1a,\x00\x00\x00\x00\x00\x00\x00\x00\x00\x00\x00\x00\x00\x00\x00'
                        '__pyarmor_exit_23540__'
                    [Disassembly]
                        0       NOP                             
                        2       NOP                             
                        4       PUSH_NULL                       
                        6       LOAD_CONST                      2: '__pyarmor_enter_23539__'
                        8       LOAD_CONST                      3: b'<COAddr>\x05\x00\x00\x1a,\x00\x00\x00\x00\x00\x00\x00\x00\x00\x00\x00\x00\x00\x00\x00'
                        10      BUILD_TUPLE                     1
                        12      CALL_FUNCTION_EX                0
                        14      POP_TOP                         
                        16      RESUME                          0
                        18      NOP                             
                        20      NOP                             
                        22      NOP                             
                        24      NOP                             
                        26      NOP                             
                        28      LOAD_FAST                       0: self
                        30      LOAD_ATTR                       0: _dc_id
                        50      NOP                             
                        52      NOP                             
                        54      NOP                             
                        56      JUMP_FORWARD                    20 (to 98)
                        58      CALL                            1
                        66      POP_TOP                         
                        68      RETURN_VALUE                    
                        70      PUSH_EXC_INFO                   
                        72      PUSH_NULL                       
                        74      LOAD_CONST                      4: '__pyarmor_exit_23540__'
                        76      NOP                             
                        78      LOAD_CONST                      3: b'<COAddr>\x05\x00\x00\x1a,\x00\x00\x00\x00\x00\x00\x00\x00\x00\x00\x00\x00\x00\x00\x00'
                        80      CALL                            1
                        88      POP_TOP                         
                        90      RERAISE                         0
                        92      COPY                            3
                        94      POP_EXCEPT                      
                        96      RERAISE                         1
                        98      PUSH_NULL                       
                        100     LOAD_CONST                      4: '__pyarmor_exit_23540__'
                        102     LOAD_CONST                      3: b'<COAddr>\x05\x00\x00\x1a,\x00\x00\x00\x00\x00\x00\x00\x00\x00\x00\x00\x00\x00\x00\x00'
                        104     BUILD_TUPLE                     1
                        106     CALL_FUNCTION_EX                0
                        108     POP_TOP                         
                        110     RETURN_VALUE                    
                    [Exception Table]
                        28 to 50 -> 70 [0] 
                        70 to 92 -> 92 [1] lasti
                [Code]
                    File Name: <frozen multithon.sessions.memory>
                    Object Name: server_address
                    Qualified Name: MemorySession.server_address
                    Arg Count: 1
                    Pos Only Arg Count: 0
                    KW Only Arg Count: 0
                    Stack Size: 5
                    Flags: 0x20000003 (CO_OPTIMIZED | CO_NEWLOCALS | CO_PYARMOR_OBFUSCATED)
                    [Names]
                        '_server_address'
                    [Locals+Names]
                        'self'
                        '__assert_armored__'
                    [Constants]
                        None
                        '__pyarmor_assert_23541__'
                        '__pyarmor_enter_23542__'
                        b'<COAddr>\x07\x00\x00\x1a,\x00\x00\x00\x00\x00\x00\x00\x00\x00\x00\x00\x00\x00\x00\x00'
                        '__pyarmor_exit_23543__'
                    [Disassembly]
                        0       NOP                             
                        2       NOP                             
                        4       PUSH_NULL                       
                        6       LOAD_CONST                      2: '__pyarmor_enter_23542__'
                        8       LOAD_CONST                      3: b'<COAddr>\x07\x00\x00\x1a,\x00\x00\x00\x00\x00\x00\x00\x00\x00\x00\x00\x00\x00\x00\x00'
                        10      BUILD_TUPLE                     1
                        12      CALL_FUNCTION_EX                0
                        14      POP_TOP                         
                        16      RESUME                          0
                        18      NOP                             
                        20      NOP                             
                        22      NOP                             
                        24      NOP                             
                        26      NOP                             
                        28      LOAD_FAST                       0: self
                        30      LOAD_ATTR                       0: _server_address
                        50      NOP                             
                        52      NOP                             
                        54      NOP                             
                        56      JUMP_FORWARD                    20 (to 98)
                        58      CALL                            1
                        66      POP_TOP                         
                        68      RETURN_VALUE                    
                        70      PUSH_EXC_INFO                   
                        72      PUSH_NULL                       
                        74      LOAD_CONST                      4: '__pyarmor_exit_23543__'
                        76      NOP                             
                        78      LOAD_CONST                      3: b'<COAddr>\x07\x00\x00\x1a,\x00\x00\x00\x00\x00\x00\x00\x00\x00\x00\x00\x00\x00\x00\x00'
                        80      CALL                            1
                        88      POP_TOP                         
                        90      RERAISE                         0
                        92      COPY                            3
                        94      POP_EXCEPT                      
                        96      RERAISE                         1
                        98      PUSH_NULL                       
                        100     LOAD_CONST                      4: '__pyarmor_exit_23543__'
                        102     LOAD_CONST                      3: b'<COAddr>\x07\x00\x00\x1a,\x00\x00\x00\x00\x00\x00\x00\x00\x00\x00\x00\x00\x00\x00\x00'
                        104     BUILD_TUPLE                     1
                        106     CALL_FUNCTION_EX                0
                        108     POP_TOP                         
                        110     RETURN_VALUE                    
                    [Exception Table]
                        28 to 50 -> 70 [0] 
                        70 to 92 -> 92 [1] lasti
                [Code]
                    File Name: <frozen multithon.sessions.memory>
                    Object Name: port
                    Qualified Name: MemorySession.port
                    Arg Count: 1
                    Pos Only Arg Count: 0
                    KW Only Arg Count: 0
                    Stack Size: 5
                    Flags: 0x20000003 (CO_OPTIMIZED | CO_NEWLOCALS | CO_PYARMOR_OBFUSCATED)
                    [Names]
                        '_port'
                    [Locals+Names]
                        'self'
                        '__assert_armored__'
                    [Constants]
                        None
                        '__pyarmor_assert_23544__'
                        '__pyarmor_enter_23545__'
                        b'<COAddr>\x05\x00\x00\x1a,\x00\x00\x00\x00\x00\x00\x00\x00\x00\x00\x00\x00\x00\x00\x00'
                        '__pyarmor_exit_23546__'
                    [Disassembly]
                        0       NOP                             
                        2       NOP                             
                        4       PUSH_NULL                       
                        6       LOAD_CONST                      2: '__pyarmor_enter_23545__'
                        8       LOAD_CONST                      3: b'<COAddr>\x05\x00\x00\x1a,\x00\x00\x00\x00\x00\x00\x00\x00\x00\x00\x00\x00\x00\x00\x00'
                        10      BUILD_TUPLE                     1
                        12      CALL_FUNCTION_EX                0
                        14      POP_TOP                         
                        16      RESUME                          0
                        18      NOP                             
                        20      NOP                             
                        22      NOP                             
                        24      NOP                             
                        26      NOP                             
                        28      LOAD_FAST                       0: self
                        30      LOAD_ATTR                       0: _port
                        50      NOP                             
                        52      NOP                             
                        54      NOP                             
                        56      JUMP_FORWARD                    20 (to 98)
                        58      CALL                            1
                        66      POP_TOP                         
                        68      RETURN_VALUE                    
                        70      PUSH_EXC_INFO                   
                        72      PUSH_NULL                       
                        74      LOAD_CONST                      4: '__pyarmor_exit_23546__'
                        76      NOP                             
                        78      LOAD_CONST                      3: b'<COAddr>\x05\x00\x00\x1a,\x00\x00\x00\x00\x00\x00\x00\x00\x00\x00\x00\x00\x00\x00\x00'
                        80      CALL                            1
                        88      POP_TOP                         
                        90      RERAISE                         0
                        92      COPY                            3
                        94      POP_EXCEPT                      
                        96      RERAISE                         1
                        98      PUSH_NULL                       
                        100     LOAD_CONST                      4: '__pyarmor_exit_23546__'
                        102     LOAD_CONST                      3: b'<COAddr>\x05\x00\x00\x1a,\x00\x00\x00\x00\x00\x00\x00\x00\x00\x00\x00\x00\x00\x00\x00'
                        104     BUILD_TUPLE                     1
                        106     CALL_FUNCTION_EX                0
                        108     POP_TOP                         
                        110     RETURN_VALUE                    
                    [Exception Table]
                        28 to 50 -> 70 [0] 
                        70 to 92 -> 92 [1] lasti
                [Code]
                    File Name: <frozen multithon.sessions.memory>
                    Object Name: auth_key
                    Qualified Name: MemorySession.auth_key
                    Arg Count: 1
                    Pos Only Arg Count: 0
                    KW Only Arg Count: 0
                    Stack Size: 5
                    Flags: 0x20000003 (CO_OPTIMIZED | CO_NEWLOCALS | CO_PYARMOR_OBFUSCATED)
                    [Names]
                        '_auth_key'
                    [Locals+Names]
                        'self'
                        '__assert_armored__'
                    [Constants]
                        None
                        '__pyarmor_assert_23547__'
                        '__pyarmor_enter_23548__'
                        b'<COAddr>\x05\x00\x00\x1a,\x00\x00\x00\x00\x00\x00\x00\x00\x00\x00\x00\x00\x00\x00\x00'
                        '__pyarmor_exit_23549__'
                    [Disassembly]
                        0       NOP                             
                        2       NOP                             
                        4       PUSH_NULL                       
                        6       LOAD_CONST                      2: '__pyarmor_enter_23548__'
                        8       LOAD_CONST                      3: b'<COAddr>\x05\x00\x00\x1a,\x00\x00\x00\x00\x00\x00\x00\x00\x00\x00\x00\x00\x00\x00\x00'
                        10      BUILD_TUPLE                     1
                        12      CALL_FUNCTION_EX                0
                        14      POP_TOP                         
                        16      RESUME                          0
                        18      NOP                             
                        20      NOP                             
                        22      NOP                             
                        24      NOP                             
                        26      NOP                             
                        28      LOAD_FAST                       0: self
                        30      LOAD_ATTR                       0: _auth_key
                        50      NOP                             
                        52      NOP                             
                        54      NOP                             
                        56      JUMP_FORWARD                    20 (to 98)
                        58      CALL                            1
                        66      POP_TOP                         
                        68      RETURN_VALUE                    
                        70      PUSH_EXC_INFO                   
                        72      PUSH_NULL                       
                        74      LOAD_CONST                      4: '__pyarmor_exit_23549__'
                        76      NOP                             
                        78      LOAD_CONST                      3: b'<COAddr>\x05\x00\x00\x1a,\x00\x00\x00\x00\x00\x00\x00\x00\x00\x00\x00\x00\x00\x00\x00'
                        80      CALL                            1
                        88      POP_TOP                         
                        90      RERAISE                         0
                        92      COPY                            3
                        94      POP_EXCEPT                      
                        96      RERAISE                         1
                        98      PUSH_NULL                       
                        100     LOAD_CONST                      4: '__pyarmor_exit_23549__'
                        102     LOAD_CONST                      3: b'<COAddr>\x05\x00\x00\x1a,\x00\x00\x00\x00\x00\x00\x00\x00\x00\x00\x00\x00\x00\x00\x00'
                        104     BUILD_TUPLE                     1
                        106     CALL_FUNCTION_EX                0
                        108     POP_TOP                         
                        110     RETURN_VALUE                    
                    [Exception Table]
                        28 to 50 -> 70 [0] 
                        70 to 92 -> 92 [1] lasti
                [Code]
                    File Name: <frozen multithon.sessions.memory>
                    Object Name: auth_key
                    Qualified Name: MemorySession.auth_key
                    Arg Count: 2
                    Pos Only Arg Count: 0
                    KW Only Arg Count: 0
                    Stack Size: 5
                    Flags: 0x20000003 (CO_OPTIMIZED | CO_NEWLOCALS | CO_PYARMOR_OBFUSCATED)
                    [Names]
                        '_auth_key'
                    [Locals+Names]
                        'self'
                        'value'
                        '__assert_armored__'
                    [Constants]
                        None
                        '__pyarmor_assert_23550__'
                        '__pyarmor_enter_23551__'
                        b'<COAddr>\x07\x00\x00\x1a$\x00\x00\x00\x00\x00\x00\x00\x00\x00\x00\x00\x00\x00\x00\x00'
                        '__pyarmor_exit_23552__'
                    [Disassembly]
                        0       NOP                             
                        2       NOP                             
                        4       PUSH_NULL                       
                        6       LOAD_CONST                      2: '__pyarmor_enter_23551__'
                        8       LOAD_CONST                      3: b'<COAddr>\x07\x00\x00\x1a$\x00\x00\x00\x00\x00\x00\x00\x00\x00\x00\x00\x00\x00\x00\x00'
                        10      BUILD_TUPLE                     1
                        12      CALL_FUNCTION_EX                0
                        14      POP_TOP                         
                        16      RESUME                          0
                        18      NOP                             
                        20      NOP                             
                        22      NOP                             
                        24      NOP                             
                        26      NOP                             
                        28      LOAD_FAST                       1: value
                        30      LOAD_FAST                       0: self
                        32      STORE_ATTR                      0: _auth_key
                        42      LOAD_CONST                      0: None
                        44      NOP                             
                        46      NOP                             
                        48      NOP                             
                        50      JUMP_FORWARD                    19 (to 90)
                        58      POP_TOP                         
                        60      RETURN_CONST                    0: None
                        62      PUSH_EXC_INFO                   
                        64      PUSH_NULL                       
                        66      LOAD_CONST                      4: '__pyarmor_exit_23552__'
                        68      NOP                             
                        70      LOAD_CONST                      3: b'<COAddr>\x07\x00\x00\x1a$\x00\x00\x00\x00\x00\x00\x00\x00\x00\x00\x00\x00\x00\x00\x00'
                        72      CALL                            1
                        80      POP_TOP                         
                        82      RERAISE                         0
                        84      COPY                            3
                        86      POP_EXCEPT                      
                        88      RERAISE                         1
                        90      PUSH_NULL                       
                        92      LOAD_CONST                      4: '__pyarmor_exit_23552__'
                        94      LOAD_CONST                      3: b'<COAddr>\x07\x00\x00\x1a$\x00\x00\x00\x00\x00\x00\x00\x00\x00\x00\x00\x00\x00\x00\x00'
                        96      BUILD_TUPLE                     1
                        98      CALL_FUNCTION_EX                0
                        100     POP_TOP                         
                        102     RETURN_VALUE                    
                    [Exception Table]
                        28 to 42 -> 62 [0] 
                        62 to 84 -> 84 [1] lasti
                [Code]
                    File Name: <frozen multithon.sessions.memory>
                    Object Name: takeout_id
                    Qualified Name: MemorySession.takeout_id
                    Arg Count: 1
                    Pos Only Arg Count: 0
                    KW Only Arg Count: 0
                    Stack Size: 5
                    Flags: 0x20000003 (CO_OPTIMIZED | CO_NEWLOCALS | CO_PYARMOR_OBFUSCATED)
                    [Names]
                        '_takeout_id'
                    [Locals+Names]
                        'self'
                        '__assert_armored__'
                    [Constants]
                        None
                        '__pyarmor_assert_23553__'
                        '__pyarmor_enter_23554__'
                        b'<COAddr>\x07\x00\x00\x1a,\x00\x00\x00\x00\x00\x00\x00\x00\x00\x00\x00\x00\x00\x00\x00'
                        '__pyarmor_exit_23555__'
                    [Disassembly]
                        0       NOP                             
                        2       NOP                             
                        4       PUSH_NULL                       
                        6       LOAD_CONST                      2: '__pyarmor_enter_23554__'
                        8       LOAD_CONST                      3: b'<COAddr>\x07\x00\x00\x1a,\x00\x00\x00\x00\x00\x00\x00\x00\x00\x00\x00\x00\x00\x00\x00'
                        10      BUILD_TUPLE                     1
                        12      CALL_FUNCTION_EX                0
                        14      POP_TOP                         
                        16      RESUME                          0
                        18      NOP                             
                        20      NOP                             
                        22      NOP                             
                        24      NOP                             
                        26      NOP                             
                        28      LOAD_FAST                       0: self
                        30      LOAD_ATTR                       0: _takeout_id
                        50      NOP                             
                        52      NOP                             
                        54      NOP                             
                        56      JUMP_FORWARD                    20 (to 98)
                        58      CALL                            1
                        66      POP_TOP                         
                        68      RETURN_VALUE                    
                        70      PUSH_EXC_INFO                   
                        72      PUSH_NULL                       
                        74      LOAD_CONST                      4: '__pyarmor_exit_23555__'
                        76      NOP                             
                        78      LOAD_CONST                      3: b'<COAddr>\x07\x00\x00\x1a,\x00\x00\x00\x00\x00\x00\x00\x00\x00\x00\x00\x00\x00\x00\x00'
                        80      CALL                            1
                        88      POP_TOP                         
                        90      RERAISE                         0
                        92      COPY                            3
                        94      POP_EXCEPT                      
                        96      RERAISE                         1
                        98      PUSH_NULL                       
                        100     LOAD_CONST                      4: '__pyarmor_exit_23555__'
                        102     LOAD_CONST                      3: b'<COAddr>\x07\x00\x00\x1a,\x00\x00\x00\x00\x00\x00\x00\x00\x00\x00\x00\x00\x00\x00\x00'
                        104     BUILD_TUPLE                     1
                        106     CALL_FUNCTION_EX                0
                        108     POP_TOP                         
                        110     RETURN_VALUE                    
                    [Exception Table]
                        28 to 50 -> 70 [0] 
                        70 to 92 -> 92 [1] lasti
                [Code]
                    File Name: <frozen multithon.sessions.memory>
                    Object Name: takeout_id
                    Qualified Name: MemorySession.takeout_id
                    Arg Count: 2
                    Pos Only Arg Count: 0
                    KW Only Arg Count: 0
                    Stack Size: 5
                    Flags: 0x20000003 (CO_OPTIMIZED | CO_NEWLOCALS | CO_PYARMOR_OBFUSCATED)
                    [Names]
                        '_takeout_id'
                    [Locals+Names]
                        'self'
                        'value'
                        '__assert_armored__'
                    [Constants]
                        None
                        '__pyarmor_assert_23556__'
                        '__pyarmor_enter_23557__'
                        b'<COAddr>\x05\x00\x00\x1a$\x00\x00\x00\x00\x00\x00\x00\x00\x00\x00\x00\x00\x00\x00\x00'
                        '__pyarmor_exit_23558__'
                    [Disassembly]
                        0       NOP                             
                        2       NOP                             
                        4       PUSH_NULL                       
                        6       LOAD_CONST                      2: '__pyarmor_enter_23557__'
                        8       LOAD_CONST                      3: b'<COAddr>\x05\x00\x00\x1a$\x00\x00\x00\x00\x00\x00\x00\x00\x00\x00\x00\x00\x00\x00\x00'
                        10      BUILD_TUPLE                     1
                        12      CALL_FUNCTION_EX                0
                        14      POP_TOP                         
                        16      RESUME                          0
                        18      NOP                             
                        20      NOP                             
                        22      NOP                             
                        24      NOP                             
                        26      NOP                             
                        28      LOAD_FAST                       1: value
                        30      LOAD_FAST                       0: self
                        32      STORE_ATTR                      0: _takeout_id
                        42      LOAD_CONST                      0: None
                        44      NOP                             
                        46      NOP                             
                        48      NOP                             
                        50      JUMP_FORWARD                    19 (to 90)
                        58      POP_TOP                         
                        60      RETURN_CONST                    0: None
                        62      PUSH_EXC_INFO                   
                        64      PUSH_NULL                       
                        66      LOAD_CONST                      4: '__pyarmor_exit_23558__'
                        68      NOP                             
                        70      LOAD_CONST                      3: b'<COAddr>\x05\x00\x00\x1a$\x00\x00\x00\x00\x00\x00\x00\x00\x00\x00\x00\x00\x00\x00\x00'
                        72      CALL                            1
                        80      POP_TOP                         
                        82      RERAISE                         0
                        84      COPY                            3
                        86      POP_EXCEPT                      
                        88      RERAISE                         1
                        90      PUSH_NULL                       
                        92      LOAD_CONST                      4: '__pyarmor_exit_23558__'
                        94      LOAD_CONST                      3: b'<COAddr>\x05\x00\x00\x1a$\x00\x00\x00\x00\x00\x00\x00\x00\x00\x00\x00\x00\x00\x00\x00'
                        96      BUILD_TUPLE                     1
                        98      CALL_FUNCTION_EX                0
                        100     POP_TOP                         
                        102     RETURN_VALUE                    
                    [Exception Table]
                        28 to 42 -> 62 [0] 
                        62 to 84 -> 84 [1] lasti
                [Code]
                    File Name: <frozen multithon.sessions.memory>
                    Object Name: get_update_state
                    Qualified Name: MemorySession.get_update_state
                    Arg Count: 2
                    Pos Only Arg Count: 0
                    KW Only Arg Count: 0
                    Stack Size: 5
                    Flags: 0x20000003 (CO_OPTIMIZED | CO_NEWLOCALS | CO_PYARMOR_OBFUSCATED)
                    [Names]
                        '_update_states'
                        'get'
                    [Locals+Names]
                        'self'
                        'entity_id'
                        '__assert_armored__'
                    [Constants]
                        None
                        '__pyarmor_assert_23559__'
                        '__pyarmor_enter_23560__'
                        b'<COAddr>\x07\x00\x00\x1aL\x00\x00\x00\x00\x00\x00\x00\x00\x00\x00\x00\x00\x00\x00\x00'
                        '__pyarmor_exit_23561__'
                    [Disassembly]
                        0       NOP                             
                        2       NOP                             
                        4       PUSH_NULL                       
                        6       LOAD_CONST                      2: '__pyarmor_enter_23560__'
                        8       LOAD_CONST                      3: b'<COAddr>\x07\x00\x00\x1aL\x00\x00\x00\x00\x00\x00\x00\x00\x00\x00\x00\x00\x00\x00\x00'
                        10      BUILD_TUPLE                     1
                        12      CALL_FUNCTION_EX                0
                        14      POP_TOP                         
                        16      RESUME                          0
                        18      NOP                             
                        20      NOP                             
                        22      NOP                             
                        24      NOP                             
                        26      NOP                             
                        28      LOAD_FAST                       0: self
                        30      LOAD_ATTR                       0: _update_states
                        50      LOAD_ATTR                       3: get
                        70      LOAD_FAST                       1: entity_id
                        72      LOAD_CONST                      0: None
                        74      CALL                            2
                        82      NOP                             
                        84      NOP                             
                        86      NOP                             
                        88      JUMP_FORWARD                    20 (to 130)
                        90      CALL                            1
                        98      POP_TOP                         
                        100     RETURN_VALUE                    
                        102     PUSH_EXC_INFO                   
                        104     PUSH_NULL                       
                        106     LOAD_CONST                      4: '__pyarmor_exit_23561__'
                        108     NOP                             
                        110     LOAD_CONST                      3: b'<COAddr>\x07\x00\x00\x1aL\x00\x00\x00\x00\x00\x00\x00\x00\x00\x00\x00\x00\x00\x00\x00'
                        112     CALL                            1
                        120     POP_TOP                         
                        122     RERAISE                         0
                        124     COPY                            3
                        126     POP_EXCEPT                      
                        128     RERAISE                         1
                        130     PUSH_NULL                       
                        132     LOAD_CONST                      4: '__pyarmor_exit_23561__'
                        134     LOAD_CONST                      3: b'<COAddr>\x07\x00\x00\x1aL\x00\x00\x00\x00\x00\x00\x00\x00\x00\x00\x00\x00\x00\x00\x00'
                        136     BUILD_TUPLE                     1
                        138     CALL_FUNCTION_EX                0
                        140     POP_TOP                         
                        142     RETURN_VALUE                    
                    [Exception Table]
                        28 to 82 -> 102 [0] 
                        102 to 124 -> 124 [1] lasti
                [Code]
                    File Name: <frozen multithon.sessions.memory>
                    Object Name: set_update_state
                    Qualified Name: MemorySession.set_update_state
                    Arg Count: 3
                    Pos Only Arg Count: 0
                    KW Only Arg Count: 0
                    Stack Size: 5
                    Flags: 0x20000003 (CO_OPTIMIZED | CO_NEWLOCALS | CO_PYARMOR_OBFUSCATED)
                    [Names]
                        '_update_states'
                    [Locals+Names]
                        'self'
                        'entity_id'
                        'state'
                        '__assert_armored__'
                    [Constants]
                        None
                        '__pyarmor_assert_23562__'
                        '__pyarmor_enter_23563__'
                        b'<COAddr>\x05\x00\x00\x1a4\x00\x00\x00\x00\x00\x00\x00\x00\x00\x00\x00\x00\x00\x00\x00'
                        '__pyarmor_exit_23564__'
                    [Disassembly]
                        0       NOP                             
                        2       NOP                             
                        4       PUSH_NULL                       
                        6       LOAD_CONST                      2: '__pyarmor_enter_23563__'
                        8       LOAD_CONST                      3: b'<COAddr>\x05\x00\x00\x1a4\x00\x00\x00\x00\x00\x00\x00\x00\x00\x00\x00\x00\x00\x00\x00'
                        10      BUILD_TUPLE                     1
                        12      CALL_FUNCTION_EX                0
                        14      POP_TOP                         
                        16      RESUME                          0
                        18      NOP                             
                        20      NOP                             
                        22      NOP                             
                        24      NOP                             
                        26      NOP                             
                        28      LOAD_FAST                       2: state
                        30      LOAD_FAST                       0: self
                        32      LOAD_ATTR                       0: _update_states
                        52      LOAD_FAST                       1: entity_id
                        54      STORE_SUBSCR                    
                        58      LOAD_CONST                      0: None
                        60      NOP                             
                        62      NOP                             
                        64      NOP                             
                        66      JUMP_FORWARD                    19 (to 106)
                        74      POP_TOP                         
                        76      RETURN_CONST                    0: None
                        78      PUSH_EXC_INFO                   
                        80      PUSH_NULL                       
                        82      LOAD_CONST                      4: '__pyarmor_exit_23564__'
                        84      NOP                             
                        86      LOAD_CONST                      3: b'<COAddr>\x05\x00\x00\x1a4\x00\x00\x00\x00\x00\x00\x00\x00\x00\x00\x00\x00\x00\x00\x00'
                        88      CALL                            1
                        96      POP_TOP                         
                        98      RERAISE                         0
                        100     COPY                            3
                        102     POP_EXCEPT                      
                        104     RERAISE                         1
                        106     PUSH_NULL                       
                        108     LOAD_CONST                      4: '__pyarmor_exit_23564__'
                        110     LOAD_CONST                      3: b'<COAddr>\x05\x00\x00\x1a4\x00\x00\x00\x00\x00\x00\x00\x00\x00\x00\x00\x00\x00\x00\x00'
                        112     BUILD_TUPLE                     1
                        114     CALL_FUNCTION_EX                0
                        116     POP_TOP                         
                        118     RETURN_VALUE                    
                    [Exception Table]
                        28 to 58 -> 78 [0] 
                        78 to 100 -> 100 [1] lasti
                [Code]
                    File Name: <frozen multithon.sessions.memory>
                    Object Name: get_update_states
                    Qualified Name: MemorySession.get_update_states
                    Arg Count: 1
                    Pos Only Arg Count: 0
                    KW Only Arg Count: 0
                    Stack Size: 5
                    Flags: 0x20000003 (CO_OPTIMIZED | CO_NEWLOCALS | CO_PYARMOR_OBFUSCATED)
                    [Names]
                        '_update_states'
                        'items'
                    [Locals+Names]
                        'self'
                        '__assert_armored__'
                    [Constants]
                        None
                        '__pyarmor_assert_23565__'
                        '__pyarmor_enter_23566__'
                        b'<COAddr>\x07\x00\x00\x1aH\x00\x00\x00\x00\x00\x00\x00\x00\x00\x00\x00\x00\x00\x00\x00'
                        '__pyarmor_exit_23567__'
                    [Disassembly]
                        0       NOP                             
                        2       NOP                             
                        4       PUSH_NULL                       
                        6       LOAD_CONST                      2: '__pyarmor_enter_23566__'
                        8       LOAD_CONST                      3: b'<COAddr>\x07\x00\x00\x1aH\x00\x00\x00\x00\x00\x00\x00\x00\x00\x00\x00\x00\x00\x00\x00'
                        10      BUILD_TUPLE                     1
                        12      CALL_FUNCTION_EX                0
                        14      POP_TOP                         
                        16      RESUME                          0
                        18      NOP                             
                        20      NOP                             
                        22      NOP                             
                        24      NOP                             
                        26      NOP                             
                        28      LOAD_FAST                       0: self
                        30      LOAD_ATTR                       0: _update_states
                        50      LOAD_ATTR                       3: items
                        70      CALL                            0
                        78      NOP                             
                        80      NOP                             
                        82      NOP                             
                        84      JUMP_FORWARD                    20 (to 126)
                        86      CALL                            1
                        94      POP_TOP                         
                        96      RETURN_VALUE                    
                        98      PUSH_EXC_INFO                   
                        100     PUSH_NULL                       
                        102     LOAD_CONST                      4: '__pyarmor_exit_23567__'
                        104     NOP                             
                        106     LOAD_CONST                      3: b'<COAddr>\x07\x00\x00\x1aH\x00\x00\x00\x00\x00\x00\x00\x00\x00\x00\x00\x00\x00\x00\x00'
                        108     CALL                            1
                        116     POP_TOP                         
                        118     RERAISE                         0
                        120     COPY                            3
                        122     POP_EXCEPT                      
                        124     RERAISE                         1
                        126     PUSH_NULL                       
                        128     LOAD_CONST                      4: '__pyarmor_exit_23567__'
                        130     LOAD_CONST                      3: b'<COAddr>\x07\x00\x00\x1aH\x00\x00\x00\x00\x00\x00\x00\x00\x00\x00\x00\x00\x00\x00\x00'
                        132     BUILD_TUPLE                     1
                        134     CALL_FUNCTION_EX                0
                        136     POP_TOP                         
                        138     RETURN_VALUE                    
                    [Exception Table]
                        28 to 78 -> 98 [0] 
                        98 to 120 -> 120 [1] lasti
                [Code]
                    File Name: <frozen multithon.sessions.memory>
                    Object Name: close
                    Qualified Name: MemorySession.close
                    Arg Count: 1
                    Pos Only Arg Count: 0
                    KW Only Arg Count: 0
                    Stack Size: 5
                    Flags: 0x20000003 (CO_OPTIMIZED | CO_NEWLOCALS | CO_PYARMOR_OBFUSCATED)
                    [Names]
                    [Locals+Names]
                        'self'
                        '__assert_armored__'
                    [Constants]
                        None
                        '__pyarmor_assert_23568__'
                        '__pyarmor_enter_23569__'
                        b'<COAddr>\x05\x00\x00\x1a\x16\x00\x00\x00\x00\x00\x00\x00\x00\x00\x00\x00\x00\x00\x00\x00'
                        '__pyarmor_exit_23570__'
                    [Disassembly]
                        0       NOP                             
                        2       NOP                             
                        4       PUSH_NULL                       
                        6       LOAD_CONST                      2: '__pyarmor_enter_23569__'
                        8       LOAD_CONST                      3: b'<COAddr>\x05\x00\x00\x1a\x16\x00\x00\x00\x00\x00\x00\x00\x00\x00\x00\x00\x00\x00\x00\x00'
                        10      BUILD_TUPLE                     1
                        12      CALL_FUNCTION_EX                0
                        14      POP_TOP                         
                        16      RESUME                          0
                        18      NOP                             
                        20      NOP                             
                        22      NOP                             
                        24      NOP                             
                        26      NOP                             
                        28      LOAD_CONST                      0: None
                        30      NOP                             
                        32      NOP                             
                        34      NOP                             
                        36      JUMP_FORWARD                    19 (to 76)
                        44      POP_TOP                         
                        46      RETURN_CONST                    0: None
                        48      PUSH_EXC_INFO                   
                        50      PUSH_NULL                       
                        52      LOAD_CONST                      4: '__pyarmor_exit_23570__'
                        54      NOP                             
                        56      LOAD_CONST                      3: b'<COAddr>\x05\x00\x00\x1a\x16\x00\x00\x00\x00\x00\x00\x00\x00\x00\x00\x00\x00\x00\x00\x00'
                        58      CALL                            1
                        66      POP_TOP                         
                        68      RERAISE                         0
                        70      COPY                            3
                        72      POP_EXCEPT                      
                        74      RERAISE                         1
                        76      PUSH_NULL                       
                        78      LOAD_CONST                      4: '__pyarmor_exit_23570__'
                        80      LOAD_CONST                      3: b'<COAddr>\x05\x00\x00\x1a\x16\x00\x00\x00\x00\x00\x00\x00\x00\x00\x00\x00\x00\x00\x00\x00'
                        82      BUILD_TUPLE                     1
                        84      CALL_FUNCTION_EX                0
                        86      POP_TOP                         
                        88      RETURN_VALUE                    
                    [Exception Table]
                        48 to 70 -> 70 [1] lasti
                [Code]
                    File Name: <frozen multithon.sessions.memory>
                    Object Name: save
                    Qualified Name: MemorySession.save
                    Arg Count: 1
                    Pos Only Arg Count: 0
                    KW Only Arg Count: 0
                    Stack Size: 5
                    Flags: 0x20000003 (CO_OPTIMIZED | CO_NEWLOCALS | CO_PYARMOR_OBFUSCATED)
                    [Names]
                    [Locals+Names]
                        'self'
                        '__assert_armored__'
                    [Constants]
                        None
                        '__pyarmor_assert_23571__'
                        '__pyarmor_enter_23572__'
                        b'<COAddr>\x05\x00\x00\x1a\x16\x00\x00\x00\x00\x00\x00\x00\x00\x00\x00\x00\x00\x00\x00\x00'
                        '__pyarmor_exit_23573__'
                    [Disassembly]
                        0       NOP                             
                        2       NOP                             
                        4       PUSH_NULL                       
                        6       LOAD_CONST                      2: '__pyarmor_enter_23572__'
                        8       LOAD_CONST                      3: b'<COAddr>\x05\x00\x00\x1a\x16\x00\x00\x00\x00\x00\x00\x00\x00\x00\x00\x00\x00\x00\x00\x00'
                        10      BUILD_TUPLE                     1
                        12      CALL_FUNCTION_EX                0
                        14      POP_TOP                         
                        16      RESUME                          0
                        18      NOP                             
                        20      NOP                             
                        22      NOP                             
                        24      NOP                             
                        26      NOP                             
                        28      LOAD_CONST                      0: None
                        30      NOP                             
                        32      NOP                             
                        34      NOP                             
                        36      JUMP_FORWARD                    19 (to 76)
                        44      POP_TOP                         
                        46      RETURN_CONST                    0: None
                        48      PUSH_EXC_INFO                   
                        50      PUSH_NULL                       
                        52      LOAD_CONST                      4: '__pyarmor_exit_23573__'
                        54      NOP                             
                        56      LOAD_CONST                      3: b'<COAddr>\x05\x00\x00\x1a\x16\x00\x00\x00\x00\x00\x00\x00\x00\x00\x00\x00\x00\x00\x00\x00'
                        58      CALL                            1
                        66      POP_TOP                         
                        68      RERAISE                         0
                        70      COPY                            3
                        72      POP_EXCEPT                      
                        74      RERAISE                         1
                        76      PUSH_NULL                       
                        78      LOAD_CONST                      4: '__pyarmor_exit_23573__'
                        80      LOAD_CONST                      3: b'<COAddr>\x05\x00\x00\x1a\x16\x00\x00\x00\x00\x00\x00\x00\x00\x00\x00\x00\x00\x00\x00\x00'
                        82      BUILD_TUPLE                     1
                        84      CALL_FUNCTION_EX                0
                        86      POP_TOP                         
                        88      RETURN_VALUE                    
                    [Exception Table]
                        48 to 70 -> 70 [1] lasti
                [Code]
                    File Name: <frozen multithon.sessions.memory>
                    Object Name: delete
                    Qualified Name: MemorySession.delete
                    Arg Count: 1
                    Pos Only Arg Count: 0
                    KW Only Arg Count: 0
                    Stack Size: 5
                    Flags: 0x20000003 (CO_OPTIMIZED | CO_NEWLOCALS | CO_PYARMOR_OBFUSCATED)
                    [Names]
                    [Locals+Names]
                        'self'
                        '__assert_armored__'
                    [Constants]
                        None
                        '__pyarmor_assert_23574__'
                        '__pyarmor_enter_23575__'
                        b'<COAddr>\x07\x00\x00\x1a\x16\x00\x00\x00\x00\x00\x00\x00\x00\x00\x00\x00\x00\x00\x00\x00'
                        '__pyarmor_exit_23576__'
                    [Disassembly]
                        0       NOP                             
                        2       NOP                             
                        4       PUSH_NULL                       
                        6       LOAD_CONST                      2: '__pyarmor_enter_23575__'
                        8       LOAD_CONST                      3: b'<COAddr>\x07\x00\x00\x1a\x16\x00\x00\x00\x00\x00\x00\x00\x00\x00\x00\x00\x00\x00\x00\x00'
                        10      BUILD_TUPLE                     1
                        12      CALL_FUNCTION_EX                0
                        14      POP_TOP                         
                        16      RESUME                          0
                        18      NOP                             
                        20      NOP                             
                        22      NOP                             
                        24      NOP                             
                        26      NOP                             
                        28      LOAD_CONST                      0: None
                        30      NOP                             
                        32      NOP                             
                        34      NOP                             
                        36      JUMP_FORWARD                    19 (to 76)
                        44      POP_TOP                         
                        46      RETURN_CONST                    0: None
                        48      PUSH_EXC_INFO                   
                        50      PUSH_NULL                       
                        52      LOAD_CONST                      4: '__pyarmor_exit_23576__'
                        54      NOP                             
                        56      LOAD_CONST                      3: b'<COAddr>\x07\x00\x00\x1a\x16\x00\x00\x00\x00\x00\x00\x00\x00\x00\x00\x00\x00\x00\x00\x00'
                        58      CALL                            1
                        66      POP_TOP                         
                        68      RERAISE                         0
                        70      COPY                            3
                        72      POP_EXCEPT                      
                        74      RERAISE                         1
                        76      PUSH_NULL                       
                        78      LOAD_CONST                      4: '__pyarmor_exit_23576__'
                        80      LOAD_CONST                      3: b'<COAddr>\x07\x00\x00\x1a\x16\x00\x00\x00\x00\x00\x00\x00\x00\x00\x00\x00\x00\x00\x00\x00'
                        82      BUILD_TUPLE                     1
                        84      CALL_FUNCTION_EX                0
                        86      POP_TOP                         
                        88      RETURN_VALUE                    
                    [Exception Table]
                        48 to 70 -> 70 [1] lasti
                [Code]
                    File Name: <frozen multithon.sessions.memory>
                    Object Name: _entity_values_to_row
                    Qualified Name: MemorySession._entity_values_to_row
                    Arg Count: 5
                    Pos Only Arg Count: 0
                    KW Only Arg Count: 0
                    Stack Size: 5
                    Flags: 0x20000003 (CO_OPTIMIZED | CO_NEWLOCALS | CO_PYARMOR_OBFUSCATED)
                    [Names]
                    [Locals+Names]
                        'id'
                        'hash'
                        'username'
                        'phone'
                        'name'
                        '__assert_armored__'
                    [Constants]
                        None
                        '__pyarmor_assert_23577__'
                        '__pyarmor_enter_23578__'
                        b'<COAddr>\x07\x00\x00\x1a"\x00\x00\x00\x00\x00\x00\x00\x00\x00\x00\x00\x00\x00\x00\x00'
                        '__pyarmor_exit_23579__'
                    [Disassembly]
                        0       NOP                             
                        2       NOP                             
                        4       PUSH_NULL                       
                        6       LOAD_CONST                      2: '__pyarmor_enter_23578__'
                        8       LOAD_CONST                      3: b'<COAddr>\x07\x00\x00\x1a"\x00\x00\x00\x00\x00\x00\x00\x00\x00\x00\x00\x00\x00\x00\x00'
                        10      BUILD_TUPLE                     1
                        12      CALL_FUNCTION_EX                0
                        14      POP_TOP                         
                        16      RESUME                          0
                        18      NOP                             
                        20      NOP                             
                        22      NOP                             
                        24      NOP                             
                        26      NOP                             
                        28      LOAD_FAST                       0: id
                        30      LOAD_FAST                       1: hash
                        32      LOAD_FAST                       2: username
                        34      LOAD_FAST                       3: phone
                        36      LOAD_FAST                       4: name
                        38      BUILD_TUPLE                     5
                        40      NOP                             
                        42      NOP                             
                        44      NOP                             
                        46      JUMP_FORWARD                    20 (to 88)
                        48      CALL                            1
                        56      POP_TOP                         
                        58      RETURN_VALUE                    
                        60      PUSH_EXC_INFO                   
                        62      PUSH_NULL                       
                        64      LOAD_CONST                      4: '__pyarmor_exit_23579__'
                        66      NOP                             
                        68      LOAD_CONST                      3: b'<COAddr>\x07\x00\x00\x1a"\x00\x00\x00\x00\x00\x00\x00\x00\x00\x00\x00\x00\x00\x00\x00'
                        70      CALL                            1
                        78      POP_TOP                         
                        80      RERAISE                         0
                        82      COPY                            3
                        84      POP_EXCEPT                      
                        86      RERAISE                         1
                        88      PUSH_NULL                       
                        90      LOAD_CONST                      4: '__pyarmor_exit_23579__'
                        92      LOAD_CONST                      3: b'<COAddr>\x07\x00\x00\x1a"\x00\x00\x00\x00\x00\x00\x00\x00\x00\x00\x00\x00\x00\x00\x00'
                        94      BUILD_TUPLE                     1
                        96      CALL_FUNCTION_EX                0
                        98      POP_TOP                         
                        100     RETURN_VALUE                    
                    [Exception Table]
                        28 to 40 -> 60 [0] 
                        60 to 82 -> 82 [1] lasti
                [Code]
                    File Name: <frozen multithon.sessions.memory>
                    Object Name: _entity_to_row
                    Qualified Name: MemorySession._entity_to_row
                    Arg Count: 2
                    Pos Only Arg Count: 0
                    KW Only Arg Count: 0
                    Stack Size: 7
                    Flags: 0x20000003 (CO_OPTIMIZED | CO_NEWLOCALS | CO_PYARMOR_OBFUSCATED)
                    [Names]
                        'isinstance'
                        'TLObject'
                        'utils'
                        'get_input_peer'
                        'get_peer_id'
                        'TypeError'
                        'InputPeerUser'
                        'InputPeerChannel'
                        'access_hash'
                        'InputPeerChat'
                        'getattr'
                        'lower'
                        'get_display_name'
                        '_entity_values_to_row'
                    [Locals+Names]
                        'self'
                        'e'
                        '__assert_armored__'
                        '_var_var_0'
                        '_var_var_1'
                        '_var_var_2'
                        '_var_var_3'
                        '_var_var_4'
                        '_var_var_5'
                    [Constants]
                        None
                        '__pyarmor_assert_23580__'
                        '__pyarmor_enter_23581__'
                        b'<COAddr>\x07\x00\x00\x1a\x12\x02\x00\x00\x00\x00\x00\x00\x00\x00\x00\x00\x00\x00\x00\x00'
                        '__pyarmor_exit_23582__'
                        False
                        (
                            'allow_self'
                        )
                        0
                        'username'
                        'phone'
                    [Disassembly]
                        0       NOP                             
                        2       NOP                             
                        4       PUSH_NULL                       
                        6       LOAD_CONST                      2: '__pyarmor_enter_23581__'
                        8       LOAD_CONST                      3: b'<COAddr>\x07\x00\x00\x1a\x12\x02\x00\x00\x00\x00\x00\x00\x00\x00\x00\x00\x00\x00\x00\x00'
                        10      BUILD_TUPLE                     1
                        12      CALL_FUNCTION_EX                0
                        14      POP_TOP                         
                        16      RESUME                          0
                        18      NOP                             
                        20      NOP                             
                        22      NOP                             
                        24      NOP                             
                        26      NOP                             
                        28      LOAD_GLOBAL                     1: NULL + isinstance
                        38      LOAD_FAST                       1: e
                        40      LOAD_GLOBAL                     2: TLObject
                        50      CALL                            2
                        58      POP_JUMP_IF_TRUE                11 (to 82)
                        60      NOP                             
                        62      LOAD_CONST                      0: None
                        64      NOP                             
                        66      NOP                             
                        68      JUMP_FORWARD                    256 (to 584)
                        78      POP_TOP                         
                        80      RETURN_CONST                    0: None
                        82      NOP                             
                        84      LOAD_GLOBAL                     5: NULL + utils
                        94      LOAD_ATTR                       6: get_input_peer
                        114     LOAD_FAST                       1: e
                        116     LOAD_CONST                      5: False
                        118     KW_NAMES                        6: ('allow_self',)
                        120     CALL                            2
                        128     STORE_FAST                      3: _var_var_0
                        130     LOAD_GLOBAL                     5: NULL + utils
                        140     LOAD_ATTR                       8: get_peer_id
                        160     LOAD_FAST                       3: _var_var_0
                        162     CALL                            1
                        170     STORE_FAST                      4: _var_var_1
                        172     LOAD_GLOBAL                     1: NULL + isinstance
                        182     LOAD_FAST                       3: _var_var_0
                        184     LOAD_GLOBAL                     12: InputPeerUser
                        194     LOAD_GLOBAL                     14: InputPeerChannel
                        204     BUILD_TUPLE                     2
                        206     CALL                            2
                        214     POP_JUMP_IF_FALSE               13 (to 242)
                        216     LOAD_FAST                       3: _var_var_0
                        218     LOAD_ATTR                       16: access_hash
                        238     STORE_FAST                      5: _var_var_2
                        240     JUMP_FORWARD                    30 (to 302)
                        242     LOAD_GLOBAL                     1: NULL + isinstance
                        252     LOAD_FAST                       3: _var_var_0
                        254     LOAD_GLOBAL                     18: InputPeerChat
                        264     CALL                            2
                        272     POP_JUMP_IF_FALSE               3 (to 280)
                        274     LOAD_CONST                      7: 0
                        276     STORE_FAST                      5: _var_var_2
                        278     JUMP_FORWARD                    11 (to 302)
                        280     NOP                             
                        282     LOAD_CONST                      0: None
                        284     NOP                             
                        286     NOP                             
                        288     NOP                             
                        290     JUMP_FORWARD                    146 (to 584)
                        298     POP_TOP                         
                        300     RETURN_CONST                    0: None
                        302     LOAD_GLOBAL                     21: NULL + getattr
                        312     LOAD_FAST                       1: e
                        314     LOAD_CONST                      8: 'username'
                        316     LOAD_CONST                      0: None
                        318     CALL                            3
                        326     COPY                            1
                        328     POP_JUMP_IF_TRUE                2 (to 334)
                        330     POP_TOP                         
                        332     LOAD_CONST                      0: None
                        334     STORE_FAST                      6: _var_var_3
                        336     LOAD_FAST                       6: _var_var_3
                        338     POP_JUMP_IF_NONE                16 (to 372)
                        340     LOAD_FAST                       6: _var_var_3
                        342     LOAD_ATTR                       23: lower
                        362     CALL                            0
                        370     STORE_FAST                      6: _var_var_3
                        372     LOAD_GLOBAL                     21: NULL + getattr
                        382     LOAD_FAST                       1: e
                        384     LOAD_CONST                      9: 'phone'
                        386     LOAD_CONST                      0: None
                        388     CALL                            3
                        396     STORE_FAST                      7: _var_var_4
                        398     LOAD_GLOBAL                     5: NULL + utils
                        408     LOAD_ATTR                       24: get_display_name
                        428     LOAD_FAST                       1: e
                        430     CALL                            1
                        438     COPY                            1
                        440     POP_JUMP_IF_TRUE                2 (to 446)
                        442     POP_TOP                         
                        444     LOAD_CONST                      0: None
                        446     STORE_FAST                      8: _var_var_5
                        448     LOAD_FAST                       0: self
                        450     LOAD_ATTR                       27: _entity_values_to_row
                        470     LOAD_FAST                       4: _var_var_1
                        472     LOAD_FAST                       5: _var_var_2
                        474     LOAD_FAST                       6: _var_var_3
                        476     LOAD_FAST                       7: _var_var_4
                        478     LOAD_FAST                       8: _var_var_5
                        480     CALL                            5
                        488     NOP                             
                        490     NOP                             
                        492     NOP                             
                        494     JUMP_FORWARD                    44 (to 584)
                        496     CALL                            1
                        504     POP_TOP                         
                        506     RETURN_VALUE                    
                        508     PUSH_EXC_INFO                   
                        510     LOAD_GLOBAL                     10: TypeError
                        520     CHECK_EXC_MATCH                 
                        522     POP_JUMP_IF_FALSE               12 (to 548)
                        524     POP_TOP                         
                        526     POP_EXCEPT                      
                        528     LOAD_CONST                      0: None
                        530     NOP                             
                        532     NOP                             
                        534     NOP                             
                        536     JUMP_FORWARD                    23 (to 584)
                        544     POP_TOP                         
                        546     RETURN_CONST                    0: None
                        548     RERAISE                         0
                        550     COPY                            3
                        552     POP_EXCEPT                      
                        554     RERAISE                         1
                        556     PUSH_EXC_INFO                   
                        558     PUSH_NULL                       
                        560     LOAD_CONST                      4: '__pyarmor_exit_23582__'
                        562     NOP                             
                        564     LOAD_CONST                      3: b'<COAddr>\x07\x00\x00\x1a\x12\x02\x00\x00\x00\x00\x00\x00\x00\x00\x00\x00\x00\x00\x00\x00'
                        566     CALL                            1
                        574     POP_TOP                         
                        576     RERAISE                         0
                        578     COPY                            3
                        580     POP_EXCEPT                      
                        582     RERAISE                         1
                        584     PUSH_NULL                       
                        586     LOAD_CONST                      4: '__pyarmor_exit_23582__'
                        588     LOAD_CONST                      3: b'<COAddr>\x07\x00\x00\x1a\x12\x02\x00\x00\x00\x00\x00\x00\x00\x00\x00\x00\x00\x00\x00\x00'
                        590     BUILD_TUPLE                     1
                        592     CALL_FUNCTION_EX                0
                        594     POP_TOP                         
                        596     RETURN_VALUE                    
                    [Exception Table]
                        28 to 60 -> 556 [0] 
                        84 to 172 -> 508 [0] 
                        172 to 280 -> 556 [0] 
                        302 to 488 -> 556 [0] 
                        508 to 526 -> 550 [1] lasti
                        526 to 528 -> 556 [0] 
                        548 to 550 -> 550 [1] lasti
                        550 to 556 -> 556 [0] 
                        556 to 578 -> 578 [1] lasti
                [Code]
                    File Name: <frozen multithon.sessions.memory>
                    Object Name: _entities_to_rows
                    Qualified Name: MemorySession._entities_to_rows
                    Arg Count: 2
                    Pos Only Arg Count: 0
                    KW Only Arg Count: 0
                    Stack Size: 5
                    Flags: 0x20000003 (CO_OPTIMIZED | CO_NEWLOCALS | CO_PYARMOR_OBFUSCATED)
                    [Names]
                        'isinstance'
                        'TLObject'
                        'utils'
                        'is_list_like'
                        'hasattr'
                        'append'
                        'user'
                        'chat'
                        'chats'
                        'extend'
                        'users'
                        '_entity_to_row'
                    [Locals+Names]
                        'self'
                        'tlo'
                        '__assert_armored__'
                        '_var_var_6'
                        '_var_var_7'
                        '_var_var_8'
                        '_var_var_9'
                    [Constants]
                        None
                        '__pyarmor_assert_23583__'
                        '__pyarmor_enter_23584__'
                        b'<COAddr>\x05\x00\x00\x1a|\x02\x00\x00\x00\x00\x00\x00\x00\x00\x00\x00\x00\x00\x00\x00'
                        'user'
                        'chat'
                        'chats'
                        'users'
                        '__pyarmor_exit_23585__'
                    [Disassembly]
                        0       NOP                             
                        2       NOP                             
                        4       PUSH_NULL                       
                        6       LOAD_CONST                      2: '__pyarmor_enter_23584__'
                        8       LOAD_CONST                      3: b'<COAddr>\x05\x00\x00\x1a|\x02\x00\x00\x00\x00\x00\x00\x00\x00\x00\x00\x00\x00\x00\x00'
                        10      BUILD_TUPLE                     1
                        12      CALL_FUNCTION_EX                0
                        14      POP_TOP                         
                        16      RESUME                          0
                        18      NOP                             
                        20      NOP                             
                        22      NOP                             
                        24      NOP                             
                        26      NOP                             
                        28      LOAD_GLOBAL                     1: NULL + isinstance
                        38      LOAD_FAST                       1: tlo
                        40      LOAD_GLOBAL                     2: TLObject
                        50      CALL                            2
                        58      POP_JUMP_IF_TRUE                24 (to 108)
                        60      LOAD_GLOBAL                     5: NULL + utils
                        70      LOAD_ATTR                       6: is_list_like
                        90      LOAD_FAST                       1: tlo
                        92      CALL                            1
                        100     POP_JUMP_IF_FALSE               3 (to 108)
                        102     LOAD_FAST                       1: tlo
                        104     STORE_FAST                      3: _var_var_6
                        106     JUMP_FORWARD                    220 (to 548)
                        108     BUILD_LIST                      0
                        110     STORE_FAST                      3: _var_var_6
                        112     LOAD_GLOBAL                     9: NULL + hasattr
                        122     LOAD_FAST                       1: tlo
                        124     LOAD_CONST                      4: 'user'
                        126     CALL                            2
                        134     POP_JUMP_IF_FALSE               27 (to 190)
                        136     LOAD_FAST                       3: _var_var_6
                        138     LOAD_ATTR                       11: append
                        158     LOAD_FAST                       1: tlo
                        160     LOAD_ATTR                       12: user
                        180     CALL                            1
                        188     POP_TOP                         
                        190     LOAD_GLOBAL                     9: NULL + hasattr
                        200     LOAD_FAST                       1: tlo
                        202     LOAD_CONST                      5: 'chat'
                        204     CALL                            2
                        212     POP_JUMP_IF_FALSE               27 (to 268)
                        214     LOAD_FAST                       3: _var_var_6
                        216     LOAD_ATTR                       11: append
                        236     LOAD_FAST                       1: tlo
                        238     LOAD_ATTR                       14: chat
                        258     CALL                            1
                        266     POP_TOP                         
                        268     LOAD_GLOBAL                     9: NULL + hasattr
                        278     LOAD_FAST                       1: tlo
                        280     LOAD_CONST                      6: 'chats'
                        282     CALL                            2
                        290     POP_JUMP_IF_FALSE               58 (to 408)
                        292     LOAD_GLOBAL                     5: NULL + utils
                        302     LOAD_ATTR                       6: is_list_like
                        322     LOAD_FAST                       1: tlo
                        324     LOAD_ATTR                       16: chats
                        344     CALL                            1
                        352     POP_JUMP_IF_FALSE               27 (to 408)
                        354     LOAD_FAST                       3: _var_var_6
                        356     LOAD_ATTR                       19: extend
                        376     LOAD_FAST                       1: tlo
                        378     LOAD_ATTR                       16: chats
                        398     CALL                            1
                        406     POP_TOP                         
                        408     LOAD_GLOBAL                     9: NULL + hasattr
                        418     LOAD_FAST                       1: tlo
                        420     LOAD_CONST                      7: 'users'
                        422     CALL                            2
                        430     POP_JUMP_IF_FALSE               58 (to 548)
                        432     LOAD_GLOBAL                     5: NULL + utils
                        442     LOAD_ATTR                       6: is_list_like
                        462     LOAD_FAST                       1: tlo
                        464     LOAD_ATTR                       20: users
                        484     CALL                            1
                        492     POP_JUMP_IF_FALSE               27 (to 548)
                        494     LOAD_FAST                       3: _var_var_6
                        496     LOAD_ATTR                       19: extend
                        516     LOAD_FAST                       1: tlo
                        518     LOAD_ATTR                       20: users
                        538     CALL                            1
                        546     POP_TOP                         
                        548     BUILD_LIST                      0
                        550     STORE_FAST                      4: _var_var_7
                        552     LOAD_FAST                       3: _var_var_6
                        554     GET_ITER                        
                        556     FOR_ITER                        39 (to 636)
                        560     STORE_FAST                      5: _var_var_8
                        562     LOAD_FAST                       0: self
                        564     LOAD_ATTR                       23: _entity_to_row
                        584     LOAD_FAST                       5: _var_var_8
                        586     CALL                            1
                        594     STORE_FAST                      6: _var_var_9
                        596     LOAD_FAST                       6: _var_var_9
                        598     POP_JUMP_IF_TRUE                1 (to 602)
                        600     JUMP_BACKWARD                   23 (to 556)
                        602     LOAD_FAST                       4: _var_var_7
                        604     LOAD_ATTR                       11: append
                        624     LOAD_FAST                       6: _var_var_9
                        626     CALL                            1
                        634     POP_TOP                         
                        636     JUMP_BACKWARD                   41 (to 556)
                        638     END_FOR                         
                        640     LOAD_FAST                       4: _var_var_7
                        642     NOP                             
                        644     NOP                             
                        646     NOP                             
                        648     JUMP_FORWARD                    20 (to 690)
                        650     CALL                            1
                        658     POP_TOP                         
                        660     RETURN_VALUE                    
                        662     PUSH_EXC_INFO                   
                        664     PUSH_NULL                       
                        666     LOAD_CONST                      8: '__pyarmor_exit_23585__'
                        668     NOP                             
                        670     LOAD_CONST                      3: b'<COAddr>\x05\x00\x00\x1a|\x02\x00\x00\x00\x00\x00\x00\x00\x00\x00\x00\x00\x00\x00\x00'
                        672     CALL                            1
                        680     POP_TOP                         
                        682     RERAISE                         0
                        684     COPY                            3
                        686     POP_EXCEPT                      
                        688     RERAISE                         1
                        690     PUSH_NULL                       
                        692     LOAD_CONST                      8: '__pyarmor_exit_23585__'
                        694     LOAD_CONST                      3: b'<COAddr>\x05\x00\x00\x1a|\x02\x00\x00\x00\x00\x00\x00\x00\x00\x00\x00\x00\x00\x00\x00'
                        696     BUILD_TUPLE                     1
                        698     CALL_FUNCTION_EX                0
                        700     POP_TOP                         
                        702     RETURN_VALUE                    
                    [Exception Table]
                        28 to 600 -> 662 [0] 
                        602 to 642 -> 662 [0] 
                        662 to 684 -> 684 [1] lasti
                [Code]
                    File Name: <frozen multithon.sessions.memory>
                    Object Name: process_entities
                    Qualified Name: MemorySession.process_entities
                    Arg Count: 2
                    Pos Only Arg Count: 0
                    KW Only Arg Count: 0
                    Stack Size: 7
                    Flags: 0x20000003 (CO_OPTIMIZED | CO_NEWLOCALS | CO_PYARMOR_OBFUSCATED)
                    [Names]
                        '_entities'
                        'set'
                        '_entities_to_rows'
                    [Locals+Names]
                        'self'
                        'tlo'
                        '__assert_armored__'
                    [Constants]
                        None
                        '__pyarmor_assert_23586__'
                        '__pyarmor_enter_23587__'
                        b'<COAddr>\x07\x00\x00\x1ap\x00\x00\x00\x00\x00\x00\x00\x00\x00\x00\x00\x00\x00\x00\x00'
                        '__pyarmor_exit_23588__'
                    [Disassembly]
                        0       NOP                             
                        2       NOP                             
                        4       PUSH_NULL                       
                        6       LOAD_CONST                      2: '__pyarmor_enter_23587__'
                        8       LOAD_CONST                      3: b'<COAddr>\x07\x00\x00\x1ap\x00\x00\x00\x00\x00\x00\x00\x00\x00\x00\x00\x00\x00\x00\x00'
                        10      BUILD_TUPLE                     1
                        12      CALL_FUNCTION_EX                0
                        14      POP_TOP                         
                        16      RESUME                          0
                        18      NOP                             
                        20      NOP                             
                        22      NOP                             
                        24      NOP                             
                        26      NOP                             
                        28      LOAD_FAST                       0: self
                        30      COPY                            1
                        32      LOAD_ATTR                       0: _entities
                        52      LOAD_GLOBAL                     3: NULL + set
                        62      LOAD_FAST                       0: self
                        64      LOAD_ATTR                       5: _entities_to_rows
                        84      LOAD_FAST                       1: tlo
                        86      CALL                            1
                        94      CALL                            1
                        102     BINARY_OP                       20 (|=)
                        106     SWAP                            2
                        108     STORE_ATTR                      0: _entities
                        118     LOAD_CONST                      0: None
                        120     NOP                             
                        122     NOP                             
                        124     NOP                             
                        126     JUMP_FORWARD                    19 (to 166)
                        134     POP_TOP                         
                        136     RETURN_CONST                    0: None
                        138     PUSH_EXC_INFO                   
                        140     PUSH_NULL                       
                        142     LOAD_CONST                      4: '__pyarmor_exit_23588__'
                        144     NOP                             
                        146     LOAD_CONST                      3: b'<COAddr>\x07\x00\x00\x1ap\x00\x00\x00\x00\x00\x00\x00\x00\x00\x00\x00\x00\x00\x00\x00'
                        148     CALL                            1
                        156     POP_TOP                         
                        158     RERAISE                         0
                        160     COPY                            3
                        162     POP_EXCEPT                      
                        164     RERAISE                         1
                        166     PUSH_NULL                       
                        168     LOAD_CONST                      4: '__pyarmor_exit_23588__'
                        170     LOAD_CONST                      3: b'<COAddr>\x07\x00\x00\x1ap\x00\x00\x00\x00\x00\x00\x00\x00\x00\x00\x00\x00\x00\x00\x00'
                        172     BUILD_TUPLE                     1
                        174     CALL_FUNCTION_EX                0
                        176     POP_TOP                         
                        178     RETURN_VALUE                    
                    [Exception Table]
                        28 to 118 -> 138 [0] 
                        138 to 160 -> 160 [1] lasti
                [Code]
                    File Name: <frozen multithon.sessions.memory>
                    Object Name: get_entity_rows_by_phone
                    Qualified Name: MemorySession.get_entity_rows_by_phone
                    Arg Count: 2
                    Pos Only Arg Count: 0
                    KW Only Arg Count: 0
                    Stack Size: 5
                    Flags: 0x20000003 (CO_OPTIMIZED | CO_NEWLOCALS | CO_PYARMOR_OBFUSCATED)
                    [Names]
                        'next'
                        '_entities'
                        'StopIteration'
                    [Locals+Names]
                        'self'
                        'phone'
                        '__assert_armored__'
                    [Constants]
                        None
                        '__pyarmor_assert_23589__'
                        '__pyarmor_enter_23590__'
                        b'<COAddr>\x05\x00\x00\x1c\x86\x00\x00\x00\x00\x00\x00\x00\x00\x00\x00\x00\x00\x00\x00\x00'
                        [Code]
                            File Name: <frozen multithon.sessions.memory>
                            Object Name: <genexpr>
                            Qualified Name: MemorySession.get_entity_rows_by_phone.<locals>.<genexpr>
                            Arg Count: 1
                            Pos Only Arg Count: 0
                            KW Only Arg Count: 0
                            Stack Size: 6
                            Flags: 0x00000033 (CO_OPTIMIZED | CO_NEWLOCALS | CO_NESTED | CO_GENERATOR)
                            [Names]
                            [Locals+Names]
                                '.0'
                                '_var_var_10'
                                '_var_var_11'
                                '_var_var_12'
                                '_var_var_13'
                                'phone'
                            [Constants]
                                None
                            [Disassembly]
                                0       COPY_FREE_VARS                  1
                                2       RETURN_GENERATOR                
                                4       POP_TOP                         
                                6       RESUME                          0
                                8       LOAD_FAST                       0: .0
                                10      FOR_ITER                        19 (to 50)
                                14      UNPACK_SEQUENCE                 5
                                18      STORE_FAST                      1: _var_var_10
                                20      STORE_FAST                      2: _var_var_11
                                22      STORE_FAST                      3: _var_var_12
                                24      STORE_FAST                      4: _var_var_13
                                26      STORE_FAST                      3: _var_var_12
                                28      LOAD_FAST                       4: _var_var_13
                                30      LOAD_DEREF                      5: phone
                                32      COMPARE_OP                      40 (==)
                                36      POP_JUMP_IF_FALSE               6 (to 50)
                                38      LOAD_FAST                       1: _var_var_10
                                40      LOAD_FAST                       2: _var_var_11
                                42      BUILD_TUPLE                     2
                                44      YIELD_VALUE                     1
                                46      RESUME                          1
                                48      POP_TOP                         
                                50      JUMP_BACKWARD                   21 (to 10)
                                52      END_FOR                         
                                54      RETURN_CONST                    0: None
                                56      CALL_INTRINSIC_1                3 (INTRINSIC_STOPITERATION_ERROR)
                                58      RERAISE                         1
                            [Exception Table]
                                6 to 56 -> 56 [0] lasti
                        '__pyarmor_exit_23591__'
                    [Disassembly]
                        0       MAKE_CELL                       1: phone
                        2       NOP                             
                        4       NOP                             
                        6       PUSH_NULL                       
                        8       LOAD_CONST                      2: '__pyarmor_enter_23590__'
                        10      LOAD_CONST                      3: b'<COAddr>\x05\x00\x00\x1c\x86\x00\x00\x00\x00\x00\x00\x00\x00\x00\x00\x00\x00\x00\x00\x00'
                        12      BUILD_TUPLE                     1
                        14      CALL_FUNCTION_EX                0
                        16      POP_TOP                         
                        18      RESUME                          0
                        20      NOP                             
                        22      NOP                             
                        24      NOP                             
                        26      NOP                             
                        28      NOP                             
                        30      NOP                             
                        32      LOAD_GLOBAL                     1: NULL + next
                        42      LOAD_CLOSURE                    1: phone
                        44      BUILD_TUPLE                     1
                        46      LOAD_CONST                      4: <CODE> <genexpr>
                        48      MAKE_FUNCTION                   8
                        50      LOAD_FAST                       0: self
                        52      LOAD_ATTR                       2: _entities
                        72      GET_ITER                        
                        74      CALL                            0
                        82      CALL                            1
                        90      NOP                             
                        92      NOP                             
                        94      NOP                             
                        96      JUMP_FORWARD                    46 (to 190)
                        98      CALL                            1
                        106     POP_TOP                         
                        108     RETURN_VALUE                    
                        110     PUSH_EXC_INFO                   
                        112     LOAD_GLOBAL                     4: StopIteration
                        122     CHECK_EXC_MATCH                 
                        124     POP_JUMP_IF_FALSE               3 (to 132)
                        126     POP_TOP                         
                        128     POP_EXCEPT                      
                        130     JUMP_FORWARD                    4 (to 140)
                        132     RERAISE                         0
                        134     COPY                            3
                        136     POP_EXCEPT                      
                        138     RERAISE                         1
                        140     NOP                             
                        142     LOAD_CONST                      0: None
                        144     NOP                             
                        146     NOP                             
                        148     NOP                             
                        150     JUMP_FORWARD                    19 (to 190)
                        158     POP_TOP                         
                        160     RETURN_CONST                    0: None
                        162     PUSH_EXC_INFO                   
                        164     PUSH_NULL                       
                        166     LOAD_CONST                      5: '__pyarmor_exit_23591__'
                        168     NOP                             
                        170     LOAD_CONST                      3: b'<COAddr>\x05\x00\x00\x1c\x86\x00\x00\x00\x00\x00\x00\x00\x00\x00\x00\x00\x00\x00\x00\x00'
                        172     CALL                            1
                        180     POP_TOP                         
                        182     RERAISE                         0
                        184     COPY                            3
                        186     POP_EXCEPT                      
                        188     RERAISE                         1
                        190     PUSH_NULL                       
                        192     LOAD_CONST                      5: '__pyarmor_exit_23591__'
                        194     LOAD_CONST                      3: b'<COAddr>\x05\x00\x00\x1c\x86\x00\x00\x00\x00\x00\x00\x00\x00\x00\x00\x00\x00\x00\x00\x00'
                        196     BUILD_TUPLE                     1
                        198     CALL_FUNCTION_EX                0
                        200     POP_TOP                         
                        202     RETURN_VALUE                    
                    [Exception Table]
                        32 to 90 -> 110 [0] 
                        110 to 128 -> 134 [1] lasti
                        128 to 132 -> 162 [0] 
                        132 to 134 -> 134 [1] lasti
                        134 to 140 -> 162 [0] 
                        162 to 184 -> 184 [1] lasti
                [Code]
                    File Name: <frozen multithon.sessions.memory>
                    Object Name: get_entity_rows_by_username
                    Qualified Name: MemorySession.get_entity_rows_by_username
                    Arg Count: 2
                    Pos Only Arg Count: 0
                    KW Only Arg Count: 0
                    Stack Size: 5
                    Flags: 0x20000003 (CO_OPTIMIZED | CO_NEWLOCALS | CO_PYARMOR_OBFUSCATED)
                    [Names]
                        'next'
                        '_entities'
                        'StopIteration'
                    [Locals+Names]
                        'self'
                        'username'
                        '__assert_armored__'
                    [Constants]
                        None
                        '__pyarmor_assert_23592__'
                        '__pyarmor_enter_23593__'
                        b'<COAddr>\x05\x00\x00\x1c\x86\x00\x00\x00\x00\x00\x00\x00\x00\x00\x00\x00\x00\x00\x00\x00'
                        [Code]
                            File Name: <frozen multithon.sessions.memory>
                            Object Name: <genexpr>
                            Qualified Name: MemorySession.get_entity_rows_by_username.<locals>.<genexpr>
                            Arg Count: 1
                            Pos Only Arg Count: 0
                            KW Only Arg Count: 0
                            Stack Size: 6
                            Flags: 0x00000033 (CO_OPTIMIZED | CO_NEWLOCALS | CO_NESTED | CO_GENERATOR)
                            [Names]
                            [Locals+Names]
                                '.0'
                                '_var_var_10'
                                '_var_var_11'
                                '_var_var_14'
                                '_var_var_12'
                                'username'
                            [Constants]
                                None
                            [Disassembly]
                                0       COPY_FREE_VARS                  1
                                2       RETURN_GENERATOR                
                                4       POP_TOP                         
                                6       RESUME                          0
                                8       LOAD_FAST                       0: .0
                                10      FOR_ITER                        19 (to 50)
                                14      UNPACK_SEQUENCE                 5
                                18      STORE_FAST                      1: _var_var_10
                                20      STORE_FAST                      2: _var_var_11
                                22      STORE_FAST                      3: _var_var_14
                                24      STORE_FAST                      4: _var_var_12
                                26      STORE_FAST                      4: _var_var_12
                                28      LOAD_FAST                       3: _var_var_14
                                30      LOAD_DEREF                      5: username
                                32      COMPARE_OP                      40 (==)
                                36      POP_JUMP_IF_FALSE               6 (to 50)
                                38      LOAD_FAST                       1: _var_var_10
                                40      LOAD_FAST                       2: _var_var_11
                                42      BUILD_TUPLE                     2
                                44      YIELD_VALUE                     1
                                46      RESUME                          1
                                48      POP_TOP                         
                                50      JUMP_BACKWARD                   21 (to 10)
                                52      END_FOR                         
                                54      RETURN_CONST                    0: None
                                56      CALL_INTRINSIC_1                3 (INTRINSIC_STOPITERATION_ERROR)
                                58      RERAISE                         1
                            [Exception Table]
                                6 to 56 -> 56 [0] lasti
                        '__pyarmor_exit_23594__'
                    [Disassembly]
                        0       MAKE_CELL                       1: username
                        2       NOP                             
                        4       NOP                             
                        6       PUSH_NULL                       
                        8       LOAD_CONST                      2: '__pyarmor_enter_23593__'
                        10      LOAD_CONST                      3: b'<COAddr>\x05\x00\x00\x1c\x86\x00\x00\x00\x00\x00\x00\x00\x00\x00\x00\x00\x00\x00\x00\x00'
                        12      BUILD_TUPLE                     1
                        14      CALL_FUNCTION_EX                0
                        16      POP_TOP                         
                        18      RESUME                          0
                        20      NOP                             
                        22      NOP                             
                        24      NOP                             
                        26      NOP                             
                        28      NOP                             
                        30      NOP                             
                        32      LOAD_GLOBAL                     1: NULL + next
                        42      LOAD_CLOSURE                    1: username
                        44      BUILD_TUPLE                     1
                        46      LOAD_CONST                      4: <CODE> <genexpr>
                        48      MAKE_FUNCTION                   8
                        50      LOAD_FAST                       0: self
                        52      LOAD_ATTR                       2: _entities
                        72      GET_ITER                        
                        74      CALL                            0
                        82      CALL                            1
                        90      NOP                             
                        92      NOP                             
                        94      NOP                             
                        96      JUMP_FORWARD                    46 (to 190)
                        98      CALL                            1
                        106     POP_TOP                         
                        108     RETURN_VALUE                    
                        110     PUSH_EXC_INFO                   
                        112     LOAD_GLOBAL                     4: StopIteration
                        122     CHECK_EXC_MATCH                 
                        124     POP_JUMP_IF_FALSE               3 (to 132)
                        126     POP_TOP                         
                        128     POP_EXCEPT                      
                        130     JUMP_FORWARD                    4 (to 140)
                        132     RERAISE                         0
                        134     COPY                            3
                        136     POP_EXCEPT                      
                        138     RERAISE                         1
                        140     NOP                             
                        142     LOAD_CONST                      0: None
                        144     NOP                             
                        146     NOP                             
                        148     NOP                             
                        150     JUMP_FORWARD                    19 (to 190)
                        158     POP_TOP                         
                        160     RETURN_CONST                    0: None
                        162     PUSH_EXC_INFO                   
                        164     PUSH_NULL                       
                        166     LOAD_CONST                      5: '__pyarmor_exit_23594__'
                        168     NOP                             
                        170     LOAD_CONST                      3: b'<COAddr>\x05\x00\x00\x1c\x86\x00\x00\x00\x00\x00\x00\x00\x00\x00\x00\x00\x00\x00\x00\x00'
                        172     CALL                            1
                        180     POP_TOP                         
                        182     RERAISE                         0
                        184     COPY                            3
                        186     POP_EXCEPT                      
                        188     RERAISE                         1
                        190     PUSH_NULL                       
                        192     LOAD_CONST                      5: '__pyarmor_exit_23594__'
                        194     LOAD_CONST                      3: b'<COAddr>\x05\x00\x00\x1c\x86\x00\x00\x00\x00\x00\x00\x00\x00\x00\x00\x00\x00\x00\x00\x00'
                        196     BUILD_TUPLE                     1
                        198     CALL_FUNCTION_EX                0
                        200     POP_TOP                         
                        202     RETURN_VALUE                    
                    [Exception Table]
                        32 to 90 -> 110 [0] 
                        110 to 128 -> 134 [1] lasti
                        128 to 132 -> 162 [0] 
                        132 to 134 -> 134 [1] lasti
                        134 to 140 -> 162 [0] 
                        162 to 184 -> 184 [1] lasti
                [Code]
                    File Name: <frozen multithon.sessions.memory>
                    Object Name: get_entity_rows_by_name
                    Qualified Name: MemorySession.get_entity_rows_by_name
                    Arg Count: 2
                    Pos Only Arg Count: 0
                    KW Only Arg Count: 0
                    Stack Size: 5
                    Flags: 0x20000003 (CO_OPTIMIZED | CO_NEWLOCALS | CO_PYARMOR_OBFUSCATED)
                    [Names]
                        'next'
                        '_entities'
                        'StopIteration'
                    [Locals+Names]
                        'self'
                        'name'
                        '__assert_armored__'
                    [Constants]
                        None
                        '__pyarmor_assert_23595__'
                        '__pyarmor_enter_23596__'
                        b'<COAddr>\x07\x00\x00\x1c\x86\x00\x00\x00\x00\x00\x00\x00\x00\x00\x00\x00\x00\x00\x00\x00'
                        [Code]
                            File Name: <frozen multithon.sessions.memory>
                            Object Name: <genexpr>
                            Qualified Name: MemorySession.get_entity_rows_by_name.<locals>.<genexpr>
                            Arg Count: 1
                            Pos Only Arg Count: 0
                            KW Only Arg Count: 0
                            Stack Size: 6
                            Flags: 0x00000033 (CO_OPTIMIZED | CO_NEWLOCALS | CO_NESTED | CO_GENERATOR)
                            [Names]
                            [Locals+Names]
                                '.0'
                                '_var_var_10'
                                '_var_var_11'
                                '_var_var_12'
                                '_var_var_15'
                                'name'
                            [Constants]
                                None
                            [Disassembly]
                                0       COPY_FREE_VARS                  1
                                2       RETURN_GENERATOR                
                                4       POP_TOP                         
                                6       RESUME                          0
                                8       LOAD_FAST                       0: .0
                                10      FOR_ITER                        19 (to 50)
                                14      UNPACK_SEQUENCE                 5
                                18      STORE_FAST                      1: _var_var_10
                                20      STORE_FAST                      2: _var_var_11
                                22      STORE_FAST                      3: _var_var_12
                                24      STORE_FAST                      3: _var_var_12
                                26      STORE_FAST                      4: _var_var_15
                                28      LOAD_FAST                       4: _var_var_15
                                30      LOAD_DEREF                      5: name
                                32      COMPARE_OP                      40 (==)
                                36      POP_JUMP_IF_FALSE               6 (to 50)
                                38      LOAD_FAST                       1: _var_var_10
                                40      LOAD_FAST                       2: _var_var_11
                                42      BUILD_TUPLE                     2
                                44      YIELD_VALUE                     1
                                46      RESUME                          1
                                48      POP_TOP                         
                                50      JUMP_BACKWARD                   21 (to 10)
                                52      END_FOR                         
                                54      RETURN_CONST                    0: None
                                56      CALL_INTRINSIC_1                3 (INTRINSIC_STOPITERATION_ERROR)
                                58      RERAISE                         1
                            [Exception Table]
                                6 to 56 -> 56 [0] lasti
                        '__pyarmor_exit_23597__'
                    [Disassembly]
                        0       MAKE_CELL                       1: name
                        2       NOP                             
                        4       NOP                             
                        6       PUSH_NULL                       
                        8       LOAD_CONST                      2: '__pyarmor_enter_23596__'
                        10      LOAD_CONST                      3: b'<COAddr>\x07\x00\x00\x1c\x86\x00\x00\x00\x00\x00\x00\x00\x00\x00\x00\x00\x00\x00\x00\x00'
                        12      BUILD_TUPLE                     1
                        14      CALL_FUNCTION_EX                0
                        16      POP_TOP                         
                        18      RESUME                          0
                        20      NOP                             
                        22      NOP                             
                        24      NOP                             
                        26      NOP                             
                        28      NOP                             
                        30      NOP                             
                        32      LOAD_GLOBAL                     1: NULL + next
                        42      LOAD_CLOSURE                    1: name
                        44      BUILD_TUPLE                     1
                        46      LOAD_CONST                      4: <CODE> <genexpr>
                        48      MAKE_FUNCTION                   8
                        50      LOAD_FAST                       0: self
                        52      LOAD_ATTR                       2: _entities
                        72      GET_ITER                        
                        74      CALL                            0
                        82      CALL                            1
                        90      NOP                             
                        92      NOP                             
                        94      NOP                             
                        96      JUMP_FORWARD                    46 (to 190)
                        98      CALL                            1
                        106     POP_TOP                         
                        108     RETURN_VALUE                    
                        110     PUSH_EXC_INFO                   
                        112     LOAD_GLOBAL                     4: StopIteration
                        122     CHECK_EXC_MATCH                 
                        124     POP_JUMP_IF_FALSE               3 (to 132)
                        126     POP_TOP                         
                        128     POP_EXCEPT                      
                        130     JUMP_FORWARD                    4 (to 140)
                        132     RERAISE                         0
                        134     COPY                            3
                        136     POP_EXCEPT                      
                        138     RERAISE                         1
                        140     NOP                             
                        142     LOAD_CONST                      0: None
                        144     NOP                             
                        146     NOP                             
                        148     NOP                             
                        150     JUMP_FORWARD                    19 (to 190)
                        158     POP_TOP                         
                        160     RETURN_CONST                    0: None
                        162     PUSH_EXC_INFO                   
                        164     PUSH_NULL                       
                        166     LOAD_CONST                      5: '__pyarmor_exit_23597__'
                        168     NOP                             
                        170     LOAD_CONST                      3: b'<COAddr>\x07\x00\x00\x1c\x86\x00\x00\x00\x00\x00\x00\x00\x00\x00\x00\x00\x00\x00\x00\x00'
                        172     CALL                            1
                        180     POP_TOP                         
                        182     RERAISE                         0
                        184     COPY                            3
                        186     POP_EXCEPT                      
                        188     RERAISE                         1
                        190     PUSH_NULL                       
                        192     LOAD_CONST                      5: '__pyarmor_exit_23597__'
                        194     LOAD_CONST                      3: b'<COAddr>\x07\x00\x00\x1c\x86\x00\x00\x00\x00\x00\x00\x00\x00\x00\x00\x00\x00\x00\x00\x00'
                        196     BUILD_TUPLE                     1
                        198     CALL_FUNCTION_EX                0
                        200     POP_TOP                         
                        202     RETURN_VALUE                    
                    [Exception Table]
                        32 to 90 -> 110 [0] 
                        110 to 128 -> 134 [1] lasti
                        128 to 132 -> 162 [0] 
                        132 to 134 -> 134 [1] lasti
                        134 to 140 -> 162 [0] 
                        162 to 184 -> 184 [1] lasti
                [Code]
                    File Name: <frozen multithon.sessions.memory>
                    Object Name: get_entity_rows_by_id
                    Qualified Name: MemorySession.get_entity_rows_by_id
                    Arg Count: 3
                    Pos Only Arg Count: 0
                    KW Only Arg Count: 0
                    Stack Size: 7
                    Flags: 0x20000003 (CO_OPTIMIZED | CO_NEWLOCALS | CO_PYARMOR_OBFUSCATED)
                    [Names]
                        'next'
                        '_entities'
                        'utils'
                        'get_peer_id'
                        'PeerUser'
                        'PeerChat'
                        'PeerChannel'
                        'StopIteration'
                    [Locals+Names]
                        'self'
                        'id'
                        'exact'
                        '__assert_armored__'
                        '_var_var_16'
                    [Constants]
                        None
                        '__pyarmor_assert_23598__'
                        '__pyarmor_enter_23599__'
                        b'<COAddr>\x07\x00\x00\x1e\x8a\x01\x00\x00\x00\x00\x00\x00\x00\x00\x00\x00\x00\x00\x00\x00'
                        [Code]
                            File Name: <frozen multithon.sessions.memory>
                            Object Name: <genexpr>
                            Qualified Name: MemorySession.get_entity_rows_by_id.<locals>.<genexpr>
                            Arg Count: 1
                            Pos Only Arg Count: 0
                            KW Only Arg Count: 0
                            Stack Size: 6
                            Flags: 0x00000033 (CO_OPTIMIZED | CO_NEWLOCALS | CO_NESTED | CO_GENERATOR)
                            [Names]
                            [Locals+Names]
                                '.0'
                                '_var_var_17'
                                '_var_var_11'
                                '_var_var_12'
                                'id'
                            [Constants]
                                None
                            [Disassembly]
                                0       COPY_FREE_VARS                  1
                                2       RETURN_GENERATOR                
                                4       POP_TOP                         
                                6       RESUME                          0
                                8       LOAD_FAST                       0: .0
                                10      FOR_ITER                        19 (to 50)
                                14      UNPACK_SEQUENCE                 5
                                18      STORE_FAST                      1: _var_var_17
                                20      STORE_FAST                      2: _var_var_11
                                22      STORE_FAST                      3: _var_var_12
                                24      STORE_FAST                      3: _var_var_12
                                26      STORE_FAST                      3: _var_var_12
                                28      LOAD_FAST                       1: _var_var_17
                                30      LOAD_DEREF                      4: id
                                32      COMPARE_OP                      40 (==)
                                36      POP_JUMP_IF_FALSE               6 (to 50)
                                38      LOAD_FAST                       1: _var_var_17
                                40      LOAD_FAST                       2: _var_var_11
                                42      BUILD_TUPLE                     2
                                44      YIELD_VALUE                     1
                                46      RESUME                          1
                                48      POP_TOP                         
                                50      JUMP_BACKWARD                   21 (to 10)
                                52      END_FOR                         
                                54      RETURN_CONST                    0: None
                                56      CALL_INTRINSIC_1                3 (INTRINSIC_STOPITERATION_ERROR)
                                58      RERAISE                         1
                            [Exception Table]
                                6 to 56 -> 56 [0] lasti
                        '__pyarmor_exit_23600__'
                        [Code]
                            File Name: <frozen multithon.sessions.memory>
                            Object Name: <genexpr>
                            Qualified Name: MemorySession.get_entity_rows_by_id.<locals>.<genexpr>
                            Arg Count: 1
                            Pos Only Arg Count: 0
                            KW Only Arg Count: 0
                            Stack Size: 6
                            Flags: 0x00000033 (CO_OPTIMIZED | CO_NEWLOCALS | CO_NESTED | CO_GENERATOR)
                            [Names]
                            [Locals+Names]
                                '.0'
                                '_var_var_17'
                                '_var_var_11'
                                '_var_var_12'
                                '_var_var_16'
                            [Constants]
                                None
                            [Disassembly]
                                0       COPY_FREE_VARS                  1
                                2       RETURN_GENERATOR                
                                4       POP_TOP                         
                                6       RESUME                          0
                                8       LOAD_FAST                       0: .0
                                10      FOR_ITER                        18 (to 48)
                                14      UNPACK_SEQUENCE                 5
                                18      STORE_FAST                      1: _var_var_17
                                20      STORE_FAST                      2: _var_var_11
                                22      STORE_FAST                      3: _var_var_12
                                24      STORE_FAST                      3: _var_var_12
                                26      STORE_FAST                      3: _var_var_12
                                28      LOAD_FAST                       1: _var_var_17
                                30      LOAD_DEREF                      4: _var_var_16
                                32      CONTAINS_OP                     0 (in)
                                34      POP_JUMP_IF_FALSE               6 (to 48)
                                36      LOAD_FAST                       1: _var_var_17
                                38      LOAD_FAST                       2: _var_var_11
                                40      BUILD_TUPLE                     2
                                42      YIELD_VALUE                     1
                                44      RESUME                          1
                                46      POP_TOP                         
                                48      JUMP_BACKWARD                   20 (to 10)
                                50      END_FOR                         
                                52      RETURN_CONST                    0: None
                                54      CALL_INTRINSIC_1                3 (INTRINSIC_STOPITERATION_ERROR)
                                56      RERAISE                         1
                            [Exception Table]
                                6 to 54 -> 54 [0] lasti
                    [Disassembly]
                        0       MAKE_CELL                       1: id
                        2       MAKE_CELL                       4: _var_var_16
                        4       NOP                             
                        6       NOP                             
                        8       PUSH_NULL                       
                        10      LOAD_CONST                      2: '__pyarmor_enter_23599__'
                        12      LOAD_CONST                      3: b'<COAddr>\x07\x00\x00\x1e\x8a\x01\x00\x00\x00\x00\x00\x00\x00\x00\x00\x00\x00\x00\x00\x00'
                        14      BUILD_TUPLE                     1
                        16      CALL_FUNCTION_EX                0
                        18      POP_TOP                         
                        20      RESUME                          0
                        22      NOP                             
                        24      NOP                             
                        26      NOP                             
                        28      NOP                             
                        30      NOP                             
                        32      NOP                             
                        34      LOAD_FAST                       2: exact
                        36      POP_JUMP_IF_FALSE               39 (to 116)
                        38      LOAD_GLOBAL                     1: NULL + next
                        48      LOAD_CLOSURE                    1: id
                        50      BUILD_TUPLE                     1
                        52      LOAD_CONST                      4: <CODE> <genexpr>
                        54      MAKE_FUNCTION                   8
                        56      LOAD_FAST                       0: self
                        58      LOAD_ATTR                       2: _entities
                        78      GET_ITER                        
                        80      CALL                            0
                        88      CALL                            1
                        96      NOP                             
                        98      NOP                             
                        100     NOP                             
                        102     JUMP_FORWARD                    174 (to 452)
                        104     CALL                            1
                        112     POP_TOP                         
                        114     RETURN_VALUE                    
                        116     LOAD_GLOBAL                     5: NULL + utils
                        126     LOAD_ATTR                       6: get_peer_id
                        146     LOAD_GLOBAL                     9: NULL + PeerUser
                        156     LOAD_DEREF                      1: id
                        158     CALL                            1
                        166     CALL                            1
                        174     LOAD_GLOBAL                     5: NULL + utils
                        184     LOAD_ATTR                       6: get_peer_id
                        204     LOAD_GLOBAL                     11: NULL + PeerChat
                        214     LOAD_DEREF                      1: id
                        216     CALL                            1
                        224     CALL                            1
                        232     LOAD_GLOBAL                     5: NULL + utils
                        242     LOAD_ATTR                       6: get_peer_id
                        262     LOAD_GLOBAL                     13: NULL + PeerChannel
                        272     LOAD_DEREF                      1: id
                        274     CALL                            1
                        282     CALL                            1
                        290     BUILD_TUPLE                     3
                        292     STORE_DEREF                     4: _var_var_16
                        294     LOAD_GLOBAL                     1: NULL + next
                        304     LOAD_CLOSURE                    4: _var_var_16
                        306     BUILD_TUPLE                     1
                        308     LOAD_CONST                      6: <CODE> <genexpr>
                        310     MAKE_FUNCTION                   8
                        312     LOAD_FAST                       0: self
                        314     LOAD_ATTR                       2: _entities
                        334     GET_ITER                        
                        336     CALL                            0
                        344     CALL                            1
                        352     NOP                             
                        354     NOP                             
                        356     NOP                             
                        358     JUMP_FORWARD                    46 (to 452)
                        360     CALL                            1
                        368     POP_TOP                         
                        370     RETURN_VALUE                    
                        372     PUSH_EXC_INFO                   
                        374     LOAD_GLOBAL                     14: StopIteration
                        384     CHECK_EXC_MATCH                 
                        386     POP_JUMP_IF_FALSE               3 (to 394)
                        388     POP_TOP                         
                        390     POP_EXCEPT                      
                        392     JUMP_FORWARD                    4 (to 402)
                        394     RERAISE                         0
                        396     COPY                            3
                        398     POP_EXCEPT                      
                        400     RERAISE                         1
                        402     NOP                             
                        404     LOAD_CONST                      0: None
                        406     NOP                             
                        408     NOP                             
                        410     NOP                             
                        412     JUMP_FORWARD                    19 (to 452)
                        420     POP_TOP                         
                        422     RETURN_CONST                    0: None
                        424     PUSH_EXC_INFO                   
                        426     PUSH_NULL                       
                        428     LOAD_CONST                      5: '__pyarmor_exit_23600__'
                        430     NOP                             
                        432     LOAD_CONST                      3: b'<COAddr>\x07\x00\x00\x1e\x8a\x01\x00\x00\x00\x00\x00\x00\x00\x00\x00\x00\x00\x00\x00\x00'
                        434     CALL                            1
                        442     POP_TOP                         
                        444     RERAISE                         0
                        446     COPY                            3
                        448     POP_EXCEPT                      
                        450     RERAISE                         1
                        452     PUSH_NULL                       
                        454     LOAD_CONST                      5: '__pyarmor_exit_23600__'
                        456     LOAD_CONST                      3: b'<COAddr>\x07\x00\x00\x1e\x8a\x01\x00\x00\x00\x00\x00\x00\x00\x00\x00\x00\x00\x00\x00\x00'
                        458     BUILD_TUPLE                     1
                        460     CALL_FUNCTION_EX                0
                        462     POP_TOP                         
                        464     RETURN_VALUE                    
                    [Exception Table]
                        34 to 96 -> 372 [0] 
                        116 to 352 -> 372 [0] 
                        372 to 390 -> 396 [1] lasti
                        390 to 394 -> 424 [0] 
                        394 to 396 -> 396 [1] lasti
                        396 to 402 -> 424 [0] 
                        424 to 446 -> 446 [1] lasti
                [Code]
                    File Name: <frozen multithon.sessions.memory>
                    Object Name: get_input_entity
                    Qualified Name: MemorySession.get_input_entity
                    Arg Count: 2
                    Pos Only Arg Count: 0
                    KW Only Arg Count: 0
                    Stack Size: 5
                    Flags: 0x20000003 (CO_OPTIMIZED | CO_NEWLOCALS | CO_PYARMOR_OBFUSCATED)
                    [Names]
                        'SUBCLASS_OF_ID'
                        'utils'
                        'get_input_peer'
                        'AttributeError'
                        'TypeError'
                        'isinstance'
                        'TLObject'
                        'get_peer_id'
                        'int'
                        'str'
                        'parse_phone'
                        'get_entity_rows_by_phone'
                        'parse_username'
                        'get_entity_rows_by_username'
                        'resolve_invite_link'
                        'get_entity_rows_by_id'
                        'get_entity_rows_by_name'
                        'resolve_id'
                        'PeerUser'
                        'InputPeerUser'
                        'PeerChat'
                        'InputPeerChat'
                        'PeerChannel'
                        'InputPeerChannel'
                        'ValueError'
                    [Locals+Names]
                        'self'
                        'key'
                        '__assert_armored__'
                        '_var_var_18'
                        '_var_var_19'
                        '_var_var_4'
                        '_var_var_3'
                        '_var_var_20'
                        '_var_var_21'
                        '_var_var_22'
                        '_var_var_23'
                        '_var_var_24'
                    [Constants]
                        None
                        '__pyarmor_assert_23601__'
                        '__pyarmor_enter_23602__'
                        b'<COAddr>\x05\x00\x00\x1a\xfe\x03\x00\x00\x00\x00\x00\x00\x00\x00\x00\x00\x00\x00\x00\x00'
                        (
                            0xC91C90B6
                            0xE669BF46
                            1089602301
                        )
                        '__pyarmor_exit_23603__'
                        True
                        0
                        1
                        False
                        (
                            'exact'
                        )
                        'Could not find input entity with key '   # b'\x81\xc1\x17\x06?\xfe\xfe\xdc\x14\xeeM\xc6e\xe2\xfc\xc5\x06S\xab\xb2\xbe\x8bK\xc2\x11f\xb7E@\xa6\x17\xf12\x12+\x08\x81\x8a'
                    [Disassembly]
                        0       NOP                             
                        2       NOP                             
                        4       PUSH_NULL                       
                        6       LOAD_CONST                      2: '__pyarmor_enter_23602__'
                        8       LOAD_CONST                      3: b'<COAddr>\x05\x00\x00\x1a\xfe\x03\x00\x00\x00\x00\x00\x00\x00\x00\x00\x00\x00\x00\x00\x00'
                        10      BUILD_TUPLE                     1
                        12      CALL_FUNCTION_EX                0
                        14      POP_TOP                         
                        16      RESUME                          0
                        18      NOP                             
                        20      NOP                             
                        22      NOP                             
                        24      NOP                             
                        26      NOP                             
                        28      NOP                             
                        30      LOAD_FAST                       1: key
                        32      LOAD_ATTR                       0: SUBCLASS_OF_ID
                        52      LOAD_CONST                      4: (0xC91C90B6, 0xE669BF46, 1089602301)
                        54      CONTAINS_OP                     0 (in)
                        56      POP_JUMP_IF_FALSE               11 (to 80)
                        58      LOAD_FAST                       1: key
                        60      NOP                             
                        62      NOP                             
                        64      JUMP_FORWARD                    504 (to 1076)
                        68      CALL                            1
                        76      POP_TOP                         
                        78      RETURN_VALUE                    
                        80      LOAD_GLOBAL                     3: NULL + utils
                        90      LOAD_ATTR                       4: get_input_peer
                        110     LOAD_FAST                       1: key
                        112     CALL                            1
                        120     NOP                             
                        122     NOP                             
                        124     JUMP_FORWARD                    474 (to 1076)
                        128     CALL                            1
                        136     POP_TOP                         
                        138     RETURN_VALUE                    
                        140     PUSH_EXC_INFO                   
                        142     LOAD_GLOBAL                     6: AttributeError
                        152     LOAD_GLOBAL                     8: TypeError
                        162     BUILD_TUPLE                     2
                        164     CHECK_EXC_MATCH                 
                        166     POP_JUMP_IF_FALSE               67 (to 302)
                        168     POP_TOP                         
                        170     LOAD_GLOBAL                     11: NULL + isinstance
                        180     LOAD_FAST                       1: key
                        182     LOAD_GLOBAL                     12: TLObject
                        192     CALL                            2
                        200     POP_JUMP_IF_FALSE               24 (to 250)
                        202     LOAD_GLOBAL                     3: NULL + utils
                        212     LOAD_ATTR                       14: get_peer_id
                        232     LOAD_FAST                       1: key
                        234     CALL                            1
                        242     STORE_FAST                      1: key
                        244     LOAD_CONST                      6: True
                        246     STORE_FAST                      3: _var_var_18
                        248     JUMP_FORWARD                    24 (to 298)
                        250     LOAD_GLOBAL                     11: NULL + isinstance
                        260     LOAD_FAST                       1: key
                        262     LOAD_GLOBAL                     16: int
                        272     CALL                            2
                        280     UNARY_NOT                       
                        282     COPY                            1
                        284     POP_JUMP_IF_TRUE                5 (to 296)
                        286     POP_TOP                         
                        288     LOAD_FAST                       1: key
                        290     LOAD_CONST                      7: 0
                        292     COMPARE_OP                      2 (<)
                        296     STORE_FAST                      3: _var_var_18
                        298     POP_EXCEPT                      
                        300     JUMP_FORWARD                    4 (to 310)
                        302     RERAISE                         0
                        304     COPY                            3
                        306     POP_EXCEPT                      
                        308     RERAISE                         1
                        310     LOAD_CONST                      0: None
                        312     STORE_FAST                      4: _var_var_19
                        314     LOAD_GLOBAL                     11: NULL + isinstance
                        324     LOAD_FAST                       1: key
                        326     LOAD_GLOBAL                     18: str
                        336     CALL                            2
                        344     POP_JUMP_IF_FALSE               133 (to 612)
                        346     LOAD_GLOBAL                     3: NULL + utils
                        356     LOAD_ATTR                       20: parse_phone
                        376     LOAD_FAST                       1: key
                        378     CALL                            1
                        386     STORE_FAST                      5: _var_var_4
                        388     LOAD_FAST                       5: _var_var_4
                        390     POP_JUMP_IF_FALSE               18 (to 428)
                        392     LOAD_FAST                       0: self
                        394     LOAD_ATTR                       23: get_entity_rows_by_phone
                        414     LOAD_FAST                       5: _var_var_4
                        416     CALL                            1
                        424     STORE_FAST                      4: _var_var_19
                        426     JUMP_FORWARD                    126 (to 680)
                        428     LOAD_GLOBAL                     3: NULL + utils
                        438     LOAD_ATTR                       24: parse_username
                        458     LOAD_FAST                       1: key
                        460     CALL                            1
                        468     UNPACK_SEQUENCE                 2
                        472     STORE_FAST                      6: _var_var_3
                        474     STORE_FAST                      7: _var_var_20
                        476     LOAD_FAST                       6: _var_var_3
                        478     POP_JUMP_IF_FALSE               20 (to 520)
                        480     LOAD_FAST                       7: _var_var_20
                        482     POP_JUMP_IF_TRUE                18 (to 520)
                        484     LOAD_FAST                       0: self
                        486     LOAD_ATTR                       27: get_entity_rows_by_username
                        506     LOAD_FAST                       6: _var_var_3
                        508     CALL                            1
                        516     STORE_FAST                      4: _var_var_19
                        518     JUMP_FORWARD                    80 (to 680)
                        520     LOAD_GLOBAL                     3: NULL + utils
                        530     LOAD_ATTR                       28: resolve_invite_link
                        550     LOAD_FAST                       1: key
                        552     CALL                            1
                        560     LOAD_CONST                      8: 1
                        562     BINARY_SUBSCR                   
                        566     STORE_FAST                      8: _var_var_21
                        568     LOAD_FAST                       8: _var_var_21
                        570     POP_JUMP_IF_FALSE               54 (to 680)
                        572     LOAD_FAST                       0: self
                        574     LOAD_ATTR                       31: get_entity_rows_by_id
                        594     LOAD_FAST                       8: _var_var_21
                        596     LOAD_CONST                      9: False
                        598     KW_NAMES                        10: ('exact',)
                        600     CALL                            2
                        608     STORE_FAST                      4: _var_var_19
                        610     JUMP_FORWARD                    34 (to 680)
                        612     LOAD_GLOBAL                     11: NULL + isinstance
                        622     LOAD_FAST                       1: key
                        624     LOAD_GLOBAL                     16: int
                        634     CALL                            2
                        642     POP_JUMP_IF_FALSE               18 (to 680)
                        644     LOAD_FAST                       0: self
                        646     LOAD_ATTR                       31: get_entity_rows_by_id
                        666     LOAD_FAST                       1: key
                        668     LOAD_FAST                       3: _var_var_18
                        670     CALL                            2
                        678     STORE_FAST                      4: _var_var_19
                        680     LOAD_FAST                       4: _var_var_19
                        682     POP_JUMP_IF_TRUE                33 (to 750)
                        684     LOAD_GLOBAL                     11: NULL + isinstance
                        694     LOAD_FAST                       1: key
                        696     LOAD_GLOBAL                     18: str
                        706     CALL                            2
                        714     POP_JUMP_IF_FALSE               17 (to 750)
                        716     LOAD_FAST                       0: self
                        718     LOAD_ATTR                       33: get_entity_rows_by_name
                        738     LOAD_FAST                       1: key
                        740     CALL                            1
                        748     STORE_FAST                      4: _var_var_19
                        750     LOAD_FAST                       4: _var_var_19
                        752     POP_JUMP_IF_FALSE               118 (to 990)
                        754     LOAD_FAST                       4: _var_var_19
                        756     UNPACK_SEQUENCE                 2
                        760     STORE_FAST                      9: _var_var_22
                        762     STORE_FAST                      10: _var_var_23
                        764     LOAD_GLOBAL                     3: NULL + utils
                        774     LOAD_ATTR                       34: resolve_id
                        794     LOAD_FAST                       9: _var_var_22
                        796     CALL                            1
                        804     UNPACK_SEQUENCE                 2
                        808     STORE_FAST                      9: _var_var_22
                        810     STORE_FAST                      11: _var_var_24
                        812     LOAD_FAST                       11: _var_var_24
                        814     LOAD_GLOBAL                     36: PeerUser
                        824     COMPARE_OP                      40 (==)
                        828     POP_JUMP_IF_FALSE               21 (to 872)
                        830     LOAD_GLOBAL                     39: NULL + InputPeerUser
                        840     LOAD_FAST                       9: _var_var_22
                        842     LOAD_FAST                       10: _var_var_23
                        844     CALL                            2
                        852     NOP                             
                        854     NOP                             
                        856     NOP                             
                        858     JUMP_FORWARD                    108 (to 1076)
                        860     CALL                            1
                        868     POP_TOP                         
                        870     RETURN_VALUE                    
                        872     LOAD_FAST                       11: _var_var_24
                        874     LOAD_GLOBAL                     40: PeerChat
                        884     COMPARE_OP                      40 (==)
                        888     POP_JUMP_IF_FALSE               20 (to 930)
                        890     LOAD_GLOBAL                     43: NULL + InputPeerChat
                        900     LOAD_FAST                       9: _var_var_22
                        902     CALL                            1
                        910     NOP                             
                        912     NOP                             
                        914     NOP                             
                        916     JUMP_FORWARD                    79 (to 1076)
                        918     CALL                            1
                        926     POP_TOP                         
                        928     RETURN_VALUE                    
                        930     LOAD_FAST                       11: _var_var_24
                        932     LOAD_GLOBAL                     44: PeerChannel
                        942     COMPARE_OP                      40 (==)
                        946     POP_JUMP_IF_FALSE               39 (to 1026)
                        948     LOAD_GLOBAL                     47: NULL + InputPeerChannel
                        958     LOAD_FAST                       9: _var_var_22
                        960     LOAD_FAST                       10: _var_var_23
                        962     CALL                            2
                        970     NOP                             
                        972     NOP                             
                        974     NOP                             
                        976     JUMP_FORWARD                    49 (to 1076)
                        978     CALL                            1
                        986     POP_TOP                         
                        988     RETURN_VALUE                    
                        990     LOAD_GLOBAL                     49: NULL + ValueError
                        1000    PUSH_NULL                       
                        1002    LOAD_CONST                      1: '__pyarmor_assert_23601__'
                        1004    LOAD_CONST                      11: 'Could not find input entity with key '   # b'\x81\xc1\x17\x06?\xfe\xfe\xdc\x14\xeeM\xc6e\xe2\xfc\xc5\x06S\xab\xb2\xbe\x8bK\xc2\x11f\xb7E@\xa6\x17\xf12\x12+\x08\x81\x8a'
                        1006    CALL                            1
                        1014    LOAD_FAST                       1: key
                        1016    CALL                            2
                        1024    RAISE_VARARGS                   1
                        1026    NOP                             
                        1028    LOAD_CONST                      0: None
                        1030    NOP                             
                        1032    NOP                             
                        1034    NOP                             
                        1036    JUMP_FORWARD                    19 (to 1076)
                        1044    POP_TOP                         
                        1046    RETURN_CONST                    0: None
                        1048    PUSH_EXC_INFO                   
                        1050    PUSH_NULL                       
                        1052    LOAD_CONST                      5: '__pyarmor_exit_23603__'
                        1054    NOP                             
                        1056    LOAD_CONST                      3: b'<COAddr>\x05\x00\x00\x1a\xfe\x03\x00\x00\x00\x00\x00\x00\x00\x00\x00\x00\x00\x00\x00\x00'
                        1058    CALL                            1
                        1066    POP_TOP                         
                        1068    RERAISE                         0
                        1070    COPY                            3
                        1072    POP_EXCEPT                      
                        1074    RERAISE                         1
                        1076    PUSH_NULL                       
                        1078    LOAD_CONST                      5: '__pyarmor_exit_23603__'
                        1080    LOAD_CONST                      3: b'<COAddr>\x05\x00\x00\x1a\xfe\x03\x00\x00\x00\x00\x00\x00\x00\x00\x00\x00\x00\x00\x00\x00'
                        1082    BUILD_TUPLE                     1
                        1084    CALL_FUNCTION_EX                0
                        1086    POP_TOP                         
                        1088    RETURN_VALUE                    
                    [Exception Table]
                        30 to 60 -> 140 [0] 
                        80 to 120 -> 140 [0] 
                        140 to 298 -> 304 [1] lasti
                        298 to 302 -> 1048 [0] 
                        302 to 304 -> 304 [1] lasti
                        304 to 852 -> 1048 [0] 
                        872 to 910 -> 1048 [0] 
                        930 to 970 -> 1048 [0] 
                        990 to 1026 -> 1048 [0] 
                        1048 to 1070 -> 1070 [1] lasti
                [Code]
                    File Name: <frozen multithon.sessions.memory>
                    Object Name: cache_file
                    Qualified Name: MemorySession.cache_file
                    Arg Count: 4
                    Pos Only Arg Count: 0
                    KW Only Arg Count: 0
                    Stack Size: 7
                    Flags: 0x20000003 (CO_OPTIMIZED | CO_NEWLOCALS | CO_PYARMOR_OBFUSCATED)
                    [Names]
                        'isinstance'
                        'InputDocument'
                        'InputPhoto'
                        'TypeError'
                        'type'
                        '_SentFileType'
                        'from_type'
                        'id'
                        'access_hash'
                        '_files'
                    [Locals+Names]
                        'self'
                        'md5_digest'
                        'file_size'
                        'instance'
                        '__assert_armored__'
                        '_var_var_25'
                        '_var_var_26'
                    [Constants]
                        None
                        '__pyarmor_assert_23604__'
                        '__pyarmor_enter_23605__'
                        b'<COAddr>\x05\x00\x00\x1a\x0c\x01\x00\x00\x00\x00\x00\x00\x00\x00\x00\x00\x00\x00\x00\x00'
                        'Cannot cache %s instance'   # b'\x81\xc1\x19\x1d=\xf5\xaa\x92\x18\xfb\x0e\xc8i\xac\xbd\x96OT\xb5\xb4\xbe\xca@\xcf\x00'
                        '__pyarmor_exit_23606__'
                    [Disassembly]
                        0       NOP                             
                        2       NOP                             
                        4       PUSH_NULL                       
                        6       LOAD_CONST                      2: '__pyarmor_enter_23605__'
                        8       LOAD_CONST                      3: b'<COAddr>\x05\x00\x00\x1a\x0c\x01\x00\x00\x00\x00\x00\x00\x00\x00\x00\x00\x00\x00\x00\x00'
                        10      BUILD_TUPLE                     1
                        12      CALL_FUNCTION_EX                0
                        14      POP_TOP                         
                        16      RESUME                          0
                        18      NOP                             
                        20      NOP                             
                        22      NOP                             
                        24      NOP                             
                        26      NOP                             
                        28      LOAD_GLOBAL                     1: NULL + isinstance
                        38      LOAD_FAST                       3: instance
                        40      LOAD_GLOBAL                     2: InputDocument
                        50      LOAD_GLOBAL                     4: InputPhoto
                        60      BUILD_TUPLE                     2
                        62      CALL                            2
                        70      POP_JUMP_IF_TRUE                29 (to 130)
                        72      LOAD_GLOBAL                     7: NULL + TypeError
                        82      PUSH_NULL                       
                        84      LOAD_CONST                      1: '__pyarmor_assert_23604__'
                        86      LOAD_CONST                      4: 'Cannot cache %s instance'   # b'\x81\xc1\x19\x1d=\xf5\xaa\x92\x18\xfb\x0e\xc8i\xac\xbd\x96OT\xb5\xb4\xbe\xca@\xcf\x00'
                        88      CALL                            1
                        96      LOAD_GLOBAL                     9: NULL + type
                        106     LOAD_FAST                       3: instance
                        108     CALL                            1
                        116     BINARY_OP                       6 (%)
                        120     CALL                            1
                        128     RAISE_VARARGS                   1
                        130     LOAD_FAST                       1: md5_digest
                        132     LOAD_FAST                       2: file_size
                        134     LOAD_GLOBAL                     10: _SentFileType
                        144     LOAD_ATTR                       13: from_type
                        164     LOAD_GLOBAL                     9: NULL + type
                        174     LOAD_FAST                       3: instance
                        176     CALL                            1
                        184     CALL                            1
                        192     BUILD_TUPLE                     3
                        194     STORE_FAST                      5: _var_var_25
                        196     LOAD_FAST                       3: instance
                        198     LOAD_ATTR                       14: id
                        218     LOAD_FAST                       3: instance
                        220     LOAD_ATTR                       16: access_hash
                        240     BUILD_TUPLE                     2
                        242     STORE_FAST                      6: _var_var_26
                        244     LOAD_FAST                       6: _var_var_26
                        246     LOAD_FAST                       0: self
                        248     LOAD_ATTR                       18: _files
                        268     LOAD_FAST                       5: _var_var_25
                        270     STORE_SUBSCR                    
                        274     LOAD_CONST                      0: None
                        276     NOP                             
                        278     NOP                             
                        280     NOP                             
                        282     JUMP_FORWARD                    19 (to 322)
                        290     POP_TOP                         
                        292     RETURN_CONST                    0: None
                        294     PUSH_EXC_INFO                   
                        296     PUSH_NULL                       
                        298     LOAD_CONST                      5: '__pyarmor_exit_23606__'
                        300     NOP                             
                        302     LOAD_CONST                      3: b'<COAddr>\x05\x00\x00\x1a\x0c\x01\x00\x00\x00\x00\x00\x00\x00\x00\x00\x00\x00\x00\x00\x00'
                        304     CALL                            1
                        312     POP_TOP                         
                        314     RERAISE                         0
                        316     COPY                            3
                        318     POP_EXCEPT                      
                        320     RERAISE                         1
                        322     PUSH_NULL                       
                        324     LOAD_CONST                      5: '__pyarmor_exit_23606__'
                        326     LOAD_CONST                      3: b'<COAddr>\x05\x00\x00\x1a\x0c\x01\x00\x00\x00\x00\x00\x00\x00\x00\x00\x00\x00\x00\x00\x00'
                        328     BUILD_TUPLE                     1
                        330     CALL_FUNCTION_EX                0
                        332     POP_TOP                         
                        334     RETURN_VALUE                    
                    [Exception Table]
                        28 to 274 -> 294 [0] 
                        294 to 316 -> 316 [1] lasti
                [Code]
                    File Name: <frozen multithon.sessions.memory>
                    Object Name: get_file
                    Qualified Name: MemorySession.get_file
                    Arg Count: 4
                    Pos Only Arg Count: 0
                    KW Only Arg Count: 0
                    Stack Size: 5
                    Flags: 0x20000003 (CO_OPTIMIZED | CO_NEWLOCALS | CO_PYARMOR_OBFUSCATED)
                    [Names]
                        '_SentFileType'
                        'from_type'
                        '_files'
                        'KeyError'
                    [Locals+Names]
                        'self'
                        'md5_digest'
                        'file_size'
                        'cls'
                        '__assert_armored__'
                        '_var_var_25'
                    [Constants]
                        None
                        '__pyarmor_assert_23607__'
                        '__pyarmor_enter_23608__'
                        b'<COAddr>\x05\x00\x00\x1a\x9a\x00\x00\x00\x00\x00\x00\x00\x00\x00\x00\x00\x00\x00\x00\x00'
                        '__pyarmor_exit_23609__'
                    [Disassembly]
                        0       NOP                             
                        2       NOP                             
                        4       PUSH_NULL                       
                        6       LOAD_CONST                      2: '__pyarmor_enter_23608__'
                        8       LOAD_CONST                      3: b'<COAddr>\x05\x00\x00\x1a\x9a\x00\x00\x00\x00\x00\x00\x00\x00\x00\x00\x00\x00\x00\x00\x00'
                        10      BUILD_TUPLE                     1
                        12      CALL_FUNCTION_EX                0
                        14      POP_TOP                         
                        16      RESUME                          0
                        18      NOP                             
                        20      NOP                             
                        22      NOP                             
                        24      NOP                             
                        26      NOP                             
                        28      LOAD_FAST                       1: md5_digest
                        30      LOAD_FAST                       2: file_size
                        32      LOAD_GLOBAL                     0: _SentFileType
                        42      LOAD_ATTR                       3: from_type
                        62      LOAD_FAST                       3: cls
                        64      CALL                            1
                        72      BUILD_TUPLE                     3
                        74      STORE_FAST                      5: _var_var_25
                        76      NOP                             
                        78      PUSH_NULL                       
                        80      LOAD_FAST                       3: cls
                        82      LOAD_FAST                       0: self
                        84      LOAD_ATTR                       4: _files
                        104     LOAD_FAST                       5: _var_var_25
                        106     BINARY_SUBSCR                   
                        110     CALL_FUNCTION_EX                0
                        112     NOP                             
                        114     NOP                             
                        116     NOP                             
                        118     JUMP_FORWARD                    44 (to 208)
                        120     CALL                            1
                        128     POP_TOP                         
                        130     RETURN_VALUE                    
                        132     PUSH_EXC_INFO                   
                        134     LOAD_GLOBAL                     6: KeyError
                        144     CHECK_EXC_MATCH                 
                        146     POP_JUMP_IF_FALSE               12 (to 172)
                        148     POP_TOP                         
                        150     POP_EXCEPT                      
                        152     LOAD_CONST                      0: None
                        154     NOP                             
                        156     NOP                             
                        158     NOP                             
                        160     JUMP_FORWARD                    23 (to 208)
                        168     POP_TOP                         
                        170     RETURN_CONST                    0: None
                        172     RERAISE                         0
                        174     COPY                            3
                        176     POP_EXCEPT                      
                        178     RERAISE                         1
                        180     PUSH_EXC_INFO                   
                        182     PUSH_NULL                       
                        184     LOAD_CONST                      4: '__pyarmor_exit_23609__'
                        186     NOP                             
                        188     LOAD_CONST                      3: b'<COAddr>\x05\x00\x00\x1a\x9a\x00\x00\x00\x00\x00\x00\x00\x00\x00\x00\x00\x00\x00\x00\x00'
                        190     CALL                            1
                        198     POP_TOP                         
                        200     RERAISE                         0
                        202     COPY                            3
                        204     POP_EXCEPT                      
                        206     RERAISE                         1
                        208     PUSH_NULL                       
                        210     LOAD_CONST                      4: '__pyarmor_exit_23609__'
                        212     LOAD_CONST                      3: b'<COAddr>\x05\x00\x00\x1a\x9a\x00\x00\x00\x00\x00\x00\x00\x00\x00\x00\x00\x00\x00\x00\x00'
                        214     BUILD_TUPLE                     1
                        216     CALL_FUNCTION_EX                0
                        218     POP_TOP                         
                        220     RETURN_VALUE                    
                    [Exception Table]
                        28 to 76 -> 180 [0] 
                        78 to 112 -> 132 [0] 
                        132 to 150 -> 174 [1] lasti
                        150 to 152 -> 180 [0] 
                        172 to 174 -> 174 [1] lasti
                        174 to 180 -> 180 [0] 
                        180 to 202 -> 202 [1] lasti
                '__pyarmor_exit_23531__'
                (
                    True
                )
            [Disassembly]
                0       MAKE_CELL                       0: __class__
                2       NOP                             
                4       LOAD_NAME                       0: __name__
                6       STORE_NAME                      1: __module__
                8       LOAD_CONST                      0: 'MemorySession'
                10      STORE_NAME                      2: __qualname__
                12      NOP                             
                14      PUSH_NULL                       
                16      LOAD_CONST                      2: '__pyarmor_enter_23530__'
                18      LOAD_CONST                      3: b'<COAddr>\x05\x00\x00$6\x01\x00\x00\x00\x00\x00\x00\x00\x00\x00\x00\x00\x00\x00\x00'
                20      BUILD_TUPLE                     1
                22      CALL_FUNCTION_EX                0
                24      POP_TOP                         
                26      RESUME                          0
                28      NOP                             
                30      NOP                             
                32      NOP                             
                34      NOP                             
                36      NOP                             
                38      LOAD_CLOSURE                    0: __class__
                40      BUILD_TUPLE                     1
                42      LOAD_CONST                      4: <CODE> __init__
                44      MAKE_FUNCTION                   8
                46      STORE_NAME                      4: __init__
                48      LOAD_CONST                      5: <CODE> set_dc
                50      MAKE_FUNCTION                   0
                52      STORE_NAME                      5: set_dc
                54      LOAD_NAME                       6: property
                56      LOAD_CONST                      6: <CODE> dc_id
                58      MAKE_FUNCTION                   0
                60      CALL                            0
                68      STORE_NAME                      7: dc_id
                70      LOAD_NAME                       6: property
                72      LOAD_CONST                      7: <CODE> server_address
                74      MAKE_FUNCTION                   0
                76      CALL                            0
                84      STORE_NAME                      8: server_address
                86      LOAD_NAME                       6: property
                88      LOAD_CONST                      8: <CODE> port
                90      MAKE_FUNCTION                   0
                92      CALL                            0
                100     STORE_NAME                      9: port
                102     LOAD_NAME                       6: property
                104     LOAD_CONST                      9: <CODE> auth_key
                106     MAKE_FUNCTION                   0
                108     CALL                            0
                116     STORE_NAME                      10: auth_key
                118     LOAD_NAME                       10: auth_key
                120     LOAD_ATTR                       22: setter
                140     LOAD_CONST                      10: <CODE> auth_key
                142     MAKE_FUNCTION                   0
                144     CALL                            0
                152     STORE_NAME                      10: auth_key
                154     LOAD_NAME                       6: property
                156     LOAD_CONST                      11: <CODE> takeout_id
                158     MAKE_FUNCTION                   0
                160     CALL                            0
                168     STORE_NAME                      12: takeout_id
                170     LOAD_NAME                       12: takeout_id
                172     LOAD_ATTR                       22: setter
                192     LOAD_CONST                      12: <CODE> takeout_id
                194     MAKE_FUNCTION                   0
                196     CALL                            0
                204     STORE_NAME                      12: takeout_id
                206     LOAD_CONST                      13: <CODE> get_update_state
                208     MAKE_FUNCTION                   0
                210     STORE_NAME                      13: get_update_state
                212     LOAD_CONST                      14: <CODE> set_update_state
                214     MAKE_FUNCTION                   0
                216     STORE_NAME                      14: set_update_state
                218     LOAD_CONST                      15: <CODE> get_update_states
                220     MAKE_FUNCTION                   0
                222     STORE_NAME                      15: get_update_states
                224     LOAD_CONST                      16: <CODE> close
                226     MAKE_FUNCTION                   0
                228     STORE_NAME                      16: close
                230     LOAD_CONST                      17: <CODE> save
                232     MAKE_FUNCTION                   0
                234     STORE_NAME                      17: save
                236     LOAD_CONST                      18: <CODE> delete
                238     MAKE_FUNCTION                   0
                240     STORE_NAME                      18: delete
                242     LOAD_NAME                       19: staticmethod
                244     LOAD_CONST                      19: <CODE> _entity_values_to_row
                246     MAKE_FUNCTION                   0
                248     CALL                            0
                256     STORE_NAME                      20: _entity_values_to_row
                258     LOAD_CONST                      20: <CODE> _entity_to_row
                260     MAKE_FUNCTION                   0
                262     STORE_NAME                      21: _entity_to_row
                264     LOAD_CONST                      21: <CODE> _entities_to_rows
                266     MAKE_FUNCTION                   0
                268     STORE_NAME                      22: _entities_to_rows
                270     LOAD_CONST                      22: <CODE> process_entities
                272     MAKE_FUNCTION                   0
                274     STORE_NAME                      23: process_entities
                276     LOAD_CONST                      23: <CODE> get_entity_rows_by_phone
                278     MAKE_FUNCTION                   0
                280     STORE_NAME                      24: get_entity_rows_by_phone
                282     LOAD_CONST                      24: <CODE> get_entity_rows_by_username
                284     MAKE_FUNCTION                   0
                286     STORE_NAME                      25: get_entity_rows_by_username
                288     LOAD_CONST                      25: <CODE> get_entity_rows_by_name
                290     MAKE_FUNCTION                   0
                292     STORE_NAME                      26: get_entity_rows_by_name
                294     LOAD_CONST                      31: (True,)
                296     LOAD_CONST                      26: <CODE> get_entity_rows_by_id
                298     MAKE_FUNCTION                   1
                300     STORE_NAME                      27: get_entity_rows_by_id
                302     LOAD_CONST                      27: <CODE> get_input_entity
                304     MAKE_FUNCTION                   0
                306     STORE_NAME                      28: get_input_entity
                308     LOAD_CONST                      28: <CODE> cache_file
                310     MAKE_FUNCTION                   0
                312     STORE_NAME                      29: cache_file
                314     LOAD_CONST                      29: <CODE> get_file
                316     MAKE_FUNCTION                   0
                318     STORE_NAME                      30: get_file
                320     LOAD_CLOSURE                    0: __class__
                322     COPY                            1
                324     STORE_NAME                      31: __classcell__
                326     NOP                             
                328     NOP                             
                330     NOP                             
                332     JUMP_FORWARD                    20 (to 374)
                336     POP_TOP                         
                338     LOAD_CLOSURE                    0: __class__
                340     COPY                            1
                342     STORE_NAME                      31: __classcell__
                344     RETURN_VALUE                    
                346     PUSH_EXC_INFO                   
                348     PUSH_NULL                       
                350     LOAD_CONST                      30: '__pyarmor_exit_23531__'
                352     NOP                             
                354     LOAD_CONST                      3: b'<COAddr>\x05\x00\x00$6\x01\x00\x00\x00\x00\x00\x00\x00\x00\x00\x00\x00\x00\x00\x00'
                356     CALL                            1
                364     POP_TOP                         
                366     RERAISE                         0
                368     COPY                            3
                370     POP_EXCEPT                      
                372     RERAISE                         1
                374     PUSH_NULL                       
                376     LOAD_CONST                      30: '__pyarmor_exit_23531__'
                378     LOAD_CONST                      3: b'<COAddr>\x05\x00\x00$6\x01\x00\x00\x00\x00\x00\x00\x00\x00\x00\x00\x00\x00\x00\x00'
                380     BUILD_TUPLE                     1
                382     CALL_FUNCTION_EX                0
                384     POP_TOP                         
                386     RETURN_VALUE                    
            [Exception Table]
                38 to 320 -> 346 [0] 
                346 to 368 -> 368 [1] lasti
        'MemorySession'
        '__pyarmor_exit_23522__'
        None
    [Disassembly]
        0       NOP                             
        2       NOP                             
        4       PUSH_NULL                       
        6       LOAD_CONST                      1: '__pyarmor_enter_23521__'
        8       LOAD_CONST                      2: b'<COAddr>\x07\x00\x00\x1a\x98\x00\x00\x00\x00\x00\x00\x00\x00\x00\x00\x00\x00\x00\x00\x00'
        10      BUILD_TUPLE                     1
        12      CALL_FUNCTION_EX                0
        14      POP_TOP                         
        16      RESUME                          0
        18      NOP                             
        20      NOP                             
        22      NOP                             
        24      NOP                             
        26      LOAD_CONST                      3: 0
        28      LOAD_CONST                      4: ('Enum',)
        30      IMPORT_NAME                     1: enum
        32      IMPORT_FROM                     2: Enum
        34      STORE_NAME                      2: Enum
        36      POP_TOP                         
        38      LOAD_CONST                      5: 1
        40      LOAD_CONST                      6: ('Session',)
        42      IMPORT_NAME                     3: abstract
        44      IMPORT_FROM                     4: Session
        46      STORE_NAME                      4: Session
        48      POP_TOP                         
        50      LOAD_CONST                      7: 2
        52      LOAD_CONST                      8: ('utils',)
        54      IMPORT_NAME                     5: 
        56      IMPORT_FROM                     6: utils
        58      STORE_NAME                      6: utils
        60      POP_TOP                         
        62      LOAD_CONST                      7: 2
        64      LOAD_CONST                      9: ('TLObject',)
        66      IMPORT_NAME                     7: tl
        68      IMPORT_FROM                     8: TLObject
        70      STORE_NAME                      8: TLObject
        72      POP_TOP                         
        74      LOAD_CONST                      7: 2
        76      LOAD_CONST                      10: ('PeerUser', 'PeerChat', 'PeerChannel', 'InputPeerUser', 'InputPeerChat', 'InputPeerChannel', 'InputPhoto', 'InputDocument')
        78      IMPORT_NAME                     9: tl.types
        80      IMPORT_FROM                     10: PeerUser
        82      STORE_NAME                      10: PeerUser
        84      IMPORT_FROM                     11: PeerChat
        86      STORE_NAME                      11: PeerChat
        88      IMPORT_FROM                     12: PeerChannel
        90      STORE_NAME                      12: PeerChannel
        92      IMPORT_FROM                     13: InputPeerUser
        94      STORE_NAME                      13: InputPeerUser
        96      IMPORT_FROM                     14: InputPeerChat
        98      STORE_NAME                      14: InputPeerChat
        100     IMPORT_FROM                     15: InputPeerChannel
        102     STORE_NAME                      15: InputPeerChannel
        104     IMPORT_FROM                     16: InputPhoto
        106     STORE_NAME                      16: InputPhoto
        108     IMPORT_FROM                     17: InputDocument
        110     STORE_NAME                      17: InputDocument
        112     POP_TOP                         
        114     PUSH_NULL                       
        116     LOAD_BUILD_CLASS                
        118     LOAD_CONST                      11: <CODE> _SentFileType
        120     MAKE_FUNCTION                   0
        122     LOAD_CONST                      12: '_SentFileType'
        124     LOAD_NAME                       2: Enum
        126     CALL                            3
        134     STORE_NAME                      18: _SentFileType
        136     PUSH_NULL                       
        138     LOAD_BUILD_CLASS                
        140     LOAD_CONST                      13: <CODE> MemorySession
        142     MAKE_FUNCTION                   0
        144     LOAD_CONST                      14: 'MemorySession'
        146     LOAD_NAME                       4: Session
        148     CALL                            3
        156     STORE_NAME                      19: MemorySession
        158     LOAD_CONST                      16: None
        160     NOP                             
        162     NOP                             
        164     NOP                             
        166     JUMP_FORWARD                    19 (to 206)
        174     POP_TOP                         
        176     RETURN_CONST                    16: None
        178     PUSH_EXC_INFO                   
        180     PUSH_NULL                       
        182     LOAD_CONST                      15: '__pyarmor_exit_23522__'
        184     NOP                             
        186     LOAD_CONST                      2: b'<COAddr>\x07\x00\x00\x1a\x98\x00\x00\x00\x00\x00\x00\x00\x00\x00\x00\x00\x00\x00\x00\x00'
        188     CALL                            1
        196     POP_TOP                         
        198     RERAISE                         0
        200     COPY                            3
        202     POP_EXCEPT                      
        204     RERAISE                         1
        206     PUSH_NULL                       
        208     LOAD_CONST                      15: '__pyarmor_exit_23522__'
        210     LOAD_CONST                      2: b'<COAddr>\x07\x00\x00\x1a\x98\x00\x00\x00\x00\x00\x00\x00\x00\x00\x00\x00\x00\x00\x00\x00'
        212     BUILD_TUPLE                     1
        214     CALL_FUNCTION_EX                0
        216     POP_TOP                         
        218     RETURN_VALUE                    
    [Exception Table]
        26 to 158 -> 178 [0] 
        178 to 200 -> 200 [1] lasti
