#decoded by lolz.live/mrpenny / t.me/zeus_jackpot
# ================================
# Примечания по Pyarmor:
# - Байт-код и объекты кода Pyarmor соответствуют стандартному Python, но присутствуют специальные вызовы функций среды выполнения (runtime) Pyarmor.
# - Вызовы строк — это не ошибки, а маркеры, которые обрабатываются Pyarmor во время выполнения.
#
# Руководство по декомпиляции (без среды выполнения):
# 1. Игнорируйте зашифрованные байты после `#`; используйте только строку до `#`.
# 2. Удалите "__pyarmor_enter_xxx__"(b"<COAddr>...") и "__pyarmor_leave_xxx__"(b"<COAddr>...") (пролог/эпилог).
# 3. "__pyarmor_assert_xxx__"(A) не является настоящим оператором assert.
#    - Если A — это имя или читаемая строка: замените на A.
#    - Если A — это (X, "Y"): замените на X.Y.
#    - Если A — это (X, "Y", Z): замените на X.Y = Z.
#    - В противном случае: выберите наиболее подходящую/логичную замену.
# 4. "__pyarmor_bcc_xxx__"(...) указывает на машинный (нативный) код; тело функции недоступно. Добавьте комментарий.
# ================================

[Code]
    File Name: <frozen multithon.sessions.sqlite>
    Object Name: <module>
    Qualified Name: <module>
    Arg Count: 0
    Pos Only Arg Count: 0
    KW Only Arg Count: 0
    Stack Size: 5
    Flags: 0x20000000 (CO_PYARMOR_OBFUSCATED)
    [Names]
        '__assert_armored__'
        'datetime'
        'os'
        'time'
        'tl'
        'types'
        'memory'
        'MemorySession'
        '_SentFileType'
        ''
        'utils'
        'crypto'
        'AuthKey'
        'tl.types'
        'InputPhoto'
        'InputDocument'
        'PeerUser'
        'PeerChat'
        'PeerChannel'
        'sqlite3'
        'sqlite3_err'
        'ImportError'
        'e'
        'type'
        'EXTENSION'
        'CURRENT_VERSION'
        'SQLiteSession'
    [Locals+Names]
    [Constants]
        '__pyarmor_assert_23610__'
        '__pyarmor_enter_23611__'
        b'<COAddr>\x05\x00\x00\x1a\xe0\x00\x00\x00\x00\x00\x00\x00\x00\x00\x00\x00\x00\x00\x00\x00'
        0
        None
        2
        (
            'types'
        )
        1
        (
            'MemorySession'
            '_SentFileType'
        )
        (
            'utils'
        )
        (
            'AuthKey'
        )
        (
            'InputPhoto'
            'InputDocument'
            'PeerUser'
            'PeerChat'
            'PeerChannel'
        )
        '.session'
        7
        [Code]
            File Name: <frozen multithon.sessions.sqlite>
            Object Name: SQLiteSession
            Qualified Name: SQLiteSession
            Arg Count: 0
            Pos Only Arg Count: 0
            KW Only Arg Count: 0
            Stack Size: 5
            Flags: 0x20000000 (CO_PYARMOR_OBFUSCATED)
            [Names]
                '__name__'
                '__module__'
                '__qualname__'
                '__doc__'
                '__assert_armored__'
                '__init__'
                'clone'
                '_upgrade_database'
                'staticmethod'
                '_create_table'
                'set_dc'
                'MemorySession'
                'auth_key'
                'setter'
                'takeout_id'
                '_update_session_table'
                'get_update_state'
                'set_update_state'
                'get_update_states'
                'save'
                '_cursor'
                '_execute'
                'close'
                'delete'
                'classmethod'
                'list_sessions'
                'process_entities'
                'get_entity_rows_by_phone'
                'get_entity_rows_by_username'
                'get_entity_rows_by_name'
                'get_entity_rows_by_id'
                'get_file'
                'cache_file'
                '__classcell__'
            [Locals+Names]
                '__class__'
            [Constants]
                'SQLiteSession'
                'This session contains the required information to login into your\n       Telegram account. NEVER give the saved session file to anyone, since\n       they would gain instant access to all your messages and contacts.\n\n       If you think the session has been compromised, close all the sessions\n       through an official Telegram client to revoke the authorization.\n    '
                '__pyarmor_assert_23613__'
                '__pyarmor_enter_23614__'
                b'<COAddr>\x07\x00\x00(6\x01\x00\x00\x00\x00\x00\x00\x00\x00\x00\x00\x00\x00\x00\x00'
                [Code]
                    File Name: <frozen multithon.sessions.sqlite>
                    Object Name: __init__
                    Qualified Name: SQLiteSession.__init__
                    Arg Count: 2
                    Pos Only Arg Count: 0
                    KW Only Arg Count: 0
                    Stack Size: 10
                    Flags: 0x20000003 (CO_OPTIMIZED | CO_NEWLOCALS | CO_PYARMOR_OBFUSCATED)
                    [Names]
                        'sqlite3'
                        'sqlite3_err'
                        'super'
                        '__init__'
                        'filename'
                        'save_entities'
                        'endswith'
                        'EXTENSION'
                        '_conn'
                        '_cursor'
                        'execute'
                        'fetchone'
                        'CURRENT_VERSION'
                        '_upgrade_database'
                        'save'
                        'int'
                        'time'
                        '_dc_id'
                        '_server_address'
                        '_port'
                        '_takeout_id'
                        'AuthKey'
                        '_auth_key'
                        'close'
                        '_create_table'
                        '_update_session_table'
                    [Locals+Names]
                        'self'
                        'session_id'
                        '__assert_armored__'
                        '_var_var_0'
                        '_var_var_1'
                        '_var_var_2'
                        '_var_var_3'
                        '__class__'
                    [Constants]
                        None
                        '__pyarmor_assert_23616__'
                        '__pyarmor_enter_23617__'
                        b'<COAddr>\x05\x00\x00\x1c\x16\x05\x00\x00\x00\x00\x00\x00\x00\x00\x00\x00\x00\x00\x00\x00'
                        ':memory:'
                        True
                        "select name from sqlite_master where type='table' and name='version'"   # b'\x81\xf1\x1d\x1f6\xf9\xaa\x92\x15\xfb\x00\xc5,\xea\xea\x8a\x02\x1d\xa8\xb6\xa6\xc2Z\xc9:b\xa2O\x14\xb4\x0c\xa5-Z%\x1f\x9d\x8a\xa07\x08\xec\xa5\x1a\xc9\xd9\rK2\xaa\x16\xfa\x89tF\xe36\xe6\x9e@_]4ADA\n\x8d\x9a'
                        'select version from version'   # b'\x81\xf1\x1d\x1f6\xf9\xaa\x92\r\xff\x1f\xd3e\xe3\xf6\xc5\tO\xb4\xaa\xea\xddK\xde\x16f\xacR'
                        0
                        (
                            'old'
                        )
                        'delete from version'   # b'\x81\xe6\x1d\x1f6\xee\xbb\x92\x1d\xe8\x02\xcd,\xfa\xfd\x97\x1cT\xb4\xa9'
                        'insert into version values (?)'   # b'\x81\xeb\x16\x006\xe8\xaa\x92\x12\xf4\x19\xcf,\xfa\xfd\x97\x1cT\xb4\xa9\xea\xddO\xc0\x10j\xb0\x1cH\xeeW'
                        'delete from entities where date < '   # b'\x81\xe6\x1d\x1f6\xee\xbb\x92\x1d\xe8\x02\xcd,\xe9\xf6\x91\x06I\xb2\xa2\xb9\x8bY\xc4\x00}\xa6\x1c\x04\xb0\n\xe0z\x0e`'
                        432000
                        'delete from update_state'   # b'\x81\xe6\x1d\x1f6\xee\xbb\x92\x1d\xe8\x02\xcd,\xf9\xe8\x81\x0eI\xbe\x98\xb9\xdfO\xd8\x00'
                        'select * from sessions'   # b'\x81\xf1\x1d\x1f6\xf9\xaa\x92Q\xba\x0b\xd2c\xe1\xb8\x96\nN\xa8\xae\xa5\xc5]'
                        (
                            'data'
                        )
                        'version (version integer primary key)'   # b'\x81\xf4\x1d\x01 \xf3\xb1\xdc[\xb2\x1b\xc5~\xff\xf1\x8a\x01\x1d\xb2\xa9\xbe\xceI\xc9\x17/\xb3N\t\xbc\x1f\xf7#\x12+\x08\x81\x83'
                        'sessions (\n                    dc_id integer primary key,\n                    server_address text,\n                    port integer,\n                    auth_key blob,\n                    takeout_id integer\n                )'   # b'\x81\xf1\x1d\x00 \xf3\xb1\xdc\x08\xbaE\xaa,\xac\xb8\xc5O\x1d\xfb\xe7\xea\x8b\x0e\x8cE/\xe3\x1c@\xf1^\xa5>Q\x1f\x04\x9c\x8a\xbd \x0c\xec\xffX\xcf\x98\x1fU>\xe0W\xe9\x9e0\r\xe8.\xa7\xf1]X\x0bq\x13\x17\x08E\xc3\x9dw\xac\xff\xd3"|~\x00\xf9H\x82\xa4\x95\x92\xac\xad0\x03E\xc0\xa5\x88\xff\x8c1\xcd\xb6\xfcD\xf1\x19{Hd|\x0f_\xf8\xc2\r\xa7\xbd{\xf2z\xf2X8\xb4\x15KcCxb\xb9K\xb1\xf9\xee\xa8\x17\xb2K\xdcQ\xccq\x15T\xb9\xfa|\x1c\xf88\xf0\xa6\x9c%\x17\x89 \xbd\xb2\xac\x1e\xf5\xc7\xc3\xdc\x92Fg"\xce\xa3\xb0[\xed\xde!RDj\x1c\xa5QZ\xfbrb\xde7\x95[5Q\\\x11\x1b\xa3Ok\xcb\xfeD\ns-\xa0l\x0c\xa4\x0c\x8e\xb6\x96S,\x8b9_;j*\xf3\x9d\xabD\\b\x96\xdb\xa2\xab'
                        'entities (\n                    id integer primary key,\n                    hash integer not null,\n                    username text,\n                    phone integer,\n                    name text,\n                    date integer\n                )'   # b'\x81\xe7\x16\x07:\xee\xb7\xd7\x08\xbaE\xaa,\xac\xb8\xc5O\x1d\xfb\xe7\xea\x8b\x0e\x8cE/\xe3\x1c@\xf1^\xa53V`\x04\x96\xde\xb1)\x1d\xfb\xb8M\xcf\xd1\x02F%\xf4\x16\xf0\x82iJ\x87w\xab\xdb]X\x0bq\x13\x17\x08E\xc3\x9dw\xac\xff\xd3"|~H\xb8\x1b\x99\xe1\x8e\x8a\xbd\xba\x08\x07S\x84\xb9\x82\xf8\xdf\x7f\xcc\xbf\xe8\x1c\xd73{Hd|\x0f_\xf8\xc2\r\xa7\xbd{\xf2z\xf2X8\xb4\x15\x1e`Ixx\xf8O\xba\xad\xff\xaa\n\xb4K\xdcQ\xccq\x15T\xb9\xfa|\x1c\xf88\xf0\xa6\x9c%\x17\x89 \xbd\xb2\xbd\x03\xee\xc1\xf9\x97\x9eQ3%\xc5\xa9\xa0[\xed\xde!RDj\x1c\xa5QZ\xfbrb\xde7\x95[5Q\\\x11\x01\xa3Ik\x84\xffU-ne\x8a%B\xf0I\xc9\xf3\xc4y,\x8b9_;j*\xf3\x9d\xabD\\&\xd7\x8f\xe7\xa2\x1e\x93:\x1f\x93\xef\x14)\x08c\xe9_\x02c\x95)\xe6\xba\xd0V|\x8bT\x90\xbc'
                        'sent_files (\n                    md5_digest blob,\n                    file_size integer,\n                    type integer,\n                    id integer,\n                    hash integer,\n                    primary key(md5_digest, file_size, type)\n                )'   # b'\x81\xf1\x1d\x1d\'\xc5\xb8\xdb\x17\xff\x1e\x80$\x86\xb8\xc5O\x1d\xfb\xe7\xea\x8b\x0e\x8cE/\xe3\x1c@\xf1^\xa5z\x12-\t\xcd\xf5\xb0\'\x1f\xec\xebI\x9d\xda\x03H5\xa1<\xbb\xc70F\xadw\xab\xdb]X\x0bq\x13\x17\x08E\xc3\x9dw\xac\xb9\x9an9\x01S\xb0\x12\x94\xe1\x8e\x8a\xbd\xba\x08\x07S\x88\xdd\xcd\xac\xdf1\x99\xf3\xa4\x10\xfd3{Hd|\x0f_\xf8\xc2\r\xa7\xe9"\xa2?\xf2\x11v\xe0P\x0cv^&\x1c\xb9\x02\xff\xad\xab\xefR\xe0G\xf6Q\xccq\x15T\xb9\xfa|\x1c\xf8q\xb4\xa6\xd5kC\xccg\xf8\xe0\xe1a\xa1\x8f\xbc\x97\xd7\x1fg`\x82\xec\xf2W\xc7\xde!RDj\x1c\xa5\x19\x1b\xa8:b\x97y\xc1\x1er\x14\x0e\x1de\xe2\x04.\x84\xab\x10u:i\xa0%B\xf0I\xc9\xf3\xc4y,\x8bi\rr\'k\xa1\xc4\xab\x0f\x19;\x9e\x96\xe6\xb7(\x99\'\x1d\x91\xf9\x12\x0f\x08%\xa0\x13G\x1c\xc6`\xbc\xff\xdcV(\xd2\x04\xd5\xbcpl\xb1)\xb8\xf5\xedV\x12&\x1e\x98&\xe0b\xbe]\x00'
                        'update_state (\n                    id integer primary key,\n                    pts integer,\n                    qts integer,\n                    date integer,\n                    seq integer\n                )'   # b'\x81\xf7\x08\x172\xee\xbb\xed\x08\xee\x0c\xd4i\xac\xb0\xefO\x1d\xfb\xe7\xea\x8b\x0e\x8cE/\xe3\x1c@\xf1^\xa5z\x12`M\x91\xce\xf4\'\x16\xfd\xfdZ\xd8\xcaOW%\xe4[\xfa\x95iF\xe62\xf2\xd7wX\x0bq\x13\x17\x08E\xc3\x9dw\xac\xff\xd3"|~\x00\xf9H\xd1\xb1\x93\x97\xe9\xb6\x01\x16D\xc3\xb2\x9f\xa0\xf51\x99\xf3\xa4\x10\xfd3{Hd|\x0f_\xf8\xc2\r\xa7\xbd{\xf2+\xa6\x0b8\xfd[\x1fvKod\xb5(\xff\xad\xab\xefR\xe0G\xf6Q\xccq\x15T\xb9\xfa|\x1c\xf88\xf0\xe2\xddqR\x89i\xf3\xe6\xa8\x0c\xe4\xdd\xb0\xbd\xd7\x1fg`\x82\xec\xf2W\xc7\xde!RDj\x1c\xa5QZ\xfbr1\x9bf\x95\x12{\x05\x19V\n\xb0..\x84\xab\x10u:i\xa0%B\xf0I\xc9\xf3\xc4y%'
                        '__pyarmor_exit_23618__'
                    [Disassembly]
                        0       COPY_FREE_VARS                  1
                        2       NOP                             
                        4       NOP                             
                        6       PUSH_NULL                       
                        8       LOAD_CONST                      2: '__pyarmor_enter_23617__'
                        10      LOAD_CONST                      3: b'<COAddr>\x05\x00\x00\x1c\x16\x05\x00\x00\x00\x00\x00\x00\x00\x00\x00\x00\x00\x00\x00\x00'
                        12      BUILD_TUPLE                     1
                        14      CALL_FUNCTION_EX                0
                        16      POP_TOP                         
                        18      RESUME                          0
                        20      NOP                             
                        22      NOP                             
                        24      NOP                             
                        26      NOP                             
                        28      NOP                             
                        30      LOAD_GLOBAL                     0: sqlite3
                        40      POP_JUMP_IF_NOT_NONE            6 (to 54)
                        42      LOAD_GLOBAL                     2: sqlite3_err
                        52      RAISE_VARARGS                   1
                        54      LOAD_GLOBAL                     4: super
                        64      LOAD_DEREF                      7: __class__
                        66      LOAD_FAST                       0: self
                        68      LOAD_SUPER_ATTR                 13: __init__
                        72      CALL                            0
                        80      POP_TOP                         
                        82      LOAD_CONST                      4: ':memory:'
                        84      LOAD_FAST                       0: self
                        86      STORE_ATTR                      4: filename
                        96      LOAD_CONST                      5: True
                        98      LOAD_FAST                       0: self
                        100     STORE_ATTR                      5: save_entities
                        110     LOAD_FAST                       1: session_id
                        112     POP_JUMP_IF_FALSE               63 (to 240)
                        114     LOAD_FAST                       1: session_id
                        116     LOAD_FAST                       0: self
                        118     STORE_ATTR                      4: filename
                        128     LOAD_FAST                       0: self
                        130     LOAD_ATTR                       8: filename
                        150     LOAD_ATTR                       13: endswith
                        170     LOAD_GLOBAL                     14: EXTENSION
                        180     CALL                            1
                        188     POP_JUMP_IF_TRUE                25 (to 240)
                        190     LOAD_FAST                       0: self
                        192     COPY                            1
                        194     LOAD_ATTR                       8: filename
                        214     LOAD_GLOBAL                     14: EXTENSION
                        224     BINARY_OP                       13 (+=)
                        228     SWAP                            2
                        230     STORE_ATTR                      4: filename
                        240     LOAD_CONST                      0: None
                        242     LOAD_FAST                       0: self
                        244     STORE_ATTR                      8: _conn
                        254     LOAD_FAST                       0: self
                        256     LOAD_ATTR                       19: _cursor
                        276     CALL                            0
                        284     STORE_FAST                      3: _var_var_0
                        286     LOAD_FAST                       3: _var_var_0
                        288     LOAD_ATTR                       21: execute
                        308     PUSH_NULL                       
                        310     LOAD_CONST                      1: '__pyarmor_assert_23616__'
                        312     LOAD_CONST                      6: "select name from sqlite_master where type='table' and name='version'"   # b'\x81\xf1\x1d\x1f6\xf9\xaa\x92\x15\xfb\x00\xc5,\xea\xea\x8a\x02\x1d\xa8\xb6\xa6\xc2Z\xc9:b\xa2O\x14\xb4\x0c\xa5-Z%\x1f\x9d\x8a\xa07\x08\xec\xa5\x1a\xc9\xd9\rK2\xaa\x16\xfa\x89tF\xe36\xe6\x9e@_]4ADA\n\x8d\x9a'
                        314     CALL                            1
                        322     CALL                            1
                        330     POP_TOP                         
                        332     LOAD_FAST                       3: _var_var_0
                        334     LOAD_ATTR                       23: fetchone
                        354     CALL                            0
                        362     POP_JUMP_IF_FALSE               336 (to 1038)
                        366     LOAD_FAST                       3: _var_var_0
                        368     LOAD_ATTR                       21: execute
                        388     PUSH_NULL                       
                        390     LOAD_CONST                      1: '__pyarmor_assert_23616__'
                        392     LOAD_CONST                      7: 'select version from version'   # b'\x81\xf1\x1d\x1f6\xf9\xaa\x92\r\xff\x1f\xd3e\xe3\xf6\xc5\tO\xb4\xaa\xea\xddK\xde\x16f\xacR'
                        394     CALL                            1
                        402     CALL                            1
                        410     POP_TOP                         
                        412     LOAD_FAST                       3: _var_var_0
                        414     LOAD_ATTR                       23: fetchone
                        434     CALL                            0
                        442     LOAD_CONST                      8: 0
                        444     BINARY_SUBSCR                   
                        448     STORE_FAST                      4: _var_var_1
                        450     LOAD_FAST                       4: _var_var_1
                        452     LOAD_GLOBAL                     24: CURRENT_VERSION
                        462     COMPARE_OP                      2 (<)
                        466     POP_JUMP_IF_FALSE               86 (to 640)
                        468     LOAD_FAST                       0: self
                        470     LOAD_ATTR                       27: _upgrade_database
                        490     LOAD_FAST                       4: _var_var_1
                        492     KW_NAMES                        9: ('old',)
                        494     CALL                            1
                        502     POP_TOP                         
                        504     LOAD_FAST                       3: _var_var_0
                        506     LOAD_ATTR                       21: execute
                        526     PUSH_NULL                       
                        528     LOAD_CONST                      1: '__pyarmor_assert_23616__'
                        530     LOAD_CONST                      10: 'delete from version'   # b'\x81\xe6\x1d\x1f6\xee\xbb\x92\x1d\xe8\x02\xcd,\xfa\xfd\x97\x1cT\xb4\xa9'
                        532     CALL                            1
                        540     CALL                            1
                        548     POP_TOP                         
                        550     LOAD_FAST                       3: _var_var_0
                        552     LOAD_ATTR                       21: execute
                        572     PUSH_NULL                       
                        574     LOAD_CONST                      1: '__pyarmor_assert_23616__'
                        576     LOAD_CONST                      11: 'insert into version values (?)'   # b'\x81\xeb\x16\x006\xe8\xaa\x92\x12\xf4\x19\xcf,\xfa\xfd\x97\x1cT\xb4\xa9\xea\xddO\xc0\x10j\xb0\x1cH\xeeW'
                        578     CALL                            1
                        586     LOAD_GLOBAL                     24: CURRENT_VERSION
                        596     BUILD_TUPLE                     1
                        598     CALL                            2
                        606     POP_TOP                         
                        608     LOAD_FAST                       0: self
                        610     LOAD_ATTR                       29: save
                        630     CALL                            0
                        638     POP_TOP                         
                        640     NOP                             
                        642     LOAD_FAST                       3: _var_var_0
                        644     LOAD_ATTR                       21: execute
                        664     PUSH_NULL                       
                        666     LOAD_CONST                      1: '__pyarmor_assert_23616__'
                        668     LOAD_CONST                      12: 'delete from entities where date < '   # b'\x81\xe6\x1d\x1f6\xee\xbb\x92\x1d\xe8\x02\xcd,\xe9\xf6\x91\x06I\xb2\xa2\xb9\x8bY\xc4\x00}\xa6\x1c\x04\xb0\n\xe0z\x0e`'
                        670     CALL                            1
                        678     LOAD_GLOBAL                     31: NULL + int
                        688     LOAD_GLOBAL                     33: NULL + time
                        698     LOAD_ATTR                       32: time
                        718     CALL                            0
                        726     LOAD_CONST                      13: 432000
                        728     BINARY_OP                       10 (-)
                        732     CALL                            1
                        740     FORMAT_VALUE                    0 (FVC_NONE)
                        742     BUILD_STRING                    2
                        744     CALL                            1
                        752     POP_TOP                         
                        754     LOAD_FAST                       3: _var_var_0
                        756     LOAD_ATTR                       21: execute
                        776     PUSH_NULL                       
                        778     LOAD_CONST                      1: '__pyarmor_assert_23616__'
                        780     LOAD_CONST                      14: 'delete from update_state'   # b'\x81\xe6\x1d\x1f6\xee\xbb\x92\x1d\xe8\x02\xcd,\xf9\xe8\x81\x0eI\xbe\x98\xb9\xdfO\xd8\x00'
                        782     CALL                            1
                        790     CALL                            1
                        798     POP_TOP                         
                        800     LOAD_FAST                       0: self
                        802     LOAD_ATTR                       29: save
                        822     CALL                            0
                        830     POP_TOP                         
                        832     LOAD_FAST                       3: _var_var_0
                        834     LOAD_ATTR                       21: execute
                        854     PUSH_NULL                       
                        856     LOAD_CONST                      1: '__pyarmor_assert_23616__'
                        858     LOAD_CONST                      15: 'select * from sessions'   # b'\x81\xf1\x1d\x1f6\xf9\xaa\x92Q\xba\x0b\xd2c\xe1\xb8\x96\nN\xa8\xae\xa5\xc5]'
                        860     CALL                            1
                        868     CALL                            1
                        876     POP_TOP                         
                        878     LOAD_FAST                       3: _var_var_0
                        880     LOAD_ATTR                       23: fetchone
                        900     CALL                            0
                        908     STORE_FAST                      5: _var_var_2
                        910     LOAD_FAST                       5: _var_var_2
                        912     POP_JUMP_IF_FALSE               45 (to 1004)
                        914     LOAD_FAST                       5: _var_var_2
                        916     UNPACK_SEQUENCE                 5
                        920     LOAD_FAST                       0: self
                        922     STORE_ATTR                      17: _dc_id
                        932     LOAD_FAST                       0: self
                        934     STORE_ATTR                      18: _server_address
                        944     LOAD_FAST                       0: self
                        946     STORE_ATTR                      19: _port
                        956     STORE_FAST                      6: _var_var_3
                        958     LOAD_FAST                       0: self
                        960     STORE_ATTR                      20: _takeout_id
                        970     LOAD_GLOBAL                     43: NULL + AuthKey
                        980     LOAD_FAST                       6: _var_var_3
                        982     KW_NAMES                        16: ('data',)
                        984     CALL                            1
                        992     LOAD_FAST                       0: self
                        994     STORE_ATTR                      22: _auth_key
                        1004    LOAD_FAST                       3: _var_var_0
                        1006    LOAD_ATTR                       47: close
                        1026    CALL                            0
                        1034    POP_TOP                         
                        1036    JUMP_FORWARD                    129 (to 1296)
                        1038    LOAD_FAST                       0: self
                        1040    LOAD_ATTR                       49: _create_table
                        1060    LOAD_FAST                       3: _var_var_0
                        1062    PUSH_NULL                       
                        1064    LOAD_CONST                      1: '__pyarmor_assert_23616__'
                        1066    LOAD_CONST                      17: 'version (version integer primary key)'   # b'\x81\xf4\x1d\x01 \xf3\xb1\xdc[\xb2\x1b\xc5~\xff\xf1\x8a\x01\x1d\xb2\xa9\xbe\xceI\xc9\x17/\xb3N\t\xbc\x1f\xf7#\x12+\x08\x81\x83'
                        1068    CALL                            1
                        1076    PUSH_NULL                       
                        1078    LOAD_CONST                      1: '__pyarmor_assert_23616__'
                        1080    LOAD_CONST                      18: 'sessions (\n                    dc_id integer primary key,\n                    server_address text,\n                    port integer,\n                    auth_key blob,\n                    takeout_id integer\n                )'   # b'\x81\xf1\x1d\x00 \xf3\xb1\xdc\x08\xbaE\xaa,\xac\xb8\xc5O\x1d\xfb\xe7\xea\x8b\x0e\x8cE/\xe3\x1c@\xf1^\xa5>Q\x1f\x04\x9c\x8a\xbd \x0c\xec\xffX\xcf\x98\x1fU>\xe0W\xe9\x9e0\r\xe8.\xa7\xf1]X\x0bq\x13\x17\x08E\xc3\x9dw\xac\xff\xd3"|~\x00\xf9H\x82\xa4\x95\x92\xac\xad0\x03E\xc0\xa5\x88\xff\x8c1\xcd\xb6\xfcD\xf1\x19{Hd|\x0f_\xf8\xc2\r\xa7\xbd{\xf2z\xf2X8\xb4\x15KcCxb\xb9K\xb1\xf9\xee\xa8\x17\xb2K\xdcQ\xccq\x15T\xb9\xfa|\x1c\xf88\xf0\xa6\x9c%\x17\x89 \xbd\xb2\xac\x1e\xf5\xc7\xc3\xdc\x92Fg"\xce\xa3\xb0[\xed\xde!RDj\x1c\xa5QZ\xfbrb\xde7\x95[5Q\\\x11\x1b\xa3Ok\xcb\xfeD\ns-\xa0l\x0c\xa4\x0c\x8e\xb6\x96S,\x8b9_;j*\xf3\x9d\xabD\\b\x96\xdb\xa2\xab'
                        1082    CALL                            1
                        1090    PUSH_NULL                       
                        1092    LOAD_CONST                      1: '__pyarmor_assert_23616__'
                        1094    LOAD_CONST                      19: 'entities (\n                    id integer primary key,\n                    hash integer not null,\n                    username text,\n                    phone integer,\n                    name text,\n                    date integer\n                )'   # b'\x81\xe7\x16\x07:\xee\xb7\xd7\x08\xbaE\xaa,\xac\xb8\xc5O\x1d\xfb\xe7\xea\x8b\x0e\x8cE/\xe3\x1c@\xf1^\xa53V`\x04\x96\xde\xb1)\x1d\xfb\xb8M\xcf\xd1\x02F%\xf4\x16\xf0\x82iJ\x87w\xab\xdb]X\x0bq\x13\x17\x08E\xc3\x9dw\xac\xff\xd3"|~H\xb8\x1b\x99\xe1\x8e\x8a\xbd\xba\x08\x07S\x84\xb9\x82\xf8\xdf\x7f\xcc\xbf\xe8\x1c\xd73{Hd|\x0f_\xf8\xc2\r\xa7\xbd{\xf2z\xf2X8\xb4\x15\x1e`Ixx\xf8O\xba\xad\xff\xaa\n\xb4K\xdcQ\xccq\x15T\xb9\xfa|\x1c\xf88\xf0\xa6\x9c%\x17\x89 \xbd\xb2\xbd\x03\xee\xc1\xf9\x97\x9eQ3%\xc5\xa9\xa0[\xed\xde!RDj\x1c\xa5QZ\xfbrb\xde7\x95[5Q\\\x11\x01\xa3Ik\x84\xffU-ne\x8a%B\xf0I\xc9\xf3\xc4y,\x8b9_;j*\xf3\x9d\xabD\\&\xd7\x8f\xe7\xa2\x1e\x93:\x1f\x93\xef\x14)\x08c\xe9_\x02c\x95)\xe6\xba\xd0V|\x8bT\x90\xbc'
                        1096    CALL                            1
                        1104    PUSH_NULL                       
                        1106    LOAD_CONST                      1: '__pyarmor_assert_23616__'
                        1108    LOAD_CONST                      20: 'sent_files (\n                    md5_digest blob,\n                    file_size integer,\n                    type integer,\n                    id integer,\n                    hash integer,\n                    primary key(md5_digest, file_size, type)\n                )'   # b'\x81\xf1\x1d\x1d\'\xc5\xb8\xdb\x17\xff\x1e\x80$\x86\xb8\xc5O\x1d\xfb\xe7\xea\x8b\x0e\x8cE/\xe3\x1c@\xf1^\xa5z\x12-\t\xcd\xf5\xb0\'\x1f\xec\xebI\x9d\xda\x03H5\xa1<\xbb\xc70F\xadw\xab\xdb]X\x0bq\x13\x17\x08E\xc3\x9dw\xac\xb9\x9an9\x01S\xb0\x12\x94\xe1\x8e\x8a\xbd\xba\x08\x07S\x88\xdd\xcd\xac\xdf1\x99\xf3\xa4\x10\xfd3{Hd|\x0f_\xf8\xc2\r\xa7\xe9"\xa2?\xf2\x11v\xe0P\x0cv^&\x1c\xb9\x02\xff\xad\xab\xefR\xe0G\xf6Q\xccq\x15T\xb9\xfa|\x1c\xf8q\xb4\xa6\xd5kC\xccg\xf8\xe0\xe1a\xa1\x8f\xbc\x97\xd7\x1fg`\x82\xec\xf2W\xc7\xde!RDj\x1c\xa5\x19\x1b\xa8:b\x97y\xc1\x1er\x14\x0e\x1de\xe2\x04.\x84\xab\x10u:i\xa0%B\xf0I\xc9\xf3\xc4y,\x8bi\rr\'k\xa1\xc4\xab\x0f\x19;\x9e\x96\xe6\xb7(\x99\'\x1d\x91\xf9\x12\x0f\x08%\xa0\x13G\x1c\xc6`\xbc\xff\xdcV(\xd2\x04\xd5\xbcpl\xb1)\xb8\xf5\xedV\x12&\x1e\x98&\xe0b\xbe]\x00'
                        1110    CALL                            1
                        1118    PUSH_NULL                       
                        1120    LOAD_CONST                      1: '__pyarmor_assert_23616__'
                        1122    LOAD_CONST                      21: 'update_state (\n                    id integer primary key,\n                    pts integer,\n                    qts integer,\n                    date integer,\n                    seq integer\n                )'   # b'\x81\xf7\x08\x172\xee\xbb\xed\x08\xee\x0c\xd4i\xac\xb0\xefO\x1d\xfb\xe7\xea\x8b\x0e\x8cE/\xe3\x1c@\xf1^\xa5z\x12`M\x91\xce\xf4\'\x16\xfd\xfdZ\xd8\xcaOW%\xe4[\xfa\x95iF\xe62\xf2\xd7wX\x0bq\x13\x17\x08E\xc3\x9dw\xac\xff\xd3"|~\x00\xf9H\xd1\xb1\x93\x97\xe9\xb6\x01\x16D\xc3\xb2\x9f\xa0\xf51\x99\xf3\xa4\x10\xfd3{Hd|\x0f_\xf8\xc2\r\xa7\xbd{\xf2+\xa6\x0b8\xfd[\x1fvKod\xb5(\xff\xad\xab\xefR\xe0G\xf6Q\xccq\x15T\xb9\xfa|\x1c\xf88\xf0\xe2\xddqR\x89i\xf3\xe6\xa8\x0c\xe4\xdd\xb0\xbd\xd7\x1fg`\x82\xec\xf2W\xc7\xde!RDj\x1c\xa5QZ\xfbr1\x9bf\x95\x12{\x05\x19V\n\xb0..\x84\xab\x10u:i\xa0%B\xf0I\xc9\xf3\xc4y%'
                        1124    CALL                            1
                        1132    CALL                            6
                        1140    POP_TOP                         
                        1142    LOAD_FAST                       3: _var_var_0
                        1144    LOAD_ATTR                       21: execute
                        1164    PUSH_NULL                       
                        1166    LOAD_CONST                      1: '__pyarmor_assert_23616__'
                        1168    LOAD_CONST                      11: 'insert into version values (?)'   # b'\x81\xeb\x16\x006\xe8\xaa\x92\x12\xf4\x19\xcf,\xfa\xfd\x97\x1cT\xb4\xa9\xea\xddO\xc0\x10j\xb0\x1cH\xeeW'
                        1170    CALL                            1
                        1178    LOAD_GLOBAL                     24: CURRENT_VERSION
                        1188    BUILD_TUPLE                     1
                        1190    CALL                            2
                        1198    POP_TOP                         
                        1200    LOAD_FAST                       0: self
                        1202    LOAD_ATTR                       51: _update_session_table
                        1222    CALL                            0
                        1230    POP_TOP                         
                        1232    LOAD_FAST                       3: _var_var_0
                        1234    LOAD_ATTR                       47: close
                        1254    CALL                            0
                        1262    POP_TOP                         
                        1264    LOAD_FAST                       0: self
                        1266    LOAD_ATTR                       29: save
                        1286    CALL                            0
                        1294    POP_TOP                         
                        1296    LOAD_CONST                      0: None
                        1298    NOP                             
                        1300    NOP                             
                        1302    NOP                             
                        1304    JUMP_FORWARD                    26 (to 1358)
                        1312    POP_TOP                         
                        1314    RETURN_CONST                    0: None
                        1316    PUSH_EXC_INFO                   
                        1318    POP_TOP                         
                        1320    POP_EXCEPT                      
                        1322    JUMP_BACKWARD                   246 (to 832)
                        1324    COPY                            3
                        1326    POP_EXCEPT                      
                        1328    RERAISE                         1
                        1330    PUSH_EXC_INFO                   
                        1332    PUSH_NULL                       
                        1334    LOAD_CONST                      22: '__pyarmor_exit_23618__'
                        1336    NOP                             
                        1338    LOAD_CONST                      3: b'<COAddr>\x05\x00\x00\x1c\x16\x05\x00\x00\x00\x00\x00\x00\x00\x00\x00\x00\x00\x00\x00\x00'
                        1340    CALL                            1
                        1348    POP_TOP                         
                        1350    RERAISE                         0
                        1352    COPY                            3
                        1354    POP_EXCEPT                      
                        1356    RERAISE                         1
                        1358    PUSH_NULL                       
                        1360    LOAD_CONST                      22: '__pyarmor_exit_23618__'
                        1362    LOAD_CONST                      3: b'<COAddr>\x05\x00\x00\x1c\x16\x05\x00\x00\x00\x00\x00\x00\x00\x00\x00\x00\x00\x00\x00\x00'
                        1364    BUILD_TUPLE                     1
                        1366    CALL_FUNCTION_EX                0
                        1368    POP_TOP                         
                        1370    RETURN_VALUE                    
                    [Exception Table]
                        30 to 640 -> 1330 [0] 
                        642 to 832 -> 1316 [0] 
                        832 to 1296 -> 1330 [0] 
                        1316 to 1320 -> 1324 [1] lasti
                        1320 to 1330 -> 1330 [0] 
                        1330 to 1352 -> 1352 [1] lasti
                [Code]
                    File Name: <frozen multithon.sessions.sqlite>
                    Object Name: clone
                    Qualified Name: SQLiteSession.clone
                    Arg Count: 2
                    Pos Only Arg Count: 0
                    KW Only Arg Count: 0
                    Stack Size: 5
                    Flags: 0x20000003 (CO_OPTIMIZED | CO_NEWLOCALS | CO_PYARMOR_OBFUSCATED)
                    [Names]
                        'super'
                        'clone'
                        'save_entities'
                    [Locals+Names]
                        'self'
                        'to_instance'
                        '__assert_armored__'
                        '_var_var_4'
                        '__class__'
                    [Constants]
                        None
                        '__pyarmor_assert_23619__'
                        '__pyarmor_enter_23620__'
                        b'<COAddr>\x05\x00\x00\x1cX\x00\x00\x00\x00\x00\x00\x00\x00\x00\x00\x00\x00\x00\x00\x00'
                        '__pyarmor_exit_23621__'
                    [Disassembly]
                        0       COPY_FREE_VARS                  1
                        2       NOP                             
                        4       NOP                             
                        6       PUSH_NULL                       
                        8       LOAD_CONST                      2: '__pyarmor_enter_23620__'
                        10      LOAD_CONST                      3: b'<COAddr>\x05\x00\x00\x1cX\x00\x00\x00\x00\x00\x00\x00\x00\x00\x00\x00\x00\x00\x00\x00'
                        12      BUILD_TUPLE                     1
                        14      CALL_FUNCTION_EX                0
                        16      POP_TOP                         
                        18      RESUME                          0
                        20      NOP                             
                        22      NOP                             
                        24      NOP                             
                        26      NOP                             
                        28      NOP                             
                        30      LOAD_GLOBAL                     0: super
                        40      LOAD_DEREF                      4: __class__
                        42      LOAD_FAST                       0: self
                        44      LOAD_SUPER_ATTR                 5: clone
                        48      LOAD_FAST                       1: to_instance
                        50      CALL                            1
                        58      STORE_FAST                      3: _var_var_4
                        60      LOAD_FAST                       0: self
                        62      LOAD_ATTR                       4: save_entities
                        82      LOAD_FAST                       3: _var_var_4
                        84      STORE_ATTR                      2: save_entities
                        94      LOAD_FAST                       3: _var_var_4
                        96      NOP                             
                        98      NOP                             
                        100     NOP                             
                        102     JUMP_FORWARD                    20 (to 144)
                        104     CALL                            1
                        112     POP_TOP                         
                        114     RETURN_VALUE                    
                        116     PUSH_EXC_INFO                   
                        118     PUSH_NULL                       
                        120     LOAD_CONST                      4: '__pyarmor_exit_23621__'
                        122     NOP                             
                        124     LOAD_CONST                      3: b'<COAddr>\x05\x00\x00\x1cX\x00\x00\x00\x00\x00\x00\x00\x00\x00\x00\x00\x00\x00\x00\x00'
                        126     CALL                            1
                        134     POP_TOP                         
                        136     RERAISE                         0
                        138     COPY                            3
                        140     POP_EXCEPT                      
                        142     RERAISE                         1
                        144     PUSH_NULL                       
                        146     LOAD_CONST                      4: '__pyarmor_exit_23621__'
                        148     LOAD_CONST                      3: b'<COAddr>\x05\x00\x00\x1cX\x00\x00\x00\x00\x00\x00\x00\x00\x00\x00\x00\x00\x00\x00\x00'
                        150     BUILD_TUPLE                     1
                        152     CALL_FUNCTION_EX                0
                        154     POP_TOP                         
                        156     RETURN_VALUE                    
                    [Exception Table]
                        30 to 96 -> 116 [0] 
                        116 to 138 -> 138 [1] lasti
                [Code]
                    File Name: <frozen multithon.sessions.sqlite>
                    Object Name: _upgrade_database
                    Qualified Name: SQLiteSession._upgrade_database
                    Arg Count: 2
                    Pos Only Arg Count: 0
                    KW Only Arg Count: 0
                    Stack Size: 6
                    Flags: 0x20000003 (CO_OPTIMIZED | CO_NEWLOCALS | CO_PYARMOR_OBFUSCATED)
                    [Names]
                        '_cursor'
                        'execute'
                        '_create_table'
                        'close'
                    [Locals+Names]
                        'self'
                        'old'
                        '__assert_armored__'
                        '_var_var_0'
                    [Constants]
                        None
                        '__pyarmor_assert_23622__'
                        '__pyarmor_enter_23623__'
                        b'<COAddr>\x05\x00\x00\x1a\xe6\x01\x00\x00\x00\x00\x00\x00\x00\x00\x00\x00\x00\x00\x00\x00'
                        1
                        2
                        'drop table sent_files'   # b'\x81\xe6\n\x1c#\xba\xaa\xd3\x19\xf6\x08\x80\x7f\xe9\xf6\x910[\xb2\xab\xaf\xd8'
                        'sent_files (\n                md5_digest blob,\n                file_size integer,\n                type integer,\n                id integer,\n                hash integer,\n                primary key(md5_digest, file_size, type)\n            )'   # b"\x81\xf1\x1d\x1d'\xc5\xb8\xdb\x17\xff\x1e\x80$\x86\xb8\xc5O\x1d\xfb\xe7\xea\x8b\x0e\x8cE/\xe3\x1c@\xf1\x13\xe1om$\x04\x9f\xcf\xa7:X\xeb\xf4R\xdf\x94e\x07w\xad\x16\xbb\xc70F\xadw\xab\xdb]X\x0bqU^D\x00\xbc\xce>\xf6\xba\xd3k2*E\xbe\r\x83\xed\xed\xc4\xe9\xffOB\x01\x84\xf7\xcd\xac\xdf1\x99\xf3\xa4\x10\xa9j+\rd5A\x0b\xbd\x85H\xf5\xb1Q\xf2z\xf2X8\xb4\x15K3\x0c*6\xb9\x02\xff\xad\xe2\xabR\xa9\t\xa2\x14\x8b4GX\x93\xfa|\x1c\xf88\xf0\xa6\x9c%\x17\x89 \xbd\xb2\xedK\xe9\xce\xef\xdf\xd7V)4\xc7\xab\xb7\x05\xcb\xf4!RDj\x1c\xa5QZ\xfbrb\xde7\x95[5\x01\x0eX\x02\xa3Vw\x84\xe0U,2$\xe40=\xb4\x00\x8e\xb6\x97- \x8b\x7f\x16w/U\xa0\xd4\xf1\x01Pb\xc2\x82\xf2\xe7^\xf7nZ\xd4\xaaF\x03\x08c\xe9_\x02c\x9c"
                        3
                        'update_state (\n                id integer primary key,\n                pts integer,\n                qts integer,\n                date integer,\n                seq integer\n            )'   # b'\x81\xf7\x08\x172\xee\xbb\xed\x08\xee\x0c\xd4i\xac\xb0\xefO\x1d\xfb\xe7\xea\x8b\x0e\x8cE/\xe3\x1c@\xf1^\xa53V`\x04\x96\xde\xb1)\x1d\xfb\xb8M\xcf\xd1\x02F%\xf4\x16\xf0\x82iJ\x87w\xab\xdb]X\x0bq\x13\x17\x08E\xc3\x9dw\xac\xff\x83v/~I\xb7\x1c\x94\xa6\x82\x96\xe5\xd5OB\x01\x84\xf7\xcd\xac\xdf1\x99\xf3\xa4\x10\xfd3{\x190/\x0f\x16\xb6\x96H\xe0\xf8)\xfeP\xf2X8\xb4\x15K3\x0c*6\xb9\x02\xff\xad\xab\xef\x16\xa1\x13\xb3Q\x85?A\x11\xfe\xbf.\x10\xd28\xf0\xa6\x9c%\x17\x89 \xbd\xb2\xedK\xa1\x8f\xbc\x97\x84Z6`\xcb\xa2\xa6\x12\x80\x9bsxDj\x1c\xa5QZ\xfbrb\xde7\x95R'
                        4
                        'alter table sessions add column takeout_id integer'   # b"\x81\xe3\x14\x076\xe8\xfe\xc6\x1a\xf8\x01\xc5,\xff\xfd\x96\x1cT\xb4\xa9\xb9\x8bO\xc8\x01/\xa0S\x0c\xa4\x13\xebzF!\x06\x9d\xc5\xa1:'\xe0\xfc\x1d\xd4\xd6\x1bB0\xe8D"
                        5
                        'delete from entities'   # b'\x81\xe6\x1d\x1f6\xee\xbb\x92\x1d\xe8\x02\xcd,\xe9\xf6\x91\x06I\xb2\xa2\xb9'
                        6
                        'alter table entities add column date integer'   # b'\x81\xe3\x14\x076\xe8\xfe\xc6\x1a\xf8\x01\xc5,\xe9\xf6\x91\x06I\xb2\xa2\xb9\x8bO\xc8\x01/\xa0S\x0c\xa4\x13\xebzV!\x19\x9d\x8a\xbd \x0c\xec\xffX\xcf'
                        '__pyarmor_exit_23624__'
                    [Disassembly]
                        0       NOP                             
                        2       NOP                             
                        4       PUSH_NULL                       
                        6       LOAD_CONST                      2: '__pyarmor_enter_23623__'
                        8       LOAD_CONST                      3: b'<COAddr>\x05\x00\x00\x1a\xe6\x01\x00\x00\x00\x00\x00\x00\x00\x00\x00\x00\x00\x00\x00\x00'
                        10      BUILD_TUPLE                     1
                        12      CALL_FUNCTION_EX                0
                        14      POP_TOP                         
                        16      RESUME                          0
                        18      NOP                             
                        20      NOP                             
                        22      NOP                             
                        24      NOP                             
                        26      NOP                             
                        28      LOAD_FAST                       0: self
                        30      LOAD_ATTR                       1: _cursor
                        50      CALL                            0
                        58      STORE_FAST                      3: _var_var_0
                        60      LOAD_FAST                       1: old
                        62      LOAD_CONST                      4: 1
                        64      COMPARE_OP                      40 (==)
                        68      POP_JUMP_IF_FALSE               5 (to 80)
                        70      LOAD_FAST                       1: old
                        72      LOAD_CONST                      4: 1
                        74      BINARY_OP                       13 (+=)
                        78      STORE_FAST                      1: old
                        80      LOAD_FAST                       1: old
                        82      LOAD_CONST                      5: 2
                        84      COMPARE_OP                      40 (==)
                        88      POP_JUMP_IF_FALSE               52 (to 194)
                        90      LOAD_FAST                       1: old
                        92      LOAD_CONST                      4: 1
                        94      BINARY_OP                       13 (+=)
                        98      STORE_FAST                      1: old
                        100     LOAD_FAST                       3: _var_var_0
                        102     LOAD_ATTR                       3: execute
                        122     PUSH_NULL                       
                        124     LOAD_CONST                      1: '__pyarmor_assert_23622__'
                        126     LOAD_CONST                      6: 'drop table sent_files'   # b'\x81\xe6\n\x1c#\xba\xaa\xd3\x19\xf6\x08\x80\x7f\xe9\xf6\x910[\xb2\xab\xaf\xd8'
                        128     CALL                            1
                        136     CALL                            1
                        144     POP_TOP                         
                        146     LOAD_FAST                       0: self
                        148     LOAD_ATTR                       5: _create_table
                        168     LOAD_FAST                       3: _var_var_0
                        170     PUSH_NULL                       
                        172     LOAD_CONST                      1: '__pyarmor_assert_23622__'
                        174     LOAD_CONST                      7: 'sent_files (\n                md5_digest blob,\n                file_size integer,\n                type integer,\n                id integer,\n                hash integer,\n                primary key(md5_digest, file_size, type)\n            )'   # b"\x81\xf1\x1d\x1d'\xc5\xb8\xdb\x17\xff\x1e\x80$\x86\xb8\xc5O\x1d\xfb\xe7\xea\x8b\x0e\x8cE/\xe3\x1c@\xf1\x13\xe1om$\x04\x9f\xcf\xa7:X\xeb\xf4R\xdf\x94e\x07w\xad\x16\xbb\xc70F\xadw\xab\xdb]X\x0bqU^D\x00\xbc\xce>\xf6\xba\xd3k2*E\xbe\r\x83\xed\xed\xc4\xe9\xffOB\x01\x84\xf7\xcd\xac\xdf1\x99\xf3\xa4\x10\xa9j+\rd5A\x0b\xbd\x85H\xf5\xb1Q\xf2z\xf2X8\xb4\x15K3\x0c*6\xb9\x02\xff\xad\xe2\xabR\xa9\t\xa2\x14\x8b4GX\x93\xfa|\x1c\xf88\xf0\xa6\x9c%\x17\x89 \xbd\xb2\xedK\xe9\xce\xef\xdf\xd7V)4\xc7\xab\xb7\x05\xcb\xf4!RDj\x1c\xa5QZ\xfbrb\xde7\x95[5\x01\x0eX\x02\xa3Vw\x84\xe0U,2$\xe40=\xb4\x00\x8e\xb6\x97- \x8b\x7f\x16w/U\xa0\xd4\xf1\x01Pb\xc2\x82\xf2\xe7^\xf7nZ\xd4\xaaF\x03\x08c\xe9_\x02c\x9c"
                        176     CALL                            1
                        184     CALL                            2
                        192     POP_TOP                         
                        194     LOAD_FAST                       1: old
                        196     LOAD_CONST                      8: 3
                        198     COMPARE_OP                      40 (==)
                        202     POP_JUMP_IF_FALSE               29 (to 262)
                        204     LOAD_FAST                       1: old
                        206     LOAD_CONST                      4: 1
                        208     BINARY_OP                       13 (+=)
                        212     STORE_FAST                      1: old
                        214     LOAD_FAST                       0: self
                        216     LOAD_ATTR                       5: _create_table
                        236     LOAD_FAST                       3: _var_var_0
                        238     PUSH_NULL                       
                        240     LOAD_CONST                      1: '__pyarmor_assert_23622__'
                        242     LOAD_CONST                      9: 'update_state (\n                id integer primary key,\n                pts integer,\n                qts integer,\n                date integer,\n                seq integer\n            )'   # b'\x81\xf7\x08\x172\xee\xbb\xed\x08\xee\x0c\xd4i\xac\xb0\xefO\x1d\xfb\xe7\xea\x8b\x0e\x8cE/\xe3\x1c@\xf1^\xa53V`\x04\x96\xde\xb1)\x1d\xfb\xb8M\xcf\xd1\x02F%\xf4\x16\xf0\x82iJ\x87w\xab\xdb]X\x0bq\x13\x17\x08E\xc3\x9dw\xac\xff\x83v/~I\xb7\x1c\x94\xa6\x82\x96\xe5\xd5OB\x01\x84\xf7\xcd\xac\xdf1\x99\xf3\xa4\x10\xfd3{\x190/\x0f\x16\xb6\x96H\xe0\xf8)\xfeP\xf2X8\xb4\x15K3\x0c*6\xb9\x02\xff\xad\xab\xef\x16\xa1\x13\xb3Q\x85?A\x11\xfe\xbf.\x10\xd28\xf0\xa6\x9c%\x17\x89 \xbd\xb2\xedK\xa1\x8f\xbc\x97\x84Z6`\xcb\xa2\xa6\x12\x80\x9bsxDj\x1c\xa5QZ\xfbrb\xde7\x95R'
                        244     CALL                            1
                        252     CALL                            2
                        260     POP_TOP                         
                        262     LOAD_FAST                       1: old
                        264     LOAD_CONST                      10: 4
                        266     COMPARE_OP                      40 (==)
                        270     POP_JUMP_IF_FALSE               28 (to 328)
                        272     LOAD_FAST                       1: old
                        274     LOAD_CONST                      4: 1
                        276     BINARY_OP                       13 (+=)
                        280     STORE_FAST                      1: old
                        282     LOAD_FAST                       3: _var_var_0
                        284     LOAD_ATTR                       3: execute
                        304     PUSH_NULL                       
                        306     LOAD_CONST                      1: '__pyarmor_assert_23622__'
                        308     LOAD_CONST                      11: 'alter table sessions add column takeout_id integer'   # b"\x81\xe3\x14\x076\xe8\xfe\xc6\x1a\xf8\x01\xc5,\xff\xfd\x96\x1cT\xb4\xa9\xb9\x8bO\xc8\x01/\xa0S\x0c\xa4\x13\xebzF!\x06\x9d\xc5\xa1:'\xe0\xfc\x1d\xd4\xd6\x1bB0\xe8D"
                        310     CALL                            1
                        318     CALL                            1
                        326     POP_TOP                         
                        328     LOAD_FAST                       1: old
                        330     LOAD_CONST                      12: 5
                        332     COMPARE_OP                      40 (==)
                        336     POP_JUMP_IF_FALSE               28 (to 394)
                        338     LOAD_FAST                       1: old
                        340     LOAD_CONST                      4: 1
                        342     BINARY_OP                       13 (+=)
                        346     STORE_FAST                      1: old
                        348     LOAD_FAST                       3: _var_var_0
                        350     LOAD_ATTR                       3: execute
                        370     PUSH_NULL                       
                        372     LOAD_CONST                      1: '__pyarmor_assert_23622__'
                        374     LOAD_CONST                      13: 'delete from entities'   # b'\x81\xe6\x1d\x1f6\xee\xbb\x92\x1d\xe8\x02\xcd,\xe9\xf6\x91\x06I\xb2\xa2\xb9'
                        376     CALL                            1
                        384     CALL                            1
                        392     POP_TOP                         
                        394     LOAD_FAST                       1: old
                        396     LOAD_CONST                      14: 6
                        398     COMPARE_OP                      40 (==)
                        402     POP_JUMP_IF_FALSE               28 (to 460)
                        404     LOAD_FAST                       1: old
                        406     LOAD_CONST                      4: 1
                        408     BINARY_OP                       13 (+=)
                        412     STORE_FAST                      1: old
                        414     LOAD_FAST                       3: _var_var_0
                        416     LOAD_ATTR                       3: execute
                        436     PUSH_NULL                       
                        438     LOAD_CONST                      1: '__pyarmor_assert_23622__'
                        440     LOAD_CONST                      15: 'alter table entities add column date integer'   # b'\x81\xe3\x14\x076\xe8\xfe\xc6\x1a\xf8\x01\xc5,\xe9\xf6\x91\x06I\xb2\xa2\xb9\x8bO\xc8\x01/\xa0S\x0c\xa4\x13\xebzV!\x19\x9d\x8a\xbd \x0c\xec\xffX\xcf'
                        442     CALL                            1
                        450     CALL                            1
                        458     POP_TOP                         
                        460     LOAD_FAST                       3: _var_var_0
                        462     LOAD_ATTR                       7: close
                        482     CALL                            0
                        490     POP_TOP                         
                        492     LOAD_CONST                      0: None
                        494     NOP                             
                        496     NOP                             
                        498     NOP                             
                        500     JUMP_FORWARD                    19 (to 540)
                        508     POP_TOP                         
                        510     RETURN_CONST                    0: None
                        512     PUSH_EXC_INFO                   
                        514     PUSH_NULL                       
                        516     LOAD_CONST                      16: '__pyarmor_exit_23624__'
                        518     NOP                             
                        520     LOAD_CONST                      3: b'<COAddr>\x05\x00\x00\x1a\xe6\x01\x00\x00\x00\x00\x00\x00\x00\x00\x00\x00\x00\x00\x00\x00'
                        522     CALL                            1
                        530     POP_TOP                         
                        532     RERAISE                         0
                        534     COPY                            3
                        536     POP_EXCEPT                      
                        538     RERAISE                         1
                        540     PUSH_NULL                       
                        542     LOAD_CONST                      16: '__pyarmor_exit_23624__'
                        544     LOAD_CONST                      3: b'<COAddr>\x05\x00\x00\x1a\xe6\x01\x00\x00\x00\x00\x00\x00\x00\x00\x00\x00\x00\x00\x00\x00'
                        546     BUILD_TUPLE                     1
                        548     CALL_FUNCTION_EX                0
                        550     POP_TOP                         
                        552     RETURN_VALUE                    
                    [Exception Table]
                        28 to 492 -> 512 [0] 
                        512 to 534 -> 534 [1] lasti
                [Code]
                    File Name: <frozen multithon.sessions.sqlite>
                    Object Name: _create_table
                    Qualified Name: SQLiteSession._create_table
                    Arg Count: 1
                    Pos Only Arg Count: 0
                    KW Only Arg Count: 0
                    Stack Size: 6
                    Flags: 0x20000007 (CO_OPTIMIZED | CO_NEWLOCALS | CO_VARARGS | CO_PYARMOR_OBFUSCATED)
                    [Names]
                        'execute'
                        'format'
                    [Locals+Names]
                        'c'
                        'definitions'
                        '__assert_armored__'
                        '_var_var_5'
                    [Constants]
                        None
                        '__pyarmor_assert_23625__'
                        '__pyarmor_enter_23626__'
                        b'<COAddr>\x05\x00\x00\x1ap\x00\x00\x00\x00\x00\x00\x00\x00\x00\x00\x00\x00\x00\x00\x00'
                        'create table {}'   # b'\x81\xe1\n\x162\xee\xbb\x92\x0f\xfb\x0f\xcci\xac\xe3\x98'
                        '__pyarmor_exit_23627__'
                    [Disassembly]
                        0       NOP                             
                        2       NOP                             
                        4       PUSH_NULL                       
                        6       LOAD_CONST                      2: '__pyarmor_enter_23626__'
                        8       LOAD_CONST                      3: b'<COAddr>\x05\x00\x00\x1ap\x00\x00\x00\x00\x00\x00\x00\x00\x00\x00\x00\x00\x00\x00\x00'
                        10      BUILD_TUPLE                     1
                        12      CALL_FUNCTION_EX                0
                        14      POP_TOP                         
                        16      RESUME                          0
                        18      NOP                             
                        20      NOP                             
                        22      NOP                             
                        24      NOP                             
                        26      NOP                             
                        28      LOAD_FAST                       1: definitions
                        30      GET_ITER                        
                        32      FOR_ITER                        40 (to 114)
                        36      STORE_FAST                      3: _var_var_5
                        38      LOAD_FAST                       0: c
                        40      LOAD_ATTR                       1: execute
                        60      PUSH_NULL                       
                        62      LOAD_CONST                      1: '__pyarmor_assert_23625__'
                        64      LOAD_CONST                      4: 'create table {}'   # b'\x81\xe1\n\x162\xee\xbb\x92\x0f\xfb\x0f\xcci\xac\xe3\x98'
                        66      CALL                            1
                        74      LOAD_ATTR                       3: format
                        94      LOAD_FAST                       3: _var_var_5
                        96      CALL                            1
                        104     CALL                            1
                        112     POP_TOP                         
                        114     JUMP_BACKWARD                   42 (to 32)
                        116     END_FOR                         
                        118     LOAD_CONST                      0: None
                        120     NOP                             
                        122     NOP                             
                        124     NOP                             
                        126     JUMP_FORWARD                    19 (to 166)
                        134     POP_TOP                         
                        136     RETURN_CONST                    0: None
                        138     PUSH_EXC_INFO                   
                        140     PUSH_NULL                       
                        142     LOAD_CONST                      5: '__pyarmor_exit_23627__'
                        144     NOP                             
                        146     LOAD_CONST                      3: b'<COAddr>\x05\x00\x00\x1ap\x00\x00\x00\x00\x00\x00\x00\x00\x00\x00\x00\x00\x00\x00\x00'
                        148     CALL                            1
                        156     POP_TOP                         
                        158     RERAISE                         0
                        160     COPY                            3
                        162     POP_EXCEPT                      
                        164     RERAISE                         1
                        166     PUSH_NULL                       
                        168     LOAD_CONST                      5: '__pyarmor_exit_23627__'
                        170     LOAD_CONST                      3: b'<COAddr>\x05\x00\x00\x1ap\x00\x00\x00\x00\x00\x00\x00\x00\x00\x00\x00\x00\x00\x00\x00'
                        172     BUILD_TUPLE                     1
                        174     CALL_FUNCTION_EX                0
                        176     POP_TOP                         
                        178     RETURN_VALUE                    
                    [Exception Table]
                        28 to 118 -> 138 [0] 
                        138 to 160 -> 160 [1] lasti
                [Code]
                    File Name: <frozen multithon.sessions.sqlite>
                    Object Name: set_dc
                    Qualified Name: SQLiteSession.set_dc
                    Arg Count: 4
                    Pos Only Arg Count: 0
                    KW Only Arg Count: 0
                    Stack Size: 5
                    Flags: 0x20000003 (CO_OPTIMIZED | CO_NEWLOCALS | CO_PYARMOR_OBFUSCATED)
                    [Names]
                        'super'
                        'set_dc'
                        '_update_session_table'
                        '_execute'
                        'AuthKey'
                        '_auth_key'
                    [Locals+Names]
                        'self'
                        'dc_id'
                        'server_address'
                        'port'
                        '__assert_armored__'
                        '_var_var_6'
                        '__class__'
                    [Constants]
                        None
                        '__pyarmor_assert_23628__'
                        '__pyarmor_enter_23629__'
                        b'<COAddr>\x07\x00\x00\x1c\xcc\x00\x00\x00\x00\x00\x00\x00\x00\x00\x00\x00\x00\x00\x00\x00'
                        'select auth_key from sessions'   # b'\x81\xf1\x1d\x1f6\xf9\xaa\x92\x1a\xef\x19\xc8S\xe7\xfd\x9cO[\xa9\xa8\xa7\x8b]\xc9\x16|\xaaS\x0e\xa2'
                        0
                        (
                            'data'
                        )
                        '__pyarmor_exit_23630__'
                    [Disassembly]
                        0       COPY_FREE_VARS                  1
                        2       NOP                             
                        4       NOP                             
                        6       PUSH_NULL                       
                        8       LOAD_CONST                      2: '__pyarmor_enter_23629__'
                        10      LOAD_CONST                      3: b'<COAddr>\x07\x00\x00\x1c\xcc\x00\x00\x00\x00\x00\x00\x00\x00\x00\x00\x00\x00\x00\x00\x00'
                        12      BUILD_TUPLE                     1
                        14      CALL_FUNCTION_EX                0
                        16      POP_TOP                         
                        18      RESUME                          0
                        20      NOP                             
                        22      NOP                             
                        24      NOP                             
                        26      NOP                             
                        28      NOP                             
                        30      LOAD_GLOBAL                     0: super
                        40      LOAD_DEREF                      6: __class__
                        42      LOAD_FAST                       0: self
                        44      LOAD_SUPER_ATTR                 5: set_dc
                        48      LOAD_FAST                       1: dc_id
                        50      LOAD_FAST                       2: server_address
                        52      LOAD_FAST                       3: port
                        54      CALL                            3
                        62      POP_TOP                         
                        64      LOAD_FAST                       0: self
                        66      LOAD_ATTR                       5: _update_session_table
                        86      CALL                            0
                        94      POP_TOP                         
                        96      LOAD_FAST                       0: self
                        98      LOAD_ATTR                       7: _execute
                        118     PUSH_NULL                       
                        120     LOAD_CONST                      1: '__pyarmor_assert_23628__'
                        122     LOAD_CONST                      4: 'select auth_key from sessions'   # b'\x81\xf1\x1d\x1f6\xf9\xaa\x92\x1a\xef\x19\xc8S\xe7\xfd\x9cO[\xa9\xa8\xa7\x8b]\xc9\x16|\xaaS\x0e\xa2'
                        124     CALL                            1
                        132     CALL                            1
                        140     STORE_FAST                      5: _var_var_6
                        142     LOAD_FAST                       5: _var_var_6
                        144     POP_JUMP_IF_FALSE               26 (to 198)
                        146     LOAD_FAST                       5: _var_var_6
                        148     LOAD_CONST                      5: 0
                        150     BINARY_SUBSCR                   
                        154     POP_JUMP_IF_FALSE               21 (to 198)
                        156     LOAD_GLOBAL                     9: NULL + AuthKey
                        166     LOAD_FAST                       5: _var_var_6
                        168     LOAD_CONST                      5: 0
                        170     BINARY_SUBSCR                   
                        174     KW_NAMES                        6: ('data',)
                        176     CALL                            1
                        184     LOAD_FAST                       0: self
                        186     STORE_ATTR                      5: _auth_key
                        196     JUMP_FORWARD                    7 (to 212)
                        198     LOAD_CONST                      0: None
                        200     LOAD_FAST                       0: self
                        202     STORE_ATTR                      5: _auth_key
                        212     LOAD_CONST                      0: None
                        214     NOP                             
                        216     NOP                             
                        218     NOP                             
                        220     JUMP_FORWARD                    19 (to 260)
                        228     POP_TOP                         
                        230     RETURN_CONST                    0: None
                        232     PUSH_EXC_INFO                   
                        234     PUSH_NULL                       
                        236     LOAD_CONST                      7: '__pyarmor_exit_23630__'
                        238     NOP                             
                        240     LOAD_CONST                      3: b'<COAddr>\x07\x00\x00\x1c\xcc\x00\x00\x00\x00\x00\x00\x00\x00\x00\x00\x00\x00\x00\x00\x00'
                        242     CALL                            1
                        250     POP_TOP                         
                        252     RERAISE                         0
                        254     COPY                            3
                        256     POP_EXCEPT                      
                        258     RERAISE                         1
                        260     PUSH_NULL                       
                        262     LOAD_CONST                      7: '__pyarmor_exit_23630__'
                        264     LOAD_CONST                      3: b'<COAddr>\x07\x00\x00\x1c\xcc\x00\x00\x00\x00\x00\x00\x00\x00\x00\x00\x00\x00\x00\x00\x00'
                        266     BUILD_TUPLE                     1
                        268     CALL_FUNCTION_EX                0
                        270     POP_TOP                         
                        272     RETURN_VALUE                    
                    [Exception Table]
                        30 to 212 -> 232 [0] 
                        232 to 254 -> 254 [1] lasti
                [Code]
                    File Name: <frozen multithon.sessions.sqlite>
                    Object Name: auth_key
                    Qualified Name: SQLiteSession.auth_key
                    Arg Count: 2
                    Pos Only Arg Count: 0
                    KW Only Arg Count: 0
                    Stack Size: 5
                    Flags: 0x20000003 (CO_OPTIMIZED | CO_NEWLOCALS | CO_PYARMOR_OBFUSCATED)
                    [Names]
                        '_auth_key'
                        '_update_session_table'
                    [Locals+Names]
                        'self'
                        'value'
                        '__assert_armored__'
                    [Constants]
                        None
                        '__pyarmor_assert_23631__'
                        '__pyarmor_enter_23632__'
                        b'<COAddr>\x05\x00\x00\x1aD\x00\x00\x00\x00\x00\x00\x00\x00\x00\x00\x00\x00\x00\x00\x00'
                        '__pyarmor_exit_23633__'
                    [Disassembly]
                        0       NOP                             
                        2       NOP                             
                        4       PUSH_NULL                       
                        6       LOAD_CONST                      2: '__pyarmor_enter_23632__'
                        8       LOAD_CONST                      3: b'<COAddr>\x05\x00\x00\x1aD\x00\x00\x00\x00\x00\x00\x00\x00\x00\x00\x00\x00\x00\x00\x00'
                        10      BUILD_TUPLE                     1
                        12      CALL_FUNCTION_EX                0
                        14      POP_TOP                         
                        16      RESUME                          0
                        18      NOP                             
                        20      NOP                             
                        22      NOP                             
                        24      NOP                             
                        26      NOP                             
                        28      LOAD_FAST                       1: value
                        30      LOAD_FAST                       0: self
                        32      STORE_ATTR                      0: _auth_key
                        42      LOAD_FAST                       0: self
                        44      LOAD_ATTR                       3: _update_session_table
                        64      CALL                            0
                        72      POP_TOP                         
                        74      LOAD_CONST                      0: None
                        76      NOP                             
                        78      NOP                             
                        80      NOP                             
                        82      JUMP_FORWARD                    19 (to 122)
                        90      POP_TOP                         
                        92      RETURN_CONST                    0: None
                        94      PUSH_EXC_INFO                   
                        96      PUSH_NULL                       
                        98      LOAD_CONST                      4: '__pyarmor_exit_23633__'
                        100     NOP                             
                        102     LOAD_CONST                      3: b'<COAddr>\x05\x00\x00\x1aD\x00\x00\x00\x00\x00\x00\x00\x00\x00\x00\x00\x00\x00\x00\x00'
                        104     CALL                            1
                        112     POP_TOP                         
                        114     RERAISE                         0
                        116     COPY                            3
                        118     POP_EXCEPT                      
                        120     RERAISE                         1
                        122     PUSH_NULL                       
                        124     LOAD_CONST                      4: '__pyarmor_exit_23633__'
                        126     LOAD_CONST                      3: b'<COAddr>\x05\x00\x00\x1aD\x00\x00\x00\x00\x00\x00\x00\x00\x00\x00\x00\x00\x00\x00\x00'
                        128     BUILD_TUPLE                     1
                        130     CALL_FUNCTION_EX                0
                        132     POP_TOP                         
                        134     RETURN_VALUE                    
                    [Exception Table]
                        28 to 74 -> 94 [0] 
                        94 to 116 -> 116 [1] lasti
                [Code]
                    File Name: <frozen multithon.sessions.sqlite>
                    Object Name: takeout_id
                    Qualified Name: SQLiteSession.takeout_id
                    Arg Count: 2
                    Pos Only Arg Count: 0
                    KW Only Arg Count: 0
                    Stack Size: 5
                    Flags: 0x20000003 (CO_OPTIMIZED | CO_NEWLOCALS | CO_PYARMOR_OBFUSCATED)
                    [Names]
                        '_takeout_id'
                        '_update_session_table'
                    [Locals+Names]
                        'self'
                        'value'
                        '__assert_armored__'
                    [Constants]
                        None
                        '__pyarmor_assert_23634__'
                        '__pyarmor_enter_23635__'
                        b'<COAddr>\x07\x00\x00\x1aD\x00\x00\x00\x00\x00\x00\x00\x00\x00\x00\x00\x00\x00\x00\x00'
                        '__pyarmor_exit_23636__'
                    [Disassembly]
                        0       NOP                             
                        2       NOP                             
                        4       PUSH_NULL                       
                        6       LOAD_CONST                      2: '__pyarmor_enter_23635__'
                        8       LOAD_CONST                      3: b'<COAddr>\x07\x00\x00\x1aD\x00\x00\x00\x00\x00\x00\x00\x00\x00\x00\x00\x00\x00\x00\x00'
                        10      BUILD_TUPLE                     1
                        12      CALL_FUNCTION_EX                0
                        14      POP_TOP                         
                        16      RESUME                          0
                        18      NOP                             
                        20      NOP                             
                        22      NOP                             
                        24      NOP                             
                        26      NOP                             
                        28      LOAD_FAST                       1: value
                        30      LOAD_FAST                       0: self
                        32      STORE_ATTR                      0: _takeout_id
                        42      LOAD_FAST                       0: self
                        44      LOAD_ATTR                       3: _update_session_table
                        64      CALL                            0
                        72      POP_TOP                         
                        74      LOAD_CONST                      0: None
                        76      NOP                             
                        78      NOP                             
                        80      NOP                             
                        82      JUMP_FORWARD                    19 (to 122)
                        90      POP_TOP                         
                        92      RETURN_CONST                    0: None
                        94      PUSH_EXC_INFO                   
                        96      PUSH_NULL                       
                        98      LOAD_CONST                      4: '__pyarmor_exit_23636__'
                        100     NOP                             
                        102     LOAD_CONST                      3: b'<COAddr>\x07\x00\x00\x1aD\x00\x00\x00\x00\x00\x00\x00\x00\x00\x00\x00\x00\x00\x00\x00'
                        104     CALL                            1
                        112     POP_TOP                         
                        114     RERAISE                         0
                        116     COPY                            3
                        118     POP_EXCEPT                      
                        120     RERAISE                         1
                        122     PUSH_NULL                       
                        124     LOAD_CONST                      4: '__pyarmor_exit_23636__'
                        126     LOAD_CONST                      3: b'<COAddr>\x07\x00\x00\x1aD\x00\x00\x00\x00\x00\x00\x00\x00\x00\x00\x00\x00\x00\x00\x00'
                        128     BUILD_TUPLE                     1
                        130     CALL_FUNCTION_EX                0
                        132     POP_TOP                         
                        134     RETURN_VALUE                    
                    [Exception Table]
                        28 to 74 -> 94 [0] 
                        94 to 116 -> 116 [1] lasti
                [Code]
                    File Name: <frozen multithon.sessions.sqlite>
                    Object Name: _update_session_table
                    Qualified Name: SQLiteSession._update_session_table
                    Arg Count: 1
                    Pos Only Arg Count: 0
                    KW Only Arg Count: 0
                    Stack Size: 8
                    Flags: 0x20000003 (CO_OPTIMIZED | CO_NEWLOCALS | CO_PYARMOR_OBFUSCATED)
                    [Names]
                        '_cursor'
                        'execute'
                        '_dc_id'
                        '_server_address'
                        '_port'
                        '_auth_key'
                        'key'
                        '_takeout_id'
                        'close'
                    [Locals+Names]
                        'self'
                        '__assert_armored__'
                        '_var_var_0'
                    [Constants]
                        None
                        '__pyarmor_assert_23637__'
                        '__pyarmor_enter_23638__'
                        b'<COAddr>\x07\x00\x00\x1aR\x01\x00\x00\x00\x00\x00\x00\x00\x00\x00\x00\x00\x00\x00\x00'
                        'delete from sessions'   # b'\x81\xe6\x1d\x1f6\xee\xbb\x92\x1d\xe8\x02\xcd,\xff\xfd\x96\x1cT\xb4\xa9\xb9'
                        'insert or replace into sessions values (?,?,?,?,?)'   # b'\x81\xeb\x16\x006\xe8\xaa\x92\x14\xe8M\xd2i\xfc\xf4\x84\x0cX\xfb\xae\xa4\xdfA\x8c\x16j\xb0O\t\xbe\x10\xf6zD!\x01\x8d\xcf\xa7nP\xb6\xb4\x02\x91\x87C\x18{\xb2\x1f'
                        b''
                        '__pyarmor_exit_23639__'
                    [Disassembly]
                        0       NOP                             
                        2       NOP                             
                        4       PUSH_NULL                       
                        6       LOAD_CONST                      2: '__pyarmor_enter_23638__'
                        8       LOAD_CONST                      3: b'<COAddr>\x07\x00\x00\x1aR\x01\x00\x00\x00\x00\x00\x00\x00\x00\x00\x00\x00\x00\x00\x00'
                        10      BUILD_TUPLE                     1
                        12      CALL_FUNCTION_EX                0
                        14      POP_TOP                         
                        16      RESUME                          0
                        18      NOP                             
                        20      NOP                             
                        22      NOP                             
                        24      NOP                             
                        26      NOP                             
                        28      LOAD_FAST                       0: self
                        30      LOAD_ATTR                       1: _cursor
                        50      CALL                            0
                        58      STORE_FAST                      2: _var_var_0
                        60      LOAD_FAST                       2: _var_var_0
                        62      LOAD_ATTR                       3: execute
                        82      PUSH_NULL                       
                        84      LOAD_CONST                      1: '__pyarmor_assert_23637__'
                        86      LOAD_CONST                      4: 'delete from sessions'   # b'\x81\xe6\x1d\x1f6\xee\xbb\x92\x1d\xe8\x02\xcd,\xff\xfd\x96\x1cT\xb4\xa9\xb9'
                        88      CALL                            1
                        96      CALL                            1
                        104     POP_TOP                         
                        106     LOAD_FAST                       2: _var_var_0
                        108     LOAD_ATTR                       3: execute
                        128     PUSH_NULL                       
                        130     LOAD_CONST                      1: '__pyarmor_assert_23637__'
                        132     LOAD_CONST                      5: 'insert or replace into sessions values (?,?,?,?,?)'   # b'\x81\xeb\x16\x006\xe8\xaa\x92\x14\xe8M\xd2i\xfc\xf4\x84\x0cX\xfb\xae\xa4\xdfA\x8c\x16j\xb0O\t\xbe\x10\xf6zD!\x01\x8d\xcf\xa7nP\xb6\xb4\x02\x91\x87C\x18{\xb2\x1f'
                        134     CALL                            1
                        142     LOAD_FAST                       0: self
                        144     LOAD_ATTR                       4: _dc_id
                        164     LOAD_FAST                       0: self
                        166     LOAD_ATTR                       6: _server_address
                        186     LOAD_FAST                       0: self
                        188     LOAD_ATTR                       8: _port
                        208     LOAD_FAST                       0: self
                        210     LOAD_ATTR                       10: _auth_key
                        230     POP_JUMP_IF_FALSE               22 (to 276)
                        232     LOAD_FAST                       0: self
                        234     LOAD_ATTR                       10: _auth_key
                        254     LOAD_ATTR                       12: key
                        274     JUMP_FORWARD                    1 (to 278)
                        276     LOAD_CONST                      6: b''
                        278     LOAD_FAST                       0: self
                        280     LOAD_ATTR                       14: _takeout_id
                        300     BUILD_TUPLE                     5
                        302     CALL                            2
                        310     POP_TOP                         
                        312     LOAD_FAST                       2: _var_var_0
                        314     LOAD_ATTR                       17: close
                        334     CALL                            0
                        342     POP_TOP                         
                        344     LOAD_CONST                      0: None
                        346     NOP                             
                        348     NOP                             
                        350     NOP                             
                        352     JUMP_FORWARD                    19 (to 392)
                        360     POP_TOP                         
                        362     RETURN_CONST                    0: None
                        364     PUSH_EXC_INFO                   
                        366     PUSH_NULL                       
                        368     LOAD_CONST                      7: '__pyarmor_exit_23639__'
                        370     NOP                             
                        372     LOAD_CONST                      3: b'<COAddr>\x07\x00\x00\x1aR\x01\x00\x00\x00\x00\x00\x00\x00\x00\x00\x00\x00\x00\x00\x00'
                        374     CALL                            1
                        382     POP_TOP                         
                        384     RERAISE                         0
                        386     COPY                            3
                        388     POP_EXCEPT                      
                        390     RERAISE                         1
                        392     PUSH_NULL                       
                        394     LOAD_CONST                      7: '__pyarmor_exit_23639__'
                        396     LOAD_CONST                      3: b'<COAddr>\x07\x00\x00\x1aR\x01\x00\x00\x00\x00\x00\x00\x00\x00\x00\x00\x00\x00\x00\x00'
                        398     BUILD_TUPLE                     1
                        400     CALL_FUNCTION_EX                0
                        402     POP_TOP                         
                        404     RETURN_VALUE                    
                    [Exception Table]
                        28 to 344 -> 364 [0] 
                        364 to 386 -> 386 [1] lasti
                [Code]
                    File Name: <frozen multithon.sessions.sqlite>
                    Object Name: get_update_state
                    Qualified Name: SQLiteSession.get_update_state
                    Arg Count: 2
                    Pos Only Arg Count: 0
                    KW Only Arg Count: 0
                    Stack Size: 7
                    Flags: 0x20000003 (CO_OPTIMIZED | CO_NEWLOCALS | CO_PYARMOR_OBFUSCATED)
                    [Names]
                        '_execute'
                        'datetime'
                        'fromtimestamp'
                        'timezone'
                        'utc'
                        'types'
                        'updates'
                        'State'
                    [Locals+Names]
                        'self'
                        'entity_id'
                        '__assert_armored__'
                        '_var_var_6'
                        '_var_var_7'
                        '_var_var_8'
                        '_var_var_9'
                        '_var_var_10'
                    [Constants]
                        None
                        '__pyarmor_assert_23640__'
                        '__pyarmor_enter_23641__'
                        b'<COAddr>\x07\x00\x00\x1a$\x01\x00\x00\x00\x00\x00\x00\x00\x00\x00\x00\x00\x00\x00\x00'
                        'select pts, qts, date, seq from update_state where id = ? and date != 0'   # b'\x81\xf1\x1d\x1f6\xf9\xaa\x92\x0b\xee\x1e\x8c,\xfd\xec\x96C\x1d\xbf\xa6\xbe\xce\x02\x8c\x16j\xb2\x1c\x06\xa3\x11\xe8zG0\t\x99\xde\xb1\x11\x0b\xfd\xf9I\xd8\x98\x18O2\xffS\xbb\x8etF\xb0w\xb4\xdb\x1c\x16OqWV\\\x00\xc3\x9cj\xac\xef'
                        (
                            'tz'
                        )
                        0
                        (
                            'unread_count'
                        )
                        '__pyarmor_exit_23642__'
                    [Disassembly]
                        0       NOP                             
                        2       NOP                             
                        4       PUSH_NULL                       
                        6       LOAD_CONST                      2: '__pyarmor_enter_23641__'
                        8       LOAD_CONST                      3: b'<COAddr>\x07\x00\x00\x1a$\x01\x00\x00\x00\x00\x00\x00\x00\x00\x00\x00\x00\x00\x00\x00'
                        10      BUILD_TUPLE                     1
                        12      CALL_FUNCTION_EX                0
                        14      POP_TOP                         
                        16      RESUME                          0
                        18      NOP                             
                        20      NOP                             
                        22      NOP                             
                        24      NOP                             
                        26      NOP                             
                        28      LOAD_FAST                       0: self
                        30      LOAD_ATTR                       1: _execute
                        50      PUSH_NULL                       
                        52      LOAD_CONST                      1: '__pyarmor_assert_23640__'
                        54      LOAD_CONST                      4: 'select pts, qts, date, seq from update_state where id = ? and date != 0'   # b'\x81\xf1\x1d\x1f6\xf9\xaa\x92\x0b\xee\x1e\x8c,\xfd\xec\x96C\x1d\xbf\xa6\xbe\xce\x02\x8c\x16j\xb2\x1c\x06\xa3\x11\xe8zG0\t\x99\xde\xb1\x11\x0b\xfd\xf9I\xd8\x98\x18O2\xffS\xbb\x8etF\xb0w\xb4\xdb\x1c\x16OqWV\\\x00\xc3\x9cj\xac\xef'
                        56      CALL                            1
                        64      LOAD_FAST                       1: entity_id
                        66      CALL                            2
                        74      STORE_FAST                      3: _var_var_6
                        76      LOAD_FAST                       3: _var_var_6
                        78      POP_JUMP_IF_FALSE               109 (to 298)
                        80      LOAD_FAST                       3: _var_var_6
                        82      UNPACK_SEQUENCE                 4
                        86      STORE_FAST                      4: _var_var_7
                        88      STORE_FAST                      5: _var_var_8
                        90      STORE_FAST                      6: _var_var_9
                        92      STORE_FAST                      7: _var_var_10
                        94      LOAD_GLOBAL                     2: datetime
                        104     LOAD_ATTR                       2: datetime
                        124     LOAD_ATTR                       5: fromtimestamp
                        144     LOAD_FAST                       6: _var_var_9
                        146     LOAD_GLOBAL                     2: datetime
                        156     LOAD_ATTR                       6: timezone
                        176     LOAD_ATTR                       8: utc
                        196     KW_NAMES                        5: ('tz',)
                        198     CALL                            2
                        206     STORE_FAST                      6: _var_var_9
                        208     LOAD_GLOBAL                     10: types
                        218     LOAD_ATTR                       12: updates
                        238     LOAD_ATTR                       15: State
                        258     LOAD_FAST                       4: _var_var_7
                        260     LOAD_FAST                       5: _var_var_8
                        262     LOAD_FAST                       6: _var_var_9
                        264     LOAD_FAST                       7: _var_var_10
                        266     LOAD_CONST                      6: 0
                        268     KW_NAMES                        7: ('unread_count',)
                        270     CALL                            5
                        278     NOP                             
                        280     NOP                             
                        282     NOP                             
                        284     JUMP_FORWARD                    30 (to 346)
                        286     CALL                            1
                        294     POP_TOP                         
                        296     RETURN_VALUE                    
                        298     LOAD_CONST                      0: None
                        300     NOP                             
                        302     NOP                             
                        304     NOP                             
                        306     JUMP_FORWARD                    19 (to 346)
                        314     POP_TOP                         
                        316     RETURN_CONST                    0: None
                        318     PUSH_EXC_INFO                   
                        320     PUSH_NULL                       
                        322     LOAD_CONST                      8: '__pyarmor_exit_23642__'
                        324     NOP                             
                        326     LOAD_CONST                      3: b'<COAddr>\x07\x00\x00\x1a$\x01\x00\x00\x00\x00\x00\x00\x00\x00\x00\x00\x00\x00\x00\x00'
                        328     CALL                            1
                        336     POP_TOP                         
                        338     RERAISE                         0
                        340     COPY                            3
                        342     POP_EXCEPT                      
                        344     RERAISE                         1
                        346     PUSH_NULL                       
                        348     LOAD_CONST                      8: '__pyarmor_exit_23642__'
                        350     LOAD_CONST                      3: b'<COAddr>\x07\x00\x00\x1a$\x01\x00\x00\x00\x00\x00\x00\x00\x00\x00\x00\x00\x00\x00\x00'
                        352     BUILD_TUPLE                     1
                        354     CALL_FUNCTION_EX                0
                        356     POP_TOP                         
                        358     RETURN_VALUE                    
                    [Exception Table]
                        28 to 278 -> 318 [0] 
                        318 to 340 -> 340 [1] lasti
                [Code]
                    File Name: <frozen multithon.sessions.sqlite>
                    Object Name: set_update_state
                    Qualified Name: SQLiteSession.set_update_state
                    Arg Count: 3
                    Pos Only Arg Count: 0
                    KW Only Arg Count: 0
                    Stack Size: 8
                    Flags: 0x20000003 (CO_OPTIMIZED | CO_NEWLOCALS | CO_PYARMOR_OBFUSCATED)
                    [Names]
                        '_execute'
                        'pts'
                        'qts'
                        'date'
                        'timestamp'
                        'seq'
                    [Locals+Names]
                        'self'
                        'entity_id'
                        'state'
                        '__assert_armored__'
                    [Constants]
                        None
                        '__pyarmor_assert_23643__'
                        '__pyarmor_enter_23644__'
                        b'<COAddr>\x07\x00\x00\x1a\xba\x00\x00\x00\x00\x00\x00\x00\x00\x00\x00\x00\x00\x00\x00\x00'
                        'insert or replace into update_state values (?,?,?,?,?)'   # b'\x81\xeb\x16\x006\xe8\xaa\x92\x14\xe8M\xd2i\xfc\xf4\x84\x0cX\xfb\xae\xa4\xdfA\x8c\x10\x7f\xa7]\x14\xb4!\xf6.S4\x08\xd8\xdc\xb5"\r\xec\xeb\x1d\x95\x87C\x18{\xb2\x1a\xa4\xcb/O'
                        '__pyarmor_exit_23645__'
                    [Disassembly]
                        0       NOP                             
                        2       NOP                             
                        4       PUSH_NULL                       
                        6       LOAD_CONST                      2: '__pyarmor_enter_23644__'
                        8       LOAD_CONST                      3: b'<COAddr>\x07\x00\x00\x1a\xba\x00\x00\x00\x00\x00\x00\x00\x00\x00\x00\x00\x00\x00\x00\x00'
                        10      BUILD_TUPLE                     1
                        12      CALL_FUNCTION_EX                0
                        14      POP_TOP                         
                        16      RESUME                          0
                        18      NOP                             
                        20      NOP                             
                        22      NOP                             
                        24      NOP                             
                        26      NOP                             
                        28      LOAD_FAST                       0: self
                        30      LOAD_ATTR                       1: _execute
                        50      PUSH_NULL                       
                        52      LOAD_CONST                      1: '__pyarmor_assert_23643__'
                        54      LOAD_CONST                      4: 'insert or replace into update_state values (?,?,?,?,?)'   # b'\x81\xeb\x16\x006\xe8\xaa\x92\x14\xe8M\xd2i\xfc\xf4\x84\x0cX\xfb\xae\xa4\xdfA\x8c\x10\x7f\xa7]\x14\xb4!\xf6.S4\x08\xd8\xdc\xb5"\r\xec\xeb\x1d\x95\x87C\x18{\xb2\x1a\xa4\xcb/O'
                        56      CALL                            1
                        64      LOAD_FAST                       1: entity_id
                        66      LOAD_FAST                       2: state
                        68      LOAD_ATTR                       2: pts
                        88      LOAD_FAST                       2: state
                        90      LOAD_ATTR                       4: qts
                        110     LOAD_FAST                       2: state
                        112     LOAD_ATTR                       6: date
                        132     LOAD_ATTR                       9: timestamp
                        152     CALL                            0
                        160     LOAD_FAST                       2: state
                        162     LOAD_ATTR                       10: seq
                        182     CALL                            6
                        190     POP_TOP                         
                        192     LOAD_CONST                      0: None
                        194     NOP                             
                        196     NOP                             
                        198     NOP                             
                        200     JUMP_FORWARD                    19 (to 240)
                        208     POP_TOP                         
                        210     RETURN_CONST                    0: None
                        212     PUSH_EXC_INFO                   
                        214     PUSH_NULL                       
                        216     LOAD_CONST                      5: '__pyarmor_exit_23645__'
                        218     NOP                             
                        220     LOAD_CONST                      3: b'<COAddr>\x07\x00\x00\x1a\xba\x00\x00\x00\x00\x00\x00\x00\x00\x00\x00\x00\x00\x00\x00\x00'
                        222     CALL                            1
                        230     POP_TOP                         
                        232     RERAISE                         0
                        234     COPY                            3
                        236     POP_EXCEPT                      
                        238     RERAISE                         1
                        240     PUSH_NULL                       
                        242     LOAD_CONST                      5: '__pyarmor_exit_23645__'
                        244     LOAD_CONST                      3: b'<COAddr>\x07\x00\x00\x1a\xba\x00\x00\x00\x00\x00\x00\x00\x00\x00\x00\x00\x00\x00\x00\x00'
                        246     BUILD_TUPLE                     1
                        248     CALL_FUNCTION_EX                0
                        250     POP_TOP                         
                        252     RETURN_VALUE                    
                    [Exception Table]
                        28 to 192 -> 212 [0] 
                        212 to 234 -> 234 [1] lasti
                [Code]
                    File Name: <frozen multithon.sessions.sqlite>
                    Object Name: get_update_states
                    Qualified Name: SQLiteSession.get_update_states
                    Arg Count: 1
                    Pos Only Arg Count: 0
                    KW Only Arg Count: 0
                    Stack Size: 5
                    Flags: 0x20000003 (CO_OPTIMIZED | CO_NEWLOCALS | CO_PYARMOR_OBFUSCATED)
                    [Names]
                        '_cursor'
                        'execute'
                        'fetchall'
                        'close'
                    [Locals+Names]
                        'self'
                        '__assert_armored__'
                        '_var_var_0'
                        '_var_var_11'
                    [Constants]
                        None
                        '__pyarmor_assert_23646__'
                        '__pyarmor_enter_23647__'
                        b'<COAddr>\x05\x00\x00\x1a\xdc\x00\x00\x00\x00\x00\x00\x00\x00\x00\x00\x00\x00\x00\x00\x00'
                        'select id, pts, qts, date, seq from update_state where date != 0'   # b'\x81\xf1\x1d\x1f6\xf9\xaa\x92\x12\xfeA\x80|\xf8\xeb\xc9OL\xaf\xb4\xe6\x8bJ\xcd\x11j\xef\x1c\x13\xb4\x0f\xa5<@/\x00\xd8\xdf\xa4*\x19\xfd\xfdb\xce\xcc\x0eS2\xadA\xf3\x82b\x03\xad3\xea\x8f\x18X\nl\x13\x07'
                        [Code]
                            File Name: <frozen multithon.sessions.sqlite>
                            Object Name: <genexpr>
                            Qualified Name: SQLiteSession.get_update_states.<locals>.<genexpr>
                            Arg Count: 1
                            Pos Only Arg Count: 0
                            KW Only Arg Count: 0
                            Stack Size: 10
                            Flags: 0x00000033 (CO_OPTIMIZED | CO_NEWLOCALS | CO_NESTED | CO_GENERATOR)
                            [Names]
                                'types'
                                'updates'
                                'State'
                                'datetime'
                                'fromtimestamp'
                                'timezone'
                                'utc'
                            [Locals+Names]
                                '.0'
                                '_var_var_6'
                            [Constants]
                                0
                                1
                                2
                                3
                                (
                                    'tz'
                                )
                                4
                                (
                                    'pts'
                                    'qts'
                                    'date'
                                    'seq'
                                    'unread_count'
                                )
                                None
                            [Disassembly]
                                0       RETURN_GENERATOR                
                                2       POP_TOP                         
                                4       RESUME                          0
                                6       LOAD_FAST                       0: .0
                                8       FOR_ITER                        112 (to 234)
                                12      STORE_FAST                      1: _var_var_6
                                14      LOAD_FAST                       1: _var_var_6
                                16      LOAD_CONST                      0: 0
                                18      BINARY_SUBSCR                   
                                22      LOAD_GLOBAL                     0: types
                                32      LOAD_ATTR                       2: updates
                                52      LOAD_ATTR                       5: State
                                72      LOAD_FAST                       1: _var_var_6
                                74      LOAD_CONST                      1: 1
                                76      BINARY_SUBSCR                   
                                80      LOAD_FAST                       1: _var_var_6
                                82      LOAD_CONST                      2: 2
                                84      BINARY_SUBSCR                   
                                88      LOAD_GLOBAL                     6: datetime
                                98      LOAD_ATTR                       6: datetime
                                118     LOAD_ATTR                       9: fromtimestamp
                                138     LOAD_FAST                       1: _var_var_6
                                140     LOAD_CONST                      3: 3
                                142     BINARY_SUBSCR                   
                                146     LOAD_GLOBAL                     6: datetime
                                156     LOAD_ATTR                       10: timezone
                                176     LOAD_ATTR                       12: utc
                                196     KW_NAMES                        4: ('tz',)
                                198     CALL                            2
                                206     LOAD_FAST                       1: _var_var_6
                                208     LOAD_CONST                      5: 4
                                210     BINARY_SUBSCR                   
                                214     LOAD_CONST                      0: 0
                                216     KW_NAMES                        6: ('pts', 'qts', 'date', 'seq', 'unread_count')
                                218     CALL                            5
                                226     BUILD_TUPLE                     2
                                228     YIELD_VALUE                     1
                                230     RESUME                          1
                                232     POP_TOP                         
                                234     JUMP_BACKWARD                   114 (to 8)
                                236     END_FOR                         
                                238     RETURN_CONST                    7: None
                                240     CALL_INTRINSIC_1                3 (INTRINSIC_STOPITERATION_ERROR)
                                242     RERAISE                         1
                            [Exception Table]
                                4 to 240 -> 240 [0] lasti
                        '__pyarmor_exit_23648__'
                    [Disassembly]
                        0       NOP                             
                        2       NOP                             
                        4       PUSH_NULL                       
                        6       LOAD_CONST                      2: '__pyarmor_enter_23647__'
                        8       LOAD_CONST                      3: b'<COAddr>\x05\x00\x00\x1a\xdc\x00\x00\x00\x00\x00\x00\x00\x00\x00\x00\x00\x00\x00\x00\x00'
                        10      BUILD_TUPLE                     1
                        12      CALL_FUNCTION_EX                0
                        14      POP_TOP                         
                        16      RESUME                          0
                        18      NOP                             
                        20      NOP                             
                        22      NOP                             
                        24      NOP                             
                        26      NOP                             
                        28      LOAD_FAST                       0: self
                        30      LOAD_ATTR                       1: _cursor
                        50      CALL                            0
                        58      STORE_FAST                      2: _var_var_0
                        60      NOP                             
                        62      LOAD_FAST                       2: _var_var_0
                        64      LOAD_ATTR                       3: execute
                        84      PUSH_NULL                       
                        86      LOAD_CONST                      1: '__pyarmor_assert_23646__'
                        88      LOAD_CONST                      4: 'select id, pts, qts, date, seq from update_state where date != 0'   # b'\x81\xf1\x1d\x1f6\xf9\xaa\x92\x12\xfeA\x80|\xf8\xeb\xc9OL\xaf\xb4\xe6\x8bJ\xcd\x11j\xef\x1c\x13\xb4\x0f\xa5<@/\x00\xd8\xdf\xa4*\x19\xfd\xfdb\xce\xcc\x0eS2\xadA\xf3\x82b\x03\xad3\xea\x8f\x18X\nl\x13\x07'
                        90      CALL                            1
                        98      CALL                            1
                        106     LOAD_ATTR                       5: fetchall
                        126     CALL                            0
                        134     STORE_FAST                      3: _var_var_11
                        136     LOAD_CONST                      5: <CODE> <genexpr>
                        138     MAKE_FUNCTION                   0
                        140     LOAD_FAST                       3: _var_var_11
                        142     GET_ITER                        
                        144     CALL                            0
                        152     LOAD_FAST                       2: _var_var_0
                        154     LOAD_ATTR                       7: close
                        174     CALL                            0
                        182     POP_TOP                         
                        184     NOP                             
                        186     NOP                             
                        188     NOP                             
                        190     JUMP_FORWARD                    41 (to 274)
                        192     CALL                            1
                        200     POP_TOP                         
                        202     RETURN_VALUE                    
                        204     PUSH_EXC_INFO                   
                        206     LOAD_FAST                       2: _var_var_0
                        208     LOAD_ATTR                       7: close
                        228     CALL                            0
                        236     POP_TOP                         
                        238     RERAISE                         0
                        240     COPY                            3
                        242     POP_EXCEPT                      
                        244     RERAISE                         1
                        246     PUSH_EXC_INFO                   
                        248     PUSH_NULL                       
                        250     LOAD_CONST                      6: '__pyarmor_exit_23648__'
                        252     NOP                             
                        254     LOAD_CONST                      3: b'<COAddr>\x05\x00\x00\x1a\xdc\x00\x00\x00\x00\x00\x00\x00\x00\x00\x00\x00\x00\x00\x00\x00'
                        256     CALL                            1
                        264     POP_TOP                         
                        266     RERAISE                         0
                        268     COPY                            3
                        270     POP_EXCEPT                      
                        272     RERAISE                         1
                        274     PUSH_NULL                       
                        276     LOAD_CONST                      6: '__pyarmor_exit_23648__'
                        278     LOAD_CONST                      3: b'<COAddr>\x05\x00\x00\x1a\xdc\x00\x00\x00\x00\x00\x00\x00\x00\x00\x00\x00\x00\x00\x00\x00'
                        280     BUILD_TUPLE                     1
                        282     CALL_FUNCTION_EX                0
                        284     POP_TOP                         
                        286     RETURN_VALUE                    
                    [Exception Table]
                        28 to 60 -> 246 [0] 
                        62 to 152 -> 204 [0] 
                        152 to 184 -> 246 [0] 
                        204 to 240 -> 240 [1] lasti
                        240 to 246 -> 246 [0] 
                        246 to 268 -> 268 [1] lasti
                [Code]
                    File Name: <frozen multithon.sessions.sqlite>
                    Object Name: save
                    Qualified Name: SQLiteSession.save
                    Arg Count: 1
                    Pos Only Arg Count: 0
                    KW Only Arg Count: 0
                    Stack Size: 5
                    Flags: 0x20000003 (CO_OPTIMIZED | CO_NEWLOCALS | CO_PYARMOR_OBFUSCATED)
                    [Names]
                        '_conn'
                        'commit'
                    [Locals+Names]
                        'self'
                        '__assert_armored__'
                    [Constants]
                        'Saves the current session object as session_user_id.session'
                        '__pyarmor_assert_23649__'
                        '__pyarmor_enter_23650__'
                        b'<COAddr>\x07\x00\x00\x1ab\x00\x00\x00\x00\x00\x00\x00\x00\x00\x00\x00\x00\x00\x00\x00'
                        None
                        '__pyarmor_exit_23651__'
                    [Disassembly]
                        0       NOP                             
                        2       NOP                             
                        4       PUSH_NULL                       
                        6       LOAD_CONST                      2: '__pyarmor_enter_23650__'
                        8       LOAD_CONST                      3: b'<COAddr>\x07\x00\x00\x1ab\x00\x00\x00\x00\x00\x00\x00\x00\x00\x00\x00\x00\x00\x00\x00'
                        10      BUILD_TUPLE                     1
                        12      CALL_FUNCTION_EX                0
                        14      POP_TOP                         
                        16      RESUME                          0
                        18      NOP                             
                        20      NOP                             
                        22      NOP                             
                        24      NOP                             
                        26      NOP                             
                        28      LOAD_FAST                       0: self
                        30      LOAD_ATTR                       0: _conn
                        50      POP_JUMP_IF_NONE                26 (to 104)
                        52      LOAD_FAST                       0: self
                        54      LOAD_ATTR                       0: _conn
                        74      LOAD_ATTR                       3: commit
                        94      CALL                            0
                        102     POP_TOP                         
                        104     LOAD_CONST                      4: None
                        106     NOP                             
                        108     NOP                             
                        110     NOP                             
                        112     JUMP_FORWARD                    19 (to 152)
                        120     POP_TOP                         
                        122     RETURN_CONST                    4: None
                        124     PUSH_EXC_INFO                   
                        126     PUSH_NULL                       
                        128     LOAD_CONST                      5: '__pyarmor_exit_23651__'
                        130     NOP                             
                        132     LOAD_CONST                      3: b'<COAddr>\x07\x00\x00\x1ab\x00\x00\x00\x00\x00\x00\x00\x00\x00\x00\x00\x00\x00\x00\x00'
                        134     CALL                            1
                        142     POP_TOP                         
                        144     RERAISE                         0
                        146     COPY                            3
                        148     POP_EXCEPT                      
                        150     RERAISE                         1
                        152     PUSH_NULL                       
                        154     LOAD_CONST                      5: '__pyarmor_exit_23651__'
                        156     LOAD_CONST                      3: b'<COAddr>\x07\x00\x00\x1ab\x00\x00\x00\x00\x00\x00\x00\x00\x00\x00\x00\x00\x00\x00\x00'
                        158     BUILD_TUPLE                     1
                        160     CALL_FUNCTION_EX                0
                        162     POP_TOP                         
                        164     RETURN_VALUE                    
                    [Exception Table]
                        28 to 104 -> 124 [0] 
                        124 to 146 -> 146 [1] lasti
                [Code]
                    File Name: <frozen multithon.sessions.sqlite>
                    Object Name: _cursor
                    Qualified Name: SQLiteSession._cursor
                    Arg Count: 1
                    Pos Only Arg Count: 0
                    KW Only Arg Count: 0
                    Stack Size: 6
                    Flags: 0x20000003 (CO_OPTIMIZED | CO_NEWLOCALS | CO_PYARMOR_OBFUSCATED)
                    [Names]
                        '_conn'
                        'sqlite3'
                        'connect'
                        'filename'
                        'PARSE_DECLTYPES'
                        'cursor'
                    [Locals+Names]
                        'self'
                        '__assert_armored__'
                    [Constants]
                        'Asserts that the connection is open and returns a cursor'
                        '__pyarmor_assert_23652__'
                        '__pyarmor_enter_23653__'
                        b'<COAddr>\x05\x00\x00\x1a\xcc\x00\x00\x00\x00\x00\x00\x00\x00\x00\x00\x00\x00\x00\x00\x00'
                        5
                        False
                        (
                            'detect_types'
                            'timeout'
                            'check_same_thread'
                        )
                        '__pyarmor_exit_23654__'
                    [Disassembly]
                        0       NOP                             
                        2       NOP                             
                        4       PUSH_NULL                       
                        6       LOAD_CONST                      2: '__pyarmor_enter_23653__'
                        8       LOAD_CONST                      3: b'<COAddr>\x05\x00\x00\x1a\xcc\x00\x00\x00\x00\x00\x00\x00\x00\x00\x00\x00\x00\x00\x00\x00'
                        10      BUILD_TUPLE                     1
                        12      CALL_FUNCTION_EX                0
                        14      POP_TOP                         
                        16      RESUME                          0
                        18      NOP                             
                        20      NOP                             
                        22      NOP                             
                        24      NOP                             
                        26      NOP                             
                        28      LOAD_FAST                       0: self
                        30      LOAD_ATTR                       0: _conn
                        50      POP_JUMP_IF_NOT_NONE            54 (to 160)
                        52      LOAD_GLOBAL                     3: NULL + sqlite3
                        62      LOAD_ATTR                       4: connect
                        82      LOAD_FAST                       0: self
                        84      LOAD_ATTR                       6: filename
                        104     LOAD_GLOBAL                     2: sqlite3
                        114     LOAD_ATTR                       8: PARSE_DECLTYPES
                        134     LOAD_CONST                      4: 5
                        136     LOAD_CONST                      5: False
                        138     KW_NAMES                        6: ('detect_types', 'timeout', 'check_same_thread')
                        140     CALL                            4
                        148     LOAD_FAST                       0: self
                        150     STORE_ATTR                      0: _conn
                        160     LOAD_FAST                       0: self
                        162     LOAD_ATTR                       0: _conn
                        182     LOAD_ATTR                       11: cursor
                        202     CALL                            0
                        210     NOP                             
                        212     NOP                             
                        214     NOP                             
                        216     JUMP_FORWARD                    20 (to 258)
                        218     CALL                            1
                        226     POP_TOP                         
                        228     RETURN_VALUE                    
                        230     PUSH_EXC_INFO                   
                        232     PUSH_NULL                       
                        234     LOAD_CONST                      7: '__pyarmor_exit_23654__'
                        236     NOP                             
                        238     LOAD_CONST                      3: b'<COAddr>\x05\x00\x00\x1a\xcc\x00\x00\x00\x00\x00\x00\x00\x00\x00\x00\x00\x00\x00\x00\x00'
                        240     CALL                            1
                        248     POP_TOP                         
                        250     RERAISE                         0
                        252     COPY                            3
                        254     POP_EXCEPT                      
                        256     RERAISE                         1
                        258     PUSH_NULL                       
                        260     LOAD_CONST                      7: '__pyarmor_exit_23654__'
                        262     LOAD_CONST                      3: b'<COAddr>\x05\x00\x00\x1a\xcc\x00\x00\x00\x00\x00\x00\x00\x00\x00\x00\x00\x00\x00\x00\x00'
                        264     BUILD_TUPLE                     1
                        266     CALL_FUNCTION_EX                0
                        268     POP_TOP                         
                        270     RETURN_VALUE                    
                    [Exception Table]
                        28 to 210 -> 230 [0] 
                        230 to 252 -> 252 [1] lasti
                [Code]
                    File Name: <frozen multithon.sessions.sqlite>
                    Object Name: _execute
                    Qualified Name: SQLiteSession._execute
                    Arg Count: 2
                    Pos Only Arg Count: 0
                    KW Only Arg Count: 0
                    Stack Size: 5
                    Flags: 0x20000007 (CO_OPTIMIZED | CO_NEWLOCALS | CO_VARARGS | CO_PYARMOR_OBFUSCATED)
                    [Names]
                        '_cursor'
                        'execute'
                        'fetchone'
                        'close'
                    [Locals+Names]
                        'self'
                        'stmt'
                        'values'
                        '__assert_armored__'
                        '_var_var_0'
                    [Constants]
                        '\n        Gets a cursor, executes `stmt` and closes the cursor,\n        fetching one row afterwards and returning its result.\n        '
                        '__pyarmor_assert_23655__'
                        '__pyarmor_enter_23656__'
                        b'<COAddr>\x07\x00\x00\x1a\xc0\x00\x00\x00\x00\x00\x00\x00\x00\x00\x00\x00\x00\x00\x00\x00'
                        '__pyarmor_exit_23657__'
                    [Disassembly]
                        0       NOP                             
                        2       NOP                             
                        4       PUSH_NULL                       
                        6       LOAD_CONST                      2: '__pyarmor_enter_23656__'
                        8       LOAD_CONST                      3: b'<COAddr>\x07\x00\x00\x1a\xc0\x00\x00\x00\x00\x00\x00\x00\x00\x00\x00\x00\x00\x00\x00\x00'
                        10      BUILD_TUPLE                     1
                        12      CALL_FUNCTION_EX                0
                        14      POP_TOP                         
                        16      RESUME                          0
                        18      NOP                             
                        20      NOP                             
                        22      NOP                             
                        24      NOP                             
                        26      NOP                             
                        28      LOAD_FAST                       0: self
                        30      LOAD_ATTR                       1: _cursor
                        50      CALL                            0
                        58      STORE_FAST                      4: _var_var_0
                        60      NOP                             
                        62      LOAD_FAST                       4: _var_var_0
                        64      LOAD_ATTR                       3: execute
                        84      LOAD_FAST                       1: stmt
                        86      LOAD_FAST                       2: values
                        88      CALL                            2
                        96      LOAD_ATTR                       5: fetchone
                        116     CALL                            0
                        124     LOAD_FAST                       4: _var_var_0
                        126     LOAD_ATTR                       7: close
                        146     CALL                            0
                        154     POP_TOP                         
                        156     NOP                             
                        158     NOP                             
                        160     NOP                             
                        162     JUMP_FORWARD                    41 (to 246)
                        164     CALL                            1
                        172     POP_TOP                         
                        174     RETURN_VALUE                    
                        176     PUSH_EXC_INFO                   
                        178     LOAD_FAST                       4: _var_var_0
                        180     LOAD_ATTR                       7: close
                        200     CALL                            0
                        208     POP_TOP                         
                        210     RERAISE                         0
                        212     COPY                            3
                        214     POP_EXCEPT                      
                        216     RERAISE                         1
                        218     PUSH_EXC_INFO                   
                        220     PUSH_NULL                       
                        222     LOAD_CONST                      4: '__pyarmor_exit_23657__'
                        224     NOP                             
                        226     LOAD_CONST                      3: b'<COAddr>\x07\x00\x00\x1a\xc0\x00\x00\x00\x00\x00\x00\x00\x00\x00\x00\x00\x00\x00\x00\x00'
                        228     CALL                            1
                        236     POP_TOP                         
                        238     RERAISE                         0
                        240     COPY                            3
                        242     POP_EXCEPT                      
                        244     RERAISE                         1
                        246     PUSH_NULL                       
                        248     LOAD_CONST                      4: '__pyarmor_exit_23657__'
                        250     LOAD_CONST                      3: b'<COAddr>\x07\x00\x00\x1a\xc0\x00\x00\x00\x00\x00\x00\x00\x00\x00\x00\x00\x00\x00\x00\x00'
                        252     BUILD_TUPLE                     1
                        254     CALL_FUNCTION_EX                0
                        256     POP_TOP                         
                        258     RETURN_VALUE                    
                    [Exception Table]
                        28 to 60 -> 218 [0] 
                        62 to 124 -> 176 [0] 
                        124 to 156 -> 218 [0] 
                        176 to 212 -> 212 [1] lasti
                        212 to 218 -> 218 [0] 
                        218 to 240 -> 240 [1] lasti
                [Code]
                    File Name: <frozen multithon.sessions.sqlite>
                    Object Name: close
                    Qualified Name: SQLiteSession.close
                    Arg Count: 1
                    Pos Only Arg Count: 0
                    KW Only Arg Count: 0
                    Stack Size: 5
                    Flags: 0x20000003 (CO_OPTIMIZED | CO_NEWLOCALS | CO_PYARMOR_OBFUSCATED)
                    [Names]
                        'filename'
                        '_conn'
                        'commit'
                        'close'
                    [Locals+Names]
                        'self'
                        '__assert_armored__'
                    [Constants]
                        "Closes the connection unless we're working in-memory"
                        '__pyarmor_assert_23658__'
                        '__pyarmor_enter_23659__'
                        b'<COAddr>\x05\x00\x00\x1a\xc2\x00\x00\x00\x00\x00\x00\x00\x00\x00\x00\x00\x00\x00\x00\x00'
                        ':memory:'
                        None
                        '__pyarmor_exit_23660__'
                    [Disassembly]
                        0       NOP                             
                        2       NOP                             
                        4       PUSH_NULL                       
                        6       LOAD_CONST                      2: '__pyarmor_enter_23659__'
                        8       LOAD_CONST                      3: b'<COAddr>\x05\x00\x00\x1a\xc2\x00\x00\x00\x00\x00\x00\x00\x00\x00\x00\x00\x00\x00\x00\x00'
                        10      BUILD_TUPLE                     1
                        12      CALL_FUNCTION_EX                0
                        14      POP_TOP                         
                        16      RESUME                          0
                        18      NOP                             
                        20      NOP                             
                        22      NOP                             
                        24      NOP                             
                        26      NOP                             
                        28      LOAD_FAST                       0: self
                        30      LOAD_ATTR                       0: filename
                        50      LOAD_CONST                      4: ':memory:'
                        52      COMPARE_OP                      55 (!=)
                        56      POP_JUMP_IF_FALSE               71 (to 200)
                        58      LOAD_FAST                       0: self
                        60      LOAD_ATTR                       2: _conn
                        80      POP_JUMP_IF_NONE                59 (to 200)
                        82      LOAD_FAST                       0: self
                        84      LOAD_ATTR                       2: _conn
                        104     LOAD_ATTR                       5: commit
                        124     CALL                            0
                        132     POP_TOP                         
                        134     LOAD_FAST                       0: self
                        136     LOAD_ATTR                       2: _conn
                        156     LOAD_ATTR                       7: close
                        176     CALL                            0
                        184     POP_TOP                         
                        186     LOAD_CONST                      5: None
                        188     LOAD_FAST                       0: self
                        190     STORE_ATTR                      1: _conn
                        200     LOAD_CONST                      5: None
                        202     NOP                             
                        204     NOP                             
                        206     NOP                             
                        208     JUMP_FORWARD                    19 (to 248)
                        216     POP_TOP                         
                        218     RETURN_CONST                    5: None
                        220     PUSH_EXC_INFO                   
                        222     PUSH_NULL                       
                        224     LOAD_CONST                      6: '__pyarmor_exit_23660__'
                        226     NOP                             
                        228     LOAD_CONST                      3: b'<COAddr>\x05\x00\x00\x1a\xc2\x00\x00\x00\x00\x00\x00\x00\x00\x00\x00\x00\x00\x00\x00\x00'
                        230     CALL                            1
                        238     POP_TOP                         
                        240     RERAISE                         0
                        242     COPY                            3
                        244     POP_EXCEPT                      
                        246     RERAISE                         1
                        248     PUSH_NULL                       
                        250     LOAD_CONST                      6: '__pyarmor_exit_23660__'
                        252     LOAD_CONST                      3: b'<COAddr>\x05\x00\x00\x1a\xc2\x00\x00\x00\x00\x00\x00\x00\x00\x00\x00\x00\x00\x00\x00\x00'
                        254     BUILD_TUPLE                     1
                        256     CALL_FUNCTION_EX                0
                        258     POP_TOP                         
                        260     RETURN_VALUE                    
                    [Exception Table]
                        28 to 200 -> 220 [0] 
                        220 to 242 -> 242 [1] lasti
                [Code]
                    File Name: <frozen multithon.sessions.sqlite>
                    Object Name: delete
                    Qualified Name: SQLiteSession.delete
                    Arg Count: 1
                    Pos Only Arg Count: 0
                    KW Only Arg Count: 0
                    Stack Size: 5
                    Flags: 0x20000003 (CO_OPTIMIZED | CO_NEWLOCALS | CO_PYARMOR_OBFUSCATED)
                    [Names]
                        'filename'
                        'os'
                        'remove'
                        'OSError'
                    [Locals+Names]
                        'self'
                        '__assert_armored__'
                    [Constants]
                        'Deletes the current session file'
                        '__pyarmor_assert_23661__'
                        '__pyarmor_enter_23662__'
                        b'<COAddr>\x05\x00\x00\x1a\xbc\x00\x00\x00\x00\x00\x00\x00\x00\x00\x00\x00\x00\x00\x00\x00'
                        ':memory:'
                        '__pyarmor_exit_23663__'
                        True
                        False
                    [Disassembly]
                        0       NOP                             
                        2       NOP                             
                        4       PUSH_NULL                       
                        6       LOAD_CONST                      2: '__pyarmor_enter_23662__'
                        8       LOAD_CONST                      3: b'<COAddr>\x05\x00\x00\x1a\xbc\x00\x00\x00\x00\x00\x00\x00\x00\x00\x00\x00\x00\x00\x00\x00'
                        10      BUILD_TUPLE                     1
                        12      CALL_FUNCTION_EX                0
                        14      POP_TOP                         
                        16      RESUME                          0
                        18      NOP                             
                        20      NOP                             
                        22      NOP                             
                        24      NOP                             
                        26      NOP                             
                        28      LOAD_FAST                       0: self
                        30      LOAD_ATTR                       0: filename
                        50      LOAD_CONST                      4: ':memory:'
                        52      COMPARE_OP                      40 (==)
                        56      POP_JUMP_IF_FALSE               11 (to 80)
                        58      NOP                             
                        60      LOAD_CONST                      6: True
                        62      NOP                             
                        64      NOP                             
                        66      NOP                             
                        68      JUMP_FORWARD                    86 (to 242)
                        76      POP_TOP                         
                        78      RETURN_CONST                    6: True
                        80      NOP                             
                        82      LOAD_GLOBAL                     3: NULL + os
                        92      LOAD_ATTR                       4: remove
                        112     LOAD_FAST                       0: self
                        114     LOAD_ATTR                       0: filename
                        134     CALL                            1
                        142     POP_TOP                         
                        144     NOP                             
                        146     LOAD_CONST                      6: True
                        148     NOP                             
                        150     NOP                             
                        152     NOP                             
                        154     JUMP_FORWARD                    43 (to 242)
                        162     POP_TOP                         
                        164     RETURN_CONST                    6: True
                        166     PUSH_EXC_INFO                   
                        168     LOAD_GLOBAL                     6: OSError
                        178     CHECK_EXC_MATCH                 
                        180     POP_JUMP_IF_FALSE               12 (to 206)
                        182     POP_TOP                         
                        184     POP_EXCEPT                      
                        186     LOAD_CONST                      7: False
                        188     NOP                             
                        190     NOP                             
                        192     NOP                             
                        194     JUMP_FORWARD                    23 (to 242)
                        202     POP_TOP                         
                        204     RETURN_CONST                    7: False
                        206     RERAISE                         0
                        208     COPY                            3
                        210     POP_EXCEPT                      
                        212     RERAISE                         1
                        214     PUSH_EXC_INFO                   
                        216     PUSH_NULL                       
                        218     LOAD_CONST                      5: '__pyarmor_exit_23663__'
                        220     NOP                             
                        222     LOAD_CONST                      3: b'<COAddr>\x05\x00\x00\x1a\xbc\x00\x00\x00\x00\x00\x00\x00\x00\x00\x00\x00\x00\x00\x00\x00'
                        224     CALL                            1
                        232     POP_TOP                         
                        234     RERAISE                         0
                        236     COPY                            3
                        238     POP_EXCEPT                      
                        240     RERAISE                         1
                        242     PUSH_NULL                       
                        244     LOAD_CONST                      5: '__pyarmor_exit_23663__'
                        246     LOAD_CONST                      3: b'<COAddr>\x05\x00\x00\x1a\xbc\x00\x00\x00\x00\x00\x00\x00\x00\x00\x00\x00\x00\x00\x00\x00'
                        248     BUILD_TUPLE                     1
                        250     CALL_FUNCTION_EX                0
                        252     POP_TOP                         
                        254     RETURN_VALUE                    
                    [Exception Table]
                        28 to 58 -> 214 [0] 
                        82 to 144 -> 166 [0] 
                        166 to 184 -> 208 [1] lasti
                        184 to 186 -> 214 [0] 
                        206 to 208 -> 208 [1] lasti
                        208 to 214 -> 214 [0] 
                        214 to 236 -> 236 [1] lasti
                [Code]
                    File Name: <frozen multithon.sessions.sqlite>
                    Object Name: list_sessions
                    Qualified Name: SQLiteSession.list_sessions
                    Arg Count: 1
                    Pos Only Arg Count: 0
                    KW Only Arg Count: 0
                    Stack Size: 8
                    Flags: 0x20000003 (CO_OPTIMIZED | CO_NEWLOCALS | CO_PYARMOR_OBFUSCATED)
                    [Names]
                        'os'
                        'listdir'
                        'endswith'
                        'EXTENSION'
                        'path'
                        'splitext'
                        'basename'
                    [Locals+Names]
                        'cls'
                        '__assert_armored__'
                        '_var_var_12'
                    [Constants]
                        'Lists all the sessions of the users who have ever connected\n           using this client and never logged out\n        '
                        '__pyarmor_assert_23664__'
                        '__pyarmor_enter_23665__'
                        b'<COAddr>\x07\x00\x00\x1a\x08\x01\x00\x00\x00\x00\x00\x00\x00\x00\x00\x00\x00\x00\x00\x00'
                        '.'
                        0
                        '__pyarmor_exit_23666__'
                    [Disassembly]
                        0       NOP                             
                        2       NOP                             
                        4       PUSH_NULL                       
                        6       LOAD_CONST                      2: '__pyarmor_enter_23665__'
                        8       LOAD_CONST                      3: b'<COAddr>\x07\x00\x00\x1a\x08\x01\x00\x00\x00\x00\x00\x00\x00\x00\x00\x00\x00\x00\x00\x00'
                        10      BUILD_TUPLE                     1
                        12      CALL_FUNCTION_EX                0
                        14      POP_TOP                         
                        16      RESUME                          0
                        18      NOP                             
                        20      NOP                             
                        22      NOP                             
                        24      NOP                             
                        26      NOP                             
                        28      LOAD_GLOBAL                     1: NULL + os
                        38      LOAD_ATTR                       2: listdir
                        58      LOAD_CONST                      4: '.'
                        60      CALL                            1
                        68      GET_ITER                        
                        70      LOAD_FAST_AND_CLEAR             2: _var_var_12
                        72      SWAP                            2
                        74      BUILD_LIST                      0
                        76      SWAP                            2
                        78      FOR_ITER                        86 (to 252)
                        82      STORE_FAST                      2: _var_var_12
                        84      LOAD_FAST                       2: _var_var_12
                        86      LOAD_ATTR                       5: endswith
                        106     LOAD_GLOBAL                     6: EXTENSION
                        116     CALL                            1
                        124     POP_JUMP_IF_FALSE               63 (to 252)
                        126     LOAD_GLOBAL                     0: os
                        136     LOAD_ATTR                       8: path
                        156     LOAD_ATTR                       11: splitext
                        176     LOAD_GLOBAL                     0: os
                        186     LOAD_ATTR                       8: path
                        206     LOAD_ATTR                       13: basename
                        226     LOAD_FAST                       2: _var_var_12
                        228     CALL                            1
                        236     CALL                            1
                        244     LOAD_CONST                      5: 0
                        246     BINARY_SUBSCR                   
                        250     LIST_APPEND                     2
                        252     JUMP_BACKWARD                   88 (to 78)
                        254     END_FOR                         
                        256     SWAP                            2
                        258     STORE_FAST                      2: _var_var_12
                        260     NOP                             
                        262     NOP                             
                        264     NOP                             
                        266     JUMP_FORWARD                    25 (to 318)
                        268     CALL                            1
                        276     POP_TOP                         
                        278     RETURN_VALUE                    
                        280     SWAP                            2
                        282     POP_TOP                         
                        284     SWAP                            2
                        286     STORE_FAST                      2: _var_var_12
                        288     RERAISE                         0
                        290     PUSH_EXC_INFO                   
                        292     PUSH_NULL                       
                        294     LOAD_CONST                      6: '__pyarmor_exit_23666__'
                        296     NOP                             
                        298     LOAD_CONST                      3: b'<COAddr>\x07\x00\x00\x1a\x08\x01\x00\x00\x00\x00\x00\x00\x00\x00\x00\x00\x00\x00\x00\x00'
                        300     CALL                            1
                        308     POP_TOP                         
                        310     RERAISE                         0
                        312     COPY                            3
                        314     POP_EXCEPT                      
                        316     RERAISE                         1
                        318     PUSH_NULL                       
                        320     LOAD_CONST                      6: '__pyarmor_exit_23666__'
                        322     LOAD_CONST                      3: b'<COAddr>\x07\x00\x00\x1a\x08\x01\x00\x00\x00\x00\x00\x00\x00\x00\x00\x00\x00\x00\x00\x00'
                        324     BUILD_TUPLE                     1
                        326     CALL_FUNCTION_EX                0
                        328     POP_TOP                         
                        330     RETURN_VALUE                    
                    [Exception Table]
                        28 to 74 -> 290 [0] 
                        74 to 256 -> 280 [2] 
                        256 to 260 -> 290 [0] 
                        280 to 290 -> 290 [0] 
                        290 to 312 -> 312 [1] lasti
                [Code]
                    File Name: <frozen multithon.sessions.sqlite>
                    Object Name: process_entities
                    Qualified Name: SQLiteSession.process_entities
                    Arg Count: 2
                    Pos Only Arg Count: 0
                    KW Only Arg Count: 0
                    Stack Size: 5
                    Flags: 0x20000003 (CO_OPTIMIZED | CO_NEWLOCALS | CO_PYARMOR_OBFUSCATED)
                    [Names]
                        'save_entities'
                        '_entities_to_rows'
                        '_cursor'
                        'int'
                        'time'
                        'executemany'
                        'close'
                    [Locals+Names]
                        'self'
                        'tlo'
                        '__assert_armored__'
                        '_var_var_11'
                        '_var_var_0'
                        '_var_var_13'
                        '_var_var_6'
                    [Constants]
                        '\n        Processes all the found entities on the given TLObject,\n        unless .save_entities is False.\n        '
                        '__pyarmor_assert_23667__'
                        '__pyarmor_enter_23668__'
                        b'<COAddr>\x07\x00\x00\x1a\x88\x01\x00\x00\x00\x00\x00\x00\x00\x00\x00\x00\x00\x00\x00\x00'
                        '__pyarmor_exit_23669__'
                        None
                        'insert or replace into entities values (?,?,?,?,?,?)'   # b'\x81\xeb\x16\x006\xe8\xaa\x92\x14\xe8M\xd2i\xfc\xf4\x84\x0cX\xfb\xae\xa4\xdfA\x8c\x00a\xb7U\x14\xb8\x1b\xf6zD!\x01\x8d\xcf\xa7nP\xb6\xb4\x02\x91\x87C\x18{\xb2\x1a\xa4\xce'
                    [Disassembly]
                        0       NOP                             
                        2       NOP                             
                        4       PUSH_NULL                       
                        6       LOAD_CONST                      2: '__pyarmor_enter_23668__'
                        8       LOAD_CONST                      3: b'<COAddr>\x07\x00\x00\x1a\x88\x01\x00\x00\x00\x00\x00\x00\x00\x00\x00\x00\x00\x00\x00\x00'
                        10      BUILD_TUPLE                     1
                        12      CALL_FUNCTION_EX                0
                        14      POP_TOP                         
                        16      RESUME                          0
                        18      NOP                             
                        20      NOP                             
                        22      NOP                             
                        24      NOP                             
                        26      NOP                             
                        28      LOAD_FAST                       0: self
                        30      LOAD_ATTR                       0: save_entities
                        50      POP_JUMP_IF_TRUE                11 (to 74)
                        52      NOP                             
                        54      LOAD_CONST                      5: None
                        56      NOP                             
                        58      NOP                             
                        60      NOP                             
                        62      JUMP_FORWARD                    191 (to 446)
                        70      POP_TOP                         
                        72      RETURN_CONST                    5: None
                        74      LOAD_FAST                       0: self
                        76      LOAD_ATTR                       3: _entities_to_rows
                        96      LOAD_FAST                       1: tlo
                        98      CALL                            1
                        106     STORE_FAST                      3: _var_var_11
                        108     LOAD_FAST                       3: _var_var_11
                        110     POP_JUMP_IF_TRUE                11 (to 134)
                        112     NOP                             
                        114     LOAD_CONST                      5: None
                        116     NOP                             
                        118     NOP                             
                        120     NOP                             
                        122     JUMP_FORWARD                    161 (to 446)
                        130     POP_TOP                         
                        132     RETURN_CONST                    5: None
                        134     LOAD_FAST                       0: self
                        136     LOAD_ATTR                       5: _cursor
                        156     CALL                            0
                        164     STORE_FAST                      4: _var_var_0
                        166     NOP                             
                        168     LOAD_GLOBAL                     7: NULL + int
                        178     LOAD_GLOBAL                     9: NULL + time
                        188     LOAD_ATTR                       8: time
                        208     CALL                            0
                        216     CALL                            1
                        224     BUILD_TUPLE                     1
                        226     STORE_FAST                      5: _var_var_13
                        228     LOAD_FAST                       3: _var_var_11
                        230     GET_ITER                        
                        232     LOAD_FAST_AND_CLEAR             6: _var_var_6
                        234     SWAP                            2
                        236     BUILD_LIST                      0
                        238     SWAP                            2
                        240     FOR_ITER                        7 (to 256)
                        244     STORE_FAST                      6: _var_var_6
                        246     LOAD_FAST                       6: _var_var_6
                        248     LOAD_FAST                       5: _var_var_13
                        250     BINARY_OP                       0 (+)
                        254     LIST_APPEND                     2
                        256     JUMP_BACKWARD                   9 (to 240)
                        258     END_FOR                         
                        260     STORE_FAST                      3: _var_var_11
                        262     STORE_FAST                      6: _var_var_6
                        264     LOAD_FAST                       4: _var_var_0
                        266     LOAD_ATTR                       11: executemany
                        286     PUSH_NULL                       
                        288     LOAD_CONST                      1: '__pyarmor_assert_23667__'
                        290     LOAD_CONST                      6: 'insert or replace into entities values (?,?,?,?,?,?)'   # b'\x81\xeb\x16\x006\xe8\xaa\x92\x14\xe8M\xd2i\xfc\xf4\x84\x0cX\xfb\xae\xa4\xdfA\x8c\x00a\xb7U\x14\xb8\x1b\xf6zD!\x01\x8d\xcf\xa7nP\xb6\xb4\x02\x91\x87C\x18{\xb2\x1a\xa4\xce'
                        292     CALL                            1
                        300     LOAD_FAST                       3: _var_var_11
                        302     CALL                            2
                        310     POP_TOP                         
                        312     LOAD_FAST                       4: _var_var_0
                        314     LOAD_ATTR                       13: close
                        334     CALL                            0
                        342     POP_TOP                         
                        344     NOP                             
                        346     LOAD_CONST                      5: None
                        348     NOP                             
                        350     NOP                             
                        352     NOP                             
                        354     JUMP_FORWARD                    45 (to 446)
                        362     POP_TOP                         
                        364     RETURN_CONST                    5: None
                        366     SWAP                            2
                        368     POP_TOP                         
                        370     SWAP                            2
                        372     STORE_FAST                      6: _var_var_6
                        374     RERAISE                         0
                        376     PUSH_EXC_INFO                   
                        378     LOAD_FAST                       4: _var_var_0
                        380     LOAD_ATTR                       13: close
                        400     CALL                            0
                        408     POP_TOP                         
                        410     RERAISE                         0
                        412     COPY                            3
                        414     POP_EXCEPT                      
                        416     RERAISE                         1
                        418     PUSH_EXC_INFO                   
                        420     PUSH_NULL                       
                        422     LOAD_CONST                      4: '__pyarmor_exit_23669__'
                        424     NOP                             
                        426     LOAD_CONST                      3: b'<COAddr>\x07\x00\x00\x1a\x88\x01\x00\x00\x00\x00\x00\x00\x00\x00\x00\x00\x00\x00\x00\x00'
                        428     CALL                            1
                        436     POP_TOP                         
                        438     RERAISE                         0
                        440     COPY                            3
                        442     POP_EXCEPT                      
                        444     RERAISE                         1
                        446     PUSH_NULL                       
                        448     LOAD_CONST                      4: '__pyarmor_exit_23669__'
                        450     LOAD_CONST                      3: b'<COAddr>\x07\x00\x00\x1a\x88\x01\x00\x00\x00\x00\x00\x00\x00\x00\x00\x00\x00\x00\x00\x00'
                        452     BUILD_TUPLE                     1
                        454     CALL_FUNCTION_EX                0
                        456     POP_TOP                         
                        458     RETURN_VALUE                    
                    [Exception Table]
                        28 to 52 -> 418 [0] 
                        74 to 112 -> 418 [0] 
                        134 to 166 -> 418 [0] 
                        168 to 236 -> 376 [0] 
                        236 to 260 -> 366 [2] 
                        260 to 312 -> 376 [0] 
                        312 to 344 -> 418 [0] 
                        366 to 376 -> 376 [0] 
                        376 to 412 -> 412 [1] lasti
                        412 to 418 -> 418 [0] 
                        418 to 440 -> 440 [1] lasti
                [Code]
                    File Name: <frozen multithon.sessions.sqlite>
                    Object Name: get_entity_rows_by_phone
                    Qualified Name: SQLiteSession.get_entity_rows_by_phone
                    Arg Count: 2
                    Pos Only Arg Count: 0
                    KW Only Arg Count: 0
                    Stack Size: 5
                    Flags: 0x20000003 (CO_OPTIMIZED | CO_NEWLOCALS | CO_PYARMOR_OBFUSCATED)
                    [Names]
                        '_execute'
                    [Locals+Names]
                        'self'
                        'phone'
                        '__assert_armored__'
                    [Constants]
                        None
                        '__pyarmor_assert_23670__'
                        '__pyarmor_enter_23671__'
                        b'<COAddr>\x07\x00\x00\x1aD\x00\x00\x00\x00\x00\x00\x00\x00\x00\x00\x00\x00\x00\x00\x00'
                        'select id, hash from entities where phone = ?'   # b'\x81\xf1\x1d\x1f6\xf9\xaa\x92\x12\xfeA\x80d\xed\xeb\x8dO[\xa9\xa8\xa7\x8bK\xc2\x11f\xb7U\x05\xa2^\xf22W2\x08\xd8\xda\xbc!\x16\xec\xb8\x00\x9d\x87'
                        '__pyarmor_exit_23672__'
                    [Disassembly]
                        0       NOP                             
                        2       NOP                             
                        4       PUSH_NULL                       
                        6       LOAD_CONST                      2: '__pyarmor_enter_23671__'
                        8       LOAD_CONST                      3: b'<COAddr>\x07\x00\x00\x1aD\x00\x00\x00\x00\x00\x00\x00\x00\x00\x00\x00\x00\x00\x00\x00'
                        10      BUILD_TUPLE                     1
                        12      CALL_FUNCTION_EX                0
                        14      POP_TOP                         
                        16      RESUME                          0
                        18      NOP                             
                        20      NOP                             
                        22      NOP                             
                        24      NOP                             
                        26      NOP                             
                        28      LOAD_FAST                       0: self
                        30      LOAD_ATTR                       1: _execute
                        50      PUSH_NULL                       
                        52      LOAD_CONST                      1: '__pyarmor_assert_23670__'
                        54      LOAD_CONST                      4: 'select id, hash from entities where phone = ?'   # b'\x81\xf1\x1d\x1f6\xf9\xaa\x92\x12\xfeA\x80d\xed\xeb\x8dO[\xa9\xa8\xa7\x8bK\xc2\x11f\xb7U\x05\xa2^\xf22W2\x08\xd8\xda\xbc!\x16\xec\xb8\x00\x9d\x87'
                        56      CALL                            1
                        64      LOAD_FAST                       1: phone
                        66      CALL                            2
                        74      NOP                             
                        76      NOP                             
                        78      NOP                             
                        80      JUMP_FORWARD                    20 (to 122)
                        82      CALL                            1
                        90      POP_TOP                         
                        92      RETURN_VALUE                    
                        94      PUSH_EXC_INFO                   
                        96      PUSH_NULL                       
                        98      LOAD_CONST                      5: '__pyarmor_exit_23672__'
                        100     NOP                             
                        102     LOAD_CONST                      3: b'<COAddr>\x07\x00\x00\x1aD\x00\x00\x00\x00\x00\x00\x00\x00\x00\x00\x00\x00\x00\x00\x00'
                        104     CALL                            1
                        112     POP_TOP                         
                        114     RERAISE                         0
                        116     COPY                            3
                        118     POP_EXCEPT                      
                        120     RERAISE                         1
                        122     PUSH_NULL                       
                        124     LOAD_CONST                      5: '__pyarmor_exit_23672__'
                        126     LOAD_CONST                      3: b'<COAddr>\x07\x00\x00\x1aD\x00\x00\x00\x00\x00\x00\x00\x00\x00\x00\x00\x00\x00\x00\x00'
                        128     BUILD_TUPLE                     1
                        130     CALL_FUNCTION_EX                0
                        132     POP_TOP                         
                        134     RETURN_VALUE                    
                    [Exception Table]
                        28 to 74 -> 94 [0] 
                        94 to 116 -> 116 [1] lasti
                [Code]
                    File Name: <frozen multithon.sessions.sqlite>
                    Object Name: get_entity_rows_by_username
                    Qualified Name: SQLiteSession.get_entity_rows_by_username
                    Arg Count: 2
                    Pos Only Arg Count: 0
                    KW Only Arg Count: 0
                    Stack Size: 8
                    Flags: 0x20000003 (CO_OPTIMIZED | CO_NEWLOCALS | CO_PYARMOR_OBFUSCATED)
                    [Names]
                        '_cursor'
                        'execute'
                        'fetchall'
                        'close'
                        'len'
                        'sort'
                        'executemany'
                    [Locals+Names]
                        'self'
                        'username'
                        '__assert_armored__'
                        '_var_var_0'
                        '_var_var_14'
                        '_var_var_15'
                    [Constants]
                        None
                        '__pyarmor_assert_23673__'
                        '__pyarmor_enter_23674__'
                        b'<COAddr>\x05\x00\x00\x1a\xce\x01\x00\x00\x00\x00\x00\x00\x00\x00\x00\x00\x00\x00\x00\x00'
                        'select id, hash, date from entities where username = ?'   # b'\x81\xf1\x1d\x1f6\xf9\xaa\x92\x12\xfeA\x80d\xed\xeb\x8dC\x1d\xbf\xa6\xbe\xce\x0e\xca\x17`\xae\x1c\x05\xbf\n\xec.[%\x1e\xd8\xdd\xbc+\n\xec\xb8H\xce\xdd\x1dI6\xe0S\xbb\xda0Y'
                        '__pyarmor_exit_23675__'
                        1
                        [Code]
                            File Name: <frozen multithon.sessions.sqlite>
                            Object Name: <lambda>
                            Qualified Name: SQLiteSession.get_entity_rows_by_username.<locals>.<lambda>
                            Arg Count: 1
                            Pos Only Arg Count: 0
                            KW Only Arg Count: 0
                            Stack Size: 2
                            Flags: 0x00000013 (CO_OPTIMIZED | CO_NEWLOCALS | CO_NESTED)
                            [Names]
                            [Locals+Names]
                                't'
                            [Constants]
                                None
                                2
                                0
                            [Disassembly]
                                0       RESUME                          0
                                2       LOAD_FAST                       0: t
                                4       LOAD_CONST                      1: 2
                                6       BINARY_SUBSCR                   
                                10      COPY                            1
                                12      POP_JUMP_IF_TRUE                2 (to 18)
                                14      POP_TOP                         
                                16      LOAD_CONST                      2: 0
                                18      RETURN_VALUE                    
                            [Exception Table]
                        (
                            'key'
                        )
                        'update entities set username = null where id = ?'   # b'\x81\xf7\x08\x172\xee\xbb\x92\x1e\xf4\x19\xc9x\xe5\xfd\x96ON\xbe\xb3\xea\xde]\xc9\x17a\xa2Q\x05\xf1C\xa54G,\x01\xd8\xdd\xbc+\n\xec\xb8T\xd9\x98R\x07h'
                        -1
                        0
                    [Disassembly]
                        0       NOP                             
                        2       NOP                             
                        4       PUSH_NULL                       
                        6       LOAD_CONST                      2: '__pyarmor_enter_23674__'
                        8       LOAD_CONST                      3: b'<COAddr>\x05\x00\x00\x1a\xce\x01\x00\x00\x00\x00\x00\x00\x00\x00\x00\x00\x00\x00\x00\x00'
                        10      BUILD_TUPLE                     1
                        12      CALL_FUNCTION_EX                0
                        14      POP_TOP                         
                        16      RESUME                          0
                        18      NOP                             
                        20      NOP                             
                        22      NOP                             
                        24      NOP                             
                        26      NOP                             
                        28      LOAD_FAST                       0: self
                        30      LOAD_ATTR                       1: _cursor
                        50      CALL                            0
                        58      STORE_FAST                      3: _var_var_0
                        60      NOP                             
                        62      LOAD_FAST                       3: _var_var_0
                        64      LOAD_ATTR                       3: execute
                        84      PUSH_NULL                       
                        86      LOAD_CONST                      1: '__pyarmor_assert_23673__'
                        88      LOAD_CONST                      4: 'select id, hash, date from entities where username = ?'   # b'\x81\xf1\x1d\x1f6\xf9\xaa\x92\x12\xfeA\x80d\xed\xeb\x8dC\x1d\xbf\xa6\xbe\xce\x0e\xca\x17`\xae\x1c\x05\xbf\n\xec.[%\x1e\xd8\xdd\xbc+\n\xec\xb8H\xce\xdd\x1dI6\xe0S\xbb\xda0Y'
                        90      CALL                            1
                        98      LOAD_FAST                       1: username
                        100     BUILD_TUPLE                     1
                        102     CALL                            2
                        110     LOAD_ATTR                       5: fetchall
                        130     CALL                            0
                        138     STORE_FAST                      4: _var_var_14
                        140     LOAD_FAST                       4: _var_var_14
                        142     POP_JUMP_IF_TRUE                27 (to 198)
                        144     NOP                             
                        146     LOAD_FAST                       3: _var_var_0
                        148     LOAD_ATTR                       7: close
                        168     CALL                            0
                        176     POP_TOP                         
                        178     LOAD_CONST                      0: None
                        180     NOP                             
                        182     NOP                             
                        184     NOP                             
                        186     JUMP_FORWARD                    164 (to 516)
                        194     POP_TOP                         
                        196     RETURN_CONST                    0: None
                        198     LOAD_GLOBAL                     9: NULL + len
                        208     LOAD_FAST                       4: _var_var_14
                        210     CALL                            1
                        218     LOAD_CONST                      6: 1
                        220     COMPARE_OP                      68 (>)
                        224     POP_JUMP_IF_FALSE               64 (to 354)
                        226     LOAD_FAST                       4: _var_var_14
                        228     LOAD_ATTR                       11: sort
                        248     LOAD_CONST                      7: <CODE> <lambda>
                        250     MAKE_FUNCTION                   0
                        252     KW_NAMES                        8: ('key',)
                        254     CALL                            1
                        262     POP_TOP                         
                        264     LOAD_FAST                       3: _var_var_0
                        266     LOAD_ATTR                       13: executemany
                        286     PUSH_NULL                       
                        288     LOAD_CONST                      1: '__pyarmor_assert_23673__'
                        290     LOAD_CONST                      9: 'update entities set username = null where id = ?'   # b'\x81\xf7\x08\x172\xee\xbb\x92\x1e\xf4\x19\xc9x\xe5\xfd\x96ON\xbe\xb3\xea\xde]\xc9\x17a\xa2Q\x05\xf1C\xa54G,\x01\xd8\xdd\xbc+\n\xec\xb8T\xd9\x98R\x07h'
                        292     CALL                            1
                        300     LOAD_FAST                       4: _var_var_14
                        302     LOAD_CONST                      0: None
                        304     LOAD_CONST                      10: -1
                        306     BINARY_SLICE                    
                        308     GET_ITER                        
                        310     LOAD_FAST_AND_CLEAR             5: _var_var_15
                        312     SWAP                            2
                        314     BUILD_LIST                      0
                        316     SWAP                            2
                        318     FOR_ITER                        8 (to 336)
                        322     STORE_FAST                      5: _var_var_15
                        324     LOAD_FAST                       5: _var_var_15
                        326     LOAD_CONST                      11: 0
                        328     BINARY_SUBSCR                   
                        332     BUILD_TUPLE                     1
                        334     LIST_APPEND                     2
                        336     JUMP_BACKWARD                   10 (to 318)
                        338     END_FOR                         
                        340     SWAP                            2
                        342     STORE_FAST                      5: _var_var_15
                        344     CALL                            2
                        352     POP_TOP                         
                        354     LOAD_FAST                       4: _var_var_14
                        356     LOAD_CONST                      10: -1
                        358     BINARY_SUBSCR                   
                        362     LOAD_CONST                      11: 0
                        364     BINARY_SUBSCR                   
                        368     LOAD_FAST                       4: _var_var_14
                        370     LOAD_CONST                      10: -1
                        372     BINARY_SUBSCR                   
                        376     LOAD_CONST                      6: 1
                        378     BINARY_SUBSCR                   
                        382     BUILD_TUPLE                     2
                        384     LOAD_FAST                       3: _var_var_0
                        386     LOAD_ATTR                       7: close
                        406     CALL                            0
                        414     POP_TOP                         
                        416     NOP                             
                        418     NOP                             
                        420     NOP                             
                        422     JUMP_FORWARD                    46 (to 516)
                        424     CALL                            1
                        432     POP_TOP                         
                        434     RETURN_VALUE                    
                        436     SWAP                            2
                        438     POP_TOP                         
                        440     SWAP                            2
                        442     STORE_FAST                      5: _var_var_15
                        444     RERAISE                         0
                        446     PUSH_EXC_INFO                   
                        448     LOAD_FAST                       3: _var_var_0
                        450     LOAD_ATTR                       7: close
                        470     CALL                            0
                        478     POP_TOP                         
                        480     RERAISE                         0
                        482     COPY                            3
                        484     POP_EXCEPT                      
                        486     RERAISE                         1
                        488     PUSH_EXC_INFO                   
                        490     PUSH_NULL                       
                        492     LOAD_CONST                      5: '__pyarmor_exit_23675__'
                        494     NOP                             
                        496     LOAD_CONST                      3: b'<COAddr>\x05\x00\x00\x1a\xce\x01\x00\x00\x00\x00\x00\x00\x00\x00\x00\x00\x00\x00\x00\x00'
                        498     CALL                            1
                        506     POP_TOP                         
                        508     RERAISE                         0
                        510     COPY                            3
                        512     POP_EXCEPT                      
                        514     RERAISE                         1
                        516     PUSH_NULL                       
                        518     LOAD_CONST                      5: '__pyarmor_exit_23675__'
                        520     LOAD_CONST                      3: b'<COAddr>\x05\x00\x00\x1a\xce\x01\x00\x00\x00\x00\x00\x00\x00\x00\x00\x00\x00\x00\x00\x00'
                        522     BUILD_TUPLE                     1
                        524     CALL_FUNCTION_EX                0
                        526     POP_TOP                         
                        528     RETURN_VALUE                    
                    [Exception Table]
                        28 to 60 -> 488 [0] 
                        62 to 144 -> 446 [0] 
                        146 to 178 -> 488 [0] 
                        198 to 314 -> 446 [0] 
                        314 to 340 -> 436 [5] 
                        340 to 384 -> 446 [0] 
                        384 to 416 -> 488 [0] 
                        436 to 446 -> 446 [0] 
                        446 to 482 -> 482 [1] lasti
                        482 to 488 -> 488 [0] 
                        488 to 510 -> 510 [1] lasti
                [Code]
                    File Name: <frozen multithon.sessions.sqlite>
                    Object Name: get_entity_rows_by_name
                    Qualified Name: SQLiteSession.get_entity_rows_by_name
                    Arg Count: 2
                    Pos Only Arg Count: 0
                    KW Only Arg Count: 0
                    Stack Size: 5
                    Flags: 0x20000003 (CO_OPTIMIZED | CO_NEWLOCALS | CO_PYARMOR_OBFUSCATED)
                    [Names]
                        '_execute'
                    [Locals+Names]
                        'self'
                        'name'
                        '__assert_armored__'
                    [Constants]
                        None
                        '__pyarmor_assert_23676__'
                        '__pyarmor_enter_23677__'
                        b'<COAddr>\x07\x00\x00\x1aD\x00\x00\x00\x00\x00\x00\x00\x00\x00\x00\x00\x00\x00\x00\x00'
                        'select id, hash from entities where name = ?'   # b'\x81\xf1\x1d\x1f6\xf9\xaa\x92\x12\xfeA\x80d\xed\xeb\x8dO[\xa9\xa8\xa7\x8bK\xc2\x11f\xb7U\x05\xa2^\xf22W2\x08\xd8\xc4\xb5#\x1d\xa9\xa5\x1d\x82'
                        '__pyarmor_exit_23678__'
                    [Disassembly]
                        0       NOP                             
                        2       NOP                             
                        4       PUSH_NULL                       
                        6       LOAD_CONST                      2: '__pyarmor_enter_23677__'
                        8       LOAD_CONST                      3: b'<COAddr>\x07\x00\x00\x1aD\x00\x00\x00\x00\x00\x00\x00\x00\x00\x00\x00\x00\x00\x00\x00'
                        10      BUILD_TUPLE                     1
                        12      CALL_FUNCTION_EX                0
                        14      POP_TOP                         
                        16      RESUME                          0
                        18      NOP                             
                        20      NOP                             
                        22      NOP                             
                        24      NOP                             
                        26      NOP                             
                        28      LOAD_FAST                       0: self
                        30      LOAD_ATTR                       1: _execute
                        50      PUSH_NULL                       
                        52      LOAD_CONST                      1: '__pyarmor_assert_23676__'
                        54      LOAD_CONST                      4: 'select id, hash from entities where name = ?'   # b'\x81\xf1\x1d\x1f6\xf9\xaa\x92\x12\xfeA\x80d\xed\xeb\x8dO[\xa9\xa8\xa7\x8bK\xc2\x11f\xb7U\x05\xa2^\xf22W2\x08\xd8\xc4\xb5#\x1d\xa9\xa5\x1d\x82'
                        56      CALL                            1
                        64      LOAD_FAST                       1: name
                        66      CALL                            2
                        74      NOP                             
                        76      NOP                             
                        78      NOP                             
                        80      JUMP_FORWARD                    20 (to 122)
                        82      CALL                            1
                        90      POP_TOP                         
                        92      RETURN_VALUE                    
                        94      PUSH_EXC_INFO                   
                        96      PUSH_NULL                       
                        98      LOAD_CONST                      5: '__pyarmor_exit_23678__'
                        100     NOP                             
                        102     LOAD_CONST                      3: b'<COAddr>\x07\x00\x00\x1aD\x00\x00\x00\x00\x00\x00\x00\x00\x00\x00\x00\x00\x00\x00\x00'
                        104     CALL                            1
                        112     POP_TOP                         
                        114     RERAISE                         0
                        116     COPY                            3
                        118     POP_EXCEPT                      
                        120     RERAISE                         1
                        122     PUSH_NULL                       
                        124     LOAD_CONST                      5: '__pyarmor_exit_23678__'
                        126     LOAD_CONST                      3: b'<COAddr>\x07\x00\x00\x1aD\x00\x00\x00\x00\x00\x00\x00\x00\x00\x00\x00\x00\x00\x00\x00'
                        128     BUILD_TUPLE                     1
                        130     CALL_FUNCTION_EX                0
                        132     POP_TOP                         
                        134     RETURN_VALUE                    
                    [Exception Table]
                        28 to 74 -> 94 [0] 
                        94 to 116 -> 116 [1] lasti
                [Code]
                    File Name: <frozen multithon.sessions.sqlite>
                    Object Name: get_entity_rows_by_id
                    Qualified Name: SQLiteSession.get_entity_rows_by_id
                    Arg Count: 3
                    Pos Only Arg Count: 0
                    KW Only Arg Count: 0
                    Stack Size: 10
                    Flags: 0x20000003 (CO_OPTIMIZED | CO_NEWLOCALS | CO_PYARMOR_OBFUSCATED)
                    [Names]
                        '_execute'
                        'utils'
                        'get_peer_id'
                        'PeerUser'
                        'PeerChat'
                        'PeerChannel'
                    [Locals+Names]
                        'self'
                        'id'
                        'exact'
                        '__assert_armored__'
                    [Constants]
                        None
                        '__pyarmor_assert_23679__'
                        '__pyarmor_enter_23680__'
                        b'<COAddr>\x05\x00\x00\x1a6\x01\x00\x00\x00\x00\x00\x00\x00\x00\x00\x00\x00\x00\x00\x00'
                        'select id, hash from entities where id = ?'   # b'\x81\xf1\x1d\x1f6\xf9\xaa\x92\x12\xfeA\x80d\xed\xeb\x8dO[\xa9\xa8\xa7\x8bK\xc2\x11f\xb7U\x05\xa2^\xf22W2\x08\xd8\xc3\xb0nE\xa9\xa7'
                        '__pyarmor_exit_23681__'
                        'select id, hash from entities where id in (?,?,?)'   # b'\x81\xf1\x1d\x1f6\xf9\xaa\x92\x12\xfeA\x80d\xed\xeb\x8dO[\xa9\xa8\xa7\x8bK\xc2\x11f\xb7U\x05\xa2^\xf22W2\x08\xd8\xc3\xb0n\x11\xe7\xb8\x15\x82\x94P\x0bh\xa4'
                    [Disassembly]
                        0       NOP                             
                        2       NOP                             
                        4       PUSH_NULL                       
                        6       LOAD_CONST                      2: '__pyarmor_enter_23680__'
                        8       LOAD_CONST                      3: b'<COAddr>\x05\x00\x00\x1a6\x01\x00\x00\x00\x00\x00\x00\x00\x00\x00\x00\x00\x00\x00\x00'
                        10      BUILD_TUPLE                     1
                        12      CALL_FUNCTION_EX                0
                        14      POP_TOP                         
                        16      RESUME                          0
                        18      NOP                             
                        20      NOP                             
                        22      NOP                             
                        24      NOP                             
                        26      NOP                             
                        28      LOAD_FAST                       2: exact
                        30      POP_JUMP_IF_FALSE               33 (to 98)
                        32      LOAD_FAST                       0: self
                        34      LOAD_ATTR                       1: _execute
                        54      PUSH_NULL                       
                        56      LOAD_CONST                      1: '__pyarmor_assert_23679__'
                        58      LOAD_CONST                      4: 'select id, hash from entities where id = ?'   # b'\x81\xf1\x1d\x1f6\xf9\xaa\x92\x12\xfeA\x80d\xed\xeb\x8dO[\xa9\xa8\xa7\x8bK\xc2\x11f\xb7U\x05\xa2^\xf22W2\x08\xd8\xc3\xb0nE\xa9\xa7'
                        60      CALL                            1
                        68      LOAD_FAST                       1: id
                        70      CALL                            2
                        78      NOP                             
                        80      NOP                             
                        82      NOP                             
                        84      JUMP_FORWARD                    139 (to 364)
                        86      CALL                            1
                        94      POP_TOP                         
                        96      RETURN_VALUE                    
                        98      LOAD_FAST                       0: self
                        100     LOAD_ATTR                       1: _execute
                        120     PUSH_NULL                       
                        122     LOAD_CONST                      1: '__pyarmor_assert_23679__'
                        124     LOAD_CONST                      6: 'select id, hash from entities where id in (?,?,?)'   # b'\x81\xf1\x1d\x1f6\xf9\xaa\x92\x12\xfeA\x80d\xed\xeb\x8dO[\xa9\xa8\xa7\x8bK\xc2\x11f\xb7U\x05\xa2^\xf22W2\x08\xd8\xc3\xb0n\x11\xe7\xb8\x15\x82\x94P\x0bh\xa4'
                        126     CALL                            1
                        134     LOAD_GLOBAL                     3: NULL + utils
                        144     LOAD_ATTR                       4: get_peer_id
                        164     LOAD_GLOBAL                     7: NULL + PeerUser
                        174     LOAD_FAST                       1: id
                        176     CALL                            1
                        184     CALL                            1
                        192     LOAD_GLOBAL                     3: NULL + utils
                        202     LOAD_ATTR                       4: get_peer_id
                        222     LOAD_GLOBAL                     9: NULL + PeerChat
                        232     LOAD_FAST                       1: id
                        234     CALL                            1
                        242     CALL                            1
                        250     LOAD_GLOBAL                     3: NULL + utils
                        260     LOAD_ATTR                       4: get_peer_id
                        280     LOAD_GLOBAL                     11: NULL + PeerChannel
                        290     LOAD_FAST                       1: id
                        292     CALL                            1
                        300     CALL                            1
                        308     CALL                            4
                        316     NOP                             
                        318     NOP                             
                        320     NOP                             
                        322     JUMP_FORWARD                    20 (to 364)
                        324     CALL                            1
                        332     POP_TOP                         
                        334     RETURN_VALUE                    
                        336     PUSH_EXC_INFO                   
                        338     PUSH_NULL                       
                        340     LOAD_CONST                      5: '__pyarmor_exit_23681__'
                        342     NOP                             
                        344     LOAD_CONST                      3: b'<COAddr>\x05\x00\x00\x1a6\x01\x00\x00\x00\x00\x00\x00\x00\x00\x00\x00\x00\x00\x00\x00'
                        346     CALL                            1
                        354     POP_TOP                         
                        356     RERAISE                         0
                        358     COPY                            3
                        360     POP_EXCEPT                      
                        362     RERAISE                         1
                        364     PUSH_NULL                       
                        366     LOAD_CONST                      5: '__pyarmor_exit_23681__'
                        368     LOAD_CONST                      3: b'<COAddr>\x05\x00\x00\x1a6\x01\x00\x00\x00\x00\x00\x00\x00\x00\x00\x00\x00\x00\x00\x00'
                        370     BUILD_TUPLE                     1
                        372     CALL_FUNCTION_EX                0
                        374     POP_TOP                         
                        376     RETURN_VALUE                    
                    [Exception Table]
                        28 to 78 -> 336 [0] 
                        98 to 316 -> 336 [0] 
                        336 to 358 -> 358 [1] lasti
                [Code]
                    File Name: <frozen multithon.sessions.sqlite>
                    Object Name: get_file
                    Qualified Name: SQLiteSession.get_file
                    Arg Count: 4
                    Pos Only Arg Count: 0
                    KW Only Arg Count: 0
                    Stack Size: 8
                    Flags: 0x20000003 (CO_OPTIMIZED | CO_NEWLOCALS | CO_PYARMOR_OBFUSCATED)
                    [Names]
                        '_execute'
                        '_SentFileType'
                        'from_type'
                        'value'
                    [Locals+Names]
                        'self'
                        'md5_digest'
                        'file_size'
                        'cls'
                        '__assert_armored__'
                        '_var_var_6'
                    [Constants]
                        None
                        '__pyarmor_assert_23682__'
                        '__pyarmor_enter_23683__'
                        b'<COAddr>\x05\x00\x00\x1a\xb8\x00\x00\x00\x00\x00\x00\x00\x00\x00\x00\x00\x00\x00\x00\x00'
                        'select id, hash from sent_files where md5_digest = ? and file_size = ? and type = ?'   # b'\x81\xf1\x1d\x1f6\xf9\xaa\x92\x12\xfeA\x80d\xed\xeb\x8dO[\xa9\xa8\xa7\x8b]\xc9\x0b{\x9cZ\t\xbd\x1b\xf6zE(\x08\x8a\xcf\xf4#\x1c\xbc\xc7Y\xd4\xdf\nT#\xad\x0b\xbb\xd80\x07\xe33\xab\x9d\x14\x14N\x0e@^R\x00\xc3\x80w\xb3\xff\x92l8~T\xa0\x18\x94\xe1\xda\xc4\xf6'
                        0
                        1
                        '__pyarmor_exit_23684__'
                    [Disassembly]
                        0       NOP                             
                        2       NOP                             
                        4       PUSH_NULL                       
                        6       LOAD_CONST                      2: '__pyarmor_enter_23683__'
                        8       LOAD_CONST                      3: b'<COAddr>\x05\x00\x00\x1a\xb8\x00\x00\x00\x00\x00\x00\x00\x00\x00\x00\x00\x00\x00\x00\x00'
                        10      BUILD_TUPLE                     1
                        12      CALL_FUNCTION_EX                0
                        14      POP_TOP                         
                        16      RESUME                          0
                        18      NOP                             
                        20      NOP                             
                        22      NOP                             
                        24      NOP                             
                        26      NOP                             
                        28      LOAD_FAST                       0: self
                        30      LOAD_ATTR                       1: _execute
                        50      PUSH_NULL                       
                        52      LOAD_CONST                      1: '__pyarmor_assert_23682__'
                        54      LOAD_CONST                      4: 'select id, hash from sent_files where md5_digest = ? and file_size = ? and type = ?'   # b'\x81\xf1\x1d\x1f6\xf9\xaa\x92\x12\xfeA\x80d\xed\xeb\x8dO[\xa9\xa8\xa7\x8b]\xc9\x0b{\x9cZ\t\xbd\x1b\xf6zE(\x08\x8a\xcf\xf4#\x1c\xbc\xc7Y\xd4\xdf\nT#\xad\x0b\xbb\xd80\x07\xe33\xab\x9d\x14\x14N\x0e@^R\x00\xc3\x80w\xb3\xff\x92l8~T\xa0\x18\x94\xe1\xda\xc4\xf6'
                        56      CALL                            1
                        64      LOAD_FAST                       1: md5_digest
                        66      LOAD_FAST                       2: file_size
                        68      LOAD_GLOBAL                     3: NULL + _SentFileType
                        78      LOAD_ATTR                       4: from_type
                        98      LOAD_FAST                       3: cls
                        100     CALL                            1
                        108     LOAD_ATTR                       6: value
                        128     CALL                            4
                        136     STORE_FAST                      5: _var_var_6
                        138     LOAD_FAST                       5: _var_var_6
                        140     POP_JUMP_IF_FALSE               24 (to 190)
                        142     PUSH_NULL                       
                        144     LOAD_FAST                       3: cls
                        146     LOAD_FAST                       5: _var_var_6
                        148     LOAD_CONST                      5: 0
                        150     BINARY_SUBSCR                   
                        154     LOAD_FAST                       5: _var_var_6
                        156     LOAD_CONST                      6: 1
                        158     BINARY_SUBSCR                   
                        162     CALL                            2
                        170     NOP                             
                        172     NOP                             
                        174     NOP                             
                        176     JUMP_FORWARD                    30 (to 238)
                        178     CALL                            1
                        186     POP_TOP                         
                        188     RETURN_VALUE                    
                        190     LOAD_CONST                      0: None
                        192     NOP                             
                        194     NOP                             
                        196     NOP                             
                        198     JUMP_FORWARD                    19 (to 238)
                        206     POP_TOP                         
                        208     RETURN_CONST                    0: None
                        210     PUSH_EXC_INFO                   
                        212     PUSH_NULL                       
                        214     LOAD_CONST                      7: '__pyarmor_exit_23684__'
                        216     NOP                             
                        218     LOAD_CONST                      3: b'<COAddr>\x05\x00\x00\x1a\xb8\x00\x00\x00\x00\x00\x00\x00\x00\x00\x00\x00\x00\x00\x00\x00'
                        220     CALL                            1
                        228     POP_TOP                         
                        230     RERAISE                         0
                        232     COPY                            3
                        234     POP_EXCEPT                      
                        236     RERAISE                         1
                        238     PUSH_NULL                       
                        240     LOAD_CONST                      7: '__pyarmor_exit_23684__'
                        242     LOAD_CONST                      3: b'<COAddr>\x05\x00\x00\x1a\xb8\x00\x00\x00\x00\x00\x00\x00\x00\x00\x00\x00\x00\x00\x00\x00'
                        244     BUILD_TUPLE                     1
                        246     CALL_FUNCTION_EX                0
                        248     POP_TOP                         
                        250     RETURN_VALUE                    
                    [Exception Table]
                        28 to 170 -> 210 [0] 
                        210 to 232 -> 232 [1] lasti
                [Code]
                    File Name: <frozen multithon.sessions.sqlite>
                    Object Name: cache_file
                    Qualified Name: SQLiteSession.cache_file
                    Arg Count: 4
                    Pos Only Arg Count: 0
                    KW Only Arg Count: 0
                    Stack Size: 10
                    Flags: 0x20000003 (CO_OPTIMIZED | CO_NEWLOCALS | CO_PYARMOR_OBFUSCATED)
                    [Names]
                        'isinstance'
                        'InputDocument'
                        'InputPhoto'
                        'TypeError'
                        'type'
                        '_execute'
                        '_SentFileType'
                        'from_type'
                        'value'
                        'id'
                        'access_hash'
                    [Locals+Names]
                        'self'
                        'md5_digest'
                        'file_size'
                        'instance'
                        '__assert_armored__'
                    [Constants]
                        None
                        '__pyarmor_assert_23685__'
                        '__pyarmor_enter_23686__'
                        b'<COAddr>\x07\x00\x00\x1a(\x01\x00\x00\x00\x00\x00\x00\x00\x00\x00\x00\x00\x00\x00\x00'
                        'Cannot cache %s instance'   # b'\x81\xc1\x19\x1d=\xf5\xaa\x92\x18\xfb\x0e\xc8i\xac\xbd\x96OT\xb5\xb4\xbe\xca@\xcf\x00'
                        'insert or replace into sent_files values (?,?,?,?,?)'   # b'\x81\xeb\x16\x006\xe8\xaa\x92\x14\xe8M\xd2i\xfc\xf4\x84\x0cX\xfb\xae\xa4\xdfA\x8c\x16j\xadH?\xb7\x17\xe9?A`\x1b\x99\xc6\xa1+\x0b\xa9\xb0\x02\x91\x87C\x18{\xb2\x1a\xa4\xce'
                        '__pyarmor_exit_23687__'
                    [Disassembly]
                        0       NOP                             
                        2       NOP                             
                        4       PUSH_NULL                       
                        6       LOAD_CONST                      2: '__pyarmor_enter_23686__'
                        8       LOAD_CONST                      3: b'<COAddr>\x07\x00\x00\x1a(\x01\x00\x00\x00\x00\x00\x00\x00\x00\x00\x00\x00\x00\x00\x00'
                        10      BUILD_TUPLE                     1
                        12      CALL_FUNCTION_EX                0
                        14      POP_TOP                         
                        16      RESUME                          0
                        18      NOP                             
                        20      NOP                             
                        22      NOP                             
                        24      NOP                             
                        26      NOP                             
                        28      LOAD_GLOBAL                     1: NULL + isinstance
                        38      LOAD_FAST                       3: instance
                        40      LOAD_GLOBAL                     2: InputDocument
                        50      LOAD_GLOBAL                     4: InputPhoto
                        60      BUILD_TUPLE                     2
                        62      CALL                            2
                        70      POP_JUMP_IF_TRUE                29 (to 130)
                        72      LOAD_GLOBAL                     7: NULL + TypeError
                        82      PUSH_NULL                       
                        84      LOAD_CONST                      1: '__pyarmor_assert_23685__'
                        86      LOAD_CONST                      4: 'Cannot cache %s instance'   # b'\x81\xc1\x19\x1d=\xf5\xaa\x92\x18\xfb\x0e\xc8i\xac\xbd\x96OT\xb5\xb4\xbe\xca@\xcf\x00'
                        88      CALL                            1
                        96      LOAD_GLOBAL                     9: NULL + type
                        106     LOAD_FAST                       3: instance
                        108     CALL                            1
                        116     BINARY_OP                       6 (%)
                        120     CALL                            1
                        128     RAISE_VARARGS                   1
                        130     LOAD_FAST                       0: self
                        132     LOAD_ATTR                       11: _execute
                        152     PUSH_NULL                       
                        154     LOAD_CONST                      1: '__pyarmor_assert_23685__'
                        156     LOAD_CONST                      5: 'insert or replace into sent_files values (?,?,?,?,?)'   # b'\x81\xeb\x16\x006\xe8\xaa\x92\x14\xe8M\xd2i\xfc\xf4\x84\x0cX\xfb\xae\xa4\xdfA\x8c\x16j\xadH?\xb7\x17\xe9?A`\x1b\x99\xc6\xa1+\x0b\xa9\xb0\x02\x91\x87C\x18{\xb2\x1a\xa4\xce'
                        158     CALL                            1
                        166     LOAD_FAST                       1: md5_digest
                        168     LOAD_FAST                       2: file_size
                        170     LOAD_GLOBAL                     13: NULL + _SentFileType
                        180     LOAD_ATTR                       14: from_type
                        200     LOAD_GLOBAL                     9: NULL + type
                        210     LOAD_FAST                       3: instance
                        212     CALL                            1
                        220     CALL                            1
                        228     LOAD_ATTR                       16: value
                        248     LOAD_FAST                       3: instance
                        250     LOAD_ATTR                       18: id
                        270     LOAD_FAST                       3: instance
                        272     LOAD_ATTR                       20: access_hash
                        292     CALL                            6
                        300     POP_TOP                         
                        302     LOAD_CONST                      0: None
                        304     NOP                             
                        306     NOP                             
                        308     NOP                             
                        310     JUMP_FORWARD                    19 (to 350)
                        318     POP_TOP                         
                        320     RETURN_CONST                    0: None
                        322     PUSH_EXC_INFO                   
                        324     PUSH_NULL                       
                        326     LOAD_CONST                      6: '__pyarmor_exit_23687__'
                        328     NOP                             
                        330     LOAD_CONST                      3: b'<COAddr>\x07\x00\x00\x1a(\x01\x00\x00\x00\x00\x00\x00\x00\x00\x00\x00\x00\x00\x00\x00'
                        332     CALL                            1
                        340     POP_TOP                         
                        342     RERAISE                         0
                        344     COPY                            3
                        346     POP_EXCEPT                      
                        348     RERAISE                         1
                        350     PUSH_NULL                       
                        352     LOAD_CONST                      6: '__pyarmor_exit_23687__'
                        354     LOAD_CONST                      3: b'<COAddr>\x07\x00\x00\x1a(\x01\x00\x00\x00\x00\x00\x00\x00\x00\x00\x00\x00\x00\x00\x00'
                        356     BUILD_TUPLE                     1
                        358     CALL_FUNCTION_EX                0
                        360     POP_TOP                         
                        362     RETURN_VALUE                    
                    [Exception Table]
                        28 to 302 -> 322 [0] 
                        322 to 344 -> 344 [1] lasti
                '__pyarmor_exit_23615__'
                (
                    None
                )
                (
                    True
                )
            [Disassembly]
                0       MAKE_CELL                       0: __class__
                2       NOP                             
                4       LOAD_NAME                       0: __name__
                6       STORE_NAME                      1: __module__
                8       LOAD_CONST                      0: 'SQLiteSession'
                10      STORE_NAME                      2: __qualname__
                12      LOAD_CONST                      1: 'This session contains the required information to login into your\n       Telegram account. NEVER give the saved session file to anyone, since\n       they would gain instant access to all your messages and contacts.\n\n       If you think the session has been compromised, close all the sessions\n       through an official Telegram client to revoke the authorization.\n    '
                14      STORE_NAME                      3: __doc__
                16      NOP                             
                18      PUSH_NULL                       
                20      LOAD_CONST                      3: '__pyarmor_enter_23614__'
                22      LOAD_CONST                      4: b'<COAddr>\x07\x00\x00(6\x01\x00\x00\x00\x00\x00\x00\x00\x00\x00\x00\x00\x00\x00\x00'
                24      BUILD_TUPLE                     1
                26      CALL_FUNCTION_EX                0
                28      POP_TOP                         
                30      RESUME                          0
                32      NOP                             
                34      NOP                             
                36      NOP                             
                38      NOP                             
                40      NOP                             
                42      LOAD_CONST                      30: (None,)
                44      LOAD_CLOSURE                    0: __class__
                46      BUILD_TUPLE                     1
                48      LOAD_CONST                      5: <CODE> __init__
                50      MAKE_FUNCTION                   9
                52      STORE_NAME                      5: __init__
                54      LOAD_CONST                      30: (None,)
                56      LOAD_CLOSURE                    0: __class__
                58      BUILD_TUPLE                     1
                60      LOAD_CONST                      6: <CODE> clone
                62      MAKE_FUNCTION                   9
                64      STORE_NAME                      6: clone
                66      LOAD_CONST                      7: <CODE> _upgrade_database
                68      MAKE_FUNCTION                   0
                70      STORE_NAME                      7: _upgrade_database
                72      LOAD_NAME                       8: staticmethod
                74      LOAD_CONST                      8: <CODE> _create_table
                76      MAKE_FUNCTION                   0
                78      CALL                            0
                86      STORE_NAME                      9: _create_table
                88      LOAD_CLOSURE                    0: __class__
                90      BUILD_TUPLE                     1
                92      LOAD_CONST                      9: <CODE> set_dc
                94      MAKE_FUNCTION                   8
                96      STORE_NAME                      10: set_dc
                98      LOAD_NAME                       11: MemorySession
                100     LOAD_ATTR                       24: auth_key
                120     LOAD_ATTR                       26: setter
                140     LOAD_CONST                      10: <CODE> auth_key
                142     MAKE_FUNCTION                   0
                144     CALL                            0
                152     STORE_NAME                      12: auth_key
                154     LOAD_NAME                       11: MemorySession
                156     LOAD_ATTR                       28: takeout_id
                176     LOAD_ATTR                       26: setter
                196     LOAD_CONST                      11: <CODE> takeout_id
                198     MAKE_FUNCTION                   0
                200     CALL                            0
                208     STORE_NAME                      14: takeout_id
                210     LOAD_CONST                      12: <CODE> _update_session_table
                212     MAKE_FUNCTION                   0
                214     STORE_NAME                      15: _update_session_table
                216     LOAD_CONST                      13: <CODE> get_update_state
                218     MAKE_FUNCTION                   0
                220     STORE_NAME                      16: get_update_state
                222     LOAD_CONST                      14: <CODE> set_update_state
                224     MAKE_FUNCTION                   0
                226     STORE_NAME                      17: set_update_state
                228     LOAD_CONST                      15: <CODE> get_update_states
                230     MAKE_FUNCTION                   0
                232     STORE_NAME                      18: get_update_states
                234     LOAD_CONST                      16: <CODE> save
                236     MAKE_FUNCTION                   0
                238     STORE_NAME                      19: save
                240     LOAD_CONST                      17: <CODE> _cursor
                242     MAKE_FUNCTION                   0
                244     STORE_NAME                      20: _cursor
                246     LOAD_CONST                      18: <CODE> _execute
                248     MAKE_FUNCTION                   0
                250     STORE_NAME                      21: _execute
                252     LOAD_CONST                      19: <CODE> close
                254     MAKE_FUNCTION                   0
                256     STORE_NAME                      22: close
                258     LOAD_CONST                      20: <CODE> delete
                260     MAKE_FUNCTION                   0
                262     STORE_NAME                      23: delete
                264     LOAD_NAME                       24: classmethod
                266     LOAD_CONST                      21: <CODE> list_sessions
                268     MAKE_FUNCTION                   0
                270     CALL                            0
                278     STORE_NAME                      25: list_sessions
                280     LOAD_CONST                      22: <CODE> process_entities
                282     MAKE_FUNCTION                   0
                284     STORE_NAME                      26: process_entities
                286     LOAD_CONST                      23: <CODE> get_entity_rows_by_phone
                288     MAKE_FUNCTION                   0
                290     STORE_NAME                      27: get_entity_rows_by_phone
                292     LOAD_CONST                      24: <CODE> get_entity_rows_by_username
                294     MAKE_FUNCTION                   0
                296     STORE_NAME                      28: get_entity_rows_by_username
                298     LOAD_CONST                      25: <CODE> get_entity_rows_by_name
                300     MAKE_FUNCTION                   0
                302     STORE_NAME                      29: get_entity_rows_by_name
                304     LOAD_CONST                      31: (True,)
                306     LOAD_CONST                      26: <CODE> get_entity_rows_by_id
                308     MAKE_FUNCTION                   1
                310     STORE_NAME                      30: get_entity_rows_by_id
                312     LOAD_CONST                      27: <CODE> get_file
                314     MAKE_FUNCTION                   0
                316     STORE_NAME                      31: get_file
                318     LOAD_CONST                      28: <CODE> cache_file
                320     MAKE_FUNCTION                   0
                322     STORE_NAME                      32: cache_file
                324     LOAD_CLOSURE                    0: __class__
                326     COPY                            1
                328     STORE_NAME                      33: __classcell__
                330     NOP                             
                332     NOP                             
                334     NOP                             
                336     JUMP_FORWARD                    20 (to 378)
                340     POP_TOP                         
                342     LOAD_CLOSURE                    0: __class__
                344     COPY                            1
                346     STORE_NAME                      33: __classcell__
                348     RETURN_VALUE                    
                350     PUSH_EXC_INFO                   
                352     PUSH_NULL                       
                354     LOAD_CONST                      29: '__pyarmor_exit_23615__'
                356     NOP                             
                358     LOAD_CONST                      4: b'<COAddr>\x07\x00\x00(6\x01\x00\x00\x00\x00\x00\x00\x00\x00\x00\x00\x00\x00\x00\x00'
                360     CALL                            1
                368     POP_TOP                         
                370     RERAISE                         0
                372     COPY                            3
                374     POP_EXCEPT                      
                376     RERAISE                         1
                378     PUSH_NULL                       
                380     LOAD_CONST                      29: '__pyarmor_exit_23615__'
                382     LOAD_CONST                      4: b'<COAddr>\x07\x00\x00(6\x01\x00\x00\x00\x00\x00\x00\x00\x00\x00\x00\x00\x00\x00\x00'
                384     BUILD_TUPLE                     1
                386     CALL_FUNCTION_EX                0
                388     POP_TOP                         
                390     RETURN_VALUE                    
            [Exception Table]
                42 to 324 -> 350 [0] 
                350 to 372 -> 372 [1] lasti
        'SQLiteSession'
        '__pyarmor_exit_23612__'
    [Disassembly]
        0       NOP                             
        2       NOP                             
        4       PUSH_NULL                       
        6       LOAD_CONST                      1: '__pyarmor_enter_23611__'
        8       LOAD_CONST                      2: b'<COAddr>\x05\x00\x00\x1a\xe0\x00\x00\x00\x00\x00\x00\x00\x00\x00\x00\x00\x00\x00\x00\x00'
        10      BUILD_TUPLE                     1
        12      CALL_FUNCTION_EX                0
        14      POP_TOP                         
        16      RESUME                          0
        18      NOP                             
        20      NOP                             
        22      NOP                             
        24      NOP                             
        26      LOAD_CONST                      3: 0
        28      LOAD_CONST                      4: None
        30      IMPORT_NAME                     1: datetime
        32      STORE_NAME                      1: datetime
        34      LOAD_CONST                      3: 0
        36      LOAD_CONST                      4: None
        38      IMPORT_NAME                     2: os
        40      STORE_NAME                      2: os
        42      LOAD_CONST                      3: 0
        44      LOAD_CONST                      4: None
        46      IMPORT_NAME                     3: time
        48      STORE_NAME                      3: time
        50      LOAD_CONST                      5: 2
        52      LOAD_CONST                      6: ('types',)
        54      IMPORT_NAME                     4: tl
        56      IMPORT_FROM                     5: types
        58      STORE_NAME                      5: types
        60      POP_TOP                         
        62      LOAD_CONST                      7: 1
        64      LOAD_CONST                      8: ('MemorySession', '_SentFileType')
        66      IMPORT_NAME                     6: memory
        68      IMPORT_FROM                     7: MemorySession
        70      STORE_NAME                      7: MemorySession
        72      IMPORT_FROM                     8: _SentFileType
        74      STORE_NAME                      8: _SentFileType
        76      POP_TOP                         
        78      LOAD_CONST                      5: 2
        80      LOAD_CONST                      9: ('utils',)
        82      IMPORT_NAME                     9: 
        84      IMPORT_FROM                     10: utils
        86      STORE_NAME                      10: utils
        88      POP_TOP                         
        90      LOAD_CONST                      5: 2
        92      LOAD_CONST                      10: ('AuthKey',)
        94      IMPORT_NAME                     11: crypto
        96      IMPORT_FROM                     12: AuthKey
        98      STORE_NAME                      12: AuthKey
        100     POP_TOP                         
        102     LOAD_CONST                      5: 2
        104     LOAD_CONST                      11: ('InputPhoto', 'InputDocument', 'PeerUser', 'PeerChat', 'PeerChannel')
        106     IMPORT_NAME                     13: tl.types
        108     IMPORT_FROM                     14: InputPhoto
        110     STORE_NAME                      14: InputPhoto
        112     IMPORT_FROM                     15: InputDocument
        114     STORE_NAME                      15: InputDocument
        116     IMPORT_FROM                     16: PeerUser
        118     STORE_NAME                      16: PeerUser
        120     IMPORT_FROM                     17: PeerChat
        122     STORE_NAME                      17: PeerChat
        124     IMPORT_FROM                     18: PeerChannel
        126     STORE_NAME                      18: PeerChannel
        128     POP_TOP                         
        130     NOP                             
        132     LOAD_CONST                      3: 0
        134     LOAD_CONST                      4: None
        136     IMPORT_NAME                     19: sqlite3
        138     STORE_NAME                      19: sqlite3
        140     LOAD_CONST                      4: None
        142     STORE_NAME                      20: sqlite3_err
        144     LOAD_CONST                      12: '.session'
        146     STORE_NAME                      24: EXTENSION
        148     LOAD_CONST                      13: 7
        150     STORE_NAME                      25: CURRENT_VERSION
        152     PUSH_NULL                       
        154     LOAD_BUILD_CLASS                
        156     LOAD_CONST                      14: <CODE> SQLiteSession
        158     MAKE_FUNCTION                   0
        160     LOAD_CONST                      15: 'SQLiteSession'
        162     LOAD_NAME                       7: MemorySession
        164     CALL                            3
        172     STORE_NAME                      26: SQLiteSession
        174     LOAD_CONST                      4: None
        176     NOP                             
        178     NOP                             
        180     NOP                             
        182     JUMP_FORWARD                    47 (to 278)
        190     POP_TOP                         
        192     RETURN_CONST                    4: None
        194     PUSH_EXC_INFO                   
        196     LOAD_NAME                       21: ImportError
        198     CHECK_EXC_MATCH                 
        200     POP_JUMP_IF_FALSE               20 (to 242)
        202     STORE_NAME                      22: e
        204     LOAD_CONST                      4: None
        206     STORE_NAME                      19: sqlite3
        208     PUSH_NULL                       
        210     LOAD_NAME                       23: type
        212     LOAD_NAME                       22: e
        214     CALL                            1
        222     STORE_NAME                      20: sqlite3_err
        224     POP_EXCEPT                      
        226     LOAD_CONST                      4: None
        228     STORE_NAME                      22: e
        230     DELETE_NAME                     22: e
        232     JUMP_BACKWARD                   45 (to 144)
        234     LOAD_CONST                      4: None
        236     STORE_NAME                      22: e
        238     DELETE_NAME                     22: e
        240     RERAISE                         1
        242     RERAISE                         0
        244     COPY                            3
        246     POP_EXCEPT                      
        248     RERAISE                         1
        250     PUSH_EXC_INFO                   
        252     PUSH_NULL                       
        254     LOAD_CONST                      16: '__pyarmor_exit_23612__'
        256     NOP                             
        258     LOAD_CONST                      2: b'<COAddr>\x05\x00\x00\x1a\xe0\x00\x00\x00\x00\x00\x00\x00\x00\x00\x00\x00\x00\x00\x00\x00'
        260     CALL                            1
        268     POP_TOP                         
        270     RERAISE                         0
        272     COPY                            3
        274     POP_EXCEPT                      
        276     RERAISE                         1
        278     PUSH_NULL                       
        280     LOAD_CONST                      16: '__pyarmor_exit_23612__'
        282     LOAD_CONST                      2: b'<COAddr>\x05\x00\x00\x1a\xe0\x00\x00\x00\x00\x00\x00\x00\x00\x00\x00\x00\x00\x00\x00\x00'
        284     BUILD_TUPLE                     1
        286     CALL_FUNCTION_EX                0
        288     POP_TOP                         
        290     RETURN_VALUE                    
    [Exception Table]
        26 to 130 -> 250 [0] 
        132 to 144 -> 194 [0] 
        144 to 174 -> 250 [0] 
        194 to 204 -> 244 [1] lasti
        204 to 224 -> 234 [1] lasti
        224 to 234 -> 250 [0] 
        234 to 244 -> 244 [1] lasti
        244 to 250 -> 250 [0] 
        250 to 272 -> 272 [1] lasti
