#decoded by lolz.live/mrpenny / t.me/zeus_jackpot
# ================================
# Примечания по Pyarmor:
# - Байт-код и объекты кода Pyarmor соответствуют стандартному Python, но присутствуют специальные вызовы функций среды выполнения (runtime) Pyarmor.
# - Вызовы строк — это не ошибки, а маркеры, которые обрабатываются Pyarmor во время выполнения.
#
# Руководство по декомпиляции (без среды выполнения):
# 1. Игнорируйте зашифрованные байты после `#`; используйте только строку до `#`.
# 2. Удалите "__pyarmor_enter_xxx__"(b"<COAddr>...") и "__pyarmor_leave_xxx__"(b"<COAddr>...") (пролог/эпилог).
# 3. "__pyarmor_assert_xxx__"(A) не является настоящим оператором assert.
#    - Если A — это имя или читаемая строка: замените на A.
#    - Если A — это (X, "Y"): замените на X.Y.
#    - Если A — это (X, "Y", Z): замените на X.Y = Z.
#    - В противном случае: выберите наиболее подходящую/логичную замену.
# 4. "__pyarmor_bcc_xxx__"(...) указывает на машинный (нативный) код; тело функции недоступно. Добавьте комментарий.
# ================================

[Code]
    File Name: <frozen multithon.password>
    Object Name: <module>
    Qualified Name: <module>
    Arg Count: 0
    Pos Only Arg Count: 0
    KW Only Arg Count: 0
    Stack Size: 6
    Flags: 0x20000000 (CO_PYARMOR_OBFUSCATED)
    [Names]
        '__assert_armored__'
        'hashlib'
        'os'
        'crypto'
        'factorization'
        'tl'
        'types'
        'int'
        'check_prime_and_good_check'
        'bytes'
        'check_prime_and_good'
        'bool'
        'is_good_large'
        'SIZE_FOR_HASH'
        'num_bytes_for_hash'
        'big_num_for_hash'
        'sha256'
        'is_good_mod_exp_first'
        'xor'
        'pbkdf2sha512'
        'PasswordKdfAlgoSHA256SHA256PBKDF2HMACSHA512iter100000SHA256ModPow'
        'str'
        'compute_hash'
        'compute_digest'
        'account'
        'Password'
        'compute_check'
    [Locals+Names]
    [Constants]
        '__pyarmor_assert_16428__'
        '__pyarmor_enter_16429__'
        b'<COAddr>\x07\x00\x00\x1aX\x01\x00\x00\x00\x00\x00\x00\x00\x00\x00\x00\x00\x00\x00\x00'
        0
        None
        1
        (
            'factorization'
        )
        (
            'types'
        )
        'prime'
        'g'
        [Code]
            File Name: <frozen multithon.password>
            Object Name: check_prime_and_good_check
            Qualified Name: check_prime_and_good_check
            Arg Count: 2
            Pos Only Arg Count: 0
            KW Only Arg Count: 0
            Stack Size: 7
            Flags: 0x20000003 (CO_OPTIMIZED | CO_NEWLOCALS | CO_PYARMOR_OBFUSCATED)
            [Names]
                'bit_length'
                'ValueError'
                'format'
                'factorization'
                'Factorization'
                'factorize'
            [Locals+Names]
                'prime'
                'g'
                '__assert_armored__'
                '_var_var_0'
                '_var_var_1'
            [Constants]
                None
                '__pyarmor_assert_16431__'
                '__pyarmor_enter_16432__'
                b'<COAddr>\x07\x00\x00\x1a\xb6\x03\x00\x00\x00\x00\x00\x00\x00\x00\x00\x00\x00\x00\x00\x00'
                2048
                0
                'bad prime count {}, expected {}'   # b'\x81\xe0\x19\x17s\xea\xac\xdb\x16\xffM\xc3c\xf9\xf6\x91OF\xa6\xeb\xea\xceV\xdc\x00l\xb7Y\x04\xf1\x05\xf8'
                1
                'given "prime" is not prime'   # b'\x81\xe5\x11\x056\xf4\xfe\x90\x0b\xe8\x04\xcdi\xae\xb8\x8c\x1c\x1d\xb5\xa8\xbe\x8b^\xde\x0cb\xa6'
                2
                8
                7
                'bad g {}, mod8 {}'   # b'\x81\xe0\x19\x17s\xfd\xfe\xc9\x06\xb6M\xcdc\xe8\xa0\xc5\x14@'
                3
                'bad g {}, mod3 {}'   # b'\x81\xe0\x19\x17s\xfd\xfe\xc9\x06\xb6M\xcdc\xe8\xab\xc5\x14@'
                4
                5
                (
                    1
                    4
                )
                'bad g {}, mod5 {}'   # b'\x81\xe0\x19\x17s\xfd\xfe\xc9\x06\xb6M\xcdc\xe8\xad\xc5\x14@'
                6
                24
                (
                    19
                    23
                )
                'bad g {}, mod24 {}'   # b'\x81\xe0\x19\x17s\xfd\xfe\xc9\x06\xb6M\xcdc\xe8\xaa\xd1OF\xa6'
                (
                    3
                    5
                    6
                )
                'bad g {}, mod7 {}'   # b'\x81\xe0\x19\x17s\xfd\xfe\xc9\x06\xb6M\xcdc\xe8\xaf\xc5\x14@'
                'bad g {}'
                '(prime - 1) // 2 is not prime'   # b'\x81\xaa\x08\x01:\xf7\xbb\x92V\xba\\\x89,\xa3\xb7\xc5]\x1d\xb2\xb4\xea\xc5A\xd8E\x7f\xb1U\r\xb4'
                '__pyarmor_exit_16433__'
            [Disassembly]
                0       NOP                             
                2       NOP                             
                4       PUSH_NULL                       
                6       LOAD_CONST                      2: '__pyarmor_enter_16432__'
                8       LOAD_CONST                      3: b'<COAddr>\x07\x00\x00\x1a\xb6\x03\x00\x00\x00\x00\x00\x00\x00\x00\x00\x00\x00\x00\x00\x00'
                10      BUILD_TUPLE                     1
                12      CALL_FUNCTION_EX                0
                14      POP_TOP                         
                16      RESUME                          0
                18      NOP                             
                20      NOP                             
                22      NOP                             
                24      NOP                             
                26      NOP                             
                28      LOAD_CONST                      4: 2048
                30      STORE_FAST                      3: _var_var_0
                32      LOAD_FAST                       0: prime
                34      LOAD_CONST                      5: 0
                36      COMPARE_OP                      2 (<)
                40      POP_JUMP_IF_TRUE                19 (to 80)
                42      LOAD_FAST                       0: prime
                44      LOAD_ATTR                       1: bit_length
                64      CALL                            0
                72      LOAD_FAST                       3: _var_var_0
                74      COMPARE_OP                      55 (!=)
                78      POP_JUMP_IF_FALSE               47 (to 174)
                80      LOAD_GLOBAL                     3: NULL + ValueError
                90      PUSH_NULL                       
                92      LOAD_CONST                      1: '__pyarmor_assert_16431__'
                94      LOAD_CONST                      6: 'bad prime count {}, expected {}'   # b'\x81\xe0\x19\x17s\xea\xac\xdb\x16\xffM\xc3c\xf9\xf6\x91OF\xa6\xeb\xea\xceV\xdc\x00l\xb7Y\x04\xf1\x05\xf8'
                96      CALL                            1
                104     LOAD_ATTR                       5: format
                124     LOAD_FAST                       0: prime
                126     LOAD_ATTR                       1: bit_length
                146     CALL                            0
                154     LOAD_FAST                       3: _var_var_0
                156     CALL                            2
                164     CALL                            1
                172     RAISE_VARARGS                   1
                174     LOAD_GLOBAL                     6: factorization
                184     LOAD_ATTR                       8: Factorization
                204     LOAD_ATTR                       11: factorize
                224     LOAD_FAST                       0: prime
                226     CALL                            1
                234     LOAD_CONST                      5: 0
                236     BINARY_SUBSCR                   
                240     LOAD_CONST                      7: 1
                242     COMPARE_OP                      55 (!=)
                246     POP_JUMP_IF_FALSE               17 (to 282)
                248     LOAD_GLOBAL                     3: NULL + ValueError
                258     PUSH_NULL                       
                260     LOAD_CONST                      1: '__pyarmor_assert_16431__'
                262     LOAD_CONST                      8: 'given "prime" is not prime'   # b'\x81\xe5\x11\x056\xf4\xfe\x90\x0b\xe8\x04\xcdi\xae\xb8\x8c\x1c\x1d\xb5\xa8\xbe\x8b^\xde\x0cb\xa6'
                264     CALL                            1
                272     CALL                            1
                280     RAISE_VARARGS                   1
                282     LOAD_FAST                       1: g
                284     LOAD_CONST                      9: 2
                286     COMPARE_OP                      40 (==)
                290     POP_JUMP_IF_FALSE               45 (to 382)
                292     LOAD_FAST                       0: prime
                294     LOAD_CONST                      10: 8
                296     BINARY_OP                       6 (%)
                300     LOAD_CONST                      11: 7
                302     COMPARE_OP                      55 (!=)
                306     POP_JUMP_IF_FALSE               261 (to 832)
                310     LOAD_GLOBAL                     3: NULL + ValueError
                320     PUSH_NULL                       
                322     LOAD_CONST                      1: '__pyarmor_assert_16431__'
                324     LOAD_CONST                      12: 'bad g {}, mod8 {}'   # b'\x81\xe0\x19\x17s\xfd\xfe\xc9\x06\xb6M\xcdc\xe8\xa0\xc5\x14@'
                326     CALL                            1
                334     LOAD_ATTR                       5: format
                354     LOAD_FAST                       1: g
                356     LOAD_FAST                       0: prime
                358     LOAD_CONST                      10: 8
                360     BINARY_OP                       6 (%)
                364     CALL                            2
                372     CALL                            1
                380     RAISE_VARARGS                   1
                382     LOAD_FAST                       1: g
                384     LOAD_CONST                      13: 3
                386     COMPARE_OP                      40 (==)
                390     POP_JUMP_IF_FALSE               44 (to 480)
                392     LOAD_FAST                       0: prime
                394     LOAD_CONST                      13: 3
                396     BINARY_OP                       6 (%)
                400     LOAD_CONST                      9: 2
                402     COMPARE_OP                      55 (!=)
                406     POP_JUMP_IF_FALSE               212 (to 832)
                408     LOAD_GLOBAL                     3: NULL + ValueError
                418     PUSH_NULL                       
                420     LOAD_CONST                      1: '__pyarmor_assert_16431__'
                422     LOAD_CONST                      14: 'bad g {}, mod3 {}'   # b'\x81\xe0\x19\x17s\xfd\xfe\xc9\x06\xb6M\xcdc\xe8\xab\xc5\x14@'
                424     CALL                            1
                432     LOAD_ATTR                       5: format
                452     LOAD_FAST                       1: g
                454     LOAD_FAST                       0: prime
                456     LOAD_CONST                      13: 3
                458     BINARY_OP                       6 (%)
                462     CALL                            2
                470     CALL                            1
                478     RAISE_VARARGS                   1
                480     LOAD_FAST                       1: g
                482     LOAD_CONST                      15: 4
                484     COMPARE_OP                      40 (==)
                488     POP_JUMP_IF_FALSE               1 (to 492)
                490     JUMP_FORWARD                    170 (to 832)
                492     LOAD_FAST                       1: g
                494     LOAD_CONST                      16: 5
                496     COMPARE_OP                      40 (==)
                500     POP_JUMP_IF_FALSE               43 (to 588)
                502     LOAD_FAST                       0: prime
                504     LOAD_CONST                      16: 5
                506     BINARY_OP                       6 (%)
                510     LOAD_CONST                      17: (1, 4)
                512     CONTAINS_OP                     1 (not in)
                514     POP_JUMP_IF_FALSE               158 (to 832)
                516     LOAD_GLOBAL                     3: NULL + ValueError
                526     PUSH_NULL                       
                528     LOAD_CONST                      1: '__pyarmor_assert_16431__'
                530     LOAD_CONST                      18: 'bad g {}, mod5 {}'   # b'\x81\xe0\x19\x17s\xfd\xfe\xc9\x06\xb6M\xcdc\xe8\xad\xc5\x14@'
                532     CALL                            1
                540     LOAD_ATTR                       5: format
                560     LOAD_FAST                       1: g
                562     LOAD_FAST                       0: prime
                564     LOAD_CONST                      16: 5
                566     BINARY_OP                       6 (%)
                570     CALL                            2
                578     CALL                            1
                586     RAISE_VARARGS                   1
                588     LOAD_FAST                       1: g
                590     LOAD_CONST                      19: 6
                592     COMPARE_OP                      40 (==)
                596     POP_JUMP_IF_FALSE               43 (to 684)
                598     LOAD_FAST                       0: prime
                600     LOAD_CONST                      20: 24
                602     BINARY_OP                       6 (%)
                606     LOAD_CONST                      21: (19, 23)
                608     CONTAINS_OP                     1 (not in)
                610     POP_JUMP_IF_FALSE               110 (to 832)
                612     LOAD_GLOBAL                     3: NULL + ValueError
                622     PUSH_NULL                       
                624     LOAD_CONST                      1: '__pyarmor_assert_16431__'
                626     LOAD_CONST                      22: 'bad g {}, mod24 {}'   # b'\x81\xe0\x19\x17s\xfd\xfe\xc9\x06\xb6M\xcdc\xe8\xaa\xd1OF\xa6'
                628     CALL                            1
                636     LOAD_ATTR                       5: format
                656     LOAD_FAST                       1: g
                658     LOAD_FAST                       0: prime
                660     LOAD_CONST                      20: 24
                662     BINARY_OP                       6 (%)
                666     CALL                            2
                674     CALL                            1
                682     RAISE_VARARGS                   1
                684     LOAD_FAST                       1: g
                686     LOAD_CONST                      11: 7
                688     COMPARE_OP                      40 (==)
                692     POP_JUMP_IF_FALSE               43 (to 780)
                694     LOAD_FAST                       0: prime
                696     LOAD_CONST                      11: 7
                698     BINARY_OP                       6 (%)
                702     LOAD_CONST                      23: (3, 5, 6)
                704     CONTAINS_OP                     1 (not in)
                706     POP_JUMP_IF_FALSE               62 (to 832)
                708     LOAD_GLOBAL                     3: NULL + ValueError
                718     PUSH_NULL                       
                720     LOAD_CONST                      1: '__pyarmor_assert_16431__'
                722     LOAD_CONST                      24: 'bad g {}, mod7 {}'   # b'\x81\xe0\x19\x17s\xfd\xfe\xc9\x06\xb6M\xcdc\xe8\xaf\xc5\x14@'
                724     CALL                            1
                732     LOAD_ATTR                       5: format
                752     LOAD_FAST                       1: g
                754     LOAD_FAST                       0: prime
                756     LOAD_CONST                      11: 7
                758     BINARY_OP                       6 (%)
                762     CALL                            2
                770     CALL                            1
                778     RAISE_VARARGS                   1
                780     LOAD_GLOBAL                     3: NULL + ValueError
                790     LOAD_CONST                      25: 'bad g {}'
                792     LOAD_ATTR                       5: format
                812     LOAD_FAST                       1: g
                814     CALL                            1
                822     CALL                            1
                830     RAISE_VARARGS                   1
                832     LOAD_FAST                       0: prime
                834     LOAD_CONST                      7: 1
                836     BINARY_OP                       10 (-)
                840     LOAD_CONST                      9: 2
                842     BINARY_OP                       2 (//)
                846     STORE_FAST                      4: _var_var_1
                848     LOAD_GLOBAL                     6: factorization
                858     LOAD_ATTR                       8: Factorization
                878     LOAD_ATTR                       11: factorize
                898     LOAD_FAST                       4: _var_var_1
                900     CALL                            1
                908     LOAD_CONST                      5: 0
                910     BINARY_SUBSCR                   
                914     LOAD_CONST                      7: 1
                916     COMPARE_OP                      55 (!=)
                920     POP_JUMP_IF_FALSE               17 (to 956)
                922     LOAD_GLOBAL                     3: NULL + ValueError
                932     PUSH_NULL                       
                934     LOAD_CONST                      1: '__pyarmor_assert_16431__'
                936     LOAD_CONST                      26: '(prime - 1) // 2 is not prime'   # b'\x81\xaa\x08\x01:\xf7\xbb\x92V\xba\\\x89,\xa3\xb7\xc5]\x1d\xb2\xb4\xea\xc5A\xd8E\x7f\xb1U\r\xb4'
                938     CALL                            1
                946     CALL                            1
                954     RAISE_VARARGS                   1
                956     LOAD_CONST                      0: None
                958     NOP                             
                960     NOP                             
                962     NOP                             
                964     JUMP_FORWARD                    19 (to 1004)
                972     POP_TOP                         
                974     RETURN_CONST                    0: None
                976     PUSH_EXC_INFO                   
                978     PUSH_NULL                       
                980     LOAD_CONST                      27: '__pyarmor_exit_16433__'
                982     NOP                             
                984     LOAD_CONST                      3: b'<COAddr>\x07\x00\x00\x1a\xb6\x03\x00\x00\x00\x00\x00\x00\x00\x00\x00\x00\x00\x00\x00\x00'
                986     CALL                            1
                994     POP_TOP                         
                996     RERAISE                         0
                998     COPY                            3
                1000    POP_EXCEPT                      
                1002    RERAISE                         1
                1004    PUSH_NULL                       
                1006    LOAD_CONST                      27: '__pyarmor_exit_16433__'
                1008    LOAD_CONST                      3: b'<COAddr>\x07\x00\x00\x1a\xb6\x03\x00\x00\x00\x00\x00\x00\x00\x00\x00\x00\x00\x00\x00\x00'
                1010    BUILD_TUPLE                     1
                1012    CALL_FUNCTION_EX                0
                1014    POP_TOP                         
                1016    RETURN_VALUE                    
            [Exception Table]
                28 to 956 -> 976 [0] 
                976 to 998 -> 998 [1] lasti
        'prime_bytes'
        [Code]
            File Name: <frozen multithon.password>
            Object Name: check_prime_and_good
            Qualified Name: check_prime_and_good
            Arg Count: 2
            Pos Only Arg Count: 0
            KW Only Arg Count: 0
            Stack Size: 6
            Flags: 0x20000003 (CO_OPTIMIZED | CO_NEWLOCALS | CO_PYARMOR_OBFUSCATED)
            [Names]
                'bytes'
                'check_prime_and_good_check'
                'int'
                'from_bytes'
            [Locals+Names]
                'prime_bytes'
                'g'
                '__assert_armored__'
                '_var_var_2'
            [Constants]
                None
                '__pyarmor_assert_16434__'
                '__pyarmor_enter_16435__'
                b'<COAddr>\x07\x00\x00\x1a\x94\x00\x00\x00\x00\x00\x00\x00\x00\x00\x00\x00\x00\x00\x00\x00'
                (
                    199
                    28
                    174
                    185
                    198
                    177
                    201
                    4
                    142
                    108
                    82
                    47
                    112
                    241
                    63
                    115
                    152
                    13
                    64
                    35
                    142
                    62
                    33
                    193
                    73
                    52
                    208
                    55
                    86
                    61
                    147
                    15
                    72
                    25
                    138
                    10
                    167
                    193
                    64
                    88
                    34
                    148
                    147
                    210
                    37
                    48
                    244
                    219
                    250
                    51
                    111
                    110
                    10
                    201
                    37
                    19
                    149
                    67
                    174
                    212
                    76
                    206
                    124
                    55
                    32
                    253
                    81
                    246
                    148
                    88
                    112
                    90
                    198
                    140
                    212
                    254
                    107
                    107
                    19
                    171
                    220
                    151
                    70
                    81
                    41
                    105
                    50
                    132
                    84
                    241
                    143
                    175
                    140
                    89
                    95
                    100
                    36
                    119
                    254
                    150
                    187
                    42
                    148
                    29
                    91
                    205
                    29
                    74
                    200
                    204
                    73
                    136
                    7
                    8
                    250
                    155
                    55
                    142
                    60
                    79
                    58
                    144
                    96
                    190
                    230
                    124
                    249
                    164
                    164
                    166
                    149
                    129
                    16
                    81
                    144
                    126
                    22
                    39
                    83
                    181
                    107
                    15
                    107
                    65
                    13
                    186
                    116
                    216
                    168
                    75
                    42
                    20
                    179
                    20
                    78
                    14
                    241
                    40
                    71
                    84
                    253
                    23
                    237
                    149
                    13
                    89
                    101
                    180
                    185
                    221
                    70
                    88
                    45
                    177
                    23
                    141
                    22
                    156
                    107
                    196
                    101
                    176
                    214
                    255
                    156
                    163
                    146
                    143
                    239
                    91
                    154
                    228
                    228
                    24
                    252
                    21
                    232
                    62
                    190
                    160
                    248
                    127
                    169
                    255
                    94
                    237
                    112
                    5
                    13
                    237
                    40
                    73
                    244
                    123
                    249
                    89
                    217
                    86
                    133
                    12
                    233
                    41
                    133
                    31
                    13
                    129
                    21
                    246
                    53
                    177
                    5
                    238
                    46
                    78
                    21
                    208
                    75
                    36
                    84
                    191
                    111
                    79
                    173
                    240
                    52
                    177
                    4
                    3
                    17
                    156
                    216
                    227
                    185
                    47
                    204
                    91
                )
                (
                    3
                    4
                    5
                    7
                )
                '__pyarmor_exit_16436__'
                'big'
            [Disassembly]
                0       NOP                             
                2       NOP                             
                4       PUSH_NULL                       
                6       LOAD_CONST                      2: '__pyarmor_enter_16435__'
                8       LOAD_CONST                      3: b'<COAddr>\x07\x00\x00\x1a\x94\x00\x00\x00\x00\x00\x00\x00\x00\x00\x00\x00\x00\x00\x00\x00'
                10      BUILD_TUPLE                     1
                12      CALL_FUNCTION_EX                0
                14      POP_TOP                         
                16      RESUME                          0
                18      NOP                             
                20      NOP                             
                22      NOP                             
                24      NOP                             
                26      NOP                             
                28      LOAD_GLOBAL                     1: NULL + bytes
                38      LOAD_CONST                      4: (199, 28, 174, 185, 198, 177, 201, 4, 142, 108, 82, 47, 112, 241, 63, 115, 152, 13, 64, 35, 142, 62, 33, 193, 73, 52, 208, 55, 86, 61, 147, 15, 72, 25, 138, 10, 167, 193, 64, 88, 34, 148, 147, 210, 37, 48, 244, 219, 250, 51, 111, 110, 10, 201, 37, 19, 149, 67, 174, 212, 76, 206, 124, 55, 32, 253, 81, 246, 148, 88, 112, 90, 198, 140, 212, 254, 107, 107, 19, 171, 220, 151, 70, 81, 41, 105, 50, 132, 84, 241, 143, 175, 140, 89, 95, 100, 36, 119, 254, 150, 187, 42, 148, 29, 91, 205, 29, 74, 200, 204, 73, 136, 7, 8, 250, 155, 55, 142, 60, 79, 58, 144, 96, 190, 230, 124, 249, 164, 164, 166, 149, 129, 16, 81, 144, 126, 22, 39, 83, 181, 107, 15, 107, 65, 13, 186, 116, 216, 168, 75, 42, 20, 179, 20, 78, 14, 241, 40, 71, 84, 253, 23, 237, 149, 13, 89, 101, 180, 185, 221, 70, 88, 45, 177, 23, 141, 22, 156, 107, 196, 101, 176, 214, 255, 156, 163, 146, 143, 239, 91, 154, 228, 228, 24, 252, 21, 232, 62, 190, 160, 248, 127, 169, 255, 94, 237, 112, 5, 13, 237, 40, 73, 244, 123, 249, 89, 217, 86, 133, 12, 233, 41, 133, 31, 13, 129, 21, 246, 53, 177, 5, 238, 46, 78, 21, 208, 75, 36, 84, 191, 111, 79, 173, 240, 52, 177, 4, 3, 17, 156, 216, 227, 185, 47, 204, 91)
                40      CALL                            1
                48      STORE_FAST                      3: _var_var_2
                50      LOAD_FAST                       3: _var_var_2
                52      LOAD_FAST                       0: prime_bytes
                54      COMPARE_OP                      40 (==)
                58      POP_JUMP_IF_FALSE               15 (to 90)
                60      LOAD_FAST                       1: g
                62      LOAD_CONST                      5: (3, 4, 5, 7)
                64      CONTAINS_OP                     0 (in)
                66      POP_JUMP_IF_FALSE               11 (to 90)
                68      NOP                             
                70      LOAD_CONST                      0: None
                72      NOP                             
                74      NOP                             
                76      NOP                             
                78      JUMP_FORWARD                    61 (to 202)
                86      POP_TOP                         
                88      RETURN_CONST                    0: None
                90      LOAD_GLOBAL                     3: NULL + check_prime_and_good_check
                100     LOAD_GLOBAL                     4: int
                110     LOAD_ATTR                       7: from_bytes
                130     LOAD_FAST                       0: prime_bytes
                132     LOAD_CONST                      7: 'big'
                134     CALL                            2
                142     LOAD_FAST                       1: g
                144     CALL                            2
                152     POP_TOP                         
                154     LOAD_CONST                      0: None
                156     NOP                             
                158     NOP                             
                160     NOP                             
                162     JUMP_FORWARD                    19 (to 202)
                170     POP_TOP                         
                172     RETURN_CONST                    0: None
                174     PUSH_EXC_INFO                   
                176     PUSH_NULL                       
                178     LOAD_CONST                      6: '__pyarmor_exit_16436__'
                180     NOP                             
                182     LOAD_CONST                      3: b'<COAddr>\x07\x00\x00\x1a\x94\x00\x00\x00\x00\x00\x00\x00\x00\x00\x00\x00\x00\x00\x00\x00'
                184     CALL                            1
                192     POP_TOP                         
                194     RERAISE                         0
                196     COPY                            3
                198     POP_EXCEPT                      
                200     RERAISE                         1
                202     PUSH_NULL                       
                204     LOAD_CONST                      6: '__pyarmor_exit_16436__'
                206     LOAD_CONST                      3: b'<COAddr>\x07\x00\x00\x1a\x94\x00\x00\x00\x00\x00\x00\x00\x00\x00\x00\x00\x00\x00\x00\x00'
                208     BUILD_TUPLE                     1
                210     CALL_FUNCTION_EX                0
                212     POP_TOP                         
                214     RETURN_VALUE                    
            [Exception Table]
                28 to 68 -> 174 [0] 
                90 to 154 -> 174 [0] 
                174 to 196 -> 196 [1] lasti
        'number'
        'p'
        'return'
        [Code]
            File Name: <frozen multithon.password>
            Object Name: is_good_large
            Qualified Name: is_good_large
            Arg Count: 2
            Pos Only Arg Count: 0
            KW Only Arg Count: 0
            Stack Size: 5
            Flags: 0x20000003 (CO_OPTIMIZED | CO_NEWLOCALS | CO_PYARMOR_OBFUSCATED)
            [Names]
            [Locals+Names]
                'number'
                'p'
                '__assert_armored__'
            [Constants]
                None
                '__pyarmor_assert_16437__'
                '__pyarmor_enter_16438__'
                b'<COAddr>\x07\x00\x00\x1a2\x00\x00\x00\x00\x00\x00\x00\x00\x00\x00\x00\x00\x00\x00\x00'
                0
                '__pyarmor_exit_16439__'
            [Disassembly]
                0       NOP                             
                2       NOP                             
                4       PUSH_NULL                       
                6       LOAD_CONST                      2: '__pyarmor_enter_16438__'
                8       LOAD_CONST                      3: b'<COAddr>\x07\x00\x00\x1a2\x00\x00\x00\x00\x00\x00\x00\x00\x00\x00\x00\x00\x00\x00\x00'
                10      BUILD_TUPLE                     1
                12      CALL_FUNCTION_EX                0
                14      POP_TOP                         
                16      RESUME                          0
                18      NOP                             
                20      NOP                             
                22      NOP                             
                24      NOP                             
                26      NOP                             
                28      LOAD_FAST                       0: number
                30      LOAD_CONST                      4: 0
                32      COMPARE_OP                      68 (>)
                36      COPY                            1
                38      POP_JUMP_IF_FALSE               8 (to 56)
                40      POP_TOP                         
                42      LOAD_FAST                       1: p
                44      LOAD_FAST                       0: number
                46      BINARY_OP                       10 (-)
                50      LOAD_CONST                      4: 0
                52      COMPARE_OP                      68 (>)
                56      NOP                             
                58      NOP                             
                60      NOP                             
                62      JUMP_FORWARD                    20 (to 104)
                64      CALL                            1
                72      POP_TOP                         
                74      RETURN_VALUE                    
                76      PUSH_EXC_INFO                   
                78      PUSH_NULL                       
                80      LOAD_CONST                      5: '__pyarmor_exit_16439__'
                82      NOP                             
                84      LOAD_CONST                      3: b'<COAddr>\x07\x00\x00\x1a2\x00\x00\x00\x00\x00\x00\x00\x00\x00\x00\x00\x00\x00\x00\x00'
                86      CALL                            1
                94      POP_TOP                         
                96      RERAISE                         0
                98      COPY                            3
                100     POP_EXCEPT                      
                102     RERAISE                         1
                104     PUSH_NULL                       
                106     LOAD_CONST                      5: '__pyarmor_exit_16439__'
                108     LOAD_CONST                      3: b'<COAddr>\x07\x00\x00\x1a2\x00\x00\x00\x00\x00\x00\x00\x00\x00\x00\x00\x00\x00\x00\x00'
                110     BUILD_TUPLE                     1
                112     CALL_FUNCTION_EX                0
                114     POP_TOP                         
                116     RETURN_VALUE                    
            [Exception Table]
                28 to 56 -> 76 [0] 
                76 to 98 -> 98 [1] lasti
        256
        [Code]
            File Name: <frozen multithon.password>
            Object Name: num_bytes_for_hash
            Qualified Name: num_bytes_for_hash
            Arg Count: 1
            Pos Only Arg Count: 0
            KW Only Arg Count: 0
            Stack Size: 6
            Flags: 0x20000003 (CO_OPTIMIZED | CO_NEWLOCALS | CO_PYARMOR_OBFUSCATED)
            [Names]
                'bytes'
                'SIZE_FOR_HASH'
                'len'
            [Locals+Names]
                'number'
                '__assert_armored__'
            [Constants]
                None
                '__pyarmor_assert_16440__'
                '__pyarmor_enter_16441__'
                b'<COAddr>\x07\x00\x00\x1aP\x00\x00\x00\x00\x00\x00\x00\x00\x00\x00\x00\x00\x00\x00\x00'
                '__pyarmor_exit_16442__'
            [Disassembly]
                0       NOP                             
                2       NOP                             
                4       PUSH_NULL                       
                6       LOAD_CONST                      2: '__pyarmor_enter_16441__'
                8       LOAD_CONST                      3: b'<COAddr>\x07\x00\x00\x1aP\x00\x00\x00\x00\x00\x00\x00\x00\x00\x00\x00\x00\x00\x00\x00'
                10      BUILD_TUPLE                     1
                12      CALL_FUNCTION_EX                0
                14      POP_TOP                         
                16      RESUME                          0
                18      NOP                             
                20      NOP                             
                22      NOP                             
                24      NOP                             
                26      NOP                             
                28      LOAD_GLOBAL                     1: NULL + bytes
                38      LOAD_GLOBAL                     2: SIZE_FOR_HASH
                48      LOAD_GLOBAL                     5: NULL + len
                58      LOAD_FAST                       0: number
                60      CALL                            1
                68      BINARY_OP                       10 (-)
                72      CALL                            1
                80      LOAD_FAST                       0: number
                82      BINARY_OP                       0 (+)
                86      NOP                             
                88      NOP                             
                90      NOP                             
                92      JUMP_FORWARD                    20 (to 134)
                94      CALL                            1
                102     POP_TOP                         
                104     RETURN_VALUE                    
                106     PUSH_EXC_INFO                   
                108     PUSH_NULL                       
                110     LOAD_CONST                      4: '__pyarmor_exit_16442__'
                112     NOP                             
                114     LOAD_CONST                      3: b'<COAddr>\x07\x00\x00\x1aP\x00\x00\x00\x00\x00\x00\x00\x00\x00\x00\x00\x00\x00\x00\x00'
                116     CALL                            1
                124     POP_TOP                         
                126     RERAISE                         0
                128     COPY                            3
                130     POP_EXCEPT                      
                132     RERAISE                         1
                134     PUSH_NULL                       
                136     LOAD_CONST                      4: '__pyarmor_exit_16442__'
                138     LOAD_CONST                      3: b'<COAddr>\x07\x00\x00\x1aP\x00\x00\x00\x00\x00\x00\x00\x00\x00\x00\x00\x00\x00\x00\x00'
                140     BUILD_TUPLE                     1
                142     CALL_FUNCTION_EX                0
                144     POP_TOP                         
                146     RETURN_VALUE                    
            [Exception Table]
                28 to 86 -> 106 [0] 
                106 to 128 -> 128 [1] lasti
        [Code]
            File Name: <frozen multithon.password>
            Object Name: big_num_for_hash
            Qualified Name: big_num_for_hash
            Arg Count: 1
            Pos Only Arg Count: 0
            KW Only Arg Count: 0
            Stack Size: 5
            Flags: 0x20000003 (CO_OPTIMIZED | CO_NEWLOCALS | CO_PYARMOR_OBFUSCATED)
            [Names]
                'to_bytes'
                'SIZE_FOR_HASH'
            [Locals+Names]
                'g'
                '__assert_armored__'
            [Constants]
                None
                '__pyarmor_assert_16443__'
                '__pyarmor_enter_16444__'
                b'<COAddr>\x05\x00\x00\x1a@\x00\x00\x00\x00\x00\x00\x00\x00\x00\x00\x00\x00\x00\x00\x00'
                'big'
                '__pyarmor_exit_16445__'
            [Disassembly]
                0       NOP                             
                2       NOP                             
                4       PUSH_NULL                       
                6       LOAD_CONST                      2: '__pyarmor_enter_16444__'
                8       LOAD_CONST                      3: b'<COAddr>\x05\x00\x00\x1a@\x00\x00\x00\x00\x00\x00\x00\x00\x00\x00\x00\x00\x00\x00\x00'
                10      BUILD_TUPLE                     1
                12      CALL_FUNCTION_EX                0
                14      POP_TOP                         
                16      RESUME                          0
                18      NOP                             
                20      NOP                             
                22      NOP                             
                24      NOP                             
                26      NOP                             
                28      LOAD_FAST                       0: g
                30      LOAD_ATTR                       1: to_bytes
                50      LOAD_GLOBAL                     2: SIZE_FOR_HASH
                60      LOAD_CONST                      4: 'big'
                62      CALL                            2
                70      NOP                             
                72      NOP                             
                74      NOP                             
                76      JUMP_FORWARD                    20 (to 118)
                78      CALL                            1
                86      POP_TOP                         
                88      RETURN_VALUE                    
                90      PUSH_EXC_INFO                   
                92      PUSH_NULL                       
                94      LOAD_CONST                      5: '__pyarmor_exit_16445__'
                96      NOP                             
                98      LOAD_CONST                      3: b'<COAddr>\x05\x00\x00\x1a@\x00\x00\x00\x00\x00\x00\x00\x00\x00\x00\x00\x00\x00\x00\x00'
                100     CALL                            1
                108     POP_TOP                         
                110     RERAISE                         0
                112     COPY                            3
                114     POP_EXCEPT                      
                116     RERAISE                         1
                118     PUSH_NULL                       
                120     LOAD_CONST                      5: '__pyarmor_exit_16445__'
                122     LOAD_CONST                      3: b'<COAddr>\x05\x00\x00\x1a@\x00\x00\x00\x00\x00\x00\x00\x00\x00\x00\x00\x00\x00\x00\x00'
                124     BUILD_TUPLE                     1
                126     CALL_FUNCTION_EX                0
                128     POP_TOP                         
                130     RETURN_VALUE                    
            [Exception Table]
                28 to 70 -> 90 [0] 
                90 to 112 -> 112 [1] lasti
        [Code]
            File Name: <frozen multithon.password>
            Object Name: sha256
            Qualified Name: sha256
            Arg Count: 0
            Pos Only Arg Count: 0
            KW Only Arg Count: 0
            Stack Size: 5
            Flags: 0x20000007 (CO_OPTIMIZED | CO_NEWLOCALS | CO_VARARGS | CO_PYARMOR_OBFUSCATED)
            [Names]
                'hashlib'
                'sha256'
                'update'
                'digest'
            [Locals+Names]
                'p'
                '__assert_armored__'
                '_var_var_3'
                '_var_var_4'
            [Constants]
                None
                '__pyarmor_assert_16446__'
                '__pyarmor_enter_16447__'
                b'<COAddr>\x07\x00\x00\x1a\x8c\x00\x00\x00\x00\x00\x00\x00\x00\x00\x00\x00\x00\x00\x00\x00'
                '__pyarmor_exit_16448__'
            [Disassembly]
                0       NOP                             
                2       NOP                             
                4       PUSH_NULL                       
                6       LOAD_CONST                      2: '__pyarmor_enter_16447__'
                8       LOAD_CONST                      3: b'<COAddr>\x07\x00\x00\x1a\x8c\x00\x00\x00\x00\x00\x00\x00\x00\x00\x00\x00\x00\x00\x00\x00'
                10      BUILD_TUPLE                     1
                12      CALL_FUNCTION_EX                0
                14      POP_TOP                         
                16      RESUME                          0
                18      NOP                             
                20      NOP                             
                22      NOP                             
                24      NOP                             
                26      NOP                             
                28      LOAD_GLOBAL                     1: NULL + hashlib
                38      LOAD_ATTR                       2: sha256
                58      CALL                            0
                66      STORE_FAST                      2: _var_var_3
                68      LOAD_FAST                       0: p
                70      GET_ITER                        
                72      FOR_ITER                        19 (to 112)
                76      STORE_FAST                      3: _var_var_4
                78      LOAD_FAST                       2: _var_var_3
                80      LOAD_ATTR                       5: update
                100     LOAD_FAST                       3: _var_var_4
                102     CALL                            1
                110     POP_TOP                         
                112     JUMP_BACKWARD                   21 (to 72)
                114     END_FOR                         
                116     LOAD_FAST                       2: _var_var_3
                118     LOAD_ATTR                       7: digest
                138     CALL                            0
                146     NOP                             
                148     NOP                             
                150     NOP                             
                152     JUMP_FORWARD                    20 (to 194)
                154     CALL                            1
                162     POP_TOP                         
                164     RETURN_VALUE                    
                166     PUSH_EXC_INFO                   
                168     PUSH_NULL                       
                170     LOAD_CONST                      4: '__pyarmor_exit_16448__'
                172     NOP                             
                174     LOAD_CONST                      3: b'<COAddr>\x07\x00\x00\x1a\x8c\x00\x00\x00\x00\x00\x00\x00\x00\x00\x00\x00\x00\x00\x00\x00'
                176     CALL                            1
                184     POP_TOP                         
                186     RERAISE                         0
                188     COPY                            3
                190     POP_EXCEPT                      
                192     RERAISE                         1
                194     PUSH_NULL                       
                196     LOAD_CONST                      4: '__pyarmor_exit_16448__'
                198     LOAD_CONST                      3: b'<COAddr>\x07\x00\x00\x1a\x8c\x00\x00\x00\x00\x00\x00\x00\x00\x00\x00\x00\x00\x00\x00\x00'
                200     BUILD_TUPLE                     1
                202     CALL_FUNCTION_EX                0
                204     POP_TOP                         
                206     RETURN_VALUE                    
            [Exception Table]
                28 to 146 -> 166 [0] 
                166 to 188 -> 188 [1] lasti
        [Code]
            File Name: <frozen multithon.password>
            Object Name: is_good_mod_exp_first
            Qualified Name: is_good_mod_exp_first
            Arg Count: 2
            Pos Only Arg Count: 0
            KW Only Arg Count: 0
            Stack Size: 5
            Flags: 0x20000003 (CO_OPTIMIZED | CO_NEWLOCALS | CO_PYARMOR_OBFUSCATED)
            [Names]
                'bit_length'
            [Locals+Names]
                'modexp'
                'prime'
                '__assert_armored__'
                '_var_var_5'
                '_var_var_6'
                '_var_var_7'
            [Constants]
                None
                '__pyarmor_assert_16449__'
                '__pyarmor_enter_16450__'
                b'<COAddr>\x05\x00\x00\x1a\xc6\x00\x00\x00\x00\x00\x00\x00\x00\x00\x00\x00\x00\x00\x00\x00'
                1984
                256
                0
                7
                8
                '__pyarmor_exit_16451__'
                False
                True
            [Disassembly]
                0       NOP                             
                2       NOP                             
                4       PUSH_NULL                       
                6       LOAD_CONST                      2: '__pyarmor_enter_16450__'
                8       LOAD_CONST                      3: b'<COAddr>\x05\x00\x00\x1a\xc6\x00\x00\x00\x00\x00\x00\x00\x00\x00\x00\x00\x00\x00\x00\x00'
                10      BUILD_TUPLE                     1
                12      CALL_FUNCTION_EX                0
                14      POP_TOP                         
                16      RESUME                          0
                18      NOP                             
                20      NOP                             
                22      NOP                             
                24      NOP                             
                26      NOP                             
                28      LOAD_FAST                       1: prime
                30      LOAD_FAST                       0: modexp
                32      BINARY_OP                       10 (-)
                36      STORE_FAST                      3: _var_var_5
                38      LOAD_CONST                      4: 1984
                40      STORE_FAST                      4: _var_var_6
                42      LOAD_CONST                      5: 256
                44      STORE_FAST                      5: _var_var_7
                46      LOAD_FAST                       3: _var_var_5
                48      LOAD_CONST                      6: 0
                50      COMPARE_OP                      2 (<)
                54      POP_JUMP_IF_TRUE                63 (to 182)
                56      LOAD_FAST                       3: _var_var_5
                58      LOAD_ATTR                       1: bit_length
                78      CALL                            0
                86      LOAD_FAST                       4: _var_var_6
                88      COMPARE_OP                      2 (<)
                92      POP_JUMP_IF_TRUE                44 (to 182)
                94      LOAD_FAST                       0: modexp
                96      LOAD_ATTR                       1: bit_length
                116     CALL                            0
                124     LOAD_FAST                       4: _var_var_6
                126     COMPARE_OP                      2 (<)
                130     POP_JUMP_IF_TRUE                25 (to 182)
                132     LOAD_FAST                       0: modexp
                134     LOAD_ATTR                       1: bit_length
                154     CALL                            0
                162     LOAD_CONST                      7: 7
                164     BINARY_OP                       0 (+)
                168     LOAD_CONST                      8: 8
                170     BINARY_OP                       2 (//)
                174     LOAD_FAST                       5: _var_var_7
                176     COMPARE_OP                      68 (>)
                180     POP_JUMP_IF_FALSE               11 (to 204)
                182     NOP                             
                184     LOAD_CONST                      10: False
                186     NOP                             
                188     NOP                             
                190     NOP                             
                192     JUMP_FORWARD                    29 (to 252)
                200     POP_TOP                         
                202     RETURN_CONST                    10: False
                204     LOAD_CONST                      11: True
                206     NOP                             
                208     NOP                             
                210     NOP                             
                212     JUMP_FORWARD                    19 (to 252)
                220     POP_TOP                         
                222     RETURN_CONST                    11: True
                224     PUSH_EXC_INFO                   
                226     PUSH_NULL                       
                228     LOAD_CONST                      9: '__pyarmor_exit_16451__'
                230     NOP                             
                232     LOAD_CONST                      3: b'<COAddr>\x05\x00\x00\x1a\xc6\x00\x00\x00\x00\x00\x00\x00\x00\x00\x00\x00\x00\x00\x00\x00'
                234     CALL                            1
                242     POP_TOP                         
                244     RERAISE                         0
                246     COPY                            3
                248     POP_EXCEPT                      
                250     RERAISE                         1
                252     PUSH_NULL                       
                254     LOAD_CONST                      9: '__pyarmor_exit_16451__'
                256     LOAD_CONST                      3: b'<COAddr>\x05\x00\x00\x1a\xc6\x00\x00\x00\x00\x00\x00\x00\x00\x00\x00\x00\x00\x00\x00\x00'
                258     BUILD_TUPLE                     1
                260     CALL_FUNCTION_EX                0
                262     POP_TOP                         
                264     RETURN_VALUE                    
            [Exception Table]
                28 to 182 -> 224 [0] 
                224 to 246 -> 246 [1] lasti
        'a'
        'b'
        [Code]
            File Name: <frozen multithon.password>
            Object Name: xor
            Qualified Name: xor
            Arg Count: 2
            Pos Only Arg Count: 0
            KW Only Arg Count: 0
            Stack Size: 7
            Flags: 0x20000003 (CO_OPTIMIZED | CO_NEWLOCALS | CO_PYARMOR_OBFUSCATED)
            [Names]
                'bytes'
                'zip'
            [Locals+Names]
                'a'
                'b'
                '__assert_armored__'
            [Constants]
                None
                '__pyarmor_assert_16452__'
                '__pyarmor_enter_16453__'
                b'<COAddr>\x07\x00\x00\x1aL\x00\x00\x00\x00\x00\x00\x00\x00\x00\x00\x00\x00\x00\x00\x00'
                [Code]
                    File Name: <frozen multithon.password>
                    Object Name: <genexpr>
                    Qualified Name: xor.<locals>.<genexpr>
                    Arg Count: 1
                    Pos Only Arg Count: 0
                    KW Only Arg Count: 0
                    Stack Size: 3
                    Flags: 0x00000033 (CO_OPTIMIZED | CO_NEWLOCALS | CO_NESTED | CO_GENERATOR)
                    [Names]
                    [Locals+Names]
                        '.0'
                        '_var_var_8'
                        '_var_var_9'
                    [Constants]
                        None
                    [Disassembly]
                        0       RETURN_GENERATOR                
                        2       POP_TOP                         
                        4       RESUME                          0
                        6       LOAD_FAST                       0: .0
                        8       FOR_ITER                        12 (to 34)
                        12      UNPACK_SEQUENCE                 2
                        16      STORE_FAST                      1: _var_var_8
                        18      STORE_FAST                      2: _var_var_9
                        20      LOAD_FAST                       1: _var_var_8
                        22      LOAD_FAST                       2: _var_var_9
                        24      BINARY_OP                       12 (^)
                        28      YIELD_VALUE                     1
                        30      RESUME                          1
                        32      POP_TOP                         
                        34      JUMP_BACKWARD                   14 (to 8)
                        36      END_FOR                         
                        38      RETURN_CONST                    0: None
                        40      CALL_INTRINSIC_1                3 (INTRINSIC_STOPITERATION_ERROR)
                        42      RERAISE                         1
                    [Exception Table]
                        4 to 40 -> 40 [0] lasti
                '__pyarmor_exit_16454__'
            [Disassembly]
                0       NOP                             
                2       NOP                             
                4       PUSH_NULL                       
                6       LOAD_CONST                      2: '__pyarmor_enter_16453__'
                8       LOAD_CONST                      3: b'<COAddr>\x07\x00\x00\x1aL\x00\x00\x00\x00\x00\x00\x00\x00\x00\x00\x00\x00\x00\x00\x00'
                10      BUILD_TUPLE                     1
                12      CALL_FUNCTION_EX                0
                14      POP_TOP                         
                16      RESUME                          0
                18      NOP                             
                20      NOP                             
                22      NOP                             
                24      NOP                             
                26      NOP                             
                28      LOAD_GLOBAL                     1: NULL + bytes
                38      LOAD_CONST                      4: <CODE> <genexpr>
                40      MAKE_FUNCTION                   0
                42      LOAD_GLOBAL                     3: NULL + zip
                52      LOAD_FAST                       0: a
                54      LOAD_FAST                       1: b
                56      CALL                            2
                64      GET_ITER                        
                66      CALL                            0
                74      CALL                            1
                82      NOP                             
                84      NOP                             
                86      NOP                             
                88      JUMP_FORWARD                    20 (to 130)
                90      CALL                            1
                98      POP_TOP                         
                100     RETURN_VALUE                    
                102     PUSH_EXC_INFO                   
                104     PUSH_NULL                       
                106     LOAD_CONST                      5: '__pyarmor_exit_16454__'
                108     NOP                             
                110     LOAD_CONST                      3: b'<COAddr>\x07\x00\x00\x1aL\x00\x00\x00\x00\x00\x00\x00\x00\x00\x00\x00\x00\x00\x00\x00'
                112     CALL                            1
                120     POP_TOP                         
                122     RERAISE                         0
                124     COPY                            3
                126     POP_EXCEPT                      
                128     RERAISE                         1
                130     PUSH_NULL                       
                132     LOAD_CONST                      5: '__pyarmor_exit_16454__'
                134     LOAD_CONST                      3: b'<COAddr>\x07\x00\x00\x1aL\x00\x00\x00\x00\x00\x00\x00\x00\x00\x00\x00\x00\x00\x00\x00'
                136     BUILD_TUPLE                     1
                138     CALL_FUNCTION_EX                0
                140     POP_TOP                         
                142     RETURN_VALUE                    
            [Exception Table]
                28 to 82 -> 102 [0] 
                102 to 124 -> 124 [1] lasti
        'password'
        'salt'
        'iterations'
        [Code]
            File Name: <frozen multithon.password>
            Object Name: pbkdf2sha512
            Qualified Name: pbkdf2sha512
            Arg Count: 3
            Pos Only Arg Count: 0
            KW Only Arg Count: 0
            Stack Size: 6
            Flags: 0x20000003 (CO_OPTIMIZED | CO_NEWLOCALS | CO_PYARMOR_OBFUSCATED)
            [Names]
                'hashlib'
                'pbkdf2_hmac'
            [Locals+Names]
                'password'
                'salt'
                'iterations'
                '__assert_armored__'
            [Constants]
                None
                '__pyarmor_assert_16455__'
                '__pyarmor_enter_16456__'
                b'<COAddr>\x07\x00\x00\x1aD\x00\x00\x00\x00\x00\x00\x00\x00\x00\x00\x00\x00\x00\x00\x00'
                'sha512'
                '__pyarmor_exit_16457__'
            [Disassembly]
                0       NOP                             
                2       NOP                             
                4       PUSH_NULL                       
                6       LOAD_CONST                      2: '__pyarmor_enter_16456__'
                8       LOAD_CONST                      3: b'<COAddr>\x07\x00\x00\x1aD\x00\x00\x00\x00\x00\x00\x00\x00\x00\x00\x00\x00\x00\x00\x00'
                10      BUILD_TUPLE                     1
                12      CALL_FUNCTION_EX                0
                14      POP_TOP                         
                16      RESUME                          0
                18      NOP                             
                20      NOP                             
                22      NOP                             
                24      NOP                             
                26      NOP                             
                28      LOAD_GLOBAL                     1: NULL + hashlib
                38      LOAD_ATTR                       2: pbkdf2_hmac
                58      LOAD_CONST                      4: 'sha512'
                60      LOAD_FAST                       0: password
                62      LOAD_FAST                       1: salt
                64      LOAD_FAST                       2: iterations
                66      CALL                            4
                74      NOP                             
                76      NOP                             
                78      NOP                             
                80      JUMP_FORWARD                    20 (to 122)
                82      CALL                            1
                90      POP_TOP                         
                92      RETURN_VALUE                    
                94      PUSH_EXC_INFO                   
                96      PUSH_NULL                       
                98      LOAD_CONST                      5: '__pyarmor_exit_16457__'
                100     NOP                             
                102     LOAD_CONST                      3: b'<COAddr>\x07\x00\x00\x1aD\x00\x00\x00\x00\x00\x00\x00\x00\x00\x00\x00\x00\x00\x00\x00'
                104     CALL                            1
                112     POP_TOP                         
                114     RERAISE                         0
                116     COPY                            3
                118     POP_EXCEPT                      
                120     RERAISE                         1
                122     PUSH_NULL                       
                124     LOAD_CONST                      5: '__pyarmor_exit_16457__'
                126     LOAD_CONST                      3: b'<COAddr>\x07\x00\x00\x1aD\x00\x00\x00\x00\x00\x00\x00\x00\x00\x00\x00\x00\x00\x00\x00'
                128     BUILD_TUPLE                     1
                130     CALL_FUNCTION_EX                0
                132     POP_TOP                         
                134     RETURN_VALUE                    
            [Exception Table]
                28 to 74 -> 94 [0] 
                94 to 116 -> 116 [1] lasti
        'algo'
        [Code]
            File Name: <frozen multithon.password>
            Object Name: compute_hash
            Qualified Name: compute_hash
            Arg Count: 2
            Pos Only Arg Count: 0
            KW Only Arg Count: 0
            Stack Size: 6
            Flags: 0x20000003 (CO_OPTIMIZED | CO_NEWLOCALS | CO_PYARMOR_OBFUSCATED)
            [Names]
                'sha256'
                'salt1'
                'encode'
                'salt2'
                'pbkdf2sha512'
            [Locals+Names]
                'algo'
                'password'
                '__assert_armored__'
                '_var_var_10'
                '_var_var_11'
                '_var_var_12'
            [Constants]
                None
                '__pyarmor_assert_16458__'
                '__pyarmor_enter_16459__'
                b'<COAddr>\x05\x00\x00\x1a&\x01\x00\x00\x00\x00\x00\x00\x00\x00\x00\x00\x00\x00\x00\x00'
                'utf-8'
                100000
                '__pyarmor_exit_16460__'
            [Disassembly]
                0       NOP                             
                2       NOP                             
                4       PUSH_NULL                       
                6       LOAD_CONST                      2: '__pyarmor_enter_16459__'
                8       LOAD_CONST                      3: b'<COAddr>\x05\x00\x00\x1a&\x01\x00\x00\x00\x00\x00\x00\x00\x00\x00\x00\x00\x00\x00\x00'
                10      BUILD_TUPLE                     1
                12      CALL_FUNCTION_EX                0
                14      POP_TOP                         
                16      RESUME                          0
                18      NOP                             
                20      NOP                             
                22      NOP                             
                24      NOP                             
                26      NOP                             
                28      LOAD_GLOBAL                     1: NULL + sha256
                38      LOAD_FAST                       0: algo
                40      LOAD_ATTR                       2: salt1
                60      LOAD_FAST                       1: password
                62      LOAD_ATTR                       5: encode
                82      LOAD_CONST                      4: 'utf-8'
                84      CALL                            1
                92      LOAD_FAST                       0: algo
                94      LOAD_ATTR                       2: salt1
                114     CALL                            3
                122     STORE_FAST                      3: _var_var_10
                124     LOAD_GLOBAL                     1: NULL + sha256
                134     LOAD_FAST                       0: algo
                136     LOAD_ATTR                       6: salt2
                156     LOAD_FAST                       3: _var_var_10
                158     LOAD_FAST                       0: algo
                160     LOAD_ATTR                       6: salt2
                180     CALL                            3
                188     STORE_FAST                      4: _var_var_11
                190     LOAD_GLOBAL                     9: NULL + pbkdf2sha512
                200     LOAD_FAST                       4: _var_var_11
                202     LOAD_FAST                       0: algo
                204     LOAD_ATTR                       2: salt1
                224     LOAD_CONST                      5: 100000
                226     CALL                            3
                234     STORE_FAST                      5: _var_var_12
                236     LOAD_GLOBAL                     1: NULL + sha256
                246     LOAD_FAST                       0: algo
                248     LOAD_ATTR                       6: salt2
                268     LOAD_FAST                       5: _var_var_12
                270     LOAD_FAST                       0: algo
                272     LOAD_ATTR                       6: salt2
                292     CALL                            3
                300     NOP                             
                302     NOP                             
                304     NOP                             
                306     JUMP_FORWARD                    20 (to 348)
                308     CALL                            1
                316     POP_TOP                         
                318     RETURN_VALUE                    
                320     PUSH_EXC_INFO                   
                322     PUSH_NULL                       
                324     LOAD_CONST                      6: '__pyarmor_exit_16460__'
                326     NOP                             
                328     LOAD_CONST                      3: b'<COAddr>\x05\x00\x00\x1a&\x01\x00\x00\x00\x00\x00\x00\x00\x00\x00\x00\x00\x00\x00\x00'
                330     CALL                            1
                338     POP_TOP                         
                340     RERAISE                         0
                342     COPY                            3
                344     POP_EXCEPT                      
                346     RERAISE                         1
                348     PUSH_NULL                       
                350     LOAD_CONST                      6: '__pyarmor_exit_16460__'
                352     LOAD_CONST                      3: b'<COAddr>\x05\x00\x00\x1a&\x01\x00\x00\x00\x00\x00\x00\x00\x00\x00\x00\x00\x00\x00\x00'
                354     BUILD_TUPLE                     1
                356     CALL_FUNCTION_EX                0
                358     POP_TOP                         
                360     RETURN_VALUE                    
            [Exception Table]
                28 to 300 -> 320 [0] 
                320 to 342 -> 342 [1] lasti
        [Code]
            File Name: <frozen multithon.password>
            Object Name: compute_digest
            Qualified Name: compute_digest
            Arg Count: 2
            Pos Only Arg Count: 0
            KW Only Arg Count: 0
            Stack Size: 9
            Flags: 0x20000003 (CO_OPTIMIZED | CO_NEWLOCALS | CO_PYARMOR_OBFUSCATED)
            [Names]
                'check_prime_and_good'
                'p'
                'g'
                'ValueError'
                'pow'
                'int'
                'from_bytes'
                'compute_hash'
                'big_num_for_hash'
            [Locals+Names]
                'algo'
                'password'
                '__assert_armored__'
                '_var_var_13'
            [Constants]
                None
                '__pyarmor_assert_16461__'
                '__pyarmor_enter_16462__'
                b'<COAddr>\x05\x00\x00\x1aN\x01\x00\x00\x00\x00\x00\x00\x00\x00\x00\x00\x00\x00\x00\x00'
                'bad p/g in password'   # b'\x81\xe0\x19\x17s\xea\xf1\xd5[\xf3\x03\x80|\xed\xeb\x96\x18R\xa9\xa3'
                'big'
                '__pyarmor_exit_16463__'
            [Disassembly]
                0       NOP                             
                2       NOP                             
                4       PUSH_NULL                       
                6       LOAD_CONST                      2: '__pyarmor_enter_16462__'
                8       LOAD_CONST                      3: b'<COAddr>\x05\x00\x00\x1aN\x01\x00\x00\x00\x00\x00\x00\x00\x00\x00\x00\x00\x00\x00\x00'
                10      BUILD_TUPLE                     1
                12      CALL_FUNCTION_EX                0
                14      POP_TOP                         
                16      RESUME                          0
                18      NOP                             
                20      NOP                             
                22      NOP                             
                24      NOP                             
                26      NOP                             
                28      NOP                             
                30      LOAD_GLOBAL                     1: NULL + check_prime_and_good
                40      LOAD_FAST                       0: algo
                42      LOAD_ATTR                       2: p
                62      LOAD_FAST                       0: algo
                64      LOAD_ATTR                       4: g
                84      CALL                            2
                92      POP_TOP                         
                94      LOAD_GLOBAL                     9: NULL + pow
                104     LOAD_FAST                       0: algo
                106     LOAD_ATTR                       4: g
                126     LOAD_GLOBAL                     10: int
                136     LOAD_ATTR                       13: from_bytes
                156     LOAD_GLOBAL                     15: NULL + compute_hash
                166     LOAD_FAST                       0: algo
                168     LOAD_FAST                       1: password
                170     CALL                            2
                178     LOAD_CONST                      5: 'big'
                180     CALL                            2
                188     LOAD_GLOBAL                     10: int
                198     LOAD_ATTR                       13: from_bytes
                218     LOAD_FAST                       0: algo
                220     LOAD_ATTR                       2: p
                240     LOAD_CONST                      5: 'big'
                242     CALL                            2
                250     CALL                            3
                258     STORE_FAST                      3: _var_var_13
                260     LOAD_GLOBAL                     17: NULL + big_num_for_hash
                270     LOAD_FAST                       3: _var_var_13
                272     CALL                            1
                280     NOP                             
                282     NOP                             
                284     NOP                             
                286     JUMP_FORWARD                    50 (to 388)
                288     CALL                            1
                296     POP_TOP                         
                298     RETURN_VALUE                    
                300     PUSH_EXC_INFO                   
                302     LOAD_GLOBAL                     6: ValueError
                312     CHECK_EXC_MATCH                 
                314     POP_JUMP_IF_FALSE               18 (to 352)
                316     POP_TOP                         
                318     LOAD_GLOBAL                     7: NULL + ValueError
                328     PUSH_NULL                       
                330     LOAD_CONST                      1: '__pyarmor_assert_16461__'
                332     LOAD_CONST                      4: 'bad p/g in password'   # b'\x81\xe0\x19\x17s\xea\xf1\xd5[\xf3\x03\x80|\xed\xeb\x96\x18R\xa9\xa3'
                334     CALL                            1
                342     CALL                            1
                350     RAISE_VARARGS                   1
                352     RERAISE                         0
                354     COPY                            3
                356     POP_EXCEPT                      
                358     RERAISE                         1
                360     PUSH_EXC_INFO                   
                362     PUSH_NULL                       
                364     LOAD_CONST                      6: '__pyarmor_exit_16463__'
                366     NOP                             
                368     LOAD_CONST                      3: b'<COAddr>\x05\x00\x00\x1aN\x01\x00\x00\x00\x00\x00\x00\x00\x00\x00\x00\x00\x00\x00\x00'
                370     CALL                            1
                378     POP_TOP                         
                380     RERAISE                         0
                382     COPY                            3
                384     POP_EXCEPT                      
                386     RERAISE                         1
                388     PUSH_NULL                       
                390     LOAD_CONST                      6: '__pyarmor_exit_16463__'
                392     LOAD_CONST                      3: b'<COAddr>\x05\x00\x00\x1aN\x01\x00\x00\x00\x00\x00\x00\x00\x00\x00\x00\x00\x00\x00\x00'
                394     BUILD_TUPLE                     1
                396     CALL_FUNCTION_EX                0
                398     POP_TOP                         
                400     RETURN_VALUE                    
            [Exception Table]
                30 to 94 -> 300 [0] 
                94 to 280 -> 360 [0] 
                300 to 354 -> 354 [1] lasti
                354 to 360 -> 360 [0] 
                360 to 382 -> 382 [1] lasti
        'request'
        [Code]
            File Name: <frozen multithon.password>
            Object Name: compute_check
            Qualified Name: compute_check
            Arg Count: 2
            Pos Only Arg Count: 0
            KW Only Arg Count: 0
            Stack Size: 8
            Flags: 0x20000003 (CO_OPTIMIZED | CO_NEWLOCALS | CO_PYARMOR_OBFUSCATED)
            [Names]
                'current_algo'
                'isinstance'
                'types'
                'PasswordKdfAlgoSHA256SHA256PBKDF2HMACSHA512iter100000SHA256ModPow'
                'ValueError'
                'format'
                '__class__'
                '__name__'
                'compute_hash'
                'int'
                'from_bytes'
                'p'
                'g'
                'srp_B'
                'check_prime_and_good'
                'is_good_large'
                'num_bytes_for_hash'
                'big_num_for_hash'
                'pow'
                'sha256'
                'is_good_mod_exp_first'
                'xor'
                'salt1'
                'salt2'
                'InputCheckPasswordSRP'
                'srp_id'
                'bytes'
            [Locals+Names]
                'request'
                'password'
                '__assert_armored__'
                '_var_var_17'
                '_var_var_18'
                '_var_var_19'
                '_var_var_8'
                '_var_var_20'
                '_var_var_21'
                '_var_var_22'
                '_var_var_23'
                '_var_var_24'
                '_var_var_25'
                '_var_var_26'
                '_var_var_27'
                '_var_var_28'
                '_var_var_29'
                '_var_var_30'
                '_var_var_31'
                '_var_var_32'
                '_var_var_33'
                '_var_var_34'
                '_var_var_14'
                '_var_var_15'
                '_var_var_16'
            [Constants]
                None
                '__pyarmor_assert_16464__'
                '__pyarmor_enter_16465__'
                b'<COAddr>\x07\x00\x00 \xde\x04\x00\x00\x00\x00\x00\x00\x00\x00\x00\x00\x00\x00\x00\x00'
                'unsupported password algorithm {}'   # b'\x81\xf7\x16\x00&\xea\xae\xdd\t\xee\x08\xc4,\xfc\xf9\x96\x1cJ\xb4\xb5\xae\x8bO\xc0\x02`\xb1U\x14\xb9\x13\xa5!O'
                'big'
                'bad p/g in password'   # b'\x81\xe0\x19\x17s\xea\xf1\xd5[\xf3\x03\x80|\xed\xeb\x96\x18R\xa9\xa3'
                'bad b in check'   # b'\x81\xe0\x19\x17s\xf8\xfe\xdb\x15\xba\x0e\xc8i\xef\xf3'
                [Code]
                    File Name: <frozen multithon.password>
                    Object Name: generate_and_check_random
                    Qualified Name: compute_check.<locals>.generate_and_check_random
                    Arg Count: 0
                    Pos Only Arg Count: 0
                    KW Only Arg Count: 0
                    Stack Size: 6
                    Flags: 0x20000013 (CO_OPTIMIZED | CO_NEWLOCALS | CO_NESTED | CO_PYARMOR_OBFUSCATED)
                    [Names]
                        'os'
                        'urandom'
                        'int'
                        'from_bytes'
                        'pow'
                        'is_good_mod_exp_first'
                        'big_num_for_hash'
                        'sha256'
                    [Locals+Names]
                        '__assert_armored__'
                        '_var_var_35'
                        '_var_var_36'
                        '_var_var_26'
                        '_var_var_37'
                        '_var_var_27'
                        '_var_var_28'
                        '_var_var_14'
                        '_var_var_15'
                        '_var_var_16'
                    [Constants]
                        None
                        '__pyarmor_assert_16467__'
                        '__pyarmor_enter_16468__'
                        b'<COAddr>\x05\x00\x00\x1c\x0e\x01\x00\x00\x00\x00\x00\x00\x00\x00\x00\x00\x00\x00\x00\x00'
                        256
                        'big'
                        0
                        '__pyarmor_exit_16469__'
                    [Disassembly]
                        0       COPY_FREE_VARS                  3
                        2       NOP                             
                        4       NOP                             
                        6       PUSH_NULL                       
                        8       LOAD_CONST                      2: '__pyarmor_enter_16468__'
                        10      LOAD_CONST                      3: b'<COAddr>\x05\x00\x00\x1c\x0e\x01\x00\x00\x00\x00\x00\x00\x00\x00\x00\x00\x00\x00\x00\x00'
                        12      BUILD_TUPLE                     1
                        14      CALL_FUNCTION_EX                0
                        16      POP_TOP                         
                        18      RESUME                          0
                        20      NOP                             
                        22      NOP                             
                        24      NOP                             
                        26      NOP                             
                        28      NOP                             
                        30      LOAD_CONST                      4: 256
                        32      STORE_FAST                      1: _var_var_35
                        34      NOP                             
                        36      LOAD_GLOBAL                     1: NULL + os
                        46      LOAD_ATTR                       2: urandom
                        66      LOAD_FAST                       1: _var_var_35
                        68      CALL                            1
                        76      STORE_FAST                      2: _var_var_36
                        78      LOAD_GLOBAL                     4: int
                        88      LOAD_ATTR                       7: from_bytes
                        108     LOAD_FAST                       2: _var_var_36
                        110     LOAD_CONST                      5: 'big'
                        112     CALL                            2
                        120     STORE_FAST                      3: _var_var_26
                        122     LOAD_GLOBAL                     9: NULL + pow
                        132     LOAD_DEREF                      8: _var_var_15
                        134     LOAD_FAST                       3: _var_var_26
                        136     LOAD_DEREF                      9: _var_var_16
                        138     CALL                            3
                        146     STORE_FAST                      4: _var_var_37
                        148     LOAD_GLOBAL                     11: NULL + is_good_mod_exp_first
                        158     LOAD_FAST                       4: _var_var_37
                        160     LOAD_DEREF                      9: _var_var_16
                        162     CALL                            2
                        170     POP_JUMP_IF_FALSE               62 (to 296)
                        172     LOAD_GLOBAL                     13: NULL + big_num_for_hash
                        182     LOAD_FAST                       4: _var_var_37
                        184     CALL                            1
                        192     STORE_FAST                      5: _var_var_27
                        194     LOAD_GLOBAL                     4: int
                        204     LOAD_ATTR                       7: from_bytes
                        224     LOAD_GLOBAL                     15: NULL + sha256
                        234     LOAD_FAST                       5: _var_var_27
                        236     LOAD_DEREF                      7: _var_var_14
                        238     CALL                            2
                        246     LOAD_CONST                      5: 'big'
                        248     CALL                            2
                        256     STORE_FAST                      6: _var_var_28
                        258     LOAD_FAST                       6: _var_var_28
                        260     LOAD_CONST                      6: 0
                        262     COMPARE_OP                      68 (>)
                        266     POP_JUMP_IF_FALSE               14 (to 296)
                        268     LOAD_FAST                       3: _var_var_26
                        270     LOAD_FAST                       5: _var_var_27
                        272     LOAD_FAST                       6: _var_var_28
                        274     BUILD_TUPLE                     3
                        276     NOP                             
                        278     NOP                             
                        280     NOP                             
                        282     JUMP_FORWARD                    21 (to 326)
                        284     CALL                            1
                        292     POP_TOP                         
                        294     RETURN_VALUE                    
                        296     JUMP_BACKWARD                   131 (to 36)
                        298     PUSH_EXC_INFO                   
                        300     PUSH_NULL                       
                        302     LOAD_CONST                      7: '__pyarmor_exit_16469__'
                        304     NOP                             
                        306     LOAD_CONST                      3: b'<COAddr>\x05\x00\x00\x1c\x0e\x01\x00\x00\x00\x00\x00\x00\x00\x00\x00\x00\x00\x00\x00\x00'
                        308     CALL                            1
                        316     POP_TOP                         
                        318     RERAISE                         0
                        320     COPY                            3
                        322     POP_EXCEPT                      
                        324     RERAISE                         1
                        326     PUSH_NULL                       
                        328     LOAD_CONST                      7: '__pyarmor_exit_16469__'
                        330     LOAD_CONST                      3: b'<COAddr>\x05\x00\x00\x1c\x0e\x01\x00\x00\x00\x00\x00\x00\x00\x00\x00\x00\x00\x00\x00\x00'
                        332     BUILD_TUPLE                     1
                        334     CALL_FUNCTION_EX                0
                        336     POP_TOP                         
                        338     RETURN_VALUE                    
                    [Exception Table]
                        30 to 276 -> 298 [0] 
                        296 to 298 -> 298 [0] 
                        298 to 320 -> 320 [1] lasti
                'bad g_b'
                '__pyarmor_exit_16466__'
            [Disassembly]
                0       MAKE_CELL                       22: _var_var_14
                2       MAKE_CELL                       23: _var_var_15
                4       MAKE_CELL                       24: _var_var_16
                6       NOP                             
                8       NOP                             
                10      PUSH_NULL                       
                12      LOAD_CONST                      2: '__pyarmor_enter_16465__'
                14      LOAD_CONST                      3: b'<COAddr>\x07\x00\x00 \xde\x04\x00\x00\x00\x00\x00\x00\x00\x00\x00\x00\x00\x00\x00\x00'
                16      BUILD_TUPLE                     1
                18      CALL_FUNCTION_EX                0
                20      POP_TOP                         
                22      RESUME                          0
                24      NOP                             
                26      NOP                             
                28      NOP                             
                30      NOP                             
                32      NOP                             
                34      LOAD_FAST                       0: request
                36      LOAD_ATTR                       0: current_algo
                56      STORE_FAST                      3: _var_var_17
                58      LOAD_GLOBAL                     3: NULL + isinstance
                68      LOAD_FAST                       3: _var_var_17
                70      LOAD_GLOBAL                     4: types
                80      LOAD_ATTR                       6: PasswordKdfAlgoSHA256SHA256PBKDF2HMACSHA512iter100000SHA256ModPow
                100     CALL                            2
                108     POP_JUMP_IF_TRUE                52 (to 214)
                110     LOAD_GLOBAL                     9: NULL + ValueError
                120     PUSH_NULL                       
                122     LOAD_CONST                      1: '__pyarmor_assert_16464__'
                124     LOAD_CONST                      4: 'unsupported password algorithm {}'   # b'\x81\xf7\x16\x00&\xea\xae\xdd\t\xee\x08\xc4,\xfc\xf9\x96\x1cJ\xb4\xb5\xae\x8bO\xc0\x02`\xb1U\x14\xb9\x13\xa5!O'
                126     CALL                            1
                134     LOAD_ATTR                       11: format
                154     LOAD_FAST                       3: _var_var_17
                156     LOAD_ATTR                       12: __class__
                176     LOAD_ATTR                       14: __name__
                196     CALL                            1
                204     CALL                            1
                212     RAISE_VARARGS                   1
                214     LOAD_GLOBAL                     17: NULL + compute_hash
                224     LOAD_FAST                       3: _var_var_17
                226     LOAD_FAST                       1: password
                228     CALL                            2
                236     STORE_FAST                      4: _var_var_18
                238     LOAD_GLOBAL                     18: int
                248     LOAD_ATTR                       21: from_bytes
                268     LOAD_FAST                       3: _var_var_17
                270     LOAD_ATTR                       22: p
                290     LOAD_CONST                      5: 'big'
                292     CALL                            2
                300     STORE_DEREF                     24: _var_var_16
                302     LOAD_FAST                       3: _var_var_17
                304     LOAD_ATTR                       24: g
                324     STORE_DEREF                     23: _var_var_15
                326     LOAD_GLOBAL                     18: int
                336     LOAD_ATTR                       21: from_bytes
                356     LOAD_FAST                       0: request
                358     LOAD_ATTR                       26: srp_B
                378     LOAD_CONST                      5: 'big'
                380     CALL                            2
                388     STORE_FAST                      5: _var_var_19
                390     NOP                             
                392     LOAD_GLOBAL                     29: NULL + check_prime_and_good
                402     LOAD_FAST                       3: _var_var_17
                404     LOAD_ATTR                       22: p
                424     LOAD_DEREF                      23: _var_var_15
                426     CALL                            2
                434     POP_TOP                         
                436     LOAD_GLOBAL                     31: NULL + is_good_large
                446     LOAD_FAST                       5: _var_var_19
                448     LOAD_DEREF                      24: _var_var_16
                450     CALL                            2
                458     POP_JUMP_IF_TRUE                17 (to 494)
                460     LOAD_GLOBAL                     9: NULL + ValueError
                470     PUSH_NULL                       
                472     LOAD_CONST                      1: '__pyarmor_assert_16464__'
                474     LOAD_CONST                      7: 'bad b in check'   # b'\x81\xe0\x19\x17s\xf8\xfe\xdb\x15\xba\x0e\xc8i\xef\xf3'
                476     CALL                            1
                484     CALL                            1
                492     RAISE_VARARGS                   1
                494     LOAD_GLOBAL                     18: int
                504     LOAD_ATTR                       21: from_bytes
                524     LOAD_FAST                       4: _var_var_18
                526     LOAD_CONST                      5: 'big'
                528     CALL                            2
                536     STORE_FAST                      6: _var_var_8
                538     LOAD_GLOBAL                     33: NULL + num_bytes_for_hash
                548     LOAD_FAST                       3: _var_var_17
                550     LOAD_ATTR                       22: p
                570     CALL                            1
                578     STORE_FAST                      7: _var_var_20
                580     LOAD_GLOBAL                     35: NULL + big_num_for_hash
                590     LOAD_DEREF                      23: _var_var_15
                592     CALL                            1
                600     STORE_FAST                      8: _var_var_21
                602     LOAD_GLOBAL                     33: NULL + num_bytes_for_hash
                612     LOAD_FAST                       0: request
                614     LOAD_ATTR                       26: srp_B
                634     CALL                            1
                642     STORE_DEREF                     22: _var_var_14
                644     LOAD_GLOBAL                     37: NULL + pow
                654     LOAD_DEREF                      23: _var_var_15
                656     LOAD_FAST                       6: _var_var_8
                658     LOAD_DEREF                      24: _var_var_16
                660     CALL                            3
                668     STORE_FAST                      9: _var_var_22
                670     LOAD_GLOBAL                     18: int
                680     LOAD_ATTR                       21: from_bytes
                700     LOAD_GLOBAL                     39: NULL + sha256
                710     LOAD_FAST                       7: _var_var_20
                712     LOAD_FAST                       8: _var_var_21
                714     CALL                            2
                722     LOAD_CONST                      5: 'big'
                724     CALL                            2
                732     STORE_FAST                      10: _var_var_23
                734     LOAD_FAST                       10: _var_var_23
                736     LOAD_FAST                       9: _var_var_22
                738     BINARY_OP                       5 (*)
                742     LOAD_DEREF                      24: _var_var_16
                744     BINARY_OP                       6 (%)
                748     STORE_FAST                      11: _var_var_24
                750     LOAD_CLOSURE                    22: _var_var_14
                752     LOAD_CLOSURE                    23: _var_var_15
                754     LOAD_CLOSURE                    24: _var_var_16
                756     BUILD_TUPLE                     3
                758     LOAD_CONST                      8: <CODE> generate_and_check_random
                760     MAKE_FUNCTION                   8
                762     STORE_FAST                      12: _var_var_25
                764     PUSH_NULL                       
                766     LOAD_FAST                       12: _var_var_25
                768     CALL                            0
                776     UNPACK_SEQUENCE                 3
                780     STORE_FAST                      13: _var_var_26
                782     STORE_FAST                      14: _var_var_27
                784     STORE_FAST                      15: _var_var_28
                786     LOAD_FAST                       5: _var_var_19
                788     LOAD_FAST                       11: _var_var_24
                790     BINARY_OP                       10 (-)
                794     LOAD_DEREF                      24: _var_var_16
                796     BINARY_OP                       6 (%)
                800     STORE_FAST                      16: _var_var_29
                802     LOAD_GLOBAL                     41: NULL + is_good_mod_exp_first
                812     LOAD_FAST                       16: _var_var_29
                814     LOAD_DEREF                      24: _var_var_16
                816     CALL                            2
                824     POP_JUMP_IF_TRUE                11 (to 848)
                826     LOAD_GLOBAL                     9: NULL + ValueError
                836     LOAD_CONST                      9: 'bad g_b'
                838     CALL                            1
                846     RAISE_VARARGS                   1
                848     LOAD_FAST                       15: _var_var_28
                850     LOAD_FAST                       6: _var_var_8
                852     BINARY_OP                       5 (*)
                856     STORE_FAST                      17: _var_var_30
                858     LOAD_FAST                       13: _var_var_26
                860     LOAD_FAST                       17: _var_var_30
                862     BINARY_OP                       0 (+)
                866     STORE_FAST                      18: _var_var_31
                868     LOAD_GLOBAL                     37: NULL + pow
                878     LOAD_FAST                       16: _var_var_29
                880     LOAD_FAST                       18: _var_var_31
                882     LOAD_DEREF                      24: _var_var_16
                884     CALL                            3
                892     STORE_FAST                      19: _var_var_32
                894     LOAD_GLOBAL                     39: NULL + sha256
                904     LOAD_GLOBAL                     35: NULL + big_num_for_hash
                914     LOAD_FAST                       19: _var_var_32
                916     CALL                            1
                924     CALL                            1
                932     STORE_FAST                      20: _var_var_33
                934     LOAD_GLOBAL                     39: NULL + sha256
                944     LOAD_GLOBAL                     43: NULL + xor
                954     LOAD_GLOBAL                     39: NULL + sha256
                964     LOAD_FAST                       7: _var_var_20
                966     CALL                            1
                974     LOAD_GLOBAL                     39: NULL + sha256
                984     LOAD_FAST                       8: _var_var_21
                986     CALL                            1
                994     CALL                            2
                1002    LOAD_GLOBAL                     39: NULL + sha256
                1012    LOAD_FAST                       3: _var_var_17
                1014    LOAD_ATTR                       44: salt1
                1034    CALL                            1
                1042    LOAD_GLOBAL                     39: NULL + sha256
                1052    LOAD_FAST                       3: _var_var_17
                1054    LOAD_ATTR                       46: salt2
                1074    CALL                            1
                1082    LOAD_FAST                       14: _var_var_27
                1084    LOAD_DEREF                      22: _var_var_14
                1086    LOAD_FAST                       20: _var_var_33
                1088    CALL                            6
                1096    STORE_FAST                      21: _var_var_34
                1098    LOAD_GLOBAL                     5: NULL + types
                1108    LOAD_ATTR                       48: InputCheckPasswordSRP
                1128    LOAD_FAST                       0: request
                1130    LOAD_ATTR                       50: srp_id
                1150    LOAD_GLOBAL                     53: NULL + bytes
                1160    LOAD_FAST                       14: _var_var_27
                1162    CALL                            1
                1170    LOAD_GLOBAL                     53: NULL + bytes
                1180    LOAD_FAST                       21: _var_var_34
                1182    CALL                            1
                1190    CALL                            3
                1198    NOP                             
                1200    NOP                             
                1202    NOP                             
                1204    JUMP_FORWARD                    50 (to 1306)
                1206    CALL                            1
                1214    POP_TOP                         
                1216    RETURN_VALUE                    
                1218    PUSH_EXC_INFO                   
                1220    LOAD_GLOBAL                     8: ValueError
                1230    CHECK_EXC_MATCH                 
                1232    POP_JUMP_IF_FALSE               18 (to 1270)
                1234    POP_TOP                         
                1236    LOAD_GLOBAL                     9: NULL + ValueError
                1246    PUSH_NULL                       
                1248    LOAD_CONST                      1: '__pyarmor_assert_16464__'
                1250    LOAD_CONST                      6: 'bad p/g in password'   # b'\x81\xe0\x19\x17s\xea\xf1\xd5[\xf3\x03\x80|\xed\xeb\x96\x18R\xa9\xa3'
                1252    CALL                            1
                1260    CALL                            1
                1268    RAISE_VARARGS                   1
                1270    RERAISE                         0
                1272    COPY                            3
                1274    POP_EXCEPT                      
                1276    RERAISE                         1
                1278    PUSH_EXC_INFO                   
                1280    PUSH_NULL                       
                1282    LOAD_CONST                      10: '__pyarmor_exit_16466__'
                1284    NOP                             
                1286    LOAD_CONST                      3: b'<COAddr>\x07\x00\x00 \xde\x04\x00\x00\x00\x00\x00\x00\x00\x00\x00\x00\x00\x00\x00\x00'
                1288    CALL                            1
                1296    POP_TOP                         
                1298    RERAISE                         0
                1300    COPY                            3
                1302    POP_EXCEPT                      
                1304    RERAISE                         1
                1306    PUSH_NULL                       
                1308    LOAD_CONST                      10: '__pyarmor_exit_16466__'
                1310    LOAD_CONST                      3: b'<COAddr>\x07\x00\x00 \xde\x04\x00\x00\x00\x00\x00\x00\x00\x00\x00\x00\x00\x00\x00\x00'
                1312    BUILD_TUPLE                     1
                1314    CALL_FUNCTION_EX                0
                1316    POP_TOP                         
                1318    RETURN_VALUE                    
            [Exception Table]
                34 to 390 -> 1278 [0] 
                392 to 436 -> 1218 [0] 
                436 to 1198 -> 1278 [0] 
                1218 to 1272 -> 1272 [1] lasti
                1272 to 1278 -> 1278 [0] 
                1278 to 1300 -> 1300 [1] lasti
        '__pyarmor_exit_16430__'
    [Disassembly]
        0       NOP                             
        2       NOP                             
        4       PUSH_NULL                       
        6       LOAD_CONST                      1: '__pyarmor_enter_16429__'
        8       LOAD_CONST                      2: b'<COAddr>\x07\x00\x00\x1aX\x01\x00\x00\x00\x00\x00\x00\x00\x00\x00\x00\x00\x00\x00\x00'
        10      BUILD_TUPLE                     1
        12      CALL_FUNCTION_EX                0
        14      POP_TOP                         
        16      RESUME                          0
        18      NOP                             
        20      NOP                             
        22      NOP                             
        24      NOP                             
        26      LOAD_CONST                      3: 0
        28      LOAD_CONST                      4: None
        30      IMPORT_NAME                     1: hashlib
        32      STORE_NAME                      1: hashlib
        34      LOAD_CONST                      3: 0
        36      LOAD_CONST                      4: None
        38      IMPORT_NAME                     2: os
        40      STORE_NAME                      2: os
        42      LOAD_CONST                      5: 1
        44      LOAD_CONST                      6: ('factorization',)
        46      IMPORT_NAME                     3: crypto
        48      IMPORT_FROM                     4: factorization
        50      STORE_NAME                      4: factorization
        52      POP_TOP                         
        54      LOAD_CONST                      5: 1
        56      LOAD_CONST                      7: ('types',)
        58      IMPORT_NAME                     5: tl
        60      IMPORT_FROM                     6: types
        62      STORE_NAME                      6: types
        64      POP_TOP                         
        66      LOAD_CONST                      8: 'prime'
        68      LOAD_NAME                       7: int
        70      LOAD_CONST                      9: 'g'
        72      LOAD_NAME                       7: int
        74      BUILD_TUPLE                     4
        76      LOAD_CONST                      10: <CODE> check_prime_and_good_check
        78      MAKE_FUNCTION                   4
        80      STORE_NAME                      8: check_prime_and_good_check
        82      LOAD_CONST                      11: 'prime_bytes'
        84      LOAD_NAME                       9: bytes
        86      LOAD_CONST                      9: 'g'
        88      LOAD_NAME                       7: int
        90      BUILD_TUPLE                     4
        92      LOAD_CONST                      12: <CODE> check_prime_and_good
        94      MAKE_FUNCTION                   4
        96      STORE_NAME                      10: check_prime_and_good
        98      LOAD_CONST                      13: 'number'
        100     LOAD_NAME                       7: int
        102     LOAD_CONST                      14: 'p'
        104     LOAD_NAME                       7: int
        106     LOAD_CONST                      15: 'return'
        108     LOAD_NAME                       11: bool
        110     BUILD_TUPLE                     6
        112     LOAD_CONST                      16: <CODE> is_good_large
        114     MAKE_FUNCTION                   4
        116     STORE_NAME                      12: is_good_large
        118     LOAD_CONST                      17: 256
        120     STORE_NAME                      13: SIZE_FOR_HASH
        122     LOAD_CONST                      13: 'number'
        124     LOAD_NAME                       9: bytes
        126     LOAD_CONST                      15: 'return'
        128     LOAD_NAME                       9: bytes
        130     BUILD_TUPLE                     4
        132     LOAD_CONST                      18: <CODE> num_bytes_for_hash
        134     MAKE_FUNCTION                   4
        136     STORE_NAME                      14: num_bytes_for_hash
        138     LOAD_CONST                      9: 'g'
        140     LOAD_NAME                       7: int
        142     LOAD_CONST                      15: 'return'
        144     LOAD_NAME                       9: bytes
        146     BUILD_TUPLE                     4
        148     LOAD_CONST                      19: <CODE> big_num_for_hash
        150     MAKE_FUNCTION                   4
        152     STORE_NAME                      15: big_num_for_hash
        154     LOAD_CONST                      14: 'p'
        156     LOAD_NAME                       9: bytes
        158     LOAD_CONST                      15: 'return'
        160     LOAD_NAME                       9: bytes
        162     BUILD_TUPLE                     4
        164     LOAD_CONST                      20: <CODE> sha256
        166     MAKE_FUNCTION                   4
        168     STORE_NAME                      16: sha256
        170     LOAD_CONST                      15: 'return'
        172     LOAD_NAME                       11: bool
        174     BUILD_TUPLE                     2
        176     LOAD_CONST                      21: <CODE> is_good_mod_exp_first
        178     MAKE_FUNCTION                   4
        180     STORE_NAME                      17: is_good_mod_exp_first
        182     LOAD_CONST                      22: 'a'
        184     LOAD_NAME                       9: bytes
        186     LOAD_CONST                      23: 'b'
        188     LOAD_NAME                       9: bytes
        190     LOAD_CONST                      15: 'return'
        192     LOAD_NAME                       9: bytes
        194     BUILD_TUPLE                     6
        196     LOAD_CONST                      24: <CODE> xor
        198     MAKE_FUNCTION                   4
        200     STORE_NAME                      18: xor
        202     LOAD_CONST                      25: 'password'
        204     LOAD_NAME                       9: bytes
        206     LOAD_CONST                      26: 'salt'
        208     LOAD_NAME                       9: bytes
        210     LOAD_CONST                      27: 'iterations'
        212     LOAD_NAME                       7: int
        214     BUILD_TUPLE                     6
        216     LOAD_CONST                      28: <CODE> pbkdf2sha512
        218     MAKE_FUNCTION                   4
        220     STORE_NAME                      19: pbkdf2sha512
        222     LOAD_CONST                      29: 'algo'
        224     LOAD_NAME                       6: types
        226     LOAD_ATTR                       40: PasswordKdfAlgoSHA256SHA256PBKDF2HMACSHA512iter100000SHA256ModPow
        246     LOAD_CONST                      25: 'password'
        248     LOAD_NAME                       21: str
        250     BUILD_TUPLE                     4
        252     LOAD_CONST                      30: <CODE> compute_hash
        254     MAKE_FUNCTION                   4
        256     STORE_NAME                      22: compute_hash
        258     LOAD_CONST                      29: 'algo'
        260     LOAD_NAME                       6: types
        262     LOAD_ATTR                       40: PasswordKdfAlgoSHA256SHA256PBKDF2HMACSHA512iter100000SHA256ModPow
        282     LOAD_CONST                      25: 'password'
        284     LOAD_NAME                       21: str
        286     BUILD_TUPLE                     4
        288     LOAD_CONST                      31: <CODE> compute_digest
        290     MAKE_FUNCTION                   4
        292     STORE_NAME                      23: compute_digest
        294     LOAD_CONST                      32: 'request'
        296     LOAD_NAME                       6: types
        298     LOAD_ATTR                       48: account
        318     LOAD_ATTR                       50: Password
        338     LOAD_CONST                      25: 'password'
        340     LOAD_NAME                       21: str
        342     BUILD_TUPLE                     4
        344     LOAD_CONST                      33: <CODE> compute_check
        346     MAKE_FUNCTION                   4
        348     STORE_NAME                      26: compute_check
        350     LOAD_CONST                      4: None
        352     NOP                             
        354     NOP                             
        356     NOP                             
        358     JUMP_FORWARD                    19 (to 398)
        366     POP_TOP                         
        368     RETURN_CONST                    4: None
        370     PUSH_EXC_INFO                   
        372     PUSH_NULL                       
        374     LOAD_CONST                      34: '__pyarmor_exit_16430__'
        376     NOP                             
        378     LOAD_CONST                      2: b'<COAddr>\x07\x00\x00\x1aX\x01\x00\x00\x00\x00\x00\x00\x00\x00\x00\x00\x00\x00\x00\x00'
        380     CALL                            1
        388     POP_TOP                         
        390     RERAISE                         0
        392     COPY                            3
        394     POP_EXCEPT                      
        396     RERAISE                         1
        398     PUSH_NULL                       
        400     LOAD_CONST                      34: '__pyarmor_exit_16430__'
        402     LOAD_CONST                      2: b'<COAddr>\x07\x00\x00\x1aX\x01\x00\x00\x00\x00\x00\x00\x00\x00\x00\x00\x00\x00\x00\x00'
        404     BUILD_TUPLE                     1
        406     CALL_FUNCTION_EX                0
        408     POP_TOP                         
        410     RETURN_VALUE                    
    [Exception Table]
        26 to 350 -> 370 [0] 
        370 to 392 -> 392 [1] lasti
