#decoded by lolz.live/mrpenny / t.me/zeus_jackpot
# ================================
# Примечания по Pyarmor:
# - Байт-код и объекты кода Pyarmor соответствуют стандартному Python, но присутствуют специальные вызовы функций среды выполнения (runtime) Pyarmor.
# - Вызовы строк — это не ошибки, а маркеры, которые обрабатываются Pyarmor во время выполнения.
#
# Руководство по декомпиляции (без среды выполнения):
# 1. Игнорируйте зашифрованные байты после `#`; используйте только строку до `#`.
# 2. Удалите "__pyarmor_enter_xxx__"(b"<COAddr>...") и "__pyarmor_leave_xxx__"(b"<COAddr>...") (пролог/эпилог).
# 3. "__pyarmor_assert_xxx__"(A) не является настоящим оператором assert.
#    - Если A — это имя или читаемая строка: замените на A.
#    - Если A — это (X, "Y"): замените на X.Y.
#    - Если A — это (X, "Y", Z): замените на X.Y = Z.
#    - В противном случае: выберите наиболее подходящую/логичную замену.
# 4. "__pyarmor_bcc_xxx__"(...) указывает на машинный (нативный) код; тело функции недоступно. Добавьте комментарий.
# ================================

[Code]
    File Name: <frozen multithon.tl.custom.adminlogevent>
    Object Name: <module>
    Qualified Name: <module>
    Arg Count: 0
    Pos Only Arg Count: 0
    KW Only Arg Count: 0
    Stack Size: 5
    Flags: 0x20000000 (CO_PYARMOR_OBFUSCATED)
    [Names]
        '__assert_armored__'
        'tl'
        'types'
        'utils'
        'get_input_peer'
        'AdminLogEvent'
    [Locals+Names]
    [Constants]
        '__pyarmor_assert_23841__'
        '__pyarmor_enter_23842__'
        b'<COAddr>\x07\x00\x00\x1a@\x00\x00\x00\x00\x00\x00\x00\x00\x00\x00\x00\x00\x00\x00\x00'
        3
        (
            'types'
        )
        (
            'get_input_peer'
        )
        [Code]
            File Name: <frozen multithon.tl.custom.adminlogevent>
            Object Name: AdminLogEvent
            Qualified Name: AdminLogEvent
            Arg Count: 0
            Pos Only Arg Count: 0
            KW Only Arg Count: 0
            Stack Size: 5
            Flags: 0x20000000 (CO_PYARMOR_OBFUSCATED)
            [Names]
                '__name__'
                '__module__'
                '__qualname__'
                '__doc__'
                '__assert_armored__'
                '__init__'
                'property'
                'id'
                'date'
                'user_id'
                'action'
                'old'
                'new'
                'changed_about'
                'changed_title'
                'changed_username'
                'changed_photo'
                'changed_sticker_set'
                'changed_message'
                'deleted_message'
                'changed_admin'
                'changed_restrictions'
                'changed_invites'
                'changed_location'
                'joined'
                'joined_invite'
                'left'
                'changed_hide_history'
                'changed_signatures'
                'changed_pin'
                'changed_default_banned_rights'
                'stopped_poll'
                'started_group_call'
                'discarded_group_call'
                'user_muted'
                'user_unmutted'
                'changed_call_settings'
                'changed_history_ttl'
                'deleted_exported_invite'
                'edited_exported_invite'
                'revoked_exported_invite'
                'joined_by_invite'
                'changed_user_volume'
                '__str__'
                'stringify'
            [Locals+Names]
            [Constants]
                'AdminLogEvent'
                '\n    Represents a more friendly interface for admin log events.\n\n    Members:\n        original (:tl:`ChannelAdminLogEvent`):\n            The original :tl:`ChannelAdminLogEvent`.\n\n        entities (`dict`):\n            A dictionary mapping user IDs to :tl:`User`.\n\n            When `old` and `new` are :tl:`ChannelParticipant`, you can\n            use this dictionary to map the ``user_id``, ``kicked_by``,\n            ``inviter_id`` and ``promoted_by`` IDs to their :tl:`User`.\n\n        user (:tl:`User`):\n            The user that caused this action (``entities[original.user_id]``).\n\n        input_user (:tl:`InputPeerUser`):\n            Input variant of `user`.\n    '
                '__pyarmor_assert_23844__'
                '__pyarmor_enter_23845__'
                b'<COAddr>\x07\x00\x00&h\x02\x00\x00\x00\x00\x00\x00\x00\x00\x00\x00\x00\x00\x00\x00'
                [Code]
                    File Name: <frozen multithon.tl.custom.adminlogevent>
                    Object Name: __init__
                    Qualified Name: AdminLogEvent.__init__
                    Arg Count: 3
                    Pos Only Arg Count: 0
                    KW Only Arg Count: 0
                    Stack Size: 5
                    Flags: 0x20000003 (CO_OPTIMIZED | CO_NEWLOCALS | CO_PYARMOR_OBFUSCATED)
                    [Names]
                        'original'
                        'entities'
                        'user_id'
                        'user'
                        'get_input_peer'
                        'input_user'
                    [Locals+Names]
                        'self'
                        'original'
                        'entities'
                        '__assert_armored__'
                    [Constants]
                        None
                        '__pyarmor_assert_23847__'
                        '__pyarmor_enter_23848__'
                        b'<COAddr>\x07\x00\x00\x1a\x8e\x00\x00\x00\x00\x00\x00\x00\x00\x00\x00\x00\x00\x00\x00\x00'
                        '__pyarmor_exit_23849__'
                    [Disassembly]
                        0       NOP                             
                        2       NOP                             
                        4       PUSH_NULL                       
                        6       LOAD_CONST                      2: '__pyarmor_enter_23848__'
                        8       LOAD_CONST                      3: b'<COAddr>\x07\x00\x00\x1a\x8e\x00\x00\x00\x00\x00\x00\x00\x00\x00\x00\x00\x00\x00\x00\x00'
                        10      BUILD_TUPLE                     1
                        12      CALL_FUNCTION_EX                0
                        14      POP_TOP                         
                        16      RESUME                          0
                        18      NOP                             
                        20      NOP                             
                        22      NOP                             
                        24      NOP                             
                        26      NOP                             
                        28      LOAD_FAST                       1: original
                        30      LOAD_FAST                       0: self
                        32      STORE_ATTR                      0: original
                        42      LOAD_FAST                       2: entities
                        44      LOAD_FAST                       0: self
                        46      STORE_ATTR                      1: entities
                        56      LOAD_FAST                       2: entities
                        58      LOAD_FAST                       1: original
                        60      LOAD_ATTR                       4: user_id
                        80      BINARY_SUBSCR                   
                        84      LOAD_FAST                       0: self
                        86      STORE_ATTR                      3: user
                        96      LOAD_GLOBAL                     9: NULL + get_input_peer
                        106     LOAD_FAST                       0: self
                        108     LOAD_ATTR                       6: user
                        128     CALL                            1
                        136     LOAD_FAST                       0: self
                        138     STORE_ATTR                      5: input_user
                        148     LOAD_CONST                      0: None
                        150     NOP                             
                        152     NOP                             
                        154     NOP                             
                        156     JUMP_FORWARD                    19 (to 196)
                        164     POP_TOP                         
                        166     RETURN_CONST                    0: None
                        168     PUSH_EXC_INFO                   
                        170     PUSH_NULL                       
                        172     LOAD_CONST                      4: '__pyarmor_exit_23849__'
                        174     NOP                             
                        176     LOAD_CONST                      3: b'<COAddr>\x07\x00\x00\x1a\x8e\x00\x00\x00\x00\x00\x00\x00\x00\x00\x00\x00\x00\x00\x00\x00'
                        178     CALL                            1
                        186     POP_TOP                         
                        188     RERAISE                         0
                        190     COPY                            3
                        192     POP_EXCEPT                      
                        194     RERAISE                         1
                        196     PUSH_NULL                       
                        198     LOAD_CONST                      4: '__pyarmor_exit_23849__'
                        200     LOAD_CONST                      3: b'<COAddr>\x07\x00\x00\x1a\x8e\x00\x00\x00\x00\x00\x00\x00\x00\x00\x00\x00\x00\x00\x00\x00'
                        202     BUILD_TUPLE                     1
                        204     CALL_FUNCTION_EX                0
                        206     POP_TOP                         
                        208     RETURN_VALUE                    
                    [Exception Table]
                        28 to 148 -> 168 [0] 
                        168 to 190 -> 190 [1] lasti
                [Code]
                    File Name: <frozen multithon.tl.custom.adminlogevent>
                    Object Name: id
                    Qualified Name: AdminLogEvent.id
                    Arg Count: 1
                    Pos Only Arg Count: 0
                    KW Only Arg Count: 0
                    Stack Size: 5
                    Flags: 0x20000003 (CO_OPTIMIZED | CO_NEWLOCALS | CO_PYARMOR_OBFUSCATED)
                    [Names]
                        'original'
                        'id'
                    [Locals+Names]
                        'self'
                        '__assert_armored__'
                    [Constants]
                        '\n        The ID of this event.\n        '
                        '__pyarmor_assert_23850__'
                        '__pyarmor_enter_23851__'
                        b'<COAddr>\x05\x00\x00\x1a@\x00\x00\x00\x00\x00\x00\x00\x00\x00\x00\x00\x00\x00\x00\x00'
                        '__pyarmor_exit_23852__'
                    [Disassembly]
                        0       NOP                             
                        2       NOP                             
                        4       PUSH_NULL                       
                        6       LOAD_CONST                      2: '__pyarmor_enter_23851__'
                        8       LOAD_CONST                      3: b'<COAddr>\x05\x00\x00\x1a@\x00\x00\x00\x00\x00\x00\x00\x00\x00\x00\x00\x00\x00\x00\x00'
                        10      BUILD_TUPLE                     1
                        12      CALL_FUNCTION_EX                0
                        14      POP_TOP                         
                        16      RESUME                          0
                        18      NOP                             
                        20      NOP                             
                        22      NOP                             
                        24      NOP                             
                        26      NOP                             
                        28      LOAD_FAST                       0: self
                        30      LOAD_ATTR                       0: original
                        50      LOAD_ATTR                       2: id
                        70      NOP                             
                        72      NOP                             
                        74      NOP                             
                        76      JUMP_FORWARD                    20 (to 118)
                        78      CALL                            1
                        86      POP_TOP                         
                        88      RETURN_VALUE                    
                        90      PUSH_EXC_INFO                   
                        92      PUSH_NULL                       
                        94      LOAD_CONST                      4: '__pyarmor_exit_23852__'
                        96      NOP                             
                        98      LOAD_CONST                      3: b'<COAddr>\x05\x00\x00\x1a@\x00\x00\x00\x00\x00\x00\x00\x00\x00\x00\x00\x00\x00\x00\x00'
                        100     CALL                            1
                        108     POP_TOP                         
                        110     RERAISE                         0
                        112     COPY                            3
                        114     POP_EXCEPT                      
                        116     RERAISE                         1
                        118     PUSH_NULL                       
                        120     LOAD_CONST                      4: '__pyarmor_exit_23852__'
                        122     LOAD_CONST                      3: b'<COAddr>\x05\x00\x00\x1a@\x00\x00\x00\x00\x00\x00\x00\x00\x00\x00\x00\x00\x00\x00\x00'
                        124     BUILD_TUPLE                     1
                        126     CALL_FUNCTION_EX                0
                        128     POP_TOP                         
                        130     RETURN_VALUE                    
                    [Exception Table]
                        28 to 70 -> 90 [0] 
                        90 to 112 -> 112 [1] lasti
                [Code]
                    File Name: <frozen multithon.tl.custom.adminlogevent>
                    Object Name: date
                    Qualified Name: AdminLogEvent.date
                    Arg Count: 1
                    Pos Only Arg Count: 0
                    KW Only Arg Count: 0
                    Stack Size: 5
                    Flags: 0x20000003 (CO_OPTIMIZED | CO_NEWLOCALS | CO_PYARMOR_OBFUSCATED)
                    [Names]
                        'original'
                        'date'
                    [Locals+Names]
                        'self'
                        '__assert_armored__'
                    [Constants]
                        '\n        The date when this event occurred.\n        '
                        '__pyarmor_assert_23853__'
                        '__pyarmor_enter_23854__'
                        b'<COAddr>\x07\x00\x00\x1a@\x00\x00\x00\x00\x00\x00\x00\x00\x00\x00\x00\x00\x00\x00\x00'
                        '__pyarmor_exit_23855__'
                    [Disassembly]
                        0       NOP                             
                        2       NOP                             
                        4       PUSH_NULL                       
                        6       LOAD_CONST                      2: '__pyarmor_enter_23854__'
                        8       LOAD_CONST                      3: b'<COAddr>\x07\x00\x00\x1a@\x00\x00\x00\x00\x00\x00\x00\x00\x00\x00\x00\x00\x00\x00\x00'
                        10      BUILD_TUPLE                     1
                        12      CALL_FUNCTION_EX                0
                        14      POP_TOP                         
                        16      RESUME                          0
                        18      NOP                             
                        20      NOP                             
                        22      NOP                             
                        24      NOP                             
                        26      NOP                             
                        28      LOAD_FAST                       0: self
                        30      LOAD_ATTR                       0: original
                        50      LOAD_ATTR                       2: date
                        70      NOP                             
                        72      NOP                             
                        74      NOP                             
                        76      JUMP_FORWARD                    20 (to 118)
                        78      CALL                            1
                        86      POP_TOP                         
                        88      RETURN_VALUE                    
                        90      PUSH_EXC_INFO                   
                        92      PUSH_NULL                       
                        94      LOAD_CONST                      4: '__pyarmor_exit_23855__'
                        96      NOP                             
                        98      LOAD_CONST                      3: b'<COAddr>\x07\x00\x00\x1a@\x00\x00\x00\x00\x00\x00\x00\x00\x00\x00\x00\x00\x00\x00\x00'
                        100     CALL                            1
                        108     POP_TOP                         
                        110     RERAISE                         0
                        112     COPY                            3
                        114     POP_EXCEPT                      
                        116     RERAISE                         1
                        118     PUSH_NULL                       
                        120     LOAD_CONST                      4: '__pyarmor_exit_23855__'
                        122     LOAD_CONST                      3: b'<COAddr>\x07\x00\x00\x1a@\x00\x00\x00\x00\x00\x00\x00\x00\x00\x00\x00\x00\x00\x00\x00'
                        124     BUILD_TUPLE                     1
                        126     CALL_FUNCTION_EX                0
                        128     POP_TOP                         
                        130     RETURN_VALUE                    
                    [Exception Table]
                        28 to 70 -> 90 [0] 
                        90 to 112 -> 112 [1] lasti
                [Code]
                    File Name: <frozen multithon.tl.custom.adminlogevent>
                    Object Name: user_id
                    Qualified Name: AdminLogEvent.user_id
                    Arg Count: 1
                    Pos Only Arg Count: 0
                    KW Only Arg Count: 0
                    Stack Size: 5
                    Flags: 0x20000003 (CO_OPTIMIZED | CO_NEWLOCALS | CO_PYARMOR_OBFUSCATED)
                    [Names]
                        'original'
                        'user_id'
                    [Locals+Names]
                        'self'
                        '__assert_armored__'
                    [Constants]
                        '\n        The ID of the user that triggered this event.\n        '
                        '__pyarmor_assert_23856__'
                        '__pyarmor_enter_23857__'
                        b'<COAddr>\x07\x00\x00\x1a@\x00\x00\x00\x00\x00\x00\x00\x00\x00\x00\x00\x00\x00\x00\x00'
                        '__pyarmor_exit_23858__'
                    [Disassembly]
                        0       NOP                             
                        2       NOP                             
                        4       PUSH_NULL                       
                        6       LOAD_CONST                      2: '__pyarmor_enter_23857__'
                        8       LOAD_CONST                      3: b'<COAddr>\x07\x00\x00\x1a@\x00\x00\x00\x00\x00\x00\x00\x00\x00\x00\x00\x00\x00\x00\x00'
                        10      BUILD_TUPLE                     1
                        12      CALL_FUNCTION_EX                0
                        14      POP_TOP                         
                        16      RESUME                          0
                        18      NOP                             
                        20      NOP                             
                        22      NOP                             
                        24      NOP                             
                        26      NOP                             
                        28      LOAD_FAST                       0: self
                        30      LOAD_ATTR                       0: original
                        50      LOAD_ATTR                       2: user_id
                        70      NOP                             
                        72      NOP                             
                        74      NOP                             
                        76      JUMP_FORWARD                    20 (to 118)
                        78      CALL                            1
                        86      POP_TOP                         
                        88      RETURN_VALUE                    
                        90      PUSH_EXC_INFO                   
                        92      PUSH_NULL                       
                        94      LOAD_CONST                      4: '__pyarmor_exit_23858__'
                        96      NOP                             
                        98      LOAD_CONST                      3: b'<COAddr>\x07\x00\x00\x1a@\x00\x00\x00\x00\x00\x00\x00\x00\x00\x00\x00\x00\x00\x00\x00'
                        100     CALL                            1
                        108     POP_TOP                         
                        110     RERAISE                         0
                        112     COPY                            3
                        114     POP_EXCEPT                      
                        116     RERAISE                         1
                        118     PUSH_NULL                       
                        120     LOAD_CONST                      4: '__pyarmor_exit_23858__'
                        122     LOAD_CONST                      3: b'<COAddr>\x07\x00\x00\x1a@\x00\x00\x00\x00\x00\x00\x00\x00\x00\x00\x00\x00\x00\x00\x00'
                        124     BUILD_TUPLE                     1
                        126     CALL_FUNCTION_EX                0
                        128     POP_TOP                         
                        130     RETURN_VALUE                    
                    [Exception Table]
                        28 to 70 -> 90 [0] 
                        90 to 112 -> 112 [1] lasti
                [Code]
                    File Name: <frozen multithon.tl.custom.adminlogevent>
                    Object Name: action
                    Qualified Name: AdminLogEvent.action
                    Arg Count: 1
                    Pos Only Arg Count: 0
                    KW Only Arg Count: 0
                    Stack Size: 5
                    Flags: 0x20000003 (CO_OPTIMIZED | CO_NEWLOCALS | CO_PYARMOR_OBFUSCATED)
                    [Names]
                        'original'
                        'action'
                    [Locals+Names]
                        'self'
                        '__assert_armored__'
                    [Constants]
                        '\n        The original :tl:`ChannelAdminLogEventAction`.\n        '
                        '__pyarmor_assert_23859__'
                        '__pyarmor_enter_23860__'
                        b'<COAddr>\x05\x00\x00\x1a@\x00\x00\x00\x00\x00\x00\x00\x00\x00\x00\x00\x00\x00\x00\x00'
                        '__pyarmor_exit_23861__'
                    [Disassembly]
                        0       NOP                             
                        2       NOP                             
                        4       PUSH_NULL                       
                        6       LOAD_CONST                      2: '__pyarmor_enter_23860__'
                        8       LOAD_CONST                      3: b'<COAddr>\x05\x00\x00\x1a@\x00\x00\x00\x00\x00\x00\x00\x00\x00\x00\x00\x00\x00\x00\x00'
                        10      BUILD_TUPLE                     1
                        12      CALL_FUNCTION_EX                0
                        14      POP_TOP                         
                        16      RESUME                          0
                        18      NOP                             
                        20      NOP                             
                        22      NOP                             
                        24      NOP                             
                        26      NOP                             
                        28      LOAD_FAST                       0: self
                        30      LOAD_ATTR                       0: original
                        50      LOAD_ATTR                       2: action
                        70      NOP                             
                        72      NOP                             
                        74      NOP                             
                        76      JUMP_FORWARD                    20 (to 118)
                        78      CALL                            1
                        86      POP_TOP                         
                        88      RETURN_VALUE                    
                        90      PUSH_EXC_INFO                   
                        92      PUSH_NULL                       
                        94      LOAD_CONST                      4: '__pyarmor_exit_23861__'
                        96      NOP                             
                        98      LOAD_CONST                      3: b'<COAddr>\x05\x00\x00\x1a@\x00\x00\x00\x00\x00\x00\x00\x00\x00\x00\x00\x00\x00\x00\x00'
                        100     CALL                            1
                        108     POP_TOP                         
                        110     RERAISE                         0
                        112     COPY                            3
                        114     POP_EXCEPT                      
                        116     RERAISE                         1
                        118     PUSH_NULL                       
                        120     LOAD_CONST                      4: '__pyarmor_exit_23861__'
                        122     LOAD_CONST                      3: b'<COAddr>\x05\x00\x00\x1a@\x00\x00\x00\x00\x00\x00\x00\x00\x00\x00\x00\x00\x00\x00\x00'
                        124     BUILD_TUPLE                     1
                        126     CALL_FUNCTION_EX                0
                        128     POP_TOP                         
                        130     RETURN_VALUE                    
                    [Exception Table]
                        28 to 70 -> 90 [0] 
                        90 to 112 -> 112 [1] lasti
                [Code]
                    File Name: <frozen multithon.tl.custom.adminlogevent>
                    Object Name: old
                    Qualified Name: AdminLogEvent.old
                    Arg Count: 1
                    Pos Only Arg Count: 0
                    KW Only Arg Count: 0
                    Stack Size: 8
                    Flags: 0x20000003 (CO_OPTIMIZED | CO_NEWLOCALS | CO_PYARMOR_OBFUSCATED)
                    [Names]
                        'original'
                        'action'
                        'isinstance'
                        'types'
                        'ChannelAdminLogEventActionChangeAbout'
                        'ChannelAdminLogEventActionChangeTitle'
                        'ChannelAdminLogEventActionChangeUsername'
                        'ChannelAdminLogEventActionChangeLocation'
                        'ChannelAdminLogEventActionChangeHistoryTTL'
                        'prev_value'
                        'ChannelAdminLogEventActionChangePhoto'
                        'prev_photo'
                        'ChannelAdminLogEventActionChangeStickerSet'
                        'prev_stickerset'
                        'ChannelAdminLogEventActionEditMessage'
                        'prev_message'
                        'ChannelAdminLogEventActionParticipantToggleAdmin'
                        'ChannelAdminLogEventActionParticipantToggleBan'
                        'prev_participant'
                        'ChannelAdminLogEventActionToggleInvites'
                        'ChannelAdminLogEventActionTogglePreHistoryHidden'
                        'ChannelAdminLogEventActionToggleSignatures'
                        'new_value'
                        'ChannelAdminLogEventActionDeleteMessage'
                        'message'
                        'ChannelAdminLogEventActionDefaultBannedRights'
                        'prev_banned_rights'
                        'ChannelAdminLogEventActionDiscardGroupCall'
                        'call'
                        'ChannelAdminLogEventActionExportedInviteDelete'
                        'ChannelAdminLogEventActionExportedInviteRevoke'
                        'ChannelAdminLogEventActionParticipantJoinByInvite'
                        'invite'
                        'ChannelAdminLogEventActionExportedInviteEdit'
                        'prev_invite'
                    [Locals+Names]
                        'self'
                        '__assert_armored__'
                        '_var_var_0'
                    [Constants]
                        '\n        The old value from the event.\n        '
                        '__pyarmor_assert_23862__'
                        '__pyarmor_enter_23863__'
                        b'<COAddr>\x07\x00\x00\x1af\x05\x00\x00\x00\x00\x00\x00\x00\x00\x00\x00\x00\x00\x00\x00'
                        '__pyarmor_exit_23864__'
                        None
                    [Disassembly]
                        0       NOP                             
                        2       NOP                             
                        4       PUSH_NULL                       
                        6       LOAD_CONST                      2: '__pyarmor_enter_23863__'
                        8       LOAD_CONST                      3: b'<COAddr>\x07\x00\x00\x1af\x05\x00\x00\x00\x00\x00\x00\x00\x00\x00\x00\x00\x00\x00\x00'
                        10      BUILD_TUPLE                     1
                        12      CALL_FUNCTION_EX                0
                        14      POP_TOP                         
                        16      RESUME                          0
                        18      NOP                             
                        20      NOP                             
                        22      NOP                             
                        24      NOP                             
                        26      NOP                             
                        28      LOAD_FAST                       0: self
                        30      LOAD_ATTR                       0: original
                        50      LOAD_ATTR                       2: action
                        70      STORE_FAST                      2: _var_var_0
                        72      LOAD_GLOBAL                     5: NULL + isinstance
                        82      LOAD_FAST                       2: _var_var_0
                        84      LOAD_GLOBAL                     6: types
                        94      LOAD_ATTR                       8: ChannelAdminLogEventActionChangeAbout
                        114     LOAD_GLOBAL                     6: types
                        124     LOAD_ATTR                       10: ChannelAdminLogEventActionChangeTitle
                        144     LOAD_GLOBAL                     6: types
                        154     LOAD_ATTR                       12: ChannelAdminLogEventActionChangeUsername
                        174     LOAD_GLOBAL                     6: types
                        184     LOAD_ATTR                       14: ChannelAdminLogEventActionChangeLocation
                        204     LOAD_GLOBAL                     6: types
                        214     LOAD_ATTR                       16: ChannelAdminLogEventActionChangeHistoryTTL
                        234     BUILD_TUPLE                     5
                        236     CALL                            2
                        244     POP_JUMP_IF_FALSE               21 (to 288)
                        246     LOAD_FAST                       2: _var_var_0
                        248     LOAD_ATTR                       18: prev_value
                        268     NOP                             
                        270     NOP                             
                        272     JUMP_FORWARD                    580 (to 1436)
                        276     CALL                            1
                        284     POP_TOP                         
                        286     RETURN_VALUE                    
                        288     LOAD_GLOBAL                     5: NULL + isinstance
                        298     LOAD_FAST                       2: _var_var_0
                        300     LOAD_GLOBAL                     6: types
                        310     LOAD_ATTR                       20: ChannelAdminLogEventActionChangePhoto
                        330     CALL                            2
                        338     POP_JUMP_IF_FALSE               21 (to 382)
                        340     LOAD_FAST                       2: _var_var_0
                        342     LOAD_ATTR                       22: prev_photo
                        362     NOP                             
                        364     NOP                             
                        366     JUMP_FORWARD                    533 (to 1436)
                        370     CALL                            1
                        378     POP_TOP                         
                        380     RETURN_VALUE                    
                        382     LOAD_GLOBAL                     5: NULL + isinstance
                        392     LOAD_FAST                       2: _var_var_0
                        394     LOAD_GLOBAL                     6: types
                        404     LOAD_ATTR                       24: ChannelAdminLogEventActionChangeStickerSet
                        424     CALL                            2
                        432     POP_JUMP_IF_FALSE               21 (to 476)
                        434     LOAD_FAST                       2: _var_var_0
                        436     LOAD_ATTR                       26: prev_stickerset
                        456     NOP                             
                        458     NOP                             
                        460     JUMP_FORWARD                    486 (to 1436)
                        464     CALL                            1
                        472     POP_TOP                         
                        474     RETURN_VALUE                    
                        476     LOAD_GLOBAL                     5: NULL + isinstance
                        486     LOAD_FAST                       2: _var_var_0
                        488     LOAD_GLOBAL                     6: types
                        498     LOAD_ATTR                       28: ChannelAdminLogEventActionEditMessage
                        518     CALL                            2
                        526     POP_JUMP_IF_FALSE               21 (to 570)
                        528     LOAD_FAST                       2: _var_var_0
                        530     LOAD_ATTR                       30: prev_message
                        550     NOP                             
                        552     NOP                             
                        554     JUMP_FORWARD                    439 (to 1436)
                        558     CALL                            1
                        566     POP_TOP                         
                        568     RETURN_VALUE                    
                        570     LOAD_GLOBAL                     5: NULL + isinstance
                        580     LOAD_FAST                       2: _var_var_0
                        582     LOAD_GLOBAL                     6: types
                        592     LOAD_ATTR                       32: ChannelAdminLogEventActionParticipantToggleAdmin
                        612     LOAD_GLOBAL                     6: types
                        622     LOAD_ATTR                       34: ChannelAdminLogEventActionParticipantToggleBan
                        642     BUILD_TUPLE                     2
                        644     CALL                            2
                        652     POP_JUMP_IF_FALSE               21 (to 696)
                        654     LOAD_FAST                       2: _var_var_0
                        656     LOAD_ATTR                       36: prev_participant
                        676     NOP                             
                        678     NOP                             
                        680     JUMP_FORWARD                    376 (to 1436)
                        684     CALL                            1
                        692     POP_TOP                         
                        694     RETURN_VALUE                    
                        696     LOAD_GLOBAL                     5: NULL + isinstance
                        706     LOAD_FAST                       2: _var_var_0
                        708     LOAD_GLOBAL                     6: types
                        718     LOAD_ATTR                       38: ChannelAdminLogEventActionToggleInvites
                        738     LOAD_GLOBAL                     6: types
                        748     LOAD_ATTR                       40: ChannelAdminLogEventActionTogglePreHistoryHidden
                        768     LOAD_GLOBAL                     6: types
                        778     LOAD_ATTR                       42: ChannelAdminLogEventActionToggleSignatures
                        798     BUILD_TUPLE                     3
                        800     CALL                            2
                        808     POP_JUMP_IF_FALSE               22 (to 854)
                        810     LOAD_FAST                       2: _var_var_0
                        812     LOAD_ATTR                       44: new_value
                        832     UNARY_NOT                       
                        834     NOP                             
                        836     NOP                             
                        838     JUMP_FORWARD                    297 (to 1436)
                        842     CALL                            1
                        850     POP_TOP                         
                        852     RETURN_VALUE                    
                        854     LOAD_GLOBAL                     5: NULL + isinstance
                        864     LOAD_FAST                       2: _var_var_0
                        866     LOAD_GLOBAL                     6: types
                        876     LOAD_ATTR                       46: ChannelAdminLogEventActionDeleteMessage
                        896     CALL                            2
                        904     POP_JUMP_IF_FALSE               21 (to 948)
                        906     LOAD_FAST                       2: _var_var_0
                        908     LOAD_ATTR                       48: message
                        928     NOP                             
                        930     NOP                             
                        932     NOP                             
                        934     JUMP_FORWARD                    250 (to 1436)
                        936     CALL                            1
                        944     POP_TOP                         
                        946     RETURN_VALUE                    
                        948     LOAD_GLOBAL                     5: NULL + isinstance
                        958     LOAD_FAST                       2: _var_var_0
                        960     LOAD_GLOBAL                     6: types
                        970     LOAD_ATTR                       50: ChannelAdminLogEventActionDefaultBannedRights
                        990     CALL                            2
                        998     POP_JUMP_IF_FALSE               21 (to 1042)
                        1000    LOAD_FAST                       2: _var_var_0
                        1002    LOAD_ATTR                       52: prev_banned_rights
                        1022    NOP                             
                        1024    NOP                             
                        1026    NOP                             
                        1028    JUMP_FORWARD                    203 (to 1436)
                        1030    CALL                            1
                        1038    POP_TOP                         
                        1040    RETURN_VALUE                    
                        1042    LOAD_GLOBAL                     5: NULL + isinstance
                        1052    LOAD_FAST                       2: _var_var_0
                        1054    LOAD_GLOBAL                     6: types
                        1064    LOAD_ATTR                       54: ChannelAdminLogEventActionDiscardGroupCall
                        1084    CALL                            2
                        1092    POP_JUMP_IF_FALSE               21 (to 1136)
                        1094    LOAD_FAST                       2: _var_var_0
                        1096    LOAD_ATTR                       56: call
                        1116    NOP                             
                        1118    NOP                             
                        1120    NOP                             
                        1122    JUMP_FORWARD                    156 (to 1436)
                        1124    CALL                            1
                        1132    POP_TOP                         
                        1134    RETURN_VALUE                    
                        1136    LOAD_GLOBAL                     5: NULL + isinstance
                        1146    LOAD_FAST                       2: _var_var_0
                        1148    LOAD_GLOBAL                     6: types
                        1158    LOAD_ATTR                       58: ChannelAdminLogEventActionExportedInviteDelete
                        1178    LOAD_GLOBAL                     6: types
                        1188    LOAD_ATTR                       60: ChannelAdminLogEventActionExportedInviteRevoke
                        1208    LOAD_GLOBAL                     6: types
                        1218    LOAD_ATTR                       62: ChannelAdminLogEventActionParticipantJoinByInvite
                        1238    BUILD_TUPLE                     3
                        1240    CALL                            2
                        1248    POP_JUMP_IF_FALSE               21 (to 1292)
                        1250    LOAD_FAST                       2: _var_var_0
                        1252    LOAD_ATTR                       64: invite
                        1272    NOP                             
                        1274    NOP                             
                        1276    NOP                             
                        1278    JUMP_FORWARD                    78 (to 1436)
                        1280    CALL                            1
                        1288    POP_TOP                         
                        1290    RETURN_VALUE                    
                        1292    LOAD_GLOBAL                     5: NULL + isinstance
                        1302    LOAD_FAST                       2: _var_var_0
                        1304    LOAD_GLOBAL                     6: types
                        1314    LOAD_ATTR                       66: ChannelAdminLogEventActionExportedInviteEdit
                        1334    CALL                            2
                        1342    POP_JUMP_IF_FALSE               21 (to 1386)
                        1344    LOAD_FAST                       2: _var_var_0
                        1346    LOAD_ATTR                       68: prev_invite
                        1366    NOP                             
                        1368    NOP                             
                        1370    NOP                             
                        1372    JUMP_FORWARD                    31 (to 1436)
                        1374    CALL                            1
                        1382    POP_TOP                         
                        1384    RETURN_VALUE                    
                        1386    NOP                             
                        1388    LOAD_CONST                      5: None
                        1390    NOP                             
                        1392    NOP                             
                        1394    NOP                             
                        1396    JUMP_FORWARD                    19 (to 1436)
                        1404    POP_TOP                         
                        1406    RETURN_CONST                    5: None
                        1408    PUSH_EXC_INFO                   
                        1410    PUSH_NULL                       
                        1412    LOAD_CONST                      4: '__pyarmor_exit_23864__'
                        1414    NOP                             
                        1416    LOAD_CONST                      3: b'<COAddr>\x07\x00\x00\x1af\x05\x00\x00\x00\x00\x00\x00\x00\x00\x00\x00\x00\x00\x00\x00'
                        1418    CALL                            1
                        1426    POP_TOP                         
                        1428    RERAISE                         0
                        1430    COPY                            3
                        1432    POP_EXCEPT                      
                        1434    RERAISE                         1
                        1436    PUSH_NULL                       
                        1438    LOAD_CONST                      4: '__pyarmor_exit_23864__'
                        1440    LOAD_CONST                      3: b'<COAddr>\x07\x00\x00\x1af\x05\x00\x00\x00\x00\x00\x00\x00\x00\x00\x00\x00\x00\x00\x00'
                        1442    BUILD_TUPLE                     1
                        1444    CALL_FUNCTION_EX                0
                        1446    POP_TOP                         
                        1448    RETURN_VALUE                    
                    [Exception Table]
                        28 to 268 -> 1408 [0] 
                        288 to 362 -> 1408 [0] 
                        382 to 456 -> 1408 [0] 
                        476 to 550 -> 1408 [0] 
                        570 to 676 -> 1408 [0] 
                        696 to 834 -> 1408 [0] 
                        854 to 928 -> 1408 [0] 
                        948 to 1022 -> 1408 [0] 
                        1042 to 1116 -> 1408 [0] 
                        1136 to 1272 -> 1408 [0] 
                        1292 to 1366 -> 1408 [0] 
                        1408 to 1430 -> 1430 [1] lasti
                [Code]
                    File Name: <frozen multithon.tl.custom.adminlogevent>
                    Object Name: new
                    Qualified Name: AdminLogEvent.new
                    Arg Count: 1
                    Pos Only Arg Count: 0
                    KW Only Arg Count: 0
                    Stack Size: 11
                    Flags: 0x20000003 (CO_OPTIMIZED | CO_NEWLOCALS | CO_PYARMOR_OBFUSCATED)
                    [Names]
                        'original'
                        'action'
                        'isinstance'
                        'types'
                        'ChannelAdminLogEventActionChangeAbout'
                        'ChannelAdminLogEventActionChangeTitle'
                        'ChannelAdminLogEventActionChangeUsername'
                        'ChannelAdminLogEventActionToggleInvites'
                        'ChannelAdminLogEventActionTogglePreHistoryHidden'
                        'ChannelAdminLogEventActionToggleSignatures'
                        'ChannelAdminLogEventActionChangeLocation'
                        'ChannelAdminLogEventActionChangeHistoryTTL'
                        'new_value'
                        'ChannelAdminLogEventActionChangePhoto'
                        'new_photo'
                        'ChannelAdminLogEventActionChangeStickerSet'
                        'new_stickerset'
                        'ChannelAdminLogEventActionEditMessage'
                        'new_message'
                        'ChannelAdminLogEventActionParticipantToggleAdmin'
                        'ChannelAdminLogEventActionParticipantToggleBan'
                        'new_participant'
                        'ChannelAdminLogEventActionParticipantInvite'
                        'ChannelAdminLogEventActionParticipantVolume'
                        'participant'
                        'ChannelAdminLogEventActionDefaultBannedRights'
                        'new_banned_rights'
                        'ChannelAdminLogEventActionStopPoll'
                        'message'
                        'ChannelAdminLogEventActionStartGroupCall'
                        'call'
                        'ChannelAdminLogEventActionParticipantMute'
                        'ChannelAdminLogEventActionParticipantUnmute'
                        'ChannelAdminLogEventActionToggleGroupCallSetting'
                        'join_muted'
                        'ChannelAdminLogEventActionExportedInviteEdit'
                        'new_invite'
                    [Locals+Names]
                        'self'
                        '__assert_armored__'
                        '_var_var_0'
                    [Constants]
                        '\n        The new value present in the event.\n        '
                        '__pyarmor_assert_23865__'
                        '__pyarmor_enter_23866__'
                        b'<COAddr>\x07\x00\x00\x1a\xe0\x05\x00\x00\x00\x00\x00\x00\x00\x00\x00\x00\x00\x00\x00\x00'
                        '__pyarmor_exit_23867__'
                        None
                    [Disassembly]
                        0       NOP                             
                        2       NOP                             
                        4       PUSH_NULL                       
                        6       LOAD_CONST                      2: '__pyarmor_enter_23866__'
                        8       LOAD_CONST                      3: b'<COAddr>\x07\x00\x00\x1a\xe0\x05\x00\x00\x00\x00\x00\x00\x00\x00\x00\x00\x00\x00\x00\x00'
                        10      BUILD_TUPLE                     1
                        12      CALL_FUNCTION_EX                0
                        14      POP_TOP                         
                        16      RESUME                          0
                        18      NOP                             
                        20      NOP                             
                        22      NOP                             
                        24      NOP                             
                        26      NOP                             
                        28      LOAD_FAST                       0: self
                        30      LOAD_ATTR                       0: original
                        50      LOAD_ATTR                       2: action
                        70      STORE_FAST                      2: _var_var_0
                        72      LOAD_GLOBAL                     5: NULL + isinstance
                        82      LOAD_FAST                       2: _var_var_0
                        84      LOAD_GLOBAL                     6: types
                        94      LOAD_ATTR                       8: ChannelAdminLogEventActionChangeAbout
                        114     LOAD_GLOBAL                     6: types
                        124     LOAD_ATTR                       10: ChannelAdminLogEventActionChangeTitle
                        144     LOAD_GLOBAL                     6: types
                        154     LOAD_ATTR                       12: ChannelAdminLogEventActionChangeUsername
                        174     LOAD_GLOBAL                     6: types
                        184     LOAD_ATTR                       14: ChannelAdminLogEventActionToggleInvites
                        204     LOAD_GLOBAL                     6: types
                        214     LOAD_ATTR                       16: ChannelAdminLogEventActionTogglePreHistoryHidden
                        234     LOAD_GLOBAL                     6: types
                        244     LOAD_ATTR                       18: ChannelAdminLogEventActionToggleSignatures
                        264     LOAD_GLOBAL                     6: types
                        274     LOAD_ATTR                       20: ChannelAdminLogEventActionChangeLocation
                        294     LOAD_GLOBAL                     6: types
                        304     LOAD_ATTR                       22: ChannelAdminLogEventActionChangeHistoryTTL
                        324     BUILD_TUPLE                     8
                        326     CALL                            2
                        334     POP_JUMP_IF_FALSE               21 (to 378)
                        336     LOAD_FAST                       2: _var_var_0
                        338     LOAD_ATTR                       24: new_value
                        358     NOP                             
                        360     NOP                             
                        362     JUMP_FORWARD                    596 (to 1558)
                        366     CALL                            1
                        374     POP_TOP                         
                        376     RETURN_VALUE                    
                        378     LOAD_GLOBAL                     5: NULL + isinstance
                        388     LOAD_FAST                       2: _var_var_0
                        390     LOAD_GLOBAL                     6: types
                        400     LOAD_ATTR                       26: ChannelAdminLogEventActionChangePhoto
                        420     CALL                            2
                        428     POP_JUMP_IF_FALSE               21 (to 472)
                        430     LOAD_FAST                       2: _var_var_0
                        432     LOAD_ATTR                       28: new_photo
                        452     NOP                             
                        454     NOP                             
                        456     JUMP_FORWARD                    549 (to 1558)
                        460     CALL                            1
                        468     POP_TOP                         
                        470     RETURN_VALUE                    
                        472     LOAD_GLOBAL                     5: NULL + isinstance
                        482     LOAD_FAST                       2: _var_var_0
                        484     LOAD_GLOBAL                     6: types
                        494     LOAD_ATTR                       30: ChannelAdminLogEventActionChangeStickerSet
                        514     CALL                            2
                        522     POP_JUMP_IF_FALSE               21 (to 566)
                        524     LOAD_FAST                       2: _var_var_0
                        526     LOAD_ATTR                       32: new_stickerset
                        546     NOP                             
                        548     NOP                             
                        550     JUMP_FORWARD                    502 (to 1558)
                        554     CALL                            1
                        562     POP_TOP                         
                        564     RETURN_VALUE                    
                        566     LOAD_GLOBAL                     5: NULL + isinstance
                        576     LOAD_FAST                       2: _var_var_0
                        578     LOAD_GLOBAL                     6: types
                        588     LOAD_ATTR                       34: ChannelAdminLogEventActionEditMessage
                        608     CALL                            2
                        616     POP_JUMP_IF_FALSE               21 (to 660)
                        618     LOAD_FAST                       2: _var_var_0
                        620     LOAD_ATTR                       36: new_message
                        640     NOP                             
                        642     NOP                             
                        644     JUMP_FORWARD                    455 (to 1558)
                        648     CALL                            1
                        656     POP_TOP                         
                        658     RETURN_VALUE                    
                        660     LOAD_GLOBAL                     5: NULL + isinstance
                        670     LOAD_FAST                       2: _var_var_0
                        672     LOAD_GLOBAL                     6: types
                        682     LOAD_ATTR                       38: ChannelAdminLogEventActionParticipantToggleAdmin
                        702     LOAD_GLOBAL                     6: types
                        712     LOAD_ATTR                       40: ChannelAdminLogEventActionParticipantToggleBan
                        732     BUILD_TUPLE                     2
                        734     CALL                            2
                        742     POP_JUMP_IF_FALSE               21 (to 786)
                        744     LOAD_FAST                       2: _var_var_0
                        746     LOAD_ATTR                       42: new_participant
                        766     NOP                             
                        768     NOP                             
                        770     JUMP_FORWARD                    392 (to 1558)
                        774     CALL                            1
                        782     POP_TOP                         
                        784     RETURN_VALUE                    
                        786     LOAD_GLOBAL                     5: NULL + isinstance
                        796     LOAD_FAST                       2: _var_var_0
                        798     LOAD_GLOBAL                     6: types
                        808     LOAD_ATTR                       44: ChannelAdminLogEventActionParticipantInvite
                        828     LOAD_GLOBAL                     6: types
                        838     LOAD_ATTR                       46: ChannelAdminLogEventActionParticipantVolume
                        858     BUILD_TUPLE                     2
                        860     CALL                            2
                        868     POP_JUMP_IF_FALSE               21 (to 912)
                        870     LOAD_FAST                       2: _var_var_0
                        872     LOAD_ATTR                       48: participant
                        892     NOP                             
                        894     NOP                             
                        896     JUMP_FORWARD                    329 (to 1558)
                        900     CALL                            1
                        908     POP_TOP                         
                        910     RETURN_VALUE                    
                        912     LOAD_GLOBAL                     5: NULL + isinstance
                        922     LOAD_FAST                       2: _var_var_0
                        924     LOAD_GLOBAL                     6: types
                        934     LOAD_ATTR                       50: ChannelAdminLogEventActionDefaultBannedRights
                        954     CALL                            2
                        962     POP_JUMP_IF_FALSE               21 (to 1006)
                        964     LOAD_FAST                       2: _var_var_0
                        966     LOAD_ATTR                       52: new_banned_rights
                        986     NOP                             
                        988     NOP                             
                        990     JUMP_FORWARD                    282 (to 1558)
                        994     CALL                            1
                        1002    POP_TOP                         
                        1004    RETURN_VALUE                    
                        1006    LOAD_GLOBAL                     5: NULL + isinstance
                        1016    LOAD_FAST                       2: _var_var_0
                        1018    LOAD_GLOBAL                     6: types
                        1028    LOAD_ATTR                       54: ChannelAdminLogEventActionStopPoll
                        1048    CALL                            2
                        1056    POP_JUMP_IF_FALSE               21 (to 1100)
                        1058    LOAD_FAST                       2: _var_var_0
                        1060    LOAD_ATTR                       56: message
                        1080    NOP                             
                        1082    NOP                             
                        1084    NOP                             
                        1086    JUMP_FORWARD                    235 (to 1558)
                        1088    CALL                            1
                        1096    POP_TOP                         
                        1098    RETURN_VALUE                    
                        1100    LOAD_GLOBAL                     5: NULL + isinstance
                        1110    LOAD_FAST                       2: _var_var_0
                        1112    LOAD_GLOBAL                     6: types
                        1122    LOAD_ATTR                       58: ChannelAdminLogEventActionStartGroupCall
                        1142    CALL                            2
                        1150    POP_JUMP_IF_FALSE               21 (to 1194)
                        1152    LOAD_FAST                       2: _var_var_0
                        1154    LOAD_ATTR                       60: call
                        1174    NOP                             
                        1176    NOP                             
                        1178    NOP                             
                        1180    JUMP_FORWARD                    188 (to 1558)
                        1182    CALL                            1
                        1190    POP_TOP                         
                        1192    RETURN_VALUE                    
                        1194    LOAD_GLOBAL                     5: NULL + isinstance
                        1204    LOAD_FAST                       2: _var_var_0
                        1206    LOAD_GLOBAL                     6: types
                        1216    LOAD_ATTR                       62: ChannelAdminLogEventActionParticipantMute
                        1236    LOAD_GLOBAL                     6: types
                        1246    LOAD_ATTR                       64: ChannelAdminLogEventActionParticipantUnmute
                        1266    BUILD_TUPLE                     2
                        1268    CALL                            2
                        1276    POP_JUMP_IF_FALSE               21 (to 1320)
                        1278    LOAD_FAST                       2: _var_var_0
                        1280    LOAD_ATTR                       48: participant
                        1300    NOP                             
                        1302    NOP                             
                        1304    NOP                             
                        1306    JUMP_FORWARD                    125 (to 1558)
                        1308    CALL                            1
                        1316    POP_TOP                         
                        1318    RETURN_VALUE                    
                        1320    LOAD_GLOBAL                     5: NULL + isinstance
                        1330    LOAD_FAST                       2: _var_var_0
                        1332    LOAD_GLOBAL                     6: types
                        1342    LOAD_ATTR                       66: ChannelAdminLogEventActionToggleGroupCallSetting
                        1362    CALL                            2
                        1370    POP_JUMP_IF_FALSE               21 (to 1414)
                        1372    LOAD_FAST                       2: _var_var_0
                        1374    LOAD_ATTR                       68: join_muted
                        1394    NOP                             
                        1396    NOP                             
                        1398    NOP                             
                        1400    JUMP_FORWARD                    78 (to 1558)
                        1402    CALL                            1
                        1410    POP_TOP                         
                        1412    RETURN_VALUE                    
                        1414    LOAD_GLOBAL                     5: NULL + isinstance
                        1424    LOAD_FAST                       2: _var_var_0
                        1426    LOAD_GLOBAL                     6: types
                        1436    LOAD_ATTR                       70: ChannelAdminLogEventActionExportedInviteEdit
                        1456    CALL                            2
                        1464    POP_JUMP_IF_FALSE               21 (to 1508)
                        1466    LOAD_FAST                       2: _var_var_0
                        1468    LOAD_ATTR                       72: new_invite
                        1488    NOP                             
                        1490    NOP                             
                        1492    NOP                             
                        1494    JUMP_FORWARD                    31 (to 1558)
                        1496    CALL                            1
                        1504    POP_TOP                         
                        1506    RETURN_VALUE                    
                        1508    NOP                             
                        1510    LOAD_CONST                      5: None
                        1512    NOP                             
                        1514    NOP                             
                        1516    NOP                             
                        1518    JUMP_FORWARD                    19 (to 1558)
                        1526    POP_TOP                         
                        1528    RETURN_CONST                    5: None
                        1530    PUSH_EXC_INFO                   
                        1532    PUSH_NULL                       
                        1534    LOAD_CONST                      4: '__pyarmor_exit_23867__'
                        1536    NOP                             
                        1538    LOAD_CONST                      3: b'<COAddr>\x07\x00\x00\x1a\xe0\x05\x00\x00\x00\x00\x00\x00\x00\x00\x00\x00\x00\x00\x00\x00'
                        1540    CALL                            1
                        1548    POP_TOP                         
                        1550    RERAISE                         0
                        1552    COPY                            3
                        1554    POP_EXCEPT                      
                        1556    RERAISE                         1
                        1558    PUSH_NULL                       
                        1560    LOAD_CONST                      4: '__pyarmor_exit_23867__'
                        1562    LOAD_CONST                      3: b'<COAddr>\x07\x00\x00\x1a\xe0\x05\x00\x00\x00\x00\x00\x00\x00\x00\x00\x00\x00\x00\x00\x00'
                        1564    BUILD_TUPLE                     1
                        1566    CALL_FUNCTION_EX                0
                        1568    POP_TOP                         
                        1570    RETURN_VALUE                    
                    [Exception Table]
                        28 to 358 -> 1530 [0] 
                        378 to 452 -> 1530 [0] 
                        472 to 546 -> 1530 [0] 
                        566 to 640 -> 1530 [0] 
                        660 to 766 -> 1530 [0] 
                        786 to 892 -> 1530 [0] 
                        912 to 986 -> 1530 [0] 
                        1006 to 1080 -> 1530 [0] 
                        1100 to 1174 -> 1530 [0] 
                        1194 to 1300 -> 1530 [0] 
                        1320 to 1394 -> 1530 [0] 
                        1414 to 1488 -> 1530 [0] 
                        1530 to 1552 -> 1552 [1] lasti
                [Code]
                    File Name: <frozen multithon.tl.custom.adminlogevent>
                    Object Name: changed_about
                    Qualified Name: AdminLogEvent.changed_about
                    Arg Count: 1
                    Pos Only Arg Count: 0
                    KW Only Arg Count: 0
                    Stack Size: 5
                    Flags: 0x20000003 (CO_OPTIMIZED | CO_NEWLOCALS | CO_PYARMOR_OBFUSCATED)
                    [Names]
                        'isinstance'
                        'original'
                        'action'
                        'types'
                        'ChannelAdminLogEventActionChangeAbout'
                    [Locals+Names]
                        'self'
                        '__assert_armored__'
                    [Constants]
                        "\n        Whether the channel's about was changed or not.\n\n        If `True`, `old` and `new` will be present as `str`.\n        "
                        '__pyarmor_assert_23868__'
                        '__pyarmor_enter_23869__'
                        b'<COAddr>\x07\x00\x00\x1ap\x00\x00\x00\x00\x00\x00\x00\x00\x00\x00\x00\x00\x00\x00\x00'
                        '__pyarmor_exit_23870__'
                    [Disassembly]
                        0       NOP                             
                        2       NOP                             
                        4       PUSH_NULL                       
                        6       LOAD_CONST                      2: '__pyarmor_enter_23869__'
                        8       LOAD_CONST                      3: b'<COAddr>\x07\x00\x00\x1ap\x00\x00\x00\x00\x00\x00\x00\x00\x00\x00\x00\x00\x00\x00\x00'
                        10      BUILD_TUPLE                     1
                        12      CALL_FUNCTION_EX                0
                        14      POP_TOP                         
                        16      RESUME                          0
                        18      NOP                             
                        20      NOP                             
                        22      NOP                             
                        24      NOP                             
                        26      NOP                             
                        28      LOAD_GLOBAL                     1: NULL + isinstance
                        38      LOAD_FAST                       0: self
                        40      LOAD_ATTR                       2: original
                        60      LOAD_ATTR                       4: action
                        80      LOAD_GLOBAL                     6: types
                        90      LOAD_ATTR                       8: ChannelAdminLogEventActionChangeAbout
                        110     CALL                            2
                        118     NOP                             
                        120     NOP                             
                        122     NOP                             
                        124     JUMP_FORWARD                    20 (to 166)
                        126     CALL                            1
                        134     POP_TOP                         
                        136     RETURN_VALUE                    
                        138     PUSH_EXC_INFO                   
                        140     PUSH_NULL                       
                        142     LOAD_CONST                      4: '__pyarmor_exit_23870__'
                        144     NOP                             
                        146     LOAD_CONST                      3: b'<COAddr>\x07\x00\x00\x1ap\x00\x00\x00\x00\x00\x00\x00\x00\x00\x00\x00\x00\x00\x00\x00'
                        148     CALL                            1
                        156     POP_TOP                         
                        158     RERAISE                         0
                        160     COPY                            3
                        162     POP_EXCEPT                      
                        164     RERAISE                         1
                        166     PUSH_NULL                       
                        168     LOAD_CONST                      4: '__pyarmor_exit_23870__'
                        170     LOAD_CONST                      3: b'<COAddr>\x07\x00\x00\x1ap\x00\x00\x00\x00\x00\x00\x00\x00\x00\x00\x00\x00\x00\x00\x00'
                        172     BUILD_TUPLE                     1
                        174     CALL_FUNCTION_EX                0
                        176     POP_TOP                         
                        178     RETURN_VALUE                    
                    [Exception Table]
                        28 to 118 -> 138 [0] 
                        138 to 160 -> 160 [1] lasti
                [Code]
                    File Name: <frozen multithon.tl.custom.adminlogevent>
                    Object Name: changed_title
                    Qualified Name: AdminLogEvent.changed_title
                    Arg Count: 1
                    Pos Only Arg Count: 0
                    KW Only Arg Count: 0
                    Stack Size: 5
                    Flags: 0x20000003 (CO_OPTIMIZED | CO_NEWLOCALS | CO_PYARMOR_OBFUSCATED)
                    [Names]
                        'isinstance'
                        'original'
                        'action'
                        'types'
                        'ChannelAdminLogEventActionChangeTitle'
                    [Locals+Names]
                        'self'
                        '__assert_armored__'
                    [Constants]
                        "\n        Whether the channel's title was changed or not.\n\n        If `True`, `old` and `new` will be present as `str`.\n        "
                        '__pyarmor_assert_23871__'
                        '__pyarmor_enter_23872__'
                        b'<COAddr>\x05\x00\x00\x1ap\x00\x00\x00\x00\x00\x00\x00\x00\x00\x00\x00\x00\x00\x00\x00'
                        '__pyarmor_exit_23873__'
                    [Disassembly]
                        0       NOP                             
                        2       NOP                             
                        4       PUSH_NULL                       
                        6       LOAD_CONST                      2: '__pyarmor_enter_23872__'
                        8       LOAD_CONST                      3: b'<COAddr>\x05\x00\x00\x1ap\x00\x00\x00\x00\x00\x00\x00\x00\x00\x00\x00\x00\x00\x00\x00'
                        10      BUILD_TUPLE                     1
                        12      CALL_FUNCTION_EX                0
                        14      POP_TOP                         
                        16      RESUME                          0
                        18      NOP                             
                        20      NOP                             
                        22      NOP                             
                        24      NOP                             
                        26      NOP                             
                        28      LOAD_GLOBAL                     1: NULL + isinstance
                        38      LOAD_FAST                       0: self
                        40      LOAD_ATTR                       2: original
                        60      LOAD_ATTR                       4: action
                        80      LOAD_GLOBAL                     6: types
                        90      LOAD_ATTR                       8: ChannelAdminLogEventActionChangeTitle
                        110     CALL                            2
                        118     NOP                             
                        120     NOP                             
                        122     NOP                             
                        124     JUMP_FORWARD                    20 (to 166)
                        126     CALL                            1
                        134     POP_TOP                         
                        136     RETURN_VALUE                    
                        138     PUSH_EXC_INFO                   
                        140     PUSH_NULL                       
                        142     LOAD_CONST                      4: '__pyarmor_exit_23873__'
                        144     NOP                             
                        146     LOAD_CONST                      3: b'<COAddr>\x05\x00\x00\x1ap\x00\x00\x00\x00\x00\x00\x00\x00\x00\x00\x00\x00\x00\x00\x00'
                        148     CALL                            1
                        156     POP_TOP                         
                        158     RERAISE                         0
                        160     COPY                            3
                        162     POP_EXCEPT                      
                        164     RERAISE                         1
                        166     PUSH_NULL                       
                        168     LOAD_CONST                      4: '__pyarmor_exit_23873__'
                        170     LOAD_CONST                      3: b'<COAddr>\x05\x00\x00\x1ap\x00\x00\x00\x00\x00\x00\x00\x00\x00\x00\x00\x00\x00\x00\x00'
                        172     BUILD_TUPLE                     1
                        174     CALL_FUNCTION_EX                0
                        176     POP_TOP                         
                        178     RETURN_VALUE                    
                    [Exception Table]
                        28 to 118 -> 138 [0] 
                        138 to 160 -> 160 [1] lasti
                [Code]
                    File Name: <frozen multithon.tl.custom.adminlogevent>
                    Object Name: changed_username
                    Qualified Name: AdminLogEvent.changed_username
                    Arg Count: 1
                    Pos Only Arg Count: 0
                    KW Only Arg Count: 0
                    Stack Size: 5
                    Flags: 0x20000003 (CO_OPTIMIZED | CO_NEWLOCALS | CO_PYARMOR_OBFUSCATED)
                    [Names]
                        'isinstance'
                        'original'
                        'action'
                        'types'
                        'ChannelAdminLogEventActionChangeUsername'
                    [Locals+Names]
                        'self'
                        '__assert_armored__'
                    [Constants]
                        "\n        Whether the channel's username was changed or not.\n\n        If `True`, `old` and `new` will be present as `str`.\n        "
                        '__pyarmor_assert_23874__'
                        '__pyarmor_enter_23875__'
                        b'<COAddr>\x05\x00\x00\x1ap\x00\x00\x00\x00\x00\x00\x00\x00\x00\x00\x00\x00\x00\x00\x00'
                        '__pyarmor_exit_23876__'
                    [Disassembly]
                        0       NOP                             
                        2       NOP                             
                        4       PUSH_NULL                       
                        6       LOAD_CONST                      2: '__pyarmor_enter_23875__'
                        8       LOAD_CONST                      3: b'<COAddr>\x05\x00\x00\x1ap\x00\x00\x00\x00\x00\x00\x00\x00\x00\x00\x00\x00\x00\x00\x00'
                        10      BUILD_TUPLE                     1
                        12      CALL_FUNCTION_EX                0
                        14      POP_TOP                         
                        16      RESUME                          0
                        18      NOP                             
                        20      NOP                             
                        22      NOP                             
                        24      NOP                             
                        26      NOP                             
                        28      LOAD_GLOBAL                     1: NULL + isinstance
                        38      LOAD_FAST                       0: self
                        40      LOAD_ATTR                       2: original
                        60      LOAD_ATTR                       4: action
                        80      LOAD_GLOBAL                     6: types
                        90      LOAD_ATTR                       8: ChannelAdminLogEventActionChangeUsername
                        110     CALL                            2
                        118     NOP                             
                        120     NOP                             
                        122     NOP                             
                        124     JUMP_FORWARD                    20 (to 166)
                        126     CALL                            1
                        134     POP_TOP                         
                        136     RETURN_VALUE                    
                        138     PUSH_EXC_INFO                   
                        140     PUSH_NULL                       
                        142     LOAD_CONST                      4: '__pyarmor_exit_23876__'
                        144     NOP                             
                        146     LOAD_CONST                      3: b'<COAddr>\x05\x00\x00\x1ap\x00\x00\x00\x00\x00\x00\x00\x00\x00\x00\x00\x00\x00\x00\x00'
                        148     CALL                            1
                        156     POP_TOP                         
                        158     RERAISE                         0
                        160     COPY                            3
                        162     POP_EXCEPT                      
                        164     RERAISE                         1
                        166     PUSH_NULL                       
                        168     LOAD_CONST                      4: '__pyarmor_exit_23876__'
                        170     LOAD_CONST                      3: b'<COAddr>\x05\x00\x00\x1ap\x00\x00\x00\x00\x00\x00\x00\x00\x00\x00\x00\x00\x00\x00\x00'
                        172     BUILD_TUPLE                     1
                        174     CALL_FUNCTION_EX                0
                        176     POP_TOP                         
                        178     RETURN_VALUE                    
                    [Exception Table]
                        28 to 118 -> 138 [0] 
                        138 to 160 -> 160 [1] lasti
                [Code]
                    File Name: <frozen multithon.tl.custom.adminlogevent>
                    Object Name: changed_photo
                    Qualified Name: AdminLogEvent.changed_photo
                    Arg Count: 1
                    Pos Only Arg Count: 0
                    KW Only Arg Count: 0
                    Stack Size: 5
                    Flags: 0x20000003 (CO_OPTIMIZED | CO_NEWLOCALS | CO_PYARMOR_OBFUSCATED)
                    [Names]
                        'isinstance'
                        'original'
                        'action'
                        'types'
                        'ChannelAdminLogEventActionChangePhoto'
                    [Locals+Names]
                        'self'
                        '__assert_armored__'
                    [Constants]
                        "\n        Whether the channel's photo was changed or not.\n\n        If `True`, `old` and `new` will be present as :tl:`Photo`.\n        "
                        '__pyarmor_assert_23877__'
                        '__pyarmor_enter_23878__'
                        b'<COAddr>\x07\x00\x00\x1ap\x00\x00\x00\x00\x00\x00\x00\x00\x00\x00\x00\x00\x00\x00\x00'
                        '__pyarmor_exit_23879__'
                    [Disassembly]
                        0       NOP                             
                        2       NOP                             
                        4       PUSH_NULL                       
                        6       LOAD_CONST                      2: '__pyarmor_enter_23878__'
                        8       LOAD_CONST                      3: b'<COAddr>\x07\x00\x00\x1ap\x00\x00\x00\x00\x00\x00\x00\x00\x00\x00\x00\x00\x00\x00\x00'
                        10      BUILD_TUPLE                     1
                        12      CALL_FUNCTION_EX                0
                        14      POP_TOP                         
                        16      RESUME                          0
                        18      NOP                             
                        20      NOP                             
                        22      NOP                             
                        24      NOP                             
                        26      NOP                             
                        28      LOAD_GLOBAL                     1: NULL + isinstance
                        38      LOAD_FAST                       0: self
                        40      LOAD_ATTR                       2: original
                        60      LOAD_ATTR                       4: action
                        80      LOAD_GLOBAL                     6: types
                        90      LOAD_ATTR                       8: ChannelAdminLogEventActionChangePhoto
                        110     CALL                            2
                        118     NOP                             
                        120     NOP                             
                        122     NOP                             
                        124     JUMP_FORWARD                    20 (to 166)
                        126     CALL                            1
                        134     POP_TOP                         
                        136     RETURN_VALUE                    
                        138     PUSH_EXC_INFO                   
                        140     PUSH_NULL                       
                        142     LOAD_CONST                      4: '__pyarmor_exit_23879__'
                        144     NOP                             
                        146     LOAD_CONST                      3: b'<COAddr>\x07\x00\x00\x1ap\x00\x00\x00\x00\x00\x00\x00\x00\x00\x00\x00\x00\x00\x00\x00'
                        148     CALL                            1
                        156     POP_TOP                         
                        158     RERAISE                         0
                        160     COPY                            3
                        162     POP_EXCEPT                      
                        164     RERAISE                         1
                        166     PUSH_NULL                       
                        168     LOAD_CONST                      4: '__pyarmor_exit_23879__'
                        170     LOAD_CONST                      3: b'<COAddr>\x07\x00\x00\x1ap\x00\x00\x00\x00\x00\x00\x00\x00\x00\x00\x00\x00\x00\x00\x00'
                        172     BUILD_TUPLE                     1
                        174     CALL_FUNCTION_EX                0
                        176     POP_TOP                         
                        178     RETURN_VALUE                    
                    [Exception Table]
                        28 to 118 -> 138 [0] 
                        138 to 160 -> 160 [1] lasti
                [Code]
                    File Name: <frozen multithon.tl.custom.adminlogevent>
                    Object Name: changed_sticker_set
                    Qualified Name: AdminLogEvent.changed_sticker_set
                    Arg Count: 1
                    Pos Only Arg Count: 0
                    KW Only Arg Count: 0
                    Stack Size: 5
                    Flags: 0x20000003 (CO_OPTIMIZED | CO_NEWLOCALS | CO_PYARMOR_OBFUSCATED)
                    [Names]
                        'isinstance'
                        'original'
                        'action'
                        'types'
                        'ChannelAdminLogEventActionChangeStickerSet'
                    [Locals+Names]
                        'self'
                        '__assert_armored__'
                    [Constants]
                        "\n        Whether the channel's sticker set was changed or not.\n\n        If `True`, `old` and `new` will be present as :tl:`InputStickerSet`.\n        "
                        '__pyarmor_assert_23880__'
                        '__pyarmor_enter_23881__'
                        b'<COAddr>\x07\x00\x00\x1ap\x00\x00\x00\x00\x00\x00\x00\x00\x00\x00\x00\x00\x00\x00\x00'
                        '__pyarmor_exit_23882__'
                    [Disassembly]
                        0       NOP                             
                        2       NOP                             
                        4       PUSH_NULL                       
                        6       LOAD_CONST                      2: '__pyarmor_enter_23881__'
                        8       LOAD_CONST                      3: b'<COAddr>\x07\x00\x00\x1ap\x00\x00\x00\x00\x00\x00\x00\x00\x00\x00\x00\x00\x00\x00\x00'
                        10      BUILD_TUPLE                     1
                        12      CALL_FUNCTION_EX                0
                        14      POP_TOP                         
                        16      RESUME                          0
                        18      NOP                             
                        20      NOP                             
                        22      NOP                             
                        24      NOP                             
                        26      NOP                             
                        28      LOAD_GLOBAL                     1: NULL + isinstance
                        38      LOAD_FAST                       0: self
                        40      LOAD_ATTR                       2: original
                        60      LOAD_ATTR                       4: action
                        80      LOAD_GLOBAL                     6: types
                        90      LOAD_ATTR                       8: ChannelAdminLogEventActionChangeStickerSet
                        110     CALL                            2
                        118     NOP                             
                        120     NOP                             
                        122     NOP                             
                        124     JUMP_FORWARD                    20 (to 166)
                        126     CALL                            1
                        134     POP_TOP                         
                        136     RETURN_VALUE                    
                        138     PUSH_EXC_INFO                   
                        140     PUSH_NULL                       
                        142     LOAD_CONST                      4: '__pyarmor_exit_23882__'
                        144     NOP                             
                        146     LOAD_CONST                      3: b'<COAddr>\x07\x00\x00\x1ap\x00\x00\x00\x00\x00\x00\x00\x00\x00\x00\x00\x00\x00\x00\x00'
                        148     CALL                            1
                        156     POP_TOP                         
                        158     RERAISE                         0
                        160     COPY                            3
                        162     POP_EXCEPT                      
                        164     RERAISE                         1
                        166     PUSH_NULL                       
                        168     LOAD_CONST                      4: '__pyarmor_exit_23882__'
                        170     LOAD_CONST                      3: b'<COAddr>\x07\x00\x00\x1ap\x00\x00\x00\x00\x00\x00\x00\x00\x00\x00\x00\x00\x00\x00\x00'
                        172     BUILD_TUPLE                     1
                        174     CALL_FUNCTION_EX                0
                        176     POP_TOP                         
                        178     RETURN_VALUE                    
                    [Exception Table]
                        28 to 118 -> 138 [0] 
                        138 to 160 -> 160 [1] lasti
                [Code]
                    File Name: <frozen multithon.tl.custom.adminlogevent>
                    Object Name: changed_message
                    Qualified Name: AdminLogEvent.changed_message
                    Arg Count: 1
                    Pos Only Arg Count: 0
                    KW Only Arg Count: 0
                    Stack Size: 5
                    Flags: 0x20000003 (CO_OPTIMIZED | CO_NEWLOCALS | CO_PYARMOR_OBFUSCATED)
                    [Names]
                        'isinstance'
                        'original'
                        'action'
                        'types'
                        'ChannelAdminLogEventActionEditMessage'
                    [Locals+Names]
                        'self'
                        '__assert_armored__'
                    [Constants]
                        '\n        Whether a message in this channel was edited or not.\n\n        If `True`, `old` and `new` will be present as\n        `Message <telethon.tl.custom.message.Message>`.\n        '
                        '__pyarmor_assert_23883__'
                        '__pyarmor_enter_23884__'
                        b'<COAddr>\x07\x00\x00\x1ap\x00\x00\x00\x00\x00\x00\x00\x00\x00\x00\x00\x00\x00\x00\x00'
                        '__pyarmor_exit_23885__'
                    [Disassembly]
                        0       NOP                             
                        2       NOP                             
                        4       PUSH_NULL                       
                        6       LOAD_CONST                      2: '__pyarmor_enter_23884__'
                        8       LOAD_CONST                      3: b'<COAddr>\x07\x00\x00\x1ap\x00\x00\x00\x00\x00\x00\x00\x00\x00\x00\x00\x00\x00\x00\x00'
                        10      BUILD_TUPLE                     1
                        12      CALL_FUNCTION_EX                0
                        14      POP_TOP                         
                        16      RESUME                          0
                        18      NOP                             
                        20      NOP                             
                        22      NOP                             
                        24      NOP                             
                        26      NOP                             
                        28      LOAD_GLOBAL                     1: NULL + isinstance
                        38      LOAD_FAST                       0: self
                        40      LOAD_ATTR                       2: original
                        60      LOAD_ATTR                       4: action
                        80      LOAD_GLOBAL                     6: types
                        90      LOAD_ATTR                       8: ChannelAdminLogEventActionEditMessage
                        110     CALL                            2
                        118     NOP                             
                        120     NOP                             
                        122     NOP                             
                        124     JUMP_FORWARD                    20 (to 166)
                        126     CALL                            1
                        134     POP_TOP                         
                        136     RETURN_VALUE                    
                        138     PUSH_EXC_INFO                   
                        140     PUSH_NULL                       
                        142     LOAD_CONST                      4: '__pyarmor_exit_23885__'
                        144     NOP                             
                        146     LOAD_CONST                      3: b'<COAddr>\x07\x00\x00\x1ap\x00\x00\x00\x00\x00\x00\x00\x00\x00\x00\x00\x00\x00\x00\x00'
                        148     CALL                            1
                        156     POP_TOP                         
                        158     RERAISE                         0
                        160     COPY                            3
                        162     POP_EXCEPT                      
                        164     RERAISE                         1
                        166     PUSH_NULL                       
                        168     LOAD_CONST                      4: '__pyarmor_exit_23885__'
                        170     LOAD_CONST                      3: b'<COAddr>\x07\x00\x00\x1ap\x00\x00\x00\x00\x00\x00\x00\x00\x00\x00\x00\x00\x00\x00\x00'
                        172     BUILD_TUPLE                     1
                        174     CALL_FUNCTION_EX                0
                        176     POP_TOP                         
                        178     RETURN_VALUE                    
                    [Exception Table]
                        28 to 118 -> 138 [0] 
                        138 to 160 -> 160 [1] lasti
                [Code]
                    File Name: <frozen multithon.tl.custom.adminlogevent>
                    Object Name: deleted_message
                    Qualified Name: AdminLogEvent.deleted_message
                    Arg Count: 1
                    Pos Only Arg Count: 0
                    KW Only Arg Count: 0
                    Stack Size: 5
                    Flags: 0x20000003 (CO_OPTIMIZED | CO_NEWLOCALS | CO_PYARMOR_OBFUSCATED)
                    [Names]
                        'isinstance'
                        'original'
                        'action'
                        'types'
                        'ChannelAdminLogEventActionDeleteMessage'
                    [Locals+Names]
                        'self'
                        '__assert_armored__'
                    [Constants]
                        '\n        Whether a message in this channel was deleted or not.\n\n        If `True`, `old` will be present as\n        `Message <telethon.tl.custom.message.Message>`.\n        '
                        '__pyarmor_assert_23886__'
                        '__pyarmor_enter_23887__'
                        b'<COAddr>\x05\x00\x00\x1ap\x00\x00\x00\x00\x00\x00\x00\x00\x00\x00\x00\x00\x00\x00\x00'
                        '__pyarmor_exit_23888__'
                    [Disassembly]
                        0       NOP                             
                        2       NOP                             
                        4       PUSH_NULL                       
                        6       LOAD_CONST                      2: '__pyarmor_enter_23887__'
                        8       LOAD_CONST                      3: b'<COAddr>\x05\x00\x00\x1ap\x00\x00\x00\x00\x00\x00\x00\x00\x00\x00\x00\x00\x00\x00\x00'
                        10      BUILD_TUPLE                     1
                        12      CALL_FUNCTION_EX                0
                        14      POP_TOP                         
                        16      RESUME                          0
                        18      NOP                             
                        20      NOP                             
                        22      NOP                             
                        24      NOP                             
                        26      NOP                             
                        28      LOAD_GLOBAL                     1: NULL + isinstance
                        38      LOAD_FAST                       0: self
                        40      LOAD_ATTR                       2: original
                        60      LOAD_ATTR                       4: action
                        80      LOAD_GLOBAL                     6: types
                        90      LOAD_ATTR                       8: ChannelAdminLogEventActionDeleteMessage
                        110     CALL                            2
                        118     NOP                             
                        120     NOP                             
                        122     NOP                             
                        124     JUMP_FORWARD                    20 (to 166)
                        126     CALL                            1
                        134     POP_TOP                         
                        136     RETURN_VALUE                    
                        138     PUSH_EXC_INFO                   
                        140     PUSH_NULL                       
                        142     LOAD_CONST                      4: '__pyarmor_exit_23888__'
                        144     NOP                             
                        146     LOAD_CONST                      3: b'<COAddr>\x05\x00\x00\x1ap\x00\x00\x00\x00\x00\x00\x00\x00\x00\x00\x00\x00\x00\x00\x00'
                        148     CALL                            1
                        156     POP_TOP                         
                        158     RERAISE                         0
                        160     COPY                            3
                        162     POP_EXCEPT                      
                        164     RERAISE                         1
                        166     PUSH_NULL                       
                        168     LOAD_CONST                      4: '__pyarmor_exit_23888__'
                        170     LOAD_CONST                      3: b'<COAddr>\x05\x00\x00\x1ap\x00\x00\x00\x00\x00\x00\x00\x00\x00\x00\x00\x00\x00\x00\x00'
                        172     BUILD_TUPLE                     1
                        174     CALL_FUNCTION_EX                0
                        176     POP_TOP                         
                        178     RETURN_VALUE                    
                    [Exception Table]
                        28 to 118 -> 138 [0] 
                        138 to 160 -> 160 [1] lasti
                [Code]
                    File Name: <frozen multithon.tl.custom.adminlogevent>
                    Object Name: changed_admin
                    Qualified Name: AdminLogEvent.changed_admin
                    Arg Count: 1
                    Pos Only Arg Count: 0
                    KW Only Arg Count: 0
                    Stack Size: 5
                    Flags: 0x20000003 (CO_OPTIMIZED | CO_NEWLOCALS | CO_PYARMOR_OBFUSCATED)
                    [Names]
                        'isinstance'
                        'original'
                        'action'
                        'types'
                        'ChannelAdminLogEventActionParticipantToggleAdmin'
                    [Locals+Names]
                        'self'
                        '__assert_armored__'
                    [Constants]
                        '\n        Whether the permissions for an admin in this channel\n        changed or not.\n\n        If `True`, `old` and `new` will be present as\n        :tl:`ChannelParticipant`.\n        '
                        '__pyarmor_assert_23889__'
                        '__pyarmor_enter_23890__'
                        b'<COAddr>\x07\x00\x00\x1ap\x00\x00\x00\x00\x00\x00\x00\x00\x00\x00\x00\x00\x00\x00\x00'
                        '__pyarmor_exit_23891__'
                    [Disassembly]
                        0       NOP                             
                        2       NOP                             
                        4       PUSH_NULL                       
                        6       LOAD_CONST                      2: '__pyarmor_enter_23890__'
                        8       LOAD_CONST                      3: b'<COAddr>\x07\x00\x00\x1ap\x00\x00\x00\x00\x00\x00\x00\x00\x00\x00\x00\x00\x00\x00\x00'
                        10      BUILD_TUPLE                     1
                        12      CALL_FUNCTION_EX                0
                        14      POP_TOP                         
                        16      RESUME                          0
                        18      NOP                             
                        20      NOP                             
                        22      NOP                             
                        24      NOP                             
                        26      NOP                             
                        28      LOAD_GLOBAL                     1: NULL + isinstance
                        38      LOAD_FAST                       0: self
                        40      LOAD_ATTR                       2: original
                        60      LOAD_ATTR                       4: action
                        80      LOAD_GLOBAL                     6: types
                        90      LOAD_ATTR                       8: ChannelAdminLogEventActionParticipantToggleAdmin
                        110     CALL                            2
                        118     NOP                             
                        120     NOP                             
                        122     NOP                             
                        124     JUMP_FORWARD                    20 (to 166)
                        126     CALL                            1
                        134     POP_TOP                         
                        136     RETURN_VALUE                    
                        138     PUSH_EXC_INFO                   
                        140     PUSH_NULL                       
                        142     LOAD_CONST                      4: '__pyarmor_exit_23891__'
                        144     NOP                             
                        146     LOAD_CONST                      3: b'<COAddr>\x07\x00\x00\x1ap\x00\x00\x00\x00\x00\x00\x00\x00\x00\x00\x00\x00\x00\x00\x00'
                        148     CALL                            1
                        156     POP_TOP                         
                        158     RERAISE                         0
                        160     COPY                            3
                        162     POP_EXCEPT                      
                        164     RERAISE                         1
                        166     PUSH_NULL                       
                        168     LOAD_CONST                      4: '__pyarmor_exit_23891__'
                        170     LOAD_CONST                      3: b'<COAddr>\x07\x00\x00\x1ap\x00\x00\x00\x00\x00\x00\x00\x00\x00\x00\x00\x00\x00\x00\x00'
                        172     BUILD_TUPLE                     1
                        174     CALL_FUNCTION_EX                0
                        176     POP_TOP                         
                        178     RETURN_VALUE                    
                    [Exception Table]
                        28 to 118 -> 138 [0] 
                        138 to 160 -> 160 [1] lasti
                [Code]
                    File Name: <frozen multithon.tl.custom.adminlogevent>
                    Object Name: changed_restrictions
                    Qualified Name: AdminLogEvent.changed_restrictions
                    Arg Count: 1
                    Pos Only Arg Count: 0
                    KW Only Arg Count: 0
                    Stack Size: 5
                    Flags: 0x20000003 (CO_OPTIMIZED | CO_NEWLOCALS | CO_PYARMOR_OBFUSCATED)
                    [Names]
                        'isinstance'
                        'original'
                        'action'
                        'types'
                        'ChannelAdminLogEventActionParticipantToggleBan'
                    [Locals+Names]
                        'self'
                        '__assert_armored__'
                    [Constants]
                        '\n        Whether a message in this channel was edited or not.\n\n        If `True`, `old` and `new` will be present as\n        :tl:`ChannelParticipant`.\n        '
                        '__pyarmor_assert_23892__'
                        '__pyarmor_enter_23893__'
                        b'<COAddr>\x07\x00\x00\x1ap\x00\x00\x00\x00\x00\x00\x00\x00\x00\x00\x00\x00\x00\x00\x00'
                        '__pyarmor_exit_23894__'
                    [Disassembly]
                        0       NOP                             
                        2       NOP                             
                        4       PUSH_NULL                       
                        6       LOAD_CONST                      2: '__pyarmor_enter_23893__'
                        8       LOAD_CONST                      3: b'<COAddr>\x07\x00\x00\x1ap\x00\x00\x00\x00\x00\x00\x00\x00\x00\x00\x00\x00\x00\x00\x00'
                        10      BUILD_TUPLE                     1
                        12      CALL_FUNCTION_EX                0
                        14      POP_TOP                         
                        16      RESUME                          0
                        18      NOP                             
                        20      NOP                             
                        22      NOP                             
                        24      NOP                             
                        26      NOP                             
                        28      LOAD_GLOBAL                     1: NULL + isinstance
                        38      LOAD_FAST                       0: self
                        40      LOAD_ATTR                       2: original
                        60      LOAD_ATTR                       4: action
                        80      LOAD_GLOBAL                     6: types
                        90      LOAD_ATTR                       8: ChannelAdminLogEventActionParticipantToggleBan
                        110     CALL                            2
                        118     NOP                             
                        120     NOP                             
                        122     NOP                             
                        124     JUMP_FORWARD                    20 (to 166)
                        126     CALL                            1
                        134     POP_TOP                         
                        136     RETURN_VALUE                    
                        138     PUSH_EXC_INFO                   
                        140     PUSH_NULL                       
                        142     LOAD_CONST                      4: '__pyarmor_exit_23894__'
                        144     NOP                             
                        146     LOAD_CONST                      3: b'<COAddr>\x07\x00\x00\x1ap\x00\x00\x00\x00\x00\x00\x00\x00\x00\x00\x00\x00\x00\x00\x00'
                        148     CALL                            1
                        156     POP_TOP                         
                        158     RERAISE                         0
                        160     COPY                            3
                        162     POP_EXCEPT                      
                        164     RERAISE                         1
                        166     PUSH_NULL                       
                        168     LOAD_CONST                      4: '__pyarmor_exit_23894__'
                        170     LOAD_CONST                      3: b'<COAddr>\x07\x00\x00\x1ap\x00\x00\x00\x00\x00\x00\x00\x00\x00\x00\x00\x00\x00\x00\x00'
                        172     BUILD_TUPLE                     1
                        174     CALL_FUNCTION_EX                0
                        176     POP_TOP                         
                        178     RETURN_VALUE                    
                    [Exception Table]
                        28 to 118 -> 138 [0] 
                        138 to 160 -> 160 [1] lasti
                [Code]
                    File Name: <frozen multithon.tl.custom.adminlogevent>
                    Object Name: changed_invites
                    Qualified Name: AdminLogEvent.changed_invites
                    Arg Count: 1
                    Pos Only Arg Count: 0
                    KW Only Arg Count: 0
                    Stack Size: 5
                    Flags: 0x20000003 (CO_OPTIMIZED | CO_NEWLOCALS | CO_PYARMOR_OBFUSCATED)
                    [Names]
                        'isinstance'
                        'original'
                        'action'
                        'types'
                        'ChannelAdminLogEventActionToggleInvites'
                    [Locals+Names]
                        'self'
                        '__assert_armored__'
                    [Constants]
                        '\n        Whether the invites in the channel were toggled or not.\n\n        If `True`, `old` and `new` will be present as `bool`.\n        '
                        '__pyarmor_assert_23895__'
                        '__pyarmor_enter_23896__'
                        b'<COAddr>\x07\x00\x00\x1ap\x00\x00\x00\x00\x00\x00\x00\x00\x00\x00\x00\x00\x00\x00\x00'
                        '__pyarmor_exit_23897__'
                    [Disassembly]
                        0       NOP                             
                        2       NOP                             
                        4       PUSH_NULL                       
                        6       LOAD_CONST                      2: '__pyarmor_enter_23896__'
                        8       LOAD_CONST                      3: b'<COAddr>\x07\x00\x00\x1ap\x00\x00\x00\x00\x00\x00\x00\x00\x00\x00\x00\x00\x00\x00\x00'
                        10      BUILD_TUPLE                     1
                        12      CALL_FUNCTION_EX                0
                        14      POP_TOP                         
                        16      RESUME                          0
                        18      NOP                             
                        20      NOP                             
                        22      NOP                             
                        24      NOP                             
                        26      NOP                             
                        28      LOAD_GLOBAL                     1: NULL + isinstance
                        38      LOAD_FAST                       0: self
                        40      LOAD_ATTR                       2: original
                        60      LOAD_ATTR                       4: action
                        80      LOAD_GLOBAL                     6: types
                        90      LOAD_ATTR                       8: ChannelAdminLogEventActionToggleInvites
                        110     CALL                            2
                        118     NOP                             
                        120     NOP                             
                        122     NOP                             
                        124     JUMP_FORWARD                    20 (to 166)
                        126     CALL                            1
                        134     POP_TOP                         
                        136     RETURN_VALUE                    
                        138     PUSH_EXC_INFO                   
                        140     PUSH_NULL                       
                        142     LOAD_CONST                      4: '__pyarmor_exit_23897__'
                        144     NOP                             
                        146     LOAD_CONST                      3: b'<COAddr>\x07\x00\x00\x1ap\x00\x00\x00\x00\x00\x00\x00\x00\x00\x00\x00\x00\x00\x00\x00'
                        148     CALL                            1
                        156     POP_TOP                         
                        158     RERAISE                         0
                        160     COPY                            3
                        162     POP_EXCEPT                      
                        164     RERAISE                         1
                        166     PUSH_NULL                       
                        168     LOAD_CONST                      4: '__pyarmor_exit_23897__'
                        170     LOAD_CONST                      3: b'<COAddr>\x07\x00\x00\x1ap\x00\x00\x00\x00\x00\x00\x00\x00\x00\x00\x00\x00\x00\x00\x00'
                        172     BUILD_TUPLE                     1
                        174     CALL_FUNCTION_EX                0
                        176     POP_TOP                         
                        178     RETURN_VALUE                    
                    [Exception Table]
                        28 to 118 -> 138 [0] 
                        138 to 160 -> 160 [1] lasti
                [Code]
                    File Name: <frozen multithon.tl.custom.adminlogevent>
                    Object Name: changed_location
                    Qualified Name: AdminLogEvent.changed_location
                    Arg Count: 1
                    Pos Only Arg Count: 0
                    KW Only Arg Count: 0
                    Stack Size: 5
                    Flags: 0x20000003 (CO_OPTIMIZED | CO_NEWLOCALS | CO_PYARMOR_OBFUSCATED)
                    [Names]
                        'isinstance'
                        'original'
                        'action'
                        'types'
                        'ChannelAdminLogEventActionChangeLocation'
                    [Locals+Names]
                        'self'
                        '__assert_armored__'
                    [Constants]
                        '\n        Whether the location setting of the channel has changed or not.\n\n        If `True`, `old` and `new` will be present as :tl:`ChannelLocation`.\n        '
                        '__pyarmor_assert_23898__'
                        '__pyarmor_enter_23899__'
                        b'<COAddr>\x05\x00\x00\x1ap\x00\x00\x00\x00\x00\x00\x00\x00\x00\x00\x00\x00\x00\x00\x00'
                        '__pyarmor_exit_23900__'
                    [Disassembly]
                        0       NOP                             
                        2       NOP                             
                        4       PUSH_NULL                       
                        6       LOAD_CONST                      2: '__pyarmor_enter_23899__'
                        8       LOAD_CONST                      3: b'<COAddr>\x05\x00\x00\x1ap\x00\x00\x00\x00\x00\x00\x00\x00\x00\x00\x00\x00\x00\x00\x00'
                        10      BUILD_TUPLE                     1
                        12      CALL_FUNCTION_EX                0
                        14      POP_TOP                         
                        16      RESUME                          0
                        18      NOP                             
                        20      NOP                             
                        22      NOP                             
                        24      NOP                             
                        26      NOP                             
                        28      LOAD_GLOBAL                     1: NULL + isinstance
                        38      LOAD_FAST                       0: self
                        40      LOAD_ATTR                       2: original
                        60      LOAD_ATTR                       4: action
                        80      LOAD_GLOBAL                     6: types
                        90      LOAD_ATTR                       8: ChannelAdminLogEventActionChangeLocation
                        110     CALL                            2
                        118     NOP                             
                        120     NOP                             
                        122     NOP                             
                        124     JUMP_FORWARD                    20 (to 166)
                        126     CALL                            1
                        134     POP_TOP                         
                        136     RETURN_VALUE                    
                        138     PUSH_EXC_INFO                   
                        140     PUSH_NULL                       
                        142     LOAD_CONST                      4: '__pyarmor_exit_23900__'
                        144     NOP                             
                        146     LOAD_CONST                      3: b'<COAddr>\x05\x00\x00\x1ap\x00\x00\x00\x00\x00\x00\x00\x00\x00\x00\x00\x00\x00\x00\x00'
                        148     CALL                            1
                        156     POP_TOP                         
                        158     RERAISE                         0
                        160     COPY                            3
                        162     POP_EXCEPT                      
                        164     RERAISE                         1
                        166     PUSH_NULL                       
                        168     LOAD_CONST                      4: '__pyarmor_exit_23900__'
                        170     LOAD_CONST                      3: b'<COAddr>\x05\x00\x00\x1ap\x00\x00\x00\x00\x00\x00\x00\x00\x00\x00\x00\x00\x00\x00\x00'
                        172     BUILD_TUPLE                     1
                        174     CALL_FUNCTION_EX                0
                        176     POP_TOP                         
                        178     RETURN_VALUE                    
                    [Exception Table]
                        28 to 118 -> 138 [0] 
                        138 to 160 -> 160 [1] lasti
                [Code]
                    File Name: <frozen multithon.tl.custom.adminlogevent>
                    Object Name: joined
                    Qualified Name: AdminLogEvent.joined
                    Arg Count: 1
                    Pos Only Arg Count: 0
                    KW Only Arg Count: 0
                    Stack Size: 5
                    Flags: 0x20000003 (CO_OPTIMIZED | CO_NEWLOCALS | CO_PYARMOR_OBFUSCATED)
                    [Names]
                        'isinstance'
                        'original'
                        'action'
                        'types'
                        'ChannelAdminLogEventActionParticipantJoin'
                    [Locals+Names]
                        'self'
                        '__assert_armored__'
                    [Constants]
                        "\n        Whether `user` joined through the channel's\n        public username or not.\n        "
                        '__pyarmor_assert_23901__'
                        '__pyarmor_enter_23902__'
                        b'<COAddr>\x07\x00\x00\x1ap\x00\x00\x00\x00\x00\x00\x00\x00\x00\x00\x00\x00\x00\x00\x00'
                        '__pyarmor_exit_23903__'
                    [Disassembly]
                        0       NOP                             
                        2       NOP                             
                        4       PUSH_NULL                       
                        6       LOAD_CONST                      2: '__pyarmor_enter_23902__'
                        8       LOAD_CONST                      3: b'<COAddr>\x07\x00\x00\x1ap\x00\x00\x00\x00\x00\x00\x00\x00\x00\x00\x00\x00\x00\x00\x00'
                        10      BUILD_TUPLE                     1
                        12      CALL_FUNCTION_EX                0
                        14      POP_TOP                         
                        16      RESUME                          0
                        18      NOP                             
                        20      NOP                             
                        22      NOP                             
                        24      NOP                             
                        26      NOP                             
                        28      LOAD_GLOBAL                     1: NULL + isinstance
                        38      LOAD_FAST                       0: self
                        40      LOAD_ATTR                       2: original
                        60      LOAD_ATTR                       4: action
                        80      LOAD_GLOBAL                     6: types
                        90      LOAD_ATTR                       8: ChannelAdminLogEventActionParticipantJoin
                        110     CALL                            2
                        118     NOP                             
                        120     NOP                             
                        122     NOP                             
                        124     JUMP_FORWARD                    20 (to 166)
                        126     CALL                            1
                        134     POP_TOP                         
                        136     RETURN_VALUE                    
                        138     PUSH_EXC_INFO                   
                        140     PUSH_NULL                       
                        142     LOAD_CONST                      4: '__pyarmor_exit_23903__'
                        144     NOP                             
                        146     LOAD_CONST                      3: b'<COAddr>\x07\x00\x00\x1ap\x00\x00\x00\x00\x00\x00\x00\x00\x00\x00\x00\x00\x00\x00\x00'
                        148     CALL                            1
                        156     POP_TOP                         
                        158     RERAISE                         0
                        160     COPY                            3
                        162     POP_EXCEPT                      
                        164     RERAISE                         1
                        166     PUSH_NULL                       
                        168     LOAD_CONST                      4: '__pyarmor_exit_23903__'
                        170     LOAD_CONST                      3: b'<COAddr>\x07\x00\x00\x1ap\x00\x00\x00\x00\x00\x00\x00\x00\x00\x00\x00\x00\x00\x00\x00'
                        172     BUILD_TUPLE                     1
                        174     CALL_FUNCTION_EX                0
                        176     POP_TOP                         
                        178     RETURN_VALUE                    
                    [Exception Table]
                        28 to 118 -> 138 [0] 
                        138 to 160 -> 160 [1] lasti
                [Code]
                    File Name: <frozen multithon.tl.custom.adminlogevent>
                    Object Name: joined_invite
                    Qualified Name: AdminLogEvent.joined_invite
                    Arg Count: 1
                    Pos Only Arg Count: 0
                    KW Only Arg Count: 0
                    Stack Size: 5
                    Flags: 0x20000003 (CO_OPTIMIZED | CO_NEWLOCALS | CO_PYARMOR_OBFUSCATED)
                    [Names]
                        'isinstance'
                        'original'
                        'action'
                        'types'
                        'ChannelAdminLogEventActionParticipantInvite'
                    [Locals+Names]
                        'self'
                        '__assert_armored__'
                    [Constants]
                        '\n        Whether a new user joined through an invite\n        link to the channel or not.\n\n        If `True`, `new` will be present as\n        :tl:`ChannelParticipant`.\n        '
                        '__pyarmor_assert_23904__'
                        '__pyarmor_enter_23905__'
                        b'<COAddr>\x05\x00\x00\x1ap\x00\x00\x00\x00\x00\x00\x00\x00\x00\x00\x00\x00\x00\x00\x00'
                        '__pyarmor_exit_23906__'
                    [Disassembly]
                        0       NOP                             
                        2       NOP                             
                        4       PUSH_NULL                       
                        6       LOAD_CONST                      2: '__pyarmor_enter_23905__'
                        8       LOAD_CONST                      3: b'<COAddr>\x05\x00\x00\x1ap\x00\x00\x00\x00\x00\x00\x00\x00\x00\x00\x00\x00\x00\x00\x00'
                        10      BUILD_TUPLE                     1
                        12      CALL_FUNCTION_EX                0
                        14      POP_TOP                         
                        16      RESUME                          0
                        18      NOP                             
                        20      NOP                             
                        22      NOP                             
                        24      NOP                             
                        26      NOP                             
                        28      LOAD_GLOBAL                     1: NULL + isinstance
                        38      LOAD_FAST                       0: self
                        40      LOAD_ATTR                       2: original
                        60      LOAD_ATTR                       4: action
                        80      LOAD_GLOBAL                     6: types
                        90      LOAD_ATTR                       8: ChannelAdminLogEventActionParticipantInvite
                        110     CALL                            2
                        118     NOP                             
                        120     NOP                             
                        122     NOP                             
                        124     JUMP_FORWARD                    20 (to 166)
                        126     CALL                            1
                        134     POP_TOP                         
                        136     RETURN_VALUE                    
                        138     PUSH_EXC_INFO                   
                        140     PUSH_NULL                       
                        142     LOAD_CONST                      4: '__pyarmor_exit_23906__'
                        144     NOP                             
                        146     LOAD_CONST                      3: b'<COAddr>\x05\x00\x00\x1ap\x00\x00\x00\x00\x00\x00\x00\x00\x00\x00\x00\x00\x00\x00\x00'
                        148     CALL                            1
                        156     POP_TOP                         
                        158     RERAISE                         0
                        160     COPY                            3
                        162     POP_EXCEPT                      
                        164     RERAISE                         1
                        166     PUSH_NULL                       
                        168     LOAD_CONST                      4: '__pyarmor_exit_23906__'
                        170     LOAD_CONST                      3: b'<COAddr>\x05\x00\x00\x1ap\x00\x00\x00\x00\x00\x00\x00\x00\x00\x00\x00\x00\x00\x00\x00'
                        172     BUILD_TUPLE                     1
                        174     CALL_FUNCTION_EX                0
                        176     POP_TOP                         
                        178     RETURN_VALUE                    
                    [Exception Table]
                        28 to 118 -> 138 [0] 
                        138 to 160 -> 160 [1] lasti
                [Code]
                    File Name: <frozen multithon.tl.custom.adminlogevent>
                    Object Name: left
                    Qualified Name: AdminLogEvent.left
                    Arg Count: 1
                    Pos Only Arg Count: 0
                    KW Only Arg Count: 0
                    Stack Size: 5
                    Flags: 0x20000003 (CO_OPTIMIZED | CO_NEWLOCALS | CO_PYARMOR_OBFUSCATED)
                    [Names]
                        'isinstance'
                        'original'
                        'action'
                        'types'
                        'ChannelAdminLogEventActionParticipantLeave'
                    [Locals+Names]
                        'self'
                        '__assert_armored__'
                    [Constants]
                        '\n        Whether `user` left the channel or not.\n        '
                        '__pyarmor_assert_23907__'
                        '__pyarmor_enter_23908__'
                        b'<COAddr>\x05\x00\x00\x1ap\x00\x00\x00\x00\x00\x00\x00\x00\x00\x00\x00\x00\x00\x00\x00'
                        '__pyarmor_exit_23909__'
                    [Disassembly]
                        0       NOP                             
                        2       NOP                             
                        4       PUSH_NULL                       
                        6       LOAD_CONST                      2: '__pyarmor_enter_23908__'
                        8       LOAD_CONST                      3: b'<COAddr>\x05\x00\x00\x1ap\x00\x00\x00\x00\x00\x00\x00\x00\x00\x00\x00\x00\x00\x00\x00'
                        10      BUILD_TUPLE                     1
                        12      CALL_FUNCTION_EX                0
                        14      POP_TOP                         
                        16      RESUME                          0
                        18      NOP                             
                        20      NOP                             
                        22      NOP                             
                        24      NOP                             
                        26      NOP                             
                        28      LOAD_GLOBAL                     1: NULL + isinstance
                        38      LOAD_FAST                       0: self
                        40      LOAD_ATTR                       2: original
                        60      LOAD_ATTR                       4: action
                        80      LOAD_GLOBAL                     6: types
                        90      LOAD_ATTR                       8: ChannelAdminLogEventActionParticipantLeave
                        110     CALL                            2
                        118     NOP                             
                        120     NOP                             
                        122     NOP                             
                        124     JUMP_FORWARD                    20 (to 166)
                        126     CALL                            1
                        134     POP_TOP                         
                        136     RETURN_VALUE                    
                        138     PUSH_EXC_INFO                   
                        140     PUSH_NULL                       
                        142     LOAD_CONST                      4: '__pyarmor_exit_23909__'
                        144     NOP                             
                        146     LOAD_CONST                      3: b'<COAddr>\x05\x00\x00\x1ap\x00\x00\x00\x00\x00\x00\x00\x00\x00\x00\x00\x00\x00\x00\x00'
                        148     CALL                            1
                        156     POP_TOP                         
                        158     RERAISE                         0
                        160     COPY                            3
                        162     POP_EXCEPT                      
                        164     RERAISE                         1
                        166     PUSH_NULL                       
                        168     LOAD_CONST                      4: '__pyarmor_exit_23909__'
                        170     LOAD_CONST                      3: b'<COAddr>\x05\x00\x00\x1ap\x00\x00\x00\x00\x00\x00\x00\x00\x00\x00\x00\x00\x00\x00\x00'
                        172     BUILD_TUPLE                     1
                        174     CALL_FUNCTION_EX                0
                        176     POP_TOP                         
                        178     RETURN_VALUE                    
                    [Exception Table]
                        28 to 118 -> 138 [0] 
                        138 to 160 -> 160 [1] lasti
                [Code]
                    File Name: <frozen multithon.tl.custom.adminlogevent>
                    Object Name: changed_hide_history
                    Qualified Name: AdminLogEvent.changed_hide_history
                    Arg Count: 1
                    Pos Only Arg Count: 0
                    KW Only Arg Count: 0
                    Stack Size: 5
                    Flags: 0x20000003 (CO_OPTIMIZED | CO_NEWLOCALS | CO_PYARMOR_OBFUSCATED)
                    [Names]
                        'isinstance'
                        'original'
                        'action'
                        'types'
                        'ChannelAdminLogEventActionTogglePreHistoryHidden'
                    [Locals+Names]
                        'self'
                        '__assert_armored__'
                    [Constants]
                        '\n        Whether hiding the previous message history for new members\n        in the channel was toggled or not.\n\n        If `True`, `old` and `new` will be present as `bool`.\n        '
                        '__pyarmor_assert_23910__'
                        '__pyarmor_enter_23911__'
                        b'<COAddr>\x05\x00\x00\x1ap\x00\x00\x00\x00\x00\x00\x00\x00\x00\x00\x00\x00\x00\x00\x00'
                        '__pyarmor_exit_23912__'
                    [Disassembly]
                        0       NOP                             
                        2       NOP                             
                        4       PUSH_NULL                       
                        6       LOAD_CONST                      2: '__pyarmor_enter_23911__'
                        8       LOAD_CONST                      3: b'<COAddr>\x05\x00\x00\x1ap\x00\x00\x00\x00\x00\x00\x00\x00\x00\x00\x00\x00\x00\x00\x00'
                        10      BUILD_TUPLE                     1
                        12      CALL_FUNCTION_EX                0
                        14      POP_TOP                         
                        16      RESUME                          0
                        18      NOP                             
                        20      NOP                             
                        22      NOP                             
                        24      NOP                             
                        26      NOP                             
                        28      LOAD_GLOBAL                     1: NULL + isinstance
                        38      LOAD_FAST                       0: self
                        40      LOAD_ATTR                       2: original
                        60      LOAD_ATTR                       4: action
                        80      LOAD_GLOBAL                     6: types
                        90      LOAD_ATTR                       8: ChannelAdminLogEventActionTogglePreHistoryHidden
                        110     CALL                            2
                        118     NOP                             
                        120     NOP                             
                        122     NOP                             
                        124     JUMP_FORWARD                    20 (to 166)
                        126     CALL                            1
                        134     POP_TOP                         
                        136     RETURN_VALUE                    
                        138     PUSH_EXC_INFO                   
                        140     PUSH_NULL                       
                        142     LOAD_CONST                      4: '__pyarmor_exit_23912__'
                        144     NOP                             
                        146     LOAD_CONST                      3: b'<COAddr>\x05\x00\x00\x1ap\x00\x00\x00\x00\x00\x00\x00\x00\x00\x00\x00\x00\x00\x00\x00'
                        148     CALL                            1
                        156     POP_TOP                         
                        158     RERAISE                         0
                        160     COPY                            3
                        162     POP_EXCEPT                      
                        164     RERAISE                         1
                        166     PUSH_NULL                       
                        168     LOAD_CONST                      4: '__pyarmor_exit_23912__'
                        170     LOAD_CONST                      3: b'<COAddr>\x05\x00\x00\x1ap\x00\x00\x00\x00\x00\x00\x00\x00\x00\x00\x00\x00\x00\x00\x00'
                        172     BUILD_TUPLE                     1
                        174     CALL_FUNCTION_EX                0
                        176     POP_TOP                         
                        178     RETURN_VALUE                    
                    [Exception Table]
                        28 to 118 -> 138 [0] 
                        138 to 160 -> 160 [1] lasti
                [Code]
                    File Name: <frozen multithon.tl.custom.adminlogevent>
                    Object Name: changed_signatures
                    Qualified Name: AdminLogEvent.changed_signatures
                    Arg Count: 1
                    Pos Only Arg Count: 0
                    KW Only Arg Count: 0
                    Stack Size: 5
                    Flags: 0x20000003 (CO_OPTIMIZED | CO_NEWLOCALS | CO_PYARMOR_OBFUSCATED)
                    [Names]
                        'isinstance'
                        'original'
                        'action'
                        'types'
                        'ChannelAdminLogEventActionToggleSignatures'
                    [Locals+Names]
                        'self'
                        '__assert_armored__'
                    [Constants]
                        '\n        Whether the message signatures in the channel were toggled\n        or not.\n\n        If `True`, `old` and `new` will be present as `bool`.\n        '
                        '__pyarmor_assert_23913__'
                        '__pyarmor_enter_23914__'
                        b'<COAddr>\x07\x00\x00\x1ap\x00\x00\x00\x00\x00\x00\x00\x00\x00\x00\x00\x00\x00\x00\x00'
                        '__pyarmor_exit_23915__'
                    [Disassembly]
                        0       NOP                             
                        2       NOP                             
                        4       PUSH_NULL                       
                        6       LOAD_CONST                      2: '__pyarmor_enter_23914__'
                        8       LOAD_CONST                      3: b'<COAddr>\x07\x00\x00\x1ap\x00\x00\x00\x00\x00\x00\x00\x00\x00\x00\x00\x00\x00\x00\x00'
                        10      BUILD_TUPLE                     1
                        12      CALL_FUNCTION_EX                0
                        14      POP_TOP                         
                        16      RESUME                          0
                        18      NOP                             
                        20      NOP                             
                        22      NOP                             
                        24      NOP                             
                        26      NOP                             
                        28      LOAD_GLOBAL                     1: NULL + isinstance
                        38      LOAD_FAST                       0: self
                        40      LOAD_ATTR                       2: original
                        60      LOAD_ATTR                       4: action
                        80      LOAD_GLOBAL                     6: types
                        90      LOAD_ATTR                       8: ChannelAdminLogEventActionToggleSignatures
                        110     CALL                            2
                        118     NOP                             
                        120     NOP                             
                        122     NOP                             
                        124     JUMP_FORWARD                    20 (to 166)
                        126     CALL                            1
                        134     POP_TOP                         
                        136     RETURN_VALUE                    
                        138     PUSH_EXC_INFO                   
                        140     PUSH_NULL                       
                        142     LOAD_CONST                      4: '__pyarmor_exit_23915__'
                        144     NOP                             
                        146     LOAD_CONST                      3: b'<COAddr>\x07\x00\x00\x1ap\x00\x00\x00\x00\x00\x00\x00\x00\x00\x00\x00\x00\x00\x00\x00'
                        148     CALL                            1
                        156     POP_TOP                         
                        158     RERAISE                         0
                        160     COPY                            3
                        162     POP_EXCEPT                      
                        164     RERAISE                         1
                        166     PUSH_NULL                       
                        168     LOAD_CONST                      4: '__pyarmor_exit_23915__'
                        170     LOAD_CONST                      3: b'<COAddr>\x07\x00\x00\x1ap\x00\x00\x00\x00\x00\x00\x00\x00\x00\x00\x00\x00\x00\x00\x00'
                        172     BUILD_TUPLE                     1
                        174     CALL_FUNCTION_EX                0
                        176     POP_TOP                         
                        178     RETURN_VALUE                    
                    [Exception Table]
                        28 to 118 -> 138 [0] 
                        138 to 160 -> 160 [1] lasti
                [Code]
                    File Name: <frozen multithon.tl.custom.adminlogevent>
                    Object Name: changed_pin
                    Qualified Name: AdminLogEvent.changed_pin
                    Arg Count: 1
                    Pos Only Arg Count: 0
                    KW Only Arg Count: 0
                    Stack Size: 5
                    Flags: 0x20000003 (CO_OPTIMIZED | CO_NEWLOCALS | CO_PYARMOR_OBFUSCATED)
                    [Names]
                        'isinstance'
                        'original'
                        'action'
                        'types'
                        'ChannelAdminLogEventActionUpdatePinned'
                    [Locals+Names]
                        'self'
                        '__assert_armored__'
                    [Constants]
                        '\n        Whether a new message in this channel was pinned or not.\n\n        If `True`, `new` will be present as\n        `Message <telethon.tl.custom.message.Message>`.\n        '
                        '__pyarmor_assert_23916__'
                        '__pyarmor_enter_23917__'
                        b'<COAddr>\x05\x00\x00\x1ap\x00\x00\x00\x00\x00\x00\x00\x00\x00\x00\x00\x00\x00\x00\x00'
                        '__pyarmor_exit_23918__'
                    [Disassembly]
                        0       NOP                             
                        2       NOP                             
                        4       PUSH_NULL                       
                        6       LOAD_CONST                      2: '__pyarmor_enter_23917__'
                        8       LOAD_CONST                      3: b'<COAddr>\x05\x00\x00\x1ap\x00\x00\x00\x00\x00\x00\x00\x00\x00\x00\x00\x00\x00\x00\x00'
                        10      BUILD_TUPLE                     1
                        12      CALL_FUNCTION_EX                0
                        14      POP_TOP                         
                        16      RESUME                          0
                        18      NOP                             
                        20      NOP                             
                        22      NOP                             
                        24      NOP                             
                        26      NOP                             
                        28      LOAD_GLOBAL                     1: NULL + isinstance
                        38      LOAD_FAST                       0: self
                        40      LOAD_ATTR                       2: original
                        60      LOAD_ATTR                       4: action
                        80      LOAD_GLOBAL                     6: types
                        90      LOAD_ATTR                       8: ChannelAdminLogEventActionUpdatePinned
                        110     CALL                            2
                        118     NOP                             
                        120     NOP                             
                        122     NOP                             
                        124     JUMP_FORWARD                    20 (to 166)
                        126     CALL                            1
                        134     POP_TOP                         
                        136     RETURN_VALUE                    
                        138     PUSH_EXC_INFO                   
                        140     PUSH_NULL                       
                        142     LOAD_CONST                      4: '__pyarmor_exit_23918__'
                        144     NOP                             
                        146     LOAD_CONST                      3: b'<COAddr>\x05\x00\x00\x1ap\x00\x00\x00\x00\x00\x00\x00\x00\x00\x00\x00\x00\x00\x00\x00'
                        148     CALL                            1
                        156     POP_TOP                         
                        158     RERAISE                         0
                        160     COPY                            3
                        162     POP_EXCEPT                      
                        164     RERAISE                         1
                        166     PUSH_NULL                       
                        168     LOAD_CONST                      4: '__pyarmor_exit_23918__'
                        170     LOAD_CONST                      3: b'<COAddr>\x05\x00\x00\x1ap\x00\x00\x00\x00\x00\x00\x00\x00\x00\x00\x00\x00\x00\x00\x00'
                        172     BUILD_TUPLE                     1
                        174     CALL_FUNCTION_EX                0
                        176     POP_TOP                         
                        178     RETURN_VALUE                    
                    [Exception Table]
                        28 to 118 -> 138 [0] 
                        138 to 160 -> 160 [1] lasti
                [Code]
                    File Name: <frozen multithon.tl.custom.adminlogevent>
                    Object Name: changed_default_banned_rights
                    Qualified Name: AdminLogEvent.changed_default_banned_rights
                    Arg Count: 1
                    Pos Only Arg Count: 0
                    KW Only Arg Count: 0
                    Stack Size: 5
                    Flags: 0x20000003 (CO_OPTIMIZED | CO_NEWLOCALS | CO_PYARMOR_OBFUSCATED)
                    [Names]
                        'isinstance'
                        'original'
                        'action'
                        'types'
                        'ChannelAdminLogEventActionDefaultBannedRights'
                    [Locals+Names]
                        'self'
                        '__assert_armored__'
                    [Constants]
                        '\n        Whether the default banned rights were changed or not.\n\n        If `True`, `old` and `new` will\n        be present as :tl:`ChatBannedRights`.\n        '
                        '__pyarmor_assert_23919__'
                        '__pyarmor_enter_23920__'
                        b'<COAddr>\x05\x00\x00\x1ap\x00\x00\x00\x00\x00\x00\x00\x00\x00\x00\x00\x00\x00\x00\x00'
                        '__pyarmor_exit_23921__'
                    [Disassembly]
                        0       NOP                             
                        2       NOP                             
                        4       PUSH_NULL                       
                        6       LOAD_CONST                      2: '__pyarmor_enter_23920__'
                        8       LOAD_CONST                      3: b'<COAddr>\x05\x00\x00\x1ap\x00\x00\x00\x00\x00\x00\x00\x00\x00\x00\x00\x00\x00\x00\x00'
                        10      BUILD_TUPLE                     1
                        12      CALL_FUNCTION_EX                0
                        14      POP_TOP                         
                        16      RESUME                          0
                        18      NOP                             
                        20      NOP                             
                        22      NOP                             
                        24      NOP                             
                        26      NOP                             
                        28      LOAD_GLOBAL                     1: NULL + isinstance
                        38      LOAD_FAST                       0: self
                        40      LOAD_ATTR                       2: original
                        60      LOAD_ATTR                       4: action
                        80      LOAD_GLOBAL                     6: types
                        90      LOAD_ATTR                       8: ChannelAdminLogEventActionDefaultBannedRights
                        110     CALL                            2
                        118     NOP                             
                        120     NOP                             
                        122     NOP                             
                        124     JUMP_FORWARD                    20 (to 166)
                        126     CALL                            1
                        134     POP_TOP                         
                        136     RETURN_VALUE                    
                        138     PUSH_EXC_INFO                   
                        140     PUSH_NULL                       
                        142     LOAD_CONST                      4: '__pyarmor_exit_23921__'
                        144     NOP                             
                        146     LOAD_CONST                      3: b'<COAddr>\x05\x00\x00\x1ap\x00\x00\x00\x00\x00\x00\x00\x00\x00\x00\x00\x00\x00\x00\x00'
                        148     CALL                            1
                        156     POP_TOP                         
                        158     RERAISE                         0
                        160     COPY                            3
                        162     POP_EXCEPT                      
                        164     RERAISE                         1
                        166     PUSH_NULL                       
                        168     LOAD_CONST                      4: '__pyarmor_exit_23921__'
                        170     LOAD_CONST                      3: b'<COAddr>\x05\x00\x00\x1ap\x00\x00\x00\x00\x00\x00\x00\x00\x00\x00\x00\x00\x00\x00\x00'
                        172     BUILD_TUPLE                     1
                        174     CALL_FUNCTION_EX                0
                        176     POP_TOP                         
                        178     RETURN_VALUE                    
                    [Exception Table]
                        28 to 118 -> 138 [0] 
                        138 to 160 -> 160 [1] lasti
                [Code]
                    File Name: <frozen multithon.tl.custom.adminlogevent>
                    Object Name: stopped_poll
                    Qualified Name: AdminLogEvent.stopped_poll
                    Arg Count: 1
                    Pos Only Arg Count: 0
                    KW Only Arg Count: 0
                    Stack Size: 5
                    Flags: 0x20000003 (CO_OPTIMIZED | CO_NEWLOCALS | CO_PYARMOR_OBFUSCATED)
                    [Names]
                        'isinstance'
                        'original'
                        'action'
                        'types'
                        'ChannelAdminLogEventActionStopPoll'
                    [Locals+Names]
                        'self'
                        '__assert_armored__'
                    [Constants]
                        '\n        Whether a poll was stopped or not.\n\n        If `True`, `new` will be present as\n        `Message <telethon.tl.custom.message.Message>`.\n        '
                        '__pyarmor_assert_23922__'
                        '__pyarmor_enter_23923__'
                        b'<COAddr>\x05\x00\x00\x1ap\x00\x00\x00\x00\x00\x00\x00\x00\x00\x00\x00\x00\x00\x00\x00'
                        '__pyarmor_exit_23924__'
                    [Disassembly]
                        0       NOP                             
                        2       NOP                             
                        4       PUSH_NULL                       
                        6       LOAD_CONST                      2: '__pyarmor_enter_23923__'
                        8       LOAD_CONST                      3: b'<COAddr>\x05\x00\x00\x1ap\x00\x00\x00\x00\x00\x00\x00\x00\x00\x00\x00\x00\x00\x00\x00'
                        10      BUILD_TUPLE                     1
                        12      CALL_FUNCTION_EX                0
                        14      POP_TOP                         
                        16      RESUME                          0
                        18      NOP                             
                        20      NOP                             
                        22      NOP                             
                        24      NOP                             
                        26      NOP                             
                        28      LOAD_GLOBAL                     1: NULL + isinstance
                        38      LOAD_FAST                       0: self
                        40      LOAD_ATTR                       2: original
                        60      LOAD_ATTR                       4: action
                        80      LOAD_GLOBAL                     6: types
                        90      LOAD_ATTR                       8: ChannelAdminLogEventActionStopPoll
                        110     CALL                            2
                        118     NOP                             
                        120     NOP                             
                        122     NOP                             
                        124     JUMP_FORWARD                    20 (to 166)
                        126     CALL                            1
                        134     POP_TOP                         
                        136     RETURN_VALUE                    
                        138     PUSH_EXC_INFO                   
                        140     PUSH_NULL                       
                        142     LOAD_CONST                      4: '__pyarmor_exit_23924__'
                        144     NOP                             
                        146     LOAD_CONST                      3: b'<COAddr>\x05\x00\x00\x1ap\x00\x00\x00\x00\x00\x00\x00\x00\x00\x00\x00\x00\x00\x00\x00'
                        148     CALL                            1
                        156     POP_TOP                         
                        158     RERAISE                         0
                        160     COPY                            3
                        162     POP_EXCEPT                      
                        164     RERAISE                         1
                        166     PUSH_NULL                       
                        168     LOAD_CONST                      4: '__pyarmor_exit_23924__'
                        170     LOAD_CONST                      3: b'<COAddr>\x05\x00\x00\x1ap\x00\x00\x00\x00\x00\x00\x00\x00\x00\x00\x00\x00\x00\x00\x00'
                        172     BUILD_TUPLE                     1
                        174     CALL_FUNCTION_EX                0
                        176     POP_TOP                         
                        178     RETURN_VALUE                    
                    [Exception Table]
                        28 to 118 -> 138 [0] 
                        138 to 160 -> 160 [1] lasti
                [Code]
                    File Name: <frozen multithon.tl.custom.adminlogevent>
                    Object Name: started_group_call
                    Qualified Name: AdminLogEvent.started_group_call
                    Arg Count: 1
                    Pos Only Arg Count: 0
                    KW Only Arg Count: 0
                    Stack Size: 5
                    Flags: 0x20000003 (CO_OPTIMIZED | CO_NEWLOCALS | CO_PYARMOR_OBFUSCATED)
                    [Names]
                        'isinstance'
                        'original'
                        'action'
                        'types'
                        'ChannelAdminLogEventActionStartGroupCall'
                    [Locals+Names]
                        'self'
                        '__assert_armored__'
                    [Constants]
                        '\n        Whether a group call was started or not.\n\n        If `True`, `new` will be present as :tl:`InputGroupCall`.\n        '
                        '__pyarmor_assert_23925__'
                        '__pyarmor_enter_23926__'
                        b'<COAddr>\x07\x00\x00\x1ap\x00\x00\x00\x00\x00\x00\x00\x00\x00\x00\x00\x00\x00\x00\x00'
                        '__pyarmor_exit_23927__'
                    [Disassembly]
                        0       NOP                             
                        2       NOP                             
                        4       PUSH_NULL                       
                        6       LOAD_CONST                      2: '__pyarmor_enter_23926__'
                        8       LOAD_CONST                      3: b'<COAddr>\x07\x00\x00\x1ap\x00\x00\x00\x00\x00\x00\x00\x00\x00\x00\x00\x00\x00\x00\x00'
                        10      BUILD_TUPLE                     1
                        12      CALL_FUNCTION_EX                0
                        14      POP_TOP                         
                        16      RESUME                          0
                        18      NOP                             
                        20      NOP                             
                        22      NOP                             
                        24      NOP                             
                        26      NOP                             
                        28      LOAD_GLOBAL                     1: NULL + isinstance
                        38      LOAD_FAST                       0: self
                        40      LOAD_ATTR                       2: original
                        60      LOAD_ATTR                       4: action
                        80      LOAD_GLOBAL                     6: types
                        90      LOAD_ATTR                       8: ChannelAdminLogEventActionStartGroupCall
                        110     CALL                            2
                        118     NOP                             
                        120     NOP                             
                        122     NOP                             
                        124     JUMP_FORWARD                    20 (to 166)
                        126     CALL                            1
                        134     POP_TOP                         
                        136     RETURN_VALUE                    
                        138     PUSH_EXC_INFO                   
                        140     PUSH_NULL                       
                        142     LOAD_CONST                      4: '__pyarmor_exit_23927__'
                        144     NOP                             
                        146     LOAD_CONST                      3: b'<COAddr>\x07\x00\x00\x1ap\x00\x00\x00\x00\x00\x00\x00\x00\x00\x00\x00\x00\x00\x00\x00'
                        148     CALL                            1
                        156     POP_TOP                         
                        158     RERAISE                         0
                        160     COPY                            3
                        162     POP_EXCEPT                      
                        164     RERAISE                         1
                        166     PUSH_NULL                       
                        168     LOAD_CONST                      4: '__pyarmor_exit_23927__'
                        170     LOAD_CONST                      3: b'<COAddr>\x07\x00\x00\x1ap\x00\x00\x00\x00\x00\x00\x00\x00\x00\x00\x00\x00\x00\x00\x00'
                        172     BUILD_TUPLE                     1
                        174     CALL_FUNCTION_EX                0
                        176     POP_TOP                         
                        178     RETURN_VALUE                    
                    [Exception Table]
                        28 to 118 -> 138 [0] 
                        138 to 160 -> 160 [1] lasti
                [Code]
                    File Name: <frozen multithon.tl.custom.adminlogevent>
                    Object Name: discarded_group_call
                    Qualified Name: AdminLogEvent.discarded_group_call
                    Arg Count: 1
                    Pos Only Arg Count: 0
                    KW Only Arg Count: 0
                    Stack Size: 5
                    Flags: 0x20000003 (CO_OPTIMIZED | CO_NEWLOCALS | CO_PYARMOR_OBFUSCATED)
                    [Names]
                        'isinstance'
                        'original'
                        'action'
                        'types'
                        'ChannelAdminLogEventActionDiscardGroupCall'
                    [Locals+Names]
                        'self'
                        '__assert_armored__'
                    [Constants]
                        '\n        Whether a group call was started or not.\n\n        If `True`, `old` will be present as :tl:`InputGroupCall`.\n        '
                        '__pyarmor_assert_23928__'
                        '__pyarmor_enter_23929__'
                        b'<COAddr>\x05\x00\x00\x1ap\x00\x00\x00\x00\x00\x00\x00\x00\x00\x00\x00\x00\x00\x00\x00'
                        '__pyarmor_exit_23930__'
                    [Disassembly]
                        0       NOP                             
                        2       NOP                             
                        4       PUSH_NULL                       
                        6       LOAD_CONST                      2: '__pyarmor_enter_23929__'
                        8       LOAD_CONST                      3: b'<COAddr>\x05\x00\x00\x1ap\x00\x00\x00\x00\x00\x00\x00\x00\x00\x00\x00\x00\x00\x00\x00'
                        10      BUILD_TUPLE                     1
                        12      CALL_FUNCTION_EX                0
                        14      POP_TOP                         
                        16      RESUME                          0
                        18      NOP                             
                        20      NOP                             
                        22      NOP                             
                        24      NOP                             
                        26      NOP                             
                        28      LOAD_GLOBAL                     1: NULL + isinstance
                        38      LOAD_FAST                       0: self
                        40      LOAD_ATTR                       2: original
                        60      LOAD_ATTR                       4: action
                        80      LOAD_GLOBAL                     6: types
                        90      LOAD_ATTR                       8: ChannelAdminLogEventActionDiscardGroupCall
                        110     CALL                            2
                        118     NOP                             
                        120     NOP                             
                        122     NOP                             
                        124     JUMP_FORWARD                    20 (to 166)
                        126     CALL                            1
                        134     POP_TOP                         
                        136     RETURN_VALUE                    
                        138     PUSH_EXC_INFO                   
                        140     PUSH_NULL                       
                        142     LOAD_CONST                      4: '__pyarmor_exit_23930__'
                        144     NOP                             
                        146     LOAD_CONST                      3: b'<COAddr>\x05\x00\x00\x1ap\x00\x00\x00\x00\x00\x00\x00\x00\x00\x00\x00\x00\x00\x00\x00'
                        148     CALL                            1
                        156     POP_TOP                         
                        158     RERAISE                         0
                        160     COPY                            3
                        162     POP_EXCEPT                      
                        164     RERAISE                         1
                        166     PUSH_NULL                       
                        168     LOAD_CONST                      4: '__pyarmor_exit_23930__'
                        170     LOAD_CONST                      3: b'<COAddr>\x05\x00\x00\x1ap\x00\x00\x00\x00\x00\x00\x00\x00\x00\x00\x00\x00\x00\x00\x00'
                        172     BUILD_TUPLE                     1
                        174     CALL_FUNCTION_EX                0
                        176     POP_TOP                         
                        178     RETURN_VALUE                    
                    [Exception Table]
                        28 to 118 -> 138 [0] 
                        138 to 160 -> 160 [1] lasti
                [Code]
                    File Name: <frozen multithon.tl.custom.adminlogevent>
                    Object Name: user_muted
                    Qualified Name: AdminLogEvent.user_muted
                    Arg Count: 1
                    Pos Only Arg Count: 0
                    KW Only Arg Count: 0
                    Stack Size: 5
                    Flags: 0x20000003 (CO_OPTIMIZED | CO_NEWLOCALS | CO_PYARMOR_OBFUSCATED)
                    [Names]
                        'isinstance'
                        'original'
                        'action'
                        'types'
                        'ChannelAdminLogEventActionParticipantMute'
                    [Locals+Names]
                        'self'
                        '__assert_armored__'
                    [Constants]
                        '\n        Whether a participant was muted in the ongoing group call or not.\n\n        If `True`, `new` will be present as :tl:`GroupCallParticipant`.\n        '
                        '__pyarmor_assert_23931__'
                        '__pyarmor_enter_23932__'
                        b'<COAddr>\x05\x00\x00\x1ap\x00\x00\x00\x00\x00\x00\x00\x00\x00\x00\x00\x00\x00\x00\x00'
                        '__pyarmor_exit_23933__'
                    [Disassembly]
                        0       NOP                             
                        2       NOP                             
                        4       PUSH_NULL                       
                        6       LOAD_CONST                      2: '__pyarmor_enter_23932__'
                        8       LOAD_CONST                      3: b'<COAddr>\x05\x00\x00\x1ap\x00\x00\x00\x00\x00\x00\x00\x00\x00\x00\x00\x00\x00\x00\x00'
                        10      BUILD_TUPLE                     1
                        12      CALL_FUNCTION_EX                0
                        14      POP_TOP                         
                        16      RESUME                          0
                        18      NOP                             
                        20      NOP                             
                        22      NOP                             
                        24      NOP                             
                        26      NOP                             
                        28      LOAD_GLOBAL                     1: NULL + isinstance
                        38      LOAD_FAST                       0: self
                        40      LOAD_ATTR                       2: original
                        60      LOAD_ATTR                       4: action
                        80      LOAD_GLOBAL                     6: types
                        90      LOAD_ATTR                       8: ChannelAdminLogEventActionParticipantMute
                        110     CALL                            2
                        118     NOP                             
                        120     NOP                             
                        122     NOP                             
                        124     JUMP_FORWARD                    20 (to 166)
                        126     CALL                            1
                        134     POP_TOP                         
                        136     RETURN_VALUE                    
                        138     PUSH_EXC_INFO                   
                        140     PUSH_NULL                       
                        142     LOAD_CONST                      4: '__pyarmor_exit_23933__'
                        144     NOP                             
                        146     LOAD_CONST                      3: b'<COAddr>\x05\x00\x00\x1ap\x00\x00\x00\x00\x00\x00\x00\x00\x00\x00\x00\x00\x00\x00\x00'
                        148     CALL                            1
                        156     POP_TOP                         
                        158     RERAISE                         0
                        160     COPY                            3
                        162     POP_EXCEPT                      
                        164     RERAISE                         1
                        166     PUSH_NULL                       
                        168     LOAD_CONST                      4: '__pyarmor_exit_23933__'
                        170     LOAD_CONST                      3: b'<COAddr>\x05\x00\x00\x1ap\x00\x00\x00\x00\x00\x00\x00\x00\x00\x00\x00\x00\x00\x00\x00'
                        172     BUILD_TUPLE                     1
                        174     CALL_FUNCTION_EX                0
                        176     POP_TOP                         
                        178     RETURN_VALUE                    
                    [Exception Table]
                        28 to 118 -> 138 [0] 
                        138 to 160 -> 160 [1] lasti
                [Code]
                    File Name: <frozen multithon.tl.custom.adminlogevent>
                    Object Name: user_unmutted
                    Qualified Name: AdminLogEvent.user_unmutted
                    Arg Count: 1
                    Pos Only Arg Count: 0
                    KW Only Arg Count: 0
                    Stack Size: 5
                    Flags: 0x20000003 (CO_OPTIMIZED | CO_NEWLOCALS | CO_PYARMOR_OBFUSCATED)
                    [Names]
                        'isinstance'
                        'original'
                        'action'
                        'types'
                        'ChannelAdminLogEventActionParticipantUnmute'
                    [Locals+Names]
                        'self'
                        '__assert_armored__'
                    [Constants]
                        '\n        Whether a participant was unmuted from the ongoing group call or not.\n\n        If `True`, `new` will be present as :tl:`GroupCallParticipant`.\n        '
                        '__pyarmor_assert_23934__'
                        '__pyarmor_enter_23935__'
                        b'<COAddr>\x05\x00\x00\x1ap\x00\x00\x00\x00\x00\x00\x00\x00\x00\x00\x00\x00\x00\x00\x00'
                        '__pyarmor_exit_23936__'
                    [Disassembly]
                        0       NOP                             
                        2       NOP                             
                        4       PUSH_NULL                       
                        6       LOAD_CONST                      2: '__pyarmor_enter_23935__'
                        8       LOAD_CONST                      3: b'<COAddr>\x05\x00\x00\x1ap\x00\x00\x00\x00\x00\x00\x00\x00\x00\x00\x00\x00\x00\x00\x00'
                        10      BUILD_TUPLE                     1
                        12      CALL_FUNCTION_EX                0
                        14      POP_TOP                         
                        16      RESUME                          0
                        18      NOP                             
                        20      NOP                             
                        22      NOP                             
                        24      NOP                             
                        26      NOP                             
                        28      LOAD_GLOBAL                     1: NULL + isinstance
                        38      LOAD_FAST                       0: self
                        40      LOAD_ATTR                       2: original
                        60      LOAD_ATTR                       4: action
                        80      LOAD_GLOBAL                     6: types
                        90      LOAD_ATTR                       8: ChannelAdminLogEventActionParticipantUnmute
                        110     CALL                            2
                        118     NOP                             
                        120     NOP                             
                        122     NOP                             
                        124     JUMP_FORWARD                    20 (to 166)
                        126     CALL                            1
                        134     POP_TOP                         
                        136     RETURN_VALUE                    
                        138     PUSH_EXC_INFO                   
                        140     PUSH_NULL                       
                        142     LOAD_CONST                      4: '__pyarmor_exit_23936__'
                        144     NOP                             
                        146     LOAD_CONST                      3: b'<COAddr>\x05\x00\x00\x1ap\x00\x00\x00\x00\x00\x00\x00\x00\x00\x00\x00\x00\x00\x00\x00'
                        148     CALL                            1
                        156     POP_TOP                         
                        158     RERAISE                         0
                        160     COPY                            3
                        162     POP_EXCEPT                      
                        164     RERAISE                         1
                        166     PUSH_NULL                       
                        168     LOAD_CONST                      4: '__pyarmor_exit_23936__'
                        170     LOAD_CONST                      3: b'<COAddr>\x05\x00\x00\x1ap\x00\x00\x00\x00\x00\x00\x00\x00\x00\x00\x00\x00\x00\x00\x00'
                        172     BUILD_TUPLE                     1
                        174     CALL_FUNCTION_EX                0
                        176     POP_TOP                         
                        178     RETURN_VALUE                    
                    [Exception Table]
                        28 to 118 -> 138 [0] 
                        138 to 160 -> 160 [1] lasti
                [Code]
                    File Name: <frozen multithon.tl.custom.adminlogevent>
                    Object Name: changed_call_settings
                    Qualified Name: AdminLogEvent.changed_call_settings
                    Arg Count: 1
                    Pos Only Arg Count: 0
                    KW Only Arg Count: 0
                    Stack Size: 5
                    Flags: 0x20000003 (CO_OPTIMIZED | CO_NEWLOCALS | CO_PYARMOR_OBFUSCATED)
                    [Names]
                        'isinstance'
                        'original'
                        'action'
                        'types'
                        'ChannelAdminLogEventActionToggleGroupCallSetting'
                    [Locals+Names]
                        'self'
                        '__assert_armored__'
                    [Constants]
                        '\n        Whether the group call settings were changed or not.\n\n        If `True`, `new` will be `True` if new users are muted on join.\n        '
                        '__pyarmor_assert_23937__'
                        '__pyarmor_enter_23938__'
                        b'<COAddr>\x07\x00\x00\x1ap\x00\x00\x00\x00\x00\x00\x00\x00\x00\x00\x00\x00\x00\x00\x00'
                        '__pyarmor_exit_23939__'
                    [Disassembly]
                        0       NOP                             
                        2       NOP                             
                        4       PUSH_NULL                       
                        6       LOAD_CONST                      2: '__pyarmor_enter_23938__'
                        8       LOAD_CONST                      3: b'<COAddr>\x07\x00\x00\x1ap\x00\x00\x00\x00\x00\x00\x00\x00\x00\x00\x00\x00\x00\x00\x00'
                        10      BUILD_TUPLE                     1
                        12      CALL_FUNCTION_EX                0
                        14      POP_TOP                         
                        16      RESUME                          0
                        18      NOP                             
                        20      NOP                             
                        22      NOP                             
                        24      NOP                             
                        26      NOP                             
                        28      LOAD_GLOBAL                     1: NULL + isinstance
                        38      LOAD_FAST                       0: self
                        40      LOAD_ATTR                       2: original
                        60      LOAD_ATTR                       4: action
                        80      LOAD_GLOBAL                     6: types
                        90      LOAD_ATTR                       8: ChannelAdminLogEventActionToggleGroupCallSetting
                        110     CALL                            2
                        118     NOP                             
                        120     NOP                             
                        122     NOP                             
                        124     JUMP_FORWARD                    20 (to 166)
                        126     CALL                            1
                        134     POP_TOP                         
                        136     RETURN_VALUE                    
                        138     PUSH_EXC_INFO                   
                        140     PUSH_NULL                       
                        142     LOAD_CONST                      4: '__pyarmor_exit_23939__'
                        144     NOP                             
                        146     LOAD_CONST                      3: b'<COAddr>\x07\x00\x00\x1ap\x00\x00\x00\x00\x00\x00\x00\x00\x00\x00\x00\x00\x00\x00\x00'
                        148     CALL                            1
                        156     POP_TOP                         
                        158     RERAISE                         0
                        160     COPY                            3
                        162     POP_EXCEPT                      
                        164     RERAISE                         1
                        166     PUSH_NULL                       
                        168     LOAD_CONST                      4: '__pyarmor_exit_23939__'
                        170     LOAD_CONST                      3: b'<COAddr>\x07\x00\x00\x1ap\x00\x00\x00\x00\x00\x00\x00\x00\x00\x00\x00\x00\x00\x00\x00'
                        172     BUILD_TUPLE                     1
                        174     CALL_FUNCTION_EX                0
                        176     POP_TOP                         
                        178     RETURN_VALUE                    
                    [Exception Table]
                        28 to 118 -> 138 [0] 
                        138 to 160 -> 160 [1] lasti
                [Code]
                    File Name: <frozen multithon.tl.custom.adminlogevent>
                    Object Name: changed_history_ttl
                    Qualified Name: AdminLogEvent.changed_history_ttl
                    Arg Count: 1
                    Pos Only Arg Count: 0
                    KW Only Arg Count: 0
                    Stack Size: 5
                    Flags: 0x20000003 (CO_OPTIMIZED | CO_NEWLOCALS | CO_PYARMOR_OBFUSCATED)
                    [Names]
                        'isinstance'
                        'original'
                        'action'
                        'types'
                        'ChannelAdminLogEventActionChangeHistoryTTL'
                    [Locals+Names]
                        'self'
                        '__assert_armored__'
                    [Constants]
                        '\n        Whether the Time To Live of the message history has changed.\n\n        Messages sent after this change will have a ``ttl_period`` in seconds\n        indicating how long they should live for before being auto-deleted.\n\n        If `True`, `old` will be the old TTL, and `new` the new TTL, in seconds.\n        '
                        '__pyarmor_assert_23940__'
                        '__pyarmor_enter_23941__'
                        b'<COAddr>\x05\x00\x00\x1ap\x00\x00\x00\x00\x00\x00\x00\x00\x00\x00\x00\x00\x00\x00\x00'
                        '__pyarmor_exit_23942__'
                    [Disassembly]
                        0       NOP                             
                        2       NOP                             
                        4       PUSH_NULL                       
                        6       LOAD_CONST                      2: '__pyarmor_enter_23941__'
                        8       LOAD_CONST                      3: b'<COAddr>\x05\x00\x00\x1ap\x00\x00\x00\x00\x00\x00\x00\x00\x00\x00\x00\x00\x00\x00\x00'
                        10      BUILD_TUPLE                     1
                        12      CALL_FUNCTION_EX                0
                        14      POP_TOP                         
                        16      RESUME                          0
                        18      NOP                             
                        20      NOP                             
                        22      NOP                             
                        24      NOP                             
                        26      NOP                             
                        28      LOAD_GLOBAL                     1: NULL + isinstance
                        38      LOAD_FAST                       0: self
                        40      LOAD_ATTR                       2: original
                        60      LOAD_ATTR                       4: action
                        80      LOAD_GLOBAL                     6: types
                        90      LOAD_ATTR                       8: ChannelAdminLogEventActionChangeHistoryTTL
                        110     CALL                            2
                        118     NOP                             
                        120     NOP                             
                        122     NOP                             
                        124     JUMP_FORWARD                    20 (to 166)
                        126     CALL                            1
                        134     POP_TOP                         
                        136     RETURN_VALUE                    
                        138     PUSH_EXC_INFO                   
                        140     PUSH_NULL                       
                        142     LOAD_CONST                      4: '__pyarmor_exit_23942__'
                        144     NOP                             
                        146     LOAD_CONST                      3: b'<COAddr>\x05\x00\x00\x1ap\x00\x00\x00\x00\x00\x00\x00\x00\x00\x00\x00\x00\x00\x00\x00'
                        148     CALL                            1
                        156     POP_TOP                         
                        158     RERAISE                         0
                        160     COPY                            3
                        162     POP_EXCEPT                      
                        164     RERAISE                         1
                        166     PUSH_NULL                       
                        168     LOAD_CONST                      4: '__pyarmor_exit_23942__'
                        170     LOAD_CONST                      3: b'<COAddr>\x05\x00\x00\x1ap\x00\x00\x00\x00\x00\x00\x00\x00\x00\x00\x00\x00\x00\x00\x00'
                        172     BUILD_TUPLE                     1
                        174     CALL_FUNCTION_EX                0
                        176     POP_TOP                         
                        178     RETURN_VALUE                    
                    [Exception Table]
                        28 to 118 -> 138 [0] 
                        138 to 160 -> 160 [1] lasti
                [Code]
                    File Name: <frozen multithon.tl.custom.adminlogevent>
                    Object Name: deleted_exported_invite
                    Qualified Name: AdminLogEvent.deleted_exported_invite
                    Arg Count: 1
                    Pos Only Arg Count: 0
                    KW Only Arg Count: 0
                    Stack Size: 5
                    Flags: 0x20000003 (CO_OPTIMIZED | CO_NEWLOCALS | CO_PYARMOR_OBFUSCATED)
                    [Names]
                        'isinstance'
                        'original'
                        'action'
                        'types'
                        'ChannelAdminLogEventActionExportedInviteDelete'
                    [Locals+Names]
                        'self'
                        '__assert_armored__'
                    [Constants]
                        '\n        Whether the exported chat invite has been deleted.\n\n        If `True`, `old` will be the deleted :tl:`ExportedChatInvite`.\n        '
                        '__pyarmor_assert_23943__'
                        '__pyarmor_enter_23944__'
                        b'<COAddr>\x05\x00\x00\x1ap\x00\x00\x00\x00\x00\x00\x00\x00\x00\x00\x00\x00\x00\x00\x00'
                        '__pyarmor_exit_23945__'
                    [Disassembly]
                        0       NOP                             
                        2       NOP                             
                        4       PUSH_NULL                       
                        6       LOAD_CONST                      2: '__pyarmor_enter_23944__'
                        8       LOAD_CONST                      3: b'<COAddr>\x05\x00\x00\x1ap\x00\x00\x00\x00\x00\x00\x00\x00\x00\x00\x00\x00\x00\x00\x00'
                        10      BUILD_TUPLE                     1
                        12      CALL_FUNCTION_EX                0
                        14      POP_TOP                         
                        16      RESUME                          0
                        18      NOP                             
                        20      NOP                             
                        22      NOP                             
                        24      NOP                             
                        26      NOP                             
                        28      LOAD_GLOBAL                     1: NULL + isinstance
                        38      LOAD_FAST                       0: self
                        40      LOAD_ATTR                       2: original
                        60      LOAD_ATTR                       4: action
                        80      LOAD_GLOBAL                     6: types
                        90      LOAD_ATTR                       8: ChannelAdminLogEventActionExportedInviteDelete
                        110     CALL                            2
                        118     NOP                             
                        120     NOP                             
                        122     NOP                             
                        124     JUMP_FORWARD                    20 (to 166)
                        126     CALL                            1
                        134     POP_TOP                         
                        136     RETURN_VALUE                    
                        138     PUSH_EXC_INFO                   
                        140     PUSH_NULL                       
                        142     LOAD_CONST                      4: '__pyarmor_exit_23945__'
                        144     NOP                             
                        146     LOAD_CONST                      3: b'<COAddr>\x05\x00\x00\x1ap\x00\x00\x00\x00\x00\x00\x00\x00\x00\x00\x00\x00\x00\x00\x00'
                        148     CALL                            1
                        156     POP_TOP                         
                        158     RERAISE                         0
                        160     COPY                            3
                        162     POP_EXCEPT                      
                        164     RERAISE                         1
                        166     PUSH_NULL                       
                        168     LOAD_CONST                      4: '__pyarmor_exit_23945__'
                        170     LOAD_CONST                      3: b'<COAddr>\x05\x00\x00\x1ap\x00\x00\x00\x00\x00\x00\x00\x00\x00\x00\x00\x00\x00\x00\x00'
                        172     BUILD_TUPLE                     1
                        174     CALL_FUNCTION_EX                0
                        176     POP_TOP                         
                        178     RETURN_VALUE                    
                    [Exception Table]
                        28 to 118 -> 138 [0] 
                        138 to 160 -> 160 [1] lasti
                [Code]
                    File Name: <frozen multithon.tl.custom.adminlogevent>
                    Object Name: edited_exported_invite
                    Qualified Name: AdminLogEvent.edited_exported_invite
                    Arg Count: 1
                    Pos Only Arg Count: 0
                    KW Only Arg Count: 0
                    Stack Size: 5
                    Flags: 0x20000003 (CO_OPTIMIZED | CO_NEWLOCALS | CO_PYARMOR_OBFUSCATED)
                    [Names]
                        'isinstance'
                        'original'
                        'action'
                        'types'
                        'ChannelAdminLogEventActionExportedInviteEdit'
                    [Locals+Names]
                        'self'
                        '__assert_armored__'
                    [Constants]
                        '\n        Whether the exported chat invite has been edited.\n\n        If `True`, `old` and `new` will be the old and new\n        :tl:`ExportedChatInvite`, respectively.\n        '
                        '__pyarmor_assert_23946__'
                        '__pyarmor_enter_23947__'
                        b'<COAddr>\x05\x00\x00\x1ap\x00\x00\x00\x00\x00\x00\x00\x00\x00\x00\x00\x00\x00\x00\x00'
                        '__pyarmor_exit_23948__'
                    [Disassembly]
                        0       NOP                             
                        2       NOP                             
                        4       PUSH_NULL                       
                        6       LOAD_CONST                      2: '__pyarmor_enter_23947__'
                        8       LOAD_CONST                      3: b'<COAddr>\x05\x00\x00\x1ap\x00\x00\x00\x00\x00\x00\x00\x00\x00\x00\x00\x00\x00\x00\x00'
                        10      BUILD_TUPLE                     1
                        12      CALL_FUNCTION_EX                0
                        14      POP_TOP                         
                        16      RESUME                          0
                        18      NOP                             
                        20      NOP                             
                        22      NOP                             
                        24      NOP                             
                        26      NOP                             
                        28      LOAD_GLOBAL                     1: NULL + isinstance
                        38      LOAD_FAST                       0: self
                        40      LOAD_ATTR                       2: original
                        60      LOAD_ATTR                       4: action
                        80      LOAD_GLOBAL                     6: types
                        90      LOAD_ATTR                       8: ChannelAdminLogEventActionExportedInviteEdit
                        110     CALL                            2
                        118     NOP                             
                        120     NOP                             
                        122     NOP                             
                        124     JUMP_FORWARD                    20 (to 166)
                        126     CALL                            1
                        134     POP_TOP                         
                        136     RETURN_VALUE                    
                        138     PUSH_EXC_INFO                   
                        140     PUSH_NULL                       
                        142     LOAD_CONST                      4: '__pyarmor_exit_23948__'
                        144     NOP                             
                        146     LOAD_CONST                      3: b'<COAddr>\x05\x00\x00\x1ap\x00\x00\x00\x00\x00\x00\x00\x00\x00\x00\x00\x00\x00\x00\x00'
                        148     CALL                            1
                        156     POP_TOP                         
                        158     RERAISE                         0
                        160     COPY                            3
                        162     POP_EXCEPT                      
                        164     RERAISE                         1
                        166     PUSH_NULL                       
                        168     LOAD_CONST                      4: '__pyarmor_exit_23948__'
                        170     LOAD_CONST                      3: b'<COAddr>\x05\x00\x00\x1ap\x00\x00\x00\x00\x00\x00\x00\x00\x00\x00\x00\x00\x00\x00\x00'
                        172     BUILD_TUPLE                     1
                        174     CALL_FUNCTION_EX                0
                        176     POP_TOP                         
                        178     RETURN_VALUE                    
                    [Exception Table]
                        28 to 118 -> 138 [0] 
                        138 to 160 -> 160 [1] lasti
                [Code]
                    File Name: <frozen multithon.tl.custom.adminlogevent>
                    Object Name: revoked_exported_invite
                    Qualified Name: AdminLogEvent.revoked_exported_invite
                    Arg Count: 1
                    Pos Only Arg Count: 0
                    KW Only Arg Count: 0
                    Stack Size: 5
                    Flags: 0x20000003 (CO_OPTIMIZED | CO_NEWLOCALS | CO_PYARMOR_OBFUSCATED)
                    [Names]
                        'isinstance'
                        'original'
                        'action'
                        'types'
                        'ChannelAdminLogEventActionExportedInviteRevoke'
                    [Locals+Names]
                        'self'
                        '__assert_armored__'
                    [Constants]
                        '\n        Whether the exported chat invite has been revoked.\n\n        If `True`, `old` will be the revoked :tl:`ExportedChatInvite`.\n        '
                        '__pyarmor_assert_23949__'
                        '__pyarmor_enter_23950__'
                        b'<COAddr>\x07\x00\x00\x1ap\x00\x00\x00\x00\x00\x00\x00\x00\x00\x00\x00\x00\x00\x00\x00'
                        '__pyarmor_exit_23951__'
                    [Disassembly]
                        0       NOP                             
                        2       NOP                             
                        4       PUSH_NULL                       
                        6       LOAD_CONST                      2: '__pyarmor_enter_23950__'
                        8       LOAD_CONST                      3: b'<COAddr>\x07\x00\x00\x1ap\x00\x00\x00\x00\x00\x00\x00\x00\x00\x00\x00\x00\x00\x00\x00'
                        10      BUILD_TUPLE                     1
                        12      CALL_FUNCTION_EX                0
                        14      POP_TOP                         
                        16      RESUME                          0
                        18      NOP                             
                        20      NOP                             
                        22      NOP                             
                        24      NOP                             
                        26      NOP                             
                        28      LOAD_GLOBAL                     1: NULL + isinstance
                        38      LOAD_FAST                       0: self
                        40      LOAD_ATTR                       2: original
                        60      LOAD_ATTR                       4: action
                        80      LOAD_GLOBAL                     6: types
                        90      LOAD_ATTR                       8: ChannelAdminLogEventActionExportedInviteRevoke
                        110     CALL                            2
                        118     NOP                             
                        120     NOP                             
                        122     NOP                             
                        124     JUMP_FORWARD                    20 (to 166)
                        126     CALL                            1
                        134     POP_TOP                         
                        136     RETURN_VALUE                    
                        138     PUSH_EXC_INFO                   
                        140     PUSH_NULL                       
                        142     LOAD_CONST                      4: '__pyarmor_exit_23951__'
                        144     NOP                             
                        146     LOAD_CONST                      3: b'<COAddr>\x07\x00\x00\x1ap\x00\x00\x00\x00\x00\x00\x00\x00\x00\x00\x00\x00\x00\x00\x00'
                        148     CALL                            1
                        156     POP_TOP                         
                        158     RERAISE                         0
                        160     COPY                            3
                        162     POP_EXCEPT                      
                        164     RERAISE                         1
                        166     PUSH_NULL                       
                        168     LOAD_CONST                      4: '__pyarmor_exit_23951__'
                        170     LOAD_CONST                      3: b'<COAddr>\x07\x00\x00\x1ap\x00\x00\x00\x00\x00\x00\x00\x00\x00\x00\x00\x00\x00\x00\x00'
                        172     BUILD_TUPLE                     1
                        174     CALL_FUNCTION_EX                0
                        176     POP_TOP                         
                        178     RETURN_VALUE                    
                    [Exception Table]
                        28 to 118 -> 138 [0] 
                        138 to 160 -> 160 [1] lasti
                [Code]
                    File Name: <frozen multithon.tl.custom.adminlogevent>
                    Object Name: joined_by_invite
                    Qualified Name: AdminLogEvent.joined_by_invite
                    Arg Count: 1
                    Pos Only Arg Count: 0
                    KW Only Arg Count: 0
                    Stack Size: 5
                    Flags: 0x20000003 (CO_OPTIMIZED | CO_NEWLOCALS | CO_PYARMOR_OBFUSCATED)
                    [Names]
                        'isinstance'
                        'original'
                        'action'
                        'types'
                        'ChannelAdminLogEventActionParticipantJoinByInvite'
                    [Locals+Names]
                        'self'
                        '__assert_armored__'
                    [Constants]
                        '\n        Whether a new participant has joined with the use of an invite link.\n\n        If `True`, `old` will be pre-existing (old) :tl:`ExportedChatInvite`\n        used to join.\n        '
                        '__pyarmor_assert_23952__'
                        '__pyarmor_enter_23953__'
                        b'<COAddr>\x05\x00\x00\x1ap\x00\x00\x00\x00\x00\x00\x00\x00\x00\x00\x00\x00\x00\x00\x00'
                        '__pyarmor_exit_23954__'
                    [Disassembly]
                        0       NOP                             
                        2       NOP                             
                        4       PUSH_NULL                       
                        6       LOAD_CONST                      2: '__pyarmor_enter_23953__'
                        8       LOAD_CONST                      3: b'<COAddr>\x05\x00\x00\x1ap\x00\x00\x00\x00\x00\x00\x00\x00\x00\x00\x00\x00\x00\x00\x00'
                        10      BUILD_TUPLE                     1
                        12      CALL_FUNCTION_EX                0
                        14      POP_TOP                         
                        16      RESUME                          0
                        18      NOP                             
                        20      NOP                             
                        22      NOP                             
                        24      NOP                             
                        26      NOP                             
                        28      LOAD_GLOBAL                     1: NULL + isinstance
                        38      LOAD_FAST                       0: self
                        40      LOAD_ATTR                       2: original
                        60      LOAD_ATTR                       4: action
                        80      LOAD_GLOBAL                     6: types
                        90      LOAD_ATTR                       8: ChannelAdminLogEventActionParticipantJoinByInvite
                        110     CALL                            2
                        118     NOP                             
                        120     NOP                             
                        122     NOP                             
                        124     JUMP_FORWARD                    20 (to 166)
                        126     CALL                            1
                        134     POP_TOP                         
                        136     RETURN_VALUE                    
                        138     PUSH_EXC_INFO                   
                        140     PUSH_NULL                       
                        142     LOAD_CONST                      4: '__pyarmor_exit_23954__'
                        144     NOP                             
                        146     LOAD_CONST                      3: b'<COAddr>\x05\x00\x00\x1ap\x00\x00\x00\x00\x00\x00\x00\x00\x00\x00\x00\x00\x00\x00\x00'
                        148     CALL                            1
                        156     POP_TOP                         
                        158     RERAISE                         0
                        160     COPY                            3
                        162     POP_EXCEPT                      
                        164     RERAISE                         1
                        166     PUSH_NULL                       
                        168     LOAD_CONST                      4: '__pyarmor_exit_23954__'
                        170     LOAD_CONST                      3: b'<COAddr>\x05\x00\x00\x1ap\x00\x00\x00\x00\x00\x00\x00\x00\x00\x00\x00\x00\x00\x00\x00'
                        172     BUILD_TUPLE                     1
                        174     CALL_FUNCTION_EX                0
                        176     POP_TOP                         
                        178     RETURN_VALUE                    
                    [Exception Table]
                        28 to 118 -> 138 [0] 
                        138 to 160 -> 160 [1] lasti
                [Code]
                    File Name: <frozen multithon.tl.custom.adminlogevent>
                    Object Name: changed_user_volume
                    Qualified Name: AdminLogEvent.changed_user_volume
                    Arg Count: 1
                    Pos Only Arg Count: 0
                    KW Only Arg Count: 0
                    Stack Size: 5
                    Flags: 0x20000003 (CO_OPTIMIZED | CO_NEWLOCALS | CO_PYARMOR_OBFUSCATED)
                    [Names]
                        'isinstance'
                        'original'
                        'action'
                        'types'
                        'ChannelAdminLogEventActionParticipantVolume'
                    [Locals+Names]
                        'self'
                        '__assert_armored__'
                    [Constants]
                        "\n        Whether a participant's volume in a call has been changed.\n\n        If `True`, `new` will be the updated :tl:`GroupCallParticipant`.\n        "
                        '__pyarmor_assert_23955__'
                        '__pyarmor_enter_23956__'
                        b'<COAddr>\x05\x00\x00\x1ap\x00\x00\x00\x00\x00\x00\x00\x00\x00\x00\x00\x00\x00\x00\x00'
                        '__pyarmor_exit_23957__'
                    [Disassembly]
                        0       NOP                             
                        2       NOP                             
                        4       PUSH_NULL                       
                        6       LOAD_CONST                      2: '__pyarmor_enter_23956__'
                        8       LOAD_CONST                      3: b'<COAddr>\x05\x00\x00\x1ap\x00\x00\x00\x00\x00\x00\x00\x00\x00\x00\x00\x00\x00\x00\x00'
                        10      BUILD_TUPLE                     1
                        12      CALL_FUNCTION_EX                0
                        14      POP_TOP                         
                        16      RESUME                          0
                        18      NOP                             
                        20      NOP                             
                        22      NOP                             
                        24      NOP                             
                        26      NOP                             
                        28      LOAD_GLOBAL                     1: NULL + isinstance
                        38      LOAD_FAST                       0: self
                        40      LOAD_ATTR                       2: original
                        60      LOAD_ATTR                       4: action
                        80      LOAD_GLOBAL                     6: types
                        90      LOAD_ATTR                       8: ChannelAdminLogEventActionParticipantVolume
                        110     CALL                            2
                        118     NOP                             
                        120     NOP                             
                        122     NOP                             
                        124     JUMP_FORWARD                    20 (to 166)
                        126     CALL                            1
                        134     POP_TOP                         
                        136     RETURN_VALUE                    
                        138     PUSH_EXC_INFO                   
                        140     PUSH_NULL                       
                        142     LOAD_CONST                      4: '__pyarmor_exit_23957__'
                        144     NOP                             
                        146     LOAD_CONST                      3: b'<COAddr>\x05\x00\x00\x1ap\x00\x00\x00\x00\x00\x00\x00\x00\x00\x00\x00\x00\x00\x00\x00'
                        148     CALL                            1
                        156     POP_TOP                         
                        158     RERAISE                         0
                        160     COPY                            3
                        162     POP_EXCEPT                      
                        164     RERAISE                         1
                        166     PUSH_NULL                       
                        168     LOAD_CONST                      4: '__pyarmor_exit_23957__'
                        170     LOAD_CONST                      3: b'<COAddr>\x05\x00\x00\x1ap\x00\x00\x00\x00\x00\x00\x00\x00\x00\x00\x00\x00\x00\x00\x00'
                        172     BUILD_TUPLE                     1
                        174     CALL_FUNCTION_EX                0
                        176     POP_TOP                         
                        178     RETURN_VALUE                    
                    [Exception Table]
                        28 to 118 -> 138 [0] 
                        138 to 160 -> 160 [1] lasti
                [Code]
                    File Name: <frozen multithon.tl.custom.adminlogevent>
                    Object Name: __str__
                    Qualified Name: AdminLogEvent.__str__
                    Arg Count: 1
                    Pos Only Arg Count: 0
                    KW Only Arg Count: 0
                    Stack Size: 5
                    Flags: 0x20000003 (CO_OPTIMIZED | CO_NEWLOCALS | CO_PYARMOR_OBFUSCATED)
                    [Names]
                        'str'
                        'original'
                    [Locals+Names]
                        'self'
                        '__assert_armored__'
                    [Constants]
                        None
                        '__pyarmor_assert_23958__'
                        '__pyarmor_enter_23959__'
                        b'<COAddr>\x05\x00\x00\x1a>\x00\x00\x00\x00\x00\x00\x00\x00\x00\x00\x00\x00\x00\x00\x00'
                        '__pyarmor_exit_23960__'
                    [Disassembly]
                        0       NOP                             
                        2       NOP                             
                        4       PUSH_NULL                       
                        6       LOAD_CONST                      2: '__pyarmor_enter_23959__'
                        8       LOAD_CONST                      3: b'<COAddr>\x05\x00\x00\x1a>\x00\x00\x00\x00\x00\x00\x00\x00\x00\x00\x00\x00\x00\x00\x00'
                        10      BUILD_TUPLE                     1
                        12      CALL_FUNCTION_EX                0
                        14      POP_TOP                         
                        16      RESUME                          0
                        18      NOP                             
                        20      NOP                             
                        22      NOP                             
                        24      NOP                             
                        26      NOP                             
                        28      LOAD_GLOBAL                     1: NULL + str
                        38      LOAD_FAST                       0: self
                        40      LOAD_ATTR                       2: original
                        60      CALL                            1
                        68      NOP                             
                        70      NOP                             
                        72      NOP                             
                        74      JUMP_FORWARD                    20 (to 116)
                        76      CALL                            1
                        84      POP_TOP                         
                        86      RETURN_VALUE                    
                        88      PUSH_EXC_INFO                   
                        90      PUSH_NULL                       
                        92      LOAD_CONST                      4: '__pyarmor_exit_23960__'
                        94      NOP                             
                        96      LOAD_CONST                      3: b'<COAddr>\x05\x00\x00\x1a>\x00\x00\x00\x00\x00\x00\x00\x00\x00\x00\x00\x00\x00\x00\x00'
                        98      CALL                            1
                        106     POP_TOP                         
                        108     RERAISE                         0
                        110     COPY                            3
                        112     POP_EXCEPT                      
                        114     RERAISE                         1
                        116     PUSH_NULL                       
                        118     LOAD_CONST                      4: '__pyarmor_exit_23960__'
                        120     LOAD_CONST                      3: b'<COAddr>\x05\x00\x00\x1a>\x00\x00\x00\x00\x00\x00\x00\x00\x00\x00\x00\x00\x00\x00\x00'
                        122     BUILD_TUPLE                     1
                        124     CALL_FUNCTION_EX                0
                        126     POP_TOP                         
                        128     RETURN_VALUE                    
                    [Exception Table]
                        28 to 68 -> 88 [0] 
                        88 to 110 -> 110 [1] lasti
                [Code]
                    File Name: <frozen multithon.tl.custom.adminlogevent>
                    Object Name: stringify
                    Qualified Name: AdminLogEvent.stringify
                    Arg Count: 1
                    Pos Only Arg Count: 0
                    KW Only Arg Count: 0
                    Stack Size: 5
                    Flags: 0x20000003 (CO_OPTIMIZED | CO_NEWLOCALS | CO_PYARMOR_OBFUSCATED)
                    [Names]
                        'original'
                        'stringify'
                    [Locals+Names]
                        'self'
                        '__assert_armored__'
                    [Constants]
                        None
                        '__pyarmor_assert_23961__'
                        '__pyarmor_enter_23962__'
                        b'<COAddr>\x05\x00\x00\x1aH\x00\x00\x00\x00\x00\x00\x00\x00\x00\x00\x00\x00\x00\x00\x00'
                        '__pyarmor_exit_23963__'
                    [Disassembly]
                        0       NOP                             
                        2       NOP                             
                        4       PUSH_NULL                       
                        6       LOAD_CONST                      2: '__pyarmor_enter_23962__'
                        8       LOAD_CONST                      3: b'<COAddr>\x05\x00\x00\x1aH\x00\x00\x00\x00\x00\x00\x00\x00\x00\x00\x00\x00\x00\x00\x00'
                        10      BUILD_TUPLE                     1
                        12      CALL_FUNCTION_EX                0
                        14      POP_TOP                         
                        16      RESUME                          0
                        18      NOP                             
                        20      NOP                             
                        22      NOP                             
                        24      NOP                             
                        26      NOP                             
                        28      LOAD_FAST                       0: self
                        30      LOAD_ATTR                       0: original
                        50      LOAD_ATTR                       3: stringify
                        70      CALL                            0
                        78      NOP                             
                        80      NOP                             
                        82      NOP                             
                        84      JUMP_FORWARD                    20 (to 126)
                        86      CALL                            1
                        94      POP_TOP                         
                        96      RETURN_VALUE                    
                        98      PUSH_EXC_INFO                   
                        100     PUSH_NULL                       
                        102     LOAD_CONST                      4: '__pyarmor_exit_23963__'
                        104     NOP                             
                        106     LOAD_CONST                      3: b'<COAddr>\x05\x00\x00\x1aH\x00\x00\x00\x00\x00\x00\x00\x00\x00\x00\x00\x00\x00\x00\x00'
                        108     CALL                            1
                        116     POP_TOP                         
                        118     RERAISE                         0
                        120     COPY                            3
                        122     POP_EXCEPT                      
                        124     RERAISE                         1
                        126     PUSH_NULL                       
                        128     LOAD_CONST                      4: '__pyarmor_exit_23963__'
                        130     LOAD_CONST                      3: b'<COAddr>\x05\x00\x00\x1aH\x00\x00\x00\x00\x00\x00\x00\x00\x00\x00\x00\x00\x00\x00\x00'
                        132     BUILD_TUPLE                     1
                        134     CALL_FUNCTION_EX                0
                        136     POP_TOP                         
                        138     RETURN_VALUE                    
                    [Exception Table]
                        28 to 78 -> 98 [0] 
                        98 to 120 -> 120 [1] lasti
                '__pyarmor_exit_23846__'
                None
            [Disassembly]
                0       NOP                             
                2       LOAD_NAME                       0: __name__
                4       STORE_NAME                      1: __module__
                6       LOAD_CONST                      0: 'AdminLogEvent'
                8       STORE_NAME                      2: __qualname__
                10      LOAD_CONST                      1: '\n    Represents a more friendly interface for admin log events.\n\n    Members:\n        original (:tl:`ChannelAdminLogEvent`):\n            The original :tl:`ChannelAdminLogEvent`.\n\n        entities (`dict`):\n            A dictionary mapping user IDs to :tl:`User`.\n\n            When `old` and `new` are :tl:`ChannelParticipant`, you can\n            use this dictionary to map the ``user_id``, ``kicked_by``,\n            ``inviter_id`` and ``promoted_by`` IDs to their :tl:`User`.\n\n        user (:tl:`User`):\n            The user that caused this action (``entities[original.user_id]``).\n\n        input_user (:tl:`InputPeerUser`):\n            Input variant of `user`.\n    '
                12      STORE_NAME                      3: __doc__
                14      NOP                             
                16      PUSH_NULL                       
                18      LOAD_CONST                      3: '__pyarmor_enter_23845__'
                20      LOAD_CONST                      4: b'<COAddr>\x07\x00\x00&h\x02\x00\x00\x00\x00\x00\x00\x00\x00\x00\x00\x00\x00\x00\x00'
                22      BUILD_TUPLE                     1
                24      CALL_FUNCTION_EX                0
                26      POP_TOP                         
                28      RESUME                          0
                30      NOP                             
                32      NOP                             
                34      NOP                             
                36      NOP                             
                38      NOP                             
                40      LOAD_CONST                      5: <CODE> __init__
                42      MAKE_FUNCTION                   0
                44      STORE_NAME                      5: __init__
                46      LOAD_NAME                       6: property
                48      LOAD_CONST                      6: <CODE> id
                50      MAKE_FUNCTION                   0
                52      CALL                            0
                60      STORE_NAME                      7: id
                62      LOAD_NAME                       6: property
                64      LOAD_CONST                      7: <CODE> date
                66      MAKE_FUNCTION                   0
                68      CALL                            0
                76      STORE_NAME                      8: date
                78      LOAD_NAME                       6: property
                80      LOAD_CONST                      8: <CODE> user_id
                82      MAKE_FUNCTION                   0
                84      CALL                            0
                92      STORE_NAME                      9: user_id
                94      LOAD_NAME                       6: property
                96      LOAD_CONST                      9: <CODE> action
                98      MAKE_FUNCTION                   0
                100     CALL                            0
                108     STORE_NAME                      10: action
                110     LOAD_NAME                       6: property
                112     LOAD_CONST                      10: <CODE> old
                114     MAKE_FUNCTION                   0
                116     CALL                            0
                124     STORE_NAME                      11: old
                126     LOAD_NAME                       6: property
                128     LOAD_CONST                      11: <CODE> new
                130     MAKE_FUNCTION                   0
                132     CALL                            0
                140     STORE_NAME                      12: new
                142     LOAD_NAME                       6: property
                144     LOAD_CONST                      12: <CODE> changed_about
                146     MAKE_FUNCTION                   0
                148     CALL                            0
                156     STORE_NAME                      13: changed_about
                158     LOAD_NAME                       6: property
                160     LOAD_CONST                      13: <CODE> changed_title
                162     MAKE_FUNCTION                   0
                164     CALL                            0
                172     STORE_NAME                      14: changed_title
                174     LOAD_NAME                       6: property
                176     LOAD_CONST                      14: <CODE> changed_username
                178     MAKE_FUNCTION                   0
                180     CALL                            0
                188     STORE_NAME                      15: changed_username
                190     LOAD_NAME                       6: property
                192     LOAD_CONST                      15: <CODE> changed_photo
                194     MAKE_FUNCTION                   0
                196     CALL                            0
                204     STORE_NAME                      16: changed_photo
                206     LOAD_NAME                       6: property
                208     LOAD_CONST                      16: <CODE> changed_sticker_set
                210     MAKE_FUNCTION                   0
                212     CALL                            0
                220     STORE_NAME                      17: changed_sticker_set
                222     LOAD_NAME                       6: property
                224     LOAD_CONST                      17: <CODE> changed_message
                226     MAKE_FUNCTION                   0
                228     CALL                            0
                236     STORE_NAME                      18: changed_message
                238     LOAD_NAME                       6: property
                240     LOAD_CONST                      18: <CODE> deleted_message
                242     MAKE_FUNCTION                   0
                244     CALL                            0
                252     STORE_NAME                      19: deleted_message
                254     LOAD_NAME                       6: property
                256     LOAD_CONST                      19: <CODE> changed_admin
                258     MAKE_FUNCTION                   0
                260     CALL                            0
                268     STORE_NAME                      20: changed_admin
                270     LOAD_NAME                       6: property
                272     LOAD_CONST                      20: <CODE> changed_restrictions
                274     MAKE_FUNCTION                   0
                276     CALL                            0
                284     STORE_NAME                      21: changed_restrictions
                286     LOAD_NAME                       6: property
                288     LOAD_CONST                      21: <CODE> changed_invites
                290     MAKE_FUNCTION                   0
                292     CALL                            0
                300     STORE_NAME                      22: changed_invites
                302     LOAD_NAME                       6: property
                304     LOAD_CONST                      22: <CODE> changed_location
                306     MAKE_FUNCTION                   0
                308     CALL                            0
                316     STORE_NAME                      23: changed_location
                318     LOAD_NAME                       6: property
                320     LOAD_CONST                      23: <CODE> joined
                322     MAKE_FUNCTION                   0
                324     CALL                            0
                332     STORE_NAME                      24: joined
                334     LOAD_NAME                       6: property
                336     LOAD_CONST                      24: <CODE> joined_invite
                338     MAKE_FUNCTION                   0
                340     CALL                            0
                348     STORE_NAME                      25: joined_invite
                350     LOAD_NAME                       6: property
                352     LOAD_CONST                      25: <CODE> left
                354     MAKE_FUNCTION                   0
                356     CALL                            0
                364     STORE_NAME                      26: left
                366     LOAD_NAME                       6: property
                368     LOAD_CONST                      26: <CODE> changed_hide_history
                370     MAKE_FUNCTION                   0
                372     CALL                            0
                380     STORE_NAME                      27: changed_hide_history
                382     LOAD_NAME                       6: property
                384     LOAD_CONST                      27: <CODE> changed_signatures
                386     MAKE_FUNCTION                   0
                388     CALL                            0
                396     STORE_NAME                      28: changed_signatures
                398     LOAD_NAME                       6: property
                400     LOAD_CONST                      28: <CODE> changed_pin
                402     MAKE_FUNCTION                   0
                404     CALL                            0
                412     STORE_NAME                      29: changed_pin
                414     LOAD_NAME                       6: property
                416     LOAD_CONST                      29: <CODE> changed_default_banned_rights
                418     MAKE_FUNCTION                   0
                420     CALL                            0
                428     STORE_NAME                      30: changed_default_banned_rights
                430     LOAD_NAME                       6: property
                432     LOAD_CONST                      30: <CODE> stopped_poll
                434     MAKE_FUNCTION                   0
                436     CALL                            0
                444     STORE_NAME                      31: stopped_poll
                446     LOAD_NAME                       6: property
                448     LOAD_CONST                      31: <CODE> started_group_call
                450     MAKE_FUNCTION                   0
                452     CALL                            0
                460     STORE_NAME                      32: started_group_call
                462     LOAD_NAME                       6: property
                464     LOAD_CONST                      32: <CODE> discarded_group_call
                466     MAKE_FUNCTION                   0
                468     CALL                            0
                476     STORE_NAME                      33: discarded_group_call
                478     LOAD_NAME                       6: property
                480     LOAD_CONST                      33: <CODE> user_muted
                482     MAKE_FUNCTION                   0
                484     CALL                            0
                492     STORE_NAME                      34: user_muted
                494     LOAD_NAME                       6: property
                496     LOAD_CONST                      34: <CODE> user_unmutted
                498     MAKE_FUNCTION                   0
                500     CALL                            0
                508     STORE_NAME                      35: user_unmutted
                510     LOAD_NAME                       6: property
                512     LOAD_CONST                      35: <CODE> changed_call_settings
                514     MAKE_FUNCTION                   0
                516     CALL                            0
                524     STORE_NAME                      36: changed_call_settings
                526     LOAD_NAME                       6: property
                528     LOAD_CONST                      36: <CODE> changed_history_ttl
                530     MAKE_FUNCTION                   0
                532     CALL                            0
                540     STORE_NAME                      37: changed_history_ttl
                542     LOAD_NAME                       6: property
                544     LOAD_CONST                      37: <CODE> deleted_exported_invite
                546     MAKE_FUNCTION                   0
                548     CALL                            0
                556     STORE_NAME                      38: deleted_exported_invite
                558     LOAD_NAME                       6: property
                560     LOAD_CONST                      38: <CODE> edited_exported_invite
                562     MAKE_FUNCTION                   0
                564     CALL                            0
                572     STORE_NAME                      39: edited_exported_invite
                574     LOAD_NAME                       6: property
                576     LOAD_CONST                      39: <CODE> revoked_exported_invite
                578     MAKE_FUNCTION                   0
                580     CALL                            0
                588     STORE_NAME                      40: revoked_exported_invite
                590     LOAD_NAME                       6: property
                592     LOAD_CONST                      40: <CODE> joined_by_invite
                594     MAKE_FUNCTION                   0
                596     CALL                            0
                604     STORE_NAME                      41: joined_by_invite
                606     LOAD_NAME                       6: property
                608     LOAD_CONST                      41: <CODE> changed_user_volume
                610     MAKE_FUNCTION                   0
                612     CALL                            0
                620     STORE_NAME                      42: changed_user_volume
                622     LOAD_CONST                      42: <CODE> __str__
                624     MAKE_FUNCTION                   0
                626     STORE_NAME                      43: __str__
                628     LOAD_CONST                      43: <CODE> stringify
                630     MAKE_FUNCTION                   0
                632     STORE_NAME                      44: stringify
                634     LOAD_CONST                      45: None
                636     NOP                             
                638     NOP                             
                640     NOP                             
                642     JUMP_FORWARD                    19 (to 682)
                650     POP_TOP                         
                652     RETURN_CONST                    45: None
                654     PUSH_EXC_INFO                   
                656     PUSH_NULL                       
                658     LOAD_CONST                      44: '__pyarmor_exit_23846__'
                660     NOP                             
                662     LOAD_CONST                      4: b'<COAddr>\x07\x00\x00&h\x02\x00\x00\x00\x00\x00\x00\x00\x00\x00\x00\x00\x00\x00\x00'
                664     CALL                            1
                672     POP_TOP                         
                674     RERAISE                         0
                676     COPY                            3
                678     POP_EXCEPT                      
                680     RERAISE                         1
                682     PUSH_NULL                       
                684     LOAD_CONST                      44: '__pyarmor_exit_23846__'
                686     LOAD_CONST                      4: b'<COAddr>\x07\x00\x00&h\x02\x00\x00\x00\x00\x00\x00\x00\x00\x00\x00\x00\x00\x00\x00'
                688     BUILD_TUPLE                     1
                690     CALL_FUNCTION_EX                0
                692     POP_TOP                         
                694     RETURN_VALUE                    
            [Exception Table]
                40 to 634 -> 654 [0] 
                654 to 676 -> 676 [1] lasti
        'AdminLogEvent'
        '__pyarmor_exit_23843__'
        None
    [Disassembly]
        0       NOP                             
        2       NOP                             
        4       PUSH_NULL                       
        6       LOAD_CONST                      1: '__pyarmor_enter_23842__'
        8       LOAD_CONST                      2: b'<COAddr>\x07\x00\x00\x1a@\x00\x00\x00\x00\x00\x00\x00\x00\x00\x00\x00\x00\x00\x00\x00'
        10      BUILD_TUPLE                     1
        12      CALL_FUNCTION_EX                0
        14      POP_TOP                         
        16      RESUME                          0
        18      NOP                             
        20      NOP                             
        22      NOP                             
        24      NOP                             
        26      LOAD_CONST                      3: 3
        28      LOAD_CONST                      4: ('types',)
        30      IMPORT_NAME                     1: tl
        32      IMPORT_FROM                     2: types
        34      STORE_NAME                      2: types
        36      POP_TOP                         
        38      LOAD_CONST                      3: 3
        40      LOAD_CONST                      5: ('get_input_peer',)
        42      IMPORT_NAME                     3: utils
        44      IMPORT_FROM                     4: get_input_peer
        46      STORE_NAME                      4: get_input_peer
        48      POP_TOP                         
        50      PUSH_NULL                       
        52      LOAD_BUILD_CLASS                
        54      LOAD_CONST                      6: <CODE> AdminLogEvent
        56      MAKE_FUNCTION                   0
        58      LOAD_CONST                      7: 'AdminLogEvent'
        60      CALL                            2
        68      STORE_NAME                      5: AdminLogEvent
        70      LOAD_CONST                      9: None
        72      NOP                             
        74      NOP                             
        76      NOP                             
        78      JUMP_FORWARD                    19 (to 118)
        86      POP_TOP                         
        88      RETURN_CONST                    9: None
        90      PUSH_EXC_INFO                   
        92      PUSH_NULL                       
        94      LOAD_CONST                      8: '__pyarmor_exit_23843__'
        96      NOP                             
        98      LOAD_CONST                      2: b'<COAddr>\x07\x00\x00\x1a@\x00\x00\x00\x00\x00\x00\x00\x00\x00\x00\x00\x00\x00\x00\x00'
        100     CALL                            1
        108     POP_TOP                         
        110     RERAISE                         0
        112     COPY                            3
        114     POP_EXCEPT                      
        116     RERAISE                         1
        118     PUSH_NULL                       
        120     LOAD_CONST                      8: '__pyarmor_exit_23843__'
        122     LOAD_CONST                      2: b'<COAddr>\x07\x00\x00\x1a@\x00\x00\x00\x00\x00\x00\x00\x00\x00\x00\x00\x00\x00\x00\x00'
        124     BUILD_TUPLE                     1
        126     CALL_FUNCTION_EX                0
        128     POP_TOP                         
        130     RETURN_VALUE                    
    [Exception Table]
        26 to 70 -> 90 [0] 
        90 to 112 -> 112 [1] lasti
