#decoded by lolz.live/mrpenny / t.me/zeus_jackpot
# ================================
# Примечания по Pyarmor:
# - Байт-код и объекты кода Pyarmor соответствуют стандартному Python, но присутствуют специальные вызовы функций среды выполнения (runtime) Pyarmor.
# - Вызовы строк — это не ошибки, а маркеры, которые обрабатываются Pyarmor во время выполнения.
#
# Руководство по декомпиляции (без среды выполнения):
# 1. Игнорируйте зашифрованные байты после `#`; используйте только строку до `#`.
# 2. Удалите "__pyarmor_enter_xxx__"(b"<COAddr>...") и "__pyarmor_leave_xxx__"(b"<COAddr>...") (пролог/эпилог).
# 3. "__pyarmor_assert_xxx__"(A) не является настоящим оператором assert.
#    - Если A — это имя или читаемая строка: замените на A.
#    - Если A — это (X, "Y"): замените на X.Y.
#    - Если A — это (X, "Y", Z): замените на X.Y = Z.
#    - В противном случае: выберите наиболее подходящую/логичную замену.
# 4. "__pyarmor_bcc_xxx__"(...) указывает на машинный (нативный) код; тело функции недоступно. Добавьте комментарий.
# ================================

[Code]
    File Name: <frozen multithon.tl.custom.button>
    Object Name: <module>
    Qualified Name: <module>
    Arg Count: 0
    Pos Only Arg Count: 0
    KW Only Arg Count: 0
    Stack Size: 5
    Flags: 0x20000000 (CO_PYARMOR_OBFUSCATED)
    [Names]
        '__assert_armored__'
        ''
        'types'
        'utils'
        'Button'
    [Locals+Names]
    [Constants]
        '__pyarmor_assert_23964__'
        '__pyarmor_enter_23965__'
        b'<COAddr>\x07\x00\x00\x1a@\x00\x00\x00\x00\x00\x00\x00\x00\x00\x00\x00\x00\x00\x00\x00'
        2
        (
            'types'
        )
        3
        (
            'utils'
        )
        [Code]
            File Name: <frozen multithon.tl.custom.button>
            Object Name: Button
            Qualified Name: Button
            Arg Count: 0
            Pos Only Arg Count: 0
            KW Only Arg Count: 0
            Stack Size: 8
            Flags: 0x20000000 (CO_PYARMOR_OBFUSCATED)
            [Names]
                '__name__'
                '__module__'
                '__qualname__'
                '__doc__'
                '__assert_armored__'
                '__init__'
                'staticmethod'
                '_is_inline'
                'inline'
                'switch_inline'
                'url'
                'auth'
                'classmethod'
                'text'
                'request_location'
                'request_phone'
                'request_poll'
                'clear'
                'force_reply'
                'buy'
                'game'
            [Locals+Names]
            [Constants]
                'Button'
                "\n    .. note::\n\n        This class is used to **define** reply markups, e.g. when\n        sending a message or replying to events. When you access\n        `Message.buttons <telethon.tl.custom.message.Message.buttons>`\n        they are actually `MessageButton\n        <telethon.tl.custom.messagebutton.MessageButton>`,\n        so you might want to refer to that class instead.\n\n    Helper class to allow defining ``reply_markup`` when\n    sending a message with inline or keyboard buttons.\n\n    You should make use of the defined class methods to create button\n    instances instead making them yourself (i.e. don't do ``Button(...)``\n    but instead use methods line `Button.inline(...) <inline>` etc.\n\n    You can use `inline`, `switch_inline`, `url`, `auth`, `buy` and `game`\n    together to create inline buttons (under the message).\n\n    You can use `text`, `request_location`, `request_phone` and `request_poll`\n    together to create a reply markup (replaces the user keyboard).\n    You can also configure the aspect of the reply with these.\n    The latest message with a reply markup will be the one shown to the user\n    (messages contain the buttons, not the chat itself).\n\n    You **cannot** mix the two type of buttons together,\n    and it will error if you try to do so.\n\n    The text for all buttons may be at most 142 characters.\n    If more characters are given, Telegram will cut the text\n    to 128 characters and add the ellipsis (…) character as\n    the 129.\n    "
                '__pyarmor_assert_23967__'
                '__pyarmor_enter_23968__'
                b'<COAddr>\x05\x00\x00&<\x01\x00\x00\x00\x00\x00\x00\x00\x00\x00\x00\x00\x00\x00\x00'
                [Code]
                    File Name: <frozen multithon.tl.custom.button>
                    Object Name: __init__
                    Qualified Name: Button.__init__
                    Arg Count: 2
                    Pos Only Arg Count: 0
                    KW Only Arg Count: 5
                    Stack Size: 5
                    Flags: 0x20000003 (CO_OPTIMIZED | CO_NEWLOCALS | CO_PYARMOR_OBFUSCATED)
                    [Names]
                        'button'
                        'resize'
                        'single_use'
                        'selective'
                        'persistent'
                        'placeholder'
                    [Locals+Names]
                        'self'
                        'button'
                        'resize'
                        'single_use'
                        'selective'
                        'persistent'
                        'placeholder'
                        '__assert_armored__'
                    [Constants]
                        None
                        '__pyarmor_assert_23970__'
                        '__pyarmor_enter_23971__'
                        b'<COAddr>\x07\x00\x00\x1aj\x00\x00\x00\x00\x00\x00\x00\x00\x00\x00\x00\x00\x00\x00\x00'
                        '__pyarmor_exit_23972__'
                    [Disassembly]
                        0       NOP                             
                        2       NOP                             
                        4       PUSH_NULL                       
                        6       LOAD_CONST                      2: '__pyarmor_enter_23971__'
                        8       LOAD_CONST                      3: b'<COAddr>\x07\x00\x00\x1aj\x00\x00\x00\x00\x00\x00\x00\x00\x00\x00\x00\x00\x00\x00\x00'
                        10      BUILD_TUPLE                     1
                        12      CALL_FUNCTION_EX                0
                        14      POP_TOP                         
                        16      RESUME                          0
                        18      NOP                             
                        20      NOP                             
                        22      NOP                             
                        24      NOP                             
                        26      NOP                             
                        28      LOAD_FAST                       1: button
                        30      LOAD_FAST                       0: self
                        32      STORE_ATTR                      0: button
                        42      LOAD_FAST                       2: resize
                        44      LOAD_FAST                       0: self
                        46      STORE_ATTR                      1: resize
                        56      LOAD_FAST                       3: single_use
                        58      LOAD_FAST                       0: self
                        60      STORE_ATTR                      2: single_use
                        70      LOAD_FAST                       4: selective
                        72      LOAD_FAST                       0: self
                        74      STORE_ATTR                      3: selective
                        84      LOAD_FAST                       5: persistent
                        86      LOAD_FAST                       0: self
                        88      STORE_ATTR                      4: persistent
                        98      LOAD_FAST                       6: placeholder
                        100     LOAD_FAST                       0: self
                        102     STORE_ATTR                      5: placeholder
                        112     LOAD_CONST                      0: None
                        114     NOP                             
                        116     NOP                             
                        118     NOP                             
                        120     JUMP_FORWARD                    19 (to 160)
                        128     POP_TOP                         
                        130     RETURN_CONST                    0: None
                        132     PUSH_EXC_INFO                   
                        134     PUSH_NULL                       
                        136     LOAD_CONST                      4: '__pyarmor_exit_23972__'
                        138     NOP                             
                        140     LOAD_CONST                      3: b'<COAddr>\x07\x00\x00\x1aj\x00\x00\x00\x00\x00\x00\x00\x00\x00\x00\x00\x00\x00\x00\x00'
                        142     CALL                            1
                        150     POP_TOP                         
                        152     RERAISE                         0
                        154     COPY                            3
                        156     POP_EXCEPT                      
                        158     RERAISE                         1
                        160     PUSH_NULL                       
                        162     LOAD_CONST                      4: '__pyarmor_exit_23972__'
                        164     LOAD_CONST                      3: b'<COAddr>\x07\x00\x00\x1aj\x00\x00\x00\x00\x00\x00\x00\x00\x00\x00\x00\x00\x00\x00\x00'
                        166     BUILD_TUPLE                     1
                        168     CALL_FUNCTION_EX                0
                        170     POP_TOP                         
                        172     RETURN_VALUE                    
                    [Exception Table]
                        28 to 112 -> 132 [0] 
                        132 to 154 -> 154 [1] lasti
                [Code]
                    File Name: <frozen multithon.tl.custom.button>
                    Object Name: _is_inline
                    Qualified Name: Button._is_inline
                    Arg Count: 1
                    Pos Only Arg Count: 0
                    KW Only Arg Count: 0
                    Stack Size: 11
                    Flags: 0x20000003 (CO_OPTIMIZED | CO_NEWLOCALS | CO_PYARMOR_OBFUSCATED)
                    [Names]
                        'isinstance'
                        'types'
                        'KeyboardButtonCopy'
                        'KeyboardButtonBuy'
                        'KeyboardButtonCallback'
                        'KeyboardButtonGame'
                        'KeyboardButtonSwitchInline'
                        'KeyboardButtonUrl'
                        'InputKeyboardButtonUrlAuth'
                        'KeyboardButtonWebView'
                    [Locals+Names]
                        'button'
                        '__assert_armored__'
                    [Constants]
                        '\n        Returns `True` if the button belongs to an inline keyboard.\n        '
                        '__pyarmor_assert_23973__'
                        '__pyarmor_enter_23974__'
                        b'<COAddr>\x05\x00\x00\x1a\x1c\x01\x00\x00\x00\x00\x00\x00\x00\x00\x00\x00\x00\x00\x00\x00'
                        '__pyarmor_exit_23975__'
                    [Disassembly]
                        0       NOP                             
                        2       NOP                             
                        4       PUSH_NULL                       
                        6       LOAD_CONST                      2: '__pyarmor_enter_23974__'
                        8       LOAD_CONST                      3: b'<COAddr>\x05\x00\x00\x1a\x1c\x01\x00\x00\x00\x00\x00\x00\x00\x00\x00\x00\x00\x00\x00\x00'
                        10      BUILD_TUPLE                     1
                        12      CALL_FUNCTION_EX                0
                        14      POP_TOP                         
                        16      RESUME                          0
                        18      NOP                             
                        20      NOP                             
                        22      NOP                             
                        24      NOP                             
                        26      NOP                             
                        28      LOAD_GLOBAL                     1: NULL + isinstance
                        38      LOAD_FAST                       0: button
                        40      LOAD_GLOBAL                     2: types
                        50      LOAD_ATTR                       4: KeyboardButtonCopy
                        70      LOAD_GLOBAL                     2: types
                        80      LOAD_ATTR                       6: KeyboardButtonBuy
                        100     LOAD_GLOBAL                     2: types
                        110     LOAD_ATTR                       8: KeyboardButtonCallback
                        130     LOAD_GLOBAL                     2: types
                        140     LOAD_ATTR                       10: KeyboardButtonGame
                        160     LOAD_GLOBAL                     2: types
                        170     LOAD_ATTR                       12: KeyboardButtonSwitchInline
                        190     LOAD_GLOBAL                     2: types
                        200     LOAD_ATTR                       14: KeyboardButtonUrl
                        220     LOAD_GLOBAL                     2: types
                        230     LOAD_ATTR                       16: InputKeyboardButtonUrlAuth
                        250     LOAD_GLOBAL                     2: types
                        260     LOAD_ATTR                       18: KeyboardButtonWebView
                        280     BUILD_TUPLE                     8
                        282     CALL                            2
                        290     NOP                             
                        292     NOP                             
                        294     NOP                             
                        296     JUMP_FORWARD                    20 (to 338)
                        298     CALL                            1
                        306     POP_TOP                         
                        308     RETURN_VALUE                    
                        310     PUSH_EXC_INFO                   
                        312     PUSH_NULL                       
                        314     LOAD_CONST                      4: '__pyarmor_exit_23975__'
                        316     NOP                             
                        318     LOAD_CONST                      3: b'<COAddr>\x05\x00\x00\x1a\x1c\x01\x00\x00\x00\x00\x00\x00\x00\x00\x00\x00\x00\x00\x00\x00'
                        320     CALL                            1
                        328     POP_TOP                         
                        330     RERAISE                         0
                        332     COPY                            3
                        334     POP_EXCEPT                      
                        336     RERAISE                         1
                        338     PUSH_NULL                       
                        340     LOAD_CONST                      4: '__pyarmor_exit_23975__'
                        342     LOAD_CONST                      3: b'<COAddr>\x05\x00\x00\x1a\x1c\x01\x00\x00\x00\x00\x00\x00\x00\x00\x00\x00\x00\x00\x00\x00'
                        344     BUILD_TUPLE                     1
                        346     CALL_FUNCTION_EX                0
                        348     POP_TOP                         
                        350     RETURN_VALUE                    
                    [Exception Table]
                        28 to 290 -> 310 [0] 
                        310 to 332 -> 332 [1] lasti
                None
                [Code]
                    File Name: <frozen multithon.tl.custom.button>
                    Object Name: inline
                    Qualified Name: Button.inline
                    Arg Count: 2
                    Pos Only Arg Count: 0
                    KW Only Arg Count: 0
                    Stack Size: 6
                    Flags: 0x20000003 (CO_OPTIMIZED | CO_NEWLOCALS | CO_PYARMOR_OBFUSCATED)
                    [Names]
                        'encode'
                        'isinstance'
                        'bytes'
                        'bytearray'
                        'memoryview'
                        'str'
                        'len'
                        'ValueError'
                        'types'
                        'KeyboardButtonCallback'
                    [Locals+Names]
                        'text'
                        'data'
                        '__assert_armored__'
                    [Constants]
                        '\n        Creates a new inline button with some payload data in it.\n\n        If `data` is omitted, the given `text` will be used as `data`.\n        In any case `data` should be either `bytes` or `str`.\n\n        Note that the given `data` must be less or equal to 64 bytes.\n        If more than 64 bytes are passed as data, ``ValueError`` is raised.\n        If you need to store more than 64 bytes, consider saving the real\n        data in a database and a reference to that data inside the button.\n\n        When the user clicks this button, `events.CallbackQuery\n        <telethon.events.callbackquery.CallbackQuery>` will trigger with the\n        same data that the button contained, so that you can determine which\n        button was pressed.\n        '
                        '__pyarmor_assert_23976__'
                        '__pyarmor_enter_23977__'
                        b'<COAddr>\x05\x00\x00\x1a\x10\x01\x00\x00\x00\x00\x00\x00\x00\x00\x00\x00\x00\x00\x00\x00'
                        'utf-8'
                        64
                        'Too many bytes for the data'   # b'\x81\xd6\x17\x1cs\xf7\xbf\xdc\x02\xba\x0f\xd9x\xe9\xeb\xc5\tR\xa9\xe7\xbe\xc3K\x8c\x01n\xb7]'
                        '__pyarmor_exit_23978__'
                    [Disassembly]
                        0       NOP                             
                        2       NOP                             
                        4       PUSH_NULL                       
                        6       LOAD_CONST                      2: '__pyarmor_enter_23977__'
                        8       LOAD_CONST                      3: b'<COAddr>\x05\x00\x00\x1a\x10\x01\x00\x00\x00\x00\x00\x00\x00\x00\x00\x00\x00\x00\x00\x00'
                        10      BUILD_TUPLE                     1
                        12      CALL_FUNCTION_EX                0
                        14      POP_TOP                         
                        16      RESUME                          0
                        18      NOP                             
                        20      NOP                             
                        22      NOP                             
                        24      NOP                             
                        26      NOP                             
                        28      LOAD_FAST                       1: data
                        30      POP_JUMP_IF_TRUE                18 (to 68)
                        32      LOAD_FAST                       0: text
                        34      LOAD_ATTR                       1: encode
                        54      LOAD_CONST                      4: 'utf-8'
                        56      CALL                            1
                        64      STORE_FAST                      1: data
                        66      JUMP_FORWARD                    53 (to 174)
                        68      LOAD_GLOBAL                     3: NULL + isinstance
                        78      LOAD_FAST                       1: data
                        80      LOAD_GLOBAL                     4: bytes
                        90      LOAD_GLOBAL                     6: bytearray
                        100     LOAD_GLOBAL                     8: memoryview
                        110     BUILD_TUPLE                     3
                        112     CALL                            2
                        120     POP_JUMP_IF_TRUE                26 (to 174)
                        122     LOAD_GLOBAL                     11: NULL + str
                        132     LOAD_FAST                       1: data
                        134     CALL                            1
                        142     LOAD_ATTR                       1: encode
                        162     LOAD_CONST                      4: 'utf-8'
                        164     CALL                            1
                        172     STORE_FAST                      1: data
                        174     LOAD_GLOBAL                     13: NULL + len
                        184     LOAD_FAST                       1: data
                        186     CALL                            1
                        194     LOAD_CONST                      5: 64
                        196     COMPARE_OP                      68 (>)
                        200     POP_JUMP_IF_FALSE               17 (to 236)
                        202     LOAD_GLOBAL                     15: NULL + ValueError
                        212     PUSH_NULL                       
                        214     LOAD_CONST                      1: '__pyarmor_assert_23976__'
                        216     LOAD_CONST                      6: 'Too many bytes for the data'   # b'\x81\xd6\x17\x1cs\xf7\xbf\xdc\x02\xba\x0f\xd9x\xe9\xeb\xc5\tR\xa9\xe7\xbe\xc3K\x8c\x01n\xb7]'
                        218     CALL                            1
                        226     CALL                            1
                        234     RAISE_VARARGS                   1
                        236     LOAD_GLOBAL                     17: NULL + types
                        246     LOAD_ATTR                       18: KeyboardButtonCallback
                        266     LOAD_FAST                       0: text
                        268     LOAD_FAST                       1: data
                        270     CALL                            2
                        278     NOP                             
                        280     NOP                             
                        282     NOP                             
                        284     JUMP_FORWARD                    20 (to 326)
                        286     CALL                            1
                        294     POP_TOP                         
                        296     RETURN_VALUE                    
                        298     PUSH_EXC_INFO                   
                        300     PUSH_NULL                       
                        302     LOAD_CONST                      7: '__pyarmor_exit_23978__'
                        304     NOP                             
                        306     LOAD_CONST                      3: b'<COAddr>\x05\x00\x00\x1a\x10\x01\x00\x00\x00\x00\x00\x00\x00\x00\x00\x00\x00\x00\x00\x00'
                        308     CALL                            1
                        316     POP_TOP                         
                        318     RERAISE                         0
                        320     COPY                            3
                        322     POP_EXCEPT                      
                        324     RERAISE                         1
                        326     PUSH_NULL                       
                        328     LOAD_CONST                      7: '__pyarmor_exit_23978__'
                        330     LOAD_CONST                      3: b'<COAddr>\x05\x00\x00\x1a\x10\x01\x00\x00\x00\x00\x00\x00\x00\x00\x00\x00\x00\x00\x00\x00'
                        332     BUILD_TUPLE                     1
                        334     CALL_FUNCTION_EX                0
                        336     POP_TOP                         
                        338     RETURN_VALUE                    
                    [Exception Table]
                        28 to 278 -> 298 [0] 
                        298 to 320 -> 320 [1] lasti
                False
                [Code]
                    File Name: <frozen multithon.tl.custom.button>
                    Object Name: switch_inline
                    Qualified Name: Button.switch_inline
                    Arg Count: 3
                    Pos Only Arg Count: 0
                    KW Only Arg Count: 0
                    Stack Size: 5
                    Flags: 0x20000003 (CO_OPTIMIZED | CO_NEWLOCALS | CO_PYARMOR_OBFUSCATED)
                    [Names]
                        'types'
                        'KeyboardButtonSwitchInline'
                    [Locals+Names]
                        'text'
                        'query'
                        'same_peer'
                        '__assert_armored__'
                    [Constants]
                        '\n        Creates a new inline button to switch to inline query.\n\n        If `query` is given, it will be the default text to be used\n        when making the inline query.\n\n        If ``same_peer is True`` the inline query will directly be\n        set under the currently opened chat. Otherwise, the user will\n        have to select a different dialog to make the query.\n\n        When the user clicks this button, after a chat is selected, their\n        input field will be filled with the username of your bot followed\n        by the query text, ready to make inline queries.\n        '
                        '__pyarmor_assert_23979__'
                        '__pyarmor_enter_23980__'
                        b'<COAddr>\x07\x00\x00\x1aB\x00\x00\x00\x00\x00\x00\x00\x00\x00\x00\x00\x00\x00\x00\x00'
                        '__pyarmor_exit_23981__'
                    [Disassembly]
                        0       NOP                             
                        2       NOP                             
                        4       PUSH_NULL                       
                        6       LOAD_CONST                      2: '__pyarmor_enter_23980__'
                        8       LOAD_CONST                      3: b'<COAddr>\x07\x00\x00\x1aB\x00\x00\x00\x00\x00\x00\x00\x00\x00\x00\x00\x00\x00\x00\x00'
                        10      BUILD_TUPLE                     1
                        12      CALL_FUNCTION_EX                0
                        14      POP_TOP                         
                        16      RESUME                          0
                        18      NOP                             
                        20      NOP                             
                        22      NOP                             
                        24      NOP                             
                        26      NOP                             
                        28      LOAD_GLOBAL                     1: NULL + types
                        38      LOAD_ATTR                       2: KeyboardButtonSwitchInline
                        58      LOAD_FAST                       0: text
                        60      LOAD_FAST                       1: query
                        62      LOAD_FAST                       2: same_peer
                        64      CALL                            3
                        72      NOP                             
                        74      NOP                             
                        76      NOP                             
                        78      JUMP_FORWARD                    20 (to 120)
                        80      CALL                            1
                        88      POP_TOP                         
                        90      RETURN_VALUE                    
                        92      PUSH_EXC_INFO                   
                        94      PUSH_NULL                       
                        96      LOAD_CONST                      4: '__pyarmor_exit_23981__'
                        98      NOP                             
                        100     LOAD_CONST                      3: b'<COAddr>\x07\x00\x00\x1aB\x00\x00\x00\x00\x00\x00\x00\x00\x00\x00\x00\x00\x00\x00\x00'
                        102     CALL                            1
                        110     POP_TOP                         
                        112     RERAISE                         0
                        114     COPY                            3
                        116     POP_EXCEPT                      
                        118     RERAISE                         1
                        120     PUSH_NULL                       
                        122     LOAD_CONST                      4: '__pyarmor_exit_23981__'
                        124     LOAD_CONST                      3: b'<COAddr>\x07\x00\x00\x1aB\x00\x00\x00\x00\x00\x00\x00\x00\x00\x00\x00\x00\x00\x00\x00'
                        126     BUILD_TUPLE                     1
                        128     CALL_FUNCTION_EX                0
                        130     POP_TOP                         
                        132     RETURN_VALUE                    
                    [Exception Table]
                        28 to 72 -> 92 [0] 
                        92 to 114 -> 114 [1] lasti
                [Code]
                    File Name: <frozen multithon.tl.custom.button>
                    Object Name: url
                    Qualified Name: Button.url
                    Arg Count: 2
                    Pos Only Arg Count: 0
                    KW Only Arg Count: 0
                    Stack Size: 5
                    Flags: 0x20000003 (CO_OPTIMIZED | CO_NEWLOCALS | CO_PYARMOR_OBFUSCATED)
                    [Names]
                        'types'
                        'KeyboardButtonUrl'
                    [Locals+Names]
                        'text'
                        'url'
                        '__assert_armored__'
                    [Constants]
                        '\n        Creates a new inline button to open the desired URL on click.\n\n        If no `url` is given, the `text` will be used as said URL instead.\n\n        You cannot detect that the user clicked this button directly.\n\n        When the user clicks this button, a confirmation box will be shown\n        to the user asking whether they want to open the displayed URL unless\n        the domain is trusted, and once confirmed the URL will open in their\n        device.\n        '
                        '__pyarmor_assert_23982__'
                        '__pyarmor_enter_23983__'
                        b'<COAddr>\x07\x00\x00\x1aH\x00\x00\x00\x00\x00\x00\x00\x00\x00\x00\x00\x00\x00\x00\x00'
                        '__pyarmor_exit_23984__'
                    [Disassembly]
                        0       NOP                             
                        2       NOP                             
                        4       PUSH_NULL                       
                        6       LOAD_CONST                      2: '__pyarmor_enter_23983__'
                        8       LOAD_CONST                      3: b'<COAddr>\x07\x00\x00\x1aH\x00\x00\x00\x00\x00\x00\x00\x00\x00\x00\x00\x00\x00\x00\x00'
                        10      BUILD_TUPLE                     1
                        12      CALL_FUNCTION_EX                0
                        14      POP_TOP                         
                        16      RESUME                          0
                        18      NOP                             
                        20      NOP                             
                        22      NOP                             
                        24      NOP                             
                        26      NOP                             
                        28      LOAD_GLOBAL                     1: NULL + types
                        38      LOAD_ATTR                       2: KeyboardButtonUrl
                        58      LOAD_FAST                       0: text
                        60      LOAD_FAST                       1: url
                        62      COPY                            1
                        64      POP_JUMP_IF_TRUE                2 (to 70)
                        66      POP_TOP                         
                        68      LOAD_FAST                       0: text
                        70      CALL                            2
                        78      NOP                             
                        80      NOP                             
                        82      NOP                             
                        84      JUMP_FORWARD                    20 (to 126)
                        86      CALL                            1
                        94      POP_TOP                         
                        96      RETURN_VALUE                    
                        98      PUSH_EXC_INFO                   
                        100     PUSH_NULL                       
                        102     LOAD_CONST                      4: '__pyarmor_exit_23984__'
                        104     NOP                             
                        106     LOAD_CONST                      3: b'<COAddr>\x07\x00\x00\x1aH\x00\x00\x00\x00\x00\x00\x00\x00\x00\x00\x00\x00\x00\x00\x00'
                        108     CALL                            1
                        116     POP_TOP                         
                        118     RERAISE                         0
                        120     COPY                            3
                        122     POP_EXCEPT                      
                        124     RERAISE                         1
                        126     PUSH_NULL                       
                        128     LOAD_CONST                      4: '__pyarmor_exit_23984__'
                        130     LOAD_CONST                      3: b'<COAddr>\x07\x00\x00\x1aH\x00\x00\x00\x00\x00\x00\x00\x00\x00\x00\x00\x00\x00\x00\x00'
                        132     BUILD_TUPLE                     1
                        134     CALL_FUNCTION_EX                0
                        136     POP_TOP                         
                        138     RETURN_VALUE                    
                    [Exception Table]
                        28 to 78 -> 98 [0] 
                        98 to 120 -> 120 [1] lasti
                (
                    'bot'
                    'write_access'
                    'fwd_text'
                )
                [Code]
                    File Name: <frozen multithon.tl.custom.button>
                    Object Name: auth
                    Qualified Name: Button.auth
                    Arg Count: 2
                    Pos Only Arg Count: 0
                    KW Only Arg Count: 3
                    Stack Size: 8
                    Flags: 0x20000003 (CO_OPTIMIZED | CO_NEWLOCALS | CO_PYARMOR_OBFUSCATED)
                    [Names]
                        'types'
                        'InputKeyboardButtonUrlAuth'
                        'utils'
                        'get_input_user'
                        'InputUserSelf'
                    [Locals+Names]
                        'text'
                        'url'
                        'bot'
                        'write_access'
                        'fwd_text'
                        '__assert_armored__'
                    [Constants]
                        '\n        Creates a new inline button to authorize the user at the given URL.\n\n        You should set the `url` to be on the same domain as the one configured\n        for the desired `bot` via `@BotFather <https://t.me/BotFather>`_ using\n        the ``/setdomain`` command.\n\n        For more information about letting the user login via Telegram to\n        a certain domain, see https://core.telegram.org/widgets/login.\n\n        If no `url` is specified, it will default to `text`.\n\n        Args:\n            bot (`hints.EntityLike`):\n                The bot that requires this authorization. By default, this\n                is the bot that is currently logged in (itself), although\n                you may pass a different input peer.\n\n                .. note::\n\n                    For now, you cannot use ID or username for this argument.\n                    If you want to use a different bot than the one currently\n                    logged in, you must manually use `client.get_input_entity()\n                    <telethon.client.users.UserMethods.get_input_entity>`.\n\n            write_access (`bool`):\n                Whether write access is required or not.\n                This is `False` by default (read-only access).\n\n            fwd_text (`str`):\n                The new text to show in the button if the message is\n                forwarded. By default, the button text will be the same.\n\n        When the user clicks this button, a confirmation box will be shown\n        to the user asking whether they want to login to the specified domain.\n        '
                        '__pyarmor_assert_23985__'
                        '__pyarmor_enter_23986__'
                        b'<COAddr>\x05\x00\x00\x1a\xa2\x00\x00\x00\x00\x00\x00\x00\x00\x00\x00\x00\x00\x00\x00\x00'
                        (
                            'text'
                            'url'
                            'bot'
                            'request_write_access'
                            'fwd_text'
                        )
                        '__pyarmor_exit_23987__'
                    [Disassembly]
                        0       NOP                             
                        2       NOP                             
                        4       PUSH_NULL                       
                        6       LOAD_CONST                      2: '__pyarmor_enter_23986__'
                        8       LOAD_CONST                      3: b'<COAddr>\x05\x00\x00\x1a\xa2\x00\x00\x00\x00\x00\x00\x00\x00\x00\x00\x00\x00\x00\x00\x00'
                        10      BUILD_TUPLE                     1
                        12      CALL_FUNCTION_EX                0
                        14      POP_TOP                         
                        16      RESUME                          0
                        18      NOP                             
                        20      NOP                             
                        22      NOP                             
                        24      NOP                             
                        26      NOP                             
                        28      LOAD_GLOBAL                     1: NULL + types
                        38      LOAD_ATTR                       2: InputKeyboardButtonUrlAuth
                        58      LOAD_FAST                       0: text
                        60      LOAD_FAST                       1: url
                        62      COPY                            1
                        64      POP_JUMP_IF_TRUE                2 (to 70)
                        66      POP_TOP                         
                        68      LOAD_FAST                       0: text
                        70      LOAD_GLOBAL                     5: NULL + utils
                        80      LOAD_ATTR                       6: get_input_user
                        100     LOAD_FAST                       2: bot
                        102     COPY                            1
                        104     POP_JUMP_IF_TRUE                20 (to 146)
                        106     POP_TOP                         
                        108     LOAD_GLOBAL                     1: NULL + types
                        118     LOAD_ATTR                       8: InputUserSelf
                        138     CALL                            0
                        146     CALL                            1
                        154     LOAD_FAST                       3: write_access
                        156     LOAD_FAST                       4: fwd_text
                        158     KW_NAMES                        4: ('text', 'url', 'bot', 'request_write_access', 'fwd_text')
                        160     CALL                            5
                        168     NOP                             
                        170     NOP                             
                        172     NOP                             
                        174     JUMP_FORWARD                    20 (to 216)
                        176     CALL                            1
                        184     POP_TOP                         
                        186     RETURN_VALUE                    
                        188     PUSH_EXC_INFO                   
                        190     PUSH_NULL                       
                        192     LOAD_CONST                      5: '__pyarmor_exit_23987__'
                        194     NOP                             
                        196     LOAD_CONST                      3: b'<COAddr>\x05\x00\x00\x1a\xa2\x00\x00\x00\x00\x00\x00\x00\x00\x00\x00\x00\x00\x00\x00\x00'
                        198     CALL                            1
                        206     POP_TOP                         
                        208     RERAISE                         0
                        210     COPY                            3
                        212     POP_EXCEPT                      
                        214     RERAISE                         1
                        216     PUSH_NULL                       
                        218     LOAD_CONST                      5: '__pyarmor_exit_23987__'
                        220     LOAD_CONST                      3: b'<COAddr>\x05\x00\x00\x1a\xa2\x00\x00\x00\x00\x00\x00\x00\x00\x00\x00\x00\x00\x00\x00\x00'
                        222     BUILD_TUPLE                     1
                        224     CALL_FUNCTION_EX                0
                        226     POP_TOP                         
                        228     RETURN_VALUE                    
                    [Exception Table]
                        28 to 168 -> 188 [0] 
                        188 to 210 -> 210 [1] lasti
                (
                    'resize'
                    'single_use'
                    'selective'
                    'persistent'
                    'placeholder'
                )
                [Code]
                    File Name: <frozen multithon.tl.custom.button>
                    Object Name: text
                    Qualified Name: Button.text
                    Arg Count: 2
                    Pos Only Arg Count: 0
                    KW Only Arg Count: 5
                    Stack Size: 8
                    Flags: 0x20000003 (CO_OPTIMIZED | CO_NEWLOCALS | CO_PYARMOR_OBFUSCATED)
                    [Names]
                        'types'
                        'KeyboardButton'
                    [Locals+Names]
                        'cls'
                        'text'
                        'resize'
                        'single_use'
                        'selective'
                        'persistent'
                        'placeholder'
                        '__assert_armored__'
                    [Constants]
                        '\n        Creates a new keyboard button with the given text.\n\n        Args:\n            text (`str`):\n                The title of the button.\n\n            resize (`bool`):\n                If present, the entire keyboard will be reconfigured to\n                be resized and be smaller if there are not many buttons.\n\n            single_use (`bool`):\n                If present, the entire keyboard will be reconfigured to\n                be usable only once before it hides itself.\n\n            selective (`bool`):\n                If present, the entire keyboard will be reconfigured to\n                be "selective". The keyboard will be shown only to specific\n                users. It will target users that are @mentioned in the text\n                of the message or to the sender of the message you reply to.\n\n            persistent (`bool`):\n                If present, always show the keyboard when the regular keyboard\n                is hidden. Defaults to false, in which case the custom keyboard\n                can be hidden and revealed via the keyboard icon.\n\n            placeholder (`str`):\n                The placeholder to be shown in the input field when the keyboard is active;\n                1-64 characters\n\n        When the user clicks this button, a text message with the same text\n        as the button will be sent, and can be handled with `events.NewMessage\n        <telethon.events.newmessage.NewMessage>`. You cannot distinguish\n        between a button press and the user typing and sending exactly the\n        same text on their own.\n        '
                        '__pyarmor_assert_23988__'
                        '__pyarmor_enter_23989__'
                        b'<COAddr>\x05\x00\x00\x1aV\x00\x00\x00\x00\x00\x00\x00\x00\x00\x00\x00\x00\x00\x00\x00'
                        (
                            'resize'
                            'single_use'
                            'selective'
                            'persistent'
                            'placeholder'
                        )
                        '__pyarmor_exit_23990__'
                    [Disassembly]
                        0       NOP                             
                        2       NOP                             
                        4       PUSH_NULL                       
                        6       LOAD_CONST                      2: '__pyarmor_enter_23989__'
                        8       LOAD_CONST                      3: b'<COAddr>\x05\x00\x00\x1aV\x00\x00\x00\x00\x00\x00\x00\x00\x00\x00\x00\x00\x00\x00\x00'
                        10      BUILD_TUPLE                     1
                        12      CALL_FUNCTION_EX                0
                        14      POP_TOP                         
                        16      RESUME                          0
                        18      NOP                             
                        20      NOP                             
                        22      NOP                             
                        24      NOP                             
                        26      NOP                             
                        28      PUSH_NULL                       
                        30      LOAD_FAST                       0: cls
                        32      LOAD_GLOBAL                     1: NULL + types
                        42      LOAD_ATTR                       2: KeyboardButton
                        62      LOAD_FAST                       1: text
                        64      CALL                            1
                        72      LOAD_FAST                       2: resize
                        74      LOAD_FAST                       3: single_use
                        76      LOAD_FAST                       4: selective
                        78      LOAD_FAST                       5: persistent
                        80      LOAD_FAST                       6: placeholder
                        82      KW_NAMES                        4: ('resize', 'single_use', 'selective', 'persistent', 'placeholder')
                        84      CALL                            6
                        92      NOP                             
                        94      NOP                             
                        96      NOP                             
                        98      JUMP_FORWARD                    20 (to 140)
                        100     CALL                            1
                        108     POP_TOP                         
                        110     RETURN_VALUE                    
                        112     PUSH_EXC_INFO                   
                        114     PUSH_NULL                       
                        116     LOAD_CONST                      5: '__pyarmor_exit_23990__'
                        118     NOP                             
                        120     LOAD_CONST                      3: b'<COAddr>\x05\x00\x00\x1aV\x00\x00\x00\x00\x00\x00\x00\x00\x00\x00\x00\x00\x00\x00\x00'
                        122     CALL                            1
                        130     POP_TOP                         
                        132     RERAISE                         0
                        134     COPY                            3
                        136     POP_EXCEPT                      
                        138     RERAISE                         1
                        140     PUSH_NULL                       
                        142     LOAD_CONST                      5: '__pyarmor_exit_23990__'
                        144     LOAD_CONST                      3: b'<COAddr>\x05\x00\x00\x1aV\x00\x00\x00\x00\x00\x00\x00\x00\x00\x00\x00\x00\x00\x00\x00'
                        146     BUILD_TUPLE                     1
                        148     CALL_FUNCTION_EX                0
                        150     POP_TOP                         
                        152     RETURN_VALUE                    
                    [Exception Table]
                        28 to 92 -> 112 [0] 
                        112 to 134 -> 134 [1] lasti
                [Code]
                    File Name: <frozen multithon.tl.custom.button>
                    Object Name: request_location
                    Qualified Name: Button.request_location
                    Arg Count: 2
                    Pos Only Arg Count: 0
                    KW Only Arg Count: 5
                    Stack Size: 8
                    Flags: 0x20000003 (CO_OPTIMIZED | CO_NEWLOCALS | CO_PYARMOR_OBFUSCATED)
                    [Names]
                        'types'
                        'KeyboardButtonRequestGeoLocation'
                    [Locals+Names]
                        'cls'
                        'text'
                        'resize'
                        'single_use'
                        'selective'
                        'persistent'
                        'placeholder'
                        '__assert_armored__'
                    [Constants]
                        "\n        Creates a new keyboard button to request the user's location on click.\n\n        ``resize``, ``single_use``, ``selective``, ``persistent`` and ``placeholder``\n         are documented in `text`.\n\n        When the user clicks this button, a confirmation box will be shown\n        to the user asking whether they want to share their location with the\n        bot, and if confirmed a message with geo media will be sent.\n        "
                        '__pyarmor_assert_23991__'
                        '__pyarmor_enter_23992__'
                        b'<COAddr>\x05\x00\x00\x1aV\x00\x00\x00\x00\x00\x00\x00\x00\x00\x00\x00\x00\x00\x00\x00'
                        (
                            'resize'
                            'single_use'
                            'selective'
                            'persistent'
                            'placeholder'
                        )
                        '__pyarmor_exit_23993__'
                    [Disassembly]
                        0       NOP                             
                        2       NOP                             
                        4       PUSH_NULL                       
                        6       LOAD_CONST                      2: '__pyarmor_enter_23992__'
                        8       LOAD_CONST                      3: b'<COAddr>\x05\x00\x00\x1aV\x00\x00\x00\x00\x00\x00\x00\x00\x00\x00\x00\x00\x00\x00\x00'
                        10      BUILD_TUPLE                     1
                        12      CALL_FUNCTION_EX                0
                        14      POP_TOP                         
                        16      RESUME                          0
                        18      NOP                             
                        20      NOP                             
                        22      NOP                             
                        24      NOP                             
                        26      NOP                             
                        28      PUSH_NULL                       
                        30      LOAD_FAST                       0: cls
                        32      LOAD_GLOBAL                     1: NULL + types
                        42      LOAD_ATTR                       2: KeyboardButtonRequestGeoLocation
                        62      LOAD_FAST                       1: text
                        64      CALL                            1
                        72      LOAD_FAST                       2: resize
                        74      LOAD_FAST                       3: single_use
                        76      LOAD_FAST                       4: selective
                        78      LOAD_FAST                       5: persistent
                        80      LOAD_FAST                       6: placeholder
                        82      KW_NAMES                        4: ('resize', 'single_use', 'selective', 'persistent', 'placeholder')
                        84      CALL                            6
                        92      NOP                             
                        94      NOP                             
                        96      NOP                             
                        98      JUMP_FORWARD                    20 (to 140)
                        100     CALL                            1
                        108     POP_TOP                         
                        110     RETURN_VALUE                    
                        112     PUSH_EXC_INFO                   
                        114     PUSH_NULL                       
                        116     LOAD_CONST                      5: '__pyarmor_exit_23993__'
                        118     NOP                             
                        120     LOAD_CONST                      3: b'<COAddr>\x05\x00\x00\x1aV\x00\x00\x00\x00\x00\x00\x00\x00\x00\x00\x00\x00\x00\x00\x00'
                        122     CALL                            1
                        130     POP_TOP                         
                        132     RERAISE                         0
                        134     COPY                            3
                        136     POP_EXCEPT                      
                        138     RERAISE                         1
                        140     PUSH_NULL                       
                        142     LOAD_CONST                      5: '__pyarmor_exit_23993__'
                        144     LOAD_CONST                      3: b'<COAddr>\x05\x00\x00\x1aV\x00\x00\x00\x00\x00\x00\x00\x00\x00\x00\x00\x00\x00\x00\x00'
                        146     BUILD_TUPLE                     1
                        148     CALL_FUNCTION_EX                0
                        150     POP_TOP                         
                        152     RETURN_VALUE                    
                    [Exception Table]
                        28 to 92 -> 112 [0] 
                        112 to 134 -> 134 [1] lasti
                [Code]
                    File Name: <frozen multithon.tl.custom.button>
                    Object Name: request_phone
                    Qualified Name: Button.request_phone
                    Arg Count: 2
                    Pos Only Arg Count: 0
                    KW Only Arg Count: 5
                    Stack Size: 8
                    Flags: 0x20000003 (CO_OPTIMIZED | CO_NEWLOCALS | CO_PYARMOR_OBFUSCATED)
                    [Names]
                        'types'
                        'KeyboardButtonRequestPhone'
                    [Locals+Names]
                        'cls'
                        'text'
                        'resize'
                        'single_use'
                        'selective'
                        'persistent'
                        'placeholder'
                        '__assert_armored__'
                    [Constants]
                        "\n        Creates a new keyboard button to request the user's phone on click.\n\n        ``resize``, ``single_use``, ``selective``, ``persistent`` and ``placeholder``\n         are documented in `text`.\n\n        When the user clicks this button, a confirmation box will be shown\n        to the user asking whether they want to share their phone with the\n        bot, and if confirmed a message with contact media will be sent.\n        "
                        '__pyarmor_assert_23994__'
                        '__pyarmor_enter_23995__'
                        b'<COAddr>\x05\x00\x00\x1aV\x00\x00\x00\x00\x00\x00\x00\x00\x00\x00\x00\x00\x00\x00\x00'
                        (
                            'resize'
                            'single_use'
                            'selective'
                            'placeholder'
                            'persistent'
                        )
                        '__pyarmor_exit_23996__'
                    [Disassembly]
                        0       NOP                             
                        2       NOP                             
                        4       PUSH_NULL                       
                        6       LOAD_CONST                      2: '__pyarmor_enter_23995__'
                        8       LOAD_CONST                      3: b'<COAddr>\x05\x00\x00\x1aV\x00\x00\x00\x00\x00\x00\x00\x00\x00\x00\x00\x00\x00\x00\x00'
                        10      BUILD_TUPLE                     1
                        12      CALL_FUNCTION_EX                0
                        14      POP_TOP                         
                        16      RESUME                          0
                        18      NOP                             
                        20      NOP                             
                        22      NOP                             
                        24      NOP                             
                        26      NOP                             
                        28      PUSH_NULL                       
                        30      LOAD_FAST                       0: cls
                        32      LOAD_GLOBAL                     1: NULL + types
                        42      LOAD_ATTR                       2: KeyboardButtonRequestPhone
                        62      LOAD_FAST                       1: text
                        64      CALL                            1
                        72      LOAD_FAST                       2: resize
                        74      LOAD_FAST                       3: single_use
                        76      LOAD_FAST                       4: selective
                        78      LOAD_FAST                       6: placeholder
                        80      LOAD_FAST                       5: persistent
                        82      KW_NAMES                        4: ('resize', 'single_use', 'selective', 'placeholder', 'persistent')
                        84      CALL                            6
                        92      NOP                             
                        94      NOP                             
                        96      NOP                             
                        98      JUMP_FORWARD                    20 (to 140)
                        100     CALL                            1
                        108     POP_TOP                         
                        110     RETURN_VALUE                    
                        112     PUSH_EXC_INFO                   
                        114     PUSH_NULL                       
                        116     LOAD_CONST                      5: '__pyarmor_exit_23996__'
                        118     NOP                             
                        120     LOAD_CONST                      3: b'<COAddr>\x05\x00\x00\x1aV\x00\x00\x00\x00\x00\x00\x00\x00\x00\x00\x00\x00\x00\x00\x00'
                        122     CALL                            1
                        130     POP_TOP                         
                        132     RERAISE                         0
                        134     COPY                            3
                        136     POP_EXCEPT                      
                        138     RERAISE                         1
                        140     PUSH_NULL                       
                        142     LOAD_CONST                      5: '__pyarmor_exit_23996__'
                        144     LOAD_CONST                      3: b'<COAddr>\x05\x00\x00\x1aV\x00\x00\x00\x00\x00\x00\x00\x00\x00\x00\x00\x00\x00\x00\x00'
                        146     BUILD_TUPLE                     1
                        148     CALL_FUNCTION_EX                0
                        150     POP_TOP                         
                        152     RETURN_VALUE                    
                    [Exception Table]
                        28 to 92 -> 112 [0] 
                        112 to 134 -> 134 [1] lasti
                (
                    'force_quiz'
                    'resize'
                    'single_use'
                    'selective'
                    'persistent'
                    'placeholder'
                )
                [Code]
                    File Name: <frozen multithon.tl.custom.button>
                    Object Name: request_poll
                    Qualified Name: Button.request_poll
                    Arg Count: 2
                    Pos Only Arg Count: 0
                    KW Only Arg Count: 6
                    Stack Size: 8
                    Flags: 0x20000003 (CO_OPTIMIZED | CO_NEWLOCALS | CO_PYARMOR_OBFUSCATED)
                    [Names]
                        'types'
                        'KeyboardButtonRequestPoll'
                    [Locals+Names]
                        'cls'
                        'text'
                        'force_quiz'
                        'resize'
                        'single_use'
                        'selective'
                        'persistent'
                        'placeholder'
                        '__assert_armored__'
                    [Constants]
                        '\n        Creates a new keyboard button to request the user to create a poll.\n\n        If `force_quiz` is `False`, the user will be allowed to choose whether\n        they want their poll to be a quiz or not. Otherwise, the user will be\n        forced to create a quiz when creating the poll.\n\n        If a poll is a quiz, there will be only one answer that is valid, and\n        the votes cannot be retracted. Otherwise, users can vote and retract\n        the vote, and the pol might be multiple choice.\n\n        ``resize``, ``single_use``, ``selective``, ``persistent`` and ``placeholder``\n         are documented in `text`.\n\n        When the user clicks this button, a screen letting the user create a\n        poll will be shown, and if they do create one, the poll will be sent.\n        '
                        '__pyarmor_assert_23997__'
                        '__pyarmor_enter_23998__'
                        b'<COAddr>\x07\x00\x00\x1aZ\x00\x00\x00\x00\x00\x00\x00\x00\x00\x00\x00\x00\x00\x00\x00'
                        (
                            'quiz'
                        )
                        (
                            'resize'
                            'single_use'
                            'selective'
                            'persistent'
                            'placeholder'
                        )
                        '__pyarmor_exit_23999__'
                    [Disassembly]
                        0       NOP                             
                        2       NOP                             
                        4       PUSH_NULL                       
                        6       LOAD_CONST                      2: '__pyarmor_enter_23998__'
                        8       LOAD_CONST                      3: b'<COAddr>\x07\x00\x00\x1aZ\x00\x00\x00\x00\x00\x00\x00\x00\x00\x00\x00\x00\x00\x00\x00'
                        10      BUILD_TUPLE                     1
                        12      CALL_FUNCTION_EX                0
                        14      POP_TOP                         
                        16      RESUME                          0
                        18      NOP                             
                        20      NOP                             
                        22      NOP                             
                        24      NOP                             
                        26      NOP                             
                        28      PUSH_NULL                       
                        30      LOAD_FAST                       0: cls
                        32      LOAD_GLOBAL                     1: NULL + types
                        42      LOAD_ATTR                       2: KeyboardButtonRequestPoll
                        62      LOAD_FAST                       1: text
                        64      LOAD_FAST                       2: force_quiz
                        66      KW_NAMES                        4: ('quiz',)
                        68      CALL                            2
                        76      LOAD_FAST                       3: resize
                        78      LOAD_FAST                       4: single_use
                        80      LOAD_FAST                       5: selective
                        82      LOAD_FAST                       6: persistent
                        84      LOAD_FAST                       7: placeholder
                        86      KW_NAMES                        5: ('resize', 'single_use', 'selective', 'persistent', 'placeholder')
                        88      CALL                            6
                        96      NOP                             
                        98      NOP                             
                        100     NOP                             
                        102     JUMP_FORWARD                    20 (to 144)
                        104     CALL                            1
                        112     POP_TOP                         
                        114     RETURN_VALUE                    
                        116     PUSH_EXC_INFO                   
                        118     PUSH_NULL                       
                        120     LOAD_CONST                      6: '__pyarmor_exit_23999__'
                        122     NOP                             
                        124     LOAD_CONST                      3: b'<COAddr>\x07\x00\x00\x1aZ\x00\x00\x00\x00\x00\x00\x00\x00\x00\x00\x00\x00\x00\x00\x00'
                        126     CALL                            1
                        134     POP_TOP                         
                        136     RERAISE                         0
                        138     COPY                            3
                        140     POP_EXCEPT                      
                        142     RERAISE                         1
                        144     PUSH_NULL                       
                        146     LOAD_CONST                      6: '__pyarmor_exit_23999__'
                        148     LOAD_CONST                      3: b'<COAddr>\x07\x00\x00\x1aZ\x00\x00\x00\x00\x00\x00\x00\x00\x00\x00\x00\x00\x00\x00\x00'
                        150     BUILD_TUPLE                     1
                        152     CALL_FUNCTION_EX                0
                        154     POP_TOP                         
                        156     RETURN_VALUE                    
                    [Exception Table]
                        28 to 96 -> 116 [0] 
                        116 to 138 -> 138 [1] lasti
                [Code]
                    File Name: <frozen multithon.tl.custom.button>
                    Object Name: clear
                    Qualified Name: Button.clear
                    Arg Count: 1
                    Pos Only Arg Count: 0
                    KW Only Arg Count: 0
                    Stack Size: 5
                    Flags: 0x20000003 (CO_OPTIMIZED | CO_NEWLOCALS | CO_PYARMOR_OBFUSCATED)
                    [Names]
                        'types'
                        'ReplyKeyboardHide'
                    [Locals+Names]
                        'selective'
                        '__assert_armored__'
                    [Constants]
                        '\n        Clears all keyboard buttons after sending a message with this markup.\n        When used, no other button should be present or it will be ignored.\n\n       ``selective`` is as documented in `text`.\n\n        '
                        '__pyarmor_assert_24000__'
                        '__pyarmor_enter_24001__'
                        b'<COAddr>\x07\x00\x00\x1a@\x00\x00\x00\x00\x00\x00\x00\x00\x00\x00\x00\x00\x00\x00\x00'
                        (
                            'selective'
                        )
                        '__pyarmor_exit_24002__'
                    [Disassembly]
                        0       NOP                             
                        2       NOP                             
                        4       PUSH_NULL                       
                        6       LOAD_CONST                      2: '__pyarmor_enter_24001__'
                        8       LOAD_CONST                      3: b'<COAddr>\x07\x00\x00\x1a@\x00\x00\x00\x00\x00\x00\x00\x00\x00\x00\x00\x00\x00\x00\x00'
                        10      BUILD_TUPLE                     1
                        12      CALL_FUNCTION_EX                0
                        14      POP_TOP                         
                        16      RESUME                          0
                        18      NOP                             
                        20      NOP                             
                        22      NOP                             
                        24      NOP                             
                        26      NOP                             
                        28      LOAD_GLOBAL                     1: NULL + types
                        38      LOAD_ATTR                       2: ReplyKeyboardHide
                        58      LOAD_FAST                       0: selective
                        60      KW_NAMES                        4: ('selective',)
                        62      CALL                            1
                        70      NOP                             
                        72      NOP                             
                        74      NOP                             
                        76      JUMP_FORWARD                    20 (to 118)
                        78      CALL                            1
                        86      POP_TOP                         
                        88      RETURN_VALUE                    
                        90      PUSH_EXC_INFO                   
                        92      PUSH_NULL                       
                        94      LOAD_CONST                      5: '__pyarmor_exit_24002__'
                        96      NOP                             
                        98      LOAD_CONST                      3: b'<COAddr>\x07\x00\x00\x1a@\x00\x00\x00\x00\x00\x00\x00\x00\x00\x00\x00\x00\x00\x00\x00'
                        100     CALL                            1
                        108     POP_TOP                         
                        110     RERAISE                         0
                        112     COPY                            3
                        114     POP_EXCEPT                      
                        116     RERAISE                         1
                        118     PUSH_NULL                       
                        120     LOAD_CONST                      5: '__pyarmor_exit_24002__'
                        122     LOAD_CONST                      3: b'<COAddr>\x07\x00\x00\x1a@\x00\x00\x00\x00\x00\x00\x00\x00\x00\x00\x00\x00\x00\x00\x00'
                        124     BUILD_TUPLE                     1
                        126     CALL_FUNCTION_EX                0
                        128     POP_TOP                         
                        130     RETURN_VALUE                    
                    [Exception Table]
                        28 to 70 -> 90 [0] 
                        90 to 112 -> 112 [1] lasti
                [Code]
                    File Name: <frozen multithon.tl.custom.button>
                    Object Name: force_reply
                    Qualified Name: Button.force_reply
                    Arg Count: 3
                    Pos Only Arg Count: 0
                    KW Only Arg Count: 0
                    Stack Size: 5
                    Flags: 0x20000003 (CO_OPTIMIZED | CO_NEWLOCALS | CO_PYARMOR_OBFUSCATED)
                    [Names]
                        'types'
                        'ReplyKeyboardForceReply'
                    [Locals+Names]
                        'single_use'
                        'selective'
                        'placeholder'
                        '__assert_armored__'
                    [Constants]
                        '\n        Forces a reply to the message with this markup. If used,\n        no other button should be present or it will be ignored.\n\n        ``single_use``, ``selective`` and ``placeholder`` are as documented in `text`.\n\n        '
                        '__pyarmor_assert_24003__'
                        '__pyarmor_enter_24004__'
                        b'<COAddr>\x07\x00\x00\x1aD\x00\x00\x00\x00\x00\x00\x00\x00\x00\x00\x00\x00\x00\x00\x00'
                        (
                            'single_use'
                            'selective'
                            'placeholder'
                        )
                        '__pyarmor_exit_24005__'
                    [Disassembly]
                        0       NOP                             
                        2       NOP                             
                        4       PUSH_NULL                       
                        6       LOAD_CONST                      2: '__pyarmor_enter_24004__'
                        8       LOAD_CONST                      3: b'<COAddr>\x07\x00\x00\x1aD\x00\x00\x00\x00\x00\x00\x00\x00\x00\x00\x00\x00\x00\x00\x00'
                        10      BUILD_TUPLE                     1
                        12      CALL_FUNCTION_EX                0
                        14      POP_TOP                         
                        16      RESUME                          0
                        18      NOP                             
                        20      NOP                             
                        22      NOP                             
                        24      NOP                             
                        26      NOP                             
                        28      LOAD_GLOBAL                     1: NULL + types
                        38      LOAD_ATTR                       2: ReplyKeyboardForceReply
                        58      LOAD_FAST                       0: single_use
                        60      LOAD_FAST                       1: selective
                        62      LOAD_FAST                       2: placeholder
                        64      KW_NAMES                        4: ('single_use', 'selective', 'placeholder')
                        66      CALL                            3
                        74      NOP                             
                        76      NOP                             
                        78      NOP                             
                        80      JUMP_FORWARD                    20 (to 122)
                        82      CALL                            1
                        90      POP_TOP                         
                        92      RETURN_VALUE                    
                        94      PUSH_EXC_INFO                   
                        96      PUSH_NULL                       
                        98      LOAD_CONST                      5: '__pyarmor_exit_24005__'
                        100     NOP                             
                        102     LOAD_CONST                      3: b'<COAddr>\x07\x00\x00\x1aD\x00\x00\x00\x00\x00\x00\x00\x00\x00\x00\x00\x00\x00\x00\x00'
                        104     CALL                            1
                        112     POP_TOP                         
                        114     RERAISE                         0
                        116     COPY                            3
                        118     POP_EXCEPT                      
                        120     RERAISE                         1
                        122     PUSH_NULL                       
                        124     LOAD_CONST                      5: '__pyarmor_exit_24005__'
                        126     LOAD_CONST                      3: b'<COAddr>\x07\x00\x00\x1aD\x00\x00\x00\x00\x00\x00\x00\x00\x00\x00\x00\x00\x00\x00\x00'
                        128     BUILD_TUPLE                     1
                        130     CALL_FUNCTION_EX                0
                        132     POP_TOP                         
                        134     RETURN_VALUE                    
                    [Exception Table]
                        28 to 74 -> 94 [0] 
                        94 to 116 -> 116 [1] lasti
                [Code]
                    File Name: <frozen multithon.tl.custom.button>
                    Object Name: buy
                    Qualified Name: Button.buy
                    Arg Count: 1
                    Pos Only Arg Count: 0
                    KW Only Arg Count: 0
                    Stack Size: 5
                    Flags: 0x20000003 (CO_OPTIMIZED | CO_NEWLOCALS | CO_PYARMOR_OBFUSCATED)
                    [Names]
                        'types'
                        'KeyboardButtonBuy'
                    [Locals+Names]
                        'text'
                        '__assert_armored__'
                    [Constants]
                        '\n        Creates a new inline button to buy a product.\n\n        This can only be used when sending files of type\n        :tl:`InputMediaInvoice`, and must be the first button.\n\n        If the button is not specified, Telegram will automatically\n        add the button to the message. See the\n        `Payments API <https://core.telegram.org/api/payments>`__\n        documentation for more information.\n        '
                        '__pyarmor_assert_24006__'
                        '__pyarmor_enter_24007__'
                        b'<COAddr>\x07\x00\x00\x1a>\x00\x00\x00\x00\x00\x00\x00\x00\x00\x00\x00\x00\x00\x00\x00'
                        '__pyarmor_exit_24008__'
                    [Disassembly]
                        0       NOP                             
                        2       NOP                             
                        4       PUSH_NULL                       
                        6       LOAD_CONST                      2: '__pyarmor_enter_24007__'
                        8       LOAD_CONST                      3: b'<COAddr>\x07\x00\x00\x1a>\x00\x00\x00\x00\x00\x00\x00\x00\x00\x00\x00\x00\x00\x00\x00'
                        10      BUILD_TUPLE                     1
                        12      CALL_FUNCTION_EX                0
                        14      POP_TOP                         
                        16      RESUME                          0
                        18      NOP                             
                        20      NOP                             
                        22      NOP                             
                        24      NOP                             
                        26      NOP                             
                        28      LOAD_GLOBAL                     1: NULL + types
                        38      LOAD_ATTR                       2: KeyboardButtonBuy
                        58      LOAD_FAST                       0: text
                        60      CALL                            1
                        68      NOP                             
                        70      NOP                             
                        72      NOP                             
                        74      JUMP_FORWARD                    20 (to 116)
                        76      CALL                            1
                        84      POP_TOP                         
                        86      RETURN_VALUE                    
                        88      PUSH_EXC_INFO                   
                        90      PUSH_NULL                       
                        92      LOAD_CONST                      4: '__pyarmor_exit_24008__'
                        94      NOP                             
                        96      LOAD_CONST                      3: b'<COAddr>\x07\x00\x00\x1a>\x00\x00\x00\x00\x00\x00\x00\x00\x00\x00\x00\x00\x00\x00\x00'
                        98      CALL                            1
                        106     POP_TOP                         
                        108     RERAISE                         0
                        110     COPY                            3
                        112     POP_EXCEPT                      
                        114     RERAISE                         1
                        116     PUSH_NULL                       
                        118     LOAD_CONST                      4: '__pyarmor_exit_24008__'
                        120     LOAD_CONST                      3: b'<COAddr>\x07\x00\x00\x1a>\x00\x00\x00\x00\x00\x00\x00\x00\x00\x00\x00\x00\x00\x00\x00'
                        122     BUILD_TUPLE                     1
                        124     CALL_FUNCTION_EX                0
                        126     POP_TOP                         
                        128     RETURN_VALUE                    
                    [Exception Table]
                        28 to 68 -> 88 [0] 
                        88 to 110 -> 110 [1] lasti
                [Code]
                    File Name: <frozen multithon.tl.custom.button>
                    Object Name: game
                    Qualified Name: Button.game
                    Arg Count: 1
                    Pos Only Arg Count: 0
                    KW Only Arg Count: 0
                    Stack Size: 5
                    Flags: 0x20000003 (CO_OPTIMIZED | CO_NEWLOCALS | CO_PYARMOR_OBFUSCATED)
                    [Names]
                        'types'
                        'KeyboardButtonGame'
                    [Locals+Names]
                        'text'
                        '__assert_armored__'
                    [Constants]
                        '\n        Creates a new inline button to start playing a game.\n\n        This should be used when sending files of type\n        :tl:`InputMediaGame`, and must be the first button.\n\n        See the\n        `Games <https://core.telegram.org/api/bots/games>`__\n        documentation for more information on using games.\n        '
                        '__pyarmor_assert_24009__'
                        '__pyarmor_enter_24010__'
                        b'<COAddr>\x07\x00\x00\x1a>\x00\x00\x00\x00\x00\x00\x00\x00\x00\x00\x00\x00\x00\x00\x00'
                        '__pyarmor_exit_24011__'
                    [Disassembly]
                        0       NOP                             
                        2       NOP                             
                        4       PUSH_NULL                       
                        6       LOAD_CONST                      2: '__pyarmor_enter_24010__'
                        8       LOAD_CONST                      3: b'<COAddr>\x07\x00\x00\x1a>\x00\x00\x00\x00\x00\x00\x00\x00\x00\x00\x00\x00\x00\x00\x00'
                        10      BUILD_TUPLE                     1
                        12      CALL_FUNCTION_EX                0
                        14      POP_TOP                         
                        16      RESUME                          0
                        18      NOP                             
                        20      NOP                             
                        22      NOP                             
                        24      NOP                             
                        26      NOP                             
                        28      LOAD_GLOBAL                     1: NULL + types
                        38      LOAD_ATTR                       2: KeyboardButtonGame
                        58      LOAD_FAST                       0: text
                        60      CALL                            1
                        68      NOP                             
                        70      NOP                             
                        72      NOP                             
                        74      JUMP_FORWARD                    20 (to 116)
                        76      CALL                            1
                        84      POP_TOP                         
                        86      RETURN_VALUE                    
                        88      PUSH_EXC_INFO                   
                        90      PUSH_NULL                       
                        92      LOAD_CONST                      4: '__pyarmor_exit_24011__'
                        94      NOP                             
                        96      LOAD_CONST                      3: b'<COAddr>\x07\x00\x00\x1a>\x00\x00\x00\x00\x00\x00\x00\x00\x00\x00\x00\x00\x00\x00\x00'
                        98      CALL                            1
                        106     POP_TOP                         
                        108     RERAISE                         0
                        110     COPY                            3
                        112     POP_EXCEPT                      
                        114     RERAISE                         1
                        116     PUSH_NULL                       
                        118     LOAD_CONST                      4: '__pyarmor_exit_24011__'
                        120     LOAD_CONST                      3: b'<COAddr>\x07\x00\x00\x1a>\x00\x00\x00\x00\x00\x00\x00\x00\x00\x00\x00\x00\x00\x00\x00'
                        122     BUILD_TUPLE                     1
                        124     CALL_FUNCTION_EX                0
                        126     POP_TOP                         
                        128     RETURN_VALUE                    
                    [Exception Table]
                        28 to 68 -> 88 [0] 
                        88 to 110 -> 110 [1] lasti
                '__pyarmor_exit_23969__'
                (
                    None
                )
                (
                    ''
                    False
                )
                (
                    None
                    None
                    None
                )
            [Disassembly]
                0       NOP                             
                2       LOAD_NAME                       0: __name__
                4       STORE_NAME                      1: __module__
                6       LOAD_CONST                      0: 'Button'
                8       STORE_NAME                      2: __qualname__
                10      LOAD_CONST                      1: "\n    .. note::\n\n        This class is used to **define** reply markups, e.g. when\n        sending a message or replying to events. When you access\n        `Message.buttons <telethon.tl.custom.message.Message.buttons>`\n        they are actually `MessageButton\n        <telethon.tl.custom.messagebutton.MessageButton>`,\n        so you might want to refer to that class instead.\n\n    Helper class to allow defining ``reply_markup`` when\n    sending a message with inline or keyboard buttons.\n\n    You should make use of the defined class methods to create button\n    instances instead making them yourself (i.e. don't do ``Button(...)``\n    but instead use methods line `Button.inline(...) <inline>` etc.\n\n    You can use `inline`, `switch_inline`, `url`, `auth`, `buy` and `game`\n    together to create inline buttons (under the message).\n\n    You can use `text`, `request_location`, `request_phone` and `request_poll`\n    together to create a reply markup (replaces the user keyboard).\n    You can also configure the aspect of the reply with these.\n    The latest message with a reply markup will be the one shown to the user\n    (messages contain the buttons, not the chat itself).\n\n    You **cannot** mix the two type of buttons together,\n    and it will error if you try to do so.\n\n    The text for all buttons may be at most 142 characters.\n    If more characters are given, Telegram will cut the text\n    to 128 characters and add the ellipsis (…) character as\n    the 129.\n    "
                12      STORE_NAME                      3: __doc__
                14      NOP                             
                16      PUSH_NULL                       
                18      LOAD_CONST                      3: '__pyarmor_enter_23968__'
                20      LOAD_CONST                      4: b'<COAddr>\x05\x00\x00&<\x01\x00\x00\x00\x00\x00\x00\x00\x00\x00\x00\x00\x00\x00\x00'
                22      BUILD_TUPLE                     1
                24      CALL_FUNCTION_EX                0
                26      POP_TOP                         
                28      RESUME                          0
                30      NOP                             
                32      NOP                             
                34      NOP                             
                36      NOP                             
                38      NOP                             
                40      LOAD_CONST                      5: <CODE> __init__
                42      MAKE_FUNCTION                   0
                44      STORE_NAME                      5: __init__
                46      LOAD_NAME                       6: staticmethod
                48      LOAD_CONST                      6: <CODE> _is_inline
                50      MAKE_FUNCTION                   0
                52      CALL                            0
                60      STORE_NAME                      7: _is_inline
                62      LOAD_NAME                       6: staticmethod
                64      LOAD_CONST                      25: (None,)
                66      LOAD_CONST                      8: <CODE> inline
                68      MAKE_FUNCTION                   1
                70      CALL                            0
                78      STORE_NAME                      8: inline
                80      LOAD_NAME                       6: staticmethod
                82      LOAD_CONST                      26: ('', False)
                84      LOAD_CONST                      10: <CODE> switch_inline
                86      MAKE_FUNCTION                   1
                88      CALL                            0
                96      STORE_NAME                      9: switch_inline
                98      LOAD_NAME                       6: staticmethod
                100     LOAD_CONST                      25: (None,)
                102     LOAD_CONST                      11: <CODE> url
                104     MAKE_FUNCTION                   1
                106     CALL                            0
                114     STORE_NAME                      10: url
                116     LOAD_NAME                       6: staticmethod
                118     LOAD_CONST                      25: (None,)
                120     LOAD_CONST                      7: None
                122     LOAD_CONST                      9: False
                124     LOAD_CONST                      7: None
                126     LOAD_CONST                      12: ('bot', 'write_access', 'fwd_text')
                128     BUILD_CONST_KEY_MAP             3
                130     LOAD_CONST                      13: <CODE> auth
                132     MAKE_FUNCTION                   3
                134     CALL                            0
                142     STORE_NAME                      11: auth
                144     LOAD_NAME                       12: classmethod
                146     LOAD_CONST                      7: None
                148     LOAD_CONST                      7: None
                150     LOAD_CONST                      7: None
                152     LOAD_CONST                      7: None
                154     LOAD_CONST                      7: None
                156     LOAD_CONST                      14: ('resize', 'single_use', 'selective', 'persistent', 'placeholder')
                158     BUILD_CONST_KEY_MAP             5
                160     LOAD_CONST                      15: <CODE> text
                162     MAKE_FUNCTION                   2
                164     CALL                            0
                172     STORE_NAME                      13: text
                174     LOAD_NAME                       12: classmethod
                176     LOAD_CONST                      7: None
                178     LOAD_CONST                      7: None
                180     LOAD_CONST                      7: None
                182     LOAD_CONST                      7: None
                184     LOAD_CONST                      7: None
                186     LOAD_CONST                      14: ('resize', 'single_use', 'selective', 'persistent', 'placeholder')
                188     BUILD_CONST_KEY_MAP             5
                190     LOAD_CONST                      16: <CODE> request_location
                192     MAKE_FUNCTION                   2
                194     CALL                            0
                202     STORE_NAME                      14: request_location
                204     LOAD_NAME                       12: classmethod
                206     LOAD_CONST                      7: None
                208     LOAD_CONST                      7: None
                210     LOAD_CONST                      7: None
                212     LOAD_CONST                      7: None
                214     LOAD_CONST                      7: None
                216     LOAD_CONST                      14: ('resize', 'single_use', 'selective', 'persistent', 'placeholder')
                218     BUILD_CONST_KEY_MAP             5
                220     LOAD_CONST                      17: <CODE> request_phone
                222     MAKE_FUNCTION                   2
                224     CALL                            0
                232     STORE_NAME                      15: request_phone
                234     LOAD_NAME                       12: classmethod
                236     LOAD_CONST                      9: False
                238     LOAD_CONST                      7: None
                240     LOAD_CONST                      7: None
                242     LOAD_CONST                      7: None
                244     LOAD_CONST                      7: None
                246     LOAD_CONST                      7: None
                248     LOAD_CONST                      18: ('force_quiz', 'resize', 'single_use', 'selective', 'persistent', 'placeholder')
                250     BUILD_CONST_KEY_MAP             6
                252     LOAD_CONST                      19: <CODE> request_poll
                254     MAKE_FUNCTION                   2
                256     CALL                            0
                264     STORE_NAME                      16: request_poll
                266     LOAD_NAME                       6: staticmethod
                268     LOAD_CONST                      25: (None,)
                270     LOAD_CONST                      20: <CODE> clear
                272     MAKE_FUNCTION                   1
                274     CALL                            0
                282     STORE_NAME                      17: clear
                284     LOAD_NAME                       6: staticmethod
                286     LOAD_CONST                      27: (None, None, None)
                288     LOAD_CONST                      21: <CODE> force_reply
                290     MAKE_FUNCTION                   1
                292     CALL                            0
                300     STORE_NAME                      18: force_reply
                302     LOAD_NAME                       6: staticmethod
                304     LOAD_CONST                      22: <CODE> buy
                306     MAKE_FUNCTION                   0
                308     CALL                            0
                316     STORE_NAME                      19: buy
                318     LOAD_NAME                       6: staticmethod
                320     LOAD_CONST                      23: <CODE> game
                322     MAKE_FUNCTION                   0
                324     CALL                            0
                332     STORE_NAME                      20: game
                334     LOAD_CONST                      7: None
                336     NOP                             
                338     NOP                             
                340     NOP                             
                342     JUMP_FORWARD                    19 (to 382)
                350     POP_TOP                         
                352     RETURN_CONST                    7: None
                354     PUSH_EXC_INFO                   
                356     PUSH_NULL                       
                358     LOAD_CONST                      24: '__pyarmor_exit_23969__'
                360     NOP                             
                362     LOAD_CONST                      4: b'<COAddr>\x05\x00\x00&<\x01\x00\x00\x00\x00\x00\x00\x00\x00\x00\x00\x00\x00\x00\x00'
                364     CALL                            1
                372     POP_TOP                         
                374     RERAISE                         0
                376     COPY                            3
                378     POP_EXCEPT                      
                380     RERAISE                         1
                382     PUSH_NULL                       
                384     LOAD_CONST                      24: '__pyarmor_exit_23969__'
                386     LOAD_CONST                      4: b'<COAddr>\x05\x00\x00&<\x01\x00\x00\x00\x00\x00\x00\x00\x00\x00\x00\x00\x00\x00\x00'
                388     BUILD_TUPLE                     1
                390     CALL_FUNCTION_EX                0
                392     POP_TOP                         
                394     RETURN_VALUE                    
            [Exception Table]
                40 to 334 -> 354 [0] 
                354 to 376 -> 376 [1] lasti
        'Button'
        '__pyarmor_exit_23966__'
        None
    [Disassembly]
        0       NOP                             
        2       NOP                             
        4       PUSH_NULL                       
        6       LOAD_CONST                      1: '__pyarmor_enter_23965__'
        8       LOAD_CONST                      2: b'<COAddr>\x07\x00\x00\x1a@\x00\x00\x00\x00\x00\x00\x00\x00\x00\x00\x00\x00\x00\x00\x00'
        10      BUILD_TUPLE                     1
        12      CALL_FUNCTION_EX                0
        14      POP_TOP                         
        16      RESUME                          0
        18      NOP                             
        20      NOP                             
        22      NOP                             
        24      NOP                             
        26      LOAD_CONST                      3: 2
        28      LOAD_CONST                      4: ('types',)
        30      IMPORT_NAME                     1: 
        32      IMPORT_FROM                     2: types
        34      STORE_NAME                      2: types
        36      POP_TOP                         
        38      LOAD_CONST                      5: 3
        40      LOAD_CONST                      6: ('utils',)
        42      IMPORT_NAME                     1: 
        44      IMPORT_FROM                     3: utils
        46      STORE_NAME                      3: utils
        48      POP_TOP                         
        50      PUSH_NULL                       
        52      LOAD_BUILD_CLASS                
        54      LOAD_CONST                      7: <CODE> Button
        56      MAKE_FUNCTION                   0
        58      LOAD_CONST                      8: 'Button'
        60      CALL                            2
        68      STORE_NAME                      4: Button
        70      LOAD_CONST                      10: None
        72      NOP                             
        74      NOP                             
        76      NOP                             
        78      JUMP_FORWARD                    19 (to 118)
        86      POP_TOP                         
        88      RETURN_CONST                    10: None
        90      PUSH_EXC_INFO                   
        92      PUSH_NULL                       
        94      LOAD_CONST                      9: '__pyarmor_exit_23966__'
        96      NOP                             
        98      LOAD_CONST                      2: b'<COAddr>\x07\x00\x00\x1a@\x00\x00\x00\x00\x00\x00\x00\x00\x00\x00\x00\x00\x00\x00\x00'
        100     CALL                            1
        108     POP_TOP                         
        110     RERAISE                         0
        112     COPY                            3
        114     POP_EXCEPT                      
        116     RERAISE                         1
        118     PUSH_NULL                       
        120     LOAD_CONST                      9: '__pyarmor_exit_23966__'
        122     LOAD_CONST                      2: b'<COAddr>\x07\x00\x00\x1a@\x00\x00\x00\x00\x00\x00\x00\x00\x00\x00\x00\x00\x00\x00\x00'
        124     BUILD_TUPLE                     1
        126     CALL_FUNCTION_EX                0
        128     POP_TOP                         
        130     RETURN_VALUE                    
    [Exception Table]
        26 to 70 -> 90 [0] 
        90 to 112 -> 112 [1] lasti
