#decoded by lolz.live/mrpenny / t.me/zeus_jackpot
# ================================
# Примечания по Pyarmor:
# - Байт-код и объекты кода Pyarmor соответствуют стандартному Python, но присутствуют специальные вызовы функций среды выполнения (runtime) Pyarmor.
# - Вызовы строк — это не ошибки, а маркеры, которые обрабатываются Pyarmor во время выполнения.
#
# Руководство по декомпиляции (без среды выполнения):
# 1. Игнорируйте зашифрованные байты после `#`; используйте только строку до `#`.
# 2. Удалите "__pyarmor_enter_xxx__"(b"<COAddr>...") и "__pyarmor_leave_xxx__"(b"<COAddr>...") (пролог/эпилог).
# 3. "__pyarmor_assert_xxx__"(A) не является настоящим оператором assert.
#    - Если A — это имя или читаемая строка: замените на A.
#    - Если A — это (X, "Y"): замените на X.Y.
#    - Если A — это (X, "Y", Z): замените на X.Y = Z.
#    - В противном случае: выберите наиболее подходящую/логичную замену.
# 4. "__pyarmor_bcc_xxx__"(...) указывает на машинный (нативный) код; тело функции недоступно. Добавьте комментарий.
# ================================

[Code]
    File Name: <frozen multithon.tl.custom.conversation>
    Object Name: <module>
    Qualified Name: <module>
    Arg Count: 0
    Pos Only Arg Count: 0
    KW Only Arg Count: 0
    Stack Size: 5
    Flags: 0x20000000 (CO_PYARMOR_OBFUSCATED)
    [Names]
        '__assert_armored__'
        'asyncio'
        'functools'
        'inspect'
        'itertools'
        'time'
        'chatgetter'
        'ChatGetter'
        ''
        'helpers'
        'utils'
        'errors'
        '_EDIT_COLLISION_DELTA'
        '_checks_cancelled'
        'Conversation'
    [Locals+Names]
    [Constants]
        '__pyarmor_assert_24045__'
        '__pyarmor_enter_24046__'
        b'<COAddr>\x07\x00\x00\x1a|\x00\x00\x00\x00\x00\x00\x00\x00\x00\x00\x00\x00\x00\x00\x00'
        0
        None
        1
        (
            'ChatGetter'
        )
        3
        (
            'helpers'
            'utils'
            'errors'
        )
        0.001
        [Code]
            File Name: <frozen multithon.tl.custom.conversation>
            Object Name: _checks_cancelled
            Qualified Name: _checks_cancelled
            Arg Count: 1
            Pos Only Arg Count: 0
            KW Only Arg Count: 0
            Stack Size: 5
            Flags: 0x20000003 (CO_OPTIMIZED | CO_NEWLOCALS | CO_PYARMOR_OBFUSCATED)
            [Names]
                'functools'
                'wraps'
            [Locals+Names]
                'f'
                '__assert_armored__'
                '_var_var_0'
            [Constants]
                None
                '__pyarmor_assert_24048__'
                '__pyarmor_enter_24049__'
                b'<COAddr>\x07\x00\x00\x1cR\x00\x00\x00\x00\x00\x00\x00\x00\x00\x00\x00\x00\x00\x00\x00'
                [Code]
                    File Name: <frozen multithon.tl.custom.conversation>
                    Object Name: wrapper
                    Qualified Name: _checks_cancelled.<locals>.wrapper
                    Arg Count: 1
                    Pos Only Arg Count: 0
                    KW Only Arg Count: 0
                    Stack Size: 5
                    Flags: 0x2000001F (CO_OPTIMIZED | CO_NEWLOCALS | CO_VARARGS | CO_VARKEYWORDS | CO_NESTED | CO_PYARMOR_OBFUSCATED)
                    [Names]
                        '_cancelled'
                        'asyncio'
                        'CancelledError'
                    [Locals+Names]
                        'self'
                        'args'
                        'kwargs'
                        '__assert_armored__'
                        'f'
                    [Constants]
                        None
                        '__pyarmor_assert_24051__'
                        '__pyarmor_enter_24052__'
                        b'<COAddr>\x07\x00\x00\x1cz\x00\x00\x00\x00\x00\x00\x00\x00\x00\x00\x00\x00\x00\x00\x00'
                        'The conversation was cancelled before'   # b'\x81\xd6\x10\x16s\xf9\xb1\xdc\r\xff\x1f\xd3m\xf8\xf1\x8a\x01\x1d\xac\xa6\xb9\x8bM\xcd\x0bl\xa6P\x0c\xb4\x1a\xa58W&\x02\x8a\xcf'
                        '__pyarmor_exit_24053__'
                    [Disassembly]
                        0       COPY_FREE_VARS                  1
                        2       NOP                             
                        4       NOP                             
                        6       PUSH_NULL                       
                        8       LOAD_CONST                      2: '__pyarmor_enter_24052__'
                        10      LOAD_CONST                      3: b'<COAddr>\x07\x00\x00\x1cz\x00\x00\x00\x00\x00\x00\x00\x00\x00\x00\x00\x00\x00\x00\x00'
                        12      BUILD_TUPLE                     1
                        14      CALL_FUNCTION_EX                0
                        16      POP_TOP                         
                        18      RESUME                          0
                        20      NOP                             
                        22      NOP                             
                        24      NOP                             
                        26      NOP                             
                        28      NOP                             
                        30      LOAD_FAST                       0: self
                        32      LOAD_ATTR                       0: _cancelled
                        52      POP_JUMP_IF_FALSE               27 (to 108)
                        54      LOAD_GLOBAL                     3: NULL + asyncio
                        64      LOAD_ATTR                       4: CancelledError
                        84      PUSH_NULL                       
                        86      LOAD_CONST                      1: '__pyarmor_assert_24051__'
                        88      LOAD_CONST                      4: 'The conversation was cancelled before'   # b'\x81\xd6\x10\x16s\xf9\xb1\xdc\r\xff\x1f\xd3m\xf8\xf1\x8a\x01\x1d\xac\xa6\xb9\x8bM\xcd\x0bl\xa6P\x0c\xb4\x1a\xa58W&\x02\x8a\xcf'
                        90      CALL                            1
                        98      CALL                            1
                        106     RAISE_VARARGS                   1
                        108     PUSH_NULL                       
                        110     LOAD_DEREF                      4: f
                        112     LOAD_FAST                       0: self
                        114     BUILD_LIST                      1
                        116     LOAD_FAST                       1: args
                        118     LIST_EXTEND                     1
                        120     CALL_INTRINSIC_1                6 (INTRINSIC_LIST_TO_TUPLE)
                        122     BUILD_MAP                       0
                        124     LOAD_FAST                       2: kwargs
                        126     DICT_MERGE                      1
                        128     CALL_FUNCTION_EX                1
                        130     NOP                             
                        132     NOP                             
                        134     NOP                             
                        136     JUMP_FORWARD                    20 (to 178)
                        138     CALL                            1
                        146     POP_TOP                         
                        148     RETURN_VALUE                    
                        150     PUSH_EXC_INFO                   
                        152     PUSH_NULL                       
                        154     LOAD_CONST                      5: '__pyarmor_exit_24053__'
                        156     NOP                             
                        158     LOAD_CONST                      3: b'<COAddr>\x07\x00\x00\x1cz\x00\x00\x00\x00\x00\x00\x00\x00\x00\x00\x00\x00\x00\x00\x00'
                        160     CALL                            1
                        168     POP_TOP                         
                        170     RERAISE                         0
                        172     COPY                            3
                        174     POP_EXCEPT                      
                        176     RERAISE                         1
                        178     PUSH_NULL                       
                        180     LOAD_CONST                      5: '__pyarmor_exit_24053__'
                        182     LOAD_CONST                      3: b'<COAddr>\x07\x00\x00\x1cz\x00\x00\x00\x00\x00\x00\x00\x00\x00\x00\x00\x00\x00\x00\x00'
                        184     BUILD_TUPLE                     1
                        186     CALL_FUNCTION_EX                0
                        188     POP_TOP                         
                        190     RETURN_VALUE                    
                    [Exception Table]
                        30 to 130 -> 150 [0] 
                        150 to 172 -> 172 [1] lasti
                '__pyarmor_exit_24050__'
            [Disassembly]
                0       MAKE_CELL                       0: f
                2       NOP                             
                4       NOP                             
                6       PUSH_NULL                       
                8       LOAD_CONST                      2: '__pyarmor_enter_24049__'
                10      LOAD_CONST                      3: b'<COAddr>\x07\x00\x00\x1cR\x00\x00\x00\x00\x00\x00\x00\x00\x00\x00\x00\x00\x00\x00\x00'
                12      BUILD_TUPLE                     1
                14      CALL_FUNCTION_EX                0
                16      POP_TOP                         
                18      RESUME                          0
                20      NOP                             
                22      NOP                             
                24      NOP                             
                26      NOP                             
                28      NOP                             
                30      LOAD_GLOBAL                     1: NULL + functools
                40      LOAD_ATTR                       2: wraps
                60      LOAD_DEREF                      0: f
                62      CALL                            1
                70      LOAD_CLOSURE                    0: f
                72      BUILD_TUPLE                     1
                74      LOAD_CONST                      4: <CODE> wrapper
                76      MAKE_FUNCTION                   8
                78      CALL                            0
                86      STORE_FAST                      2: _var_var_0
                88      LOAD_FAST                       2: _var_var_0
                90      NOP                             
                92      NOP                             
                94      NOP                             
                96      JUMP_FORWARD                    20 (to 138)
                98      CALL                            1
                106     POP_TOP                         
                108     RETURN_VALUE                    
                110     PUSH_EXC_INFO                   
                112     PUSH_NULL                       
                114     LOAD_CONST                      5: '__pyarmor_exit_24050__'
                116     NOP                             
                118     LOAD_CONST                      3: b'<COAddr>\x07\x00\x00\x1cR\x00\x00\x00\x00\x00\x00\x00\x00\x00\x00\x00\x00\x00\x00\x00'
                120     CALL                            1
                128     POP_TOP                         
                130     RERAISE                         0
                132     COPY                            3
                134     POP_EXCEPT                      
                136     RERAISE                         1
                138     PUSH_NULL                       
                140     LOAD_CONST                      5: '__pyarmor_exit_24050__'
                142     LOAD_CONST                      3: b'<COAddr>\x07\x00\x00\x1cR\x00\x00\x00\x00\x00\x00\x00\x00\x00\x00\x00\x00\x00\x00\x00'
                144     BUILD_TUPLE                     1
                146     CALL_FUNCTION_EX                0
                148     POP_TOP                         
                150     RETURN_VALUE                    
            [Exception Table]
                30 to 90 -> 110 [0] 
                110 to 132 -> 132 [1] lasti
        [Code]
            File Name: <frozen multithon.tl.custom.conversation>
            Object Name: Conversation
            Qualified Name: Conversation
            Arg Count: 0
            Pos Only Arg Count: 0
            KW Only Arg Count: 0
            Stack Size: 5
            Flags: 0x20000000 (CO_PYARMOR_OBFUSCATED)
            [Names]
                '__name__'
                '__module__'
                '__qualname__'
                '__doc__'
                '__assert_armored__'
                '_id_counter'
                '_custom_counter'
                '__init__'
                '_checks_cancelled'
                'send_message'
                'send_file'
                'mark_read'
                'get_response'
                'get_reply'
                '_get_message'
                'get_edit'
                'wait_read'
                'wait_event'
                '_check_custom'
                '_on_new_message'
                '_on_edit'
                '_on_read'
                '_get_message_id'
                '_get_result'
                '_cancel_all'
                '__aenter__'
                'cancel'
                'cancel_all'
                '__aexit__'
                'helpers'
                '_sync_enter'
                '__enter__'
                '_sync_exit'
                '__exit__'
            [Locals+Names]
            [Constants]
                'Conversation'
                '\n    Represents a conversation inside an specific chat.\n\n    A conversation keeps track of new messages since it was\n    created until its exit and easily lets you query the\n    current state.\n\n    If you need a conversation across two or more chats,\n    you should use two conversations and synchronize them\n    as you better see fit.\n    '
                '__pyarmor_assert_24054__'
                '__pyarmor_enter_24055__'
                b'<COAddr>\x07\x00\x00&\x1e\x01\x00\x00\x00\x00\x00\x00\x00\x00\x00\x00\x00\x00\x00\x00'
                0
                [Code]
                    File Name: <frozen multithon.tl.custom.conversation>
                    Object Name: __init__
                    Qualified Name: Conversation.__init__
                    Arg Count: 3
                    Pos Only Arg Count: 0
                    KW Only Arg Count: 5
                    Stack Size: 5
                    Flags: 0x20000003 (CO_OPTIMIZED | CO_NEWLOCALS | CO_PYARMOR_OBFUSCATED)
                    [Names]
                        'ChatGetter'
                        '__init__'
                        'Conversation'
                        '_id_counter'
                        '_id'
                        '_client'
                        '_timeout'
                        '_total_timeout'
                        '_total_due'
                        'set'
                        '_outgoing'
                        '_last_outgoing'
                        '_incoming'
                        '_last_incoming'
                        '_max_incoming'
                        '_last_read'
                        '_custom'
                        '_pending_responses'
                        '_pending_replies'
                        '_pending_edits'
                        '_pending_reads'
                        '_exclusive'
                        '_cancelled'
                        '_response_indices'
                        '_reply_indices'
                        '_edit_dates'
                    [Locals+Names]
                        'self'
                        'client'
                        'input_chat'
                        'timeout'
                        'total_timeout'
                        'max_messages'
                        'exclusive'
                        'replies_are_responses'
                        '__assert_armored__'
                    [Constants]
                        None
                        '__pyarmor_assert_24057__'
                        '__pyarmor_enter_24058__'
                        b'<COAddr>\x07\x00\x00\x1a\xf0\x01\x00\x00\x00\x00\x00\x00\x00\x00\x00\x00\x00\x00\x00\x00'
                        (
                            'input_chat'
                        )
                        1
                        0
                        False
                        '__pyarmor_exit_24059__'
                    [Disassembly]
                        0       NOP                             
                        2       NOP                             
                        4       PUSH_NULL                       
                        6       LOAD_CONST                      2: '__pyarmor_enter_24058__'
                        8       LOAD_CONST                      3: b'<COAddr>\x07\x00\x00\x1a\xf0\x01\x00\x00\x00\x00\x00\x00\x00\x00\x00\x00\x00\x00\x00\x00'
                        10      BUILD_TUPLE                     1
                        12      CALL_FUNCTION_EX                0
                        14      POP_TOP                         
                        16      RESUME                          0
                        18      NOP                             
                        20      NOP                             
                        22      NOP                             
                        24      NOP                             
                        26      NOP                             
                        28      LOAD_GLOBAL                     1: NULL + ChatGetter
                        38      LOAD_ATTR                       2: __init__
                        58      LOAD_FAST                       0: self
                        60      LOAD_FAST                       2: input_chat
                        62      KW_NAMES                        4: ('input_chat',)
                        64      CALL                            2
                        72      POP_TOP                         
                        74      LOAD_GLOBAL                     4: Conversation
                        84      LOAD_ATTR                       6: _id_counter
                        104     LOAD_FAST                       0: self
                        106     STORE_ATTR                      4: _id
                        116     LOAD_GLOBAL                     4: Conversation
                        126     COPY                            1
                        128     LOAD_ATTR                       6: _id_counter
                        148     LOAD_CONST                      5: 1
                        150     BINARY_OP                       13 (+=)
                        154     SWAP                            2
                        156     STORE_ATTR                      3: _id_counter
                        166     LOAD_FAST                       1: client
                        168     LOAD_FAST                       0: self
                        170     STORE_ATTR                      5: _client
                        180     LOAD_FAST                       3: timeout
                        182     LOAD_FAST                       0: self
                        184     STORE_ATTR                      6: _timeout
                        194     LOAD_FAST                       4: total_timeout
                        196     LOAD_FAST                       0: self
                        198     STORE_ATTR                      7: _total_timeout
                        208     LOAD_CONST                      0: None
                        210     LOAD_FAST                       0: self
                        212     STORE_ATTR                      8: _total_due
                        222     LOAD_GLOBAL                     19: NULL + set
                        232     CALL                            0
                        240     LOAD_FAST                       0: self
                        242     STORE_ATTR                      10: _outgoing
                        252     LOAD_CONST                      6: 0
                        254     LOAD_FAST                       0: self
                        256     STORE_ATTR                      11: _last_outgoing
                        266     BUILD_LIST                      0
                        268     LOAD_FAST                       0: self
                        270     STORE_ATTR                      12: _incoming
                        280     LOAD_CONST                      6: 0
                        282     LOAD_FAST                       0: self
                        284     STORE_ATTR                      13: _last_incoming
                        294     LOAD_FAST                       5: max_messages
                        296     LOAD_FAST                       0: self
                        298     STORE_ATTR                      14: _max_incoming
                        308     LOAD_CONST                      0: None
                        310     LOAD_FAST                       0: self
                        312     STORE_ATTR                      15: _last_read
                        322     BUILD_MAP                       0
                        324     LOAD_FAST                       0: self
                        326     STORE_ATTR                      16: _custom
                        336     BUILD_MAP                       0
                        338     LOAD_FAST                       0: self
                        340     STORE_ATTR                      17: _pending_responses
                        350     BUILD_MAP                       0
                        352     LOAD_FAST                       0: self
                        354     STORE_ATTR                      18: _pending_replies
                        364     BUILD_MAP                       0
                        366     LOAD_FAST                       0: self
                        368     STORE_ATTR                      19: _pending_edits
                        378     BUILD_MAP                       0
                        380     LOAD_FAST                       0: self
                        382     STORE_ATTR                      20: _pending_reads
                        392     LOAD_FAST                       6: exclusive
                        394     LOAD_FAST                       0: self
                        396     STORE_ATTR                      21: _exclusive
                        406     LOAD_CONST                      7: False
                        408     LOAD_FAST                       0: self
                        410     STORE_ATTR                      22: _cancelled
                        420     BUILD_MAP                       0
                        422     LOAD_FAST                       0: self
                        424     STORE_ATTR                      23: _response_indices
                        434     LOAD_FAST                       7: replies_are_responses
                        436     POP_JUMP_IF_FALSE               18 (to 474)
                        438     LOAD_FAST                       0: self
                        440     LOAD_ATTR                       46: _response_indices
                        460     LOAD_FAST                       0: self
                        462     STORE_ATTR                      24: _reply_indices
                        472     JUMP_FORWARD                    7 (to 488)
                        474     BUILD_MAP                       0
                        476     LOAD_FAST                       0: self
                        478     STORE_ATTR                      24: _reply_indices
                        488     BUILD_MAP                       0
                        490     LOAD_FAST                       0: self
                        492     STORE_ATTR                      25: _edit_dates
                        502     LOAD_CONST                      0: None
                        504     NOP                             
                        506     NOP                             
                        508     NOP                             
                        510     JUMP_FORWARD                    19 (to 550)
                        518     POP_TOP                         
                        520     RETURN_CONST                    0: None
                        522     PUSH_EXC_INFO                   
                        524     PUSH_NULL                       
                        526     LOAD_CONST                      8: '__pyarmor_exit_24059__'
                        528     NOP                             
                        530     LOAD_CONST                      3: b'<COAddr>\x07\x00\x00\x1a\xf0\x01\x00\x00\x00\x00\x00\x00\x00\x00\x00\x00\x00\x00\x00\x00'
                        532     CALL                            1
                        540     POP_TOP                         
                        542     RERAISE                         0
                        544     COPY                            3
                        546     POP_EXCEPT                      
                        548     RERAISE                         1
                        550     PUSH_NULL                       
                        552     LOAD_CONST                      8: '__pyarmor_exit_24059__'
                        554     LOAD_CONST                      3: b'<COAddr>\x07\x00\x00\x1a\xf0\x01\x00\x00\x00\x00\x00\x00\x00\x00\x00\x00\x00\x00\x00\x00'
                        556     BUILD_TUPLE                     1
                        558     CALL_FUNCTION_EX                0
                        560     POP_TOP                         
                        562     RETURN_VALUE                    
                    [Exception Table]
                        28 to 502 -> 522 [0] 
                        522 to 544 -> 544 [1] lasti
                [Code]
                    File Name: <frozen multithon.tl.custom.conversation>
                    Object Name: send_message
                    Qualified Name: Conversation.send_message
                    Arg Count: 1
                    Pos Only Arg Count: 0
                    KW Only Arg Count: 0
                    Stack Size: 5
                    Flags: 0x2000008F (CO_OPTIMIZED | CO_NEWLOCALS | CO_VARARGS | CO_VARKEYWORDS | CO_COROUTINE | CO_PYARMOR_OBFUSCATED)
                    [Names]
                        '_client'
                        'send_message'
                        '_input_chat'
                        'isinstance'
                        'list'
                        '_outgoing'
                        'update'
                        'id'
                        '_last_outgoing'
                    [Locals+Names]
                        'self'
                        'args'
                        'kwargs'
                        '__assert_armored__'
                        '_var_var_1'
                        '_var_var_2'
                    [Constants]
                        '\n        Sends a message in the context of this conversation. Shorthand\n        for `telethon.client.messages.MessageMethods.send_message` with\n        ``entity`` already set.\n        '
                        '__pyarmor_assert_24060__'
                        '__pyarmor_enter_24061__'
                        b'<COAddr>\x07\x00\x00\x1e\x16\x01\x00\x00\x00\x00\x00\x00\x00\x00\x00\x00\x00\x00\x00\x00'
                        None
                        [Code]
                            File Name: <frozen multithon.tl.custom.conversation>
                            Object Name: <genexpr>
                            Qualified Name: Conversation.send_message.<locals>.<genexpr>
                            Arg Count: 1
                            Pos Only Arg Count: 0
                            KW Only Arg Count: 0
                            Stack Size: 2
                            Flags: 0x00000033 (CO_OPTIMIZED | CO_NEWLOCALS | CO_NESTED | CO_GENERATOR)
                            [Names]
                                'id'
                            [Locals+Names]
                                '.0'
                                '_var_var_3'
                            [Constants]
                                None
                            [Disassembly]
                                0       RETURN_GENERATOR                
                                2       POP_TOP                         
                                4       RESUME                          0
                                6       LOAD_FAST                       0: .0
                                8       FOR_ITER                        16 (to 42)
                                12      STORE_FAST                      1: _var_var_3
                                14      LOAD_FAST                       1: _var_var_3
                                16      LOAD_ATTR                       0: id
                                36      YIELD_VALUE                     1
                                38      RESUME                          1
                                40      POP_TOP                         
                                42      JUMP_BACKWARD                   18 (to 8)
                                44      END_FOR                         
                                46      RETURN_CONST                    0: None
                                48      CALL_INTRINSIC_1                3 (INTRINSIC_STOPITERATION_ERROR)
                                50      RERAISE                         1
                            [Exception Table]
                                4 to 48 -> 48 [0] lasti
                        -1
                        '__pyarmor_exit_24062__'
                    [Disassembly]
                        0       RETURN_GENERATOR                
                        2       POP_TOP                         
                        4       NOP                             
                        6       NOP                             
                        8       PUSH_NULL                       
                        10      LOAD_CONST                      2: '__pyarmor_enter_24061__'
                        12      LOAD_CONST                      3: b'<COAddr>\x07\x00\x00\x1e\x16\x01\x00\x00\x00\x00\x00\x00\x00\x00\x00\x00\x00\x00\x00\x00'
                        14      BUILD_TUPLE                     1
                        16      CALL_FUNCTION_EX                0
                        18      POP_TOP                         
                        20      RESUME                          0
                        22      NOP                             
                        24      NOP                             
                        26      NOP                             
                        28      NOP                             
                        30      NOP                             
                        32      PUSH_NULL                       
                        34      LOAD_FAST                       0: self
                        36      LOAD_ATTR                       0: _client
                        56      LOAD_ATTR                       2: send_message
                        76      LOAD_FAST                       0: self
                        78      LOAD_ATTR                       4: _input_chat
                        98      BUILD_LIST                      1
                        100     LOAD_FAST                       1: args
                        102     LIST_EXTEND                     1
                        104     CALL_INTRINSIC_1                6 (INTRINSIC_LIST_TO_TUPLE)
                        106     BUILD_MAP                       0
                        108     LOAD_FAST                       2: kwargs
                        110     DICT_MERGE                      1
                        112     CALL_FUNCTION_EX                1
                        114     GET_AWAITABLE                   0
                        116     LOAD_CONST                      4: None
                        118     SEND                            3 (to 126)
                        122     YIELD_VALUE                     3
                        124     RESUME                          3
                        126     JUMP_BACKWARD_NO_INTERRUPT      5 (to 118)
                        128     END_SEND                        
                        130     STORE_FAST                      4: _var_var_1
                        132     LOAD_GLOBAL                     7: NULL + isinstance
                        142     LOAD_FAST                       4: _var_var_1
                        144     LOAD_GLOBAL                     8: list
                        154     CALL                            2
                        162     POP_JUMP_IF_FALSE               2 (to 168)
                        164     LOAD_FAST                       4: _var_var_1
                        166     JUMP_FORWARD                    2 (to 172)
                        168     LOAD_FAST                       4: _var_var_1
                        170     BUILD_TUPLE                     1
                        172     STORE_FAST                      5: _var_var_2
                        174     LOAD_FAST                       0: self
                        176     LOAD_ATTR                       10: _outgoing
                        196     LOAD_ATTR                       13: update
                        216     LOAD_CONST                      5: <CODE> <genexpr>
                        218     MAKE_FUNCTION                   0
                        220     LOAD_FAST                       5: _var_var_2
                        222     GET_ITER                        
                        224     CALL                            0
                        232     CALL                            1
                        240     POP_TOP                         
                        242     LOAD_FAST                       5: _var_var_2
                        244     LOAD_CONST                      6: -1
                        246     BINARY_SUBSCR                   
                        250     LOAD_ATTR                       14: id
                        270     LOAD_FAST                       0: self
                        272     STORE_ATTR                      8: _last_outgoing
                        282     LOAD_FAST                       4: _var_var_1
                        284     NOP                             
                        286     NOP                             
                        288     NOP                             
                        290     JUMP_FORWARD                    24 (to 340)
                        292     CALL                            1
                        300     POP_TOP                         
                        302     RETURN_VALUE                    
                        304     CLEANUP_THROW                   
                        306     JUMP_BACKWARD                   90 (to 128)
                        308     PUSH_EXC_INFO                   
                        310     PUSH_NULL                       
                        312     LOAD_CONST                      7: '__pyarmor_exit_24062__'
                        314     NOP                             
                        316     LOAD_CONST                      3: b'<COAddr>\x07\x00\x00\x1e\x16\x01\x00\x00\x00\x00\x00\x00\x00\x00\x00\x00\x00\x00\x00\x00'
                        318     CALL                            1
                        326     POP_TOP                         
                        328     RERAISE                         0
                        330     COPY                            3
                        332     POP_EXCEPT                      
                        334     RERAISE                         1
                        336     CALL_INTRINSIC_1                3 (INTRINSIC_STOPITERATION_ERROR)
                        338     RERAISE                         1
                        340     PUSH_NULL                       
                        342     LOAD_CONST                      7: '__pyarmor_exit_24062__'
                        344     LOAD_CONST                      3: b'<COAddr>\x07\x00\x00\x1e\x16\x01\x00\x00\x00\x00\x00\x00\x00\x00\x00\x00\x00\x00\x00\x00'
                        346     BUILD_TUPLE                     1
                        348     CALL_FUNCTION_EX                0
                        350     POP_TOP                         
                        352     RETURN_VALUE                    
                    [Exception Table]
                        4 to 30 -> 336 [0] lasti
                        32 to 122 -> 308 [0] 
                        122 to 124 -> 304 [2] 
                        124 to 284 -> 308 [0] 
                        284 to 304 -> 336 [0] lasti
                        304 to 306 -> 308 [0] 
                        308 to 330 -> 330 [1] lasti
                        330 to 336 -> 336 [0] lasti
                [Code]
                    File Name: <frozen multithon.tl.custom.conversation>
                    Object Name: send_file
                    Qualified Name: Conversation.send_file
                    Arg Count: 1
                    Pos Only Arg Count: 0
                    KW Only Arg Count: 0
                    Stack Size: 5
                    Flags: 0x2000008F (CO_OPTIMIZED | CO_NEWLOCALS | CO_VARARGS | CO_VARKEYWORDS | CO_COROUTINE | CO_PYARMOR_OBFUSCATED)
                    [Names]
                        '_client'
                        'send_file'
                        '_input_chat'
                        'isinstance'
                        'list'
                        '_outgoing'
                        'update'
                        'id'
                        '_last_outgoing'
                    [Locals+Names]
                        'self'
                        'args'
                        'kwargs'
                        '__assert_armored__'
                        '_var_var_1'
                        '_var_var_2'
                    [Constants]
                        '\n        Sends a file in the context of this conversation. Shorthand\n        for `telethon.client.uploads.UploadMethods.send_file` with\n        ``entity`` already set.\n        '
                        '__pyarmor_assert_24063__'
                        '__pyarmor_enter_24064__'
                        b'<COAddr>\x05\x00\x00\x1e\x16\x01\x00\x00\x00\x00\x00\x00\x00\x00\x00\x00\x00\x00\x00\x00'
                        None
                        [Code]
                            File Name: <frozen multithon.tl.custom.conversation>
                            Object Name: <genexpr>
                            Qualified Name: Conversation.send_file.<locals>.<genexpr>
                            Arg Count: 1
                            Pos Only Arg Count: 0
                            KW Only Arg Count: 0
                            Stack Size: 2
                            Flags: 0x00000033 (CO_OPTIMIZED | CO_NEWLOCALS | CO_NESTED | CO_GENERATOR)
                            [Names]
                                'id'
                            [Locals+Names]
                                '.0'
                                '_var_var_3'
                            [Constants]
                                None
                            [Disassembly]
                                0       RETURN_GENERATOR                
                                2       POP_TOP                         
                                4       RESUME                          0
                                6       LOAD_FAST                       0: .0
                                8       FOR_ITER                        16 (to 42)
                                12      STORE_FAST                      1: _var_var_3
                                14      LOAD_FAST                       1: _var_var_3
                                16      LOAD_ATTR                       0: id
                                36      YIELD_VALUE                     1
                                38      RESUME                          1
                                40      POP_TOP                         
                                42      JUMP_BACKWARD                   18 (to 8)
                                44      END_FOR                         
                                46      RETURN_CONST                    0: None
                                48      CALL_INTRINSIC_1                3 (INTRINSIC_STOPITERATION_ERROR)
                                50      RERAISE                         1
                            [Exception Table]
                                4 to 48 -> 48 [0] lasti
                        -1
                        '__pyarmor_exit_24065__'
                    [Disassembly]
                        0       RETURN_GENERATOR                
                        2       POP_TOP                         
                        4       NOP                             
                        6       NOP                             
                        8       PUSH_NULL                       
                        10      LOAD_CONST                      2: '__pyarmor_enter_24064__'
                        12      LOAD_CONST                      3: b'<COAddr>\x05\x00\x00\x1e\x16\x01\x00\x00\x00\x00\x00\x00\x00\x00\x00\x00\x00\x00\x00\x00'
                        14      BUILD_TUPLE                     1
                        16      CALL_FUNCTION_EX                0
                        18      POP_TOP                         
                        20      RESUME                          0
                        22      NOP                             
                        24      NOP                             
                        26      NOP                             
                        28      NOP                             
                        30      NOP                             
                        32      PUSH_NULL                       
                        34      LOAD_FAST                       0: self
                        36      LOAD_ATTR                       0: _client
                        56      LOAD_ATTR                       2: send_file
                        76      LOAD_FAST                       0: self
                        78      LOAD_ATTR                       4: _input_chat
                        98      BUILD_LIST                      1
                        100     LOAD_FAST                       1: args
                        102     LIST_EXTEND                     1
                        104     CALL_INTRINSIC_1                6 (INTRINSIC_LIST_TO_TUPLE)
                        106     BUILD_MAP                       0
                        108     LOAD_FAST                       2: kwargs
                        110     DICT_MERGE                      1
                        112     CALL_FUNCTION_EX                1
                        114     GET_AWAITABLE                   0
                        116     LOAD_CONST                      4: None
                        118     SEND                            3 (to 126)
                        122     YIELD_VALUE                     3
                        124     RESUME                          3
                        126     JUMP_BACKWARD_NO_INTERRUPT      5 (to 118)
                        128     END_SEND                        
                        130     STORE_FAST                      4: _var_var_1
                        132     LOAD_GLOBAL                     7: NULL + isinstance
                        142     LOAD_FAST                       4: _var_var_1
                        144     LOAD_GLOBAL                     8: list
                        154     CALL                            2
                        162     POP_JUMP_IF_FALSE               2 (to 168)
                        164     LOAD_FAST                       4: _var_var_1
                        166     JUMP_FORWARD                    2 (to 172)
                        168     LOAD_FAST                       4: _var_var_1
                        170     BUILD_TUPLE                     1
                        172     STORE_FAST                      5: _var_var_2
                        174     LOAD_FAST                       0: self
                        176     LOAD_ATTR                       10: _outgoing
                        196     LOAD_ATTR                       13: update
                        216     LOAD_CONST                      5: <CODE> <genexpr>
                        218     MAKE_FUNCTION                   0
                        220     LOAD_FAST                       5: _var_var_2
                        222     GET_ITER                        
                        224     CALL                            0
                        232     CALL                            1
                        240     POP_TOP                         
                        242     LOAD_FAST                       5: _var_var_2
                        244     LOAD_CONST                      6: -1
                        246     BINARY_SUBSCR                   
                        250     LOAD_ATTR                       14: id
                        270     LOAD_FAST                       0: self
                        272     STORE_ATTR                      8: _last_outgoing
                        282     LOAD_FAST                       4: _var_var_1
                        284     NOP                             
                        286     NOP                             
                        288     NOP                             
                        290     JUMP_FORWARD                    24 (to 340)
                        292     CALL                            1
                        300     POP_TOP                         
                        302     RETURN_VALUE                    
                        304     CLEANUP_THROW                   
                        306     JUMP_BACKWARD                   90 (to 128)
                        308     PUSH_EXC_INFO                   
                        310     PUSH_NULL                       
                        312     LOAD_CONST                      7: '__pyarmor_exit_24065__'
                        314     NOP                             
                        316     LOAD_CONST                      3: b'<COAddr>\x05\x00\x00\x1e\x16\x01\x00\x00\x00\x00\x00\x00\x00\x00\x00\x00\x00\x00\x00\x00'
                        318     CALL                            1
                        326     POP_TOP                         
                        328     RERAISE                         0
                        330     COPY                            3
                        332     POP_EXCEPT                      
                        334     RERAISE                         1
                        336     CALL_INTRINSIC_1                3 (INTRINSIC_STOPITERATION_ERROR)
                        338     RERAISE                         1
                        340     PUSH_NULL                       
                        342     LOAD_CONST                      7: '__pyarmor_exit_24065__'
                        344     LOAD_CONST                      3: b'<COAddr>\x05\x00\x00\x1e\x16\x01\x00\x00\x00\x00\x00\x00\x00\x00\x00\x00\x00\x00\x00\x00'
                        346     BUILD_TUPLE                     1
                        348     CALL_FUNCTION_EX                0
                        350     POP_TOP                         
                        352     RETURN_VALUE                    
                    [Exception Table]
                        4 to 30 -> 336 [0] lasti
                        32 to 122 -> 308 [0] 
                        122 to 124 -> 304 [2] 
                        124 to 284 -> 308 [0] 
                        284 to 304 -> 336 [0] lasti
                        304 to 306 -> 308 [0] 
                        308 to 330 -> 330 [1] lasti
                        330 to 336 -> 336 [0] lasti
                None
                [Code]
                    File Name: <frozen multithon.tl.custom.conversation>
                    Object Name: mark_read
                    Qualified Name: Conversation.mark_read
                    Arg Count: 2
                    Pos Only Arg Count: 0
                    KW Only Arg Count: 0
                    Stack Size: 5
                    Flags: 0x20000003 (CO_OPTIMIZED | CO_NEWLOCALS | CO_PYARMOR_OBFUSCATED)
                    [Names]
                        '_incoming'
                        'id'
                        'isinstance'
                        'int'
                        '_client'
                        'send_read_acknowledge'
                        '_input_chat'
                    [Locals+Names]
                        'self'
                        'message'
                        '__assert_armored__'
                    [Constants]
                        '\n        Marks as read the latest received message if ``message is None``.\n        Otherwise, marks as read until the given message (or message ID).\n\n        This is equivalent to calling `client.send_read_acknowledge\n        <telethon.client.messages.MessageMethods.send_read_acknowledge>`.\n        '
                        '__pyarmor_assert_24066__'
                        '__pyarmor_enter_24067__'
                        b'<COAddr>\x07\x00\x00\x1a\xf0\x00\x00\x00\x00\x00\x00\x00\x00\x00\x00\x00\x00\x00\x00\x00'
                        -1
                        0
                        (
                            'max_id'
                        )
                        '__pyarmor_exit_24068__'
                    [Disassembly]
                        0       NOP                             
                        2       NOP                             
                        4       PUSH_NULL                       
                        6       LOAD_CONST                      2: '__pyarmor_enter_24067__'
                        8       LOAD_CONST                      3: b'<COAddr>\x07\x00\x00\x1a\xf0\x00\x00\x00\x00\x00\x00\x00\x00\x00\x00\x00\x00\x00\x00\x00'
                        10      BUILD_TUPLE                     1
                        12      CALL_FUNCTION_EX                0
                        14      POP_TOP                         
                        16      RESUME                          0
                        18      NOP                             
                        20      NOP                             
                        22      NOP                             
                        24      NOP                             
                        26      NOP                             
                        28      LOAD_FAST                       1: message
                        30      POP_JUMP_IF_NOT_NONE            41 (to 114)
                        32      LOAD_FAST                       0: self
                        34      LOAD_ATTR                       0: _incoming
                        54      POP_JUMP_IF_FALSE               26 (to 108)
                        56      LOAD_FAST                       0: self
                        58      LOAD_ATTR                       0: _incoming
                        78      LOAD_CONST                      4: -1
                        80      BINARY_SUBSCR                   
                        84      LOAD_ATTR                       2: id
                        104     STORE_FAST                      1: message
                        106     JUMP_FORWARD                    31 (to 170)
                        108     LOAD_CONST                      5: 0
                        110     STORE_FAST                      1: message
                        112     JUMP_FORWARD                    28 (to 170)
                        114     LOAD_GLOBAL                     5: NULL + isinstance
                        124     LOAD_FAST                       1: message
                        126     LOAD_GLOBAL                     6: int
                        136     CALL                            2
                        144     POP_JUMP_IF_TRUE                12 (to 170)
                        146     LOAD_FAST                       1: message
                        148     LOAD_ATTR                       2: id
                        168     STORE_FAST                      1: message
                        170     LOAD_FAST                       0: self
                        172     LOAD_ATTR                       8: _client
                        192     LOAD_ATTR                       11: send_read_acknowledge
                        212     LOAD_FAST                       0: self
                        214     LOAD_ATTR                       12: _input_chat
                        234     LOAD_FAST                       1: message
                        236     KW_NAMES                        6: ('max_id',)
                        238     CALL                            2
                        246     NOP                             
                        248     NOP                             
                        250     NOP                             
                        252     JUMP_FORWARD                    20 (to 294)
                        254     CALL                            1
                        262     POP_TOP                         
                        264     RETURN_VALUE                    
                        266     PUSH_EXC_INFO                   
                        268     PUSH_NULL                       
                        270     LOAD_CONST                      7: '__pyarmor_exit_24068__'
                        272     NOP                             
                        274     LOAD_CONST                      3: b'<COAddr>\x07\x00\x00\x1a\xf0\x00\x00\x00\x00\x00\x00\x00\x00\x00\x00\x00\x00\x00\x00\x00'
                        276     CALL                            1
                        284     POP_TOP                         
                        286     RERAISE                         0
                        288     COPY                            3
                        290     POP_EXCEPT                      
                        292     RERAISE                         1
                        294     PUSH_NULL                       
                        296     LOAD_CONST                      7: '__pyarmor_exit_24068__'
                        298     LOAD_CONST                      3: b'<COAddr>\x07\x00\x00\x1a\xf0\x00\x00\x00\x00\x00\x00\x00\x00\x00\x00\x00\x00\x00\x00\x00'
                        300     BUILD_TUPLE                     1
                        302     CALL_FUNCTION_EX                0
                        304     POP_TOP                         
                        306     RETURN_VALUE                    
                    [Exception Table]
                        28 to 246 -> 266 [0] 
                        266 to 288 -> 288 [1] lasti
                (
                    'timeout'
                )
                [Code]
                    File Name: <frozen multithon.tl.custom.conversation>
                    Object Name: get_response
                    Qualified Name: Conversation.get_response
                    Arg Count: 2
                    Pos Only Arg Count: 0
                    KW Only Arg Count: 1
                    Stack Size: 7
                    Flags: 0x20000003 (CO_OPTIMIZED | CO_NEWLOCALS | CO_PYARMOR_OBFUSCATED)
                    [Names]
                        '_get_message'
                        '_response_indices'
                        '_pending_responses'
                    [Locals+Names]
                        'self'
                        'message'
                        'timeout'
                        '__assert_armored__'
                    [Constants]
                        "\n        Gets the next message that responds to a previous one. This is\n        the method you need most of the time, along with `get_edit`.\n\n        Args:\n            message (`Message <telethon.tl.custom.message.Message>` | `int`, optional):\n                The message (or the message ID) for which a response\n                is expected. By default this is the last sent message.\n\n            timeout (`int` | `float`, optional):\n                If present, this `timeout` (in seconds) will override the\n                per-action timeout defined for the conversation.\n\n        .. code-block:: python\n\n            async with client.conversation(...) as conv:\n                await conv.send_message('Hey, what is your name?')\n\n                response = await conv.get_response()\n                name = response.text\n\n                await conv.send_message('Nice to meet you, {}!'.format(name))\n        "
                        '__pyarmor_assert_24069__'
                        '__pyarmor_enter_24070__'
                        b'<COAddr>\x07\x00\x00\x1ah\x00\x00\x00\x00\x00\x00\x00\x00\x00\x00\x00\x00\x00\x00\x00'
                        [Code]
                            File Name: <frozen multithon.tl.custom.conversation>
                            Object Name: <lambda>
                            Qualified Name: Conversation.get_response.<locals>.<lambda>
                            Arg Count: 2
                            Pos Only Arg Count: 0
                            KW Only Arg Count: 0
                            Stack Size: 0
                            Flags: 0x00000013 (CO_OPTIMIZED | CO_NEWLOCALS | CO_NESTED)
                            [Names]
                            [Locals+Names]
                                'x'
                                'y'
                            [Constants]
                                None
                                True
                            [Disassembly]
                                0       RESUME                          0
                                2       RETURN_CONST                    1: True
                            [Exception Table]
                        '__pyarmor_exit_24071__'
                    [Disassembly]
                        0       NOP                             
                        2       NOP                             
                        4       PUSH_NULL                       
                        6       LOAD_CONST                      2: '__pyarmor_enter_24070__'
                        8       LOAD_CONST                      3: b'<COAddr>\x07\x00\x00\x1ah\x00\x00\x00\x00\x00\x00\x00\x00\x00\x00\x00\x00\x00\x00\x00'
                        10      BUILD_TUPLE                     1
                        12      CALL_FUNCTION_EX                0
                        14      POP_TOP                         
                        16      RESUME                          0
                        18      NOP                             
                        20      NOP                             
                        22      NOP                             
                        24      NOP                             
                        26      NOP                             
                        28      LOAD_FAST                       0: self
                        30      LOAD_ATTR                       1: _get_message
                        50      LOAD_FAST                       1: message
                        52      LOAD_FAST                       0: self
                        54      LOAD_ATTR                       2: _response_indices
                        74      LOAD_FAST                       0: self
                        76      LOAD_ATTR                       4: _pending_responses
                        96      LOAD_FAST                       2: timeout
                        98      LOAD_CONST                      4: <CODE> <lambda>
                        100     MAKE_FUNCTION                   0
                        102     CALL                            5
                        110     NOP                             
                        112     NOP                             
                        114     NOP                             
                        116     JUMP_FORWARD                    20 (to 158)
                        118     CALL                            1
                        126     POP_TOP                         
                        128     RETURN_VALUE                    
                        130     PUSH_EXC_INFO                   
                        132     PUSH_NULL                       
                        134     LOAD_CONST                      5: '__pyarmor_exit_24071__'
                        136     NOP                             
                        138     LOAD_CONST                      3: b'<COAddr>\x07\x00\x00\x1ah\x00\x00\x00\x00\x00\x00\x00\x00\x00\x00\x00\x00\x00\x00\x00'
                        140     CALL                            1
                        148     POP_TOP                         
                        150     RERAISE                         0
                        152     COPY                            3
                        154     POP_EXCEPT                      
                        156     RERAISE                         1
                        158     PUSH_NULL                       
                        160     LOAD_CONST                      5: '__pyarmor_exit_24071__'
                        162     LOAD_CONST                      3: b'<COAddr>\x07\x00\x00\x1ah\x00\x00\x00\x00\x00\x00\x00\x00\x00\x00\x00\x00\x00\x00\x00'
                        164     BUILD_TUPLE                     1
                        166     CALL_FUNCTION_EX                0
                        168     POP_TOP                         
                        170     RETURN_VALUE                    
                    [Exception Table]
                        28 to 110 -> 130 [0] 
                        130 to 152 -> 152 [1] lasti
                [Code]
                    File Name: <frozen multithon.tl.custom.conversation>
                    Object Name: get_reply
                    Qualified Name: Conversation.get_reply
                    Arg Count: 2
                    Pos Only Arg Count: 0
                    KW Only Arg Count: 1
                    Stack Size: 7
                    Flags: 0x20000003 (CO_OPTIMIZED | CO_NEWLOCALS | CO_PYARMOR_OBFUSCATED)
                    [Names]
                        '_get_message'
                        '_reply_indices'
                        '_pending_replies'
                    [Locals+Names]
                        'self'
                        'message'
                        'timeout'
                        '__assert_armored__'
                    [Constants]
                        '\n        Gets the next message that explicitly replies to a previous one.\n        '
                        '__pyarmor_assert_24072__'
                        '__pyarmor_enter_24073__'
                        b'<COAddr>\x05\x00\x00\x1ah\x00\x00\x00\x00\x00\x00\x00\x00\x00\x00\x00\x00\x00\x00\x00'
                        [Code]
                            File Name: <frozen multithon.tl.custom.conversation>
                            Object Name: <lambda>
                            Qualified Name: Conversation.get_reply.<locals>.<lambda>
                            Arg Count: 2
                            Pos Only Arg Count: 0
                            KW Only Arg Count: 0
                            Stack Size: 2
                            Flags: 0x00000013 (CO_OPTIMIZED | CO_NEWLOCALS | CO_NESTED)
                            [Names]
                                'reply_to'
                                'reply_to_msg_id'
                            [Locals+Names]
                                'x'
                                'y'
                            [Constants]
                                None
                            [Disassembly]
                                0       RESUME                          0
                                2       LOAD_FAST                       0: x
                                4       LOAD_ATTR                       0: reply_to
                                24      COPY                            1
                                26      POP_JUMP_IF_FALSE               25 (to 78)
                                28      POP_TOP                         
                                30      LOAD_FAST                       0: x
                                32      LOAD_ATTR                       0: reply_to
                                52      LOAD_ATTR                       2: reply_to_msg_id
                                72      LOAD_FAST                       1: y
                                74      COMPARE_OP                      40 (==)
                                78      RETURN_VALUE                    
                            [Exception Table]
                        '__pyarmor_exit_24074__'
                    [Disassembly]
                        0       NOP                             
                        2       NOP                             
                        4       PUSH_NULL                       
                        6       LOAD_CONST                      2: '__pyarmor_enter_24073__'
                        8       LOAD_CONST                      3: b'<COAddr>\x05\x00\x00\x1ah\x00\x00\x00\x00\x00\x00\x00\x00\x00\x00\x00\x00\x00\x00\x00'
                        10      BUILD_TUPLE                     1
                        12      CALL_FUNCTION_EX                0
                        14      POP_TOP                         
                        16      RESUME                          0
                        18      NOP                             
                        20      NOP                             
                        22      NOP                             
                        24      NOP                             
                        26      NOP                             
                        28      LOAD_FAST                       0: self
                        30      LOAD_ATTR                       1: _get_message
                        50      LOAD_FAST                       1: message
                        52      LOAD_FAST                       0: self
                        54      LOAD_ATTR                       2: _reply_indices
                        74      LOAD_FAST                       0: self
                        76      LOAD_ATTR                       4: _pending_replies
                        96      LOAD_FAST                       2: timeout
                        98      LOAD_CONST                      4: <CODE> <lambda>
                        100     MAKE_FUNCTION                   0
                        102     CALL                            5
                        110     NOP                             
                        112     NOP                             
                        114     NOP                             
                        116     JUMP_FORWARD                    20 (to 158)
                        118     CALL                            1
                        126     POP_TOP                         
                        128     RETURN_VALUE                    
                        130     PUSH_EXC_INFO                   
                        132     PUSH_NULL                       
                        134     LOAD_CONST                      5: '__pyarmor_exit_24074__'
                        136     NOP                             
                        138     LOAD_CONST                      3: b'<COAddr>\x05\x00\x00\x1ah\x00\x00\x00\x00\x00\x00\x00\x00\x00\x00\x00\x00\x00\x00\x00'
                        140     CALL                            1
                        148     POP_TOP                         
                        150     RERAISE                         0
                        152     COPY                            3
                        154     POP_EXCEPT                      
                        156     RERAISE                         1
                        158     PUSH_NULL                       
                        160     LOAD_CONST                      5: '__pyarmor_exit_24074__'
                        162     LOAD_CONST                      3: b'<COAddr>\x05\x00\x00\x1ah\x00\x00\x00\x00\x00\x00\x00\x00\x00\x00\x00\x00\x00\x00\x00'
                        164     BUILD_TUPLE                     1
                        166     CALL_FUNCTION_EX                0
                        168     POP_TOP                         
                        170     RETURN_VALUE                    
                    [Exception Table]
                        28 to 110 -> 130 [0] 
                        130 to 152 -> 152 [1] lasti
                [Code]
                    File Name: <frozen multithon.tl.custom.conversation>
                    Object Name: _get_message
                    Qualified Name: Conversation._get_message
                    Arg Count: 6
                    Pos Only Arg Count: 0
                    KW Only Arg Count: 0
                    Stack Size: 7
                    Flags: 0x20000003 (CO_OPTIMIZED | CO_NEWLOCALS | CO_PYARMOR_OBFUSCATED)
                    [Names]
                        'time'
                        '_get_message_id'
                        'enumerate'
                        '_incoming'
                        'id'
                        'len'
                        '_client'
                        'loop'
                        'create_future'
                        'set_result'
                        '_get_result'
                    [Locals+Names]
                        'self'
                        'target_message'
                        'indices'
                        'pending'
                        'timeout'
                        'condition'
                        '__assert_armored__'
                        '_var_var_4'
                        '_var_var_5'
                        '_var_var_6'
                        '_var_var_7'
                        '_var_var_8'
                        '_var_var_9'
                    [Constants]
                        '\n        Gets the next desired message under the desired condition.\n\n        Args:\n            target_message (`object`):\n                The target message for which we want to find another\n                response that applies based on `condition`.\n\n            indices (`dict`):\n                This dictionary remembers the last ID chosen for the\n                input `target_message`.\n\n            pending (`dict`):\n                This dictionary remembers {msg_id: Future} to be set\n                once `condition` is met.\n\n            timeout (`int`):\n                The timeout (in seconds) override to use for this operation.\n\n            condition (`callable`):\n                The condition callable that checks if an incoming\n                message is a valid response.\n        '
                        '__pyarmor_assert_24075__'
                        '__pyarmor_enter_24076__'
                        b'<COAddr>\x05\x00\x00\x1a4\x02\x00\x00\x00\x00\x00\x00\x00\x00\x00\x00\x00\x00\x00\x00'
                        1
                        '__pyarmor_exit_24077__'
                    [Disassembly]
                        0       NOP                             
                        2       NOP                             
                        4       PUSH_NULL                       
                        6       LOAD_CONST                      2: '__pyarmor_enter_24076__'
                        8       LOAD_CONST                      3: b'<COAddr>\x05\x00\x00\x1a4\x02\x00\x00\x00\x00\x00\x00\x00\x00\x00\x00\x00\x00\x00\x00'
                        10      BUILD_TUPLE                     1
                        12      CALL_FUNCTION_EX                0
                        14      POP_TOP                         
                        16      RESUME                          0
                        18      NOP                             
                        20      NOP                             
                        22      NOP                             
                        24      NOP                             
                        26      NOP                             
                        28      LOAD_GLOBAL                     1: NULL + time
                        38      LOAD_ATTR                       0: time
                        58      CALL                            0
                        66      STORE_FAST                      7: _var_var_4
                        68      LOAD_FAST                       0: self
                        70      LOAD_ATTR                       3: _get_message_id
                        90      LOAD_FAST                       1: target_message
                        92      CALL                            1
                        100     STORE_FAST                      8: _var_var_5
                        102     LOAD_FAST                       8: _var_var_5
                        104     LOAD_FAST                       2: indices
                        106     CONTAINS_OP                     1 (not in)
                        108     POP_JUMP_IF_FALSE               75 (to 260)
                        110     LOAD_GLOBAL                     5: NULL + enumerate
                        120     LOAD_FAST                       0: self
                        122     LOAD_ATTR                       6: _incoming
                        142     CALL                            1
                        150     GET_ITER                        
                        152     FOR_ITER                        27 (to 208)
                        156     UNPACK_SEQUENCE                 2
                        160     STORE_FAST                      9: _var_var_6
                        162     STORE_FAST                      10: _var_var_7
                        164     LOAD_FAST                       10: _var_var_7
                        166     LOAD_ATTR                       8: id
                        186     LOAD_FAST                       8: _var_var_5
                        188     COMPARE_OP                      68 (>)
                        192     POP_JUMP_IF_TRUE                1 (to 196)
                        194     JUMP_BACKWARD                   22 (to 152)
                        196     LOAD_FAST                       9: _var_var_6
                        198     LOAD_FAST                       2: indices
                        200     LOAD_FAST                       8: _var_var_5
                        202     STORE_SUBSCR                    
                        206     POP_TOP                         
                        208     JUMP_FORWARD                    25 (to 260)
                        210     END_FOR                         
                        212     LOAD_GLOBAL                     11: NULL + len
                        222     LOAD_FAST                       0: self
                        224     LOAD_ATTR                       6: _incoming
                        244     CALL                            1
                        252     LOAD_FAST                       2: indices
                        254     LOAD_FAST                       8: _var_var_5
                        256     STORE_SUBSCR                    
                        260     LOAD_FAST                       0: self
                        262     LOAD_ATTR                       12: _client
                        282     LOAD_ATTR                       14: loop
                        302     LOAD_ATTR                       17: create_future
                        322     CALL                            0
                        330     STORE_FAST                      11: _var_var_8
                        332     LOAD_FAST                       2: indices
                        334     LOAD_FAST                       8: _var_var_5
                        336     BINARY_SUBSCR                   
                        340     STORE_FAST                      12: _var_var_9
                        342     LOAD_FAST                       12: _var_var_9
                        344     LOAD_GLOBAL                     11: NULL + len
                        354     LOAD_FAST                       0: self
                        356     LOAD_ATTR                       6: _incoming
                        376     CALL                            1
                        384     COMPARE_OP                      2 (<)
                        388     POP_JUMP_IF_FALSE               65 (to 520)
                        390     LOAD_FAST                       0: self
                        392     LOAD_ATTR                       6: _incoming
                        412     LOAD_FAST                       12: _var_var_9
                        414     BINARY_SUBSCR                   
                        418     STORE_FAST                      10: _var_var_7
                        420     PUSH_NULL                       
                        422     LOAD_FAST                       5: condition
                        424     LOAD_FAST                       10: _var_var_7
                        426     LOAD_FAST                       8: _var_var_5
                        428     CALL                            2
                        436     POP_JUMP_IF_FALSE               41 (to 520)
                        438     LOAD_FAST                       2: indices
                        440     LOAD_FAST                       8: _var_var_5
                        442     COPY                            2
                        444     COPY                            2
                        446     BINARY_SUBSCR                   
                        450     LOAD_CONST                      4: 1
                        452     BINARY_OP                       13 (+=)
                        456     SWAP                            3
                        458     SWAP                            2
                        460     STORE_SUBSCR                    
                        464     LOAD_FAST                       11: _var_var_8
                        466     LOAD_ATTR                       19: set_result
                        486     LOAD_FAST                       10: _var_var_7
                        488     CALL                            1
                        496     POP_TOP                         
                        498     LOAD_FAST                       11: _var_var_8
                        500     NOP                             
                        502     NOP                             
                        504     NOP                             
                        506     JUMP_FORWARD                    55 (to 618)
                        508     CALL                            1
                        516     POP_TOP                         
                        518     RETURN_VALUE                    
                        520     LOAD_FAST                       11: _var_var_8
                        522     LOAD_FAST                       3: pending
                        524     LOAD_FAST                       8: _var_var_5
                        526     STORE_SUBSCR                    
                        530     LOAD_FAST                       0: self
                        532     LOAD_ATTR                       21: _get_result
                        552     LOAD_FAST                       11: _var_var_8
                        554     LOAD_FAST                       7: _var_var_4
                        556     LOAD_FAST                       4: timeout
                        558     LOAD_FAST                       3: pending
                        560     LOAD_FAST                       8: _var_var_5
                        562     CALL                            5
                        570     NOP                             
                        572     NOP                             
                        574     NOP                             
                        576     JUMP_FORWARD                    20 (to 618)
                        578     CALL                            1
                        586     POP_TOP                         
                        588     RETURN_VALUE                    
                        590     PUSH_EXC_INFO                   
                        592     PUSH_NULL                       
                        594     LOAD_CONST                      5: '__pyarmor_exit_24077__'
                        596     NOP                             
                        598     LOAD_CONST                      3: b'<COAddr>\x05\x00\x00\x1a4\x02\x00\x00\x00\x00\x00\x00\x00\x00\x00\x00\x00\x00\x00\x00'
                        600     CALL                            1
                        608     POP_TOP                         
                        610     RERAISE                         0
                        612     COPY                            3
                        614     POP_EXCEPT                      
                        616     RERAISE                         1
                        618     PUSH_NULL                       
                        620     LOAD_CONST                      5: '__pyarmor_exit_24077__'
                        622     LOAD_CONST                      3: b'<COAddr>\x05\x00\x00\x1a4\x02\x00\x00\x00\x00\x00\x00\x00\x00\x00\x00\x00\x00\x00\x00'
                        624     BUILD_TUPLE                     1
                        626     CALL_FUNCTION_EX                0
                        628     POP_TOP                         
                        630     RETURN_VALUE                    
                    [Exception Table]
                        28 to 194 -> 590 [0] 
                        196 to 500 -> 590 [0] 
                        520 to 570 -> 590 [0] 
                        590 to 612 -> 612 [1] lasti
                [Code]
                    File Name: <frozen multithon.tl.custom.conversation>
                    Object Name: get_edit
                    Qualified Name: Conversation.get_edit
                    Arg Count: 2
                    Pos Only Arg Count: 0
                    KW Only Arg Count: 1
                    Stack Size: 7
                    Flags: 0x20000003 (CO_OPTIMIZED | CO_NEWLOCALS | CO_PYARMOR_OBFUSCATED)
                    [Names]
                        'time'
                        '_get_message_id'
                        '_edit_dates'
                        'get'
                        'min'
                        '_incoming'
                        '_client'
                        'loop'
                        'create_future'
                        'edit_date'
                        'timestamp'
                        'set_result'
                        '_pending_edits'
                        '_get_result'
                    [Locals+Names]
                        'self'
                        'message'
                        'timeout'
                        '__assert_armored__'
                        '_var_var_4'
                        '_var_var_11'
                        '_var_var_8'
                        '_var_var_10'
                        '_var_var_5'
                    [Constants]
                        '\n        Awaits for an edit after the last message to arrive.\n        The arguments are the same as those for `get_response`.\n        '
                        '__pyarmor_assert_24078__'
                        '__pyarmor_enter_24079__'
                        b'<COAddr>\x07\x00\x00\x1eD\x02\x00\x00\x00\x00\x00\x00\x00\x00\x00\x00\x00\x00\x00\x00'
                        0
                        [Code]
                            File Name: <frozen multithon.tl.custom.conversation>
                            Object Name: <genexpr>
                            Qualified Name: Conversation.get_edit.<locals>.<genexpr>
                            Arg Count: 1
                            Pos Only Arg Count: 0
                            KW Only Arg Count: 0
                            Stack Size: 3
                            Flags: 0x00000033 (CO_OPTIMIZED | CO_NEWLOCALS | CO_NESTED | CO_GENERATOR)
                            [Names]
                                'edit_date'
                                'id'
                                'timestamp'
                            [Locals+Names]
                                '.0'
                                '_var_var_12'
                                '_var_var_10'
                                '_var_var_5'
                            [Constants]
                                None
                            [Disassembly]
                                0       COPY_FREE_VARS                  2
                                2       RETURN_GENERATOR                
                                4       POP_TOP                         
                                6       RESUME                          0
                                8       LOAD_FAST                       0: .0
                                10      FOR_ITER                        62 (to 136)
                                14      STORE_FAST                      1: _var_var_12
                                16      LOAD_FAST                       1: _var_var_12
                                18      LOAD_ATTR                       0: edit_date
                                38      POP_JUMP_IF_FALSE               48 (to 136)
                                40      LOAD_FAST                       1: _var_var_12
                                42      LOAD_ATTR                       2: id
                                62      LOAD_DEREF                      3: _var_var_5
                                64      COMPARE_OP                      68 (>)
                                68      POP_JUMP_IF_FALSE               33 (to 136)
                                70      LOAD_FAST                       1: _var_var_12
                                72      LOAD_ATTR                       0: edit_date
                                92      LOAD_ATTR                       5: timestamp
                                112     CALL                            0
                                120     LOAD_DEREF                      2: _var_var_10
                                122     COMPARE_OP                      68 (>)
                                126     POP_JUMP_IF_FALSE               4 (to 136)
                                128     LOAD_FAST                       1: _var_var_12
                                130     YIELD_VALUE                     1
                                132     RESUME                          1
                                134     POP_TOP                         
                                136     JUMP_BACKWARD                   64 (to 10)
                                138     END_FOR                         
                                140     RETURN_CONST                    0: None
                                142     CALL_INTRINSIC_1                3 (INTRINSIC_STOPITERATION_ERROR)
                                144     RERAISE                         1
                            [Exception Table]
                                6 to 142 -> 142 [0] lasti
                        [Code]
                            File Name: <frozen multithon.tl.custom.conversation>
                            Object Name: <lambda>
                            Qualified Name: Conversation.get_edit.<locals>.<lambda>
                            Arg Count: 1
                            Pos Only Arg Count: 0
                            KW Only Arg Count: 0
                            Stack Size: 2
                            Flags: 0x00000013 (CO_OPTIMIZED | CO_NEWLOCALS | CO_NESTED)
                            [Names]
                                'edit_date'
                                'timestamp'
                            [Locals+Names]
                                'x'
                            [Constants]
                                None
                            [Disassembly]
                                0       RESUME                          0
                                2       LOAD_FAST                       0: x
                                4       LOAD_ATTR                       0: edit_date
                                24      LOAD_ATTR                       3: timestamp
                                44      CALL                            0
                                52      RETURN_VALUE                    
                            [Exception Table]
                        None
                        (
                            'key'
                            'default'
                        )
                        '__pyarmor_exit_24080__'
                    [Disassembly]
                        0       MAKE_CELL                       7: _var_var_10
                        2       MAKE_CELL                       8: _var_var_5
                        4       NOP                             
                        6       NOP                             
                        8       PUSH_NULL                       
                        10      LOAD_CONST                      2: '__pyarmor_enter_24079__'
                        12      LOAD_CONST                      3: b'<COAddr>\x07\x00\x00\x1eD\x02\x00\x00\x00\x00\x00\x00\x00\x00\x00\x00\x00\x00\x00\x00'
                        14      BUILD_TUPLE                     1
                        16      CALL_FUNCTION_EX                0
                        18      POP_TOP                         
                        20      RESUME                          0
                        22      NOP                             
                        24      NOP                             
                        26      NOP                             
                        28      NOP                             
                        30      NOP                             
                        32      LOAD_GLOBAL                     1: NULL + time
                        42      LOAD_ATTR                       0: time
                        62      CALL                            0
                        70      STORE_FAST                      4: _var_var_4
                        72      LOAD_FAST                       0: self
                        74      LOAD_ATTR                       3: _get_message_id
                        94      LOAD_FAST                       1: message
                        96      CALL                            1
                        104     STORE_DEREF                     8: _var_var_5
                        106     LOAD_FAST                       0: self
                        108     LOAD_ATTR                       4: _edit_dates
                        128     LOAD_ATTR                       7: get
                        148     LOAD_DEREF                      8: _var_var_5
                        150     LOAD_CONST                      4: 0
                        152     CALL                            2
                        160     STORE_DEREF                     7: _var_var_10
                        162     LOAD_GLOBAL                     9: NULL + min
                        172     LOAD_CLOSURE                    7: _var_var_10
                        174     LOAD_CLOSURE                    8: _var_var_5
                        176     BUILD_TUPLE                     2
                        178     LOAD_CONST                      5: <CODE> <genexpr>
                        180     MAKE_FUNCTION                   8
                        182     LOAD_FAST                       0: self
                        184     LOAD_ATTR                       10: _incoming
                        204     GET_ITER                        
                        206     CALL                            0
                        214     LOAD_CONST                      6: <CODE> <lambda>
                        216     MAKE_FUNCTION                   0
                        218     LOAD_CONST                      7: None
                        220     KW_NAMES                        8: ('key', 'default')
                        222     CALL                            3
                        230     STORE_FAST                      5: _var_var_11
                        232     LOAD_FAST                       0: self
                        234     LOAD_ATTR                       12: _client
                        254     LOAD_ATTR                       14: loop
                        274     LOAD_ATTR                       17: create_future
                        294     CALL                            0
                        302     STORE_FAST                      6: _var_var_8
                        304     LOAD_FAST                       5: _var_var_11
                        306     POP_JUMP_IF_FALSE               96 (to 500)
                        308     LOAD_FAST                       5: _var_var_11
                        310     LOAD_ATTR                       18: edit_date
                        330     LOAD_ATTR                       21: timestamp
                        350     CALL                            0
                        358     LOAD_DEREF                      7: _var_var_10
                        360     COMPARE_OP                      68 (>)
                        364     POP_JUMP_IF_FALSE               67 (to 500)
                        366     LOAD_FAST                       5: _var_var_11
                        368     LOAD_ATTR                       18: edit_date
                        388     LOAD_ATTR                       21: timestamp
                        408     CALL                            0
                        416     LOAD_FAST                       0: self
                        418     LOAD_ATTR                       4: _edit_dates
                        438     LOAD_DEREF                      8: _var_var_5
                        440     STORE_SUBSCR                    
                        444     LOAD_FAST                       6: _var_var_8
                        446     LOAD_ATTR                       23: set_result
                        466     LOAD_FAST                       5: _var_var_11
                        468     CALL                            1
                        476     POP_TOP                         
                        478     LOAD_FAST                       6: _var_var_8
                        480     NOP                             
                        482     NOP                             
                        484     NOP                             
                        486     JUMP_FORWARD                    75 (to 638)
                        488     CALL                            1
                        496     POP_TOP                         
                        498     RETURN_VALUE                    
                        500     LOAD_FAST                       6: _var_var_8
                        502     LOAD_FAST                       0: self
                        504     LOAD_ATTR                       24: _pending_edits
                        524     LOAD_DEREF                      8: _var_var_5
                        526     STORE_SUBSCR                    
                        530     LOAD_FAST                       0: self
                        532     LOAD_ATTR                       27: _get_result
                        552     LOAD_FAST                       6: _var_var_8
                        554     LOAD_FAST                       4: _var_var_4
                        556     LOAD_FAST                       2: timeout
                        558     LOAD_FAST                       0: self
                        560     LOAD_ATTR                       24: _pending_edits
                        580     LOAD_DEREF                      8: _var_var_5
                        582     CALL                            5
                        590     NOP                             
                        592     NOP                             
                        594     NOP                             
                        596     JUMP_FORWARD                    20 (to 638)
                        598     CALL                            1
                        606     POP_TOP                         
                        608     RETURN_VALUE                    
                        610     PUSH_EXC_INFO                   
                        612     PUSH_NULL                       
                        614     LOAD_CONST                      9: '__pyarmor_exit_24080__'
                        616     NOP                             
                        618     LOAD_CONST                      3: b'<COAddr>\x07\x00\x00\x1eD\x02\x00\x00\x00\x00\x00\x00\x00\x00\x00\x00\x00\x00\x00\x00'
                        620     CALL                            1
                        628     POP_TOP                         
                        630     RERAISE                         0
                        632     COPY                            3
                        634     POP_EXCEPT                      
                        636     RERAISE                         1
                        638     PUSH_NULL                       
                        640     LOAD_CONST                      9: '__pyarmor_exit_24080__'
                        642     LOAD_CONST                      3: b'<COAddr>\x07\x00\x00\x1eD\x02\x00\x00\x00\x00\x00\x00\x00\x00\x00\x00\x00\x00\x00\x00'
                        644     BUILD_TUPLE                     1
                        646     CALL_FUNCTION_EX                0
                        648     POP_TOP                         
                        650     RETURN_VALUE                    
                    [Exception Table]
                        32 to 480 -> 610 [0] 
                        500 to 590 -> 610 [0] 
                        610 to 632 -> 632 [1] lasti
                [Code]
                    File Name: <frozen multithon.tl.custom.conversation>
                    Object Name: wait_read
                    Qualified Name: Conversation.wait_read
                    Arg Count: 2
                    Pos Only Arg Count: 0
                    KW Only Arg Count: 1
                    Stack Size: 7
                    Flags: 0x20000003 (CO_OPTIMIZED | CO_NEWLOCALS | CO_PYARMOR_OBFUSCATED)
                    [Names]
                        'time'
                        '_client'
                        'loop'
                        'create_future'
                        '_get_message_id'
                        '_last_read'
                        '_pending_reads'
                        '_get_result'
                    [Locals+Names]
                        'self'
                        'message'
                        'timeout'
                        '__assert_armored__'
                        '_var_var_4'
                        '_var_var_8'
                        '_var_var_5'
                    [Constants]
                        "\n        Awaits for the sent message to be marked as read. Note that\n        receiving a response doesn't imply the message was read, and\n        this action will also trigger even without a response.\n        "
                        '__pyarmor_assert_24081__'
                        '__pyarmor_enter_24082__'
                        b'<COAddr>\x05\x00\x00\x1ab\x01\x00\x00\x00\x00\x00\x00\x00\x00\x00\x00\x00\x00\x00\x00'
                        None
                        1
                        '__pyarmor_exit_24083__'
                    [Disassembly]
                        0       NOP                             
                        2       NOP                             
                        4       PUSH_NULL                       
                        6       LOAD_CONST                      2: '__pyarmor_enter_24082__'
                        8       LOAD_CONST                      3: b'<COAddr>\x05\x00\x00\x1ab\x01\x00\x00\x00\x00\x00\x00\x00\x00\x00\x00\x00\x00\x00\x00'
                        10      BUILD_TUPLE                     1
                        12      CALL_FUNCTION_EX                0
                        14      POP_TOP                         
                        16      RESUME                          0
                        18      NOP                             
                        20      NOP                             
                        22      NOP                             
                        24      NOP                             
                        26      NOP                             
                        28      LOAD_GLOBAL                     1: NULL + time
                        38      LOAD_ATTR                       0: time
                        58      CALL                            0
                        66      STORE_FAST                      4: _var_var_4
                        68      LOAD_FAST                       0: self
                        70      LOAD_ATTR                       2: _client
                        90      LOAD_ATTR                       4: loop
                        110     LOAD_ATTR                       7: create_future
                        130     CALL                            0
                        138     STORE_FAST                      5: _var_var_8
                        140     LOAD_FAST                       0: self
                        142     LOAD_ATTR                       9: _get_message_id
                        162     LOAD_FAST                       1: message
                        164     CALL                            1
                        172     STORE_FAST                      6: _var_var_5
                        174     LOAD_FAST                       0: self
                        176     LOAD_ATTR                       10: _last_read
                        196     POP_JUMP_IF_NOT_NONE            10 (to 218)
                        198     LOAD_FAST                       6: _var_var_5
                        200     LOAD_CONST                      5: 1
                        202     BINARY_OP                       10 (-)
                        206     LOAD_FAST                       0: self
                        208     STORE_ATTR                      5: _last_read
                        218     LOAD_FAST                       0: self
                        220     LOAD_ATTR                       10: _last_read
                        240     LOAD_FAST                       6: _var_var_5
                        242     COMPARE_OP                      92 (>=)
                        246     POP_JUMP_IF_FALSE               11 (to 270)
                        248     NOP                             
                        250     LOAD_CONST                      4: None
                        252     NOP                             
                        254     NOP                             
                        256     NOP                             
                        258     JUMP_FORWARD                    74 (to 408)
                        266     POP_TOP                         
                        268     RETURN_CONST                    4: None
                        270     LOAD_FAST                       5: _var_var_8
                        272     LOAD_FAST                       0: self
                        274     LOAD_ATTR                       12: _pending_reads
                        294     LOAD_FAST                       6: _var_var_5
                        296     STORE_SUBSCR                    
                        300     LOAD_FAST                       0: self
                        302     LOAD_ATTR                       15: _get_result
                        322     LOAD_FAST                       5: _var_var_8
                        324     LOAD_FAST                       4: _var_var_4
                        326     LOAD_FAST                       2: timeout
                        328     LOAD_FAST                       0: self
                        330     LOAD_ATTR                       12: _pending_reads
                        350     LOAD_FAST                       6: _var_var_5
                        352     CALL                            5
                        360     NOP                             
                        362     NOP                             
                        364     NOP                             
                        366     JUMP_FORWARD                    20 (to 408)
                        368     CALL                            1
                        376     POP_TOP                         
                        378     RETURN_VALUE                    
                        380     PUSH_EXC_INFO                   
                        382     PUSH_NULL                       
                        384     LOAD_CONST                      6: '__pyarmor_exit_24083__'
                        386     NOP                             
                        388     LOAD_CONST                      3: b'<COAddr>\x05\x00\x00\x1ab\x01\x00\x00\x00\x00\x00\x00\x00\x00\x00\x00\x00\x00\x00\x00'
                        390     CALL                            1
                        398     POP_TOP                         
                        400     RERAISE                         0
                        402     COPY                            3
                        404     POP_EXCEPT                      
                        406     RERAISE                         1
                        408     PUSH_NULL                       
                        410     LOAD_CONST                      6: '__pyarmor_exit_24083__'
                        412     LOAD_CONST                      3: b'<COAddr>\x05\x00\x00\x1ab\x01\x00\x00\x00\x00\x00\x00\x00\x00\x00\x00\x00\x00\x00\x00'
                        414     BUILD_TUPLE                     1
                        416     CALL_FUNCTION_EX                0
                        418     POP_TOP                         
                        420     RETURN_VALUE                    
                    [Exception Table]
                        28 to 248 -> 380 [0] 
                        270 to 360 -> 380 [0] 
                        380 to 402 -> 402 [1] lasti
                [Code]
                    File Name: <frozen multithon.tl.custom.conversation>
                    Object Name: wait_event
                    Qualified Name: Conversation.wait_event
                    Arg Count: 2
                    Pos Only Arg Count: 0
                    KW Only Arg Count: 1
                    Stack Size: 7
                    Flags: 0x20000083 (CO_OPTIMIZED | CO_NEWLOCALS | CO_COROUTINE | CO_PYARMOR_OBFUSCATED)
                    [Names]
                        'time'
                        'isinstance'
                        'type'
                        'resolve'
                        '_client'
                        'Conversation'
                        '_custom_counter'
                        'loop'
                        'create_future'
                        '_custom'
                        '_get_result'
                        'pop'
                    [Locals+Names]
                        'self'
                        'event'
                        'timeout'
                        '__assert_armored__'
                        '_var_var_4'
                        '_var_var_13'
                        '_var_var_8'
                    [Constants]
                        '\n        Waits for a custom event to occur. Timeouts still apply.\n\n        .. note::\n\n            **Only use this if there isn\'t another method available!**\n            For example, don\'t use `wait_event` for new messages,\n            since `get_response` already exists, etc.\n\n        Unless you\'re certain that your code will run fast enough,\n        generally you should get a "handle" of this special coroutine\n        before acting. In this example you will see how to wait for a user\n        to join a group with proper use of `wait_event`:\n\n        .. code-block:: python\n\n            from multithon import TelegramClient, events\n\n            client = TelegramClient(...)\n            group_id = ...\n\n            async def main():\n                # Could also get the user id from an event; this is just an example\n                user_id = ...\n\n                async with client.conversation(user_id) as conv:\n                    # Get a handle to the future event we\'ll wait for\n                    handle = conv.wait_event(events.ChatAction(\n                        group_id,\n                        func=lambda e: e.user_joined and e.user_id == user_id\n                    ))\n\n                    # Perform whatever action in between\n                    await conv.send_message(\'Please join this group before speaking to me!\')\n\n                    # Wait for the event we registered above to fire\n                    event = await handle\n\n                    # Continue with the conversation\n                    await conv.send_message(\'Thanks!\')\n\n        This way your event can be registered before acting,\n        since the response may arrive before your event was\n        registered. It depends on your use case since this\n        also means the event can arrive before you send\n        a previous action.\n        '
                        '__pyarmor_assert_24084__'
                        '__pyarmor_enter_24085__'
                        b'<COAddr>\x07\x00\x00\x1e>\x02\x00\x00\x00\x00\x00\x00\x00\x00\x00\x00\x00\x00\x00\x00'
                        None
                        1
                        '__pyarmor_exit_24086__'
                    [Disassembly]
                        0       RETURN_GENERATOR                
                        2       POP_TOP                         
                        4       NOP                             
                        6       NOP                             
                        8       PUSH_NULL                       
                        10      LOAD_CONST                      2: '__pyarmor_enter_24085__'
                        12      LOAD_CONST                      3: b'<COAddr>\x07\x00\x00\x1e>\x02\x00\x00\x00\x00\x00\x00\x00\x00\x00\x00\x00\x00\x00\x00'
                        14      BUILD_TUPLE                     1
                        16      CALL_FUNCTION_EX                0
                        18      POP_TOP                         
                        20      RESUME                          0
                        22      NOP                             
                        24      NOP                             
                        26      NOP                             
                        28      NOP                             
                        30      NOP                             
                        32      LOAD_GLOBAL                     1: NULL + time
                        42      LOAD_ATTR                       0: time
                        62      CALL                            0
                        70      STORE_FAST                      4: _var_var_4
                        72      LOAD_GLOBAL                     3: NULL + isinstance
                        82      LOAD_FAST                       1: event
                        84      LOAD_GLOBAL                     4: type
                        94      CALL                            2
                        102     POP_JUMP_IF_FALSE               7 (to 118)
                        104     PUSH_NULL                       
                        106     LOAD_FAST                       1: event
                        108     CALL                            0
                        116     STORE_FAST                      1: event
                        118     LOAD_FAST                       1: event
                        120     LOAD_ATTR                       7: resolve
                        140     LOAD_FAST                       0: self
                        142     LOAD_ATTR                       8: _client
                        162     CALL                            1
                        170     GET_AWAITABLE                   0
                        172     LOAD_CONST                      4: None
                        174     SEND                            3 (to 182)
                        178     YIELD_VALUE                     3
                        180     RESUME                          3
                        182     JUMP_BACKWARD_NO_INTERRUPT      5 (to 174)
                        184     END_SEND                        
                        186     POP_TOP                         
                        188     LOAD_GLOBAL                     10: Conversation
                        198     LOAD_ATTR                       12: _custom_counter
                        218     STORE_FAST                      5: _var_var_13
                        220     LOAD_GLOBAL                     10: Conversation
                        230     COPY                            1
                        232     LOAD_ATTR                       12: _custom_counter
                        252     LOAD_CONST                      5: 1
                        254     BINARY_OP                       13 (+=)
                        258     SWAP                            2
                        260     STORE_ATTR                      6: _custom_counter
                        270     LOAD_FAST                       0: self
                        272     LOAD_ATTR                       8: _client
                        292     LOAD_ATTR                       14: loop
                        312     LOAD_ATTR                       17: create_future
                        332     CALL                            0
                        340     STORE_FAST                      6: _var_var_8
                        342     LOAD_FAST                       1: event
                        344     LOAD_FAST                       6: _var_var_8
                        346     BUILD_TUPLE                     2
                        348     LOAD_FAST                       0: self
                        350     LOAD_ATTR                       18: _custom
                        370     LOAD_FAST                       5: _var_var_13
                        372     STORE_SUBSCR                    
                        376     NOP                             
                        378     LOAD_FAST                       0: self
                        380     LOAD_ATTR                       21: _get_result
                        400     LOAD_FAST                       6: _var_var_8
                        402     LOAD_FAST                       4: _var_var_4
                        404     LOAD_FAST                       2: timeout
                        406     LOAD_FAST                       0: self
                        408     LOAD_ATTR                       18: _custom
                        428     LOAD_FAST                       5: _var_var_13
                        430     CALL                            5
                        438     GET_AWAITABLE                   0
                        440     LOAD_CONST                      4: None
                        442     SEND                            3 (to 450)
                        446     YIELD_VALUE                     4
                        448     RESUME                          3
                        450     JUMP_BACKWARD_NO_INTERRUPT      5 (to 442)
                        452     END_SEND                        
                        454     LOAD_FAST                       0: self
                        456     LOAD_ATTR                       18: _custom
                        476     LOAD_ATTR                       23: pop
                        496     LOAD_FAST                       5: _var_var_13
                        498     LOAD_CONST                      4: None
                        500     CALL                            2
                        508     POP_TOP                         
                        510     NOP                             
                        512     NOP                             
                        514     NOP                             
                        516     JUMP_FORWARD                    59 (to 636)
                        518     CALL                            1
                        526     POP_TOP                         
                        528     RETURN_VALUE                    
                        530     CLEANUP_THROW                   
                        532     JUMP_BACKWARD                   175 (to 184)
                        534     CLEANUP_THROW                   
                        536     JUMP_BACKWARD                   43 (to 452)
                        538     PUSH_EXC_INFO                   
                        540     LOAD_FAST                       0: self
                        542     LOAD_ATTR                       18: _custom
                        562     LOAD_ATTR                       23: pop
                        582     LOAD_FAST                       5: _var_var_13
                        584     LOAD_CONST                      4: None
                        586     CALL                            2
                        594     POP_TOP                         
                        596     RERAISE                         0
                        598     COPY                            3
                        600     POP_EXCEPT                      
                        602     RERAISE                         1
                        604     PUSH_EXC_INFO                   
                        606     PUSH_NULL                       
                        608     LOAD_CONST                      6: '__pyarmor_exit_24086__'
                        610     NOP                             
                        612     LOAD_CONST                      3: b'<COAddr>\x07\x00\x00\x1e>\x02\x00\x00\x00\x00\x00\x00\x00\x00\x00\x00\x00\x00\x00\x00'
                        614     CALL                            1
                        622     POP_TOP                         
                        624     RERAISE                         0
                        626     COPY                            3
                        628     POP_EXCEPT                      
                        630     RERAISE                         1
                        632     CALL_INTRINSIC_1                3 (INTRINSIC_STOPITERATION_ERROR)
                        634     RERAISE                         1
                        636     PUSH_NULL                       
                        638     LOAD_CONST                      6: '__pyarmor_exit_24086__'
                        640     LOAD_CONST                      3: b'<COAddr>\x07\x00\x00\x1e>\x02\x00\x00\x00\x00\x00\x00\x00\x00\x00\x00\x00\x00\x00\x00'
                        642     BUILD_TUPLE                     1
                        644     CALL_FUNCTION_EX                0
                        646     POP_TOP                         
                        648     RETURN_VALUE                    
                    [Exception Table]
                        4 to 30 -> 632 [0] lasti
                        32 to 178 -> 604 [0] 
                        178 to 180 -> 530 [2] 
                        180 to 376 -> 604 [0] 
                        378 to 446 -> 538 [0] 
                        446 to 448 -> 534 [2] 
                        448 to 454 -> 538 [0] 
                        454 to 510 -> 604 [0] 
                        510 to 530 -> 632 [0] lasti
                        530 to 532 -> 604 [0] 
                        534 to 536 -> 538 [0] 
                        538 to 598 -> 598 [1] lasti
                        598 to 604 -> 604 [0] 
                        604 to 626 -> 626 [1] lasti
                        626 to 632 -> 632 [0] lasti
                [Code]
                    File Name: <frozen multithon.tl.custom.conversation>
                    Object Name: _check_custom
                    Qualified Name: Conversation._check_custom
                    Arg Count: 2
                    Pos Only Arg Count: 0
                    KW Only Arg Count: 0
                    Stack Size: 5
                    Flags: 0x20000083 (CO_OPTIMIZED | CO_NEWLOCALS | CO_COROUTINE | CO_PYARMOR_OBFUSCATED)
                    [Names]
                        'list'
                        '_custom'
                        'items'
                        'type'
                        'filter'
                        'inspect'
                        'isawaitable'
                        'set_result'
                    [Locals+Names]
                        'self'
                        'built'
                        '__assert_armored__'
                        '_var_var_14'
                        '_var_var_15'
                        '_var_var_16'
                        '_var_var_17'
                        '_var_var_18'
                        '_var_var_19'
                    [Constants]
                        None
                        '__pyarmor_assert_24087__'
                        '__pyarmor_enter_24088__'
                        b'<COAddr>\x07\x00\x00\x1e>\x01\x00\x00\x00\x00\x00\x00\x00\x00\x00\x00\x00\x00\x00\x00'
                        '__pyarmor_exit_24089__'
                    [Disassembly]
                        0       RETURN_GENERATOR                
                        2       POP_TOP                         
                        4       NOP                             
                        6       NOP                             
                        8       PUSH_NULL                       
                        10      LOAD_CONST                      2: '__pyarmor_enter_24088__'
                        12      LOAD_CONST                      3: b'<COAddr>\x07\x00\x00\x1e>\x01\x00\x00\x00\x00\x00\x00\x00\x00\x00\x00\x00\x00\x00\x00'
                        14      BUILD_TUPLE                     1
                        16      CALL_FUNCTION_EX                0
                        18      POP_TOP                         
                        20      RESUME                          0
                        22      NOP                             
                        24      NOP                             
                        26      NOP                             
                        28      NOP                             
                        30      NOP                             
                        32      LOAD_GLOBAL                     1: NULL + list
                        42      LOAD_FAST                       0: self
                        44      LOAD_ATTR                       2: _custom
                        64      LOAD_ATTR                       5: items
                        84      CALL                            0
                        92      CALL                            1
                        100     GET_ITER                        
                        102     FOR_ITER                        108 (to 320)
                        106     UNPACK_SEQUENCE                 2
                        110     STORE_FAST                      3: _var_var_14
                        112     UNPACK_SEQUENCE                 2
                        116     STORE_FAST                      4: _var_var_15
                        118     STORE_FAST                      5: _var_var_16
                        120     LOAD_GLOBAL                     7: NULL + type
                        130     LOAD_FAST                       4: _var_var_15
                        132     CALL                            1
                        140     STORE_FAST                      6: _var_var_17
                        142     LOAD_FAST                       1: built
                        144     LOAD_FAST                       6: _var_var_17
                        146     BINARY_SUBSCR                   
                        150     STORE_FAST                      7: _var_var_18
                        152     LOAD_FAST                       7: _var_var_18
                        154     POP_JUMP_IF_TRUE                1 (to 158)
                        156     JUMP_BACKWARD                   28 (to 102)
                        158     LOAD_FAST                       4: _var_var_15
                        160     LOAD_ATTR                       9: filter
                        180     LOAD_FAST                       7: _var_var_18
                        182     CALL                            1
                        190     STORE_FAST                      8: _var_var_19
                        192     LOAD_GLOBAL                     11: NULL + inspect
                        202     LOAD_ATTR                       12: isawaitable
                        222     LOAD_FAST                       8: _var_var_19
                        224     CALL                            1
                        232     POP_JUMP_IF_FALSE               10 (to 254)
                        234     LOAD_FAST                       8: _var_var_19
                        236     GET_AWAITABLE                   0
                        238     LOAD_CONST                      0: None
                        240     SEND                            3 (to 248)
                        244     YIELD_VALUE                     3
                        246     RESUME                          3
                        248     JUMP_BACKWARD_NO_INTERRUPT      5 (to 240)
                        250     END_SEND                        
                        252     STORE_FAST                      8: _var_var_19
                        254     LOAD_FAST                       8: _var_var_19
                        256     POP_JUMP_IF_TRUE                1 (to 260)
                        258     JUMP_BACKWARD                   79 (to 102)
                        260     LOAD_FAST                       5: _var_var_16
                        262     LOAD_ATTR                       15: set_result
                        282     LOAD_FAST                       7: _var_var_18
                        284     CALL                            1
                        292     POP_TOP                         
                        294     LOAD_FAST                       0: self
                        296     LOAD_ATTR                       2: _custom
                        316     LOAD_FAST                       3: _var_var_14
                        318     DELETE_SUBSCR                   
                        320     JUMP_BACKWARD                   110 (to 102)
                        322     END_FOR                         
                        324     LOAD_CONST                      0: None
                        326     NOP                             
                        328     NOP                             
                        330     NOP                             
                        332     JUMP_FORWARD                    23 (to 380)
                        340     POP_TOP                         
                        342     RETURN_CONST                    0: None
                        344     CLEANUP_THROW                   
                        346     JUMP_BACKWARD                   49 (to 250)
                        348     PUSH_EXC_INFO                   
                        350     PUSH_NULL                       
                        352     LOAD_CONST                      4: '__pyarmor_exit_24089__'
                        354     NOP                             
                        356     LOAD_CONST                      3: b'<COAddr>\x07\x00\x00\x1e>\x01\x00\x00\x00\x00\x00\x00\x00\x00\x00\x00\x00\x00\x00\x00'
                        358     CALL                            1
                        366     POP_TOP                         
                        368     RERAISE                         0
                        370     COPY                            3
                        372     POP_EXCEPT                      
                        374     RERAISE                         1
                        376     CALL_INTRINSIC_1                3 (INTRINSIC_STOPITERATION_ERROR)
                        378     RERAISE                         1
                        380     PUSH_NULL                       
                        382     LOAD_CONST                      4: '__pyarmor_exit_24089__'
                        384     LOAD_CONST                      3: b'<COAddr>\x07\x00\x00\x1e>\x01\x00\x00\x00\x00\x00\x00\x00\x00\x00\x00\x00\x00\x00\x00'
                        386     BUILD_TUPLE                     1
                        388     CALL_FUNCTION_EX                0
                        390     POP_TOP                         
                        392     RETURN_VALUE                    
                    [Exception Table]
                        4 to 30 -> 376 [0] lasti
                        32 to 156 -> 348 [0] 
                        158 to 244 -> 348 [0] 
                        244 to 246 -> 344 [3] 
                        246 to 258 -> 348 [0] 
                        260 to 324 -> 348 [0] 
                        324 to 344 -> 376 [0] lasti
                        344 to 346 -> 348 [0] 
                        348 to 370 -> 370 [1] lasti
                        370 to 376 -> 376 [0] lasti
                [Code]
                    File Name: <frozen multithon.tl.custom.conversation>
                    Object Name: _on_new_message
                    Qualified Name: Conversation._on_new_message
                    Arg Count: 2
                    Pos Only Arg Count: 0
                    KW Only Arg Count: 0
                    Stack Size: 7
                    Flags: 0x20000003 (CO_OPTIMIZED | CO_NEWLOCALS | CO_PYARMOR_OBFUSCATED)
                    [Names]
                        'message'
                        'chat_id'
                        'out'
                        'len'
                        '_incoming'
                        '_max_incoming'
                        '_cancel_all'
                        'ValueError'
                        'append'
                        'list'
                        '_pending_responses'
                        'items'
                        '_response_indices'
                        'set_result'
                        '_pending_replies'
                        'reply_to'
                        'reply_to_msg_id'
                        '_reply_indices'
                    [Locals+Names]
                        'self'
                        'response'
                        '__assert_armored__'
                        '_var_var_20'
                        '_var_var_8'
                    [Constants]
                        None
                        '__pyarmor_assert_24090__'
                        '__pyarmor_enter_24091__'
                        b'<COAddr>\x05\x00\x00\x1aX\x03\x00\x00\x00\x00\x00\x00\x00\x00\x00\x00\x00\x00\x00\x00'
                        '__pyarmor_exit_24092__'
                        'Too many incoming messages'   # b'\x81\xd6\x17\x1cs\xf7\xbf\xdc\x02\xba\x04\xceo\xe3\xf5\x8c\x01Z\xfb\xaa\xaf\xd8]\xcd\x02j\xb0'
                    [Disassembly]
                        0       NOP                             
                        2       NOP                             
                        4       PUSH_NULL                       
                        6       LOAD_CONST                      2: '__pyarmor_enter_24091__'
                        8       LOAD_CONST                      3: b'<COAddr>\x05\x00\x00\x1aX\x03\x00\x00\x00\x00\x00\x00\x00\x00\x00\x00\x00\x00\x00\x00'
                        10      BUILD_TUPLE                     1
                        12      CALL_FUNCTION_EX                0
                        14      POP_TOP                         
                        16      RESUME                          0
                        18      NOP                             
                        20      NOP                             
                        22      NOP                             
                        24      NOP                             
                        26      NOP                             
                        28      LOAD_FAST                       1: response
                        30      LOAD_ATTR                       0: message
                        50      STORE_FAST                      1: response
                        52      LOAD_FAST                       1: response
                        54      LOAD_ATTR                       2: chat_id
                        74      LOAD_FAST                       0: self
                        76      LOAD_ATTR                       2: chat_id
                        96      COMPARE_OP                      55 (!=)
                        100     POP_JUMP_IF_TRUE                12 (to 126)
                        102     LOAD_FAST                       1: response
                        104     LOAD_ATTR                       4: out
                        124     POP_JUMP_IF_FALSE               11 (to 148)
                        126     NOP                             
                        128     LOAD_CONST                      0: None
                        130     NOP                             
                        132     NOP                             
                        134     JUMP_FORWARD                    386 (to 910)
                        144     POP_TOP                         
                        146     RETURN_CONST                    0: None
                        148     LOAD_GLOBAL                     7: NULL + len
                        158     LOAD_FAST                       0: self
                        160     LOAD_ATTR                       8: _incoming
                        180     CALL                            1
                        188     LOAD_FAST                       0: self
                        190     LOAD_ATTR                       10: _max_incoming
                        210     COMPARE_OP                      40 (==)
                        214     POP_JUMP_IF_FALSE               43 (to 302)
                        216     LOAD_FAST                       0: self
                        218     LOAD_ATTR                       13: _cancel_all
                        238     LOAD_GLOBAL                     15: NULL + ValueError
                        248     PUSH_NULL                       
                        250     LOAD_CONST                      1: '__pyarmor_assert_24090__'
                        252     LOAD_CONST                      5: 'Too many incoming messages'   # b'\x81\xd6\x17\x1cs\xf7\xbf\xdc\x02\xba\x04\xceo\xe3\xf5\x8c\x01Z\xfb\xaa\xaf\xd8]\xcd\x02j\xb0'
                        254     CALL                            1
                        262     CALL                            1
                        270     CALL                            1
                        278     POP_TOP                         
                        280     NOP                             
                        282     LOAD_CONST                      0: None
                        284     NOP                             
                        286     NOP                             
                        288     JUMP_FORWARD                    309 (to 910)
                        298     POP_TOP                         
                        300     RETURN_CONST                    0: None
                        302     LOAD_FAST                       0: self
                        304     LOAD_ATTR                       8: _incoming
                        324     LOAD_ATTR                       17: append
                        344     LOAD_FAST                       1: response
                        346     CALL                            1
                        354     POP_TOP                         
                        356     LOAD_GLOBAL                     19: NULL + list
                        366     LOAD_FAST                       0: self
                        368     LOAD_ATTR                       20: _pending_responses
                        388     LOAD_ATTR                       23: items
                        408     CALL                            0
                        416     CALL                            1
                        424     GET_ITER                        
                        426     FOR_ITER                        69 (to 566)
                        430     UNPACK_SEQUENCE                 2
                        434     STORE_FAST                      3: _var_var_20
                        436     STORE_FAST                      4: _var_var_8
                        438     LOAD_GLOBAL                     7: NULL + len
                        448     LOAD_FAST                       0: self
                        450     LOAD_ATTR                       8: _incoming
                        470     CALL                            1
                        478     LOAD_FAST                       0: self
                        480     LOAD_ATTR                       24: _response_indices
                        500     LOAD_FAST                       3: _var_var_20
                        502     STORE_SUBSCR                    
                        506     LOAD_FAST                       4: _var_var_8
                        508     LOAD_ATTR                       27: set_result
                        528     LOAD_FAST                       1: response
                        530     CALL                            1
                        538     POP_TOP                         
                        540     LOAD_FAST                       0: self
                        542     LOAD_ATTR                       20: _pending_responses
                        562     LOAD_FAST                       3: _var_var_20
                        564     DELETE_SUBSCR                   
                        566     JUMP_BACKWARD                   71 (to 426)
                        568     END_FOR                         
                        570     LOAD_GLOBAL                     19: NULL + list
                        580     LOAD_FAST                       0: self
                        582     LOAD_ATTR                       28: _pending_replies
                        602     LOAD_ATTR                       23: items
                        622     CALL                            0
                        630     CALL                            1
                        638     GET_ITER                        
                        640     FOR_ITER                        108 (to 858)
                        644     UNPACK_SEQUENCE                 2
                        648     STORE_FAST                      3: _var_var_20
                        650     STORE_FAST                      4: _var_var_8
                        652     LOAD_FAST                       1: response
                        654     LOAD_ATTR                       30: reply_to
                        674     POP_JUMP_IF_TRUE                1 (to 678)
                        676     JUMP_BACKWARD                   19 (to 640)
                        678     LOAD_FAST                       3: _var_var_20
                        680     LOAD_FAST                       1: response
                        682     LOAD_ATTR                       30: reply_to
                        702     LOAD_ATTR                       32: reply_to_msg_id
                        722     COMPARE_OP                      40 (==)
                        726     POP_JUMP_IF_TRUE                1 (to 730)
                        728     JUMP_BACKWARD                   45 (to 640)
                        730     LOAD_GLOBAL                     7: NULL + len
                        740     LOAD_FAST                       0: self
                        742     LOAD_ATTR                       8: _incoming
                        762     CALL                            1
                        770     LOAD_FAST                       0: self
                        772     LOAD_ATTR                       34: _reply_indices
                        792     LOAD_FAST                       3: _var_var_20
                        794     STORE_SUBSCR                    
                        798     LOAD_FAST                       4: _var_var_8
                        800     LOAD_ATTR                       27: set_result
                        820     LOAD_FAST                       1: response
                        822     CALL                            1
                        830     POP_TOP                         
                        832     LOAD_FAST                       0: self
                        834     LOAD_ATTR                       28: _pending_replies
                        854     LOAD_FAST                       3: _var_var_20
                        856     DELETE_SUBSCR                   
                        858     JUMP_BACKWARD                   110 (to 640)
                        860     END_FOR                         
                        862     LOAD_CONST                      0: None
                        864     NOP                             
                        866     NOP                             
                        868     NOP                             
                        870     JUMP_FORWARD                    19 (to 910)
                        878     POP_TOP                         
                        880     RETURN_CONST                    0: None
                        882     PUSH_EXC_INFO                   
                        884     PUSH_NULL                       
                        886     LOAD_CONST                      4: '__pyarmor_exit_24092__'
                        888     NOP                             
                        890     LOAD_CONST                      3: b'<COAddr>\x05\x00\x00\x1aX\x03\x00\x00\x00\x00\x00\x00\x00\x00\x00\x00\x00\x00\x00\x00'
                        892     CALL                            1
                        900     POP_TOP                         
                        902     RERAISE                         0
                        904     COPY                            3
                        906     POP_EXCEPT                      
                        908     RERAISE                         1
                        910     PUSH_NULL                       
                        912     LOAD_CONST                      4: '__pyarmor_exit_24092__'
                        914     LOAD_CONST                      3: b'<COAddr>\x05\x00\x00\x1aX\x03\x00\x00\x00\x00\x00\x00\x00\x00\x00\x00\x00\x00\x00\x00'
                        916     BUILD_TUPLE                     1
                        918     CALL_FUNCTION_EX                0
                        920     POP_TOP                         
                        922     RETURN_VALUE                    
                    [Exception Table]
                        28 to 126 -> 882 [0] 
                        148 to 280 -> 882 [0] 
                        302 to 676 -> 882 [0] 
                        678 to 728 -> 882 [0] 
                        730 to 862 -> 882 [0] 
                        882 to 904 -> 904 [1] lasti
                [Code]
                    File Name: <frozen multithon.tl.custom.conversation>
                    Object Name: _on_edit
                    Qualified Name: Conversation._on_edit
                    Arg Count: 2
                    Pos Only Arg Count: 0
                    KW Only Arg Count: 0
                    Stack Size: 6
                    Flags: 0x20000003 (CO_OPTIMIZED | CO_NEWLOCALS | CO_PYARMOR_OBFUSCATED)
                    [Names]
                        'message'
                        'chat_id'
                        'out'
                        'enumerate'
                        '_incoming'
                        'id'
                        'list'
                        '_pending_edits'
                        'items'
                        'edit_date'
                        'timestamp'
                        '_edit_dates'
                        'get'
                        '_EDIT_COLLISION_DELTA'
                        'set_result'
                    [Locals+Names]
                        'self'
                        'message'
                        '__assert_armored__'
                        '_var_var_6'
                        '_var_var_3'
                        '_var_var_20'
                        '_var_var_8'
                        '_var_var_21'
                    [Constants]
                        None
                        '__pyarmor_assert_24093__'
                        '__pyarmor_enter_24094__'
                        b'<COAddr>\x05\x00\x00\x1a\xc6\x02\x00\x00\x00\x00\x00\x00\x00\x00\x00\x00\x00\x00\x00\x00'
                        '__pyarmor_exit_24095__'
                        0
                    [Disassembly]
                        0       NOP                             
                        2       NOP                             
                        4       PUSH_NULL                       
                        6       LOAD_CONST                      2: '__pyarmor_enter_24094__'
                        8       LOAD_CONST                      3: b'<COAddr>\x05\x00\x00\x1a\xc6\x02\x00\x00\x00\x00\x00\x00\x00\x00\x00\x00\x00\x00\x00\x00'
                        10      BUILD_TUPLE                     1
                        12      CALL_FUNCTION_EX                0
                        14      POP_TOP                         
                        16      RESUME                          0
                        18      NOP                             
                        20      NOP                             
                        22      NOP                             
                        24      NOP                             
                        26      NOP                             
                        28      LOAD_FAST                       1: message
                        30      LOAD_ATTR                       0: message
                        50      STORE_FAST                      1: message
                        52      LOAD_FAST                       1: message
                        54      LOAD_ATTR                       2: chat_id
                        74      LOAD_FAST                       0: self
                        76      LOAD_ATTR                       2: chat_id
                        96      COMPARE_OP                      55 (!=)
                        100     POP_JUMP_IF_TRUE                12 (to 126)
                        102     LOAD_FAST                       1: message
                        104     LOAD_ATTR                       4: out
                        124     POP_JUMP_IF_FALSE               11 (to 148)
                        126     NOP                             
                        128     LOAD_CONST                      0: None
                        130     NOP                             
                        132     NOP                             
                        134     JUMP_FORWARD                    313 (to 764)
                        144     POP_TOP                         
                        146     RETURN_CONST                    0: None
                        148     LOAD_GLOBAL                     7: NULL + enumerate
                        158     LOAD_FAST                       0: self
                        160     LOAD_ATTR                       8: _incoming
                        180     CALL                            1
                        188     GET_ITER                        
                        190     FOR_ITER                        47 (to 286)
                        194     UNPACK_SEQUENCE                 2
                        198     STORE_FAST                      3: _var_var_6
                        200     STORE_FAST                      4: _var_var_3
                        202     LOAD_FAST                       4: _var_var_3
                        204     LOAD_ATTR                       10: id
                        224     LOAD_FAST                       1: message
                        226     LOAD_ATTR                       10: id
                        246     COMPARE_OP                      40 (==)
                        250     POP_JUMP_IF_TRUE                1 (to 254)
                        252     JUMP_BACKWARD                   32 (to 190)
                        254     LOAD_FAST                       1: message
                        256     LOAD_FAST                       0: self
                        258     LOAD_ATTR                       8: _incoming
                        278     LOAD_FAST                       3: _var_var_6
                        280     STORE_SUBSCR                    
                        284     POP_TOP                         
                        286     JUMP_FORWARD                    1 (to 290)
                        288     END_FOR                         
                        290     LOAD_GLOBAL                     13: NULL + list
                        300     LOAD_FAST                       0: self
                        302     LOAD_ATTR                       14: _pending_edits
                        322     LOAD_ATTR                       17: items
                        342     CALL                            0
                        350     CALL                            1
                        358     GET_ITER                        
                        360     FOR_ITER                        175 (to 712)
                        364     UNPACK_SEQUENCE                 2
                        368     STORE_FAST                      5: _var_var_20
                        370     STORE_FAST                      6: _var_var_8
                        372     LOAD_FAST                       5: _var_var_20
                        374     LOAD_FAST                       1: message
                        376     LOAD_ATTR                       10: id
                        396     COMPARE_OP                      2 (<)
                        400     POP_JUMP_IF_TRUE                1 (to 404)
                        402     JUMP_BACKWARD                   22 (to 360)
                        404     LOAD_FAST                       1: message
                        406     LOAD_ATTR                       18: edit_date
                        426     LOAD_ATTR                       21: timestamp
                        446     CALL                            0
                        454     STORE_FAST                      7: _var_var_21
                        456     LOAD_FAST                       7: _var_var_21
                        458     LOAD_FAST                       0: self
                        460     LOAD_ATTR                       22: _edit_dates
                        480     LOAD_ATTR                       25: get
                        500     LOAD_FAST                       5: _var_var_20
                        502     LOAD_CONST                      5: 0
                        504     CALL                            2
                        512     COMPARE_OP                      26 (<=)
                        516     POP_JUMP_IF_FALSE               28 (to 574)
                        518     LOAD_FAST                       0: self
                        520     LOAD_ATTR                       22: _edit_dates
                        540     LOAD_FAST                       5: _var_var_20
                        542     COPY                            2
                        544     COPY                            2
                        546     BINARY_SUBSCR                   
                        550     LOAD_GLOBAL                     26: _EDIT_COLLISION_DELTA
                        560     BINARY_OP                       13 (+=)
                        564     SWAP                            3
                        566     SWAP                            2
                        568     STORE_SUBSCR                    
                        572     JUMP_FORWARD                    39 (to 652)
                        574     LOAD_FAST                       1: message
                        576     LOAD_ATTR                       18: edit_date
                        596     LOAD_ATTR                       21: timestamp
                        616     CALL                            0
                        624     LOAD_FAST                       0: self
                        626     LOAD_ATTR                       22: _edit_dates
                        646     LOAD_FAST                       5: _var_var_20
                        648     STORE_SUBSCR                    
                        652     LOAD_FAST                       6: _var_var_8
                        654     LOAD_ATTR                       29: set_result
                        674     LOAD_FAST                       1: message
                        676     CALL                            1
                        684     POP_TOP                         
                        686     LOAD_FAST                       0: self
                        688     LOAD_ATTR                       14: _pending_edits
                        708     LOAD_FAST                       5: _var_var_20
                        710     DELETE_SUBSCR                   
                        712     JUMP_BACKWARD                   177 (to 360)
                        714     END_FOR                         
                        716     LOAD_CONST                      0: None
                        718     NOP                             
                        720     NOP                             
                        722     NOP                             
                        724     JUMP_FORWARD                    19 (to 764)
                        732     POP_TOP                         
                        734     RETURN_CONST                    0: None
                        736     PUSH_EXC_INFO                   
                        738     PUSH_NULL                       
                        740     LOAD_CONST                      4: '__pyarmor_exit_24095__'
                        742     NOP                             
                        744     LOAD_CONST                      3: b'<COAddr>\x05\x00\x00\x1a\xc6\x02\x00\x00\x00\x00\x00\x00\x00\x00\x00\x00\x00\x00\x00\x00'
                        746     CALL                            1
                        754     POP_TOP                         
                        756     RERAISE                         0
                        758     COPY                            3
                        760     POP_EXCEPT                      
                        762     RERAISE                         1
                        764     PUSH_NULL                       
                        766     LOAD_CONST                      4: '__pyarmor_exit_24095__'
                        768     LOAD_CONST                      3: b'<COAddr>\x05\x00\x00\x1a\xc6\x02\x00\x00\x00\x00\x00\x00\x00\x00\x00\x00\x00\x00\x00\x00'
                        770     BUILD_TUPLE                     1
                        772     CALL_FUNCTION_EX                0
                        774     POP_TOP                         
                        776     RETURN_VALUE                    
                    [Exception Table]
                        28 to 126 -> 736 [0] 
                        148 to 252 -> 736 [0] 
                        254 to 402 -> 736 [0] 
                        404 to 716 -> 736 [0] 
                        736 to 758 -> 758 [1] lasti
                [Code]
                    File Name: <frozen multithon.tl.custom.conversation>
                    Object Name: _on_read
                    Qualified Name: Conversation._on_read
                    Arg Count: 2
                    Pos Only Arg Count: 0
                    KW Only Arg Count: 0
                    Stack Size: 5
                    Flags: 0x20000003 (CO_OPTIMIZED | CO_NEWLOCALS | CO_PYARMOR_OBFUSCATED)
                    [Names]
                        'chat_id'
                        'inbox'
                        'max_id'
                        '_last_read'
                        'list'
                        '_pending_reads'
                        'items'
                        'set_result'
                    [Locals+Names]
                        'self'
                        'event'
                        '__assert_armored__'
                        '_var_var_20'
                        '_var_var_22'
                    [Constants]
                        None
                        '__pyarmor_assert_24096__'
                        '__pyarmor_enter_24097__'
                        b'<COAddr>\x05\x00\x00\x1aJ\x01\x00\x00\x00\x00\x00\x00\x00\x00\x00\x00\x00\x00\x00\x00'
                        '__pyarmor_exit_24098__'
                        True
                    [Disassembly]
                        0       NOP                             
                        2       NOP                             
                        4       PUSH_NULL                       
                        6       LOAD_CONST                      2: '__pyarmor_enter_24097__'
                        8       LOAD_CONST                      3: b'<COAddr>\x05\x00\x00\x1aJ\x01\x00\x00\x00\x00\x00\x00\x00\x00\x00\x00\x00\x00\x00\x00'
                        10      BUILD_TUPLE                     1
                        12      CALL_FUNCTION_EX                0
                        14      POP_TOP                         
                        16      RESUME                          0
                        18      NOP                             
                        20      NOP                             
                        22      NOP                             
                        24      NOP                             
                        26      NOP                             
                        28      LOAD_FAST                       1: event
                        30      LOAD_ATTR                       0: chat_id
                        50      LOAD_FAST                       0: self
                        52      LOAD_ATTR                       0: chat_id
                        72      COMPARE_OP                      55 (!=)
                        76      POP_JUMP_IF_TRUE                12 (to 102)
                        78      LOAD_FAST                       1: event
                        80      LOAD_ATTR                       2: inbox
                        100     POP_JUMP_IF_FALSE               11 (to 124)
                        102     NOP                             
                        104     LOAD_CONST                      0: None
                        106     NOP                             
                        108     NOP                             
                        110     NOP                             
                        112     JUMP_FORWARD                    135 (to 384)
                        120     POP_TOP                         
                        122     RETURN_CONST                    0: None
                        124     LOAD_FAST                       1: event
                        126     LOAD_ATTR                       4: max_id
                        146     LOAD_FAST                       0: self
                        148     STORE_ATTR                      3: _last_read
                        158     LOAD_GLOBAL                     9: NULL + list
                        168     LOAD_FAST                       0: self
                        170     LOAD_ATTR                       10: _pending_reads
                        190     LOAD_ATTR                       13: items
                        210     CALL                            0
                        218     CALL                            1
                        226     GET_ITER                        
                        228     FOR_ITER                        51 (to 332)
                        232     UNPACK_SEQUENCE                 2
                        236     STORE_FAST                      3: _var_var_20
                        238     STORE_FAST                      4: _var_var_22
                        240     LOAD_FAST                       3: _var_var_20
                        242     LOAD_FAST                       0: self
                        244     LOAD_ATTR                       6: _last_read
                        264     COMPARE_OP                      92 (>=)
                        268     POP_JUMP_IF_TRUE                1 (to 272)
                        270     JUMP_BACKWARD                   22 (to 228)
                        272     LOAD_FAST                       4: _var_var_22
                        274     LOAD_ATTR                       15: set_result
                        294     LOAD_CONST                      5: True
                        296     CALL                            1
                        304     POP_TOP                         
                        306     LOAD_FAST                       0: self
                        308     LOAD_ATTR                       10: _pending_reads
                        328     LOAD_FAST                       3: _var_var_20
                        330     DELETE_SUBSCR                   
                        332     JUMP_BACKWARD                   53 (to 228)
                        334     END_FOR                         
                        336     LOAD_CONST                      0: None
                        338     NOP                             
                        340     NOP                             
                        342     NOP                             
                        344     JUMP_FORWARD                    19 (to 384)
                        352     POP_TOP                         
                        354     RETURN_CONST                    0: None
                        356     PUSH_EXC_INFO                   
                        358     PUSH_NULL                       
                        360     LOAD_CONST                      4: '__pyarmor_exit_24098__'
                        362     NOP                             
                        364     LOAD_CONST                      3: b'<COAddr>\x05\x00\x00\x1aJ\x01\x00\x00\x00\x00\x00\x00\x00\x00\x00\x00\x00\x00\x00\x00'
                        366     CALL                            1
                        374     POP_TOP                         
                        376     RERAISE                         0
                        378     COPY                            3
                        380     POP_EXCEPT                      
                        382     RERAISE                         1
                        384     PUSH_NULL                       
                        386     LOAD_CONST                      4: '__pyarmor_exit_24098__'
                        388     LOAD_CONST                      3: b'<COAddr>\x05\x00\x00\x1aJ\x01\x00\x00\x00\x00\x00\x00\x00\x00\x00\x00\x00\x00\x00\x00'
                        390     BUILD_TUPLE                     1
                        392     CALL_FUNCTION_EX                0
                        394     POP_TOP                         
                        396     RETURN_VALUE                    
                    [Exception Table]
                        28 to 102 -> 356 [0] 
                        124 to 270 -> 356 [0] 
                        272 to 336 -> 356 [0] 
                        356 to 378 -> 378 [1] lasti
                [Code]
                    File Name: <frozen multithon.tl.custom.conversation>
                    Object Name: _get_message_id
                    Qualified Name: Conversation._get_message_id
                    Arg Count: 2
                    Pos Only Arg Count: 0
                    KW Only Arg Count: 0
                    Stack Size: 5
                    Flags: 0x20000003 (CO_OPTIMIZED | CO_NEWLOCALS | CO_PYARMOR_OBFUSCATED)
                    [Names]
                        'isinstance'
                        'int'
                        'id'
                        '_last_outgoing'
                        'ValueError'
                    [Locals+Names]
                        'self'
                        'message'
                        '__assert_armored__'
                    [Constants]
                        None
                        '__pyarmor_assert_24099__'
                        '__pyarmor_enter_24100__'
                        b'<COAddr>\x07\x00\x00\x1a\xba\x00\x00\x00\x00\x00\x00\x00\x00\x00\x00\x00\x00\x00\x00\x00'
                        '__pyarmor_exit_24101__'
                        'No message was sent previously'   # b'\x81\xcc\x17S>\xff\xad\xc1\x1a\xfd\x08\x80{\xed\xeb\xc5\x1cX\xb5\xb3\xea\xdb\\\xc9\x13f\xacI\x13\xbd\x07'
                    [Disassembly]
                        0       NOP                             
                        2       NOP                             
                        4       PUSH_NULL                       
                        6       LOAD_CONST                      2: '__pyarmor_enter_24100__'
                        8       LOAD_CONST                      3: b'<COAddr>\x07\x00\x00\x1a\xba\x00\x00\x00\x00\x00\x00\x00\x00\x00\x00\x00\x00\x00\x00\x00'
                        10      BUILD_TUPLE                     1
                        12      CALL_FUNCTION_EX                0
                        14      POP_TOP                         
                        16      RESUME                          0
                        18      NOP                             
                        20      NOP                             
                        22      NOP                             
                        24      NOP                             
                        26      NOP                             
                        28      LOAD_FAST                       1: message
                        30      POP_JUMP_IF_NONE                40 (to 112)
                        32      LOAD_GLOBAL                     1: NULL + isinstance
                        42      LOAD_FAST                       1: message
                        44      LOAD_GLOBAL                     2: int
                        54      CALL                            2
                        62      POP_JUMP_IF_FALSE               2 (to 68)
                        64      LOAD_FAST                       1: message
                        66      JUMP_FORWARD                    11 (to 90)
                        68      LOAD_FAST                       1: message
                        70      LOAD_ATTR                       4: id
                        90      NOP                             
                        92      NOP                             
                        94      NOP                             
                        96      NOP                             
                        98      JUMP_FORWARD                    70 (to 240)
                        100     CALL                            1
                        108     POP_TOP                         
                        110     RETURN_VALUE                    
                        112     LOAD_FAST                       0: self
                        114     LOAD_ATTR                       6: _last_outgoing
                        134     POP_JUMP_IF_FALSE               21 (to 178)
                        136     LOAD_FAST                       0: self
                        138     LOAD_ATTR                       6: _last_outgoing
                        158     NOP                             
                        160     NOP                             
                        162     NOP                             
                        164     JUMP_FORWARD                    37 (to 240)
                        166     CALL                            1
                        174     POP_TOP                         
                        176     RETURN_VALUE                    
                        178     LOAD_GLOBAL                     9: NULL + ValueError
                        188     PUSH_NULL                       
                        190     LOAD_CONST                      1: '__pyarmor_assert_24099__'
                        192     LOAD_CONST                      5: 'No message was sent previously'   # b'\x81\xcc\x17S>\xff\xad\xc1\x1a\xfd\x08\x80{\xed\xeb\xc5\x1cX\xb5\xb3\xea\xdb\\\xc9\x13f\xacI\x13\xbd\x07'
                        194     CALL                            1
                        202     CALL                            1
                        210     RAISE_VARARGS                   1
                        212     PUSH_EXC_INFO                   
                        214     PUSH_NULL                       
                        216     LOAD_CONST                      4: '__pyarmor_exit_24101__'
                        218     NOP                             
                        220     LOAD_CONST                      3: b'<COAddr>\x07\x00\x00\x1a\xba\x00\x00\x00\x00\x00\x00\x00\x00\x00\x00\x00\x00\x00\x00\x00'
                        222     CALL                            1
                        230     POP_TOP                         
                        232     RERAISE                         0
                        234     COPY                            3
                        236     POP_EXCEPT                      
                        238     RERAISE                         1
                        240     PUSH_NULL                       
                        242     LOAD_CONST                      4: '__pyarmor_exit_24101__'
                        244     LOAD_CONST                      3: b'<COAddr>\x07\x00\x00\x1a\xba\x00\x00\x00\x00\x00\x00\x00\x00\x00\x00\x00\x00\x00\x00\x00'
                        246     BUILD_TUPLE                     1
                        248     CALL_FUNCTION_EX                0
                        250     POP_TOP                         
                        252     RETURN_VALUE                    
                    [Exception Table]
                        28 to 90 -> 212 [0] 
                        112 to 158 -> 212 [0] 
                        178 to 212 -> 212 [0] 
                        212 to 234 -> 234 [1] lasti
                [Code]
                    File Name: <frozen multithon.tl.custom.conversation>
                    Object Name: _get_result
                    Qualified Name: Conversation._get_result
                    Arg Count: 6
                    Pos Only Arg Count: 0
                    KW Only Arg Count: 0
                    Stack Size: 7
                    Flags: 0x20000003 (CO_OPTIMIZED | CO_NEWLOCALS | CO_PYARMOR_OBFUSCATED)
                    [Names]
                        '_total_due'
                        '_timeout'
                        'min'
                        'asyncio'
                        'wait_for'
                        'float'
                        'time'
                    [Locals+Names]
                        'self'
                        'future'
                        'start_time'
                        'timeout'
                        'pending'
                        'target_id'
                        '__assert_armored__'
                        '_var_var_23'
                    [Constants]
                        None
                        '__pyarmor_assert_24102__'
                        '__pyarmor_enter_24103__'
                        b'<COAddr>\x07\x00\x00\x1a\xe2\x00\x00\x00\x00\x00\x00\x00\x00\x00\x00\x00\x00\x00\x00\x00'
                        'inf'
                        (
                            'timeout'
                        )
                        '__pyarmor_exit_24104__'
                    [Disassembly]
                        0       NOP                             
                        2       NOP                             
                        4       PUSH_NULL                       
                        6       LOAD_CONST                      2: '__pyarmor_enter_24103__'
                        8       LOAD_CONST                      3: b'<COAddr>\x07\x00\x00\x1a\xe2\x00\x00\x00\x00\x00\x00\x00\x00\x00\x00\x00\x00\x00\x00\x00'
                        10      BUILD_TUPLE                     1
                        12      CALL_FUNCTION_EX                0
                        14      POP_TOP                         
                        16      RESUME                          0
                        18      NOP                             
                        20      NOP                             
                        22      NOP                             
                        24      NOP                             
                        26      NOP                             
                        28      LOAD_FAST                       0: self
                        30      LOAD_ATTR                       0: _total_due
                        50      STORE_FAST                      7: _var_var_23
                        52      LOAD_FAST                       3: timeout
                        54      POP_JUMP_IF_NOT_NONE            12 (to 80)
                        56      LOAD_FAST                       0: self
                        58      LOAD_ATTR                       2: _timeout
                        78      STORE_FAST                      3: timeout
                        80      LOAD_FAST                       3: timeout
                        82      POP_JUMP_IF_NONE                15 (to 114)
                        84      LOAD_GLOBAL                     5: NULL + min
                        94      LOAD_FAST                       7: _var_var_23
                        96      LOAD_FAST                       2: start_time
                        98      LOAD_FAST                       3: timeout
                        100     BINARY_OP                       0 (+)
                        104     CALL                            2
                        112     STORE_FAST                      7: _var_var_23
                        114     LOAD_GLOBAL                     7: NULL + asyncio
                        124     LOAD_ATTR                       8: wait_for
                        144     LOAD_FAST                       1: future
                        146     LOAD_FAST                       7: _var_var_23
                        148     LOAD_GLOBAL                     11: NULL + float
                        158     LOAD_CONST                      4: 'inf'
                        160     CALL                            1
                        168     COMPARE_OP                      40 (==)
                        172     POP_JUMP_IF_FALSE               2 (to 178)
                        174     LOAD_CONST                      0: None
                        176     JUMP_FORWARD                    22 (to 222)
                        178     LOAD_FAST                       7: _var_var_23
                        180     LOAD_GLOBAL                     13: NULL + time
                        190     LOAD_ATTR                       12: time
                        210     CALL                            0
                        218     BINARY_OP                       10 (-)
                        222     KW_NAMES                        5: ('timeout',)
                        224     CALL                            2
                        232     NOP                             
                        234     NOP                             
                        236     NOP                             
                        238     JUMP_FORWARD                    20 (to 280)
                        240     CALL                            1
                        248     POP_TOP                         
                        250     RETURN_VALUE                    
                        252     PUSH_EXC_INFO                   
                        254     PUSH_NULL                       
                        256     LOAD_CONST                      6: '__pyarmor_exit_24104__'
                        258     NOP                             
                        260     LOAD_CONST                      3: b'<COAddr>\x07\x00\x00\x1a\xe2\x00\x00\x00\x00\x00\x00\x00\x00\x00\x00\x00\x00\x00\x00\x00'
                        262     CALL                            1
                        270     POP_TOP                         
                        272     RERAISE                         0
                        274     COPY                            3
                        276     POP_EXCEPT                      
                        278     RERAISE                         1
                        280     PUSH_NULL                       
                        282     LOAD_CONST                      6: '__pyarmor_exit_24104__'
                        284     LOAD_CONST                      3: b'<COAddr>\x07\x00\x00\x1a\xe2\x00\x00\x00\x00\x00\x00\x00\x00\x00\x00\x00\x00\x00\x00\x00'
                        286     BUILD_TUPLE                     1
                        288     CALL_FUNCTION_EX                0
                        290     POP_TOP                         
                        292     RETURN_VALUE                    
                    [Exception Table]
                        28 to 232 -> 252 [0] 
                        252 to 274 -> 274 [1] lasti
                [Code]
                    File Name: <frozen multithon.tl.custom.conversation>
                    Object Name: _cancel_all
                    Qualified Name: Conversation._cancel_all
                    Arg Count: 2
                    Pos Only Arg Count: 0
                    KW Only Arg Count: 0
                    Stack Size: 6
                    Flags: 0x20000003 (CO_OPTIMIZED | CO_NEWLOCALS | CO_PYARMOR_OBFUSCATED)
                    [Names]
                        '_cancelled'
                        'itertools'
                        'chain'
                        '_pending_responses'
                        'values'
                        '_pending_replies'
                        '_pending_edits'
                        'set_exception'
                        'cancel'
                        '_custom'
                    [Locals+Names]
                        'self'
                        'exception'
                        '__assert_armored__'
                        '_var_var_22'
                        '_var_var_24'
                        '_var_var_16'
                    [Constants]
                        None
                        '__pyarmor_assert_24105__'
                        '__pyarmor_enter_24106__'
                        b'<COAddr>\x07\x00\x00\x1a\xc0\x01\x00\x00\x00\x00\x00\x00\x00\x00\x00\x00\x00\x00\x00\x00'
                        True
                        '__pyarmor_exit_24107__'
                    [Disassembly]
                        0       NOP                             
                        2       NOP                             
                        4       PUSH_NULL                       
                        6       LOAD_CONST                      2: '__pyarmor_enter_24106__'
                        8       LOAD_CONST                      3: b'<COAddr>\x07\x00\x00\x1a\xc0\x01\x00\x00\x00\x00\x00\x00\x00\x00\x00\x00\x00\x00\x00\x00'
                        10      BUILD_TUPLE                     1
                        12      CALL_FUNCTION_EX                0
                        14      POP_TOP                         
                        16      RESUME                          0
                        18      NOP                             
                        20      NOP                             
                        22      NOP                             
                        24      NOP                             
                        26      NOP                             
                        28      LOAD_CONST                      4: True
                        30      LOAD_FAST                       0: self
                        32      STORE_ATTR                      0: _cancelled
                        42      LOAD_GLOBAL                     3: NULL + itertools
                        52      LOAD_ATTR                       4: chain
                        72      LOAD_FAST                       0: self
                        74      LOAD_ATTR                       6: _pending_responses
                        94      LOAD_ATTR                       9: values
                        114     CALL                            0
                        122     LOAD_FAST                       0: self
                        124     LOAD_ATTR                       10: _pending_replies
                        144     LOAD_ATTR                       9: values
                        164     CALL                            0
                        172     LOAD_FAST                       0: self
                        174     LOAD_ATTR                       12: _pending_edits
                        194     LOAD_ATTR                       9: values
                        214     CALL                            0
                        222     CALL                            3
                        230     GET_ITER                        
                        232     FOR_ITER                        38 (to 310)
                        236     STORE_FAST                      3: _var_var_22
                        238     LOAD_FAST                       1: exception
                        240     POP_JUMP_IF_FALSE               18 (to 278)
                        242     LOAD_FAST                       3: _var_var_22
                        244     LOAD_ATTR                       15: set_exception
                        264     LOAD_FAST                       1: exception
                        266     CALL                            1
                        274     POP_TOP                         
                        276     JUMP_BACKWARD                   23 (to 232)
                        278     LOAD_FAST                       3: _var_var_22
                        280     LOAD_ATTR                       17: cancel
                        300     CALL                            0
                        308     POP_TOP                         
                        310     JUMP_BACKWARD                   40 (to 232)
                        312     END_FOR                         
                        314     LOAD_FAST                       0: self
                        316     LOAD_ATTR                       18: _custom
                        336     LOAD_ATTR                       9: values
                        356     CALL                            0
                        364     GET_ITER                        
                        366     FOR_ITER                        41 (to 450)
                        370     UNPACK_SEQUENCE                 2
                        374     STORE_FAST                      4: _var_var_24
                        376     STORE_FAST                      5: _var_var_16
                        378     LOAD_FAST                       1: exception
                        380     POP_JUMP_IF_FALSE               18 (to 418)
                        382     LOAD_FAST                       5: _var_var_16
                        384     LOAD_ATTR                       15: set_exception
                        404     LOAD_FAST                       1: exception
                        406     CALL                            1
                        414     POP_TOP                         
                        416     JUMP_BACKWARD                   26 (to 366)
                        418     LOAD_FAST                       5: _var_var_16
                        420     LOAD_ATTR                       17: cancel
                        440     CALL                            0
                        448     POP_TOP                         
                        450     JUMP_BACKWARD                   43 (to 366)
                        452     END_FOR                         
                        454     LOAD_CONST                      0: None
                        456     NOP                             
                        458     NOP                             
                        460     NOP                             
                        462     JUMP_FORWARD                    19 (to 502)
                        470     POP_TOP                         
                        472     RETURN_CONST                    0: None
                        474     PUSH_EXC_INFO                   
                        476     PUSH_NULL                       
                        478     LOAD_CONST                      5: '__pyarmor_exit_24107__'
                        480     NOP                             
                        482     LOAD_CONST                      3: b'<COAddr>\x07\x00\x00\x1a\xc0\x01\x00\x00\x00\x00\x00\x00\x00\x00\x00\x00\x00\x00\x00\x00'
                        484     CALL                            1
                        492     POP_TOP                         
                        494     RERAISE                         0
                        496     COPY                            3
                        498     POP_EXCEPT                      
                        500     RERAISE                         1
                        502     PUSH_NULL                       
                        504     LOAD_CONST                      5: '__pyarmor_exit_24107__'
                        506     LOAD_CONST                      3: b'<COAddr>\x07\x00\x00\x1a\xc0\x01\x00\x00\x00\x00\x00\x00\x00\x00\x00\x00\x00\x00\x00\x00'
                        508     BUILD_TUPLE                     1
                        510     CALL_FUNCTION_EX                0
                        512     POP_TOP                         
                        514     RETURN_VALUE                    
                    [Exception Table]
                        28 to 454 -> 474 [0] 
                        474 to 496 -> 496 [1] lasti
                [Code]
                    File Name: <frozen multithon.tl.custom.conversation>
                    Object Name: __aenter__
                    Qualified Name: Conversation.__aenter__
                    Arg Count: 1
                    Pos Only Arg Count: 0
                    KW Only Arg Count: 0
                    Stack Size: 9
                    Flags: 0x20000083 (CO_OPTIMIZED | CO_NEWLOCALS | CO_COROUTINE | CO_PYARMOR_OBFUSCATED)
                    [Names]
                        '_client'
                        'get_input_entity'
                        '_input_chat'
                        'utils'
                        'get_peer'
                        '_chat_peer'
                        'get_peer_id'
                        '_conversations'
                        '_exclusive'
                        'errors'
                        'AlreadyInConversationError'
                        'add'
                        '_cancelled'
                        '_last_outgoing'
                        '_last_incoming'
                        '_outgoing'
                        '_incoming'
                        '_pending_responses'
                        '_pending_replies'
                        '_pending_edits'
                        '_response_indices'
                        '_reply_indices'
                        '_edit_dates'
                        '_custom'
                        'clear'
                        '_total_timeout'
                        'time'
                        '_total_due'
                        'float'
                    [Locals+Names]
                        'self'
                        '__assert_armored__'
                        '_var_var_25'
                        '_var_var_26'
                        '_var_var_27'
                    [Constants]
                        None
                        '__pyarmor_assert_24108__'
                        '__pyarmor_enter_24109__'
                        b'<COAddr>\x07\x00\x00\x1eD\x03\x00\x00\x00\x00\x00\x00\x00\x00\x00\x00\x00\x00\x00\x00'
                        False
                        0
                        'inf'
                        '__pyarmor_exit_24110__'
                    [Disassembly]
                        0       RETURN_GENERATOR                
                        2       POP_TOP                         
                        4       NOP                             
                        6       NOP                             
                        8       PUSH_NULL                       
                        10      LOAD_CONST                      2: '__pyarmor_enter_24109__'
                        12      LOAD_CONST                      3: b'<COAddr>\x07\x00\x00\x1eD\x03\x00\x00\x00\x00\x00\x00\x00\x00\x00\x00\x00\x00\x00\x00'
                        14      BUILD_TUPLE                     1
                        16      CALL_FUNCTION_EX                0
                        18      POP_TOP                         
                        20      RESUME                          0
                        22      NOP                             
                        24      NOP                             
                        26      NOP                             
                        28      NOP                             
                        30      NOP                             
                        32      LOAD_FAST                       0: self
                        34      LOAD_ATTR                       0: _client
                        54      LOAD_ATTR                       3: get_input_entity
                        74      LOAD_FAST                       0: self
                        76      LOAD_ATTR                       4: _input_chat
                        96      CALL                            1
                        104     GET_AWAITABLE                   0
                        106     LOAD_CONST                      0: None
                        108     SEND                            3 (to 116)
                        112     YIELD_VALUE                     3
                        114     RESUME                          3
                        116     JUMP_BACKWARD_NO_INTERRUPT      5 (to 108)
                        118     END_SEND                        
                        120     LOAD_FAST                       0: self
                        122     STORE_ATTR                      2: _input_chat
                        132     LOAD_GLOBAL                     7: NULL + utils
                        142     LOAD_ATTR                       8: get_peer
                        162     LOAD_FAST                       0: self
                        164     LOAD_ATTR                       4: _input_chat
                        184     CALL                            1
                        192     LOAD_FAST                       0: self
                        194     STORE_ATTR                      5: _chat_peer
                        204     LOAD_GLOBAL                     7: NULL + utils
                        214     LOAD_ATTR                       12: get_peer_id
                        234     LOAD_FAST                       0: self
                        236     LOAD_ATTR                       10: _chat_peer
                        256     CALL                            1
                        264     STORE_FAST                      2: _var_var_25
                        266     LOAD_FAST                       0: self
                        268     LOAD_ATTR                       0: _client
                        288     LOAD_ATTR                       14: _conversations
                        308     LOAD_FAST                       2: _var_var_25
                        310     BINARY_SUBSCR                   
                        314     STORE_FAST                      3: _var_var_26
                        316     LOAD_FAST                       0: self
                        318     LOAD_ATTR                       16: _exclusive
                        338     POP_JUMP_IF_FALSE               22 (to 384)
                        340     LOAD_FAST                       3: _var_var_26
                        342     POP_JUMP_IF_FALSE               20 (to 384)
                        344     LOAD_GLOBAL                     19: NULL + errors
                        354     LOAD_ATTR                       20: AlreadyInConversationError
                        374     CALL                            0
                        382     RAISE_VARARGS                   1
                        384     LOAD_FAST                       3: _var_var_26
                        386     LOAD_ATTR                       23: add
                        406     LOAD_FAST                       0: self
                        408     CALL                            1
                        416     POP_TOP                         
                        418     LOAD_CONST                      4: False
                        420     LOAD_FAST                       0: self
                        422     STORE_ATTR                      12: _cancelled
                        432     LOAD_CONST                      5: 0
                        434     LOAD_FAST                       0: self
                        436     STORE_ATTR                      13: _last_outgoing
                        446     LOAD_CONST                      5: 0
                        448     LOAD_FAST                       0: self
                        450     STORE_ATTR                      14: _last_incoming
                        460     LOAD_FAST                       0: self
                        462     LOAD_ATTR                       30: _outgoing
                        482     LOAD_FAST                       0: self
                        484     LOAD_ATTR                       32: _incoming
                        504     LOAD_FAST                       0: self
                        506     LOAD_ATTR                       34: _pending_responses
                        526     LOAD_FAST                       0: self
                        528     LOAD_ATTR                       36: _pending_replies
                        548     LOAD_FAST                       0: self
                        550     LOAD_ATTR                       38: _pending_edits
                        570     LOAD_FAST                       0: self
                        572     LOAD_ATTR                       40: _response_indices
                        592     LOAD_FAST                       0: self
                        594     LOAD_ATTR                       42: _reply_indices
                        614     LOAD_FAST                       0: self
                        616     LOAD_ATTR                       44: _edit_dates
                        636     LOAD_FAST                       0: self
                        638     LOAD_ATTR                       46: _custom
                        658     BUILD_TUPLE                     9
                        660     GET_ITER                        
                        662     FOR_ITER                        18 (to 700)
                        666     STORE_FAST                      4: _var_var_27
                        668     LOAD_FAST                       4: _var_var_27
                        670     LOAD_ATTR                       49: clear
                        690     CALL                            0
                        698     POP_TOP                         
                        700     JUMP_BACKWARD                   20 (to 662)
                        702     END_FOR                         
                        704     LOAD_FAST                       0: self
                        706     LOAD_ATTR                       50: _total_timeout
                        726     POP_JUMP_IF_FALSE               39 (to 806)
                        728     LOAD_GLOBAL                     53: NULL + time
                        738     LOAD_ATTR                       52: time
                        758     CALL                            0
                        766     LOAD_FAST                       0: self
                        768     LOAD_ATTR                       50: _total_timeout
                        788     BINARY_OP                       0 (+)
                        792     LOAD_FAST                       0: self
                        794     STORE_ATTR                      27: _total_due
                        804     JUMP_FORWARD                    16 (to 838)
                        806     LOAD_GLOBAL                     57: NULL + float
                        816     LOAD_CONST                      6: 'inf'
                        818     CALL                            1
                        826     LOAD_FAST                       0: self
                        828     STORE_ATTR                      27: _total_due
                        838     LOAD_FAST                       0: self
                        840     NOP                             
                        842     NOP                             
                        844     NOP                             
                        846     JUMP_FORWARD                    25 (to 898)
                        848     CALL                            1
                        856     POP_TOP                         
                        858     RETURN_VALUE                    
                        860     CLEANUP_THROW                   
                        862     JUMP_BACKWARD                   374 (to 118)
                        866     PUSH_EXC_INFO                   
                        868     PUSH_NULL                       
                        870     LOAD_CONST                      7: '__pyarmor_exit_24110__'
                        872     NOP                             
                        874     LOAD_CONST                      3: b'<COAddr>\x07\x00\x00\x1eD\x03\x00\x00\x00\x00\x00\x00\x00\x00\x00\x00\x00\x00\x00\x00'
                        876     CALL                            1
                        884     POP_TOP                         
                        886     RERAISE                         0
                        888     COPY                            3
                        890     POP_EXCEPT                      
                        892     RERAISE                         1
                        894     CALL_INTRINSIC_1                3 (INTRINSIC_STOPITERATION_ERROR)
                        896     RERAISE                         1
                        898     PUSH_NULL                       
                        900     LOAD_CONST                      7: '__pyarmor_exit_24110__'
                        902     LOAD_CONST                      3: b'<COAddr>\x07\x00\x00\x1eD\x03\x00\x00\x00\x00\x00\x00\x00\x00\x00\x00\x00\x00\x00\x00'
                        904     BUILD_TUPLE                     1
                        906     CALL_FUNCTION_EX                0
                        908     POP_TOP                         
                        910     RETURN_VALUE                    
                    [Exception Table]
                        4 to 30 -> 894 [0] lasti
                        32 to 112 -> 866 [0] 
                        112 to 114 -> 860 [2] 
                        114 to 840 -> 866 [0] 
                        840 to 860 -> 894 [0] lasti
                        860 to 862 -> 866 [0] 
                        866 to 888 -> 888 [1] lasti
                        888 to 894 -> 894 [0] lasti
                [Code]
                    File Name: <frozen multithon.tl.custom.conversation>
                    Object Name: cancel
                    Qualified Name: Conversation.cancel
                    Arg Count: 1
                    Pos Only Arg Count: 0
                    KW Only Arg Count: 0
                    Stack Size: 5
                    Flags: 0x20000003 (CO_OPTIMIZED | CO_NEWLOCALS | CO_PYARMOR_OBFUSCATED)
                    [Names]
                        '_cancel_all'
                    [Locals+Names]
                        'self'
                        '__assert_armored__'
                    [Constants]
                        '\n        Cancels the current conversation. Pending responses and subsequent\n        calls to get a response will raise ``asyncio.CancelledError``.\n\n        This method is synchronous and should not be awaited.\n        '
                        '__pyarmor_assert_24111__'
                        '__pyarmor_enter_24112__'
                        b'<COAddr>\x07\x00\x00\x1a6\x00\x00\x00\x00\x00\x00\x00\x00\x00\x00\x00\x00\x00\x00\x00'
                        '__pyarmor_exit_24113__'
                        None
                    [Disassembly]
                        0       NOP                             
                        2       NOP                             
                        4       PUSH_NULL                       
                        6       LOAD_CONST                      2: '__pyarmor_enter_24112__'
                        8       LOAD_CONST                      3: b'<COAddr>\x07\x00\x00\x1a6\x00\x00\x00\x00\x00\x00\x00\x00\x00\x00\x00\x00\x00\x00\x00'
                        10      BUILD_TUPLE                     1
                        12      CALL_FUNCTION_EX                0
                        14      POP_TOP                         
                        16      RESUME                          0
                        18      NOP                             
                        20      NOP                             
                        22      NOP                             
                        24      NOP                             
                        26      NOP                             
                        28      LOAD_FAST                       0: self
                        30      LOAD_ATTR                       1: _cancel_all
                        50      CALL                            0
                        58      POP_TOP                         
                        60      LOAD_CONST                      5: None
                        62      NOP                             
                        64      NOP                             
                        66      NOP                             
                        68      JUMP_FORWARD                    19 (to 108)
                        76      POP_TOP                         
                        78      RETURN_CONST                    5: None
                        80      PUSH_EXC_INFO                   
                        82      PUSH_NULL                       
                        84      LOAD_CONST                      4: '__pyarmor_exit_24113__'
                        86      NOP                             
                        88      LOAD_CONST                      3: b'<COAddr>\x07\x00\x00\x1a6\x00\x00\x00\x00\x00\x00\x00\x00\x00\x00\x00\x00\x00\x00\x00'
                        90      CALL                            1
                        98      POP_TOP                         
                        100     RERAISE                         0
                        102     COPY                            3
                        104     POP_EXCEPT                      
                        106     RERAISE                         1
                        108     PUSH_NULL                       
                        110     LOAD_CONST                      4: '__pyarmor_exit_24113__'
                        112     LOAD_CONST                      3: b'<COAddr>\x07\x00\x00\x1a6\x00\x00\x00\x00\x00\x00\x00\x00\x00\x00\x00\x00\x00\x00\x00'
                        114     BUILD_TUPLE                     1
                        116     CALL_FUNCTION_EX                0
                        118     POP_TOP                         
                        120     RETURN_VALUE                    
                    [Exception Table]
                        28 to 60 -> 80 [0] 
                        80 to 102 -> 102 [1] lasti
                [Code]
                    File Name: <frozen multithon.tl.custom.conversation>
                    Object Name: cancel_all
                    Qualified Name: Conversation.cancel_all
                    Arg Count: 1
                    Pos Only Arg Count: 0
                    KW Only Arg Count: 0
                    Stack Size: 5
                    Flags: 0x20000083 (CO_OPTIMIZED | CO_NEWLOCALS | CO_COROUTINE | CO_PYARMOR_OBFUSCATED)
                    [Names]
                        '_client'
                        'get_peer_id'
                        '_input_chat'
                        '_conversations'
                        'cancel'
                    [Locals+Names]
                        'self'
                        '__assert_armored__'
                        '_var_var_25'
                        '_var_var_28'
                    [Constants]
                        "\n        Calls `cancel` on *all* conversations in this chat.\n\n        Note that you should ``await`` this method, since it's meant to be\n        used outside of a context manager, and it needs to resolve the chat.\n        "
                        '__pyarmor_assert_24114__'
                        '__pyarmor_enter_24115__'
                        b'<COAddr>\x05\x00\x00\x1e\xd0\x00\x00\x00\x00\x00\x00\x00\x00\x00\x00\x00\x00\x00\x00\x00'
                        None
                        '__pyarmor_exit_24116__'
                    [Disassembly]
                        0       RETURN_GENERATOR                
                        2       POP_TOP                         
                        4       NOP                             
                        6       NOP                             
                        8       PUSH_NULL                       
                        10      LOAD_CONST                      2: '__pyarmor_enter_24115__'
                        12      LOAD_CONST                      3: b'<COAddr>\x05\x00\x00\x1e\xd0\x00\x00\x00\x00\x00\x00\x00\x00\x00\x00\x00\x00\x00\x00\x00'
                        14      BUILD_TUPLE                     1
                        16      CALL_FUNCTION_EX                0
                        18      POP_TOP                         
                        20      RESUME                          0
                        22      NOP                             
                        24      NOP                             
                        26      NOP                             
                        28      NOP                             
                        30      NOP                             
                        32      LOAD_FAST                       0: self
                        34      LOAD_ATTR                       0: _client
                        54      LOAD_ATTR                       3: get_peer_id
                        74      LOAD_FAST                       0: self
                        76      LOAD_ATTR                       4: _input_chat
                        96      CALL                            1
                        104     GET_AWAITABLE                   0
                        106     LOAD_CONST                      4: None
                        108     SEND                            3 (to 116)
                        112     YIELD_VALUE                     3
                        114     RESUME                          3
                        116     JUMP_BACKWARD_NO_INTERRUPT      5 (to 108)
                        118     END_SEND                        
                        120     STORE_FAST                      2: _var_var_25
                        122     LOAD_FAST                       0: self
                        124     LOAD_ATTR                       0: _client
                        144     LOAD_ATTR                       6: _conversations
                        164     LOAD_FAST                       2: _var_var_25
                        166     BINARY_SUBSCR                   
                        170     GET_ITER                        
                        172     FOR_ITER                        18 (to 210)
                        176     STORE_FAST                      3: _var_var_28
                        178     LOAD_FAST                       3: _var_var_28
                        180     LOAD_ATTR                       9: cancel
                        200     CALL                            0
                        208     POP_TOP                         
                        210     JUMP_BACKWARD                   20 (to 172)
                        212     END_FOR                         
                        214     LOAD_CONST                      4: None
                        216     NOP                             
                        218     NOP                             
                        220     NOP                             
                        222     JUMP_FORWARD                    23 (to 270)
                        230     POP_TOP                         
                        232     RETURN_CONST                    4: None
                        234     CLEANUP_THROW                   
                        236     JUMP_BACKWARD                   60 (to 118)
                        238     PUSH_EXC_INFO                   
                        240     PUSH_NULL                       
                        242     LOAD_CONST                      5: '__pyarmor_exit_24116__'
                        244     NOP                             
                        246     LOAD_CONST                      3: b'<COAddr>\x05\x00\x00\x1e\xd0\x00\x00\x00\x00\x00\x00\x00\x00\x00\x00\x00\x00\x00\x00\x00'
                        248     CALL                            1
                        256     POP_TOP                         
                        258     RERAISE                         0
                        260     COPY                            3
                        262     POP_EXCEPT                      
                        264     RERAISE                         1
                        266     CALL_INTRINSIC_1                3 (INTRINSIC_STOPITERATION_ERROR)
                        268     RERAISE                         1
                        270     PUSH_NULL                       
                        272     LOAD_CONST                      5: '__pyarmor_exit_24116__'
                        274     LOAD_CONST                      3: b'<COAddr>\x05\x00\x00\x1e\xd0\x00\x00\x00\x00\x00\x00\x00\x00\x00\x00\x00\x00\x00\x00\x00'
                        276     BUILD_TUPLE                     1
                        278     CALL_FUNCTION_EX                0
                        280     POP_TOP                         
                        282     RETURN_VALUE                    
                    [Exception Table]
                        4 to 30 -> 266 [0] lasti
                        32 to 112 -> 238 [0] 
                        112 to 114 -> 234 [2] 
                        114 to 214 -> 238 [0] 
                        214 to 234 -> 266 [0] lasti
                        234 to 236 -> 238 [0] 
                        238 to 260 -> 260 [1] lasti
                        260 to 266 -> 266 [0] lasti
                [Code]
                    File Name: <frozen multithon.tl.custom.conversation>
                    Object Name: __aexit__
                    Qualified Name: Conversation.__aexit__
                    Arg Count: 4
                    Pos Only Arg Count: 0
                    KW Only Arg Count: 0
                    Stack Size: 5
                    Flags: 0x20000083 (CO_OPTIMIZED | CO_NEWLOCALS | CO_COROUTINE | CO_PYARMOR_OBFUSCATED)
                    [Names]
                        'utils'
                        'get_peer_id'
                        '_chat_peer'
                        '_client'
                        '_conversations'
                        'discard'
                        '_cancel_all'
                    [Locals+Names]
                        'self'
                        'exc_type'
                        'exc_val'
                        'exc_tb'
                        '__assert_armored__'
                        '_var_var_25'
                        '_var_var_26'
                    [Constants]
                        None
                        '__pyarmor_assert_24117__'
                        '__pyarmor_enter_24118__'
                        b'<COAddr>\x07\x00\x00\x1e\xfa\x00\x00\x00\x00\x00\x00\x00\x00\x00\x00\x00\x00\x00\x00\x00'
                        '__pyarmor_exit_24119__'
                    [Disassembly]
                        0       RETURN_GENERATOR                
                        2       POP_TOP                         
                        4       NOP                             
                        6       NOP                             
                        8       PUSH_NULL                       
                        10      LOAD_CONST                      2: '__pyarmor_enter_24118__'
                        12      LOAD_CONST                      3: b'<COAddr>\x07\x00\x00\x1e\xfa\x00\x00\x00\x00\x00\x00\x00\x00\x00\x00\x00\x00\x00\x00\x00'
                        14      BUILD_TUPLE                     1
                        16      CALL_FUNCTION_EX                0
                        18      POP_TOP                         
                        20      RESUME                          0
                        22      NOP                             
                        24      NOP                             
                        26      NOP                             
                        28      NOP                             
                        30      NOP                             
                        32      LOAD_GLOBAL                     1: NULL + utils
                        42      LOAD_ATTR                       2: get_peer_id
                        62      LOAD_FAST                       0: self
                        64      LOAD_ATTR                       4: _chat_peer
                        84      CALL                            1
                        92      STORE_FAST                      5: _var_var_25
                        94      LOAD_FAST                       0: self
                        96      LOAD_ATTR                       6: _client
                        116     LOAD_ATTR                       8: _conversations
                        136     LOAD_FAST                       5: _var_var_25
                        138     BINARY_SUBSCR                   
                        142     STORE_FAST                      6: _var_var_26
                        144     LOAD_FAST                       6: _var_var_26
                        146     LOAD_ATTR                       11: discard
                        166     LOAD_FAST                       0: self
                        168     CALL                            1
                        176     POP_TOP                         
                        178     LOAD_FAST                       6: _var_var_26
                        180     POP_JUMP_IF_TRUE                23 (to 228)
                        182     LOAD_FAST                       0: self
                        184     LOAD_ATTR                       6: _client
                        204     LOAD_ATTR                       8: _conversations
                        224     LOAD_FAST                       5: _var_var_25
                        226     DELETE_SUBSCR                   
                        228     LOAD_FAST                       0: self
                        230     LOAD_ATTR                       13: _cancel_all
                        250     CALL                            0
                        258     POP_TOP                         
                        260     LOAD_CONST                      0: None
                        262     NOP                             
                        264     NOP                             
                        266     NOP                             
                        268     JUMP_FORWARD                    21 (to 312)
                        276     POP_TOP                         
                        278     RETURN_CONST                    0: None
                        280     PUSH_EXC_INFO                   
                        282     PUSH_NULL                       
                        284     LOAD_CONST                      4: '__pyarmor_exit_24119__'
                        286     NOP                             
                        288     LOAD_CONST                      3: b'<COAddr>\x07\x00\x00\x1e\xfa\x00\x00\x00\x00\x00\x00\x00\x00\x00\x00\x00\x00\x00\x00\x00'
                        290     CALL                            1
                        298     POP_TOP                         
                        300     RERAISE                         0
                        302     COPY                            3
                        304     POP_EXCEPT                      
                        306     RERAISE                         1
                        308     CALL_INTRINSIC_1                3 (INTRINSIC_STOPITERATION_ERROR)
                        310     RERAISE                         1
                        312     PUSH_NULL                       
                        314     LOAD_CONST                      4: '__pyarmor_exit_24119__'
                        316     LOAD_CONST                      3: b'<COAddr>\x07\x00\x00\x1e\xfa\x00\x00\x00\x00\x00\x00\x00\x00\x00\x00\x00\x00\x00\x00\x00'
                        318     BUILD_TUPLE                     1
                        320     CALL_FUNCTION_EX                0
                        322     POP_TOP                         
                        324     RETURN_VALUE                    
                    [Exception Table]
                        4 to 30 -> 308 [0] lasti
                        32 to 260 -> 280 [0] 
                        260 to 280 -> 308 [0] lasti
                        280 to 302 -> 302 [1] lasti
                        302 to 308 -> 308 [0] lasti
                '__pyarmor_exit_24056__'
                (
                    None
                )
            [Disassembly]
                0       NOP                             
                2       LOAD_NAME                       0: __name__
                4       STORE_NAME                      1: __module__
                6       LOAD_CONST                      0: 'Conversation'
                8       STORE_NAME                      2: __qualname__
                10      LOAD_CONST                      1: '\n    Represents a conversation inside an specific chat.\n\n    A conversation keeps track of new messages since it was\n    created until its exit and easily lets you query the\n    current state.\n\n    If you need a conversation across two or more chats,\n    you should use two conversations and synchronize them\n    as you better see fit.\n    '
                12      STORE_NAME                      3: __doc__
                14      NOP                             
                16      PUSH_NULL                       
                18      LOAD_CONST                      3: '__pyarmor_enter_24055__'
                20      LOAD_CONST                      4: b'<COAddr>\x07\x00\x00&\x1e\x01\x00\x00\x00\x00\x00\x00\x00\x00\x00\x00\x00\x00\x00\x00'
                22      BUILD_TUPLE                     1
                24      CALL_FUNCTION_EX                0
                26      POP_TOP                         
                28      RESUME                          0
                30      NOP                             
                32      NOP                             
                34      NOP                             
                36      NOP                             
                38      NOP                             
                40      LOAD_CONST                      5: 0
                42      STORE_NAME                      5: _id_counter
                44      LOAD_CONST                      5: 0
                46      STORE_NAME                      6: _custom_counter
                48      LOAD_CONST                      6: <CODE> __init__
                50      MAKE_FUNCTION                   0
                52      STORE_NAME                      7: __init__
                54      LOAD_NAME                       8: _checks_cancelled
                56      LOAD_CONST                      7: <CODE> send_message
                58      MAKE_FUNCTION                   0
                60      CALL                            0
                68      STORE_NAME                      9: send_message
                70      LOAD_NAME                       8: _checks_cancelled
                72      LOAD_CONST                      8: <CODE> send_file
                74      MAKE_FUNCTION                   0
                76      CALL                            0
                84      STORE_NAME                      10: send_file
                86      LOAD_NAME                       8: _checks_cancelled
                88      LOAD_CONST                      30: (None,)
                90      LOAD_CONST                      10: <CODE> mark_read
                92      MAKE_FUNCTION                   1
                94      CALL                            0
                102     STORE_NAME                      11: mark_read
                104     LOAD_CONST                      30: (None,)
                106     LOAD_CONST                      9: None
                108     LOAD_CONST                      11: ('timeout',)
                110     BUILD_CONST_KEY_MAP             1
                112     LOAD_CONST                      12: <CODE> get_response
                114     MAKE_FUNCTION                   3
                116     STORE_NAME                      12: get_response
                118     LOAD_CONST                      30: (None,)
                120     LOAD_CONST                      9: None
                122     LOAD_CONST                      11: ('timeout',)
                124     BUILD_CONST_KEY_MAP             1
                126     LOAD_CONST                      13: <CODE> get_reply
                128     MAKE_FUNCTION                   3
                130     STORE_NAME                      13: get_reply
                132     LOAD_CONST                      14: <CODE> _get_message
                134     MAKE_FUNCTION                   0
                136     STORE_NAME                      14: _get_message
                138     LOAD_CONST                      30: (None,)
                140     LOAD_CONST                      9: None
                142     LOAD_CONST                      11: ('timeout',)
                144     BUILD_CONST_KEY_MAP             1
                146     LOAD_CONST                      15: <CODE> get_edit
                148     MAKE_FUNCTION                   3
                150     STORE_NAME                      15: get_edit
                152     LOAD_CONST                      30: (None,)
                154     LOAD_CONST                      9: None
                156     LOAD_CONST                      11: ('timeout',)
                158     BUILD_CONST_KEY_MAP             1
                160     LOAD_CONST                      16: <CODE> wait_read
                162     MAKE_FUNCTION                   3
                164     STORE_NAME                      16: wait_read
                166     LOAD_CONST                      9: None
                168     LOAD_CONST                      11: ('timeout',)
                170     BUILD_CONST_KEY_MAP             1
                172     LOAD_CONST                      17: <CODE> wait_event
                174     MAKE_FUNCTION                   2
                176     STORE_NAME                      17: wait_event
                178     LOAD_CONST                      18: <CODE> _check_custom
                180     MAKE_FUNCTION                   0
                182     STORE_NAME                      18: _check_custom
                184     LOAD_CONST                      19: <CODE> _on_new_message
                186     MAKE_FUNCTION                   0
                188     STORE_NAME                      19: _on_new_message
                190     LOAD_CONST                      20: <CODE> _on_edit
                192     MAKE_FUNCTION                   0
                194     STORE_NAME                      20: _on_edit
                196     LOAD_CONST                      21: <CODE> _on_read
                198     MAKE_FUNCTION                   0
                200     STORE_NAME                      21: _on_read
                202     LOAD_CONST                      22: <CODE> _get_message_id
                204     MAKE_FUNCTION                   0
                206     STORE_NAME                      22: _get_message_id
                208     LOAD_NAME                       8: _checks_cancelled
                210     LOAD_CONST                      23: <CODE> _get_result
                212     MAKE_FUNCTION                   0
                214     CALL                            0
                222     STORE_NAME                      23: _get_result
                224     LOAD_CONST                      30: (None,)
                226     LOAD_CONST                      24: <CODE> _cancel_all
                228     MAKE_FUNCTION                   1
                230     STORE_NAME                      24: _cancel_all
                232     LOAD_CONST                      25: <CODE> __aenter__
                234     MAKE_FUNCTION                   0
                236     STORE_NAME                      25: __aenter__
                238     LOAD_CONST                      26: <CODE> cancel
                240     MAKE_FUNCTION                   0
                242     STORE_NAME                      26: cancel
                244     LOAD_CONST                      27: <CODE> cancel_all
                246     MAKE_FUNCTION                   0
                248     STORE_NAME                      27: cancel_all
                250     LOAD_CONST                      28: <CODE> __aexit__
                252     MAKE_FUNCTION                   0
                254     STORE_NAME                      28: __aexit__
                256     LOAD_NAME                       29: helpers
                258     LOAD_ATTR                       60: _sync_enter
                278     STORE_NAME                      31: __enter__
                280     LOAD_NAME                       29: helpers
                282     LOAD_ATTR                       64: _sync_exit
                302     STORE_NAME                      33: __exit__
                304     LOAD_CONST                      9: None
                306     NOP                             
                308     NOP                             
                310     NOP                             
                312     JUMP_FORWARD                    19 (to 352)
                320     POP_TOP                         
                322     RETURN_CONST                    9: None
                324     PUSH_EXC_INFO                   
                326     PUSH_NULL                       
                328     LOAD_CONST                      29: '__pyarmor_exit_24056__'
                330     NOP                             
                332     LOAD_CONST                      4: b'<COAddr>\x07\x00\x00&\x1e\x01\x00\x00\x00\x00\x00\x00\x00\x00\x00\x00\x00\x00\x00\x00'
                334     CALL                            1
                342     POP_TOP                         
                344     RERAISE                         0
                346     COPY                            3
                348     POP_EXCEPT                      
                350     RERAISE                         1
                352     PUSH_NULL                       
                354     LOAD_CONST                      29: '__pyarmor_exit_24056__'
                356     LOAD_CONST                      4: b'<COAddr>\x07\x00\x00&\x1e\x01\x00\x00\x00\x00\x00\x00\x00\x00\x00\x00\x00\x00\x00\x00'
                358     BUILD_TUPLE                     1
                360     CALL_FUNCTION_EX                0
                362     POP_TOP                         
                364     RETURN_VALUE                    
            [Exception Table]
                40 to 304 -> 324 [0] 
                324 to 346 -> 346 [1] lasti
        'Conversation'
        '__pyarmor_exit_24047__'
    [Disassembly]
        0       NOP                             
        2       NOP                             
        4       PUSH_NULL                       
        6       LOAD_CONST                      1: '__pyarmor_enter_24046__'
        8       LOAD_CONST                      2: b'<COAddr>\x07\x00\x00\x1a|\x00\x00\x00\x00\x00\x00\x00\x00\x00\x00\x00\x00\x00\x00\x00'
        10      BUILD_TUPLE                     1
        12      CALL_FUNCTION_EX                0
        14      POP_TOP                         
        16      RESUME                          0
        18      NOP                             
        20      NOP                             
        22      NOP                             
        24      NOP                             
        26      LOAD_CONST                      3: 0
        28      LOAD_CONST                      4: None
        30      IMPORT_NAME                     1: asyncio
        32      STORE_NAME                      1: asyncio
        34      LOAD_CONST                      3: 0
        36      LOAD_CONST                      4: None
        38      IMPORT_NAME                     2: functools
        40      STORE_NAME                      2: functools
        42      LOAD_CONST                      3: 0
        44      LOAD_CONST                      4: None
        46      IMPORT_NAME                     3: inspect
        48      STORE_NAME                      3: inspect
        50      LOAD_CONST                      3: 0
        52      LOAD_CONST                      4: None
        54      IMPORT_NAME                     4: itertools
        56      STORE_NAME                      4: itertools
        58      LOAD_CONST                      3: 0
        60      LOAD_CONST                      4: None
        62      IMPORT_NAME                     5: time
        64      STORE_NAME                      5: time
        66      LOAD_CONST                      5: 1
        68      LOAD_CONST                      6: ('ChatGetter',)
        70      IMPORT_NAME                     6: chatgetter
        72      IMPORT_FROM                     7: ChatGetter
        74      STORE_NAME                      7: ChatGetter
        76      POP_TOP                         
        78      LOAD_CONST                      7: 3
        80      LOAD_CONST                      8: ('helpers', 'utils', 'errors')
        82      IMPORT_NAME                     8: 
        84      IMPORT_FROM                     9: helpers
        86      STORE_NAME                      9: helpers
        88      IMPORT_FROM                     10: utils
        90      STORE_NAME                      10: utils
        92      IMPORT_FROM                     11: errors
        94      STORE_NAME                      11: errors
        96      POP_TOP                         
        98      LOAD_CONST                      9: 0.001
        100     STORE_NAME                      12: _EDIT_COLLISION_DELTA
        102     LOAD_CONST                      10: <CODE> _checks_cancelled
        104     MAKE_FUNCTION                   0
        106     STORE_NAME                      13: _checks_cancelled
        108     PUSH_NULL                       
        110     LOAD_BUILD_CLASS                
        112     LOAD_CONST                      11: <CODE> Conversation
        114     MAKE_FUNCTION                   0
        116     LOAD_CONST                      12: 'Conversation'
        118     LOAD_NAME                       7: ChatGetter
        120     CALL                            3
        128     STORE_NAME                      14: Conversation
        130     LOAD_CONST                      4: None
        132     NOP                             
        134     NOP                             
        136     NOP                             
        138     JUMP_FORWARD                    19 (to 178)
        146     POP_TOP                         
        148     RETURN_CONST                    4: None
        150     PUSH_EXC_INFO                   
        152     PUSH_NULL                       
        154     LOAD_CONST                      13: '__pyarmor_exit_24047__'
        156     NOP                             
        158     LOAD_CONST                      2: b'<COAddr>\x07\x00\x00\x1a|\x00\x00\x00\x00\x00\x00\x00\x00\x00\x00\x00\x00\x00\x00\x00'
        160     CALL                            1
        168     POP_TOP                         
        170     RERAISE                         0
        172     COPY                            3
        174     POP_EXCEPT                      
        176     RERAISE                         1
        178     PUSH_NULL                       
        180     LOAD_CONST                      13: '__pyarmor_exit_24047__'
        182     LOAD_CONST                      2: b'<COAddr>\x07\x00\x00\x1a|\x00\x00\x00\x00\x00\x00\x00\x00\x00\x00\x00\x00\x00\x00\x00'
        184     BUILD_TUPLE                     1
        186     CALL_FUNCTION_EX                0
        188     POP_TOP                         
        190     RETURN_VALUE                    
    [Exception Table]
        26 to 130 -> 150 [0] 
        150 to 172 -> 172 [1] lasti
