#decoded by lolz.live/mrpenny / t.me/zeus_jackpot
# ================================
# Примечания по Pyarmor:
# - Байт-код и объекты кода Pyarmor соответствуют стандартному Python, но присутствуют специальные вызовы функций среды выполнения (runtime) Pyarmor.
# - Вызовы строк — это не ошибки, а маркеры, которые обрабатываются Pyarmor во время выполнения.
#
# Руководство по декомпиляции (без среды выполнения):
# 1. Игнорируйте зашифрованные байты после `#`; используйте только строку до `#`.
# 2. Удалите "__pyarmor_enter_xxx__"(b"<COAddr>...") и "__pyarmor_leave_xxx__"(b"<COAddr>...") (пролог/эпилог).
# 3. "__pyarmor_assert_xxx__"(A) не является настоящим оператором assert.
#    - Если A — это имя или читаемая строка: замените на A.
#    - Если A — это (X, "Y"): замените на X.Y.
#    - Если A — это (X, "Y", Z): замените на X.Y = Z.
#    - В противном случае: выберите наиболее подходящую/логичную замену.
# 4. "__pyarmor_bcc_xxx__"(...) указывает на машинный (нативный) код; тело функции недоступно. Добавьте комментарий.
# ================================

[Code]
    File Name: <frozen program.modules.account_booster>
    Object Name: <module>
    Qualified Name: <module>
    Arg Count: 0
    Pos Only Arg Count: 0
    KW Only Arg Count: 0
    Stack Size: 5
    Flags: 0x20000000 (CO_PYARMOR_OBFUSCATED)
    [Names]
        '__assert_armored__'
        'os'
        'eel'
        'json'
        'random'
        'concurrent.futures'
        'concurrent'
        'threading'
        'Thread'
        'Event'
        'multithon.sync'
        'functions'
        'errors'
        'multithon.errors'
        'StopProgram'
        'program.static_classes'
        'AutoStop'
        'GetLang'
        'Logs'
        'check_module'
        'logging'
        'memory_check_switcher'
        'memory_set_pid'
        'program.telegram'
        'DelayOnline'
        'Disconnect'
        'Restart_wait'
        'Thread_wait'
        'account_works'
        'get_account_json'
        'program.general'
        'GetConfig'
        'GetFileTXT'
        'GetProxy'
        'StopDetect'
        'check_get_settings'
        'del_task_manager'
        'getFile'
        'set_task_manager'
        'account_booster'
        'START'
        'json_get_usernames'
        'bool'
        'list'
        'get_random_array_file'
        'str'
        'get_smile'
        'int'
        'mark_mess_read'
        'get_username_hash'
        'tg_send_message'
        'Booster'
    [Locals+Names]
    [Constants]
        '__pyarmor_assert_12885__'
        '__pyarmor_enter_12886__'
        b'<COAddr>\x05\x00\x00\x1a\xc4\x01\x00\x00\x00\x00\x00\x00\x00\x00\x00\x00\x00\x00\x00\x00'
        0
        None
        (
            'Thread'
            'Event'
        )
        (
            'functions'
            'errors'
        )
        (
            'StopProgram'
        )
        (
            'AutoStop'
        )
        (
            'GetLang'
        )
        (
            'Logs'
        )
        (
            'check_module'
        )
        (
            'logging'
        )
        (
            'memory_check_switcher'
        )
        (
            'memory_set_pid'
        )
        (
            'DelayOnline'
        )
        (
            'Disconnect'
        )
        (
            'Restart_wait'
        )
        (
            'Thread_wait'
        )
        (
            'account_works'
        )
        (
            'get_account_json'
        )
        (
            'GetConfig'
        )
        (
            'GetFileTXT'
        )
        (
            'GetProxy'
        )
        (
            'StopDetect'
        )
        (
            'check_get_settings'
        )
        (
            'del_task_manager'
        )
        (
            'getFile'
        )
        (
            'set_task_manager'
        )
        [Code]
            File Name: <frozen program.modules.account_booster>
            Object Name: getFile
            Qualified Name: getFile
            Arg Count: 1
            Pos Only Arg Count: 0
            KW Only Arg Count: 0
            Stack Size: 5
            Flags: 0x20000003 (CO_OPTIMIZED | CO_NEWLOCALS | CO_PYARMOR_OBFUSCATED)
            [Names]
                'GetFileTXT'
                'eel'
                'LoadFilePathes'
            [Locals+Names]
                'data'
                '__assert_armored__'
                '_var_var_0'
            [Constants]
                None
                '__pyarmor_assert_12888__'
                '__pyarmor_enter_12889__'
                b'<COAddr>\x05\x00\x00\x1an\x00\x00\x00\x00\x00\x00\x00\x00\x00\x00\x00\x00\x00\x00\x00'
                ''
                0
                'filename'
                '__pyarmor_exit_12890__'
            [Disassembly]
                0       NOP                             
                2       NOP                             
                4       PUSH_NULL                       
                6       LOAD_CONST                      2: '__pyarmor_enter_12889__'
                8       LOAD_CONST                      3: b'<COAddr>\x05\x00\x00\x1an\x00\x00\x00\x00\x00\x00\x00\x00\x00\x00\x00\x00\x00\x00\x00'
                10      BUILD_TUPLE                     1
                12      CALL_FUNCTION_EX                0
                14      POP_TOP                         
                16      RESUME                          0
                18      NOP                             
                20      NOP                             
                22      NOP                             
                24      NOP                             
                26      NOP                             
                28      LOAD_GLOBAL                     1: NULL + GetFileTXT
                38      CALL                            0
                46      STORE_FAST                      2: _var_var_0
                48      LOAD_FAST                       2: _var_var_0
                50      POP_JUMP_IF_NOT_NONE            2 (to 56)
                52      LOAD_CONST                      4: ''
                54      JUMP_FORWARD                    4 (to 64)
                56      LOAD_FAST                       2: _var_var_0
                58      LOAD_CONST                      5: 0
                60      BINARY_SUBSCR                   
                64      STORE_FAST                      2: _var_var_0
                66      LOAD_GLOBAL                     3: NULL + eel
                76      LOAD_ATTR                       4: LoadFilePathes
                96      LOAD_FAST                       0: data
                98      LOAD_CONST                      6: 'filename'
                100     BINARY_SUBSCR                   
                104     LOAD_FAST                       2: _var_var_0
                106     CALL                            2
                114     POP_TOP                         
                116     LOAD_CONST                      0: None
                118     NOP                             
                120     NOP                             
                122     NOP                             
                124     JUMP_FORWARD                    19 (to 164)
                132     POP_TOP                         
                134     RETURN_CONST                    0: None
                136     PUSH_EXC_INFO                   
                138     PUSH_NULL                       
                140     LOAD_CONST                      7: '__pyarmor_exit_12890__'
                142     NOP                             
                144     LOAD_CONST                      3: b'<COAddr>\x05\x00\x00\x1an\x00\x00\x00\x00\x00\x00\x00\x00\x00\x00\x00\x00\x00\x00\x00'
                146     CALL                            1
                154     POP_TOP                         
                156     RERAISE                         0
                158     COPY                            3
                160     POP_EXCEPT                      
                162     RERAISE                         1
                164     PUSH_NULL                       
                166     LOAD_CONST                      7: '__pyarmor_exit_12890__'
                168     LOAD_CONST                      3: b'<COAddr>\x05\x00\x00\x1an\x00\x00\x00\x00\x00\x00\x00\x00\x00\x00\x00\x00\x00\x00\x00'
                170     BUILD_TUPLE                     1
                172     CALL_FUNCTION_EX                0
                174     POP_TOP                         
                176     RETURN_VALUE                    
            [Exception Table]
                28 to 116 -> 136 [0] 
                136 to 158 -> 158 [1] lasti
        [Code]
            File Name: <frozen program.modules.account_booster>
            Object Name: account_booster
            Qualified Name: account_booster
            Arg Count: 1
            Pos Only Arg Count: 0
            KW Only Arg Count: 0
            Stack Size: 8
            Flags: 0x20000003 (CO_OPTIMIZED | CO_NEWLOCALS | CO_PYARMOR_OBFUSCATED)
            [Names]
                'get'
                'getFile'
                'GetConfig'
                'config'
                'GetLang'
                'Lang'
                'GetProxy'
                'eel'
                'sendSuccessBox'
                'memory_check_switcher'
                'check_module'
                'Event'
                'memory_set_pid'
                'Thread'
                'START'
                'start'
                'Logs'
                'WaitStopAnsfer'
                'UpdateLogInWindow'
                'BaseException'
                'logging'
            [Locals+Names]
                'data'
                '__assert_armored__'
                '_var_var_1'
                '_var_var_2'
                '_var_var_3'
                '_var_var_4'
            [Constants]
                None
                '__pyarmor_assert_12891__'
                '__pyarmor_enter_12892__'
                b'<COAddr>\x05\x00\x00\x1a\xda\x02\x00\x00\x00\x00\x00\x00\x00\x00\x00\x00\x00\x00\x00\x00'
                'action'
                'getFile'
                '__pyarmor_exit_12893__'
                'program_running'   # b'\x81\xf2\n\x1c4\xe8\xbf\xdf$\xe8\x18\xceb\xe5\xf6\x82'
                False
                9
                (
                    'target'
                    'args'
                )
                True
                (
                    'target'
                    'args'
                    'daemon'
                )
            [Disassembly]
                0       NOP                             
                2       NOP                             
                4       PUSH_NULL                       
                6       LOAD_CONST                      2: '__pyarmor_enter_12892__'
                8       LOAD_CONST                      3: b'<COAddr>\x05\x00\x00\x1a\xda\x02\x00\x00\x00\x00\x00\x00\x00\x00\x00\x00\x00\x00\x00\x00'
                10      BUILD_TUPLE                     1
                12      CALL_FUNCTION_EX                0
                14      POP_TOP                         
                16      RESUME                          0
                18      NOP                             
                20      NOP                             
                22      NOP                             
                24      NOP                             
                26      NOP                             
                28      NOP                             
                30      LOAD_FAST                       0: data
                32      LOAD_ATTR                       1: get
                52      LOAD_CONST                      4: 'action'
                54      CALL                            1
                62      POP_JUMP_IF_NONE                28 (to 120)
                64      LOAD_FAST                       0: data
                66      LOAD_CONST                      4: 'action'
                68      BINARY_SUBSCR                   
                72      LOAD_CONST                      5: 'getFile'
                74      COMPARE_OP                      40 (==)
                78      POP_JUMP_IF_FALSE               20 (to 120)
                80      LOAD_GLOBAL                     3: NULL + getFile
                90      LOAD_FAST                       0: data
                92      CALL                            1
                100     NOP                             
                102     NOP                             
                104     JUMP_FORWARD                    338 (to 784)
                108     CALL                            1
                116     POP_TOP                         
                118     RETURN_VALUE                    
                120     LOAD_GLOBAL                     5: NULL + GetConfig
                130     CALL                            0
                138     STORE_GLOBAL                    3: config
                140     LOAD_GLOBAL                     9: NULL + GetLang
                150     LOAD_GLOBAL                     6: config
                160     CALL                            1
                168     STORE_GLOBAL                    5: Lang
                170     LOAD_GLOBAL                     13: NULL + GetProxy
                180     CALL                            0
                188     STORE_FAST                      2: _var_var_1
                190     LOAD_GLOBAL                     15: NULL + eel
                200     LOAD_ATTR                       16: sendSuccessBox
                220     LOAD_GLOBAL                     10: Lang
                230     PUSH_NULL                       
                232     LOAD_CONST                      1: '__pyarmor_assert_12891__'
                234     LOAD_CONST                      7: 'program_running'   # b'\x81\xf2\n\x1c4\xe8\xbf\xdf$\xe8\x18\xceb\xe5\xf6\x82'
                236     CALL                            1
                244     BINARY_SUBSCR                   
                248     CALL                            1
                256     POP_TOP                         
                258     LOAD_GLOBAL                     19: NULL + memory_check_switcher
                268     CALL                            0
                276     POP_JUMP_IF_TRUE                11 (to 300)
                278     NOP                             
                280     LOAD_CONST                      8: False
                282     NOP                             
                284     NOP                             
                286     NOP                             
                288     JUMP_FORWARD                    247 (to 784)
                296     POP_TOP                         
                298     RETURN_CONST                    8: False
                300     LOAD_GLOBAL                     21: NULL + check_module
                310     LOAD_CONST                      9: 9
                312     CALL                            1
                320     POP_JUMP_IF_TRUE                11 (to 344)
                322     NOP                             
                324     LOAD_CONST                      8: False
                326     NOP                             
                328     NOP                             
                330     NOP                             
                332     JUMP_FORWARD                    225 (to 784)
                340     POP_TOP                         
                342     RETURN_CONST                    8: False
                344     LOAD_GLOBAL                     23: NULL + Event
                354     CALL                            0
                362     STORE_FAST                      3: _var_var_2
                364     LOAD_GLOBAL                     25: NULL + memory_set_pid
                374     CALL                            0
                382     STORE_FAST                      4: _var_var_3
                384     LOAD_GLOBAL                     27: NULL + Thread
                394     LOAD_GLOBAL                     28: START
                404     LOAD_FAST                       0: data
                406     LOAD_GLOBAL                     6: config
                416     LOAD_FAST                       4: _var_var_3
                418     LOAD_FAST                       2: _var_var_1
                420     LOAD_FAST                       3: _var_var_2
                422     BUILD_TUPLE                     5
                424     KW_NAMES                        10: ('target', 'args')
                426     CALL                            2
                434     LOAD_ATTR                       31: start
                454     CALL                            0
                462     POP_TOP                         
                464     LOAD_GLOBAL                     27: NULL + Thread
                474     LOAD_GLOBAL                     32: Logs
                484     LOAD_ATTR                       34: WaitStopAnsfer
                504     LOAD_GLOBAL                     6: config
                514     LOAD_FAST                       4: _var_var_3
                516     LOAD_FAST                       3: _var_var_2
                518     BUILD_TUPLE                     3
                520     LOAD_CONST                      11: True
                522     KW_NAMES                        12: ('target', 'args', 'daemon')
                524     CALL                            3
                532     LOAD_ATTR                       31: start
                552     CALL                            0
                560     POP_TOP                         
                562     LOAD_GLOBAL                     27: NULL + Thread
                572     LOAD_GLOBAL                     32: Logs
                582     LOAD_ATTR                       36: UpdateLogInWindow
                602     LOAD_GLOBAL                     6: config
                612     LOAD_FAST                       4: _var_var_3
                614     LOAD_FAST                       3: _var_var_2
                616     BUILD_TUPLE                     3
                618     LOAD_CONST                      11: True
                620     KW_NAMES                        12: ('target', 'args', 'daemon')
                622     CALL                            3
                630     LOAD_ATTR                       31: start
                650     CALL                            0
                658     POP_TOP                         
                660     LOAD_CONST                      0: None
                662     NOP                             
                664     NOP                             
                666     NOP                             
                668     JUMP_FORWARD                    57 (to 784)
                676     POP_TOP                         
                678     RETURN_CONST                    0: None
                680     PUSH_EXC_INFO                   
                682     LOAD_GLOBAL                     38: BaseException
                692     CHECK_EXC_MATCH                 
                694     POP_JUMP_IF_FALSE               26 (to 748)
                696     STORE_FAST                      5: _var_var_4
                698     PUSH_NULL                       
                700     LOAD_GLOBAL                     41: NULL + logging
                710     LOAD_FAST                       5: _var_var_4
                712     CALL                            1
                720     CALL                            0
                728     POP_TOP                         
                730     POP_EXCEPT                      
                732     LOAD_CONST                      0: None
                734     STORE_FAST                      5: _var_var_4
                736     DELETE_FAST                     5: _var_var_4
                738     JUMP_BACKWARD                   40 (to 660)
                740     LOAD_CONST                      0: None
                742     STORE_FAST                      5: _var_var_4
                744     DELETE_FAST                     5: _var_var_4
                746     RERAISE                         1
                748     RERAISE                         0
                750     COPY                            3
                752     POP_EXCEPT                      
                754     RERAISE                         1
                756     PUSH_EXC_INFO                   
                758     PUSH_NULL                       
                760     LOAD_CONST                      6: '__pyarmor_exit_12893__'
                762     NOP                             
                764     LOAD_CONST                      3: b'<COAddr>\x05\x00\x00\x1a\xda\x02\x00\x00\x00\x00\x00\x00\x00\x00\x00\x00\x00\x00\x00\x00'
                766     CALL                            1
                774     POP_TOP                         
                776     RERAISE                         0
                778     COPY                            3
                780     POP_EXCEPT                      
                782     RERAISE                         1
                784     PUSH_NULL                       
                786     LOAD_CONST                      6: '__pyarmor_exit_12893__'
                788     LOAD_CONST                      3: b'<COAddr>\x05\x00\x00\x1a\xda\x02\x00\x00\x00\x00\x00\x00\x00\x00\x00\x00\x00\x00\x00\x00'
                790     BUILD_TUPLE                     1
                792     CALL_FUNCTION_EX                0
                794     POP_TOP                         
                796     RETURN_VALUE                    
            [Exception Table]
                30 to 100 -> 680 [0] 
                120 to 278 -> 680 [0] 
                300 to 322 -> 680 [0] 
                344 to 660 -> 680 [0] 
                680 to 698 -> 750 [1] lasti
                698 to 730 -> 740 [1] lasti
                730 to 740 -> 756 [0] 
                740 to 750 -> 750 [1] lasti
                750 to 756 -> 756 [0] 
                756 to 778 -> 778 [1] lasti
        [Code]
            File Name: <frozen program.modules.account_booster>
            Object Name: START
            Qualified Name: START
            Arg Count: 5
            Pos Only Arg Count: 0
            KW Only Arg Count: 0
            Stack Size: 15
            Flags: 0x20000003 (CO_OPTIMIZED | CO_NEWLOCALS | CO_PYARMOR_OBFUSCATED)
            [Names]
                'is_set'
                'StopProgram'
                'check_get_settings'
                'get'
                'os'
                'listdir'
                'path'
                'exists'
                'replace'
                'append'
                'isinstance'
                'list'
                'int'
                'len'
                'eel'
                'sendErrorBox'
                'Lang'
                'Logs'
                'LangCheck'
                'json_get_usernames'
                'get_random_array_file'
                'PrintLog'
                'set_task_manager'
                'concurrent'
                'futures'
                'ThreadPoolExecutor'
                'StreamStat'
                'json'
                'dumps'
                'submit'
                'Booster'
                'as_completed'
                'result'
                'AutoStop'
                'start'
                'Restart_wait'
                'BaseException'
                'logging'
                'del_task_manager'
                'StopDetect'
            [Locals+Names]
                'data'
                'config'
                'pid'
                'proxy'
                'stop_thread'
                '__assert_armored__'
                '_var_var_5'
                '_var_var_6'
                '_var_var_7'
                '_var_var_8'
                '_var_var_9'
                '_var_var_10'
                '_var_var_11'
                '_var_var_12'
                '_var_var_13'
                '_var_var_14'
                '_var_var_15'
                '_var_var_16'
                '_var_var_17'
                '_var_var_18'
                '_var_var_19'
                '_var_var_20'
                '_var_var_21'
                '_var_var_22'
                '_var_var_23'
                '_var_var_24'
                '_var_var_25'
                '_var_var_26'
                '_var_var_27'
                '_var_var_28'
                '_var_var_29'
                '_var_var_4'
            [Constants]
                None
                '__pyarmor_assert_12894__'
                '__pyarmor_enter_12895__'
                b'<COAddr>\x07\x00\x00\x1a\xfc\x0c\x00\x00\x00\x00\x00\x00\x00\x00\x00\x00\x00\x00\x00\x00'
                'Settings'
                'all_accounts'   # b'\x81\xe3\x14\x1f\x0c\xfb\xbd\xd1\x14\xef\x03\xd4\x7f'
                'sessions/active'   # b'\x81\xf1\x1d\x00 \xf3\xb1\xdc\x08\xb5\x0c\xc3x\xe5\xee\x80'
                '.json'
                'sessions/active//'   # b'\x81\xf1\x1d\x00 \xf3\xb1\xdc\x08\xb5\x0c\xc3x\xe5\xee\x80@\x12'
                '.session'
                True
                ''
                'Accounts'
                1
                'select_accounts_works'   # b'\x81\xf1\x1d\x1f6\xf9\xaa\xed\x1a\xf9\x0e\xcfy\xe2\xec\x960J\xb4\xb5\xa1\xd8'
                'select_more_accounts'   # b'\x81\xf1\x1d\x1f6\xf9\xaa\xed\x16\xf5\x1f\xc5S\xed\xfb\x86\x00H\xb5\xb3\xb9'
                'autostop_rules'   # b'\x81\xe3\r\x07<\xe9\xaa\xdd\x0b\xc5\x1f\xd5`\xe9\xeb'
                'autostop_ban'   # b'\x81\xe3\r\x07<\xe9\xaa\xdd\x0b\xc5\x0f\xc1b'
                'autostop_spamblock'   # b'\x81\xe3\r\x07<\xe9\xaa\xdd\x0b\xc5\x1e\xd0m\xe1\xfa\x89\x00^\xb0'
                'autostop_flood'   # b'\x81\xe3\r\x07<\xe9\xaa\xdd\x0b\xc5\x0b\xccc\xe3\xfc'
                'autostop_sequential'   # b'\x81\xe3\r\x07<\xe9\xaa\xdd\x0b\xc5\x1e\xc5}\xf9\xfd\x8b\x1bT\xba\xab'
                'thread_rules'   # b'\x81\xf6\x10\x016\xfb\xba\xed\t\xef\x01\xc5\x7f'
                'thread_count'   # b'\x81\xf6\x10\x016\xfb\xba\xed\x18\xf5\x18\xcex'
                'start_rules'   # b'\x81\xf1\x0c\x12!\xee\x81\xc0\x0e\xf6\x08\xd3'
                'start_count'   # b'\x81\xf1\x0c\x12!\xee\x81\xd1\x14\xef\x03\xd4'
                False
                'booster_need_username'   # b'\x81\xe0\x17\x1c \xee\xbb\xc0$\xf4\x08\xc5h\xd3\xed\x96\nO\xb5\xa6\xa7\xce'
                'file_txt'
                'booster_need_more_strings'   # b'\x81\xe0\x17\x1c \xee\xbb\xc0$\xf4\x08\xc5h\xd3\xf5\x8a\x1dX\x84\xb4\xbe\xd9G\xc2\x02|'
                'option_01'   # b'\x81\xed\x08\x07:\xf5\xb0\xedK\xab'
                'option_02'   # b'\x81\xed\x08\x07:\xf5\xb0\xedK\xa8'
                2
                'option_03'   # b'\x81\xed\x08\x07:\xf5\xb0\xedK\xa9'
                3
                'booster_more_mess'   # b'\x81\xe0\x17\x1c \xee\xbb\xc0$\xf7\x02\xd2i\xd3\xf5\x80\x1cN'
                (
                    'message'
                )
                0
                'stuff'
                (
                    'accounts'
                    'name'
                )
                'launch_no'   # b'\x81\xee\x19\x06=\xf9\xb6\xed\x15\xf5'
                (
                    'message'
                    'param'
                )
                (
                    'max_workers'
                )
                'st_task'
                'st_stream'   # b'\x81\xf1\x0c, \xee\xac\xd7\x1a\xf7'
                'st_wait'
                'st_done'
                'Launch N'
                'completed'   # b'\x81\xe1\x17\x1e#\xf6\xbb\xc6\x1e\xfe'
                (
                    'message'
                    'param'
                    'end'
                )
                'booster_sending_done_switch_mode'   # b'\x81\xe0\x17\x1c \xee\xbb\xc0$\xe9\x08\xceh\xe5\xf6\x820Y\xb4\xa9\xaf\xf4]\xdb\x0c{\xa0T?\xbc\x11\xe1?'
                'delay_between_launches_activated'   # b'\x81\xe6\x1d\x1f2\xe3\x81\xd0\x1e\xee\x1a\xc5i\xe2\xc7\x89\x0eH\xb5\xa4\xa2\xce]\xf3\x04l\xb7U\x16\xb0\n\xe0>'
                '__pyarmor_exit_12896__'
                'Done'
            [Disassembly]
                0       NOP                             
                2       NOP                             
                4       PUSH_NULL                       
                6       LOAD_CONST                      2: '__pyarmor_enter_12895__'
                8       LOAD_CONST                      3: b'<COAddr>\x07\x00\x00\x1a\xfc\x0c\x00\x00\x00\x00\x00\x00\x00\x00\x00\x00\x00\x00\x00\x00'
                10      BUILD_TUPLE                     1
                12      CALL_FUNCTION_EX                0
                14      POP_TOP                         
                16      RESUME                          0
                18      NOP                             
                20      NOP                             
                22      NOP                             
                24      NOP                             
                26      NOP                             
                28      NOP                             
                30      LOAD_FAST                       4: stop_thread
                32      LOAD_ATTR                       1: is_set
                52      CALL                            0
                60      POP_JUMP_IF_FALSE               10 (to 82)
                62      LOAD_GLOBAL                     3: NULL + StopProgram
                72      CALL                            0
                80      RAISE_VARARGS                   1
                82      LOAD_GLOBAL                     5: NULL + check_get_settings
                92      LOAD_FAST                       0: data
                94      LOAD_ATTR                       7: get
                114     LOAD_CONST                      4: 'Settings'
                116     CALL                            1
                124     CALL                            1
                132     POP_TOP                         
                134     LOAD_FAST                       0: data
                136     LOAD_CONST                      4: 'Settings'
                138     BINARY_SUBSCR                   
                142     LOAD_ATTR                       7: get
                162     PUSH_NULL                       
                164     LOAD_CONST                      1: '__pyarmor_assert_12894__'
                166     LOAD_CONST                      5: 'all_accounts'   # b'\x81\xe3\x14\x1f\x0c\xfb\xbd\xd1\x14\xef\x03\xd4\x7f'
                168     CALL                            1
                176     CALL                            1
                184     POP_JUMP_IF_FALSE               133 (to 452)
                186     BUILD_LIST                      0
                188     STORE_FAST                      6: _var_var_5
                190     LOAD_GLOBAL                     9: NULL + os
                200     LOAD_ATTR                       10: listdir
                220     PUSH_NULL                       
                222     LOAD_CONST                      1: '__pyarmor_assert_12894__'
                224     LOAD_CONST                      6: 'sessions/active'   # b'\x81\xf1\x1d\x00 \xf3\xb1\xdc\x08\xb5\x0c\xc3x\xe5\xee\x80'
                226     CALL                            1
                234     CALL                            1
                242     GET_ITER                        
                244     FOR_ITER                        100 (to 446)
                248     STORE_FAST                      7: _var_var_6
                250     LOAD_CONST                      7: '.json'
                252     LOAD_FAST                       7: _var_var_6
                254     CONTAINS_OP                     0 (in)
                256     POP_JUMP_IF_TRUE                1 (to 260)
                258     JUMP_BACKWARD                   8 (to 244)
                260     LOAD_GLOBAL                     8: os
                270     LOAD_ATTR                       12: path
                290     LOAD_ATTR                       15: exists
                310     PUSH_NULL                       
                312     LOAD_CONST                      1: '__pyarmor_assert_12894__'
                314     LOAD_CONST                      8: 'sessions/active//'   # b'\x81\xf1\x1d\x00 \xf3\xb1\xdc\x08\xb5\x0c\xc3x\xe5\xee\x80@\x12'
                316     CALL                            1
                324     LOAD_FAST                       7: _var_var_6
                326     LOAD_ATTR                       17: replace
                346     LOAD_CONST                      7: '.json'
                348     LOAD_CONST                      9: '.session'
                350     CALL                            2
                358     FORMAT_VALUE                    0 (FVC_NONE)
                360     BUILD_STRING                    2
                362     CALL                            1
                370     LOAD_CONST                      10: True
                372     COMPARE_OP                      40 (==)
                376     POP_JUMP_IF_TRUE                1 (to 380)
                378     JUMP_BACKWARD                   68 (to 244)
                380     LOAD_FAST                       6: _var_var_5
                382     LOAD_ATTR                       19: append
                402     LOAD_FAST                       7: _var_var_6
                404     LOAD_ATTR                       17: replace
                424     LOAD_CONST                      7: '.json'
                426     LOAD_CONST                      11: ''
                428     CALL                            2
                436     CALL                            1
                444     POP_TOP                         
                446     JUMP_BACKWARD                   102 (to 244)
                448     END_FOR                         
                450     JUMP_FORWARD                    158 (to 768)
                452     LOAD_FAST                       0: data
                454     LOAD_CONST                      12: 'Accounts'
                456     BINARY_SUBSCR                   
                460     STORE_FAST                      6: _var_var_5
                462     LOAD_GLOBAL                     21: NULL + isinstance
                472     LOAD_FAST                       6: _var_var_5
                474     LOAD_GLOBAL                     22: list
                484     CALL                            2
                492     POP_JUMP_IF_TRUE                3 (to 500)
                494     LOAD_FAST                       6: _var_var_5
                496     BUILD_LIST                      1
                498     STORE_FAST                      6: _var_var_5
                500     LOAD_GLOBAL                     25: NULL + int
                510     LOAD_GLOBAL                     27: NULL + len
                520     LOAD_FAST                       6: _var_var_5
                522     CALL                            1
                530     CALL                            1
                538     LOAD_CONST                      13: 1
                540     COMPARE_OP                      2 (<)
                544     POP_JUMP_IF_FALSE               44 (to 634)
                546     LOAD_GLOBAL                     29: NULL + eel
                556     LOAD_ATTR                       30: sendErrorBox
                576     LOAD_GLOBAL                     32: Lang
                586     PUSH_NULL                       
                588     LOAD_CONST                      1: '__pyarmor_assert_12894__'
                590     LOAD_CONST                      14: 'select_accounts_works'   # b'\x81\xf1\x1d\x1f6\xf9\xaa\xed\x1a\xf9\x0e\xcfy\xe2\xec\x960J\xb4\xb5\xa1\xd8'
                592     CALL                            1
                600     BINARY_SUBSCR                   
                604     CALL                            1
                612     POP_TOP                         
                614     LOAD_GLOBAL                     3: NULL + StopProgram
                624     CALL                            0
                632     RAISE_VARARGS                   1
                634     LOAD_GLOBAL                     25: NULL + int
                644     LOAD_GLOBAL                     27: NULL + len
                654     LOAD_FAST                       6: _var_var_5
                656     CALL                            1
                664     CALL                            1
                672     LOAD_CONST                      13: 1
                674     COMPARE_OP                      40 (==)
                678     POP_JUMP_IF_FALSE               44 (to 768)
                680     LOAD_GLOBAL                     29: NULL + eel
                690     LOAD_ATTR                       30: sendErrorBox
                710     LOAD_GLOBAL                     32: Lang
                720     PUSH_NULL                       
                722     LOAD_CONST                      1: '__pyarmor_assert_12894__'
                724     LOAD_CONST                      15: 'select_more_accounts'   # b'\x81\xf1\x1d\x1f6\xf9\xaa\xed\x16\xf5\x1f\xc5S\xed\xfb\x86\x00H\xb5\xb3\xb9'
                726     CALL                            1
                734     BINARY_SUBSCR                   
                738     CALL                            1
                746     POP_TOP                         
                748     LOAD_GLOBAL                     3: NULL + StopProgram
                758     CALL                            0
                766     RAISE_VARARGS                   1
                768     LOAD_FAST                       0: data
                770     LOAD_CONST                      4: 'Settings'
                772     BINARY_SUBSCR                   
                776     LOAD_ATTR                       7: get
                796     PUSH_NULL                       
                798     LOAD_CONST                      1: '__pyarmor_assert_12894__'
                800     LOAD_CONST                      16: 'autostop_rules'   # b'\x81\xe3\r\x07<\xe9\xaa\xdd\x0b\xc5\x1f\xd5`\xe9\xeb'
                802     CALL                            1
                810     CALL                            1
                818     STORE_FAST                      8: _var_var_7
                820     LOAD_GLOBAL                     25: NULL + int
                830     LOAD_FAST                       0: data
                832     LOAD_CONST                      4: 'Settings'
                834     BINARY_SUBSCR                   
                838     LOAD_ATTR                       7: get
                858     PUSH_NULL                       
                860     LOAD_CONST                      1: '__pyarmor_assert_12894__'
                862     LOAD_CONST                      17: 'autostop_ban'   # b'\x81\xe3\r\x07<\xe9\xaa\xdd\x0b\xc5\x0f\xc1b'
                864     CALL                            1
                872     CALL                            1
                880     CALL                            1
                888     STORE_FAST                      9: _var_var_8
                890     LOAD_GLOBAL                     25: NULL + int
                900     LOAD_FAST                       0: data
                902     LOAD_CONST                      4: 'Settings'
                904     BINARY_SUBSCR                   
                908     LOAD_ATTR                       7: get
                928     PUSH_NULL                       
                930     LOAD_CONST                      1: '__pyarmor_assert_12894__'
                932     LOAD_CONST                      18: 'autostop_spamblock'   # b'\x81\xe3\r\x07<\xe9\xaa\xdd\x0b\xc5\x1e\xd0m\xe1\xfa\x89\x00^\xb0'
                934     CALL                            1
                942     CALL                            1
                950     CALL                            1
                958     STORE_FAST                      10: _var_var_9
                960     LOAD_GLOBAL                     25: NULL + int
                970     LOAD_FAST                       0: data
                972     LOAD_CONST                      4: 'Settings'
                974     BINARY_SUBSCR                   
                978     LOAD_ATTR                       7: get
                998     PUSH_NULL                       
                1000    LOAD_CONST                      1: '__pyarmor_assert_12894__'
                1002    LOAD_CONST                      19: 'autostop_flood'   # b'\x81\xe3\r\x07<\xe9\xaa\xdd\x0b\xc5\x0b\xccc\xe3\xfc'
                1004    CALL                            1
                1012    CALL                            1
                1020    CALL                            1
                1028    STORE_FAST                      11: _var_var_10
                1030    LOAD_FAST                       0: data
                1032    LOAD_CONST                      4: 'Settings'
                1034    BINARY_SUBSCR                   
                1038    LOAD_ATTR                       7: get
                1058    PUSH_NULL                       
                1060    LOAD_CONST                      1: '__pyarmor_assert_12894__'
                1062    LOAD_CONST                      20: 'autostop_sequential'   # b'\x81\xe3\r\x07<\xe9\xaa\xdd\x0b\xc5\x1e\xc5}\xf9\xfd\x8b\x1bT\xba\xab'
                1064    CALL                            1
                1072    CALL                            1
                1080    STORE_FAST                      12: _var_var_11
                1082    LOAD_FAST                       0: data
                1084    LOAD_CONST                      4: 'Settings'
                1086    BINARY_SUBSCR                   
                1090    LOAD_ATTR                       7: get
                1110    PUSH_NULL                       
                1112    LOAD_CONST                      1: '__pyarmor_assert_12894__'
                1114    LOAD_CONST                      21: 'thread_rules'   # b'\x81\xf6\x10\x016\xfb\xba\xed\t\xef\x01\xc5\x7f'
                1116    CALL                            1
                1124    CALL                            1
                1132    LOAD_CONST                      10: True
                1134    COMPARE_OP                      40 (==)
                1138    POP_JUMP_IF_FALSE               36 (to 1212)
                1140    LOAD_GLOBAL                     25: NULL + int
                1150    LOAD_FAST                       0: data
                1152    LOAD_CONST                      4: 'Settings'
                1154    BINARY_SUBSCR                   
                1158    LOAD_ATTR                       7: get
                1178    PUSH_NULL                       
                1180    LOAD_CONST                      1: '__pyarmor_assert_12894__'
                1182    LOAD_CONST                      22: 'thread_count'   # b'\x81\xf6\x10\x016\xfb\xba\xed\x18\xf5\x18\xcex'
                1184    CALL                            1
                1192    CALL                            1
                1200    CALL                            1
                1208    STORE_FAST                      13: _var_var_12
                1210    JUMP_FORWARD                    11 (to 1234)
                1212    LOAD_FAST                       1: config
                1214    PUSH_NULL                       
                1216    LOAD_CONST                      1: '__pyarmor_assert_12894__'
                1218    LOAD_CONST                      22: 'thread_count'   # b'\x81\xf6\x10\x016\xfb\xba\xed\x18\xf5\x18\xcex'
                1220    CALL                            1
                1228    BINARY_SUBSCR                   
                1232    STORE_FAST                      13: _var_var_12
                1234    LOAD_FAST                       0: data
                1236    LOAD_CONST                      4: 'Settings'
                1238    BINARY_SUBSCR                   
                1242    LOAD_ATTR                       7: get
                1262    PUSH_NULL                       
                1264    LOAD_CONST                      1: '__pyarmor_assert_12894__'
                1266    LOAD_CONST                      23: 'start_rules'   # b'\x81\xf1\x0c\x12!\xee\x81\xc0\x0e\xf6\x08\xd3'
                1268    CALL                            1
                1276    CALL                            1
                1284    STORE_FAST                      14: _var_var_13
                1286    LOAD_FAST                       14: _var_var_13
                1288    LOAD_CONST                      10: True
                1290    COMPARE_OP                      40 (==)
                1294    POP_JUMP_IF_FALSE               36 (to 1368)
                1296    LOAD_GLOBAL                     25: NULL + int
                1306    LOAD_FAST                       0: data
                1308    LOAD_CONST                      4: 'Settings'
                1310    BINARY_SUBSCR                   
                1314    LOAD_ATTR                       7: get
                1334    PUSH_NULL                       
                1336    LOAD_CONST                      1: '__pyarmor_assert_12894__'
                1338    LOAD_CONST                      24: 'start_count'   # b'\x81\xf1\x0c\x12!\xee\x81\xd1\x14\xef\x03\xd4'
                1340    CALL                            1
                1348    CALL                            1
                1356    CALL                            1
                1364    STORE_FAST                      15: _var_var_14
                1366    JUMP_FORWARD                    2 (to 1372)
                1368    LOAD_CONST                      13: 1
                1370    STORE_FAST                      15: _var_var_14
                1372    LOAD_GLOBAL                     35: NULL + Logs
                1382    LOAD_ATTR                       36: LangCheck
                1402    CALL                            0
                1410    POP_TOP                         
                1412    LOAD_GLOBAL                     39: NULL + json_get_usernames
                1422    LOAD_FAST                       6: _var_var_5
                1424    CALL                            1
                1432    STORE_FAST                      16: _var_var_15
                1434    LOAD_FAST                       16: _var_var_15
                1436    LOAD_CONST                      25: False
                1438    COMPARE_OP                      40 (==)
                1442    POP_JUMP_IF_FALSE               44 (to 1532)
                1444    LOAD_GLOBAL                     29: NULL + eel
                1454    LOAD_ATTR                       30: sendErrorBox
                1474    LOAD_GLOBAL                     32: Lang
                1484    PUSH_NULL                       
                1486    LOAD_CONST                      1: '__pyarmor_assert_12894__'
                1488    LOAD_CONST                      26: 'booster_need_username'   # b'\x81\xe0\x17\x1c \xee\xbb\xc0$\xf4\x08\xc5h\xd3\xed\x96\nO\xb5\xa6\xa7\xce'
                1490    CALL                            1
                1498    BINARY_SUBSCR                   
                1502    CALL                            1
                1510    POP_TOP                         
                1512    LOAD_GLOBAL                     3: NULL + StopProgram
                1522    CALL                            0
                1530    RAISE_VARARGS                   1
                1532    LOAD_FAST                       0: data
                1534    LOAD_CONST                      4: 'Settings'
                1536    BINARY_SUBSCR                   
                1540    LOAD_ATTR                       7: get
                1560    LOAD_CONST                      27: 'file_txt'
                1562    LOAD_CONST                      25: False
                1564    CALL                            2
                1572    STORE_FAST                      17: _var_var_16
                1574    LOAD_GLOBAL                     41: NULL + get_random_array_file
                1584    LOAD_FAST                       17: _var_var_16
                1586    CALL                            1
                1594    STORE_FAST                      18: _var_var_17
                1596    LOAD_FAST                       18: _var_var_17
                1598    LOAD_CONST                      25: False
                1600    COMPARE_OP                      40 (==)
                1604    POP_JUMP_IF_FALSE               44 (to 1694)
                1606    LOAD_GLOBAL                     29: NULL + eel
                1616    LOAD_ATTR                       30: sendErrorBox
                1636    LOAD_GLOBAL                     32: Lang
                1646    PUSH_NULL                       
                1648    LOAD_CONST                      1: '__pyarmor_assert_12894__'
                1650    LOAD_CONST                      28: 'booster_need_more_strings'   # b'\x81\xe0\x17\x1c \xee\xbb\xc0$\xf4\x08\xc5h\xd3\xf5\x8a\x1dX\x84\xb4\xbe\xd9G\xc2\x02|'
                1652    CALL                            1
                1660    BINARY_SUBSCR                   
                1664    CALL                            1
                1672    POP_TOP                         
                1674    LOAD_GLOBAL                     3: NULL + StopProgram
                1684    CALL                            0
                1692    RAISE_VARARGS                   1
                1694    LOAD_FAST                       0: data
                1696    LOAD_CONST                      4: 'Settings'
                1698    BINARY_SUBSCR                   
                1702    LOAD_ATTR                       7: get
                1722    PUSH_NULL                       
                1724    LOAD_CONST                      1: '__pyarmor_assert_12894__'
                1726    LOAD_CONST                      29: 'option_01'   # b'\x81\xed\x08\x07:\xf5\xb0\xedK\xab'
                1728    CALL                            1
                1736    LOAD_CONST                      25: False
                1738    CALL                            2
                1746    POP_JUMP_IF_FALSE               3 (to 1754)
                1748    LOAD_CONST                      13: 1
                1750    STORE_FAST                      19: _var_var_18
                1752    JUMP_FORWARD                    62 (to 1878)
                1754    LOAD_FAST                       0: data
                1756    LOAD_CONST                      4: 'Settings'
                1758    BINARY_SUBSCR                   
                1762    LOAD_ATTR                       7: get
                1782    PUSH_NULL                       
                1784    LOAD_CONST                      1: '__pyarmor_assert_12894__'
                1786    LOAD_CONST                      30: 'option_02'   # b'\x81\xed\x08\x07:\xf5\xb0\xedK\xa8'
                1788    CALL                            1
                1796    LOAD_CONST                      25: False
                1798    CALL                            2
                1806    POP_JUMP_IF_FALSE               3 (to 1814)
                1808    LOAD_CONST                      31: 2
                1810    STORE_FAST                      19: _var_var_18
                1812    JUMP_FORWARD                    32 (to 1878)
                1814    LOAD_FAST                       0: data
                1816    LOAD_CONST                      4: 'Settings'
                1818    BINARY_SUBSCR                   
                1822    LOAD_ATTR                       7: get
                1842    PUSH_NULL                       
                1844    LOAD_CONST                      1: '__pyarmor_assert_12894__'
                1846    LOAD_CONST                      32: 'option_03'   # b'\x81\xed\x08\x07:\xf5\xb0\xedK\xa9'
                1848    CALL                            1
                1856    LOAD_CONST                      25: False
                1858    CALL                            2
                1866    POP_JUMP_IF_FALSE               3 (to 1874)
                1868    LOAD_CONST                      33: 3
                1870    STORE_FAST                      19: _var_var_18
                1872    JUMP_FORWARD                    2 (to 1878)
                1874    LOAD_CONST                      33: 3
                1876    STORE_FAST                      19: _var_var_18
                1878    LOAD_FAST                       19: _var_var_18
                1880    LOAD_CONST                      31: 2
                1882    COMPARE_OP                      40 (==)
                1886    POP_JUMP_IF_FALSE               50 (to 1988)
                1888    LOAD_FAST                       15: _var_var_14
                1890    LOAD_CONST                      13: 1
                1892    COMPARE_OP                      40 (==)
                1896    POP_JUMP_IF_FALSE               45 (to 1988)
                1898    LOAD_GLOBAL                     35: NULL + Logs
                1908    LOAD_ATTR                       42: PrintLog
                1928    LOAD_GLOBAL                     32: Lang
                1938    PUSH_NULL                       
                1940    LOAD_CONST                      1: '__pyarmor_assert_12894__'
                1942    LOAD_CONST                      34: 'booster_more_mess'   # b'\x81\xe0\x17\x1c \xee\xbb\xc0$\xf7\x02\xd2i\xd3\xf5\x80\x1cN'
                1944    CALL                            1
                1952    BINARY_SUBSCR                   
                1956    KW_NAMES                        35: ('message',)
                1958    CALL                            1
                1966    POP_TOP                         
                1968    LOAD_GLOBAL                     3: NULL + StopProgram
                1978    CALL                            0
                1986    RAISE_VARARGS                   1
                1988    LOAD_CONST                      36: 0
                1990    STORE_FAST                      20: _var_var_19
                1992    LOAD_GLOBAL                     45: NULL + set_task_manager
                2002    LOAD_FAST                       2: pid
                2004    LOAD_FAST                       6: _var_var_5
                2006    LOAD_FAST                       0: data
                2008    LOAD_CONST                      37: 'stuff'
                2010    BINARY_SUBSCR                   
                2014    KW_NAMES                        38: ('accounts', 'name')
                2016    CALL                            3
                2024    POP_TOP                         
                2026    LOAD_FAST                       20: _var_var_19
                2028    LOAD_FAST                       15: _var_var_14
                2030    COMPARE_OP                      2 (<)
                2034    POP_JUMP_IF_FALSE               525 (to 3088)
                2038    LOAD_FAST                       4: stop_thread
                2040    LOAD_ATTR                       1: is_set
                2060    CALL                            0
                2068    POP_JUMP_IF_FALSE               10 (to 2090)
                2070    LOAD_GLOBAL                     3: NULL + StopProgram
                2080    CALL                            0
                2088    RAISE_VARARGS                   1
                2090    LOAD_FAST                       20: _var_var_19
                2092    LOAD_CONST                      13: 1
                2094    BINARY_OP                       13 (+=)
                2098    STORE_FAST                      20: _var_var_19
                2100    LOAD_FAST                       15: _var_var_14
                2102    LOAD_CONST                      13: 1
                2104    COMPARE_OP                      68 (>)
                2108    POP_JUMP_IF_FALSE               36 (to 2182)
                2110    LOAD_GLOBAL                     35: NULL + Logs
                2120    LOAD_ATTR                       42: PrintLog
                2140    LOAD_GLOBAL                     32: Lang
                2150    PUSH_NULL                       
                2152    LOAD_CONST                      1: '__pyarmor_assert_12894__'
                2154    LOAD_CONST                      39: 'launch_no'   # b'\x81\xee\x19\x06=\xf9\xb6\xed\x15\xf5'
                2156    CALL                            1
                2164    BINARY_SUBSCR                   
                2168    LOAD_FAST                       20: _var_var_19
                2170    KW_NAMES                        40: ('message', 'param')
                2172    CALL                            2
                2180    POP_TOP                         
                2182    LOAD_GLOBAL                     46: concurrent
                2192    LOAD_ATTR                       48: futures
                2212    LOAD_ATTR                       51: ThreadPoolExecutor
                2232    LOAD_FAST                       13: _var_var_12
                2234    KW_NAMES                        41: ('max_workers',)
                2236    CALL                            1
                2244    BEFORE_WITH                     
                2246    STORE_FAST                      21: _var_var_20
                2248    BUILD_LIST                      0
                2250    STORE_FAST                      22: _var_var_21
                2252    LOAD_GLOBAL                     27: NULL + len
                2262    LOAD_FAST                       6: _var_var_5
                2264    CALL                            1
                2272    STORE_FAST                      23: _var_var_22
                2274    LOAD_FAST                       13: _var_var_12
                2276    STORE_FAST                      24: _var_var_23
                2278    LOAD_FAST                       23: _var_var_22
                2280    STORE_FAST                      25: _var_var_24
                2282    LOAD_CONST                      36: 0
                2284    STORE_FAST                      26: _var_var_25
                2286    LOAD_GLOBAL                     29: NULL + eel
                2296    LOAD_ATTR                       52: StreamStat
                2316    LOAD_GLOBAL                     55: NULL + json
                2326    LOAD_ATTR                       56: dumps
                2346    LOAD_CONST                      42: 'st_task'
                2348    LOAD_FAST                       23: _var_var_22
                2350    PUSH_NULL                       
                2352    LOAD_CONST                      1: '__pyarmor_assert_12894__'
                2354    LOAD_CONST                      43: 'st_stream'   # b'\x81\xf1\x0c, \xee\xac\xd7\x1a\xf7'
                2356    CALL                            1
                2364    LOAD_FAST                       24: _var_var_23
                2366    LOAD_CONST                      44: 'st_wait'
                2368    LOAD_FAST                       25: _var_var_24
                2370    LOAD_CONST                      45: 'st_done'
                2372    LOAD_FAST                       26: _var_var_25
                2374    BUILD_MAP                       4
                2376    CALL                            1
                2384    CALL                            1
                2392    POP_TOP                         
                2394    LOAD_FAST                       6: _var_var_5
                2396    GET_ITER                        
                2398    FOR_ITER                        46 (to 2492)
                2402    STORE_FAST                      27: _var_var_26
                2404    LOAD_FAST                       22: _var_var_21
                2406    LOAD_ATTR                       19: append
                2426    LOAD_FAST                       21: _var_var_20
                2428    LOAD_ATTR                       59: submit
                2448    LOAD_GLOBAL                     60: Booster
                2458    LOAD_FAST                       27: _var_var_26
                2460    LOAD_FAST                       1: config
                2462    LOAD_FAST                       3: proxy
                2464    LOAD_FAST                       0: data
                2466    LOAD_FAST                       16: _var_var_15
                2468    LOAD_FAST                       18: _var_var_17
                2470    LOAD_FAST                       19: _var_var_18
                2472    LOAD_FAST                       4: stop_thread
                2474    CALL                            9
                2482    CALL                            1
                2490    POP_TOP                         
                2492    JUMP_BACKWARD                   48 (to 2398)
                2494    END_FOR                         
                2496    BUILD_LIST                      0
                2498    STORE_FAST                      28: _var_var_27
                2500    LOAD_GLOBAL                     46: concurrent
                2510    LOAD_ATTR                       48: futures
                2530    LOAD_ATTR                       63: as_completed
                2550    LOAD_FAST                       22: _var_var_21
                2552    CALL                            1
                2560    GET_ITER                        
                2562    FOR_ITER                        110 (to 2784)
                2566    STORE_FAST                      29: _var_var_28
                2568    LOAD_FAST                       26: _var_var_25
                2570    LOAD_CONST                      13: 1
                2572    BINARY_OP                       13 (+=)
                2576    STORE_FAST                      26: _var_var_25
                2578    LOAD_FAST                       25: _var_var_24
                2580    LOAD_CONST                      13: 1
                2582    BINARY_OP                       23 (-=)
                2586    STORE_FAST                      25: _var_var_24
                2588    LOAD_GLOBAL                     29: NULL + eel
                2598    LOAD_ATTR                       52: StreamStat
                2618    LOAD_GLOBAL                     55: NULL + json
                2628    LOAD_ATTR                       56: dumps
                2648    LOAD_CONST                      42: 'st_task'
                2650    LOAD_FAST                       23: _var_var_22
                2652    PUSH_NULL                       
                2654    LOAD_CONST                      1: '__pyarmor_assert_12894__'
                2656    LOAD_CONST                      43: 'st_stream'   # b'\x81\xf1\x0c, \xee\xac\xd7\x1a\xf7'
                2658    CALL                            1
                2666    LOAD_FAST                       24: _var_var_23
                2668    LOAD_CONST                      44: 'st_wait'
                2670    LOAD_FAST                       25: _var_var_24
                2672    LOAD_CONST                      45: 'st_done'
                2674    LOAD_FAST                       26: _var_var_25
                2676    BUILD_MAP                       4
                2678    CALL                            1
                2686    CALL                            1
                2694    POP_TOP                         
                2696    LOAD_FAST                       29: _var_var_28
                2698    LOAD_ATTR                       65: result
                2718    CALL                            0
                2726    STORE_FAST                      30: _var_var_29
                2728    LOAD_GLOBAL                     67: NULL + AutoStop
                2738    LOAD_FAST                       30: _var_var_29
                2740    LOAD_FAST                       28: _var_var_27
                2742    LOAD_FAST                       0: data
                2744    LOAD_FAST                       4: stop_thread
                2746    CALL                            4
                2754    LOAD_ATTR                       69: start
                2774    CALL                            0
                2782    STORE_FAST                      28: _var_var_27
                2784    JUMP_BACKWARD                   112 (to 2562)
                2786    END_FOR                         
                2788    DELETE_FAST                     22: _var_var_21
                2790    LOAD_CONST                      0: None
                2792    LOAD_CONST                      0: None
                2794    LOAD_CONST                      0: None
                2796    CALL                            2
                2804    POP_TOP                         
                2806    LOAD_FAST                       15: _var_var_14
                2808    LOAD_CONST                      13: 1
                2810    COMPARE_OP                      68 (>)
                2814    POP_JUMP_IF_FALSE               129 (to 3074)
                2816    LOAD_GLOBAL                     35: NULL + Logs
                2826    LOAD_ATTR                       42: PrintLog
                2846    LOAD_CONST                      46: 'Launch N'
                2848    LOAD_FAST                       20: _var_var_19
                2850    PUSH_NULL                       
                2852    LOAD_CONST                      1: '__pyarmor_assert_12894__'
                2854    LOAD_CONST                      47: 'completed'   # b'\x81\xe1\x17\x1e#\xf6\xbb\xc6\x1e\xfe'
                2856    CALL                            1
                2864    KW_NAMES                        48: ('message', 'param', 'end')
                2866    CALL                            3
                2874    POP_TOP                         
                2876    LOAD_FAST                       19: _var_var_18
                2878    LOAD_CONST                      31: 2
                2880    COMPARE_OP                      40 (==)
                2884    POP_JUMP_IF_FALSE               42 (to 2970)
                2886    LOAD_FAST                       20: _var_var_19
                2888    LOAD_CONST                      13: 1
                2890    COMPARE_OP                      40 (==)
                2894    POP_JUMP_IF_FALSE               37 (to 2970)
                2896    LOAD_GLOBAL                     35: NULL + Logs
                2906    LOAD_ATTR                       42: PrintLog
                2926    LOAD_GLOBAL                     32: Lang
                2936    PUSH_NULL                       
                2938    LOAD_CONST                      1: '__pyarmor_assert_12894__'
                2940    LOAD_CONST                      49: 'booster_sending_done_switch_mode'   # b'\x81\xe0\x17\x1c \xee\xbb\xc0$\xe9\x08\xceh\xe5\xf6\x820Y\xb4\xa9\xaf\xf4]\xdb\x0c{\xa0T?\xbc\x11\xe1?'
                2942    CALL                            1
                2950    BINARY_SUBSCR                   
                2954    KW_NAMES                        35: ('message',)
                2956    CALL                            1
                2964    POP_TOP                         
                2966    LOAD_CONST                      33: 3
                2968    STORE_FAST                      19: _var_var_18
                2970    LOAD_FAST                       20: _var_var_19
                2972    LOAD_FAST                       15: _var_var_14
                2974    COMPARE_OP                      55 (!=)
                2978    POP_JUMP_IF_FALSE               47 (to 3074)
                2980    LOAD_GLOBAL                     35: NULL + Logs
                2990    LOAD_ATTR                       42: PrintLog
                3010    LOAD_GLOBAL                     32: Lang
                3020    PUSH_NULL                       
                3022    LOAD_CONST                      1: '__pyarmor_assert_12894__'
                3024    LOAD_CONST                      50: 'delay_between_launches_activated'   # b'\x81\xe6\x1d\x1f2\xe3\x81\xd0\x1e\xee\x1a\xc5i\xe2\xc7\x89\x0eH\xb5\xa4\xa2\xce]\xf3\x04l\xb7U\x16\xb0\n\xe0>'
                3026    CALL                            1
                3034    BINARY_SUBSCR                   
                3038    KW_NAMES                        35: ('message',)
                3040    CALL                            1
                3048    POP_TOP                         
                3050    LOAD_GLOBAL                     71: NULL + Restart_wait
                3060    LOAD_FAST                       0: data
                3062    LOAD_FAST                       4: stop_thread
                3064    CALL                            2
                3072    POP_TOP                         
                3074    LOAD_FAST                       20: _var_var_19
                3076    LOAD_FAST                       15: _var_var_14
                3078    COMPARE_OP                      2 (<)
                3082    POP_JUMP_IF_FALSE               2 (to 3088)
                3084    JUMP_BACKWARD                   525 (to 2038)
                3088    LOAD_GLOBAL                     77: NULL + del_task_manager
                3098    LOAD_FAST                       2: pid
                3100    CALL                            1
                3108    POP_TOP                         
                3110    LOAD_GLOBAL                     79: NULL + StopDetect
                3120    LOAD_FAST                       4: stop_thread
                3122    CALL                            1
                3130    POP_TOP                         
                3132    NOP                             
                3134    LOAD_CONST                      52: 'Done'
                3136    NOP                             
                3138    NOP                             
                3140    NOP                             
                3142    JUMP_FORWARD                    117 (to 3378)
                3150    POP_TOP                         
                3152    RETURN_CONST                    52: 'Done'
                3154    PUSH_EXC_INFO                   
                3156    WITH_EXCEPT_START               
                3158    POP_JUMP_IF_TRUE                1 (to 3162)
                3160    RERAISE                         2
                3162    POP_TOP                         
                3164    POP_EXCEPT                      
                3166    POP_TOP                         
                3168    POP_TOP                         
                3170    JUMP_BACKWARD                   183 (to 2806)
                3172    COPY                            3
                3174    POP_EXCEPT                      
                3176    RERAISE                         1
                3178    PUSH_EXC_INFO                   
                3180    LOAD_GLOBAL                     2: StopProgram
                3190    CHECK_EXC_MATCH                 
                3192    POP_JUMP_IF_FALSE               3 (to 3200)
                3194    POP_TOP                         
                3196    POP_EXCEPT                      
                3198    JUMP_BACKWARD                   56 (to 3088)
                3200    LOAD_GLOBAL                     72: BaseException
                3210    CHECK_EXC_MATCH                 
                3212    POP_JUMP_IF_FALSE               26 (to 3266)
                3214    STORE_FAST                      31: _var_var_4
                3216    PUSH_NULL                       
                3218    LOAD_GLOBAL                     75: NULL + logging
                3228    LOAD_FAST                       31: _var_var_4
                3230    CALL                            1
                3238    CALL                            0
                3246    POP_TOP                         
                3248    POP_EXCEPT                      
                3250    LOAD_CONST                      0: None
                3252    STORE_FAST                      31: _var_var_4
                3254    DELETE_FAST                     31: _var_var_4
                3256    JUMP_BACKWARD                   85 (to 3088)
                3258    LOAD_CONST                      0: None
                3260    STORE_FAST                      31: _var_var_4
                3262    DELETE_FAST                     31: _var_var_4
                3264    RERAISE                         1
                3266    RERAISE                         0
                3268    COPY                            3
                3270    POP_EXCEPT                      
                3272    RERAISE                         1
                3274    PUSH_EXC_INFO                   
                3276    LOAD_GLOBAL                     77: NULL + del_task_manager
                3286    LOAD_FAST                       2: pid
                3288    CALL                            1
                3296    POP_TOP                         
                3298    LOAD_GLOBAL                     79: NULL + StopDetect
                3308    LOAD_FAST                       4: stop_thread
                3310    CALL                            1
                3318    POP_TOP                         
                3320    POP_TOP                         
                3322    POP_EXCEPT                      
                3324    LOAD_CONST                      52: 'Done'
                3326    NOP                             
                3328    NOP                             
                3330    NOP                             
                3332    JUMP_FORWARD                    22 (to 3378)
                3340    POP_TOP                         
                3342    RETURN_CONST                    52: 'Done'
                3344    COPY                            3
                3346    POP_EXCEPT                      
                3348    RERAISE                         1
                3350    PUSH_EXC_INFO                   
                3352    PUSH_NULL                       
                3354    LOAD_CONST                      51: '__pyarmor_exit_12896__'
                3356    NOP                             
                3358    LOAD_CONST                      3: b'<COAddr>\x07\x00\x00\x1a\xfc\x0c\x00\x00\x00\x00\x00\x00\x00\x00\x00\x00\x00\x00\x00\x00'
                3360    CALL                            1
                3368    POP_TOP                         
                3370    RERAISE                         0
                3372    COPY                            3
                3374    POP_EXCEPT                      
                3376    RERAISE                         1
                3378    PUSH_NULL                       
                3380    LOAD_CONST                      51: '__pyarmor_exit_12896__'
                3382    LOAD_CONST                      3: b'<COAddr>\x07\x00\x00\x1a\xfc\x0c\x00\x00\x00\x00\x00\x00\x00\x00\x00\x00\x00\x00\x00\x00'
                3384    BUILD_TUPLE                     1
                3386    CALL_FUNCTION_EX                0
                3388    POP_TOP                         
                3390    RETURN_VALUE                    
            [Exception Table]
                30 to 258 -> 3178 [0] 
                260 to 378 -> 3178 [0] 
                380 to 2246 -> 3178 [0] 
                2246 to 2790 -> 3154 [1] lasti
                2790 to 3084 -> 3178 [0] 
                3088 to 3132 -> 3350 [0] 
                3154 to 3164 -> 3172 [3] lasti
                3164 to 3178 -> 3178 [0] 
                3178 to 3196 -> 3268 [1] lasti
                3196 to 3200 -> 3274 [0] 
                3200 to 3216 -> 3268 [1] lasti
                3216 to 3248 -> 3258 [1] lasti
                3248 to 3258 -> 3274 [0] 
                3258 to 3268 -> 3268 [1] lasti
                3268 to 3274 -> 3274 [0] 
                3274 to 3322 -> 3344 [1] lasti
                3322 to 3324 -> 3350 [0] 
                3344 to 3350 -> 3350 [0] 
                3350 to 3372 -> 3372 [1] lasti
        [Code]
            File Name: <frozen program.modules.account_booster>
            Object Name: json_get_usernames
            Qualified Name: json_get_usernames
            Arg Count: 1
            Pos Only Arg Count: 0
            KW Only Arg Count: 0
            Stack Size: 5
            Flags: 0x20000003 (CO_OPTIMIZED | CO_NEWLOCALS | CO_PYARMOR_OBFUSCATED)
            [Names]
                'get_account_json'
                'append'
            [Locals+Names]
                'accounts'
                '__assert_armored__'
                '_var_var_15'
                '_var_var_26'
                '_var_var_30'
                '_var_var_31'
            [Constants]
                ' Проверяем есть ли в списке аккаунты без юзернейма '
                '__pyarmor_assert_12897__'
                '__pyarmor_enter_12898__'
                b'<COAddr>\x07\x00\x00\x1a\xaa\x00\x00\x00\x00\x00\x00\x00\x00\x00\x00\x00\x00\x00\x00\x00'
                'username'
                'Not set'
                None
                False
                ''
                '__pyarmor_exit_12899__'
            [Disassembly]
                0       NOP                             
                2       NOP                             
                4       PUSH_NULL                       
                6       LOAD_CONST                      2: '__pyarmor_enter_12898__'
                8       LOAD_CONST                      3: b'<COAddr>\x07\x00\x00\x1a\xaa\x00\x00\x00\x00\x00\x00\x00\x00\x00\x00\x00\x00\x00\x00\x00'
                10      BUILD_TUPLE                     1
                12      CALL_FUNCTION_EX                0
                14      POP_TOP                         
                16      RESUME                          0
                18      NOP                             
                20      NOP                             
                22      NOP                             
                24      NOP                             
                26      NOP                             
                28      BUILD_LIST                      0
                30      STORE_FAST                      2: _var_var_15
                32      LOAD_FAST                       0: accounts
                34      GET_ITER                        
                36      FOR_ITER                        66 (to 170)
                40      STORE_FAST                      3: _var_var_26
                42      LOAD_GLOBAL                     1: NULL + get_account_json
                52      LOAD_FAST                       3: _var_var_26
                54      CALL                            1
                62      STORE_FAST                      4: _var_var_30
                64      LOAD_FAST                       4: _var_var_30
                66      LOAD_CONST                      4: 'username'
                68      BINARY_SUBSCR                   
                72      STORE_FAST                      5: _var_var_31
                74      LOAD_FAST                       5: _var_var_31
                76      LOAD_CONST                      5: 'Not set'
                78      COMPARE_OP                      40 (==)
                82      POP_JUMP_IF_TRUE                15 (to 114)
                84      LOAD_FAST                       5: _var_var_31
                86      LOAD_CONST                      6: None
                88      COMPARE_OP                      40 (==)
                92      POP_JUMP_IF_TRUE                10 (to 114)
                94      LOAD_FAST                       5: _var_var_31
                96      LOAD_CONST                      7: False
                98      COMPARE_OP                      40 (==)
                102     POP_JUMP_IF_TRUE                5 (to 114)
                104     LOAD_FAST                       5: _var_var_31
                106     LOAD_CONST                      8: ''
                108     COMPARE_OP                      40 (==)
                112     POP_JUMP_IF_FALSE               11 (to 136)
                114     POP_TOP                         
                116     LOAD_CONST                      7: False
                118     NOP                             
                120     NOP                             
                122     NOP                             
                124     JUMP_FORWARD                    49 (to 224)
                132     POP_TOP                         
                134     RETURN_CONST                    7: False
                136     LOAD_FAST                       2: _var_var_15
                138     LOAD_ATTR                       3: append
                158     LOAD_FAST                       5: _var_var_31
                160     CALL                            1
                168     POP_TOP                         
                170     JUMP_BACKWARD                   68 (to 36)
                172     END_FOR                         
                174     LOAD_FAST                       2: _var_var_15
                176     NOP                             
                178     NOP                             
                180     NOP                             
                182     JUMP_FORWARD                    20 (to 224)
                184     CALL                            1
                192     POP_TOP                         
                194     RETURN_VALUE                    
                196     PUSH_EXC_INFO                   
                198     PUSH_NULL                       
                200     LOAD_CONST                      9: '__pyarmor_exit_12899__'
                202     NOP                             
                204     LOAD_CONST                      3: b'<COAddr>\x07\x00\x00\x1a\xaa\x00\x00\x00\x00\x00\x00\x00\x00\x00\x00\x00\x00\x00\x00\x00'
                206     CALL                            1
                214     POP_TOP                         
                216     RERAISE                         0
                218     COPY                            3
                220     POP_EXCEPT                      
                222     RERAISE                         1
                224     PUSH_NULL                       
                226     LOAD_CONST                      9: '__pyarmor_exit_12899__'
                228     LOAD_CONST                      3: b'<COAddr>\x07\x00\x00\x1a\xaa\x00\x00\x00\x00\x00\x00\x00\x00\x00\x00\x00\x00\x00\x00\x00'
                230     BUILD_TUPLE                     1
                232     CALL_FUNCTION_EX                0
                234     POP_TOP                         
                236     RETURN_VALUE                    
            [Exception Table]
                28 to 116 -> 196 [0] 
                136 to 176 -> 196 [0] 
                196 to 218 -> 218 [1] lasti
        'return'
        [Code]
            File Name: <frozen program.modules.account_booster>
            Object Name: get_random_array_file
            Qualified Name: get_random_array_file
            Arg Count: 1
            Pos Only Arg Count: 0
            KW Only Arg Count: 0
            Stack Size: 5
            Flags: 0x20000003 (CO_OPTIMIZED | CO_NEWLOCALS | CO_PYARMOR_OBFUSCATED)
            [Names]
                'open'
                'readlines'
                'close'
                'random'
                'shuffle'
                'strip'
                'append'
                'len'
            [Locals+Names]
                'path'
                '__assert_armored__'
                '_var_var_32'
                '_var_var_33'
                '_var_var_34'
            [Constants]
                None
                '__pyarmor_assert_12900__'
                '__pyarmor_enter_12901__'
                b'<COAddr>\x07\x00\x00\x1al\x01\x00\x00\x00\x00\x00\x00\x00\x00\x00\x00\x00\x00\x00\x00'
                '__pyarmor_exit_12902__'
                False
                'r'
                'utf-8'
                (
                    'encoding'
                )
                10
            [Disassembly]
                0       NOP                             
                2       NOP                             
                4       PUSH_NULL                       
                6       LOAD_CONST                      2: '__pyarmor_enter_12901__'
                8       LOAD_CONST                      3: b'<COAddr>\x07\x00\x00\x1al\x01\x00\x00\x00\x00\x00\x00\x00\x00\x00\x00\x00\x00\x00\x00'
                10      BUILD_TUPLE                     1
                12      CALL_FUNCTION_EX                0
                14      POP_TOP                         
                16      RESUME                          0
                18      NOP                             
                20      NOP                             
                22      NOP                             
                24      NOP                             
                26      NOP                             
                28      NOP                             
                30      LOAD_FAST                       0: path
                32      POP_JUMP_IF_TRUE                11 (to 56)
                34      NOP                             
                36      LOAD_CONST                      5: False
                38      NOP                             
                40      NOP                             
                42      NOP                             
                44      JUMP_FORWARD                    186 (to 418)
                52      POP_TOP                         
                54      RETURN_CONST                    5: False
                56      LOAD_GLOBAL                     1: NULL + open
                66      LOAD_FAST                       0: path
                68      LOAD_CONST                      6: 'r'
                70      LOAD_CONST                      7: 'utf-8'
                72      KW_NAMES                        8: ('encoding',)
                74      CALL                            3
                82      STORE_FAST                      0: path
                84      LOAD_FAST                       0: path
                86      LOAD_ATTR                       3: readlines
                106     CALL                            0
                114     STORE_FAST                      2: _var_var_32
                116     LOAD_FAST                       0: path
                118     LOAD_ATTR                       5: close
                138     CALL                            0
                146     POP_TOP                         
                148     LOAD_GLOBAL                     7: NULL + random
                158     LOAD_ATTR                       8: shuffle
                178     LOAD_FAST                       2: _var_var_32
                180     CALL                            1
                188     POP_TOP                         
                190     BUILD_LIST                      0
                192     STORE_FAST                      3: _var_var_33
                194     LOAD_FAST                       2: _var_var_32
                196     GET_ITER                        
                198     FOR_ITER                        50 (to 300)
                202     STORE_FAST                      4: _var_var_34
                204     LOAD_FAST                       4: _var_var_34
                206     LOAD_ATTR                       11: strip
                226     CALL                            0
                234     POP_JUMP_IF_TRUE                1 (to 238)
                236     JUMP_BACKWARD                   20 (to 198)
                238     LOAD_FAST                       3: _var_var_33
                240     LOAD_ATTR                       13: append
                260     LOAD_FAST                       4: _var_var_34
                262     LOAD_ATTR                       11: strip
                282     CALL                            0
                290     CALL                            1
                298     POP_TOP                         
                300     JUMP_BACKWARD                   52 (to 198)
                302     END_FOR                         
                304     LOAD_GLOBAL                     15: NULL + len
                314     LOAD_FAST                       3: _var_var_33
                316     CALL                            1
                324     LOAD_CONST                      9: 10
                326     COMPARE_OP                      68 (>)
                330     POP_JUMP_IF_FALSE               11 (to 354)
                332     LOAD_FAST                       3: _var_var_33
                334     NOP                             
                336     NOP                             
                338     NOP                             
                340     JUMP_FORWARD                    38 (to 418)
                342     CALL                            1
                350     POP_TOP                         
                352     RETURN_VALUE                    
                354     NOP                             
                356     LOAD_CONST                      5: False
                358     NOP                             
                360     NOP                             
                362     NOP                             
                364     JUMP_FORWARD                    26 (to 418)
                372     POP_TOP                         
                374     RETURN_CONST                    5: False
                376     PUSH_EXC_INFO                   
                378     POP_TOP                         
                380     POP_EXCEPT                      
                382     JUMP_BACKWARD                   14 (to 356)
                384     COPY                            3
                386     POP_EXCEPT                      
                388     RERAISE                         1
                390     PUSH_EXC_INFO                   
                392     PUSH_NULL                       
                394     LOAD_CONST                      4: '__pyarmor_exit_12902__'
                396     NOP                             
                398     LOAD_CONST                      3: b'<COAddr>\x07\x00\x00\x1al\x01\x00\x00\x00\x00\x00\x00\x00\x00\x00\x00\x00\x00\x00\x00'
                400     CALL                            1
                408     POP_TOP                         
                410     RERAISE                         0
                412     COPY                            3
                414     POP_EXCEPT                      
                416     RERAISE                         1
                418     PUSH_NULL                       
                420     LOAD_CONST                      4: '__pyarmor_exit_12902__'
                422     LOAD_CONST                      3: b'<COAddr>\x07\x00\x00\x1al\x01\x00\x00\x00\x00\x00\x00\x00\x00\x00\x00\x00\x00\x00\x00'
                424     BUILD_TUPLE                     1
                426     CALL_FUNCTION_EX                0
                428     POP_TOP                         
                430     RETURN_VALUE                    
            [Exception Table]
                30 to 34 -> 376 [0] 
                56 to 236 -> 376 [0] 
                238 to 334 -> 376 [0] 
                354 to 356 -> 390 [0] 
                376 to 380 -> 384 [1] lasti
                380 to 390 -> 390 [0] 
                390 to 412 -> 412 [1] lasti
        [Code]
            File Name: <frozen program.modules.account_booster>
            Object Name: get_smile
            Qualified Name: get_smile
            Arg Count: 0
            Pos Only Arg Count: 0
            KW Only Arg Count: 0
            Stack Size: 8
            Flags: 0x20000003 (CO_OPTIMIZED | CO_NEWLOCALS | CO_PYARMOR_OBFUSCATED)
            [Names]
                'len'
                'random'
                'randint'
                'str'
            [Locals+Names]
                '__assert_armored__'
                '_var_var_35'
                '_var_var_36'
                '_var_var_37'
                '_var_var_38'
            [Constants]
                ' Получаяем рандомные смайлы '
                '__pyarmor_assert_12903__'
                '__pyarmor_enter_12904__'
                b'<COAddr>\x05\x00\x00\x1aT\x01\x00\x00\x00\x00\x00\x00\x00\x00\x00\x00\x00\x00\x00\x00'
                (
                    '😊'
                    '👍'
                    '😀'
                    '☺'
                    '🤓'
                    '😁'
                    '👌'
                    '🧐'
                    '🙈'
                    '😌'
                    '😉'
                    '👇'
                    '👉'
                    '😃'
                    '😀'
                    '😃'
                    '😄'
                    '😅'
                    '🙃'
                    '🙂'
                    '☺'
                    '️😊'
                    '😎'
                    '😏'
                    '🤔'
                    '🤭'
                    '👐'
                    '🤝'
                    '👍'
                    '🤟'
                    '✌'
                    '️👌'
                    '✋'
                    '🖐'
                    '🙏'
                    '🐰'
                    '🐹'
                    '🐭'
                    '🐱'
                    '🐯'
                    '🦁'
                    '🐮'
                    '🐷'
                    '🙈'
                    '🐵'
                    '🙊'
                    '🐶'
                    '☀'
                    '️🌤'
                    '☂'
                    '️🚗'
                    '🚕'
                    '🚙'
                    '📞'
                    '☎'
                    '️✡'
                    '️💟'
                    '❤'
                    '️✅'
                    '🕐'
                    '🕑'
                    '💲'
                    '🚬'
                )
                1
                0
                1000
                ''
                300
                '__pyarmor_exit_12905__'
                800
                ' '
            [Disassembly]
                0       NOP                             
                2       NOP                             
                4       PUSH_NULL                       
                6       LOAD_CONST                      2: '__pyarmor_enter_12904__'
                8       LOAD_CONST                      3: b'<COAddr>\x05\x00\x00\x1aT\x01\x00\x00\x00\x00\x00\x00\x00\x00\x00\x00\x00\x00\x00\x00'
                10      BUILD_TUPLE                     1
                12      CALL_FUNCTION_EX                0
                14      POP_TOP                         
                16      RESUME                          0
                18      NOP                             
                20      NOP                             
                22      NOP                             
                24      NOP                             
                26      NOP                             
                28      BUILD_LIST                      0
                30      LOAD_CONST                      4: ('😊', '👍', '😀', '☺', '🤓', '😁', '👌', '🧐', '🙈', '😌', '😉', '👇', '👉', '😃', '😀', '😃', '😄', '😅', '🙃', '🙂', '☺', '️😊', '😎', '😏', '🤔', '🤭', '👐', '🤝', '👍', '🤟', '✌', '️👌', '✋', '🖐', '🙏', '🐰', '🐹', '🐭', '🐱', '🐯', '🦁', '🐮', '🐷', '🙈', '🐵', '🙊', '🐶', '☀', '️🌤', '☂', '️🚗', '🚕', '🚙', '📞', '☎', '️✡', '️💟', '❤', '️✅', '🕐', '🕑', '💲', '🚬')
                32      LIST_EXTEND                     1
                34      STORE_FAST                      1: _var_var_35
                36      LOAD_GLOBAL                     1: NULL + len
                46      LOAD_FAST                       1: _var_var_35
                48      CALL                            1
                56      LOAD_CONST                      5: 1
                58      BINARY_OP                       10 (-)
                62      STORE_FAST                      2: _var_var_36
                64      LOAD_GLOBAL                     3: NULL + random
                74      LOAD_ATTR                       4: randint
                94      LOAD_CONST                      6: 0
                96      LOAD_CONST                      7: 1000
                98      CALL                            2
                106     STORE_FAST                      3: _var_var_37
                108     LOAD_CONST                      8: ''
                110     STORE_FAST                      4: _var_var_38
                112     LOAD_FAST                       3: _var_var_37
                114     LOAD_CONST                      9: 300
                116     COMPARE_OP                      2 (<)
                120     POP_JUMP_IF_FALSE               34 (to 190)
                122     LOAD_FAST                       1: _var_var_35
                124     LOAD_GLOBAL                     3: NULL + random
                134     LOAD_ATTR                       4: randint
                154     LOAD_CONST                      6: 0
                156     LOAD_FAST                       2: _var_var_36
                158     CALL                            2
                166     BINARY_SUBSCR                   
                170     NOP                             
                172     NOP                             
                174     NOP                             
                176     JUMP_FORWARD                    108 (to 394)
                178     CALL                            1
                186     POP_TOP                         
                188     RETURN_VALUE                    
                190     LOAD_FAST                       3: _var_var_37
                192     LOAD_CONST                      11: 800
                194     COMPARE_OP                      68 (>)
                198     POP_JUMP_IF_FALSE               72 (to 344)
                200     LOAD_GLOBAL                     7: NULL + str
                210     LOAD_FAST                       1: _var_var_35
                212     LOAD_GLOBAL                     3: NULL + random
                222     LOAD_ATTR                       4: randint
                242     LOAD_CONST                      6: 0
                244     LOAD_FAST                       2: _var_var_36
                246     CALL                            2
                254     BINARY_SUBSCR                   
                258     LOAD_CONST                      12: ' '
                260     BINARY_OP                       0 (+)
                264     LOAD_FAST                       1: _var_var_35
                266     LOAD_GLOBAL                     3: NULL + random
                276     LOAD_ATTR                       4: randint
                296     LOAD_CONST                      6: 0
                298     LOAD_FAST                       2: _var_var_36
                300     CALL                            2
                308     BINARY_SUBSCR                   
                312     BINARY_OP                       0 (+)
                316     CALL                            1
                324     NOP                             
                326     NOP                             
                328     NOP                             
                330     JUMP_FORWARD                    31 (to 394)
                332     CALL                            1
                340     POP_TOP                         
                342     RETURN_VALUE                    
                344     LOAD_FAST                       4: _var_var_38
                346     NOP                             
                348     NOP                             
                350     NOP                             
                352     JUMP_FORWARD                    20 (to 394)
                354     CALL                            1
                362     POP_TOP                         
                364     RETURN_VALUE                    
                366     PUSH_EXC_INFO                   
                368     PUSH_NULL                       
                370     LOAD_CONST                      10: '__pyarmor_exit_12905__'
                372     NOP                             
                374     LOAD_CONST                      3: b'<COAddr>\x05\x00\x00\x1aT\x01\x00\x00\x00\x00\x00\x00\x00\x00\x00\x00\x00\x00\x00\x00'
                376     CALL                            1
                384     POP_TOP                         
                386     RERAISE                         0
                388     COPY                            3
                390     POP_EXCEPT                      
                392     RERAISE                         1
                394     PUSH_NULL                       
                396     LOAD_CONST                      10: '__pyarmor_exit_12905__'
                398     LOAD_CONST                      3: b'<COAddr>\x05\x00\x00\x1aT\x01\x00\x00\x00\x00\x00\x00\x00\x00\x00\x00\x00\x00\x00\x00'
                400     BUILD_TUPLE                     1
                402     CALL_FUNCTION_EX                0
                404     POP_TOP                         
                406     RETURN_VALUE                    
            [Exception Table]
                28 to 170 -> 366 [0] 
                190 to 324 -> 366 [0] 
                344 to 346 -> 366 [0] 
                366 to 388 -> 388 [1] lasti
        [Code]
            File Name: <frozen program.modules.account_booster>
            Object Name: mark_mess_read
            Qualified Name: mark_mess_read
            Arg Count: 1
            Pos Only Arg Count: 0
            KW Only Arg Count: 0
            Stack Size: 6
            Flags: 0x20000003 (CO_OPTIMIZED | CO_NEWLOCALS | CO_PYARMOR_OBFUSCATED)
            [Names]
                'iter_dialogs'
                'random'
                'randint'
                'unread_count'
                'get_entity'
                'id'
                'get_messages'
                'send_read_acknowledge'
            [Locals+Names]
                'client'
                '__assert_armored__'
                '_var_var_39'
                '_var_var_40'
                '_var_var_41'
                '_var_var_42'
            [Constants]
                ' Прочитываем диалоги в аккаунте '
                '__pyarmor_assert_12906__'
                '__pyarmor_enter_12907__'
                b'<COAddr>\x05\x00\x00\x1a\\\x01\x00\x00\x00\x00\x00\x00\x00\x00\x00\x00\x00\x00\x00\x00'
                0
                50
                150
                (
                    'limit'
                )
                1
                (
                    'max_id'
                )
                '__pyarmor_exit_12908__'
            [Disassembly]
                0       NOP                             
                2       NOP                             
                4       PUSH_NULL                       
                6       LOAD_CONST                      2: '__pyarmor_enter_12907__'
                8       LOAD_CONST                      3: b'<COAddr>\x05\x00\x00\x1a\\\x01\x00\x00\x00\x00\x00\x00\x00\x00\x00\x00\x00\x00\x00\x00'
                10      BUILD_TUPLE                     1
                12      CALL_FUNCTION_EX                0
                14      POP_TOP                         
                16      RESUME                          0
                18      NOP                             
                20      NOP                             
                22      NOP                             
                24      NOP                             
                26      NOP                             
                28      NOP                             
                30      LOAD_CONST                      4: 0
                32      STORE_FAST                      2: _var_var_39
                34      LOAD_FAST                       0: client
                36      LOAD_ATTR                       1: iter_dialogs
                56      LOAD_GLOBAL                     3: NULL + random
                66      LOAD_ATTR                       4: randint
                86      LOAD_CONST                      5: 50
                88      LOAD_CONST                      6: 150
                90      CALL                            2
                98      KW_NAMES                        7: ('limit',)
                100     CALL                            1
                108     STORE_FAST                      3: _var_var_40
                110     LOAD_FAST                       3: _var_var_40
                112     GET_ITER                        
                114     FOR_ITER                        92 (to 300)
                118     STORE_FAST                      4: _var_var_41
                120     NOP                             
                122     LOAD_FAST                       4: _var_var_41
                124     LOAD_ATTR                       6: unread_count
                144     LOAD_CONST                      4: 0
                146     COMPARE_OP                      55 (!=)
                150     POP_JUMP_IF_FALSE               74 (to 300)
                152     LOAD_FAST                       0: client
                154     LOAD_ATTR                       9: get_entity
                174     LOAD_FAST                       4: _var_var_41
                176     LOAD_ATTR                       10: id
                196     CALL                            1
                204     STORE_FAST                      4: _var_var_41
                206     LOAD_FAST                       0: client
                208     LOAD_ATTR                       13: get_messages
                228     LOAD_FAST                       4: _var_var_41
                230     LOAD_CONST                      8: 1
                232     KW_NAMES                        7: ('limit',)
                234     CALL                            2
                242     STORE_FAST                      5: _var_var_42
                244     LOAD_FAST                       0: client
                246     LOAD_ATTR                       15: send_read_acknowledge
                266     LOAD_FAST                       4: _var_var_41
                268     LOAD_FAST                       5: _var_var_42
                270     LOAD_CONST                      4: 0
                272     BINARY_SUBSCR                   
                276     LOAD_CONST                      4: 0
                278     KW_NAMES                        9: ('max_id',)
                280     CALL                            3
                288     POP_TOP                         
                290     LOAD_FAST                       2: _var_var_39
                292     LOAD_CONST                      8: 1
                294     BINARY_OP                       13 (+=)
                298     STORE_FAST                      2: _var_var_39
                300     JUMP_BACKWARD                   94 (to 114)
                302     END_FOR                         
                304     DELETE_FAST                     3: _var_var_40
                306     LOAD_FAST                       2: _var_var_39
                308     NOP                             
                310     NOP                             
                312     NOP                             
                314     JUMP_FORWARD                    43 (to 402)
                316     CALL                            1
                324     POP_TOP                         
                326     RETURN_VALUE                    
                328     PUSH_EXC_INFO                   
                330     POP_TOP                         
                332     POP_EXCEPT                      
                334     JUMP_BACKWARD                   111 (to 114)
                336     COPY                            3
                338     POP_EXCEPT                      
                340     RERAISE                         1
                342     PUSH_EXC_INFO                   
                344     POP_TOP                         
                346     POP_EXCEPT                      
                348     LOAD_CONST                      4: 0
                350     NOP                             
                352     NOP                             
                354     NOP                             
                356     JUMP_FORWARD                    22 (to 402)
                364     POP_TOP                         
                366     RETURN_CONST                    4: 0
                368     COPY                            3
                370     POP_EXCEPT                      
                372     RERAISE                         1
                374     PUSH_EXC_INFO                   
                376     PUSH_NULL                       
                378     LOAD_CONST                      10: '__pyarmor_exit_12908__'
                380     NOP                             
                382     LOAD_CONST                      3: b'<COAddr>\x05\x00\x00\x1a\\\x01\x00\x00\x00\x00\x00\x00\x00\x00\x00\x00\x00\x00\x00\x00'
                384     CALL                            1
                392     POP_TOP                         
                394     RERAISE                         0
                396     COPY                            3
                398     POP_EXCEPT                      
                400     RERAISE                         1
                402     PUSH_NULL                       
                404     LOAD_CONST                      10: '__pyarmor_exit_12908__'
                406     LOAD_CONST                      3: b'<COAddr>\x05\x00\x00\x1a\\\x01\x00\x00\x00\x00\x00\x00\x00\x00\x00\x00\x00\x00\x00\x00'
                408     BUILD_TUPLE                     1
                410     CALL_FUNCTION_EX                0
                412     POP_TOP                         
                414     RETURN_VALUE                    
            [Exception Table]
                30 to 120 -> 342 [0] 
                122 to 300 -> 328 [1] 
                300 to 308 -> 342 [0] 
                328 to 332 -> 336 [2] lasti
                332 to 342 -> 342 [0] 
                342 to 346 -> 368 [1] lasti
                346 to 348 -> 374 [0] 
                368 to 374 -> 374 [0] 
                374 to 396 -> 396 [1] lasti
        [Code]
            File Name: <frozen program.modules.account_booster>
            Object Name: get_username_hash
            Qualified Name: get_username_hash
            Arg Count: 1
            Pos Only Arg Count: 0
            KW Only Arg Count: 0
            Stack Size: 5
            Flags: 0x20000003 (CO_OPTIMIZED | CO_NEWLOCALS | CO_PYARMOR_OBFUSCATED)
            [Names]
                'replace'
                'strip'
            [Locals+Names]
                'link'
                '__assert_armored__'
            [Constants]
                ' Выризаем весь мусор из юзернейма '
                '__pyarmor_assert_12909__'
                '__pyarmor_enter_12910__'
                b'<COAddr>\x07\x00\x00\x1a\x8c\x01\x00\x00\x00\x00\x00\x00\x00\x00\x00\x00\x00\x00\x00\x00'
                'https'
                ''
                'http'
                '/'
                '+'
                ':'
                '@'
                't.me'
                'telegram.me'   # b'\x81\xf6\x1d\x1f6\xfd\xac\xd3\x16\xb4\x00\xc5'
                'joinchat'
                ' '
                '__pyarmor_exit_12911__'
            [Disassembly]
                0       NOP                             
                2       NOP                             
                4       PUSH_NULL                       
                6       LOAD_CONST                      2: '__pyarmor_enter_12910__'
                8       LOAD_CONST                      3: b'<COAddr>\x07\x00\x00\x1a\x8c\x01\x00\x00\x00\x00\x00\x00\x00\x00\x00\x00\x00\x00\x00\x00'
                10      BUILD_TUPLE                     1
                12      CALL_FUNCTION_EX                0
                14      POP_TOP                         
                16      RESUME                          0
                18      NOP                             
                20      NOP                             
                22      NOP                             
                24      NOP                             
                26      NOP                             
                28      LOAD_FAST                       0: link
                30      LOAD_ATTR                       1: replace
                50      LOAD_CONST                      4: 'https'
                52      LOAD_CONST                      5: ''
                54      CALL                            2
                62      LOAD_ATTR                       1: replace
                82      LOAD_CONST                      6: 'http'
                84      LOAD_CONST                      5: ''
                86      CALL                            2
                94      LOAD_ATTR                       1: replace
                114     LOAD_CONST                      7: '/'
                116     LOAD_CONST                      5: ''
                118     CALL                            2
                126     LOAD_ATTR                       1: replace
                146     LOAD_CONST                      8: '+'
                148     LOAD_CONST                      5: ''
                150     CALL                            2
                158     LOAD_ATTR                       1: replace
                178     LOAD_CONST                      9: ':'
                180     LOAD_CONST                      5: ''
                182     CALL                            2
                190     LOAD_ATTR                       1: replace
                210     LOAD_CONST                      10: '@'
                212     LOAD_CONST                      5: ''
                214     CALL                            2
                222     STORE_FAST                      0: link
                224     LOAD_FAST                       0: link
                226     LOAD_ATTR                       1: replace
                246     LOAD_CONST                      11: 't.me'
                248     LOAD_CONST                      5: ''
                250     CALL                            2
                258     LOAD_ATTR                       1: replace
                278     PUSH_NULL                       
                280     LOAD_CONST                      1: '__pyarmor_assert_12909__'
                282     LOAD_CONST                      12: 'telegram.me'   # b'\x81\xf6\x1d\x1f6\xfd\xac\xd3\x16\xb4\x00\xc5'
                284     CALL                            1
                292     LOAD_CONST                      5: ''
                294     CALL                            2
                302     LOAD_ATTR                       1: replace
                322     LOAD_CONST                      13: 'joinchat'
                324     LOAD_CONST                      5: ''
                326     CALL                            2
                334     LOAD_ATTR                       1: replace
                354     LOAD_CONST                      14: ' '
                356     LOAD_CONST                      5: ''
                358     CALL                            2
                366     STORE_FAST                      0: link
                368     LOAD_FAST                       0: link
                370     LOAD_ATTR                       3: strip
                390     CALL                            0
                398     STORE_FAST                      0: link
                400     LOAD_FAST                       0: link
                402     NOP                             
                404     NOP                             
                406     NOP                             
                408     JUMP_FORWARD                    20 (to 450)
                410     CALL                            1
                418     POP_TOP                         
                420     RETURN_VALUE                    
                422     PUSH_EXC_INFO                   
                424     PUSH_NULL                       
                426     LOAD_CONST                      15: '__pyarmor_exit_12911__'
                428     NOP                             
                430     LOAD_CONST                      3: b'<COAddr>\x07\x00\x00\x1a\x8c\x01\x00\x00\x00\x00\x00\x00\x00\x00\x00\x00\x00\x00\x00\x00'
                432     CALL                            1
                440     POP_TOP                         
                442     RERAISE                         0
                444     COPY                            3
                446     POP_EXCEPT                      
                448     RERAISE                         1
                450     PUSH_NULL                       
                452     LOAD_CONST                      15: '__pyarmor_exit_12911__'
                454     LOAD_CONST                      3: b'<COAddr>\x07\x00\x00\x1a\x8c\x01\x00\x00\x00\x00\x00\x00\x00\x00\x00\x00\x00\x00\x00\x00'
                456     BUILD_TUPLE                     1
                458     CALL_FUNCTION_EX                0
                460     POP_TOP                         
                462     RETURN_VALUE                    
            [Exception Table]
                28 to 402 -> 422 [0] 
                422 to 444 -> 444 [1] lasti
        [Code]
            File Name: <frozen program.modules.account_booster>
            Object Name: tg_send_message
            Qualified Name: tg_send_message
            Arg Count: 6
            Pos Only Arg Count: 0
            KW Only Arg Count: 0
            Stack Size: 9
            Flags: 0x20000003 (CO_OPTIMIZED | CO_NEWLOCALS | CO_PYARMOR_OBFUSCATED)
            [Names]
                'send_message'
                'errors'
                'FloodWaitError'
                'int'
                'seconds'
                'Logs'
                'PrintLog'
                'config'
                'Lang'
                'DelayOnline'
                'tg_send_message'
                'UserDeactivatedBanError'
                'BadRequestError'
                'StopProgram'
                'Exception'
            [Locals+Names]
                'client'
                'account'
                'user'
                'mess'
                'max_flood_wait'
                'stop_thread'
                '__assert_armored__'
                '_var_var_4'
                '_var_var_43'
            [Constants]
                ' Отправляем сообщение в тг '
                '__pyarmor_assert_12912__'
                '__pyarmor_enter_12913__'
                b'<COAddr>\x07\x00\x00\x1a\x8c\x03\x00\x00\x00\x00\x00\x00\x00\x00\x00\x00\x00\x00\x00\x00'
                'md'
                (
                    'parse_mode'
                )
                '__pyarmor_exit_12914__'
                True
                'flood_wait_more_sec'   # b'\x81\xe4\x14\x1c<\xfe\x81\xc5\x1a\xf3\x19\xffa\xe3\xea\x800N\xbe\xa4'
                (
                    'config'
                    'account'
                    'message'
                    'param'
                )
                'sending_stopped'   # b'\x81\xf1\x1d\x1d7\xf3\xb0\xd5$\xe9\x19\xcf|\xfc\xfd\x81'
                (
                    'config'
                    'account'
                    'message'
                )
                None
                False
                100
                'algorithm_running_wait'   # b'\x81\xe3\x14\x14<\xe8\xb7\xc6\x13\xf72\xd2y\xe2\xf6\x8c\x01Z\x84\xb0\xab\xc2Z'
                'back_in_ranks'   # b'\x81\xe0\x19\x108\xc5\xb7\xdc$\xe8\x0c\xceg\xff'
                'booster_mess_not_send'   # b'\x81\xe0\x17\x1c \xee\xbb\xc0$\xf7\x08\xd3\x7f\xd3\xf6\x8a\x1bb\xa8\xa2\xa4\xcf'
            [Disassembly]
                0       NOP                             
                2       NOP                             
                4       PUSH_NULL                       
                6       LOAD_CONST                      2: '__pyarmor_enter_12913__'
                8       LOAD_CONST                      3: b'<COAddr>\x07\x00\x00\x1a\x8c\x03\x00\x00\x00\x00\x00\x00\x00\x00\x00\x00\x00\x00\x00\x00'
                10      BUILD_TUPLE                     1
                12      CALL_FUNCTION_EX                0
                14      POP_TOP                         
                16      RESUME                          0
                18      NOP                             
                20      NOP                             
                22      NOP                             
                24      NOP                             
                26      NOP                             
                28      NOP                             
                30      LOAD_FAST                       0: client
                32      LOAD_ATTR                       1: send_message
                52      LOAD_FAST                       2: user
                54      LOAD_FAST                       3: mess
                56      LOAD_CONST                      4: 'md'
                58      KW_NAMES                        5: ('parse_mode',)
                60      CALL                            3
                68      POP_TOP                         
                70      NOP                             
                72      LOAD_CONST                      7: True
                74      NOP                             
                76      NOP                             
                78      JUMP_FORWARD                    440 (to 962)
                88      POP_TOP                         
                90      RETURN_CONST                    7: True
                92      PUSH_EXC_INFO                   
                94      LOAD_GLOBAL                     2: errors
                104     LOAD_ATTR                       4: FloodWaitError
                124     CHECK_EXC_MATCH                 
                126     POP_JUMP_IF_FALSE               261 (to 652)
                130     STORE_FAST                      7: _var_var_4
                132     LOAD_GLOBAL                     7: NULL + int
                142     LOAD_FAST                       7: _var_var_4
                144     LOAD_ATTR                       8: seconds
                164     CALL                            1
                172     STORE_FAST                      8: _var_var_43
                174     LOAD_FAST                       8: _var_var_43
                176     LOAD_FAST                       4: max_flood_wait
                178     COMPARE_OP                      68 (>)
                182     POP_JUMP_IF_FALSE               97 (to 378)
                184     LOAD_GLOBAL                     11: NULL + Logs
                194     LOAD_ATTR                       12: PrintLog
                214     LOAD_GLOBAL                     14: config
                224     LOAD_FAST                       1: account
                226     LOAD_GLOBAL                     16: Lang
                236     PUSH_NULL                       
                238     LOAD_CONST                      1: '__pyarmor_assert_12912__'
                240     LOAD_CONST                      8: 'flood_wait_more_sec'   # b'\x81\xe4\x14\x1c<\xfe\x81\xc5\x1a\xf3\x19\xffa\xe3\xea\x800N\xbe\xa4'
                242     CALL                            1
                250     BINARY_SUBSCR                   
                254     LOAD_FAST                       4: max_flood_wait
                256     KW_NAMES                        9: ('config', 'account', 'message', 'param')
                258     CALL                            4
                266     POP_TOP                         
                268     LOAD_GLOBAL                     11: NULL + Logs
                278     LOAD_ATTR                       12: PrintLog
                298     LOAD_GLOBAL                     14: config
                308     LOAD_FAST                       1: account
                310     LOAD_GLOBAL                     16: Lang
                320     PUSH_NULL                       
                322     LOAD_CONST                      1: '__pyarmor_assert_12912__'
                324     LOAD_CONST                      10: 'sending_stopped'   # b'\x81\xf1\x1d\x1d7\xf3\xb0\xd5$\xe9\x19\xcf|\xfc\xfd\x81'
                326     CALL                            1
                334     BINARY_SUBSCR                   
                338     KW_NAMES                        11: ('config', 'account', 'message')
                340     CALL                            3
                348     POP_TOP                         
                350     POP_EXCEPT                      
                352     LOAD_CONST                      12: None
                354     STORE_FAST                      7: _var_var_4
                356     DELETE_FAST                     7: _var_var_4
                358     LOAD_CONST                      13: False
                360     NOP                             
                362     NOP                             
                364     JUMP_FORWARD                    297 (to 962)
                374     POP_TOP                         
                376     RETURN_CONST                    13: False
                378     LOAD_FAST                       8: _var_var_43
                380     LOAD_CONST                      14: 100
                382     BINARY_OP                       0 (+)
                386     STORE_FAST                      8: _var_var_43
                388     LOAD_GLOBAL                     11: NULL + Logs
                398     LOAD_ATTR                       12: PrintLog
                418     LOAD_GLOBAL                     14: config
                428     LOAD_FAST                       1: account
                430     LOAD_GLOBAL                     16: Lang
                440     PUSH_NULL                       
                442     LOAD_CONST                      1: '__pyarmor_assert_12912__'
                444     LOAD_CONST                      15: 'algorithm_running_wait'   # b'\x81\xe3\x14\x14<\xe8\xb7\xc6\x13\xf72\xd2y\xe2\xf6\x8c\x01Z\x84\xb0\xab\xc2Z'
                446     CALL                            1
                454     BINARY_SUBSCR                   
                458     LOAD_FAST                       8: _var_var_43
                460     KW_NAMES                        9: ('config', 'account', 'message', 'param')
                462     CALL                            4
                470     POP_TOP                         
                472     LOAD_GLOBAL                     19: NULL + DelayOnline
                482     LOAD_FAST                       1: account
                484     LOAD_FAST                       0: client
                486     LOAD_FAST                       8: _var_var_43
                488     LOAD_FAST                       8: _var_var_43
                490     LOAD_FAST                       5: stop_thread
                492     CALL                            5
                500     POP_TOP                         
                502     LOAD_GLOBAL                     11: NULL + Logs
                512     LOAD_ATTR                       12: PrintLog
                532     LOAD_GLOBAL                     14: config
                542     LOAD_FAST                       1: account
                544     LOAD_GLOBAL                     16: Lang
                554     PUSH_NULL                       
                556     LOAD_CONST                      1: '__pyarmor_assert_12912__'
                558     LOAD_CONST                      16: 'back_in_ranks'   # b'\x81\xe0\x19\x108\xc5\xb7\xdc$\xe8\x0c\xceg\xff'
                560     CALL                            1
                568     BINARY_SUBSCR                   
                572     KW_NAMES                        11: ('config', 'account', 'message')
                574     CALL                            3
                582     POP_TOP                         
                584     LOAD_GLOBAL                     21: NULL + tg_send_message
                594     LOAD_FAST                       0: client
                596     LOAD_FAST                       1: account
                598     LOAD_FAST                       2: user
                600     LOAD_FAST                       3: mess
                602     LOAD_FAST                       4: max_flood_wait
                604     LOAD_FAST                       5: stop_thread
                606     CALL                            6
                614     SWAP                            2
                616     POP_EXCEPT                      
                618     LOAD_CONST                      12: None
                620     STORE_FAST                      7: _var_var_4
                622     DELETE_FAST                     7: _var_var_4
                624     NOP                             
                626     NOP                             
                628     NOP                             
                630     JUMP_FORWARD                    165 (to 962)
                632     CALL                            1
                640     POP_TOP                         
                642     RETURN_VALUE                    
                644     LOAD_CONST                      12: None
                646     STORE_FAST                      7: _var_var_4
                648     DELETE_FAST                     7: _var_var_4
                650     RERAISE                         1
                652     LOAD_GLOBAL                     2: errors
                662     LOAD_ATTR                       22: UserDeactivatedBanError
                682     LOAD_GLOBAL                     2: errors
                692     LOAD_ATTR                       22: UserDeactivatedBanError
                712     LOAD_GLOBAL                     2: errors
                722     LOAD_ATTR                       24: BadRequestError
                742     BUILD_TUPLE                     3
                744     CHECK_EXC_MATCH                 
                746     POP_JUMP_IF_FALSE               12 (to 772)
                748     POP_TOP                         
                750     POP_EXCEPT                      
                752     LOAD_CONST                      13: False
                754     NOP                             
                756     NOP                             
                758     NOP                             
                760     JUMP_FORWARD                    100 (to 962)
                768     POP_TOP                         
                770     RETURN_CONST                    13: False
                772     LOAD_GLOBAL                     26: StopProgram
                782     CHECK_EXC_MATCH                 
                784     POP_JUMP_IF_FALSE               2 (to 790)
                786     POP_TOP                         
                788     RAISE_VARARGS                   0
                790     LOAD_GLOBAL                     28: Exception
                800     CHECK_EXC_MATCH                 
                802     POP_JUMP_IF_FALSE               61 (to 926)
                804     STORE_FAST                      7: _var_var_4
                806     LOAD_GLOBAL                     11: NULL + Logs
                816     LOAD_ATTR                       12: PrintLog
                836     LOAD_GLOBAL                     14: config
                846     LOAD_FAST                       1: account
                848     LOAD_GLOBAL                     16: Lang
                858     PUSH_NULL                       
                860     LOAD_CONST                      1: '__pyarmor_assert_12912__'
                862     LOAD_CONST                      17: 'booster_mess_not_send'   # b'\x81\xe0\x17\x1c \xee\xbb\xc0$\xf7\x08\xd3\x7f\xd3\xf6\x8a\x1bb\xa8\xa2\xa4\xcf'
                864     CALL                            1
                872     BINARY_SUBSCR                   
                876     LOAD_FAST                       7: _var_var_4
                878     KW_NAMES                        9: ('config', 'account', 'message', 'param')
                880     CALL                            4
                888     POP_TOP                         
                890     POP_EXCEPT                      
                892     LOAD_CONST                      12: None
                894     STORE_FAST                      7: _var_var_4
                896     DELETE_FAST                     7: _var_var_4
                898     LOAD_CONST                      13: False
                900     NOP                             
                902     NOP                             
                904     NOP                             
                906     JUMP_FORWARD                    27 (to 962)
                914     POP_TOP                         
                916     RETURN_CONST                    13: False
                918     LOAD_CONST                      12: None
                920     STORE_FAST                      7: _var_var_4
                922     DELETE_FAST                     7: _var_var_4
                924     RERAISE                         1
                926     RERAISE                         0
                928     COPY                            3
                930     POP_EXCEPT                      
                932     RERAISE                         1
                934     PUSH_EXC_INFO                   
                936     PUSH_NULL                       
                938     LOAD_CONST                      6: '__pyarmor_exit_12914__'
                940     NOP                             
                942     LOAD_CONST                      3: b'<COAddr>\x07\x00\x00\x1a\x8c\x03\x00\x00\x00\x00\x00\x00\x00\x00\x00\x00\x00\x00\x00\x00'
                944     CALL                            1
                952     POP_TOP                         
                954     RERAISE                         0
                956     COPY                            3
                958     POP_EXCEPT                      
                960     RERAISE                         1
                962     PUSH_NULL                       
                964     LOAD_CONST                      6: '__pyarmor_exit_12914__'
                966     LOAD_CONST                      3: b'<COAddr>\x07\x00\x00\x1a\x8c\x03\x00\x00\x00\x00\x00\x00\x00\x00\x00\x00\x00\x00\x00\x00'
                968     BUILD_TUPLE                     1
                970     CALL_FUNCTION_EX                0
                972     POP_TOP                         
                974     RETURN_VALUE                    
            [Exception Table]
                30 to 70 -> 92 [0] 
                92 to 132 -> 928 [1] lasti
                132 to 350 -> 644 [1] lasti
                350 to 358 -> 934 [0] 
                378 to 614 -> 644 [1] lasti
                614 to 616 -> 928 [1] lasti
                616 to 624 -> 934 [0] 
                644 to 750 -> 928 [1] lasti
                750 to 752 -> 934 [0] 
                772 to 806 -> 928 [1] lasti
                806 to 890 -> 918 [1] lasti
                890 to 898 -> 934 [0] 
                918 to 928 -> 928 [1] lasti
                928 to 934 -> 934 [0] 
                934 to 956 -> 956 [1] lasti
        [Code]
            File Name: <frozen program.modules.account_booster>
            Object Name: Booster
            Qualified Name: Booster
            Arg Count: 8
            Pos Only Arg Count: 0
            KW Only Arg Count: 0
            Stack Size: 11
            Flags: 0x20000003 (CO_OPTIMIZED | CO_NEWLOCALS | CO_PYARMOR_OBFUSCATED)
            [Names]
                'Thread_wait'
                'account_works'
                'Lang'
                'Disconnect'
                'Logs'
                'PrintLog'
                'int'
                'get'
                'mark_mess_read'
                'range'
                'is_set'
                'StopProgram'
                'get_entity'
                'str'
                'random'
                'choice'
                'hasattr'
                'mutual_contact'
                'last_name'
                'functions'
                'contacts'
                'AddContactRequest'
                'first_name'
                'Exception'
                'tg_send_message'
                'get_smile'
                'DelayOnline'
                'get_dialogs'
                'entity'
                'username'
                'BaseException'
                'logging'
            [Locals+Names]
                'account'
                'config'
                'proxy'
                'data'
                'usernames'
                'messages'
                'mode'
                'stop_thread'
                '__assert_armored__'
                '_var_var_44'
                '_var_var_45'
                '_var_var_46'
                '_var_var_47'
                '_var_var_48'
                '_var_var_49'
                '_var_var_50'
                '_var_var_51'
                '_var_var_52'
                '_var_var_53'
                '_var_var_4'
                '_var_var_41'
            [Constants]
                None
                '__pyarmor_assert_12915__'
                '__pyarmor_enter_12916__'
                b'<COAddr>\x07\x00\x00\x1ap\r\x00\x00\x00\x00\x00\x00\x00\x00\x00\x00\x00\x00\x00\x00'
                'Booster'
                (
                    'module'
                )
                False
                'false'
                (
                    'account'
                    'status'
                )
                'work_account_completed'   # b'\x81\xf5\x17\x018\xc5\xbf\xd1\x18\xf5\x18\xcex\xd3\xfb\x8a\x02M\xb7\xa2\xbe\xceJ'
                (
                    'config'
                    'account'
                    'message'
                )
                'done'
                '__pyarmor_exit_12917__'
                'Settings'
                'kol_sms'
                'wait_from'   # b"\x81\xf5\x19\x1a'\xc5\xb8\xc0\x14\xf7"
                'wait_to'
                'max_flood_wait'   # b'\x81\xef\x19\x0b\x0c\xfc\xb2\xdd\x14\xfe2\xd7m\xe5\xec'
                'contact_off'   # b"\x81\xe1\x17\x1d'\xfb\xbd\xc6$\xf5\x0b\xc6"
                'booster_mess_read'   # b'\x81\xe0\x17\x1c \xee\xbb\xc0$\xf7\x08\xd3\x7f\xd3\xea\x80\x0eY'
                (
                    'config'
                    'account'
                    'message'
                    'param'
                )
                1
                2
                'booster_mode_sending_is_activated'   # b'\x81\xe0\x17\x1c \xee\xbb\xc0$\xf7\x02\xc4i\xd3\xeb\x80\x01Y\xb2\xa9\xad\xf4G\xdf:n\xa0H\t\xa7\x1f\xf1?V'
                'sms'
                (
                    'config'
                    'account'
                    'message'
                    'param'
                    'end'
                )
                'mutual_contact'   # b'\x81\xef\r\x07&\xfb\xb2\xed\x18\xf5\x03\xd4m\xef\xec'
                True
                ''
                (
                    'id'
                    'first_name'
                    'last_name'
                    'phone'
                    'add_phone_privacy_exception'
                )
                'booster_error_add_user'   # b'\x81\xe0\x17\x1c \xee\xbb\xc0$\xff\x1f\xd2c\xfe\xc7\x84\x0bY\x84\xb2\xb9\xce\\'
                ' '
                'booster_mess_is_send'   # b'\x81\xe0\x17\x1c \xee\xbb\xc0$\xf7\x08\xd3\x7f\xd3\xf1\x960N\xbe\xa9\xae'
                'booster_mess_not_send'   # b'\x81\xe0\x17\x1c \xee\xbb\xc0$\xf7\x08\xd3\x7f\xd3\xf6\x8a\x1bb\xa8\xa2\xa4\xcf'
                'booster_cant_send_mess'   # b'\x81\xe0\x17\x1c \xee\xbb\xc0$\xf9\x0c\xcex\xd3\xeb\x80\x01Y\x84\xaa\xaf\xd8]'
                (
                    'config'
                    'account'
                    'message'
                    'end'
                )
                'booster_mode_ansfer_activated'   # b'\x81\xe0\x17\x1c \xee\xbb\xc0$\xf7\x02\xc4i\xd3\xf9\x8b\x1c[\xbe\xb5\x95\xcaM\xd8\x0cy\xa2H\x05\xb5'
                'entity'
                'username'
                'booster_ansfer_is_send'   # b'\x81\xe0\x17\x1c \xee\xbb\xc0$\xfb\x03\xd3j\xe9\xea\xba\x06N\x84\xb4\xaf\xc5J'
                'booster_ansfer_is_not_send'   # b'\x81\xe0\x17\x1c \xee\xbb\xc0$\xfb\x03\xd3j\xe9\xea\xba\x06N\x84\xa9\xa5\xdfq\xdf\x00a\xa7'
                'booster_cant_send_ansfer'   # b'\x81\xe0\x17\x1c \xee\xbb\xc0$\xf9\x0c\xcex\xd3\xeb\x80\x01Y\x84\xa6\xa4\xd8H\xc9\x17'
            [Disassembly]
                0       NOP                             
                2       NOP                             
                4       PUSH_NULL                       
                6       LOAD_CONST                      2: '__pyarmor_enter_12916__'
                8       LOAD_CONST                      3: b'<COAddr>\x07\x00\x00\x1ap\r\x00\x00\x00\x00\x00\x00\x00\x00\x00\x00\x00\x00\x00\x00'
                10      BUILD_TUPLE                     1
                12      CALL_FUNCTION_EX                0
                14      POP_TOP                         
                16      RESUME                          0
                18      NOP                             
                20      NOP                             
                22      NOP                             
                24      NOP                             
                26      NOP                             
                28      NOP                             
                30      LOAD_GLOBAL                     1: NULL + Thread_wait
                40      LOAD_FAST                       3: data
                42      LOAD_FAST                       1: config
                44      LOAD_FAST                       7: stop_thread
                46      CALL                            3
                54      POP_TOP                         
                56      LOAD_GLOBAL                     3: NULL + account_works
                66      LOAD_FAST                       1: config
                68      LOAD_GLOBAL                     4: Lang
                78      LOAD_FAST                       2: proxy
                80      LOAD_FAST                       0: account
                82      LOAD_FAST                       7: stop_thread
                84      LOAD_CONST                      4: 'Booster'
                86      KW_NAMES                        5: ('module',)
                88      CALL                            6
                96      STORE_FAST                      9: _var_var_44
                98      LOAD_FAST                       9: _var_var_44
                100     LOAD_CONST                      6: False
                102     COMPARE_OP                      40 (==)
                106     POP_JUMP_IF_FALSE               68 (to 244)
                108     LOAD_FAST                       0: account
                110     LOAD_CONST                      7: 'false'
                112     LOAD_CONST                      8: ('account', 'status')
                114     BUILD_CONST_KEY_MAP             2
                116     LOAD_GLOBAL                     7: NULL + Disconnect
                126     LOAD_FAST                       9: _var_var_44
                128     CALL                            1
                136     POP_TOP                         
                138     LOAD_GLOBAL                     9: NULL + Logs
                148     LOAD_ATTR                       10: PrintLog
                168     LOAD_FAST                       1: config
                170     LOAD_FAST                       0: account
                172     LOAD_GLOBAL                     4: Lang
                182     PUSH_NULL                       
                184     LOAD_CONST                      1: '__pyarmor_assert_12915__'
                186     LOAD_CONST                      9: 'work_account_completed'   # b'\x81\xf5\x17\x018\xc5\xbf\xd1\x18\xf5\x18\xcex\xd3\xfb\x8a\x02M\xb7\xa2\xbe\xceJ'
                188     CALL                            1
                196     BINARY_SUBSCR                   
                200     KW_NAMES                        10: ('config', 'account', 'message')
                202     CALL                            3
                210     POP_TOP                         
                212     LOAD_FAST                       0: account
                214     LOAD_CONST                      11: 'done'
                216     LOAD_CONST                      8: ('account', 'status')
                218     BUILD_CONST_KEY_MAP             2
                220     SWAP                            2
                222     POP_TOP                         
                224     NOP                             
                226     NOP                             
                228     JUMP_FORWARD                    1631 (to 3494)
                232     CALL                            1
                240     POP_TOP                         
                242     RETURN_VALUE                    
                244     LOAD_GLOBAL                     13: NULL + int
                254     LOAD_FAST                       3: data
                256     LOAD_CONST                      13: 'Settings'
                258     BINARY_SUBSCR                   
                262     LOAD_ATTR                       15: get
                282     LOAD_CONST                      14: 'kol_sms'
                284     CALL                            1
                292     CALL                            1
                300     STORE_FAST                      10: _var_var_45
                302     LOAD_GLOBAL                     13: NULL + int
                312     LOAD_FAST                       3: data
                314     LOAD_CONST                      13: 'Settings'
                316     BINARY_SUBSCR                   
                320     LOAD_ATTR                       15: get
                340     PUSH_NULL                       
                342     LOAD_CONST                      1: '__pyarmor_assert_12915__'
                344     LOAD_CONST                      15: 'wait_from'   # b"\x81\xf5\x19\x1a'\xc5\xb8\xc0\x14\xf7"
                346     CALL                            1
                354     CALL                            1
                362     CALL                            1
                370     STORE_FAST                      11: _var_var_46
                372     LOAD_GLOBAL                     13: NULL + int
                382     LOAD_FAST                       3: data
                384     LOAD_CONST                      13: 'Settings'
                386     BINARY_SUBSCR                   
                390     LOAD_ATTR                       15: get
                410     LOAD_CONST                      16: 'wait_to'
                412     CALL                            1
                420     CALL                            1
                428     STORE_FAST                      12: _var_var_47
                430     LOAD_GLOBAL                     13: NULL + int
                440     LOAD_FAST                       3: data
                442     LOAD_CONST                      13: 'Settings'
                444     BINARY_SUBSCR                   
                448     LOAD_ATTR                       15: get
                468     PUSH_NULL                       
                470     LOAD_CONST                      1: '__pyarmor_assert_12915__'
                472     LOAD_CONST                      17: 'max_flood_wait'   # b'\x81\xef\x19\x0b\x0c\xfc\xb2\xdd\x14\xfe2\xd7m\xe5\xec'
                474     CALL                            1
                482     CALL                            1
                490     CALL                            1
                498     STORE_FAST                      13: _var_var_48
                500     LOAD_FAST                       3: data
                502     LOAD_CONST                      13: 'Settings'
                504     BINARY_SUBSCR                   
                508     LOAD_ATTR                       15: get
                528     PUSH_NULL                       
                530     LOAD_CONST                      1: '__pyarmor_assert_12915__'
                532     LOAD_CONST                      18: 'contact_off'   # b"\x81\xe1\x17\x1d'\xfb\xbd\xc6$\xf5\x0b\xc6"
                534     CALL                            1
                542     LOAD_CONST                      6: False
                544     CALL                            2
                552     STORE_FAST                      14: _var_var_49
                554     LOAD_GLOBAL                     17: NULL + mark_mess_read
                564     LOAD_FAST                       9: _var_var_44
                566     CALL                            1
                574     STORE_FAST                      15: _var_var_50
                576     LOAD_GLOBAL                     9: NULL + Logs
                586     LOAD_ATTR                       10: PrintLog
                606     LOAD_FAST                       1: config
                608     LOAD_FAST                       0: account
                610     LOAD_GLOBAL                     4: Lang
                620     PUSH_NULL                       
                622     LOAD_CONST                      1: '__pyarmor_assert_12915__'
                624     LOAD_CONST                      19: 'booster_mess_read'   # b'\x81\xe0\x17\x1c \xee\xbb\xc0$\xf7\x08\xd3\x7f\xd3\xea\x80\x0eY'
                626     CALL                            1
                634     BINARY_SUBSCR                   
                638     LOAD_FAST                       15: _var_var_50
                640     KW_NAMES                        20: ('config', 'account', 'message', 'param')
                642     CALL                            4
                650     POP_TOP                         
                652     LOAD_FAST                       6: mode
                654     LOAD_CONST                      21: 1
                656     COMPARE_OP                      40 (==)
                660     POP_JUMP_IF_TRUE                6 (to 674)
                662     LOAD_FAST                       6: mode
                664     LOAD_CONST                      22: 2
                666     COMPARE_OP                      40 (==)
                670     POP_JUMP_IF_FALSE               421 (to 1516)
                674     LOAD_GLOBAL                     9: NULL + Logs
                684     LOAD_ATTR                       10: PrintLog
                704     LOAD_FAST                       1: config
                706     LOAD_FAST                       0: account
                708     LOAD_GLOBAL                     4: Lang
                718     PUSH_NULL                       
                720     LOAD_CONST                      1: '__pyarmor_assert_12915__'
                722     LOAD_CONST                      23: 'booster_mode_sending_is_activated'   # b'\x81\xe0\x17\x1c \xee\xbb\xc0$\xf7\x02\xc4i\xd3\xeb\x80\x01Y\xb2\xa9\xad\xf4G\xdf:n\xa0H\t\xa7\x1f\xf1?V'
                724     CALL                            1
                732     BINARY_SUBSCR                   
                736     LOAD_FAST                       10: _var_var_45
                738     LOAD_CONST                      24: 'sms'
                740     KW_NAMES                        25: ('config', 'account', 'message', 'param', 'end')
                742     CALL                            5
                750     POP_TOP                         
                752     LOAD_GLOBAL                     19: NULL + range
                762     LOAD_FAST                       10: _var_var_45
                764     CALL                            1
                772     GET_ITER                        
                774     FOR_ITER                        367 (to 1512)
                780     STORE_FAST                      16: _var_var_51
                782     LOAD_FAST                       7: stop_thread
                784     LOAD_ATTR                       21: is_set
                804     CALL                            0
                812     POP_JUMP_IF_FALSE               10 (to 834)
                814     LOAD_GLOBAL                     23: NULL + StopProgram
                824     CALL                            0
                832     RAISE_VARARGS                   1
                834     NOP                             
                836     LOAD_FAST                       9: _var_var_44
                838     LOAD_ATTR                       25: get_entity
                858     LOAD_GLOBAL                     27: NULL + str
                868     LOAD_GLOBAL                     29: NULL + random
                878     LOAD_ATTR                       30: choice
                898     LOAD_FAST                       4: usernames
                900     CALL                            1
                908     CALL                            1
                916     CALL                            1
                924     STORE_FAST                      17: _var_var_52
                926     LOAD_GLOBAL                     33: NULL + hasattr
                936     LOAD_FAST                       17: _var_var_52
                938     PUSH_NULL                       
                940     LOAD_CONST                      1: '__pyarmor_assert_12915__'
                942     LOAD_CONST                      26: 'mutual_contact'   # b'\x81\xef\r\x07&\xfb\xb2\xed\x18\xf5\x03\xd4m\xef\xec'
                944     CALL                            1
                952     CALL                            2
                960     LOAD_CONST                      27: True
                962     COMPARE_OP                      40 (==)
                966     POP_JUMP_IF_FALSE               112 (to 1192)
                968     LOAD_FAST                       17: _var_var_52
                970     LOAD_ATTR                       34: mutual_contact
                990     LOAD_CONST                      27: True
                992     COMPARE_OP                      55 (!=)
                996     POP_JUMP_IF_FALSE               97 (to 1192)
                998     LOAD_FAST                       14: _var_var_49
                1000    POP_JUMP_IF_TRUE                95 (to 1192)
                1002    NOP                             
                1004    LOAD_FAST                       17: _var_var_52
                1006    LOAD_ATTR                       36: last_name
                1026    POP_JUMP_IF_NONE                15 (to 1058)
                1028    LOAD_FAST                       17: _var_var_52
                1030    LOAD_ATTR                       36: last_name
                1050    LOAD_CONST                      28: ''
                1052    COMPARE_OP                      40 (==)
                1056    POP_JUMP_IF_FALSE               3 (to 1064)
                1058    LOAD_CONST                      28: ''
                1060    STORE_FAST                      18: _var_var_53
                1062    JUMP_FORWARD                    12 (to 1088)
                1064    LOAD_FAST                       17: _var_var_52
                1066    LOAD_ATTR                       36: last_name
                1086    STORE_FAST                      18: _var_var_53
                1088    PUSH_NULL                       
                1090    LOAD_FAST                       9: _var_var_44
                1092    LOAD_GLOBAL                     38: functions
                1102    LOAD_ATTR                       40: contacts
                1122    LOAD_ATTR                       43: AddContactRequest
                1142    LOAD_FAST                       17: _var_var_52
                1144    LOAD_FAST                       17: _var_var_52
                1146    LOAD_ATTR                       44: first_name
                1166    LOAD_FAST                       18: _var_var_53
                1168    LOAD_CONST                      28: ''
                1170    LOAD_CONST                      27: True
                1172    KW_NAMES                        29: ('id', 'first_name', 'last_name', 'phone', 'add_phone_privacy_exception')
                1174    CALL                            5
                1182    CALL                            1
                1190    POP_TOP                         
                1192    LOAD_GLOBAL                     49: NULL + tg_send_message
                1202    LOAD_FAST                       9: _var_var_44
                1204    LOAD_FAST                       0: account
                1206    LOAD_FAST                       17: _var_var_52
                1208    LOAD_GLOBAL                     27: NULL + str
                1218    LOAD_GLOBAL                     29: NULL + random
                1228    LOAD_ATTR                       30: choice
                1248    LOAD_FAST                       5: messages
                1250    CALL                            1
                1258    CALL                            1
                1266    LOAD_CONST                      31: ' '
                1268    BINARY_OP                       0 (+)
                1272    LOAD_GLOBAL                     51: NULL + get_smile
                1282    CALL                            0
                1290    BINARY_OP                       0 (+)
                1294    LOAD_FAST                       13: _var_var_48
                1296    LOAD_FAST                       7: stop_thread
                1298    CALL                            6
                1306    POP_JUMP_IF_FALSE               64 (to 1436)
                1308    LOAD_GLOBAL                     9: NULL + Logs
                1318    LOAD_ATTR                       10: PrintLog
                1338    LOAD_FAST                       1: config
                1340    LOAD_FAST                       0: account
                1342    LOAD_GLOBAL                     4: Lang
                1352    PUSH_NULL                       
                1354    LOAD_CONST                      1: '__pyarmor_assert_12915__'
                1356    LOAD_CONST                      32: 'booster_mess_is_send'   # b'\x81\xe0\x17\x1c \xee\xbb\xc0$\xf7\x08\xd3\x7f\xd3\xf1\x960N\xbe\xa9\xae'
                1358    CALL                            1
                1366    BINARY_SUBSCR                   
                1370    LOAD_FAST                       17: _var_var_52
                1372    LOAD_ATTR                       44: first_name
                1392    KW_NAMES                        20: ('config', 'account', 'message', 'param')
                1394    CALL                            4
                1402    POP_TOP                         
                1404    LOAD_GLOBAL                     53: NULL + DelayOnline
                1414    LOAD_FAST                       0: account
                1416    LOAD_FAST                       9: _var_var_44
                1418    LOAD_FAST                       11: _var_var_46
                1420    LOAD_FAST                       12: _var_var_47
                1422    LOAD_FAST                       7: stop_thread
                1424    CALL                            5
                1432    POP_TOP                         
                1434    JUMP_FORWARD                    37 (to 1510)
                1436    LOAD_GLOBAL                     9: NULL + Logs
                1446    LOAD_ATTR                       10: PrintLog
                1466    LOAD_FAST                       1: config
                1468    LOAD_FAST                       0: account
                1470    LOAD_GLOBAL                     4: Lang
                1480    PUSH_NULL                       
                1482    LOAD_CONST                      1: '__pyarmor_assert_12915__'
                1484    LOAD_CONST                      33: 'booster_mess_not_send'   # b'\x81\xe0\x17\x1c \xee\xbb\xc0$\xf7\x08\xd3\x7f\xd3\xf6\x8a\x1bb\xa8\xa2\xa4\xcf'
                1486    CALL                            1
                1494    BINARY_SUBSCR                   
                1498    KW_NAMES                        10: ('config', 'account', 'message')
                1500    CALL                            3
                1508    POP_TOP                         
                1510    JUMP_BACKWARD                   370 (to 774)
                1514    END_FOR                         
                1516    LOAD_GLOBAL                     9: NULL + Logs
                1526    LOAD_ATTR                       10: PrintLog
                1546    LOAD_FAST                       1: config
                1548    LOAD_FAST                       0: account
                1550    LOAD_GLOBAL                     4: Lang
                1560    PUSH_NULL                       
                1562    LOAD_CONST                      1: '__pyarmor_assert_12915__'
                1564    LOAD_CONST                      36: 'booster_mode_ansfer_activated'   # b'\x81\xe0\x17\x1c \xee\xbb\xc0$\xf7\x02\xc4i\xd3\xf9\x8b\x1c[\xbe\xb5\x95\xcaM\xd8\x0cy\xa2H\x05\xb5'
                1566    CALL                            1
                1574    BINARY_SUBSCR                   
                1578    KW_NAMES                        10: ('config', 'account', 'message')
                1580    CALL                            3
                1588    POP_TOP                         
                1590    LOAD_FAST                       9: _var_var_44
                1592    LOAD_ATTR                       55: get_dialogs
                1612    CALL                            0
                1620    GET_ITER                        
                1622    FOR_ITER                        427 (to 2480)
                1628    STORE_FAST                      20: _var_var_41
                1630    LOAD_FAST                       7: stop_thread
                1632    LOAD_ATTR                       21: is_set
                1652    CALL                            0
                1660    POP_JUMP_IF_FALSE               10 (to 1682)
                1662    LOAD_GLOBAL                     23: NULL + StopProgram
                1672    CALL                            0
                1680    RAISE_VARARGS                   1
                1682    LOAD_GLOBAL                     33: NULL + hasattr
                1692    LOAD_FAST                       20: _var_var_41
                1694    LOAD_CONST                      37: 'entity'
                1696    CALL                            2
                1704    POP_JUMP_IF_TRUE                1 (to 1708)
                1706    JUMP_BACKWARD                   43 (to 1622)
                1708    LOAD_GLOBAL                     33: NULL + hasattr
                1718    LOAD_FAST                       20: _var_var_41
                1720    LOAD_ATTR                       56: entity
                1740    LOAD_CONST                      38: 'username'
                1742    CALL                            2
                1750    POP_JUMP_IF_TRUE                1 (to 1754)
                1752    JUMP_BACKWARD                   66 (to 1622)
                1754    LOAD_FAST                       20: _var_var_41
                1756    LOAD_ATTR                       56: entity
                1776    LOAD_ATTR                       58: username
                1796    POP_JUMP_IF_NOT_NONE            1 (to 1800)
                1798    JUMP_BACKWARD                   89 (to 1622)
                1800    LOAD_GLOBAL                     27: NULL + str
                1810    LOAD_FAST                       20: _var_var_41
                1812    LOAD_ATTR                       56: entity
                1832    LOAD_ATTR                       58: username
                1852    CALL                            1
                1860    LOAD_FAST                       4: usernames
                1862    CONTAINS_OP                     0 (in)
                1864    POP_JUMP_IF_TRUE                1 (to 1868)
                1866    JUMP_BACKWARD                   123 (to 1622)
                1868    LOAD_FAST                       20: _var_var_41
                1870    LOAD_ATTR                       56: entity
                1890    STORE_FAST                      17: _var_var_52
                1892    NOP                             
                1894    LOAD_GLOBAL                     33: NULL + hasattr
                1904    LOAD_FAST                       17: _var_var_52
                1906    PUSH_NULL                       
                1908    LOAD_CONST                      1: '__pyarmor_assert_12915__'
                1910    LOAD_CONST                      26: 'mutual_contact'   # b'\x81\xef\r\x07&\xfb\xb2\xed\x18\xf5\x03\xd4m\xef\xec'
                1912    CALL                            1
                1920    CALL                            2
                1928    LOAD_CONST                      27: True
                1930    COMPARE_OP                      40 (==)
                1934    POP_JUMP_IF_FALSE               112 (to 2160)
                1936    LOAD_FAST                       17: _var_var_52
                1938    LOAD_ATTR                       34: mutual_contact
                1958    LOAD_CONST                      27: True
                1960    COMPARE_OP                      55 (!=)
                1964    POP_JUMP_IF_FALSE               97 (to 2160)
                1966    LOAD_FAST                       14: _var_var_49
                1968    POP_JUMP_IF_TRUE                95 (to 2160)
                1970    NOP                             
                1972    LOAD_FAST                       17: _var_var_52
                1974    LOAD_ATTR                       36: last_name
                1994    POP_JUMP_IF_NONE                15 (to 2026)
                1996    LOAD_FAST                       17: _var_var_52
                1998    LOAD_ATTR                       36: last_name
                2018    LOAD_CONST                      28: ''
                2020    COMPARE_OP                      40 (==)
                2024    POP_JUMP_IF_FALSE               3 (to 2032)
                2026    LOAD_CONST                      28: ''
                2028    STORE_FAST                      18: _var_var_53
                2030    JUMP_FORWARD                    12 (to 2056)
                2032    LOAD_FAST                       17: _var_var_52
                2034    LOAD_ATTR                       36: last_name
                2054    STORE_FAST                      18: _var_var_53
                2056    PUSH_NULL                       
                2058    LOAD_FAST                       9: _var_var_44
                2060    LOAD_GLOBAL                     38: functions
                2070    LOAD_ATTR                       40: contacts
                2090    LOAD_ATTR                       43: AddContactRequest
                2110    LOAD_FAST                       17: _var_var_52
                2112    LOAD_FAST                       17: _var_var_52
                2114    LOAD_ATTR                       44: first_name
                2134    LOAD_FAST                       18: _var_var_53
                2136    LOAD_CONST                      28: ''
                2138    LOAD_CONST                      27: True
                2140    KW_NAMES                        29: ('id', 'first_name', 'last_name', 'phone', 'add_phone_privacy_exception')
                2142    CALL                            5
                2150    CALL                            1
                2158    POP_TOP                         
                2160    LOAD_GLOBAL                     49: NULL + tg_send_message
                2170    LOAD_FAST                       9: _var_var_44
                2172    LOAD_FAST                       0: account
                2174    LOAD_FAST                       17: _var_var_52
                2176    LOAD_GLOBAL                     27: NULL + str
                2186    LOAD_GLOBAL                     29: NULL + random
                2196    LOAD_ATTR                       30: choice
                2216    LOAD_FAST                       5: messages
                2218    CALL                            1
                2226    CALL                            1
                2234    LOAD_CONST                      31: ' '
                2236    BINARY_OP                       0 (+)
                2240    LOAD_GLOBAL                     51: NULL + get_smile
                2250    CALL                            0
                2258    BINARY_OP                       0 (+)
                2262    LOAD_FAST                       13: _var_var_48
                2264    LOAD_FAST                       7: stop_thread
                2266    CALL                            6
                2274    POP_JUMP_IF_FALSE               64 (to 2404)
                2276    LOAD_GLOBAL                     9: NULL + Logs
                2286    LOAD_ATTR                       10: PrintLog
                2306    LOAD_FAST                       1: config
                2308    LOAD_FAST                       0: account
                2310    LOAD_GLOBAL                     4: Lang
                2320    PUSH_NULL                       
                2322    LOAD_CONST                      1: '__pyarmor_assert_12915__'
                2324    LOAD_CONST                      39: 'booster_ansfer_is_send'   # b'\x81\xe0\x17\x1c \xee\xbb\xc0$\xfb\x03\xd3j\xe9\xea\xba\x06N\x84\xb4\xaf\xc5J'
                2326    CALL                            1
                2334    BINARY_SUBSCR                   
                2338    LOAD_FAST                       17: _var_var_52
                2340    LOAD_ATTR                       44: first_name
                2360    KW_NAMES                        20: ('config', 'account', 'message', 'param')
                2362    CALL                            4
                2370    POP_TOP                         
                2372    LOAD_GLOBAL                     53: NULL + DelayOnline
                2382    LOAD_FAST                       0: account
                2384    LOAD_FAST                       9: _var_var_44
                2386    LOAD_FAST                       11: _var_var_46
                2388    LOAD_FAST                       12: _var_var_47
                2390    LOAD_FAST                       7: stop_thread
                2392    CALL                            5
                2400    POP_TOP                         
                2402    JUMP_FORWARD                    37 (to 2478)
                2404    LOAD_GLOBAL                     9: NULL + Logs
                2414    LOAD_ATTR                       10: PrintLog
                2434    LOAD_FAST                       1: config
                2436    LOAD_FAST                       0: account
                2438    LOAD_GLOBAL                     4: Lang
                2448    PUSH_NULL                       
                2450    LOAD_CONST                      1: '__pyarmor_assert_12915__'
                2452    LOAD_CONST                      40: 'booster_ansfer_is_not_send'   # b'\x81\xe0\x17\x1c \xee\xbb\xc0$\xfb\x03\xd3j\xe9\xea\xba\x06N\x84\xa9\xa5\xdfq\xdf\x00a\xa7'
                2454    CALL                            1
                2462    BINARY_SUBSCR                   
                2466    KW_NAMES                        10: ('config', 'account', 'message')
                2468    CALL                            3
                2476    POP_TOP                         
                2478    JUMP_BACKWARD                   430 (to 1622)
                2482    END_FOR                         
                2484    NOP                             
                2486    LOAD_GLOBAL                     7: NULL + Disconnect
                2496    LOAD_FAST_CHECK                 9: _var_var_44
                2498    CALL                            1
                2506    POP_TOP                         
                2508    LOAD_GLOBAL                     9: NULL + Logs
                2518    LOAD_ATTR                       10: PrintLog
                2538    LOAD_FAST                       1: config
                2540    LOAD_FAST                       0: account
                2542    LOAD_GLOBAL                     4: Lang
                2552    PUSH_NULL                       
                2554    LOAD_CONST                      1: '__pyarmor_assert_12915__'
                2556    LOAD_CONST                      9: 'work_account_completed'   # b'\x81\xf5\x17\x018\xc5\xbf\xd1\x18\xf5\x18\xcex\xd3\xfb\x8a\x02M\xb7\xa2\xbe\xceJ'
                2558    CALL                            1
                2566    BINARY_SUBSCR                   
                2570    KW_NAMES                        10: ('config', 'account', 'message')
                2572    CALL                            3
                2580    POP_TOP                         
                2582    LOAD_FAST                       0: account
                2584    LOAD_CONST                      11: 'done'
                2586    LOAD_CONST                      8: ('account', 'status')
                2588    BUILD_CONST_KEY_MAP             2
                2590    NOP                             
                2592    NOP                             
                2594    JUMP_FORWARD                    448 (to 3494)
                2598    CALL                            1
                2606    POP_TOP                         
                2608    RETURN_VALUE                    
                2610    PUSH_EXC_INFO                   
                2612    POP_TOP                         
                2614    POP_EXCEPT                      
                2616    JUMP_BACKWARD                   1241 (to 138)
                2620    COPY                            3
                2622    POP_EXCEPT                      
                2624    RERAISE                         1
                2626    PUSH_EXC_INFO                   
                2628    LOAD_GLOBAL                     46: Exception
                2638    CHECK_EXC_MATCH                 
                2640    POP_JUMP_IF_FALSE               60 (to 2762)
                2642    STORE_FAST                      19: _var_var_4
                2644    LOAD_GLOBAL                     9: NULL + Logs
                2654    LOAD_ATTR                       10: PrintLog
                2674    LOAD_FAST                       1: config
                2676    LOAD_FAST                       0: account
                2678    LOAD_GLOBAL                     4: Lang
                2688    PUSH_NULL                       
                2690    LOAD_CONST                      1: '__pyarmor_assert_12915__'
                2692    LOAD_CONST                      30: 'booster_error_add_user'   # b'\x81\xe0\x17\x1c \xee\xbb\xc0$\xff\x1f\xd2c\xfe\xc7\x84\x0bY\x84\xb2\xb9\xce\\'
                2694    CALL                            1
                2702    BINARY_SUBSCR                   
                2706    LOAD_FAST                       17: _var_var_52
                2708    LOAD_ATTR                       44: first_name
                2728    LOAD_FAST                       19: _var_var_4
                2730    KW_NAMES                        25: ('config', 'account', 'message', 'param', 'end')
                2732    CALL                            5
                2740    POP_TOP                         
                2742    POP_EXCEPT                      
                2744    LOAD_CONST                      0: None
                2746    STORE_FAST                      19: _var_var_4
                2748    DELETE_FAST                     19: _var_var_4
                2750    JUMP_BACKWARD                   781 (to 1192)
                2754    LOAD_CONST                      0: None
                2756    STORE_FAST                      19: _var_var_4
                2758    DELETE_FAST                     19: _var_var_4
                2760    RERAISE                         1
                2762    RERAISE                         0
                2764    COPY                            3
                2766    POP_EXCEPT                      
                2768    RERAISE                         1
                2770    PUSH_EXC_INFO                   
                2772    LOAD_GLOBAL                     22: StopProgram
                2782    CHECK_EXC_MATCH                 
                2784    POP_JUMP_IF_FALSE               2 (to 2790)
                2786    POP_TOP                         
                2788    RAISE_VARARGS                   0
                2790    LOAD_GLOBAL                     46: Exception
                2800    CHECK_EXC_MATCH                 
                2802    POP_JUMP_IF_FALSE               49 (to 2902)
                2804    STORE_FAST                      19: _var_var_4
                2806    LOAD_GLOBAL                     9: NULL + Logs
                2816    LOAD_ATTR                       10: PrintLog
                2836    LOAD_FAST                       1: config
                2838    LOAD_FAST                       0: account
                2840    LOAD_GLOBAL                     4: Lang
                2850    PUSH_NULL                       
                2852    LOAD_CONST                      1: '__pyarmor_assert_12915__'
                2854    LOAD_CONST                      34: 'booster_cant_send_mess'   # b'\x81\xe0\x17\x1c \xee\xbb\xc0$\xf9\x0c\xcex\xd3\xeb\x80\x01Y\x84\xaa\xaf\xd8]'
                2856    CALL                            1
                2864    BINARY_SUBSCR                   
                2868    LOAD_FAST                       19: _var_var_4
                2870    KW_NAMES                        35: ('config', 'account', 'message', 'end')
                2872    CALL                            4
                2880    POP_TOP                         
                2882    POP_EXCEPT                      
                2884    LOAD_CONST                      0: None
                2886    STORE_FAST                      19: _var_var_4
                2888    DELETE_FAST                     19: _var_var_4
                2890    JUMP_BACKWARD                   1060 (to 774)
                2894    LOAD_CONST                      0: None
                2896    STORE_FAST                      19: _var_var_4
                2898    DELETE_FAST                     19: _var_var_4
                2900    RERAISE                         1
                2902    RERAISE                         0
                2904    COPY                            3
                2906    POP_EXCEPT                      
                2908    RERAISE                         1
                2910    PUSH_EXC_INFO                   
                2912    LOAD_GLOBAL                     46: Exception
                2922    CHECK_EXC_MATCH                 
                2924    POP_JUMP_IF_FALSE               60 (to 3046)
                2926    STORE_FAST                      19: _var_var_4
                2928    LOAD_GLOBAL                     9: NULL + Logs
                2938    LOAD_ATTR                       10: PrintLog
                2958    LOAD_FAST                       1: config
                2960    LOAD_FAST                       0: account
                2962    LOAD_GLOBAL                     4: Lang
                2972    PUSH_NULL                       
                2974    LOAD_CONST                      1: '__pyarmor_assert_12915__'
                2976    LOAD_CONST                      30: 'booster_error_add_user'   # b'\x81\xe0\x17\x1c \xee\xbb\xc0$\xff\x1f\xd2c\xfe\xc7\x84\x0bY\x84\xb2\xb9\xce\\'
                2978    CALL                            1
                2986    BINARY_SUBSCR                   
                2990    LOAD_FAST                       17: _var_var_52
                2992    LOAD_ATTR                       44: first_name
                3012    LOAD_FAST                       19: _var_var_4
                3014    KW_NAMES                        25: ('config', 'account', 'message', 'param', 'end')
                3016    CALL                            5
                3024    POP_TOP                         
                3026    POP_EXCEPT                      
                3028    LOAD_CONST                      0: None
                3030    STORE_FAST                      19: _var_var_4
                3032    DELETE_FAST                     19: _var_var_4
                3034    JUMP_BACKWARD                   439 (to 2160)
                3038    LOAD_CONST                      0: None
                3040    STORE_FAST                      19: _var_var_4
                3042    DELETE_FAST                     19: _var_var_4
                3044    RERAISE                         1
                3046    RERAISE                         0
                3048    COPY                            3
                3050    POP_EXCEPT                      
                3052    RERAISE                         1
                3054    PUSH_EXC_INFO                   
                3056    LOAD_GLOBAL                     22: StopProgram
                3066    CHECK_EXC_MATCH                 
                3068    POP_JUMP_IF_FALSE               2 (to 3074)
                3070    POP_TOP                         
                3072    RAISE_VARARGS                   0
                3074    LOAD_GLOBAL                     46: Exception
                3084    CHECK_EXC_MATCH                 
                3086    POP_JUMP_IF_FALSE               49 (to 3186)
                3088    STORE_FAST                      19: _var_var_4
                3090    LOAD_GLOBAL                     9: NULL + Logs
                3100    LOAD_ATTR                       10: PrintLog
                3120    LOAD_FAST                       1: config
                3122    LOAD_FAST                       0: account
                3124    LOAD_GLOBAL                     4: Lang
                3134    PUSH_NULL                       
                3136    LOAD_CONST                      1: '__pyarmor_assert_12915__'
                3138    LOAD_CONST                      41: 'booster_cant_send_ansfer'   # b'\x81\xe0\x17\x1c \xee\xbb\xc0$\xf9\x0c\xcex\xd3\xeb\x80\x01Y\x84\xa6\xa4\xd8H\xc9\x17'
                3140    CALL                            1
                3148    BINARY_SUBSCR                   
                3152    LOAD_FAST                       19: _var_var_4
                3154    KW_NAMES                        35: ('config', 'account', 'message', 'end')
                3156    CALL                            4
                3164    POP_TOP                         
                3166    POP_EXCEPT                      
                3168    LOAD_CONST                      0: None
                3170    STORE_FAST                      19: _var_var_4
                3172    DELETE_FAST                     19: _var_var_4
                3174    JUMP_BACKWARD                   778 (to 1622)
                3178    LOAD_CONST                      0: None
                3180    STORE_FAST                      19: _var_var_4
                3182    DELETE_FAST                     19: _var_var_4
                3184    RERAISE                         1
                3186    RERAISE                         0
                3188    COPY                            3
                3190    POP_EXCEPT                      
                3192    RERAISE                         1
                3194    PUSH_EXC_INFO                   
                3196    LOAD_GLOBAL                     22: StopProgram
                3206    CHECK_EXC_MATCH                 
                3208    POP_JUMP_IF_FALSE               4 (to 3218)
                3210    POP_TOP                         
                3212    POP_EXCEPT                      
                3214    JUMP_BACKWARD                   366 (to 2486)
                3218    LOAD_GLOBAL                     60: BaseException
                3228    CHECK_EXC_MATCH                 
                3230    POP_JUMP_IF_FALSE               27 (to 3286)
                3232    STORE_FAST                      19: _var_var_4
                3234    PUSH_NULL                       
                3236    LOAD_GLOBAL                     63: NULL + logging
                3246    LOAD_FAST                       19: _var_var_4
                3248    CALL                            1
                3256    CALL                            0
                3264    POP_TOP                         
                3266    POP_EXCEPT                      
                3268    LOAD_CONST                      0: None
                3270    STORE_FAST                      19: _var_var_4
                3272    DELETE_FAST                     19: _var_var_4
                3274    JUMP_BACKWARD                   396 (to 2486)
                3278    LOAD_CONST                      0: None
                3280    STORE_FAST                      19: _var_var_4
                3282    DELETE_FAST                     19: _var_var_4
                3284    RERAISE                         1
                3286    RERAISE                         0
                3288    COPY                            3
                3290    POP_EXCEPT                      
                3292    RERAISE                         1
                3294    PUSH_EXC_INFO                   
                3296    POP_TOP                         
                3298    POP_EXCEPT                      
                3300    JUMP_BACKWARD                   398 (to 2508)
                3304    COPY                            3
                3306    POP_EXCEPT                      
                3308    RERAISE                         1
                3310    PUSH_EXC_INFO                   
                3312    LOAD_GLOBAL                     7: NULL + Disconnect
                3322    LOAD_FAST_CHECK                 9: _var_var_44
                3324    CALL                            1
                3332    POP_TOP                         
                3334    JUMP_FORWARD                    7 (to 3350)
                3336    PUSH_EXC_INFO                   
                3338    POP_TOP                         
                3340    POP_EXCEPT                      
                3342    JUMP_FORWARD                    3 (to 3350)
                3344    COPY                            3
                3346    POP_EXCEPT                      
                3348    RERAISE                         1
                3350    LOAD_GLOBAL                     9: NULL + Logs
                3360    LOAD_ATTR                       10: PrintLog
                3380    LOAD_FAST                       1: config
                3382    LOAD_FAST                       0: account
                3384    LOAD_GLOBAL                     4: Lang
                3394    PUSH_NULL                       
                3396    LOAD_CONST                      1: '__pyarmor_assert_12915__'
                3398    LOAD_CONST                      9: 'work_account_completed'   # b'\x81\xf5\x17\x018\xc5\xbf\xd1\x18\xf5\x18\xcex\xd3\xfb\x8a\x02M\xb7\xa2\xbe\xceJ'
                3400    CALL                            1
                3408    BINARY_SUBSCR                   
                3412    KW_NAMES                        10: ('config', 'account', 'message')
                3414    CALL                            3
                3422    POP_TOP                         
                3424    LOAD_FAST                       0: account
                3426    LOAD_CONST                      11: 'done'
                3428    LOAD_CONST                      8: ('account', 'status')
                3430    BUILD_CONST_KEY_MAP             2
                3432    SWAP                            2
                3434    POP_TOP                         
                3436    SWAP                            2
                3438    POP_EXCEPT                      
                3440    NOP                             
                3442    NOP                             
                3444    NOP                             
                3446    JUMP_FORWARD                    23 (to 3494)
                3448    CALL                            1
                3456    POP_TOP                         
                3458    RETURN_VALUE                    
                3460    COPY                            3
                3462    POP_EXCEPT                      
                3464    RERAISE                         1
                3466    PUSH_EXC_INFO                   
                3468    PUSH_NULL                       
                3470    LOAD_CONST                      12: '__pyarmor_exit_12917__'
                3472    NOP                             
                3474    LOAD_CONST                      3: b'<COAddr>\x07\x00\x00\x1ap\r\x00\x00\x00\x00\x00\x00\x00\x00\x00\x00\x00\x00\x00\x00'
                3476    CALL                            1
                3484    POP_TOP                         
                3486    RERAISE                         0
                3488    COPY                            3
                3490    POP_EXCEPT                      
                3492    RERAISE                         1
                3494    PUSH_NULL                       
                3496    LOAD_CONST                      12: '__pyarmor_exit_12917__'
                3498    LOAD_CONST                      3: b'<COAddr>\x07\x00\x00\x1ap\r\x00\x00\x00\x00\x00\x00\x00\x00\x00\x00\x00\x00\x00\x00'
                3500    BUILD_TUPLE                     1
                3502    CALL_FUNCTION_EX                0
                3504    POP_TOP                         
                3506    RETURN_VALUE                    
            [Exception Table]
                30 to 116 -> 3194 [0] 
                116 to 138 -> 2610 [1] 
                138 to 224 -> 3466 [0] 
                244 to 834 -> 3194 [0] 
                836 to 1002 -> 2770 [1] 
                1004 to 1192 -> 2626 [1] 
                1192 to 1510 -> 2770 [1] 
                1510 to 1706 -> 3194 [0] 
                1708 to 1752 -> 3194 [0] 
                1754 to 1798 -> 3194 [0] 
                1800 to 1866 -> 3194 [0] 
                1868 to 1892 -> 3194 [0] 
                1894 to 1970 -> 3054 [1] 
                1972 to 2160 -> 2910 [1] 
                2160 to 2478 -> 3054 [1] 
                2478 to 2484 -> 3194 [0] 
                2484 to 2486 -> 3310 [0] 
                2486 to 2508 -> 3294 [0] 
                2508 to 2590 -> 3466 [0] 
                2610 to 2614 -> 2620 [2] lasti
                2614 to 2626 -> 3466 [0] 
                2626 to 2644 -> 2764 [2] lasti
                2644 to 2742 -> 2754 [2] lasti
                2742 to 2754 -> 2770 [1] 
                2754 to 2764 -> 2764 [2] lasti
                2764 to 2770 -> 2770 [1] 
                2770 to 2806 -> 2904 [2] lasti
                2806 to 2882 -> 2894 [2] lasti
                2882 to 2894 -> 3194 [0] 
                2894 to 2904 -> 2904 [2] lasti
                2904 to 2910 -> 3194 [0] 
                2910 to 2928 -> 3048 [2] lasti
                2928 to 3026 -> 3038 [2] lasti
                3026 to 3038 -> 3054 [1] 
                3038 to 3048 -> 3048 [2] lasti
                3048 to 3054 -> 3054 [1] 
                3054 to 3090 -> 3188 [2] lasti
                3090 to 3166 -> 3178 [2] lasti
                3166 to 3178 -> 3194 [0] 
                3178 to 3188 -> 3188 [2] lasti
                3188 to 3194 -> 3194 [0] 
                3194 to 3212 -> 3288 [1] lasti
                3212 to 3218 -> 3310 [0] 
                3218 to 3234 -> 3288 [1] lasti
                3234 to 3266 -> 3278 [1] lasti
                3266 to 3278 -> 3310 [0] 
                3278 to 3288 -> 3288 [1] lasti
                3288 to 3294 -> 3310 [0] 
                3294 to 3298 -> 3304 [1] lasti
                3298 to 3310 -> 3466 [0] 
                3310 to 3312 -> 3460 [1] lasti
                3312 to 3334 -> 3336 [2] 
                3334 to 3336 -> 3460 [1] lasti
                3336 to 3340 -> 3344 [3] lasti
                3340 to 3438 -> 3460 [1] lasti
                3438 to 3440 -> 3466 [0] 
                3460 to 3466 -> 3466 [0] 
                3466 to 3488 -> 3488 [1] lasti
        '__pyarmor_exit_12887__'
    [Disassembly]
        0       NOP                             
        2       NOP                             
        4       PUSH_NULL                       
        6       LOAD_CONST                      1: '__pyarmor_enter_12886__'
        8       LOAD_CONST                      2: b'<COAddr>\x05\x00\x00\x1a\xc4\x01\x00\x00\x00\x00\x00\x00\x00\x00\x00\x00\x00\x00\x00\x00'
        10      BUILD_TUPLE                     1
        12      CALL_FUNCTION_EX                0
        14      POP_TOP                         
        16      RESUME                          0
        18      NOP                             
        20      NOP                             
        22      NOP                             
        24      NOP                             
        26      LOAD_CONST                      3: 0
        28      LOAD_CONST                      4: None
        30      IMPORT_NAME                     1: os
        32      STORE_NAME                      1: os
        34      LOAD_CONST                      3: 0
        36      LOAD_CONST                      4: None
        38      IMPORT_NAME                     2: eel
        40      STORE_NAME                      2: eel
        42      LOAD_CONST                      3: 0
        44      LOAD_CONST                      4: None
        46      IMPORT_NAME                     3: json
        48      STORE_NAME                      3: json
        50      LOAD_CONST                      3: 0
        52      LOAD_CONST                      4: None
        54      IMPORT_NAME                     4: random
        56      STORE_NAME                      4: random
        58      LOAD_CONST                      3: 0
        60      LOAD_CONST                      4: None
        62      IMPORT_NAME                     5: concurrent.futures
        64      STORE_NAME                      6: concurrent
        66      LOAD_CONST                      3: 0
        68      LOAD_CONST                      5: ('Thread', 'Event')
        70      IMPORT_NAME                     7: threading
        72      IMPORT_FROM                     8: Thread
        74      STORE_NAME                      8: Thread
        76      IMPORT_FROM                     9: Event
        78      STORE_NAME                      9: Event
        80      POP_TOP                         
        82      LOAD_CONST                      3: 0
        84      LOAD_CONST                      6: ('functions', 'errors')
        86      IMPORT_NAME                     10: multithon.sync
        88      IMPORT_FROM                     11: functions
        90      STORE_NAME                      11: functions
        92      IMPORT_FROM                     12: errors
        94      STORE_NAME                      12: errors
        96      POP_TOP                         
        98      LOAD_CONST                      3: 0
        100     LOAD_CONST                      7: ('StopProgram',)
        102     IMPORT_NAME                     13: multithon.errors
        104     IMPORT_FROM                     14: StopProgram
        106     STORE_NAME                      14: StopProgram
        108     POP_TOP                         
        110     LOAD_CONST                      3: 0
        112     LOAD_CONST                      8: ('AutoStop',)
        114     IMPORT_NAME                     15: program.static_classes
        116     IMPORT_FROM                     16: AutoStop
        118     STORE_NAME                      16: AutoStop
        120     POP_TOP                         
        122     LOAD_CONST                      3: 0
        124     LOAD_CONST                      9: ('GetLang',)
        126     IMPORT_NAME                     15: program.static_classes
        128     IMPORT_FROM                     17: GetLang
        130     STORE_NAME                      17: GetLang
        132     POP_TOP                         
        134     LOAD_CONST                      3: 0
        136     LOAD_CONST                      10: ('Logs',)
        138     IMPORT_NAME                     15: program.static_classes
        140     IMPORT_FROM                     18: Logs
        142     STORE_NAME                      18: Logs
        144     POP_TOP                         
        146     LOAD_CONST                      3: 0
        148     LOAD_CONST                      11: ('check_module',)
        150     IMPORT_NAME                     15: program.static_classes
        152     IMPORT_FROM                     19: check_module
        154     STORE_NAME                      19: check_module
        156     POP_TOP                         
        158     LOAD_CONST                      3: 0
        160     LOAD_CONST                      12: ('logging',)
        162     IMPORT_NAME                     15: program.static_classes
        164     IMPORT_FROM                     20: logging
        166     STORE_NAME                      20: logging
        168     POP_TOP                         
        170     LOAD_CONST                      3: 0
        172     LOAD_CONST                      13: ('memory_check_switcher',)
        174     IMPORT_NAME                     15: program.static_classes
        176     IMPORT_FROM                     21: memory_check_switcher
        178     STORE_NAME                      21: memory_check_switcher
        180     POP_TOP                         
        182     LOAD_CONST                      3: 0
        184     LOAD_CONST                      14: ('memory_set_pid',)
        186     IMPORT_NAME                     15: program.static_classes
        188     IMPORT_FROM                     22: memory_set_pid
        190     STORE_NAME                      22: memory_set_pid
        192     POP_TOP                         
        194     LOAD_CONST                      3: 0
        196     LOAD_CONST                      15: ('DelayOnline',)
        198     IMPORT_NAME                     23: program.telegram
        200     IMPORT_FROM                     24: DelayOnline
        202     STORE_NAME                      24: DelayOnline
        204     POP_TOP                         
        206     LOAD_CONST                      3: 0
        208     LOAD_CONST                      16: ('Disconnect',)
        210     IMPORT_NAME                     23: program.telegram
        212     IMPORT_FROM                     25: Disconnect
        214     STORE_NAME                      25: Disconnect
        216     POP_TOP                         
        218     LOAD_CONST                      3: 0
        220     LOAD_CONST                      17: ('Restart_wait',)
        222     IMPORT_NAME                     23: program.telegram
        224     IMPORT_FROM                     26: Restart_wait
        226     STORE_NAME                      26: Restart_wait
        228     POP_TOP                         
        230     LOAD_CONST                      3: 0
        232     LOAD_CONST                      18: ('Thread_wait',)
        234     IMPORT_NAME                     23: program.telegram
        236     IMPORT_FROM                     27: Thread_wait
        238     STORE_NAME                      27: Thread_wait
        240     POP_TOP                         
        242     LOAD_CONST                      3: 0
        244     LOAD_CONST                      19: ('account_works',)
        246     IMPORT_NAME                     23: program.telegram
        248     IMPORT_FROM                     28: account_works
        250     STORE_NAME                      28: account_works
        252     POP_TOP                         
        254     LOAD_CONST                      3: 0
        256     LOAD_CONST                      20: ('get_account_json',)
        258     IMPORT_NAME                     23: program.telegram
        260     IMPORT_FROM                     29: get_account_json
        262     STORE_NAME                      29: get_account_json
        264     POP_TOP                         
        266     LOAD_CONST                      3: 0
        268     LOAD_CONST                      21: ('GetConfig',)
        270     IMPORT_NAME                     30: program.general
        272     IMPORT_FROM                     31: GetConfig
        274     STORE_NAME                      31: GetConfig
        276     POP_TOP                         
        278     LOAD_CONST                      3: 0
        280     LOAD_CONST                      22: ('GetFileTXT',)
        282     IMPORT_NAME                     30: program.general
        284     IMPORT_FROM                     32: GetFileTXT
        286     STORE_NAME                      32: GetFileTXT
        288     POP_TOP                         
        290     LOAD_CONST                      3: 0
        292     LOAD_CONST                      23: ('GetProxy',)
        294     IMPORT_NAME                     30: program.general
        296     IMPORT_FROM                     33: GetProxy
        298     STORE_NAME                      33: GetProxy
        300     POP_TOP                         
        302     LOAD_CONST                      3: 0
        304     LOAD_CONST                      24: ('StopDetect',)
        306     IMPORT_NAME                     30: program.general
        308     IMPORT_FROM                     34: StopDetect
        310     STORE_NAME                      34: StopDetect
        312     POP_TOP                         
        314     LOAD_CONST                      3: 0
        316     LOAD_CONST                      25: ('check_get_settings',)
        318     IMPORT_NAME                     30: program.general
        320     IMPORT_FROM                     35: check_get_settings
        322     STORE_NAME                      35: check_get_settings
        324     POP_TOP                         
        326     LOAD_CONST                      3: 0
        328     LOAD_CONST                      26: ('del_task_manager',)
        330     IMPORT_NAME                     30: program.general
        332     IMPORT_FROM                     36: del_task_manager
        334     STORE_NAME                      36: del_task_manager
        336     POP_TOP                         
        338     LOAD_CONST                      3: 0
        340     LOAD_CONST                      27: ('getFile',)
        342     IMPORT_NAME                     30: program.general
        344     IMPORT_FROM                     37: getFile
        346     STORE_NAME                      37: getFile
        348     POP_TOP                         
        350     LOAD_CONST                      3: 0
        352     LOAD_CONST                      28: ('set_task_manager',)
        354     IMPORT_NAME                     30: program.general
        356     IMPORT_FROM                     38: set_task_manager
        358     STORE_NAME                      38: set_task_manager
        360     POP_TOP                         
        362     LOAD_CONST                      29: <CODE> getFile
        364     MAKE_FUNCTION                   0
        366     STORE_NAME                      37: getFile
        368     LOAD_CONST                      30: <CODE> account_booster
        370     MAKE_FUNCTION                   0
        372     STORE_NAME                      39: account_booster
        374     LOAD_CONST                      31: <CODE> START
        376     MAKE_FUNCTION                   0
        378     STORE_NAME                      40: START
        380     LOAD_CONST                      32: <CODE> json_get_usernames
        382     MAKE_FUNCTION                   0
        384     STORE_NAME                      41: json_get_usernames
        386     LOAD_CONST                      33: 'return'
        388     LOAD_NAME                       42: bool
        390     LOAD_NAME                       43: list
        392     BINARY_OP                       7 (|)
        396     BUILD_TUPLE                     2
        398     LOAD_CONST                      34: <CODE> get_random_array_file
        400     MAKE_FUNCTION                   4
        402     STORE_NAME                      44: get_random_array_file
        404     LOAD_CONST                      33: 'return'
        406     LOAD_NAME                       45: str
        408     BUILD_TUPLE                     2
        410     LOAD_CONST                      35: <CODE> get_smile
        412     MAKE_FUNCTION                   4
        414     STORE_NAME                      46: get_smile
        416     LOAD_CONST                      33: 'return'
        418     LOAD_NAME                       47: int
        420     BUILD_TUPLE                     2
        422     LOAD_CONST                      36: <CODE> mark_mess_read
        424     MAKE_FUNCTION                   4
        426     STORE_NAME                      48: mark_mess_read
        428     LOAD_CONST                      33: 'return'
        430     LOAD_NAME                       45: str
        432     BUILD_TUPLE                     2
        434     LOAD_CONST                      37: <CODE> get_username_hash
        436     MAKE_FUNCTION                   4
        438     STORE_NAME                      49: get_username_hash
        440     LOAD_CONST                      33: 'return'
        442     LOAD_NAME                       42: bool
        444     BUILD_TUPLE                     2
        446     LOAD_CONST                      38: <CODE> tg_send_message
        448     MAKE_FUNCTION                   4
        450     STORE_NAME                      50: tg_send_message
        452     LOAD_CONST                      39: <CODE> Booster
        454     MAKE_FUNCTION                   0
        456     STORE_NAME                      51: Booster
        458     LOAD_CONST                      4: None
        460     NOP                             
        462     NOP                             
        464     NOP                             
        466     JUMP_FORWARD                    19 (to 506)
        474     POP_TOP                         
        476     RETURN_CONST                    4: None
        478     PUSH_EXC_INFO                   
        480     PUSH_NULL                       
        482     LOAD_CONST                      40: '__pyarmor_exit_12887__'
        484     NOP                             
        486     LOAD_CONST                      2: b'<COAddr>\x05\x00\x00\x1a\xc4\x01\x00\x00\x00\x00\x00\x00\x00\x00\x00\x00\x00\x00\x00\x00'
        488     CALL                            1
        496     POP_TOP                         
        498     RERAISE                         0
        500     COPY                            3
        502     POP_EXCEPT                      
        504     RERAISE                         1
        506     PUSH_NULL                       
        508     LOAD_CONST                      40: '__pyarmor_exit_12887__'
        510     LOAD_CONST                      2: b'<COAddr>\x05\x00\x00\x1a\xc4\x01\x00\x00\x00\x00\x00\x00\x00\x00\x00\x00\x00\x00\x00\x00'
        512     BUILD_TUPLE                     1
        514     CALL_FUNCTION_EX                0
        516     POP_TOP                         
        518     RETURN_VALUE                    
    [Exception Table]
        26 to 458 -> 478 [0] 
        478 to 500 -> 500 [1] lasti
