#decoded by lolz.live/mrpenny / t.me/zeus_jackpot
# ================================
# Примечания по Pyarmor:
# - Байт-код и объекты кода Pyarmor соответствуют стандартному Python, но присутствуют специальные вызовы функций среды выполнения (runtime) Pyarmor.
# - Вызовы строк — это не ошибки, а маркеры, которые обрабатываются Pyarmor во время выполнения.
#
# Руководство по декомпиляции (без среды выполнения):
# 1. Игнорируйте зашифрованные байты после `#`; используйте только строку до `#`.
# 2. Удалите "__pyarmor_enter_xxx__"(b"<COAddr>...") и "__pyarmor_leave_xxx__"(b"<COAddr>...") (пролог/эпилог).
# 3. "__pyarmor_assert_xxx__"(A) не является настоящим оператором assert.
#    - Если A — это имя или читаемая строка: замените на A.
#    - Если A — это (X, "Y"): замените на X.Y.
#    - Если A — это (X, "Y", Z): замените на X.Y = Z.
#    - В противном случае: выберите наиболее подходящую/логичную замену.
# 4. "__pyarmor_bcc_xxx__"(...) указывает на машинный (нативный) код; тело функции недоступно. Добавьте комментарий.
# ================================

[Code]
    File Name: <frozen program.modules.accounts_check>
    Object Name: <module>
    Qualified Name: <module>
    Arg Count: 0
    Pos Only Arg Count: 0
    KW Only Arg Count: 0
    Stack Size: 5
    Flags: 0x20000000 (CO_PYARMOR_OBFUSCATED)
    [Names]
        '__assert_armored__'
        'os'
        're'
        'eel'
        'time'
        'json'
        'asyncio'
        'concurrent.futures'
        'concurrent'
        'threading'
        'Thread'
        'Event'
        'multithon.sync'
        'TelegramClient'
        'functions'
        'errors'
        'pathlib'
        'Path'
        'multithon.errors'
        'StopProgram'
        'program.static_classes'
        'GetLang'
        'Logs'
        'VersionControl'
        'get_logger'
        'logging'
        'memory_check_switcher'
        'memory_set_pid'
        'proxy_hide'
        'program.telegram'
        'Disconnect'
        'Thread_wait'
        'get_account_json'
        'get_account_proxy'
        'set_account_json'
        'program.general'
        'GetConfig'
        'GetProxy'
        'StopDetect'
        'check_get_settings'
        'accounts_check'
        'START'
        'worker'
        'move_acc_to_folder'
    [Locals+Names]
    [Constants]
        '__pyarmor_assert_12765__'
        '__pyarmor_enter_12766__'
        b'<COAddr>\x05\x00\x00\x1al\x01\x00\x00\x00\x00\x00\x00\x00\x00\x00\x00\x00\x00\x00\x00'
        0
        None
        (
            'Thread'
            'Event'
        )
        (
            'TelegramClient'
            'functions'
            'errors'
        )
        (
            'Path'
        )
        (
            'StopProgram'
        )
        (
            'GetLang'
        )
        (
            'Logs'
        )
        (
            'VersionControl'
        )
        (
            'get_logger'
        )
        (
            'logging'
        )
        (
            'memory_check_switcher'
        )
        (
            'memory_set_pid'
        )
        (
            'proxy_hide'
        )
        (
            'Disconnect'
        )
        (
            'Thread_wait'
        )
        (
            'get_account_json'
        )
        (
            'get_account_proxy'
        )
        (
            'set_account_json'
        )
        (
            'GetConfig'
        )
        (
            'GetProxy'
        )
        (
            'StopDetect'
        )
        (
            'check_get_settings'
        )
        [Code]
            File Name: <frozen program.modules.accounts_check>
            Object Name: accounts_check
            Qualified Name: accounts_check
            Arg Count: 1
            Pos Only Arg Count: 0
            KW Only Arg Count: 0
            Stack Size: 8
            Flags: 0x20000003 (CO_OPTIMIZED | CO_NEWLOCALS | CO_PYARMOR_OBFUSCATED)
            [Names]
                'GetConfig'
                'config'
                'GetLang'
                'Lang'
                'GetProxy'
                'eel'
                'sendSuccessBox'
                'memory_check_switcher'
                'Event'
                'memory_set_pid'
                'Thread'
                'START'
                'start'
                'Logs'
                'WaitStopAnsfer'
                'UpdateLogInWindow'
                'BaseException'
                'logging'
            [Locals+Names]
                'data'
                '__assert_armored__'
                '_var_var_0'
                '_var_var_1'
                '_var_var_2'
                '_var_var_3'
            [Constants]
                None
                '__pyarmor_assert_12768__'
                '__pyarmor_enter_12769__'
                b'<COAddr>\x07\x00\x00\x1aT\x02\x00\x00\x00\x00\x00\x00\x00\x00\x00\x00\x00\x00\x00\x00'
                'program_running'   # b'\x81\xf2\n\x1c4\xe8\xbf\xdf$\xe8\x18\xceb\xe5\xf6\x82'
                '__pyarmor_exit_12770__'
                False
                (
                    'target'
                    'args'
                )
                True
                (
                    'target'
                    'args'
                    'daemon'
                )
            [Disassembly]
                0       NOP                             
                2       NOP                             
                4       PUSH_NULL                       
                6       LOAD_CONST                      2: '__pyarmor_enter_12769__'
                8       LOAD_CONST                      3: b'<COAddr>\x07\x00\x00\x1aT\x02\x00\x00\x00\x00\x00\x00\x00\x00\x00\x00\x00\x00\x00\x00'
                10      BUILD_TUPLE                     1
                12      CALL_FUNCTION_EX                0
                14      POP_TOP                         
                16      RESUME                          0
                18      NOP                             
                20      NOP                             
                22      NOP                             
                24      NOP                             
                26      NOP                             
                28      NOP                             
                30      LOAD_GLOBAL                     1: NULL + GetConfig
                40      CALL                            0
                48      STORE_GLOBAL                    1: config
                50      LOAD_GLOBAL                     5: NULL + GetLang
                60      LOAD_GLOBAL                     2: config
                70      CALL                            1
                78      STORE_GLOBAL                    3: Lang
                80      LOAD_GLOBAL                     9: NULL + GetProxy
                90      CALL                            0
                98      STORE_FAST                      2: _var_var_0
                100     LOAD_GLOBAL                     11: NULL + eel
                110     LOAD_ATTR                       12: sendSuccessBox
                130     LOAD_GLOBAL                     6: Lang
                140     PUSH_NULL                       
                142     LOAD_CONST                      1: '__pyarmor_assert_12768__'
                144     LOAD_CONST                      4: 'program_running'   # b'\x81\xf2\n\x1c4\xe8\xbf\xdf$\xe8\x18\xceb\xe5\xf6\x82'
                146     CALL                            1
                154     BINARY_SUBSCR                   
                158     CALL                            1
                166     POP_TOP                         
                168     LOAD_GLOBAL                     15: NULL + memory_check_switcher
                178     CALL                            0
                186     POP_JUMP_IF_TRUE                11 (to 210)
                188     NOP                             
                190     LOAD_CONST                      6: False
                192     NOP                             
                194     NOP                             
                196     NOP                             
                198     JUMP_FORWARD                    225 (to 650)
                206     POP_TOP                         
                208     RETURN_CONST                    6: False
                210     LOAD_GLOBAL                     17: NULL + Event
                220     CALL                            0
                228     STORE_FAST                      3: _var_var_1
                230     LOAD_GLOBAL                     19: NULL + memory_set_pid
                240     CALL                            0
                248     STORE_FAST                      4: _var_var_2
                250     LOAD_GLOBAL                     21: NULL + Thread
                260     LOAD_GLOBAL                     22: START
                270     LOAD_FAST                       0: data
                272     LOAD_GLOBAL                     2: config
                282     LOAD_FAST                       4: _var_var_2
                284     LOAD_FAST                       2: _var_var_0
                286     LOAD_FAST                       3: _var_var_1
                288     BUILD_TUPLE                     5
                290     KW_NAMES                        7: ('target', 'args')
                292     CALL                            2
                300     LOAD_ATTR                       25: start
                320     CALL                            0
                328     POP_TOP                         
                330     LOAD_GLOBAL                     21: NULL + Thread
                340     LOAD_GLOBAL                     26: Logs
                350     LOAD_ATTR                       28: WaitStopAnsfer
                370     LOAD_GLOBAL                     2: config
                380     LOAD_FAST                       4: _var_var_2
                382     LOAD_FAST                       3: _var_var_1
                384     BUILD_TUPLE                     3
                386     LOAD_CONST                      8: True
                388     KW_NAMES                        9: ('target', 'args', 'daemon')
                390     CALL                            3
                398     LOAD_ATTR                       25: start
                418     CALL                            0
                426     POP_TOP                         
                428     LOAD_GLOBAL                     21: NULL + Thread
                438     LOAD_GLOBAL                     26: Logs
                448     LOAD_ATTR                       30: UpdateLogInWindow
                468     LOAD_GLOBAL                     2: config
                478     LOAD_FAST                       4: _var_var_2
                480     LOAD_FAST                       3: _var_var_1
                482     BUILD_TUPLE                     3
                484     LOAD_CONST                      8: True
                486     KW_NAMES                        9: ('target', 'args', 'daemon')
                488     CALL                            3
                496     LOAD_ATTR                       25: start
                516     CALL                            0
                524     POP_TOP                         
                526     LOAD_CONST                      0: None
                528     NOP                             
                530     NOP                             
                532     NOP                             
                534     JUMP_FORWARD                    57 (to 650)
                542     POP_TOP                         
                544     RETURN_CONST                    0: None
                546     PUSH_EXC_INFO                   
                548     LOAD_GLOBAL                     32: BaseException
                558     CHECK_EXC_MATCH                 
                560     POP_JUMP_IF_FALSE               26 (to 614)
                562     STORE_FAST                      5: _var_var_3
                564     PUSH_NULL                       
                566     LOAD_GLOBAL                     35: NULL + logging
                576     LOAD_FAST                       5: _var_var_3
                578     CALL                            1
                586     CALL                            0
                594     POP_TOP                         
                596     POP_EXCEPT                      
                598     LOAD_CONST                      0: None
                600     STORE_FAST                      5: _var_var_3
                602     DELETE_FAST                     5: _var_var_3
                604     JUMP_BACKWARD                   40 (to 526)
                606     LOAD_CONST                      0: None
                608     STORE_FAST                      5: _var_var_3
                610     DELETE_FAST                     5: _var_var_3
                612     RERAISE                         1
                614     RERAISE                         0
                616     COPY                            3
                618     POP_EXCEPT                      
                620     RERAISE                         1
                622     PUSH_EXC_INFO                   
                624     PUSH_NULL                       
                626     LOAD_CONST                      5: '__pyarmor_exit_12770__'
                628     NOP                             
                630     LOAD_CONST                      3: b'<COAddr>\x07\x00\x00\x1aT\x02\x00\x00\x00\x00\x00\x00\x00\x00\x00\x00\x00\x00\x00\x00'
                632     CALL                            1
                640     POP_TOP                         
                642     RERAISE                         0
                644     COPY                            3
                646     POP_EXCEPT                      
                648     RERAISE                         1
                650     PUSH_NULL                       
                652     LOAD_CONST                      5: '__pyarmor_exit_12770__'
                654     LOAD_CONST                      3: b'<COAddr>\x07\x00\x00\x1aT\x02\x00\x00\x00\x00\x00\x00\x00\x00\x00\x00\x00\x00\x00\x00'
                656     BUILD_TUPLE                     1
                658     CALL_FUNCTION_EX                0
                660     POP_TOP                         
                662     RETURN_VALUE                    
            [Exception Table]
                30 to 188 -> 546 [0] 
                210 to 526 -> 546 [0] 
                546 to 564 -> 616 [1] lasti
                564 to 596 -> 606 [1] lasti
                596 to 606 -> 622 [0] 
                606 to 616 -> 616 [1] lasti
                616 to 622 -> 622 [0] 
                622 to 644 -> 644 [1] lasti
        [Code]
            File Name: <frozen program.modules.accounts_check>
            Object Name: START
            Qualified Name: START
            Arg Count: 5
            Pos Only Arg Count: 0
            KW Only Arg Count: 0
            Stack Size: 14
            Flags: 0x20000003 (CO_OPTIMIZED | CO_NEWLOCALS | CO_PYARMOR_OBFUSCATED)
            [Names]
                'is_set'
                'StopProgram'
                'check_get_settings'
                'get'
                'os'
                'listdir'
                'path'
                'exists'
                'replace'
                'append'
                'isinstance'
                'list'
                'int'
                'len'
                'eel'
                'sendErrorBox'
                'Lang'
                'Logs'
                'LangCheck'
                'concurrent'
                'futures'
                'ThreadPoolExecutor'
                'StreamStat'
                'json'
                'dumps'
                'submit'
                'worker'
                'as_completed'
                'BaseException'
                'logging'
                'StopDetect'
            [Locals+Names]
                'data'
                'config'
                'pid'
                'proxy'
                'stop_thread'
                '__assert_armored__'
                '_var_var_4'
                '_var_var_5'
                '_var_var_6'
                '_var_var_7'
                '_var_var_8'
                '_var_var_9'
                '_var_var_10'
                '_var_var_11'
                '_var_var_12'
                '_var_var_13'
                '_var_var_14'
                '_var_var_3'
            [Constants]
                None
                '__pyarmor_assert_12771__'
                '__pyarmor_enter_12772__'
                b'<COAddr>\x05\x00\x00\x1a\x04\x06\x00\x00\x00\x00\x00\x00\x00\x00\x00\x00\x00\x00\x00\x00'
                'Settings'
                'accounts_choose_all'   # b'\x81\xe3\x1b\x10<\xef\xb0\xc6\x08\xc5\x0e\xc8c\xe3\xeb\x800\\\xb7\xab'
                'sessions/active'   # b'\x81\xf1\x1d\x00 \xf3\xb1\xdc\x08\xb5\x0c\xc3x\xe5\xee\x80'
                '.json'
                'sessions/active//'   # b'\x81\xf1\x1d\x00 \xf3\xb1\xdc\x08\xb5\x0c\xc3x\xe5\xee\x80@\x12'
                '.session'
                ''
                'Accounts'
                1
                'select_accounts_works'   # b'\x81\xf1\x1d\x1f6\xf9\xaa\xed\x1a\xf9\x0e\xcfy\xe2\xec\x960J\xb4\xb5\xa1\xd8'
                'thread_rules'   # b'\x81\xf6\x10\x016\xfb\xba\xed\t\xef\x01\xc5\x7f'
                True
                'thread_count'   # b'\x81\xf6\x10\x016\xfb\xba\xed\x18\xf5\x18\xcex'
                (
                    'max_workers'
                )
                0
                'st_task'
                'st_stream'   # b'\x81\xf1\x0c, \xee\xac\xd7\x1a\xf7'
                'st_wait'
                'st_done'
                '__pyarmor_exit_12773__'
                'Done'
            [Disassembly]
                0       NOP                             
                2       NOP                             
                4       PUSH_NULL                       
                6       LOAD_CONST                      2: '__pyarmor_enter_12772__'
                8       LOAD_CONST                      3: b'<COAddr>\x05\x00\x00\x1a\x04\x06\x00\x00\x00\x00\x00\x00\x00\x00\x00\x00\x00\x00\x00\x00'
                10      BUILD_TUPLE                     1
                12      CALL_FUNCTION_EX                0
                14      POP_TOP                         
                16      RESUME                          0
                18      NOP                             
                20      NOP                             
                22      NOP                             
                24      NOP                             
                26      NOP                             
                28      NOP                             
                30      LOAD_FAST                       4: stop_thread
                32      LOAD_ATTR                       1: is_set
                52      CALL                            0
                60      POP_JUMP_IF_FALSE               10 (to 82)
                62      LOAD_GLOBAL                     3: NULL + StopProgram
                72      CALL                            0
                80      RAISE_VARARGS                   1
                82      LOAD_GLOBAL                     5: NULL + check_get_settings
                92      LOAD_FAST                       0: data
                94      LOAD_ATTR                       7: get
                114     LOAD_CONST                      4: 'Settings'
                116     CALL                            1
                124     CALL                            1
                132     POP_TOP                         
                134     LOAD_FAST                       0: data
                136     LOAD_CONST                      4: 'Settings'
                138     BINARY_SUBSCR                   
                142     LOAD_ATTR                       7: get
                162     PUSH_NULL                       
                164     LOAD_CONST                      1: '__pyarmor_assert_12771__'
                166     LOAD_CONST                      5: 'accounts_choose_all'   # b'\x81\xe3\x1b\x10<\xef\xb0\xc6\x08\xc5\x0e\xc8c\xe3\xeb\x800\\\xb7\xab'
                168     CALL                            1
                176     CALL                            1
                184     POP_JUMP_IF_FALSE               130 (to 446)
                186     BUILD_LIST                      0
                188     STORE_FAST                      6: _var_var_4
                190     LOAD_GLOBAL                     9: NULL + os
                200     LOAD_ATTR                       10: listdir
                220     PUSH_NULL                       
                222     LOAD_CONST                      1: '__pyarmor_assert_12771__'
                224     LOAD_CONST                      6: 'sessions/active'   # b'\x81\xf1\x1d\x00 \xf3\xb1\xdc\x08\xb5\x0c\xc3x\xe5\xee\x80'
                226     CALL                            1
                234     CALL                            1
                242     GET_ITER                        
                244     FOR_ITER                        97 (to 440)
                248     STORE_FAST                      7: _var_var_5
                250     LOAD_CONST                      7: '.json'
                252     LOAD_FAST                       7: _var_var_5
                254     CONTAINS_OP                     0 (in)
                256     POP_JUMP_IF_TRUE                1 (to 260)
                258     JUMP_BACKWARD                   8 (to 244)
                260     LOAD_GLOBAL                     8: os
                270     LOAD_ATTR                       12: path
                290     LOAD_ATTR                       15: exists
                310     PUSH_NULL                       
                312     LOAD_CONST                      1: '__pyarmor_assert_12771__'
                314     LOAD_CONST                      8: 'sessions/active//'   # b'\x81\xf1\x1d\x00 \xf3\xb1\xdc\x08\xb5\x0c\xc3x\xe5\xee\x80@\x12'
                316     CALL                            1
                324     LOAD_FAST                       7: _var_var_5
                326     LOAD_ATTR                       17: replace
                346     LOAD_CONST                      7: '.json'
                348     LOAD_CONST                      9: '.session'
                350     CALL                            2
                358     FORMAT_VALUE                    0 (FVC_NONE)
                360     BUILD_STRING                    2
                362     CALL                            1
                370     POP_JUMP_IF_TRUE                1 (to 374)
                372     JUMP_BACKWARD                   65 (to 244)
                374     LOAD_FAST                       6: _var_var_4
                376     LOAD_ATTR                       19: append
                396     LOAD_FAST                       7: _var_var_5
                398     LOAD_ATTR                       17: replace
                418     LOAD_CONST                      7: '.json'
                420     LOAD_CONST                      10: ''
                422     CALL                            2
                430     CALL                            1
                438     POP_TOP                         
                440     JUMP_BACKWARD                   99 (to 244)
                442     END_FOR                         
                444     JUMP_FORWARD                    24 (to 494)
                446     LOAD_FAST                       0: data
                448     LOAD_CONST                      11: 'Accounts'
                450     BINARY_SUBSCR                   
                454     STORE_FAST                      6: _var_var_4
                456     LOAD_GLOBAL                     21: NULL + isinstance
                466     LOAD_FAST                       6: _var_var_4
                468     LOAD_GLOBAL                     22: list
                478     CALL                            2
                486     POP_JUMP_IF_TRUE                3 (to 494)
                488     LOAD_FAST                       6: _var_var_4
                490     BUILD_LIST                      1
                492     STORE_FAST                      6: _var_var_4
                494     LOAD_GLOBAL                     25: NULL + int
                504     LOAD_GLOBAL                     27: NULL + len
                514     LOAD_FAST                       6: _var_var_4
                516     CALL                            1
                524     CALL                            1
                532     LOAD_CONST                      12: 1
                534     COMPARE_OP                      2 (<)
                538     POP_JUMP_IF_FALSE               44 (to 628)
                540     LOAD_GLOBAL                     29: NULL + eel
                550     LOAD_ATTR                       30: sendErrorBox
                570     LOAD_GLOBAL                     32: Lang
                580     PUSH_NULL                       
                582     LOAD_CONST                      1: '__pyarmor_assert_12771__'
                584     LOAD_CONST                      13: 'select_accounts_works'   # b'\x81\xf1\x1d\x1f6\xf9\xaa\xed\x1a\xf9\x0e\xcfy\xe2\xec\x960J\xb4\xb5\xa1\xd8'
                586     CALL                            1
                594     BINARY_SUBSCR                   
                598     CALL                            1
                606     POP_TOP                         
                608     LOAD_GLOBAL                     3: NULL + StopProgram
                618     CALL                            0
                626     RAISE_VARARGS                   1
                628     LOAD_FAST                       0: data
                630     LOAD_CONST                      4: 'Settings'
                632     BINARY_SUBSCR                   
                636     LOAD_ATTR                       7: get
                656     PUSH_NULL                       
                658     LOAD_CONST                      1: '__pyarmor_assert_12771__'
                660     LOAD_CONST                      14: 'thread_rules'   # b'\x81\xf6\x10\x016\xfb\xba\xed\t\xef\x01\xc5\x7f'
                662     CALL                            1
                670     CALL                            1
                678     LOAD_CONST                      15: True
                680     COMPARE_OP                      40 (==)
                684     POP_JUMP_IF_FALSE               36 (to 758)
                686     LOAD_GLOBAL                     25: NULL + int
                696     LOAD_FAST                       0: data
                698     LOAD_CONST                      4: 'Settings'
                700     BINARY_SUBSCR                   
                704     LOAD_ATTR                       7: get
                724     PUSH_NULL                       
                726     LOAD_CONST                      1: '__pyarmor_assert_12771__'
                728     LOAD_CONST                      16: 'thread_count'   # b'\x81\xf6\x10\x016\xfb\xba\xed\x18\xf5\x18\xcex'
                730     CALL                            1
                738     CALL                            1
                746     CALL                            1
                754     STORE_FAST                      8: _var_var_6
                756     JUMP_FORWARD                    11 (to 780)
                758     LOAD_FAST                       1: config
                760     PUSH_NULL                       
                762     LOAD_CONST                      1: '__pyarmor_assert_12771__'
                764     LOAD_CONST                      16: 'thread_count'   # b'\x81\xf6\x10\x016\xfb\xba\xed\x18\xf5\x18\xcex'
                766     CALL                            1
                774     BINARY_SUBSCR                   
                778     STORE_FAST                      8: _var_var_6
                780     LOAD_GLOBAL                     35: NULL + Logs
                790     LOAD_ATTR                       36: LangCheck
                810     CALL                            0
                818     POP_TOP                         
                820     LOAD_GLOBAL                     38: concurrent
                830     LOAD_ATTR                       40: futures
                850     LOAD_ATTR                       43: ThreadPoolExecutor
                870     LOAD_FAST                       8: _var_var_6
                872     KW_NAMES                        17: ('max_workers',)
                874     CALL                            1
                882     BEFORE_WITH                     
                884     STORE_FAST                      9: _var_var_7
                886     BUILD_LIST                      0
                888     STORE_FAST                      10: _var_var_8
                890     LOAD_GLOBAL                     27: NULL + len
                900     LOAD_FAST                       6: _var_var_4
                902     CALL                            1
                910     STORE_FAST                      11: _var_var_9
                912     LOAD_FAST                       8: _var_var_6
                914     STORE_FAST                      12: _var_var_10
                916     LOAD_FAST                       11: _var_var_9
                918     STORE_FAST                      13: _var_var_11
                920     LOAD_CONST                      18: 0
                922     STORE_FAST                      14: _var_var_12
                924     LOAD_GLOBAL                     29: NULL + eel
                934     LOAD_ATTR                       44: StreamStat
                954     LOAD_GLOBAL                     47: NULL + json
                964     LOAD_ATTR                       48: dumps
                984     LOAD_CONST                      19: 'st_task'
                986     LOAD_FAST                       11: _var_var_9
                988     PUSH_NULL                       
                990     LOAD_CONST                      1: '__pyarmor_assert_12771__'
                992     LOAD_CONST                      20: 'st_stream'   # b'\x81\xf1\x0c, \xee\xac\xd7\x1a\xf7'
                994     CALL                            1
                1002    LOAD_FAST                       12: _var_var_10
                1004    LOAD_CONST                      21: 'st_wait'
                1006    LOAD_FAST                       13: _var_var_11
                1008    LOAD_CONST                      22: 'st_done'
                1010    LOAD_FAST                       14: _var_var_12
                1012    BUILD_MAP                       4
                1014    CALL                            1
                1022    CALL                            1
                1030    POP_TOP                         
                1032    LOAD_FAST                       6: _var_var_4
                1034    GET_ITER                        
                1036    FOR_ITER                        44 (to 1126)
                1040    STORE_FAST                      15: _var_var_13
                1042    LOAD_FAST                       10: _var_var_8
                1044    LOAD_ATTR                       19: append
                1064    LOAD_FAST                       9: _var_var_7
                1066    LOAD_ATTR                       51: submit
                1086    LOAD_GLOBAL                     52: worker
                1096    LOAD_FAST                       15: _var_var_13
                1098    LOAD_FAST                       1: config
                1100    LOAD_FAST                       3: proxy
                1102    LOAD_FAST                       0: data
                1104    LOAD_CONST                      18: 0
                1106    LOAD_FAST                       4: stop_thread
                1108    CALL                            7
                1116    CALL                            1
                1124    POP_TOP                         
                1126    JUMP_BACKWARD                   46 (to 1036)
                1128    END_FOR                         
                1130    LOAD_GLOBAL                     38: concurrent
                1140    LOAD_ATTR                       40: futures
                1160    LOAD_ATTR                       55: as_completed
                1180    LOAD_FAST                       10: _var_var_8
                1182    CALL                            1
                1190    GET_ITER                        
                1192    FOR_ITER                        66 (to 1326)
                1196    STORE_FAST                      16: _var_var_14
                1198    LOAD_FAST                       14: _var_var_12
                1200    LOAD_CONST                      12: 1
                1202    BINARY_OP                       13 (+=)
                1206    STORE_FAST                      14: _var_var_12
                1208    LOAD_FAST                       13: _var_var_11
                1210    LOAD_CONST                      12: 1
                1212    BINARY_OP                       23 (-=)
                1216    STORE_FAST                      13: _var_var_11
                1218    LOAD_GLOBAL                     29: NULL + eel
                1228    LOAD_ATTR                       44: StreamStat
                1248    LOAD_GLOBAL                     47: NULL + json
                1258    LOAD_ATTR                       48: dumps
                1278    LOAD_CONST                      19: 'st_task'
                1280    LOAD_FAST                       11: _var_var_9
                1282    PUSH_NULL                       
                1284    LOAD_CONST                      1: '__pyarmor_assert_12771__'
                1286    LOAD_CONST                      20: 'st_stream'   # b'\x81\xf1\x0c, \xee\xac\xd7\x1a\xf7'
                1288    CALL                            1
                1296    LOAD_FAST                       12: _var_var_10
                1298    LOAD_CONST                      21: 'st_wait'
                1300    LOAD_FAST                       13: _var_var_11
                1302    LOAD_CONST                      22: 'st_done'
                1304    LOAD_FAST                       14: _var_var_12
                1306    BUILD_MAP                       4
                1308    CALL                            1
                1316    CALL                            1
                1324    POP_TOP                         
                1326    JUMP_BACKWARD                   68 (to 1192)
                1328    END_FOR                         
                1330    NOP                             
                1332    LOAD_CONST                      0: None
                1334    LOAD_CONST                      0: None
                1336    LOAD_CONST                      0: None
                1338    CALL                            2
                1346    POP_TOP                         
                1348    LOAD_GLOBAL                     61: NULL + StopDetect
                1358    LOAD_FAST                       4: stop_thread
                1360    CALL                            1
                1368    POP_TOP                         
                1370    NOP                             
                1372    LOAD_CONST                      24: 'Done'
                1374    NOP                             
                1376    NOP                             
                1378    NOP                             
                1380    JUMP_FORWARD                    106 (to 1594)
                1388    POP_TOP                         
                1390    RETURN_CONST                    24: 'Done'
                1392    PUSH_EXC_INFO                   
                1394    WITH_EXCEPT_START               
                1396    POP_JUMP_IF_TRUE                1 (to 1400)
                1398    RERAISE                         2
                1400    POP_TOP                         
                1402    POP_EXCEPT                      
                1404    POP_TOP                         
                1406    POP_TOP                         
                1408    JUMP_BACKWARD                   31 (to 1348)
                1410    COPY                            3
                1412    POP_EXCEPT                      
                1414    RERAISE                         1
                1416    PUSH_EXC_INFO                   
                1418    LOAD_GLOBAL                     2: StopProgram
                1428    CHECK_EXC_MATCH                 
                1430    POP_JUMP_IF_FALSE               3 (to 1438)
                1432    POP_TOP                         
                1434    POP_EXCEPT                      
                1436    JUMP_BACKWARD                   45 (to 1348)
                1438    LOAD_GLOBAL                     56: BaseException
                1448    CHECK_EXC_MATCH                 
                1450    POP_JUMP_IF_FALSE               26 (to 1504)
                1452    STORE_FAST                      17: _var_var_3
                1454    PUSH_NULL                       
                1456    LOAD_GLOBAL                     59: NULL + logging
                1466    LOAD_FAST                       17: _var_var_3
                1468    CALL                            1
                1476    CALL                            0
                1484    POP_TOP                         
                1486    POP_EXCEPT                      
                1488    LOAD_CONST                      0: None
                1490    STORE_FAST                      17: _var_var_3
                1492    DELETE_FAST                     17: _var_var_3
                1494    JUMP_BACKWARD                   74 (to 1348)
                1496    LOAD_CONST                      0: None
                1498    STORE_FAST                      17: _var_var_3
                1500    DELETE_FAST                     17: _var_var_3
                1502    RERAISE                         1
                1504    RERAISE                         0
                1506    COPY                            3
                1508    POP_EXCEPT                      
                1510    RERAISE                         1
                1512    PUSH_EXC_INFO                   
                1514    LOAD_GLOBAL                     61: NULL + StopDetect
                1524    LOAD_FAST                       4: stop_thread
                1526    CALL                            1
                1534    POP_TOP                         
                1536    POP_TOP                         
                1538    POP_EXCEPT                      
                1540    LOAD_CONST                      24: 'Done'
                1542    NOP                             
                1544    NOP                             
                1546    NOP                             
                1548    JUMP_FORWARD                    22 (to 1594)
                1556    POP_TOP                         
                1558    RETURN_CONST                    24: 'Done'
                1560    COPY                            3
                1562    POP_EXCEPT                      
                1564    RERAISE                         1
                1566    PUSH_EXC_INFO                   
                1568    PUSH_NULL                       
                1570    LOAD_CONST                      23: '__pyarmor_exit_12773__'
                1572    NOP                             
                1574    LOAD_CONST                      3: b'<COAddr>\x05\x00\x00\x1a\x04\x06\x00\x00\x00\x00\x00\x00\x00\x00\x00\x00\x00\x00\x00\x00'
                1576    CALL                            1
                1584    POP_TOP                         
                1586    RERAISE                         0
                1588    COPY                            3
                1590    POP_EXCEPT                      
                1592    RERAISE                         1
                1594    PUSH_NULL                       
                1596    LOAD_CONST                      23: '__pyarmor_exit_12773__'
                1598    LOAD_CONST                      3: b'<COAddr>\x05\x00\x00\x1a\x04\x06\x00\x00\x00\x00\x00\x00\x00\x00\x00\x00\x00\x00\x00\x00'
                1600    BUILD_TUPLE                     1
                1602    CALL_FUNCTION_EX                0
                1604    POP_TOP                         
                1606    RETURN_VALUE                    
            [Exception Table]
                30 to 258 -> 1416 [0] 
                260 to 372 -> 1416 [0] 
                374 to 884 -> 1416 [0] 
                884 to 1330 -> 1392 [1] lasti
                1332 to 1348 -> 1416 [0] 
                1348 to 1370 -> 1566 [0] 
                1392 to 1402 -> 1410 [3] lasti
                1402 to 1416 -> 1416 [0] 
                1416 to 1434 -> 1506 [1] lasti
                1434 to 1438 -> 1512 [0] 
                1438 to 1454 -> 1506 [1] lasti
                1454 to 1486 -> 1496 [1] lasti
                1486 to 1496 -> 1512 [0] 
                1496 to 1506 -> 1506 [1] lasti
                1506 to 1512 -> 1512 [0] 
                1512 to 1538 -> 1560 [1] lasti
                1538 to 1540 -> 1566 [0] 
                1560 to 1566 -> 1566 [0] 
                1566 to 1588 -> 1588 [1] lasti
        [Code]
            File Name: <frozen program.modules.accounts_check>
            Object Name: worker
            Qualified Name: worker
            Arg Count: 6
            Pos Only Arg Count: 0
            KW Only Arg Count: 0
            Stack Size: 10
            Flags: 0x20000003 (CO_OPTIMIZED | CO_NEWLOCALS | CO_PYARMOR_OBFUSCATED)
            [Names]
                'Thread_wait'
                'get_account_json'
                'get_account_proxy'
                'get'
                'VersionControl'
                'Lang'
                'check'
                'is_set'
                'StopProgram'
                'asyncio'
                'new_event_loop'
                'set_event_loop'
                'TelegramClient'
                'get_logger'
                'Logs'
                'PrintLog'
                'proxy_hide'
                'connect'
                'is_user_authorized'
                'get_entity'
                'send_message'
                'errors'
                'YouBlockedUserError'
                'functions'
                'contacts'
                'UnblockRequest'
                'Exception'
                'time'
                'sleep'
                'iter_messages'
                'hasattr'
                'reply_markup'
                'len'
                'rows'
                're'
                'search'
                'message'
                'str'
                'int'
                'end'
                'text'
                'click'
                'UnauthorizedError'
                'UserDeactivatedBanError'
                'AuthKeyUnregisteredError'
                'SessionRevokedError'
                'common'
                'AuthKeyNotFound'
                'AuthKeyDuplicatedError'
                'BadRequestError'
                'TimeoutError'
                'TimedoutError'
                'TimedOutError'
                'BaseException'
                'Disconnect'
                'worker'
                'set_account_json'
                'move_acc_to_folder'
                'logging'
            [Locals+Names]
                'account'
                'config'
                'proxy'
                'data'
                'error'
                'stop_thread'
                '__assert_armored__'
                '_var_var_15'
                '_var_var_16'
                '_var_var_17'
                '_var_var_18'
                '_var_var_19'
                '_var_var_20'
                '_var_var_21'
                '_var_var_22'
                '_var_var_23'
                '_var_var_24'
                '_var_var_25'
                '_var_var_26'
                '_var_var_27'
                '_var_var_28'
                '_var_var_29'
                '_var_var_30'
                '_var_var_31'
                '_var_var_32'
                '_var_var_33'
                '_var_var_34'
                '_var_var_35'
                '_var_var_36'
                '_var_var_37'
                '_var_var_3'
            [Constants]
                None
                '__pyarmor_assert_12774__'
                '__pyarmor_enter_12775__'
                b'<COAddr>\x07\x00\x00\x1a\\\x10\x00\x00\x00\x00\x00\x00\x00\x00\x00\x00\x00\x00\x00\x00'
                'sessions/active'   # b'\x81\xf1\x1d\x00 \xf3\xb1\xdc\x08\xb5\x0c\xc3x\xe5\xee\x80'
                'proxy'
                'ipv6'
                '/'
                '.json'
                '.session'
                'Settings'
                'option'
                'active'
                'spamblock'   # b'\x81\xf1\x08\x12>\xf8\xb2\xdd\x18\xf1'
                'spamblock_temp'   # b'\x81\xf1\x08\x12>\xf8\xb2\xdd\x18\xf12\xd4i\xe1\xe8'
                'deleted'
                'Free'
                True
                'app_id'
                'app_version'   # b'\x81\xe3\x08\x03\x0c\xec\xbb\xc0\x08\xf3\x02\xce'
                '__pyarmor_exit_12776__'
                False
                'session'
                'api_id'
                'api_hash'
                'app_hash'
                'device_model'
                'device'
                'system_version'
                'sdk'
                'app_version'
                'lang_code'
                'lang_code'   # b'\x81\xee\x19\x1d4\xc5\xbd\xdd\x1f\xff'
                'system_lang_code'
                'system_lang_code'   # b"\x81\xf1\x01\x00'\xff\xb3\xed\x17\xfb\x03\xc7S\xef\xf7\x81\n"
                'lang_pack'
                'lang_pack'   # b'\x81\xee\x19\x1d4\xc5\xae\xd3\x18\xf1'
                'device_token'
                'device_token'   # b'\x81\xe6\x1d\x05:\xf9\xbb\xed\x0f\xf5\x06\xc5b'
                'tz_offset'
                'tz_offset'   # b'\x81\xf6\x02,<\xfc\xb8\xc1\x1e\xee'
                'perf_cat'
                0
                'use_ipv6'
                1
                'timeout'
                'request_retries'
                'connection_retries'
                60
                'retry_delay'
                'flood_sleep_threshold'
                'flood_wait'   # b'\x81\xe4\x14\x1c<\xfe\x81\xc5\x1a\xf3\x19'
                'auto_reconnect'
                'sequential_updates'
                'receive_updates'
                'raise_last_call_error'
                'stop_thread'
                'base_logger'
                'loop'
                (
                    'config'
                    'account'
                    'message'
                    'param'
                )
                'connected'   # b'\x81\xe1\x17\x1d=\xff\xbd\xc6\x1e\xfe'
                (
                    'config'
                    'account'
                    'message'
                )
                'Ban'
                'spambot'
                '/start'
                'ErrorConnection'   # b'\x81\xc7\n\x01<\xe8\x9d\xdd\x15\xf4\x08\xc3x\xe5\xf7\x8b'
                (
                    'limit'
                )
                'rows'
                'SpamBlock'   # b'\x81\xd1\x08\x12>\xd8\xb2\xdd\x18\xf1'
                2
                '[0-9][0-9]:[0-9][0-9] UTC'   # b'\x81\xd9H^j\xc7\x85\x82V\xa30\x9aW\xbc\xb5\xdc2f\xeb\xea\xf3\xf6\x0e\xf91L'
                22
                'TempSpamBlock('   # b'\x81\xd6\x1d\x1e#\xc9\xae\xd3\x16\xd8\x01\xcfo\xe7\xb0'
                ')'
                '(https://telegram.org/tos)'   # b"\x81\xaa\x10\x07'\xea\xad\x88T\xb5\x19\xc5`\xe9\xff\x97\x0eP\xf5\xa8\xb8\xcc\x01\xd8\n|\xea"
                'TempSpamBlock(Frozen)'   # b'\x81\xd6\x1d\x1e#\xc9\xae\xd3\x16\xd8\x01\xcfo\xe7\xb0\xa3\x1dR\xa1\xa2\xa4\x82'
                'Telegram Premium'   # b'\x81\xd6\x1d\x1f6\xfd\xac\xd3\x16\xba=\xd2i\xe1\xf1\x90\x02'
                'TempSpamBlock(GeoNumber)'   # b'\x81\xd6\x1d\x1e#\xc9\xae\xd3\x16\xd8\x01\xcfo\xe7\xb0\xa2\nR\x95\xb2\xa7\xc9K\xdeL'
                0.5
                'Status: '
                3
                'error_reconnecting'   # b'\x81\xe7\n\x01<\xe8\x81\xc0\x1e\xf9\x02\xceb\xe9\xfb\x91\x06S\xbc'
                (
                    'file_path'
                    'status'
                    'work'
                )
                'TempSpamBlock'   # b'\x81\xd6\x1d\x1e#\xc9\xae\xd3\x16\xd8\x01\xcfo\xe7'
                'account_is_move_success'   # b'\x81\xe3\x1b\x10<\xef\xb0\xc6$\xf3\x1e\xffa\xe3\xee\x800N\xae\xa4\xa9\xce]\xdf'
                'work_account_completed'   # b'\x81\xf5\x17\x018\xc5\xbf\xd1\x18\xf5\x18\xcex\xd3\xfb\x8a\x02M\xb7\xa2\xbe\xceJ'
                'done'
                (
                    'account'
                    'status'
                )
                (
                )
            [Disassembly]
                0       NOP                             
                2       NOP                             
                4       PUSH_NULL                       
                6       LOAD_CONST                      2: '__pyarmor_enter_12775__'
                8       LOAD_CONST                      3: b'<COAddr>\x07\x00\x00\x1a\\\x10\x00\x00\x00\x00\x00\x00\x00\x00\x00\x00\x00\x00\x00\x00'
                10      BUILD_TUPLE                     1
                12      CALL_FUNCTION_EX                0
                14      POP_TOP                         
                16      RESUME                          0
                18      NOP                             
                20      NOP                             
                22      NOP                             
                24      NOP                             
                26      NOP                             
                28      NOP                             
                30      LOAD_GLOBAL                     1: NULL + Thread_wait
                40      LOAD_FAST                       3: data
                42      LOAD_FAST                       1: config
                44      LOAD_FAST                       5: stop_thread
                46      CALL                            3
                54      POP_TOP                         
                56      PUSH_NULL                       
                58      LOAD_CONST                      1: '__pyarmor_assert_12774__'
                60      LOAD_CONST                      4: 'sessions/active'   # b'\x81\xf1\x1d\x00 \xf3\xb1\xdc\x08\xb5\x0c\xc3x\xe5\xee\x80'
                62      CALL                            1
                70      STORE_FAST                      7: _var_var_15
                72      LOAD_GLOBAL                     3: NULL + get_account_json
                82      LOAD_FAST                       0: account
                84      LOAD_FAST                       7: _var_var_15
                86      CALL                            2
                94      STORE_FAST                      8: _var_var_16
                96      LOAD_GLOBAL                     5: NULL + get_account_proxy
                106     LOAD_FAST                       1: config
                108     LOAD_FAST                       2: proxy
                110     LOAD_FAST                       8: _var_var_16
                112     LOAD_CONST                      5: 'proxy'
                114     BINARY_SUBSCR                   
                118     LOAD_FAST                       8: _var_var_16
                120     LOAD_CONST                      6: 'ipv6'
                122     BINARY_SUBSCR                   
                126     CALL                            4
                134     STORE_FAST                      9: _var_var_17
                136     LOAD_FAST                       7: _var_var_15
                138     LOAD_CONST                      7: '/'
                140     BINARY_OP                       0 (+)
                144     LOAD_FAST                       0: account
                146     BINARY_OP                       0 (+)
                150     LOAD_CONST                      8: '.json'
                152     BINARY_OP                       0 (+)
                156     STORE_FAST                      10: _var_var_18
                158     LOAD_FAST                       7: _var_var_15
                160     LOAD_CONST                      7: '/'
                162     BINARY_OP                       0 (+)
                166     LOAD_FAST                       0: account
                168     BINARY_OP                       0 (+)
                172     LOAD_CONST                      9: '.session'
                174     BINARY_OP                       0 (+)
                178     STORE_FAST                      11: _var_var_19
                180     LOAD_FAST                       3: data
                182     LOAD_CONST                      10: 'Settings'
                184     BINARY_SUBSCR                   
                188     LOAD_ATTR                       7: get
                208     LOAD_CONST                      11: 'option'
                210     CALL                            1
                218     STORE_FAST                      12: _var_var_20
                220     LOAD_FAST                       3: data
                222     LOAD_CONST                      10: 'Settings'
                224     BINARY_SUBSCR                   
                228     LOAD_ATTR                       7: get
                248     LOAD_CONST                      12: 'active'
                250     CALL                            1
                258     STORE_FAST                      13: _var_var_21
                260     LOAD_FAST                       3: data
                262     LOAD_CONST                      10: 'Settings'
                264     BINARY_SUBSCR                   
                268     LOAD_ATTR                       7: get
                288     PUSH_NULL                       
                290     LOAD_CONST                      1: '__pyarmor_assert_12774__'
                292     LOAD_CONST                      13: 'spamblock'   # b'\x81\xf1\x08\x12>\xf8\xb2\xdd\x18\xf1'
                294     CALL                            1
                302     CALL                            1
                310     STORE_FAST                      14: _var_var_22
                312     LOAD_FAST                       3: data
                314     LOAD_CONST                      10: 'Settings'
                316     BINARY_SUBSCR                   
                320     LOAD_ATTR                       7: get
                340     PUSH_NULL                       
                342     LOAD_CONST                      1: '__pyarmor_assert_12774__'
                344     LOAD_CONST                      14: 'spamblock_temp'   # b'\x81\xf1\x08\x12>\xf8\xb2\xdd\x18\xf12\xd4i\xe1\xe8'
                346     CALL                            1
                354     CALL                            1
                362     STORE_FAST                      15: _var_var_23
                364     LOAD_FAST                       3: data
                366     LOAD_CONST                      10: 'Settings'
                368     BINARY_SUBSCR                   
                372     LOAD_ATTR                       7: get
                392     LOAD_CONST                      15: 'deleted'
                394     CALL                            1
                402     STORE_FAST                      16: _var_var_24
                404     LOAD_CONST                      16: 'Free'
                406     STORE_FAST                      17: _var_var_25
                408     LOAD_GLOBAL                     9: NULL + VersionControl
                418     LOAD_FAST                       1: config
                420     LOAD_GLOBAL                     10: Lang
                430     LOAD_CONST                      17: True
                432     CALL                            3
                440     LOAD_ATTR                       13: check
                460     LOAD_FAST                       0: account
                462     LOAD_FAST                       8: _var_var_16
                464     LOAD_CONST                      18: 'app_id'
                466     BINARY_SUBSCR                   
                470     LOAD_FAST                       8: _var_var_16
                472     PUSH_NULL                       
                474     LOAD_CONST                      1: '__pyarmor_assert_12774__'
                476     LOAD_CONST                      19: 'app_version'   # b'\x81\xe3\x08\x03\x0c\xec\xbb\xc0\x08\xf3\x02\xce'
                478     CALL                            1
                486     BINARY_SUBSCR                   
                490     CALL                            3
                498     STORE_FAST                      18: _var_var_26
                500     LOAD_FAST                       18: _var_var_26
                502     POP_JUMP_IF_TRUE                11 (to 526)
                504     NOP                             
                506     LOAD_CONST                      21: False
                508     NOP                             
                510     NOP                             
                512     JUMP_FORWARD                    1863 (to 4242)
                522     POP_TOP                         
                524     RETURN_CONST                    21: False
                526     LOAD_FAST                       5: stop_thread
                528     LOAD_ATTR                       15: is_set
                548     CALL                            0
                556     POP_JUMP_IF_FALSE               10 (to 578)
                558     LOAD_GLOBAL                     17: NULL + StopProgram
                568     CALL                            0
                576     RAISE_VARARGS                   1
                578     NOP                             
                580     LOAD_GLOBAL                     19: NULL + asyncio
                590     LOAD_ATTR                       20: new_event_loop
                610     CALL                            0
                618     STORE_FAST                      19: _var_var_27
                620     LOAD_GLOBAL                     19: NULL + asyncio
                630     LOAD_ATTR                       22: set_event_loop
                650     LOAD_FAST                       19: _var_var_27
                652     CALL                            1
                660     POP_TOP                         
                662     LOAD_GLOBAL                     25: NULL + TelegramClient
                672     LOAD_CONST                      88: ()
                674     BUILD_MAP                       0
                676     LOAD_CONST                      22: 'session'
                678     LOAD_FAST                       11: _var_var_19
                680     MAP_ADD                         1
                682     LOAD_CONST                      23: 'api_id'
                684     LOAD_FAST                       8: _var_var_16
                686     LOAD_CONST                      18: 'app_id'
                688     BINARY_SUBSCR                   
                692     MAP_ADD                         1
                694     LOAD_CONST                      24: 'api_hash'
                696     LOAD_FAST                       8: _var_var_16
                698     LOAD_CONST                      25: 'app_hash'
                700     BINARY_SUBSCR                   
                704     MAP_ADD                         1
                706     LOAD_CONST                      26: 'device_model'
                708     LOAD_FAST                       8: _var_var_16
                710     LOAD_CONST                      27: 'device'
                712     BINARY_SUBSCR                   
                716     MAP_ADD                         1
                718     LOAD_CONST                      28: 'system_version'
                720     LOAD_FAST                       8: _var_var_16
                722     LOAD_CONST                      29: 'sdk'
                724     BINARY_SUBSCR                   
                728     MAP_ADD                         1
                730     LOAD_CONST                      30: 'app_version'
                732     LOAD_FAST                       8: _var_var_16
                734     PUSH_NULL                       
                736     LOAD_CONST                      1: '__pyarmor_assert_12774__'
                738     LOAD_CONST                      19: 'app_version'   # b'\x81\xe3\x08\x03\x0c\xec\xbb\xc0\x08\xf3\x02\xce'
                740     CALL                            1
                748     BINARY_SUBSCR                   
                752     MAP_ADD                         1
                754     LOAD_CONST                      31: 'lang_code'
                756     LOAD_FAST                       8: _var_var_16
                758     PUSH_NULL                       
                760     LOAD_CONST                      1: '__pyarmor_assert_12774__'
                762     LOAD_CONST                      32: 'lang_code'   # b'\x81\xee\x19\x1d4\xc5\xbd\xdd\x1f\xff'
                764     CALL                            1
                772     BINARY_SUBSCR                   
                776     MAP_ADD                         1
                778     LOAD_CONST                      33: 'system_lang_code'
                780     LOAD_FAST                       8: _var_var_16
                782     PUSH_NULL                       
                784     LOAD_CONST                      1: '__pyarmor_assert_12774__'
                786     LOAD_CONST                      34: 'system_lang_code'   # b"\x81\xf1\x01\x00'\xff\xb3\xed\x17\xfb\x03\xc7S\xef\xf7\x81\n"
                788     CALL                            1
                796     BINARY_SUBSCR                   
                800     MAP_ADD                         1
                802     LOAD_CONST                      35: 'lang_pack'
                804     LOAD_FAST                       8: _var_var_16
                806     PUSH_NULL                       
                808     LOAD_CONST                      1: '__pyarmor_assert_12774__'
                810     LOAD_CONST                      36: 'lang_pack'   # b'\x81\xee\x19\x1d4\xc5\xae\xd3\x18\xf1'
                812     CALL                            1
                820     BINARY_SUBSCR                   
                824     MAP_ADD                         1
                826     LOAD_CONST                      37: 'device_token'
                828     LOAD_FAST                       8: _var_var_16
                830     PUSH_NULL                       
                832     LOAD_CONST                      1: '__pyarmor_assert_12774__'
                834     LOAD_CONST                      38: 'device_token'   # b'\x81\xe6\x1d\x05:\xf9\xbb\xed\x0f\xf5\x06\xc5b'
                836     CALL                            1
                844     BINARY_SUBSCR                   
                848     MAP_ADD                         1
                850     LOAD_CONST                      39: 'tz_offset'
                852     LOAD_FAST                       8: _var_var_16
                854     PUSH_NULL                       
                856     LOAD_CONST                      1: '__pyarmor_assert_12774__'
                858     LOAD_CONST                      40: 'tz_offset'   # b'\x81\xf6\x02,<\xfc\xb8\xc1\x1e\xee'
                860     CALL                            1
                868     BINARY_SUBSCR                   
                872     MAP_ADD                         1
                874     LOAD_CONST                      41: 'perf_cat'
                876     LOAD_FAST                       8: _var_var_16
                878     LOAD_CONST                      41: 'perf_cat'
                880     BINARY_SUBSCR                   
                884     MAP_ADD                         1
                886     LOAD_CONST                      5: 'proxy'
                888     LOAD_FAST                       9: _var_var_17
                890     LOAD_CONST                      42: 0
                892     BINARY_SUBSCR                   
                896     MAP_ADD                         1
                898     LOAD_CONST                      43: 'use_ipv6'
                900     LOAD_FAST                       9: _var_var_17
                902     LOAD_CONST                      44: 1
                904     BINARY_SUBSCR                   
                908     MAP_ADD                         1
                910     LOAD_CONST                      45: 'timeout'
                912     LOAD_FAST                       1: config
                914     LOAD_CONST                      45: 'timeout'
                916     BINARY_SUBSCR                   
                920     MAP_ADD                         1
                922     LOAD_CONST                      46: 'request_retries'
                924     LOAD_CONST                      44: 1
                926     MAP_ADD                         1
                928     LOAD_CONST                      47: 'connection_retries'
                930     LOAD_CONST                      48: 60
                932     MAP_ADD                         1
                934     LOAD_CONST                      49: 'retry_delay'
                936     LOAD_CONST                      44: 1
                938     MAP_ADD                         1
                940     LOAD_CONST                      50: 'flood_sleep_threshold'
                942     LOAD_FAST                       1: config
                944     PUSH_NULL                       
                946     LOAD_CONST                      1: '__pyarmor_assert_12774__'
                948     LOAD_CONST                      51: 'flood_wait'   # b'\x81\xe4\x14\x1c<\xfe\x81\xc5\x1a\xf3\x19'
                950     CALL                            1
                958     BINARY_SUBSCR                   
                962     MAP_ADD                         1
                964     LOAD_CONST                      52: 'auto_reconnect'
                966     LOAD_CONST                      17: True
                968     MAP_ADD                         1
                970     LOAD_CONST                      53: 'sequential_updates'
                972     LOAD_CONST                      17: True
                974     MAP_ADD                         1
                976     LOAD_CONST                      54: 'receive_updates'
                978     LOAD_CONST                      17: True
                980     MAP_ADD                         1
                982     LOAD_CONST                      55: 'raise_last_call_error'
                984     LOAD_CONST                      17: True
                986     MAP_ADD                         1
                988     LOAD_CONST                      56: 'stop_thread'
                990     LOAD_FAST                       5: stop_thread
                992     MAP_ADD                         1
                994     LOAD_CONST                      57: 'base_logger'
                996     LOAD_GLOBAL                     27: NULL + get_logger
                1006    LOAD_FAST                       0: account
                1008    CALL                            1
                1016    MAP_ADD                         1
                1018    LOAD_CONST                      58: 'loop'
                1020    LOAD_FAST                       19: _var_var_27
                1022    MAP_ADD                         1
                1024    CALL_FUNCTION_EX                1
                1026    STORE_FAST                      20: _var_var_28
                1028    LOAD_GLOBAL                     29: NULL + Logs
                1038    LOAD_ATTR                       30: PrintLog
                1058    LOAD_FAST                       1: config
                1060    LOAD_FAST                       0: account
                1062    LOAD_GLOBAL                     10: Lang
                1072    LOAD_CONST                      5: 'proxy'
                1074    BINARY_SUBSCR                   
                1078    LOAD_GLOBAL                     33: NULL + proxy_hide
                1088    LOAD_FAST                       9: _var_var_17
                1090    CALL                            1
                1098    KW_NAMES                        59: ('config', 'account', 'message', 'param')
                1100    CALL                            4
                1108    POP_TOP                         
                1110    LOAD_FAST                       20: _var_var_28
                1112    LOAD_ATTR                       35: connect
                1132    CALL                            0
                1140    POP_TOP                         
                1142    LOAD_GLOBAL                     29: NULL + Logs
                1152    LOAD_ATTR                       30: PrintLog
                1172    LOAD_FAST                       1: config
                1174    LOAD_FAST                       0: account
                1176    LOAD_GLOBAL                     10: Lang
                1186    PUSH_NULL                       
                1188    LOAD_CONST                      1: '__pyarmor_assert_12774__'
                1190    LOAD_CONST                      60: 'connected'   # b'\x81\xe1\x17\x1d=\xff\xbd\xc6\x1e\xfe'
                1192    CALL                            1
                1200    BINARY_SUBSCR                   
                1204    KW_NAMES                        61: ('config', 'account', 'message')
                1206    CALL                            3
                1214    POP_TOP                         
                1216    LOAD_FAST                       20: _var_var_28
                1218    LOAD_ATTR                       37: is_user_authorized
                1238    CALL                            0
                1246    POP_JUMP_IF_TRUE                2 (to 1252)
                1248    LOAD_CONST                      62: 'Ban'
                1250    STORE_FAST                      17: _var_var_25
                1252    LOAD_FAST                       12: _var_var_20
                1254    LOAD_CONST                      63: 'spambot'
                1256    COMPARE_OP                      40 (==)
                1260    POP_JUMP_IF_FALSE               413 (to 2090)
                1264    LOAD_FAST                       17: _var_var_25
                1266    LOAD_CONST                      62: 'Ban'
                1268    COMPARE_OP                      55 (!=)
                1272    POP_JUMP_IF_FALSE               407 (to 2090)
                1276    LOAD_FAST                       20: _var_var_28
                1278    LOAD_ATTR                       39: get_entity
                1298    LOAD_CONST                      63: 'spambot'
                1300    CALL                            1
                1308    STORE_FAST                      21: _var_var_29
                1310    NOP                             
                1312    LOAD_FAST                       20: _var_var_28
                1314    LOAD_ATTR                       41: send_message
                1334    LOAD_FAST                       21: _var_var_29
                1336    LOAD_CONST                      64: '/start'
                1338    CALL                            2
                1346    POP_TOP                         
                1348    LOAD_GLOBAL                     55: NULL + time
                1358    LOAD_ATTR                       56: sleep
                1378    LOAD_CONST                      44: 1
                1380    CALL                            1
                1388    POP_TOP                         
                1390    LOAD_FAST                       20: _var_var_28
                1392    LOAD_ATTR                       59: iter_messages
                1412    LOAD_FAST                       21: _var_var_29
                1414    LOAD_CONST                      44: 1
                1416    KW_NAMES                        66: ('limit',)
                1418    CALL                            2
                1426    GET_ITER                        
                1428    FOR_ITER                        327 (to 2086)
                1434    STORE_FAST                      22: _var_var_30
                1436    LOAD_GLOBAL                     61: NULL + hasattr
                1446    LOAD_FAST                       22: _var_var_30
                1448    LOAD_ATTR                       62: reply_markup
                1468    LOAD_CONST                      67: 'rows'
                1470    CALL                            2
                1478    POP_JUMP_IF_TRUE                11 (to 1502)
                1480    PUSH_NULL                       
                1482    LOAD_CONST                      1: '__pyarmor_assert_12774__'
                1484    LOAD_CONST                      68: 'SpamBlock'   # b'\x81\xd1\x08\x12>\xd8\xb2\xdd\x18\xf1'
                1486    CALL                            1
                1494    STORE_FAST                      17: _var_var_25
                1496    POP_TOP                         
                1498    JUMP_FORWARD                    294 (to 2090)
                1502    LOAD_GLOBAL                     65: NULL + len
                1512    LOAD_FAST                       22: _var_var_30
                1514    LOAD_ATTR                       62: reply_markup
                1534    LOAD_ATTR                       66: rows
                1554    CALL                            1
                1562    STORE_FAST                      23: _var_var_31
                1564    LOAD_FAST                       23: _var_var_31
                1566    LOAD_CONST                      69: 2
                1568    COMPARE_OP                      68 (>)
                1572    POP_JUMP_IF_FALSE               176 (to 1926)
                1574    LOAD_GLOBAL                     69: NULL + re
                1584    LOAD_ATTR                       70: search
                1604    PUSH_NULL                       
                1606    LOAD_CONST                      1: '__pyarmor_assert_12774__'
                1608    LOAD_CONST                      70: '[0-9][0-9]:[0-9][0-9] UTC'   # b'\x81\xd9H^j\xc7\x85\x82V\xa30\x9aW\xbc\xb5\xdc2f\xeb\xea\xf3\xf6\x0e\xf91L'
                1610    CALL                            1
                1618    LOAD_FAST                       22: _var_var_30
                1620    LOAD_ATTR                       72: message
                1640    CALL                            2
                1648    STORE_FAST                      24: _var_var_32
                1650    LOAD_FAST                       24: _var_var_32
                1652    LOAD_CONST                      0: None
                1654    COMPARE_OP                      55 (!=)
                1658    POP_JUMP_IF_FALSE               93 (to 1846)
                1660    LOAD_GLOBAL                     75: NULL + str
                1670    LOAD_FAST                       22: _var_var_30
                1672    LOAD_ATTR                       72: message
                1692    CALL                            1
                1700    STORE_FAST                      25: _var_var_33
                1702    LOAD_GLOBAL                     77: NULL + int
                1712    LOAD_FAST                       24: _var_var_32
                1714    LOAD_ATTR                       79: end
                1734    CALL                            0
                1742    CALL                            1
                1750    LOAD_CONST                      71: 22
                1752    BINARY_OP                       10 (-)
                1756    STORE_FAST                      26: _var_var_34
                1758    LOAD_GLOBAL                     77: NULL + int
                1768    LOAD_FAST                       24: _var_var_32
                1770    LOAD_ATTR                       79: end
                1790    CALL                            0
                1798    CALL                            1
                1806    STORE_FAST                      27: _var_var_35
                1808    LOAD_FAST                       25: _var_var_33
                1810    LOAD_FAST                       26: _var_var_34
                1812    LOAD_FAST                       27: _var_var_35
                1814    BINARY_SLICE                    
                1816    STORE_FAST                      28: _var_var_36
                1818    PUSH_NULL                       
                1820    LOAD_CONST                      1: '__pyarmor_assert_12774__'
                1822    LOAD_CONST                      72: 'TempSpamBlock('   # b'\x81\xd6\x1d\x1e#\xc9\xae\xd3\x16\xd8\x01\xcfo\xe7\xb0'
                1824    CALL                            1
                1832    LOAD_FAST                       28: _var_var_36
                1834    FORMAT_VALUE                    0 (FVC_NONE)
                1836    LOAD_CONST                      73: ')'
                1838    BUILD_STRING                    3
                1840    STORE_FAST                      17: _var_var_25
                1842    POP_TOP                         
                1844    JUMP_FORWARD                    122 (to 2090)
                1846    PUSH_NULL                       
                1848    LOAD_CONST                      1: '__pyarmor_assert_12774__'
                1850    LOAD_CONST                      74: '(https://telegram.org/tos)'   # b"\x81\xaa\x10\x07'\xea\xad\x88T\xb5\x19\xc5`\xe9\xff\x97\x0eP\xf5\xa8\xb8\xcc\x01\xd8\n|\xea"
                1852    CALL                            1
                1860    LOAD_FAST                       22: _var_var_30
                1862    LOAD_ATTR                       80: text
                1882    CONTAINS_OP                     0 (in)
                1884    POP_JUMP_IF_FALSE               10 (to 1906)
                1886    PUSH_NULL                       
                1888    LOAD_CONST                      1: '__pyarmor_assert_12774__'
                1890    LOAD_CONST                      75: 'TempSpamBlock(Frozen)'   # b'\x81\xd6\x1d\x1e#\xc9\xae\xd3\x16\xd8\x01\xcfo\xe7\xb0\xa3\x1dR\xa1\xa2\xa4\x82'
                1892    CALL                            1
                1900    STORE_FAST                      17: _var_var_25
                1902    POP_TOP                         
                1904    JUMP_FORWARD                    92 (to 2090)
                1906    PUSH_NULL                       
                1908    LOAD_CONST                      1: '__pyarmor_assert_12774__'
                1910    LOAD_CONST                      68: 'SpamBlock'   # b'\x81\xd1\x08\x12>\xd8\xb2\xdd\x18\xf1'
                1912    CALL                            1
                1920    STORE_FAST                      17: _var_var_25
                1922    POP_TOP                         
                1924    JUMP_FORWARD                    82 (to 2090)
                1926    PUSH_NULL                       
                1928    LOAD_CONST                      1: '__pyarmor_assert_12774__'
                1930    LOAD_CONST                      76: 'Telegram Premium'   # b'\x81\xd6\x1d\x1f6\xfd\xac\xd3\x16\xba=\xd2i\xe1\xf1\x90\x02'
                1932    CALL                            1
                1940    LOAD_GLOBAL                     75: NULL + str
                1950    LOAD_FAST                       22: _var_var_30
                1952    LOAD_ATTR                       72: message
                1972    CALL                            1
                1980    CONTAINS_OP                     0 (in)
                1982    POP_JUMP_IF_FALSE               10 (to 2004)
                1984    PUSH_NULL                       
                1986    LOAD_CONST                      1: '__pyarmor_assert_12774__'
                1988    LOAD_CONST                      77: 'TempSpamBlock(GeoNumber)'   # b'\x81\xd6\x1d\x1e#\xc9\xae\xd3\x16\xd8\x01\xcfo\xe7\xb0\xa2\nR\x95\xb2\xa7\xc9K\xdeL'
                1990    CALL                            1
                1998    STORE_FAST                      17: _var_var_25
                2000    POP_TOP                         
                2002    JUMP_FORWARD                    43 (to 2090)
                2004    LOAD_CONST                      16: 'Free'
                2006    STORE_FAST                      17: _var_var_25
                2008    LOAD_GLOBAL                     55: NULL + time
                2018    LOAD_ATTR                       56: sleep
                2038    LOAD_CONST                      78: 0.5
                2040    CALL                            1
                2048    POP_TOP                         
                2050    LOAD_FAST                       22: _var_var_30
                2052    LOAD_ATTR                       83: click
                2072    LOAD_CONST                      42: 0
                2074    CALL                            1
                2082    POP_TOP                         
                2084    POP_TOP                         
                2086    JUMP_FORWARD                    1 (to 2090)
                2088    END_FOR                         
                2090    LOAD_GLOBAL                     109: NULL + Disconnect
                2100    LOAD_FAST_CHECK                 20: _var_var_28
                2102    CALL                            1
                2110    POP_TOP                         
                2112    LOAD_GLOBAL                     29: NULL + Logs
                2122    LOAD_ATTR                       30: PrintLog
                2142    LOAD_FAST                       1: config
                2144    LOAD_FAST                       0: account
                2146    LOAD_CONST                      79: 'Status: '
                2148    LOAD_FAST                       17: _var_var_25
                2150    FORMAT_VALUE                    0 (FVC_NONE)
                2152    BUILD_STRING                    2
                2154    KW_NAMES                        61: ('config', 'account', 'message')
                2156    CALL                            3
                2164    POP_TOP                         
                2166    LOAD_FAST                       17: _var_var_25
                2168    PUSH_NULL                       
                2170    LOAD_CONST                      1: '__pyarmor_assert_12774__'
                2172    LOAD_CONST                      65: 'ErrorConnection'   # b'\x81\xc7\n\x01<\xe8\x9d\xdd\x15\xf4\x08\xc3x\xe5\xf7\x8b'
                2174    CALL                            1
                2182    COMPARE_OP                      40 (==)
                2186    POP_JUMP_IF_FALSE               72 (to 2332)
                2188    LOAD_FAST                       4: error
                2190    LOAD_CONST                      44: 1
                2192    BINARY_OP                       13 (+=)
                2196    STORE_FAST                      4: error
                2198    LOAD_FAST                       4: error
                2200    LOAD_CONST                      80: 3
                2202    COMPARE_OP                      2 (<)
                2206    POP_JUMP_IF_FALSE               62 (to 2332)
                2208    LOAD_GLOBAL                     29: NULL + Logs
                2218    LOAD_ATTR                       30: PrintLog
                2238    LOAD_FAST                       1: config
                2240    LOAD_FAST                       0: account
                2242    LOAD_GLOBAL                     10: Lang
                2252    PUSH_NULL                       
                2254    LOAD_CONST                      1: '__pyarmor_assert_12774__'
                2256    LOAD_CONST                      81: 'error_reconnecting'   # b'\x81\xe7\n\x01<\xe8\x81\xc0\x1e\xf9\x02\xceb\xe9\xfb\x91\x06S\xbc'
                2258    CALL                            1
                2266    BINARY_SUBSCR                   
                2270    KW_NAMES                        61: ('config', 'account', 'message')
                2272    CALL                            3
                2280    POP_TOP                         
                2282    LOAD_GLOBAL                     111: NULL + worker
                2292    LOAD_FAST                       0: account
                2294    LOAD_FAST                       1: config
                2296    LOAD_FAST                       2: proxy
                2298    LOAD_FAST                       3: data
                2300    LOAD_FAST                       4: error
                2302    LOAD_FAST                       5: stop_thread
                2304    CALL                            6
                2312    NOP                             
                2314    NOP                             
                2316    JUMP_FORWARD                    961 (to 4242)
                2320    CALL                            1
                2328    POP_TOP                         
                2330    RETURN_VALUE                    
                2332    LOAD_GLOBAL                     113: NULL + set_account_json
                2342    LOAD_FAST                       10: _var_var_18
                2344    LOAD_FAST                       17: _var_var_25
                2346    LOAD_CONST                      42: 0
                2348    KW_NAMES                        82: ('file_path', 'status', 'work')
                2350    CALL                            3
                2358    POP_TOP                         
                2360    LOAD_CONST                      21: False
                2362    STORE_FAST                      29: _var_var_37
                2364    LOAD_FAST                       17: _var_var_25
                2366    LOAD_CONST                      16: 'Free'
                2368    COMPARE_OP                      40 (==)
                2372    POP_JUMP_IF_FALSE               12 (to 2398)
                2374    LOAD_GLOBAL                     115: NULL + move_acc_to_folder
                2384    LOAD_FAST                       0: account
                2386    LOAD_FAST                       13: _var_var_21
                2388    CALL                            2
                2396    STORE_FAST                      29: _var_var_37
                2398    LOAD_FAST                       17: _var_var_25
                2400    PUSH_NULL                       
                2402    LOAD_CONST                      1: '__pyarmor_assert_12774__'
                2404    LOAD_CONST                      68: 'SpamBlock'   # b'\x81\xd1\x08\x12>\xd8\xb2\xdd\x18\xf1'
                2406    CALL                            1
                2414    COMPARE_OP                      40 (==)
                2418    POP_JUMP_IF_FALSE               12 (to 2444)
                2420    LOAD_GLOBAL                     115: NULL + move_acc_to_folder
                2430    LOAD_FAST                       0: account
                2432    LOAD_FAST                       14: _var_var_22
                2434    CALL                            2
                2442    STORE_FAST                      29: _var_var_37
                2444    LOAD_FAST                       17: _var_var_25
                2446    LOAD_CONST                      62: 'Ban'
                2448    COMPARE_OP                      40 (==)
                2452    POP_JUMP_IF_FALSE               12 (to 2478)
                2454    LOAD_GLOBAL                     115: NULL + move_acc_to_folder
                2464    LOAD_FAST                       0: account
                2466    LOAD_FAST                       16: _var_var_24
                2468    CALL                            2
                2476    STORE_FAST                      29: _var_var_37
                2478    PUSH_NULL                       
                2480    LOAD_CONST                      1: '__pyarmor_assert_12774__'
                2482    LOAD_CONST                      83: 'TempSpamBlock'   # b'\x81\xd6\x1d\x1e#\xc9\xae\xd3\x16\xd8\x01\xcfo\xe7'
                2484    CALL                            1
                2492    LOAD_FAST                       17: _var_var_25
                2494    CONTAINS_OP                     0 (in)
                2496    POP_JUMP_IF_FALSE               12 (to 2522)
                2498    LOAD_GLOBAL                     115: NULL + move_acc_to_folder
                2508    LOAD_FAST                       0: account
                2510    LOAD_FAST                       15: _var_var_23
                2512    CALL                            2
                2520    STORE_FAST                      29: _var_var_37
                2522    LOAD_FAST                       29: _var_var_37
                2524    POP_JUMP_IF_FALSE               37 (to 2600)
                2526    LOAD_GLOBAL                     29: NULL + Logs
                2536    LOAD_ATTR                       30: PrintLog
                2556    LOAD_FAST                       1: config
                2558    LOAD_FAST                       0: account
                2560    LOAD_GLOBAL                     10: Lang
                2570    PUSH_NULL                       
                2572    LOAD_CONST                      1: '__pyarmor_assert_12774__'
                2574    LOAD_CONST                      84: 'account_is_move_success'   # b'\x81\xe3\x1b\x10<\xef\xb0\xc6$\xf3\x1e\xffa\xe3\xee\x800N\xae\xa4\xa9\xce]\xdf'
                2576    CALL                            1
                2584    BINARY_SUBSCR                   
                2588    KW_NAMES                        61: ('config', 'account', 'message')
                2590    CALL                            3
                2598    POP_TOP                         
                2600    LOAD_GLOBAL                     29: NULL + Logs
                2610    LOAD_ATTR                       30: PrintLog
                2630    LOAD_FAST                       1: config
                2632    LOAD_FAST                       0: account
                2634    LOAD_GLOBAL                     10: Lang
                2644    PUSH_NULL                       
                2646    LOAD_CONST                      1: '__pyarmor_assert_12774__'
                2648    LOAD_CONST                      85: 'work_account_completed'   # b'\x81\xf5\x17\x018\xc5\xbf\xd1\x18\xf5\x18\xcex\xd3\xfb\x8a\x02M\xb7\xa2\xbe\xceJ'
                2650    CALL                            1
                2658    BINARY_SUBSCR                   
                2662    KW_NAMES                        61: ('config', 'account', 'message')
                2664    CALL                            3
                2672    POP_TOP                         
                2674    NOP                             
                2676    LOAD_FAST                       0: account
                2678    LOAD_CONST                      86: 'done'
                2680    LOAD_CONST                      87: ('account', 'status')
                2682    BUILD_CONST_KEY_MAP             2
                2684    NOP                             
                2686    NOP                             
                2688    JUMP_FORWARD                    775 (to 4242)
                2692    CALL                            1
                2700    POP_TOP                         
                2702    RETURN_VALUE                    
                2704    PUSH_EXC_INFO                   
                2706    LOAD_GLOBAL                     42: errors
                2716    LOAD_ATTR                       44: YouBlockedUserError
                2736    CHECK_EXC_MATCH                 
                2738    POP_JUMP_IF_FALSE               59 (to 2858)
                2740    POP_TOP                         
                2742    PUSH_NULL                       
                2744    LOAD_FAST                       20: _var_var_28
                2746    LOAD_GLOBAL                     46: functions
                2756    LOAD_ATTR                       48: contacts
                2776    LOAD_ATTR                       51: UnblockRequest
                2796    LOAD_CONST                      63: 'spambot'
                2798    CALL                            1
                2806    CALL                            1
                2814    POP_TOP                         
                2816    LOAD_FAST                       20: _var_var_28
                2818    LOAD_ATTR                       41: send_message
                2838    LOAD_FAST                       21: _var_var_29
                2840    LOAD_CONST                      64: '/start'
                2842    CALL                            2
                2850    POP_TOP                         
                2852    POP_EXCEPT                      
                2854    JUMP_BACKWARD                   755 (to 1348)
                2858    LOAD_GLOBAL                     52: Exception
                2868    CHECK_EXC_MATCH                 
                2870    POP_JUMP_IF_FALSE               12 (to 2896)
                2872    POP_TOP                         
                2874    PUSH_NULL                       
                2876    LOAD_CONST                      1: '__pyarmor_assert_12774__'
                2878    LOAD_CONST                      65: 'ErrorConnection'   # b'\x81\xc7\n\x01<\xe8\x9d\xdd\x15\xf4\x08\xc3x\xe5\xf7\x8b'
                2880    CALL                            1
                2888    STORE_FAST                      17: _var_var_25
                2890    POP_EXCEPT                      
                2892    JUMP_BACKWARD                   774 (to 1348)
                2896    RERAISE                         0
                2898    COPY                            3
                2900    POP_EXCEPT                      
                2902    RERAISE                         1
                2904    PUSH_EXC_INFO                   
                2906    LOAD_GLOBAL                     42: errors
                2916    LOAD_ATTR                       84: UnauthorizedError
                2936    CHECK_EXC_MATCH                 
                2938    POP_JUMP_IF_FALSE               6 (to 2952)
                2940    POP_TOP                         
                2942    LOAD_CONST                      62: 'Ban'
                2944    STORE_FAST                      17: _var_var_25
                2946    POP_EXCEPT                      
                2948    JUMP_BACKWARD                   431 (to 2090)
                2952    LOAD_GLOBAL                     42: errors
                2962    LOAD_ATTR                       86: UserDeactivatedBanError
                2982    CHECK_EXC_MATCH                 
                2984    POP_JUMP_IF_FALSE               6 (to 2998)
                2986    POP_TOP                         
                2988    LOAD_CONST                      62: 'Ban'
                2990    STORE_FAST                      17: _var_var_25
                2992    POP_EXCEPT                      
                2994    JUMP_BACKWARD                   454 (to 2090)
                2998    LOAD_GLOBAL                     42: errors
                3008    LOAD_ATTR                       88: AuthKeyUnregisteredError
                3028    CHECK_EXC_MATCH                 
                3030    POP_JUMP_IF_FALSE               6 (to 3044)
                3032    POP_TOP                         
                3034    LOAD_CONST                      62: 'Ban'
                3036    STORE_FAST                      17: _var_var_25
                3038    POP_EXCEPT                      
                3040    JUMP_BACKWARD                   477 (to 2090)
                3044    LOAD_GLOBAL                     42: errors
                3054    LOAD_ATTR                       90: SessionRevokedError
                3074    CHECK_EXC_MATCH                 
                3076    POP_JUMP_IF_FALSE               6 (to 3090)
                3078    POP_TOP                         
                3080    LOAD_CONST                      62: 'Ban'
                3082    STORE_FAST                      17: _var_var_25
                3084    POP_EXCEPT                      
                3086    JUMP_BACKWARD                   500 (to 2090)
                3090    LOAD_GLOBAL                     42: errors
                3100    LOAD_ATTR                       92: common
                3120    LOAD_ATTR                       94: AuthKeyNotFound
                3140    CHECK_EXC_MATCH                 
                3142    POP_JUMP_IF_FALSE               6 (to 3156)
                3144    POP_TOP                         
                3146    LOAD_CONST                      62: 'Ban'
                3148    STORE_FAST                      17: _var_var_25
                3150    POP_EXCEPT                      
                3152    JUMP_BACKWARD                   533 (to 2090)
                3156    LOAD_GLOBAL                     42: errors
                3166    LOAD_ATTR                       96: AuthKeyDuplicatedError
                3186    CHECK_EXC_MATCH                 
                3188    POP_JUMP_IF_FALSE               6 (to 3202)
                3190    POP_TOP                         
                3192    LOAD_CONST                      62: 'Ban'
                3194    STORE_FAST                      17: _var_var_25
                3196    POP_EXCEPT                      
                3198    JUMP_BACKWARD                   556 (to 2090)
                3202    LOAD_GLOBAL                     42: errors
                3212    LOAD_ATTR                       98: BadRequestError
                3232    CHECK_EXC_MATCH                 
                3234    POP_JUMP_IF_FALSE               12 (to 3260)
                3236    POP_TOP                         
                3238    PUSH_NULL                       
                3240    LOAD_CONST                      1: '__pyarmor_assert_12774__'
                3242    LOAD_CONST                      65: 'ErrorConnection'   # b'\x81\xc7\n\x01<\xe8\x9d\xdd\x15\xf4\x08\xc3x\xe5\xf7\x8b'
                3244    CALL                            1
                3252    STORE_FAST                      17: _var_var_25
                3254    POP_EXCEPT                      
                3256    JUMP_BACKWARD                   585 (to 2090)
                3260    LOAD_GLOBAL                     42: errors
                3270    LOAD_ATTR                       100: TimeoutError
                3290    CHECK_EXC_MATCH                 
                3292    POP_JUMP_IF_FALSE               12 (to 3318)
                3294    POP_TOP                         
                3296    PUSH_NULL                       
                3298    LOAD_CONST                      1: '__pyarmor_assert_12774__'
                3300    LOAD_CONST                      65: 'ErrorConnection'   # b'\x81\xc7\n\x01<\xe8\x9d\xdd\x15\xf4\x08\xc3x\xe5\xf7\x8b'
                3302    CALL                            1
                3310    STORE_FAST                      17: _var_var_25
                3312    POP_EXCEPT                      
                3314    JUMP_BACKWARD                   614 (to 2090)
                3318    LOAD_GLOBAL                     42: errors
                3328    LOAD_ATTR                       102: TimedoutError
                3348    CHECK_EXC_MATCH                 
                3350    POP_JUMP_IF_FALSE               12 (to 3376)
                3352    POP_TOP                         
                3354    PUSH_NULL                       
                3356    LOAD_CONST                      1: '__pyarmor_assert_12774__'
                3358    LOAD_CONST                      65: 'ErrorConnection'   # b'\x81\xc7\n\x01<\xe8\x9d\xdd\x15\xf4\x08\xc3x\xe5\xf7\x8b'
                3360    CALL                            1
                3368    STORE_FAST                      17: _var_var_25
                3370    POP_EXCEPT                      
                3372    JUMP_BACKWARD                   643 (to 2090)
                3376    LOAD_GLOBAL                     42: errors
                3386    LOAD_ATTR                       104: TimedOutError
                3406    CHECK_EXC_MATCH                 
                3408    POP_JUMP_IF_FALSE               12 (to 3434)
                3410    POP_TOP                         
                3412    PUSH_NULL                       
                3414    LOAD_CONST                      1: '__pyarmor_assert_12774__'
                3416    LOAD_CONST                      65: 'ErrorConnection'   # b'\x81\xc7\n\x01<\xe8\x9d\xdd\x15\xf4\x08\xc3x\xe5\xf7\x8b'
                3418    CALL                            1
                3426    STORE_FAST                      17: _var_var_25
                3428    POP_EXCEPT                      
                3430    JUMP_BACKWARD                   672 (to 2090)
                3434    LOAD_GLOBAL                     106: BaseException
                3444    CHECK_EXC_MATCH                 
                3446    POP_JUMP_IF_FALSE               12 (to 3472)
                3448    POP_TOP                         
                3450    PUSH_NULL                       
                3452    LOAD_CONST                      1: '__pyarmor_assert_12774__'
                3454    LOAD_CONST                      65: 'ErrorConnection'   # b'\x81\xc7\n\x01<\xe8\x9d\xdd\x15\xf4\x08\xc3x\xe5\xf7\x8b'
                3456    CALL                            1
                3464    STORE_FAST                      17: _var_var_25
                3466    POP_EXCEPT                      
                3468    JUMP_BACKWARD                   691 (to 2090)
                3472    RERAISE                         0
                3474    COPY                            3
                3476    POP_EXCEPT                      
                3478    RERAISE                         1
                3480    PUSH_EXC_INFO                   
                3482    POP_TOP                         
                3484    POP_EXCEPT                      
                3486    JUMP_BACKWARD                   689 (to 2112)
                3490    COPY                            3
                3492    POP_EXCEPT                      
                3494    RERAISE                         1
                3496    PUSH_EXC_INFO                   
                3498    LOAD_GLOBAL                     109: NULL + Disconnect
                3508    LOAD_FAST_CHECK                 20: _var_var_28
                3510    CALL                            1
                3518    POP_TOP                         
                3520    JUMP_FORWARD                    7 (to 3536)
                3522    PUSH_EXC_INFO                   
                3524    POP_TOP                         
                3526    POP_EXCEPT                      
                3528    JUMP_FORWARD                    3 (to 3536)
                3530    COPY                            3
                3532    POP_EXCEPT                      
                3534    RERAISE                         1
                3536    LOAD_GLOBAL                     29: NULL + Logs
                3546    LOAD_ATTR                       30: PrintLog
                3566    LOAD_FAST                       1: config
                3568    LOAD_FAST                       0: account
                3570    LOAD_CONST                      79: 'Status: '
                3572    LOAD_FAST                       17: _var_var_25
                3574    FORMAT_VALUE                    0 (FVC_NONE)
                3576    BUILD_STRING                    2
                3578    KW_NAMES                        61: ('config', 'account', 'message')
                3580    CALL                            3
                3588    POP_TOP                         
                3590    LOAD_FAST                       17: _var_var_25
                3592    PUSH_NULL                       
                3594    LOAD_CONST                      1: '__pyarmor_assert_12774__'
                3596    LOAD_CONST                      65: 'ErrorConnection'   # b'\x81\xc7\n\x01<\xe8\x9d\xdd\x15\xf4\x08\xc3x\xe5\xf7\x8b'
                3598    CALL                            1
                3606    COMPARE_OP                      40 (==)
                3610    POP_JUMP_IF_FALSE               76 (to 3764)
                3612    LOAD_FAST                       4: error
                3614    LOAD_CONST                      44: 1
                3616    BINARY_OP                       13 (+=)
                3620    STORE_FAST                      4: error
                3622    LOAD_FAST                       4: error
                3624    LOAD_CONST                      80: 3
                3626    COMPARE_OP                      2 (<)
                3630    POP_JUMP_IF_FALSE               66 (to 3764)
                3632    LOAD_GLOBAL                     29: NULL + Logs
                3642    LOAD_ATTR                       30: PrintLog
                3662    LOAD_FAST                       1: config
                3664    LOAD_FAST                       0: account
                3666    LOAD_GLOBAL                     10: Lang
                3676    PUSH_NULL                       
                3678    LOAD_CONST                      1: '__pyarmor_assert_12774__'
                3680    LOAD_CONST                      81: 'error_reconnecting'   # b'\x81\xe7\n\x01<\xe8\x81\xc0\x1e\xf9\x02\xceb\xe9\xfb\x91\x06S\xbc'
                3682    CALL                            1
                3690    BINARY_SUBSCR                   
                3694    KW_NAMES                        61: ('config', 'account', 'message')
                3696    CALL                            3
                3704    POP_TOP                         
                3706    LOAD_GLOBAL                     111: NULL + worker
                3716    LOAD_FAST                       0: account
                3718    LOAD_FAST                       1: config
                3720    LOAD_FAST                       2: proxy
                3722    LOAD_FAST                       3: data
                3724    LOAD_FAST                       4: error
                3726    LOAD_FAST                       5: stop_thread
                3728    CALL                            6
                3736    SWAP                            2
                3738    POP_TOP                         
                3740    SWAP                            2
                3742    POP_EXCEPT                      
                3744    NOP                             
                3746    NOP                             
                3748    NOP                             
                3750    JUMP_FORWARD                    245 (to 4242)
                3752    CALL                            1
                3760    POP_TOP                         
                3762    RETURN_VALUE                    
                3764    LOAD_GLOBAL                     113: NULL + set_account_json
                3774    LOAD_FAST                       10: _var_var_18
                3776    LOAD_FAST                       17: _var_var_25
                3778    LOAD_CONST                      42: 0
                3780    KW_NAMES                        82: ('file_path', 'status', 'work')
                3782    CALL                            3
                3790    POP_TOP                         
                3792    LOAD_CONST                      21: False
                3794    STORE_FAST                      29: _var_var_37
                3796    LOAD_FAST                       17: _var_var_25
                3798    LOAD_CONST                      16: 'Free'
                3800    COMPARE_OP                      40 (==)
                3804    POP_JUMP_IF_FALSE               12 (to 3830)
                3806    LOAD_GLOBAL                     115: NULL + move_acc_to_folder
                3816    LOAD_FAST                       0: account
                3818    LOAD_FAST                       13: _var_var_21
                3820    CALL                            2
                3828    STORE_FAST                      29: _var_var_37
                3830    LOAD_FAST                       17: _var_var_25
                3832    PUSH_NULL                       
                3834    LOAD_CONST                      1: '__pyarmor_assert_12774__'
                3836    LOAD_CONST                      68: 'SpamBlock'   # b'\x81\xd1\x08\x12>\xd8\xb2\xdd\x18\xf1'
                3838    CALL                            1
                3846    COMPARE_OP                      40 (==)
                3850    POP_JUMP_IF_FALSE               12 (to 3876)
                3852    LOAD_GLOBAL                     115: NULL + move_acc_to_folder
                3862    LOAD_FAST                       0: account
                3864    LOAD_FAST                       14: _var_var_22
                3866    CALL                            2
                3874    STORE_FAST                      29: _var_var_37
                3876    LOAD_FAST                       17: _var_var_25
                3878    LOAD_CONST                      62: 'Ban'
                3880    COMPARE_OP                      40 (==)
                3884    POP_JUMP_IF_FALSE               12 (to 3910)
                3886    LOAD_GLOBAL                     115: NULL + move_acc_to_folder
                3896    LOAD_FAST                       0: account
                3898    LOAD_FAST                       16: _var_var_24
                3900    CALL                            2
                3908    STORE_FAST                      29: _var_var_37
                3910    PUSH_NULL                       
                3912    LOAD_CONST                      1: '__pyarmor_assert_12774__'
                3914    LOAD_CONST                      83: 'TempSpamBlock'   # b'\x81\xd6\x1d\x1e#\xc9\xae\xd3\x16\xd8\x01\xcfo\xe7'
                3916    CALL                            1
                3924    LOAD_FAST                       17: _var_var_25
                3926    CONTAINS_OP                     0 (in)
                3928    POP_JUMP_IF_FALSE               12 (to 3954)
                3930    LOAD_GLOBAL                     115: NULL + move_acc_to_folder
                3940    LOAD_FAST                       0: account
                3942    LOAD_FAST                       15: _var_var_23
                3944    CALL                            2
                3952    STORE_FAST                      29: _var_var_37
                3954    LOAD_FAST                       29: _var_var_37
                3956    POP_JUMP_IF_FALSE               37 (to 4032)
                3958    LOAD_GLOBAL                     29: NULL + Logs
                3968    LOAD_ATTR                       30: PrintLog
                3988    LOAD_FAST                       1: config
                3990    LOAD_FAST                       0: account
                3992    LOAD_GLOBAL                     10: Lang
                4002    PUSH_NULL                       
                4004    LOAD_CONST                      1: '__pyarmor_assert_12774__'
                4006    LOAD_CONST                      84: 'account_is_move_success'   # b'\x81\xe3\x1b\x10<\xef\xb0\xc6$\xf3\x1e\xffa\xe3\xee\x800N\xae\xa4\xa9\xce]\xdf'
                4008    CALL                            1
                4016    BINARY_SUBSCR                   
                4020    KW_NAMES                        61: ('config', 'account', 'message')
                4022    CALL                            3
                4030    POP_TOP                         
                4032    LOAD_GLOBAL                     29: NULL + Logs
                4042    LOAD_ATTR                       30: PrintLog
                4062    LOAD_FAST                       1: config
                4064    LOAD_FAST                       0: account
                4066    LOAD_GLOBAL                     10: Lang
                4076    PUSH_NULL                       
                4078    LOAD_CONST                      1: '__pyarmor_assert_12774__'
                4080    LOAD_CONST                      85: 'work_account_completed'   # b'\x81\xf5\x17\x018\xc5\xbf\xd1\x18\xf5\x18\xcex\xd3\xfb\x8a\x02M\xb7\xa2\xbe\xceJ'
                4082    CALL                            1
                4090    BINARY_SUBSCR                   
                4094    KW_NAMES                        61: ('config', 'account', 'message')
                4096    CALL                            3
                4104    POP_TOP                         
                4106    RERAISE                         0
                4108    COPY                            3
                4110    POP_EXCEPT                      
                4112    RERAISE                         1
                4114    PUSH_EXC_INFO                   
                4116    LOAD_GLOBAL                     16: StopProgram
                4126    CHECK_EXC_MATCH                 
                4128    POP_JUMP_IF_FALSE               4 (to 4138)
                4130    POP_TOP                         
                4132    POP_EXCEPT                      
                4134    JUMP_BACKWARD                   731 (to 2676)
                4138    LOAD_GLOBAL                     106: BaseException
                4148    CHECK_EXC_MATCH                 
                4150    POP_JUMP_IF_FALSE               27 (to 4206)
                4152    STORE_FAST                      30: _var_var_3
                4154    PUSH_NULL                       
                4156    LOAD_GLOBAL                     117: NULL + logging
                4166    LOAD_FAST                       30: _var_var_3
                4168    CALL                            1
                4176    CALL                            0
                4184    POP_TOP                         
                4186    POP_EXCEPT                      
                4188    LOAD_CONST                      0: None
                4190    STORE_FAST                      30: _var_var_3
                4192    DELETE_FAST                     30: _var_var_3
                4194    JUMP_BACKWARD                   761 (to 2676)
                4198    LOAD_CONST                      0: None
                4200    STORE_FAST                      30: _var_var_3
                4202    DELETE_FAST                     30: _var_var_3
                4204    RERAISE                         1
                4206    RERAISE                         0
                4208    COPY                            3
                4210    POP_EXCEPT                      
                4212    RERAISE                         1
                4214    PUSH_EXC_INFO                   
                4216    PUSH_NULL                       
                4218    LOAD_CONST                      20: '__pyarmor_exit_12776__'
                4220    NOP                             
                4222    LOAD_CONST                      3: b'<COAddr>\x07\x00\x00\x1a\\\x10\x00\x00\x00\x00\x00\x00\x00\x00\x00\x00\x00\x00\x00\x00'
                4224    CALL                            1
                4232    POP_TOP                         
                4234    RERAISE                         0
                4236    COPY                            3
                4238    POP_EXCEPT                      
                4240    RERAISE                         1
                4242    PUSH_NULL                       
                4244    LOAD_CONST                      20: '__pyarmor_exit_12776__'
                4246    LOAD_CONST                      3: b'<COAddr>\x07\x00\x00\x1a\\\x10\x00\x00\x00\x00\x00\x00\x00\x00\x00\x00\x00\x00\x00\x00'
                4248    BUILD_TUPLE                     1
                4250    CALL_FUNCTION_EX                0
                4252    POP_TOP                         
                4254    RETURN_VALUE                    
            [Exception Table]
                30 to 504 -> 4114 [0] 
                526 to 578 -> 4114 [0] 
                580 to 1310 -> 2904 [0] 
                1312 to 1348 -> 2704 [0] 
                1348 to 2090 -> 2904 [0] 
                2090 to 2112 -> 3480 [0] 
                2112 to 2312 -> 4114 [0] 
                2332 to 2674 -> 4114 [0] 
                2674 to 2684 -> 4214 [0] 
                2704 to 2852 -> 2898 [1] lasti
                2852 to 2858 -> 2904 [0] 
                2858 to 2890 -> 2898 [1] lasti
                2890 to 2896 -> 2904 [0] 
                2896 to 2898 -> 2898 [1] lasti
                2898 to 2904 -> 2904 [0] 
                2904 to 2946 -> 3474 [1] lasti
                2946 to 2952 -> 3496 [0] 
                2952 to 2992 -> 3474 [1] lasti
                2992 to 2998 -> 3496 [0] 
                2998 to 3038 -> 3474 [1] lasti
                3038 to 3044 -> 3496 [0] 
                3044 to 3084 -> 3474 [1] lasti
                3084 to 3090 -> 3496 [0] 
                3090 to 3150 -> 3474 [1] lasti
                3150 to 3156 -> 3496 [0] 
                3156 to 3196 -> 3474 [1] lasti
                3196 to 3202 -> 3496 [0] 
                3202 to 3254 -> 3474 [1] lasti
                3254 to 3260 -> 3496 [0] 
                3260 to 3312 -> 3474 [1] lasti
                3312 to 3318 -> 3496 [0] 
                3318 to 3370 -> 3474 [1] lasti
                3370 to 3376 -> 3496 [0] 
                3376 to 3428 -> 3474 [1] lasti
                3428 to 3434 -> 3496 [0] 
                3434 to 3466 -> 3474 [1] lasti
                3466 to 3472 -> 3496 [0] 
                3472 to 3474 -> 3474 [1] lasti
                3474 to 3480 -> 3496 [0] 
                3480 to 3484 -> 3490 [1] lasti
                3484 to 3496 -> 4114 [0] 
                3496 to 3498 -> 4108 [1] lasti
                3498 to 3520 -> 3522 [2] 
                3520 to 3522 -> 4108 [1] lasti
                3522 to 3526 -> 3530 [3] lasti
                3526 to 3742 -> 4108 [1] lasti
                3742 to 3744 -> 4114 [0] 
                3764 to 4108 -> 4108 [1] lasti
                4108 to 4114 -> 4114 [0] 
                4114 to 4132 -> 4208 [1] lasti
                4132 to 4138 -> 4214 [0] 
                4138 to 4154 -> 4208 [1] lasti
                4154 to 4186 -> 4198 [1] lasti
                4186 to 4198 -> 4214 [0] 
                4198 to 4208 -> 4208 [1] lasti
                4208 to 4214 -> 4214 [0] 
                4214 to 4236 -> 4236 [1] lasti
        [Code]
            File Name: <frozen program.modules.accounts_check>
            Object Name: move_acc_to_folder
            Qualified Name: move_acc_to_folder
            Arg Count: 2
            Pos Only Arg Count: 0
            KW Only Arg Count: 0
            Stack Size: 5
            Flags: 0x20000003 (CO_OPTIMIZED | CO_NEWLOCALS | CO_PYARMOR_OBFUSCATED)
            [Names]
                'Path'
                'os'
                'replace'
                'BaseException'
                'logging'
            [Locals+Names]
                'account'
                'destination'
                '__assert_armored__'
                '_var_var_15'
                '_var_var_38'
                '_var_var_39'
                '_var_var_40'
                '_var_var_41'
                '_var_var_42'
                '_var_var_3'
            [Constants]
                None
                '__pyarmor_assert_12777__'
                '__pyarmor_enter_12778__'
                b'<COAddr>\x05\x00\x00\x1a|\x01\x00\x00\x00\x00\x00\x00\x00\x00\x00\x00\x00\x00\x00\x00'
                'sessions/active'   # b'\x81\xf1\x1d\x00 \xf3\xb1\xdc\x08\xb5\x0c\xc3x\xe5\xee\x80'
                'sessions/'   # b'\x81\xf1\x1d\x00 \xf3\xb1\xdc\x08\xb5'
                '__pyarmor_exit_12779__'
                False
                '.json'
                '.session'
                True
            [Disassembly]
                0       NOP                             
                2       NOP                             
                4       PUSH_NULL                       
                6       LOAD_CONST                      2: '__pyarmor_enter_12778__'
                8       LOAD_CONST                      3: b'<COAddr>\x05\x00\x00\x1a|\x01\x00\x00\x00\x00\x00\x00\x00\x00\x00\x00\x00\x00\x00\x00'
                10      BUILD_TUPLE                     1
                12      CALL_FUNCTION_EX                0
                14      POP_TOP                         
                16      RESUME                          0
                18      NOP                             
                20      NOP                             
                22      NOP                             
                24      NOP                             
                26      NOP                             
                28      NOP                             
                30      LOAD_GLOBAL                     1: NULL + Path
                40      PUSH_NULL                       
                42      LOAD_CONST                      1: '__pyarmor_assert_12777__'
                44      LOAD_CONST                      4: 'sessions/active'   # b'\x81\xf1\x1d\x00 \xf3\xb1\xdc\x08\xb5\x0c\xc3x\xe5\xee\x80'
                46      CALL                            1
                54      CALL                            1
                62      STORE_FAST                      3: _var_var_15
                64      LOAD_GLOBAL                     1: NULL + Path
                74      PUSH_NULL                       
                76      LOAD_CONST                      1: '__pyarmor_assert_12777__'
                78      LOAD_CONST                      5: 'sessions/'   # b'\x81\xf1\x1d\x00 \xf3\xb1\xdc\x08\xb5'
                80      CALL                            1
                88      LOAD_FAST                       1: destination
                90      FORMAT_VALUE                    0 (FVC_NONE)
                92      BUILD_STRING                    2
                94      CALL                            1
                102     STORE_FAST                      4: _var_var_38
                104     LOAD_FAST                       3: _var_var_15
                106     LOAD_FAST                       4: _var_var_38
                108     COMPARE_OP                      40 (==)
                112     POP_JUMP_IF_FALSE               11 (to 136)
                114     NOP                             
                116     LOAD_CONST                      7: False
                118     NOP                             
                120     NOP                             
                122     NOP                             
                124     JUMP_FORWARD                    154 (to 434)
                132     POP_TOP                         
                134     RETURN_CONST                    7: False
                136     LOAD_FAST                       3: _var_var_15
                138     LOAD_FAST                       0: account
                140     FORMAT_VALUE                    0 (FVC_NONE)
                142     LOAD_CONST                      8: '.json'
                144     BUILD_STRING                    2
                146     BINARY_OP                       11 (/)
                150     STORE_FAST                      5: _var_var_39
                152     LOAD_FAST                       3: _var_var_15
                154     LOAD_FAST                       0: account
                156     FORMAT_VALUE                    0 (FVC_NONE)
                158     LOAD_CONST                      9: '.session'
                160     BUILD_STRING                    2
                162     BINARY_OP                       11 (/)
                166     STORE_FAST                      6: _var_var_40
                168     LOAD_FAST                       4: _var_var_38
                170     LOAD_FAST                       0: account
                172     FORMAT_VALUE                    0 (FVC_NONE)
                174     LOAD_CONST                      8: '.json'
                176     BUILD_STRING                    2
                178     BINARY_OP                       11 (/)
                182     STORE_FAST                      7: _var_var_41
                184     LOAD_FAST                       4: _var_var_38
                186     LOAD_FAST                       0: account
                188     FORMAT_VALUE                    0 (FVC_NONE)
                190     LOAD_CONST                      9: '.session'
                192     BUILD_STRING                    2
                194     BINARY_OP                       11 (/)
                198     STORE_FAST                      8: _var_var_42
                200     LOAD_GLOBAL                     3: NULL + os
                210     LOAD_ATTR                       4: replace
                230     LOAD_FAST                       6: _var_var_40
                232     LOAD_FAST                       8: _var_var_42
                234     CALL                            2
                242     POP_TOP                         
                244     LOAD_GLOBAL                     3: NULL + os
                254     LOAD_ATTR                       4: replace
                274     LOAD_FAST                       5: _var_var_39
                276     LOAD_FAST                       7: _var_var_41
                278     CALL                            2
                286     POP_TOP                         
                288     NOP                             
                290     LOAD_CONST                      10: True
                292     NOP                             
                294     NOP                             
                296     NOP                             
                298     JUMP_FORWARD                    67 (to 434)
                306     POP_TOP                         
                308     RETURN_CONST                    10: True
                310     PUSH_EXC_INFO                   
                312     LOAD_GLOBAL                     6: BaseException
                322     CHECK_EXC_MATCH                 
                324     POP_JUMP_IF_FALSE               26 (to 378)
                326     STORE_FAST                      9: _var_var_3
                328     PUSH_NULL                       
                330     LOAD_GLOBAL                     9: NULL + logging
                340     LOAD_FAST                       9: _var_var_3
                342     CALL                            1
                350     CALL                            0
                358     POP_TOP                         
                360     POP_EXCEPT                      
                362     LOAD_CONST                      0: None
                364     STORE_FAST                      9: _var_var_3
                366     DELETE_FAST                     9: _var_var_3
                368     JUMP_FORWARD                    8 (to 386)
                370     LOAD_CONST                      0: None
                372     STORE_FAST                      9: _var_var_3
                374     DELETE_FAST                     9: _var_var_3
                376     RERAISE                         1
                378     RERAISE                         0
                380     COPY                            3
                382     POP_EXCEPT                      
                384     RERAISE                         1
                386     LOAD_CONST                      7: False
                388     NOP                             
                390     NOP                             
                392     NOP                             
                394     JUMP_FORWARD                    19 (to 434)
                402     POP_TOP                         
                404     RETURN_CONST                    7: False
                406     PUSH_EXC_INFO                   
                408     PUSH_NULL                       
                410     LOAD_CONST                      6: '__pyarmor_exit_12779__'
                412     NOP                             
                414     LOAD_CONST                      3: b'<COAddr>\x05\x00\x00\x1a|\x01\x00\x00\x00\x00\x00\x00\x00\x00\x00\x00\x00\x00\x00\x00'
                416     CALL                            1
                424     POP_TOP                         
                426     RERAISE                         0
                428     COPY                            3
                430     POP_EXCEPT                      
                432     RERAISE                         1
                434     PUSH_NULL                       
                436     LOAD_CONST                      6: '__pyarmor_exit_12779__'
                438     LOAD_CONST                      3: b'<COAddr>\x05\x00\x00\x1a|\x01\x00\x00\x00\x00\x00\x00\x00\x00\x00\x00\x00\x00\x00\x00'
                440     BUILD_TUPLE                     1
                442     CALL_FUNCTION_EX                0
                444     POP_TOP                         
                446     RETURN_VALUE                    
            [Exception Table]
                30 to 114 -> 310 [0] 
                136 to 288 -> 310 [0] 
                310 to 328 -> 380 [1] lasti
                328 to 360 -> 370 [1] lasti
                360 to 370 -> 406 [0] 
                370 to 380 -> 380 [1] lasti
                380 to 386 -> 406 [0] 
                406 to 428 -> 428 [1] lasti
        '__pyarmor_exit_12767__'
    [Disassembly]
        0       NOP                             
        2       NOP                             
        4       PUSH_NULL                       
        6       LOAD_CONST                      1: '__pyarmor_enter_12766__'
        8       LOAD_CONST                      2: b'<COAddr>\x05\x00\x00\x1al\x01\x00\x00\x00\x00\x00\x00\x00\x00\x00\x00\x00\x00\x00\x00'
        10      BUILD_TUPLE                     1
        12      CALL_FUNCTION_EX                0
        14      POP_TOP                         
        16      RESUME                          0
        18      NOP                             
        20      NOP                             
        22      NOP                             
        24      NOP                             
        26      LOAD_CONST                      3: 0
        28      LOAD_CONST                      4: None
        30      IMPORT_NAME                     1: os
        32      STORE_NAME                      1: os
        34      LOAD_CONST                      3: 0
        36      LOAD_CONST                      4: None
        38      IMPORT_NAME                     2: re
        40      STORE_NAME                      2: re
        42      LOAD_CONST                      3: 0
        44      LOAD_CONST                      4: None
        46      IMPORT_NAME                     3: eel
        48      STORE_NAME                      3: eel
        50      LOAD_CONST                      3: 0
        52      LOAD_CONST                      4: None
        54      IMPORT_NAME                     4: time
        56      STORE_NAME                      4: time
        58      LOAD_CONST                      3: 0
        60      LOAD_CONST                      4: None
        62      IMPORT_NAME                     5: json
        64      STORE_NAME                      5: json
        66      LOAD_CONST                      3: 0
        68      LOAD_CONST                      4: None
        70      IMPORT_NAME                     6: asyncio
        72      STORE_NAME                      6: asyncio
        74      LOAD_CONST                      3: 0
        76      LOAD_CONST                      4: None
        78      IMPORT_NAME                     7: concurrent.futures
        80      STORE_NAME                      8: concurrent
        82      LOAD_CONST                      3: 0
        84      LOAD_CONST                      5: ('Thread', 'Event')
        86      IMPORT_NAME                     9: threading
        88      IMPORT_FROM                     10: Thread
        90      STORE_NAME                      10: Thread
        92      IMPORT_FROM                     11: Event
        94      STORE_NAME                      11: Event
        96      POP_TOP                         
        98      LOAD_CONST                      3: 0
        100     LOAD_CONST                      6: ('TelegramClient', 'functions', 'errors')
        102     IMPORT_NAME                     12: multithon.sync
        104     IMPORT_FROM                     13: TelegramClient
        106     STORE_NAME                      13: TelegramClient
        108     IMPORT_FROM                     14: functions
        110     STORE_NAME                      14: functions
        112     IMPORT_FROM                     15: errors
        114     STORE_NAME                      15: errors
        116     POP_TOP                         
        118     LOAD_CONST                      3: 0
        120     LOAD_CONST                      7: ('Path',)
        122     IMPORT_NAME                     16: pathlib
        124     IMPORT_FROM                     17: Path
        126     STORE_NAME                      17: Path
        128     POP_TOP                         
        130     LOAD_CONST                      3: 0
        132     LOAD_CONST                      8: ('StopProgram',)
        134     IMPORT_NAME                     18: multithon.errors
        136     IMPORT_FROM                     19: StopProgram
        138     STORE_NAME                      19: StopProgram
        140     POP_TOP                         
        142     LOAD_CONST                      3: 0
        144     LOAD_CONST                      9: ('GetLang',)
        146     IMPORT_NAME                     20: program.static_classes
        148     IMPORT_FROM                     21: GetLang
        150     STORE_NAME                      21: GetLang
        152     POP_TOP                         
        154     LOAD_CONST                      3: 0
        156     LOAD_CONST                      10: ('Logs',)
        158     IMPORT_NAME                     20: program.static_classes
        160     IMPORT_FROM                     22: Logs
        162     STORE_NAME                      22: Logs
        164     POP_TOP                         
        166     LOAD_CONST                      3: 0
        168     LOAD_CONST                      11: ('VersionControl',)
        170     IMPORT_NAME                     20: program.static_classes
        172     IMPORT_FROM                     23: VersionControl
        174     STORE_NAME                      23: VersionControl
        176     POP_TOP                         
        178     LOAD_CONST                      3: 0
        180     LOAD_CONST                      12: ('get_logger',)
        182     IMPORT_NAME                     20: program.static_classes
        184     IMPORT_FROM                     24: get_logger
        186     STORE_NAME                      24: get_logger
        188     POP_TOP                         
        190     LOAD_CONST                      3: 0
        192     LOAD_CONST                      13: ('logging',)
        194     IMPORT_NAME                     20: program.static_classes
        196     IMPORT_FROM                     25: logging
        198     STORE_NAME                      25: logging
        200     POP_TOP                         
        202     LOAD_CONST                      3: 0
        204     LOAD_CONST                      14: ('memory_check_switcher',)
        206     IMPORT_NAME                     20: program.static_classes
        208     IMPORT_FROM                     26: memory_check_switcher
        210     STORE_NAME                      26: memory_check_switcher
        212     POP_TOP                         
        214     LOAD_CONST                      3: 0
        216     LOAD_CONST                      15: ('memory_set_pid',)
        218     IMPORT_NAME                     20: program.static_classes
        220     IMPORT_FROM                     27: memory_set_pid
        222     STORE_NAME                      27: memory_set_pid
        224     POP_TOP                         
        226     LOAD_CONST                      3: 0
        228     LOAD_CONST                      16: ('proxy_hide',)
        230     IMPORT_NAME                     20: program.static_classes
        232     IMPORT_FROM                     28: proxy_hide
        234     STORE_NAME                      28: proxy_hide
        236     POP_TOP                         
        238     LOAD_CONST                      3: 0
        240     LOAD_CONST                      17: ('Disconnect',)
        242     IMPORT_NAME                     29: program.telegram
        244     IMPORT_FROM                     30: Disconnect
        246     STORE_NAME                      30: Disconnect
        248     POP_TOP                         
        250     LOAD_CONST                      3: 0
        252     LOAD_CONST                      18: ('Thread_wait',)
        254     IMPORT_NAME                     29: program.telegram
        256     IMPORT_FROM                     31: Thread_wait
        258     STORE_NAME                      31: Thread_wait
        260     POP_TOP                         
        262     LOAD_CONST                      3: 0
        264     LOAD_CONST                      19: ('get_account_json',)
        266     IMPORT_NAME                     29: program.telegram
        268     IMPORT_FROM                     32: get_account_json
        270     STORE_NAME                      32: get_account_json
        272     POP_TOP                         
        274     LOAD_CONST                      3: 0
        276     LOAD_CONST                      20: ('get_account_proxy',)
        278     IMPORT_NAME                     29: program.telegram
        280     IMPORT_FROM                     33: get_account_proxy
        282     STORE_NAME                      33: get_account_proxy
        284     POP_TOP                         
        286     LOAD_CONST                      3: 0
        288     LOAD_CONST                      21: ('set_account_json',)
        290     IMPORT_NAME                     29: program.telegram
        292     IMPORT_FROM                     34: set_account_json
        294     STORE_NAME                      34: set_account_json
        296     POP_TOP                         
        298     LOAD_CONST                      3: 0
        300     LOAD_CONST                      22: ('GetConfig',)
        302     IMPORT_NAME                     35: program.general
        304     IMPORT_FROM                     36: GetConfig
        306     STORE_NAME                      36: GetConfig
        308     POP_TOP                         
        310     LOAD_CONST                      3: 0
        312     LOAD_CONST                      23: ('GetProxy',)
        314     IMPORT_NAME                     35: program.general
        316     IMPORT_FROM                     37: GetProxy
        318     STORE_NAME                      37: GetProxy
        320     POP_TOP                         
        322     LOAD_CONST                      3: 0
        324     LOAD_CONST                      24: ('StopDetect',)
        326     IMPORT_NAME                     35: program.general
        328     IMPORT_FROM                     38: StopDetect
        330     STORE_NAME                      38: StopDetect
        332     POP_TOP                         
        334     LOAD_CONST                      3: 0
        336     LOAD_CONST                      25: ('check_get_settings',)
        338     IMPORT_NAME                     35: program.general
        340     IMPORT_FROM                     39: check_get_settings
        342     STORE_NAME                      39: check_get_settings
        344     POP_TOP                         
        346     LOAD_CONST                      26: <CODE> accounts_check
        348     MAKE_FUNCTION                   0
        350     STORE_NAME                      40: accounts_check
        352     LOAD_CONST                      27: <CODE> START
        354     MAKE_FUNCTION                   0
        356     STORE_NAME                      41: START
        358     LOAD_CONST                      28: <CODE> worker
        360     MAKE_FUNCTION                   0
        362     STORE_NAME                      42: worker
        364     LOAD_CONST                      29: <CODE> move_acc_to_folder
        366     MAKE_FUNCTION                   0
        368     STORE_NAME                      43: move_acc_to_folder
        370     LOAD_CONST                      4: None
        372     NOP                             
        374     NOP                             
        376     NOP                             
        378     JUMP_FORWARD                    19 (to 418)
        386     POP_TOP                         
        388     RETURN_CONST                    4: None
        390     PUSH_EXC_INFO                   
        392     PUSH_NULL                       
        394     LOAD_CONST                      30: '__pyarmor_exit_12767__'
        396     NOP                             
        398     LOAD_CONST                      2: b'<COAddr>\x05\x00\x00\x1al\x01\x00\x00\x00\x00\x00\x00\x00\x00\x00\x00\x00\x00\x00\x00'
        400     CALL                            1
        408     POP_TOP                         
        410     RERAISE                         0
        412     COPY                            3
        414     POP_EXCEPT                      
        416     RERAISE                         1
        418     PUSH_NULL                       
        420     LOAD_CONST                      30: '__pyarmor_exit_12767__'
        422     LOAD_CONST                      2: b'<COAddr>\x05\x00\x00\x1al\x01\x00\x00\x00\x00\x00\x00\x00\x00\x00\x00\x00\x00\x00\x00'
        424     BUILD_TUPLE                     1
        426     CALL_FUNCTION_EX                0
        428     POP_TOP                         
        430     RETURN_VALUE                    
    [Exception Table]
        26 to 370 -> 390 [0] 
        390 to 412 -> 412 [1] lasti
