#decoded by lolz.live/mrpenny / t.me/zeus_jackpot
# ================================
# Примечания по Pyarmor:
# - Байт-код и объекты кода Pyarmor соответствуют стандартному Python, но присутствуют специальные вызовы функций среды выполнения (runtime) Pyarmor.
# - Вызовы строк — это не ошибки, а маркеры, которые обрабатываются Pyarmor во время выполнения.
#
# Руководство по декомпиляции (без среды выполнения):
# 1. Игнорируйте зашифрованные байты после `#`; используйте только строку до `#`.
# 2. Удалите "__pyarmor_enter_xxx__"(b"<COAddr>...") и "__pyarmor_leave_xxx__"(b"<COAddr>...") (пролог/эпилог).
# 3. "__pyarmor_assert_xxx__"(A) не является настоящим оператором assert.
#    - Если A — это имя или читаемая строка: замените на A.
#    - Если A — это (X, "Y"): замените на X.Y.
#    - Если A — это (X, "Y", Z): замените на X.Y = Z.
#    - В противном случае: выберите наиболее подходящую/логичную замену.
# 4. "__pyarmor_bcc_xxx__"(...) указывает на машинный (нативный) код; тело функции недоступно. Добавьте комментарий.
# ================================

[Code]
    File Name: <frozen program.modules.Check_links_no_accounts>
    Object Name: <module>
    Qualified Name: <module>
    Arg Count: 0
    Pos Only Arg Count: 0
    KW Only Arg Count: 0
    Stack Size: 5
    Flags: 0x20000000 (CO_PYARMOR_OBFUSCATED)
    [Names]
        '__assert_armored__'
        're'
        'eel'
        'json'
        'time'
        'random'
        'sqlite3'
        'requests'
        'datetime'
        'concurrent.futures'
        'concurrent'
        'threading'
        'Thread'
        'Event'
        'requests.adapters'
        'HTTPAdapter'
        'Retry'
        'multithon.errors'
        'StopProgram'
        'program.static_classes'
        'GetLang'
        'Logs'
        'logging'
        'memory_check_switcher'
        'memory_set_pid'
        'program.telegram'
        'Thread_wait'
        'tg_links'
        'program.general'
        'GetConfig'
        'GetProxy'
        'StopDetect'
        'del_task_manager'
        'program.database'
        'db_check_links_no_accounts'
        'Check_links_no_accounts'
        'START'
        'write_to_file'
        'extract_number'
        'worker'
    [Locals+Names]
    [Constants]
        '__pyarmor_assert_13179__'
        '__pyarmor_enter_13180__'
        b'<COAddr>\x05\x00\x00\x1a8\x01\x00\x00\x00\x00\x00\x00\x00\x00\x00\x00\x00\x00\x00\x00'
        0
        None
        (
            'Thread'
            'Event'
        )
        (
            'HTTPAdapter'
            'Retry'
        )
        (
            'StopProgram'
        )
        (
            'GetLang'
        )
        (
            'Logs'
        )
        (
            'logging'
        )
        (
            'memory_check_switcher'
        )
        (
            'memory_set_pid'
        )
        (
            'Thread_wait'
        )
        (
            'tg_links'
        )
        (
            'GetConfig'
        )
        (
            'GetProxy'
        )
        (
            'StopDetect'
        )
        (
            'del_task_manager'
        )
        (
            'db_check_links_no_accounts'
        )
        [Code]
            File Name: <frozen program.modules.Check_links_no_accounts>
            Object Name: Check_links_no_accounts
            Qualified Name: Check_links_no_accounts
            Arg Count: 1
            Pos Only Arg Count: 0
            KW Only Arg Count: 0
            Stack Size: 8
            Flags: 0x20000003 (CO_OPTIMIZED | CO_NEWLOCALS | CO_PYARMOR_OBFUSCATED)
            [Names]
                'GetConfig'
                'config'
                'GetLang'
                'Lang'
                'GetProxy'
                'eel'
                'sendSuccessBox'
                'memory_check_switcher'
                'Event'
                'memory_set_pid'
                'Thread'
                'START'
                'start'
                'Logs'
                'WaitStopAnsfer'
                'UpdateLogInWindow'
                'BaseException'
                'logging'
            [Locals+Names]
                'data'
                '__assert_armored__'
                '_var_var_0'
                '_var_var_1'
                '_var_var_2'
                '_var_var_3'
            [Constants]
                None
                '__pyarmor_assert_13182__'
                '__pyarmor_enter_13183__'
                b'<COAddr>\x07\x00\x00\x1aT\x02\x00\x00\x00\x00\x00\x00\x00\x00\x00\x00\x00\x00\x00\x00'
                'program_running'   # b'\x81\xf2\n\x1c4\xe8\xbf\xdf$\xe8\x18\xceb\xe5\xf6\x82'
                '__pyarmor_exit_13184__'
                False
                (
                    'target'
                    'args'
                )
                True
                (
                    'target'
                    'args'
                    'daemon'
                )
            [Disassembly]
                0       NOP                             
                2       NOP                             
                4       PUSH_NULL                       
                6       LOAD_CONST                      2: '__pyarmor_enter_13183__'
                8       LOAD_CONST                      3: b'<COAddr>\x07\x00\x00\x1aT\x02\x00\x00\x00\x00\x00\x00\x00\x00\x00\x00\x00\x00\x00\x00'
                10      BUILD_TUPLE                     1
                12      CALL_FUNCTION_EX                0
                14      POP_TOP                         
                16      RESUME                          0
                18      NOP                             
                20      NOP                             
                22      NOP                             
                24      NOP                             
                26      NOP                             
                28      NOP                             
                30      LOAD_GLOBAL                     1: NULL + GetConfig
                40      CALL                            0
                48      STORE_GLOBAL                    1: config
                50      LOAD_GLOBAL                     5: NULL + GetLang
                60      LOAD_GLOBAL                     2: config
                70      CALL                            1
                78      STORE_GLOBAL                    3: Lang
                80      LOAD_GLOBAL                     9: NULL + GetProxy
                90      CALL                            0
                98      STORE_FAST                      2: _var_var_0
                100     LOAD_GLOBAL                     11: NULL + eel
                110     LOAD_ATTR                       12: sendSuccessBox
                130     LOAD_GLOBAL                     6: Lang
                140     PUSH_NULL                       
                142     LOAD_CONST                      1: '__pyarmor_assert_13182__'
                144     LOAD_CONST                      4: 'program_running'   # b'\x81\xf2\n\x1c4\xe8\xbf\xdf$\xe8\x18\xceb\xe5\xf6\x82'
                146     CALL                            1
                154     BINARY_SUBSCR                   
                158     CALL                            1
                166     POP_TOP                         
                168     LOAD_GLOBAL                     15: NULL + memory_check_switcher
                178     CALL                            0
                186     POP_JUMP_IF_TRUE                11 (to 210)
                188     NOP                             
                190     LOAD_CONST                      6: False
                192     NOP                             
                194     NOP                             
                196     NOP                             
                198     JUMP_FORWARD                    225 (to 650)
                206     POP_TOP                         
                208     RETURN_CONST                    6: False
                210     LOAD_GLOBAL                     17: NULL + Event
                220     CALL                            0
                228     STORE_FAST                      3: _var_var_1
                230     LOAD_GLOBAL                     19: NULL + memory_set_pid
                240     CALL                            0
                248     STORE_FAST                      4: _var_var_2
                250     LOAD_GLOBAL                     21: NULL + Thread
                260     LOAD_GLOBAL                     22: START
                270     LOAD_FAST                       0: data
                272     LOAD_GLOBAL                     2: config
                282     LOAD_FAST                       4: _var_var_2
                284     LOAD_FAST                       2: _var_var_0
                286     LOAD_FAST                       3: _var_var_1
                288     BUILD_TUPLE                     5
                290     KW_NAMES                        7: ('target', 'args')
                292     CALL                            2
                300     LOAD_ATTR                       25: start
                320     CALL                            0
                328     POP_TOP                         
                330     LOAD_GLOBAL                     21: NULL + Thread
                340     LOAD_GLOBAL                     26: Logs
                350     LOAD_ATTR                       28: WaitStopAnsfer
                370     LOAD_GLOBAL                     2: config
                380     LOAD_FAST                       4: _var_var_2
                382     LOAD_FAST                       3: _var_var_1
                384     BUILD_TUPLE                     3
                386     LOAD_CONST                      8: True
                388     KW_NAMES                        9: ('target', 'args', 'daemon')
                390     CALL                            3
                398     LOAD_ATTR                       25: start
                418     CALL                            0
                426     POP_TOP                         
                428     LOAD_GLOBAL                     21: NULL + Thread
                438     LOAD_GLOBAL                     26: Logs
                448     LOAD_ATTR                       30: UpdateLogInWindow
                468     LOAD_GLOBAL                     2: config
                478     LOAD_FAST                       4: _var_var_2
                480     LOAD_FAST                       3: _var_var_1
                482     BUILD_TUPLE                     3
                484     LOAD_CONST                      8: True
                486     KW_NAMES                        9: ('target', 'args', 'daemon')
                488     CALL                            3
                496     LOAD_ATTR                       25: start
                516     CALL                            0
                524     POP_TOP                         
                526     LOAD_CONST                      0: None
                528     NOP                             
                530     NOP                             
                532     NOP                             
                534     JUMP_FORWARD                    57 (to 650)
                542     POP_TOP                         
                544     RETURN_CONST                    0: None
                546     PUSH_EXC_INFO                   
                548     LOAD_GLOBAL                     32: BaseException
                558     CHECK_EXC_MATCH                 
                560     POP_JUMP_IF_FALSE               26 (to 614)
                562     STORE_FAST                      5: _var_var_3
                564     PUSH_NULL                       
                566     LOAD_GLOBAL                     35: NULL + logging
                576     LOAD_FAST                       5: _var_var_3
                578     CALL                            1
                586     CALL                            0
                594     POP_TOP                         
                596     POP_EXCEPT                      
                598     LOAD_CONST                      0: None
                600     STORE_FAST                      5: _var_var_3
                602     DELETE_FAST                     5: _var_var_3
                604     JUMP_BACKWARD                   40 (to 526)
                606     LOAD_CONST                      0: None
                608     STORE_FAST                      5: _var_var_3
                610     DELETE_FAST                     5: _var_var_3
                612     RERAISE                         1
                614     RERAISE                         0
                616     COPY                            3
                618     POP_EXCEPT                      
                620     RERAISE                         1
                622     PUSH_EXC_INFO                   
                624     PUSH_NULL                       
                626     LOAD_CONST                      5: '__pyarmor_exit_13184__'
                628     NOP                             
                630     LOAD_CONST                      3: b'<COAddr>\x07\x00\x00\x1aT\x02\x00\x00\x00\x00\x00\x00\x00\x00\x00\x00\x00\x00\x00\x00'
                632     CALL                            1
                640     POP_TOP                         
                642     RERAISE                         0
                644     COPY                            3
                646     POP_EXCEPT                      
                648     RERAISE                         1
                650     PUSH_NULL                       
                652     LOAD_CONST                      5: '__pyarmor_exit_13184__'
                654     LOAD_CONST                      3: b'<COAddr>\x07\x00\x00\x1aT\x02\x00\x00\x00\x00\x00\x00\x00\x00\x00\x00\x00\x00\x00\x00'
                656     BUILD_TUPLE                     1
                658     CALL_FUNCTION_EX                0
                660     POP_TOP                         
                662     RETURN_VALUE                    
            [Exception Table]
                30 to 188 -> 546 [0] 
                210 to 526 -> 546 [0] 
                546 to 564 -> 616 [1] lasti
                564 to 596 -> 606 [1] lasti
                596 to 606 -> 622 [0] 
                606 to 616 -> 616 [1] lasti
                616 to 622 -> 622 [0] 
                622 to 644 -> 644 [1] lasti
        [Code]
            File Name: <frozen program.modules.Check_links_no_accounts>
            Object Name: START
            Qualified Name: START
            Arg Count: 5
            Pos Only Arg Count: 0
            KW Only Arg Count: 0
            Stack Size: 14
            Flags: 0x20000003 (CO_OPTIMIZED | CO_NEWLOCALS | CO_PYARMOR_OBFUSCATED)
            [Names]
                'is_set'
                'StopProgram'
                'Logs'
                'PrintLog'
                'Lang'
                'datetime'
                'now'
                'strftime'
                'db_check_links_no_accounts'
                'create'
                'eel'
                'WriteResult'
                'get'
                'tg_links'
                'clear_username'
                'append'
                'list'
                'dict'
                'fromkeys'
                'write_to_file'
                'sqlite3'
                'connect'
                'PARSE_DECLTYPES'
                'cursor'
                'execute'
                'fetchall'
                'int'
                'concurrent'
                'futures'
                'ThreadPoolExecutor'
                'len'
                'StreamStat'
                'json'
                'dumps'
                'submit'
                'worker'
                'as_completed'
                'BaseException'
                'logging'
                'del_task_manager'
                'StopDetect'
            [Locals+Names]
                'data'
                'config'
                'pid'
                'proxy'
                'stop_thread'
                '__assert_armored__'
                '_var_var_4'
                '_var_var_5'
                '_var_var_6'
                '_var_var_7'
                '_var_var_8'
                '_var_var_9'
                '_var_var_10'
                '_var_var_11'
                '_var_var_12'
                '_var_var_13'
                '_var_var_14'
                '_var_var_15'
                '_var_var_16'
                '_var_var_17'
                '_var_var_18'
                '_var_var_19'
                '_var_var_20'
                '_var_var_3'
            [Constants]
                None
                '__pyarmor_assert_13185__'
                '__pyarmor_enter_13186__'
                b'<COAddr>\x07\x00\x00\x1a\x1c\n\x00\x00\x00\x00\x00\x00\x00\x00\x00\x00\x00\x00\x00\x00'
                'program_running'   # b'\x81\xf2\n\x1c4\xe8\xbf\xdf$\xe8\x18\xceb\xe5\xf6\x82'
                (
                    'config'
                    'message'
                )
                '%Y-%m-%d_%H-%M-%S'   # b'\x81\xa7!^v\xf7\xf3\x97\x1f\xc5H\xe8!\xa9\xd5\xc8Jn'
                'additives/check_links_no_accounts/'   # b'\x81\xe3\x1c\x17:\xee\xb7\xc4\x1e\xe9B\xc3d\xe9\xfb\x8e0Q\xb2\xa9\xa1\xd8q\xc2\nP\xa2_\x03\xbe\x0b\xeb.Ao'
                '_base.db'
                'Base'
                'check_links_no_accounts'   # b'\x81\xe1\x10\x160\xf1\x81\xde\x12\xf4\x06\xd3S\xe2\xf7\xba\x0e^\xb8\xa8\xbf\xc5Z\xdf'
                'Settings'
                'usernames'   # b'\x81\xf7\x0b\x16!\xf4\xbf\xdf\x1e\xe9'
                'create_txt'   # b'\x81\xe1\n\x162\xee\xbb\xed\x0f\xe2\x19'
                '_channels.txt'   # b'\x81\xdd\x1b\x1b2\xf4\xb0\xd7\x17\xe9C\xd4t\xf8'
                'Channels'
                '_groups.txt'   # b'\x81\xdd\x1f\x01<\xef\xae\xc1U\xee\x15\xd4'
                'Groups'
                '_users.txt'   # b'\x81\xdd\r\x006\xe8\xad\x9c\x0f\xe2\x19'
                'Users'
                '_bots.txt'   # b"\x81\xdd\x1a\x1c'\xe9\xf0\xc6\x03\xee"
                'Bots'
                '_invalid.txt'   # b'\x81\xdd\x11\x1d%\xfb\xb2\xdb\x1f\xb4\x19\xd8x'
                'Invalid'
                'use_proxy'   # b'\x81\xf7\x0b\x16\x0c\xea\xac\xdd\x03\xe3'
                'settings/proxy.db'   # b"\x81\xf1\x1d\x07'\xf3\xb0\xd5\x08\xb5\x1d\xd2c\xf4\xe1\xcb\x0b_"
                5
                False
                (
                    'detect_types'
                    'timeout'
                    'check_same_thread'
                )
                'SELECT * FROM PROXY ORDER BY RANDOM()'   # b'\x81\xd1=?\x16\xd9\x8a\x92Q\xba+\xf2C\xc1\xb8\xb5=r\x83\x9e\xea\xe4|\xe8 ]\xe3~9\xf1,\xc4\x14v\x0f \xd0\x83'
                'thread_rules'   # b'\x81\xf6\x10\x016\xfb\xba\xed\t\xef\x01\xc5\x7f'
                True
                'thread_count'   # b'\x81\xf6\x10\x016\xfb\xba\xed\x18\xf5\x18\xcex'
                (
                    'max_workers'
                )
                0
                'st_task'
                'st_stream'   # b'\x81\xf1\x0c, \xee\xac\xd7\x1a\xf7'
                'st_wait'
                'st_done'
                1
                'job_done'
                '__pyarmor_exit_13187__'
                'Done'
            [Disassembly]
                0       NOP                             
                2       NOP                             
                4       PUSH_NULL                       
                6       LOAD_CONST                      2: '__pyarmor_enter_13186__'
                8       LOAD_CONST                      3: b'<COAddr>\x07\x00\x00\x1a\x1c\n\x00\x00\x00\x00\x00\x00\x00\x00\x00\x00\x00\x00\x00\x00'
                10      BUILD_TUPLE                     1
                12      CALL_FUNCTION_EX                0
                14      POP_TOP                         
                16      RESUME                          0
                18      NOP                             
                20      NOP                             
                22      NOP                             
                24      NOP                             
                26      NOP                             
                28      NOP                             
                30      LOAD_FAST                       4: stop_thread
                32      LOAD_ATTR                       1: is_set
                52      CALL                            0
                60      POP_JUMP_IF_FALSE               10 (to 82)
                62      LOAD_GLOBAL                     3: NULL + StopProgram
                72      CALL                            0
                80      RAISE_VARARGS                   1
                82      LOAD_GLOBAL                     5: NULL + Logs
                92      LOAD_ATTR                       6: PrintLog
                112     LOAD_FAST                       1: config
                114     LOAD_GLOBAL                     8: Lang
                124     PUSH_NULL                       
                126     LOAD_CONST                      1: '__pyarmor_assert_13185__'
                128     LOAD_CONST                      4: 'program_running'   # b'\x81\xf2\n\x1c4\xe8\xbf\xdf$\xe8\x18\xceb\xe5\xf6\x82'
                130     CALL                            1
                138     BINARY_SUBSCR                   
                142     KW_NAMES                        5: ('config', 'message')
                144     CALL                            2
                152     POP_TOP                         
                154     LOAD_GLOBAL                     10: datetime
                164     LOAD_ATTR                       10: datetime
                184     LOAD_ATTR                       13: now
                204     CALL                            0
                212     LOAD_ATTR                       15: strftime
                232     PUSH_NULL                       
                234     LOAD_CONST                      1: '__pyarmor_assert_13185__'
                236     LOAD_CONST                      6: '%Y-%m-%d_%H-%M-%S'   # b'\x81\xa7!^v\xf7\xf3\x97\x1f\xc5H\xe8!\xa9\xd5\xc8Jn'
                238     CALL                            1
                246     CALL                            1
                254     STORE_FAST                      6: _var_var_4
                256     LOAD_GLOBAL                     17: NULL + db_check_links_no_accounts
                266     PUSH_NULL                       
                268     LOAD_CONST                      1: '__pyarmor_assert_13185__'
                270     LOAD_CONST                      7: 'additives/check_links_no_accounts/'   # b'\x81\xe3\x1c\x17:\xee\xb7\xc4\x1e\xe9B\xc3d\xe9\xfb\x8e0Q\xb2\xa9\xa1\xd8q\xc2\nP\xa2_\x03\xbe\x0b\xeb.Ao'
                272     CALL                            1
                280     LOAD_FAST                       6: _var_var_4
                282     FORMAT_VALUE                    0 (FVC_NONE)
                284     LOAD_CONST                      8: '_base.db'
                286     BUILD_STRING                    3
                288     CALL                            1
                296     LOAD_ATTR                       19: create
                316     CALL                            0
                324     STORE_FAST                      7: _var_var_5
                326     LOAD_GLOBAL                     21: NULL + eel
                336     LOAD_ATTR                       22: WriteResult
                356     LOAD_CONST                      9: 'Base'
                358     PUSH_NULL                       
                360     LOAD_CONST                      1: '__pyarmor_assert_13185__'
                362     LOAD_CONST                      10: 'check_links_no_accounts'   # b'\x81\xe1\x10\x160\xf1\x81\xde\x12\xf4\x06\xd3S\xe2\xf7\xba\x0e^\xb8\xa8\xbf\xc5Z\xdf'
                364     CALL                            1
                372     LOAD_FAST                       6: _var_var_4
                374     FORMAT_VALUE                    0 (FVC_NONE)
                376     LOAD_CONST                      8: '_base.db'
                378     BUILD_STRING                    2
                380     CALL                            3
                388     POP_TOP                         
                390     LOAD_FAST                       0: data
                392     LOAD_CONST                      11: 'Settings'
                394     BINARY_SUBSCR                   
                398     LOAD_ATTR                       25: get
                418     PUSH_NULL                       
                420     LOAD_CONST                      1: '__pyarmor_assert_13185__'
                422     LOAD_CONST                      12: 'usernames'   # b'\x81\xf7\x0b\x16!\xf4\xbf\xdf\x1e\xe9'
                424     CALL                            1
                432     BUILD_LIST                      0
                434     CALL                            2
                442     STORE_FAST                      8: _var_var_6
                444     BUILD_LIST                      0
                446     STORE_FAST                      9: _var_var_7
                448     LOAD_FAST                       8: _var_var_6
                450     GET_ITER                        
                452     FOR_ITER                        40 (to 534)
                456     STORE_FAST                      10: _var_var_8
                458     LOAD_GLOBAL                     27: NULL + tg_links
                468     LOAD_ATTR                       28: clear_username
                488     LOAD_FAST                       10: _var_var_8
                490     CALL                            1
                498     STORE_FAST                      10: _var_var_8
                500     LOAD_FAST                       9: _var_var_7
                502     LOAD_ATTR                       31: append
                522     LOAD_FAST                       10: _var_var_8
                524     CALL                            1
                532     POP_TOP                         
                534     JUMP_BACKWARD                   42 (to 452)
                536     END_FOR                         
                538     LOAD_GLOBAL                     33: NULL + list
                548     LOAD_GLOBAL                     34: dict
                558     LOAD_ATTR                       37: fromkeys
                578     LOAD_FAST                       9: _var_var_7
                580     CALL                            1
                588     CALL                            1
                596     STORE_FAST                      9: _var_var_7
                598     LOAD_FAST                       0: data
                600     LOAD_CONST                      11: 'Settings'
                602     BINARY_SUBSCR                   
                606     LOAD_ATTR                       25: get
                626     PUSH_NULL                       
                628     LOAD_CONST                      1: '__pyarmor_assert_13185__'
                630     LOAD_CONST                      13: 'create_txt'   # b'\x81\xe1\n\x162\xee\xbb\xed\x0f\xe2\x19'
                632     CALL                            1
                640     CALL                            1
                648     STORE_FAST                      11: _var_var_9
                650     LOAD_FAST                       11: _var_var_9
                652     POP_JUMP_IF_FALSE               325 (to 1306)
                656     LOAD_GLOBAL                     39: NULL + write_to_file
                666     PUSH_NULL                       
                668     LOAD_CONST                      1: '__pyarmor_assert_13185__'
                670     LOAD_CONST                      7: 'additives/check_links_no_accounts/'   # b'\x81\xe3\x1c\x17:\xee\xb7\xc4\x1e\xe9B\xc3d\xe9\xfb\x8e0Q\xb2\xa9\xa1\xd8q\xc2\nP\xa2_\x03\xbe\x0b\xeb.Ao'
                672     CALL                            1
                680     LOAD_FAST                       6: _var_var_4
                682     FORMAT_VALUE                    0 (FVC_NONE)
                684     PUSH_NULL                       
                686     LOAD_CONST                      1: '__pyarmor_assert_13185__'
                688     LOAD_CONST                      14: '_channels.txt'   # b'\x81\xdd\x1b\x1b2\xf4\xb0\xd7\x17\xe9C\xd4t\xf8'
                690     CALL                            1
                698     BUILD_STRING                    3
                700     CALL                            1
                708     POP_TOP                         
                710     LOAD_GLOBAL                     21: NULL + eel
                720     LOAD_ATTR                       22: WriteResult
                740     LOAD_CONST                      15: 'Channels'
                742     PUSH_NULL                       
                744     LOAD_CONST                      1: '__pyarmor_assert_13185__'
                746     LOAD_CONST                      10: 'check_links_no_accounts'   # b'\x81\xe1\x10\x160\xf1\x81\xde\x12\xf4\x06\xd3S\xe2\xf7\xba\x0e^\xb8\xa8\xbf\xc5Z\xdf'
                748     CALL                            1
                756     LOAD_FAST                       6: _var_var_4
                758     FORMAT_VALUE                    0 (FVC_NONE)
                760     PUSH_NULL                       
                762     LOAD_CONST                      1: '__pyarmor_assert_13185__'
                764     LOAD_CONST                      14: '_channels.txt'   # b'\x81\xdd\x1b\x1b2\xf4\xb0\xd7\x17\xe9C\xd4t\xf8'
                766     CALL                            1
                774     BUILD_STRING                    2
                776     CALL                            3
                784     POP_TOP                         
                786     LOAD_GLOBAL                     39: NULL + write_to_file
                796     PUSH_NULL                       
                798     LOAD_CONST                      1: '__pyarmor_assert_13185__'
                800     LOAD_CONST                      7: 'additives/check_links_no_accounts/'   # b'\x81\xe3\x1c\x17:\xee\xb7\xc4\x1e\xe9B\xc3d\xe9\xfb\x8e0Q\xb2\xa9\xa1\xd8q\xc2\nP\xa2_\x03\xbe\x0b\xeb.Ao'
                802     CALL                            1
                810     LOAD_FAST                       6: _var_var_4
                812     FORMAT_VALUE                    0 (FVC_NONE)
                814     PUSH_NULL                       
                816     LOAD_CONST                      1: '__pyarmor_assert_13185__'
                818     LOAD_CONST                      16: '_groups.txt'   # b'\x81\xdd\x1f\x01<\xef\xae\xc1U\xee\x15\xd4'
                820     CALL                            1
                828     BUILD_STRING                    3
                830     CALL                            1
                838     POP_TOP                         
                840     LOAD_GLOBAL                     21: NULL + eel
                850     LOAD_ATTR                       22: WriteResult
                870     LOAD_CONST                      17: 'Groups'
                872     PUSH_NULL                       
                874     LOAD_CONST                      1: '__pyarmor_assert_13185__'
                876     LOAD_CONST                      10: 'check_links_no_accounts'   # b'\x81\xe1\x10\x160\xf1\x81\xde\x12\xf4\x06\xd3S\xe2\xf7\xba\x0e^\xb8\xa8\xbf\xc5Z\xdf'
                878     CALL                            1
                886     LOAD_FAST                       6: _var_var_4
                888     FORMAT_VALUE                    0 (FVC_NONE)
                890     PUSH_NULL                       
                892     LOAD_CONST                      1: '__pyarmor_assert_13185__'
                894     LOAD_CONST                      16: '_groups.txt'   # b'\x81\xdd\x1f\x01<\xef\xae\xc1U\xee\x15\xd4'
                896     CALL                            1
                904     BUILD_STRING                    2
                906     CALL                            3
                914     POP_TOP                         
                916     LOAD_GLOBAL                     39: NULL + write_to_file
                926     PUSH_NULL                       
                928     LOAD_CONST                      1: '__pyarmor_assert_13185__'
                930     LOAD_CONST                      7: 'additives/check_links_no_accounts/'   # b'\x81\xe3\x1c\x17:\xee\xb7\xc4\x1e\xe9B\xc3d\xe9\xfb\x8e0Q\xb2\xa9\xa1\xd8q\xc2\nP\xa2_\x03\xbe\x0b\xeb.Ao'
                932     CALL                            1
                940     LOAD_FAST                       6: _var_var_4
                942     FORMAT_VALUE                    0 (FVC_NONE)
                944     PUSH_NULL                       
                946     LOAD_CONST                      1: '__pyarmor_assert_13185__'
                948     LOAD_CONST                      18: '_users.txt'   # b'\x81\xdd\r\x006\xe8\xad\x9c\x0f\xe2\x19'
                950     CALL                            1
                958     BUILD_STRING                    3
                960     CALL                            1
                968     POP_TOP                         
                970     LOAD_GLOBAL                     21: NULL + eel
                980     LOAD_ATTR                       22: WriteResult
                1000    LOAD_CONST                      19: 'Users'
                1002    PUSH_NULL                       
                1004    LOAD_CONST                      1: '__pyarmor_assert_13185__'
                1006    LOAD_CONST                      10: 'check_links_no_accounts'   # b'\x81\xe1\x10\x160\xf1\x81\xde\x12\xf4\x06\xd3S\xe2\xf7\xba\x0e^\xb8\xa8\xbf\xc5Z\xdf'
                1008    CALL                            1
                1016    LOAD_FAST                       6: _var_var_4
                1018    FORMAT_VALUE                    0 (FVC_NONE)
                1020    PUSH_NULL                       
                1022    LOAD_CONST                      1: '__pyarmor_assert_13185__'
                1024    LOAD_CONST                      18: '_users.txt'   # b'\x81\xdd\r\x006\xe8\xad\x9c\x0f\xe2\x19'
                1026    CALL                            1
                1034    BUILD_STRING                    2
                1036    CALL                            3
                1044    POP_TOP                         
                1046    LOAD_GLOBAL                     39: NULL + write_to_file
                1056    PUSH_NULL                       
                1058    LOAD_CONST                      1: '__pyarmor_assert_13185__'
                1060    LOAD_CONST                      7: 'additives/check_links_no_accounts/'   # b'\x81\xe3\x1c\x17:\xee\xb7\xc4\x1e\xe9B\xc3d\xe9\xfb\x8e0Q\xb2\xa9\xa1\xd8q\xc2\nP\xa2_\x03\xbe\x0b\xeb.Ao'
                1062    CALL                            1
                1070    LOAD_FAST                       6: _var_var_4
                1072    FORMAT_VALUE                    0 (FVC_NONE)
                1074    PUSH_NULL                       
                1076    LOAD_CONST                      1: '__pyarmor_assert_13185__'
                1078    LOAD_CONST                      20: '_bots.txt'   # b"\x81\xdd\x1a\x1c'\xe9\xf0\xc6\x03\xee"
                1080    CALL                            1
                1088    BUILD_STRING                    3
                1090    CALL                            1
                1098    POP_TOP                         
                1100    LOAD_GLOBAL                     21: NULL + eel
                1110    LOAD_ATTR                       22: WriteResult
                1130    LOAD_CONST                      21: 'Bots'
                1132    PUSH_NULL                       
                1134    LOAD_CONST                      1: '__pyarmor_assert_13185__'
                1136    LOAD_CONST                      10: 'check_links_no_accounts'   # b'\x81\xe1\x10\x160\xf1\x81\xde\x12\xf4\x06\xd3S\xe2\xf7\xba\x0e^\xb8\xa8\xbf\xc5Z\xdf'
                1138    CALL                            1
                1146    LOAD_FAST                       6: _var_var_4
                1148    FORMAT_VALUE                    0 (FVC_NONE)
                1150    PUSH_NULL                       
                1152    LOAD_CONST                      1: '__pyarmor_assert_13185__'
                1154    LOAD_CONST                      20: '_bots.txt'   # b"\x81\xdd\x1a\x1c'\xe9\xf0\xc6\x03\xee"
                1156    CALL                            1
                1164    BUILD_STRING                    2
                1166    CALL                            3
                1174    POP_TOP                         
                1176    LOAD_GLOBAL                     39: NULL + write_to_file
                1186    PUSH_NULL                       
                1188    LOAD_CONST                      1: '__pyarmor_assert_13185__'
                1190    LOAD_CONST                      7: 'additives/check_links_no_accounts/'   # b'\x81\xe3\x1c\x17:\xee\xb7\xc4\x1e\xe9B\xc3d\xe9\xfb\x8e0Q\xb2\xa9\xa1\xd8q\xc2\nP\xa2_\x03\xbe\x0b\xeb.Ao'
                1192    CALL                            1
                1200    LOAD_FAST                       6: _var_var_4
                1202    FORMAT_VALUE                    0 (FVC_NONE)
                1204    PUSH_NULL                       
                1206    LOAD_CONST                      1: '__pyarmor_assert_13185__'
                1208    LOAD_CONST                      22: '_invalid.txt'   # b'\x81\xdd\x11\x1d%\xfb\xb2\xdb\x1f\xb4\x19\xd8x'
                1210    CALL                            1
                1218    BUILD_STRING                    3
                1220    CALL                            1
                1228    POP_TOP                         
                1230    LOAD_GLOBAL                     21: NULL + eel
                1240    LOAD_ATTR                       22: WriteResult
                1260    LOAD_CONST                      23: 'Invalid'
                1262    PUSH_NULL                       
                1264    LOAD_CONST                      1: '__pyarmor_assert_13185__'
                1266    LOAD_CONST                      10: 'check_links_no_accounts'   # b'\x81\xe1\x10\x160\xf1\x81\xde\x12\xf4\x06\xd3S\xe2\xf7\xba\x0e^\xb8\xa8\xbf\xc5Z\xdf'
                1268    CALL                            1
                1276    LOAD_FAST                       6: _var_var_4
                1278    FORMAT_VALUE                    0 (FVC_NONE)
                1280    PUSH_NULL                       
                1282    LOAD_CONST                      1: '__pyarmor_assert_13185__'
                1284    LOAD_CONST                      22: '_invalid.txt'   # b'\x81\xdd\x11\x1d%\xfb\xb2\xdb\x1f\xb4\x19\xd8x'
                1286    CALL                            1
                1294    BUILD_STRING                    2
                1296    CALL                            3
                1304    POP_TOP                         
                1306    LOAD_FAST                       0: data
                1308    LOAD_CONST                      11: 'Settings'
                1310    BINARY_SUBSCR                   
                1314    LOAD_ATTR                       25: get
                1334    PUSH_NULL                       
                1336    LOAD_CONST                      1: '__pyarmor_assert_13185__'
                1338    LOAD_CONST                      24: 'use_proxy'   # b'\x81\xf7\x0b\x16\x0c\xea\xac\xdd\x03\xe3'
                1340    CALL                            1
                1348    CALL                            1
                1356    STORE_FAST                      12: _var_var_10
                1358    LOAD_CONST                      0: None
                1360    STORE_FAST                      3: proxy
                1362    LOAD_FAST                       12: _var_var_10
                1364    POP_JUMP_IF_FALSE               109 (to 1584)
                1366    LOAD_GLOBAL                     41: NULL + sqlite3
                1376    LOAD_ATTR                       42: connect
                1396    PUSH_NULL                       
                1398    LOAD_CONST                      1: '__pyarmor_assert_13185__'
                1400    LOAD_CONST                      25: 'settings/proxy.db'   # b"\x81\xf1\x1d\x07'\xf3\xb0\xd5\x08\xb5\x1d\xd2c\xf4\xe1\xcb\x0b_"
                1402    CALL                            1
                1410    LOAD_GLOBAL                     40: sqlite3
                1420    LOAD_ATTR                       44: PARSE_DECLTYPES
                1440    LOAD_CONST                      26: 5
                1442    LOAD_CONST                      27: False
                1444    KW_NAMES                        28: ('detect_types', 'timeout', 'check_same_thread')
                1446    CALL                            4
                1454    BEFORE_WITH                     
                1456    STORE_FAST                      13: _var_var_11
                1458    LOAD_FAST                       13: _var_var_11
                1460    LOAD_ATTR                       47: cursor
                1480    CALL                            0
                1488    STORE_FAST                      14: _var_var_12
                1490    LOAD_FAST                       14: _var_var_12
                1492    LOAD_ATTR                       49: execute
                1512    PUSH_NULL                       
                1514    LOAD_CONST                      1: '__pyarmor_assert_13185__'
                1516    LOAD_CONST                      29: 'SELECT * FROM PROXY ORDER BY RANDOM()'   # b'\x81\xd1=?\x16\xd9\x8a\x92Q\xba+\xf2C\xc1\xb8\xb5=r\x83\x9e\xea\xe4|\xe8 ]\xe3~9\xf1,\xc4\x14v\x0f \xd0\x83'
                1518    CALL                            1
                1526    CALL                            1
                1534    POP_TOP                         
                1536    LOAD_FAST                       14: _var_var_12
                1538    LOAD_ATTR                       51: fetchall
                1558    CALL                            0
                1566    STORE_FAST                      3: proxy
                1568    LOAD_CONST                      0: None
                1570    LOAD_CONST                      0: None
                1572    LOAD_CONST                      0: None
                1574    CALL                            2
                1582    POP_TOP                         
                1584    LOAD_FAST                       0: data
                1586    LOAD_CONST                      11: 'Settings'
                1588    BINARY_SUBSCR                   
                1592    LOAD_ATTR                       25: get
                1612    PUSH_NULL                       
                1614    LOAD_CONST                      1: '__pyarmor_assert_13185__'
                1616    LOAD_CONST                      30: 'thread_rules'   # b'\x81\xf6\x10\x016\xfb\xba\xed\t\xef\x01\xc5\x7f'
                1618    CALL                            1
                1626    CALL                            1
                1634    LOAD_CONST                      31: True
                1636    COMPARE_OP                      40 (==)
                1640    POP_JUMP_IF_FALSE               36 (to 1714)
                1642    LOAD_GLOBAL                     53: NULL + int
                1652    LOAD_FAST                       0: data
                1654    LOAD_CONST                      11: 'Settings'
                1656    BINARY_SUBSCR                   
                1660    LOAD_ATTR                       25: get
                1680    PUSH_NULL                       
                1682    LOAD_CONST                      1: '__pyarmor_assert_13185__'
                1684    LOAD_CONST                      32: 'thread_count'   # b'\x81\xf6\x10\x016\xfb\xba\xed\x18\xf5\x18\xcex'
                1686    CALL                            1
                1694    CALL                            1
                1702    CALL                            1
                1710    STORE_FAST                      15: _var_var_13
                1712    JUMP_FORWARD                    11 (to 1736)
                1714    LOAD_FAST                       1: config
                1716    PUSH_NULL                       
                1718    LOAD_CONST                      1: '__pyarmor_assert_13185__'
                1720    LOAD_CONST                      32: 'thread_count'   # b'\x81\xf6\x10\x016\xfb\xba\xed\x18\xf5\x18\xcex'
                1722    CALL                            1
                1730    BINARY_SUBSCR                   
                1734    STORE_FAST                      15: _var_var_13
                1736    LOAD_GLOBAL                     54: concurrent
                1746    LOAD_ATTR                       56: futures
                1766    LOAD_ATTR                       59: ThreadPoolExecutor
                1786    LOAD_FAST                       15: _var_var_13
                1788    KW_NAMES                        33: ('max_workers',)
                1790    CALL                            1
                1798    BEFORE_WITH                     
                1800    STORE_FAST                      16: _var_var_14
                1802    BUILD_LIST                      0
                1804    STORE_FAST                      17: _var_var_15
                1806    LOAD_GLOBAL                     61: NULL + len
                1816    LOAD_FAST                       9: _var_var_7
                1818    CALL                            1
                1826    STORE_FAST                      18: _var_var_16
                1828    LOAD_FAST                       15: _var_var_13
                1830    STORE_FAST                      19: _var_var_17
                1832    LOAD_FAST                       18: _var_var_16
                1834    STORE_FAST                      20: _var_var_18
                1836    LOAD_CONST                      34: 0
                1838    STORE_FAST                      21: _var_var_19
                1840    LOAD_GLOBAL                     21: NULL + eel
                1850    LOAD_ATTR                       62: StreamStat
                1870    LOAD_GLOBAL                     65: NULL + json
                1880    LOAD_ATTR                       66: dumps
                1900    LOAD_CONST                      35: 'st_task'
                1902    LOAD_FAST                       18: _var_var_16
                1904    PUSH_NULL                       
                1906    LOAD_CONST                      1: '__pyarmor_assert_13185__'
                1908    LOAD_CONST                      36: 'st_stream'   # b'\x81\xf1\x0c, \xee\xac\xd7\x1a\xf7'
                1910    CALL                            1
                1918    LOAD_FAST                       19: _var_var_17
                1920    LOAD_CONST                      37: 'st_wait'
                1922    LOAD_FAST                       20: _var_var_18
                1924    LOAD_CONST                      38: 'st_done'
                1926    LOAD_FAST                       21: _var_var_19
                1928    BUILD_MAP                       4
                1930    CALL                            1
                1938    CALL                            1
                1946    POP_TOP                         
                1948    LOAD_FAST                       9: _var_var_7
                1950    GET_ITER                        
                1952    FOR_ITER                        45 (to 2044)
                1956    STORE_FAST                      10: _var_var_8
                1958    LOAD_FAST                       17: _var_var_15
                1960    LOAD_ATTR                       31: append
                1980    LOAD_FAST                       16: _var_var_14
                1982    LOAD_ATTR                       69: submit
                2002    LOAD_GLOBAL                     70: worker
                2012    LOAD_FAST                       0: data
                2014    LOAD_FAST                       10: _var_var_8
                2016    LOAD_FAST                       7: _var_var_5
                2018    LOAD_FAST                       6: _var_var_4
                2020    LOAD_FAST                       3: proxy
                2022    LOAD_CONST                      34: 0
                2024    LOAD_FAST                       4: stop_thread
                2026    CALL                            8
                2034    CALL                            1
                2042    POP_TOP                         
                2044    JUMP_BACKWARD                   47 (to 1952)
                2046    END_FOR                         
                2048    LOAD_GLOBAL                     54: concurrent
                2058    LOAD_ATTR                       56: futures
                2078    LOAD_ATTR                       73: as_completed
                2098    LOAD_FAST                       17: _var_var_15
                2100    CALL                            1
                2108    GET_ITER                        
                2110    FOR_ITER                        66 (to 2244)
                2114    STORE_FAST                      22: _var_var_20
                2116    LOAD_FAST                       21: _var_var_19
                2118    LOAD_CONST                      39: 1
                2120    BINARY_OP                       13 (+=)
                2124    STORE_FAST                      21: _var_var_19
                2126    LOAD_FAST                       20: _var_var_18
                2128    LOAD_CONST                      39: 1
                2130    BINARY_OP                       23 (-=)
                2134    STORE_FAST                      20: _var_var_18
                2136    LOAD_GLOBAL                     21: NULL + eel
                2146    LOAD_ATTR                       62: StreamStat
                2166    LOAD_GLOBAL                     65: NULL + json
                2176    LOAD_ATTR                       66: dumps
                2196    LOAD_CONST                      35: 'st_task'
                2198    LOAD_FAST                       18: _var_var_16
                2200    PUSH_NULL                       
                2202    LOAD_CONST                      1: '__pyarmor_assert_13185__'
                2204    LOAD_CONST                      36: 'st_stream'   # b'\x81\xf1\x0c, \xee\xac\xd7\x1a\xf7'
                2206    CALL                            1
                2214    LOAD_FAST                       19: _var_var_17
                2216    LOAD_CONST                      37: 'st_wait'
                2218    LOAD_FAST                       20: _var_var_18
                2220    LOAD_CONST                      38: 'st_done'
                2222    LOAD_FAST                       21: _var_var_19
                2224    BUILD_MAP                       4
                2226    CALL                            1
                2234    CALL                            1
                2242    POP_TOP                         
                2244    JUMP_BACKWARD                   68 (to 2110)
                2246    END_FOR                         
                2248    NOP                             
                2250    LOAD_CONST                      0: None
                2252    LOAD_CONST                      0: None
                2254    LOAD_CONST                      0: None
                2256    CALL                            2
                2264    POP_TOP                         
                2266    LOAD_GLOBAL                     5: NULL + Logs
                2276    LOAD_ATTR                       6: PrintLog
                2296    LOAD_FAST                       1: config
                2298    LOAD_GLOBAL                     8: Lang
                2308    LOAD_CONST                      40: 'job_done'
                2310    BINARY_SUBSCR                   
                2314    KW_NAMES                        5: ('config', 'message')
                2316    CALL                            2
                2324    POP_TOP                         
                2326    LOAD_GLOBAL                     79: NULL + del_task_manager
                2336    LOAD_FAST                       2: pid
                2338    CALL                            1
                2346    POP_TOP                         
                2348    LOAD_GLOBAL                     81: NULL + StopDetect
                2358    LOAD_FAST                       4: stop_thread
                2360    CALL                            1
                2368    POP_TOP                         
                2370    NOP                             
                2372    LOAD_CONST                      42: 'Done'
                2374    NOP                             
                2376    NOP                             
                2378    NOP                             
                2380    JUMP_FORWARD                    130 (to 2642)
                2388    POP_TOP                         
                2390    RETURN_CONST                    42: 'Done'
                2392    PUSH_EXC_INFO                   
                2394    WITH_EXCEPT_START               
                2396    POP_JUMP_IF_TRUE                1 (to 2400)
                2398    RERAISE                         2
                2400    POP_TOP                         
                2402    POP_EXCEPT                      
                2404    POP_TOP                         
                2406    POP_TOP                         
                2408    JUMP_BACKWARD                   414 (to 1584)
                2412    COPY                            3
                2414    POP_EXCEPT                      
                2416    RERAISE                         1
                2418    PUSH_EXC_INFO                   
                2420    WITH_EXCEPT_START               
                2422    POP_JUMP_IF_TRUE                1 (to 2426)
                2424    RERAISE                         2
                2426    POP_TOP                         
                2428    POP_EXCEPT                      
                2430    POP_TOP                         
                2432    POP_TOP                         
                2434    JUMP_BACKWARD                   85 (to 2266)
                2436    COPY                            3
                2438    POP_EXCEPT                      
                2440    RERAISE                         1
                2442    PUSH_EXC_INFO                   
                2444    LOAD_GLOBAL                     2: StopProgram
                2454    CHECK_EXC_MATCH                 
                2456    POP_JUMP_IF_FALSE               3 (to 2464)
                2458    POP_TOP                         
                2460    POP_EXCEPT                      
                2462    JUMP_BACKWARD                   69 (to 2326)
                2464    LOAD_GLOBAL                     74: BaseException
                2474    CHECK_EXC_MATCH                 
                2476    POP_JUMP_IF_FALSE               26 (to 2530)
                2478    STORE_FAST                      23: _var_var_3
                2480    PUSH_NULL                       
                2482    LOAD_GLOBAL                     77: NULL + logging
                2492    LOAD_FAST                       23: _var_var_3
                2494    CALL                            1
                2502    CALL                            0
                2510    POP_TOP                         
                2512    POP_EXCEPT                      
                2514    LOAD_CONST                      0: None
                2516    STORE_FAST                      23: _var_var_3
                2518    DELETE_FAST                     23: _var_var_3
                2520    JUMP_BACKWARD                   98 (to 2326)
                2522    LOAD_CONST                      0: None
                2524    STORE_FAST                      23: _var_var_3
                2526    DELETE_FAST                     23: _var_var_3
                2528    RERAISE                         1
                2530    RERAISE                         0
                2532    COPY                            3
                2534    POP_EXCEPT                      
                2536    RERAISE                         1
                2538    PUSH_EXC_INFO                   
                2540    LOAD_GLOBAL                     79: NULL + del_task_manager
                2550    LOAD_FAST                       2: pid
                2552    CALL                            1
                2560    POP_TOP                         
                2562    LOAD_GLOBAL                     81: NULL + StopDetect
                2572    LOAD_FAST                       4: stop_thread
                2574    CALL                            1
                2582    POP_TOP                         
                2584    POP_TOP                         
                2586    POP_EXCEPT                      
                2588    LOAD_CONST                      42: 'Done'
                2590    NOP                             
                2592    NOP                             
                2594    NOP                             
                2596    JUMP_FORWARD                    22 (to 2642)
                2604    POP_TOP                         
                2606    RETURN_CONST                    42: 'Done'
                2608    COPY                            3
                2610    POP_EXCEPT                      
                2612    RERAISE                         1
                2614    PUSH_EXC_INFO                   
                2616    PUSH_NULL                       
                2618    LOAD_CONST                      41: '__pyarmor_exit_13187__'
                2620    NOP                             
                2622    LOAD_CONST                      3: b'<COAddr>\x07\x00\x00\x1a\x1c\n\x00\x00\x00\x00\x00\x00\x00\x00\x00\x00\x00\x00\x00\x00'
                2624    CALL                            1
                2632    POP_TOP                         
                2634    RERAISE                         0
                2636    COPY                            3
                2638    POP_EXCEPT                      
                2640    RERAISE                         1
                2642    PUSH_NULL                       
                2644    LOAD_CONST                      41: '__pyarmor_exit_13187__'
                2646    LOAD_CONST                      3: b'<COAddr>\x07\x00\x00\x1a\x1c\n\x00\x00\x00\x00\x00\x00\x00\x00\x00\x00\x00\x00\x00\x00'
                2648    BUILD_TUPLE                     1
                2650    CALL_FUNCTION_EX                0
                2652    POP_TOP                         
                2654    RETURN_VALUE                    
            [Exception Table]
                30 to 1456 -> 2442 [0] 
                1456 to 1568 -> 2392 [1] lasti
                1568 to 1800 -> 2442 [0] 
                1800 to 2248 -> 2418 [1] lasti
                2250 to 2326 -> 2442 [0] 
                2326 to 2370 -> 2614 [0] 
                2392 to 2402 -> 2412 [3] lasti
                2402 to 2418 -> 2442 [0] 
                2418 to 2428 -> 2436 [3] lasti
                2428 to 2442 -> 2442 [0] 
                2442 to 2460 -> 2532 [1] lasti
                2460 to 2464 -> 2538 [0] 
                2464 to 2480 -> 2532 [1] lasti
                2480 to 2512 -> 2522 [1] lasti
                2512 to 2522 -> 2538 [0] 
                2522 to 2532 -> 2532 [1] lasti
                2532 to 2538 -> 2538 [0] 
                2538 to 2586 -> 2608 [1] lasti
                2586 to 2588 -> 2614 [0] 
                2608 to 2614 -> 2614 [0] 
                2614 to 2636 -> 2636 [1] lasti
        [Code]
            File Name: <frozen program.modules.Check_links_no_accounts>
            Object Name: write_to_file
            Qualified Name: write_to_file
            Arg Count: 2
            Pos Only Arg Count: 0
            KW Only Arg Count: 0
            Stack Size: 6
            Flags: 0x20000003 (CO_OPTIMIZED | CO_NEWLOCALS | CO_PYARMOR_OBFUSCATED)
            [Names]
                'open'
                'write'
            [Locals+Names]
                'filepath'
                'text'
                '__assert_armored__'
                '_var_var_21'
            [Constants]
                None
                '__pyarmor_assert_13188__'
                '__pyarmor_enter_13189__'
                b'<COAddr>\x07\x00\x00\x1a\xa8\x00\x00\x00\x00\x00\x00\x00\x00\x00\x00\x00\x00\x00\x00\x00'
                'a'
                '\n'
                ''
                '__pyarmor_exit_13190__'
            [Disassembly]
                0       NOP                             
                2       NOP                             
                4       PUSH_NULL                       
                6       LOAD_CONST                      2: '__pyarmor_enter_13189__'
                8       LOAD_CONST                      3: b'<COAddr>\x07\x00\x00\x1a\xa8\x00\x00\x00\x00\x00\x00\x00\x00\x00\x00\x00\x00\x00\x00\x00'
                10      BUILD_TUPLE                     1
                12      CALL_FUNCTION_EX                0
                14      POP_TOP                         
                16      RESUME                          0
                18      NOP                             
                20      NOP                             
                22      NOP                             
                24      NOP                             
                26      NOP                             
                28      LOAD_GLOBAL                     1: NULL + open
                38      LOAD_FAST                       0: filepath
                40      LOAD_CONST                      4: 'a'
                42      CALL                            2
                50      BEFORE_WITH                     
                52      STORE_FAST                      3: _var_var_21
                54      LOAD_FAST                       1: text
                56      POP_JUMP_IF_FALSE               21 (to 100)
                58      LOAD_FAST                       3: _var_var_21
                60      LOAD_ATTR                       3: write
                80      LOAD_FAST                       1: text
                82      FORMAT_VALUE                    0 (FVC_NONE)
                84      LOAD_CONST                      5: '\n'
                86      BUILD_STRING                    2
                88      CALL                            1
                96      POP_TOP                         
                98      JUMP_FORWARD                    17 (to 134)
                100     LOAD_FAST                       3: _var_var_21
                102     LOAD_ATTR                       3: write
                122     LOAD_CONST                      6: ''
                124     CALL                            1
                132     POP_TOP                         
                134     LOAD_CONST                      0: None
                136     LOAD_CONST                      0: None
                138     LOAD_CONST                      0: None
                140     CALL                            2
                148     POP_TOP                         
                150     LOAD_CONST                      0: None
                152     NOP                             
                154     NOP                             
                156     NOP                             
                158     JUMP_FORWARD                    31 (to 222)
                166     POP_TOP                         
                168     RETURN_CONST                    0: None
                170     PUSH_EXC_INFO                   
                172     WITH_EXCEPT_START               
                174     POP_JUMP_IF_TRUE                1 (to 178)
                176     RERAISE                         2
                178     POP_TOP                         
                180     POP_EXCEPT                      
                182     POP_TOP                         
                184     POP_TOP                         
                186     JUMP_BACKWARD                   19 (to 150)
                188     COPY                            3
                190     POP_EXCEPT                      
                192     RERAISE                         1
                194     PUSH_EXC_INFO                   
                196     PUSH_NULL                       
                198     LOAD_CONST                      7: '__pyarmor_exit_13190__'
                200     NOP                             
                202     LOAD_CONST                      3: b'<COAddr>\x07\x00\x00\x1a\xa8\x00\x00\x00\x00\x00\x00\x00\x00\x00\x00\x00\x00\x00\x00\x00'
                204     CALL                            1
                212     POP_TOP                         
                214     RERAISE                         0
                216     COPY                            3
                218     POP_EXCEPT                      
                220     RERAISE                         1
                222     PUSH_NULL                       
                224     LOAD_CONST                      7: '__pyarmor_exit_13190__'
                226     LOAD_CONST                      3: b'<COAddr>\x07\x00\x00\x1a\xa8\x00\x00\x00\x00\x00\x00\x00\x00\x00\x00\x00\x00\x00\x00\x00'
                228     BUILD_TUPLE                     1
                230     CALL_FUNCTION_EX                0
                232     POP_TOP                         
                234     RETURN_VALUE                    
            [Exception Table]
                28 to 52 -> 194 [0] 
                52 to 134 -> 170 [1] lasti
                134 to 150 -> 194 [0] 
                170 to 180 -> 188 [3] lasti
                180 to 194 -> 194 [0] 
                194 to 216 -> 216 [1] lasti
        [Code]
            File Name: <frozen program.modules.Check_links_no_accounts>
            Object Name: extract_number
            Qualified Name: extract_number
            Arg Count: 1
            Pos Only Arg Count: 0
            KW Only Arg Count: 0
            Stack Size: 6
            Flags: 0x20000003 (CO_OPTIMIZED | CO_NEWLOCALS | CO_PYARMOR_OBFUSCATED)
            [Names]
                're'
                'match'
                'int'
                'group'
                'replace'
            [Locals+Names]
                'text'
                '__assert_armored__'
                '_var_var_22'
                '_var_var_23'
            [Constants]
                None
                '__pyarmor_assert_13191__'
                '__pyarmor_enter_13192__'
                b'<COAddr>\x07\x00\x00\x1a\xb0\x00\x00\x00\x00\x00\x00\x00\x00\x00\x00\x00\x00\x00\x00\x00'
                '[\\d\\s]+'
                0
                ' '
                ''
                '__pyarmor_exit_13193__'
            [Disassembly]
                0       NOP                             
                2       NOP                             
                4       PUSH_NULL                       
                6       LOAD_CONST                      2: '__pyarmor_enter_13192__'
                8       LOAD_CONST                      3: b'<COAddr>\x07\x00\x00\x1a\xb0\x00\x00\x00\x00\x00\x00\x00\x00\x00\x00\x00\x00\x00\x00\x00'
                10      BUILD_TUPLE                     1
                12      CALL_FUNCTION_EX                0
                14      POP_TOP                         
                16      RESUME                          0
                18      NOP                             
                20      NOP                             
                22      NOP                             
                24      NOP                             
                26      NOP                             
                28      LOAD_GLOBAL                     1: NULL + re
                38      LOAD_ATTR                       2: match
                58      LOAD_CONST                      4: '[\\d\\s]+'
                60      LOAD_FAST                       0: text
                62      CALL                            2
                70      STORE_FAST                      2: _var_var_22
                72      LOAD_FAST                       2: _var_var_22
                74      POP_JUMP_IF_FALSE               53 (to 182)
                76      LOAD_GLOBAL                     5: NULL + int
                86      LOAD_FAST                       2: _var_var_22
                88      LOAD_ATTR                       7: group
                108     LOAD_CONST                      5: 0
                110     CALL                            1
                118     LOAD_ATTR                       9: replace
                138     LOAD_CONST                      6: ' '
                140     LOAD_CONST                      7: ''
                142     CALL                            2
                150     CALL                            1
                158     STORE_FAST                      3: _var_var_23
                160     LOAD_FAST                       3: _var_var_23
                162     NOP                             
                164     NOP                             
                166     NOP                             
                168     JUMP_FORWARD                    30 (to 230)
                170     CALL                            1
                178     POP_TOP                         
                180     RETURN_VALUE                    
                182     LOAD_CONST                      0: None
                184     NOP                             
                186     NOP                             
                188     NOP                             
                190     JUMP_FORWARD                    19 (to 230)
                198     POP_TOP                         
                200     RETURN_CONST                    0: None
                202     PUSH_EXC_INFO                   
                204     PUSH_NULL                       
                206     LOAD_CONST                      8: '__pyarmor_exit_13193__'
                208     NOP                             
                210     LOAD_CONST                      3: b'<COAddr>\x07\x00\x00\x1a\xb0\x00\x00\x00\x00\x00\x00\x00\x00\x00\x00\x00\x00\x00\x00\x00'
                212     CALL                            1
                220     POP_TOP                         
                222     RERAISE                         0
                224     COPY                            3
                226     POP_EXCEPT                      
                228     RERAISE                         1
                230     PUSH_NULL                       
                232     LOAD_CONST                      8: '__pyarmor_exit_13193__'
                234     LOAD_CONST                      3: b'<COAddr>\x07\x00\x00\x1a\xb0\x00\x00\x00\x00\x00\x00\x00\x00\x00\x00\x00\x00\x00\x00\x00'
                236     BUILD_TUPLE                     1
                238     CALL_FUNCTION_EX                0
                240     POP_TOP                         
                242     RETURN_VALUE                    
            [Exception Table]
                28 to 162 -> 202 [0] 
                202 to 224 -> 224 [1] lasti
        [Code]
            File Name: <frozen program.modules.Check_links_no_accounts>
            Object Name: worker
            Qualified Name: worker
            Arg Count: 7
            Pos Only Arg Count: 0
            KW Only Arg Count: 0
            Stack Size: 14
            Flags: 0x20000003 (CO_OPTIMIZED | CO_NEWLOCALS | CO_PYARMOR_OBFUSCATED)
            [Names]
                'Thread_wait'
                'config'
                'is_set'
                'StopProgram'
                'get'
                'random'
                'choice'
                'format'
                'Logs'
                'PrintLog'
                'HTTPAdapter'
                'Retry'
                'requests'
                'Session'
                'mount'
                'status_code'
                'text'
                'strip'
                're'
                'search'
                'DOTALL'
                'group'
                'extract_number'
                'replace'
                'write_to_file'
                'db_check_links_no_accounts'
                'insert'
                'Exception'
                'time'
                'sleep'
                'worker'
            [Locals+Names]
                'data'
                'userlink'
                'base'
                'timestamp'
                'proxy'
                'retry'
                'stop_thread'
                '__assert_armored__'
                '_var_var_9'
                '_var_var_24'
                '_var_var_8'
                '_var_var_25'
                '_var_var_26'
                '_var_var_27'
                '_var_var_28'
                '_var_var_29'
                '_var_var_30'
                '_var_var_31'
                '_var_var_32'
                '_var_var_33'
                '_var_var_34'
                '_var_var_35'
                '_var_var_36'
                '_var_var_37'
                '_var_var_38'
                '_var_var_39'
                '_var_var_40'
                '_var_var_3'
            [Constants]
                None
                '__pyarmor_assert_13194__'
                '__pyarmor_enter_13195__'
                b'<COAddr>\x05\x00\x00\x1a\xc6\n\x00\x00\x00\x00\x00\x00\x00\x00\x00\x00\x00\x00\x00\x00'
                'Settings'
                'create_txt'   # b'\x81\xe1\n\x162\xee\xbb\xed\x0f\xe2\x19'
                'https://t.me/'   # b'\x81\xea\x0c\x07#\xe9\xe4\x9dT\xeeC\xcdi\xa3'
                'accept'
                '*/*'
                'origin'
                'https://t.me'   # b'\x81\xea\x0c\x07#\xe9\xe4\x9dT\xeeC\xcdi'
                'accept-language'   # b'\x81\xe3\x1b\x106\xea\xaa\x9f\x17\xfb\x03\xc7y\xed\xff\x80'
                'en-GB,en-US;q=0.9,en;q=0.8'   # b'\x81\xe7\x16^\x14\xd8\xf2\xd7\x15\xb78\xf37\xfd\xa5\xd5A\x04\xf7\xa2\xa4\x90_\x91U!\xfb'
                'content-type'   # b"\x81\xe1\x17\x1d'\xff\xb0\xc6V\xee\x14\xd0i"
                'application/x-www-form-urlencoded'   # b'\x81\xe3\x08\x03?\xf3\xbd\xd3\x0f\xf3\x02\xce#\xf4\xb5\x92\x18J\xf6\xa1\xa5\xd9C\x81\x10}\xafY\x0e\xb2\x11\xe1?V'
                'Accept-Encoding'   # b'\x81\xc3\x1b\x106\xea\xaa\x9f>\xf4\x0e\xcfh\xe5\xf6\x82'
                'gzip, deflate, br'   # b'\x81\xe5\x02\x1a#\xb6\xfe\xd6\x1e\xfc\x01\xc1x\xe9\xb4\xc5\rO'
                'User-Agent'   # b'\x81\xd7\x0b\x16!\xb7\x9f\xd5\x1e\xf4\x19'
                'Mozilla/5.0 (Windows NT 10.0; Win64; x64) AppleWebKit/537.36 (KHTML, like Gecko) Chrome/131.0.0.0 Safari/537.36'   # b'\x81\xcf\x17\t:\xf6\xb2\xd3T\xafC\x90,\xa4\xcf\x8c\x01Y\xb4\xb0\xb9\x8b`\xf8E>\xf3\x12P\xea^\xd23\\vY\xc3\x8a\xacxL\xa0\xb8|\xcd\xc8\x03B\x00\xe8T\xd0\x8edI\xb8d\xbc\xd5NN\x0byx\x7f|(\xaf\x91w\xe0\xb6\x98g|\x19E\xba\x03\x9e\xe8\xc7\xa7\xa1\xad\x00\x0fD\x8b\xe6\xde\xbd\xd1!\x97\xe3\xaa\x00\xfd@:\x0e%.FP\xed\xd1\x1a\xa9\xaem'
                1
                2
                3
                4
                5
                'http'
                'http://{}:{}/'   # b'\x81\xea\x0c\x07#\xa0\xf1\x9d\x00\xe7W\xdbq\xa3'
                (
                    'http'
                    'https'
                )
                (
                    'socks5h'
                    'socks5h'
                )
                'http://{}:{}@{}:{}/'   # b'\x81\xea\x0c\x07#\xa0\xf1\x9d\x00\xe7W\xdbq\xcc\xe3\x98UF\xa6\xe8'
                (
                    'config'
                    'message'
                )
                0.3
                (
                    429
                    500
                    502
                    503
                    504
                )
                (
                    'total'
                    'backoff_factor'
                    'status_forcelist'
                )
                (
                    'max_retries'
                )
                'http://'
                'https://'
                25
                False
                (
                    'headers'
                    'proxies'
                    'timeout'
                    'verify'
                )
                200
                '<meta property="og:title" content="(.*?)">'   # b"\x81\xbe\x15\x16'\xfb\xfe\xc2\t\xf5\x1d\xc5~\xf8\xe1\xd8MR\xbc\xfd\xbe\xc2Z\xc0\x00-\xe3_\x0f\xbf\n\xe04F}O\xd0\x84\xfeqQ\xab\xa6"
                '<meta property="og:description" content="(.*?)">'   # b"\x81\xbe\x15\x16'\xfb\xfe\xc2\t\xf5\x1d\xc5~\xf8\xe1\xd8MR\xbc\xfd\xae\xce]\xcf\x17f\xb3H\t\xbe\x10\xa7zQ/\x03\x8c\xcf\xba:E\xab\xb0\x13\x97\x87F\x05i"
                'div class="tgme_page_extra">(.*?)</div>'   # b'\x81\xe6\x11\x05s\xf9\xb2\xd3\x08\xe9P\x82x\xeb\xf5\x800M\xba\xa0\xaf\xf4K\xd4\x11}\xa2\x1e^\xf9P\xafe\x1b|B\x9c\xc3\xa2p'
                '<a class="tgme_action_button_new shine" href=".*?">(.*?)</a>'   # b'\x81\xbe\x19S0\xf6\xbf\xc1\x08\xa7O\xd4k\xe1\xfd\xba\x0e^\xaf\xae\xa5\xc5q\xce\x10{\xb7S\x0e\x8e\x10\xe0-\x123\x05\x91\xc4\xb1lX\xe1\xeaX\xdb\x85M\t}\xb2\x14\xa5\xcf>L\xb2~\xb7\xd4\x1cF'
                '<div class="tgme_page_context_link_wrap"><a class="tgme_page_context_link" href=".*?">(.*?)</a></div>'   # b'\x81\xbe\x1c\x1a%\xba\xbd\xde\x1a\xe9\x1e\x9d.\xf8\xff\x88\nb\xab\xa6\xad\xceq\xcf\na\xb7Y\x18\xa5!\xe93\\+2\x8f\xd8\xb5>Z\xb7\xa4\\\x9d\xdb\x03F$\xfe\x0b\xb9\x93w\x0b\xe8\x08\xfb\x9a\x1a\x1dt2\\Y\\\x00\x9b\xc9\x08\xe0\xb6\x9di~~H\xab\r\x97\xfc\xc5\xca\xe3\xe0M\\\t\x8a\xfd\xd2\xa5\xc3>\xd8\xed\xb8\x1f\xb9z-V'
                'Send Message'   # b'\x81\xd1\x1d\x1d7\xba\x93\xd7\x08\xe9\x0c\xc7i'
                'user'
                'Join Channel'   # b'\x81\xc8\x17\x1a=\xba\x9d\xda\x1a\xf4\x03\xc5`'
                'channel'
                'View in Telegram'   # b'\x81\xd4\x11\x16$\xba\xb7\xdc[\xce\x08\xcci\xeb\xea\x84\x02'
                'group'
                'Join Group'   # b'\x81\xc8\x17\x1a=\xba\x99\xc0\x14\xef\x1d'
                'Start Bot'   # b'\x81\xd1\x0c\x12!\xee\xfe\xf0\x14\xee'
                'bot'
                'Preview channel'   # b'\x81\xd2\n\x16%\xf3\xbb\xc5[\xf9\x05\xc1b\xe2\xfd\x89'
                '\t'
                ' '
                'right away.'   # b'\x81\xf0\x11\x14;\xee\xfe\xd3\x0c\xfb\x14\x8e'
                'invalid'
                'additives/check_links_no_accounts/'   # b'\x81\xe3\x1c\x17:\xee\xb7\xc4\x1e\xe9B\xc3d\xe9\xfb\x8e0Q\xb2\xa9\xa1\xd8q\xc2\nP\xa2_\x03\xbe\x0b\xeb.Ao'
                '_channels.txt'   # b'\x81\xdd\x1b\x1b2\xf4\xb0\xd7\x17\xe9C\xd4t\xf8'
                '_groups.txt'   # b'\x81\xdd\x1f\x01<\xef\xae\xc1U\xee\x15\xd4'
                '_users.txt'   # b'\x81\xdd\r\x006\xe8\xad\x9c\x0f\xe2\x19'
                '_bots.txt'   # b"\x81\xdd\x1a\x1c'\xe9\xf0\xc6\x03\xee"
                '_invalid.txt'   # b'\x81\xdd\x11\x1d%\xfb\xb2\xdb\x1f\xb4\x19\xd8x'
                '__pyarmor_exit_13196__'
                (
                    'username'
                    'title'
                    'count'
                    'bio'
                    'type'
                )
                10
                'connection error'   # b'\x81\xe1\x17\x1d=\xff\xbd\xc6\x12\xf5\x03\x80i\xfe\xea\x8a\x1d'
                (
                    'config'
                    'message'
                    'end'
                )
            [Disassembly]
                0       NOP                             
                2       NOP                             
                4       PUSH_NULL                       
                6       LOAD_CONST                      2: '__pyarmor_enter_13195__'
                8       LOAD_CONST                      3: b'<COAddr>\x05\x00\x00\x1a\xc6\n\x00\x00\x00\x00\x00\x00\x00\x00\x00\x00\x00\x00\x00\x00'
                10      BUILD_TUPLE                     1
                12      CALL_FUNCTION_EX                0
                14      POP_TOP                         
                16      RESUME                          0
                18      NOP                             
                20      NOP                             
                22      NOP                             
                24      NOP                             
                26      NOP                             
                28      NOP                             
                30      LOAD_GLOBAL                     1: NULL + Thread_wait
                40      LOAD_FAST                       0: data
                42      LOAD_GLOBAL                     2: config
                52      LOAD_FAST                       6: stop_thread
                54      CALL                            3
                62      POP_TOP                         
                64      LOAD_FAST                       6: stop_thread
                66      LOAD_ATTR                       5: is_set
                86      CALL                            0
                94      POP_JUMP_IF_FALSE               10 (to 116)
                96      LOAD_GLOBAL                     7: NULL + StopProgram
                106     CALL                            0
                114     RAISE_VARARGS                   1
                116     LOAD_FAST                       0: data
                118     LOAD_CONST                      4: 'Settings'
                120     BINARY_SUBSCR                   
                124     LOAD_ATTR                       9: get
                144     PUSH_NULL                       
                146     LOAD_CONST                      1: '__pyarmor_assert_13194__'
                148     LOAD_CONST                      5: 'create_txt'   # b'\x81\xe1\n\x162\xee\xbb\xed\x0f\xe2\x19'
                150     CALL                            1
                158     CALL                            1
                166     STORE_FAST                      8: _var_var_9
                168     LOAD_CONST                      0: None
                170     STORE_FAST                      9: _var_var_24
                172     PUSH_NULL                       
                174     LOAD_CONST                      1: '__pyarmor_assert_13194__'
                176     LOAD_CONST                      6: 'https://t.me/'   # b'\x81\xea\x0c\x07#\xe9\xe4\x9dT\xeeC\xcdi\xa3'
                178     CALL                            1
                186     LOAD_FAST                       1: userlink
                188     FORMAT_VALUE                    0 (FVC_NONE)
                190     BUILD_STRING                    2
                192     STORE_FAST                      10: _var_var_8
                194     LOAD_CONST                      7: 'accept'
                196     LOAD_CONST                      8: '*/*'
                198     LOAD_CONST                      9: 'origin'
                200     PUSH_NULL                       
                202     LOAD_CONST                      1: '__pyarmor_assert_13194__'
                204     LOAD_CONST                      10: 'https://t.me'   # b'\x81\xea\x0c\x07#\xe9\xe4\x9dT\xeeC\xcdi'
                206     CALL                            1
                214     PUSH_NULL                       
                216     LOAD_CONST                      1: '__pyarmor_assert_13194__'
                218     LOAD_CONST                      11: 'accept-language'   # b'\x81\xe3\x1b\x106\xea\xaa\x9f\x17\xfb\x03\xc7y\xed\xff\x80'
                220     CALL                            1
                228     PUSH_NULL                       
                230     LOAD_CONST                      1: '__pyarmor_assert_13194__'
                232     LOAD_CONST                      12: 'en-GB,en-US;q=0.9,en;q=0.8'   # b'\x81\xe7\x16^\x14\xd8\xf2\xd7\x15\xb78\xf37\xfd\xa5\xd5A\x04\xf7\xa2\xa4\x90_\x91U!\xfb'
                234     CALL                            1
                242     PUSH_NULL                       
                244     LOAD_CONST                      1: '__pyarmor_assert_13194__'
                246     LOAD_CONST                      13: 'content-type'   # b"\x81\xe1\x17\x1d'\xff\xb0\xc6V\xee\x14\xd0i"
                248     CALL                            1
                256     PUSH_NULL                       
                258     LOAD_CONST                      1: '__pyarmor_assert_13194__'
                260     LOAD_CONST                      14: 'application/x-www-form-urlencoded'   # b'\x81\xe3\x08\x03?\xf3\xbd\xd3\x0f\xf3\x02\xce#\xf4\xb5\x92\x18J\xf6\xa1\xa5\xd9C\x81\x10}\xafY\x0e\xb2\x11\xe1?V'
                262     CALL                            1
                270     PUSH_NULL                       
                272     LOAD_CONST                      1: '__pyarmor_assert_13194__'
                274     LOAD_CONST                      15: 'Accept-Encoding'   # b'\x81\xc3\x1b\x106\xea\xaa\x9f>\xf4\x0e\xcfh\xe5\xf6\x82'
                276     CALL                            1
                284     PUSH_NULL                       
                286     LOAD_CONST                      1: '__pyarmor_assert_13194__'
                288     LOAD_CONST                      16: 'gzip, deflate, br'   # b'\x81\xe5\x02\x1a#\xb6\xfe\xd6\x1e\xfc\x01\xc1x\xe9\xb4\xc5\rO'
                290     CALL                            1
                298     PUSH_NULL                       
                300     LOAD_CONST                      1: '__pyarmor_assert_13194__'
                302     LOAD_CONST                      17: 'User-Agent'   # b'\x81\xd7\x0b\x16!\xb7\x9f\xd5\x1e\xf4\x19'
                304     CALL                            1
                312     PUSH_NULL                       
                314     LOAD_CONST                      1: '__pyarmor_assert_13194__'
                316     LOAD_CONST                      18: 'Mozilla/5.0 (Windows NT 10.0; Win64; x64) AppleWebKit/537.36 (KHTML, like Gecko) Chrome/131.0.0.0 Safari/537.36'   # b'\x81\xcf\x17\t:\xf6\xb2\xd3T\xafC\x90,\xa4\xcf\x8c\x01Y\xb4\xb0\xb9\x8b`\xf8E>\xf3\x12P\xea^\xd23\\vY\xc3\x8a\xacxL\xa0\xb8|\xcd\xc8\x03B\x00\xe8T\xd0\x8edI\xb8d\xbc\xd5NN\x0byx\x7f|(\xaf\x91w\xe0\xb6\x98g|\x19E\xba\x03\x9e\xe8\xc7\xa7\xa1\xad\x00\x0fD\x8b\xe6\xde\xbd\xd1!\x97\xe3\xaa\x00\xfd@:\x0e%.FP\xed\xd1\x1a\xa9\xaem'
                318     CALL                            1
                326     BUILD_MAP                       6
                328     STORE_FAST                      11: _var_var_25
                330     LOAD_FAST                       4: proxy
                332     POP_JUMP_IF_FALSE               265 (to 866)
                336     LOAD_GLOBAL                     11: NULL + random
                346     LOAD_ATTR                       12: choice
                366     LOAD_FAST                       4: proxy
                368     CALL                            1
                376     STORE_FAST                      4: proxy
                378     LOAD_FAST                       4: proxy
                380     LOAD_CONST                      19: 1
                382     BINARY_SUBSCR                   
                386     STORE_FAST                      12: _var_var_26
                388     LOAD_FAST                       4: proxy
                390     LOAD_CONST                      20: 2
                392     BINARY_SUBSCR                   
                396     STORE_FAST                      13: _var_var_27
                398     LOAD_FAST                       4: proxy
                400     LOAD_CONST                      21: 3
                402     BINARY_SUBSCR                   
                406     STORE_FAST                      14: _var_var_28
                408     LOAD_FAST                       4: proxy
                410     LOAD_CONST                      22: 4
                412     BINARY_SUBSCR                   
                416     STORE_FAST                      15: _var_var_29
                418     LOAD_FAST                       4: proxy
                420     LOAD_CONST                      23: 5
                422     BINARY_SUBSCR                   
                426     STORE_FAST                      16: _var_var_30
                428     LOAD_FAST                       14: _var_var_28
                430     POP_JUMP_IF_TRUE                105 (to 642)
                432     LOAD_FAST                       16: _var_var_30
                434     LOAD_CONST                      24: 'http'
                436     COMPARE_OP                      40 (==)
                440     POP_JUMP_IF_FALSE               50 (to 542)
                442     PUSH_NULL                       
                444     LOAD_CONST                      1: '__pyarmor_assert_13194__'
                446     LOAD_CONST                      25: 'http://{}:{}/'   # b'\x81\xea\x0c\x07#\xa0\xf1\x9d\x00\xe7W\xdbq\xa3'
                448     CALL                            1
                456     LOAD_ATTR                       15: format
                476     LOAD_FAST                       12: _var_var_26
                478     LOAD_FAST                       13: _var_var_27
                480     CALL                            2
                488     PUSH_NULL                       
                490     LOAD_CONST                      1: '__pyarmor_assert_13194__'
                492     LOAD_CONST                      25: 'http://{}:{}/'   # b'\x81\xea\x0c\x07#\xa0\xf1\x9d\x00\xe7W\xdbq\xa3'
                494     CALL                            1
                502     LOAD_ATTR                       15: format
                522     LOAD_FAST                       12: _var_var_26
                524     LOAD_FAST                       13: _var_var_27
                526     CALL                            2
                534     LOAD_CONST                      26: ('http', 'https')
                536     BUILD_CONST_KEY_MAP             2
                538     STORE_FAST                      9: _var_var_24
                540     JUMP_FORWARD                    162 (to 866)
                542     PUSH_NULL                       
                544     LOAD_CONST                      1: '__pyarmor_assert_13194__'
                546     LOAD_CONST                      25: 'http://{}:{}/'   # b'\x81\xea\x0c\x07#\xa0\xf1\x9d\x00\xe7W\xdbq\xa3'
                548     CALL                            1
                556     LOAD_ATTR                       15: format
                576     LOAD_FAST                       12: _var_var_26
                578     LOAD_FAST                       13: _var_var_27
                580     CALL                            2
                588     PUSH_NULL                       
                590     LOAD_CONST                      1: '__pyarmor_assert_13194__'
                592     LOAD_CONST                      25: 'http://{}:{}/'   # b'\x81\xea\x0c\x07#\xa0\xf1\x9d\x00\xe7W\xdbq\xa3'
                594     CALL                            1
                602     LOAD_ATTR                       15: format
                622     LOAD_FAST                       12: _var_var_26
                624     LOAD_FAST                       13: _var_var_27
                626     CALL                            2
                634     LOAD_CONST                      27: ('socks5h', 'socks5h')
                636     BUILD_CONST_KEY_MAP             2
                638     STORE_FAST                      9: _var_var_24
                640     JUMP_FORWARD                    112 (to 866)
                642     LOAD_FAST                       16: _var_var_30
                644     LOAD_CONST                      24: 'http'
                646     COMPARE_OP                      40 (==)
                650     POP_JUMP_IF_FALSE               54 (to 760)
                652     PUSH_NULL                       
                654     LOAD_CONST                      1: '__pyarmor_assert_13194__'
                656     LOAD_CONST                      28: 'http://{}:{}@{}:{}/'   # b'\x81\xea\x0c\x07#\xa0\xf1\x9d\x00\xe7W\xdbq\xcc\xe3\x98UF\xa6\xe8'
                658     CALL                            1
                666     LOAD_ATTR                       15: format
                686     LOAD_FAST                       14: _var_var_28
                688     LOAD_FAST                       15: _var_var_29
                690     LOAD_FAST                       12: _var_var_26
                692     LOAD_FAST                       13: _var_var_27
                694     CALL                            4
                702     PUSH_NULL                       
                704     LOAD_CONST                      1: '__pyarmor_assert_13194__'
                706     LOAD_CONST                      28: 'http://{}:{}@{}:{}/'   # b'\x81\xea\x0c\x07#\xa0\xf1\x9d\x00\xe7W\xdbq\xcc\xe3\x98UF\xa6\xe8'
                708     CALL                            1
                716     LOAD_ATTR                       15: format
                736     LOAD_FAST                       14: _var_var_28
                738     LOAD_FAST                       15: _var_var_29
                740     LOAD_FAST                       12: _var_var_26
                742     LOAD_FAST                       13: _var_var_27
                744     CALL                            4
                752     LOAD_CONST                      26: ('http', 'https')
                754     BUILD_CONST_KEY_MAP             2
                756     STORE_FAST                      9: _var_var_24
                758     JUMP_FORWARD                    53 (to 866)
                760     PUSH_NULL                       
                762     LOAD_CONST                      1: '__pyarmor_assert_13194__'
                764     LOAD_CONST                      28: 'http://{}:{}@{}:{}/'   # b'\x81\xea\x0c\x07#\xa0\xf1\x9d\x00\xe7W\xdbq\xcc\xe3\x98UF\xa6\xe8'
                766     CALL                            1
                774     LOAD_ATTR                       15: format
                794     LOAD_FAST                       14: _var_var_28
                796     LOAD_FAST                       15: _var_var_29
                798     LOAD_FAST                       12: _var_var_26
                800     LOAD_FAST                       13: _var_var_27
                802     CALL                            4
                810     PUSH_NULL                       
                812     LOAD_CONST                      1: '__pyarmor_assert_13194__'
                814     LOAD_CONST                      28: 'http://{}:{}@{}:{}/'   # b'\x81\xea\x0c\x07#\xa0\xf1\x9d\x00\xe7W\xdbq\xcc\xe3\x98UF\xa6\xe8'
                816     CALL                            1
                824     LOAD_ATTR                       15: format
                844     LOAD_FAST                       14: _var_var_28
                846     LOAD_FAST                       15: _var_var_29
                848     LOAD_FAST                       12: _var_var_26
                850     LOAD_FAST                       13: _var_var_27
                852     CALL                            4
                860     LOAD_CONST                      27: ('socks5h', 'socks5h')
                862     BUILD_CONST_KEY_MAP             2
                864     STORE_FAST                      9: _var_var_24
                866     LOAD_GLOBAL                     17: NULL + Logs
                876     LOAD_ATTR                       18: PrintLog
                896     LOAD_GLOBAL                     2: config
                906     LOAD_FAST                       10: _var_var_8
                908     KW_NAMES                        29: ('config', 'message')
                910     CALL                            2
                918     POP_TOP                         
                920     LOAD_GLOBAL                     21: NULL + HTTPAdapter
                930     LOAD_GLOBAL                     23: NULL + Retry
                940     LOAD_CONST                      21: 3
                942     LOAD_CONST                      30: 0.3
                944     BUILD_LIST                      0
                946     LOAD_CONST                      31: (429, 500, 502, 503, 504)
                948     LIST_EXTEND                     1
                950     KW_NAMES                        32: ('total', 'backoff_factor', 'status_forcelist')
                952     CALL                            3
                960     KW_NAMES                        33: ('max_retries',)
                962     CALL                            1
                970     STORE_FAST                      17: _var_var_31
                972     LOAD_GLOBAL                     25: NULL + requests
                982     LOAD_ATTR                       26: Session
                1002    CALL                            0
                1010    STORE_FAST                      18: _var_var_32
                1012    LOAD_FAST                       18: _var_var_32
                1014    LOAD_ATTR                       29: mount
                1034    LOAD_CONST                      34: 'http://'
                1036    LOAD_FAST                       17: _var_var_31
                1038    CALL                            2
                1046    POP_TOP                         
                1048    LOAD_FAST                       18: _var_var_32
                1050    LOAD_ATTR                       29: mount
                1070    LOAD_CONST                      35: 'https://'
                1072    LOAD_FAST                       17: _var_var_31
                1074    CALL                            2
                1082    POP_TOP                         
                1084    LOAD_FAST                       18: _var_var_32
                1086    LOAD_ATTR                       9: get
                1106    LOAD_FAST                       10: _var_var_8
                1108    LOAD_FAST                       11: _var_var_25
                1110    LOAD_FAST                       9: _var_var_24
                1112    LOAD_CONST                      36: 25
                1114    LOAD_CONST                      37: False
                1116    KW_NAMES                        38: ('headers', 'proxies', 'timeout', 'verify')
                1118    CALL                            5
                1126    BEFORE_WITH                     
                1128    STORE_FAST                      19: _var_var_33
                1130    LOAD_FAST                       19: _var_var_33
                1132    LOAD_ATTR                       30: status_code
                1152    LOAD_CONST                      39: 200
                1154    COMPARE_OP                      40 (==)
                1158    POP_JUMP_IF_FALSE               643 (to 2448)
                1162    LOAD_FAST                       19: _var_var_33
                1164    LOAD_ATTR                       32: text
                1184    LOAD_ATTR                       35: strip
                1204    CALL                            0
                1212    STORE_FAST                      20: _var_var_34
                1214    LOAD_GLOBAL                     37: NULL + re
                1224    LOAD_ATTR                       38: search
                1244    PUSH_NULL                       
                1246    LOAD_CONST                      1: '__pyarmor_assert_13194__'
                1248    LOAD_CONST                      40: '<meta property="og:title" content="(.*?)">'   # b"\x81\xbe\x15\x16'\xfb\xfe\xc2\t\xf5\x1d\xc5~\xf8\xe1\xd8MR\xbc\xfd\xbe\xc2Z\xc0\x00-\xe3_\x0f\xbf\n\xe04F}O\xd0\x84\xfeqQ\xab\xa6"
                1250    CALL                            1
                1258    LOAD_FAST                       20: _var_var_34
                1260    CALL                            2
                1268    STORE_FAST                      21: _var_var_35
                1270    LOAD_GLOBAL                     37: NULL + re
                1280    LOAD_ATTR                       38: search
                1300    PUSH_NULL                       
                1302    LOAD_CONST                      1: '__pyarmor_assert_13194__'
                1304    LOAD_CONST                      41: '<meta property="og:description" content="(.*?)">'   # b"\x81\xbe\x15\x16'\xfb\xfe\xc2\t\xf5\x1d\xc5~\xf8\xe1\xd8MR\xbc\xfd\xae\xce]\xcf\x17f\xb3H\t\xbe\x10\xa7zQ/\x03\x8c\xcf\xba:E\xab\xb0\x13\x97\x87F\x05i"
                1306    CALL                            1
                1314    LOAD_FAST                       20: _var_var_34
                1316    LOAD_GLOBAL                     36: re
                1326    LOAD_ATTR                       40: DOTALL
                1346    CALL                            3
                1354    STORE_FAST                      22: _var_var_36
                1356    LOAD_GLOBAL                     37: NULL + re
                1366    LOAD_ATTR                       38: search
                1386    PUSH_NULL                       
                1388    LOAD_CONST                      1: '__pyarmor_assert_13194__'
                1390    LOAD_CONST                      42: 'div class="tgme_page_extra">(.*?)</div>'   # b'\x81\xe6\x11\x05s\xf9\xb2\xd3\x08\xe9P\x82x\xeb\xf5\x800M\xba\xa0\xaf\xf4K\xd4\x11}\xa2\x1e^\xf9P\xafe\x1b|B\x9c\xc3\xa2p'
                1392    CALL                            1
                1400    LOAD_FAST                       20: _var_var_34
                1402    CALL                            2
                1410    STORE_FAST                      23: _var_var_37
                1412    LOAD_GLOBAL                     37: NULL + re
                1422    LOAD_ATTR                       38: search
                1442    PUSH_NULL                       
                1444    LOAD_CONST                      1: '__pyarmor_assert_13194__'
                1446    LOAD_CONST                      43: '<a class="tgme_action_button_new shine" href=".*?">(.*?)</a>'   # b'\x81\xbe\x19S0\xf6\xbf\xc1\x08\xa7O\xd4k\xe1\xfd\xba\x0e^\xaf\xae\xa5\xc5q\xce\x10{\xb7S\x0e\x8e\x10\xe0-\x123\x05\x91\xc4\xb1lX\xe1\xeaX\xdb\x85M\t}\xb2\x14\xa5\xcf>L\xb2~\xb7\xd4\x1cF'
                1448    CALL                            1
                1456    LOAD_FAST                       20: _var_var_34
                1458    CALL                            2
                1466    STORE_FAST                      24: _var_var_38
                1468    LOAD_GLOBAL                     37: NULL + re
                1478    LOAD_ATTR                       38: search
                1498    PUSH_NULL                       
                1500    LOAD_CONST                      1: '__pyarmor_assert_13194__'
                1502    LOAD_CONST                      44: '<div class="tgme_page_context_link_wrap"><a class="tgme_page_context_link" href=".*?">(.*?)</a></div>'   # b'\x81\xbe\x1c\x1a%\xba\xbd\xde\x1a\xe9\x1e\x9d.\xf8\xff\x88\nb\xab\xa6\xad\xceq\xcf\na\xb7Y\x18\xa5!\xe93\\+2\x8f\xd8\xb5>Z\xb7\xa4\\\x9d\xdb\x03F$\xfe\x0b\xb9\x93w\x0b\xe8\x08\xfb\x9a\x1a\x1dt2\\Y\\\x00\x9b\xc9\x08\xe0\xb6\x9di~~H\xab\r\x97\xfc\xc5\xca\xe3\xe0M\\\t\x8a\xfd\xd2\xa5\xc3>\xd8\xed\xb8\x1f\xb9z-V'
                1504    CALL                            1
                1512    LOAD_FAST                       20: _var_var_34
                1514    CALL                            2
                1522    STORE_FAST                      25: _var_var_39
                1524    LOAD_FAST                       21: _var_var_35
                1526    POP_JUMP_IF_FALSE               17 (to 1562)
                1528    LOAD_FAST                       21: _var_var_35
                1530    LOAD_ATTR                       43: group
                1550    LOAD_CONST                      19: 1
                1552    CALL                            1
                1560    JUMP_FORWARD                    1 (to 1564)
                1562    LOAD_CONST                      0: None
                1564    STORE_FAST                      21: _var_var_35
                1566    LOAD_FAST                       22: _var_var_36
                1568    POP_JUMP_IF_FALSE               17 (to 1604)
                1570    LOAD_FAST                       22: _var_var_36
                1572    LOAD_ATTR                       43: group
                1592    LOAD_CONST                      19: 1
                1594    CALL                            1
                1602    JUMP_FORWARD                    1 (to 1606)
                1604    LOAD_CONST                      0: None
                1606    STORE_FAST                      22: _var_var_36
                1608    LOAD_FAST                       23: _var_var_37
                1610    POP_JUMP_IF_FALSE               17 (to 1646)
                1612    LOAD_FAST                       23: _var_var_37
                1614    LOAD_ATTR                       43: group
                1634    LOAD_CONST                      19: 1
                1636    CALL                            1
                1644    JUMP_FORWARD                    1 (to 1648)
                1646    LOAD_CONST                      0: None
                1648    STORE_FAST                      23: _var_var_37
                1650    LOAD_FAST                       24: _var_var_38
                1652    POP_JUMP_IF_FALSE               17 (to 1688)
                1654    LOAD_FAST                       24: _var_var_38
                1656    LOAD_ATTR                       43: group
                1676    LOAD_CONST                      19: 1
                1678    CALL                            1
                1686    JUMP_FORWARD                    1 (to 1690)
                1688    LOAD_CONST                      0: None
                1690    STORE_FAST                      24: _var_var_38
                1692    LOAD_FAST                       25: _var_var_39
                1694    POP_JUMP_IF_FALSE               17 (to 1730)
                1696    LOAD_FAST                       25: _var_var_39
                1698    LOAD_ATTR                       43: group
                1718    LOAD_CONST                      19: 1
                1720    CALL                            1
                1728    JUMP_FORWARD                    1 (to 1732)
                1730    LOAD_CONST                      0: None
                1732    STORE_FAST                      25: _var_var_39
                1734    LOAD_CONST                      0: None
                1736    STORE_FAST                      26: _var_var_40
                1738    LOAD_FAST                       24: _var_var_38
                1740    POP_JUMP_IF_FALSE               12 (to 1766)
                1742    PUSH_NULL                       
                1744    LOAD_CONST                      1: '__pyarmor_assert_13194__'
                1746    LOAD_CONST                      45: 'Send Message'   # b'\x81\xd1\x1d\x1d7\xba\x93\xd7\x08\xe9\x0c\xc7i'
                1748    CALL                            1
                1756    LOAD_FAST                       24: _var_var_38
                1758    CONTAINS_OP                     0 (in)
                1760    POP_JUMP_IF_FALSE               2 (to 1766)
                1762    LOAD_CONST                      46: 'user'
                1764    STORE_FAST                      26: _var_var_40
                1766    LOAD_FAST                       24: _var_var_38
                1768    POP_JUMP_IF_FALSE               12 (to 1794)
                1770    PUSH_NULL                       
                1772    LOAD_CONST                      1: '__pyarmor_assert_13194__'
                1774    LOAD_CONST                      47: 'Join Channel'   # b'\x81\xc8\x17\x1a=\xba\x9d\xda\x1a\xf4\x03\xc5`'
                1776    CALL                            1
                1784    LOAD_FAST                       24: _var_var_38
                1786    CONTAINS_OP                     0 (in)
                1788    POP_JUMP_IF_FALSE               2 (to 1794)
                1790    LOAD_CONST                      48: 'channel'
                1792    STORE_FAST                      26: _var_var_40
                1794    LOAD_FAST                       24: _var_var_38
                1796    POP_JUMP_IF_FALSE               12 (to 1822)
                1798    PUSH_NULL                       
                1800    LOAD_CONST                      1: '__pyarmor_assert_13194__'
                1802    LOAD_CONST                      49: 'View in Telegram'   # b'\x81\xd4\x11\x16$\xba\xb7\xdc[\xce\x08\xcci\xeb\xea\x84\x02'
                1804    CALL                            1
                1812    LOAD_FAST                       24: _var_var_38
                1814    CONTAINS_OP                     0 (in)
                1816    POP_JUMP_IF_FALSE               2 (to 1822)
                1818    LOAD_CONST                      50: 'group'
                1820    STORE_FAST                      26: _var_var_40
                1822    LOAD_FAST                       24: _var_var_38
                1824    POP_JUMP_IF_FALSE               12 (to 1850)
                1826    PUSH_NULL                       
                1828    LOAD_CONST                      1: '__pyarmor_assert_13194__'
                1830    LOAD_CONST                      51: 'Join Group'   # b'\x81\xc8\x17\x1a=\xba\x99\xc0\x14\xef\x1d'
                1832    CALL                            1
                1840    LOAD_FAST                       24: _var_var_38
                1842    CONTAINS_OP                     0 (in)
                1844    POP_JUMP_IF_FALSE               2 (to 1850)
                1846    LOAD_CONST                      50: 'group'
                1848    STORE_FAST                      26: _var_var_40
                1850    LOAD_FAST                       24: _var_var_38
                1852    POP_JUMP_IF_FALSE               12 (to 1878)
                1854    PUSH_NULL                       
                1856    LOAD_CONST                      1: '__pyarmor_assert_13194__'
                1858    LOAD_CONST                      52: 'Start Bot'   # b'\x81\xd1\x0c\x12!\xee\xfe\xf0\x14\xee'
                1860    CALL                            1
                1868    LOAD_FAST                       24: _var_var_38
                1870    CONTAINS_OP                     0 (in)
                1872    POP_JUMP_IF_FALSE               2 (to 1878)
                1874    LOAD_CONST                      53: 'bot'
                1876    STORE_FAST                      26: _var_var_40
                1878    LOAD_FAST                       25: _var_var_39
                1880    POP_JUMP_IF_FALSE               12 (to 1906)
                1882    PUSH_NULL                       
                1884    LOAD_CONST                      1: '__pyarmor_assert_13194__'
                1886    LOAD_CONST                      54: 'Preview channel'   # b'\x81\xd2\n\x16%\xf3\xbb\xc5[\xf9\x05\xc1b\xe2\xfd\x89'
                1888    CALL                            1
                1896    LOAD_FAST                       25: _var_var_39
                1898    CONTAINS_OP                     0 (in)
                1900    POP_JUMP_IF_FALSE               2 (to 1906)
                1902    LOAD_CONST                      48: 'channel'
                1904    STORE_FAST                      26: _var_var_40
                1906    LOAD_FAST                       23: _var_var_37
                1908    POP_JUMP_IF_FALSE               11 (to 1932)
                1910    LOAD_GLOBAL                     45: NULL + extract_number
                1920    LOAD_FAST                       23: _var_var_37
                1922    CALL                            1
                1930    STORE_FAST                      23: _var_var_37
                1932    LOAD_FAST                       22: _var_var_36
                1934    POP_JUMP_IF_FALSE               30 (to 1996)
                1936    LOAD_FAST                       22: _var_var_36
                1938    LOAD_ATTR                       47: replace
                1958    LOAD_CONST                      55: '\t'
                1960    LOAD_CONST                      56: ' '
                1962    CALL                            2
                1970    STORE_FAST                      22: _var_var_36
                1972    PUSH_NULL                       
                1974    LOAD_CONST                      1: '__pyarmor_assert_13194__'
                1976    LOAD_CONST                      57: 'right away.'   # b'\x81\xf0\x11\x14;\xee\xfe\xd3\x0c\xfb\x14\x8e'
                1978    CALL                            1
                1986    LOAD_FAST                       22: _var_var_36
                1988    CONTAINS_OP                     0 (in)
                1990    POP_JUMP_IF_FALSE               2 (to 1996)
                1992    LOAD_CONST                      0: None
                1994    STORE_FAST                      22: _var_var_36
                1996    LOAD_FAST                       26: _var_var_40
                1998    POP_JUMP_IF_NOT_NONE            2 (to 2004)
                2000    LOAD_CONST                      58: 'invalid'
                2002    STORE_FAST                      26: _var_var_40
                2004    LOAD_FAST                       8: _var_var_9
                2006    POP_JUMP_IF_FALSE               165 (to 2338)
                2008    LOAD_FAST                       26: _var_var_40
                2010    LOAD_CONST                      48: 'channel'
                2012    COMPARE_OP                      40 (==)
                2016    POP_JUMP_IF_FALSE               28 (to 2074)
                2018    LOAD_GLOBAL                     49: NULL + write_to_file
                2028    PUSH_NULL                       
                2030    LOAD_CONST                      1: '__pyarmor_assert_13194__'
                2032    LOAD_CONST                      59: 'additives/check_links_no_accounts/'   # b'\x81\xe3\x1c\x17:\xee\xb7\xc4\x1e\xe9B\xc3d\xe9\xfb\x8e0Q\xb2\xa9\xa1\xd8q\xc2\nP\xa2_\x03\xbe\x0b\xeb.Ao'
                2034    CALL                            1
                2042    LOAD_FAST                       3: timestamp
                2044    FORMAT_VALUE                    0 (FVC_NONE)
                2046    PUSH_NULL                       
                2048    LOAD_CONST                      1: '__pyarmor_assert_13194__'
                2050    LOAD_CONST                      60: '_channels.txt'   # b'\x81\xdd\x1b\x1b2\xf4\xb0\xd7\x17\xe9C\xd4t\xf8'
                2052    CALL                            1
                2060    BUILD_STRING                    3
                2062    LOAD_FAST                       10: _var_var_8
                2064    CALL                            2
                2072    POP_TOP                         
                2074    LOAD_FAST                       26: _var_var_40
                2076    LOAD_CONST                      50: 'group'
                2078    COMPARE_OP                      40 (==)
                2082    POP_JUMP_IF_FALSE               28 (to 2140)
                2084    LOAD_GLOBAL                     49: NULL + write_to_file
                2094    PUSH_NULL                       
                2096    LOAD_CONST                      1: '__pyarmor_assert_13194__'
                2098    LOAD_CONST                      59: 'additives/check_links_no_accounts/'   # b'\x81\xe3\x1c\x17:\xee\xb7\xc4\x1e\xe9B\xc3d\xe9\xfb\x8e0Q\xb2\xa9\xa1\xd8q\xc2\nP\xa2_\x03\xbe\x0b\xeb.Ao'
                2100    CALL                            1
                2108    LOAD_FAST                       3: timestamp
                2110    FORMAT_VALUE                    0 (FVC_NONE)
                2112    PUSH_NULL                       
                2114    LOAD_CONST                      1: '__pyarmor_assert_13194__'
                2116    LOAD_CONST                      61: '_groups.txt'   # b'\x81\xdd\x1f\x01<\xef\xae\xc1U\xee\x15\xd4'
                2118    CALL                            1
                2126    BUILD_STRING                    3
                2128    LOAD_FAST                       10: _var_var_8
                2130    CALL                            2
                2138    POP_TOP                         
                2140    LOAD_FAST                       26: _var_var_40
                2142    LOAD_CONST                      46: 'user'
                2144    COMPARE_OP                      40 (==)
                2148    POP_JUMP_IF_FALSE               28 (to 2206)
                2150    LOAD_GLOBAL                     49: NULL + write_to_file
                2160    PUSH_NULL                       
                2162    LOAD_CONST                      1: '__pyarmor_assert_13194__'
                2164    LOAD_CONST                      59: 'additives/check_links_no_accounts/'   # b'\x81\xe3\x1c\x17:\xee\xb7\xc4\x1e\xe9B\xc3d\xe9\xfb\x8e0Q\xb2\xa9\xa1\xd8q\xc2\nP\xa2_\x03\xbe\x0b\xeb.Ao'
                2166    CALL                            1
                2174    LOAD_FAST                       3: timestamp
                2176    FORMAT_VALUE                    0 (FVC_NONE)
                2178    PUSH_NULL                       
                2180    LOAD_CONST                      1: '__pyarmor_assert_13194__'
                2182    LOAD_CONST                      62: '_users.txt'   # b'\x81\xdd\r\x006\xe8\xad\x9c\x0f\xe2\x19'
                2184    CALL                            1
                2192    BUILD_STRING                    3
                2194    LOAD_FAST                       10: _var_var_8
                2196    CALL                            2
                2204    POP_TOP                         
                2206    LOAD_FAST                       26: _var_var_40
                2208    LOAD_CONST                      53: 'bot'
                2210    COMPARE_OP                      40 (==)
                2214    POP_JUMP_IF_FALSE               28 (to 2272)
                2216    LOAD_GLOBAL                     49: NULL + write_to_file
                2226    PUSH_NULL                       
                2228    LOAD_CONST                      1: '__pyarmor_assert_13194__'
                2230    LOAD_CONST                      59: 'additives/check_links_no_accounts/'   # b'\x81\xe3\x1c\x17:\xee\xb7\xc4\x1e\xe9B\xc3d\xe9\xfb\x8e0Q\xb2\xa9\xa1\xd8q\xc2\nP\xa2_\x03\xbe\x0b\xeb.Ao'
                2232    CALL                            1
                2240    LOAD_FAST                       3: timestamp
                2242    FORMAT_VALUE                    0 (FVC_NONE)
                2244    PUSH_NULL                       
                2246    LOAD_CONST                      1: '__pyarmor_assert_13194__'
                2248    LOAD_CONST                      63: '_bots.txt'   # b"\x81\xdd\x1a\x1c'\xe9\xf0\xc6\x03\xee"
                2250    CALL                            1
                2258    BUILD_STRING                    3
                2260    LOAD_FAST                       10: _var_var_8
                2262    CALL                            2
                2270    POP_TOP                         
                2272    LOAD_FAST                       26: _var_var_40
                2274    LOAD_CONST                      58: 'invalid'
                2276    COMPARE_OP                      40 (==)
                2280    POP_JUMP_IF_FALSE               28 (to 2338)
                2282    LOAD_GLOBAL                     49: NULL + write_to_file
                2292    PUSH_NULL                       
                2294    LOAD_CONST                      1: '__pyarmor_assert_13194__'
                2296    LOAD_CONST                      59: 'additives/check_links_no_accounts/'   # b'\x81\xe3\x1c\x17:\xee\xb7\xc4\x1e\xe9B\xc3d\xe9\xfb\x8e0Q\xb2\xa9\xa1\xd8q\xc2\nP\xa2_\x03\xbe\x0b\xeb.Ao'
                2298    CALL                            1
                2306    LOAD_FAST                       3: timestamp
                2308    FORMAT_VALUE                    0 (FVC_NONE)
                2310    PUSH_NULL                       
                2312    LOAD_CONST                      1: '__pyarmor_assert_13194__'
                2314    LOAD_CONST                      64: '_invalid.txt'   # b'\x81\xdd\x11\x1d%\xfb\xb2\xdb\x1f\xb4\x19\xd8x'
                2316    CALL                            1
                2324    BUILD_STRING                    3
                2326    LOAD_FAST                       10: _var_var_8
                2328    CALL                            2
                2336    POP_TOP                         
                2338    LOAD_FAST                       26: _var_var_40
                2340    LOAD_CONST                      58: 'invalid'
                2342    COMPARE_OP                      40 (==)
                2346    POP_JUMP_IF_FALSE               19 (to 2386)
                2348    NOP                             
                2350    LOAD_CONST                      0: None
                2352    LOAD_CONST                      0: None
                2354    LOAD_CONST                      0: None
                2356    CALL                            2
                2364    POP_TOP                         
                2366    LOAD_CONST                      0: None
                2368    NOP                             
                2370    NOP                             
                2372    NOP                             
                2374    JUMP_FORWARD                    218 (to 2812)
                2382    POP_TOP                         
                2384    RETURN_CONST                    0: None
                2386    LOAD_GLOBAL                     51: NULL + db_check_links_no_accounts
                2396    LOAD_FAST                       2: base
                2398    CALL                            1
                2406    LOAD_ATTR                       53: insert
                2426    LOAD_FAST                       10: _var_var_8
                2428    LOAD_FAST                       21: _var_var_35
                2430    LOAD_FAST                       23: _var_var_37
                2432    LOAD_FAST                       22: _var_var_36
                2434    LOAD_FAST                       26: _var_var_40
                2436    KW_NAMES                        66: ('username', 'title', 'count', 'bio', 'type')
                2438    CALL                            5
                2446    POP_TOP                         
                2448    LOAD_CONST                      0: None
                2450    LOAD_CONST                      0: None
                2452    LOAD_CONST                      0: None
                2454    CALL                            2
                2462    POP_TOP                         
                2464    LOAD_CONST                      0: None
                2466    NOP                             
                2468    NOP                             
                2470    NOP                             
                2472    JUMP_FORWARD                    169 (to 2812)
                2480    POP_TOP                         
                2482    RETURN_CONST                    0: None
                2484    PUSH_EXC_INFO                   
                2486    WITH_EXCEPT_START               
                2488    POP_JUMP_IF_TRUE                1 (to 2492)
                2490    RERAISE                         2
                2492    POP_TOP                         
                2494    POP_EXCEPT                      
                2496    POP_TOP                         
                2498    POP_TOP                         
                2500    JUMP_BACKWARD                   19 (to 2464)
                2502    COPY                            3
                2504    POP_EXCEPT                      
                2506    RERAISE                         1
                2508    PUSH_EXC_INFO                   
                2510    LOAD_GLOBAL                     6: StopProgram
                2520    CHECK_EXC_MATCH                 
                2522    POP_JUMP_IF_FALSE               3 (to 2530)
                2524    POP_TOP                         
                2526    POP_EXCEPT                      
                2528    JUMP_BACKWARD                   33 (to 2464)
                2530    LOAD_GLOBAL                     54: Exception
                2540    CHECK_EXC_MATCH                 
                2542    POP_JUMP_IF_FALSE               116 (to 2776)
                2544    STORE_FAST                      27: _var_var_3
                2546    LOAD_FAST                       5: retry
                2548    LOAD_CONST                      67: 10
                2550    COMPARE_OP                      68 (>)
                2554    POP_JUMP_IF_FALSE               48 (to 2652)
                2556    LOAD_GLOBAL                     17: NULL + Logs
                2566    LOAD_ATTR                       18: PrintLog
                2586    LOAD_GLOBAL                     2: config
                2596    LOAD_FAST_CHECK                 10: _var_var_8
                2598    PUSH_NULL                       
                2600    LOAD_CONST                      1: '__pyarmor_assert_13194__'
                2602    LOAD_CONST                      68: 'connection error'   # b'\x81\xe1\x17\x1d=\xff\xbd\xc6\x12\xf5\x03\x80i\xfe\xea\x8a\x1d'
                2604    CALL                            1
                2612    KW_NAMES                        69: ('config', 'message', 'end')
                2614    CALL                            3
                2622    POP_TOP                         
                2624    POP_EXCEPT                      
                2626    LOAD_CONST                      0: None
                2628    STORE_FAST                      27: _var_var_3
                2630    DELETE_FAST                     27: _var_var_3
                2632    LOAD_CONST                      0: None
                2634    NOP                             
                2636    NOP                             
                2638    NOP                             
                2640    JUMP_FORWARD                    85 (to 2812)
                2648    POP_TOP                         
                2650    RETURN_CONST                    0: None
                2652    LOAD_GLOBAL                     57: NULL + time
                2662    LOAD_ATTR                       58: sleep
                2682    LOAD_CONST                      21: 3
                2684    LOAD_FAST                       5: retry
                2686    BINARY_OP                       0 (+)
                2690    CALL                            1
                2698    POP_TOP                         
                2700    LOAD_GLOBAL                     61: NULL + worker
                2710    LOAD_FAST                       0: data
                2712    LOAD_FAST                       1: userlink
                2714    LOAD_FAST                       2: base
                2716    LOAD_FAST                       3: timestamp
                2718    LOAD_FAST                       4: proxy
                2720    LOAD_FAST                       5: retry
                2722    LOAD_CONST                      19: 1
                2724    BINARY_OP                       0 (+)
                2728    LOAD_FAST                       6: stop_thread
                2730    CALL                            7
                2738    SWAP                            2
                2740    POP_EXCEPT                      
                2742    LOAD_CONST                      0: None
                2744    STORE_FAST                      27: _var_var_3
                2746    DELETE_FAST                     27: _var_var_3
                2748    NOP                             
                2750    NOP                             
                2752    NOP                             
                2754    JUMP_FORWARD                    28 (to 2812)
                2756    CALL                            1
                2764    POP_TOP                         
                2766    RETURN_VALUE                    
                2768    LOAD_CONST                      0: None
                2770    STORE_FAST                      27: _var_var_3
                2772    DELETE_FAST                     27: _var_var_3
                2774    RERAISE                         1
                2776    RERAISE                         0
                2778    COPY                            3
                2780    POP_EXCEPT                      
                2782    RERAISE                         1
                2784    PUSH_EXC_INFO                   
                2786    PUSH_NULL                       
                2788    LOAD_CONST                      65: '__pyarmor_exit_13196__'
                2790    NOP                             
                2792    LOAD_CONST                      3: b'<COAddr>\x05\x00\x00\x1a\xc6\n\x00\x00\x00\x00\x00\x00\x00\x00\x00\x00\x00\x00\x00\x00'
                2794    CALL                            1
                2802    POP_TOP                         
                2804    RERAISE                         0
                2806    COPY                            3
                2808    POP_EXCEPT                      
                2810    RERAISE                         1
                2812    PUSH_NULL                       
                2814    LOAD_CONST                      65: '__pyarmor_exit_13196__'
                2816    LOAD_CONST                      3: b'<COAddr>\x05\x00\x00\x1a\xc6\n\x00\x00\x00\x00\x00\x00\x00\x00\x00\x00\x00\x00\x00\x00'
                2818    BUILD_TUPLE                     1
                2820    CALL_FUNCTION_EX                0
                2822    POP_TOP                         
                2824    RETURN_VALUE                    
            [Exception Table]
                30 to 1128 -> 2508 [0] 
                1128 to 2350 -> 2484 [1] lasti
                2350 to 2366 -> 2508 [0] 
                2386 to 2448 -> 2484 [1] lasti
                2448 to 2464 -> 2508 [0] 
                2484 to 2494 -> 2502 [3] lasti
                2494 to 2508 -> 2508 [0] 
                2508 to 2526 -> 2778 [1] lasti
                2526 to 2530 -> 2784 [0] 
                2530 to 2546 -> 2778 [1] lasti
                2546 to 2624 -> 2768 [1] lasti
                2624 to 2632 -> 2784 [0] 
                2652 to 2738 -> 2768 [1] lasti
                2738 to 2740 -> 2778 [1] lasti
                2740 to 2748 -> 2784 [0] 
                2768 to 2778 -> 2778 [1] lasti
                2778 to 2784 -> 2784 [0] 
                2784 to 2806 -> 2806 [1] lasti
        '__pyarmor_exit_13181__'
        (
            None
        )
    [Disassembly]
        0       NOP                             
        2       NOP                             
        4       PUSH_NULL                       
        6       LOAD_CONST                      1: '__pyarmor_enter_13180__'
        8       LOAD_CONST                      2: b'<COAddr>\x05\x00\x00\x1a8\x01\x00\x00\x00\x00\x00\x00\x00\x00\x00\x00\x00\x00\x00\x00'
        10      BUILD_TUPLE                     1
        12      CALL_FUNCTION_EX                0
        14      POP_TOP                         
        16      RESUME                          0
        18      NOP                             
        20      NOP                             
        22      NOP                             
        24      NOP                             
        26      LOAD_CONST                      3: 0
        28      LOAD_CONST                      4: None
        30      IMPORT_NAME                     1: re
        32      STORE_NAME                      1: re
        34      LOAD_CONST                      3: 0
        36      LOAD_CONST                      4: None
        38      IMPORT_NAME                     2: eel
        40      STORE_NAME                      2: eel
        42      LOAD_CONST                      3: 0
        44      LOAD_CONST                      4: None
        46      IMPORT_NAME                     3: json
        48      STORE_NAME                      3: json
        50      LOAD_CONST                      3: 0
        52      LOAD_CONST                      4: None
        54      IMPORT_NAME                     4: time
        56      STORE_NAME                      4: time
        58      LOAD_CONST                      3: 0
        60      LOAD_CONST                      4: None
        62      IMPORT_NAME                     5: random
        64      STORE_NAME                      5: random
        66      LOAD_CONST                      3: 0
        68      LOAD_CONST                      4: None
        70      IMPORT_NAME                     6: sqlite3
        72      STORE_NAME                      6: sqlite3
        74      LOAD_CONST                      3: 0
        76      LOAD_CONST                      4: None
        78      IMPORT_NAME                     7: requests
        80      STORE_NAME                      7: requests
        82      LOAD_CONST                      3: 0
        84      LOAD_CONST                      4: None
        86      IMPORT_NAME                     8: datetime
        88      STORE_NAME                      8: datetime
        90      LOAD_CONST                      3: 0
        92      LOAD_CONST                      4: None
        94      IMPORT_NAME                     9: concurrent.futures
        96      STORE_NAME                      10: concurrent
        98      LOAD_CONST                      3: 0
        100     LOAD_CONST                      5: ('Thread', 'Event')
        102     IMPORT_NAME                     11: threading
        104     IMPORT_FROM                     12: Thread
        106     STORE_NAME                      12: Thread
        108     IMPORT_FROM                     13: Event
        110     STORE_NAME                      13: Event
        112     POP_TOP                         
        114     LOAD_CONST                      3: 0
        116     LOAD_CONST                      6: ('HTTPAdapter', 'Retry')
        118     IMPORT_NAME                     14: requests.adapters
        120     IMPORT_FROM                     15: HTTPAdapter
        122     STORE_NAME                      15: HTTPAdapter
        124     IMPORT_FROM                     16: Retry
        126     STORE_NAME                      16: Retry
        128     POP_TOP                         
        130     LOAD_CONST                      3: 0
        132     LOAD_CONST                      7: ('StopProgram',)
        134     IMPORT_NAME                     17: multithon.errors
        136     IMPORT_FROM                     18: StopProgram
        138     STORE_NAME                      18: StopProgram
        140     POP_TOP                         
        142     LOAD_CONST                      3: 0
        144     LOAD_CONST                      8: ('GetLang',)
        146     IMPORT_NAME                     19: program.static_classes
        148     IMPORT_FROM                     20: GetLang
        150     STORE_NAME                      20: GetLang
        152     POP_TOP                         
        154     LOAD_CONST                      3: 0
        156     LOAD_CONST                      9: ('Logs',)
        158     IMPORT_NAME                     19: program.static_classes
        160     IMPORT_FROM                     21: Logs
        162     STORE_NAME                      21: Logs
        164     POP_TOP                         
        166     LOAD_CONST                      3: 0
        168     LOAD_CONST                      10: ('logging',)
        170     IMPORT_NAME                     19: program.static_classes
        172     IMPORT_FROM                     22: logging
        174     STORE_NAME                      22: logging
        176     POP_TOP                         
        178     LOAD_CONST                      3: 0
        180     LOAD_CONST                      11: ('memory_check_switcher',)
        182     IMPORT_NAME                     19: program.static_classes
        184     IMPORT_FROM                     23: memory_check_switcher
        186     STORE_NAME                      23: memory_check_switcher
        188     POP_TOP                         
        190     LOAD_CONST                      3: 0
        192     LOAD_CONST                      12: ('memory_set_pid',)
        194     IMPORT_NAME                     19: program.static_classes
        196     IMPORT_FROM                     24: memory_set_pid
        198     STORE_NAME                      24: memory_set_pid
        200     POP_TOP                         
        202     LOAD_CONST                      3: 0
        204     LOAD_CONST                      13: ('Thread_wait',)
        206     IMPORT_NAME                     25: program.telegram
        208     IMPORT_FROM                     26: Thread_wait
        210     STORE_NAME                      26: Thread_wait
        212     POP_TOP                         
        214     LOAD_CONST                      3: 0
        216     LOAD_CONST                      14: ('tg_links',)
        218     IMPORT_NAME                     25: program.telegram
        220     IMPORT_FROM                     27: tg_links
        222     STORE_NAME                      27: tg_links
        224     POP_TOP                         
        226     LOAD_CONST                      3: 0
        228     LOAD_CONST                      15: ('GetConfig',)
        230     IMPORT_NAME                     28: program.general
        232     IMPORT_FROM                     29: GetConfig
        234     STORE_NAME                      29: GetConfig
        236     POP_TOP                         
        238     LOAD_CONST                      3: 0
        240     LOAD_CONST                      16: ('GetProxy',)
        242     IMPORT_NAME                     28: program.general
        244     IMPORT_FROM                     30: GetProxy
        246     STORE_NAME                      30: GetProxy
        248     POP_TOP                         
        250     LOAD_CONST                      3: 0
        252     LOAD_CONST                      17: ('StopDetect',)
        254     IMPORT_NAME                     28: program.general
        256     IMPORT_FROM                     31: StopDetect
        258     STORE_NAME                      31: StopDetect
        260     POP_TOP                         
        262     LOAD_CONST                      3: 0
        264     LOAD_CONST                      18: ('del_task_manager',)
        266     IMPORT_NAME                     28: program.general
        268     IMPORT_FROM                     32: del_task_manager
        270     STORE_NAME                      32: del_task_manager
        272     POP_TOP                         
        274     LOAD_CONST                      3: 0
        276     LOAD_CONST                      19: ('db_check_links_no_accounts',)
        278     IMPORT_NAME                     33: program.database
        280     IMPORT_FROM                     34: db_check_links_no_accounts
        282     STORE_NAME                      34: db_check_links_no_accounts
        284     POP_TOP                         
        286     LOAD_CONST                      20: <CODE> Check_links_no_accounts
        288     MAKE_FUNCTION                   0
        290     STORE_NAME                      35: Check_links_no_accounts
        292     LOAD_CONST                      21: <CODE> START
        294     MAKE_FUNCTION                   0
        296     STORE_NAME                      36: START
        298     LOAD_CONST                      26: (None,)
        300     LOAD_CONST                      22: <CODE> write_to_file
        302     MAKE_FUNCTION                   1
        304     STORE_NAME                      37: write_to_file
        306     LOAD_CONST                      23: <CODE> extract_number
        308     MAKE_FUNCTION                   0
        310     STORE_NAME                      38: extract_number
        312     LOAD_CONST                      24: <CODE> worker
        314     MAKE_FUNCTION                   0
        316     STORE_NAME                      39: worker
        318     LOAD_CONST                      4: None
        320     NOP                             
        322     NOP                             
        324     NOP                             
        326     JUMP_FORWARD                    19 (to 366)
        334     POP_TOP                         
        336     RETURN_CONST                    4: None
        338     PUSH_EXC_INFO                   
        340     PUSH_NULL                       
        342     LOAD_CONST                      25: '__pyarmor_exit_13181__'
        344     NOP                             
        346     LOAD_CONST                      2: b'<COAddr>\x05\x00\x00\x1a8\x01\x00\x00\x00\x00\x00\x00\x00\x00\x00\x00\x00\x00\x00\x00'
        348     CALL                            1
        356     POP_TOP                         
        358     RERAISE                         0
        360     COPY                            3
        362     POP_EXCEPT                      
        364     RERAISE                         1
        366     PUSH_NULL                       
        368     LOAD_CONST                      25: '__pyarmor_exit_13181__'
        370     LOAD_CONST                      2: b'<COAddr>\x05\x00\x00\x1a8\x01\x00\x00\x00\x00\x00\x00\x00\x00\x00\x00\x00\x00\x00\x00'
        372     BUILD_TUPLE                     1
        374     CALL_FUNCTION_EX                0
        376     POP_TOP                         
        378     RETURN_VALUE                    
    [Exception Table]
        26 to 318 -> 338 [0] 
        338 to 360 -> 360 [1] lasti
