#decoded by lolz.live/mrpenny / t.me/zeus_jackpot
# ================================
# Примечания по Pyarmor:
# - Байт-код и объекты кода Pyarmor соответствуют стандартному Python, но присутствуют специальные вызовы функций среды выполнения (runtime) Pyarmor.
# - Вызовы строк — это не ошибки, а маркеры, которые обрабатываются Pyarmor во время выполнения.
#
# Руководство по декомпиляции (без среды выполнения):
# 1. Игнорируйте зашифрованные байты после `#`; используйте только строку до `#`.
# 2. Удалите "__pyarmor_enter_xxx__"(b"<COAddr>...") и "__pyarmor_leave_xxx__"(b"<COAddr>...") (пролог/эпилог).
# 3. "__pyarmor_assert_xxx__"(A) не является настоящим оператором assert.
#    - Если A — это имя или читаемая строка: замените на A.
#    - Если A — это (X, "Y"): замените на X.Y.
#    - Если A — это (X, "Y", Z): замените на X.Y = Z.
#    - В противном случае: выберите наиболее подходящую/логичную замену.
# 4. "__pyarmor_bcc_xxx__"(...) указывает на машинный (нативный) код; тело функции недоступно. Добавьте комментарий.
# ================================

[Code]
    File Name: <frozen program.modules.Check_links>
    Object Name: <module>
    Qualified Name: <module>
    Arg Count: 0
    Pos Only Arg Count: 0
    KW Only Arg Count: 0
    Stack Size: 5
    Flags: 0x20000000 (CO_PYARMOR_OBFUSCATED)
    [Names]
        '__assert_armored__'
        'datetime'
        'json'
        'eel'
        'concurrent.futures'
        'concurrent'
        'threading'
        'Thread'
        'Event'
        'multithon.sync'
        'functions'
        'types'
        'multithon.errors'
        'StopProgram'
        'program.static_classes'
        'GetLang'
        'Logs'
        'logging'
        'memory_check_switcher'
        'memory_set_pid'
        'program.telegram'
        'DelayOnline'
        'Disconnect'
        'Thread_wait'
        'account_works'
        'entity'
        'tg_entity'
        'tg_group'
        'tg_links'
        'program.general'
        'GetConfig'
        'GetProxy'
        'StopDetect'
        'check_get_settings'
        'del_task_manager'
        'getFile'
        'set_task_manager'
        'program.database'
        'db_base'
        'db_parsing'
        'Check_links'
        'START'
        'get_bio'
        'worker'
    [Locals+Names]
    [Constants]
        '__pyarmor_assert_13164__'
        '__pyarmor_enter_13165__'
        b'<COAddr>\x07\x00\x00\x1a|\x01\x00\x00\x00\x00\x00\x00\x00\x00\x00\x00\x00\x00\x00\x00'
        0
        None
        (
            'Thread'
            'Event'
        )
        (
            'functions'
            'types'
        )
        (
            'StopProgram'
        )
        (
            'GetLang'
        )
        (
            'Logs'
        )
        (
            'logging'
        )
        (
            'memory_check_switcher'
        )
        (
            'memory_set_pid'
        )
        (
            'DelayOnline'
        )
        (
            'Disconnect'
        )
        (
            'Thread_wait'
        )
        (
            'account_works'
        )
        (
            'entity'
        )
        (
            'tg_entity'
        )
        (
            'tg_group'
        )
        (
            'tg_links'
        )
        (
            'GetConfig'
        )
        (
            'GetProxy'
        )
        (
            'StopDetect'
        )
        (
            'check_get_settings'
        )
        (
            'del_task_manager'
        )
        (
            'getFile'
        )
        (
            'set_task_manager'
        )
        (
            'db_base'
            'db_parsing'
        )
        [Code]
            File Name: <frozen program.modules.Check_links>
            Object Name: Check_links
            Qualified Name: Check_links
            Arg Count: 1
            Pos Only Arg Count: 0
            KW Only Arg Count: 0
            Stack Size: 8
            Flags: 0x20000003 (CO_OPTIMIZED | CO_NEWLOCALS | CO_PYARMOR_OBFUSCATED)
            [Names]
                'get'
                'getFile'
                'GetConfig'
                'config'
                'GetLang'
                'Lang'
                'GetProxy'
                'eel'
                'sendSuccessBox'
                'memory_check_switcher'
                'Event'
                'memory_set_pid'
                'Thread'
                'START'
                'start'
                'Logs'
                'WaitStopAnsfer'
                'UpdateLogInWindow'
                'BaseException'
                'logging'
            [Locals+Names]
                'data'
                '__assert_armored__'
                '_var_var_0'
                '_var_var_1'
                '_var_var_2'
                '_var_var_3'
            [Constants]
                None
                '__pyarmor_assert_13167__'
                '__pyarmor_enter_13168__'
                b'<COAddr>\x07\x00\x00\x1a\xae\x02\x00\x00\x00\x00\x00\x00\x00\x00\x00\x00\x00\x00\x00\x00'
                'action'
                'getFile'
                '__pyarmor_exit_13169__'
                'program_running'   # b'\x81\xf2\n\x1c4\xe8\xbf\xdf$\xe8\x18\xceb\xe5\xf6\x82'
                False
                (
                    'target'
                    'args'
                )
                True
                (
                    'target'
                    'args'
                    'daemon'
                )
            [Disassembly]
                0       NOP                             
                2       NOP                             
                4       PUSH_NULL                       
                6       LOAD_CONST                      2: '__pyarmor_enter_13168__'
                8       LOAD_CONST                      3: b'<COAddr>\x07\x00\x00\x1a\xae\x02\x00\x00\x00\x00\x00\x00\x00\x00\x00\x00\x00\x00\x00\x00'
                10      BUILD_TUPLE                     1
                12      CALL_FUNCTION_EX                0
                14      POP_TOP                         
                16      RESUME                          0
                18      NOP                             
                20      NOP                             
                22      NOP                             
                24      NOP                             
                26      NOP                             
                28      NOP                             
                30      LOAD_FAST                       0: data
                32      LOAD_ATTR                       1: get
                52      LOAD_CONST                      4: 'action'
                54      CALL                            1
                62      POP_JUMP_IF_NONE                28 (to 120)
                64      LOAD_FAST                       0: data
                66      LOAD_CONST                      4: 'action'
                68      BINARY_SUBSCR                   
                72      LOAD_CONST                      5: 'getFile'
                74      COMPARE_OP                      40 (==)
                78      POP_JUMP_IF_FALSE               20 (to 120)
                80      LOAD_GLOBAL                     3: NULL + getFile
                90      LOAD_FAST                       0: data
                92      CALL                            1
                100     NOP                             
                102     NOP                             
                104     JUMP_FORWARD                    316 (to 740)
                108     CALL                            1
                116     POP_TOP                         
                118     RETURN_VALUE                    
                120     LOAD_GLOBAL                     5: NULL + GetConfig
                130     CALL                            0
                138     STORE_GLOBAL                    3: config
                140     LOAD_GLOBAL                     9: NULL + GetLang
                150     LOAD_GLOBAL                     6: config
                160     CALL                            1
                168     STORE_GLOBAL                    5: Lang
                170     LOAD_GLOBAL                     13: NULL + GetProxy
                180     CALL                            0
                188     STORE_FAST                      2: _var_var_0
                190     LOAD_GLOBAL                     15: NULL + eel
                200     LOAD_ATTR                       16: sendSuccessBox
                220     LOAD_GLOBAL                     10: Lang
                230     PUSH_NULL                       
                232     LOAD_CONST                      1: '__pyarmor_assert_13167__'
                234     LOAD_CONST                      7: 'program_running'   # b'\x81\xf2\n\x1c4\xe8\xbf\xdf$\xe8\x18\xceb\xe5\xf6\x82'
                236     CALL                            1
                244     BINARY_SUBSCR                   
                248     CALL                            1
                256     POP_TOP                         
                258     LOAD_GLOBAL                     19: NULL + memory_check_switcher
                268     CALL                            0
                276     POP_JUMP_IF_TRUE                11 (to 300)
                278     NOP                             
                280     LOAD_CONST                      8: False
                282     NOP                             
                284     NOP                             
                286     NOP                             
                288     JUMP_FORWARD                    225 (to 740)
                296     POP_TOP                         
                298     RETURN_CONST                    8: False
                300     LOAD_GLOBAL                     21: NULL + Event
                310     CALL                            0
                318     STORE_FAST                      3: _var_var_1
                320     LOAD_GLOBAL                     23: NULL + memory_set_pid
                330     CALL                            0
                338     STORE_FAST                      4: _var_var_2
                340     LOAD_GLOBAL                     25: NULL + Thread
                350     LOAD_GLOBAL                     26: START
                360     LOAD_FAST                       0: data
                362     LOAD_GLOBAL                     6: config
                372     LOAD_FAST                       4: _var_var_2
                374     LOAD_FAST                       2: _var_var_0
                376     LOAD_FAST                       3: _var_var_1
                378     BUILD_TUPLE                     5
                380     KW_NAMES                        9: ('target', 'args')
                382     CALL                            2
                390     LOAD_ATTR                       29: start
                410     CALL                            0
                418     POP_TOP                         
                420     LOAD_GLOBAL                     25: NULL + Thread
                430     LOAD_GLOBAL                     30: Logs
                440     LOAD_ATTR                       32: WaitStopAnsfer
                460     LOAD_GLOBAL                     6: config
                470     LOAD_FAST                       4: _var_var_2
                472     LOAD_FAST                       3: _var_var_1
                474     BUILD_TUPLE                     3
                476     LOAD_CONST                      10: True
                478     KW_NAMES                        11: ('target', 'args', 'daemon')
                480     CALL                            3
                488     LOAD_ATTR                       29: start
                508     CALL                            0
                516     POP_TOP                         
                518     LOAD_GLOBAL                     25: NULL + Thread
                528     LOAD_GLOBAL                     30: Logs
                538     LOAD_ATTR                       34: UpdateLogInWindow
                558     LOAD_GLOBAL                     6: config
                568     LOAD_FAST                       4: _var_var_2
                570     LOAD_FAST                       3: _var_var_1
                572     BUILD_TUPLE                     3
                574     LOAD_CONST                      10: True
                576     KW_NAMES                        11: ('target', 'args', 'daemon')
                578     CALL                            3
                586     LOAD_ATTR                       29: start
                606     CALL                            0
                614     POP_TOP                         
                616     LOAD_CONST                      0: None
                618     NOP                             
                620     NOP                             
                622     NOP                             
                624     JUMP_FORWARD                    57 (to 740)
                632     POP_TOP                         
                634     RETURN_CONST                    0: None
                636     PUSH_EXC_INFO                   
                638     LOAD_GLOBAL                     36: BaseException
                648     CHECK_EXC_MATCH                 
                650     POP_JUMP_IF_FALSE               26 (to 704)
                652     STORE_FAST                      5: _var_var_3
                654     PUSH_NULL                       
                656     LOAD_GLOBAL                     39: NULL + logging
                666     LOAD_FAST                       5: _var_var_3
                668     CALL                            1
                676     CALL                            0
                684     POP_TOP                         
                686     POP_EXCEPT                      
                688     LOAD_CONST                      0: None
                690     STORE_FAST                      5: _var_var_3
                692     DELETE_FAST                     5: _var_var_3
                694     JUMP_BACKWARD                   40 (to 616)
                696     LOAD_CONST                      0: None
                698     STORE_FAST                      5: _var_var_3
                700     DELETE_FAST                     5: _var_var_3
                702     RERAISE                         1
                704     RERAISE                         0
                706     COPY                            3
                708     POP_EXCEPT                      
                710     RERAISE                         1
                712     PUSH_EXC_INFO                   
                714     PUSH_NULL                       
                716     LOAD_CONST                      6: '__pyarmor_exit_13169__'
                718     NOP                             
                720     LOAD_CONST                      3: b'<COAddr>\x07\x00\x00\x1a\xae\x02\x00\x00\x00\x00\x00\x00\x00\x00\x00\x00\x00\x00\x00\x00'
                722     CALL                            1
                730     POP_TOP                         
                732     RERAISE                         0
                734     COPY                            3
                736     POP_EXCEPT                      
                738     RERAISE                         1
                740     PUSH_NULL                       
                742     LOAD_CONST                      6: '__pyarmor_exit_13169__'
                744     LOAD_CONST                      3: b'<COAddr>\x07\x00\x00\x1a\xae\x02\x00\x00\x00\x00\x00\x00\x00\x00\x00\x00\x00\x00\x00\x00'
                746     BUILD_TUPLE                     1
                748     CALL_FUNCTION_EX                0
                750     POP_TOP                         
                752     RETURN_VALUE                    
            [Exception Table]
                30 to 100 -> 636 [0] 
                120 to 278 -> 636 [0] 
                300 to 616 -> 636 [0] 
                636 to 654 -> 706 [1] lasti
                654 to 686 -> 696 [1] lasti
                686 to 696 -> 712 [0] 
                696 to 706 -> 706 [1] lasti
                706 to 712 -> 712 [0] 
                712 to 734 -> 734 [1] lasti
        [Code]
            File Name: <frozen program.modules.Check_links>
            Object Name: START
            Qualified Name: START
            Arg Count: 5
            Pos Only Arg Count: 0
            KW Only Arg Count: 0
            Stack Size: 14
            Flags: 0x20000003 (CO_OPTIMIZED | CO_NEWLOCALS | CO_PYARMOR_OBFUSCATED)
            [Names]
                'is_set'
                'StopProgram'
                'check_get_settings'
                'get'
                'isinstance'
                'list'
                'int'
                'len'
                'eel'
                'sendErrorBox'
                'Lang'
                'datetime'
                'now'
                'strftime'
                'db_base'
                'import_list'
                'WriteResult'
                'db_parsing'
                'create'
                'set_task_manager'
                'concurrent'
                'futures'
                'ThreadPoolExecutor'
                'StreamStat'
                'json'
                'dumps'
                'append'
                'submit'
                'worker'
                'as_completed'
                'BaseException'
                'logging'
                'del_task_manager'
                'StopDetect'
            [Locals+Names]
                'data'
                'config'
                'pid'
                'proxy'
                'stop_thread'
                '__assert_armored__'
                '_var_var_4'
                '_var_var_5'
                '_var_var_6'
                '_var_var_7'
                '_var_var_8'
                '_var_var_9'
                '_var_var_10'
                '_var_var_11'
                '_var_var_12'
                '_var_var_13'
                '_var_var_14'
                '_var_var_15'
                '_var_var_3'
            [Constants]
                None
                '__pyarmor_assert_13170__'
                '__pyarmor_enter_13171__'
                b'<COAddr>\x07\x00\x00\x1a\\\x07\x00\x00\x00\x00\x00\x00\x00\x00\x00\x00\x00\x00\x00\x00'
                'Settings'
                'Accounts'
                1
                'select_accounts_works'   # b'\x81\xf1\x1d\x1f6\xf9\xaa\xed\x1a\xf9\x0e\xcfy\xe2\xec\x960J\xb4\xb5\xa1\xd8'
                'thread_rules'   # b'\x81\xf6\x10\x016\xfb\xba\xed\t\xef\x01\xc5\x7f'
                True
                'thread_count'   # b'\x81\xf6\x10\x016\xfb\xba\xed\x18\xf5\x18\xcex'
                '%Y-%m-%d_%H-%M-%S'   # b'\x81\xa7!^v\xf7\xf3\x97\x1f\xc5H\xe8!\xa9\xd5\xc8Jn'
                'use_data_base'   # b'\x81\xf7\x0b\x16\x0c\xfe\xbf\xc6\x1a\xc5\x0f\xc1\x7f\xe9'
                False
                'additives/check_links/'   # b'\x81\xe3\x1c\x17:\xee\xb7\xc4\x1e\xe9B\xc3d\xe9\xfb\x8e0Q\xb2\xa9\xa1\xd8\x01'
                '_base.db'
                'usernames'   # b'\x81\xf7\x0b\x16!\xf4\xbf\xdf\x1e\xe9'
                (
                    'users'
                )
                'file_db'
                'can_not_create_database'   # b'\x81\xe1\x19\x1d\x0c\xf4\xb1\xc6$\xf9\x1f\xc5m\xf8\xfd\xba\x0b\\\xaf\xa6\xa8\xca]\xc9'
                'Groups'
                'check_links'   # b'\x81\xe1\x10\x160\xf1\x81\xde\x12\xf4\x06\xd3'
                '_Parsing.db'   # b'\x81\xdd(\x12!\xe9\xb7\xdc\x1c\xb4\t\xc2'
                'Общая база данных'   # b'\x81R\xe6\xa3\xe2KWb\xcbK\xe2\x80\xdc=HU\xbf\x8a\x0bw\xea{\x9a|\xd5\xdf~\xec\xdd\x00\xf5T\xdf'
                'stuff'
                (
                    'accounts'
                    'name'
                )
                (
                    'max_workers'
                )
                0
                'st_task'
                'st_stream'   # b'\x81\xf1\x0c, \xee\xac\xd7\x1a\xf7'
                'st_wait'
                'st_done'
                '__pyarmor_exit_13172__'
                'Done'
            [Disassembly]
                0       NOP                             
                2       NOP                             
                4       PUSH_NULL                       
                6       LOAD_CONST                      2: '__pyarmor_enter_13171__'
                8       LOAD_CONST                      3: b'<COAddr>\x07\x00\x00\x1a\\\x07\x00\x00\x00\x00\x00\x00\x00\x00\x00\x00\x00\x00\x00\x00'
                10      BUILD_TUPLE                     1
                12      CALL_FUNCTION_EX                0
                14      POP_TOP                         
                16      RESUME                          0
                18      NOP                             
                20      NOP                             
                22      NOP                             
                24      NOP                             
                26      NOP                             
                28      NOP                             
                30      LOAD_FAST                       4: stop_thread
                32      LOAD_ATTR                       1: is_set
                52      CALL                            0
                60      POP_JUMP_IF_FALSE               10 (to 82)
                62      LOAD_GLOBAL                     3: NULL + StopProgram
                72      CALL                            0
                80      RAISE_VARARGS                   1
                82      LOAD_GLOBAL                     5: NULL + check_get_settings
                92      LOAD_FAST                       0: data
                94      LOAD_ATTR                       7: get
                114     LOAD_CONST                      4: 'Settings'
                116     CALL                            1
                124     CALL                            1
                132     POP_TOP                         
                134     LOAD_FAST                       0: data
                136     LOAD_CONST                      5: 'Accounts'
                138     BINARY_SUBSCR                   
                142     STORE_FAST                      6: _var_var_4
                144     LOAD_GLOBAL                     9: NULL + isinstance
                154     LOAD_FAST                       6: _var_var_4
                156     LOAD_GLOBAL                     10: list
                166     CALL                            2
                174     POP_JUMP_IF_TRUE                3 (to 182)
                176     LOAD_FAST                       6: _var_var_4
                178     BUILD_LIST                      1
                180     STORE_FAST                      6: _var_var_4
                182     LOAD_GLOBAL                     13: NULL + int
                192     LOAD_GLOBAL                     15: NULL + len
                202     LOAD_FAST                       6: _var_var_4
                204     CALL                            1
                212     CALL                            1
                220     LOAD_CONST                      6: 1
                222     COMPARE_OP                      2 (<)
                226     POP_JUMP_IF_FALSE               44 (to 316)
                228     LOAD_GLOBAL                     17: NULL + eel
                238     LOAD_ATTR                       18: sendErrorBox
                258     LOAD_GLOBAL                     20: Lang
                268     PUSH_NULL                       
                270     LOAD_CONST                      1: '__pyarmor_assert_13170__'
                272     LOAD_CONST                      7: 'select_accounts_works'   # b'\x81\xf1\x1d\x1f6\xf9\xaa\xed\x1a\xf9\x0e\xcfy\xe2\xec\x960J\xb4\xb5\xa1\xd8'
                274     CALL                            1
                282     BINARY_SUBSCR                   
                286     CALL                            1
                294     POP_TOP                         
                296     LOAD_GLOBAL                     3: NULL + StopProgram
                306     CALL                            0
                314     RAISE_VARARGS                   1
                316     LOAD_FAST                       0: data
                318     LOAD_CONST                      4: 'Settings'
                320     BINARY_SUBSCR                   
                324     LOAD_ATTR                       7: get
                344     PUSH_NULL                       
                346     LOAD_CONST                      1: '__pyarmor_assert_13170__'
                348     LOAD_CONST                      8: 'thread_rules'   # b'\x81\xf6\x10\x016\xfb\xba\xed\t\xef\x01\xc5\x7f'
                350     CALL                            1
                358     CALL                            1
                366     LOAD_CONST                      9: True
                368     COMPARE_OP                      40 (==)
                372     POP_JUMP_IF_FALSE               36 (to 446)
                374     LOAD_GLOBAL                     13: NULL + int
                384     LOAD_FAST                       0: data
                386     LOAD_CONST                      4: 'Settings'
                388     BINARY_SUBSCR                   
                392     LOAD_ATTR                       7: get
                412     PUSH_NULL                       
                414     LOAD_CONST                      1: '__pyarmor_assert_13170__'
                416     LOAD_CONST                      10: 'thread_count'   # b'\x81\xf6\x10\x016\xfb\xba\xed\x18\xf5\x18\xcex'
                418     CALL                            1
                426     CALL                            1
                434     CALL                            1
                442     STORE_FAST                      7: _var_var_5
                444     JUMP_FORWARD                    11 (to 468)
                446     LOAD_FAST                       1: config
                448     PUSH_NULL                       
                450     LOAD_CONST                      1: '__pyarmor_assert_13170__'
                452     LOAD_CONST                      10: 'thread_count'   # b'\x81\xf6\x10\x016\xfb\xba\xed\x18\xf5\x18\xcex'
                454     CALL                            1
                462     BINARY_SUBSCR                   
                466     STORE_FAST                      7: _var_var_5
                468     LOAD_GLOBAL                     22: datetime
                478     LOAD_ATTR                       22: datetime
                498     LOAD_ATTR                       25: now
                518     CALL                            0
                526     LOAD_ATTR                       27: strftime
                546     PUSH_NULL                       
                548     LOAD_CONST                      1: '__pyarmor_assert_13170__'
                550     LOAD_CONST                      11: '%Y-%m-%d_%H-%M-%S'   # b'\x81\xa7!^v\xf7\xf3\x97\x1f\xc5H\xe8!\xa9\xd5\xc8Jn'
                552     CALL                            1
                560     CALL                            1
                568     STORE_FAST                      8: _var_var_6
                570     LOAD_FAST                       0: data
                572     LOAD_CONST                      4: 'Settings'
                574     BINARY_SUBSCR                   
                578     PUSH_NULL                       
                580     LOAD_CONST                      1: '__pyarmor_assert_13170__'
                582     LOAD_CONST                      12: 'use_data_base'   # b'\x81\xf7\x0b\x16\x0c\xfe\xbf\xc6\x1a\xc5\x0f\xc1\x7f\xe9'
                584     CALL                            1
                592     BINARY_SUBSCR                   
                596     LOAD_CONST                      13: False
                598     COMPARE_OP                      40 (==)
                602     POP_JUMP_IF_FALSE               155 (to 914)
                604     LOAD_GLOBAL                     29: NULL + db_base
                614     PUSH_NULL                       
                616     LOAD_CONST                      1: '__pyarmor_assert_13170__'
                618     LOAD_CONST                      14: 'additives/check_links/'   # b'\x81\xe3\x1c\x17:\xee\xb7\xc4\x1e\xe9B\xc3d\xe9\xfb\x8e0Q\xb2\xa9\xa1\xd8\x01'
                620     CALL                            1
                628     LOAD_FAST                       8: _var_var_6
                630     FORMAT_VALUE                    0 (FVC_NONE)
                632     LOAD_CONST                      15: '_base.db'
                634     BUILD_STRING                    3
                636     CALL                            1
                644     LOAD_ATTR                       31: import_list
                664     LOAD_FAST                       0: data
                666     LOAD_CONST                      4: 'Settings'
                668     BINARY_SUBSCR                   
                672     LOAD_ATTR                       7: get
                692     PUSH_NULL                       
                694     LOAD_CONST                      1: '__pyarmor_assert_13170__'
                696     LOAD_CONST                      16: 'usernames'   # b'\x81\xf7\x0b\x16!\xf4\xbf\xdf\x1e\xe9'
                698     CALL                            1
                706     BUILD_LIST                      0
                708     CALL                            2
                716     KW_NAMES                        17: ('users',)
                718     CALL                            1
                726     LOAD_FAST                       0: data
                728     LOAD_CONST                      4: 'Settings'
                730     BINARY_SUBSCR                   
                734     LOAD_CONST                      18: 'file_db'
                736     STORE_SUBSCR                    
                740     LOAD_FAST                       0: data
                742     LOAD_CONST                      4: 'Settings'
                744     BINARY_SUBSCR                   
                748     LOAD_CONST                      18: 'file_db'
                750     BINARY_SUBSCR                   
                754     LOAD_CONST                      13: False
                756     COMPARE_OP                      40 (==)
                760     POP_JUMP_IF_FALSE               44 (to 850)
                762     LOAD_GLOBAL                     17: NULL + eel
                772     LOAD_ATTR                       18: sendErrorBox
                792     LOAD_GLOBAL                     20: Lang
                802     PUSH_NULL                       
                804     LOAD_CONST                      1: '__pyarmor_assert_13170__'
                806     LOAD_CONST                      19: 'can_not_create_database'   # b'\x81\xe1\x19\x1d\x0c\xf4\xb1\xc6$\xf9\x1f\xc5m\xf8\xfd\xba\x0b\\\xaf\xa6\xa8\xca]\xc9'
                808     CALL                            1
                816     BINARY_SUBSCR                   
                820     CALL                            1
                828     POP_TOP                         
                830     LOAD_GLOBAL                     3: NULL + StopProgram
                840     CALL                            0
                848     RAISE_VARARGS                   1
                850     LOAD_GLOBAL                     17: NULL + eel
                860     LOAD_ATTR                       32: WriteResult
                880     LOAD_CONST                      20: 'Groups'
                882     PUSH_NULL                       
                884     LOAD_CONST                      1: '__pyarmor_assert_13170__'
                886     LOAD_CONST                      21: 'check_links'   # b'\x81\xe1\x10\x160\xf1\x81\xde\x12\xf4\x06\xd3'
                888     CALL                            1
                896     LOAD_FAST                       8: _var_var_6
                898     LOAD_CONST                      15: '_base.db'
                900     BINARY_OP                       0 (+)
                904     CALL                            3
                912     POP_TOP                         
                914     LOAD_GLOBAL                     35: NULL + db_parsing
                924     PUSH_NULL                       
                926     LOAD_CONST                      1: '__pyarmor_assert_13170__'
                928     LOAD_CONST                      14: 'additives/check_links/'   # b'\x81\xe3\x1c\x17:\xee\xb7\xc4\x1e\xe9B\xc3d\xe9\xfb\x8e0Q\xb2\xa9\xa1\xd8\x01'
                930     CALL                            1
                938     LOAD_FAST                       8: _var_var_6
                940     FORMAT_VALUE                    0 (FVC_NONE)
                942     PUSH_NULL                       
                944     LOAD_CONST                      1: '__pyarmor_assert_13170__'
                946     LOAD_CONST                      22: '_Parsing.db'   # b'\x81\xdd(\x12!\xe9\xb7\xdc\x1c\xb4\t\xc2'
                948     CALL                            1
                956     BUILD_STRING                    3
                958     CALL                            1
                966     LOAD_ATTR                       37: create
                986     CALL                            0
                994     STORE_FAST                      9: _var_var_7
                996     LOAD_GLOBAL                     17: NULL + eel
                1006    LOAD_ATTR                       32: WriteResult
                1026    PUSH_NULL                       
                1028    LOAD_CONST                      1: '__pyarmor_assert_13170__'
                1030    LOAD_CONST                      23: 'Общая база данных'   # b'\x81R\xe6\xa3\xe2KWb\xcbK\xe2\x80\xdc=HU\xbf\x8a\x0bw\xea{\x9a|\xd5\xdf~\xec\xdd\x00\xf5T\xdf'
                1032    CALL                            1
                1040    PUSH_NULL                       
                1042    LOAD_CONST                      1: '__pyarmor_assert_13170__'
                1044    LOAD_CONST                      21: 'check_links'   # b'\x81\xe1\x10\x160\xf1\x81\xde\x12\xf4\x06\xd3'
                1046    CALL                            1
                1054    LOAD_FAST                       8: _var_var_6
                1056    FORMAT_VALUE                    0 (FVC_NONE)
                1058    PUSH_NULL                       
                1060    LOAD_CONST                      1: '__pyarmor_assert_13170__'
                1062    LOAD_CONST                      22: '_Parsing.db'   # b'\x81\xdd(\x12!\xe9\xb7\xdc\x1c\xb4\t\xc2'
                1064    CALL                            1
                1072    BUILD_STRING                    2
                1074    CALL                            3
                1082    POP_TOP                         
                1084    LOAD_GLOBAL                     39: NULL + set_task_manager
                1094    LOAD_FAST                       2: pid
                1096    LOAD_FAST                       6: _var_var_4
                1098    LOAD_FAST                       0: data
                1100    LOAD_CONST                      24: 'stuff'
                1102    BINARY_SUBSCR                   
                1106    KW_NAMES                        25: ('accounts', 'name')
                1108    CALL                            3
                1116    POP_TOP                         
                1118    LOAD_GLOBAL                     40: concurrent
                1128    LOAD_ATTR                       42: futures
                1148    LOAD_ATTR                       45: ThreadPoolExecutor
                1168    LOAD_FAST                       7: _var_var_5
                1170    KW_NAMES                        26: ('max_workers',)
                1172    CALL                            1
                1180    BEFORE_WITH                     
                1182    STORE_FAST                      10: _var_var_8
                1184    BUILD_LIST                      0
                1186    STORE_FAST                      11: _var_var_9
                1188    LOAD_GLOBAL                     15: NULL + len
                1198    LOAD_FAST                       6: _var_var_4
                1200    CALL                            1
                1208    STORE_FAST                      12: _var_var_10
                1210    LOAD_FAST                       7: _var_var_5
                1212    STORE_FAST                      13: _var_var_11
                1214    LOAD_FAST                       12: _var_var_10
                1216    STORE_FAST                      14: _var_var_12
                1218    LOAD_CONST                      27: 0
                1220    STORE_FAST                      15: _var_var_13
                1222    LOAD_GLOBAL                     17: NULL + eel
                1232    LOAD_ATTR                       46: StreamStat
                1252    LOAD_GLOBAL                     49: NULL + json
                1262    LOAD_ATTR                       50: dumps
                1282    LOAD_CONST                      28: 'st_task'
                1284    LOAD_FAST                       12: _var_var_10
                1286    PUSH_NULL                       
                1288    LOAD_CONST                      1: '__pyarmor_assert_13170__'
                1290    LOAD_CONST                      29: 'st_stream'   # b'\x81\xf1\x0c, \xee\xac\xd7\x1a\xf7'
                1292    CALL                            1
                1300    LOAD_FAST                       13: _var_var_11
                1302    LOAD_CONST                      30: 'st_wait'
                1304    LOAD_FAST                       14: _var_var_12
                1306    LOAD_CONST                      31: 'st_done'
                1308    LOAD_FAST                       15: _var_var_13
                1310    BUILD_MAP                       4
                1312    CALL                            1
                1320    CALL                            1
                1328    POP_TOP                         
                1330    LOAD_FAST                       6: _var_var_4
                1332    GET_ITER                        
                1334    FOR_ITER                        45 (to 1426)
                1338    STORE_FAST                      16: _var_var_14
                1340    LOAD_FAST                       11: _var_var_9
                1342    LOAD_ATTR                       53: append
                1362    LOAD_FAST                       10: _var_var_8
                1364    LOAD_ATTR                       55: submit
                1384    LOAD_GLOBAL                     56: worker
                1394    LOAD_FAST                       16: _var_var_14
                1396    LOAD_FAST                       1: config
                1398    LOAD_FAST                       3: proxy
                1400    LOAD_FAST                       0: data
                1402    LOAD_FAST                       9: _var_var_7
                1404    LOAD_FAST                       4: stop_thread
                1406    LOAD_CONST                      27: 0
                1408    CALL                            8
                1416    CALL                            1
                1424    POP_TOP                         
                1426    JUMP_BACKWARD                   47 (to 1334)
                1428    END_FOR                         
                1430    LOAD_GLOBAL                     40: concurrent
                1440    LOAD_ATTR                       42: futures
                1460    LOAD_ATTR                       59: as_completed
                1480    LOAD_FAST                       11: _var_var_9
                1482    CALL                            1
                1490    GET_ITER                        
                1492    FOR_ITER                        66 (to 1626)
                1496    STORE_FAST                      17: _var_var_15
                1498    LOAD_FAST                       15: _var_var_13
                1500    LOAD_CONST                      6: 1
                1502    BINARY_OP                       13 (+=)
                1506    STORE_FAST                      15: _var_var_13
                1508    LOAD_FAST                       14: _var_var_12
                1510    LOAD_CONST                      6: 1
                1512    BINARY_OP                       23 (-=)
                1516    STORE_FAST                      14: _var_var_12
                1518    LOAD_GLOBAL                     17: NULL + eel
                1528    LOAD_ATTR                       46: StreamStat
                1548    LOAD_GLOBAL                     49: NULL + json
                1558    LOAD_ATTR                       50: dumps
                1578    LOAD_CONST                      28: 'st_task'
                1580    LOAD_FAST                       12: _var_var_10
                1582    PUSH_NULL                       
                1584    LOAD_CONST                      1: '__pyarmor_assert_13170__'
                1586    LOAD_CONST                      29: 'st_stream'   # b'\x81\xf1\x0c, \xee\xac\xd7\x1a\xf7'
                1588    CALL                            1
                1596    LOAD_FAST                       13: _var_var_11
                1598    LOAD_CONST                      30: 'st_wait'
                1600    LOAD_FAST                       14: _var_var_12
                1602    LOAD_CONST                      31: 'st_done'
                1604    LOAD_FAST                       15: _var_var_13
                1606    BUILD_MAP                       4
                1608    CALL                            1
                1616    CALL                            1
                1624    POP_TOP                         
                1626    JUMP_BACKWARD                   68 (to 1492)
                1628    END_FOR                         
                1630    NOP                             
                1632    LOAD_CONST                      0: None
                1634    LOAD_CONST                      0: None
                1636    LOAD_CONST                      0: None
                1638    CALL                            2
                1646    POP_TOP                         
                1648    LOAD_GLOBAL                     65: NULL + del_task_manager
                1658    LOAD_FAST                       2: pid
                1660    CALL                            1
                1668    POP_TOP                         
                1670    LOAD_GLOBAL                     67: NULL + StopDetect
                1680    LOAD_FAST                       4: stop_thread
                1682    CALL                            1
                1690    POP_TOP                         
                1692    NOP                             
                1694    LOAD_CONST                      33: 'Done'
                1696    NOP                             
                1698    NOP                             
                1700    NOP                             
                1702    JUMP_FORWARD                    117 (to 1938)
                1710    POP_TOP                         
                1712    RETURN_CONST                    33: 'Done'
                1714    PUSH_EXC_INFO                   
                1716    WITH_EXCEPT_START               
                1718    POP_JUMP_IF_TRUE                1 (to 1722)
                1720    RERAISE                         2
                1722    POP_TOP                         
                1724    POP_EXCEPT                      
                1726    POP_TOP                         
                1728    POP_TOP                         
                1730    JUMP_BACKWARD                   42 (to 1648)
                1732    COPY                            3
                1734    POP_EXCEPT                      
                1736    RERAISE                         1
                1738    PUSH_EXC_INFO                   
                1740    LOAD_GLOBAL                     2: StopProgram
                1750    CHECK_EXC_MATCH                 
                1752    POP_JUMP_IF_FALSE               3 (to 1760)
                1754    POP_TOP                         
                1756    POP_EXCEPT                      
                1758    JUMP_BACKWARD                   56 (to 1648)
                1760    LOAD_GLOBAL                     60: BaseException
                1770    CHECK_EXC_MATCH                 
                1772    POP_JUMP_IF_FALSE               26 (to 1826)
                1774    STORE_FAST                      18: _var_var_3
                1776    PUSH_NULL                       
                1778    LOAD_GLOBAL                     63: NULL + logging
                1788    LOAD_FAST                       18: _var_var_3
                1790    CALL                            1
                1798    CALL                            0
                1806    POP_TOP                         
                1808    POP_EXCEPT                      
                1810    LOAD_CONST                      0: None
                1812    STORE_FAST                      18: _var_var_3
                1814    DELETE_FAST                     18: _var_var_3
                1816    JUMP_BACKWARD                   85 (to 1648)
                1818    LOAD_CONST                      0: None
                1820    STORE_FAST                      18: _var_var_3
                1822    DELETE_FAST                     18: _var_var_3
                1824    RERAISE                         1
                1826    RERAISE                         0
                1828    COPY                            3
                1830    POP_EXCEPT                      
                1832    RERAISE                         1
                1834    PUSH_EXC_INFO                   
                1836    LOAD_GLOBAL                     65: NULL + del_task_manager
                1846    LOAD_FAST                       2: pid
                1848    CALL                            1
                1856    POP_TOP                         
                1858    LOAD_GLOBAL                     67: NULL + StopDetect
                1868    LOAD_FAST                       4: stop_thread
                1870    CALL                            1
                1878    POP_TOP                         
                1880    POP_TOP                         
                1882    POP_EXCEPT                      
                1884    LOAD_CONST                      33: 'Done'
                1886    NOP                             
                1888    NOP                             
                1890    NOP                             
                1892    JUMP_FORWARD                    22 (to 1938)
                1900    POP_TOP                         
                1902    RETURN_CONST                    33: 'Done'
                1904    COPY                            3
                1906    POP_EXCEPT                      
                1908    RERAISE                         1
                1910    PUSH_EXC_INFO                   
                1912    PUSH_NULL                       
                1914    LOAD_CONST                      32: '__pyarmor_exit_13172__'
                1916    NOP                             
                1918    LOAD_CONST                      3: b'<COAddr>\x07\x00\x00\x1a\\\x07\x00\x00\x00\x00\x00\x00\x00\x00\x00\x00\x00\x00\x00\x00'
                1920    CALL                            1
                1928    POP_TOP                         
                1930    RERAISE                         0
                1932    COPY                            3
                1934    POP_EXCEPT                      
                1936    RERAISE                         1
                1938    PUSH_NULL                       
                1940    LOAD_CONST                      32: '__pyarmor_exit_13172__'
                1942    LOAD_CONST                      3: b'<COAddr>\x07\x00\x00\x1a\\\x07\x00\x00\x00\x00\x00\x00\x00\x00\x00\x00\x00\x00\x00\x00'
                1944    BUILD_TUPLE                     1
                1946    CALL_FUNCTION_EX                0
                1948    POP_TOP                         
                1950    RETURN_VALUE                    
            [Exception Table]
                30 to 1182 -> 1738 [0] 
                1182 to 1630 -> 1714 [1] lasti
                1632 to 1648 -> 1738 [0] 
                1648 to 1692 -> 1910 [0] 
                1714 to 1724 -> 1732 [3] lasti
                1724 to 1738 -> 1738 [0] 
                1738 to 1756 -> 1828 [1] lasti
                1756 to 1760 -> 1834 [0] 
                1760 to 1776 -> 1828 [1] lasti
                1776 to 1808 -> 1818 [1] lasti
                1808 to 1818 -> 1834 [0] 
                1818 to 1828 -> 1828 [1] lasti
                1828 to 1834 -> 1834 [0] 
                1834 to 1882 -> 1904 [1] lasti
                1882 to 1884 -> 1910 [0] 
                1904 to 1910 -> 1910 [0] 
                1910 to 1932 -> 1932 [1] lasti
        [Code]
            File Name: <frozen program.modules.Check_links>
            Object Name: get_bio
            Qualified Name: get_bio
            Arg Count: 2
            Pos Only Arg Count: 0
            KW Only Arg Count: 0
            Stack Size: 11
            Flags: 0x20000003 (CO_OPTIMIZED | CO_NEWLOCALS | CO_PYARMOR_OBFUSCATED)
            [Names]
                'functions'
                'users'
                'GetFullUserRequest'
                'types'
                'InputUser'
                'isinstance'
                'full_user'
                'UserFull'
                'UserFull_L210'
                'UserFull_L209'
                'UserFull_L200'
                'UserFull_L199'
                'UserFull_L195'
                'UserFull_L193'
                'UserFull_L187'
                'about'
            [Locals+Names]
                'client'
                'info'
                '__assert_armored__'
                '_var_var_16'
            [Constants]
                None
                '__pyarmor_assert_13173__'
                '__pyarmor_enter_13174__'
                b'<COAddr>\x07\x00\x00\x1a@\x02\x00\x00\x00\x00\x00\x00\x00\x00\x00\x00\x00\x00\x00\x00'
                'id'
                'access_hash'   # b'\x81\xe3\x1b\x106\xe9\xad\xed\x13\xfb\x1e\xc8'
                (
                    'user_id'
                    'access_hash'
                )
                (
                    'id'
                )
                '__pyarmor_exit_13175__'
            [Disassembly]
                0       NOP                             
                2       NOP                             
                4       PUSH_NULL                       
                6       LOAD_CONST                      2: '__pyarmor_enter_13174__'
                8       LOAD_CONST                      3: b'<COAddr>\x07\x00\x00\x1a@\x02\x00\x00\x00\x00\x00\x00\x00\x00\x00\x00\x00\x00\x00\x00'
                10      BUILD_TUPLE                     1
                12      CALL_FUNCTION_EX                0
                14      POP_TOP                         
                16      RESUME                          0
                18      NOP                             
                20      NOP                             
                22      NOP                             
                24      NOP                             
                26      NOP                             
                28      NOP                             
                30      PUSH_NULL                       
                32      LOAD_FAST                       0: client
                34      LOAD_GLOBAL                     0: functions
                44      LOAD_ATTR                       2: users
                64      LOAD_ATTR                       5: GetFullUserRequest
                84      LOAD_GLOBAL                     7: NULL + types
                94      LOAD_ATTR                       8: InputUser
                114     LOAD_FAST                       1: info
                116     LOAD_CONST                      4: 'id'
                118     BINARY_SUBSCR                   
                122     LOAD_FAST                       1: info
                124     PUSH_NULL                       
                126     LOAD_CONST                      1: '__pyarmor_assert_13173__'
                128     LOAD_CONST                      5: 'access_hash'   # b'\x81\xe3\x1b\x106\xe9\xad\xed\x13\xfb\x1e\xc8'
                130     CALL                            1
                138     BINARY_SUBSCR                   
                142     KW_NAMES                        6: ('user_id', 'access_hash')
                144     CALL                            2
                152     KW_NAMES                        7: ('id',)
                154     CALL                            1
                162     CALL                            1
                170     STORE_FAST                      3: _var_var_16
                172     LOAD_GLOBAL                     11: NULL + isinstance
                182     LOAD_FAST                       3: _var_var_16
                184     LOAD_ATTR                       12: full_user
                204     LOAD_GLOBAL                     6: types
                214     LOAD_ATTR                       14: UserFull
                234     LOAD_GLOBAL                     6: types
                244     LOAD_ATTR                       16: UserFull_L210
                264     LOAD_GLOBAL                     6: types
                274     LOAD_ATTR                       18: UserFull_L209
                294     LOAD_GLOBAL                     6: types
                304     LOAD_ATTR                       20: UserFull_L200
                324     LOAD_GLOBAL                     6: types
                334     LOAD_ATTR                       22: UserFull_L199
                354     LOAD_GLOBAL                     6: types
                364     LOAD_ATTR                       24: UserFull_L195
                384     LOAD_GLOBAL                     6: types
                394     LOAD_ATTR                       26: UserFull_L193
                414     LOAD_GLOBAL                     6: types
                424     LOAD_ATTR                       28: UserFull_L187
                444     BUILD_TUPLE                     8
                446     CALL                            2
                454     POP_JUMP_IF_FALSE               46 (to 548)
                456     LOAD_FAST                       3: _var_var_16
                458     LOAD_ATTR                       2: users
                478     BUILD_LIST                      0
                480     COMPARE_OP                      55 (!=)
                484     POP_JUMP_IF_FALSE               31 (to 548)
                486     LOAD_FAST                       3: _var_var_16
                488     LOAD_ATTR                       12: full_user
                508     LOAD_ATTR                       30: about
                528     NOP                             
                530     NOP                             
                532     NOP                             
                534     JUMP_FORWARD                    47 (to 630)
                536     CALL                            1
                544     POP_TOP                         
                546     RETURN_VALUE                    
                548     NOP                             
                550     LOAD_CONST                      0: None
                552     NOP                             
                554     NOP                             
                556     NOP                             
                558     JUMP_FORWARD                    35 (to 630)
                566     POP_TOP                         
                568     RETURN_CONST                    0: None
                570     PUSH_EXC_INFO                   
                572     POP_TOP                         
                574     POP_EXCEPT                      
                576     LOAD_CONST                      0: None
                578     NOP                             
                580     NOP                             
                582     NOP                             
                584     JUMP_FORWARD                    22 (to 630)
                592     POP_TOP                         
                594     RETURN_CONST                    0: None
                596     COPY                            3
                598     POP_EXCEPT                      
                600     RERAISE                         1
                602     PUSH_EXC_INFO                   
                604     PUSH_NULL                       
                606     LOAD_CONST                      8: '__pyarmor_exit_13175__'
                608     NOP                             
                610     LOAD_CONST                      3: b'<COAddr>\x07\x00\x00\x1a@\x02\x00\x00\x00\x00\x00\x00\x00\x00\x00\x00\x00\x00\x00\x00'
                612     CALL                            1
                620     POP_TOP                         
                622     RERAISE                         0
                624     COPY                            3
                626     POP_EXCEPT                      
                628     RERAISE                         1
                630     PUSH_NULL                       
                632     LOAD_CONST                      8: '__pyarmor_exit_13175__'
                634     LOAD_CONST                      3: b'<COAddr>\x07\x00\x00\x1a@\x02\x00\x00\x00\x00\x00\x00\x00\x00\x00\x00\x00\x00\x00\x00'
                636     BUILD_TUPLE                     1
                638     CALL_FUNCTION_EX                0
                640     POP_TOP                         
                642     RETURN_VALUE                    
            [Exception Table]
                30 to 528 -> 570 [0] 
                570 to 574 -> 596 [1] lasti
                574 to 576 -> 602 [0] 
                596 to 602 -> 602 [0] 
                602 to 624 -> 624 [1] lasti
        [Code]
            File Name: <frozen program.modules.Check_links>
            Object Name: worker
            Qualified Name: worker
            Arg Count: 7
            Pos Only Arg Count: 0
            KW Only Arg Count: 0
            Stack Size: 21
            Flags: 0x20000003 (CO_OPTIMIZED | CO_NEWLOCALS | CO_PYARMOR_OBFUSCATED)
            [Names]
                'Thread_wait'
                'account_works'
                'Lang'
                'Disconnect'
                'Logs'
                'PrintLog'
                'get'
                'int'
                'is_set'
                'StopProgram'
                'db_base'
                'tg_links'
                'standart'
                'tg_group'
                'go_to'
                'entity'
                'check'
                'type'
                'dict'
                'db_parsing'
                'insert_group'
                'update'
                'go_out'
                'tg_entity'
                'get_bio'
                'insert_user'
                'functions'
                'channels'
                'GetFullChannelRequest'
                'full_chat'
                'participants_count'
                'DelayOnline'
                'BaseException'
                'logging'
            [Locals+Names]
                'account'
                'config'
                'proxy'
                'data'
                '_parsing_'
                'stop_thread'
                'err'
                '__assert_armored__'
                '_var_var_17'
                '_var_var_18'
                '_var_var_19'
                '_var_var_20'
                '_var_var_21'
                '_var_var_22'
                '_var_var_23'
                '_var_var_24'
                '_var_var_25'
                '_var_var_26'
                '_var_var_27'
                '_var_var_28'
                '_var_var_29'
                '_var_var_30'
                '_var_var_31'
                '_var_var_32'
                '_var_var_33'
                '_var_var_3'
            [Constants]
                None
                '__pyarmor_assert_13176__'
                '__pyarmor_enter_13177__'
                b'<COAddr>\x07\x00\x00\x1a\xc0\x0e\x00\x00\x00\x00\x00\x00\x00\x00\x00\x00\x00\x00\x00\x00'
                'CheckLinks'   # b'\x81\xc1\x10\x160\xf1\x92\xdb\x15\xf1\x1e'
                (
                    'module'
                )
                False
                'false'
                (
                    'account'
                    'status'
                )
                'work_account_completed'   # b'\x81\xf5\x17\x018\xc5\xbf\xd1\x18\xf5\x18\xcex\xd3\xfb\x8a\x02M\xb7\xa2\xbe\xceJ'
                (
                    'config'
                    'account'
                    'message'
                )
                'done'
                '__pyarmor_exit_13178__'
                'Settings'
                'file_db'
                'check_count'   # b'\x81\xe1\x10\x160\xf1\x81\xd1\x14\xef\x03\xd4'
                'check_pgroup'   # b'\x81\xe1\x10\x160\xf1\x81\xc2\x1c\xe8\x02\xd5|'
                'standardize_links'   # b'\x81\xf1\x0c\x12=\xfe\xbf\xc0\x1f\xf3\x17\xc5S\xe0\xf1\x8b\x04N'
                'check_bio'   # b'\x81\xe1\x10\x160\xf1\x81\xd0\x12\xf5'
                'kol_per_acc'   # b'\x81\xe9\x17\x1f\x0c\xea\xbb\xc0$\xfb\x0e\xc3'
                'wait_from'   # b"\x81\xf5\x19\x1a'\xc5\xb8\xc0\x14\xf7"
                'wait_to'
                'max_flood_wait'   # b'\x81\xef\x19\x0b\x0c\xfc\xb2\xdd\x14\xfe2\xd7m\xe5\xec'
                0
                1
                'NO_GROUP'
                'database_none_links'   # b'\x81\xe6\x19\x072\xf8\xbf\xc1\x1e\xc5\x03\xcfb\xe9\xc7\x89\x06S\xb0\xb4'
                'joinchat'
                '+'
                'found_private_group'   # b'\x81\xe4\x17\x06=\xfe\x81\xc2\t\xf3\x1b\xc1x\xe9\xc7\x82\x1dR\xae\xb7'
                'getting_information_private_group'   # b"\x81\xe5\x1d\x07'\xf3\xb0\xd5$\xf3\x03\xc6c\xfe\xf5\x84\x1bT\xb4\xa9\x95\xdb\\\xc5\x13n\xb7Y?\xb6\x0c\xea/B"
                (
                    'config'
                    'client'
                    'account'
                    'group_link'
                    'max_flood_wait'
                    'lang'
                    'stop_thread'
                )
                'info'
                'id'
                'title'
                'count'
                'photo'
                'invite'
                'send_messages'   # b'\x81\xf1\x1d\x1d7\xc5\xb3\xd7\x08\xe9\x0c\xc7i\xff'
                'send_media'   # b'\x81\xf1\x1d\x1d7\xc5\xb3\xd7\x1f\xf3\x0c'
                'send_stickers'   # b'\x81\xf1\x1d\x1d7\xc5\xad\xc6\x12\xf9\x06\xc5~\xff'
                'send_polls'   # b'\x81\xf1\x1d\x1d7\xc5\xae\xdd\x17\xf6\x1e'
                'slow_mode'   # b'\x81\xf1\x14\x1c$\xc5\xb3\xdd\x1f\xff'
                'scam'
                'types'
                'Ready'
                (
                    'group_id'
                    'username'
                    'title'
                    'count'
                    'photo'
                    'invite'
                    'send_messages'
                    'send_media'
                    'send_stickers'
                    'send_pools'
                    'slow_mode'
                    'scam'
                    'types'
                    'status'
                )
                'Done'
                'NotFound'
                (
                    'entity'
                )
                'private_group_verification_disabled'   # b'\x81\xf2\n\x1a%\xfb\xaa\xd7$\xfd\x1f\xcfy\xfc\xc7\x93\nO\xb2\xa1\xa3\xc8O\xd8\x0c`\xadc\x04\xb8\r\xe48^%\t'
                'type'
                'user'
                'bio'
                'group_id'
                'mess_id'
                'comm_id'
                'phone'
                'username'
                'first_name'   # b'\x81\xe4\x11\x01 \xee\x81\xdc\x1a\xf7\x08'
                'last_name'   # b"\x81\xee\x19\x00'\xc5\xb0\xd3\x16\xff"
                'gender'
                'premium'
                'status'
                'time'
                'invite_status'   # b'\x81\xeb\x16\x05:\xee\xbb\xed\x08\xee\x0c\xd4y\xff'
                'send_status'   # b'\x81\xf1\x1d\x1d7\xc5\xad\xc6\x1a\xee\x18\xd3'
                (
                    'user_id'
                    'group_id'
                    'mess_id'
                    'comm_id'
                    'phone'
                    'username'
                    'first_name'
                    'last_name'
                    'bio'
                    'gender'
                    'photo'
                    'premium'
                    'status'
                    'time'
                    'invite_status'
                    'send_status'
                )
                'group'
                'entity'
                (
                    'channel'
                )
                'verification_completed'   # b'\x81\xf4\x1d\x01:\xfc\xb7\xd1\x1a\xee\x04\xcfb\xd3\xfb\x8a\x02M\xb7\xa2\xbe\xceJ'
                (
                    'config'
                    'account'
                    'message'
                    'param'
                )
                'completed_checks'   # b'\x81\xe1\x17\x1e#\xf6\xbb\xc6\x1e\xfe2\xc3d\xe9\xfb\x8e\x1c'
            [Disassembly]
                0       NOP                             
                2       NOP                             
                4       PUSH_NULL                       
                6       LOAD_CONST                      2: '__pyarmor_enter_13177__'
                8       LOAD_CONST                      3: b'<COAddr>\x07\x00\x00\x1a\xc0\x0e\x00\x00\x00\x00\x00\x00\x00\x00\x00\x00\x00\x00\x00\x00'
                10      BUILD_TUPLE                     1
                12      CALL_FUNCTION_EX                0
                14      POP_TOP                         
                16      RESUME                          0
                18      NOP                             
                20      NOP                             
                22      NOP                             
                24      NOP                             
                26      NOP                             
                28      NOP                             
                30      LOAD_GLOBAL                     1: NULL + Thread_wait
                40      LOAD_FAST                       3: data
                42      LOAD_FAST                       1: config
                44      LOAD_FAST                       5: stop_thread
                46      CALL                            3
                54      POP_TOP                         
                56      LOAD_GLOBAL                     3: NULL + account_works
                66      LOAD_FAST                       1: config
                68      LOAD_GLOBAL                     4: Lang
                78      LOAD_FAST                       2: proxy
                80      LOAD_FAST                       0: account
                82      LOAD_FAST                       5: stop_thread
                84      PUSH_NULL                       
                86      LOAD_CONST                      1: '__pyarmor_assert_13176__'
                88      LOAD_CONST                      4: 'CheckLinks'   # b'\x81\xc1\x10\x160\xf1\x92\xdb\x15\xf1\x1e'
                90      CALL                            1
                98      KW_NAMES                        5: ('module',)
                100     CALL                            6
                108     STORE_FAST                      8: _var_var_17
                110     LOAD_FAST                       8: _var_var_17
                112     LOAD_CONST                      6: False
                114     COMPARE_OP                      40 (==)
                118     POP_JUMP_IF_FALSE               68 (to 256)
                120     LOAD_FAST                       0: account
                122     LOAD_CONST                      7: 'false'
                124     LOAD_CONST                      8: ('account', 'status')
                126     BUILD_CONST_KEY_MAP             2
                128     LOAD_GLOBAL                     7: NULL + Disconnect
                138     LOAD_FAST                       8: _var_var_17
                140     CALL                            1
                148     POP_TOP                         
                150     LOAD_GLOBAL                     9: NULL + Logs
                160     LOAD_ATTR                       10: PrintLog
                180     LOAD_FAST                       1: config
                182     LOAD_FAST                       0: account
                184     LOAD_GLOBAL                     4: Lang
                194     PUSH_NULL                       
                196     LOAD_CONST                      1: '__pyarmor_assert_13176__'
                198     LOAD_CONST                      9: 'work_account_completed'   # b'\x81\xf5\x17\x018\xc5\xbf\xd1\x18\xf5\x18\xcex\xd3\xfb\x8a\x02M\xb7\xa2\xbe\xceJ'
                200     CALL                            1
                208     BINARY_SUBSCR                   
                212     KW_NAMES                        10: ('config', 'account', 'message')
                214     CALL                            3
                222     POP_TOP                         
                224     LOAD_FAST                       0: account
                226     LOAD_CONST                      11: 'done'
                228     LOAD_CONST                      8: ('account', 'status')
                230     BUILD_CONST_KEY_MAP             2
                232     SWAP                            2
                234     POP_TOP                         
                236     NOP                             
                238     NOP                             
                240     JUMP_FORWARD                    1793 (to 3830)
                244     CALL                            1
                252     POP_TOP                         
                254     RETURN_VALUE                    
                256     LOAD_FAST                       3: data
                258     LOAD_CONST                      13: 'Settings'
                260     BINARY_SUBSCR                   
                264     LOAD_ATTR                       13: get
                284     LOAD_CONST                      14: 'file_db'
                286     CALL                            1
                294     STORE_FAST                      9: _var_var_18
                296     LOAD_FAST                       3: data
                298     LOAD_CONST                      13: 'Settings'
                300     BINARY_SUBSCR                   
                304     LOAD_ATTR                       13: get
                324     PUSH_NULL                       
                326     LOAD_CONST                      1: '__pyarmor_assert_13176__'
                328     LOAD_CONST                      15: 'check_count'   # b'\x81\xe1\x10\x160\xf1\x81\xd1\x14\xef\x03\xd4'
                330     CALL                            1
                338     CALL                            1
                346     STORE_FAST                      10: _var_var_19
                348     LOAD_FAST                       3: data
                350     LOAD_CONST                      13: 'Settings'
                352     BINARY_SUBSCR                   
                356     LOAD_ATTR                       13: get
                376     PUSH_NULL                       
                378     LOAD_CONST                      1: '__pyarmor_assert_13176__'
                380     LOAD_CONST                      16: 'check_pgroup'   # b'\x81\xe1\x10\x160\xf1\x81\xc2\x1c\xe8\x02\xd5|'
                382     CALL                            1
                390     CALL                            1
                398     STORE_FAST                      11: _var_var_20
                400     LOAD_FAST                       3: data
                402     LOAD_CONST                      13: 'Settings'
                404     BINARY_SUBSCR                   
                408     LOAD_ATTR                       13: get
                428     PUSH_NULL                       
                430     LOAD_CONST                      1: '__pyarmor_assert_13176__'
                432     LOAD_CONST                      17: 'standardize_links'   # b'\x81\xf1\x0c\x12=\xfe\xbf\xc0\x1f\xf3\x17\xc5S\xe0\xf1\x8b\x04N'
                434     CALL                            1
                442     CALL                            1
                450     STORE_FAST                      12: _var_var_21
                452     LOAD_FAST                       3: data
                454     LOAD_CONST                      13: 'Settings'
                456     BINARY_SUBSCR                   
                460     LOAD_ATTR                       13: get
                480     PUSH_NULL                       
                482     LOAD_CONST                      1: '__pyarmor_assert_13176__'
                484     LOAD_CONST                      18: 'check_bio'   # b'\x81\xe1\x10\x160\xf1\x81\xd0\x12\xf5'
                486     CALL                            1
                494     CALL                            1
                502     STORE_FAST                      13: _var_var_22
                504     LOAD_GLOBAL                     15: NULL + int
                514     LOAD_FAST                       3: data
                516     LOAD_CONST                      13: 'Settings'
                518     BINARY_SUBSCR                   
                522     LOAD_ATTR                       13: get
                542     PUSH_NULL                       
                544     LOAD_CONST                      1: '__pyarmor_assert_13176__'
                546     LOAD_CONST                      19: 'kol_per_acc'   # b'\x81\xe9\x17\x1f\x0c\xea\xbb\xc0$\xfb\x0e\xc3'
                548     CALL                            1
                556     CALL                            1
                564     CALL                            1
                572     STORE_FAST                      14: _var_var_23
                574     LOAD_GLOBAL                     15: NULL + int
                584     LOAD_FAST                       3: data
                586     LOAD_CONST                      13: 'Settings'
                588     BINARY_SUBSCR                   
                592     LOAD_ATTR                       13: get
                612     PUSH_NULL                       
                614     LOAD_CONST                      1: '__pyarmor_assert_13176__'
                616     LOAD_CONST                      20: 'wait_from'   # b"\x81\xf5\x19\x1a'\xc5\xb8\xc0\x14\xf7"
                618     CALL                            1
                626     CALL                            1
                634     CALL                            1
                642     STORE_FAST                      15: _var_var_24
                644     LOAD_GLOBAL                     15: NULL + int
                654     LOAD_FAST                       3: data
                656     LOAD_CONST                      13: 'Settings'
                658     BINARY_SUBSCR                   
                662     LOAD_ATTR                       13: get
                682     LOAD_CONST                      21: 'wait_to'
                684     CALL                            1
                692     CALL                            1
                700     STORE_FAST                      16: _var_var_25
                702     LOAD_GLOBAL                     15: NULL + int
                712     LOAD_FAST                       3: data
                714     LOAD_CONST                      13: 'Settings'
                716     BINARY_SUBSCR                   
                720     LOAD_ATTR                       13: get
                740     PUSH_NULL                       
                742     LOAD_CONST                      1: '__pyarmor_assert_13176__'
                744     LOAD_CONST                      22: 'max_flood_wait'   # b'\x81\xef\x19\x0b\x0c\xfc\xb2\xdd\x14\xfe2\xd7m\xe5\xec'
                746     CALL                            1
                754     CALL                            1
                762     CALL                            1
                770     STORE_FAST                      17: _var_var_26
                772     LOAD_CONST                      23: 0
                774     STORE_FAST                      18: _var_var_27
                776     LOAD_FAST                       18: _var_var_27
                778     LOAD_FAST                       14: _var_var_23
                780     COMPARE_OP                      2 (<)
                784     POP_JUMP_IF_FALSE               1258 (to 3304)
                788     LOAD_FAST                       5: stop_thread
                790     LOAD_ATTR                       17: is_set
                810     CALL                            0
                818     POP_JUMP_IF_FALSE               10 (to 840)
                820     LOAD_GLOBAL                     19: NULL + StopProgram
                830     CALL                            0
                838     RAISE_VARARGS                   1
                840     LOAD_FAST                       18: _var_var_27
                842     LOAD_CONST                      24: 1
                844     BINARY_OP                       13 (+=)
                848     STORE_FAST                      18: _var_var_27
                850     LOAD_GLOBAL                     21: NULL + db_base
                860     LOAD_FAST                       9: _var_var_18
                862     CALL                            1
                870     LOAD_ATTR                       13: get
                890     LOAD_FAST                       0: account
                892     CALL                            1
                900     STORE_FAST                      19: _var_var_28
                902     LOAD_FAST                       19: _var_var_28
                904     LOAD_CONST                      25: 'NO_GROUP'
                906     COMPARE_OP                      40 (==)
                910     POP_JUMP_IF_FALSE               39 (to 990)
                912     LOAD_GLOBAL                     9: NULL + Logs
                922     LOAD_ATTR                       10: PrintLog
                942     LOAD_FAST                       1: config
                944     LOAD_FAST                       0: account
                946     LOAD_GLOBAL                     4: Lang
                956     PUSH_NULL                       
                958     LOAD_CONST                      1: '__pyarmor_assert_13176__'
                960     LOAD_CONST                      26: 'database_none_links'   # b'\x81\xe6\x19\x072\xf8\xbf\xc1\x1e\xc5\x03\xcfb\xe9\xc7\x89\x06S\xb0\xb4'
                962     CALL                            1
                970     BINARY_SUBSCR                   
                974     KW_NAMES                        10: ('config', 'account', 'message')
                976     CALL                            3
                984     POP_TOP                         
                986     JUMP_FORWARD                    1157 (to 3304)
                990     LOAD_FAST                       12: _var_var_21
                992     POP_JUMP_IF_FALSE               25 (to 1044)
                994     LOAD_GLOBAL                     23: NULL + tg_links
                1004    LOAD_ATTR                       24: standart
                1024    LOAD_FAST                       19: _var_var_28
                1026    LOAD_CONST                      24: 1
                1028    BINARY_SUBSCR                   
                1032    CALL                            1
                1040    STORE_FAST                      20: _var_var_29
                1042    JUMP_FORWARD                    5 (to 1054)
                1044    LOAD_FAST                       19: _var_var_28
                1046    LOAD_CONST                      24: 1
                1048    BINARY_SUBSCR                   
                1052    STORE_FAST                      20: _var_var_29
                1054    LOAD_CONST                      27: 'joinchat'
                1056    LOAD_FAST                       20: _var_var_29
                1058    CONTAINS_OP                     0 (in)
                1060    POP_JUMP_IF_TRUE                5 (to 1072)
                1062    LOAD_CONST                      28: '+'
                1064    LOAD_FAST                       20: _var_var_29
                1066    CONTAINS_OP                     0 (in)
                1068    POP_JUMP_IF_FALSE               453 (to 1978)
                1072    LOAD_GLOBAL                     9: NULL + Logs
                1082    LOAD_ATTR                       10: PrintLog
                1102    LOAD_FAST                       1: config
                1104    LOAD_FAST                       0: account
                1106    LOAD_GLOBAL                     4: Lang
                1116    PUSH_NULL                       
                1118    LOAD_CONST                      1: '__pyarmor_assert_13176__'
                1120    LOAD_CONST                      29: 'found_private_group'   # b'\x81\xe4\x17\x06=\xfe\x81\xc2\t\xf3\x1b\xc1x\xe9\xc7\x82\x1dR\xae\xb7'
                1122    CALL                            1
                1130    BINARY_SUBSCR                   
                1134    KW_NAMES                        10: ('config', 'account', 'message')
                1136    CALL                            3
                1144    POP_TOP                         
                1146    LOAD_FAST                       11: _var_var_20
                1148    POP_JUMP_IF_FALSE               374 (to 1900)
                1152    LOAD_GLOBAL                     9: NULL + Logs
                1162    LOAD_ATTR                       10: PrintLog
                1182    LOAD_FAST                       1: config
                1184    LOAD_FAST                       0: account
                1186    LOAD_GLOBAL                     4: Lang
                1196    PUSH_NULL                       
                1198    LOAD_CONST                      1: '__pyarmor_assert_13176__'
                1200    LOAD_CONST                      30: 'getting_information_private_group'   # b"\x81\xe5\x1d\x07'\xf3\xb0\xd5$\xf3\x03\xc6c\xfe\xf5\x84\x1bT\xb4\xa9\x95\xdb\\\xc5\x13n\xb7Y?\xb6\x0c\xea/B"
                1202    CALL                            1
                1210    BINARY_SUBSCR                   
                1214    KW_NAMES                        10: ('config', 'account', 'message')
                1216    CALL                            3
                1224    POP_TOP                         
                1226    LOAD_GLOBAL                     27: NULL + tg_group
                1236    LOAD_FAST                       1: config
                1238    LOAD_FAST                       8: _var_var_17
                1240    LOAD_FAST                       0: account
                1242    LOAD_FAST                       20: _var_var_29
                1244    LOAD_FAST                       17: _var_var_26
                1246    LOAD_GLOBAL                     4: Lang
                1256    LOAD_FAST                       5: stop_thread
                1258    KW_NAMES                        31: ('config', 'client', 'account', 'group_link', 'max_flood_wait', 'lang', 'stop_thread')
                1260    CALL                            7
                1268    LOAD_ATTR                       29: go_to
                1288    CALL                            0
                1296    STORE_FAST                      21: _var_var_30
                1298    LOAD_FAST                       21: _var_var_30
                1300    PUSH_NULL                       
                1302    LOAD_CONST                      1: '__pyarmor_assert_13176__'
                1304    LOAD_CONST                      22: 'max_flood_wait'   # b'\x81\xef\x19\x0b\x0c\xfc\xb2\xdd\x14\xfe2\xd7m\xe5\xec'
                1306    CALL                            1
                1314    COMPARE_OP                      40 (==)
                1318    POP_JUMP_IF_FALSE               2 (to 1324)
                1320    JUMP_FORWARD                    990 (to 3304)
                1324    LOAD_GLOBAL                     31: NULL + entity
                1334    CALL                            0
                1342    LOAD_ATTR                       33: check
                1362    LOAD_FAST                       21: _var_var_30
                1364    CALL                            1
                1372    STORE_FAST                      22: _var_var_31
                1374    LOAD_GLOBAL                     35: NULL + type
                1384    LOAD_FAST                       22: _var_var_31
                1386    CALL                            1
                1394    LOAD_GLOBAL                     36: dict
                1404    COMPARE_OP                      40 (==)
                1408    POP_JUMP_IF_FALSE               174 (to 1758)
                1410    LOAD_GLOBAL                     39: NULL + db_parsing
                1420    LOAD_FAST                       4: _parsing_
                1422    CALL                            1
                1430    LOAD_ATTR                       41: insert_group
                1450    LOAD_FAST                       22: _var_var_31
                1452    LOAD_CONST                      32: 'info'
                1454    BINARY_SUBSCR                   
                1458    LOAD_CONST                      33: 'id'
                1460    BINARY_SUBSCR                   
                1464    LOAD_FAST                       20: _var_var_29
                1466    LOAD_FAST                       22: _var_var_31
                1468    LOAD_CONST                      32: 'info'
                1470    BINARY_SUBSCR                   
                1474    LOAD_CONST                      34: 'title'
                1476    BINARY_SUBSCR                   
                1480    LOAD_FAST                       22: _var_var_31
                1482    LOAD_CONST                      32: 'info'
                1484    BINARY_SUBSCR                   
                1488    LOAD_CONST                      35: 'count'
                1490    BINARY_SUBSCR                   
                1494    LOAD_FAST                       22: _var_var_31
                1496    LOAD_CONST                      32: 'info'
                1498    BINARY_SUBSCR                   
                1502    LOAD_CONST                      36: 'photo'
                1504    BINARY_SUBSCR                   
                1508    LOAD_FAST                       22: _var_var_31
                1510    LOAD_CONST                      32: 'info'
                1512    BINARY_SUBSCR                   
                1516    LOAD_CONST                      37: 'invite'
                1518    BINARY_SUBSCR                   
                1522    LOAD_FAST                       22: _var_var_31
                1524    LOAD_CONST                      32: 'info'
                1526    BINARY_SUBSCR                   
                1530    PUSH_NULL                       
                1532    LOAD_CONST                      1: '__pyarmor_assert_13176__'
                1534    LOAD_CONST                      38: 'send_messages'   # b'\x81\xf1\x1d\x1d7\xc5\xb3\xd7\x08\xe9\x0c\xc7i\xff'
                1536    CALL                            1
                1544    BINARY_SUBSCR                   
                1548    LOAD_FAST                       22: _var_var_31
                1550    LOAD_CONST                      32: 'info'
                1552    BINARY_SUBSCR                   
                1556    PUSH_NULL                       
                1558    LOAD_CONST                      1: '__pyarmor_assert_13176__'
                1560    LOAD_CONST                      39: 'send_media'   # b'\x81\xf1\x1d\x1d7\xc5\xb3\xd7\x1f\xf3\x0c'
                1562    CALL                            1
                1570    BINARY_SUBSCR                   
                1574    LOAD_FAST                       22: _var_var_31
                1576    LOAD_CONST                      32: 'info'
                1578    BINARY_SUBSCR                   
                1582    PUSH_NULL                       
                1584    LOAD_CONST                      1: '__pyarmor_assert_13176__'
                1586    LOAD_CONST                      40: 'send_stickers'   # b'\x81\xf1\x1d\x1d7\xc5\xad\xc6\x12\xf9\x06\xc5~\xff'
                1588    CALL                            1
                1596    BINARY_SUBSCR                   
                1600    LOAD_FAST                       22: _var_var_31
                1602    LOAD_CONST                      32: 'info'
                1604    BINARY_SUBSCR                   
                1608    PUSH_NULL                       
                1610    LOAD_CONST                      1: '__pyarmor_assert_13176__'
                1612    LOAD_CONST                      41: 'send_polls'   # b'\x81\xf1\x1d\x1d7\xc5\xae\xdd\x17\xf6\x1e'
                1614    CALL                            1
                1622    BINARY_SUBSCR                   
                1626    LOAD_FAST                       22: _var_var_31
                1628    LOAD_CONST                      32: 'info'
                1630    BINARY_SUBSCR                   
                1634    PUSH_NULL                       
                1636    LOAD_CONST                      1: '__pyarmor_assert_13176__'
                1638    LOAD_CONST                      42: 'slow_mode'   # b'\x81\xf1\x14\x1c$\xc5\xb3\xdd\x1f\xff'
                1640    CALL                            1
                1648    BINARY_SUBSCR                   
                1652    LOAD_FAST                       22: _var_var_31
                1654    LOAD_CONST                      32: 'info'
                1656    BINARY_SUBSCR                   
                1660    LOAD_CONST                      43: 'scam'
                1662    BINARY_SUBSCR                   
                1666    LOAD_FAST                       22: _var_var_31
                1668    LOAD_CONST                      32: 'info'
                1670    BINARY_SUBSCR                   
                1674    LOAD_CONST                      44: 'types'
                1676    BINARY_SUBSCR                   
                1680    LOAD_CONST                      45: 'Ready'
                1682    KW_NAMES                        46: ('group_id', 'username', 'title', 'count', 'photo', 'invite', 'send_messages', 'send_media', 'send_stickers', 'send_pools', 'slow_mode', 'scam', 'types', 'status')
                1684    CALL                            14
                1692    POP_TOP                         
                1694    LOAD_GLOBAL                     21: NULL + db_base
                1704    LOAD_FAST                       9: _var_var_18
                1706    CALL                            1
                1714    LOAD_ATTR                       43: update
                1734    LOAD_FAST                       0: account
                1736    LOAD_FAST                       19: _var_var_28
                1738    LOAD_CONST                      24: 1
                1740    BINARY_SUBSCR                   
                1744    LOAD_CONST                      47: 'Done'
                1746    CALL                            3
                1754    POP_TOP                         
                1756    JUMP_FORWARD                    31 (to 1820)
                1758    LOAD_GLOBAL                     21: NULL + db_base
                1768    LOAD_FAST                       9: _var_var_18
                1770    CALL                            1
                1778    LOAD_ATTR                       43: update
                1798    LOAD_FAST                       0: account
                1800    LOAD_FAST                       19: _var_var_28
                1802    LOAD_CONST                      24: 1
                1804    BINARY_SUBSCR                   
                1808    LOAD_CONST                      48: 'NotFound'
                1810    CALL                            3
                1818    POP_TOP                         
                1820    LOAD_GLOBAL                     27: NULL + tg_group
                1830    LOAD_FAST                       1: config
                1832    LOAD_FAST                       8: _var_var_17
                1834    LOAD_FAST                       0: account
                1836    LOAD_FAST                       20: _var_var_29
                1838    LOAD_FAST                       17: _var_var_26
                1840    LOAD_GLOBAL                     4: Lang
                1850    LOAD_FAST                       5: stop_thread
                1852    KW_NAMES                        31: ('config', 'client', 'account', 'group_link', 'max_flood_wait', 'lang', 'stop_thread')
                1854    CALL                            7
                1862    LOAD_ATTR                       45: go_out
                1882    LOAD_FAST                       21: _var_var_30
                1884    KW_NAMES                        49: ('entity',)
                1886    CALL                            1
                1894    POP_TOP                         
                1896    JUMP_FORWARD                    675 (to 3250)
                1900    LOAD_GLOBAL                     9: NULL + Logs
                1910    LOAD_ATTR                       10: PrintLog
                1930    LOAD_FAST                       1: config
                1932    LOAD_FAST                       0: account
                1934    LOAD_GLOBAL                     4: Lang
                1944    PUSH_NULL                       
                1946    LOAD_CONST                      1: '__pyarmor_assert_13176__'
                1948    LOAD_CONST                      50: 'private_group_verification_disabled'   # b'\x81\xf2\n\x1a%\xfb\xaa\xd7$\xfd\x1f\xcfy\xfc\xc7\x93\nO\xb2\xa1\xa3\xc8O\xd8\x0c`\xadc\x04\xb8\r\xe48^%\t'
                1950    CALL                            1
                1958    BINARY_SUBSCR                   
                1962    KW_NAMES                        10: ('config', 'account', 'message')
                1964    CALL                            3
                1972    POP_TOP                         
                1974    JUMP_FORWARD                    636 (to 3250)
                1978    LOAD_GLOBAL                     47: NULL + tg_entity
                1988    LOAD_FAST                       1: config
                1990    LOAD_FAST                       8: _var_var_17
                1992    LOAD_FAST                       0: account
                1994    LOAD_FAST                       20: _var_var_29
                1996    LOAD_FAST                       17: _var_var_26
                1998    LOAD_GLOBAL                     4: Lang
                2008    LOAD_FAST                       5: stop_thread
                2010    CALL                            7
                2018    LOAD_ATTR                       33: check
                2038    CALL                            0
                2046    STORE_FAST                      22: _var_var_31
                2048    LOAD_FAST                       22: _var_var_31
                2050    PUSH_NULL                       
                2052    LOAD_CONST                      1: '__pyarmor_assert_13176__'
                2054    LOAD_CONST                      22: 'max_flood_wait'   # b'\x81\xef\x19\x0b\x0c\xfc\xb2\xdd\x14\xfe2\xd7m\xe5\xec'
                2056    CALL                            1
                2064    COMPARE_OP                      40 (==)
                2068    POP_JUMP_IF_FALSE               2 (to 2074)
                2070    JUMP_FORWARD                    615 (to 3304)
                2074    LOAD_GLOBAL                     35: NULL + type
                2084    LOAD_FAST                       22: _var_var_31
                2086    CALL                            1
                2094    LOAD_GLOBAL                     36: dict
                2104    COMPARE_OP                      40 (==)
                2108    POP_JUMP_IF_FALSE               226 (to 2562)
                2110    LOAD_FAST                       22: _var_var_31
                2112    LOAD_CONST                      51: 'type'
                2114    BINARY_SUBSCR                   
                2118    LOAD_CONST                      52: 'user'
                2120    COMPARE_OP                      40 (==)
                2124    POP_JUMP_IF_FALSE               218 (to 2562)
                2126    LOAD_FAST                       13: _var_var_22
                2128    POP_JUMP_IF_FALSE               21 (to 2172)
                2130    LOAD_GLOBAL                     49: NULL + get_bio
                2140    LOAD_FAST                       8: _var_var_17
                2142    LOAD_FAST                       22: _var_var_31
                2144    LOAD_CONST                      32: 'info'
                2146    BINARY_SUBSCR                   
                2150    CALL                            2
                2158    LOAD_FAST                       22: _var_var_31
                2160    LOAD_CONST                      32: 'info'
                2162    BINARY_SUBSCR                   
                2166    LOAD_CONST                      53: 'bio'
                2168    STORE_SUBSCR                    
                2172    LOAD_GLOBAL                     39: NULL + db_parsing
                2182    LOAD_FAST                       4: _parsing_
                2184    CALL                            1
                2192    LOAD_ATTR                       51: insert_user
                2212    LOAD_FAST                       22: _var_var_31
                2214    LOAD_CONST                      32: 'info'
                2216    BINARY_SUBSCR                   
                2220    LOAD_CONST                      33: 'id'
                2222    BINARY_SUBSCR                   
                2226    LOAD_FAST                       22: _var_var_31
                2228    LOAD_CONST                      32: 'info'
                2230    BINARY_SUBSCR                   
                2234    LOAD_CONST                      54: 'group_id'
                2236    BINARY_SUBSCR                   
                2240    LOAD_FAST                       22: _var_var_31
                2242    LOAD_CONST                      32: 'info'
                2244    BINARY_SUBSCR                   
                2248    LOAD_CONST                      55: 'mess_id'
                2250    BINARY_SUBSCR                   
                2254    LOAD_FAST                       22: _var_var_31
                2256    LOAD_CONST                      32: 'info'
                2258    BINARY_SUBSCR                   
                2262    LOAD_CONST                      56: 'comm_id'
                2264    BINARY_SUBSCR                   
                2268    LOAD_FAST                       22: _var_var_31
                2270    LOAD_CONST                      32: 'info'
                2272    BINARY_SUBSCR                   
                2276    LOAD_CONST                      57: 'phone'
                2278    BINARY_SUBSCR                   
                2282    LOAD_FAST                       22: _var_var_31
                2284    LOAD_CONST                      32: 'info'
                2286    BINARY_SUBSCR                   
                2290    LOAD_CONST                      58: 'username'
                2292    BINARY_SUBSCR                   
                2296    LOAD_FAST                       22: _var_var_31
                2298    LOAD_CONST                      32: 'info'
                2300    BINARY_SUBSCR                   
                2304    PUSH_NULL                       
                2306    LOAD_CONST                      1: '__pyarmor_assert_13176__'
                2308    LOAD_CONST                      59: 'first_name'   # b'\x81\xe4\x11\x01 \xee\x81\xdc\x1a\xf7\x08'
                2310    CALL                            1
                2318    BINARY_SUBSCR                   
                2322    LOAD_FAST                       22: _var_var_31
                2324    LOAD_CONST                      32: 'info'
                2326    BINARY_SUBSCR                   
                2330    PUSH_NULL                       
                2332    LOAD_CONST                      1: '__pyarmor_assert_13176__'
                2334    LOAD_CONST                      60: 'last_name'   # b"\x81\xee\x19\x00'\xc5\xb0\xd3\x16\xff"
                2336    CALL                            1
                2344    BINARY_SUBSCR                   
                2348    LOAD_FAST                       22: _var_var_31
                2350    LOAD_CONST                      32: 'info'
                2352    BINARY_SUBSCR                   
                2356    LOAD_CONST                      53: 'bio'
                2358    BINARY_SUBSCR                   
                2362    LOAD_FAST                       22: _var_var_31
                2364    LOAD_CONST                      32: 'info'
                2366    BINARY_SUBSCR                   
                2370    LOAD_CONST                      61: 'gender'
                2372    BINARY_SUBSCR                   
                2376    LOAD_FAST                       22: _var_var_31
                2378    LOAD_CONST                      32: 'info'
                2380    BINARY_SUBSCR                   
                2384    LOAD_CONST                      36: 'photo'
                2386    BINARY_SUBSCR                   
                2390    LOAD_FAST                       22: _var_var_31
                2392    LOAD_CONST                      32: 'info'
                2394    BINARY_SUBSCR                   
                2398    LOAD_CONST                      62: 'premium'
                2400    BINARY_SUBSCR                   
                2404    LOAD_FAST                       22: _var_var_31
                2406    LOAD_CONST                      32: 'info'
                2408    BINARY_SUBSCR                   
                2412    LOAD_CONST                      63: 'status'
                2414    BINARY_SUBSCR                   
                2418    LOAD_FAST                       22: _var_var_31
                2420    LOAD_CONST                      32: 'info'
                2422    BINARY_SUBSCR                   
                2426    LOAD_CONST                      64: 'time'
                2428    BINARY_SUBSCR                   
                2432    LOAD_FAST                       22: _var_var_31
                2434    LOAD_CONST                      32: 'info'
                2436    BINARY_SUBSCR                   
                2440    PUSH_NULL                       
                2442    LOAD_CONST                      1: '__pyarmor_assert_13176__'
                2444    LOAD_CONST                      65: 'invite_status'   # b'\x81\xeb\x16\x05:\xee\xbb\xed\x08\xee\x0c\xd4y\xff'
                2446    CALL                            1
                2454    BINARY_SUBSCR                   
                2458    LOAD_FAST                       22: _var_var_31
                2460    LOAD_CONST                      32: 'info'
                2462    BINARY_SUBSCR                   
                2466    PUSH_NULL                       
                2468    LOAD_CONST                      1: '__pyarmor_assert_13176__'
                2470    LOAD_CONST                      66: 'send_status'   # b'\x81\xf1\x1d\x1d7\xc5\xad\xc6\x1a\xee\x18\xd3'
                2472    CALL                            1
                2480    BINARY_SUBSCR                   
                2484    KW_NAMES                        67: ('user_id', 'group_id', 'mess_id', 'comm_id', 'phone', 'username', 'first_name', 'last_name', 'bio', 'gender', 'photo', 'premium', 'status', 'time', 'invite_status', 'send_status')
                2486    CALL                            16
                2494    POP_TOP                         
                2496    LOAD_GLOBAL                     21: NULL + db_base
                2506    LOAD_FAST                       9: _var_var_18
                2508    CALL                            1
                2516    LOAD_ATTR                       43: update
                2536    LOAD_FAST                       0: account
                2538    LOAD_FAST                       19: _var_var_28
                2540    LOAD_CONST                      24: 1
                2542    BINARY_SUBSCR                   
                2546    LOAD_CONST                      47: 'Done'
                2548    CALL                            3
                2556    POP_TOP                         
                2558    JUMP_FORWARD                    306 (to 3174)
                2562    LOAD_GLOBAL                     35: NULL + type
                2572    LOAD_FAST                       22: _var_var_31
                2574    CALL                            1
                2582    LOAD_GLOBAL                     36: dict
                2592    COMPARE_OP                      40 (==)
                2596    POP_JUMP_IF_FALSE               256 (to 3112)
                2600    LOAD_FAST                       22: _var_var_31
                2602    LOAD_CONST                      51: 'type'
                2604    BINARY_SUBSCR                   
                2608    LOAD_CONST                      68: 'group'
                2610    COMPARE_OP                      40 (==)
                2614    POP_JUMP_IF_FALSE               248 (to 3112)
                2616    LOAD_FAST                       22: _var_var_31
                2618    LOAD_CONST                      32: 'info'
                2620    BINARY_SUBSCR                   
                2624    LOAD_CONST                      35: 'count'
                2626    BINARY_SUBSCR                   
                2630    STORE_FAST                      23: _var_var_32
                2632    LOAD_FAST                       10: _var_var_19
                2634    POP_JUMP_IF_FALSE               64 (to 2764)
                2636    NOP                             
                2638    PUSH_NULL                       
                2640    LOAD_FAST                       8: _var_var_17
                2642    LOAD_GLOBAL                     52: functions
                2652    LOAD_ATTR                       54: channels
                2672    LOAD_ATTR                       57: GetFullChannelRequest
                2692    LOAD_FAST                       22: _var_var_31
                2694    LOAD_CONST                      69: 'entity'
                2696    BINARY_SUBSCR                   
                2700    KW_NAMES                        70: ('channel',)
                2702    CALL                            1
                2710    CALL                            1
                2718    STORE_FAST                      24: _var_var_33
                2720    LOAD_FAST                       24: _var_var_33
                2722    LOAD_ATTR                       58: full_chat
                2742    LOAD_ATTR                       60: participants_count
                2762    STORE_FAST                      23: _var_var_32
                2764    LOAD_GLOBAL                     39: NULL + db_parsing
                2774    LOAD_FAST                       4: _parsing_
                2776    CALL                            1
                2784    LOAD_ATTR                       41: insert_group
                2804    LOAD_FAST                       22: _var_var_31
                2806    LOAD_CONST                      32: 'info'
                2808    BINARY_SUBSCR                   
                2812    LOAD_CONST                      33: 'id'
                2814    BINARY_SUBSCR                   
                2818    LOAD_FAST                       20: _var_var_29
                2820    LOAD_FAST                       22: _var_var_31
                2822    LOAD_CONST                      32: 'info'
                2824    BINARY_SUBSCR                   
                2828    LOAD_CONST                      34: 'title'
                2830    BINARY_SUBSCR                   
                2834    LOAD_FAST                       23: _var_var_32
                2836    LOAD_FAST                       22: _var_var_31
                2838    LOAD_CONST                      32: 'info'
                2840    BINARY_SUBSCR                   
                2844    LOAD_CONST                      36: 'photo'
                2846    BINARY_SUBSCR                   
                2850    LOAD_FAST                       22: _var_var_31
                2852    LOAD_CONST                      32: 'info'
                2854    BINARY_SUBSCR                   
                2858    LOAD_CONST                      37: 'invite'
                2860    BINARY_SUBSCR                   
                2864    LOAD_FAST                       22: _var_var_31
                2866    LOAD_CONST                      32: 'info'
                2868    BINARY_SUBSCR                   
                2872    PUSH_NULL                       
                2874    LOAD_CONST                      1: '__pyarmor_assert_13176__'
                2876    LOAD_CONST                      38: 'send_messages'   # b'\x81\xf1\x1d\x1d7\xc5\xb3\xd7\x08\xe9\x0c\xc7i\xff'
                2878    CALL                            1
                2886    BINARY_SUBSCR                   
                2890    LOAD_FAST                       22: _var_var_31
                2892    LOAD_CONST                      32: 'info'
                2894    BINARY_SUBSCR                   
                2898    PUSH_NULL                       
                2900    LOAD_CONST                      1: '__pyarmor_assert_13176__'
                2902    LOAD_CONST                      39: 'send_media'   # b'\x81\xf1\x1d\x1d7\xc5\xb3\xd7\x1f\xf3\x0c'
                2904    CALL                            1
                2912    BINARY_SUBSCR                   
                2916    LOAD_FAST                       22: _var_var_31
                2918    LOAD_CONST                      32: 'info'
                2920    BINARY_SUBSCR                   
                2924    PUSH_NULL                       
                2926    LOAD_CONST                      1: '__pyarmor_assert_13176__'
                2928    LOAD_CONST                      40: 'send_stickers'   # b'\x81\xf1\x1d\x1d7\xc5\xad\xc6\x12\xf9\x06\xc5~\xff'
                2930    CALL                            1
                2938    BINARY_SUBSCR                   
                2942    LOAD_FAST                       22: _var_var_31
                2944    LOAD_CONST                      32: 'info'
                2946    BINARY_SUBSCR                   
                2950    PUSH_NULL                       
                2952    LOAD_CONST                      1: '__pyarmor_assert_13176__'
                2954    LOAD_CONST                      41: 'send_polls'   # b'\x81\xf1\x1d\x1d7\xc5\xae\xdd\x17\xf6\x1e'
                2956    CALL                            1
                2964    BINARY_SUBSCR                   
                2968    LOAD_FAST                       22: _var_var_31
                2970    LOAD_CONST                      32: 'info'
                2972    BINARY_SUBSCR                   
                2976    PUSH_NULL                       
                2978    LOAD_CONST                      1: '__pyarmor_assert_13176__'
                2980    LOAD_CONST                      42: 'slow_mode'   # b'\x81\xf1\x14\x1c$\xc5\xb3\xdd\x1f\xff'
                2982    CALL                            1
                2990    BINARY_SUBSCR                   
                2994    LOAD_FAST                       22: _var_var_31
                2996    LOAD_CONST                      32: 'info'
                2998    BINARY_SUBSCR                   
                3002    LOAD_CONST                      43: 'scam'
                3004    BINARY_SUBSCR                   
                3008    LOAD_FAST                       22: _var_var_31
                3010    LOAD_CONST                      32: 'info'
                3012    BINARY_SUBSCR                   
                3016    LOAD_CONST                      44: 'types'
                3018    BINARY_SUBSCR                   
                3022    LOAD_FAST                       22: _var_var_31
                3024    LOAD_CONST                      32: 'info'
                3026    BINARY_SUBSCR                   
                3030    LOAD_CONST                      63: 'status'
                3032    BINARY_SUBSCR                   
                3036    KW_NAMES                        46: ('group_id', 'username', 'title', 'count', 'photo', 'invite', 'send_messages', 'send_media', 'send_stickers', 'send_pools', 'slow_mode', 'scam', 'types', 'status')
                3038    CALL                            14
                3046    POP_TOP                         
                3048    LOAD_GLOBAL                     21: NULL + db_base
                3058    LOAD_FAST                       9: _var_var_18
                3060    CALL                            1
                3068    LOAD_ATTR                       43: update
                3088    LOAD_FAST                       0: account
                3090    LOAD_FAST                       19: _var_var_28
                3092    LOAD_CONST                      24: 1
                3094    BINARY_SUBSCR                   
                3098    LOAD_CONST                      47: 'Done'
                3100    CALL                            3
                3108    POP_TOP                         
                3110    JUMP_FORWARD                    31 (to 3174)
                3112    LOAD_GLOBAL                     21: NULL + db_base
                3122    LOAD_FAST                       9: _var_var_18
                3124    CALL                            1
                3132    LOAD_ATTR                       43: update
                3152    LOAD_FAST                       0: account
                3154    LOAD_FAST                       19: _var_var_28
                3156    LOAD_CONST                      24: 1
                3158    BINARY_SUBSCR                   
                3162    LOAD_CONST                      48: 'NotFound'
                3164    CALL                            3
                3172    POP_TOP                         
                3174    LOAD_GLOBAL                     9: NULL + Logs
                3184    LOAD_ATTR                       10: PrintLog
                3204    LOAD_FAST                       1: config
                3206    LOAD_FAST                       0: account
                3208    LOAD_GLOBAL                     4: Lang
                3218    PUSH_NULL                       
                3220    LOAD_CONST                      1: '__pyarmor_assert_13176__'
                3222    LOAD_CONST                      71: 'verification_completed'   # b'\x81\xf4\x1d\x01:\xfc\xb7\xd1\x1a\xee\x04\xcfb\xd3\xfb\x8a\x02M\xb7\xa2\xbe\xceJ'
                3224    CALL                            1
                3232    BINARY_SUBSCR                   
                3236    LOAD_FAST                       20: _var_var_29
                3238    KW_NAMES                        72: ('config', 'account', 'message', 'param')
                3240    CALL                            4
                3248    POP_TOP                         
                3250    LOAD_FAST                       18: _var_var_27
                3252    LOAD_FAST                       14: _var_var_23
                3254    COMPARE_OP                      55 (!=)
                3258    POP_JUMP_IF_FALSE               15 (to 3290)
                3260    LOAD_GLOBAL                     63: NULL + DelayOnline
                3270    LOAD_FAST                       0: account
                3272    LOAD_FAST                       8: _var_var_17
                3274    LOAD_FAST                       15: _var_var_24
                3276    LOAD_FAST                       16: _var_var_25
                3278    LOAD_FAST                       5: stop_thread
                3280    CALL                            5
                3288    POP_TOP                         
                3290    LOAD_FAST                       18: _var_var_27
                3292    LOAD_FAST                       14: _var_var_23
                3294    COMPARE_OP                      2 (<)
                3298    POP_JUMP_IF_FALSE               2 (to 3304)
                3300    JUMP_BACKWARD                   1258 (to 788)
                3304    LOAD_GLOBAL                     9: NULL + Logs
                3314    LOAD_ATTR                       10: PrintLog
                3334    LOAD_FAST                       1: config
                3336    LOAD_FAST                       0: account
                3338    LOAD_GLOBAL                     4: Lang
                3348    PUSH_NULL                       
                3350    LOAD_CONST                      1: '__pyarmor_assert_13176__'
                3352    LOAD_CONST                      73: 'completed_checks'   # b'\x81\xe1\x17\x1e#\xf6\xbb\xc6\x1e\xfe2\xc3d\xe9\xfb\x8e\x1c'
                3354    CALL                            1
                3362    BINARY_SUBSCR                   
                3366    LOAD_FAST                       18: _var_var_27
                3368    KW_NAMES                        72: ('config', 'account', 'message', 'param')
                3370    CALL                            4
                3378    POP_TOP                         
                3380    LOAD_GLOBAL                     7: NULL + Disconnect
                3390    LOAD_FAST_CHECK                 8: _var_var_17
                3392    CALL                            1
                3400    POP_TOP                         
                3402    LOAD_GLOBAL                     9: NULL + Logs
                3412    LOAD_ATTR                       10: PrintLog
                3432    LOAD_FAST                       1: config
                3434    LOAD_FAST                       0: account
                3436    LOAD_GLOBAL                     4: Lang
                3446    PUSH_NULL                       
                3448    LOAD_CONST                      1: '__pyarmor_assert_13176__'
                3450    LOAD_CONST                      9: 'work_account_completed'   # b'\x81\xf5\x17\x018\xc5\xbf\xd1\x18\xf5\x18\xcex\xd3\xfb\x8a\x02M\xb7\xa2\xbe\xceJ'
                3452    CALL                            1
                3460    BINARY_SUBSCR                   
                3464    KW_NAMES                        10: ('config', 'account', 'message')
                3466    CALL                            3
                3474    POP_TOP                         
                3476    LOAD_FAST                       0: account
                3478    LOAD_CONST                      11: 'done'
                3480    LOAD_CONST                      8: ('account', 'status')
                3482    BUILD_CONST_KEY_MAP             2
                3484    NOP                             
                3486    NOP                             
                3488    NOP                             
                3490    JUMP_FORWARD                    169 (to 3830)
                3492    CALL                            1
                3500    POP_TOP                         
                3502    RETURN_VALUE                    
                3504    PUSH_EXC_INFO                   
                3506    POP_TOP                         
                3508    POP_EXCEPT                      
                3510    JUMP_BACKWARD                   1682 (to 150)
                3514    COPY                            3
                3516    POP_EXCEPT                      
                3518    RERAISE                         1
                3520    PUSH_EXC_INFO                   
                3522    POP_TOP                         
                3524    POP_EXCEPT                      
                3526    JUMP_BACKWARD                   383 (to 2764)
                3530    COPY                            3
                3532    POP_EXCEPT                      
                3534    RERAISE                         1
                3536    PUSH_EXC_INFO                   
                3538    LOAD_GLOBAL                     18: StopProgram
                3548    CHECK_EXC_MATCH                 
                3550    POP_JUMP_IF_FALSE               3 (to 3558)
                3552    POP_TOP                         
                3554    POP_EXCEPT                      
                3556    JUMP_BACKWARD                   89 (to 3380)
                3558    LOAD_GLOBAL                     64: BaseException
                3568    CHECK_EXC_MATCH                 
                3570    POP_JUMP_IF_FALSE               26 (to 3624)
                3572    STORE_FAST                      25: _var_var_3
                3574    PUSH_NULL                       
                3576    LOAD_GLOBAL                     67: NULL + logging
                3586    LOAD_FAST                       25: _var_var_3
                3588    CALL                            1
                3596    CALL                            0
                3604    POP_TOP                         
                3606    POP_EXCEPT                      
                3608    LOAD_CONST                      0: None
                3610    STORE_FAST                      25: _var_var_3
                3612    DELETE_FAST                     25: _var_var_3
                3614    JUMP_BACKWARD                   118 (to 3380)
                3616    LOAD_CONST                      0: None
                3618    STORE_FAST                      25: _var_var_3
                3620    DELETE_FAST                     25: _var_var_3
                3622    RERAISE                         1
                3624    RERAISE                         0
                3626    COPY                            3
                3628    POP_EXCEPT                      
                3630    RERAISE                         1
                3632    PUSH_EXC_INFO                   
                3634    POP_TOP                         
                3636    POP_EXCEPT                      
                3638    JUMP_BACKWARD                   119 (to 3402)
                3640    COPY                            3
                3642    POP_EXCEPT                      
                3644    RERAISE                         1
                3646    PUSH_EXC_INFO                   
                3648    LOAD_GLOBAL                     7: NULL + Disconnect
                3658    LOAD_FAST_CHECK                 8: _var_var_17
                3660    CALL                            1
                3668    POP_TOP                         
                3670    JUMP_FORWARD                    7 (to 3686)
                3672    PUSH_EXC_INFO                   
                3674    POP_TOP                         
                3676    POP_EXCEPT                      
                3678    JUMP_FORWARD                    3 (to 3686)
                3680    COPY                            3
                3682    POP_EXCEPT                      
                3684    RERAISE                         1
                3686    LOAD_GLOBAL                     9: NULL + Logs
                3696    LOAD_ATTR                       10: PrintLog
                3716    LOAD_FAST                       1: config
                3718    LOAD_FAST                       0: account
                3720    LOAD_GLOBAL                     4: Lang
                3730    PUSH_NULL                       
                3732    LOAD_CONST                      1: '__pyarmor_assert_13176__'
                3734    LOAD_CONST                      9: 'work_account_completed'   # b'\x81\xf5\x17\x018\xc5\xbf\xd1\x18\xf5\x18\xcex\xd3\xfb\x8a\x02M\xb7\xa2\xbe\xceJ'
                3736    CALL                            1
                3744    BINARY_SUBSCR                   
                3748    KW_NAMES                        10: ('config', 'account', 'message')
                3750    CALL                            3
                3758    POP_TOP                         
                3760    LOAD_FAST                       0: account
                3762    LOAD_CONST                      11: 'done'
                3764    LOAD_CONST                      8: ('account', 'status')
                3766    BUILD_CONST_KEY_MAP             2
                3768    SWAP                            2
                3770    POP_TOP                         
                3772    SWAP                            2
                3774    POP_EXCEPT                      
                3776    NOP                             
                3778    NOP                             
                3780    NOP                             
                3782    JUMP_FORWARD                    23 (to 3830)
                3784    CALL                            1
                3792    POP_TOP                         
                3794    RETURN_VALUE                    
                3796    COPY                            3
                3798    POP_EXCEPT                      
                3800    RERAISE                         1
                3802    PUSH_EXC_INFO                   
                3804    PUSH_NULL                       
                3806    LOAD_CONST                      12: '__pyarmor_exit_13178__'
                3808    NOP                             
                3810    LOAD_CONST                      3: b'<COAddr>\x07\x00\x00\x1a\xc0\x0e\x00\x00\x00\x00\x00\x00\x00\x00\x00\x00\x00\x00\x00\x00'
                3812    CALL                            1
                3820    POP_TOP                         
                3822    RERAISE                         0
                3824    COPY                            3
                3826    POP_EXCEPT                      
                3828    RERAISE                         1
                3830    PUSH_NULL                       
                3832    LOAD_CONST                      12: '__pyarmor_exit_13178__'
                3834    LOAD_CONST                      3: b'<COAddr>\x07\x00\x00\x1a\xc0\x0e\x00\x00\x00\x00\x00\x00\x00\x00\x00\x00\x00\x00\x00\x00'
                3836    BUILD_TUPLE                     1
                3838    CALL_FUNCTION_EX                0
                3840    POP_TOP                         
                3842    RETURN_VALUE                    
            [Exception Table]
                30 to 128 -> 3536 [0] 
                128 to 150 -> 3504 [1] 
                150 to 236 -> 3802 [0] 
                256 to 2636 -> 3536 [0] 
                2638 to 2764 -> 3520 [0] 
                2764 to 3300 -> 3536 [0] 
                3304 to 3380 -> 3536 [0] 
                3380 to 3402 -> 3632 [0] 
                3402 to 3484 -> 3802 [0] 
                3504 to 3508 -> 3514 [2] lasti
                3508 to 3520 -> 3802 [0] 
                3520 to 3524 -> 3530 [1] lasti
                3524 to 3536 -> 3536 [0] 
                3536 to 3554 -> 3626 [1] lasti
                3554 to 3558 -> 3646 [0] 
                3558 to 3574 -> 3626 [1] lasti
                3574 to 3606 -> 3616 [1] lasti
                3606 to 3616 -> 3646 [0] 
                3616 to 3626 -> 3626 [1] lasti
                3626 to 3632 -> 3646 [0] 
                3632 to 3636 -> 3640 [1] lasti
                3636 to 3646 -> 3802 [0] 
                3646 to 3648 -> 3796 [1] lasti
                3648 to 3670 -> 3672 [2] 
                3670 to 3672 -> 3796 [1] lasti
                3672 to 3676 -> 3680 [3] lasti
                3676 to 3774 -> 3796 [1] lasti
                3774 to 3776 -> 3802 [0] 
                3796 to 3802 -> 3802 [0] 
                3802 to 3824 -> 3824 [1] lasti
        '__pyarmor_exit_13166__'
        (
            0
        )
    [Disassembly]
        0       NOP                             
        2       NOP                             
        4       PUSH_NULL                       
        6       LOAD_CONST                      1: '__pyarmor_enter_13165__'
        8       LOAD_CONST                      2: b'<COAddr>\x07\x00\x00\x1a|\x01\x00\x00\x00\x00\x00\x00\x00\x00\x00\x00\x00\x00\x00\x00'
        10      BUILD_TUPLE                     1
        12      CALL_FUNCTION_EX                0
        14      POP_TOP                         
        16      RESUME                          0
        18      NOP                             
        20      NOP                             
        22      NOP                             
        24      NOP                             
        26      NOP                             
        28      LOAD_CONST                      3: 0
        30      LOAD_CONST                      4: None
        32      IMPORT_NAME                     1: datetime
        34      STORE_NAME                      1: datetime
        36      LOAD_CONST                      3: 0
        38      LOAD_CONST                      4: None
        40      IMPORT_NAME                     2: json
        42      STORE_NAME                      2: json
        44      LOAD_CONST                      3: 0
        46      LOAD_CONST                      4: None
        48      IMPORT_NAME                     3: eel
        50      STORE_NAME                      3: eel
        52      LOAD_CONST                      3: 0
        54      LOAD_CONST                      4: None
        56      IMPORT_NAME                     4: concurrent.futures
        58      STORE_NAME                      5: concurrent
        60      LOAD_CONST                      3: 0
        62      LOAD_CONST                      5: ('Thread', 'Event')
        64      IMPORT_NAME                     6: threading
        66      IMPORT_FROM                     7: Thread
        68      STORE_NAME                      7: Thread
        70      IMPORT_FROM                     8: Event
        72      STORE_NAME                      8: Event
        74      POP_TOP                         
        76      LOAD_CONST                      3: 0
        78      LOAD_CONST                      6: ('functions', 'types')
        80      IMPORT_NAME                     9: multithon.sync
        82      IMPORT_FROM                     10: functions
        84      STORE_NAME                      10: functions
        86      IMPORT_FROM                     11: types
        88      STORE_NAME                      11: types
        90      POP_TOP                         
        92      LOAD_CONST                      3: 0
        94      LOAD_CONST                      7: ('StopProgram',)
        96      IMPORT_NAME                     12: multithon.errors
        98      IMPORT_FROM                     13: StopProgram
        100     STORE_NAME                      13: StopProgram
        102     POP_TOP                         
        104     LOAD_CONST                      3: 0
        106     LOAD_CONST                      8: ('GetLang',)
        108     IMPORT_NAME                     14: program.static_classes
        110     IMPORT_FROM                     15: GetLang
        112     STORE_NAME                      15: GetLang
        114     POP_TOP                         
        116     LOAD_CONST                      3: 0
        118     LOAD_CONST                      9: ('Logs',)
        120     IMPORT_NAME                     14: program.static_classes
        122     IMPORT_FROM                     16: Logs
        124     STORE_NAME                      16: Logs
        126     POP_TOP                         
        128     LOAD_CONST                      3: 0
        130     LOAD_CONST                      10: ('logging',)
        132     IMPORT_NAME                     14: program.static_classes
        134     IMPORT_FROM                     17: logging
        136     STORE_NAME                      17: logging
        138     POP_TOP                         
        140     LOAD_CONST                      3: 0
        142     LOAD_CONST                      11: ('memory_check_switcher',)
        144     IMPORT_NAME                     14: program.static_classes
        146     IMPORT_FROM                     18: memory_check_switcher
        148     STORE_NAME                      18: memory_check_switcher
        150     POP_TOP                         
        152     LOAD_CONST                      3: 0
        154     LOAD_CONST                      12: ('memory_set_pid',)
        156     IMPORT_NAME                     14: program.static_classes
        158     IMPORT_FROM                     19: memory_set_pid
        160     STORE_NAME                      19: memory_set_pid
        162     POP_TOP                         
        164     LOAD_CONST                      3: 0
        166     LOAD_CONST                      13: ('DelayOnline',)
        168     IMPORT_NAME                     20: program.telegram
        170     IMPORT_FROM                     21: DelayOnline
        172     STORE_NAME                      21: DelayOnline
        174     POP_TOP                         
        176     LOAD_CONST                      3: 0
        178     LOAD_CONST                      14: ('Disconnect',)
        180     IMPORT_NAME                     20: program.telegram
        182     IMPORT_FROM                     22: Disconnect
        184     STORE_NAME                      22: Disconnect
        186     POP_TOP                         
        188     LOAD_CONST                      3: 0
        190     LOAD_CONST                      15: ('Thread_wait',)
        192     IMPORT_NAME                     20: program.telegram
        194     IMPORT_FROM                     23: Thread_wait
        196     STORE_NAME                      23: Thread_wait
        198     POP_TOP                         
        200     LOAD_CONST                      3: 0
        202     LOAD_CONST                      16: ('account_works',)
        204     IMPORT_NAME                     20: program.telegram
        206     IMPORT_FROM                     24: account_works
        208     STORE_NAME                      24: account_works
        210     POP_TOP                         
        212     LOAD_CONST                      3: 0
        214     LOAD_CONST                      17: ('entity',)
        216     IMPORT_NAME                     20: program.telegram
        218     IMPORT_FROM                     25: entity
        220     STORE_NAME                      25: entity
        222     POP_TOP                         
        224     LOAD_CONST                      3: 0
        226     LOAD_CONST                      18: ('tg_entity',)
        228     IMPORT_NAME                     20: program.telegram
        230     IMPORT_FROM                     26: tg_entity
        232     STORE_NAME                      26: tg_entity
        234     POP_TOP                         
        236     LOAD_CONST                      3: 0
        238     LOAD_CONST                      19: ('tg_group',)
        240     IMPORT_NAME                     20: program.telegram
        242     IMPORT_FROM                     27: tg_group
        244     STORE_NAME                      27: tg_group
        246     POP_TOP                         
        248     LOAD_CONST                      3: 0
        250     LOAD_CONST                      20: ('tg_links',)
        252     IMPORT_NAME                     20: program.telegram
        254     IMPORT_FROM                     28: tg_links
        256     STORE_NAME                      28: tg_links
        258     POP_TOP                         
        260     LOAD_CONST                      3: 0
        262     LOAD_CONST                      21: ('GetConfig',)
        264     IMPORT_NAME                     29: program.general
        266     IMPORT_FROM                     30: GetConfig
        268     STORE_NAME                      30: GetConfig
        270     POP_TOP                         
        272     LOAD_CONST                      3: 0
        274     LOAD_CONST                      22: ('GetProxy',)
        276     IMPORT_NAME                     29: program.general
        278     IMPORT_FROM                     31: GetProxy
        280     STORE_NAME                      31: GetProxy
        282     POP_TOP                         
        284     LOAD_CONST                      3: 0
        286     LOAD_CONST                      23: ('StopDetect',)
        288     IMPORT_NAME                     29: program.general
        290     IMPORT_FROM                     32: StopDetect
        292     STORE_NAME                      32: StopDetect
        294     POP_TOP                         
        296     LOAD_CONST                      3: 0
        298     LOAD_CONST                      24: ('check_get_settings',)
        300     IMPORT_NAME                     29: program.general
        302     IMPORT_FROM                     33: check_get_settings
        304     STORE_NAME                      33: check_get_settings
        306     POP_TOP                         
        308     LOAD_CONST                      3: 0
        310     LOAD_CONST                      25: ('del_task_manager',)
        312     IMPORT_NAME                     29: program.general
        314     IMPORT_FROM                     34: del_task_manager
        316     STORE_NAME                      34: del_task_manager
        318     POP_TOP                         
        320     LOAD_CONST                      3: 0
        322     LOAD_CONST                      26: ('getFile',)
        324     IMPORT_NAME                     29: program.general
        326     IMPORT_FROM                     35: getFile
        328     STORE_NAME                      35: getFile
        330     POP_TOP                         
        332     LOAD_CONST                      3: 0
        334     LOAD_CONST                      27: ('set_task_manager',)
        336     IMPORT_NAME                     29: program.general
        338     IMPORT_FROM                     36: set_task_manager
        340     STORE_NAME                      36: set_task_manager
        342     POP_TOP                         
        344     LOAD_CONST                      3: 0
        346     LOAD_CONST                      28: ('db_base', 'db_parsing')
        348     IMPORT_NAME                     37: program.database
        350     IMPORT_FROM                     38: db_base
        352     STORE_NAME                      38: db_base
        354     IMPORT_FROM                     39: db_parsing
        356     STORE_NAME                      39: db_parsing
        358     POP_TOP                         
        360     LOAD_CONST                      29: <CODE> Check_links
        362     MAKE_FUNCTION                   0
        364     STORE_NAME                      40: Check_links
        366     LOAD_CONST                      30: <CODE> START
        368     MAKE_FUNCTION                   0
        370     STORE_NAME                      41: START
        372     LOAD_CONST                      31: <CODE> get_bio
        374     MAKE_FUNCTION                   0
        376     STORE_NAME                      42: get_bio
        378     LOAD_CONST                      34: (0,)
        380     LOAD_CONST                      32: <CODE> worker
        382     MAKE_FUNCTION                   1
        384     STORE_NAME                      43: worker
        386     LOAD_CONST                      4: None
        388     NOP                             
        390     NOP                             
        392     NOP                             
        394     JUMP_FORWARD                    19 (to 434)
        402     POP_TOP                         
        404     RETURN_CONST                    4: None
        406     PUSH_EXC_INFO                   
        408     PUSH_NULL                       
        410     LOAD_CONST                      33: '__pyarmor_exit_13166__'
        412     NOP                             
        414     LOAD_CONST                      2: b'<COAddr>\x07\x00\x00\x1a|\x01\x00\x00\x00\x00\x00\x00\x00\x00\x00\x00\x00\x00\x00\x00'
        416     CALL                            1
        424     POP_TOP                         
        426     RERAISE                         0
        428     COPY                            3
        430     POP_EXCEPT                      
        432     RERAISE                         1
        434     PUSH_NULL                       
        436     LOAD_CONST                      33: '__pyarmor_exit_13166__'
        438     LOAD_CONST                      2: b'<COAddr>\x07\x00\x00\x1a|\x01\x00\x00\x00\x00\x00\x00\x00\x00\x00\x00\x00\x00\x00\x00'
        440     BUILD_TUPLE                     1
        442     CALL_FUNCTION_EX                0
        444     POP_TOP                         
        446     RETURN_VALUE                    
    [Exception Table]
        28 to 386 -> 406 [0] 
        406 to 428 -> 428 [1] lasti
