#decoded by lolz.live/mrpenny / t.me/zeus_jackpot
# ================================
# Примечания по Pyarmor:
# - Байт-код и объекты кода Pyarmor соответствуют стандартному Python, но присутствуют специальные вызовы функций среды выполнения (runtime) Pyarmor.
# - Вызовы строк — это не ошибки, а маркеры, которые обрабатываются Pyarmor во время выполнения.
#
# Руководство по декомпиляции (без среды выполнения):
# 1. Игнорируйте зашифрованные байты после `#`; используйте только строку до `#`.
# 2. Удалите "__pyarmor_enter_xxx__"(b"<COAddr>...") и "__pyarmor_leave_xxx__"(b"<COAddr>...") (пролог/эпилог).
# 3. "__pyarmor_assert_xxx__"(A) не является настоящим оператором assert.
#    - Если A — это имя или читаемая строка: замените на A.
#    - Если A — это (X, "Y"): замените на X.Y.
#    - Если A — это (X, "Y", Z): замените на X.Y = Z.
#    - В противном случае: выберите наиболее подходящую/логичную замену.
# 4. "__pyarmor_bcc_xxx__"(...) указывает на машинный (нативный) код; тело функции недоступно. Добавьте комментарий.
# ================================

[Code]
    File Name: <frozen program.modules.Contacts_invite>
    Object Name: <module>
    Qualified Name: <module>
    Arg Count: 0
    Pos Only Arg Count: 0
    KW Only Arg Count: 0
    Stack Size: 5
    Flags: 0x20000000 (CO_PYARMOR_OBFUSCATED)
    [Names]
        '__assert_armored__'
        'eel'
        'json'
        'random'
        'datetime'
        'concurrent.futures'
        'concurrent'
        'threading'
        'Thread'
        'Event'
        'multithon.sync'
        'functions'
        'types'
        'multithon.errors'
        'StopProgram'
        'program.static_classes'
        'GetLang'
        'Logs'
        'logging'
        'memory_check_switcher'
        'memory_set_pid'
        'program.telegram'
        'DelayOnline'
        'Disconnect'
        'Thread_wait'
        'account_works'
        'tg_group'
        'tg_links'
        'program.general'
        'GetConfig'
        'GetProxy'
        'StopDetect'
        'check_get_settings'
        'del_task_manager'
        'getFile'
        'set_task_manager'
        'program.database'
        'db_statistic'
        'Contacts_invite'
        'START'
        'worker'
    [Locals+Names]
    [Constants]
        '__pyarmor_assert_13383__'
        '__pyarmor_enter_13384__'
        b'<COAddr>\x07\x00\x00\x1a^\x01\x00\x00\x00\x00\x00\x00\x00\x00\x00\x00\x00\x00\x00\x00'
        0
        None
        (
            'Thread'
            'Event'
        )
        (
            'functions'
            'types'
        )
        (
            'StopProgram'
        )
        (
            'GetLang'
        )
        (
            'Logs'
        )
        (
            'logging'
        )
        (
            'memory_check_switcher'
        )
        (
            'memory_set_pid'
        )
        (
            'DelayOnline'
        )
        (
            'Disconnect'
        )
        (
            'Thread_wait'
        )
        (
            'account_works'
        )
        (
            'tg_group'
        )
        (
            'tg_links'
        )
        (
            'GetConfig'
        )
        (
            'GetProxy'
        )
        (
            'StopDetect'
        )
        (
            'check_get_settings'
        )
        (
            'del_task_manager'
        )
        (
            'getFile'
        )
        (
            'set_task_manager'
        )
        (
            'db_statistic'
        )
        [Code]
            File Name: <frozen program.modules.Contacts_invite>
            Object Name: Contacts_invite
            Qualified Name: Contacts_invite
            Arg Count: 1
            Pos Only Arg Count: 0
            KW Only Arg Count: 0
            Stack Size: 8
            Flags: 0x20000003 (CO_OPTIMIZED | CO_NEWLOCALS | CO_PYARMOR_OBFUSCATED)
            [Names]
                'get'
                'getFile'
                'GetConfig'
                'config'
                'GetLang'
                'Lang'
                'GetProxy'
                'eel'
                'sendSuccessBox'
                'memory_check_switcher'
                'Event'
                'memory_set_pid'
                'Thread'
                'START'
                'start'
                'Logs'
                'WaitStopAnsfer'
                'UpdateLogInWindow'
                'BaseException'
                'logging'
            [Locals+Names]
                'data'
                '__assert_armored__'
                '_var_var_0'
                '_var_var_1'
                '_var_var_2'
                '_var_var_3'
            [Constants]
                None
                '__pyarmor_assert_13386__'
                '__pyarmor_enter_13387__'
                b'<COAddr>\x05\x00\x00\x1a\xae\x02\x00\x00\x00\x00\x00\x00\x00\x00\x00\x00\x00\x00\x00\x00'
                'action'
                'getFile'
                '__pyarmor_exit_13388__'
                'program_running'   # b'\x81\xf2\n\x1c4\xe8\xbf\xdf$\xe8\x18\xceb\xe5\xf6\x82'
                False
                (
                    'target'
                    'args'
                )
                True
                (
                    'target'
                    'args'
                    'daemon'
                )
            [Disassembly]
                0       NOP                             
                2       NOP                             
                4       PUSH_NULL                       
                6       LOAD_CONST                      2: '__pyarmor_enter_13387__'
                8       LOAD_CONST                      3: b'<COAddr>\x05\x00\x00\x1a\xae\x02\x00\x00\x00\x00\x00\x00\x00\x00\x00\x00\x00\x00\x00\x00'
                10      BUILD_TUPLE                     1
                12      CALL_FUNCTION_EX                0
                14      POP_TOP                         
                16      RESUME                          0
                18      NOP                             
                20      NOP                             
                22      NOP                             
                24      NOP                             
                26      NOP                             
                28      NOP                             
                30      LOAD_FAST                       0: data
                32      LOAD_ATTR                       1: get
                52      LOAD_CONST                      4: 'action'
                54      CALL                            1
                62      POP_JUMP_IF_NONE                28 (to 120)
                64      LOAD_FAST                       0: data
                66      LOAD_CONST                      4: 'action'
                68      BINARY_SUBSCR                   
                72      LOAD_CONST                      5: 'getFile'
                74      COMPARE_OP                      40 (==)
                78      POP_JUMP_IF_FALSE               20 (to 120)
                80      LOAD_GLOBAL                     3: NULL + getFile
                90      LOAD_FAST                       0: data
                92      CALL                            1
                100     NOP                             
                102     NOP                             
                104     JUMP_FORWARD                    316 (to 740)
                108     CALL                            1
                116     POP_TOP                         
                118     RETURN_VALUE                    
                120     LOAD_GLOBAL                     5: NULL + GetConfig
                130     CALL                            0
                138     STORE_GLOBAL                    3: config
                140     LOAD_GLOBAL                     9: NULL + GetLang
                150     LOAD_GLOBAL                     6: config
                160     CALL                            1
                168     STORE_GLOBAL                    5: Lang
                170     LOAD_GLOBAL                     13: NULL + GetProxy
                180     CALL                            0
                188     STORE_FAST                      2: _var_var_0
                190     LOAD_GLOBAL                     15: NULL + eel
                200     LOAD_ATTR                       16: sendSuccessBox
                220     LOAD_GLOBAL                     10: Lang
                230     PUSH_NULL                       
                232     LOAD_CONST                      1: '__pyarmor_assert_13386__'
                234     LOAD_CONST                      7: 'program_running'   # b'\x81\xf2\n\x1c4\xe8\xbf\xdf$\xe8\x18\xceb\xe5\xf6\x82'
                236     CALL                            1
                244     BINARY_SUBSCR                   
                248     CALL                            1
                256     POP_TOP                         
                258     LOAD_GLOBAL                     19: NULL + memory_check_switcher
                268     CALL                            0
                276     POP_JUMP_IF_TRUE                11 (to 300)
                278     NOP                             
                280     LOAD_CONST                      8: False
                282     NOP                             
                284     NOP                             
                286     NOP                             
                288     JUMP_FORWARD                    225 (to 740)
                296     POP_TOP                         
                298     RETURN_CONST                    8: False
                300     LOAD_GLOBAL                     21: NULL + Event
                310     CALL                            0
                318     STORE_FAST                      3: _var_var_1
                320     LOAD_GLOBAL                     23: NULL + memory_set_pid
                330     CALL                            0
                338     STORE_FAST                      4: _var_var_2
                340     LOAD_GLOBAL                     25: NULL + Thread
                350     LOAD_GLOBAL                     26: START
                360     LOAD_FAST                       0: data
                362     LOAD_GLOBAL                     6: config
                372     LOAD_FAST                       4: _var_var_2
                374     LOAD_FAST                       2: _var_var_0
                376     LOAD_FAST                       3: _var_var_1
                378     BUILD_TUPLE                     5
                380     KW_NAMES                        9: ('target', 'args')
                382     CALL                            2
                390     LOAD_ATTR                       29: start
                410     CALL                            0
                418     POP_TOP                         
                420     LOAD_GLOBAL                     25: NULL + Thread
                430     LOAD_GLOBAL                     30: Logs
                440     LOAD_ATTR                       32: WaitStopAnsfer
                460     LOAD_GLOBAL                     6: config
                470     LOAD_FAST                       4: _var_var_2
                472     LOAD_FAST                       3: _var_var_1
                474     BUILD_TUPLE                     3
                476     LOAD_CONST                      10: True
                478     KW_NAMES                        11: ('target', 'args', 'daemon')
                480     CALL                            3
                488     LOAD_ATTR                       29: start
                508     CALL                            0
                516     POP_TOP                         
                518     LOAD_GLOBAL                     25: NULL + Thread
                528     LOAD_GLOBAL                     30: Logs
                538     LOAD_ATTR                       34: UpdateLogInWindow
                558     LOAD_GLOBAL                     6: config
                568     LOAD_FAST                       4: _var_var_2
                570     LOAD_FAST                       3: _var_var_1
                572     BUILD_TUPLE                     3
                574     LOAD_CONST                      10: True
                576     KW_NAMES                        11: ('target', 'args', 'daemon')
                578     CALL                            3
                586     LOAD_ATTR                       29: start
                606     CALL                            0
                614     POP_TOP                         
                616     LOAD_CONST                      0: None
                618     NOP                             
                620     NOP                             
                622     NOP                             
                624     JUMP_FORWARD                    57 (to 740)
                632     POP_TOP                         
                634     RETURN_CONST                    0: None
                636     PUSH_EXC_INFO                   
                638     LOAD_GLOBAL                     36: BaseException
                648     CHECK_EXC_MATCH                 
                650     POP_JUMP_IF_FALSE               26 (to 704)
                652     STORE_FAST                      5: _var_var_3
                654     PUSH_NULL                       
                656     LOAD_GLOBAL                     39: NULL + logging
                666     LOAD_FAST                       5: _var_var_3
                668     CALL                            1
                676     CALL                            0
                684     POP_TOP                         
                686     POP_EXCEPT                      
                688     LOAD_CONST                      0: None
                690     STORE_FAST                      5: _var_var_3
                692     DELETE_FAST                     5: _var_var_3
                694     JUMP_BACKWARD                   40 (to 616)
                696     LOAD_CONST                      0: None
                698     STORE_FAST                      5: _var_var_3
                700     DELETE_FAST                     5: _var_var_3
                702     RERAISE                         1
                704     RERAISE                         0
                706     COPY                            3
                708     POP_EXCEPT                      
                710     RERAISE                         1
                712     PUSH_EXC_INFO                   
                714     PUSH_NULL                       
                716     LOAD_CONST                      6: '__pyarmor_exit_13388__'
                718     NOP                             
                720     LOAD_CONST                      3: b'<COAddr>\x05\x00\x00\x1a\xae\x02\x00\x00\x00\x00\x00\x00\x00\x00\x00\x00\x00\x00\x00\x00'
                722     CALL                            1
                730     POP_TOP                         
                732     RERAISE                         0
                734     COPY                            3
                736     POP_EXCEPT                      
                738     RERAISE                         1
                740     PUSH_NULL                       
                742     LOAD_CONST                      6: '__pyarmor_exit_13388__'
                744     LOAD_CONST                      3: b'<COAddr>\x05\x00\x00\x1a\xae\x02\x00\x00\x00\x00\x00\x00\x00\x00\x00\x00\x00\x00\x00\x00'
                746     BUILD_TUPLE                     1
                748     CALL_FUNCTION_EX                0
                750     POP_TOP                         
                752     RETURN_VALUE                    
            [Exception Table]
                30 to 100 -> 636 [0] 
                120 to 278 -> 636 [0] 
                300 to 616 -> 636 [0] 
                636 to 654 -> 706 [1] lasti
                654 to 686 -> 696 [1] lasti
                686 to 696 -> 712 [0] 
                696 to 706 -> 706 [1] lasti
                706 to 712 -> 712 [0] 
                712 to 734 -> 734 [1] lasti
        [Code]
            File Name: <frozen program.modules.Contacts_invite>
            Object Name: START
            Qualified Name: START
            Arg Count: 5
            Pos Only Arg Count: 0
            KW Only Arg Count: 0
            Stack Size: 14
            Flags: 0x20000003 (CO_OPTIMIZED | CO_NEWLOCALS | CO_PYARMOR_OBFUSCATED)
            [Names]
                'is_set'
                'StopProgram'
                'check_get_settings'
                'get'
                'isinstance'
                'list'
                'int'
                'len'
                'eel'
                'sendErrorBox'
                'Lang'
                'datetime'
                'now'
                'strftime'
                'db_statistic'
                'create'
                'WriteResult'
                'set_task_manager'
                'concurrent'
                'futures'
                'ThreadPoolExecutor'
                'StreamStat'
                'json'
                'dumps'
                'append'
                'submit'
                'worker'
                'as_completed'
                'BaseException'
                'logging'
                'del_task_manager'
                'StopDetect'
            [Locals+Names]
                'data'
                'config'
                'pid'
                'proxy'
                'stop_thread'
                '__assert_armored__'
                '_var_var_4'
                '_var_var_5'
                '_var_var_6'
                '_var_var_7'
                '_var_var_8'
                '_var_var_9'
                '_var_var_10'
                '_var_var_11'
                '_var_var_12'
                '_var_var_13'
                '_var_var_14'
                '_var_var_15'
                '_var_var_16'
                '_var_var_17'
                '_var_var_18'
                '_var_var_3'
            [Constants]
                None
                '__pyarmor_assert_13389__'
                '__pyarmor_enter_13390__'
                b'<COAddr>\x05\x00\x00\x1a>\x07\x00\x00\x00\x00\x00\x00\x00\x00\x00\x00\x00\x00\x00\x00'
                'Settings'
                'Accounts'
                'invitegroups'   # b'\x81\xeb\x16\x05:\xee\xbb\xd5\t\xf5\x18\xd0\x7f'
                1
                'select_accounts_works'   # b'\x81\xf1\x1d\x1f6\xf9\xaa\xed\x1a\xf9\x0e\xcfy\xe2\xec\x960J\xb4\xb5\xa1\xd8'
                0
                'Add more groups'   # b'\x81\xc3\x1c\x17s\xf7\xb1\xc0\x1e\xba\n\xd2c\xf9\xe8\x96'
                'thread_rules'   # b'\x81\xf6\x10\x016\xfb\xba\xed\t\xef\x01\xc5\x7f'
                True
                'thread_count'   # b'\x81\xf6\x10\x016\xfb\xba\xed\x18\xf5\x18\xcex'
                '%y-%m-%d_%H-%M-%S'   # b'\x81\xa7\x01^v\xf7\xf3\x97\x1f\xc5H\xe8!\xa9\xd5\xc8Jn'
                'additives/contacts_invite/'   # b'\x81\xe3\x1c\x17:\xee\xb7\xc4\x1e\xe9B\xc3c\xe2\xec\x84\x0cI\xa8\x98\xa3\xc5X\xc5\x11j\xec'
                '_invite.db'   # b'\x81\xdd\x11\x1d%\xf3\xaa\xd7U\xfe\x0f'
                'Statistic'   # b"\x81\xd1\x0c\x12'\xf3\xad\xc6\x12\xf9"
                'contacts_invite'   # b"\x81\xe1\x17\x1d'\xfb\xbd\xc6\x08\xc5\x04\xcez\xe5\xec\x80"
                'stuff'
                (
                    'accounts'
                    'name'
                )
                (
                    'max_workers'
                )
                'st_task'
                'st_stream'   # b'\x81\xf1\x0c, \xee\xac\xd7\x1a\xf7'
                'st_wait'
                'st_done'
                '__pyarmor_exit_13391__'
                'Done'
            [Disassembly]
                0       NOP                             
                2       NOP                             
                4       PUSH_NULL                       
                6       LOAD_CONST                      2: '__pyarmor_enter_13390__'
                8       LOAD_CONST                      3: b'<COAddr>\x05\x00\x00\x1a>\x07\x00\x00\x00\x00\x00\x00\x00\x00\x00\x00\x00\x00\x00\x00'
                10      BUILD_TUPLE                     1
                12      CALL_FUNCTION_EX                0
                14      POP_TOP                         
                16      RESUME                          0
                18      NOP                             
                20      NOP                             
                22      NOP                             
                24      NOP                             
                26      NOP                             
                28      NOP                             
                30      LOAD_FAST                       4: stop_thread
                32      LOAD_ATTR                       1: is_set
                52      CALL                            0
                60      POP_JUMP_IF_FALSE               10 (to 82)
                62      LOAD_GLOBAL                     3: NULL + StopProgram
                72      CALL                            0
                80      RAISE_VARARGS                   1
                82      LOAD_GLOBAL                     5: NULL + check_get_settings
                92      LOAD_FAST                       0: data
                94      LOAD_ATTR                       7: get
                114     LOAD_CONST                      4: 'Settings'
                116     CALL                            1
                124     CALL                            1
                132     POP_TOP                         
                134     LOAD_FAST                       0: data
                136     LOAD_CONST                      5: 'Accounts'
                138     BINARY_SUBSCR                   
                142     STORE_FAST                      6: _var_var_4
                144     LOAD_FAST                       0: data
                146     LOAD_CONST                      4: 'Settings'
                148     BINARY_SUBSCR                   
                152     LOAD_ATTR                       7: get
                172     PUSH_NULL                       
                174     LOAD_CONST                      1: '__pyarmor_assert_13389__'
                176     LOAD_CONST                      6: 'invitegroups'   # b'\x81\xeb\x16\x05:\xee\xbb\xd5\t\xf5\x18\xd0\x7f'
                178     CALL                            1
                186     CALL                            1
                194     STORE_FAST                      7: _var_var_5
                196     LOAD_GLOBAL                     9: NULL + isinstance
                206     LOAD_FAST                       6: _var_var_4
                208     LOAD_GLOBAL                     10: list
                218     CALL                            2
                226     POP_JUMP_IF_TRUE                3 (to 234)
                228     LOAD_FAST                       6: _var_var_4
                230     BUILD_LIST                      1
                232     STORE_FAST                      6: _var_var_4
                234     LOAD_GLOBAL                     9: NULL + isinstance
                244     LOAD_FAST                       7: _var_var_5
                246     LOAD_GLOBAL                     10: list
                256     CALL                            2
                264     POP_JUMP_IF_TRUE                3 (to 272)
                266     LOAD_FAST                       7: _var_var_5
                268     BUILD_LIST                      1
                270     STORE_FAST                      7: _var_var_5
                272     LOAD_GLOBAL                     13: NULL + int
                282     LOAD_GLOBAL                     15: NULL + len
                292     LOAD_FAST                       6: _var_var_4
                294     CALL                            1
                302     CALL                            1
                310     LOAD_CONST                      7: 1
                312     COMPARE_OP                      2 (<)
                316     POP_JUMP_IF_FALSE               44 (to 406)
                318     LOAD_GLOBAL                     17: NULL + eel
                328     LOAD_ATTR                       18: sendErrorBox
                348     LOAD_GLOBAL                     20: Lang
                358     PUSH_NULL                       
                360     LOAD_CONST                      1: '__pyarmor_assert_13389__'
                362     LOAD_CONST                      8: 'select_accounts_works'   # b'\x81\xf1\x1d\x1f6\xf9\xaa\xed\x1a\xf9\x0e\xcfy\xe2\xec\x960J\xb4\xb5\xa1\xd8'
                364     CALL                            1
                372     BINARY_SUBSCR                   
                376     CALL                            1
                384     POP_TOP                         
                386     LOAD_GLOBAL                     3: NULL + StopProgram
                396     CALL                            0
                404     RAISE_VARARGS                   1
                406     LOAD_GLOBAL                     13: NULL + int
                416     LOAD_GLOBAL                     15: NULL + len
                426     LOAD_FAST                       7: _var_var_5
                428     CALL                            1
                436     CALL                            1
                444     LOAD_CONST                      9: 0
                446     COMPARE_OP                      40 (==)
                450     POP_JUMP_IF_FALSE               37 (to 526)
                452     LOAD_GLOBAL                     17: NULL + eel
                462     LOAD_ATTR                       18: sendErrorBox
                482     PUSH_NULL                       
                484     LOAD_CONST                      1: '__pyarmor_assert_13389__'
                486     LOAD_CONST                      10: 'Add more groups'   # b'\x81\xc3\x1c\x17s\xf7\xb1\xc0\x1e\xba\n\xd2c\xf9\xe8\x96'
                488     CALL                            1
                496     CALL                            1
                504     POP_TOP                         
                506     LOAD_GLOBAL                     3: NULL + StopProgram
                516     CALL                            0
                524     RAISE_VARARGS                   1
                526     LOAD_FAST                       0: data
                528     LOAD_CONST                      4: 'Settings'
                530     BINARY_SUBSCR                   
                534     LOAD_ATTR                       7: get
                554     PUSH_NULL                       
                556     LOAD_CONST                      1: '__pyarmor_assert_13389__'
                558     LOAD_CONST                      11: 'thread_rules'   # b'\x81\xf6\x10\x016\xfb\xba\xed\t\xef\x01\xc5\x7f'
                560     CALL                            1
                568     CALL                            1
                576     LOAD_CONST                      12: True
                578     COMPARE_OP                      40 (==)
                582     POP_JUMP_IF_FALSE               36 (to 656)
                584     LOAD_GLOBAL                     13: NULL + int
                594     LOAD_FAST                       0: data
                596     LOAD_CONST                      4: 'Settings'
                598     BINARY_SUBSCR                   
                602     LOAD_ATTR                       7: get
                622     PUSH_NULL                       
                624     LOAD_CONST                      1: '__pyarmor_assert_13389__'
                626     LOAD_CONST                      13: 'thread_count'   # b'\x81\xf6\x10\x016\xfb\xba\xed\x18\xf5\x18\xcex'
                628     CALL                            1
                636     CALL                            1
                644     CALL                            1
                652     STORE_FAST                      8: _var_var_6
                654     JUMP_FORWARD                    11 (to 678)
                656     LOAD_FAST                       1: config
                658     PUSH_NULL                       
                660     LOAD_CONST                      1: '__pyarmor_assert_13389__'
                662     LOAD_CONST                      13: 'thread_count'   # b'\x81\xf6\x10\x016\xfb\xba\xed\x18\xf5\x18\xcex'
                664     CALL                            1
                672     BINARY_SUBSCR                   
                676     STORE_FAST                      8: _var_var_6
                678     LOAD_GLOBAL                     22: datetime
                688     LOAD_ATTR                       22: datetime
                708     LOAD_ATTR                       25: now
                728     CALL                            0
                736     LOAD_ATTR                       27: strftime
                756     PUSH_NULL                       
                758     LOAD_CONST                      1: '__pyarmor_assert_13389__'
                760     LOAD_CONST                      14: '%y-%m-%d_%H-%M-%S'   # b'\x81\xa7\x01^v\xf7\xf3\x97\x1f\xc5H\xe8!\xa9\xd5\xc8Jn'
                762     CALL                            1
                770     CALL                            1
                778     STORE_FAST                      9: _var_var_7
                780     LOAD_GLOBAL                     29: NULL + db_statistic
                790     PUSH_NULL                       
                792     LOAD_CONST                      1: '__pyarmor_assert_13389__'
                794     LOAD_CONST                      15: 'additives/contacts_invite/'   # b'\x81\xe3\x1c\x17:\xee\xb7\xc4\x1e\xe9B\xc3c\xe2\xec\x84\x0cI\xa8\x98\xa3\xc5X\xc5\x11j\xec'
                796     CALL                            1
                804     LOAD_FAST                       9: _var_var_7
                806     FORMAT_VALUE                    0 (FVC_NONE)
                808     PUSH_NULL                       
                810     LOAD_CONST                      1: '__pyarmor_assert_13389__'
                812     LOAD_CONST                      16: '_invite.db'   # b'\x81\xdd\x11\x1d%\xf3\xaa\xd7U\xfe\x0f'
                814     CALL                            1
                822     BUILD_STRING                    3
                824     CALL                            1
                832     LOAD_ATTR                       31: create
                852     CALL                            0
                860     STORE_FAST                      10: _var_var_8
                862     LOAD_GLOBAL                     17: NULL + eel
                872     LOAD_ATTR                       32: WriteResult
                892     PUSH_NULL                       
                894     LOAD_CONST                      1: '__pyarmor_assert_13389__'
                896     LOAD_CONST                      17: 'Statistic'   # b"\x81\xd1\x0c\x12'\xf3\xad\xc6\x12\xf9"
                898     CALL                            1
                906     PUSH_NULL                       
                908     LOAD_CONST                      1: '__pyarmor_assert_13389__'
                910     LOAD_CONST                      18: 'contacts_invite'   # b"\x81\xe1\x17\x1d'\xfb\xbd\xc6\x08\xc5\x04\xcez\xe5\xec\x80"
                912     CALL                            1
                920     LOAD_FAST                       9: _var_var_7
                922     FORMAT_VALUE                    0 (FVC_NONE)
                924     PUSH_NULL                       
                926     LOAD_CONST                      1: '__pyarmor_assert_13389__'
                928     LOAD_CONST                      16: '_invite.db'   # b'\x81\xdd\x11\x1d%\xf3\xaa\xd7U\xfe\x0f'
                930     CALL                            1
                938     BUILD_STRING                    2
                940     CALL                            3
                948     POP_TOP                         
                950     LOAD_GLOBAL                     35: NULL + set_task_manager
                960     LOAD_FAST                       2: pid
                962     LOAD_FAST                       6: _var_var_4
                964     LOAD_FAST                       0: data
                966     LOAD_CONST                      19: 'stuff'
                968     BINARY_SUBSCR                   
                972     KW_NAMES                        20: ('accounts', 'name')
                974     CALL                            3
                982     POP_TOP                         
                984     LOAD_GLOBAL                     36: concurrent
                994     LOAD_ATTR                       38: futures
                1014    LOAD_ATTR                       41: ThreadPoolExecutor
                1034    LOAD_FAST                       8: _var_var_6
                1036    KW_NAMES                        21: ('max_workers',)
                1038    CALL                            1
                1046    BEFORE_WITH                     
                1048    STORE_FAST                      11: _var_var_9
                1050    BUILD_LIST                      0
                1052    STORE_FAST                      12: _var_var_10
                1054    LOAD_GLOBAL                     15: NULL + len
                1064    LOAD_FAST                       6: _var_var_4
                1066    CALL                            1
                1074    STORE_FAST                      13: _var_var_11
                1076    LOAD_FAST                       8: _var_var_6
                1078    STORE_FAST                      14: _var_var_12
                1080    LOAD_FAST                       13: _var_var_11
                1082    STORE_FAST                      15: _var_var_13
                1084    LOAD_CONST                      9: 0
                1086    STORE_FAST                      16: _var_var_14
                1088    LOAD_CONST                      9: 0
                1090    STORE_FAST                      17: _var_var_15
                1092    LOAD_GLOBAL                     17: NULL + eel
                1102    LOAD_ATTR                       42: StreamStat
                1122    LOAD_GLOBAL                     45: NULL + json
                1132    LOAD_ATTR                       46: dumps
                1152    LOAD_CONST                      22: 'st_task'
                1154    LOAD_FAST                       13: _var_var_11
                1156    PUSH_NULL                       
                1158    LOAD_CONST                      1: '__pyarmor_assert_13389__'
                1160    LOAD_CONST                      23: 'st_stream'   # b'\x81\xf1\x0c, \xee\xac\xd7\x1a\xf7'
                1162    CALL                            1
                1170    LOAD_FAST                       14: _var_var_12
                1172    LOAD_CONST                      24: 'st_wait'
                1174    LOAD_FAST                       15: _var_var_13
                1176    LOAD_CONST                      25: 'st_done'
                1178    LOAD_FAST                       16: _var_var_14
                1180    BUILD_MAP                       4
                1182    CALL                            1
                1190    CALL                            1
                1198    POP_TOP                         
                1200    LOAD_FAST                       6: _var_var_4
                1202    GET_ITER                        
                1204    FOR_ITER                        94 (to 1394)
                1208    STORE_FAST                      18: _var_var_16
                1210    LOAD_GLOBAL                     15: NULL + len
                1220    LOAD_FAST                       7: _var_var_5
                1222    CALL                            1
                1230    LOAD_CONST                      7: 1
                1232    COMPARE_OP                      68 (>)
                1236    POP_JUMP_IF_FALSE               30 (to 1298)
                1238    LOAD_FAST                       17: _var_var_15
                1240    LOAD_GLOBAL                     15: NULL + len
                1250    LOAD_FAST                       7: _var_var_5
                1252    CALL                            1
                1260    LOAD_CONST                      7: 1
                1262    BINARY_OP                       10 (-)
                1266    COMPARE_OP                      68 (>)
                1270    POP_JUMP_IF_FALSE               2 (to 1276)
                1272    LOAD_CONST                      9: 0
                1274    STORE_FAST                      17: _var_var_15
                1276    LOAD_FAST                       7: _var_var_5
                1278    LOAD_FAST                       17: _var_var_15
                1280    BINARY_SUBSCR                   
                1284    STORE_FAST                      19: _var_var_17
                1286    LOAD_FAST                       17: _var_var_15
                1288    LOAD_CONST                      7: 1
                1290    BINARY_OP                       13 (+=)
                1294    STORE_FAST                      17: _var_var_15
                1296    JUMP_FORWARD                    5 (to 1308)
                1298    LOAD_FAST                       7: _var_var_5
                1300    LOAD_CONST                      9: 0
                1302    BINARY_SUBSCR                   
                1306    STORE_FAST                      19: _var_var_17
                1308    LOAD_FAST                       12: _var_var_10
                1310    LOAD_ATTR                       49: append
                1330    LOAD_FAST                       11: _var_var_9
                1332    LOAD_ATTR                       51: submit
                1352    LOAD_GLOBAL                     52: worker
                1362    LOAD_FAST                       19: _var_var_17
                1364    LOAD_FAST                       18: _var_var_16
                1366    LOAD_FAST                       1: config
                1368    LOAD_FAST                       3: proxy
                1370    LOAD_FAST                       0: data
                1372    LOAD_FAST                       10: _var_var_8
                1374    LOAD_FAST                       4: stop_thread
                1376    CALL                            8
                1384    CALL                            1
                1392    POP_TOP                         
                1394    JUMP_BACKWARD                   96 (to 1204)
                1396    END_FOR                         
                1398    LOAD_GLOBAL                     36: concurrent
                1408    LOAD_ATTR                       38: futures
                1428    LOAD_ATTR                       55: as_completed
                1448    LOAD_FAST                       12: _var_var_10
                1450    CALL                            1
                1458    GET_ITER                        
                1460    FOR_ITER                        66 (to 1594)
                1464    STORE_FAST                      20: _var_var_18
                1466    LOAD_FAST                       16: _var_var_14
                1468    LOAD_CONST                      7: 1
                1470    BINARY_OP                       13 (+=)
                1474    STORE_FAST                      16: _var_var_14
                1476    LOAD_FAST                       15: _var_var_13
                1478    LOAD_CONST                      7: 1
                1480    BINARY_OP                       23 (-=)
                1484    STORE_FAST                      15: _var_var_13
                1486    LOAD_GLOBAL                     17: NULL + eel
                1496    LOAD_ATTR                       42: StreamStat
                1516    LOAD_GLOBAL                     45: NULL + json
                1526    LOAD_ATTR                       46: dumps
                1546    LOAD_CONST                      22: 'st_task'
                1548    LOAD_FAST                       13: _var_var_11
                1550    PUSH_NULL                       
                1552    LOAD_CONST                      1: '__pyarmor_assert_13389__'
                1554    LOAD_CONST                      23: 'st_stream'   # b'\x81\xf1\x0c, \xee\xac\xd7\x1a\xf7'
                1556    CALL                            1
                1564    LOAD_FAST                       14: _var_var_12
                1566    LOAD_CONST                      24: 'st_wait'
                1568    LOAD_FAST                       15: _var_var_13
                1570    LOAD_CONST                      25: 'st_done'
                1572    LOAD_FAST                       16: _var_var_14
                1574    BUILD_MAP                       4
                1576    CALL                            1
                1584    CALL                            1
                1592    POP_TOP                         
                1594    JUMP_BACKWARD                   68 (to 1460)
                1596    END_FOR                         
                1598    DELETE_FAST                     12: _var_var_10
                1600    DELETE_FAST                     0: data
                1602    LOAD_CONST                      0: None
                1604    LOAD_CONST                      0: None
                1606    LOAD_CONST                      0: None
                1608    CALL                            2
                1616    POP_TOP                         
                1618    LOAD_GLOBAL                     61: NULL + del_task_manager
                1628    LOAD_FAST                       2: pid
                1630    CALL                            1
                1638    POP_TOP                         
                1640    LOAD_GLOBAL                     63: NULL + StopDetect
                1650    LOAD_FAST                       4: stop_thread
                1652    CALL                            1
                1660    POP_TOP                         
                1662    NOP                             
                1664    LOAD_CONST                      27: 'Done'
                1666    NOP                             
                1668    NOP                             
                1670    NOP                             
                1672    JUMP_FORWARD                    117 (to 1908)
                1680    POP_TOP                         
                1682    RETURN_CONST                    27: 'Done'
                1684    PUSH_EXC_INFO                   
                1686    WITH_EXCEPT_START               
                1688    POP_JUMP_IF_TRUE                1 (to 1692)
                1690    RERAISE                         2
                1692    POP_TOP                         
                1694    POP_EXCEPT                      
                1696    POP_TOP                         
                1698    POP_TOP                         
                1700    JUMP_BACKWARD                   42 (to 1618)
                1702    COPY                            3
                1704    POP_EXCEPT                      
                1706    RERAISE                         1
                1708    PUSH_EXC_INFO                   
                1710    LOAD_GLOBAL                     2: StopProgram
                1720    CHECK_EXC_MATCH                 
                1722    POP_JUMP_IF_FALSE               3 (to 1730)
                1724    POP_TOP                         
                1726    POP_EXCEPT                      
                1728    JUMP_BACKWARD                   56 (to 1618)
                1730    LOAD_GLOBAL                     56: BaseException
                1740    CHECK_EXC_MATCH                 
                1742    POP_JUMP_IF_FALSE               26 (to 1796)
                1744    STORE_FAST                      21: _var_var_3
                1746    PUSH_NULL                       
                1748    LOAD_GLOBAL                     59: NULL + logging
                1758    LOAD_FAST                       21: _var_var_3
                1760    CALL                            1
                1768    CALL                            0
                1776    POP_TOP                         
                1778    POP_EXCEPT                      
                1780    LOAD_CONST                      0: None
                1782    STORE_FAST                      21: _var_var_3
                1784    DELETE_FAST                     21: _var_var_3
                1786    JUMP_BACKWARD                   85 (to 1618)
                1788    LOAD_CONST                      0: None
                1790    STORE_FAST                      21: _var_var_3
                1792    DELETE_FAST                     21: _var_var_3
                1794    RERAISE                         1
                1796    RERAISE                         0
                1798    COPY                            3
                1800    POP_EXCEPT                      
                1802    RERAISE                         1
                1804    PUSH_EXC_INFO                   
                1806    LOAD_GLOBAL                     61: NULL + del_task_manager
                1816    LOAD_FAST                       2: pid
                1818    CALL                            1
                1826    POP_TOP                         
                1828    LOAD_GLOBAL                     63: NULL + StopDetect
                1838    LOAD_FAST                       4: stop_thread
                1840    CALL                            1
                1848    POP_TOP                         
                1850    POP_TOP                         
                1852    POP_EXCEPT                      
                1854    LOAD_CONST                      27: 'Done'
                1856    NOP                             
                1858    NOP                             
                1860    NOP                             
                1862    JUMP_FORWARD                    22 (to 1908)
                1870    POP_TOP                         
                1872    RETURN_CONST                    27: 'Done'
                1874    COPY                            3
                1876    POP_EXCEPT                      
                1878    RERAISE                         1
                1880    PUSH_EXC_INFO                   
                1882    PUSH_NULL                       
                1884    LOAD_CONST                      26: '__pyarmor_exit_13391__'
                1886    NOP                             
                1888    LOAD_CONST                      3: b'<COAddr>\x05\x00\x00\x1a>\x07\x00\x00\x00\x00\x00\x00\x00\x00\x00\x00\x00\x00\x00\x00'
                1890    CALL                            1
                1898    POP_TOP                         
                1900    RERAISE                         0
                1902    COPY                            3
                1904    POP_EXCEPT                      
                1906    RERAISE                         1
                1908    PUSH_NULL                       
                1910    LOAD_CONST                      26: '__pyarmor_exit_13391__'
                1912    LOAD_CONST                      3: b'<COAddr>\x05\x00\x00\x1a>\x07\x00\x00\x00\x00\x00\x00\x00\x00\x00\x00\x00\x00\x00\x00'
                1914    BUILD_TUPLE                     1
                1916    CALL_FUNCTION_EX                0
                1918    POP_TOP                         
                1920    RETURN_VALUE                    
            [Exception Table]
                30 to 1048 -> 1708 [0] 
                1048 to 1602 -> 1684 [1] lasti
                1602 to 1618 -> 1708 [0] 
                1618 to 1662 -> 1880 [0] 
                1684 to 1694 -> 1702 [3] lasti
                1694 to 1708 -> 1708 [0] 
                1708 to 1726 -> 1798 [1] lasti
                1726 to 1730 -> 1804 [0] 
                1730 to 1746 -> 1798 [1] lasti
                1746 to 1778 -> 1788 [1] lasti
                1778 to 1788 -> 1804 [0] 
                1788 to 1798 -> 1798 [1] lasti
                1798 to 1804 -> 1804 [0] 
                1804 to 1852 -> 1874 [1] lasti
                1852 to 1854 -> 1880 [0] 
                1874 to 1880 -> 1880 [0] 
                1880 to 1902 -> 1902 [1] lasti
        [Code]
            File Name: <frozen program.modules.Contacts_invite>
            Object Name: worker
            Qualified Name: worker
            Arg Count: 7
            Pos Only Arg Count: 0
            KW Only Arg Count: 0
            Stack Size: 11
            Flags: 0x20000003 (CO_OPTIMIZED | CO_NEWLOCALS | CO_PYARMOR_OBFUSCATED)
            [Names]
                'Thread_wait'
                'account_works'
                'Lang'
                'Disconnect'
                'tg_links'
                '_correct'
                'int'
                'get'
                'random'
                'randint'
                'tg_group'
                'go_to'
                'Logs'
                'PrintLog'
                'functions'
                'contacts'
                'GetContactsRequest'
                'len'
                'users'
                'mutual_contact'
                'is_set'
                'StopProgram'
                'DelayOnline'
                'tdlib'
                'channels'
                'InviteToChannel_tdlib_Request'
                'types'
                'InputUser'
                'id'
                'access_hash'
                'InviteToChannelRequest'
                'hasattr'
                'missing_invitees'
                'Exception'
                'type'
                '__name__'
                'seconds'
                'db_statistic'
                'insert'
                'username'
                'first_name'
                'last_name'
                'DeleteContactsRequest'
                'go_out'
                'BaseException'
                'logging'
            [Locals+Names]
                'group_dest_link'
                'account'
                'config'
                'proxy'
                'data'
                'statistic'
                'stop_thread'
                '__assert_armored__'
                '_var_var_19'
                '_var_var_20'
                '_var_var_21'
                '_var_var_22'
                '_var_var_23'
                '_var_var_24'
                '_var_var_25'
                '_var_var_26'
                '_var_var_27'
                '_var_var_28'
                '_var_var_29'
                '_var_var_30'
                '_var_var_31'
                '_var_var_32'
                '_var_var_33'
                '_var_var_34'
                '_var_var_35'
                '_var_var_36'
                '_var_var_37'
                '_var_var_3'
                '_var_var_38'
            [Constants]
                None
                '__pyarmor_assert_13392__'
                '__pyarmor_enter_13393__'
                b'<COAddr>\x05\x00\x00\x1a\x94\x12\x00\x00\x00\x00\x00\x00\x00\x00\x00\x00\x00\x00\x00\x00'
                'Contacts_invite'   # b"\x81\xc1\x17\x1d'\xfb\xbd\xc6\x08\xc5\x04\xcez\xe5\xec\x80"
                (
                    'module'
                )
                False
                'Error'
                (
                    'account'
                    'status'
                )
                'done'
                '__pyarmor_exit_13394__'
                'Settings'
                'wait_from'   # b"\x81\xf5\x19\x1a'\xc5\xb8\xc0\x14\xf7"
                'wait_to'
                'leave_chat'   # b'\x81\xee\x1d\x12%\xff\x81\xd1\x13\xfb\x19'
                'max_flood_wait'   # b'\x81\xef\x19\x0b\x0c\xfc\xb2\xdd\x14\xfe2\xd7m\xe5\xec'
                'delete_contact'   # b'\x81\xe6\x1d\x1f6\xee\xbb\xed\x18\xf5\x03\xd4m\xef\xec'
                'only_mutual'   # b'\x81\xed\x16\x1f*\xc5\xb3\xc7\x0f\xef\x0c\xcc'
                'kol_users_from'   # b'\x81\xe9\x17\x1f\x0c\xef\xad\xd7\t\xe92\xc6~\xe3\xf5'
                'kol_users_to'   # b'\x81\xe9\x17\x1f\x0c\xef\xad\xd7\t\xe92\xd4c'
                'peer_flood'   # b'\x81\xf2\x1d\x16!\xc5\xb8\xde\x14\xf5\t'
                0
                (
                    'config'
                    'client'
                    'account'
                    'group_link'
                    'max_flood_wait'
                    'lang'
                    'stop_thread'
                )
                'contacts_get'   # b"\x81\xe1\x17\x1d'\xfb\xbd\xc6\x08\xc5\n\xc5x"
                (
                    'config'
                    'account'
                    'message'
                )
                (
                    'hash'
                )
                'contacts_send_count'   # b"\x81\xe1\x17\x1d'\xfb\xbd\xc6\x08\xc5\x1e\xc5b\xe8\xc7\x86\x00H\xb5\xb3"
                (
                    'config'
                    'account'
                    'message'
                    'param'
                )
                'Done'
                1
                (
                    'user_id'
                    'access_hash'
                )
                (
                    'channel'
                    'users'
                )
                'missing_invitees'   # b'\x81\xef\x11\x00 \xf3\xb0\xd5$\xf3\x03\xd6e\xf8\xfd\x80\x1c'
                'NotInvited'   # b'\x81\xcc\x17\x07\x1a\xf4\xa8\xdb\x0f\xff\t'
                'FloodWaitError'   # b'\x81\xc4\x14\x1c<\xfe\x89\xd3\x12\xee(\xd2~\xe3\xea'
                'User: '
                ' Status: '   # b'\x81\xa2+\x072\xee\xab\xc1A\xba'
                (
                    'account'
                    'group_id'
                    'group_link'
                    'user_id'
                    'username'
                    'first_name'
                    'last_name'
                    'invite_status'
                )
                True
                (
                    'id'
                )
                'contacts_delete_send'   # b"\x81\xe1\x17\x1d'\xfb\xbd\xc6\x08\xc5\t\xc5`\xe9\xec\x800N\xbe\xa9\xae"
                'PeerFloodError'   # b'\x81\xd2\x1d\x16!\xdc\xb2\xdd\x14\xfe(\xd2~\xe3\xea'
                'restriction_detected'   # b"\x81\xf0\x1d\x00'\xe8\xb7\xd1\x0f\xf3\x02\xceS\xe8\xfd\x91\n^\xaf\xa2\xae"
                'account_spamblock_stop'   # b'\x81\xe3\x1b\x10<\xef\xb0\xc6$\xe9\x1d\xc1a\xee\xf4\x8a\x0cV\x84\xb4\xbe\xc4^'
                'ConnectionError'   # b'\x81\xc1\x17\x1d=\xff\xbd\xc6\x12\xf5\x03\xe5~\xfe\xf7\x97'
                'TimeoutError'   # b'\x81\xd6\x11\x1e6\xf5\xab\xc6>\xe8\x1f\xcf~'
                'error_reconnecting'   # b'\x81\xe7\n\x01<\xe8\x81\xc0\x1e\xf9\x02\xceb\xe9\xfb\x91\x06S\xbc'
                2
                'UserBannedInChannelError'   # b'\x81\xd7\x0b\x16!\xd8\xbf\xdc\x15\xff\t\xe9b\xcf\xf0\x84\x01S\xbe\xab\x8f\xd9\\\xc3\x17'
                'ChatWriteForbiddenError'   # b"\x81\xc1\x10\x12'\xcd\xac\xdb\x0f\xff+\xcf~\xee\xf1\x81\x0bX\xb5\x82\xb8\xd9A\xde"
                'ChannelPrivateError'   # b'\x81\xc1\x10\x12=\xf4\xbb\xde+\xe8\x04\xd6m\xf8\xfd\xa0\x1dO\xb4\xb5'
                'account_shadow_filter'   # b'\x81\xe3\x1b\x10<\xef\xb0\xc6$\xe9\x05\xc1h\xe3\xef\xba\tT\xb7\xb3\xaf\xd9'
                'UnauthorizedError'   # b'\x81\xd7\x16\x12&\xee\xb6\xdd\t\xf3\x17\xc5h\xc9\xea\x97\x00O'
                'UserDeactivatedBanError'   # b'\x81\xd7\x0b\x16!\xde\xbb\xd3\x18\xee\x04\xd6m\xf8\xfd\x81-\\\xb5\x82\xb8\xd9A\xde'
                'AuthKeyUnregisteredError'   # b'\x81\xc3\r\x07;\xd1\xbb\xcb.\xf4\x1f\xc5k\xe5\xeb\x91\nO\xbe\xa3\x8f\xd9\\\xc3\x17'
                'account_banned_exit'   # b'\x81\xe3\x1b\x10<\xef\xb0\xc6$\xf8\x0c\xceb\xe9\xfc\xba\nE\xb2\xb3'
                'AuthKeyDuplicatedError'   # b'\x81\xc3\r\x07;\xd1\xbb\xcb?\xef\x1d\xcce\xef\xf9\x91\nY\x9e\xb5\xb8\xc4\\'
                'duplicate_session_disconnect'   # b'\x81\xe6\r\x03?\xf3\xbd\xd3\x0f\xff2\xd3i\xff\xeb\x8c\x00S\x84\xa3\xa3\xd8M\xc3\x0ba\xa6_\x14'
                'TypeNotFoundError'   # b'\x81\xd6\x01\x036\xd4\xb1\xc6=\xf5\x18\xceh\xc9\xea\x97\x00O'
                'error_constructor'   # b'\x81\xe7\n\x01<\xe8\x81\xd1\x14\xf4\x1e\xd4~\xf9\xfb\x91\x00O'
                'shutting_down_my_account'   # b"\x81\xf1\x10\x06'\xee\xb7\xdc\x1c\xc5\t\xcf{\xe2\xc7\x88\x16b\xba\xa4\xa9\xc4[\xc2\x11"
                'algorithm_running'   # b'\x81\xe3\x14\x14<\xe8\xb7\xc6\x13\xf72\xd2y\xe2\xf6\x8c\x01Z'
                5
                10
                'flood_wait_more'   # b'\x81\xe4\x14\x1c<\xfe\x81\xc5\x1a\xf3\x19\xffa\xe3\xea\x80'
                'work_stopped'   # b'\x81\xf5\x17\x018\xc5\xad\xc6\x14\xea\x1d\xc5h'
                'flood_wait_bypass'   # b'\x81\xe4\x14\x1c<\xfe\x81\xc5\x1a\xf3\x19\xffn\xf5\xe8\x84\x1cN'
                'contacts_send_count_req'   # b"\x81\xe1\x17\x1d'\xfb\xbd\xc6\x08\xc5\x1e\xc5b\xe8\xc7\x86\x00H\xb5\xb3\x95\xd9K\xdd"
                (
                    'config'
                    'account'
                    'message'
                    'end'
                )
                'contacts_send_count_done'   # b"\x81\xe1\x17\x1d'\xfb\xbd\xc6\x08\xc5\x1e\xc5b\xe8\xc7\x86\x00H\xb5\xb3\x95\xcfA\xc2\x00"
                'exit_groups_on_activated'   # b"\x81\xe7\x00\x1a'\xc5\xb9\xc0\x14\xef\x1d\xd3S\xe3\xf6\xba\x0e^\xaf\xae\xbc\xcaZ\xc9\x01"
                'leaving_group'   # b'\x81\xee\x1d\x12%\xf3\xb0\xd5$\xfd\x1f\xcfy\xfc'
                (
                    'config'
                    'client'
                    'account'
                    'max_flood_wait'
                    'lang'
                    'stop_thread'
                )
                (
                    'entity'
                )
            [Disassembly]
                0       NOP                             
                2       NOP                             
                4       PUSH_NULL                       
                6       LOAD_CONST                      2: '__pyarmor_enter_13393__'
                8       LOAD_CONST                      3: b'<COAddr>\x05\x00\x00\x1a\x94\x12\x00\x00\x00\x00\x00\x00\x00\x00\x00\x00\x00\x00\x00\x00'
                10      BUILD_TUPLE                     1
                12      CALL_FUNCTION_EX                0
                14      POP_TOP                         
                16      RESUME                          0
                18      NOP                             
                20      NOP                             
                22      NOP                             
                24      NOP                             
                26      NOP                             
                28      NOP                             
                30      LOAD_GLOBAL                     1: NULL + Thread_wait
                40      LOAD_FAST                       4: data
                42      LOAD_FAST                       2: config
                44      LOAD_FAST                       6: stop_thread
                46      CALL                            3
                54      POP_TOP                         
                56      LOAD_GLOBAL                     3: NULL + account_works
                66      LOAD_FAST                       2: config
                68      LOAD_GLOBAL                     4: Lang
                78      LOAD_FAST                       3: proxy
                80      LOAD_FAST                       1: account
                82      LOAD_FAST                       6: stop_thread
                84      PUSH_NULL                       
                86      LOAD_CONST                      1: '__pyarmor_assert_13392__'
                88      LOAD_CONST                      4: 'Contacts_invite'   # b"\x81\xc1\x17\x1d'\xfb\xbd\xc6\x08\xc5\x04\xcez\xe5\xec\x80"
                90      CALL                            1
                98      KW_NAMES                        5: ('module',)
                100     CALL                            6
                108     STORE_FAST                      8: _var_var_19
                110     LOAD_FAST                       8: _var_var_19
                112     LOAD_CONST                      6: False
                114     COMPARE_OP                      40 (==)
                118     POP_JUMP_IF_FALSE               31 (to 182)
                120     LOAD_FAST                       1: account
                122     LOAD_CONST                      7: 'Error'
                124     LOAD_CONST                      8: ('account', 'status')
                126     BUILD_CONST_KEY_MAP             2
                128     LOAD_GLOBAL                     7: NULL + Disconnect
                138     LOAD_FAST                       8: _var_var_19
                140     CALL                            1
                148     POP_TOP                         
                150     LOAD_FAST                       1: account
                152     LOAD_CONST                      9: 'done'
                154     LOAD_CONST                      8: ('account', 'status')
                156     BUILD_CONST_KEY_MAP             2
                158     SWAP                            2
                160     POP_TOP                         
                162     NOP                             
                164     NOP                             
                166     JUMP_FORWARD                    2320 (to 4810)
                170     CALL                            1
                178     POP_TOP                         
                180     RETURN_VALUE                    
                182     LOAD_GLOBAL                     9: NULL + tg_links
                192     CALL                            0
                200     LOAD_ATTR                       11: _correct
                220     LOAD_FAST                       0: group_dest_link
                222     CALL                            1
                230     STORE_FAST                      0: group_dest_link
                232     LOAD_GLOBAL                     13: NULL + int
                242     LOAD_FAST                       4: data
                244     LOAD_CONST                      11: 'Settings'
                246     BINARY_SUBSCR                   
                250     LOAD_ATTR                       15: get
                270     PUSH_NULL                       
                272     LOAD_CONST                      1: '__pyarmor_assert_13392__'
                274     LOAD_CONST                      12: 'wait_from'   # b"\x81\xf5\x19\x1a'\xc5\xb8\xc0\x14\xf7"
                276     CALL                            1
                284     CALL                            1
                292     CALL                            1
                300     STORE_FAST                      9: _var_var_20
                302     LOAD_GLOBAL                     13: NULL + int
                312     LOAD_FAST                       4: data
                314     LOAD_CONST                      11: 'Settings'
                316     BINARY_SUBSCR                   
                320     LOAD_ATTR                       15: get
                340     LOAD_CONST                      13: 'wait_to'
                342     CALL                            1
                350     CALL                            1
                358     STORE_FAST                      10: _var_var_21
                360     LOAD_FAST                       4: data
                362     LOAD_CONST                      11: 'Settings'
                364     BINARY_SUBSCR                   
                368     LOAD_ATTR                       15: get
                388     PUSH_NULL                       
                390     LOAD_CONST                      1: '__pyarmor_assert_13392__'
                392     LOAD_CONST                      14: 'leave_chat'   # b'\x81\xee\x1d\x12%\xff\x81\xd1\x13\xfb\x19'
                394     CALL                            1
                402     CALL                            1
                410     STORE_FAST                      11: _var_var_22
                412     LOAD_GLOBAL                     13: NULL + int
                422     LOAD_FAST                       4: data
                424     LOAD_CONST                      11: 'Settings'
                426     BINARY_SUBSCR                   
                430     LOAD_ATTR                       15: get
                450     PUSH_NULL                       
                452     LOAD_CONST                      1: '__pyarmor_assert_13392__'
                454     LOAD_CONST                      15: 'max_flood_wait'   # b'\x81\xef\x19\x0b\x0c\xfc\xb2\xdd\x14\xfe2\xd7m\xe5\xec'
                456     CALL                            1
                464     CALL                            1
                472     CALL                            1
                480     STORE_FAST                      12: _var_var_23
                482     LOAD_FAST                       4: data
                484     LOAD_CONST                      11: 'Settings'
                486     BINARY_SUBSCR                   
                490     LOAD_ATTR                       15: get
                510     PUSH_NULL                       
                512     LOAD_CONST                      1: '__pyarmor_assert_13392__'
                514     LOAD_CONST                      16: 'delete_contact'   # b'\x81\xe6\x1d\x1f6\xee\xbb\xed\x18\xf5\x03\xd4m\xef\xec'
                516     CALL                            1
                524     CALL                            1
                532     STORE_FAST                      13: _var_var_24
                534     LOAD_FAST                       4: data
                536     LOAD_CONST                      11: 'Settings'
                538     BINARY_SUBSCR                   
                542     LOAD_ATTR                       15: get
                562     PUSH_NULL                       
                564     LOAD_CONST                      1: '__pyarmor_assert_13392__'
                566     LOAD_CONST                      17: 'only_mutual'   # b'\x81\xed\x16\x1f*\xc5\xb3\xc7\x0f\xef\x0c\xcc'
                568     CALL                            1
                576     CALL                            1
                584     STORE_FAST                      14: _var_var_25
                586     LOAD_GLOBAL                     17: NULL + random
                596     LOAD_ATTR                       18: randint
                616     LOAD_GLOBAL                     13: NULL + int
                626     LOAD_FAST                       4: data
                628     LOAD_CONST                      11: 'Settings'
                630     BINARY_SUBSCR                   
                634     LOAD_ATTR                       15: get
                654     PUSH_NULL                       
                656     LOAD_CONST                      1: '__pyarmor_assert_13392__'
                658     LOAD_CONST                      18: 'kol_users_from'   # b'\x81\xe9\x17\x1f\x0c\xef\xad\xd7\t\xe92\xc6~\xe3\xf5'
                660     CALL                            1
                668     CALL                            1
                676     CALL                            1
                684     LOAD_GLOBAL                     13: NULL + int
                694     LOAD_FAST                       4: data
                696     LOAD_CONST                      11: 'Settings'
                698     BINARY_SUBSCR                   
                702     LOAD_ATTR                       15: get
                722     PUSH_NULL                       
                724     LOAD_CONST                      1: '__pyarmor_assert_13392__'
                726     LOAD_CONST                      19: 'kol_users_to'   # b'\x81\xe9\x17\x1f\x0c\xef\xad\xd7\t\xe92\xd4c'
                728     CALL                            1
                736     CALL                            1
                744     CALL                            1
                752     CALL                            2
                760     STORE_FAST                      15: _var_var_26
                762     LOAD_FAST                       2: config
                764     PUSH_NULL                       
                766     LOAD_CONST                      1: '__pyarmor_assert_13392__'
                768     LOAD_CONST                      20: 'peer_flood'   # b'\x81\xf2\x1d\x16!\xc5\xb8\xde\x14\xf5\t'
                770     CALL                            1
                778     BINARY_SUBSCR                   
                782     STORE_FAST                      16: _var_var_27
                784     LOAD_CONST                      21: 0
                786     STORE_FAST                      17: _var_var_28
                788     LOAD_CONST                      21: 0
                790     STORE_FAST                      18: _var_var_29
                792     LOAD_GLOBAL                     21: NULL + tg_group
                802     LOAD_FAST                       2: config
                804     LOAD_FAST                       8: _var_var_19
                806     LOAD_FAST                       1: account
                808     LOAD_FAST                       0: group_dest_link
                810     LOAD_FAST                       12: _var_var_23
                812     LOAD_GLOBAL                     4: Lang
                822     LOAD_FAST                       6: stop_thread
                824     KW_NAMES                        22: ('config', 'client', 'account', 'group_link', 'max_flood_wait', 'lang', 'stop_thread')
                826     CALL                            7
                834     LOAD_ATTR                       23: go_to
                854     CALL                            0
                862     STORE_FAST                      19: _var_var_30
                864     LOAD_FAST                       19: _var_var_30
                866     POP_JUMP_IF_NONE                11 (to 890)
                868     LOAD_FAST                       19: _var_var_30
                870     PUSH_NULL                       
                872     LOAD_CONST                      1: '__pyarmor_assert_13392__'
                874     LOAD_CONST                      15: 'max_flood_wait'   # b'\x81\xef\x19\x0b\x0c\xfc\xb2\xdd\x14\xfe2\xd7m\xe5\xec'
                876     CALL                            1
                884     COMPARE_OP                      40 (==)
                888     POP_JUMP_IF_FALSE               48 (to 986)
                890     LOAD_GLOBAL                     7: NULL + Disconnect
                900     LOAD_FAST                       8: _var_var_19
                902     CALL                            1
                910     POP_TOP                         
                912     LOAD_FAST                       1: account
                914     PUSH_NULL                       
                916     LOAD_CONST                      1: '__pyarmor_assert_13392__'
                918     LOAD_CONST                      15: 'max_flood_wait'   # b'\x81\xef\x19\x0b\x0c\xfc\xb2\xdd\x14\xfe2\xd7m\xe5\xec'
                920     CALL                            1
                928     LOAD_CONST                      8: ('account', 'status')
                930     BUILD_CONST_KEY_MAP             2
                932     LOAD_GLOBAL                     7: NULL + Disconnect
                942     LOAD_FAST                       8: _var_var_19
                944     CALL                            1
                952     POP_TOP                         
                954     LOAD_FAST                       1: account
                956     LOAD_CONST                      9: 'done'
                958     LOAD_CONST                      8: ('account', 'status')
                960     BUILD_CONST_KEY_MAP             2
                962     SWAP                            2
                964     POP_TOP                         
                966     NOP                             
                968     NOP                             
                970     JUMP_FORWARD                    1918 (to 4810)
                974     CALL                            1
                982     POP_TOP                         
                984     RETURN_VALUE                    
                986     LOAD_GLOBAL                     25: NULL + Logs
                996     LOAD_ATTR                       26: PrintLog
                1016    LOAD_FAST                       2: config
                1018    LOAD_FAST                       1: account
                1020    LOAD_GLOBAL                     4: Lang
                1030    PUSH_NULL                       
                1032    LOAD_CONST                      1: '__pyarmor_assert_13392__'
                1034    LOAD_CONST                      23: 'contacts_get'   # b"\x81\xe1\x17\x1d'\xfb\xbd\xc6\x08\xc5\n\xc5x"
                1036    CALL                            1
                1044    BINARY_SUBSCR                   
                1048    KW_NAMES                        24: ('config', 'account', 'message')
                1050    CALL                            3
                1058    POP_TOP                         
                1060    PUSH_NULL                       
                1062    LOAD_FAST                       8: _var_var_19
                1064    LOAD_GLOBAL                     28: functions
                1074    LOAD_ATTR                       30: contacts
                1094    LOAD_ATTR                       33: GetContactsRequest
                1114    LOAD_CONST                      21: 0
                1116    KW_NAMES                        25: ('hash',)
                1118    CALL                            1
                1126    CALL                            1
                1134    STORE_FAST                      20: _var_var_31
                1136    LOAD_GLOBAL                     25: NULL + Logs
                1146    LOAD_ATTR                       26: PrintLog
                1166    LOAD_FAST                       2: config
                1168    LOAD_FAST                       1: account
                1170    LOAD_GLOBAL                     4: Lang
                1180    PUSH_NULL                       
                1182    LOAD_CONST                      1: '__pyarmor_assert_13392__'
                1184    LOAD_CONST                      26: 'contacts_send_count'   # b"\x81\xe1\x17\x1d'\xfb\xbd\xc6\x08\xc5\x1e\xc5b\xe8\xc7\x86\x00H\xb5\xb3"
                1186    CALL                            1
                1194    BINARY_SUBSCR                   
                1198    LOAD_GLOBAL                     35: NULL + len
                1208    LOAD_FAST                       20: _var_var_31
                1210    LOAD_ATTR                       36: users
                1230    CALL                            1
                1238    KW_NAMES                        27: ('config', 'account', 'message', 'param')
                1240    CALL                            4
                1248    POP_TOP                         
                1250    LOAD_FAST                       20: _var_var_31
                1252    LOAD_ATTR                       36: users
                1272    STORE_FAST                      21: _var_var_32
                1274    LOAD_FAST                       21: _var_var_32
                1276    GET_ITER                        
                1278    FOR_ITER                        1319 (to 3920)
                1284    STORE_FAST                      22: _var_var_33
                1286    LOAD_FAST                       14: _var_var_25
                1288    POP_JUMP_IF_FALSE               13 (to 1316)
                1290    LOAD_FAST                       22: _var_var_33
                1292    LOAD_ATTR                       38: mutual_contact
                1312    POP_JUMP_IF_TRUE                1 (to 1316)
                1314    JUMP_BACKWARD                   19 (to 1278)
                1316    LOAD_CONST                      28: 'Done'
                1318    STORE_FAST                      23: _var_var_34
                1320    LOAD_CONST                      21: 0
                1322    STORE_FAST                      24: _var_var_35
                1324    LOAD_CONST                      6: False
                1326    STORE_FAST                      25: _var_var_36
                1328    NOP                             
                1330    LOAD_FAST                       6: stop_thread
                1332    LOAD_ATTR                       41: is_set
                1352    CALL                            0
                1360    POP_JUMP_IF_FALSE               10 (to 1382)
                1362    LOAD_GLOBAL                     43: NULL + StopProgram
                1372    CALL                            0
                1380    RAISE_VARARGS                   1
                1382    LOAD_GLOBAL                     45: NULL + DelayOnline
                1392    LOAD_FAST                       1: account
                1394    LOAD_FAST                       8: _var_var_19
                1396    LOAD_FAST                       9: _var_var_20
                1398    LOAD_FAST                       10: _var_var_21
                1400    LOAD_FAST                       6: stop_thread
                1402    CALL                            5
                1410    POP_TOP                         
                1412    LOAD_FAST                       17: _var_var_28
                1414    LOAD_CONST                      29: 1
                1416    BINARY_OP                       13 (+=)
                1420    STORE_FAST                      17: _var_var_28
                1422    LOAD_FAST                       8: _var_var_19
                1424    LOAD_ATTR                       46: tdlib
                1444    POP_JUMP_IF_FALSE               82 (to 1610)
                1446    PUSH_NULL                       
                1448    LOAD_FAST                       8: _var_var_19
                1450    LOAD_GLOBAL                     28: functions
                1460    LOAD_ATTR                       48: channels
                1480    LOAD_ATTR                       51: InviteToChannel_tdlib_Request
                1500    LOAD_FAST                       19: _var_var_30
                1502    LOAD_GLOBAL                     53: NULL + types
                1512    LOAD_ATTR                       54: InputUser
                1532    LOAD_FAST                       22: _var_var_33
                1534    LOAD_ATTR                       56: id
                1554    LOAD_FAST                       22: _var_var_33
                1556    LOAD_ATTR                       58: access_hash
                1576    KW_NAMES                        30: ('user_id', 'access_hash')
                1578    CALL                            2
                1586    BUILD_LIST                      1
                1588    KW_NAMES                        31: ('channel', 'users')
                1590    CALL                            2
                1598    CALL                            1
                1606    STORE_FAST                      26: _var_var_37
                1608    JUMP_FORWARD                    81 (to 1772)
                1610    PUSH_NULL                       
                1612    LOAD_FAST                       8: _var_var_19
                1614    LOAD_GLOBAL                     28: functions
                1624    LOAD_ATTR                       48: channels
                1644    LOAD_ATTR                       61: InviteToChannelRequest
                1664    LOAD_FAST                       19: _var_var_30
                1666    LOAD_GLOBAL                     53: NULL + types
                1676    LOAD_ATTR                       54: InputUser
                1696    LOAD_FAST                       22: _var_var_33
                1698    LOAD_ATTR                       56: id
                1718    LOAD_FAST                       22: _var_var_33
                1720    LOAD_ATTR                       58: access_hash
                1740    KW_NAMES                        30: ('user_id', 'access_hash')
                1742    CALL                            2
                1750    BUILD_LIST                      1
                1752    KW_NAMES                        31: ('channel', 'users')
                1754    CALL                            2
                1762    CALL                            1
                1770    STORE_FAST                      26: _var_var_37
                1772    LOAD_GLOBAL                     63: NULL + hasattr
                1782    LOAD_FAST                       26: _var_var_37
                1784    PUSH_NULL                       
                1786    LOAD_CONST                      1: '__pyarmor_assert_13392__'
                1788    LOAD_CONST                      32: 'missing_invitees'   # b'\x81\xef\x11\x00 \xf3\xb0\xd5$\xf3\x03\xd6e\xf8\xfd\x80\x1c'
                1790    CALL                            1
                1798    CALL                            2
                1806    POP_JUMP_IF_FALSE               32 (to 1872)
                1808    LOAD_GLOBAL                     35: NULL + len
                1818    LOAD_FAST                       26: _var_var_37
                1820    LOAD_ATTR                       64: missing_invitees
                1840    CALL                            1
                1848    LOAD_CONST                      29: 1
                1850    COMPARE_OP                      40 (==)
                1854    POP_JUMP_IF_FALSE               8 (to 1872)
                1856    PUSH_NULL                       
                1858    LOAD_CONST                      1: '__pyarmor_assert_13392__'
                1860    LOAD_CONST                      33: 'NotInvited'   # b'\x81\xcc\x17\x07\x1a\xf4\xa8\xdb\x0f\xff\t'
                1862    CALL                            1
                1870    STORE_FAST                      23: _var_var_34
                1872    LOAD_GLOBAL                     25: NULL + Logs
                1882    LOAD_ATTR                       26: PrintLog
                1902    LOAD_FAST                       2: config
                1904    LOAD_FAST                       1: account
                1906    LOAD_CONST                      35: 'User: '
                1908    LOAD_FAST                       22: _var_var_33
                1910    LOAD_ATTR                       56: id
                1930    FORMAT_VALUE                    0 (FVC_NONE)
                1932    PUSH_NULL                       
                1934    LOAD_CONST                      1: '__pyarmor_assert_13392__'
                1936    LOAD_CONST                      36: ' Status: '   # b'\x81\xa2+\x072\xee\xab\xc1A\xba'
                1938    CALL                            1
                1946    LOAD_FAST                       23: _var_var_34
                1948    FORMAT_VALUE                    0 (FVC_NONE)
                1950    BUILD_STRING                    4
                1952    KW_NAMES                        24: ('config', 'account', 'message')
                1954    CALL                            3
                1962    POP_TOP                         
                1964    LOAD_GLOBAL                     75: NULL + db_statistic
                1974    LOAD_FAST                       5: statistic
                1976    CALL                            1
                1984    LOAD_ATTR                       77: insert
                2004    LOAD_FAST                       1: account
                2006    LOAD_FAST                       19: _var_var_30
                2008    LOAD_ATTR                       56: id
                2028    LOAD_FAST                       0: group_dest_link
                2030    LOAD_FAST                       22: _var_var_33
                2032    LOAD_ATTR                       56: id
                2052    LOAD_FAST                       22: _var_var_33
                2054    LOAD_ATTR                       78: username
                2074    LOAD_FAST                       22: _var_var_33
                2076    LOAD_ATTR                       80: first_name
                2096    LOAD_FAST                       22: _var_var_33
                2098    LOAD_ATTR                       82: last_name
                2118    LOAD_FAST                       23: _var_var_34
                2120    KW_NAMES                        37: ('account', 'group_id', 'group_link', 'user_id', 'username', 'first_name', 'last_name', 'invite_status')
                2122    CALL                            8
                2130    POP_TOP                         
                2132    LOAD_FAST                       23: _var_var_34
                2134    LOAD_CONST                      28: 'Done'
                2136    COMPARE_OP                      40 (==)
                2140    POP_JUMP_IF_FALSE               5 (to 2152)
                2142    LOAD_FAST                       18: _var_var_29
                2144    LOAD_CONST                      29: 1
                2146    BINARY_OP                       13 (+=)
                2150    STORE_FAST                      18: _var_var_29
                2152    LOAD_FAST                       13: _var_var_24
                2154    LOAD_CONST                      38: True
                2156    COMPARE_OP                      40 (==)
                2160    POP_JUMP_IF_FALSE               82 (to 2326)
                2162    LOAD_FAST                       23: _var_var_34
                2164    LOAD_CONST                      28: 'Done'
                2166    COMPARE_OP                      40 (==)
                2170    POP_JUMP_IF_FALSE               77 (to 2326)
                2172    NOP                             
                2174    PUSH_NULL                       
                2176    LOAD_FAST                       8: _var_var_19
                2178    LOAD_GLOBAL                     28: functions
                2188    LOAD_ATTR                       30: contacts
                2208    LOAD_ATTR                       85: DeleteContactsRequest
                2228    LOAD_FAST                       22: _var_var_33
                2230    BUILD_LIST                      1
                2232    KW_NAMES                        39: ('id',)
                2234    CALL                            1
                2242    CALL                            1
                2250    POP_TOP                         
                2252    LOAD_GLOBAL                     25: NULL + Logs
                2262    LOAD_ATTR                       26: PrintLog
                2282    LOAD_FAST                       2: config
                2284    LOAD_FAST                       1: account
                2286    LOAD_GLOBAL                     4: Lang
                2296    PUSH_NULL                       
                2298    LOAD_CONST                      1: '__pyarmor_assert_13392__'
                2300    LOAD_CONST                      40: 'contacts_delete_send'   # b"\x81\xe1\x17\x1d'\xfb\xbd\xc6\x08\xc5\t\xc5`\xe9\xec\x800N\xbe\xa9\xae"
                2302    CALL                            1
                2310    BINARY_SUBSCR                   
                2314    KW_NAMES                        24: ('config', 'account', 'message')
                2316    CALL                            3
                2324    POP_TOP                         
                2326    LOAD_FAST                       23: _var_var_34
                2328    PUSH_NULL                       
                2330    LOAD_CONST                      1: '__pyarmor_assert_13392__'
                2332    LOAD_CONST                      41: 'PeerFloodError'   # b'\x81\xd2\x1d\x16!\xdc\xb2\xdd\x14\xfe(\xd2~\xe3\xea'
                2334    CALL                            1
                2342    COMPARE_OP                      40 (==)
                2346    POP_JUMP_IF_FALSE               17 (to 2382)
                2348    LOAD_FAST                       16: _var_var_27
                2350    LOAD_CONST                      21: 0
                2352    COMPARE_OP                      68 (>)
                2356    POP_JUMP_IF_FALSE               12 (to 2382)
                2358    LOAD_FAST                       16: _var_var_27
                2360    LOAD_CONST                      29: 1
                2362    BINARY_OP                       23 (-=)
                2366    STORE_FAST                      16: _var_var_27
                2368    LOAD_FAST                       15: _var_var_26
                2370    LOAD_CONST                      29: 1
                2372    BINARY_OP                       13 (+=)
                2376    STORE_FAST                      15: _var_var_26
                2378    LOAD_CONST                      6: False
                2380    STORE_FAST                      25: _var_var_36
                2382    LOAD_FAST                       23: _var_var_34
                2384    PUSH_NULL                       
                2386    LOAD_CONST                      1: '__pyarmor_assert_13392__'
                2388    LOAD_CONST                      41: 'PeerFloodError'   # b'\x81\xd2\x1d\x16!\xdc\xb2\xdd\x14\xfe(\xd2~\xe3\xea'
                2390    CALL                            1
                2398    COMPARE_OP                      40 (==)
                2402    POP_JUMP_IF_FALSE               81 (to 2566)
                2404    LOAD_FAST                       16: _var_var_27
                2406    LOAD_CONST                      21: 0
                2408    COMPARE_OP                      26 (<=)
                2412    POP_JUMP_IF_FALSE               76 (to 2566)
                2414    LOAD_GLOBAL                     25: NULL + Logs
                2424    LOAD_ATTR                       26: PrintLog
                2444    LOAD_FAST                       2: config
                2446    LOAD_FAST                       1: account
                2448    LOAD_GLOBAL                     4: Lang
                2458    PUSH_NULL                       
                2460    LOAD_CONST                      1: '__pyarmor_assert_13392__'
                2462    LOAD_CONST                      42: 'restriction_detected'   # b"\x81\xf0\x1d\x00'\xe8\xb7\xd1\x0f\xf3\x02\xceS\xe8\xfd\x91\n^\xaf\xa2\xae"
                2464    CALL                            1
                2472    BINARY_SUBSCR                   
                2476    KW_NAMES                        24: ('config', 'account', 'message')
                2478    CALL                            3
                2486    POP_TOP                         
                2488    LOAD_GLOBAL                     25: NULL + Logs
                2498    LOAD_ATTR                       26: PrintLog
                2518    LOAD_FAST                       2: config
                2520    LOAD_FAST                       1: account
                2522    LOAD_GLOBAL                     4: Lang
                2532    PUSH_NULL                       
                2534    LOAD_CONST                      1: '__pyarmor_assert_13392__'
                2536    LOAD_CONST                      43: 'account_spamblock_stop'   # b'\x81\xe3\x1b\x10<\xef\xb0\xc6$\xe9\x1d\xc1a\xee\xf4\x8a\x0cV\x84\xb4\xbe\xc4^'
                2538    CALL                            1
                2546    BINARY_SUBSCR                   
                2550    KW_NAMES                        24: ('config', 'account', 'message')
                2552    CALL                            3
                2560    POP_TOP                         
                2562    LOAD_CONST                      38: True
                2564    STORE_FAST                      25: _var_var_36
                2566    LOAD_FAST                       23: _var_var_34
                2568    PUSH_NULL                       
                2570    LOAD_CONST                      1: '__pyarmor_assert_13392__'
                2572    LOAD_CONST                      44: 'ConnectionError'   # b'\x81\xc1\x17\x1d=\xff\xbd\xc6\x12\xf5\x03\xe5~\xfe\xf7\x97'
                2574    CALL                            1
                2582    PUSH_NULL                       
                2584    LOAD_CONST                      1: '__pyarmor_assert_13392__'
                2586    LOAD_CONST                      45: 'TimeoutError'   # b'\x81\xd6\x11\x1e6\xf5\xab\xc6>\xe8\x1f\xcf~'
                2588    CALL                            1
                2596    BUILD_TUPLE                     2
                2598    CONTAINS_OP                     0 (in)
                2600    POP_JUMP_IF_FALSE               52 (to 2706)
                2602    LOAD_GLOBAL                     25: NULL + Logs
                2612    LOAD_ATTR                       26: PrintLog
                2632    LOAD_FAST                       2: config
                2634    LOAD_FAST                       1: account
                2636    LOAD_GLOBAL                     4: Lang
                2646    PUSH_NULL                       
                2648    LOAD_CONST                      1: '__pyarmor_assert_13392__'
                2650    LOAD_CONST                      46: 'error_reconnecting'   # b'\x81\xe7\n\x01<\xe8\x81\xc0\x1e\xf9\x02\xceb\xe9\xfb\x91\x06S\xbc'
                2652    CALL                            1
                2660    BINARY_SUBSCR                   
                2664    KW_NAMES                        24: ('config', 'account', 'message')
                2666    CALL                            3
                2674    POP_TOP                         
                2676    LOAD_GLOBAL                     45: NULL + DelayOnline
                2686    LOAD_FAST                       1: account
                2688    LOAD_FAST                       8: _var_var_19
                2690    LOAD_CONST                      29: 1
                2692    LOAD_CONST                      47: 2
                2694    LOAD_FAST                       6: stop_thread
                2696    CALL                            5
                2704    POP_TOP                         
                2706    LOAD_FAST                       23: _var_var_34
                2708    PUSH_NULL                       
                2710    LOAD_CONST                      1: '__pyarmor_assert_13392__'
                2712    LOAD_CONST                      48: 'UserBannedInChannelError'   # b'\x81\xd7\x0b\x16!\xd8\xbf\xdc\x15\xff\t\xe9b\xcf\xf0\x84\x01S\xbe\xab\x8f\xd9\\\xc3\x17'
                2714    CALL                            1
                2722    COMPARE_OP                      40 (==)
                2726    POP_JUMP_IF_FALSE               76 (to 2880)
                2728    LOAD_GLOBAL                     25: NULL + Logs
                2738    LOAD_ATTR                       26: PrintLog
                2758    LOAD_FAST                       2: config
                2760    LOAD_FAST                       1: account
                2762    LOAD_GLOBAL                     4: Lang
                2772    PUSH_NULL                       
                2774    LOAD_CONST                      1: '__pyarmor_assert_13392__'
                2776    LOAD_CONST                      42: 'restriction_detected'   # b"\x81\xf0\x1d\x00'\xe8\xb7\xd1\x0f\xf3\x02\xceS\xe8\xfd\x91\n^\xaf\xa2\xae"
                2778    CALL                            1
                2786    BINARY_SUBSCR                   
                2790    KW_NAMES                        24: ('config', 'account', 'message')
                2792    CALL                            3
                2800    POP_TOP                         
                2802    LOAD_GLOBAL                     25: NULL + Logs
                2812    LOAD_ATTR                       26: PrintLog
                2832    LOAD_FAST                       2: config
                2834    LOAD_FAST                       1: account
                2836    LOAD_GLOBAL                     4: Lang
                2846    PUSH_NULL                       
                2848    LOAD_CONST                      1: '__pyarmor_assert_13392__'
                2850    LOAD_CONST                      43: 'account_spamblock_stop'   # b'\x81\xe3\x1b\x10<\xef\xb0\xc6$\xe9\x1d\xc1a\xee\xf4\x8a\x0cV\x84\xb4\xbe\xc4^'
                2852    CALL                            1
                2860    BINARY_SUBSCR                   
                2864    KW_NAMES                        24: ('config', 'account', 'message')
                2866    CALL                            3
                2874    POP_TOP                         
                2876    LOAD_CONST                      38: True
                2878    STORE_FAST                      25: _var_var_36
                2880    LOAD_FAST                       23: _var_var_34
                2882    PUSH_NULL                       
                2884    LOAD_CONST                      1: '__pyarmor_assert_13392__'
                2886    LOAD_CONST                      49: 'ChatWriteForbiddenError'   # b"\x81\xc1\x10\x12'\xcd\xac\xdb\x0f\xff+\xcf~\xee\xf1\x81\x0bX\xb5\x82\xb8\xd9A\xde"
                2888    CALL                            1
                2896    PUSH_NULL                       
                2898    LOAD_CONST                      1: '__pyarmor_assert_13392__'
                2900    LOAD_CONST                      50: 'ChannelPrivateError'   # b'\x81\xc1\x10\x12=\xf4\xbb\xde+\xe8\x04\xd6m\xf8\xfd\xa0\x1dO\xb4\xb5'
                2902    CALL                            1
                2910    BUILD_TUPLE                     2
                2912    CONTAINS_OP                     0 (in)
                2914    POP_JUMP_IF_FALSE               39 (to 2994)
                2916    LOAD_GLOBAL                     25: NULL + Logs
                2926    LOAD_ATTR                       26: PrintLog
                2946    LOAD_FAST                       2: config
                2948    LOAD_FAST                       1: account
                2950    LOAD_GLOBAL                     4: Lang
                2960    PUSH_NULL                       
                2962    LOAD_CONST                      1: '__pyarmor_assert_13392__'
                2964    LOAD_CONST                      51: 'account_shadow_filter'   # b'\x81\xe3\x1b\x10<\xef\xb0\xc6$\xe9\x05\xc1h\xe3\xef\xba\tT\xb7\xb3\xaf\xd9'
                2966    CALL                            1
                2974    BINARY_SUBSCR                   
                2978    KW_NAMES                        24: ('config', 'account', 'message')
                2980    CALL                            3
                2988    POP_TOP                         
                2990    LOAD_CONST                      38: True
                2992    STORE_FAST                      25: _var_var_36
                2994    LOAD_FAST                       23: _var_var_34
                2996    PUSH_NULL                       
                2998    LOAD_CONST                      1: '__pyarmor_assert_13392__'
                3000    LOAD_CONST                      52: 'UnauthorizedError'   # b'\x81\xd7\x16\x12&\xee\xb6\xdd\t\xf3\x17\xc5h\xc9\xea\x97\x00O'
                3002    CALL                            1
                3010    PUSH_NULL                       
                3012    LOAD_CONST                      1: '__pyarmor_assert_13392__'
                3014    LOAD_CONST                      53: 'UserDeactivatedBanError'   # b'\x81\xd7\x0b\x16!\xde\xbb\xd3\x18\xee\x04\xd6m\xf8\xfd\x81-\\\xb5\x82\xb8\xd9A\xde'
                3016    CALL                            1
                3024    PUSH_NULL                       
                3026    LOAD_CONST                      1: '__pyarmor_assert_13392__'
                3028    LOAD_CONST                      54: 'AuthKeyUnregisteredError'   # b'\x81\xc3\r\x07;\xd1\xbb\xcb.\xf4\x1f\xc5k\xe5\xeb\x91\nO\xbe\xa3\x8f\xd9\\\xc3\x17'
                3030    CALL                            1
                3038    BUILD_TUPLE                     3
                3040    CONTAINS_OP                     0 (in)
                3042    POP_JUMP_IF_FALSE               39 (to 3122)
                3044    LOAD_GLOBAL                     25: NULL + Logs
                3054    LOAD_ATTR                       26: PrintLog
                3074    LOAD_FAST                       2: config
                3076    LOAD_FAST                       1: account
                3078    LOAD_GLOBAL                     4: Lang
                3088    PUSH_NULL                       
                3090    LOAD_CONST                      1: '__pyarmor_assert_13392__'
                3092    LOAD_CONST                      55: 'account_banned_exit'   # b'\x81\xe3\x1b\x10<\xef\xb0\xc6$\xf8\x0c\xceb\xe9\xfc\xba\nE\xb2\xb3'
                3094    CALL                            1
                3102    BINARY_SUBSCR                   
                3106    KW_NAMES                        24: ('config', 'account', 'message')
                3108    CALL                            3
                3116    POP_TOP                         
                3118    LOAD_CONST                      38: True
                3120    STORE_FAST                      25: _var_var_36
                3122    LOAD_FAST                       23: _var_var_34
                3124    PUSH_NULL                       
                3126    LOAD_CONST                      1: '__pyarmor_assert_13392__'
                3128    LOAD_CONST                      56: 'AuthKeyDuplicatedError'   # b'\x81\xc3\r\x07;\xd1\xbb\xcb?\xef\x1d\xcce\xef\xf9\x91\nY\x9e\xb5\xb8\xc4\\'
                3130    CALL                            1
                3138    COMPARE_OP                      40 (==)
                3142    POP_JUMP_IF_FALSE               39 (to 3222)
                3144    LOAD_GLOBAL                     25: NULL + Logs
                3154    LOAD_ATTR                       26: PrintLog
                3174    LOAD_FAST                       2: config
                3176    LOAD_FAST                       1: account
                3178    LOAD_GLOBAL                     4: Lang
                3188    PUSH_NULL                       
                3190    LOAD_CONST                      1: '__pyarmor_assert_13392__'
                3192    LOAD_CONST                      57: 'duplicate_session_disconnect'   # b'\x81\xe6\r\x03?\xf3\xbd\xd3\x0f\xff2\xd3i\xff\xeb\x8c\x00S\x84\xa3\xa3\xd8M\xc3\x0ba\xa6_\x14'
                3194    CALL                            1
                3202    BINARY_SUBSCR                   
                3206    KW_NAMES                        24: ('config', 'account', 'message')
                3208    CALL                            3
                3216    POP_TOP                         
                3218    LOAD_CONST                      38: True
                3220    STORE_FAST                      25: _var_var_36
                3222    LOAD_FAST                       23: _var_var_34
                3224    PUSH_NULL                       
                3226    LOAD_CONST                      1: '__pyarmor_assert_13392__'
                3228    LOAD_CONST                      58: 'TypeNotFoundError'   # b'\x81\xd6\x01\x036\xd4\xb1\xc6=\xf5\x18\xceh\xc9\xea\x97\x00O'
                3230    CALL                            1
                3238    COMPARE_OP                      40 (==)
                3242    POP_JUMP_IF_FALSE               76 (to 3396)
                3244    LOAD_GLOBAL                     25: NULL + Logs
                3254    LOAD_ATTR                       26: PrintLog
                3274    LOAD_FAST                       2: config
                3276    LOAD_FAST                       1: account
                3278    LOAD_GLOBAL                     4: Lang
                3288    PUSH_NULL                       
                3290    LOAD_CONST                      1: '__pyarmor_assert_13392__'
                3292    LOAD_CONST                      59: 'error_constructor'   # b'\x81\xe7\n\x01<\xe8\x81\xd1\x14\xf4\x1e\xd4~\xf9\xfb\x91\x00O'
                3294    CALL                            1
                3302    BINARY_SUBSCR                   
                3306    KW_NAMES                        24: ('config', 'account', 'message')
                3308    CALL                            3
                3316    POP_TOP                         
                3318    LOAD_GLOBAL                     25: NULL + Logs
                3328    LOAD_ATTR                       26: PrintLog
                3348    LOAD_FAST                       2: config
                3350    LOAD_FAST                       1: account
                3352    LOAD_GLOBAL                     4: Lang
                3362    PUSH_NULL                       
                3364    LOAD_CONST                      1: '__pyarmor_assert_13392__'
                3366    LOAD_CONST                      60: 'shutting_down_my_account'   # b"\x81\xf1\x10\x06'\xee\xb7\xdc\x1c\xc5\t\xcf{\xe2\xc7\x88\x16b\xba\xa4\xa9\xc4[\xc2\x11"
                3368    CALL                            1
                3376    BINARY_SUBSCR                   
                3380    KW_NAMES                        24: ('config', 'account', 'message')
                3382    CALL                            3
                3390    POP_TOP                         
                3392    LOAD_CONST                      38: True
                3394    STORE_FAST                      25: _var_var_36
                3396    LOAD_FAST                       23: _var_var_34
                3398    PUSH_NULL                       
                3400    LOAD_CONST                      1: '__pyarmor_assert_13392__'
                3402    LOAD_CONST                      34: 'FloodWaitError'   # b'\x81\xc4\x14\x1c<\xfe\x89\xd3\x12\xee(\xd2~\xe3\xea'
                3404    CALL                            1
                3412    COMPARE_OP                      40 (==)
                3416    POP_JUMP_IF_FALSE               234 (to 3886)
                3418    LOAD_GLOBAL                     25: NULL + Logs
                3428    LOAD_ATTR                       26: PrintLog
                3448    LOAD_FAST                       2: config
                3450    LOAD_FAST                       1: account
                3452    LOAD_GLOBAL                     4: Lang
                3462    PUSH_NULL                       
                3464    LOAD_CONST                      1: '__pyarmor_assert_13392__'
                3466    LOAD_CONST                      42: 'restriction_detected'   # b"\x81\xf0\x1d\x00'\xe8\xb7\xd1\x0f\xf3\x02\xceS\xe8\xfd\x91\n^\xaf\xa2\xae"
                3468    CALL                            1
                3476    BINARY_SUBSCR                   
                3480    KW_NAMES                        24: ('config', 'account', 'message')
                3482    CALL                            3
                3490    POP_TOP                         
                3492    LOAD_GLOBAL                     25: NULL + Logs
                3502    LOAD_ATTR                       26: PrintLog
                3522    LOAD_FAST                       2: config
                3524    LOAD_FAST                       1: account
                3526    LOAD_GLOBAL                     4: Lang
                3536    PUSH_NULL                       
                3538    LOAD_CONST                      1: '__pyarmor_assert_13392__'
                3540    LOAD_CONST                      61: 'algorithm_running'   # b'\x81\xe3\x14\x14<\xe8\xb7\xc6\x13\xf72\xd2y\xe2\xf6\x8c\x01Z'
                3542    CALL                            1
                3550    BINARY_SUBSCR                   
                3554    KW_NAMES                        24: ('config', 'account', 'message')
                3556    CALL                            3
                3564    POP_TOP                         
                3566    LOAD_FAST                       24: _var_var_35
                3568    LOAD_GLOBAL                     17: NULL + random
                3578    LOAD_ATTR                       18: randint
                3598    LOAD_CONST                      62: 5
                3600    LOAD_CONST                      63: 10
                3602    CALL                            2
                3610    BINARY_OP                       0 (+)
                3614    STORE_FAST                      28: _var_var_38
                3616    LOAD_FAST                       24: _var_var_35
                3618    LOAD_FAST                       12: _var_var_23
                3620    COMPARE_OP                      68 (>)
                3624    POP_JUMP_IF_FALSE               77 (to 3780)
                3626    LOAD_GLOBAL                     25: NULL + Logs
                3636    LOAD_ATTR                       26: PrintLog
                3656    LOAD_FAST                       2: config
                3658    LOAD_FAST                       1: account
                3660    LOAD_GLOBAL                     4: Lang
                3670    PUSH_NULL                       
                3672    LOAD_CONST                      1: '__pyarmor_assert_13392__'
                3674    LOAD_CONST                      64: 'flood_wait_more'   # b'\x81\xe4\x14\x1c<\xfe\x81\xc5\x1a\xf3\x19\xffa\xe3\xea\x80'
                3676    CALL                            1
                3684    BINARY_SUBSCR                   
                3688    LOAD_FAST                       12: _var_var_23
                3690    KW_NAMES                        27: ('config', 'account', 'message', 'param')
                3692    CALL                            4
                3700    POP_TOP                         
                3702    LOAD_GLOBAL                     25: NULL + Logs
                3712    LOAD_ATTR                       26: PrintLog
                3732    LOAD_FAST                       2: config
                3734    LOAD_FAST                       1: account
                3736    LOAD_GLOBAL                     4: Lang
                3746    PUSH_NULL                       
                3748    LOAD_CONST                      1: '__pyarmor_assert_13392__'
                3750    LOAD_CONST                      65: 'work_stopped'   # b'\x81\xf5\x17\x018\xc5\xad\xc6\x14\xea\x1d\xc5h'
                3752    CALL                            1
                3760    BINARY_SUBSCR                   
                3764    KW_NAMES                        24: ('config', 'account', 'message')
                3766    CALL                            3
                3774    POP_TOP                         
                3776    LOAD_CONST                      38: True
                3778    STORE_FAST                      25: _var_var_36
                3780    LOAD_GLOBAL                     25: NULL + Logs
                3790    LOAD_ATTR                       26: PrintLog
                3810    LOAD_FAST                       2: config
                3812    LOAD_FAST                       1: account
                3814    LOAD_GLOBAL                     4: Lang
                3824    PUSH_NULL                       
                3826    LOAD_CONST                      1: '__pyarmor_assert_13392__'
                3828    LOAD_CONST                      66: 'flood_wait_bypass'   # b'\x81\xe4\x14\x1c<\xfe\x81\xc5\x1a\xf3\x19\xffn\xf5\xe8\x84\x1cN'
                3830    CALL                            1
                3838    BINARY_SUBSCR                   
                3842    LOAD_FAST                       28: _var_var_38
                3844    KW_NAMES                        27: ('config', 'account', 'message', 'param')
                3846    CALL                            4
                3854    POP_TOP                         
                3856    LOAD_GLOBAL                     45: NULL + DelayOnline
                3866    LOAD_FAST                       1: account
                3868    LOAD_FAST                       8: _var_var_19
                3870    LOAD_FAST                       28: _var_var_38
                3872    LOAD_FAST                       28: _var_var_38
                3874    LOAD_FAST                       6: stop_thread
                3876    CALL                            5
                3884    POP_TOP                         
                3886    LOAD_FAST                       25: _var_var_36
                3888    POP_JUMP_IF_FALSE               2 (to 3894)
                3890    POP_TOP                         
                3892    JUMP_FORWARD                    15 (to 3924)
                3894    LOAD_FAST                       15: _var_var_26
                3896    LOAD_CONST                      29: 1
                3898    BINARY_OP                       23 (-=)
                3902    STORE_FAST                      15: _var_var_26
                3904    LOAD_FAST                       15: _var_var_26
                3906    LOAD_CONST                      21: 0
                3908    COMPARE_OP                      26 (<=)
                3912    POP_JUMP_IF_TRUE                2 (to 3918)
                3914    JUMP_BACKWARD                   1320 (to 1278)
                3918    POP_TOP                         
                3920    JUMP_FORWARD                    1 (to 3924)
                3922    END_FOR                         
                3924    LOAD_GLOBAL                     25: NULL + Logs
                3934    LOAD_ATTR                       26: PrintLog
                3954    LOAD_FAST                       2: config
                3956    LOAD_FAST                       1: account
                3958    LOAD_GLOBAL                     4: Lang
                3968    PUSH_NULL                       
                3970    LOAD_CONST                      1: '__pyarmor_assert_13392__'
                3972    LOAD_CONST                      67: 'contacts_send_count_req'   # b"\x81\xe1\x17\x1d'\xfb\xbd\xc6\x08\xc5\x1e\xc5b\xe8\xc7\x86\x00H\xb5\xb3\x95\xd9K\xdd"
                3974    CALL                            1
                3982    BINARY_SUBSCR                   
                3986    LOAD_FAST                       17: _var_var_28
                3988    KW_NAMES                        68: ('config', 'account', 'message', 'end')
                3990    CALL                            4
                3998    POP_TOP                         
                4000    LOAD_GLOBAL                     25: NULL + Logs
                4010    LOAD_ATTR                       26: PrintLog
                4030    LOAD_FAST                       2: config
                4032    LOAD_FAST                       1: account
                4034    LOAD_GLOBAL                     4: Lang
                4044    PUSH_NULL                       
                4046    LOAD_CONST                      1: '__pyarmor_assert_13392__'
                4048    LOAD_CONST                      69: 'contacts_send_count_done'   # b"\x81\xe1\x17\x1d'\xfb\xbd\xc6\x08\xc5\x1e\xc5b\xe8\xc7\x86\x00H\xb5\xb3\x95\xcfA\xc2\x00"
                4050    CALL                            1
                4058    BINARY_SUBSCR                   
                4062    LOAD_FAST                       18: _var_var_29
                4064    KW_NAMES                        68: ('config', 'account', 'message', 'end')
                4066    CALL                            4
                4074    POP_TOP                         
                4076    LOAD_FAST                       11: _var_var_22
                4078    POP_JUMP_IF_FALSE               111 (to 4302)
                4080    LOAD_GLOBAL                     25: NULL + Logs
                4090    LOAD_ATTR                       26: PrintLog
                4110    LOAD_FAST                       2: config
                4112    LOAD_FAST                       1: account
                4114    LOAD_GLOBAL                     4: Lang
                4124    PUSH_NULL                       
                4126    LOAD_CONST                      1: '__pyarmor_assert_13392__'
                4128    LOAD_CONST                      70: 'exit_groups_on_activated'   # b"\x81\xe7\x00\x1a'\xc5\xb9\xc0\x14\xef\x1d\xd3S\xe3\xf6\xba\x0e^\xaf\xae\xbc\xcaZ\xc9\x01"
                4130    CALL                            1
                4138    BINARY_SUBSCR                   
                4142    KW_NAMES                        24: ('config', 'account', 'message')
                4144    CALL                            3
                4152    POP_TOP                         
                4154    LOAD_GLOBAL                     25: NULL + Logs
                4164    LOAD_ATTR                       26: PrintLog
                4184    LOAD_FAST                       2: config
                4186    LOAD_FAST                       1: account
                4188    LOAD_GLOBAL                     4: Lang
                4198    PUSH_NULL                       
                4200    LOAD_CONST                      1: '__pyarmor_assert_13392__'
                4202    LOAD_CONST                      71: 'leaving_group'   # b'\x81\xee\x1d\x12%\xf3\xb0\xd5$\xfd\x1f\xcfy\xfc'
                4204    CALL                            1
                4212    BINARY_SUBSCR                   
                4216    KW_NAMES                        24: ('config', 'account', 'message')
                4218    CALL                            3
                4226    POP_TOP                         
                4228    LOAD_GLOBAL                     21: NULL + tg_group
                4238    LOAD_FAST                       2: config
                4240    LOAD_FAST                       8: _var_var_19
                4242    LOAD_FAST                       1: account
                4244    LOAD_FAST                       12: _var_var_23
                4246    LOAD_GLOBAL                     4: Lang
                4256    LOAD_FAST                       6: stop_thread
                4258    KW_NAMES                        72: ('config', 'client', 'account', 'max_flood_wait', 'lang', 'stop_thread')
                4260    CALL                            6
                4268    LOAD_ATTR                       87: go_out
                4288    LOAD_FAST                       19: _var_var_30
                4290    KW_NAMES                        73: ('entity',)
                4292    CALL                            1
                4300    POP_TOP                         
                4302    LOAD_GLOBAL                     7: NULL + Disconnect
                4312    LOAD_FAST_CHECK                 8: _var_var_19
                4314    CALL                            1
                4322    POP_TOP                         
                4324    LOAD_FAST                       1: account
                4326    LOAD_CONST                      9: 'done'
                4328    LOAD_CONST                      8: ('account', 'status')
                4330    BUILD_CONST_KEY_MAP             2
                4332    NOP                             
                4334    NOP                             
                4336    NOP                             
                4338    JUMP_FORWARD                    235 (to 4810)
                4340    CALL                            1
                4348    POP_TOP                         
                4350    RETURN_VALUE                    
                4352    PUSH_EXC_INFO                   
                4354    POP_TOP                         
                4356    POP_EXCEPT                      
                4358    JUMP_BACKWARD                   2106 (to 150)
                4362    COPY                            3
                4364    POP_EXCEPT                      
                4366    RERAISE                         1
                4368    PUSH_EXC_INFO                   
                4370    POP_TOP                         
                4372    POP_EXCEPT                      
                4374    JUMP_BACKWARD                   1733 (to 912)
                4378    COPY                            3
                4380    POP_EXCEPT                      
                4382    RERAISE                         1
                4384    PUSH_EXC_INFO                   
                4386    POP_TOP                         
                4388    POP_EXCEPT                      
                4390    JUMP_BACKWARD                   1720 (to 954)
                4394    COPY                            3
                4396    POP_EXCEPT                      
                4398    RERAISE                         1
                4400    PUSH_EXC_INFO                   
                4402    LOAD_GLOBAL                     42: StopProgram
                4412    CHECK_EXC_MATCH                 
                4414    POP_JUMP_IF_FALSE               4 (to 4424)
                4416    POP_TOP                         
                4418    POP_EXCEPT                      
                4420    POP_TOP                         
                4422    JUMP_BACKWARD                   250 (to 3924)
                4424    LOAD_GLOBAL                     66: Exception
                4434    CHECK_EXC_MATCH                 
                4436    POP_JUMP_IF_FALSE               64 (to 4566)
                4438    STORE_FAST                      27: _var_var_3
                4440    LOAD_GLOBAL                     69: NULL + type
                4450    LOAD_FAST                       27: _var_var_3
                4452    CALL                            1
                4460    LOAD_ATTR                       70: __name__
                4480    STORE_FAST                      23: _var_var_34
                4482    LOAD_FAST                       23: _var_var_34
                4484    PUSH_NULL                       
                4486    LOAD_CONST                      1: '__pyarmor_assert_13392__'
                4488    LOAD_CONST                      34: 'FloodWaitError'   # b'\x81\xc4\x14\x1c<\xfe\x89\xd3\x12\xee(\xd2~\xe3\xea'
                4490    CALL                            1
                4498    COMPARE_OP                      40 (==)
                4502    POP_JUMP_IF_FALSE               21 (to 4546)
                4504    LOAD_GLOBAL                     13: NULL + int
                4514    LOAD_FAST                       27: _var_var_3
                4516    LOAD_ATTR                       72: seconds
                4536    CALL                            1
                4544    STORE_FAST                      24: _var_var_35
                4546    POP_EXCEPT                      
                4548    LOAD_CONST                      0: None
                4550    STORE_FAST                      27: _var_var_3
                4552    DELETE_FAST                     27: _var_var_3
                4554    JUMP_BACKWARD                   1343 (to 1872)
                4558    LOAD_CONST                      0: None
                4560    STORE_FAST                      27: _var_var_3
                4562    DELETE_FAST                     27: _var_var_3
                4564    RERAISE                         1
                4566    RERAISE                         0
                4568    COPY                            3
                4570    POP_EXCEPT                      
                4572    RERAISE                         1
                4574    PUSH_EXC_INFO                   
                4576    POP_TOP                         
                4578    POP_EXCEPT                      
                4580    JUMP_BACKWARD                   1129 (to 2326)
                4584    COPY                            3
                4586    POP_EXCEPT                      
                4588    RERAISE                         1
                4590    PUSH_EXC_INFO                   
                4592    LOAD_GLOBAL                     42: StopProgram
                4602    CHECK_EXC_MATCH                 
                4604    POP_JUMP_IF_FALSE               3 (to 4612)
                4606    POP_TOP                         
                4608    POP_EXCEPT                      
                4610    JUMP_BACKWARD                   155 (to 4302)
                4612    LOAD_GLOBAL                     88: BaseException
                4622    CHECK_EXC_MATCH                 
                4624    POP_JUMP_IF_FALSE               26 (to 4678)
                4626    STORE_FAST                      27: _var_var_3
                4628    PUSH_NULL                       
                4630    LOAD_GLOBAL                     91: NULL + logging
                4640    LOAD_FAST                       27: _var_var_3
                4642    CALL                            1
                4650    CALL                            0
                4658    POP_TOP                         
                4660    POP_EXCEPT                      
                4662    LOAD_CONST                      0: None
                4664    STORE_FAST                      27: _var_var_3
                4666    DELETE_FAST                     27: _var_var_3
                4668    JUMP_BACKWARD                   184 (to 4302)
                4670    LOAD_CONST                      0: None
                4672    STORE_FAST                      27: _var_var_3
                4674    DELETE_FAST                     27: _var_var_3
                4676    RERAISE                         1
                4678    RERAISE                         0
                4680    COPY                            3
                4682    POP_EXCEPT                      
                4684    RERAISE                         1
                4686    PUSH_EXC_INFO                   
                4688    POP_TOP                         
                4690    POP_EXCEPT                      
                4692    JUMP_BACKWARD                   185 (to 4324)
                4694    COPY                            3
                4696    POP_EXCEPT                      
                4698    RERAISE                         1
                4700    PUSH_EXC_INFO                   
                4702    LOAD_GLOBAL                     7: NULL + Disconnect
                4712    LOAD_FAST_CHECK                 8: _var_var_19
                4714    CALL                            1
                4722    POP_TOP                         
                4724    JUMP_FORWARD                    7 (to 4740)
                4726    PUSH_EXC_INFO                   
                4728    POP_TOP                         
                4730    POP_EXCEPT                      
                4732    JUMP_FORWARD                    3 (to 4740)
                4734    COPY                            3
                4736    POP_EXCEPT                      
                4738    RERAISE                         1
                4740    LOAD_FAST                       1: account
                4742    LOAD_CONST                      9: 'done'
                4744    LOAD_CONST                      8: ('account', 'status')
                4746    BUILD_CONST_KEY_MAP             2
                4748    SWAP                            2
                4750    POP_TOP                         
                4752    SWAP                            2
                4754    POP_EXCEPT                      
                4756    NOP                             
                4758    NOP                             
                4760    NOP                             
                4762    JUMP_FORWARD                    23 (to 4810)
                4764    CALL                            1
                4772    POP_TOP                         
                4774    RETURN_VALUE                    
                4776    COPY                            3
                4778    POP_EXCEPT                      
                4780    RERAISE                         1
                4782    PUSH_EXC_INFO                   
                4784    PUSH_NULL                       
                4786    LOAD_CONST                      10: '__pyarmor_exit_13394__'
                4788    NOP                             
                4790    LOAD_CONST                      3: b'<COAddr>\x05\x00\x00\x1a\x94\x12\x00\x00\x00\x00\x00\x00\x00\x00\x00\x00\x00\x00\x00\x00'
                4792    CALL                            1
                4800    POP_TOP                         
                4802    RERAISE                         0
                4804    COPY                            3
                4806    POP_EXCEPT                      
                4808    RERAISE                         1
                4810    PUSH_NULL                       
                4812    LOAD_CONST                      10: '__pyarmor_exit_13394__'
                4814    LOAD_CONST                      3: b'<COAddr>\x05\x00\x00\x1a\x94\x12\x00\x00\x00\x00\x00\x00\x00\x00\x00\x00\x00\x00\x00\x00'
                4816    BUILD_TUPLE                     1
                4818    CALL_FUNCTION_EX                0
                4820    POP_TOP                         
                4822    RETURN_VALUE                    
            [Exception Table]
                30 to 128 -> 4590 [0] 
                128 to 150 -> 4352 [1] 
                150 to 162 -> 4782 [0] 
                182 to 890 -> 4590 [0] 
                890 to 912 -> 4368 [0] 
                912 to 932 -> 4590 [0] 
                932 to 954 -> 4384 [1] 
                954 to 966 -> 4782 [0] 
                986 to 1328 -> 4590 [0] 
                1330 to 1872 -> 4400 [1] 
                1872 to 2172 -> 4590 [0] 
                2174 to 2326 -> 4574 [1] 
                2326 to 3914 -> 4590 [0] 
                3918 to 4302 -> 4590 [0] 
                4302 to 4324 -> 4686 [0] 
                4324 to 4332 -> 4782 [0] 
                4352 to 4356 -> 4362 [2] lasti
                4356 to 4368 -> 4782 [0] 
                4368 to 4372 -> 4378 [1] lasti
                4372 to 4384 -> 4590 [0] 
                4384 to 4388 -> 4394 [2] lasti
                4388 to 4400 -> 4782 [0] 
                4400 to 4418 -> 4568 [2] lasti
                4418 to 4424 -> 4590 [0] 
                4424 to 4440 -> 4568 [2] lasti
                4440 to 4546 -> 4558 [2] lasti
                4546 to 4558 -> 4590 [0] 
                4558 to 4568 -> 4568 [2] lasti
                4568 to 4574 -> 4590 [0] 
                4574 to 4578 -> 4584 [2] lasti
                4578 to 4590 -> 4590 [0] 
                4590 to 4608 -> 4680 [1] lasti
                4608 to 4612 -> 4700 [0] 
                4612 to 4628 -> 4680 [1] lasti
                4628 to 4660 -> 4670 [1] lasti
                4660 to 4670 -> 4700 [0] 
                4670 to 4680 -> 4680 [1] lasti
                4680 to 4686 -> 4700 [0] 
                4686 to 4690 -> 4694 [1] lasti
                4690 to 4700 -> 4782 [0] 
                4700 to 4702 -> 4776 [1] lasti
                4702 to 4724 -> 4726 [2] 
                4724 to 4726 -> 4776 [1] lasti
                4726 to 4730 -> 4734 [3] lasti
                4730 to 4754 -> 4776 [1] lasti
                4754 to 4756 -> 4782 [0] 
                4776 to 4782 -> 4782 [0] 
                4782 to 4804 -> 4804 [1] lasti
        '__pyarmor_exit_13385__'
    [Disassembly]
        0       NOP                             
        2       NOP                             
        4       PUSH_NULL                       
        6       LOAD_CONST                      1: '__pyarmor_enter_13384__'
        8       LOAD_CONST                      2: b'<COAddr>\x07\x00\x00\x1a^\x01\x00\x00\x00\x00\x00\x00\x00\x00\x00\x00\x00\x00\x00\x00'
        10      BUILD_TUPLE                     1
        12      CALL_FUNCTION_EX                0
        14      POP_TOP                         
        16      RESUME                          0
        18      NOP                             
        20      NOP                             
        22      NOP                             
        24      NOP                             
        26      LOAD_CONST                      3: 0
        28      LOAD_CONST                      4: None
        30      IMPORT_NAME                     1: eel
        32      STORE_NAME                      1: eel
        34      LOAD_CONST                      3: 0
        36      LOAD_CONST                      4: None
        38      IMPORT_NAME                     2: json
        40      STORE_NAME                      2: json
        42      LOAD_CONST                      3: 0
        44      LOAD_CONST                      4: None
        46      IMPORT_NAME                     3: random
        48      STORE_NAME                      3: random
        50      LOAD_CONST                      3: 0
        52      LOAD_CONST                      4: None
        54      IMPORT_NAME                     4: datetime
        56      STORE_NAME                      4: datetime
        58      LOAD_CONST                      3: 0
        60      LOAD_CONST                      4: None
        62      IMPORT_NAME                     5: concurrent.futures
        64      STORE_NAME                      6: concurrent
        66      LOAD_CONST                      3: 0
        68      LOAD_CONST                      5: ('Thread', 'Event')
        70      IMPORT_NAME                     7: threading
        72      IMPORT_FROM                     8: Thread
        74      STORE_NAME                      8: Thread
        76      IMPORT_FROM                     9: Event
        78      STORE_NAME                      9: Event
        80      POP_TOP                         
        82      LOAD_CONST                      3: 0
        84      LOAD_CONST                      6: ('functions', 'types')
        86      IMPORT_NAME                     10: multithon.sync
        88      IMPORT_FROM                     11: functions
        90      STORE_NAME                      11: functions
        92      IMPORT_FROM                     12: types
        94      STORE_NAME                      12: types
        96      POP_TOP                         
        98      LOAD_CONST                      3: 0
        100     LOAD_CONST                      7: ('StopProgram',)
        102     IMPORT_NAME                     13: multithon.errors
        104     IMPORT_FROM                     14: StopProgram
        106     STORE_NAME                      14: StopProgram
        108     POP_TOP                         
        110     LOAD_CONST                      3: 0
        112     LOAD_CONST                      8: ('GetLang',)
        114     IMPORT_NAME                     15: program.static_classes
        116     IMPORT_FROM                     16: GetLang
        118     STORE_NAME                      16: GetLang
        120     POP_TOP                         
        122     LOAD_CONST                      3: 0
        124     LOAD_CONST                      9: ('Logs',)
        126     IMPORT_NAME                     15: program.static_classes
        128     IMPORT_FROM                     17: Logs
        130     STORE_NAME                      17: Logs
        132     POP_TOP                         
        134     LOAD_CONST                      3: 0
        136     LOAD_CONST                      10: ('logging',)
        138     IMPORT_NAME                     15: program.static_classes
        140     IMPORT_FROM                     18: logging
        142     STORE_NAME                      18: logging
        144     POP_TOP                         
        146     LOAD_CONST                      3: 0
        148     LOAD_CONST                      11: ('memory_check_switcher',)
        150     IMPORT_NAME                     15: program.static_classes
        152     IMPORT_FROM                     19: memory_check_switcher
        154     STORE_NAME                      19: memory_check_switcher
        156     POP_TOP                         
        158     LOAD_CONST                      3: 0
        160     LOAD_CONST                      12: ('memory_set_pid',)
        162     IMPORT_NAME                     15: program.static_classes
        164     IMPORT_FROM                     20: memory_set_pid
        166     STORE_NAME                      20: memory_set_pid
        168     POP_TOP                         
        170     LOAD_CONST                      3: 0
        172     LOAD_CONST                      13: ('DelayOnline',)
        174     IMPORT_NAME                     21: program.telegram
        176     IMPORT_FROM                     22: DelayOnline
        178     STORE_NAME                      22: DelayOnline
        180     POP_TOP                         
        182     LOAD_CONST                      3: 0
        184     LOAD_CONST                      14: ('Disconnect',)
        186     IMPORT_NAME                     21: program.telegram
        188     IMPORT_FROM                     23: Disconnect
        190     STORE_NAME                      23: Disconnect
        192     POP_TOP                         
        194     LOAD_CONST                      3: 0
        196     LOAD_CONST                      15: ('Thread_wait',)
        198     IMPORT_NAME                     21: program.telegram
        200     IMPORT_FROM                     24: Thread_wait
        202     STORE_NAME                      24: Thread_wait
        204     POP_TOP                         
        206     LOAD_CONST                      3: 0
        208     LOAD_CONST                      16: ('account_works',)
        210     IMPORT_NAME                     21: program.telegram
        212     IMPORT_FROM                     25: account_works
        214     STORE_NAME                      25: account_works
        216     POP_TOP                         
        218     LOAD_CONST                      3: 0
        220     LOAD_CONST                      17: ('tg_group',)
        222     IMPORT_NAME                     21: program.telegram
        224     IMPORT_FROM                     26: tg_group
        226     STORE_NAME                      26: tg_group
        228     POP_TOP                         
        230     LOAD_CONST                      3: 0
        232     LOAD_CONST                      18: ('tg_links',)
        234     IMPORT_NAME                     21: program.telegram
        236     IMPORT_FROM                     27: tg_links
        238     STORE_NAME                      27: tg_links
        240     POP_TOP                         
        242     LOAD_CONST                      3: 0
        244     LOAD_CONST                      19: ('GetConfig',)
        246     IMPORT_NAME                     28: program.general
        248     IMPORT_FROM                     29: GetConfig
        250     STORE_NAME                      29: GetConfig
        252     POP_TOP                         
        254     LOAD_CONST                      3: 0
        256     LOAD_CONST                      20: ('GetProxy',)
        258     IMPORT_NAME                     28: program.general
        260     IMPORT_FROM                     30: GetProxy
        262     STORE_NAME                      30: GetProxy
        264     POP_TOP                         
        266     LOAD_CONST                      3: 0
        268     LOAD_CONST                      21: ('StopDetect',)
        270     IMPORT_NAME                     28: program.general
        272     IMPORT_FROM                     31: StopDetect
        274     STORE_NAME                      31: StopDetect
        276     POP_TOP                         
        278     LOAD_CONST                      3: 0
        280     LOAD_CONST                      22: ('check_get_settings',)
        282     IMPORT_NAME                     28: program.general
        284     IMPORT_FROM                     32: check_get_settings
        286     STORE_NAME                      32: check_get_settings
        288     POP_TOP                         
        290     LOAD_CONST                      3: 0
        292     LOAD_CONST                      23: ('del_task_manager',)
        294     IMPORT_NAME                     28: program.general
        296     IMPORT_FROM                     33: del_task_manager
        298     STORE_NAME                      33: del_task_manager
        300     POP_TOP                         
        302     LOAD_CONST                      3: 0
        304     LOAD_CONST                      24: ('getFile',)
        306     IMPORT_NAME                     28: program.general
        308     IMPORT_FROM                     34: getFile
        310     STORE_NAME                      34: getFile
        312     POP_TOP                         
        314     LOAD_CONST                      3: 0
        316     LOAD_CONST                      25: ('set_task_manager',)
        318     IMPORT_NAME                     28: program.general
        320     IMPORT_FROM                     35: set_task_manager
        322     STORE_NAME                      35: set_task_manager
        324     POP_TOP                         
        326     LOAD_CONST                      3: 0
        328     LOAD_CONST                      26: ('db_statistic',)
        330     IMPORT_NAME                     36: program.database
        332     IMPORT_FROM                     37: db_statistic
        334     STORE_NAME                      37: db_statistic
        336     POP_TOP                         
        338     LOAD_CONST                      27: <CODE> Contacts_invite
        340     MAKE_FUNCTION                   0
        342     STORE_NAME                      38: Contacts_invite
        344     LOAD_CONST                      28: <CODE> START
        346     MAKE_FUNCTION                   0
        348     STORE_NAME                      39: START
        350     LOAD_CONST                      29: <CODE> worker
        352     MAKE_FUNCTION                   0
        354     STORE_NAME                      40: worker
        356     LOAD_CONST                      4: None
        358     NOP                             
        360     NOP                             
        362     NOP                             
        364     JUMP_FORWARD                    19 (to 404)
        372     POP_TOP                         
        374     RETURN_CONST                    4: None
        376     PUSH_EXC_INFO                   
        378     PUSH_NULL                       
        380     LOAD_CONST                      30: '__pyarmor_exit_13385__'
        382     NOP                             
        384     LOAD_CONST                      2: b'<COAddr>\x07\x00\x00\x1a^\x01\x00\x00\x00\x00\x00\x00\x00\x00\x00\x00\x00\x00\x00\x00'
        386     CALL                            1
        394     POP_TOP                         
        396     RERAISE                         0
        398     COPY                            3
        400     POP_EXCEPT                      
        402     RERAISE                         1
        404     PUSH_NULL                       
        406     LOAD_CONST                      30: '__pyarmor_exit_13385__'
        408     LOAD_CONST                      2: b'<COAddr>\x07\x00\x00\x1a^\x01\x00\x00\x00\x00\x00\x00\x00\x00\x00\x00\x00\x00\x00\x00'
        410     BUILD_TUPLE                     1
        412     CALL_FUNCTION_EX                0
        414     POP_TOP                         
        416     RETURN_VALUE                    
    [Exception Table]
        26 to 356 -> 376 [0] 
        376 to 398 -> 398 [1] lasti
