#decoded by lolz.live/mrpenny / t.me/zeus_jackpot
# ================================
# Примечания по Pyarmor:
# - Байт-код и объекты кода Pyarmor соответствуют стандартному Python, но присутствуют специальные вызовы функций среды выполнения (runtime) Pyarmor.
# - Вызовы строк — это не ошибки, а маркеры, которые обрабатываются Pyarmor во время выполнения.
#
# Руководство по декомпиляции (без среды выполнения):
# 1. Игнорируйте зашифрованные байты после `#`; используйте только строку до `#`.
# 2. Удалите "__pyarmor_enter_xxx__"(b"<COAddr>...") и "__pyarmor_leave_xxx__"(b"<COAddr>...") (пролог/эпилог).
# 3. "__pyarmor_assert_xxx__"(A) не является настоящим оператором assert.
#    - Если A — это имя или читаемая строка: замените на A.
#    - Если A — это (X, "Y"): замените на X.Y.
#    - Если A — это (X, "Y", Z): замените на X.Y = Z.
#    - В противном случае: выберите наиболее подходящую/логичную замену.
# 4. "__pyarmor_bcc_xxx__"(...) указывает на машинный (нативный) код; тело функции недоступно. Добавьте комментарий.
# ================================

[Code]
    File Name: <frozen program.modules.Create_channels>
    Object Name: <module>
    Qualified Name: <module>
    Arg Count: 0
    Pos Only Arg Count: 0
    KW Only Arg Count: 0
    Stack Size: 5
    Flags: 0x20000000 (CO_PYARMOR_OBFUSCATED)
    [Names]
        '__assert_armored__'
        'eel'
        'json'
        'time'
        'random'
        'string'
        'spintax'
        'datetime'
        'concurrent.futures'
        'concurrent'
        'threading'
        'Thread'
        'Event'
        'multithon.sync'
        'functions'
        'types'
        'errors'
        'multithon.errors'
        'StopProgram'
        'program.static_classes'
        'GetLang'
        'Logs'
        'logging'
        'memory_check_switcher'
        'memory_set_pid'
        'program.telegram'
        'DelayOnline'
        'Disconnect'
        'Thread_wait'
        'account_works'
        'program.general'
        'GetConfig'
        'GetProxy'
        'StopDetect'
        'check_get_settings'
        'del_task_manager'
        'getFile'
        'getPath'
        'set_task_manager'
        'program.database'
        'db_create_channels'
        'Create_channels'
        'generator_list'
        'generator_get'
        'START'
        'channel_create'
        'channel_set_username'
        'channel_get_link'
        'channel_set_photo'
        'channel_add_admins'
        'worker'
    [Locals+Names]
    [Constants]
        '__pyarmor_assert_13431__'
        '__pyarmor_enter_13432__'
        b'<COAddr>\x07\x00\x00\x1a\x9a\x01\x00\x00\x00\x00\x00\x00\x00\x00\x00\x00\x00\x00\x00\x00'
        0
        None
        (
            'Thread'
            'Event'
        )
        (
            'functions'
            'types'
            'errors'
        )
        (
            'StopProgram'
        )
        (
            'GetLang'
        )
        (
            'Logs'
        )
        (
            'logging'
        )
        (
            'memory_check_switcher'
        )
        (
            'memory_set_pid'
        )
        (
            'DelayOnline'
        )
        (
            'Disconnect'
        )
        (
            'Thread_wait'
        )
        (
            'account_works'
        )
        (
            'GetConfig'
        )
        (
            'GetProxy'
        )
        (
            'StopDetect'
        )
        (
            'check_get_settings'
        )
        (
            'del_task_manager'
        )
        (
            'getFile'
        )
        (
            'getPath'
        )
        (
            'set_task_manager'
        )
        (
            'db_create_channels'
        )
        [Code]
            File Name: <frozen program.modules.Create_channels>
            Object Name: Create_channels
            Qualified Name: Create_channels
            Arg Count: 1
            Pos Only Arg Count: 0
            KW Only Arg Count: 0
            Stack Size: 8
            Flags: 0x20000003 (CO_OPTIMIZED | CO_NEWLOCALS | CO_PYARMOR_OBFUSCATED)
            [Names]
                'get'
                'getFile'
                'getPath'
                'GetConfig'
                'config'
                'GetLang'
                'Lang'
                'GetProxy'
                'eel'
                'sendSuccessBox'
                'memory_check_switcher'
                'Event'
                'memory_set_pid'
                'Thread'
                'START'
                'start'
                'Logs'
                'WaitStopAnsfer'
                'UpdateLogInWindow'
                'BaseException'
                'logging'
            [Locals+Names]
                'data'
                '__assert_armored__'
                '_var_var_0'
                '_var_var_1'
                '_var_var_2'
                '_var_var_3'
            [Constants]
                None
                '__pyarmor_assert_13434__'
                '__pyarmor_enter_13435__'
                b'<COAddr>\x05\x00\x00\x1a\x08\x03\x00\x00\x00\x00\x00\x00\x00\x00\x00\x00\x00\x00\x00\x00'
                'action'
                'getFile'
                '__pyarmor_exit_13436__'
                'getPath'
                'program_running'   # b'\x81\xf2\n\x1c4\xe8\xbf\xdf$\xe8\x18\xceb\xe5\xf6\x82'
                False
                (
                    'target'
                    'args'
                )
                True
                (
                    'target'
                    'args'
                    'daemon'
                )
            [Disassembly]
                0       NOP                             
                2       NOP                             
                4       PUSH_NULL                       
                6       LOAD_CONST                      2: '__pyarmor_enter_13435__'
                8       LOAD_CONST                      3: b'<COAddr>\x05\x00\x00\x1a\x08\x03\x00\x00\x00\x00\x00\x00\x00\x00\x00\x00\x00\x00\x00\x00'
                10      BUILD_TUPLE                     1
                12      CALL_FUNCTION_EX                0
                14      POP_TOP                         
                16      RESUME                          0
                18      NOP                             
                20      NOP                             
                22      NOP                             
                24      NOP                             
                26      NOP                             
                28      NOP                             
                30      LOAD_FAST                       0: data
                32      LOAD_ATTR                       1: get
                52      LOAD_CONST                      4: 'action'
                54      CALL                            1
                62      POP_JUMP_IF_NONE                28 (to 120)
                64      LOAD_FAST                       0: data
                66      LOAD_CONST                      4: 'action'
                68      BINARY_SUBSCR                   
                72      LOAD_CONST                      5: 'getFile'
                74      COMPARE_OP                      40 (==)
                78      POP_JUMP_IF_FALSE               20 (to 120)
                80      LOAD_GLOBAL                     3: NULL + getFile
                90      LOAD_FAST                       0: data
                92      CALL                            1
                100     NOP                             
                102     NOP                             
                104     JUMP_FORWARD                    361 (to 830)
                108     CALL                            1
                116     POP_TOP                         
                118     RETURN_VALUE                    
                120     LOAD_FAST                       0: data
                122     LOAD_ATTR                       1: get
                142     LOAD_CONST                      4: 'action'
                144     CALL                            1
                152     POP_JUMP_IF_NONE                28 (to 210)
                154     LOAD_FAST                       0: data
                156     LOAD_CONST                      4: 'action'
                158     BINARY_SUBSCR                   
                162     LOAD_CONST                      7: 'getPath'
                164     COMPARE_OP                      40 (==)
                168     POP_JUMP_IF_FALSE               20 (to 210)
                170     LOAD_GLOBAL                     5: NULL + getPath
                180     LOAD_FAST                       0: data
                182     CALL                            1
                190     NOP                             
                192     NOP                             
                194     JUMP_FORWARD                    316 (to 830)
                198     CALL                            1
                206     POP_TOP                         
                208     RETURN_VALUE                    
                210     LOAD_GLOBAL                     7: NULL + GetConfig
                220     CALL                            0
                228     STORE_GLOBAL                    4: config
                230     LOAD_GLOBAL                     11: NULL + GetLang
                240     LOAD_GLOBAL                     8: config
                250     CALL                            1
                258     STORE_GLOBAL                    6: Lang
                260     LOAD_GLOBAL                     15: NULL + GetProxy
                270     CALL                            0
                278     STORE_FAST                      2: _var_var_0
                280     LOAD_GLOBAL                     17: NULL + eel
                290     LOAD_ATTR                       18: sendSuccessBox
                310     LOAD_GLOBAL                     12: Lang
                320     PUSH_NULL                       
                322     LOAD_CONST                      1: '__pyarmor_assert_13434__'
                324     LOAD_CONST                      8: 'program_running'   # b'\x81\xf2\n\x1c4\xe8\xbf\xdf$\xe8\x18\xceb\xe5\xf6\x82'
                326     CALL                            1
                334     BINARY_SUBSCR                   
                338     CALL                            1
                346     POP_TOP                         
                348     LOAD_GLOBAL                     21: NULL + memory_check_switcher
                358     CALL                            0
                366     POP_JUMP_IF_TRUE                11 (to 390)
                368     NOP                             
                370     LOAD_CONST                      9: False
                372     NOP                             
                374     NOP                             
                376     NOP                             
                378     JUMP_FORWARD                    225 (to 830)
                386     POP_TOP                         
                388     RETURN_CONST                    9: False
                390     LOAD_GLOBAL                     23: NULL + Event
                400     CALL                            0
                408     STORE_FAST                      3: _var_var_1
                410     LOAD_GLOBAL                     25: NULL + memory_set_pid
                420     CALL                            0
                428     STORE_FAST                      4: _var_var_2
                430     LOAD_GLOBAL                     27: NULL + Thread
                440     LOAD_GLOBAL                     28: START
                450     LOAD_FAST                       0: data
                452     LOAD_GLOBAL                     8: config
                462     LOAD_FAST                       4: _var_var_2
                464     LOAD_FAST                       2: _var_var_0
                466     LOAD_FAST                       3: _var_var_1
                468     BUILD_TUPLE                     5
                470     KW_NAMES                        10: ('target', 'args')
                472     CALL                            2
                480     LOAD_ATTR                       31: start
                500     CALL                            0
                508     POP_TOP                         
                510     LOAD_GLOBAL                     27: NULL + Thread
                520     LOAD_GLOBAL                     32: Logs
                530     LOAD_ATTR                       34: WaitStopAnsfer
                550     LOAD_GLOBAL                     8: config
                560     LOAD_FAST                       4: _var_var_2
                562     LOAD_FAST                       3: _var_var_1
                564     BUILD_TUPLE                     3
                566     LOAD_CONST                      11: True
                568     KW_NAMES                        12: ('target', 'args', 'daemon')
                570     CALL                            3
                578     LOAD_ATTR                       31: start
                598     CALL                            0
                606     POP_TOP                         
                608     LOAD_GLOBAL                     27: NULL + Thread
                618     LOAD_GLOBAL                     32: Logs
                628     LOAD_ATTR                       36: UpdateLogInWindow
                648     LOAD_GLOBAL                     8: config
                658     LOAD_FAST                       4: _var_var_2
                660     LOAD_FAST                       3: _var_var_1
                662     BUILD_TUPLE                     3
                664     LOAD_CONST                      11: True
                666     KW_NAMES                        12: ('target', 'args', 'daemon')
                668     CALL                            3
                676     LOAD_ATTR                       31: start
                696     CALL                            0
                704     POP_TOP                         
                706     LOAD_CONST                      0: None
                708     NOP                             
                710     NOP                             
                712     NOP                             
                714     JUMP_FORWARD                    57 (to 830)
                722     POP_TOP                         
                724     RETURN_CONST                    0: None
                726     PUSH_EXC_INFO                   
                728     LOAD_GLOBAL                     38: BaseException
                738     CHECK_EXC_MATCH                 
                740     POP_JUMP_IF_FALSE               26 (to 794)
                742     STORE_FAST                      5: _var_var_3
                744     PUSH_NULL                       
                746     LOAD_GLOBAL                     41: NULL + logging
                756     LOAD_FAST                       5: _var_var_3
                758     CALL                            1
                766     CALL                            0
                774     POP_TOP                         
                776     POP_EXCEPT                      
                778     LOAD_CONST                      0: None
                780     STORE_FAST                      5: _var_var_3
                782     DELETE_FAST                     5: _var_var_3
                784     JUMP_BACKWARD                   40 (to 706)
                786     LOAD_CONST                      0: None
                788     STORE_FAST                      5: _var_var_3
                790     DELETE_FAST                     5: _var_var_3
                792     RERAISE                         1
                794     RERAISE                         0
                796     COPY                            3
                798     POP_EXCEPT                      
                800     RERAISE                         1
                802     PUSH_EXC_INFO                   
                804     PUSH_NULL                       
                806     LOAD_CONST                      6: '__pyarmor_exit_13436__'
                808     NOP                             
                810     LOAD_CONST                      3: b'<COAddr>\x05\x00\x00\x1a\x08\x03\x00\x00\x00\x00\x00\x00\x00\x00\x00\x00\x00\x00\x00\x00'
                812     CALL                            1
                820     POP_TOP                         
                822     RERAISE                         0
                824     COPY                            3
                826     POP_EXCEPT                      
                828     RERAISE                         1
                830     PUSH_NULL                       
                832     LOAD_CONST                      6: '__pyarmor_exit_13436__'
                834     LOAD_CONST                      3: b'<COAddr>\x05\x00\x00\x1a\x08\x03\x00\x00\x00\x00\x00\x00\x00\x00\x00\x00\x00\x00\x00\x00'
                836     BUILD_TUPLE                     1
                838     CALL_FUNCTION_EX                0
                840     POP_TOP                         
                842     RETURN_VALUE                    
            [Exception Table]
                30 to 100 -> 726 [0] 
                120 to 190 -> 726 [0] 
                210 to 368 -> 726 [0] 
                390 to 706 -> 726 [0] 
                726 to 744 -> 796 [1] lasti
                744 to 776 -> 786 [1] lasti
                776 to 786 -> 802 [0] 
                786 to 796 -> 796 [1] lasti
                796 to 802 -> 802 [0] 
                802 to 824 -> 824 [1] lasti
        [Code]
            File Name: <frozen program.modules.Create_channels>
            Object Name: generator_list
            Qualified Name: generator_list
            Arg Count: 1
            Pos Only Arg Count: 0
            KW Only Arg Count: 0
            Stack Size: 5
            Flags: 0x20000023 (CO_OPTIMIZED | CO_NEWLOCALS | CO_GENERATOR | CO_PYARMOR_OBFUSCATED)
            [Names]
                'len'
            [Locals+Names]
                'datalist'
                '__assert_armored__'
                '_var_var_4'
                '_var_var_5'
            [Constants]
                ' Генератор юзернеймов '
                '__pyarmor_assert_13437__'
                '__pyarmor_enter_13438__'
                b'<COAddr>\x05\x00\x00\x1e\xa6\x00\x00\x00\x00\x00\x00\x00\x00\x00\x00\x00\x00\x00\x00\x00'
                0
                False
                None
                1
                '__pyarmor_exit_13439__'
            [Disassembly]
                0       RETURN_GENERATOR                
                2       POP_TOP                         
                4       NOP                             
                6       NOP                             
                8       PUSH_NULL                       
                10      LOAD_CONST                      2: '__pyarmor_enter_13438__'
                12      LOAD_CONST                      3: b'<COAddr>\x05\x00\x00\x1e\xa6\x00\x00\x00\x00\x00\x00\x00\x00\x00\x00\x00\x00\x00\x00\x00'
                14      BUILD_TUPLE                     1
                16      CALL_FUNCTION_EX                0
                18      POP_TOP                         
                20      RESUME                          0
                22      NOP                             
                24      NOP                             
                26      NOP                             
                28      NOP                             
                30      NOP                             
                32      LOAD_CONST                      4: 0
                34      STORE_FAST                      2: _var_var_4
                36      LOAD_FAST                       0: datalist
                38      LOAD_CONST                      5: False
                40      COMPARE_OP                      40 (==)
                44      POP_JUMP_IF_FALSE               6 (to 58)
                46      NOP                             
                48      LOAD_CONST                      6: None
                50      YIELD_VALUE                     2
                52      RESUME                          1
                54      POP_TOP                         
                56      JUMP_BACKWARD                   5 (to 48)
                58      LOAD_GLOBAL                     1: NULL + len
                68      LOAD_FAST                       0: datalist
                70      CALL                            1
                78      STORE_FAST                      3: _var_var_5
                80      LOAD_FAST                       2: _var_var_4
                82      LOAD_GLOBAL                     1: NULL + len
                92      LOAD_FAST                       0: datalist
                94      CALL                            1
                102     COMPARE_OP                      2 (<)
                106     POP_JUMP_IF_FALSE               34 (to 176)
                108     LOAD_FAST                       0: datalist
                110     LOAD_FAST                       2: _var_var_4
                112     BINARY_SUBSCR                   
                116     YIELD_VALUE                     2
                118     RESUME                          1
                120     POP_TOP                         
                122     LOAD_FAST                       2: _var_var_4
                124     LOAD_CONST                      7: 1
                126     BINARY_OP                       13 (+=)
                130     STORE_FAST                      2: _var_var_4
                132     LOAD_FAST                       3: _var_var_5
                134     LOAD_FAST                       2: _var_var_4
                136     COMPARE_OP                      40 (==)
                140     POP_JUMP_IF_FALSE               2 (to 146)
                142     LOAD_CONST                      4: 0
                144     STORE_FAST                      2: _var_var_4
                146     LOAD_FAST                       2: _var_var_4
                148     LOAD_GLOBAL                     1: NULL + len
                158     LOAD_FAST                       0: datalist
                160     CALL                            1
                168     COMPARE_OP                      2 (<)
                172     POP_JUMP_IF_FALSE               1 (to 176)
                174     JUMP_BACKWARD                   34 (to 108)
                176     LOAD_CONST                      6: None
                178     NOP                             
                180     NOP                             
                182     NOP                             
                184     JUMP_FORWARD                    21 (to 228)
                192     POP_TOP                         
                194     RETURN_CONST                    6: None
                196     PUSH_EXC_INFO                   
                198     PUSH_NULL                       
                200     LOAD_CONST                      8: '__pyarmor_exit_13439__'
                202     NOP                             
                204     LOAD_CONST                      3: b'<COAddr>\x05\x00\x00\x1e\xa6\x00\x00\x00\x00\x00\x00\x00\x00\x00\x00\x00\x00\x00\x00\x00'
                206     CALL                            1
                214     POP_TOP                         
                216     RERAISE                         0
                218     COPY                            3
                220     POP_EXCEPT                      
                222     RERAISE                         1
                224     CALL_INTRINSIC_1                3 (INTRINSIC_STOPITERATION_ERROR)
                226     RERAISE                         1
                228     PUSH_NULL                       
                230     LOAD_CONST                      8: '__pyarmor_exit_13439__'
                232     LOAD_CONST                      3: b'<COAddr>\x05\x00\x00\x1e\xa6\x00\x00\x00\x00\x00\x00\x00\x00\x00\x00\x00\x00\x00\x00\x00'
                234     BUILD_TUPLE                     1
                236     CALL_FUNCTION_EX                0
                238     POP_TOP                         
                240     RETURN_VALUE                    
            [Exception Table]
                4 to 30 -> 224 [0] lasti
                32 to 174 -> 196 [0] 
                176 to 196 -> 224 [0] lasti
                196 to 218 -> 218 [1] lasti
                218 to 224 -> 224 [0] lasti
        [Code]
            File Name: <frozen program.modules.Create_channels>
            Object Name: generator_get
            Qualified Name: generator_get
            Arg Count: 2
            Pos Only Arg Count: 0
            KW Only Arg Count: 0
            Stack Size: 6
            Flags: 0x20000003 (CO_OPTIMIZED | CO_NEWLOCALS | CO_PYARMOR_OBFUSCATED)
            [Names]
                'range'
                'append'
                'next'
            [Locals+Names]
                'kol'
                'generator'
                '__assert_armored__'
                '_var_var_6'
                '_var_var_7'
            [Constants]
                None
                '__pyarmor_assert_13440__'
                '__pyarmor_enter_13441__'
                b'<COAddr>\x07\x00\x00\x1a\x9a\x00\x00\x00\x00\x00\x00\x00\x00\x00\x00\x00\x00\x00\x00\x00'
                0
                False
                '__pyarmor_exit_13442__'
            [Disassembly]
                0       NOP                             
                2       NOP                             
                4       PUSH_NULL                       
                6       LOAD_CONST                      2: '__pyarmor_enter_13441__'
                8       LOAD_CONST                      3: b'<COAddr>\x07\x00\x00\x1a\x9a\x00\x00\x00\x00\x00\x00\x00\x00\x00\x00\x00\x00\x00\x00\x00'
                10      BUILD_TUPLE                     1
                12      CALL_FUNCTION_EX                0
                14      POP_TOP                         
                16      RESUME                          0
                18      NOP                             
                20      NOP                             
                22      NOP                             
                24      NOP                             
                26      NOP                             
                28      LOAD_FAST                       0: kol
                30      LOAD_CONST                      4: 0
                32      COMPARE_OP                      40 (==)
                36      POP_JUMP_IF_TRUE                5 (to 48)
                38      LOAD_FAST                       1: generator
                40      LOAD_CONST                      5: False
                42      COMPARE_OP                      40 (==)
                46      POP_JUMP_IF_FALSE               11 (to 70)
                48      NOP                             
                50      LOAD_CONST                      5: False
                52      NOP                             
                54      NOP                             
                56      NOP                             
                58      JUMP_FORWARD                    74 (to 208)
                66      POP_TOP                         
                68      RETURN_CONST                    5: False
                70      BUILD_LIST                      0
                72      STORE_FAST                      3: _var_var_6
                74      LOAD_GLOBAL                     1: NULL + range
                84      LOAD_FAST                       0: kol
                86      CALL                            1
                94      GET_ITER                        
                96      FOR_ITER                        28 (to 154)
                100     STORE_FAST                      4: _var_var_7
                102     LOAD_FAST                       3: _var_var_6
                104     LOAD_ATTR                       3: append
                124     LOAD_GLOBAL                     5: NULL + next
                134     LOAD_FAST                       1: generator
                136     CALL                            1
                144     CALL                            1
                152     POP_TOP                         
                154     JUMP_BACKWARD                   30 (to 96)
                156     END_FOR                         
                158     LOAD_FAST                       3: _var_var_6
                160     NOP                             
                162     NOP                             
                164     NOP                             
                166     JUMP_FORWARD                    20 (to 208)
                168     CALL                            1
                176     POP_TOP                         
                178     RETURN_VALUE                    
                180     PUSH_EXC_INFO                   
                182     PUSH_NULL                       
                184     LOAD_CONST                      6: '__pyarmor_exit_13442__'
                186     NOP                             
                188     LOAD_CONST                      3: b'<COAddr>\x07\x00\x00\x1a\x9a\x00\x00\x00\x00\x00\x00\x00\x00\x00\x00\x00\x00\x00\x00\x00'
                190     CALL                            1
                198     POP_TOP                         
                200     RERAISE                         0
                202     COPY                            3
                204     POP_EXCEPT                      
                206     RERAISE                         1
                208     PUSH_NULL                       
                210     LOAD_CONST                      6: '__pyarmor_exit_13442__'
                212     LOAD_CONST                      3: b'<COAddr>\x07\x00\x00\x1a\x9a\x00\x00\x00\x00\x00\x00\x00\x00\x00\x00\x00\x00\x00\x00\x00'
                214     BUILD_TUPLE                     1
                216     CALL_FUNCTION_EX                0
                218     POP_TOP                         
                220     RETURN_VALUE                    
            [Exception Table]
                28 to 48 -> 180 [0] 
                70 to 160 -> 180 [0] 
                180 to 202 -> 202 [1] lasti
        [Code]
            File Name: <frozen program.modules.Create_channels>
            Object Name: START
            Qualified Name: START
            Arg Count: 5
            Pos Only Arg Count: 0
            KW Only Arg Count: 0
            Stack Size: 17
            Flags: 0x20000003 (CO_OPTIMIZED | CO_NEWLOCALS | CO_PYARMOR_OBFUSCATED)
            [Names]
                'is_set'
                'StopProgram'
                'check_get_settings'
                'get'
                'isinstance'
                'list'
                'int'
                'len'
                'eel'
                'sendErrorBox'
                'Lang'
                'datetime'
                'now'
                'strftime'
                'db_create_channels'
                'create'
                'WriteResult'
                'HideStopButton'
                'generator_list'
                'set_task_manager'
                'concurrent'
                'futures'
                'ThreadPoolExecutor'
                'StreamStat'
                'json'
                'dumps'
                'random'
                'randint'
                'generator_get'
                'append'
                'submit'
                'worker'
                'as_completed'
                'BaseException'
                'logging'
                'del_task_manager'
                'StopDetect'
            [Locals+Names]
                'data'
                'config'
                'pid'
                'proxy'
                'stop_thread'
                '__assert_armored__'
                '_var_var_8'
                '_var_var_9'
                '_var_var_10'
                '_var_var_11'
                '_var_var_12'
                '_var_var_13'
                '_var_var_14'
                '_var_var_15'
                '_var_var_16'
                '_var_var_17'
                '_var_var_18'
                '_var_var_19'
                '_var_var_20'
                '_var_var_21'
                '_var_var_22'
                '_var_var_23'
                '_var_var_24'
                '_var_var_25'
                '_var_var_26'
                '_var_var_27'
                '_var_var_28'
                '_var_var_29'
                '_var_var_30'
                '_var_var_31'
                '_var_var_3'
            [Constants]
                None
                '__pyarmor_assert_13443__'
                '__pyarmor_enter_13444__'
                b'<COAddr>\x07\x00\x00\x1a\x8e\x0b\x00\x00\x00\x00\x00\x00\x00\x00\x00\x00\x00\x00\x00\x00'
                'Settings'
                'Accounts'
                1
                'select_accounts_works'   # b'\x81\xf1\x1d\x1f6\xf9\xaa\xed\x1a\xf9\x0e\xcfy\xe2\xec\x960J\xb4\xb5\xa1\xd8'
                'thread_rules'   # b'\x81\xf6\x10\x016\xfb\xba\xed\t\xef\x01\xc5\x7f'
                True
                'thread_count'   # b'\x81\xf6\x10\x016\xfb\xba\xed\x18\xf5\x18\xcex'
                '%y-%m-%d_%H-%M-%S'   # b'\x81\xa7\x01^v\xf7\xf3\x97\x1f\xc5H\xe8!\xa9\xd5\xc8Jn'
                'additives/create_channels/'   # b'\x81\xe3\x1c\x17:\xee\xb7\xc4\x1e\xe9B\xc3~\xe9\xf9\x91\nb\xb8\xaf\xab\xc5@\xc9\t|\xec'
                '_result.db'   # b'\x81\xdd\n\x16 \xef\xb2\xc6U\xfe\x0f'
                'Result'
                'create_channels'   # b'\x81\xe1\n\x162\xee\xbb\xed\x18\xf2\x0c\xceb\xe9\xf4\x96'
                'direct_send'   # b'\x81\xe6\x11\x016\xf9\xaa\xed\x08\xff\x03\xc4'
                'message'
                'forward'
                0
                False
                'bots'
                'bot'
                'posts'
                ''
                'Username @PostBot is not specified'   # b'\x81\xd7\x0b\x16!\xf4\xbf\xdf\x1e\xba-\xf0c\xff\xec\xa7\x00I\xfb\xae\xb9\x8b@\xc3\x11/\xb0L\x05\xb2\x17\xe33W$'
                'list_names'   # b"\x81\xee\x11\x00'\xc5\xb0\xd3\x16\xff\x1e"
                'no_names_in_list'   # b'\x81\xec\x17,=\xfb\xb3\xd7\x08\xc5\x04\xceS\xe0\xf1\x96\x1b'
                'create_public_link'   # b'\x81\xe1\n\x162\xee\xbb\xed\x0b\xef\x0f\xcce\xef\xc7\x89\x06S\xb0'
                'list_links'   # b"\x81\xee\x11\x00'\xc5\xb2\xdb\x15\xf1\x1e"
                'no_links_in_list'   # b'\x81\xec\x17,?\xf3\xb0\xd9\x08\xc5\x04\xceS\xe0\xf1\x96\x1b'
                'set_avatar'   # b'\x81\xf1\x1d\x07\x0c\xfb\xa8\xd3\x0f\xfb\x1f'
                'avatar_path'   # b"\x81\xe3\x0e\x12'\xfb\xac\xed\x0b\xfb\x19\xc8"
                'no_image_in_folder'   # b'\x81\xec\x17,:\xf7\xbf\xd5\x1e\xc5\x04\xceS\xea\xf7\x89\x0bX\xa9'
                'stuff'
                (
                    'accounts'
                    'name'
                )
                (
                    'max_workers'
                )
                'st_task'
                'st_stream'   # b'\x81\xf1\x0c, \xee\xac\xd7\x1a\xf7'
                'st_wait'
                'st_done'
                'kol_channels_from'   # b'\x81\xe9\x17\x1f\x0c\xf9\xb6\xd3\x15\xf4\x08\xcc\x7f\xd3\xfe\x97\x00P'
                'kol_channels_to'   # b'\x81\xe9\x17\x1f\x0c\xf9\xb6\xd3\x15\xf4\x08\xcc\x7f\xd3\xec\x8a'
                '__pyarmor_exit_13445__'
                'Done'
            [Disassembly]
                0       NOP                             
                2       NOP                             
                4       PUSH_NULL                       
                6       LOAD_CONST                      2: '__pyarmor_enter_13444__'
                8       LOAD_CONST                      3: b'<COAddr>\x07\x00\x00\x1a\x8e\x0b\x00\x00\x00\x00\x00\x00\x00\x00\x00\x00\x00\x00\x00\x00'
                10      BUILD_TUPLE                     1
                12      CALL_FUNCTION_EX                0
                14      POP_TOP                         
                16      RESUME                          0
                18      NOP                             
                20      NOP                             
                22      NOP                             
                24      NOP                             
                26      NOP                             
                28      NOP                             
                30      LOAD_FAST                       4: stop_thread
                32      LOAD_ATTR                       1: is_set
                52      CALL                            0
                60      POP_JUMP_IF_FALSE               10 (to 82)
                62      LOAD_GLOBAL                     3: NULL + StopProgram
                72      CALL                            0
                80      RAISE_VARARGS                   1
                82      LOAD_GLOBAL                     5: NULL + check_get_settings
                92      LOAD_FAST                       0: data
                94      LOAD_ATTR                       7: get
                114     LOAD_CONST                      4: 'Settings'
                116     CALL                            1
                124     CALL                            1
                132     POP_TOP                         
                134     LOAD_FAST                       0: data
                136     LOAD_CONST                      5: 'Accounts'
                138     BINARY_SUBSCR                   
                142     STORE_FAST                      6: _var_var_8
                144     LOAD_GLOBAL                     9: NULL + isinstance
                154     LOAD_FAST                       6: _var_var_8
                156     LOAD_GLOBAL                     10: list
                166     CALL                            2
                174     POP_JUMP_IF_TRUE                3 (to 182)
                176     LOAD_FAST                       6: _var_var_8
                178     BUILD_LIST                      1
                180     STORE_FAST                      6: _var_var_8
                182     LOAD_GLOBAL                     13: NULL + int
                192     LOAD_GLOBAL                     15: NULL + len
                202     LOAD_FAST                       6: _var_var_8
                204     CALL                            1
                212     CALL                            1
                220     LOAD_CONST                      6: 1
                222     COMPARE_OP                      2 (<)
                226     POP_JUMP_IF_FALSE               44 (to 316)
                228     LOAD_GLOBAL                     17: NULL + eel
                238     LOAD_ATTR                       18: sendErrorBox
                258     LOAD_GLOBAL                     20: Lang
                268     PUSH_NULL                       
                270     LOAD_CONST                      1: '__pyarmor_assert_13443__'
                272     LOAD_CONST                      7: 'select_accounts_works'   # b'\x81\xf1\x1d\x1f6\xf9\xaa\xed\x1a\xf9\x0e\xcfy\xe2\xec\x960J\xb4\xb5\xa1\xd8'
                274     CALL                            1
                282     BINARY_SUBSCR                   
                286     CALL                            1
                294     POP_TOP                         
                296     LOAD_GLOBAL                     3: NULL + StopProgram
                306     CALL                            0
                314     RAISE_VARARGS                   1
                316     LOAD_FAST                       0: data
                318     LOAD_CONST                      4: 'Settings'
                320     BINARY_SUBSCR                   
                324     LOAD_ATTR                       7: get
                344     PUSH_NULL                       
                346     LOAD_CONST                      1: '__pyarmor_assert_13443__'
                348     LOAD_CONST                      8: 'thread_rules'   # b'\x81\xf6\x10\x016\xfb\xba\xed\t\xef\x01\xc5\x7f'
                350     CALL                            1
                358     CALL                            1
                366     LOAD_CONST                      9: True
                368     COMPARE_OP                      40 (==)
                372     POP_JUMP_IF_FALSE               36 (to 446)
                374     LOAD_GLOBAL                     13: NULL + int
                384     LOAD_FAST                       0: data
                386     LOAD_CONST                      4: 'Settings'
                388     BINARY_SUBSCR                   
                392     LOAD_ATTR                       7: get
                412     PUSH_NULL                       
                414     LOAD_CONST                      1: '__pyarmor_assert_13443__'
                416     LOAD_CONST                      10: 'thread_count'   # b'\x81\xf6\x10\x016\xfb\xba\xed\x18\xf5\x18\xcex'
                418     CALL                            1
                426     CALL                            1
                434     CALL                            1
                442     STORE_FAST                      7: _var_var_9
                444     JUMP_FORWARD                    11 (to 468)
                446     LOAD_FAST                       1: config
                448     PUSH_NULL                       
                450     LOAD_CONST                      1: '__pyarmor_assert_13443__'
                452     LOAD_CONST                      10: 'thread_count'   # b'\x81\xf6\x10\x016\xfb\xba\xed\x18\xf5\x18\xcex'
                454     CALL                            1
                462     BINARY_SUBSCR                   
                466     STORE_FAST                      7: _var_var_9
                468     LOAD_GLOBAL                     22: datetime
                478     LOAD_ATTR                       22: datetime
                498     LOAD_ATTR                       25: now
                518     CALL                            0
                526     LOAD_ATTR                       27: strftime
                546     PUSH_NULL                       
                548     LOAD_CONST                      1: '__pyarmor_assert_13443__'
                550     LOAD_CONST                      11: '%y-%m-%d_%H-%M-%S'   # b'\x81\xa7\x01^v\xf7\xf3\x97\x1f\xc5H\xe8!\xa9\xd5\xc8Jn'
                552     CALL                            1
                560     CALL                            1
                568     STORE_FAST                      8: _var_var_10
                570     LOAD_GLOBAL                     29: NULL + db_create_channels
                580     PUSH_NULL                       
                582     LOAD_CONST                      1: '__pyarmor_assert_13443__'
                584     LOAD_CONST                      12: 'additives/create_channels/'   # b'\x81\xe3\x1c\x17:\xee\xb7\xc4\x1e\xe9B\xc3~\xe9\xf9\x91\nb\xb8\xaf\xab\xc5@\xc9\t|\xec'
                586     CALL                            1
                594     LOAD_FAST                       8: _var_var_10
                596     FORMAT_VALUE                    0 (FVC_NONE)
                598     PUSH_NULL                       
                600     LOAD_CONST                      1: '__pyarmor_assert_13443__'
                602     LOAD_CONST                      13: '_result.db'   # b'\x81\xdd\n\x16 \xef\xb2\xc6U\xfe\x0f'
                604     CALL                            1
                612     BUILD_STRING                    3
                614     CALL                            1
                622     LOAD_ATTR                       31: create
                642     CALL                            0
                650     STORE_FAST                      9: _var_var_11
                652     LOAD_GLOBAL                     17: NULL + eel
                662     LOAD_ATTR                       32: WriteResult
                682     LOAD_CONST                      14: 'Result'
                684     PUSH_NULL                       
                686     LOAD_CONST                      1: '__pyarmor_assert_13443__'
                688     LOAD_CONST                      15: 'create_channels'   # b'\x81\xe1\n\x162\xee\xbb\xed\x18\xf2\x0c\xceb\xe9\xf4\x96'
                690     CALL                            1
                698     LOAD_FAST                       8: _var_var_10
                700     FORMAT_VALUE                    0 (FVC_NONE)
                702     PUSH_NULL                       
                704     LOAD_CONST                      1: '__pyarmor_assert_13443__'
                706     LOAD_CONST                      13: '_result.db'   # b'\x81\xdd\n\x16 \xef\xb2\xc6U\xfe\x0f'
                708     CALL                            1
                716     BUILD_STRING                    2
                718     CALL                            3
                726     POP_TOP                         
                728     LOAD_FAST                       0: data
                730     LOAD_CONST                      4: 'Settings'
                732     BINARY_SUBSCR                   
                736     LOAD_ATTR                       7: get
                756     PUSH_NULL                       
                758     LOAD_CONST                      1: '__pyarmor_assert_13443__'
                760     LOAD_CONST                      16: 'direct_send'   # b'\x81\xe6\x11\x016\xf9\xaa\xed\x08\xff\x03\xc4'
                762     CALL                            1
                770     CALL                            1
                778     STORE_FAST                      10: _var_var_12
                780     LOAD_FAST                       0: data
                782     LOAD_CONST                      4: 'Settings'
                784     BINARY_SUBSCR                   
                788     LOAD_CONST                      17: 'message'
                790     BINARY_SUBSCR                   
                794     LOAD_ATTR                       7: get
                814     LOAD_CONST                      18: 'forward'
                816     CALL                            1
                824     STORE_FAST                      11: _var_var_13
                826     LOAD_GLOBAL                     15: NULL + len
                836     LOAD_FAST                       11: _var_var_13
                838     CALL                            1
                846     LOAD_CONST                      19: 0
                848     COMPARE_OP                      68 (>)
                852     POP_JUMP_IF_FALSE               3 (to 860)
                854     LOAD_CONST                      9: True
                856     STORE_FAST                      11: _var_var_13
                858     JUMP_FORWARD                    2 (to 864)
                860     LOAD_CONST                      20: False
                862     STORE_FAST                      11: _var_var_13
                864     LOAD_FAST                       0: data
                866     LOAD_CONST                      4: 'Settings'
                868     BINARY_SUBSCR                   
                872     LOAD_CONST                      17: 'message'
                874     BINARY_SUBSCR                   
                878     LOAD_CONST                      21: 'bots'
                880     BINARY_SUBSCR                   
                884     LOAD_ATTR                       7: get
                904     LOAD_CONST                      22: 'bot'
                906     CALL                            1
                914     STORE_FAST                      12: _var_var_14
                916     LOAD_FAST                       0: data
                918     LOAD_CONST                      4: 'Settings'
                920     BINARY_SUBSCR                   
                924     LOAD_CONST                      17: 'message'
                926     BINARY_SUBSCR                   
                930     LOAD_CONST                      21: 'bots'
                932     BINARY_SUBSCR                   
                936     LOAD_ATTR                       7: get
                956     LOAD_CONST                      23: 'posts'
                958     CALL                            1
                966     STORE_FAST                      13: _var_var_15
                968     LOAD_GLOBAL                     15: NULL + len
                978     LOAD_FAST                       13: _var_var_15
                980     CALL                            1
                988     LOAD_CONST                      19: 0
                990     COMPARE_OP                      68 (>)
                994     POP_JUMP_IF_FALSE               64 (to 1124)
                996     LOAD_CONST                      9: True
                998     STORE_FAST                      10: _var_var_12
                1000    LOAD_FAST                       12: _var_var_14
                1002    LOAD_CONST                      24: ''
                1004    COMPARE_OP                      40 (==)
                1008    POP_JUMP_IF_FALSE               57 (to 1124)
                1010    LOAD_GLOBAL                     17: NULL + eel
                1020    LOAD_ATTR                       18: sendErrorBox
                1040    PUSH_NULL                       
                1042    LOAD_CONST                      1: '__pyarmor_assert_13443__'
                1044    LOAD_CONST                      25: 'Username @PostBot is not specified'   # b'\x81\xd7\x0b\x16!\xf4\xbf\xdf\x1e\xba-\xf0c\xff\xec\xa7\x00I\xfb\xae\xb9\x8b@\xc3\x11/\xb0L\x05\xb2\x17\xe33W$'
                1046    CALL                            1
                1054    CALL                            1
                1062    POP_TOP                         
                1064    LOAD_GLOBAL                     17: NULL + eel
                1074    LOAD_ATTR                       34: HideStopButton
                1094    CALL                            0
                1102    POP_TOP                         
                1104    LOAD_GLOBAL                     3: NULL + StopProgram
                1114    CALL                            0
                1122    RAISE_VARARGS                   1
                1124    LOAD_FAST                       0: data
                1126    LOAD_CONST                      4: 'Settings'
                1128    BINARY_SUBSCR                   
                1132    LOAD_ATTR                       7: get
                1152    PUSH_NULL                       
                1154    LOAD_CONST                      1: '__pyarmor_assert_13443__'
                1156    LOAD_CONST                      26: 'list_names'   # b"\x81\xee\x11\x00'\xc5\xb0\xd3\x16\xff\x1e"
                1158    CALL                            1
                1166    CALL                            1
                1174    STORE_FAST                      14: _var_var_16
                1176    LOAD_GLOBAL                     9: NULL + isinstance
                1186    LOAD_FAST                       14: _var_var_16
                1188    LOAD_GLOBAL                     10: list
                1198    CALL                            2
                1206    POP_JUMP_IF_FALSE               14 (to 1236)
                1208    LOAD_GLOBAL                     15: NULL + len
                1218    LOAD_FAST                       14: _var_var_16
                1220    CALL                            1
                1228    LOAD_CONST                      6: 1
                1230    COMPARE_OP                      2 (<)
                1234    POP_JUMP_IF_FALSE               44 (to 1324)
                1236    LOAD_GLOBAL                     17: NULL + eel
                1246    LOAD_ATTR                       18: sendErrorBox
                1266    LOAD_GLOBAL                     20: Lang
                1276    PUSH_NULL                       
                1278    LOAD_CONST                      1: '__pyarmor_assert_13443__'
                1280    LOAD_CONST                      27: 'no_names_in_list'   # b'\x81\xec\x17,=\xfb\xb3\xd7\x08\xc5\x04\xceS\xe0\xf1\x96\x1b'
                1282    CALL                            1
                1290    BINARY_SUBSCR                   
                1294    CALL                            1
                1302    POP_TOP                         
                1304    LOAD_GLOBAL                     3: NULL + StopProgram
                1314    CALL                            0
                1322    RAISE_VARARGS                   1
                1324    LOAD_GLOBAL                     37: NULL + generator_list
                1334    LOAD_FAST                       14: _var_var_16
                1336    CALL                            1
                1344    STORE_FAST                      15: _var_var_17
                1346    LOAD_FAST                       0: data
                1348    LOAD_CONST                      4: 'Settings'
                1350    BINARY_SUBSCR                   
                1354    LOAD_ATTR                       7: get
                1374    PUSH_NULL                       
                1376    LOAD_CONST                      1: '__pyarmor_assert_13443__'
                1378    LOAD_CONST                      28: 'create_public_link'   # b'\x81\xe1\n\x162\xee\xbb\xed\x0b\xef\x0f\xcce\xef\xc7\x89\x06S\xb0'
                1380    CALL                            1
                1388    CALL                            1
                1396    POP_JUMP_IF_FALSE               100 (to 1598)
                1398    LOAD_FAST                       0: data
                1400    LOAD_CONST                      4: 'Settings'
                1402    BINARY_SUBSCR                   
                1406    LOAD_ATTR                       7: get
                1426    PUSH_NULL                       
                1428    LOAD_CONST                      1: '__pyarmor_assert_13443__'
                1430    LOAD_CONST                      29: 'list_links'   # b"\x81\xee\x11\x00'\xc5\xb2\xdb\x15\xf1\x1e"
                1432    CALL                            1
                1440    CALL                            1
                1448    STORE_FAST                      16: _var_var_18
                1450    LOAD_GLOBAL                     9: NULL + isinstance
                1460    LOAD_FAST                       16: _var_var_18
                1462    LOAD_GLOBAL                     10: list
                1472    CALL                            2
                1480    POP_JUMP_IF_FALSE               14 (to 1510)
                1482    LOAD_GLOBAL                     15: NULL + len
                1492    LOAD_FAST                       16: _var_var_18
                1494    CALL                            1
                1502    LOAD_CONST                      6: 1
                1504    COMPARE_OP                      2 (<)
                1508    POP_JUMP_IF_FALSE               46 (to 1602)
                1510    LOAD_GLOBAL                     17: NULL + eel
                1520    LOAD_ATTR                       18: sendErrorBox
                1540    LOAD_GLOBAL                     20: Lang
                1550    PUSH_NULL                       
                1552    LOAD_CONST                      1: '__pyarmor_assert_13443__'
                1554    LOAD_CONST                      30: 'no_links_in_list'   # b'\x81\xec\x17,?\xf3\xb0\xd9\x08\xc5\x04\xceS\xe0\xf1\x96\x1b'
                1556    CALL                            1
                1564    BINARY_SUBSCR                   
                1568    CALL                            1
                1576    POP_TOP                         
                1578    LOAD_GLOBAL                     3: NULL + StopProgram
                1588    CALL                            0
                1596    RAISE_VARARGS                   1
                1598    LOAD_CONST                      20: False
                1600    STORE_FAST                      16: _var_var_18
                1602    LOAD_GLOBAL                     37: NULL + generator_list
                1612    LOAD_FAST                       16: _var_var_18
                1614    CALL                            1
                1622    STORE_FAST                      17: _var_var_19
                1624    LOAD_FAST                       0: data
                1626    LOAD_CONST                      4: 'Settings'
                1628    BINARY_SUBSCR                   
                1632    LOAD_ATTR                       7: get
                1652    PUSH_NULL                       
                1654    LOAD_CONST                      1: '__pyarmor_assert_13443__'
                1656    LOAD_CONST                      31: 'set_avatar'   # b'\x81\xf1\x1d\x07\x0c\xfb\xa8\xd3\x0f\xfb\x1f'
                1658    CALL                            1
                1666    CALL                            1
                1674    POP_JUMP_IF_FALSE               100 (to 1876)
                1676    LOAD_FAST                       0: data
                1678    LOAD_CONST                      4: 'Settings'
                1680    BINARY_SUBSCR                   
                1684    LOAD_ATTR                       7: get
                1704    PUSH_NULL                       
                1706    LOAD_CONST                      1: '__pyarmor_assert_13443__'
                1708    LOAD_CONST                      32: 'avatar_path'   # b"\x81\xe3\x0e\x12'\xfb\xac\xed\x0b\xfb\x19\xc8"
                1710    CALL                            1
                1718    CALL                            1
                1726    STORE_FAST                      18: _var_var_20
                1728    LOAD_GLOBAL                     9: NULL + isinstance
                1738    LOAD_FAST                       18: _var_var_20
                1740    LOAD_GLOBAL                     10: list
                1750    CALL                            2
                1758    POP_JUMP_IF_FALSE               14 (to 1788)
                1760    LOAD_GLOBAL                     15: NULL + len
                1770    LOAD_FAST                       18: _var_var_20
                1772    CALL                            1
                1780    LOAD_CONST                      6: 1
                1782    COMPARE_OP                      2 (<)
                1786    POP_JUMP_IF_FALSE               46 (to 1880)
                1788    LOAD_GLOBAL                     17: NULL + eel
                1798    LOAD_ATTR                       18: sendErrorBox
                1818    LOAD_GLOBAL                     20: Lang
                1828    PUSH_NULL                       
                1830    LOAD_CONST                      1: '__pyarmor_assert_13443__'
                1832    LOAD_CONST                      33: 'no_image_in_folder'   # b'\x81\xec\x17,:\xf7\xbf\xd5\x1e\xc5\x04\xceS\xea\xf7\x89\x0bX\xa9'
                1834    CALL                            1
                1842    BINARY_SUBSCR                   
                1846    CALL                            1
                1854    POP_TOP                         
                1856    LOAD_GLOBAL                     3: NULL + StopProgram
                1866    CALL                            0
                1874    RAISE_VARARGS                   1
                1876    LOAD_CONST                      20: False
                1878    STORE_FAST                      18: _var_var_20
                1880    LOAD_GLOBAL                     37: NULL + generator_list
                1890    LOAD_FAST                       18: _var_var_20
                1892    CALL                            1
                1900    STORE_FAST                      19: _var_var_21
                1902    LOAD_GLOBAL                     39: NULL + set_task_manager
                1912    LOAD_FAST                       2: pid
                1914    LOAD_FAST                       6: _var_var_8
                1916    LOAD_FAST                       0: data
                1918    LOAD_CONST                      34: 'stuff'
                1920    BINARY_SUBSCR                   
                1924    KW_NAMES                        35: ('accounts', 'name')
                1926    CALL                            3
                1934    POP_TOP                         
                1936    LOAD_GLOBAL                     40: concurrent
                1946    LOAD_ATTR                       42: futures
                1966    LOAD_ATTR                       45: ThreadPoolExecutor
                1986    LOAD_FAST                       7: _var_var_9
                1988    KW_NAMES                        36: ('max_workers',)
                1990    CALL                            1
                1998    BEFORE_WITH                     
                2000    STORE_FAST                      20: _var_var_22
                2002    BUILD_LIST                      0
                2004    STORE_FAST                      21: _var_var_23
                2006    LOAD_GLOBAL                     15: NULL + len
                2016    LOAD_FAST                       6: _var_var_8
                2018    CALL                            1
                2026    STORE_FAST                      22: _var_var_24
                2028    LOAD_FAST                       7: _var_var_9
                2030    STORE_FAST                      23: _var_var_25
                2032    LOAD_FAST                       22: _var_var_24
                2034    STORE_FAST                      24: _var_var_26
                2036    LOAD_CONST                      19: 0
                2038    STORE_FAST                      25: _var_var_27
                2040    LOAD_GLOBAL                     17: NULL + eel
                2050    LOAD_ATTR                       46: StreamStat
                2070    LOAD_GLOBAL                     49: NULL + json
                2080    LOAD_ATTR                       50: dumps
                2100    LOAD_CONST                      37: 'st_task'
                2102    LOAD_FAST                       22: _var_var_24
                2104    PUSH_NULL                       
                2106    LOAD_CONST                      1: '__pyarmor_assert_13443__'
                2108    LOAD_CONST                      38: 'st_stream'   # b'\x81\xf1\x0c, \xee\xac\xd7\x1a\xf7'
                2110    CALL                            1
                2118    LOAD_FAST                       23: _var_var_25
                2120    LOAD_CONST                      39: 'st_wait'
                2122    LOAD_FAST                       24: _var_var_26
                2124    LOAD_CONST                      40: 'st_done'
                2126    LOAD_FAST                       25: _var_var_27
                2128    BUILD_MAP                       4
                2130    CALL                            1
                2138    CALL                            1
                2146    POP_TOP                         
                2148    LOAD_FAST                       6: _var_var_8
                2150    GET_ITER                        
                2152    FOR_ITER                        172 (to 2498)
                2156    STORE_FAST                      26: _var_var_28
                2158    LOAD_GLOBAL                     53: NULL + random
                2168    LOAD_ATTR                       54: randint
                2188    LOAD_GLOBAL                     13: NULL + int
                2198    LOAD_FAST                       0: data
                2200    LOAD_CONST                      4: 'Settings'
                2202    BINARY_SUBSCR                   
                2206    LOAD_ATTR                       7: get
                2226    PUSH_NULL                       
                2228    LOAD_CONST                      1: '__pyarmor_assert_13443__'
                2230    LOAD_CONST                      41: 'kol_channels_from'   # b'\x81\xe9\x17\x1f\x0c\xf9\xb6\xd3\x15\xf4\x08\xcc\x7f\xd3\xfe\x97\x00P'
                2232    CALL                            1
                2240    CALL                            1
                2248    CALL                            1
                2256    LOAD_GLOBAL                     13: NULL + int
                2266    LOAD_FAST                       0: data
                2268    LOAD_CONST                      4: 'Settings'
                2270    BINARY_SUBSCR                   
                2274    LOAD_ATTR                       7: get
                2294    PUSH_NULL                       
                2296    LOAD_CONST                      1: '__pyarmor_assert_13443__'
                2298    LOAD_CONST                      42: 'kol_channels_to'   # b'\x81\xe9\x17\x1f\x0c\xf9\xb6\xd3\x15\xf4\x08\xcc\x7f\xd3\xec\x8a'
                2300    CALL                            1
                2308    CALL                            1
                2316    CALL                            1
                2324    CALL                            2
                2332    STORE_FAST                      27: _var_var_29
                2334    LOAD_GLOBAL                     57: NULL + generator_get
                2344    LOAD_FAST                       27: _var_var_29
                2346    LOAD_FAST                       15: _var_var_17
                2348    CALL                            2
                2356    STORE_FAST                      14: _var_var_16
                2358    LOAD_GLOBAL                     57: NULL + generator_get
                2368    LOAD_FAST                       27: _var_var_29
                2370    LOAD_FAST                       17: _var_var_19
                2372    CALL                            2
                2380    STORE_FAST                      16: _var_var_18
                2382    LOAD_GLOBAL                     57: NULL + generator_get
                2392    LOAD_FAST                       27: _var_var_29
                2394    LOAD_FAST                       19: _var_var_21
                2396    CALL                            2
                2404    STORE_FAST                      28: _var_var_30
                2406    LOAD_FAST                       21: _var_var_23
                2408    LOAD_ATTR                       59: append
                2428    LOAD_FAST                       20: _var_var_22
                2430    LOAD_ATTR                       61: submit
                2450    LOAD_GLOBAL                     62: worker
                2460    LOAD_FAST                       26: _var_var_28
                2462    LOAD_FAST                       1: config
                2464    LOAD_FAST                       3: proxy
                2466    LOAD_FAST                       0: data
                2468    LOAD_FAST                       9: _var_var_11
                2470    LOAD_FAST                       27: _var_var_29
                2472    LOAD_FAST                       14: _var_var_16
                2474    LOAD_FAST                       16: _var_var_18
                2476    LOAD_FAST                       28: _var_var_30
                2478    LOAD_FAST                       4: stop_thread
                2480    CALL                            11
                2488    CALL                            1
                2496    POP_TOP                         
                2498    JUMP_BACKWARD                   174 (to 2152)
                2500    END_FOR                         
                2502    LOAD_GLOBAL                     40: concurrent
                2512    LOAD_ATTR                       42: futures
                2532    LOAD_ATTR                       65: as_completed
                2552    LOAD_FAST                       21: _var_var_23
                2554    CALL                            1
                2562    GET_ITER                        
                2564    FOR_ITER                        66 (to 2698)
                2568    STORE_FAST                      29: _var_var_31
                2570    LOAD_FAST                       25: _var_var_27
                2572    LOAD_CONST                      6: 1
                2574    BINARY_OP                       13 (+=)
                2578    STORE_FAST                      25: _var_var_27
                2580    LOAD_FAST                       24: _var_var_26
                2582    LOAD_CONST                      6: 1
                2584    BINARY_OP                       23 (-=)
                2588    STORE_FAST                      24: _var_var_26
                2590    LOAD_GLOBAL                     17: NULL + eel
                2600    LOAD_ATTR                       46: StreamStat
                2620    LOAD_GLOBAL                     49: NULL + json
                2630    LOAD_ATTR                       50: dumps
                2650    LOAD_CONST                      37: 'st_task'
                2652    LOAD_FAST                       22: _var_var_24
                2654    PUSH_NULL                       
                2656    LOAD_CONST                      1: '__pyarmor_assert_13443__'
                2658    LOAD_CONST                      38: 'st_stream'   # b'\x81\xf1\x0c, \xee\xac\xd7\x1a\xf7'
                2660    CALL                            1
                2668    LOAD_FAST                       23: _var_var_25
                2670    LOAD_CONST                      39: 'st_wait'
                2672    LOAD_FAST                       24: _var_var_26
                2674    LOAD_CONST                      40: 'st_done'
                2676    LOAD_FAST                       25: _var_var_27
                2678    BUILD_MAP                       4
                2680    CALL                            1
                2688    CALL                            1
                2696    POP_TOP                         
                2698    JUMP_BACKWARD                   68 (to 2564)
                2700    END_FOR                         
                2702    DELETE_FAST                     21: _var_var_23
                2704    DELETE_FAST                     0: data
                2706    LOAD_CONST                      0: None
                2708    LOAD_CONST                      0: None
                2710    LOAD_CONST                      0: None
                2712    CALL                            2
                2720    POP_TOP                         
                2722    LOAD_GLOBAL                     71: NULL + del_task_manager
                2732    LOAD_FAST                       2: pid
                2734    CALL                            1
                2742    POP_TOP                         
                2744    LOAD_GLOBAL                     73: NULL + StopDetect
                2754    LOAD_FAST                       4: stop_thread
                2756    CALL                            1
                2764    POP_TOP                         
                2766    NOP                             
                2768    LOAD_CONST                      44: 'Done'
                2770    NOP                             
                2772    NOP                             
                2774    NOP                             
                2776    JUMP_FORWARD                    117 (to 3012)
                2784    POP_TOP                         
                2786    RETURN_CONST                    44: 'Done'
                2788    PUSH_EXC_INFO                   
                2790    WITH_EXCEPT_START               
                2792    POP_JUMP_IF_TRUE                1 (to 2796)
                2794    RERAISE                         2
                2796    POP_TOP                         
                2798    POP_EXCEPT                      
                2800    POP_TOP                         
                2802    POP_TOP                         
                2804    JUMP_BACKWARD                   42 (to 2722)
                2806    COPY                            3
                2808    POP_EXCEPT                      
                2810    RERAISE                         1
                2812    PUSH_EXC_INFO                   
                2814    LOAD_GLOBAL                     2: StopProgram
                2824    CHECK_EXC_MATCH                 
                2826    POP_JUMP_IF_FALSE               3 (to 2834)
                2828    POP_TOP                         
                2830    POP_EXCEPT                      
                2832    JUMP_BACKWARD                   56 (to 2722)
                2834    LOAD_GLOBAL                     66: BaseException
                2844    CHECK_EXC_MATCH                 
                2846    POP_JUMP_IF_FALSE               26 (to 2900)
                2848    STORE_FAST                      30: _var_var_3
                2850    PUSH_NULL                       
                2852    LOAD_GLOBAL                     69: NULL + logging
                2862    LOAD_FAST                       30: _var_var_3
                2864    CALL                            1
                2872    CALL                            0
                2880    POP_TOP                         
                2882    POP_EXCEPT                      
                2884    LOAD_CONST                      0: None
                2886    STORE_FAST                      30: _var_var_3
                2888    DELETE_FAST                     30: _var_var_3
                2890    JUMP_BACKWARD                   85 (to 2722)
                2892    LOAD_CONST                      0: None
                2894    STORE_FAST                      30: _var_var_3
                2896    DELETE_FAST                     30: _var_var_3
                2898    RERAISE                         1
                2900    RERAISE                         0
                2902    COPY                            3
                2904    POP_EXCEPT                      
                2906    RERAISE                         1
                2908    PUSH_EXC_INFO                   
                2910    LOAD_GLOBAL                     71: NULL + del_task_manager
                2920    LOAD_FAST                       2: pid
                2922    CALL                            1
                2930    POP_TOP                         
                2932    LOAD_GLOBAL                     73: NULL + StopDetect
                2942    LOAD_FAST                       4: stop_thread
                2944    CALL                            1
                2952    POP_TOP                         
                2954    POP_TOP                         
                2956    POP_EXCEPT                      
                2958    LOAD_CONST                      44: 'Done'
                2960    NOP                             
                2962    NOP                             
                2964    NOP                             
                2966    JUMP_FORWARD                    22 (to 3012)
                2974    POP_TOP                         
                2976    RETURN_CONST                    44: 'Done'
                2978    COPY                            3
                2980    POP_EXCEPT                      
                2982    RERAISE                         1
                2984    PUSH_EXC_INFO                   
                2986    PUSH_NULL                       
                2988    LOAD_CONST                      43: '__pyarmor_exit_13445__'
                2990    NOP                             
                2992    LOAD_CONST                      3: b'<COAddr>\x07\x00\x00\x1a\x8e\x0b\x00\x00\x00\x00\x00\x00\x00\x00\x00\x00\x00\x00\x00\x00'
                2994    CALL                            1
                3002    POP_TOP                         
                3004    RERAISE                         0
                3006    COPY                            3
                3008    POP_EXCEPT                      
                3010    RERAISE                         1
                3012    PUSH_NULL                       
                3014    LOAD_CONST                      43: '__pyarmor_exit_13445__'
                3016    LOAD_CONST                      3: b'<COAddr>\x07\x00\x00\x1a\x8e\x0b\x00\x00\x00\x00\x00\x00\x00\x00\x00\x00\x00\x00\x00\x00'
                3018    BUILD_TUPLE                     1
                3020    CALL_FUNCTION_EX                0
                3022    POP_TOP                         
                3024    RETURN_VALUE                    
            [Exception Table]
                30 to 2000 -> 2812 [0] 
                2000 to 2706 -> 2788 [1] lasti
                2706 to 2722 -> 2812 [0] 
                2722 to 2766 -> 2984 [0] 
                2788 to 2798 -> 2806 [3] lasti
                2798 to 2812 -> 2812 [0] 
                2812 to 2830 -> 2902 [1] lasti
                2830 to 2834 -> 2908 [0] 
                2834 to 2850 -> 2902 [1] lasti
                2850 to 2882 -> 2892 [1] lasti
                2882 to 2892 -> 2908 [0] 
                2892 to 2902 -> 2902 [1] lasti
                2902 to 2908 -> 2908 [0] 
                2908 to 2956 -> 2978 [1] lasti
                2956 to 2958 -> 2984 [0] 
                2978 to 2984 -> 2984 [0] 
                2984 to 3006 -> 3006 [1] lasti
        [Code]
            File Name: <frozen program.modules.Create_channels>
            Object Name: channel_create
            Qualified Name: channel_create
            Arg Count: 5
            Pos Only Arg Count: 0
            KW Only Arg Count: 0
            Stack Size: 8
            Flags: 0x20000003 (CO_OPTIMIZED | CO_NEWLOCALS | CO_PYARMOR_OBFUSCATED)
            [Names]
                'functions'
                'channels'
                'CreateChannelRequest'
                'chats'
                'Logs'
                'PrintLog'
                'config'
                'Lang'
                'Exception'
            [Locals+Names]
                'account'
                'client'
                'channel_name'
                'broadcast'
                'megagroup'
                '__assert_armored__'
                '_var_var_32'
                '_var_var_33'
                '_var_var_3'
            [Constants]
                None
                '__pyarmor_assert_13446__'
                '__pyarmor_enter_13447__'
                b'<COAddr>\x05\x00\x00\x1ab\x01\x00\x00\x00\x00\x00\x00\x00\x00\x00\x00\x00\x00\x00\x00'
                ''
                (
                    'title'
                    'about'
                    'broadcast'
                    'megagroup'
                )
                0
                'chat_created'   # b"\x81\xe1\x10\x12'\xc5\xbd\xc0\x1e\xfb\x19\xc5h"
                (
                    'config'
                    'account'
                    'message'
                )
                '__pyarmor_exit_13448__'
                'Error create channel or channel:'   # b'\x81\xc7\n\x01<\xe8\xfe\xd1\t\xff\x0c\xd4i\xac\xfb\x8d\x0eS\xb5\xa2\xa6\x8bA\xdeEl\xab]\x0e\xbf\x1b\xe9`'
                (
                    'config'
                    'account'
                    'message'
                    'param'
                )
                False
            [Disassembly]
                0       NOP                             
                2       NOP                             
                4       PUSH_NULL                       
                6       LOAD_CONST                      2: '__pyarmor_enter_13447__'
                8       LOAD_CONST                      3: b'<COAddr>\x05\x00\x00\x1ab\x01\x00\x00\x00\x00\x00\x00\x00\x00\x00\x00\x00\x00\x00\x00'
                10      BUILD_TUPLE                     1
                12      CALL_FUNCTION_EX                0
                14      POP_TOP                         
                16      RESUME                          0
                18      NOP                             
                20      NOP                             
                22      NOP                             
                24      NOP                             
                26      NOP                             
                28      NOP                             
                30      PUSH_NULL                       
                32      LOAD_FAST                       1: client
                34      LOAD_GLOBAL                     0: functions
                44      LOAD_ATTR                       2: channels
                64      LOAD_ATTR                       5: CreateChannelRequest
                84      LOAD_FAST                       2: channel_name
                86      LOAD_CONST                      4: ''
                88      LOAD_FAST                       3: broadcast
                90      LOAD_FAST                       4: megagroup
                92      KW_NAMES                        5: ('title', 'about', 'broadcast', 'megagroup')
                94      CALL                            4
                102     CALL                            1
                110     STORE_FAST                      6: _var_var_32
                112     LOAD_FAST                       6: _var_var_32
                114     LOAD_ATTR                       6: chats
                134     LOAD_CONST                      6: 0
                136     BINARY_SUBSCR                   
                140     STORE_FAST                      7: _var_var_33
                142     LOAD_GLOBAL                     9: NULL + Logs
                152     LOAD_ATTR                       10: PrintLog
                172     LOAD_GLOBAL                     12: config
                182     LOAD_FAST                       0: account
                184     LOAD_GLOBAL                     14: Lang
                194     PUSH_NULL                       
                196     LOAD_CONST                      1: '__pyarmor_assert_13446__'
                198     LOAD_CONST                      7: 'chat_created'   # b"\x81\xe1\x10\x12'\xc5\xbd\xc0\x1e\xfb\x19\xc5h"
                200     CALL                            1
                208     BINARY_SUBSCR                   
                212     KW_NAMES                        8: ('config', 'account', 'message')
                214     CALL                            3
                222     POP_TOP                         
                224     LOAD_FAST                       7: _var_var_33
                226     NOP                             
                228     NOP                             
                230     NOP                             
                232     JUMP_FORWARD                    87 (to 408)
                234     CALL                            1
                242     POP_TOP                         
                244     RETURN_VALUE                    
                246     PUSH_EXC_INFO                   
                248     LOAD_GLOBAL                     16: Exception
                258     CHECK_EXC_MATCH                 
                260     POP_JUMP_IF_FALSE               45 (to 352)
                262     STORE_FAST                      8: _var_var_3
                264     LOAD_GLOBAL                     9: NULL + Logs
                274     LOAD_ATTR                       10: PrintLog
                294     LOAD_GLOBAL                     12: config
                304     LOAD_FAST                       0: account
                306     PUSH_NULL                       
                308     LOAD_CONST                      1: '__pyarmor_assert_13446__'
                310     LOAD_CONST                      10: 'Error create channel or channel:'   # b'\x81\xc7\n\x01<\xe8\xfe\xd1\t\xff\x0c\xd4i\xac\xfb\x8d\x0eS\xb5\xa2\xa6\x8bA\xdeEl\xab]\x0e\xbf\x1b\xe9`'
                312     CALL                            1
                320     LOAD_FAST                       8: _var_var_3
                322     KW_NAMES                        11: ('config', 'account', 'message', 'param')
                324     CALL                            4
                332     POP_TOP                         
                334     POP_EXCEPT                      
                336     LOAD_CONST                      0: None
                338     STORE_FAST                      8: _var_var_3
                340     DELETE_FAST                     8: _var_var_3
                342     JUMP_FORWARD                    8 (to 360)
                344     LOAD_CONST                      0: None
                346     STORE_FAST                      8: _var_var_3
                348     DELETE_FAST                     8: _var_var_3
                350     RERAISE                         1
                352     RERAISE                         0
                354     COPY                            3
                356     POP_EXCEPT                      
                358     RERAISE                         1
                360     LOAD_CONST                      12: False
                362     NOP                             
                364     NOP                             
                366     NOP                             
                368     JUMP_FORWARD                    19 (to 408)
                376     POP_TOP                         
                378     RETURN_CONST                    12: False
                380     PUSH_EXC_INFO                   
                382     PUSH_NULL                       
                384     LOAD_CONST                      9: '__pyarmor_exit_13448__'
                386     NOP                             
                388     LOAD_CONST                      3: b'<COAddr>\x05\x00\x00\x1ab\x01\x00\x00\x00\x00\x00\x00\x00\x00\x00\x00\x00\x00\x00\x00'
                390     CALL                            1
                398     POP_TOP                         
                400     RERAISE                         0
                402     COPY                            3
                404     POP_EXCEPT                      
                406     RERAISE                         1
                408     PUSH_NULL                       
                410     LOAD_CONST                      9: '__pyarmor_exit_13448__'
                412     LOAD_CONST                      3: b'<COAddr>\x05\x00\x00\x1ab\x01\x00\x00\x00\x00\x00\x00\x00\x00\x00\x00\x00\x00\x00\x00'
                414     BUILD_TUPLE                     1
                416     CALL_FUNCTION_EX                0
                418     POP_TOP                         
                420     RETURN_VALUE                    
            [Exception Table]
                30 to 226 -> 246 [0] 
                246 to 264 -> 354 [1] lasti
                264 to 334 -> 344 [1] lasti
                334 to 344 -> 380 [0] 
                344 to 354 -> 354 [1] lasti
                354 to 360 -> 380 [0] 
                380 to 402 -> 402 [1] lasti
        [Code]
            File Name: <frozen program.modules.Create_channels>
            Object Name: channel_set_username
            Qualified Name: channel_set_username
            Arg Count: 6
            Pos Only Arg Count: 0
            KW Only Arg Count: 0
            Stack Size: 9
            Flags: 0x20000003 (CO_OPTIMIZED | CO_NEWLOCALS | CO_PYARMOR_OBFUSCATED)
            [Names]
                'functions'
                'channels'
                'UpdateUsernameRequest'
                'errors'
                'UsernameInvalidError'
                'UsernameNotModifiedError'
                'UsernameOccupiedError'
                'UsernameNotOccupiedError'
                'UsernamePurchaseAvailableError'
                'time'
                'sleep'
                'FloodWaitError'
                'Logs'
                'PrintLog'
                'config'
                'Lang'
                'int'
                'seconds'
                'DelayOnline'
                'Exception'
            [Locals+Names]
                'account'
                'client'
                'channel'
                'channel_link'
                'stop_thread'
                'max_flood_wait'
                '__assert_armored__'
                '_var_var_34'
                '_var_var_35'
                '_var_var_36'
                '_var_var_37'
                '_var_var_3'
                '_var_var_38'
            [Constants]
                None
                '__pyarmor_assert_13449__'
                '__pyarmor_enter_13450__'
                b'<COAddr>\x05\x00\x00\x1a\x84\x04\x00\x00\x00\x00\x00\x00\x00\x00\x00\x00\x00\x00\x00\x00'
                [Code]
                    File Name: <frozen program.modules.Create_channels>
                    Object Name: get_random_username
                    Qualified Name: channel_set_username.<locals>.get_random_username
                    Arg Count: 1
                    Pos Only Arg Count: 0
                    KW Only Arg Count: 0
                    Stack Size: 6
                    Flags: 0x20000013 (CO_OPTIMIZED | CO_NEWLOCALS | CO_NESTED | CO_PYARMOR_OBFUSCATED)
                    [Names]
                        'join'
                        'range'
                    [Locals+Names]
                        'username'
                        '__assert_armored__'
                        '_var_var_39'
                    [Constants]
                        None
                        '__pyarmor_assert_13452__'
                        '__pyarmor_enter_13453__'
                        b'<COAddr>\x07\x00\x00\x1af\x00\x00\x00\x00\x00\x00\x00\x00\x00\x00\x00\x00\x00\x00\x00'
                        ''
                        [Code]
                            File Name: <frozen program.modules.Create_channels>
                            Object Name: <genexpr>
                            Qualified Name: channel_set_username.<locals>.get_random_username.<locals>.<genexpr>
                            Arg Count: 1
                            Pos Only Arg Count: 0
                            KW Only Arg Count: 0
                            Stack Size: 4
                            Flags: 0x00000033 (CO_OPTIMIZED | CO_NEWLOCALS | CO_NESTED | CO_GENERATOR)
                            [Names]
                                'random'
                                'choice'
                                'string'
                                'ascii_lowercase'
                            [Locals+Names]
                                '.0'
                                '_var_var_40'
                            [Constants]
                                None
                            [Disassembly]
                                0       RETURN_GENERATOR                
                                2       POP_TOP                         
                                4       RESUME                          0
                                6       LOAD_FAST                       0: .0
                                8       FOR_ITER                        39 (to 88)
                                12      STORE_FAST                      1: _var_var_40
                                14      LOAD_GLOBAL                     1: NULL + random
                                24      LOAD_ATTR                       2: choice
                                44      LOAD_GLOBAL                     4: string
                                54      LOAD_ATTR                       6: ascii_lowercase
                                74      CALL                            1
                                82      YIELD_VALUE                     1
                                84      RESUME                          1
                                86      POP_TOP                         
                                88      JUMP_BACKWARD                   41 (to 8)
                                90      END_FOR                         
                                92      RETURN_CONST                    0: None
                                94      CALL_INTRINSIC_1                3 (INTRINSIC_STOPITERATION_ERROR)
                                96      RERAISE                         1
                            [Exception Table]
                                4 to 94 -> 94 [0] lasti
                        5
                        '__pyarmor_exit_13454__'
                    [Disassembly]
                        0       NOP                             
                        2       NOP                             
                        4       PUSH_NULL                       
                        6       LOAD_CONST                      2: '__pyarmor_enter_13453__'
                        8       LOAD_CONST                      3: b'<COAddr>\x07\x00\x00\x1af\x00\x00\x00\x00\x00\x00\x00\x00\x00\x00\x00\x00\x00\x00\x00'
                        10      BUILD_TUPLE                     1
                        12      CALL_FUNCTION_EX                0
                        14      POP_TOP                         
                        16      RESUME                          0
                        18      NOP                             
                        20      NOP                             
                        22      NOP                             
                        24      NOP                             
                        26      NOP                             
                        28      LOAD_CONST                      4: ''
                        30      LOAD_ATTR                       1: join
                        50      LOAD_CONST                      5: <CODE> <genexpr>
                        52      MAKE_FUNCTION                   0
                        54      LOAD_GLOBAL                     3: NULL + range
                        64      LOAD_CONST                      6: 5
                        66      CALL                            1
                        74      GET_ITER                        
                        76      CALL                            0
                        84      CALL                            1
                        92      STORE_FAST                      2: _var_var_39
                        94      LOAD_FAST                       0: username
                        96      LOAD_CONST                      4: ''
                        98      BINARY_OP                       0 (+)
                        102     LOAD_FAST                       2: _var_var_39
                        104     BINARY_OP                       0 (+)
                        108     NOP                             
                        110     NOP                             
                        112     NOP                             
                        114     JUMP_FORWARD                    20 (to 156)
                        116     CALL                            1
                        124     POP_TOP                         
                        126     RETURN_VALUE                    
                        128     PUSH_EXC_INFO                   
                        130     PUSH_NULL                       
                        132     LOAD_CONST                      7: '__pyarmor_exit_13454__'
                        134     NOP                             
                        136     LOAD_CONST                      3: b'<COAddr>\x07\x00\x00\x1af\x00\x00\x00\x00\x00\x00\x00\x00\x00\x00\x00\x00\x00\x00\x00'
                        138     CALL                            1
                        146     POP_TOP                         
                        148     RERAISE                         0
                        150     COPY                            3
                        152     POP_EXCEPT                      
                        154     RERAISE                         1
                        156     PUSH_NULL                       
                        158     LOAD_CONST                      7: '__pyarmor_exit_13454__'
                        160     LOAD_CONST                      3: b'<COAddr>\x07\x00\x00\x1af\x00\x00\x00\x00\x00\x00\x00\x00\x00\x00\x00\x00\x00\x00\x00'
                        162     BUILD_TUPLE                     1
                        164     CALL_FUNCTION_EX                0
                        166     POP_TOP                         
                        168     RETURN_VALUE                    
                    [Exception Table]
                        28 to 108 -> 128 [0] 
                        128 to 150 -> 150 [1] lasti
                5
                (
                    'channel'
                    'username'
                )
                '__pyarmor_exit_13451__'
                1
                0
                'restriction_detected'   # b"\x81\xf0\x1d\x00'\xe8\xb7\xd1\x0f\xf3\x02\xceS\xe8\xfd\x91\n^\xaf\xa2\xae"
                (
                    'config'
                    'account'
                    'message'
                )
                'algorithm_running'   # b'\x81\xe3\x14\x14<\xe8\xb7\xc6\x13\xf72\xd2y\xe2\xf6\x8c\x01Z'
                'flood_wait_more_sec'   # b'\x81\xe4\x14\x1c<\xfe\x81\xc5\x1a\xf3\x19\xffa\xe3\xea\x800N\xbe\xa4'
                (
                    'config'
                    'account'
                    'message'
                    'param'
                )
                'sending_stopped'   # b'\x81\xf1\x1d\x1d7\xf3\xb0\xd5$\xe9\x19\xcf|\xfc\xfd\x81'
                'algorithm_running_wait'   # b'\x81\xe3\x14\x14<\xe8\xb7\xc6\x13\xf72\xd2y\xe2\xf6\x8c\x01Z\x84\xb0\xab\xc2Z'
                'back_in_ranks'   # b'\x81\xe0\x19\x108\xc5\xb7\xdc$\xe8\x0c\xceg\xff'
                'channel set username:'   # b'\x81\xe1\x10\x12=\xf4\xbb\xde[\xe9\x08\xd4,\xf9\xeb\x80\x1dS\xba\xaa\xaf\x91'
                False
            [Disassembly]
                0       NOP                             
                2       NOP                             
                4       PUSH_NULL                       
                6       LOAD_CONST                      2: '__pyarmor_enter_13450__'
                8       LOAD_CONST                      3: b'<COAddr>\x05\x00\x00\x1a\x84\x04\x00\x00\x00\x00\x00\x00\x00\x00\x00\x00\x00\x00\x00\x00'
                10      BUILD_TUPLE                     1
                12      CALL_FUNCTION_EX                0
                14      POP_TOP                         
                16      RESUME                          0
                18      NOP                             
                20      NOP                             
                22      NOP                             
                24      NOP                             
                26      NOP                             
                28      LOAD_CONST                      4: <CODE> get_random_username
                30      MAKE_FUNCTION                   0
                32      STORE_FAST                      7: _var_var_34
                34      LOAD_CONST                      5: 5
                36      STORE_FAST                      8: _var_var_35
                38      LOAD_FAST                       3: channel_link
                40      STORE_FAST                      9: _var_var_36
                42      NOP                             
                44      NOP                             
                46      PUSH_NULL                       
                48      LOAD_FAST                       1: client
                50      LOAD_GLOBAL                     0: functions
                60      LOAD_ATTR                       2: channels
                80      LOAD_ATTR                       5: UpdateUsernameRequest
                100     LOAD_FAST                       2: channel
                102     LOAD_FAST                       9: _var_var_36
                104     KW_NAMES                        6: ('channel', 'username')
                106     CALL                            2
                114     CALL                            1
                122     POP_TOP                         
                124     LOAD_FAST                       9: _var_var_36
                126     NOP                             
                128     NOP                             
                130     JUMP_FORWARD                    538 (to 1210)
                134     CALL                            1
                142     POP_TOP                         
                144     RETURN_VALUE                    
                146     PUSH_EXC_INFO                   
                148     LOAD_GLOBAL                     6: errors
                158     LOAD_ATTR                       8: UsernameInvalidError
                178     LOAD_GLOBAL                     6: errors
                188     LOAD_ATTR                       10: UsernameNotModifiedError
                208     LOAD_GLOBAL                     6: errors
                218     LOAD_ATTR                       12: UsernameOccupiedError
                238     LOAD_GLOBAL                     6: errors
                248     LOAD_ATTR                       14: UsernameNotOccupiedError
                268     LOAD_GLOBAL                     6: errors
                278     LOAD_ATTR                       16: UsernamePurchaseAvailableError
                298     BUILD_TUPLE                     5
                300     CHECK_EXC_MATCH                 
                302     POP_JUMP_IF_FALSE               46 (to 396)
                304     POP_TOP                         
                306     PUSH_NULL                       
                308     LOAD_FAST                       7: _var_var_34
                310     LOAD_FAST                       9: _var_var_36
                312     CALL                            1
                320     STORE_FAST                      9: _var_var_36
                322     LOAD_GLOBAL                     19: NULL + time
                332     LOAD_ATTR                       20: sleep
                352     LOAD_CONST                      8: 1
                354     CALL                            1
                362     POP_TOP                         
                364     LOAD_FAST                       8: _var_var_35
                366     LOAD_CONST                      8: 1
                368     BINARY_OP                       23 (-=)
                372     STORE_FAST                      8: _var_var_35
                374     LOAD_FAST                       8: _var_var_35
                376     LOAD_CONST                      9: 0
                378     COMPARE_OP                      40 (==)
                382     POP_JUMP_IF_FALSE               3 (to 390)
                384     POP_EXCEPT                      
                386     JUMP_FORWARD                    386 (to 1162)
                390     POP_EXCEPT                      
                392     JUMP_FORWARD                    381 (to 1158)
                396     LOAD_GLOBAL                     6: errors
                406     LOAD_ATTR                       22: FloodWaitError
                426     CHECK_EXC_MATCH                 
                428     POP_JUMP_IF_FALSE               307 (to 1046)
                432     STORE_FAST                      10: _var_var_37
                434     LOAD_GLOBAL                     25: NULL + Logs
                444     LOAD_ATTR                       26: PrintLog
                464     LOAD_GLOBAL                     28: config
                474     LOAD_FAST                       0: account
                476     LOAD_GLOBAL                     30: Lang
                486     PUSH_NULL                       
                488     LOAD_CONST                      1: '__pyarmor_assert_13449__'
                490     LOAD_CONST                      10: 'restriction_detected'   # b"\x81\xf0\x1d\x00'\xe8\xb7\xd1\x0f\xf3\x02\xceS\xe8\xfd\x91\n^\xaf\xa2\xae"
                492     CALL                            1
                500     BINARY_SUBSCR                   
                504     KW_NAMES                        11: ('config', 'account', 'message')
                506     CALL                            3
                514     POP_TOP                         
                516     LOAD_GLOBAL                     25: NULL + Logs
                526     LOAD_ATTR                       26: PrintLog
                546     LOAD_GLOBAL                     28: config
                556     LOAD_FAST                       0: account
                558     LOAD_GLOBAL                     30: Lang
                568     PUSH_NULL                       
                570     LOAD_CONST                      1: '__pyarmor_assert_13449__'
                572     LOAD_CONST                      12: 'algorithm_running'   # b'\x81\xe3\x14\x14<\xe8\xb7\xc6\x13\xf72\xd2y\xe2\xf6\x8c\x01Z'
                574     CALL                            1
                582     BINARY_SUBSCR                   
                586     KW_NAMES                        11: ('config', 'account', 'message')
                588     CALL                            3
                596     POP_TOP                         
                598     LOAD_GLOBAL                     33: NULL + int
                608     LOAD_FAST_CHECK                 11: _var_var_3
                610     LOAD_ATTR                       34: seconds
                630     CALL                            1
                638     LOAD_CONST                      5: 5
                640     BINARY_OP                       0 (+)
                644     STORE_FAST                      12: _var_var_38
                646     LOAD_FAST                       12: _var_var_38
                648     LOAD_FAST                       5: max_flood_wait
                650     COMPARE_OP                      68 (>)
                654     POP_JUMP_IF_FALSE               88 (to 832)
                656     LOAD_GLOBAL                     25: NULL + Logs
                666     LOAD_ATTR                       26: PrintLog
                686     LOAD_GLOBAL                     28: config
                696     LOAD_FAST                       0: account
                698     LOAD_GLOBAL                     30: Lang
                708     PUSH_NULL                       
                710     LOAD_CONST                      1: '__pyarmor_assert_13449__'
                712     LOAD_CONST                      13: 'flood_wait_more_sec'   # b'\x81\xe4\x14\x1c<\xfe\x81\xc5\x1a\xf3\x19\xffa\xe3\xea\x800N\xbe\xa4'
                714     CALL                            1
                722     BINARY_SUBSCR                   
                726     LOAD_FAST                       5: max_flood_wait
                728     KW_NAMES                        14: ('config', 'account', 'message', 'param')
                730     CALL                            4
                738     POP_TOP                         
                740     LOAD_GLOBAL                     25: NULL + Logs
                750     LOAD_ATTR                       26: PrintLog
                770     LOAD_GLOBAL                     28: config
                780     LOAD_FAST                       0: account
                782     LOAD_GLOBAL                     30: Lang
                792     PUSH_NULL                       
                794     LOAD_CONST                      1: '__pyarmor_assert_13449__'
                796     LOAD_CONST                      15: 'sending_stopped'   # b'\x81\xf1\x1d\x1d7\xf3\xb0\xd5$\xe9\x19\xcf|\xfc\xfd\x81'
                798     CALL                            1
                806     BINARY_SUBSCR                   
                810     KW_NAMES                        11: ('config', 'account', 'message')
                812     CALL                            3
                820     POP_TOP                         
                822     POP_EXCEPT                      
                824     LOAD_CONST                      0: None
                826     STORE_FAST                      10: _var_var_37
                828     DELETE_FAST                     10: _var_var_37
                830     JUMP_FORWARD                    165 (to 1162)
                832     LOAD_GLOBAL                     25: NULL + Logs
                842     LOAD_ATTR                       26: PrintLog
                862     LOAD_GLOBAL                     28: config
                872     LOAD_FAST                       0: account
                874     LOAD_GLOBAL                     30: Lang
                884     PUSH_NULL                       
                886     LOAD_CONST                      1: '__pyarmor_assert_13449__'
                888     LOAD_CONST                      16: 'algorithm_running_wait'   # b'\x81\xe3\x14\x14<\xe8\xb7\xc6\x13\xf72\xd2y\xe2\xf6\x8c\x01Z\x84\xb0\xab\xc2Z'
                890     CALL                            1
                898     BINARY_SUBSCR                   
                902     LOAD_FAST                       12: _var_var_38
                904     KW_NAMES                        14: ('config', 'account', 'message', 'param')
                906     CALL                            4
                914     POP_TOP                         
                916     LOAD_GLOBAL                     37: NULL + DelayOnline
                926     LOAD_FAST                       0: account
                928     LOAD_FAST                       1: client
                930     LOAD_FAST                       12: _var_var_38
                932     LOAD_FAST                       12: _var_var_38
                934     LOAD_FAST                       4: stop_thread
                936     CALL                            5
                944     POP_TOP                         
                946     LOAD_GLOBAL                     25: NULL + Logs
                956     LOAD_ATTR                       26: PrintLog
                976     LOAD_GLOBAL                     28: config
                986     LOAD_FAST                       0: account
                988     LOAD_GLOBAL                     30: Lang
                998     PUSH_NULL                       
                1000    LOAD_CONST                      1: '__pyarmor_assert_13449__'
                1002    LOAD_CONST                      17: 'back_in_ranks'   # b'\x81\xe0\x19\x108\xc5\xb7\xdc$\xe8\x0c\xceg\xff'
                1004    CALL                            1
                1012    BINARY_SUBSCR                   
                1016    KW_NAMES                        11: ('config', 'account', 'message')
                1018    CALL                            3
                1026    POP_TOP                         
                1028    POP_EXCEPT                      
                1030    LOAD_CONST                      0: None
                1032    STORE_FAST                      10: _var_var_37
                1034    DELETE_FAST                     10: _var_var_37
                1036    JUMP_FORWARD                    60 (to 1158)
                1038    LOAD_CONST                      0: None
                1040    STORE_FAST                      10: _var_var_37
                1042    DELETE_FAST                     10: _var_var_37
                1044    RERAISE                         1
                1046    LOAD_GLOBAL                     38: Exception
                1056    CHECK_EXC_MATCH                 
                1058    POP_JUMP_IF_FALSE               45 (to 1150)
                1060    STORE_FAST                      11: _var_var_3
                1062    LOAD_GLOBAL                     25: NULL + Logs
                1072    LOAD_ATTR                       26: PrintLog
                1092    LOAD_GLOBAL                     28: config
                1102    LOAD_FAST                       0: account
                1104    PUSH_NULL                       
                1106    LOAD_CONST                      1: '__pyarmor_assert_13449__'
                1108    LOAD_CONST                      18: 'channel set username:'   # b'\x81\xe1\x10\x12=\xf4\xbb\xde[\xe9\x08\xd4,\xf9\xeb\x80\x1dS\xba\xaa\xaf\x91'
                1110    CALL                            1
                1118    LOAD_FAST                       11: _var_var_3
                1120    KW_NAMES                        14: ('config', 'account', 'message', 'param')
                1122    CALL                            4
                1130    POP_TOP                         
                1132    POP_EXCEPT                      
                1134    LOAD_CONST                      0: None
                1136    STORE_FAST                      11: _var_var_3
                1138    DELETE_FAST                     11: _var_var_3
                1140    JUMP_FORWARD                    10 (to 1162)
                1142    LOAD_CONST                      0: None
                1144    STORE_FAST                      11: _var_var_3
                1146    DELETE_FAST                     11: _var_var_3
                1148    RERAISE                         1
                1150    RERAISE                         0
                1152    COPY                            3
                1154    POP_EXCEPT                      
                1156    RERAISE                         1
                1158    JUMP_BACKWARD                   559 (to 44)
                1162    LOAD_CONST                      19: False
                1164    NOP                             
                1166    NOP                             
                1168    NOP                             
                1170    JUMP_FORWARD                    19 (to 1210)
                1178    POP_TOP                         
                1180    RETURN_CONST                    19: False
                1182    PUSH_EXC_INFO                   
                1184    PUSH_NULL                       
                1186    LOAD_CONST                      7: '__pyarmor_exit_13451__'
                1188    NOP                             
                1190    LOAD_CONST                      3: b'<COAddr>\x05\x00\x00\x1a\x84\x04\x00\x00\x00\x00\x00\x00\x00\x00\x00\x00\x00\x00\x00\x00'
                1192    CALL                            1
                1200    POP_TOP                         
                1202    RERAISE                         0
                1204    COPY                            3
                1206    POP_EXCEPT                      
                1208    RERAISE                         1
                1210    PUSH_NULL                       
                1212    LOAD_CONST                      7: '__pyarmor_exit_13451__'
                1214    LOAD_CONST                      3: b'<COAddr>\x05\x00\x00\x1a\x84\x04\x00\x00\x00\x00\x00\x00\x00\x00\x00\x00\x00\x00\x00\x00'
                1216    BUILD_TUPLE                     1
                1218    CALL_FUNCTION_EX                0
                1220    POP_TOP                         
                1222    RETURN_VALUE                    
            [Exception Table]
                28 to 44 -> 1182 [0] 
                46 to 126 -> 146 [0] 
                146 to 384 -> 1152 [1] lasti
                384 to 396 -> 1182 [0] 
                396 to 434 -> 1152 [1] lasti
                434 to 822 -> 1038 [1] lasti
                822 to 832 -> 1182 [0] 
                832 to 1028 -> 1038 [1] lasti
                1028 to 1038 -> 1182 [0] 
                1038 to 1062 -> 1152 [1] lasti
                1062 to 1132 -> 1142 [1] lasti
                1132 to 1142 -> 1182 [0] 
                1142 to 1152 -> 1152 [1] lasti
                1152 to 1162 -> 1182 [0] 
                1182 to 1204 -> 1204 [1] lasti
        [Code]
            File Name: <frozen program.modules.Create_channels>
            Object Name: channel_get_link
            Qualified Name: channel_get_link
            Arg Count: 3
            Pos Only Arg Count: 0
            KW Only Arg Count: 0
            Stack Size: 8
            Flags: 0x20000003 (CO_OPTIMIZED | CO_NEWLOCALS | CO_PYARMOR_OBFUSCATED)
            [Names]
                'functions'
                'messages'
                'ExportChatInviteRequest'
                'Logs'
                'PrintLog'
                'config'
                'link'
                'Exception'
            [Locals+Names]
                'account'
                'client'
                'channel'
                '__assert_armored__'
                '_var_var_32'
                '_var_var_3'
            [Constants]
                None
                '__pyarmor_assert_13455__'
                '__pyarmor_enter_13456__'
                b'<COAddr>\x05\x00\x00\x1a\\\x01\x00\x00\x00\x00\x00\x00\x00\x00\x00\x00\x00\x00\x00\x00'
                ''
                (
                    'peer'
                    'title'
                )
                'Get link:'   # b'\x81\xc5\x1d\x07s\xf6\xb7\xdc\x10\xa0'
                (
                    'config'
                    'account'
                    'message'
                    'end'
                )
                '__pyarmor_exit_13457__'
                'channel_get_link'   # b'\x81\xe1\x10\x12=\xf4\xbb\xde$\xfd\x08\xd4S\xe0\xf1\x8b\x04'
                (
                    'config'
                    'account'
                    'message'
                    'param'
                )
                False
            [Disassembly]
                0       NOP                             
                2       NOP                             
                4       PUSH_NULL                       
                6       LOAD_CONST                      2: '__pyarmor_enter_13456__'
                8       LOAD_CONST                      3: b'<COAddr>\x05\x00\x00\x1a\\\x01\x00\x00\x00\x00\x00\x00\x00\x00\x00\x00\x00\x00\x00\x00'
                10      BUILD_TUPLE                     1
                12      CALL_FUNCTION_EX                0
                14      POP_TOP                         
                16      RESUME                          0
                18      NOP                             
                20      NOP                             
                22      NOP                             
                24      NOP                             
                26      NOP                             
                28      NOP                             
                30      PUSH_NULL                       
                32      LOAD_FAST                       1: client
                34      LOAD_GLOBAL                     0: functions
                44      LOAD_ATTR                       2: messages
                64      LOAD_ATTR                       5: ExportChatInviteRequest
                84      LOAD_FAST                       2: channel
                86      LOAD_CONST                      4: ''
                88      KW_NAMES                        5: ('peer', 'title')
                90      CALL                            2
                98      CALL                            1
                106     STORE_FAST                      4: _var_var_32
                108     LOAD_GLOBAL                     7: NULL + Logs
                118     LOAD_ATTR                       8: PrintLog
                138     LOAD_GLOBAL                     10: config
                148     LOAD_FAST                       0: account
                150     PUSH_NULL                       
                152     LOAD_CONST                      1: '__pyarmor_assert_13455__'
                154     LOAD_CONST                      6: 'Get link:'   # b'\x81\xc5\x1d\x07s\xf6\xb7\xdc\x10\xa0'
                156     CALL                            1
                164     LOAD_FAST                       4: _var_var_32
                166     LOAD_ATTR                       12: link
                186     KW_NAMES                        7: ('config', 'account', 'message', 'end')
                188     CALL                            4
                196     POP_TOP                         
                198     LOAD_FAST                       4: _var_var_32
                200     LOAD_ATTR                       12: link
                220     NOP                             
                222     NOP                             
                224     NOP                             
                226     JUMP_FORWARD                    87 (to 402)
                228     CALL                            1
                236     POP_TOP                         
                238     RETURN_VALUE                    
                240     PUSH_EXC_INFO                   
                242     LOAD_GLOBAL                     14: Exception
                252     CHECK_EXC_MATCH                 
                254     POP_JUMP_IF_FALSE               45 (to 346)
                256     STORE_FAST                      5: _var_var_3
                258     LOAD_GLOBAL                     7: NULL + Logs
                268     LOAD_ATTR                       8: PrintLog
                288     LOAD_GLOBAL                     10: config
                298     LOAD_FAST                       0: account
                300     PUSH_NULL                       
                302     LOAD_CONST                      1: '__pyarmor_assert_13455__'
                304     LOAD_CONST                      9: 'channel_get_link'   # b'\x81\xe1\x10\x12=\xf4\xbb\xde$\xfd\x08\xd4S\xe0\xf1\x8b\x04'
                306     CALL                            1
                314     LOAD_FAST                       5: _var_var_3
                316     KW_NAMES                        10: ('config', 'account', 'message', 'param')
                318     CALL                            4
                326     POP_TOP                         
                328     POP_EXCEPT                      
                330     LOAD_CONST                      0: None
                332     STORE_FAST                      5: _var_var_3
                334     DELETE_FAST                     5: _var_var_3
                336     JUMP_FORWARD                    8 (to 354)
                338     LOAD_CONST                      0: None
                340     STORE_FAST                      5: _var_var_3
                342     DELETE_FAST                     5: _var_var_3
                344     RERAISE                         1
                346     RERAISE                         0
                348     COPY                            3
                350     POP_EXCEPT                      
                352     RERAISE                         1
                354     LOAD_CONST                      11: False
                356     NOP                             
                358     NOP                             
                360     NOP                             
                362     JUMP_FORWARD                    19 (to 402)
                370     POP_TOP                         
                372     RETURN_CONST                    11: False
                374     PUSH_EXC_INFO                   
                376     PUSH_NULL                       
                378     LOAD_CONST                      8: '__pyarmor_exit_13457__'
                380     NOP                             
                382     LOAD_CONST                      3: b'<COAddr>\x05\x00\x00\x1a\\\x01\x00\x00\x00\x00\x00\x00\x00\x00\x00\x00\x00\x00\x00\x00'
                384     CALL                            1
                392     POP_TOP                         
                394     RERAISE                         0
                396     COPY                            3
                398     POP_EXCEPT                      
                400     RERAISE                         1
                402     PUSH_NULL                       
                404     LOAD_CONST                      8: '__pyarmor_exit_13457__'
                406     LOAD_CONST                      3: b'<COAddr>\x05\x00\x00\x1a\\\x01\x00\x00\x00\x00\x00\x00\x00\x00\x00\x00\x00\x00\x00\x00'
                408     BUILD_TUPLE                     1
                410     CALL_FUNCTION_EX                0
                412     POP_TOP                         
                414     RETURN_VALUE                    
            [Exception Table]
                30 to 220 -> 240 [0] 
                240 to 258 -> 348 [1] lasti
                258 to 328 -> 338 [1] lasti
                328 to 338 -> 374 [0] 
                338 to 348 -> 348 [1] lasti
                348 to 354 -> 374 [0] 
                374 to 396 -> 396 [1] lasti
        [Code]
            File Name: <frozen program.modules.Create_channels>
            Object Name: channel_set_photo
            Qualified Name: channel_set_photo
            Arg Count: 4
            Pos Only Arg Count: 0
            KW Only Arg Count: 0
            Stack Size: 8
            Flags: 0x20000003 (CO_OPTIMIZED | CO_NEWLOCALS | CO_PYARMOR_OBFUSCATED)
            [Names]
                'functions'
                'channels'
                'EditPhotoRequest'
                'upload_file'
                'Logs'
                'PrintLog'
                'config'
                'Exception'
            [Locals+Names]
                'account'
                'client'
                'channel'
                'channel_img'
                '__assert_armored__'
                '_var_var_3'
            [Constants]
                None
                '__pyarmor_assert_13458__'
                '__pyarmor_enter_13459__'
                b'<COAddr>\x07\x00\x00\x1aP\x01\x00\x00\x00\x00\x00\x00\x00\x00\x00\x00\x00\x00\x00\x00'
                (
                    'channel'
                    'photo'
                )
                'Photo is set'   # b"\x81\xd2\x10\x1c'\xf5\xfe\xdb\x08\xba\x1e\xc5x"
                (
                    'config'
                    'account'
                    'message'
                )
                '__pyarmor_exit_13460__'
                True
                'Photo not set'   # b"\x81\xd2\x10\x1c'\xf5\xfe\xdc\x14\xeeM\xd3i\xf8"
                (
                    'config'
                    'account'
                    'message'
                    'param'
                )
                False
            [Disassembly]
                0       NOP                             
                2       NOP                             
                4       PUSH_NULL                       
                6       LOAD_CONST                      2: '__pyarmor_enter_13459__'
                8       LOAD_CONST                      3: b'<COAddr>\x07\x00\x00\x1aP\x01\x00\x00\x00\x00\x00\x00\x00\x00\x00\x00\x00\x00\x00\x00'
                10      BUILD_TUPLE                     1
                12      CALL_FUNCTION_EX                0
                14      POP_TOP                         
                16      RESUME                          0
                18      NOP                             
                20      NOP                             
                22      NOP                             
                24      NOP                             
                26      NOP                             
                28      NOP                             
                30      PUSH_NULL                       
                32      LOAD_FAST                       1: client
                34      LOAD_GLOBAL                     0: functions
                44      LOAD_ATTR                       2: channels
                64      LOAD_ATTR                       5: EditPhotoRequest
                84      LOAD_FAST                       2: channel
                86      LOAD_FAST                       1: client
                88      LOAD_ATTR                       7: upload_file
                108     LOAD_FAST                       3: channel_img
                110     CALL                            1
                118     KW_NAMES                        4: ('channel', 'photo')
                120     CALL                            2
                128     CALL                            1
                136     POP_TOP                         
                138     LOAD_GLOBAL                     9: NULL + Logs
                148     LOAD_ATTR                       10: PrintLog
                168     LOAD_GLOBAL                     12: config
                178     LOAD_FAST                       0: account
                180     PUSH_NULL                       
                182     LOAD_CONST                      1: '__pyarmor_assert_13458__'
                184     LOAD_CONST                      5: 'Photo is set'   # b"\x81\xd2\x10\x1c'\xf5\xfe\xdb\x08\xba\x1e\xc5x"
                186     CALL                            1
                194     KW_NAMES                        6: ('config', 'account', 'message')
                196     CALL                            3
                204     POP_TOP                         
                206     NOP                             
                208     LOAD_CONST                      8: True
                210     NOP                             
                212     NOP                             
                214     NOP                             
                216     JUMP_FORWARD                    86 (to 390)
                224     POP_TOP                         
                226     RETURN_CONST                    8: True
                228     PUSH_EXC_INFO                   
                230     LOAD_GLOBAL                     14: Exception
                240     CHECK_EXC_MATCH                 
                242     POP_JUMP_IF_FALSE               45 (to 334)
                244     STORE_FAST                      5: _var_var_3
                246     LOAD_GLOBAL                     9: NULL + Logs
                256     LOAD_ATTR                       10: PrintLog
                276     LOAD_GLOBAL                     12: config
                286     LOAD_FAST                       0: account
                288     PUSH_NULL                       
                290     LOAD_CONST                      1: '__pyarmor_assert_13458__'
                292     LOAD_CONST                      9: 'Photo not set'   # b"\x81\xd2\x10\x1c'\xf5\xfe\xdc\x14\xeeM\xd3i\xf8"
                294     CALL                            1
                302     LOAD_FAST                       5: _var_var_3
                304     KW_NAMES                        10: ('config', 'account', 'message', 'param')
                306     CALL                            4
                314     POP_TOP                         
                316     POP_EXCEPT                      
                318     LOAD_CONST                      0: None
                320     STORE_FAST                      5: _var_var_3
                322     DELETE_FAST                     5: _var_var_3
                324     JUMP_FORWARD                    8 (to 342)
                326     LOAD_CONST                      0: None
                328     STORE_FAST                      5: _var_var_3
                330     DELETE_FAST                     5: _var_var_3
                332     RERAISE                         1
                334     RERAISE                         0
                336     COPY                            3
                338     POP_EXCEPT                      
                340     RERAISE                         1
                342     LOAD_CONST                      11: False
                344     NOP                             
                346     NOP                             
                348     NOP                             
                350     JUMP_FORWARD                    19 (to 390)
                358     POP_TOP                         
                360     RETURN_CONST                    11: False
                362     PUSH_EXC_INFO                   
                364     PUSH_NULL                       
                366     LOAD_CONST                      7: '__pyarmor_exit_13460__'
                368     NOP                             
                370     LOAD_CONST                      3: b'<COAddr>\x07\x00\x00\x1aP\x01\x00\x00\x00\x00\x00\x00\x00\x00\x00\x00\x00\x00\x00\x00'
                372     CALL                            1
                380     POP_TOP                         
                382     RERAISE                         0
                384     COPY                            3
                386     POP_EXCEPT                      
                388     RERAISE                         1
                390     PUSH_NULL                       
                392     LOAD_CONST                      7: '__pyarmor_exit_13460__'
                394     LOAD_CONST                      3: b'<COAddr>\x07\x00\x00\x1aP\x01\x00\x00\x00\x00\x00\x00\x00\x00\x00\x00\x00\x00\x00\x00'
                396     BUILD_TUPLE                     1
                398     CALL_FUNCTION_EX                0
                400     POP_TOP                         
                402     RETURN_VALUE                    
            [Exception Table]
                30 to 206 -> 228 [0] 
                228 to 246 -> 336 [1] lasti
                246 to 316 -> 326 [1] lasti
                316 to 326 -> 362 [0] 
                326 to 336 -> 336 [1] lasti
                336 to 342 -> 362 [0] 
                362 to 384 -> 384 [1] lasti
        [Code]
            File Name: <frozen program.modules.Create_channels>
            Object Name: channel_add_admins
            Qualified Name: channel_add_admins
            Arg Count: 4
            Pos Only Arg Count: 0
            KW Only Arg Count: 0
            Stack Size: 21
            Flags: 0x20000003 (CO_OPTIMIZED | CO_NEWLOCALS | CO_PYARMOR_OBFUSCATED)
            [Names]
                'Logs'
                'PrintLog'
                'config'
                'functions'
                'channels'
                'EditAdminRequest'
                'types'
                'ChatAdminRights'
                'time'
                'sleep'
                'Exception'
            [Locals+Names]
                'account'
                'client'
                'channel'
                'list_admins'
                '__assert_armored__'
                '_var_var_41'
                '_var_var_3'
            [Constants]
                None
                '__pyarmor_assert_13461__'
                '__pyarmor_enter_13462__'
                b'<COAddr>\x07\x00\x00\x1a\x14\x02\x00\x00\x00\x00\x00\x00\x00\x00\x00\x00\x00\x00\x00\x00'
                'Add administrators is started'   # b'\x81\xc3\x1c\x17s\xfb\xba\xdf\x12\xf4\x04\xd3x\xfe\xf9\x91\x00O\xa8\xe7\xa3\xd8\x0e\xdf\x11n\xb1H\x05\xb5'
                (
                    'config'
                    'account'
                    'message'
                )
                'Add administrator'   # b'\x81\xc3\x1c\x17s\xfb\xba\xdf\x12\xf4\x04\xd3x\xfe\xf9\x91\x00O'
                (
                    'config'
                    'account'
                    'message'
                    'end'
                )
                True
                (
                    'change_info'
                    'post_messages'
                    'edit_messages'
                    'delete_messages'
                    'ban_users'
                    'invite_users'
                    'pin_messages'
                    'add_admins'
                    'anonymous'
                    'manage_call'
                    'other'
                    'manage_topics'
                )
                ''
                (
                    'channel'
                    'user_id'
                    'admin_rights'
                    'rank'
                )
                'Done, wait 3 sec...'   # b'\x81\xc6\x17\x1d6\xb6\xfe\xc5\x1a\xf3\x19\x80?\xac\xeb\x80\x0c\x13\xf5\xe9'
                3
                'Error'
                (
                    'config'
                    'account'
                    'message'
                    'param'
                )
                '__pyarmor_exit_13463__'
            [Disassembly]
                0       NOP                             
                2       NOP                             
                4       PUSH_NULL                       
                6       LOAD_CONST                      2: '__pyarmor_enter_13462__'
                8       LOAD_CONST                      3: b'<COAddr>\x07\x00\x00\x1a\x14\x02\x00\x00\x00\x00\x00\x00\x00\x00\x00\x00\x00\x00\x00\x00'
                10      BUILD_TUPLE                     1
                12      CALL_FUNCTION_EX                0
                14      POP_TOP                         
                16      RESUME                          0
                18      NOP                             
                20      NOP                             
                22      NOP                             
                24      NOP                             
                26      NOP                             
                28      LOAD_GLOBAL                     1: NULL + Logs
                38      LOAD_ATTR                       2: PrintLog
                58      LOAD_GLOBAL                     4: config
                68      LOAD_FAST                       0: account
                70      PUSH_NULL                       
                72      LOAD_CONST                      1: '__pyarmor_assert_13461__'
                74      LOAD_CONST                      4: 'Add administrators is started'   # b'\x81\xc3\x1c\x17s\xfb\xba\xdf\x12\xf4\x04\xd3x\xfe\xf9\x91\x00O\xa8\xe7\xa3\xd8\x0e\xdf\x11n\xb1H\x05\xb5'
                76      CALL                            1
                84      KW_NAMES                        5: ('config', 'account', 'message')
                86      CALL                            3
                94      POP_TOP                         
                96      LOAD_FAST                       3: list_admins
                98      GET_ITER                        
                100     FOR_ITER                        165 (to 432)
                104     STORE_FAST                      5: _var_var_41
                106     NOP                             
                108     LOAD_GLOBAL                     1: NULL + Logs
                118     LOAD_ATTR                       2: PrintLog
                138     LOAD_GLOBAL                     4: config
                148     LOAD_FAST                       0: account
                150     PUSH_NULL                       
                152     LOAD_CONST                      1: '__pyarmor_assert_13461__'
                154     LOAD_CONST                      6: 'Add administrator'   # b'\x81\xc3\x1c\x17s\xfb\xba\xdf\x12\xf4\x04\xd3x\xfe\xf9\x91\x00O'
                156     CALL                            1
                164     LOAD_FAST                       5: _var_var_41
                166     KW_NAMES                        7: ('config', 'account', 'message', 'end')
                168     CALL                            4
                176     POP_TOP                         
                178     PUSH_NULL                       
                180     LOAD_FAST                       1: client
                182     LOAD_GLOBAL                     6: functions
                192     LOAD_ATTR                       8: channels
                212     LOAD_ATTR                       11: EditAdminRequest
                232     LOAD_FAST                       2: channel
                234     LOAD_FAST                       5: _var_var_41
                236     LOAD_GLOBAL                     13: NULL + types
                246     LOAD_ATTR                       14: ChatAdminRights
                266     LOAD_CONST                      8: True
                268     LOAD_CONST                      8: True
                270     LOAD_CONST                      8: True
                272     LOAD_CONST                      8: True
                274     LOAD_CONST                      8: True
                276     LOAD_CONST                      8: True
                278     LOAD_CONST                      8: True
                280     LOAD_CONST                      8: True
                282     LOAD_CONST                      8: True
                284     LOAD_CONST                      8: True
                286     LOAD_CONST                      8: True
                288     LOAD_CONST                      8: True
                290     KW_NAMES                        9: ('change_info', 'post_messages', 'edit_messages', 'delete_messages', 'ban_users', 'invite_users', 'pin_messages', 'add_admins', 'anonymous', 'manage_call', 'other', 'manage_topics')
                292     CALL                            12
                300     LOAD_CONST                      10: ''
                302     KW_NAMES                        11: ('channel', 'user_id', 'admin_rights', 'rank')
                304     CALL                            4
                312     CALL                            1
                320     POP_TOP                         
                322     LOAD_GLOBAL                     1: NULL + Logs
                332     LOAD_ATTR                       2: PrintLog
                352     LOAD_GLOBAL                     4: config
                362     LOAD_FAST                       0: account
                364     PUSH_NULL                       
                366     LOAD_CONST                      1: '__pyarmor_assert_13461__'
                368     LOAD_CONST                      12: 'Done, wait 3 sec...'   # b'\x81\xc6\x17\x1d6\xb6\xfe\xc5\x1a\xf3\x19\x80?\xac\xeb\x80\x0c\x13\xf5\xe9'
                370     CALL                            1
                378     KW_NAMES                        5: ('config', 'account', 'message')
                380     CALL                            3
                388     POP_TOP                         
                390     LOAD_GLOBAL                     17: NULL + time
                400     LOAD_ATTR                       18: sleep
                420     LOAD_CONST                      13: 3
                422     CALL                            1
                430     POP_TOP                         
                432     JUMP_BACKWARD                   167 (to 100)
                434     END_FOR                         
                436     LOAD_CONST                      8: True
                438     NOP                             
                440     NOP                             
                442     NOP                             
                444     JUMP_FORWARD                    70 (to 586)
                452     POP_TOP                         
                454     RETURN_CONST                    8: True
                456     PUSH_EXC_INFO                   
                458     LOAD_GLOBAL                     20: Exception
                468     CHECK_EXC_MATCH                 
                470     POP_JUMP_IF_FALSE               39 (to 550)
                472     STORE_FAST                      6: _var_var_3
                474     LOAD_GLOBAL                     1: NULL + Logs
                484     LOAD_ATTR                       2: PrintLog
                504     LOAD_GLOBAL                     4: config
                514     LOAD_FAST                       0: account
                516     LOAD_CONST                      14: 'Error'
                518     LOAD_FAST                       6: _var_var_3
                520     KW_NAMES                        15: ('config', 'account', 'message', 'param')
                522     CALL                            4
                530     POP_TOP                         
                532     POP_EXCEPT                      
                534     LOAD_CONST                      0: None
                536     STORE_FAST                      6: _var_var_3
                538     DELETE_FAST                     6: _var_var_3
                540     JUMP_BACKWARD                   221 (to 100)
                542     LOAD_CONST                      0: None
                544     STORE_FAST                      6: _var_var_3
                546     DELETE_FAST                     6: _var_var_3
                548     RERAISE                         1
                550     RERAISE                         0
                552     COPY                            3
                554     POP_EXCEPT                      
                556     RERAISE                         1
                558     PUSH_EXC_INFO                   
                560     PUSH_NULL                       
                562     LOAD_CONST                      16: '__pyarmor_exit_13463__'
                564     NOP                             
                566     LOAD_CONST                      3: b'<COAddr>\x07\x00\x00\x1a\x14\x02\x00\x00\x00\x00\x00\x00\x00\x00\x00\x00\x00\x00\x00\x00'
                568     CALL                            1
                576     POP_TOP                         
                578     RERAISE                         0
                580     COPY                            3
                582     POP_EXCEPT                      
                584     RERAISE                         1
                586     PUSH_NULL                       
                588     LOAD_CONST                      16: '__pyarmor_exit_13463__'
                590     LOAD_CONST                      3: b'<COAddr>\x07\x00\x00\x1a\x14\x02\x00\x00\x00\x00\x00\x00\x00\x00\x00\x00\x00\x00\x00\x00'
                592     BUILD_TUPLE                     1
                594     CALL_FUNCTION_EX                0
                596     POP_TOP                         
                598     RETURN_VALUE                    
            [Exception Table]
                28 to 106 -> 558 [0] 
                108 to 432 -> 456 [1] 
                432 to 436 -> 558 [0] 
                456 to 474 -> 552 [2] lasti
                474 to 532 -> 542 [2] lasti
                532 to 542 -> 558 [0] 
                542 to 552 -> 552 [2] lasti
                552 to 558 -> 558 [0] 
                558 to 580 -> 580 [1] lasti
        [Code]
            File Name: <frozen program.modules.Create_channels>
            Object Name: worker
            Qualified Name: worker
            Arg Count: 10
            Pos Only Arg Count: 0
            KW Only Arg Count: 0
            Stack Size: 10
            Flags: 0x20000003 (CO_OPTIMIZED | CO_NEWLOCALS | CO_PYARMOR_OBFUSCATED)
            [Names]
                'Thread_wait'
                'account_works'
                'Lang'
                'Disconnect'
                'Logs'
                'PrintLog'
                'int'
                'get'
                'is_set'
                'StopProgram'
                'range'
                'DelayOnline'
                'channel_create'
                'channel_set_username'
                'channel_get_link'
                'channel_set_photo'
                'channel_add_admins'
                'spintax'
                'spin'
                'len'
                'random'
                'choice'
                'upload_file'
                'str'
                'send_file'
                'replace'
                'split'
                'get_entity'
                'forward_messages'
                'inline_query'
                'click'
                'send_message'
                'Exception'
                'db_create_channels'
                'set_data'
                'id'
                'title'
                'BaseException'
                'logging'
            [Locals+Names]
                'account'
                'config'
                'proxy'
                'data'
                'db_result'
                'kol_channels'
                'list_names'
                'list_links'
                'list_avatars'
                'stop_thread'
                '__assert_armored__'
                '_var_var_42'
                '_var_var_43'
                '_var_var_44'
                '_var_var_45'
                '_var_var_46'
                '_var_var_47'
                '_var_var_48'
                '_var_var_49'
                '_var_var_50'
                '_var_var_51'
                '_var_var_52'
                '_var_var_53'
                '_var_var_54'
                '_var_var_55'
                '_var_var_13'
                '_var_var_4'
                '_var_var_56'
                '_var_var_57'
                '_var_var_7'
                '_var_var_58'
                '_var_var_59'
                '_var_var_60'
                '_var_var_36'
                '_var_var_61'
                '_var_var_62'
                '_var_var_63'
                '_var_var_64'
                '_var_var_65'
                '_var_var_66'
                '_var_var_67'
                '_var_var_68'
                '_var_var_69'
                '_var_var_70'
                '_var_var_71'
                '_var_var_72'
                '_var_var_73'
                '_var_var_74'
                '_var_var_37'
                '_var_var_3'
            [Constants]
                None
                '__pyarmor_assert_13464__'
                '__pyarmor_enter_13465__'
                b'<COAddr>\x07\x00\x00\x1ap\x10\x00\x00\x00\x00\x00\x00\x00\x00\x00\x00\x00\x00\x00\x00'
                'CreateChannel'   # b'\x81\xc1\n\x162\xee\xbb\xf1\x13\xfb\x03\xcei\xe0'
                (
                    'module'
                )
                False
                'false'
                (
                    'account'
                    'status'
                )
                'work_account_completed'   # b'\x81\xf5\x17\x018\xc5\xbf\xd1\x18\xf5\x18\xcex\xd3\xfb\x8a\x02M\xb7\xa2\xbe\xceJ'
                (
                    'config'
                    'account'
                    'message'
                )
                'done'
                '__pyarmor_exit_13466__'
                'Settings'
                'wait_from'   # b"\x81\xf5\x19\x1a'\xc5\xb8\xc0\x14\xf7"
                'wait_to'
                'max_flood_wait'   # b'\x81\xef\x19\x0b\x0c\xfc\xb2\xdd\x14\xfe2\xd7m\xe5\xec'
                'channel_type'   # b'\x81\xe1\x10\x12=\xf4\xbb\xde$\xee\x14\xd0i'
                'set_avatar'   # b'\x81\xf1\x1d\x07\x0c\xfb\xa8\xd3\x0f\xfb\x1f'
                'create_public_link'   # b'\x81\xe1\n\x162\xee\xbb\xed\x0b\xef\x0f\xcce\xef\xc7\x89\x06S\xb0'
                'send_message'   # b'\x81\xf1\x1d\x1d7\xc5\xb3\xd7\x08\xe9\x0c\xc7i'
                'add_admins'   # b'\x81\xe3\x1c\x17\x0c\xfb\xba\xdf\x12\xf4\x1e'
                'list_admins'   # b"\x81\xee\x11\x00'\xc5\xbf\xd6\x16\xf3\x03\xd3"
                'message'
                'bots'
                'bot'
                'posts'
                'img'
                'forward'
                0
                'channel_private'   # b'\x81\xe1\x10\x12=\xf4\xbb\xde$\xea\x1f\xc9z\xed\xec\x80'
                'channel_public'   # b'\x81\xe1\x10\x12=\xf4\xbb\xde$\xea\x18\xc2`\xe5\xfb'
                True
                'group_private'   # b'\x81\xe5\n\x1c&\xea\x81\xc2\t\xf3\x1b\xc1x\xe9'
                'group_public'   # b'\x81\xe5\n\x1c&\xea\x81\xc2\x0e\xf8\x01\xc9o'
                ''
                'Error, account is stopped'   # b'\x81\xc7\n\x01<\xe8\xf2\x92\x1a\xf9\x0e\xcfy\xe2\xec\xc5\x06N\xfb\xb4\xbe\xc4^\xdc\x00k'
                'Получаем приватную ссылку'   # b'\x81R\xe7\xa3\xedJec\xf8K\xeap\xbc\\-5\xd3\x1d\x0bx\x1b+\xfe\x14\xb5\xbd\x13\x8c\xb1S\xae8\x8b\xb1\x91\xe3\xd8{U\x9f\xf9X\x13\xed\x06h\xd5\xf6\xd4'
                'Не смог получить ссылку, останавливаю аккаунт'   # b'\x81R\xe5\xa3\xe6\xba\x0f3\xab&\xbd\x1e\xdc?\xb85\xd0\xede\x17qz\xad}\xe2\xdf{\xed\xe2\x00\xf2\xa5\x8b\xb3\x91\xec)!\x04\xf5\xa83I\xbe\x91\x98\xbf\x99\x86\x0c\xe7\x197\xa0\xb60\x87;+\xcf\xa8\x90\x81\x8b\xe7\x9a\xb5Sl\xd9\xac\x0fC\xd2\xe6\x8e\x9a\t\xd8 B7Y\x18]'
                'text'
                'http'
                'https'
                '.ogg'
                '.mp3'
                'type_defined_voice_message'   # b'\x81\xf6\x01\x036\xc5\xba\xd7\x1d\xf3\x03\xc5h\xd3\xee\x8a\x06^\xbe\x98\xa7\xce]\xdf\x04h\xa6'
                (
                    'voice_note'
                )
                'type_defined_file_description'   # b'\x81\xf6\x01\x036\xc5\xba\xd7\x1d\xf3\x03\xc5h\xd3\xfe\x8c\x03X\x84\xa3\xaf\xd8M\xde\x0c\x7f\xb7U\x0f\xbf'
                ' '
                (
                    'caption'
                )
                'type_defined_repost'   # b'\x81\xf6\x01\x036\xc5\xba\xd7\x1d\xf3\x03\xc5h\xd3\xea\x80\x1fR\xa8\xb3'
                'https://t.me/'   # b'\x81\xea\x0c\x07#\xe9\xe4\x9dT\xeeC\xcdi\xa3'
                'http://t.me/'   # b'\x81\xea\x0c\x07#\xa0\xf1\x9d\x0f\xb4\x00\xc5#'
                '/'
                1
                'type_defined_postbot'   # b'\x81\xf6\x01\x036\xc5\xba\xd7\x1d\xf3\x03\xc5h\xd3\xe8\x8a\x1cI\xb9\xa8\xbe'
                'type_defined_text'   # b'\x81\xf6\x01\x036\xc5\xba\xd7\x1d\xf3\x03\xc5h\xd3\xec\x80\x17I'
                'md'
                (
                    'parse_mode'
                )
                'Message is send'   # b'\x81\xcf\x1d\x00 \xfb\xb9\xd7[\xf3\x1e\x80\x7f\xe9\xf6\x81'
                'an_unhandled_error_was_detected'   # b'\x81\xe3\x16,&\xf4\xb6\xd3\x15\xfe\x01\xc5h\xd3\xfd\x97\x1dR\xa9\x98\xbd\xca]\xf3\x01j\xb7Y\x03\xa5\x1b\xe1'
                (
                    'config'
                    'account'
                    'message'
                    'param'
                )
                'Done'
            [Disassembly]
                0       NOP                             
                2       NOP                             
                4       PUSH_NULL                       
                6       LOAD_CONST                      2: '__pyarmor_enter_13465__'
                8       LOAD_CONST                      3: b'<COAddr>\x07\x00\x00\x1ap\x10\x00\x00\x00\x00\x00\x00\x00\x00\x00\x00\x00\x00\x00\x00'
                10      BUILD_TUPLE                     1
                12      CALL_FUNCTION_EX                0
                14      POP_TOP                         
                16      RESUME                          0
                18      NOP                             
                20      NOP                             
                22      NOP                             
                24      NOP                             
                26      NOP                             
                28      NOP                             
                30      LOAD_GLOBAL                     1: NULL + Thread_wait
                40      LOAD_FAST                       3: data
                42      LOAD_FAST                       1: config
                44      LOAD_FAST                       9: stop_thread
                46      CALL                            3
                54      POP_TOP                         
                56      LOAD_GLOBAL                     3: NULL + account_works
                66      LOAD_FAST                       1: config
                68      LOAD_GLOBAL                     4: Lang
                78      LOAD_FAST                       2: proxy
                80      LOAD_FAST                       0: account
                82      LOAD_FAST                       9: stop_thread
                84      PUSH_NULL                       
                86      LOAD_CONST                      1: '__pyarmor_assert_13464__'
                88      LOAD_CONST                      4: 'CreateChannel'   # b'\x81\xc1\n\x162\xee\xbb\xf1\x13\xfb\x03\xcei\xe0'
                90      CALL                            1
                98      KW_NAMES                        5: ('module',)
                100     CALL                            6
                108     STORE_FAST                      11: _var_var_42
                110     LOAD_FAST                       11: _var_var_42
                112     LOAD_CONST                      6: False
                114     COMPARE_OP                      40 (==)
                118     POP_JUMP_IF_FALSE               68 (to 256)
                120     LOAD_FAST                       0: account
                122     LOAD_CONST                      7: 'false'
                124     LOAD_CONST                      8: ('account', 'status')
                126     BUILD_CONST_KEY_MAP             2
                128     LOAD_GLOBAL                     7: NULL + Disconnect
                138     LOAD_FAST                       11: _var_var_42
                140     CALL                            1
                148     POP_TOP                         
                150     LOAD_GLOBAL                     9: NULL + Logs
                160     LOAD_ATTR                       10: PrintLog
                180     LOAD_FAST                       1: config
                182     LOAD_FAST                       0: account
                184     LOAD_GLOBAL                     4: Lang
                194     PUSH_NULL                       
                196     LOAD_CONST                      1: '__pyarmor_assert_13464__'
                198     LOAD_CONST                      9: 'work_account_completed'   # b'\x81\xf5\x17\x018\xc5\xbf\xd1\x18\xf5\x18\xcex\xd3\xfb\x8a\x02M\xb7\xa2\xbe\xceJ'
                200     CALL                            1
                208     BINARY_SUBSCR                   
                212     KW_NAMES                        10: ('config', 'account', 'message')
                214     CALL                            3
                222     POP_TOP                         
                224     LOAD_FAST                       0: account
                226     LOAD_CONST                      11: 'done'
                228     LOAD_CONST                      8: ('account', 'status')
                230     BUILD_CONST_KEY_MAP             2
                232     SWAP                            2
                234     POP_TOP                         
                236     NOP                             
                238     NOP                             
                240     JUMP_FORWARD                    2009 (to 4262)
                244     CALL                            1
                252     POP_TOP                         
                254     RETURN_VALUE                    
                256     LOAD_GLOBAL                     13: NULL + int
                266     LOAD_FAST                       3: data
                268     LOAD_CONST                      13: 'Settings'
                270     BINARY_SUBSCR                   
                274     LOAD_ATTR                       15: get
                294     PUSH_NULL                       
                296     LOAD_CONST                      1: '__pyarmor_assert_13464__'
                298     LOAD_CONST                      14: 'wait_from'   # b"\x81\xf5\x19\x1a'\xc5\xb8\xc0\x14\xf7"
                300     CALL                            1
                308     CALL                            1
                316     CALL                            1
                324     STORE_FAST                      12: _var_var_43
                326     LOAD_GLOBAL                     13: NULL + int
                336     LOAD_FAST                       3: data
                338     LOAD_CONST                      13: 'Settings'
                340     BINARY_SUBSCR                   
                344     LOAD_ATTR                       15: get
                364     LOAD_CONST                      15: 'wait_to'
                366     CALL                            1
                374     CALL                            1
                382     STORE_FAST                      13: _var_var_44
                384     LOAD_GLOBAL                     13: NULL + int
                394     LOAD_FAST                       3: data
                396     LOAD_CONST                      13: 'Settings'
                398     BINARY_SUBSCR                   
                402     LOAD_ATTR                       15: get
                422     PUSH_NULL                       
                424     LOAD_CONST                      1: '__pyarmor_assert_13464__'
                426     LOAD_CONST                      16: 'max_flood_wait'   # b'\x81\xef\x19\x0b\x0c\xfc\xb2\xdd\x14\xfe2\xd7m\xe5\xec'
                428     CALL                            1
                436     CALL                            1
                444     CALL                            1
                452     STORE_FAST                      14: _var_var_45
                454     LOAD_FAST                       3: data
                456     LOAD_CONST                      13: 'Settings'
                458     BINARY_SUBSCR                   
                462     LOAD_ATTR                       15: get
                482     PUSH_NULL                       
                484     LOAD_CONST                      1: '__pyarmor_assert_13464__'
                486     LOAD_CONST                      17: 'channel_type'   # b'\x81\xe1\x10\x12=\xf4\xbb\xde$\xee\x14\xd0i'
                488     CALL                            1
                496     CALL                            1
                504     STORE_FAST                      15: _var_var_46
                506     LOAD_FAST                       3: data
                508     LOAD_CONST                      13: 'Settings'
                510     BINARY_SUBSCR                   
                514     LOAD_ATTR                       15: get
                534     PUSH_NULL                       
                536     LOAD_CONST                      1: '__pyarmor_assert_13464__'
                538     LOAD_CONST                      18: 'set_avatar'   # b'\x81\xf1\x1d\x07\x0c\xfb\xa8\xd3\x0f\xfb\x1f'
                540     CALL                            1
                548     CALL                            1
                556     STORE_FAST                      16: _var_var_47
                558     LOAD_FAST                       3: data
                560     LOAD_CONST                      13: 'Settings'
                562     BINARY_SUBSCR                   
                566     LOAD_ATTR                       15: get
                586     PUSH_NULL                       
                588     LOAD_CONST                      1: '__pyarmor_assert_13464__'
                590     LOAD_CONST                      19: 'create_public_link'   # b'\x81\xe1\n\x162\xee\xbb\xed\x0b\xef\x0f\xcce\xef\xc7\x89\x06S\xb0'
                592     CALL                            1
                600     CALL                            1
                608     STORE_FAST                      17: _var_var_48
                610     LOAD_FAST                       3: data
                612     LOAD_CONST                      13: 'Settings'
                614     BINARY_SUBSCR                   
                618     LOAD_ATTR                       15: get
                638     PUSH_NULL                       
                640     LOAD_CONST                      1: '__pyarmor_assert_13464__'
                642     LOAD_CONST                      20: 'send_message'   # b'\x81\xf1\x1d\x1d7\xc5\xb3\xd7\x08\xe9\x0c\xc7i'
                644     CALL                            1
                652     CALL                            1
                660     STORE_FAST                      18: _var_var_49
                662     LOAD_FAST                       3: data
                664     LOAD_CONST                      13: 'Settings'
                666     BINARY_SUBSCR                   
                670     LOAD_ATTR                       15: get
                690     PUSH_NULL                       
                692     LOAD_CONST                      1: '__pyarmor_assert_13464__'
                694     LOAD_CONST                      21: 'add_admins'   # b'\x81\xe3\x1c\x17\x0c\xfb\xba\xdf\x12\xf4\x1e'
                696     CALL                            1
                704     CALL                            1
                712     STORE_FAST                      19: _var_var_50
                714     LOAD_FAST                       3: data
                716     LOAD_CONST                      13: 'Settings'
                718     BINARY_SUBSCR                   
                722     LOAD_ATTR                       15: get
                742     PUSH_NULL                       
                744     LOAD_CONST                      1: '__pyarmor_assert_13464__'
                746     LOAD_CONST                      22: 'list_admins'   # b"\x81\xee\x11\x00'\xc5\xbf\xd6\x16\xf3\x03\xd3"
                748     CALL                            1
                756     CALL                            1
                764     STORE_FAST                      20: _var_var_51
                766     LOAD_FAST                       3: data
                768     LOAD_CONST                      13: 'Settings'
                770     BINARY_SUBSCR                   
                774     LOAD_ATTR                       15: get
                794     PUSH_NULL                       
                796     LOAD_CONST                      1: '__pyarmor_assert_13464__'
                798     LOAD_CONST                      17: 'channel_type'   # b'\x81\xe1\x10\x12=\xf4\xbb\xde$\xee\x14\xd0i'
                800     CALL                            1
                808     CALL                            1
                816     STORE_FAST                      15: _var_var_46
                818     LOAD_FAST                       3: data
                820     LOAD_CONST                      13: 'Settings'
                822     BINARY_SUBSCR                   
                826     LOAD_ATTR                       15: get
                846     LOAD_CONST                      23: 'message'
                848     CALL                            1
                856     STORE_FAST                      21: _var_var_52
                858     LOAD_FAST                       3: data
                860     LOAD_CONST                      13: 'Settings'
                862     BINARY_SUBSCR                   
                866     LOAD_CONST                      23: 'message'
                868     BINARY_SUBSCR                   
                872     LOAD_CONST                      24: 'bots'
                874     BINARY_SUBSCR                   
                878     LOAD_ATTR                       15: get
                898     LOAD_CONST                      25: 'bot'
                900     CALL                            1
                908     STORE_FAST                      22: _var_var_53
                910     LOAD_FAST                       3: data
                912     LOAD_CONST                      13: 'Settings'
                914     BINARY_SUBSCR                   
                918     LOAD_CONST                      23: 'message'
                920     BINARY_SUBSCR                   
                924     LOAD_CONST                      24: 'bots'
                926     BINARY_SUBSCR                   
                930     LOAD_ATTR                       15: get
                950     LOAD_CONST                      26: 'posts'
                952     CALL                            1
                960     STORE_FAST                      23: _var_var_54
                962     LOAD_FAST                       21: _var_var_52
                964     LOAD_ATTR                       15: get
                984     LOAD_CONST                      27: 'img'
                986     CALL                            1
                994     STORE_FAST                      24: _var_var_55
                996     LOAD_FAST                       21: _var_var_52
                998     LOAD_ATTR                       15: get
                1018    LOAD_CONST                      28: 'forward'
                1020    CALL                            1
                1028    STORE_FAST                      25: _var_var_13
                1030    LOAD_CONST                      29: 0
                1032    STORE_FAST                      26: _var_var_4
                1034    LOAD_FAST                       9: stop_thread
                1036    LOAD_ATTR                       17: is_set
                1056    CALL                            0
                1064    POP_JUMP_IF_FALSE               10 (to 1086)
                1066    LOAD_GLOBAL                     19: NULL + StopProgram
                1076    CALL                            0
                1084    RAISE_VARARGS                   1
                1086    LOAD_FAST                       15: _var_var_46
                1088    PUSH_NULL                       
                1090    LOAD_CONST                      1: '__pyarmor_assert_13464__'
                1092    LOAD_CONST                      30: 'channel_private'   # b'\x81\xe1\x10\x12=\xf4\xbb\xde$\xea\x1f\xc9z\xed\xec\x80'
                1094    CALL                            1
                1102    COMPARE_OP                      40 (==)
                1106    POP_JUMP_IF_TRUE                11 (to 1130)
                1108    LOAD_FAST                       15: _var_var_46
                1110    PUSH_NULL                       
                1112    LOAD_CONST                      1: '__pyarmor_assert_13464__'
                1114    LOAD_CONST                      31: 'channel_public'   # b'\x81\xe1\x10\x12=\xf4\xbb\xde$\xea\x18\xc2`\xe5\xfb'
                1116    CALL                            1
                1124    COMPARE_OP                      40 (==)
                1128    POP_JUMP_IF_FALSE               3 (to 1136)
                1130    LOAD_CONST                      32: True
                1132    STORE_FAST                      27: _var_var_56
                1134    JUMP_FORWARD                    2 (to 1140)
                1136    LOAD_CONST                      6: False
                1138    STORE_FAST                      27: _var_var_56
                1140    LOAD_FAST                       15: _var_var_46
                1142    PUSH_NULL                       
                1144    LOAD_CONST                      1: '__pyarmor_assert_13464__'
                1146    LOAD_CONST                      33: 'group_private'   # b'\x81\xe5\n\x1c&\xea\x81\xc2\t\xf3\x1b\xc1x\xe9'
                1148    CALL                            1
                1156    COMPARE_OP                      40 (==)
                1160    POP_JUMP_IF_TRUE                11 (to 1184)
                1162    LOAD_FAST                       15: _var_var_46
                1164    PUSH_NULL                       
                1166    LOAD_CONST                      1: '__pyarmor_assert_13464__'
                1168    LOAD_CONST                      34: 'group_public'   # b'\x81\xe5\n\x1c&\xea\x81\xc2\x0e\xf8\x01\xc9o'
                1170    CALL                            1
                1178    COMPARE_OP                      40 (==)
                1182    POP_JUMP_IF_FALSE               3 (to 1190)
                1184    LOAD_CONST                      32: True
                1186    STORE_FAST                      28: _var_var_57
                1188    JUMP_FORWARD                    2 (to 1194)
                1190    LOAD_CONST                      6: False
                1192    STORE_FAST                      28: _var_var_57
                1194    LOAD_GLOBAL                     21: NULL + range
                1204    LOAD_FAST                       5: kol_channels
                1206    CALL                            1
                1214    GET_ITER                        
                1216    FOR_ITER                        1200 (to 3620)
                1222    STORE_FAST                      29: _var_var_7
                1224    LOAD_GLOBAL                     23: NULL + DelayOnline
                1234    LOAD_FAST                       0: account
                1236    LOAD_FAST                       11: _var_var_42
                1238    LOAD_FAST                       12: _var_var_43
                1240    LOAD_FAST                       13: _var_var_44
                1242    LOAD_FAST                       9: stop_thread
                1244    CALL                            5
                1252    POP_TOP                         
                1254    LOAD_FAST                       6: list_names
                1256    LOAD_FAST                       26: _var_var_4
                1258    BINARY_SUBSCR                   
                1262    STORE_FAST                      30: _var_var_58
                1264    LOAD_FAST                       7: list_links
                1266    LOAD_FAST                       26: _var_var_4
                1268    BINARY_SUBSCR                   
                1272    STORE_FAST                      31: _var_var_59
                1274    LOAD_FAST                       8: list_avatars
                1276    LOAD_FAST                       26: _var_var_4
                1278    BINARY_SUBSCR                   
                1282    STORE_FAST                      32: _var_var_60
                1284    LOAD_CONST                      6: False
                1286    STORE_FAST                      33: _var_var_36
                1288    LOAD_CONST                      6: False
                1290    STORE_FAST                      34: _var_var_61
                1292    LOAD_CONST                      35: ''
                1294    STORE_FAST                      35: _var_var_62
                1296    LOAD_GLOBAL                     25: NULL + channel_create
                1306    LOAD_FAST                       0: account
                1308    LOAD_FAST                       11: _var_var_42
                1310    LOAD_FAST                       30: _var_var_58
                1312    LOAD_FAST                       27: _var_var_56
                1314    LOAD_FAST                       28: _var_var_57
                1316    CALL                            5
                1324    STORE_FAST                      34: _var_var_61
                1326    LOAD_FAST                       34: _var_var_61
                1328    LOAD_CONST                      6: False
                1330    COMPARE_OP                      40 (==)
                1334    POP_JUMP_IF_FALSE               109 (to 1554)
                1336    LOAD_GLOBAL                     9: NULL + Logs
                1346    LOAD_ATTR                       10: PrintLog
                1366    LOAD_FAST                       1: config
                1368    LOAD_FAST                       0: account
                1370    PUSH_NULL                       
                1372    LOAD_CONST                      1: '__pyarmor_assert_13464__'
                1374    LOAD_CONST                      36: 'Error, account is stopped'   # b'\x81\xc7\n\x01<\xe8\xf2\x92\x1a\xf9\x0e\xcfy\xe2\xec\xc5\x06N\xfb\xb4\xbe\xc4^\xdc\x00k'
                1376    CALL                            1
                1384    KW_NAMES                        10: ('config', 'account', 'message')
                1386    CALL                            3
                1394    POP_TOP                         
                1396    LOAD_GLOBAL                     7: NULL + Disconnect
                1406    LOAD_FAST                       11: _var_var_42
                1408    CALL                            1
                1416    POP_TOP                         
                1418    LOAD_FAST                       0: account
                1420    BUILD_LIST                      1
                1422    SWAP                            2
                1424    POP_TOP                         
                1426    LOAD_GLOBAL                     7: NULL + Disconnect
                1436    LOAD_FAST                       11: _var_var_42
                1438    CALL                            1
                1446    POP_TOP                         
                1448    LOAD_GLOBAL                     9: NULL + Logs
                1458    LOAD_ATTR                       10: PrintLog
                1478    LOAD_FAST                       1: config
                1480    LOAD_FAST                       0: account
                1482    LOAD_GLOBAL                     4: Lang
                1492    PUSH_NULL                       
                1494    LOAD_CONST                      1: '__pyarmor_assert_13464__'
                1496    LOAD_CONST                      9: 'work_account_completed'   # b'\x81\xf5\x17\x018\xc5\xbf\xd1\x18\xf5\x18\xcex\xd3\xfb\x8a\x02M\xb7\xa2\xbe\xceJ'
                1498    CALL                            1
                1506    BINARY_SUBSCR                   
                1510    KW_NAMES                        10: ('config', 'account', 'message')
                1512    CALL                            3
                1520    POP_TOP                         
                1522    LOAD_FAST                       0: account
                1524    LOAD_CONST                      11: 'done'
                1526    LOAD_CONST                      8: ('account', 'status')
                1528    BUILD_CONST_KEY_MAP             2
                1530    SWAP                            2
                1532    POP_TOP                         
                1534    NOP                             
                1536    NOP                             
                1538    JUMP_FORWARD                    1360 (to 4262)
                1542    CALL                            1
                1550    POP_TOP                         
                1552    RETURN_VALUE                    
                1554    LOAD_FAST                       17: _var_var_48
                1556    LOAD_CONST                      32: True
                1558    COMPARE_OP                      40 (==)
                1562    POP_JUMP_IF_FALSE               38 (to 1640)
                1564    LOAD_FAST                       15: _var_var_46
                1566    PUSH_NULL                       
                1568    LOAD_CONST                      1: '__pyarmor_assert_13464__'
                1570    LOAD_CONST                      31: 'channel_public'   # b'\x81\xe1\x10\x12=\xf4\xbb\xde$\xea\x18\xc2`\xe5\xfb'
                1572    CALL                            1
                1580    COMPARE_OP                      40 (==)
                1584    POP_JUMP_IF_TRUE                11 (to 1608)
                1586    LOAD_FAST                       15: _var_var_46
                1588    PUSH_NULL                       
                1590    LOAD_CONST                      1: '__pyarmor_assert_13464__'
                1592    LOAD_CONST                      34: 'group_public'   # b'\x81\xe5\n\x1c&\xea\x81\xc2\x0e\xf8\x01\xc9o'
                1594    CALL                            1
                1602    COMPARE_OP                      40 (==)
                1606    POP_JUMP_IF_FALSE               16 (to 1640)
                1608    LOAD_GLOBAL                     27: NULL + channel_set_username
                1618    LOAD_FAST                       0: account
                1620    LOAD_FAST                       11: _var_var_42
                1622    LOAD_FAST                       34: _var_var_61
                1624    LOAD_FAST                       31: _var_var_59
                1626    LOAD_FAST                       9: stop_thread
                1628    LOAD_FAST                       14: _var_var_45
                1630    CALL                            6
                1638    STORE_FAST                      33: _var_var_36
                1640    LOAD_FAST                       33: _var_var_36
                1642    LOAD_CONST                      6: False
                1644    COMPARE_OP                      40 (==)
                1648    POP_JUMP_IF_FALSE               157 (to 1964)
                1650    LOAD_GLOBAL                     9: NULL + Logs
                1660    LOAD_ATTR                       10: PrintLog
                1680    LOAD_FAST                       1: config
                1682    LOAD_FAST                       0: account
                1684    PUSH_NULL                       
                1686    LOAD_CONST                      1: '__pyarmor_assert_13464__'
                1688    LOAD_CONST                      37: 'Получаем приватную ссылку'   # b'\x81R\xe7\xa3\xedJec\xf8K\xeap\xbc\\-5\xd3\x1d\x0bx\x1b+\xfe\x14\xb5\xbd\x13\x8c\xb1S\xae8\x8b\xb1\x91\xe3\xd8{U\x9f\xf9X\x13\xed\x06h\xd5\xf6\xd4'
                1690    CALL                            1
                1698    KW_NAMES                        10: ('config', 'account', 'message')
                1700    CALL                            3
                1708    POP_TOP                         
                1710    LOAD_GLOBAL                     29: NULL + channel_get_link
                1720    LOAD_FAST                       0: account
                1722    LOAD_FAST                       11: _var_var_42
                1724    LOAD_FAST                       34: _var_var_61
                1726    CALL                            3
                1734    STORE_FAST                      33: _var_var_36
                1736    LOAD_FAST                       33: _var_var_36
                1738    LOAD_CONST                      6: False
                1740    COMPARE_OP                      40 (==)
                1744    POP_JUMP_IF_FALSE               109 (to 1964)
                1746    LOAD_GLOBAL                     9: NULL + Logs
                1756    LOAD_ATTR                       10: PrintLog
                1776    LOAD_FAST                       1: config
                1778    LOAD_FAST                       0: account
                1780    PUSH_NULL                       
                1782    LOAD_CONST                      1: '__pyarmor_assert_13464__'
                1784    LOAD_CONST                      38: 'Не смог получить ссылку, останавливаю аккаунт'   # b'\x81R\xe5\xa3\xe6\xba\x0f3\xab&\xbd\x1e\xdc?\xb85\xd0\xede\x17qz\xad}\xe2\xdf{\xed\xe2\x00\xf2\xa5\x8b\xb3\x91\xec)!\x04\xf5\xa83I\xbe\x91\x98\xbf\x99\x86\x0c\xe7\x197\xa0\xb60\x87;+\xcf\xa8\x90\x81\x8b\xe7\x9a\xb5Sl\xd9\xac\x0fC\xd2\xe6\x8e\x9a\t\xd8 B7Y\x18]'
                1786    CALL                            1
                1794    KW_NAMES                        10: ('config', 'account', 'message')
                1796    CALL                            3
                1804    POP_TOP                         
                1806    LOAD_GLOBAL                     7: NULL + Disconnect
                1816    LOAD_FAST                       11: _var_var_42
                1818    CALL                            1
                1826    POP_TOP                         
                1828    LOAD_FAST                       0: account
                1830    BUILD_LIST                      1
                1832    SWAP                            2
                1834    POP_TOP                         
                1836    LOAD_GLOBAL                     7: NULL + Disconnect
                1846    LOAD_FAST                       11: _var_var_42
                1848    CALL                            1
                1856    POP_TOP                         
                1858    LOAD_GLOBAL                     9: NULL + Logs
                1868    LOAD_ATTR                       10: PrintLog
                1888    LOAD_FAST                       1: config
                1890    LOAD_FAST                       0: account
                1892    LOAD_GLOBAL                     4: Lang
                1902    PUSH_NULL                       
                1904    LOAD_CONST                      1: '__pyarmor_assert_13464__'
                1906    LOAD_CONST                      9: 'work_account_completed'   # b'\x81\xf5\x17\x018\xc5\xbf\xd1\x18\xf5\x18\xcex\xd3\xfb\x8a\x02M\xb7\xa2\xbe\xceJ'
                1908    CALL                            1
                1916    BINARY_SUBSCR                   
                1920    KW_NAMES                        10: ('config', 'account', 'message')
                1922    CALL                            3
                1930    POP_TOP                         
                1932    LOAD_FAST                       0: account
                1934    LOAD_CONST                      11: 'done'
                1936    LOAD_CONST                      8: ('account', 'status')
                1938    BUILD_CONST_KEY_MAP             2
                1940    SWAP                            2
                1942    POP_TOP                         
                1944    NOP                             
                1946    NOP                             
                1948    JUMP_FORWARD                    1155 (to 4262)
                1952    CALL                            1
                1960    POP_TOP                         
                1962    RETURN_VALUE                    
                1964    LOAD_FAST                       16: _var_var_47
                1966    POP_JUMP_IF_FALSE               14 (to 1996)
                1968    LOAD_GLOBAL                     31: NULL + channel_set_photo
                1978    LOAD_FAST                       0: account
                1980    LOAD_FAST                       11: _var_var_42
                1982    LOAD_FAST                       34: _var_var_61
                1984    LOAD_FAST                       32: _var_var_60
                1986    CALL                            4
                1994    POP_TOP                         
                1996    LOAD_FAST                       19: _var_var_50
                1998    POP_JUMP_IF_FALSE               14 (to 2028)
                2000    LOAD_GLOBAL                     33: NULL + channel_add_admins
                2010    LOAD_FAST                       0: account
                2012    LOAD_FAST                       11: _var_var_42
                2014    LOAD_FAST                       34: _var_var_61
                2016    LOAD_FAST                       20: _var_var_51
                2018    CALL                            4
                2026    POP_TOP                         
                2028    LOAD_FAST                       18: _var_var_49
                2030    POP_JUMP_IF_FALSE               736 (to 3506)
                2034    NOP                             
                2036    LOAD_FAST                       21: _var_var_52
                2038    LOAD_ATTR                       15: get
                2058    LOAD_CONST                      39: 'text'
                2060    CALL                            1
                2068    STORE_FAST                      36: _var_var_63
                2070    LOAD_FAST                       36: _var_var_63
                2072    LOAD_CONST                      35: ''
                2074    COMPARE_OP                      40 (==)
                2078    POP_JUMP_IF_TRUE                2 (to 2084)
                2080    LOAD_FAST                       36: _var_var_63
                2082    POP_JUMP_IF_NOT_NONE            3 (to 2090)
                2084    LOAD_CONST                      0: None
                2086    STORE_FAST                      36: _var_var_63
                2088    JUMP_FORWARD                    21 (to 2132)
                2090    LOAD_GLOBAL                     35: NULL + spintax
                2100    LOAD_ATTR                       36: spin
                2120    LOAD_FAST                       36: _var_var_63
                2122    CALL                            1
                2130    STORE_FAST                      36: _var_var_63
                2132    LOAD_FAST                       24: _var_var_55
                2134    POP_JUMP_IF_NONE                226 (to 2588)
                2136    LOAD_GLOBAL                     39: NULL + len
                2146    LOAD_FAST                       24: _var_var_55
                2148    CALL                            1
                2156    LOAD_CONST                      29: 0
                2158    COMPARE_OP                      55 (!=)
                2162    POP_JUMP_IF_FALSE               212 (to 2588)
                2164    LOAD_GLOBAL                     41: NULL + random
                2174    LOAD_ATTR                       42: choice
                2194    LOAD_FAST                       24: _var_var_55
                2196    CALL                            1
                2204    STORE_FAST                      37: _var_var_64
                2206    LOAD_CONST                      40: 'http'
                2208    LOAD_FAST                       37: _var_var_64
                2210    CONTAINS_OP                     0 (in)
                2212    POP_JUMP_IF_TRUE                4 (to 2222)
                2214    LOAD_CONST                      41: 'https'
                2216    LOAD_FAST                       37: _var_var_64
                2218    CONTAINS_OP                     0 (in)
                2220    POP_JUMP_IF_FALSE               3 (to 2228)
                2222    LOAD_FAST                       37: _var_var_64
                2224    STORE_FAST                      38: _var_var_65
                2226    JUMP_FORWARD                    17 (to 2262)
                2228    LOAD_FAST                       11: _var_var_42
                2230    LOAD_ATTR                       45: upload_file
                2250    LOAD_FAST                       37: _var_var_64
                2252    CALL                            1
                2260    STORE_FAST                      38: _var_var_65
                2262    LOAD_CONST                      42: '.ogg'
                2264    LOAD_FAST                       37: _var_var_64
                2266    CONTAINS_OP                     0 (in)
                2268    POP_JUMP_IF_TRUE                4 (to 2278)
                2270    LOAD_CONST                      43: '.mp3'
                2272    LOAD_FAST                       37: _var_var_64
                2274    CONTAINS_OP                     0 (in)
                2276    POP_JUMP_IF_FALSE               70 (to 2418)
                2278    LOAD_GLOBAL                     9: NULL + Logs
                2288    LOAD_ATTR                       10: PrintLog
                2308    LOAD_FAST                       1: config
                2310    LOAD_FAST                       0: account
                2312    LOAD_GLOBAL                     4: Lang
                2322    PUSH_NULL                       
                2324    LOAD_CONST                      1: '__pyarmor_assert_13464__'
                2326    LOAD_CONST                      44: 'type_defined_voice_message'   # b'\x81\xf6\x01\x036\xc5\xba\xd7\x1d\xf3\x03\xc5h\xd3\xee\x8a\x06^\xbe\x98\xa7\xce]\xdf\x04h\xa6'
                2328    CALL                            1
                2336    BINARY_SUBSCR                   
                2340    KW_NAMES                        10: ('config', 'account', 'message')
                2342    CALL                            3
                2350    POP_TOP                         
                2352    LOAD_GLOBAL                     47: NULL + str
                2362    LOAD_FAST                       37: _var_var_64
                2364    CALL                            1
                2372    STORE_FAST                      35: _var_var_62
                2374    LOAD_FAST                       11: _var_var_42
                2376    LOAD_ATTR                       49: send_file
                2396    LOAD_FAST                       34: _var_var_61
                2398    LOAD_FAST                       38: _var_var_65
                2400    LOAD_CONST                      32: True
                2402    KW_NAMES                        45: ('voice_note',)
                2404    CALL                            3
                2412    STORE_FAST                      39: _var_var_66
                2414    JUMP_FORWARD                    514 (to 3446)
                2418    LOAD_GLOBAL                     9: NULL + Logs
                2428    LOAD_ATTR                       10: PrintLog
                2448    LOAD_FAST                       1: config
                2450    LOAD_FAST                       0: account
                2452    LOAD_GLOBAL                     4: Lang
                2462    PUSH_NULL                       
                2464    LOAD_CONST                      1: '__pyarmor_assert_13464__'
                2466    LOAD_CONST                      46: 'type_defined_file_description'   # b'\x81\xf6\x01\x036\xc5\xba\xd7\x1d\xf3\x03\xc5h\xd3\xfe\x8c\x03X\x84\xa3\xaf\xd8M\xde\x0c\x7f\xb7U\x0f\xbf'
                2468    CALL                            1
                2476    BINARY_SUBSCR                   
                2480    KW_NAMES                        10: ('config', 'account', 'message')
                2482    CALL                            3
                2490    POP_TOP                         
                2492    LOAD_GLOBAL                     47: NULL + str
                2502    LOAD_FAST                       37: _var_var_64
                2504    CALL                            1
                2512    LOAD_CONST                      47: ' '
                2514    BINARY_OP                       0 (+)
                2518    LOAD_GLOBAL                     47: NULL + str
                2528    LOAD_FAST                       36: _var_var_63
                2530    CALL                            1
                2538    BINARY_OP                       0 (+)
                2542    STORE_FAST                      35: _var_var_62
                2544    LOAD_FAST                       11: _var_var_42
                2546    LOAD_ATTR                       49: send_file
                2566    LOAD_FAST                       34: _var_var_61
                2568    LOAD_FAST                       38: _var_var_65
                2570    LOAD_FAST                       36: _var_var_63
                2572    KW_NAMES                        48: ('caption',)
                2574    CALL                            3
                2582    STORE_FAST                      39: _var_var_66
                2584    JUMP_FORWARD                    429 (to 3446)
                2588    LOAD_FAST                       25: _var_var_13
                2590    POP_JUMP_IF_NONE                218 (to 3028)
                2592    LOAD_GLOBAL                     39: NULL + len
                2602    LOAD_FAST                       25: _var_var_13
                2604    CALL                            1
                2612    LOAD_CONST                      29: 0
                2614    COMPARE_OP                      55 (!=)
                2618    POP_JUMP_IF_FALSE               204 (to 3028)
                2620    LOAD_GLOBAL                     9: NULL + Logs
                2630    LOAD_ATTR                       10: PrintLog
                2650    LOAD_FAST                       1: config
                2652    LOAD_FAST                       0: account
                2654    LOAD_GLOBAL                     4: Lang
                2664    PUSH_NULL                       
                2666    LOAD_CONST                      1: '__pyarmor_assert_13464__'
                2668    LOAD_CONST                      49: 'type_defined_repost'   # b'\x81\xf6\x01\x036\xc5\xba\xd7\x1d\xf3\x03\xc5h\xd3\xea\x80\x1fR\xa8\xb3'
                2670    CALL                            1
                2678    BINARY_SUBSCR                   
                2682    KW_NAMES                        10: ('config', 'account', 'message')
                2684    CALL                            3
                2692    POP_TOP                         
                2694    LOAD_GLOBAL                     41: NULL + random
                2704    LOAD_ATTR                       42: choice
                2724    LOAD_FAST                       25: _var_var_13
                2726    CALL                            1
                2734    STORE_FAST                      40: _var_var_67
                2736    LOAD_GLOBAL                     47: NULL + str
                2746    LOAD_FAST                       40: _var_var_67
                2748    CALL                            1
                2756    STORE_FAST                      35: _var_var_62
                2758    LOAD_FAST                       40: _var_var_67
                2760    LOAD_ATTR                       51: replace
                2780    PUSH_NULL                       
                2782    LOAD_CONST                      1: '__pyarmor_assert_13464__'
                2784    LOAD_CONST                      50: 'https://t.me/'   # b'\x81\xea\x0c\x07#\xe9\xe4\x9dT\xeeC\xcdi\xa3'
                2786    CALL                            1
                2794    LOAD_CONST                      35: ''
                2796    CALL                            2
                2804    LOAD_ATTR                       51: replace
                2824    PUSH_NULL                       
                2826    LOAD_CONST                      1: '__pyarmor_assert_13464__'
                2828    LOAD_CONST                      51: 'http://t.me/'   # b'\x81\xea\x0c\x07#\xa0\xf1\x9d\x0f\xb4\x00\xc5#'
                2830    CALL                            1
                2838    LOAD_CONST                      35: ''
                2840    CALL                            2
                2848    LOAD_ATTR                       51: replace
                2868    LOAD_CONST                      47: ' '
                2870    LOAD_CONST                      35: ''
                2872    CALL                            2
                2880    STORE_FAST                      40: _var_var_67
                2882    LOAD_FAST                       40: _var_var_67
                2884    LOAD_ATTR                       53: split
                2904    LOAD_CONST                      52: '/'
                2906    CALL                            1
                2914    STORE_FAST                      40: _var_var_67
                2916    LOAD_FAST                       40: _var_var_67
                2918    LOAD_CONST                      29: 0
                2920    BINARY_SUBSCR                   
                2924    STORE_FAST                      41: _var_var_68
                2926    LOAD_FAST                       40: _var_var_67
                2928    LOAD_CONST                      53: 1
                2930    BINARY_SUBSCR                   
                2934    STORE_FAST                      42: _var_var_69
                2936    LOAD_FAST                       11: _var_var_42
                2938    LOAD_ATTR                       55: get_entity
                2958    LOAD_FAST                       41: _var_var_68
                2960    CALL                            1
                2968    STORE_FAST                      43: _var_var_70
                2970    LOAD_FAST                       11: _var_var_42
                2972    LOAD_ATTR                       57: forward_messages
                2992    LOAD_FAST                       34: _var_var_61
                2994    LOAD_GLOBAL                     13: NULL + int
                3004    LOAD_FAST                       42: _var_var_69
                3006    CALL                            1
                3014    LOAD_FAST                       43: _var_var_70
                3016    CALL                            3
                3024    POP_TOP                         
                3026    JUMP_FORWARD                    209 (to 3446)
                3028    LOAD_GLOBAL                     39: NULL + len
                3038    LOAD_FAST                       23: _var_var_54
                3040    CALL                            1
                3048    LOAD_CONST                      29: 0
                3050    COMPARE_OP                      68 (>)
                3054    POP_JUMP_IF_FALSE               125 (to 3306)
                3056    LOAD_GLOBAL                     9: NULL + Logs
                3066    LOAD_ATTR                       10: PrintLog
                3086    LOAD_FAST                       1: config
                3088    LOAD_FAST                       0: account
                3090    LOAD_GLOBAL                     4: Lang
                3100    PUSH_NULL                       
                3102    LOAD_CONST                      1: '__pyarmor_assert_13464__'
                3104    LOAD_CONST                      54: 'type_defined_postbot'   # b'\x81\xf6\x01\x036\xc5\xba\xd7\x1d\xf3\x03\xc5h\xd3\xe8\x8a\x1cI\xb9\xa8\xbe'
                3106    CALL                            1
                3114    BINARY_SUBSCR                   
                3118    KW_NAMES                        10: ('config', 'account', 'message')
                3120    CALL                            3
                3128    POP_TOP                         
                3130    LOAD_GLOBAL                     41: NULL + random
                3140    LOAD_ATTR                       42: choice
                3160    LOAD_FAST                       23: _var_var_54
                3162    CALL                            1
                3170    STORE_FAST                      44: _var_var_71
                3172    LOAD_GLOBAL                     47: NULL + str
                3182    LOAD_FAST                       44: _var_var_71
                3184    CALL                            1
                3192    STORE_FAST                      35: _var_var_62
                3194    LOAD_FAST                       11: _var_var_42
                3196    LOAD_ATTR                       55: get_entity
                3216    LOAD_FAST                       22: _var_var_53
                3218    CALL                            1
                3226    STORE_FAST                      45: _var_var_72
                3228    LOAD_FAST                       11: _var_var_42
                3230    LOAD_ATTR                       59: inline_query
                3250    LOAD_FAST                       45: _var_var_72
                3252    LOAD_FAST                       44: _var_var_71
                3254    CALL                            2
                3262    STORE_FAST                      46: _var_var_73
                3264    LOAD_FAST                       46: _var_var_73
                3266    LOAD_CONST                      29: 0
                3268    BINARY_SUBSCR                   
                3272    LOAD_ATTR                       61: click
                3292    LOAD_FAST                       34: _var_var_61
                3294    CALL                            1
                3302    STORE_FAST                      47: _var_var_74
                3304    JUMP_FORWARD                    70 (to 3446)
                3306    LOAD_GLOBAL                     9: NULL + Logs
                3316    LOAD_ATTR                       10: PrintLog
                3336    LOAD_FAST                       1: config
                3338    LOAD_FAST                       0: account
                3340    LOAD_GLOBAL                     4: Lang
                3350    PUSH_NULL                       
                3352    LOAD_CONST                      1: '__pyarmor_assert_13464__'
                3354    LOAD_CONST                      55: 'type_defined_text'   # b'\x81\xf6\x01\x036\xc5\xba\xd7\x1d\xf3\x03\xc5h\xd3\xec\x80\x17I'
                3356    CALL                            1
                3364    BINARY_SUBSCR                   
                3368    KW_NAMES                        10: ('config', 'account', 'message')
                3370    CALL                            3
                3378    POP_TOP                         
                3380    LOAD_GLOBAL                     47: NULL + str
                3390    LOAD_FAST                       36: _var_var_63
                3392    CALL                            1
                3400    STORE_FAST                      35: _var_var_62
                3402    LOAD_FAST                       36: _var_var_63
                3404    POP_JUMP_IF_NONE                20 (to 3446)
                3406    LOAD_FAST                       11: _var_var_42
                3408    LOAD_ATTR                       63: send_message
                3428    LOAD_FAST                       34: _var_var_61
                3430    LOAD_FAST                       36: _var_var_63
                3432    LOAD_CONST                      56: 'md'
                3434    KW_NAMES                        57: ('parse_mode',)
                3436    CALL                            3
                3444    POP_TOP                         
                3446    LOAD_GLOBAL                     9: NULL + Logs
                3456    LOAD_ATTR                       10: PrintLog
                3476    LOAD_FAST                       1: config
                3478    LOAD_FAST                       0: account
                3480    PUSH_NULL                       
                3482    LOAD_CONST                      1: '__pyarmor_assert_13464__'
                3484    LOAD_CONST                      58: 'Message is send'   # b'\x81\xcf\x1d\x00 \xfb\xb9\xd7[\xf3\x1e\x80\x7f\xe9\xf6\x81'
                3486    CALL                            1
                3494    KW_NAMES                        10: ('config', 'account', 'message')
                3496    CALL                            3
                3504    POP_TOP                         
                3506    LOAD_GLOBAL                     67: NULL + db_create_channels
                3516    LOAD_FAST                       4: db_result
                3518    CALL                            1
                3526    LOAD_ATTR                       69: set_data
                3546    LOAD_FAST                       0: account
                3548    LOAD_FAST                       34: _var_var_61
                3550    LOAD_ATTR                       70: id
                3570    LOAD_FAST                       34: _var_var_61
                3572    LOAD_ATTR                       72: title
                3592    LOAD_FAST                       33: _var_var_36
                3594    LOAD_FAST                       35: _var_var_62
                3596    LOAD_CONST                      61: 'Done'
                3598    CALL                            6
                3606    POP_TOP                         
                3608    LOAD_FAST                       26: _var_var_4
                3610    LOAD_CONST                      53: 1
                3612    BINARY_OP                       13 (+=)
                3616    STORE_FAST                      26: _var_var_4
                3618    JUMP_BACKWARD                   1203 (to 1216)
                3622    END_FOR                         
                3624    NOP                             
                3626    LOAD_GLOBAL                     7: NULL + Disconnect
                3636    LOAD_FAST_CHECK                 11: _var_var_42
                3638    CALL                            1
                3646    POP_TOP                         
                3648    LOAD_GLOBAL                     9: NULL + Logs
                3658    LOAD_ATTR                       10: PrintLog
                3678    LOAD_FAST                       1: config
                3680    LOAD_FAST                       0: account
                3682    LOAD_GLOBAL                     4: Lang
                3692    PUSH_NULL                       
                3694    LOAD_CONST                      1: '__pyarmor_assert_13464__'
                3696    LOAD_CONST                      9: 'work_account_completed'   # b'\x81\xf5\x17\x018\xc5\xbf\xd1\x18\xf5\x18\xcex\xd3\xfb\x8a\x02M\xb7\xa2\xbe\xceJ'
                3698    CALL                            1
                3706    BINARY_SUBSCR                   
                3710    KW_NAMES                        10: ('config', 'account', 'message')
                3712    CALL                            3
                3720    POP_TOP                         
                3722    LOAD_FAST                       0: account
                3724    LOAD_CONST                      11: 'done'
                3726    LOAD_CONST                      8: ('account', 'status')
                3728    BUILD_CONST_KEY_MAP             2
                3730    NOP                             
                3732    NOP                             
                3734    JUMP_FORWARD                    262 (to 4262)
                3738    CALL                            1
                3746    POP_TOP                         
                3748    RETURN_VALUE                    
                3750    PUSH_EXC_INFO                   
                3752    POP_TOP                         
                3754    POP_EXCEPT                      
                3756    JUMP_BACKWARD                   1805 (to 150)
                3760    COPY                            3
                3762    POP_EXCEPT                      
                3764    RERAISE                         1
                3766    PUSH_EXC_INFO                   
                3768    POP_TOP                         
                3770    POP_EXCEPT                      
                3772    JUMP_BACKWARD                   1179 (to 1418)
                3776    COPY                            3
                3778    POP_EXCEPT                      
                3780    RERAISE                         1
                3782    PUSH_EXC_INFO                   
                3784    POP_TOP                         
                3786    POP_EXCEPT                      
                3788    JUMP_BACKWARD                   1172 (to 1448)
                3792    COPY                            3
                3794    POP_EXCEPT                      
                3796    RERAISE                         1
                3798    PUSH_EXC_INFO                   
                3800    POP_TOP                         
                3802    POP_EXCEPT                      
                3804    JUMP_BACKWARD                   990 (to 1828)
                3808    COPY                            3
                3810    POP_EXCEPT                      
                3812    RERAISE                         1
                3814    PUSH_EXC_INFO                   
                3816    POP_TOP                         
                3818    POP_EXCEPT                      
                3820    JUMP_BACKWARD                   983 (to 1858)
                3824    COPY                            3
                3826    POP_EXCEPT                      
                3828    RERAISE                         1
                3830    PUSH_EXC_INFO                   
                3832    LOAD_GLOBAL                     18: StopProgram
                3842    CHECK_EXC_MATCH                 
                3844    POP_JUMP_IF_FALSE               2 (to 3850)
                3846    POP_TOP                         
                3848    RAISE_VARARGS                   0
                3850    LOAD_GLOBAL                     64: Exception
                3860    CHECK_EXC_MATCH                 
                3862    POP_JUMP_IF_FALSE               48 (to 3960)
                3864    STORE_FAST                      48: _var_var_37
                3866    LOAD_GLOBAL                     9: NULL + Logs
                3876    LOAD_ATTR                       10: PrintLog
                3896    LOAD_FAST                       1: config
                3898    LOAD_FAST                       0: account
                3900    LOAD_GLOBAL                     4: Lang
                3910    PUSH_NULL                       
                3912    LOAD_CONST                      1: '__pyarmor_assert_13464__'
                3914    LOAD_CONST                      59: 'an_unhandled_error_was_detected'   # b'\x81\xe3\x16,&\xf4\xb6\xd3\x15\xfe\x01\xc5h\xd3\xfd\x97\x1dR\xa9\x98\xbd\xca]\xf3\x01j\xb7Y\x03\xa5\x1b\xe1'
                3916    CALL                            1
                3924    BINARY_SUBSCR                   
                3928    LOAD_FAST                       48: _var_var_37
                3930    KW_NAMES                        60: ('config', 'account', 'message', 'param')
                3932    CALL                            4
                3940    POP_TOP                         
                3942    POP_EXCEPT                      
                3944    LOAD_CONST                      0: None
                3946    STORE_FAST                      48: _var_var_37
                3948    DELETE_FAST                     48: _var_var_37
                3950    JUMP_BACKWARD                   223 (to 3506)
                3952    LOAD_CONST                      0: None
                3954    STORE_FAST                      48: _var_var_37
                3956    DELETE_FAST                     48: _var_var_37
                3958    RERAISE                         1
                3960    RERAISE                         0
                3962    COPY                            3
                3964    POP_EXCEPT                      
                3966    RERAISE                         1
                3968    PUSH_EXC_INFO                   
                3970    LOAD_GLOBAL                     18: StopProgram
                3980    CHECK_EXC_MATCH                 
                3982    POP_JUMP_IF_FALSE               3 (to 3990)
                3984    POP_TOP                         
                3986    POP_EXCEPT                      
                3988    JUMP_BACKWARD                   182 (to 3626)
                3990    LOAD_GLOBAL                     74: BaseException
                4000    CHECK_EXC_MATCH                 
                4002    POP_JUMP_IF_FALSE               26 (to 4056)
                4004    STORE_FAST                      49: _var_var_3
                4006    PUSH_NULL                       
                4008    LOAD_GLOBAL                     77: NULL + logging
                4018    LOAD_FAST                       49: _var_var_3
                4020    CALL                            1
                4028    CALL                            0
                4036    POP_TOP                         
                4038    POP_EXCEPT                      
                4040    LOAD_CONST                      0: None
                4042    STORE_FAST                      49: _var_var_3
                4044    DELETE_FAST                     49: _var_var_3
                4046    JUMP_BACKWARD                   211 (to 3626)
                4048    LOAD_CONST                      0: None
                4050    STORE_FAST                      49: _var_var_3
                4052    DELETE_FAST                     49: _var_var_3
                4054    RERAISE                         1
                4056    RERAISE                         0
                4058    COPY                            3
                4060    POP_EXCEPT                      
                4062    RERAISE                         1
                4064    PUSH_EXC_INFO                   
                4066    POP_TOP                         
                4068    POP_EXCEPT                      
                4070    JUMP_BACKWARD                   212 (to 3648)
                4072    COPY                            3
                4074    POP_EXCEPT                      
                4076    RERAISE                         1
                4078    PUSH_EXC_INFO                   
                4080    LOAD_GLOBAL                     7: NULL + Disconnect
                4090    LOAD_FAST_CHECK                 11: _var_var_42
                4092    CALL                            1
                4100    POP_TOP                         
                4102    JUMP_FORWARD                    7 (to 4118)
                4104    PUSH_EXC_INFO                   
                4106    POP_TOP                         
                4108    POP_EXCEPT                      
                4110    JUMP_FORWARD                    3 (to 4118)
                4112    COPY                            3
                4114    POP_EXCEPT                      
                4116    RERAISE                         1
                4118    LOAD_GLOBAL                     9: NULL + Logs
                4128    LOAD_ATTR                       10: PrintLog
                4148    LOAD_FAST                       1: config
                4150    LOAD_FAST                       0: account
                4152    LOAD_GLOBAL                     4: Lang
                4162    PUSH_NULL                       
                4164    LOAD_CONST                      1: '__pyarmor_assert_13464__'
                4166    LOAD_CONST                      9: 'work_account_completed'   # b'\x81\xf5\x17\x018\xc5\xbf\xd1\x18\xf5\x18\xcex\xd3\xfb\x8a\x02M\xb7\xa2\xbe\xceJ'
                4168    CALL                            1
                4176    BINARY_SUBSCR                   
                4180    KW_NAMES                        10: ('config', 'account', 'message')
                4182    CALL                            3
                4190    POP_TOP                         
                4192    LOAD_FAST                       0: account
                4194    LOAD_CONST                      11: 'done'
                4196    LOAD_CONST                      8: ('account', 'status')
                4198    BUILD_CONST_KEY_MAP             2
                4200    SWAP                            2
                4202    POP_TOP                         
                4204    SWAP                            2
                4206    POP_EXCEPT                      
                4208    NOP                             
                4210    NOP                             
                4212    NOP                             
                4214    JUMP_FORWARD                    23 (to 4262)
                4216    CALL                            1
                4224    POP_TOP                         
                4226    RETURN_VALUE                    
                4228    COPY                            3
                4230    POP_EXCEPT                      
                4232    RERAISE                         1
                4234    PUSH_EXC_INFO                   
                4236    PUSH_NULL                       
                4238    LOAD_CONST                      12: '__pyarmor_exit_13466__'
                4240    NOP                             
                4242    LOAD_CONST                      3: b'<COAddr>\x07\x00\x00\x1ap\x10\x00\x00\x00\x00\x00\x00\x00\x00\x00\x00\x00\x00\x00\x00'
                4244    CALL                            1
                4252    POP_TOP                         
                4254    RERAISE                         0
                4256    COPY                            3
                4258    POP_EXCEPT                      
                4260    RERAISE                         1
                4262    PUSH_NULL                       
                4264    LOAD_CONST                      12: '__pyarmor_exit_13466__'
                4266    LOAD_CONST                      3: b'<COAddr>\x07\x00\x00\x1ap\x10\x00\x00\x00\x00\x00\x00\x00\x00\x00\x00\x00\x00\x00\x00'
                4268    BUILD_TUPLE                     1
                4270    CALL_FUNCTION_EX                0
                4272    POP_TOP                         
                4274    RETURN_VALUE                    
            [Exception Table]
                30 to 128 -> 3968 [0] 
                128 to 150 -> 3750 [1] 
                150 to 236 -> 4234 [0] 
                256 to 1396 -> 3968 [0] 
                1396 to 1418 -> 3766 [1] 
                1418 to 1426 -> 3968 [0] 
                1426 to 1448 -> 3782 [1] 
                1448 to 1534 -> 4234 [0] 
                1554 to 1806 -> 3968 [0] 
                1806 to 1828 -> 3798 [1] 
                1828 to 1836 -> 3968 [0] 
                1836 to 1858 -> 3814 [1] 
                1858 to 1944 -> 4234 [0] 
                1964 to 2034 -> 3968 [0] 
                2036 to 3506 -> 3830 [1] 
                3506 to 3624 -> 3968 [0] 
                3624 to 3626 -> 4078 [0] 
                3626 to 3648 -> 4064 [0] 
                3648 to 3730 -> 4234 [0] 
                3750 to 3754 -> 3760 [2] lasti
                3754 to 3766 -> 4234 [0] 
                3766 to 3770 -> 3776 [2] lasti
                3770 to 3782 -> 3968 [0] 
                3782 to 3786 -> 3792 [2] lasti
                3786 to 3798 -> 4234 [0] 
                3798 to 3802 -> 3808 [2] lasti
                3802 to 3814 -> 3968 [0] 
                3814 to 3818 -> 3824 [2] lasti
                3818 to 3830 -> 4234 [0] 
                3830 to 3866 -> 3962 [2] lasti
                3866 to 3942 -> 3952 [2] lasti
                3942 to 3952 -> 3968 [0] 
                3952 to 3962 -> 3962 [2] lasti
                3962 to 3968 -> 3968 [0] 
                3968 to 3986 -> 4058 [1] lasti
                3986 to 3990 -> 4078 [0] 
                3990 to 4006 -> 4058 [1] lasti
                4006 to 4038 -> 4048 [1] lasti
                4038 to 4048 -> 4078 [0] 
                4048 to 4058 -> 4058 [1] lasti
                4058 to 4064 -> 4078 [0] 
                4064 to 4068 -> 4072 [1] lasti
                4068 to 4078 -> 4234 [0] 
                4078 to 4080 -> 4228 [1] lasti
                4080 to 4102 -> 4104 [2] 
                4102 to 4104 -> 4228 [1] lasti
                4104 to 4108 -> 4112 [3] lasti
                4108 to 4206 -> 4228 [1] lasti
                4206 to 4208 -> 4234 [0] 
                4228 to 4234 -> 4234 [0] 
                4234 to 4256 -> 4256 [1] lasti
        '__pyarmor_exit_13433__'
        (
            500
        )
    [Disassembly]
        0       NOP                             
        2       NOP                             
        4       PUSH_NULL                       
        6       LOAD_CONST                      1: '__pyarmor_enter_13432__'
        8       LOAD_CONST                      2: b'<COAddr>\x07\x00\x00\x1a\x9a\x01\x00\x00\x00\x00\x00\x00\x00\x00\x00\x00\x00\x00\x00\x00'
        10      BUILD_TUPLE                     1
        12      CALL_FUNCTION_EX                0
        14      POP_TOP                         
        16      RESUME                          0
        18      NOP                             
        20      NOP                             
        22      NOP                             
        24      NOP                             
        26      LOAD_CONST                      3: 0
        28      LOAD_CONST                      4: None
        30      IMPORT_NAME                     1: eel
        32      STORE_NAME                      1: eel
        34      LOAD_CONST                      3: 0
        36      LOAD_CONST                      4: None
        38      IMPORT_NAME                     2: json
        40      STORE_NAME                      2: json
        42      LOAD_CONST                      3: 0
        44      LOAD_CONST                      4: None
        46      IMPORT_NAME                     3: time
        48      STORE_NAME                      3: time
        50      LOAD_CONST                      3: 0
        52      LOAD_CONST                      4: None
        54      IMPORT_NAME                     4: random
        56      STORE_NAME                      4: random
        58      LOAD_CONST                      3: 0
        60      LOAD_CONST                      4: None
        62      IMPORT_NAME                     5: string
        64      STORE_NAME                      5: string
        66      LOAD_CONST                      3: 0
        68      LOAD_CONST                      4: None
        70      IMPORT_NAME                     6: spintax
        72      STORE_NAME                      6: spintax
        74      LOAD_CONST                      3: 0
        76      LOAD_CONST                      4: None
        78      IMPORT_NAME                     7: datetime
        80      STORE_NAME                      7: datetime
        82      LOAD_CONST                      3: 0
        84      LOAD_CONST                      4: None
        86      IMPORT_NAME                     8: concurrent.futures
        88      STORE_NAME                      9: concurrent
        90      LOAD_CONST                      3: 0
        92      LOAD_CONST                      5: ('Thread', 'Event')
        94      IMPORT_NAME                     10: threading
        96      IMPORT_FROM                     11: Thread
        98      STORE_NAME                      11: Thread
        100     IMPORT_FROM                     12: Event
        102     STORE_NAME                      12: Event
        104     POP_TOP                         
        106     LOAD_CONST                      3: 0
        108     LOAD_CONST                      6: ('functions', 'types', 'errors')
        110     IMPORT_NAME                     13: multithon.sync
        112     IMPORT_FROM                     14: functions
        114     STORE_NAME                      14: functions
        116     IMPORT_FROM                     15: types
        118     STORE_NAME                      15: types
        120     IMPORT_FROM                     16: errors
        122     STORE_NAME                      16: errors
        124     POP_TOP                         
        126     LOAD_CONST                      3: 0
        128     LOAD_CONST                      7: ('StopProgram',)
        130     IMPORT_NAME                     17: multithon.errors
        132     IMPORT_FROM                     18: StopProgram
        134     STORE_NAME                      18: StopProgram
        136     POP_TOP                         
        138     LOAD_CONST                      3: 0
        140     LOAD_CONST                      8: ('GetLang',)
        142     IMPORT_NAME                     19: program.static_classes
        144     IMPORT_FROM                     20: GetLang
        146     STORE_NAME                      20: GetLang
        148     POP_TOP                         
        150     LOAD_CONST                      3: 0
        152     LOAD_CONST                      9: ('Logs',)
        154     IMPORT_NAME                     19: program.static_classes
        156     IMPORT_FROM                     21: Logs
        158     STORE_NAME                      21: Logs
        160     POP_TOP                         
        162     LOAD_CONST                      3: 0
        164     LOAD_CONST                      10: ('logging',)
        166     IMPORT_NAME                     19: program.static_classes
        168     IMPORT_FROM                     22: logging
        170     STORE_NAME                      22: logging
        172     POP_TOP                         
        174     LOAD_CONST                      3: 0
        176     LOAD_CONST                      11: ('memory_check_switcher',)
        178     IMPORT_NAME                     19: program.static_classes
        180     IMPORT_FROM                     23: memory_check_switcher
        182     STORE_NAME                      23: memory_check_switcher
        184     POP_TOP                         
        186     LOAD_CONST                      3: 0
        188     LOAD_CONST                      12: ('memory_set_pid',)
        190     IMPORT_NAME                     19: program.static_classes
        192     IMPORT_FROM                     24: memory_set_pid
        194     STORE_NAME                      24: memory_set_pid
        196     POP_TOP                         
        198     LOAD_CONST                      3: 0
        200     LOAD_CONST                      13: ('DelayOnline',)
        202     IMPORT_NAME                     25: program.telegram
        204     IMPORT_FROM                     26: DelayOnline
        206     STORE_NAME                      26: DelayOnline
        208     POP_TOP                         
        210     LOAD_CONST                      3: 0
        212     LOAD_CONST                      14: ('Disconnect',)
        214     IMPORT_NAME                     25: program.telegram
        216     IMPORT_FROM                     27: Disconnect
        218     STORE_NAME                      27: Disconnect
        220     POP_TOP                         
        222     LOAD_CONST                      3: 0
        224     LOAD_CONST                      15: ('Thread_wait',)
        226     IMPORT_NAME                     25: program.telegram
        228     IMPORT_FROM                     28: Thread_wait
        230     STORE_NAME                      28: Thread_wait
        232     POP_TOP                         
        234     LOAD_CONST                      3: 0
        236     LOAD_CONST                      16: ('account_works',)
        238     IMPORT_NAME                     25: program.telegram
        240     IMPORT_FROM                     29: account_works
        242     STORE_NAME                      29: account_works
        244     POP_TOP                         
        246     LOAD_CONST                      3: 0
        248     LOAD_CONST                      17: ('GetConfig',)
        250     IMPORT_NAME                     30: program.general
        252     IMPORT_FROM                     31: GetConfig
        254     STORE_NAME                      31: GetConfig
        256     POP_TOP                         
        258     LOAD_CONST                      3: 0
        260     LOAD_CONST                      18: ('GetProxy',)
        262     IMPORT_NAME                     30: program.general
        264     IMPORT_FROM                     32: GetProxy
        266     STORE_NAME                      32: GetProxy
        268     POP_TOP                         
        270     LOAD_CONST                      3: 0
        272     LOAD_CONST                      19: ('StopDetect',)
        274     IMPORT_NAME                     30: program.general
        276     IMPORT_FROM                     33: StopDetect
        278     STORE_NAME                      33: StopDetect
        280     POP_TOP                         
        282     LOAD_CONST                      3: 0
        284     LOAD_CONST                      20: ('check_get_settings',)
        286     IMPORT_NAME                     30: program.general
        288     IMPORT_FROM                     34: check_get_settings
        290     STORE_NAME                      34: check_get_settings
        292     POP_TOP                         
        294     LOAD_CONST                      3: 0
        296     LOAD_CONST                      21: ('del_task_manager',)
        298     IMPORT_NAME                     30: program.general
        300     IMPORT_FROM                     35: del_task_manager
        302     STORE_NAME                      35: del_task_manager
        304     POP_TOP                         
        306     LOAD_CONST                      3: 0
        308     LOAD_CONST                      22: ('getFile',)
        310     IMPORT_NAME                     30: program.general
        312     IMPORT_FROM                     36: getFile
        314     STORE_NAME                      36: getFile
        316     POP_TOP                         
        318     LOAD_CONST                      3: 0
        320     LOAD_CONST                      23: ('getPath',)
        322     IMPORT_NAME                     30: program.general
        324     IMPORT_FROM                     37: getPath
        326     STORE_NAME                      37: getPath
        328     POP_TOP                         
        330     LOAD_CONST                      3: 0
        332     LOAD_CONST                      24: ('set_task_manager',)
        334     IMPORT_NAME                     30: program.general
        336     IMPORT_FROM                     38: set_task_manager
        338     STORE_NAME                      38: set_task_manager
        340     POP_TOP                         
        342     LOAD_CONST                      3: 0
        344     LOAD_CONST                      25: ('db_create_channels',)
        346     IMPORT_NAME                     39: program.database
        348     IMPORT_FROM                     40: db_create_channels
        350     STORE_NAME                      40: db_create_channels
        352     POP_TOP                         
        354     LOAD_CONST                      26: <CODE> Create_channels
        356     MAKE_FUNCTION                   0
        358     STORE_NAME                      41: Create_channels
        360     LOAD_CONST                      27: <CODE> generator_list
        362     MAKE_FUNCTION                   0
        364     STORE_NAME                      42: generator_list
        366     LOAD_CONST                      28: <CODE> generator_get
        368     MAKE_FUNCTION                   0
        370     STORE_NAME                      43: generator_get
        372     LOAD_CONST                      29: <CODE> START
        374     MAKE_FUNCTION                   0
        376     STORE_NAME                      44: START
        378     LOAD_CONST                      30: <CODE> channel_create
        380     MAKE_FUNCTION                   0
        382     STORE_NAME                      45: channel_create
        384     LOAD_CONST                      37: (500,)
        386     LOAD_CONST                      31: <CODE> channel_set_username
        388     MAKE_FUNCTION                   1
        390     STORE_NAME                      46: channel_set_username
        392     LOAD_CONST                      32: <CODE> channel_get_link
        394     MAKE_FUNCTION                   0
        396     STORE_NAME                      47: channel_get_link
        398     LOAD_CONST                      33: <CODE> channel_set_photo
        400     MAKE_FUNCTION                   0
        402     STORE_NAME                      48: channel_set_photo
        404     LOAD_CONST                      34: <CODE> channel_add_admins
        406     MAKE_FUNCTION                   0
        408     STORE_NAME                      49: channel_add_admins
        410     LOAD_CONST                      35: <CODE> worker
        412     MAKE_FUNCTION                   0
        414     STORE_NAME                      50: worker
        416     LOAD_CONST                      4: None
        418     NOP                             
        420     NOP                             
        422     NOP                             
        424     JUMP_FORWARD                    19 (to 464)
        432     POP_TOP                         
        434     RETURN_CONST                    4: None
        436     PUSH_EXC_INFO                   
        438     PUSH_NULL                       
        440     LOAD_CONST                      36: '__pyarmor_exit_13433__'
        442     NOP                             
        444     LOAD_CONST                      2: b'<COAddr>\x07\x00\x00\x1a\x9a\x01\x00\x00\x00\x00\x00\x00\x00\x00\x00\x00\x00\x00\x00\x00'
        446     CALL                            1
        454     POP_TOP                         
        456     RERAISE                         0
        458     COPY                            3
        460     POP_EXCEPT                      
        462     RERAISE                         1
        464     PUSH_NULL                       
        466     LOAD_CONST                      36: '__pyarmor_exit_13433__'
        468     LOAD_CONST                      2: b'<COAddr>\x07\x00\x00\x1a\x9a\x01\x00\x00\x00\x00\x00\x00\x00\x00\x00\x00\x00\x00\x00\x00'
        470     BUILD_TUPLE                     1
        472     CALL_FUNCTION_EX                0
        474     POP_TOP                         
        476     RETURN_VALUE                    
    [Exception Table]
        26 to 416 -> 436 [0] 
        436 to 458 -> 458 [1] lasti
