#decoded by lolz.live/mrpenny / t.me/zeus_jackpot
# ================================
# Примечания по Pyarmor:
# - Байт-код и объекты кода Pyarmor соответствуют стандартному Python, но присутствуют специальные вызовы функций среды выполнения (runtime) Pyarmor.
# - Вызовы строк — это не ошибки, а маркеры, которые обрабатываются Pyarmor во время выполнения.
#
# Руководство по декомпиляции (без среды выполнения):
# 1. Игнорируйте зашифрованные байты после `#`; используйте только строку до `#`.
# 2. Удалите "__pyarmor_enter_xxx__"(b"<COAddr>...") и "__pyarmor_leave_xxx__"(b"<COAddr>...") (пролог/эпилог).
# 3. "__pyarmor_assert_xxx__"(A) не является настоящим оператором assert.
#    - Если A — это имя или читаемая строка: замените на A.
#    - Если A — это (X, "Y"): замените на X.Y.
#    - Если A — это (X, "Y", Z): замените на X.Y = Z.
#    - В противном случае: выберите наиболее подходящую/логичную замену.
# 4. "__pyarmor_bcc_xxx__"(...) указывает на машинный (нативный) код; тело функции недоступно. Добавьте комментарий.
# ================================

[Code]
    File Name: <frozen program.modules.Create_bots>
    Object Name: <module>
    Qualified Name: <module>
    Arg Count: 0
    Pos Only Arg Count: 0
    KW Only Arg Count: 0
    Stack Size: 5
    Flags: 0x20000000 (CO_PYARMOR_OBFUSCATED)
    [Names]
        '__assert_armored__'
        'eel'
        're'
        'spintax'
        'json'
        'time'
        'string'
        'datetime'
        'random'
        'concurrent.futures'
        'concurrent'
        'threading'
        'Thread'
        'Event'
        'Lock'
        'itertools'
        'cycle'
        'multithon.sync'
        'functions'
        'errors'
        'multithon.errors'
        'StopProgram'
        'program.static_classes'
        'GetLang'
        'Logs'
        'logging'
        'memory_check_switcher'
        'memory_set_pid'
        'program.telegram'
        'DelayOnline'
        'Disconnect'
        'Thread_wait'
        'account_works'
        'program.general'
        'GetConfig'
        'GetProxy'
        'StopDetect'
        'del_task_manager'
        'set_task_manager'
        'program.database'
        'db_create_bots'
        'Create_bots'
        'START'
        'worker'
        'username_generator'
        'modify_username'
        'button_click'
        'get_message'
    [Locals+Names]
    [Constants]
        '__pyarmor_assert_13407__'
        '__pyarmor_enter_13408__'
        b'<COAddr>\x05\x00\x00\x1ax\x01\x00\x00\x00\x00\x00\x00\x00\x00\x00\x00\x00\x00\x00\x00'
        0
        None
        (
            'Thread'
            'Event'
            'Lock'
        )
        (
            'cycle'
        )
        (
            'functions'
            'errors'
        )
        (
            'StopProgram'
        )
        (
            'GetLang'
        )
        (
            'Logs'
        )
        (
            'logging'
        )
        (
            'memory_check_switcher'
        )
        (
            'memory_set_pid'
        )
        (
            'DelayOnline'
        )
        (
            'Disconnect'
        )
        (
            'Thread_wait'
        )
        (
            'account_works'
        )
        (
            'GetConfig'
        )
        (
            'GetProxy'
        )
        (
            'StopDetect'
        )
        (
            'del_task_manager'
        )
        (
            'set_task_manager'
        )
        (
            'db_create_bots'
        )
        [Code]
            File Name: <frozen program.modules.Create_bots>
            Object Name: Create_bots
            Qualified Name: Create_bots
            Arg Count: 1
            Pos Only Arg Count: 0
            KW Only Arg Count: 0
            Stack Size: 8
            Flags: 0x20000003 (CO_OPTIMIZED | CO_NEWLOCALS | CO_PYARMOR_OBFUSCATED)
            [Names]
                'GetConfig'
                'config'
                'GetLang'
                'Lang'
                'GetProxy'
                'eel'
                'sendSuccessBox'
                'memory_check_switcher'
                'Event'
                'memory_set_pid'
                'Thread'
                'START'
                'start'
                'Logs'
                'WaitStopAnsfer'
                'UpdateLogInWindow'
                'BaseException'
                'logging'
            [Locals+Names]
                'data'
                '__assert_armored__'
                '_var_var_0'
                '_var_var_1'
                '_var_var_2'
                '_var_var_3'
            [Constants]
                None
                '__pyarmor_assert_13410__'
                '__pyarmor_enter_13411__'
                b'<COAddr>\x05\x00\x00\x1aT\x02\x00\x00\x00\x00\x00\x00\x00\x00\x00\x00\x00\x00\x00\x00'
                'program_running'   # b'\x81\xf2\n\x1c4\xe8\xbf\xdf$\xe8\x18\xceb\xe5\xf6\x82'
                '__pyarmor_exit_13412__'
                False
                (
                    'target'
                    'args'
                )
                True
                (
                    'target'
                    'args'
                    'daemon'
                )
            [Disassembly]
                0       NOP                             
                2       NOP                             
                4       PUSH_NULL                       
                6       LOAD_CONST                      2: '__pyarmor_enter_13411__'
                8       LOAD_CONST                      3: b'<COAddr>\x05\x00\x00\x1aT\x02\x00\x00\x00\x00\x00\x00\x00\x00\x00\x00\x00\x00\x00\x00'
                10      BUILD_TUPLE                     1
                12      CALL_FUNCTION_EX                0
                14      POP_TOP                         
                16      RESUME                          0
                18      NOP                             
                20      NOP                             
                22      NOP                             
                24      NOP                             
                26      NOP                             
                28      NOP                             
                30      LOAD_GLOBAL                     1: NULL + GetConfig
                40      CALL                            0
                48      STORE_GLOBAL                    1: config
                50      LOAD_GLOBAL                     5: NULL + GetLang
                60      LOAD_GLOBAL                     2: config
                70      CALL                            1
                78      STORE_GLOBAL                    3: Lang
                80      LOAD_GLOBAL                     9: NULL + GetProxy
                90      CALL                            0
                98      STORE_FAST                      2: _var_var_0
                100     LOAD_GLOBAL                     11: NULL + eel
                110     LOAD_ATTR                       12: sendSuccessBox
                130     LOAD_GLOBAL                     6: Lang
                140     PUSH_NULL                       
                142     LOAD_CONST                      1: '__pyarmor_assert_13410__'
                144     LOAD_CONST                      4: 'program_running'   # b'\x81\xf2\n\x1c4\xe8\xbf\xdf$\xe8\x18\xceb\xe5\xf6\x82'
                146     CALL                            1
                154     BINARY_SUBSCR                   
                158     CALL                            1
                166     POP_TOP                         
                168     LOAD_GLOBAL                     15: NULL + memory_check_switcher
                178     CALL                            0
                186     POP_JUMP_IF_TRUE                11 (to 210)
                188     NOP                             
                190     LOAD_CONST                      6: False
                192     NOP                             
                194     NOP                             
                196     NOP                             
                198     JUMP_FORWARD                    225 (to 650)
                206     POP_TOP                         
                208     RETURN_CONST                    6: False
                210     LOAD_GLOBAL                     17: NULL + Event
                220     CALL                            0
                228     STORE_FAST                      3: _var_var_1
                230     LOAD_GLOBAL                     19: NULL + memory_set_pid
                240     CALL                            0
                248     STORE_FAST                      4: _var_var_2
                250     LOAD_GLOBAL                     21: NULL + Thread
                260     LOAD_GLOBAL                     22: START
                270     LOAD_FAST                       0: data
                272     LOAD_GLOBAL                     2: config
                282     LOAD_FAST                       4: _var_var_2
                284     LOAD_FAST                       2: _var_var_0
                286     LOAD_FAST                       3: _var_var_1
                288     BUILD_TUPLE                     5
                290     KW_NAMES                        7: ('target', 'args')
                292     CALL                            2
                300     LOAD_ATTR                       25: start
                320     CALL                            0
                328     POP_TOP                         
                330     LOAD_GLOBAL                     21: NULL + Thread
                340     LOAD_GLOBAL                     26: Logs
                350     LOAD_ATTR                       28: WaitStopAnsfer
                370     LOAD_GLOBAL                     2: config
                380     LOAD_FAST                       4: _var_var_2
                382     LOAD_FAST                       3: _var_var_1
                384     BUILD_TUPLE                     3
                386     LOAD_CONST                      8: True
                388     KW_NAMES                        9: ('target', 'args', 'daemon')
                390     CALL                            3
                398     LOAD_ATTR                       25: start
                418     CALL                            0
                426     POP_TOP                         
                428     LOAD_GLOBAL                     21: NULL + Thread
                438     LOAD_GLOBAL                     26: Logs
                448     LOAD_ATTR                       30: UpdateLogInWindow
                468     LOAD_GLOBAL                     2: config
                478     LOAD_FAST                       4: _var_var_2
                480     LOAD_FAST                       3: _var_var_1
                482     BUILD_TUPLE                     3
                484     LOAD_CONST                      8: True
                486     KW_NAMES                        9: ('target', 'args', 'daemon')
                488     CALL                            3
                496     LOAD_ATTR                       25: start
                516     CALL                            0
                524     POP_TOP                         
                526     LOAD_CONST                      0: None
                528     NOP                             
                530     NOP                             
                532     NOP                             
                534     JUMP_FORWARD                    57 (to 650)
                542     POP_TOP                         
                544     RETURN_CONST                    0: None
                546     PUSH_EXC_INFO                   
                548     LOAD_GLOBAL                     32: BaseException
                558     CHECK_EXC_MATCH                 
                560     POP_JUMP_IF_FALSE               26 (to 614)
                562     STORE_FAST                      5: _var_var_3
                564     PUSH_NULL                       
                566     LOAD_GLOBAL                     35: NULL + logging
                576     LOAD_FAST                       5: _var_var_3
                578     CALL                            1
                586     CALL                            0
                594     POP_TOP                         
                596     POP_EXCEPT                      
                598     LOAD_CONST                      0: None
                600     STORE_FAST                      5: _var_var_3
                602     DELETE_FAST                     5: _var_var_3
                604     JUMP_BACKWARD                   40 (to 526)
                606     LOAD_CONST                      0: None
                608     STORE_FAST                      5: _var_var_3
                610     DELETE_FAST                     5: _var_var_3
                612     RERAISE                         1
                614     RERAISE                         0
                616     COPY                            3
                618     POP_EXCEPT                      
                620     RERAISE                         1
                622     PUSH_EXC_INFO                   
                624     PUSH_NULL                       
                626     LOAD_CONST                      5: '__pyarmor_exit_13412__'
                628     NOP                             
                630     LOAD_CONST                      3: b'<COAddr>\x05\x00\x00\x1aT\x02\x00\x00\x00\x00\x00\x00\x00\x00\x00\x00\x00\x00\x00\x00'
                632     CALL                            1
                640     POP_TOP                         
                642     RERAISE                         0
                644     COPY                            3
                646     POP_EXCEPT                      
                648     RERAISE                         1
                650     PUSH_NULL                       
                652     LOAD_CONST                      5: '__pyarmor_exit_13412__'
                654     LOAD_CONST                      3: b'<COAddr>\x05\x00\x00\x1aT\x02\x00\x00\x00\x00\x00\x00\x00\x00\x00\x00\x00\x00\x00\x00'
                656     BUILD_TUPLE                     1
                658     CALL_FUNCTION_EX                0
                660     POP_TOP                         
                662     RETURN_VALUE                    
            [Exception Table]
                30 to 188 -> 546 [0] 
                210 to 526 -> 546 [0] 
                546 to 564 -> 616 [1] lasti
                564 to 596 -> 606 [1] lasti
                596 to 606 -> 622 [0] 
                606 to 616 -> 616 [1] lasti
                616 to 622 -> 622 [0] 
                622 to 644 -> 644 [1] lasti
        [Code]
            File Name: <frozen program.modules.Create_bots>
            Object Name: START
            Qualified Name: START
            Arg Count: 5
            Pos Only Arg Count: 0
            KW Only Arg Count: 0
            Stack Size: 15
            Flags: 0x20000003 (CO_OPTIMIZED | CO_NEWLOCALS | CO_PYARMOR_OBFUSCATED)
            [Names]
                'is_set'
                'StopProgram'
                'isinstance'
                'list'
                'int'
                'len'
                'eel'
                'sendErrorBox'
                'Lang'
                'get'
                'datetime'
                'now'
                'strftime'
                'db_create_bots'
                'create'
                'WriteResult'
                'username_generator'
                'set_task_manager'
                'concurrent'
                'futures'
                'ThreadPoolExecutor'
                'StreamStat'
                'json'
                'dumps'
                'append'
                'submit'
                'worker'
                'as_completed'
                'BaseException'
                'logging'
                'del_task_manager'
                'StopDetect'
            [Locals+Names]
                'data'
                'config'
                'pid'
                'proxy'
                'stop_thread'
                '__assert_armored__'
                '_var_var_4'
                '_var_var_5'
                '_var_var_6'
                '_var_var_7'
                '_var_var_8'
                '_var_var_9'
                '_var_var_10'
                '_var_var_11'
                '_var_var_12'
                '_var_var_13'
                '_var_var_14'
                '_var_var_15'
                '_var_var_16'
                '_var_var_17'
                '_var_var_3'
            [Constants]
                None
                '__pyarmor_assert_13413__'
                '__pyarmor_enter_13414__'
                b'<COAddr>\x07\x00\x00\x1a\x9a\x06\x00\x00\x00\x00\x00\x00\x00\x00\x00\x00\x00\x00\x00\x00'
                'Accounts'
                1
                'select_accounts_works'   # b'\x81\xf1\x1d\x1f6\xf9\xaa\xed\x1a\xf9\x0e\xcfy\xe2\xec\x960J\xb4\xb5\xa1\xd8'
                'Settings'
                'thread_rules'   # b'\x81\xf6\x10\x016\xfb\xba\xed\t\xef\x01\xc5\x7f'
                True
                'thread_count'   # b'\x81\xf6\x10\x016\xfb\xba\xed\x18\xf5\x18\xcex'
                '%Y-%m-%d_%H-%M-%S'   # b'\x81\xa7!^v\xf7\xf3\x97\x1f\xc5H\xe8!\xa9\xd5\xc8Jn'
                'additives/create_bots/'   # b'\x81\xe3\x1c\x17:\xee\xb7\xc4\x1e\xe9B\xc3~\xe9\xf9\x91\nb\xb9\xa8\xbe\xd8\x01'
                '_result.db'   # b'\x81\xdd\n\x16 \xef\xb2\xc6U\xfe\x0f'
                'Bots'
                'create_bots'   # b'\x81\xe1\n\x162\xee\xbb\xed\x19\xf5\x19\xd3'
                'names'
                'usernames'   # b'\x81\xf7\x0b\x16!\xf4\xbf\xdf\x1e\xe9'
                'stuff'
                (
                    'accounts'
                    'name'
                )
                (
                    'max_workers'
                )
                0
                'st_task'
                'st_stream'   # b'\x81\xf1\x0c, \xee\xac\xd7\x1a\xf7'
                'st_wait'
                'st_done'
                '__pyarmor_exit_13415__'
                'Done'
            [Disassembly]
                0       NOP                             
                2       NOP                             
                4       PUSH_NULL                       
                6       LOAD_CONST                      2: '__pyarmor_enter_13414__'
                8       LOAD_CONST                      3: b'<COAddr>\x07\x00\x00\x1a\x9a\x06\x00\x00\x00\x00\x00\x00\x00\x00\x00\x00\x00\x00\x00\x00'
                10      BUILD_TUPLE                     1
                12      CALL_FUNCTION_EX                0
                14      POP_TOP                         
                16      RESUME                          0
                18      NOP                             
                20      NOP                             
                22      NOP                             
                24      NOP                             
                26      NOP                             
                28      NOP                             
                30      LOAD_FAST                       4: stop_thread
                32      LOAD_ATTR                       1: is_set
                52      CALL                            0
                60      POP_JUMP_IF_FALSE               10 (to 82)
                62      LOAD_GLOBAL                     3: NULL + StopProgram
                72      CALL                            0
                80      RAISE_VARARGS                   1
                82      LOAD_FAST                       0: data
                84      LOAD_CONST                      4: 'Accounts'
                86      BINARY_SUBSCR                   
                90      STORE_FAST                      6: _var_var_4
                92      LOAD_GLOBAL                     5: NULL + isinstance
                102     LOAD_FAST                       6: _var_var_4
                104     LOAD_GLOBAL                     6: list
                114     CALL                            2
                122     POP_JUMP_IF_TRUE                3 (to 130)
                124     LOAD_FAST                       6: _var_var_4
                126     BUILD_LIST                      1
                128     STORE_FAST                      6: _var_var_4
                130     LOAD_GLOBAL                     9: NULL + int
                140     LOAD_GLOBAL                     11: NULL + len
                150     LOAD_FAST                       6: _var_var_4
                152     CALL                            1
                160     CALL                            1
                168     LOAD_CONST                      5: 1
                170     COMPARE_OP                      2 (<)
                174     POP_JUMP_IF_FALSE               44 (to 264)
                176     LOAD_GLOBAL                     13: NULL + eel
                186     LOAD_ATTR                       14: sendErrorBox
                206     LOAD_GLOBAL                     16: Lang
                216     PUSH_NULL                       
                218     LOAD_CONST                      1: '__pyarmor_assert_13413__'
                220     LOAD_CONST                      6: 'select_accounts_works'   # b'\x81\xf1\x1d\x1f6\xf9\xaa\xed\x1a\xf9\x0e\xcfy\xe2\xec\x960J\xb4\xb5\xa1\xd8'
                222     CALL                            1
                230     BINARY_SUBSCR                   
                234     CALL                            1
                242     POP_TOP                         
                244     LOAD_GLOBAL                     3: NULL + StopProgram
                254     CALL                            0
                262     RAISE_VARARGS                   1
                264     LOAD_FAST                       0: data
                266     LOAD_CONST                      7: 'Settings'
                268     BINARY_SUBSCR                   
                272     LOAD_ATTR                       19: get
                292     PUSH_NULL                       
                294     LOAD_CONST                      1: '__pyarmor_assert_13413__'
                296     LOAD_CONST                      8: 'thread_rules'   # b'\x81\xf6\x10\x016\xfb\xba\xed\t\xef\x01\xc5\x7f'
                298     CALL                            1
                306     CALL                            1
                314     LOAD_CONST                      9: True
                316     COMPARE_OP                      40 (==)
                320     POP_JUMP_IF_FALSE               36 (to 394)
                322     LOAD_GLOBAL                     9: NULL + int
                332     LOAD_FAST                       0: data
                334     LOAD_CONST                      7: 'Settings'
                336     BINARY_SUBSCR                   
                340     LOAD_ATTR                       19: get
                360     PUSH_NULL                       
                362     LOAD_CONST                      1: '__pyarmor_assert_13413__'
                364     LOAD_CONST                      10: 'thread_count'   # b'\x81\xf6\x10\x016\xfb\xba\xed\x18\xf5\x18\xcex'
                366     CALL                            1
                374     CALL                            1
                382     CALL                            1
                390     STORE_FAST                      7: _var_var_5
                392     JUMP_FORWARD                    11 (to 416)
                394     LOAD_FAST                       1: config
                396     PUSH_NULL                       
                398     LOAD_CONST                      1: '__pyarmor_assert_13413__'
                400     LOAD_CONST                      10: 'thread_count'   # b'\x81\xf6\x10\x016\xfb\xba\xed\x18\xf5\x18\xcex'
                402     CALL                            1
                410     BINARY_SUBSCR                   
                414     STORE_FAST                      7: _var_var_5
                416     LOAD_GLOBAL                     20: datetime
                426     LOAD_ATTR                       20: datetime
                446     LOAD_ATTR                       23: now
                466     CALL                            0
                474     LOAD_ATTR                       25: strftime
                494     PUSH_NULL                       
                496     LOAD_CONST                      1: '__pyarmor_assert_13413__'
                498     LOAD_CONST                      11: '%Y-%m-%d_%H-%M-%S'   # b'\x81\xa7!^v\xf7\xf3\x97\x1f\xc5H\xe8!\xa9\xd5\xc8Jn'
                500     CALL                            1
                508     CALL                            1
                516     STORE_FAST                      8: _var_var_6
                518     LOAD_GLOBAL                     27: NULL + db_create_bots
                528     PUSH_NULL                       
                530     LOAD_CONST                      1: '__pyarmor_assert_13413__'
                532     LOAD_CONST                      12: 'additives/create_bots/'   # b'\x81\xe3\x1c\x17:\xee\xb7\xc4\x1e\xe9B\xc3~\xe9\xf9\x91\nb\xb9\xa8\xbe\xd8\x01'
                534     CALL                            1
                542     LOAD_FAST                       8: _var_var_6
                544     FORMAT_VALUE                    0 (FVC_NONE)
                546     PUSH_NULL                       
                548     LOAD_CONST                      1: '__pyarmor_assert_13413__'
                550     LOAD_CONST                      13: '_result.db'   # b'\x81\xdd\n\x16 \xef\xb2\xc6U\xfe\x0f'
                552     CALL                            1
                560     BUILD_STRING                    3
                562     CALL                            1
                570     LOAD_ATTR                       29: create
                590     CALL                            0
                598     STORE_FAST                      9: _var_var_7
                600     LOAD_GLOBAL                     13: NULL + eel
                610     LOAD_ATTR                       30: WriteResult
                630     LOAD_CONST                      14: 'Bots'
                632     PUSH_NULL                       
                634     LOAD_CONST                      1: '__pyarmor_assert_13413__'
                636     LOAD_CONST                      15: 'create_bots'   # b'\x81\xe1\n\x162\xee\xbb\xed\x19\xf5\x19\xd3'
                638     CALL                            1
                646     LOAD_FAST                       8: _var_var_6
                648     FORMAT_VALUE                    0 (FVC_NONE)
                650     PUSH_NULL                       
                652     LOAD_CONST                      1: '__pyarmor_assert_13413__'
                654     LOAD_CONST                      13: '_result.db'   # b'\x81\xdd\n\x16 \xef\xb2\xc6U\xfe\x0f'
                656     CALL                            1
                664     BUILD_STRING                    2
                666     CALL                            3
                674     POP_TOP                         
                676     LOAD_FAST                       0: data
                678     LOAD_CONST                      7: 'Settings'
                680     BINARY_SUBSCR                   
                684     LOAD_ATTR                       19: get
                704     LOAD_CONST                      16: 'names'
                706     CALL                            1
                714     STORE_FAST                      10: _var_var_8
                716     LOAD_FAST                       0: data
                718     LOAD_CONST                      7: 'Settings'
                720     BINARY_SUBSCR                   
                724     LOAD_ATTR                       19: get
                744     PUSH_NULL                       
                746     LOAD_CONST                      1: '__pyarmor_assert_13413__'
                748     LOAD_CONST                      17: 'usernames'   # b'\x81\xf7\x0b\x16!\xf4\xbf\xdf\x1e\xe9'
                750     CALL                            1
                758     CALL                            1
                766     STORE_FAST                      11: _var_var_9
                768     LOAD_GLOBAL                     5: NULL + isinstance
                778     LOAD_FAST                       10: _var_var_8
                780     LOAD_GLOBAL                     6: list
                790     CALL                            2
                798     POP_JUMP_IF_TRUE                3 (to 806)
                800     LOAD_FAST                       10: _var_var_8
                802     BUILD_LIST                      1
                804     STORE_FAST                      10: _var_var_8
                806     LOAD_GLOBAL                     5: NULL + isinstance
                816     LOAD_FAST                       11: _var_var_9
                818     LOAD_GLOBAL                     6: list
                828     CALL                            2
                836     POP_JUMP_IF_TRUE                3 (to 844)
                838     LOAD_FAST                       11: _var_var_9
                840     BUILD_LIST                      1
                842     STORE_FAST                      11: _var_var_9
                844     LOAD_GLOBAL                     33: NULL + username_generator
                854     LOAD_FAST                       10: _var_var_8
                856     CALL                            1
                864     STORE_FAST                      10: _var_var_8
                866     LOAD_GLOBAL                     33: NULL + username_generator
                876     LOAD_FAST                       11: _var_var_9
                878     CALL                            1
                886     STORE_FAST                      11: _var_var_9
                888     LOAD_GLOBAL                     35: NULL + set_task_manager
                898     LOAD_FAST                       2: pid
                900     LOAD_FAST                       6: _var_var_4
                902     LOAD_FAST                       0: data
                904     LOAD_CONST                      18: 'stuff'
                906     BINARY_SUBSCR                   
                910     KW_NAMES                        19: ('accounts', 'name')
                912     CALL                            3
                920     POP_TOP                         
                922     LOAD_GLOBAL                     36: concurrent
                932     LOAD_ATTR                       38: futures
                952     LOAD_ATTR                       41: ThreadPoolExecutor
                972     LOAD_FAST                       7: _var_var_5
                974     KW_NAMES                        20: ('max_workers',)
                976     CALL                            1
                984     BEFORE_WITH                     
                986     STORE_FAST                      12: _var_var_10
                988     BUILD_LIST                      0
                990     STORE_FAST                      13: _var_var_11
                992     LOAD_GLOBAL                     11: NULL + len
                1002    LOAD_FAST                       6: _var_var_4
                1004    CALL                            1
                1012    STORE_FAST                      14: _var_var_12
                1014    LOAD_FAST                       7: _var_var_5
                1016    STORE_FAST                      15: _var_var_13
                1018    LOAD_FAST                       14: _var_var_12
                1020    STORE_FAST                      16: _var_var_14
                1022    LOAD_CONST                      21: 0
                1024    STORE_FAST                      17: _var_var_15
                1026    LOAD_GLOBAL                     13: NULL + eel
                1036    LOAD_ATTR                       42: StreamStat
                1056    LOAD_GLOBAL                     45: NULL + json
                1066    LOAD_ATTR                       46: dumps
                1086    LOAD_CONST                      22: 'st_task'
                1088    LOAD_FAST                       14: _var_var_12
                1090    PUSH_NULL                       
                1092    LOAD_CONST                      1: '__pyarmor_assert_13413__'
                1094    LOAD_CONST                      23: 'st_stream'   # b'\x81\xf1\x0c, \xee\xac\xd7\x1a\xf7'
                1096    CALL                            1
                1104    LOAD_FAST                       15: _var_var_13
                1106    LOAD_CONST                      24: 'st_wait'
                1108    LOAD_FAST                       16: _var_var_14
                1110    LOAD_CONST                      25: 'st_done'
                1112    LOAD_FAST                       17: _var_var_15
                1114    BUILD_MAP                       4
                1116    CALL                            1
                1124    CALL                            1
                1132    POP_TOP                         
                1134    LOAD_FAST                       6: _var_var_4
                1136    GET_ITER                        
                1138    FOR_ITER                        46 (to 1232)
                1142    STORE_FAST                      18: _var_var_16
                1144    LOAD_FAST                       13: _var_var_11
                1146    LOAD_ATTR                       49: append
                1166    LOAD_FAST                       12: _var_var_10
                1168    LOAD_ATTR                       51: submit
                1188    LOAD_GLOBAL                     52: worker
                1198    LOAD_FAST                       18: _var_var_16
                1200    LOAD_FAST                       1: config
                1202    LOAD_FAST                       3: proxy
                1204    LOAD_FAST                       0: data
                1206    LOAD_FAST                       9: _var_var_7
                1208    LOAD_FAST                       10: _var_var_8
                1210    LOAD_FAST                       11: _var_var_9
                1212    LOAD_FAST                       4: stop_thread
                1214    CALL                            9
                1222    CALL                            1
                1230    POP_TOP                         
                1232    JUMP_BACKWARD                   48 (to 1138)
                1234    END_FOR                         
                1236    LOAD_GLOBAL                     36: concurrent
                1246    LOAD_ATTR                       38: futures
                1266    LOAD_ATTR                       55: as_completed
                1286    LOAD_FAST                       13: _var_var_11
                1288    CALL                            1
                1296    GET_ITER                        
                1298    FOR_ITER                        66 (to 1432)
                1302    STORE_FAST                      19: _var_var_17
                1304    LOAD_FAST                       17: _var_var_15
                1306    LOAD_CONST                      5: 1
                1308    BINARY_OP                       13 (+=)
                1312    STORE_FAST                      17: _var_var_15
                1314    LOAD_FAST                       16: _var_var_14
                1316    LOAD_CONST                      5: 1
                1318    BINARY_OP                       23 (-=)
                1322    STORE_FAST                      16: _var_var_14
                1324    LOAD_GLOBAL                     13: NULL + eel
                1334    LOAD_ATTR                       42: StreamStat
                1354    LOAD_GLOBAL                     45: NULL + json
                1364    LOAD_ATTR                       46: dumps
                1384    LOAD_CONST                      22: 'st_task'
                1386    LOAD_FAST                       14: _var_var_12
                1388    PUSH_NULL                       
                1390    LOAD_CONST                      1: '__pyarmor_assert_13413__'
                1392    LOAD_CONST                      23: 'st_stream'   # b'\x81\xf1\x0c, \xee\xac\xd7\x1a\xf7'
                1394    CALL                            1
                1402    LOAD_FAST                       15: _var_var_13
                1404    LOAD_CONST                      24: 'st_wait'
                1406    LOAD_FAST                       16: _var_var_14
                1408    LOAD_CONST                      25: 'st_done'
                1410    LOAD_FAST                       17: _var_var_15
                1412    BUILD_MAP                       4
                1414    CALL                            1
                1422    CALL                            1
                1430    POP_TOP                         
                1432    JUMP_BACKWARD                   68 (to 1298)
                1434    END_FOR                         
                1436    NOP                             
                1438    LOAD_CONST                      0: None
                1440    LOAD_CONST                      0: None
                1442    LOAD_CONST                      0: None
                1444    CALL                            2
                1452    POP_TOP                         
                1454    LOAD_GLOBAL                     61: NULL + del_task_manager
                1464    LOAD_FAST                       2: pid
                1466    CALL                            1
                1474    POP_TOP                         
                1476    LOAD_GLOBAL                     63: NULL + StopDetect
                1486    LOAD_FAST                       4: stop_thread
                1488    CALL                            1
                1496    POP_TOP                         
                1498    NOP                             
                1500    LOAD_CONST                      27: 'Done'
                1502    NOP                             
                1504    NOP                             
                1506    NOP                             
                1508    JUMP_FORWARD                    117 (to 1744)
                1516    POP_TOP                         
                1518    RETURN_CONST                    27: 'Done'
                1520    PUSH_EXC_INFO                   
                1522    WITH_EXCEPT_START               
                1524    POP_JUMP_IF_TRUE                1 (to 1528)
                1526    RERAISE                         2
                1528    POP_TOP                         
                1530    POP_EXCEPT                      
                1532    POP_TOP                         
                1534    POP_TOP                         
                1536    JUMP_BACKWARD                   42 (to 1454)
                1538    COPY                            3
                1540    POP_EXCEPT                      
                1542    RERAISE                         1
                1544    PUSH_EXC_INFO                   
                1546    LOAD_GLOBAL                     2: StopProgram
                1556    CHECK_EXC_MATCH                 
                1558    POP_JUMP_IF_FALSE               3 (to 1566)
                1560    POP_TOP                         
                1562    POP_EXCEPT                      
                1564    JUMP_BACKWARD                   56 (to 1454)
                1566    LOAD_GLOBAL                     56: BaseException
                1576    CHECK_EXC_MATCH                 
                1578    POP_JUMP_IF_FALSE               26 (to 1632)
                1580    STORE_FAST                      20: _var_var_3
                1582    PUSH_NULL                       
                1584    LOAD_GLOBAL                     59: NULL + logging
                1594    LOAD_FAST                       20: _var_var_3
                1596    CALL                            1
                1604    CALL                            0
                1612    POP_TOP                         
                1614    POP_EXCEPT                      
                1616    LOAD_CONST                      0: None
                1618    STORE_FAST                      20: _var_var_3
                1620    DELETE_FAST                     20: _var_var_3
                1622    JUMP_BACKWARD                   85 (to 1454)
                1624    LOAD_CONST                      0: None
                1626    STORE_FAST                      20: _var_var_3
                1628    DELETE_FAST                     20: _var_var_3
                1630    RERAISE                         1
                1632    RERAISE                         0
                1634    COPY                            3
                1636    POP_EXCEPT                      
                1638    RERAISE                         1
                1640    PUSH_EXC_INFO                   
                1642    LOAD_GLOBAL                     61: NULL + del_task_manager
                1652    LOAD_FAST                       2: pid
                1654    CALL                            1
                1662    POP_TOP                         
                1664    LOAD_GLOBAL                     63: NULL + StopDetect
                1674    LOAD_FAST                       4: stop_thread
                1676    CALL                            1
                1684    POP_TOP                         
                1686    POP_TOP                         
                1688    POP_EXCEPT                      
                1690    LOAD_CONST                      27: 'Done'
                1692    NOP                             
                1694    NOP                             
                1696    NOP                             
                1698    JUMP_FORWARD                    22 (to 1744)
                1706    POP_TOP                         
                1708    RETURN_CONST                    27: 'Done'
                1710    COPY                            3
                1712    POP_EXCEPT                      
                1714    RERAISE                         1
                1716    PUSH_EXC_INFO                   
                1718    PUSH_NULL                       
                1720    LOAD_CONST                      26: '__pyarmor_exit_13415__'
                1722    NOP                             
                1724    LOAD_CONST                      3: b'<COAddr>\x07\x00\x00\x1a\x9a\x06\x00\x00\x00\x00\x00\x00\x00\x00\x00\x00\x00\x00\x00\x00'
                1726    CALL                            1
                1734    POP_TOP                         
                1736    RERAISE                         0
                1738    COPY                            3
                1740    POP_EXCEPT                      
                1742    RERAISE                         1
                1744    PUSH_NULL                       
                1746    LOAD_CONST                      26: '__pyarmor_exit_13415__'
                1748    LOAD_CONST                      3: b'<COAddr>\x07\x00\x00\x1a\x9a\x06\x00\x00\x00\x00\x00\x00\x00\x00\x00\x00\x00\x00\x00\x00'
                1750    BUILD_TUPLE                     1
                1752    CALL_FUNCTION_EX                0
                1754    POP_TOP                         
                1756    RETURN_VALUE                    
            [Exception Table]
                30 to 986 -> 1544 [0] 
                986 to 1436 -> 1520 [1] lasti
                1438 to 1454 -> 1544 [0] 
                1454 to 1498 -> 1716 [0] 
                1520 to 1530 -> 1538 [3] lasti
                1530 to 1544 -> 1544 [0] 
                1544 to 1562 -> 1634 [1] lasti
                1562 to 1566 -> 1640 [0] 
                1566 to 1582 -> 1634 [1] lasti
                1582 to 1614 -> 1624 [1] lasti
                1614 to 1624 -> 1640 [0] 
                1624 to 1634 -> 1634 [1] lasti
                1634 to 1640 -> 1640 [0] 
                1640 to 1688 -> 1710 [1] lasti
                1688 to 1690 -> 1716 [0] 
                1710 to 1716 -> 1716 [0] 
                1716 to 1738 -> 1738 [1] lasti
        [Code]
            File Name: <frozen program.modules.Create_bots>
            Object Name: worker
            Qualified Name: worker
            Arg Count: 8
            Pos Only Arg Count: 0
            KW Only Arg Count: 0
            Stack Size: 11
            Flags: 0x20000003 (CO_OPTIMIZED | CO_NEWLOCALS | CO_PYARMOR_OBFUSCATED)
            [Names]
                'Thread_wait'
                'account_works'
                'Lang'
                'Disconnect'
                'Logs'
                'PrintLog'
                'int'
                'get'
                'random'
                'randint'
                'isinstance'
                'list'
                'get_entity'
                'send_message'
                'errors'
                'YouBlockedUserError'
                'functions'
                'contacts'
                'UnblockRequest'
                'get_message'
                'Lock'
                'next'
                'spintax'
                'spin'
                'lower'
                'endswith'
                're'
                'search'
                'str'
                'raw_text'
                'group'
                'ValueError'
                'modify_username'
                'time'
                'sleep'
                'uniform'
                'choice'
                'button_click'
                'upload_file'
                'send_file'
                'Exception'
                'db_create_bots'
                'insert'
                'DelayOnline'
                'StopProgram'
                'BaseException'
                'logging'
            [Locals+Names]
                'account'
                'config'
                'proxy'
                'data'
                'base'
                'names'
                'usernames'
                'stop_thread'
                '__assert_armored__'
                '_var_var_18'
                '_var_var_19'
                '_var_var_20'
                '_var_var_21'
                '_var_var_22'
                '_var_var_23'
                '_var_var_24'
                '_var_var_25'
                '_var_var_26'
                '_var_var_27'
                '_var_var_28'
                '_var_var_29'
                '_var_var_30'
                '_var_var_31'
                '_var_var_32'
                '_var_var_33'
                '_var_var_34'
                '_var_var_35'
                '_var_var_36'
                '_var_var_37'
                '_var_var_38'
                '_var_var_39'
                '_var_var_40'
                '_var_var_3'
            [Constants]
                None
                '__pyarmor_assert_13416__'
                '__pyarmor_enter_13417__'
                b'<COAddr>\x07\x00\x00\x1a\xec\x11\x00\x00\x00\x00\x00\x00\x00\x00\x00\x00\x00\x00\x00\x00'
                'Subscribe_bot'   # b'\x81\xd1\r\x11 \xf9\xac\xdb\x19\xff2\xc2c\xf8'
                (
                    'module'
                )
                False
                'false'
                (
                    'account'
                    'status'
                )
                'work_account_completed'   # b'\x81\xf5\x17\x018\xc5\xbf\xd1\x18\xf5\x18\xcex\xd3\xfb\x8a\x02M\xb7\xa2\xbe\xceJ'
                (
                    'config'
                    'account'
                    'message'
                )
                'done'
                '__pyarmor_exit_13418__'
                'Settings'
                'wait_form'   # b"\x81\xf5\x19\x1a'\xc5\xb8\xdd\t\xf7"
                'wait_to'
                'set_photo'   # b'\x81\xf1\x1d\x07\x0c\xea\xb6\xdd\x0f\xf5'
                'set_photo_list'   # b'\x81\xf1\x1d\x07\x0c\xea\xb6\xdd\x0f\xf52\xcce\xff\xec'
                'set_bio'
                'bio'
                'set_description'   # b'\x81\xf1\x1d\x07\x0c\xfe\xbb\xc1\x18\xe8\x04\xd0x\xe5\xf7\x8b'
                'description'   # b'\x81\xe6\x1d\x000\xe8\xb7\xc2\x0f\xf3\x02\xce'
                'set_restrict_groups'   # b'\x81\xf1\x1d\x07\x0c\xe8\xbb\xc1\x0f\xe8\x04\xc3x\xd3\xff\x97\x00H\xab\xb4'
                'kol_min'
                'kol_max'
                'botfather'   # b'\x81\xe0\x17\x075\xfb\xaa\xda\x1e\xe8'
                'Done'
                'create_bot'   # b'\x81\xe1\n\x162\xee\xbb\xed\x19\xf5\x19'
                '/newbot'
                'spambot'
                'create_bot_done'   # b'\x81\xe1\n\x162\xee\xbb\xed\x19\xf5\x19\xffh\xe3\xf6\x80'
                'create_bot_set_name'   # b'\x81\xe1\n\x162\xee\xbb\xed\x19\xf5\x19\xff\x7f\xe9\xec\xba\x01\\\xb6\xa2'
                'create_bot_set_username'   # b'\x81\xe1\n\x162\xee\xbb\xed\x19\xf5\x19\xff\x7f\xe9\xec\xba\x1aN\xbe\xb5\xa4\xcaC\xc9'
                'bot'
                '_bot'
                0
                '\\d{10}:[A-Za-z0-9_-]{35}'   # b'\x81\xde\x1c\x08b\xaa\xa3\x88 \xdb@\xfam\xa1\xe2\xd5B\x04\x84\xea\x97\xd0\x1d\x99\x18'
                1
                3
                'Flood'
                5
                'create_bot_set_username_done'   # b'\x81\xe1\n\x162\xee\xbb\xed\x19\xf5\x19\xff\x7f\xe9\xec\xba\x1aN\xbe\xb5\xa4\xcaC\xc9:k\xacR\x05'
                (
                    'config'
                    'account'
                    'message'
                    'end'
                )
                'create_bot_set_photo'   # b'\x81\xe1\n\x162\xee\xbb\xed\x19\xf5\x19\xff\x7f\xe9\xec\xba\x1fU\xb4\xb3\xa5'
                '/setuserpic'   # b"\x81\xad\x0b\x16'\xef\xad\xd7\t\xea\x04\xc3"
                'create_bot_set_bio'   # b'\x81\xe1\n\x162\xee\xbb\xed\x19\xf5\x19\xff\x7f\xe9\xec\xba\rT\xb4'
                '/setabouttext'   # b"\x81\xad\x0b\x16'\xfb\xbc\xdd\x0e\xee\x19\xc5t\xf8"
                120
                'create_bot_set_desc'   # b'\x81\xe1\n\x162\xee\xbb\xed\x19\xf5\x19\xff\x7f\xe9\xec\xba\x0bX\xa8\xa4'
                '/setdescription'   # b"\x81\xad\x0b\x16'\xfe\xbb\xc1\x18\xe8\x04\xd0x\xe5\xf7\x8b"
                'create_bot_set_privacy'   # b'\x81\xe1\n\x162\xee\xbb\xed\x19\xf5\x19\xff\x7f\xe9\xec\xba\x1fO\xb2\xb1\xab\xc8W'
                '/setprivacy'   # b"\x81\xad\x0b\x16'\xea\xac\xdb\r\xfb\x0e\xd9"
                'Error'
                (
                    'account'
                    'token'
                    'username'
                    'name'
                    'bio'
                    'photo'
                    'description'
                    'restrict_groups'
                    'status'
                )
            [Disassembly]
                0       NOP                             
                2       NOP                             
                4       PUSH_NULL                       
                6       LOAD_CONST                      2: '__pyarmor_enter_13417__'
                8       LOAD_CONST                      3: b'<COAddr>\x07\x00\x00\x1a\xec\x11\x00\x00\x00\x00\x00\x00\x00\x00\x00\x00\x00\x00\x00\x00'
                10      BUILD_TUPLE                     1
                12      CALL_FUNCTION_EX                0
                14      POP_TOP                         
                16      RESUME                          0
                18      NOP                             
                20      NOP                             
                22      NOP                             
                24      NOP                             
                26      NOP                             
                28      NOP                             
                30      LOAD_GLOBAL                     1: NULL + Thread_wait
                40      LOAD_FAST                       3: data
                42      LOAD_FAST                       1: config
                44      LOAD_FAST                       7: stop_thread
                46      CALL                            3
                54      POP_TOP                         
                56      LOAD_GLOBAL                     3: NULL + account_works
                66      LOAD_FAST                       1: config
                68      LOAD_GLOBAL                     4: Lang
                78      LOAD_FAST                       2: proxy
                80      LOAD_FAST                       0: account
                82      LOAD_FAST                       7: stop_thread
                84      PUSH_NULL                       
                86      LOAD_CONST                      1: '__pyarmor_assert_13416__'
                88      LOAD_CONST                      4: 'Subscribe_bot'   # b'\x81\xd1\r\x11 \xf9\xac\xdb\x19\xff2\xc2c\xf8'
                90      CALL                            1
                98      KW_NAMES                        5: ('module',)
                100     CALL                            6
                108     STORE_FAST                      9: _var_var_18
                110     LOAD_FAST                       9: _var_var_18
                112     LOAD_CONST                      6: False
                114     COMPARE_OP                      40 (==)
                118     POP_JUMP_IF_FALSE               68 (to 256)
                120     LOAD_FAST                       0: account
                122     LOAD_CONST                      7: 'false'
                124     LOAD_CONST                      8: ('account', 'status')
                126     BUILD_CONST_KEY_MAP             2
                128     LOAD_GLOBAL                     7: NULL + Disconnect
                138     LOAD_FAST                       9: _var_var_18
                140     CALL                            1
                148     POP_TOP                         
                150     LOAD_GLOBAL                     9: NULL + Logs
                160     LOAD_ATTR                       10: PrintLog
                180     LOAD_FAST                       1: config
                182     LOAD_FAST                       0: account
                184     LOAD_GLOBAL                     4: Lang
                194     PUSH_NULL                       
                196     LOAD_CONST                      1: '__pyarmor_assert_13416__'
                198     LOAD_CONST                      9: 'work_account_completed'   # b'\x81\xf5\x17\x018\xc5\xbf\xd1\x18\xf5\x18\xcex\xd3\xfb\x8a\x02M\xb7\xa2\xbe\xceJ'
                200     CALL                            1
                208     BINARY_SUBSCR                   
                212     KW_NAMES                        10: ('config', 'account', 'message')
                214     CALL                            3
                222     POP_TOP                         
                224     LOAD_FAST                       0: account
                226     LOAD_CONST                      11: 'done'
                228     LOAD_CONST                      8: ('account', 'status')
                230     BUILD_CONST_KEY_MAP             2
                232     SWAP                            2
                234     POP_TOP                         
                236     NOP                             
                238     NOP                             
                240     JUMP_FORWARD                    2199 (to 4642)
                244     CALL                            1
                252     POP_TOP                         
                254     RETURN_VALUE                    
                256     LOAD_GLOBAL                     13: NULL + int
                266     LOAD_FAST                       3: data
                268     LOAD_CONST                      13: 'Settings'
                270     BINARY_SUBSCR                   
                274     LOAD_ATTR                       15: get
                294     PUSH_NULL                       
                296     LOAD_CONST                      1: '__pyarmor_assert_13416__'
                298     LOAD_CONST                      14: 'wait_form'   # b"\x81\xf5\x19\x1a'\xc5\xb8\xdd\t\xf7"
                300     CALL                            1
                308     CALL                            1
                316     CALL                            1
                324     STORE_FAST                      10: _var_var_19
                326     LOAD_GLOBAL                     13: NULL + int
                336     LOAD_FAST                       3: data
                338     LOAD_CONST                      13: 'Settings'
                340     BINARY_SUBSCR                   
                344     LOAD_ATTR                       15: get
                364     LOAD_CONST                      15: 'wait_to'
                366     CALL                            1
                374     CALL                            1
                382     STORE_FAST                      11: _var_var_20
                384     LOAD_FAST                       3: data
                386     LOAD_CONST                      13: 'Settings'
                388     BINARY_SUBSCR                   
                392     LOAD_ATTR                       15: get
                412     PUSH_NULL                       
                414     LOAD_CONST                      1: '__pyarmor_assert_13416__'
                416     LOAD_CONST                      16: 'set_photo'   # b'\x81\xf1\x1d\x07\x0c\xea\xb6\xdd\x0f\xf5'
                418     CALL                            1
                426     CALL                            1
                434     STORE_FAST                      12: _var_var_21
                436     LOAD_FAST                       3: data
                438     LOAD_CONST                      13: 'Settings'
                440     BINARY_SUBSCR                   
                444     LOAD_ATTR                       15: get
                464     PUSH_NULL                       
                466     LOAD_CONST                      1: '__pyarmor_assert_13416__'
                468     LOAD_CONST                      17: 'set_photo_list'   # b'\x81\xf1\x1d\x07\x0c\xea\xb6\xdd\x0f\xf52\xcce\xff\xec'
                470     CALL                            1
                478     CALL                            1
                486     STORE_FAST                      13: _var_var_22
                488     LOAD_FAST                       3: data
                490     LOAD_CONST                      13: 'Settings'
                492     BINARY_SUBSCR                   
                496     LOAD_ATTR                       15: get
                516     LOAD_CONST                      18: 'set_bio'
                518     CALL                            1
                526     STORE_FAST                      14: _var_var_23
                528     LOAD_FAST                       3: data
                530     LOAD_CONST                      13: 'Settings'
                532     BINARY_SUBSCR                   
                536     LOAD_ATTR                       15: get
                556     LOAD_CONST                      19: 'bio'
                558     CALL                            1
                566     STORE_FAST                      15: _var_var_24
                568     LOAD_FAST                       3: data
                570     LOAD_CONST                      13: 'Settings'
                572     BINARY_SUBSCR                   
                576     LOAD_ATTR                       15: get
                596     PUSH_NULL                       
                598     LOAD_CONST                      1: '__pyarmor_assert_13416__'
                600     LOAD_CONST                      20: 'set_description'   # b'\x81\xf1\x1d\x07\x0c\xfe\xbb\xc1\x18\xe8\x04\xd0x\xe5\xf7\x8b'
                602     CALL                            1
                610     CALL                            1
                618     STORE_FAST                      16: _var_var_25
                620     LOAD_FAST                       3: data
                622     LOAD_CONST                      13: 'Settings'
                624     BINARY_SUBSCR                   
                628     LOAD_ATTR                       15: get
                648     PUSH_NULL                       
                650     LOAD_CONST                      1: '__pyarmor_assert_13416__'
                652     LOAD_CONST                      21: 'description'   # b'\x81\xe6\x1d\x000\xe8\xb7\xc2\x0f\xf3\x02\xce'
                654     CALL                            1
                662     CALL                            1
                670     STORE_FAST                      17: _var_var_26
                672     LOAD_FAST                       3: data
                674     LOAD_CONST                      13: 'Settings'
                676     BINARY_SUBSCR                   
                680     LOAD_ATTR                       15: get
                700     PUSH_NULL                       
                702     LOAD_CONST                      1: '__pyarmor_assert_13416__'
                704     LOAD_CONST                      22: 'set_restrict_groups'   # b'\x81\xf1\x1d\x07\x0c\xe8\xbb\xc1\x0f\xe8\x04\xc3x\xd3\xff\x97\x00H\xab\xb4'
                706     CALL                            1
                714     CALL                            1
                722     STORE_FAST                      18: _var_var_27
                724     LOAD_GLOBAL                     17: NULL + random
                734     LOAD_ATTR                       18: randint
                754     LOAD_GLOBAL                     13: NULL + int
                764     LOAD_FAST                       3: data
                766     LOAD_CONST                      13: 'Settings'
                768     BINARY_SUBSCR                   
                772     LOAD_ATTR                       15: get
                792     LOAD_CONST                      23: 'kol_min'
                794     CALL                            1
                802     CALL                            1
                810     LOAD_GLOBAL                     13: NULL + int
                820     LOAD_FAST                       3: data
                822     LOAD_CONST                      13: 'Settings'
                824     BINARY_SUBSCR                   
                828     LOAD_ATTR                       15: get
                848     LOAD_CONST                      24: 'kol_max'
                850     CALL                            1
                858     CALL                            1
                866     CALL                            2
                874     STORE_FAST                      19: _var_var_28
                876     LOAD_GLOBAL                     21: NULL + isinstance
                886     LOAD_FAST                       13: _var_var_22
                888     LOAD_GLOBAL                     22: list
                898     CALL                            2
                906     POP_JUMP_IF_TRUE                3 (to 914)
                908     LOAD_FAST                       13: _var_var_22
                910     BUILD_LIST                      1
                912     STORE_FAST                      13: _var_var_22
                914     LOAD_GLOBAL                     21: NULL + isinstance
                924     LOAD_FAST                       17: _var_var_26
                926     LOAD_GLOBAL                     22: list
                936     CALL                            2
                944     POP_JUMP_IF_TRUE                3 (to 952)
                946     LOAD_FAST                       17: _var_var_26
                948     BUILD_LIST                      1
                950     STORE_FAST                      17: _var_var_26
                952     LOAD_FAST                       9: _var_var_18
                954     LOAD_ATTR                       25: get_entity
                974     PUSH_NULL                       
                976     LOAD_CONST                      1: '__pyarmor_assert_13416__'
                978     LOAD_CONST                      25: 'botfather'   # b'\x81\xe0\x17\x075\xfb\xaa\xda\x1e\xe8'
                980     CALL                            1
                988     CALL                            1
                996     STORE_FAST                      20: _var_var_29
                998     NOP                             
                1000    NOP                             
                1002    LOAD_CONST                      0: None
                1004    STORE_FAST                      21: _var_var_30
                1006    LOAD_CONST                      0: None
                1008    STORE_FAST                      22: _var_var_31
                1010    LOAD_CONST                      0: None
                1012    STORE_FAST                      23: _var_var_32
                1014    LOAD_CONST                      0: None
                1016    STORE_FAST                      24: _var_var_33
                1018    LOAD_CONST                      0: None
                1020    STORE_FAST                      25: _var_var_34
                1022    LOAD_CONST                      0: None
                1024    STORE_FAST                      26: _var_var_35
                1026    LOAD_CONST                      26: 'Done'
                1028    STORE_FAST                      27: _var_var_36
                1030    LOAD_GLOBAL                     9: NULL + Logs
                1040    LOAD_ATTR                       10: PrintLog
                1060    LOAD_FAST                       1: config
                1062    LOAD_FAST                       0: account
                1064    LOAD_GLOBAL                     4: Lang
                1074    PUSH_NULL                       
                1076    LOAD_CONST                      1: '__pyarmor_assert_13416__'
                1078    LOAD_CONST                      27: 'create_bot'   # b'\x81\xe1\n\x162\xee\xbb\xed\x19\xf5\x19'
                1080    CALL                            1
                1088    BINARY_SUBSCR                   
                1092    KW_NAMES                        10: ('config', 'account', 'message')
                1094    CALL                            3
                1102    POP_TOP                         
                1104    NOP                             
                1106    LOAD_FAST                       9: _var_var_18
                1108    LOAD_ATTR                       27: send_message
                1128    LOAD_FAST                       20: _var_var_29
                1130    LOAD_CONST                      28: '/newbot'
                1132    CALL                            2
                1140    POP_TOP                         
                1142    LOAD_GLOBAL                     9: NULL + Logs
                1152    LOAD_ATTR                       10: PrintLog
                1172    LOAD_FAST                       1: config
                1174    LOAD_FAST                       0: account
                1176    LOAD_GLOBAL                     4: Lang
                1186    PUSH_NULL                       
                1188    LOAD_CONST                      1: '__pyarmor_assert_13416__'
                1190    LOAD_CONST                      30: 'create_bot_done'   # b'\x81\xe1\n\x162\xee\xbb\xed\x19\xf5\x19\xffh\xe3\xf6\x80'
                1192    CALL                            1
                1200    BINARY_SUBSCR                   
                1204    KW_NAMES                        10: ('config', 'account', 'message')
                1206    CALL                            3
                1214    POP_TOP                         
                1216    LOAD_GLOBAL                     39: NULL + get_message
                1226    LOAD_FAST                       9: _var_var_18
                1228    LOAD_FAST                       20: _var_var_29
                1230    CALL                            2
                1238    POP_TOP                         
                1240    LOAD_GLOBAL                     9: NULL + Logs
                1250    LOAD_ATTR                       10: PrintLog
                1270    LOAD_FAST                       1: config
                1272    LOAD_FAST                       0: account
                1274    LOAD_GLOBAL                     4: Lang
                1284    PUSH_NULL                       
                1286    LOAD_CONST                      1: '__pyarmor_assert_13416__'
                1288    LOAD_CONST                      31: 'create_bot_set_name'   # b'\x81\xe1\n\x162\xee\xbb\xed\x19\xf5\x19\xff\x7f\xe9\xec\xba\x01\\\xb6\xa2'
                1290    CALL                            1
                1298    BINARY_SUBSCR                   
                1302    KW_NAMES                        10: ('config', 'account', 'message')
                1304    CALL                            3
                1312    POP_TOP                         
                1314    LOAD_GLOBAL                     41: NULL + Lock
                1324    CALL                            0
                1332    BEFORE_WITH                     
                1334    POP_TOP                         
                1336    LOAD_GLOBAL                     43: NULL + next
                1346    LOAD_FAST                       5: names
                1348    CALL                            1
                1356    STORE_FAST                      21: _var_var_30
                1358    LOAD_GLOBAL                     45: NULL + spintax
                1368    LOAD_ATTR                       46: spin
                1388    LOAD_FAST                       21: _var_var_30
                1390    CALL                            1
                1398    STORE_FAST                      21: _var_var_30
                1400    LOAD_CONST                      0: None
                1402    LOAD_CONST                      0: None
                1404    LOAD_CONST                      0: None
                1406    CALL                            2
                1414    POP_TOP                         
                1416    LOAD_FAST                       9: _var_var_18
                1418    LOAD_ATTR                       27: send_message
                1438    LOAD_FAST                       20: _var_var_29
                1440    LOAD_FAST                       21: _var_var_30
                1442    CALL                            2
                1450    POP_TOP                         
                1452    LOAD_GLOBAL                     9: NULL + Logs
                1462    LOAD_ATTR                       10: PrintLog
                1482    LOAD_FAST                       1: config
                1484    LOAD_FAST                       0: account
                1486    LOAD_GLOBAL                     4: Lang
                1496    PUSH_NULL                       
                1498    LOAD_CONST                      1: '__pyarmor_assert_13416__'
                1500    LOAD_CONST                      30: 'create_bot_done'   # b'\x81\xe1\n\x162\xee\xbb\xed\x19\xf5\x19\xffh\xe3\xf6\x80'
                1502    CALL                            1
                1510    BINARY_SUBSCR                   
                1514    KW_NAMES                        10: ('config', 'account', 'message')
                1516    CALL                            3
                1524    POP_TOP                         
                1526    LOAD_GLOBAL                     9: NULL + Logs
                1536    LOAD_ATTR                       10: PrintLog
                1556    LOAD_FAST                       1: config
                1558    LOAD_FAST                       0: account
                1560    LOAD_GLOBAL                     4: Lang
                1570    PUSH_NULL                       
                1572    LOAD_CONST                      1: '__pyarmor_assert_13416__'
                1574    LOAD_CONST                      32: 'create_bot_set_username'   # b'\x81\xe1\n\x162\xee\xbb\xed\x19\xf5\x19\xff\x7f\xe9\xec\xba\x1aN\xbe\xb5\xa4\xcaC\xc9'
                1576    CALL                            1
                1584    BINARY_SUBSCR                   
                1588    KW_NAMES                        10: ('config', 'account', 'message')
                1590    CALL                            3
                1598    POP_TOP                         
                1600    LOAD_GLOBAL                     41: NULL + Lock
                1610    CALL                            0
                1618    BEFORE_WITH                     
                1620    POP_TOP                         
                1622    LOAD_GLOBAL                     43: NULL + next
                1632    LOAD_FAST                       6: usernames
                1634    CALL                            1
                1642    STORE_FAST                      23: _var_var_32
                1644    LOAD_CONST                      0: None
                1646    LOAD_CONST                      0: None
                1648    LOAD_CONST                      0: None
                1650    CALL                            2
                1658    POP_TOP                         
                1660    LOAD_FAST                       23: _var_var_32
                1662    LOAD_ATTR                       49: lower
                1682    CALL                            0
                1690    LOAD_ATTR                       51: endswith
                1710    LOAD_CONST                      33: 'bot'
                1712    CALL                            1
                1720    POP_JUMP_IF_TRUE                5 (to 1732)
                1722    LOAD_FAST                       23: _var_var_32
                1724    FORMAT_VALUE                    0 (FVC_NONE)
                1726    LOAD_CONST                      34: '_bot'
                1728    BUILD_STRING                    2
                1730    STORE_FAST                      23: _var_var_32
                1732    LOAD_CONST                      35: 0
                1734    STORE_FAST                      28: _var_var_37
                1736    NOP                             
                1738    LOAD_FAST                       9: _var_var_18
                1740    LOAD_ATTR                       27: send_message
                1760    LOAD_FAST                       20: _var_var_29
                1762    LOAD_FAST                       23: _var_var_32
                1764    CALL                            2
                1772    POP_TOP                         
                1774    LOAD_GLOBAL                     39: NULL + get_message
                1784    LOAD_FAST                       9: _var_var_18
                1786    LOAD_FAST                       20: _var_var_29
                1788    CALL                            2
                1796    STORE_FAST                      29: _var_var_38
                1798    LOAD_GLOBAL                     53: NULL + re
                1808    LOAD_ATTR                       54: search
                1828    PUSH_NULL                       
                1830    LOAD_CONST                      1: '__pyarmor_assert_13416__'
                1832    LOAD_CONST                      36: '\\d{10}:[A-Za-z0-9_-]{35}'   # b'\x81\xde\x1c\x08b\xaa\xa3\x88 \xdb@\xfam\xa1\xe2\xd5B\x04\x84\xea\x97\xd0\x1d\x99\x18'
                1834    CALL                            1
                1842    LOAD_GLOBAL                     57: NULL + str
                1852    LOAD_FAST                       29: _var_var_38
                1854    LOAD_ATTR                       58: raw_text
                1874    CALL                            1
                1882    CALL                            2
                1890    STORE_FAST                      30: _var_var_39
                1892    LOAD_FAST                       30: _var_var_39
                1894    POP_JUMP_IF_FALSE               17 (to 1930)
                1896    LOAD_FAST                       30: _var_var_39
                1898    LOAD_ATTR                       61: group
                1918    CALL                            0
                1926    STORE_FAST                      22: _var_var_31
                1928    JUMP_FORWARD                    74 (to 2078)
                1930    LOAD_FAST                       28: _var_var_37
                1932    LOAD_CONST                      37: 1
                1934    BINARY_OP                       13 (+=)
                1938    STORE_FAST                      28: _var_var_37
                1940    LOAD_FAST                       28: _var_var_37
                1942    LOAD_CONST                      38: 3
                1944    COMPARE_OP                      68 (>)
                1948    POP_JUMP_IF_FALSE               11 (to 1972)
                1950    LOAD_GLOBAL                     63: NULL + ValueError
                1960    LOAD_CONST                      39: 'Flood'
                1962    CALL                            1
                1970    RAISE_VARARGS                   1
                1972    LOAD_GLOBAL                     65: NULL + modify_username
                1982    LOAD_FAST                       23: _var_var_32
                1984    CALL                            1
                1992    STORE_FAST                      23: _var_var_32
                1994    LOAD_GLOBAL                     67: NULL + time
                2004    LOAD_ATTR                       68: sleep
                2024    LOAD_GLOBAL                     17: NULL + random
                2034    LOAD_ATTR                       70: uniform
                2054    LOAD_CONST                      37: 1
                2056    LOAD_CONST                      40: 5
                2058    CALL                            2
                2066    CALL                            1
                2074    POP_TOP                         
                2076    JUMP_BACKWARD                   170 (to 1738)
                2078    LOAD_GLOBAL                     9: NULL + Logs
                2088    LOAD_ATTR                       10: PrintLog
                2108    LOAD_FAST                       1: config
                2110    LOAD_FAST                       0: account
                2112    LOAD_GLOBAL                     4: Lang
                2122    PUSH_NULL                       
                2124    LOAD_CONST                      1: '__pyarmor_assert_13416__'
                2126    LOAD_CONST                      41: 'create_bot_set_username_done'   # b'\x81\xe1\n\x162\xee\xbb\xed\x19\xf5\x19\xff\x7f\xe9\xec\xba\x1aN\xbe\xb5\xa4\xcaC\xc9:k\xacR\x05'
                2128    CALL                            1
                2136    BINARY_SUBSCR                   
                2140    LOAD_FAST                       23: _var_var_32
                2142    KW_NAMES                        42: ('config', 'account', 'message', 'end')
                2144    CALL                            4
                2152    POP_TOP                         
                2154    LOAD_FAST                       12: _var_var_21
                2156    POP_JUMP_IF_FALSE               207 (to 2572)
                2158    LOAD_GLOBAL                     9: NULL + Logs
                2168    LOAD_ATTR                       10: PrintLog
                2188    LOAD_FAST                       1: config
                2190    LOAD_FAST                       0: account
                2192    LOAD_GLOBAL                     4: Lang
                2202    PUSH_NULL                       
                2204    LOAD_CONST                      1: '__pyarmor_assert_13416__'
                2206    LOAD_CONST                      43: 'create_bot_set_photo'   # b'\x81\xe1\n\x162\xee\xbb\xed\x19\xf5\x19\xff\x7f\xe9\xec\xba\x1fU\xb4\xb3\xa5'
                2208    CALL                            1
                2216    BINARY_SUBSCR                   
                2220    KW_NAMES                        10: ('config', 'account', 'message')
                2222    CALL                            3
                2230    POP_TOP                         
                2232    LOAD_GLOBAL                     17: NULL + random
                2242    LOAD_ATTR                       72: choice
                2262    LOAD_FAST                       13: _var_var_22
                2264    CALL                            1
                2272    STORE_FAST                      25: _var_var_34
                2274    LOAD_FAST                       9: _var_var_18
                2276    LOAD_ATTR                       27: send_message
                2296    LOAD_FAST                       20: _var_var_29
                2298    PUSH_NULL                       
                2300    LOAD_CONST                      1: '__pyarmor_assert_13416__'
                2302    LOAD_CONST                      44: '/setuserpic'   # b"\x81\xad\x0b\x16'\xef\xad\xd7\t\xea\x04\xc3"
                2304    CALL                            1
                2312    CALL                            2
                2320    POP_TOP                         
                2322    LOAD_GLOBAL                     75: NULL + button_click
                2332    LOAD_FAST                       9: _var_var_18
                2334    LOAD_FAST                       20: _var_var_29
                2336    CALL                            2
                2344    POP_TOP                         
                2346    LOAD_FAST                       9: _var_var_18
                2348    LOAD_ATTR                       77: upload_file
                2368    LOAD_FAST                       25: _var_var_34
                2370    CALL                            1
                2378    STORE_FAST                      31: _var_var_40
                2380    LOAD_FAST                       9: _var_var_18
                2382    LOAD_ATTR                       79: send_file
                2402    LOAD_FAST                       20: _var_var_29
                2404    LOAD_FAST                       31: _var_var_40
                2406    CALL                            2
                2414    POP_TOP                         
                2416    LOAD_GLOBAL                     67: NULL + time
                2426    LOAD_ATTR                       68: sleep
                2446    LOAD_GLOBAL                     17: NULL + random
                2456    LOAD_ATTR                       70: uniform
                2476    LOAD_CONST                      37: 1
                2478    LOAD_CONST                      40: 5
                2480    CALL                            2
                2488    CALL                            1
                2496    POP_TOP                         
                2498    LOAD_GLOBAL                     9: NULL + Logs
                2508    LOAD_ATTR                       10: PrintLog
                2528    LOAD_FAST                       1: config
                2530    LOAD_FAST                       0: account
                2532    LOAD_GLOBAL                     4: Lang
                2542    PUSH_NULL                       
                2544    LOAD_CONST                      1: '__pyarmor_assert_13416__'
                2546    LOAD_CONST                      30: 'create_bot_done'   # b'\x81\xe1\n\x162\xee\xbb\xed\x19\xf5\x19\xffh\xe3\xf6\x80'
                2548    CALL                            1
                2556    BINARY_SUBSCR                   
                2560    KW_NAMES                        10: ('config', 'account', 'message')
                2562    CALL                            3
                2570    POP_TOP                         
                2572    LOAD_FAST                       14: _var_var_23
                2574    POP_JUMP_IF_FALSE               234 (to 3044)
                2576    LOAD_GLOBAL                     9: NULL + Logs
                2586    LOAD_ATTR                       10: PrintLog
                2606    LOAD_FAST                       1: config
                2608    LOAD_FAST                       0: account
                2610    LOAD_GLOBAL                     4: Lang
                2620    PUSH_NULL                       
                2622    LOAD_CONST                      1: '__pyarmor_assert_13416__'
                2624    LOAD_CONST                      45: 'create_bot_set_bio'   # b'\x81\xe1\n\x162\xee\xbb\xed\x19\xf5\x19\xff\x7f\xe9\xec\xba\rT\xb4'
                2626    CALL                            1
                2634    BINARY_SUBSCR                   
                2638    KW_NAMES                        10: ('config', 'account', 'message')
                2640    CALL                            3
                2648    POP_TOP                         
                2650    LOAD_GLOBAL                     45: NULL + spintax
                2660    LOAD_ATTR                       46: spin
                2680    LOAD_FAST                       15: _var_var_24
                2682    CALL                            1
                2690    STORE_FAST                      24: _var_var_33
                2692    LOAD_FAST                       9: _var_var_18
                2694    LOAD_ATTR                       27: send_message
                2714    LOAD_FAST                       20: _var_var_29
                2716    PUSH_NULL                       
                2718    LOAD_CONST                      1: '__pyarmor_assert_13416__'
                2720    LOAD_CONST                      46: '/setabouttext'   # b"\x81\xad\x0b\x16'\xfb\xbc\xdd\x0e\xee\x19\xc5t\xf8"
                2722    CALL                            1
                2730    CALL                            2
                2738    POP_TOP                         
                2740    LOAD_GLOBAL                     75: NULL + button_click
                2750    LOAD_FAST                       9: _var_var_18
                2752    LOAD_FAST                       20: _var_var_29
                2754    CALL                            2
                2762    POP_TOP                         
                2764    LOAD_GLOBAL                     67: NULL + time
                2774    LOAD_ATTR                       68: sleep
                2794    LOAD_GLOBAL                     17: NULL + random
                2804    LOAD_ATTR                       70: uniform
                2824    LOAD_CONST                      37: 1
                2826    LOAD_CONST                      40: 5
                2828    CALL                            2
                2836    CALL                            1
                2844    POP_TOP                         
                2846    LOAD_FAST                       9: _var_var_18
                2848    LOAD_ATTR                       27: send_message
                2868    LOAD_FAST                       20: _var_var_29
                2870    LOAD_FAST                       24: _var_var_33
                2872    LOAD_CONST                      0: None
                2874    LOAD_CONST                      47: 120
                2876    BINARY_SLICE                    
                2878    CALL                            2
                2886    POP_TOP                         
                2888    LOAD_GLOBAL                     67: NULL + time
                2898    LOAD_ATTR                       68: sleep
                2918    LOAD_GLOBAL                     17: NULL + random
                2928    LOAD_ATTR                       70: uniform
                2948    LOAD_CONST                      37: 1
                2950    LOAD_CONST                      40: 5
                2952    CALL                            2
                2960    CALL                            1
                2968    POP_TOP                         
                2970    LOAD_GLOBAL                     9: NULL + Logs
                2980    LOAD_ATTR                       10: PrintLog
                3000    LOAD_FAST                       1: config
                3002    LOAD_FAST                       0: account
                3004    LOAD_GLOBAL                     4: Lang
                3014    PUSH_NULL                       
                3016    LOAD_CONST                      1: '__pyarmor_assert_13416__'
                3018    LOAD_CONST                      30: 'create_bot_done'   # b'\x81\xe1\n\x162\xee\xbb\xed\x19\xf5\x19\xffh\xe3\xf6\x80'
                3020    CALL                            1
                3028    BINARY_SUBSCR                   
                3032    KW_NAMES                        10: ('config', 'account', 'message')
                3034    CALL                            3
                3042    POP_TOP                         
                3044    LOAD_FAST                       16: _var_var_25
                3046    POP_JUMP_IF_FALSE               250 (to 3548)
                3048    LOAD_GLOBAL                     9: NULL + Logs
                3058    LOAD_ATTR                       10: PrintLog
                3078    LOAD_FAST                       1: config
                3080    LOAD_FAST                       0: account
                3082    LOAD_GLOBAL                     4: Lang
                3092    PUSH_NULL                       
                3094    LOAD_CONST                      1: '__pyarmor_assert_13416__'
                3096    LOAD_CONST                      48: 'create_bot_set_desc'   # b'\x81\xe1\n\x162\xee\xbb\xed\x19\xf5\x19\xff\x7f\xe9\xec\xba\x0bX\xa8\xa4'
                3098    CALL                            1
                3106    BINARY_SUBSCR                   
                3110    KW_NAMES                        10: ('config', 'account', 'message')
                3112    CALL                            3
                3120    POP_TOP                         
                3122    LOAD_GLOBAL                     45: NULL + spintax
                3132    LOAD_ATTR                       46: spin
                3152    LOAD_GLOBAL                     17: NULL + random
                3162    LOAD_ATTR                       72: choice
                3182    LOAD_FAST                       17: _var_var_26
                3184    CALL                            1
                3192    CALL                            1
                3200    STORE_FAST                      26: _var_var_35
                3202    LOAD_FAST                       9: _var_var_18
                3204    LOAD_ATTR                       27: send_message
                3224    LOAD_FAST                       20: _var_var_29
                3226    PUSH_NULL                       
                3228    LOAD_CONST                      1: '__pyarmor_assert_13416__'
                3230    LOAD_CONST                      49: '/setdescription'   # b"\x81\xad\x0b\x16'\xfe\xbb\xc1\x18\xe8\x04\xd0x\xe5\xf7\x8b"
                3232    CALL                            1
                3240    CALL                            2
                3248    POP_TOP                         
                3250    LOAD_GLOBAL                     75: NULL + button_click
                3260    LOAD_FAST                       9: _var_var_18
                3262    LOAD_FAST                       20: _var_var_29
                3264    CALL                            2
                3272    POP_TOP                         
                3274    LOAD_GLOBAL                     67: NULL + time
                3284    LOAD_ATTR                       68: sleep
                3304    LOAD_GLOBAL                     17: NULL + random
                3314    LOAD_ATTR                       70: uniform
                3334    LOAD_CONST                      37: 1
                3336    LOAD_CONST                      40: 5
                3338    CALL                            2
                3346    CALL                            1
                3354    POP_TOP                         
                3356    LOAD_FAST                       9: _var_var_18
                3358    LOAD_ATTR                       27: send_message
                3378    LOAD_FAST                       20: _var_var_29
                3380    LOAD_FAST                       26: _var_var_35
                3382    CALL                            2
                3390    POP_TOP                         
                3392    LOAD_GLOBAL                     9: NULL + Logs
                3402    LOAD_ATTR                       10: PrintLog
                3422    LOAD_FAST                       1: config
                3424    LOAD_FAST                       0: account
                3426    LOAD_GLOBAL                     4: Lang
                3436    PUSH_NULL                       
                3438    LOAD_CONST                      1: '__pyarmor_assert_13416__'
                3440    LOAD_CONST                      30: 'create_bot_done'   # b'\x81\xe1\n\x162\xee\xbb\xed\x19\xf5\x19\xffh\xe3\xf6\x80'
                3442    CALL                            1
                3450    BINARY_SUBSCR                   
                3454    KW_NAMES                        10: ('config', 'account', 'message')
                3456    CALL                            3
                3464    POP_TOP                         
                3466    LOAD_GLOBAL                     67: NULL + time
                3476    LOAD_ATTR                       68: sleep
                3496    LOAD_GLOBAL                     17: NULL + random
                3506    LOAD_ATTR                       70: uniform
                3526    LOAD_CONST                      37: 1
                3528    LOAD_CONST                      40: 5
                3530    CALL                            2
                3538    CALL                            1
                3546    POP_TOP                         
                3548    LOAD_FAST                       18: _var_var_27
                3550    POP_JUMP_IF_FALSE               123 (to 3798)
                3552    LOAD_GLOBAL                     9: NULL + Logs
                3562    LOAD_ATTR                       10: PrintLog
                3582    LOAD_FAST                       1: config
                3584    LOAD_FAST                       0: account
                3586    LOAD_GLOBAL                     4: Lang
                3596    PUSH_NULL                       
                3598    LOAD_CONST                      1: '__pyarmor_assert_13416__'
                3600    LOAD_CONST                      50: 'create_bot_set_privacy'   # b'\x81\xe1\n\x162\xee\xbb\xed\x19\xf5\x19\xff\x7f\xe9\xec\xba\x1fO\xb2\xb1\xab\xc8W'
                3602    CALL                            1
                3610    BINARY_SUBSCR                   
                3614    KW_NAMES                        10: ('config', 'account', 'message')
                3616    CALL                            3
                3624    POP_TOP                         
                3626    LOAD_FAST                       9: _var_var_18
                3628    LOAD_ATTR                       27: send_message
                3648    LOAD_FAST                       20: _var_var_29
                3650    PUSH_NULL                       
                3652    LOAD_CONST                      1: '__pyarmor_assert_13416__'
                3654    LOAD_CONST                      51: '/setprivacy'   # b"\x81\xad\x0b\x16'\xea\xac\xdb\r\xfb\x0e\xd9"
                3656    CALL                            1
                3664    CALL                            2
                3672    POP_TOP                         
                3674    LOAD_GLOBAL                     75: NULL + button_click
                3684    LOAD_FAST                       9: _var_var_18
                3686    LOAD_FAST                       20: _var_var_29
                3688    CALL                            2
                3696    POP_TOP                         
                3698    LOAD_GLOBAL                     75: NULL + button_click
                3708    LOAD_FAST                       9: _var_var_18
                3710    LOAD_FAST                       20: _var_var_29
                3712    LOAD_CONST                      37: 1
                3714    CALL                            3
                3722    POP_TOP                         
                3724    LOAD_GLOBAL                     9: NULL + Logs
                3734    LOAD_ATTR                       10: PrintLog
                3754    LOAD_FAST                       1: config
                3756    LOAD_FAST                       0: account
                3758    LOAD_GLOBAL                     4: Lang
                3768    PUSH_NULL                       
                3770    LOAD_CONST                      1: '__pyarmor_assert_13416__'
                3772    LOAD_CONST                      30: 'create_bot_done'   # b'\x81\xe1\n\x162\xee\xbb\xed\x19\xf5\x19\xffh\xe3\xf6\x80'
                3774    CALL                            1
                3782    BINARY_SUBSCR                   
                3786    KW_NAMES                        10: ('config', 'account', 'message')
                3788    CALL                            3
                3796    POP_TOP                         
                3798    LOAD_GLOBAL                     83: NULL + db_create_bots
                3808    LOAD_FAST                       4: base
                3810    CALL                            1
                3818    LOAD_ATTR                       85: insert
                3838    LOAD_FAST                       0: account
                3840    LOAD_FAST_CHECK                 22: _var_var_31
                3842    LOAD_FAST_CHECK                 23: _var_var_32
                3844    LOAD_FAST_CHECK                 21: _var_var_30
                3846    LOAD_FAST_CHECK                 24: _var_var_33
                3848    LOAD_FAST_CHECK                 25: _var_var_34
                3850    LOAD_FAST_CHECK                 26: _var_var_35
                3852    LOAD_FAST                       18: _var_var_27
                3854    POP_JUMP_IF_FALSE               2 (to 3860)
                3856    LOAD_CONST                      37: 1
                3858    JUMP_FORWARD                    1 (to 3862)
                3860    LOAD_CONST                      35: 0
                3862    LOAD_FAST                       27: _var_var_36
                3864    KW_NAMES                        53: ('account', 'token', 'username', 'name', 'bio', 'photo', 'description', 'restrict_groups', 'status')
                3866    CALL                            9
                3874    POP_TOP                         
                3876    LOAD_FAST                       27: _var_var_36
                3878    LOAD_CONST                      52: 'Error'
                3880    COMPARE_OP                      40 (==)
                3884    POP_JUMP_IF_FALSE               1 (to 3888)
                3886    JUMP_FORWARD                    28 (to 3944)
                3888    LOAD_FAST                       19: _var_var_28
                3890    LOAD_CONST                      37: 1
                3892    BINARY_OP                       23 (-=)
                3896    STORE_FAST                      19: _var_var_28
                3898    LOAD_FAST                       19: _var_var_28
                3900    LOAD_CONST                      35: 0
                3902    COMPARE_OP                      26 (<=)
                3906    POP_JUMP_IF_FALSE               1 (to 3910)
                3908    JUMP_FORWARD                    17 (to 3944)
                3910    LOAD_GLOBAL                     87: NULL + DelayOnline
                3920    LOAD_FAST                       0: account
                3922    LOAD_FAST                       9: _var_var_18
                3924    LOAD_FAST                       10: _var_var_19
                3926    LOAD_FAST                       11: _var_var_20
                3928    LOAD_FAST                       7: stop_thread
                3930    CALL                            5
                3938    POP_TOP                         
                3940    JUMP_BACKWARD                   1472 (to 1000)
                3944    LOAD_GLOBAL                     7: NULL + Disconnect
                3954    LOAD_FAST_CHECK                 9: _var_var_18
                3956    CALL                            1
                3964    POP_TOP                         
                3966    LOAD_GLOBAL                     9: NULL + Logs
                3976    LOAD_ATTR                       10: PrintLog
                3996    LOAD_FAST                       1: config
                3998    LOAD_FAST                       0: account
                4000    LOAD_GLOBAL                     4: Lang
                4010    PUSH_NULL                       
                4012    LOAD_CONST                      1: '__pyarmor_assert_13416__'
                4014    LOAD_CONST                      9: 'work_account_completed'   # b'\x81\xf5\x17\x018\xc5\xbf\xd1\x18\xf5\x18\xcex\xd3\xfb\x8a\x02M\xb7\xa2\xbe\xceJ'
                4016    CALL                            1
                4024    BINARY_SUBSCR                   
                4028    KW_NAMES                        10: ('config', 'account', 'message')
                4030    CALL                            3
                4038    POP_TOP                         
                4040    LOAD_FAST                       0: account
                4042    LOAD_CONST                      11: 'done'
                4044    LOAD_CONST                      8: ('account', 'status')
                4046    BUILD_CONST_KEY_MAP             2
                4048    NOP                             
                4050    NOP                             
                4052    JUMP_FORWARD                    293 (to 4642)
                4056    CALL                            1
                4064    POP_TOP                         
                4066    RETURN_VALUE                    
                4068    PUSH_EXC_INFO                   
                4070    POP_TOP                         
                4072    POP_EXCEPT                      
                4074    JUMP_BACKWARD                   1964 (to 150)
                4078    COPY                            3
                4080    POP_EXCEPT                      
                4082    RERAISE                         1
                4084    PUSH_EXC_INFO                   
                4086    LOAD_GLOBAL                     28: errors
                4096    LOAD_ATTR                       30: YouBlockedUserError
                4116    CHECK_EXC_MATCH                 
                4118    POP_JUMP_IF_FALSE               59 (to 4238)
                4120    POP_TOP                         
                4122    PUSH_NULL                       
                4124    LOAD_FAST                       9: _var_var_18
                4126    LOAD_GLOBAL                     32: functions
                4136    LOAD_ATTR                       34: contacts
                4156    LOAD_ATTR                       37: UnblockRequest
                4176    LOAD_CONST                      29: 'spambot'
                4178    CALL                            1
                4186    CALL                            1
                4194    POP_TOP                         
                4196    LOAD_FAST                       9: _var_var_18
                4198    LOAD_ATTR                       27: send_message
                4218    LOAD_FAST                       20: _var_var_29
                4220    LOAD_CONST                      28: '/newbot'
                4222    CALL                            2
                4230    POP_TOP                         
                4232    POP_EXCEPT                      
                4234    JUMP_BACKWARD                   1548 (to 1142)
                4238    RERAISE                         0
                4240    COPY                            3
                4242    POP_EXCEPT                      
                4244    RERAISE                         1
                4246    PUSH_EXC_INFO                   
                4248    WITH_EXCEPT_START               
                4250    POP_JUMP_IF_TRUE                1 (to 4254)
                4252    RERAISE                         2
                4254    POP_TOP                         
                4256    POP_EXCEPT                      
                4258    POP_TOP                         
                4260    POP_TOP                         
                4262    JUMP_BACKWARD                   1425 (to 1416)
                4266    COPY                            3
                4268    POP_EXCEPT                      
                4270    RERAISE                         1
                4272    PUSH_EXC_INFO                   
                4274    WITH_EXCEPT_START               
                4276    POP_JUMP_IF_TRUE                1 (to 4280)
                4278    RERAISE                         2
                4280    POP_TOP                         
                4282    POP_EXCEPT                      
                4284    POP_TOP                         
                4286    POP_TOP                         
                4288    JUMP_BACKWARD                   1316 (to 1660)
                4292    COPY                            3
                4294    POP_EXCEPT                      
                4296    RERAISE                         1
                4298    PUSH_EXC_INFO                   
                4300    LOAD_GLOBAL                     80: Exception
                4310    CHECK_EXC_MATCH                 
                4312    POP_JUMP_IF_FALSE               13 (to 4340)
                4314    STORE_FAST                      32: _var_var_3
                4316    LOAD_CONST                      52: 'Error'
                4318    STORE_FAST                      27: _var_var_36
                4320    POP_EXCEPT                      
                4322    LOAD_CONST                      0: None
                4324    STORE_FAST                      32: _var_var_3
                4326    DELETE_FAST                     32: _var_var_3
                4328    JUMP_BACKWARD                   267 (to 3798)
                4332    LOAD_CONST                      0: None
                4334    STORE_FAST                      32: _var_var_3
                4336    DELETE_FAST                     32: _var_var_3
                4338    RERAISE                         1
                4340    RERAISE                         0
                4342    COPY                            3
                4344    POP_EXCEPT                      
                4346    RERAISE                         1
                4348    PUSH_EXC_INFO                   
                4350    LOAD_GLOBAL                     88: StopProgram
                4360    CHECK_EXC_MATCH                 
                4362    POP_JUMP_IF_FALSE               3 (to 4370)
                4364    POP_TOP                         
                4366    POP_EXCEPT                      
                4368    JUMP_BACKWARD                   213 (to 3944)
                4370    LOAD_GLOBAL                     90: BaseException
                4380    CHECK_EXC_MATCH                 
                4382    POP_JUMP_IF_FALSE               26 (to 4436)
                4384    STORE_FAST                      32: _var_var_3
                4386    PUSH_NULL                       
                4388    LOAD_GLOBAL                     93: NULL + logging
                4398    LOAD_FAST                       32: _var_var_3
                4400    CALL                            1
                4408    CALL                            0
                4416    POP_TOP                         
                4418    POP_EXCEPT                      
                4420    LOAD_CONST                      0: None
                4422    STORE_FAST                      32: _var_var_3
                4424    DELETE_FAST                     32: _var_var_3
                4426    JUMP_BACKWARD                   242 (to 3944)
                4428    LOAD_CONST                      0: None
                4430    STORE_FAST                      32: _var_var_3
                4432    DELETE_FAST                     32: _var_var_3
                4434    RERAISE                         1
                4436    RERAISE                         0
                4438    COPY                            3
                4440    POP_EXCEPT                      
                4442    RERAISE                         1
                4444    PUSH_EXC_INFO                   
                4446    POP_TOP                         
                4448    POP_EXCEPT                      
                4450    JUMP_BACKWARD                   243 (to 3966)
                4452    COPY                            3
                4454    POP_EXCEPT                      
                4456    RERAISE                         1
                4458    PUSH_EXC_INFO                   
                4460    LOAD_GLOBAL                     7: NULL + Disconnect
                4470    LOAD_FAST_CHECK                 9: _var_var_18
                4472    CALL                            1
                4480    POP_TOP                         
                4482    JUMP_FORWARD                    7 (to 4498)
                4484    PUSH_EXC_INFO                   
                4486    POP_TOP                         
                4488    POP_EXCEPT                      
                4490    JUMP_FORWARD                    3 (to 4498)
                4492    COPY                            3
                4494    POP_EXCEPT                      
                4496    RERAISE                         1
                4498    LOAD_GLOBAL                     9: NULL + Logs
                4508    LOAD_ATTR                       10: PrintLog
                4528    LOAD_FAST                       1: config
                4530    LOAD_FAST                       0: account
                4532    LOAD_GLOBAL                     4: Lang
                4542    PUSH_NULL                       
                4544    LOAD_CONST                      1: '__pyarmor_assert_13416__'
                4546    LOAD_CONST                      9: 'work_account_completed'   # b'\x81\xf5\x17\x018\xc5\xbf\xd1\x18\xf5\x18\xcex\xd3\xfb\x8a\x02M\xb7\xa2\xbe\xceJ'
                4548    CALL                            1
                4556    BINARY_SUBSCR                   
                4560    KW_NAMES                        10: ('config', 'account', 'message')
                4562    CALL                            3
                4570    POP_TOP                         
                4572    LOAD_FAST                       0: account
                4574    LOAD_CONST                      11: 'done'
                4576    LOAD_CONST                      8: ('account', 'status')
                4578    BUILD_CONST_KEY_MAP             2
                4580    SWAP                            2
                4582    POP_TOP                         
                4584    SWAP                            2
                4586    POP_EXCEPT                      
                4588    NOP                             
                4590    NOP                             
                4592    NOP                             
                4594    JUMP_FORWARD                    23 (to 4642)
                4596    CALL                            1
                4604    POP_TOP                         
                4606    RETURN_VALUE                    
                4608    COPY                            3
                4610    POP_EXCEPT                      
                4612    RERAISE                         1
                4614    PUSH_EXC_INFO                   
                4616    PUSH_NULL                       
                4618    LOAD_CONST                      12: '__pyarmor_exit_13418__'
                4620    NOP                             
                4622    LOAD_CONST                      3: b'<COAddr>\x07\x00\x00\x1a\xec\x11\x00\x00\x00\x00\x00\x00\x00\x00\x00\x00\x00\x00\x00\x00'
                4624    CALL                            1
                4632    POP_TOP                         
                4634    RERAISE                         0
                4636    COPY                            3
                4638    POP_EXCEPT                      
                4640    RERAISE                         1
                4642    PUSH_NULL                       
                4644    LOAD_CONST                      12: '__pyarmor_exit_13418__'
                4646    LOAD_CONST                      3: b'<COAddr>\x07\x00\x00\x1a\xec\x11\x00\x00\x00\x00\x00\x00\x00\x00\x00\x00\x00\x00\x00\x00'
                4648    BUILD_TUPLE                     1
                4650    CALL_FUNCTION_EX                0
                4652    POP_TOP                         
                4654    RETURN_VALUE                    
            [Exception Table]
                30 to 128 -> 4348 [0] 
                128 to 150 -> 4068 [1] 
                150 to 236 -> 4614 [0] 
                256 to 1000 -> 4348 [0] 
                1002 to 1104 -> 4298 [0] 
                1106 to 1142 -> 4084 [0] 
                1142 to 1334 -> 4298 [0] 
                1334 to 1400 -> 4246 [1] lasti
                1400 to 1620 -> 4298 [0] 
                1620 to 1644 -> 4272 [1] lasti
                1644 to 3798 -> 4298 [0] 
                3798 to 3944 -> 4348 [0] 
                3944 to 3966 -> 4444 [0] 
                3966 to 4048 -> 4614 [0] 
                4068 to 4072 -> 4078 [2] lasti
                4072 to 4084 -> 4614 [0] 
                4084 to 4232 -> 4240 [1] lasti
                4232 to 4238 -> 4298 [0] 
                4238 to 4240 -> 4240 [1] lasti
                4240 to 4246 -> 4298 [0] 
                4246 to 4256 -> 4266 [3] lasti
                4256 to 4272 -> 4298 [0] 
                4272 to 4282 -> 4292 [3] lasti
                4282 to 4298 -> 4298 [0] 
                4298 to 4316 -> 4342 [1] lasti
                4316 to 4320 -> 4332 [1] lasti
                4320 to 4332 -> 4348 [0] 
                4332 to 4342 -> 4342 [1] lasti
                4342 to 4348 -> 4348 [0] 
                4348 to 4366 -> 4438 [1] lasti
                4366 to 4370 -> 4458 [0] 
                4370 to 4386 -> 4438 [1] lasti
                4386 to 4418 -> 4428 [1] lasti
                4418 to 4428 -> 4458 [0] 
                4428 to 4438 -> 4438 [1] lasti
                4438 to 4444 -> 4458 [0] 
                4444 to 4448 -> 4452 [1] lasti
                4448 to 4458 -> 4614 [0] 
                4458 to 4460 -> 4608 [1] lasti
                4460 to 4482 -> 4484 [2] 
                4482 to 4484 -> 4608 [1] lasti
                4484 to 4488 -> 4492 [3] lasti
                4488 to 4586 -> 4608 [1] lasti
                4586 to 4588 -> 4614 [0] 
                4608 to 4614 -> 4614 [0] 
                4614 to 4636 -> 4636 [1] lasti
        [Code]
            File Name: <frozen program.modules.Create_bots>
            Object Name: username_generator
            Qualified Name: username_generator
            Arg Count: 1
            Pos Only Arg Count: 0
            KW Only Arg Count: 0
            Stack Size: 5
            Flags: 0x20000023 (CO_OPTIMIZED | CO_NEWLOCALS | CO_GENERATOR | CO_PYARMOR_OBFUSCATED)
            [Names]
                'cycle'
            [Locals+Names]
                'usernames'
                '__assert_armored__'
                '_var_var_41'
            [Constants]
                None
                '__pyarmor_assert_13419__'
                '__pyarmor_enter_13420__'
                b'<COAddr>\x07\x00\x00\x1eb\x00\x00\x00\x00\x00\x00\x00\x00\x00\x00\x00\x00\x00\x00\x00'
                '__pyarmor_exit_13421__'
            [Disassembly]
                0       RETURN_GENERATOR                
                2       POP_TOP                         
                4       NOP                             
                6       NOP                             
                8       PUSH_NULL                       
                10      LOAD_CONST                      2: '__pyarmor_enter_13420__'
                12      LOAD_CONST                      3: b'<COAddr>\x07\x00\x00\x1eb\x00\x00\x00\x00\x00\x00\x00\x00\x00\x00\x00\x00\x00\x00\x00'
                14      BUILD_TUPLE                     1
                16      CALL_FUNCTION_EX                0
                18      POP_TOP                         
                20      RESUME                          0
                22      NOP                             
                24      NOP                             
                26      NOP                             
                28      NOP                             
                30      NOP                             
                32      NOP                             
                34      LOAD_GLOBAL                     1: NULL + cycle
                44      LOAD_FAST                       0: usernames
                46      CALL                            1
                54      GET_ITER                        
                56      FOR_ITER                        6 (to 70)
                60      STORE_FAST                      2: _var_var_41
                62      LOAD_FAST                       2: _var_var_41
                64      YIELD_VALUE                     3
                66      RESUME                          1
                68      POP_TOP                         
                70      JUMP_BACKWARD                   8 (to 56)
                72      END_FOR                         
                74      NOP                             
                76      LOAD_CONST                      0: None
                78      NOP                             
                80      NOP                             
                82      NOP                             
                84      JUMP_FORWARD                    37 (to 160)
                92      POP_TOP                         
                94      RETURN_CONST                    0: None
                96      PUSH_EXC_INFO                   
                98      POP_TOP                         
                100     POP_EXCEPT                      
                102     LOAD_CONST                      0: None
                104     NOP                             
                106     NOP                             
                108     NOP                             
                110     JUMP_FORWARD                    24 (to 160)
                118     POP_TOP                         
                120     RETURN_CONST                    0: None
                122     COPY                            3
                124     POP_EXCEPT                      
                126     RERAISE                         1
                128     PUSH_EXC_INFO                   
                130     PUSH_NULL                       
                132     LOAD_CONST                      4: '__pyarmor_exit_13421__'
                134     NOP                             
                136     LOAD_CONST                      3: b'<COAddr>\x07\x00\x00\x1eb\x00\x00\x00\x00\x00\x00\x00\x00\x00\x00\x00\x00\x00\x00\x00'
                138     CALL                            1
                146     POP_TOP                         
                148     RERAISE                         0
                150     COPY                            3
                152     POP_EXCEPT                      
                154     RERAISE                         1
                156     CALL_INTRINSIC_1                3 (INTRINSIC_STOPITERATION_ERROR)
                158     RERAISE                         1
                160     PUSH_NULL                       
                162     LOAD_CONST                      4: '__pyarmor_exit_13421__'
                164     LOAD_CONST                      3: b'<COAddr>\x07\x00\x00\x1eb\x00\x00\x00\x00\x00\x00\x00\x00\x00\x00\x00\x00\x00\x00\x00'
                166     BUILD_TUPLE                     1
                168     CALL_FUNCTION_EX                0
                170     POP_TOP                         
                172     RETURN_VALUE                    
            [Exception Table]
                4 to 30 -> 156 [0] lasti
                34 to 74 -> 96 [0] 
                76 to 96 -> 156 [0] lasti
                96 to 100 -> 122 [1] lasti
                100 to 102 -> 128 [0] 
                102 to 122 -> 156 [0] lasti
                122 to 128 -> 128 [0] 
                128 to 150 -> 150 [1] lasti
                150 to 156 -> 156 [0] lasti
        [Code]
            File Name: <frozen program.modules.Create_bots>
            Object Name: modify_username
            Qualified Name: modify_username
            Arg Count: 1
            Pos Only Arg Count: 0
            KW Only Arg Count: 0
            Stack Size: 9
            Flags: 0x20000003 (CO_OPTIMIZED | CO_NEWLOCALS | CO_PYARMOR_OBFUSCATED)
            [Names]
                'join'
                'random'
                'choices'
                'string'
                'ascii_lowercase'
                'randint'
                'lower'
                'replace'
                'choice'
            [Locals+Names]
                'username'
                '__assert_armored__'
                '_var_var_42'
                '_var_var_43'
            [Constants]
                None
                '__pyarmor_assert_13422__'
                '__pyarmor_enter_13423__'
                b'<COAddr>\x07\x00\x00\x1a\x9a\x01\x00\x00\x00\x00\x00\x00\x00\x00\x00\x00\x00\x00\x00\x00'
                ''
                1
                5
                (
                    'k'
                )
                'robot'
                '_robot'
                'bot'
                '_bot'
                (
                    'bot'
                    '_bot'
                    'robot'
                    '_robot'
                )
                '__pyarmor_exit_13424__'
            [Disassembly]
                0       NOP                             
                2       NOP                             
                4       PUSH_NULL                       
                6       LOAD_CONST                      2: '__pyarmor_enter_13423__'
                8       LOAD_CONST                      3: b'<COAddr>\x07\x00\x00\x1a\x9a\x01\x00\x00\x00\x00\x00\x00\x00\x00\x00\x00\x00\x00\x00\x00'
                10      BUILD_TUPLE                     1
                12      CALL_FUNCTION_EX                0
                14      POP_TOP                         
                16      RESUME                          0
                18      NOP                             
                20      NOP                             
                22      NOP                             
                24      NOP                             
                26      NOP                             
                28      LOAD_CONST                      4: ''
                30      LOAD_ATTR                       1: join
                50      LOAD_GLOBAL                     3: NULL + random
                60      LOAD_ATTR                       4: choices
                80      LOAD_GLOBAL                     6: string
                90      LOAD_ATTR                       8: ascii_lowercase
                110     LOAD_GLOBAL                     3: NULL + random
                120     LOAD_ATTR                       10: randint
                140     LOAD_CONST                      5: 1
                142     LOAD_CONST                      6: 5
                144     CALL                            2
                152     KW_NAMES                        7: ('k',)
                154     CALL                            2
                162     CALL                            1
                170     STORE_FAST                      2: _var_var_42
                172     LOAD_FAST                       0: username
                174     LOAD_ATTR                       13: lower
                194     CALL                            0
                202     STORE_FAST                      0: username
                204     LOAD_CONST                      8: 'robot'
                206     LOAD_FAST                       0: username
                208     CONTAINS_OP                     0 (in)
                210     POP_JUMP_IF_FALSE               34 (to 280)
                212     LOAD_FAST                       0: username
                214     LOAD_ATTR                       15: replace
                234     LOAD_CONST                      9: '_robot'
                236     LOAD_CONST                      4: ''
                238     CALL                            2
                246     LOAD_ATTR                       15: replace
                266     LOAD_CONST                      8: 'robot'
                268     LOAD_CONST                      4: ''
                270     CALL                            2
                278     STORE_FAST                      0: username
                280     LOAD_CONST                      10: 'bot'
                282     LOAD_FAST                       0: username
                284     CONTAINS_OP                     0 (in)
                286     POP_JUMP_IF_FALSE               34 (to 356)
                288     LOAD_FAST                       0: username
                290     LOAD_ATTR                       15: replace
                310     LOAD_CONST                      11: '_bot'
                312     LOAD_CONST                      4: ''
                314     CALL                            2
                322     LOAD_ATTR                       15: replace
                342     LOAD_CONST                      10: 'bot'
                344     LOAD_CONST                      4: ''
                346     CALL                            2
                354     STORE_FAST                      0: username
                356     LOAD_GLOBAL                     3: NULL + random
                366     LOAD_ATTR                       16: choice
                386     BUILD_LIST                      0
                388     LOAD_CONST                      12: ('bot', '_bot', 'robot', '_robot')
                390     LIST_EXTEND                     1
                392     CALL                            1
                400     STORE_FAST                      3: _var_var_43
                402     LOAD_FAST                       0: username
                404     FORMAT_VALUE                    0 (FVC_NONE)
                406     LOAD_FAST                       2: _var_var_42
                408     FORMAT_VALUE                    0 (FVC_NONE)
                410     LOAD_FAST                       3: _var_var_43
                412     FORMAT_VALUE                    0 (FVC_NONE)
                414     BUILD_STRING                    3
                416     NOP                             
                418     NOP                             
                420     NOP                             
                422     JUMP_FORWARD                    20 (to 464)
                424     CALL                            1
                432     POP_TOP                         
                434     RETURN_VALUE                    
                436     PUSH_EXC_INFO                   
                438     PUSH_NULL                       
                440     LOAD_CONST                      13: '__pyarmor_exit_13424__'
                442     NOP                             
                444     LOAD_CONST                      3: b'<COAddr>\x07\x00\x00\x1a\x9a\x01\x00\x00\x00\x00\x00\x00\x00\x00\x00\x00\x00\x00\x00\x00'
                446     CALL                            1
                454     POP_TOP                         
                456     RERAISE                         0
                458     COPY                            3
                460     POP_EXCEPT                      
                462     RERAISE                         1
                464     PUSH_NULL                       
                466     LOAD_CONST                      13: '__pyarmor_exit_13424__'
                468     LOAD_CONST                      3: b'<COAddr>\x07\x00\x00\x1a\x9a\x01\x00\x00\x00\x00\x00\x00\x00\x00\x00\x00\x00\x00\x00\x00'
                470     BUILD_TUPLE                     1
                472     CALL_FUNCTION_EX                0
                474     POP_TOP                         
                476     RETURN_VALUE                    
            [Exception Table]
                28 to 416 -> 436 [0] 
                436 to 458 -> 458 [1] lasti
        [Code]
            File Name: <frozen program.modules.Create_bots>
            Object Name: button_click
            Qualified Name: button_click
            Arg Count: 3
            Pos Only Arg Count: 0
            KW Only Arg Count: 0
            Stack Size: 6
            Flags: 0x20000003 (CO_OPTIMIZED | CO_NEWLOCALS | CO_PYARMOR_OBFUSCATED)
            [Names]
                'time'
                'sleep'
                'random'
                'uniform'
                'iter_messages'
                'str'
                'raw_text'
                'ValueError'
                'len'
                'reply_markup'
                'rows'
                'click'
            [Locals+Names]
                'client'
                'botfather'
                'button_number'
                '__assert_armored__'
                '_var_var_38'
                '_var_var_44'
            [Constants]
                None
                '__pyarmor_assert_13425__'
                '__pyarmor_enter_13426__'
                b'<COAddr>\x05\x00\x00\x1af\x01\x00\x00\x00\x00\x00\x00\x00\x00\x00\x00\x00\x00\x00\x00'
                1
                5
                (
                    'limit'
                )
                'Sorry, too many attempts'   # b'\x81\xd1\x17\x01!\xe3\xf2\x92\x0f\xf5\x02\x80a\xed\xf6\x9cO\\\xaf\xb3\xaf\xc6^\xd8\x16'
                'Flood'
                0
                '__pyarmor_exit_13427__'
            [Disassembly]
                0       NOP                             
                2       NOP                             
                4       PUSH_NULL                       
                6       LOAD_CONST                      2: '__pyarmor_enter_13426__'
                8       LOAD_CONST                      3: b'<COAddr>\x05\x00\x00\x1af\x01\x00\x00\x00\x00\x00\x00\x00\x00\x00\x00\x00\x00\x00\x00'
                10      BUILD_TUPLE                     1
                12      CALL_FUNCTION_EX                0
                14      POP_TOP                         
                16      RESUME                          0
                18      NOP                             
                20      NOP                             
                22      NOP                             
                24      NOP                             
                26      NOP                             
                28      LOAD_GLOBAL                     1: NULL + time
                38      LOAD_ATTR                       2: sleep
                58      LOAD_GLOBAL                     5: NULL + random
                68      LOAD_ATTR                       6: uniform
                88      LOAD_CONST                      4: 1
                90      LOAD_CONST                      5: 5
                92      CALL                            2
                100     CALL                            1
                108     POP_TOP                         
                110     LOAD_FAST                       0: client
                112     LOAD_ATTR                       9: iter_messages
                132     LOAD_FAST                       1: botfather
                134     LOAD_CONST                      4: 1
                136     KW_NAMES                        6: ('limit',)
                138     CALL                            2
                146     GET_ITER                        
                148     FOR_ITER                        96 (to 342)
                152     STORE_FAST                      4: _var_var_38
                154     PUSH_NULL                       
                156     LOAD_CONST                      1: '__pyarmor_assert_13425__'
                158     LOAD_CONST                      7: 'Sorry, too many attempts'   # b'\x81\xd1\x17\x01!\xe3\xf2\x92\x0f\xf5\x02\x80a\xed\xf6\x9cO\\\xaf\xb3\xaf\xc6^\xd8\x16'
                160     CALL                            1
                168     LOAD_GLOBAL                     11: NULL + str
                178     LOAD_FAST                       4: _var_var_38
                180     LOAD_ATTR                       12: raw_text
                200     CALL                            1
                208     CONTAINS_OP                     0 (in)
                210     POP_JUMP_IF_FALSE               11 (to 234)
                212     LOAD_GLOBAL                     15: NULL + ValueError
                222     LOAD_CONST                      8: 'Flood'
                224     CALL                            1
                232     RAISE_VARARGS                   1
                234     LOAD_GLOBAL                     17: NULL + len
                244     LOAD_FAST                       4: _var_var_38
                246     LOAD_ATTR                       18: reply_markup
                266     LOAD_ATTR                       20: rows
                286     CALL                            1
                294     STORE_FAST                      5: _var_var_44
                296     LOAD_FAST                       5: _var_var_44
                298     LOAD_CONST                      9: 0
                300     COMPARE_OP                      68 (>)
                304     POP_JUMP_IF_TRUE                1 (to 308)
                306     JUMP_BACKWARD                   80 (to 148)
                308     LOAD_FAST                       4: _var_var_38
                310     LOAD_ATTR                       23: click
                330     LOAD_FAST                       2: button_number
                332     CALL                            1
                340     POP_TOP                         
                342     JUMP_BACKWARD                   98 (to 148)
                344     END_FOR                         
                346     LOAD_CONST                      0: None
                348     NOP                             
                350     NOP                             
                352     NOP                             
                354     JUMP_FORWARD                    28 (to 412)
                362     POP_TOP                         
                364     RETURN_CONST                    0: None
                366     PUSH_EXC_INFO                   
                368     POP_TOP                         
                370     LOAD_CONST                      9: 0
                372     STORE_FAST                      5: _var_var_44
                374     POP_EXCEPT                      
                376     JUMP_BACKWARD                   41 (to 296)
                378     COPY                            3
                380     POP_EXCEPT                      
                382     RERAISE                         1
                384     PUSH_EXC_INFO                   
                386     PUSH_NULL                       
                388     LOAD_CONST                      10: '__pyarmor_exit_13427__'
                390     NOP                             
                392     LOAD_CONST                      3: b'<COAddr>\x05\x00\x00\x1af\x01\x00\x00\x00\x00\x00\x00\x00\x00\x00\x00\x00\x00\x00\x00'
                394     CALL                            1
                402     POP_TOP                         
                404     RERAISE                         0
                406     COPY                            3
                408     POP_EXCEPT                      
                410     RERAISE                         1
                412     PUSH_NULL                       
                414     LOAD_CONST                      10: '__pyarmor_exit_13427__'
                416     LOAD_CONST                      3: b'<COAddr>\x05\x00\x00\x1af\x01\x00\x00\x00\x00\x00\x00\x00\x00\x00\x00\x00\x00\x00\x00'
                418     BUILD_TUPLE                     1
                420     CALL_FUNCTION_EX                0
                422     POP_TOP                         
                424     RETURN_VALUE                    
            [Exception Table]
                28 to 234 -> 384 [0] 
                234 to 296 -> 366 [1] 
                296 to 306 -> 384 [0] 
                308 to 346 -> 384 [0] 
                366 to 374 -> 378 [2] lasti
                374 to 384 -> 384 [0] 
                384 to 406 -> 406 [1] lasti
        [Code]
            File Name: <frozen program.modules.Create_bots>
            Object Name: get_message
            Qualified Name: get_message
            Arg Count: 2
            Pos Only Arg Count: 0
            KW Only Arg Count: 0
            Stack Size: 6
            Flags: 0x20000003 (CO_OPTIMIZED | CO_NEWLOCALS | CO_PYARMOR_OBFUSCATED)
            [Names]
                'time'
                'sleep'
                'random'
                'uniform'
                'iter_messages'
                'str'
                'raw_text'
                'ValueError'
            [Locals+Names]
                'client'
                'botfather'
                '__assert_armored__'
                '_var_var_38'
            [Constants]
                None
                '__pyarmor_assert_13428__'
                '__pyarmor_enter_13429__'
                b'<COAddr>\x05\x00\x00\x1a\x00\x01\x00\x00\x00\x00\x00\x00\x00\x00\x00\x00\x00\x00\x00\x00'
                1
                5
                (
                    'limit'
                )
                'Sorry, too many attempts'   # b'\x81\xd1\x17\x01!\xe3\xf2\x92\x0f\xf5\x02\x80a\xed\xf6\x9cO\\\xaf\xb3\xaf\xc6^\xd8\x16'
                'Flood'
                '__pyarmor_exit_13430__'
            [Disassembly]
                0       NOP                             
                2       NOP                             
                4       PUSH_NULL                       
                6       LOAD_CONST                      2: '__pyarmor_enter_13429__'
                8       LOAD_CONST                      3: b'<COAddr>\x05\x00\x00\x1a\x00\x01\x00\x00\x00\x00\x00\x00\x00\x00\x00\x00\x00\x00\x00\x00'
                10      BUILD_TUPLE                     1
                12      CALL_FUNCTION_EX                0
                14      POP_TOP                         
                16      RESUME                          0
                18      NOP                             
                20      NOP                             
                22      NOP                             
                24      NOP                             
                26      NOP                             
                28      LOAD_GLOBAL                     1: NULL + time
                38      LOAD_ATTR                       2: sleep
                58      LOAD_GLOBAL                     5: NULL + random
                68      LOAD_ATTR                       6: uniform
                88      LOAD_CONST                      4: 1
                90      LOAD_CONST                      5: 5
                92      CALL                            2
                100     CALL                            1
                108     POP_TOP                         
                110     LOAD_FAST                       0: client
                112     LOAD_ATTR                       9: iter_messages
                132     LOAD_FAST                       1: botfather
                134     LOAD_CONST                      4: 1
                136     KW_NAMES                        6: ('limit',)
                138     CALL                            2
                146     GET_ITER                        
                148     FOR_ITER                        54 (to 258)
                152     STORE_FAST                      3: _var_var_38
                154     PUSH_NULL                       
                156     LOAD_CONST                      1: '__pyarmor_assert_13428__'
                158     LOAD_CONST                      7: 'Sorry, too many attempts'   # b'\x81\xd1\x17\x01!\xe3\xf2\x92\x0f\xf5\x02\x80a\xed\xf6\x9cO\\\xaf\xb3\xaf\xc6^\xd8\x16'
                160     CALL                            1
                168     LOAD_GLOBAL                     11: NULL + str
                178     LOAD_FAST                       3: _var_var_38
                180     LOAD_ATTR                       12: raw_text
                200     CALL                            1
                208     CONTAINS_OP                     0 (in)
                210     POP_JUMP_IF_FALSE               11 (to 234)
                212     LOAD_GLOBAL                     15: NULL + ValueError
                222     LOAD_CONST                      8: 'Flood'
                224     CALL                            1
                232     RAISE_VARARGS                   1
                234     LOAD_FAST                       3: _var_var_38
                236     SWAP                            2
                238     POP_TOP                         
                240     NOP                             
                242     NOP                             
                244     NOP                             
                246     JUMP_FORWARD                    31 (to 310)
                248     CALL                            1
                256     POP_TOP                         
                258     RETURN_VALUE                    
                260     END_FOR                         
                262     LOAD_CONST                      0: None
                264     NOP                             
                266     NOP                             
                268     NOP                             
                270     JUMP_FORWARD                    19 (to 310)
                278     POP_TOP                         
                280     RETURN_CONST                    0: None
                282     PUSH_EXC_INFO                   
                284     PUSH_NULL                       
                286     LOAD_CONST                      9: '__pyarmor_exit_13430__'
                288     NOP                             
                290     LOAD_CONST                      3: b'<COAddr>\x05\x00\x00\x1a\x00\x01\x00\x00\x00\x00\x00\x00\x00\x00\x00\x00\x00\x00\x00\x00'
                292     CALL                            1
                300     POP_TOP                         
                302     RERAISE                         0
                304     COPY                            3
                306     POP_EXCEPT                      
                308     RERAISE                         1
                310     PUSH_NULL                       
                312     LOAD_CONST                      9: '__pyarmor_exit_13430__'
                314     LOAD_CONST                      3: b'<COAddr>\x05\x00\x00\x1a\x00\x01\x00\x00\x00\x00\x00\x00\x00\x00\x00\x00\x00\x00\x00\x00'
                316     BUILD_TUPLE                     1
                318     CALL_FUNCTION_EX                0
                320     POP_TOP                         
                322     RETURN_VALUE                    
            [Exception Table]
                28 to 240 -> 282 [0] 
                260 to 262 -> 282 [0] 
                282 to 304 -> 304 [1] lasti
        '__pyarmor_exit_13409__'
        (
            0
        )
    [Disassembly]
        0       NOP                             
        2       NOP                             
        4       PUSH_NULL                       
        6       LOAD_CONST                      1: '__pyarmor_enter_13408__'
        8       LOAD_CONST                      2: b'<COAddr>\x05\x00\x00\x1ax\x01\x00\x00\x00\x00\x00\x00\x00\x00\x00\x00\x00\x00\x00\x00'
        10      BUILD_TUPLE                     1
        12      CALL_FUNCTION_EX                0
        14      POP_TOP                         
        16      RESUME                          0
        18      NOP                             
        20      NOP                             
        22      NOP                             
        24      NOP                             
        26      LOAD_CONST                      3: 0
        28      LOAD_CONST                      4: None
        30      IMPORT_NAME                     1: eel
        32      STORE_NAME                      1: eel
        34      LOAD_CONST                      3: 0
        36      LOAD_CONST                      4: None
        38      IMPORT_NAME                     2: re
        40      STORE_NAME                      2: re
        42      LOAD_CONST                      3: 0
        44      LOAD_CONST                      4: None
        46      IMPORT_NAME                     3: spintax
        48      STORE_NAME                      3: spintax
        50      LOAD_CONST                      3: 0
        52      LOAD_CONST                      4: None
        54      IMPORT_NAME                     4: json
        56      STORE_NAME                      4: json
        58      LOAD_CONST                      3: 0
        60      LOAD_CONST                      4: None
        62      IMPORT_NAME                     5: time
        64      STORE_NAME                      5: time
        66      LOAD_CONST                      3: 0
        68      LOAD_CONST                      4: None
        70      IMPORT_NAME                     6: string
        72      STORE_NAME                      6: string
        74      LOAD_CONST                      3: 0
        76      LOAD_CONST                      4: None
        78      IMPORT_NAME                     7: datetime
        80      STORE_NAME                      7: datetime
        82      LOAD_CONST                      3: 0
        84      LOAD_CONST                      4: None
        86      IMPORT_NAME                     8: random
        88      STORE_NAME                      8: random
        90      LOAD_CONST                      3: 0
        92      LOAD_CONST                      4: None
        94      IMPORT_NAME                     9: concurrent.futures
        96      STORE_NAME                      10: concurrent
        98      LOAD_CONST                      3: 0
        100     LOAD_CONST                      5: ('Thread', 'Event', 'Lock')
        102     IMPORT_NAME                     11: threading
        104     IMPORT_FROM                     12: Thread
        106     STORE_NAME                      12: Thread
        108     IMPORT_FROM                     13: Event
        110     STORE_NAME                      13: Event
        112     IMPORT_FROM                     14: Lock
        114     STORE_NAME                      14: Lock
        116     POP_TOP                         
        118     LOAD_CONST                      3: 0
        120     LOAD_CONST                      6: ('cycle',)
        122     IMPORT_NAME                     15: itertools
        124     IMPORT_FROM                     16: cycle
        126     STORE_NAME                      16: cycle
        128     POP_TOP                         
        130     LOAD_CONST                      3: 0
        132     LOAD_CONST                      7: ('functions', 'errors')
        134     IMPORT_NAME                     17: multithon.sync
        136     IMPORT_FROM                     18: functions
        138     STORE_NAME                      18: functions
        140     IMPORT_FROM                     19: errors
        142     STORE_NAME                      19: errors
        144     POP_TOP                         
        146     LOAD_CONST                      3: 0
        148     LOAD_CONST                      8: ('StopProgram',)
        150     IMPORT_NAME                     20: multithon.errors
        152     IMPORT_FROM                     21: StopProgram
        154     STORE_NAME                      21: StopProgram
        156     POP_TOP                         
        158     LOAD_CONST                      3: 0
        160     LOAD_CONST                      9: ('GetLang',)
        162     IMPORT_NAME                     22: program.static_classes
        164     IMPORT_FROM                     23: GetLang
        166     STORE_NAME                      23: GetLang
        168     POP_TOP                         
        170     LOAD_CONST                      3: 0
        172     LOAD_CONST                      10: ('Logs',)
        174     IMPORT_NAME                     22: program.static_classes
        176     IMPORT_FROM                     24: Logs
        178     STORE_NAME                      24: Logs
        180     POP_TOP                         
        182     LOAD_CONST                      3: 0
        184     LOAD_CONST                      11: ('logging',)
        186     IMPORT_NAME                     22: program.static_classes
        188     IMPORT_FROM                     25: logging
        190     STORE_NAME                      25: logging
        192     POP_TOP                         
        194     LOAD_CONST                      3: 0
        196     LOAD_CONST                      12: ('memory_check_switcher',)
        198     IMPORT_NAME                     22: program.static_classes
        200     IMPORT_FROM                     26: memory_check_switcher
        202     STORE_NAME                      26: memory_check_switcher
        204     POP_TOP                         
        206     LOAD_CONST                      3: 0
        208     LOAD_CONST                      13: ('memory_set_pid',)
        210     IMPORT_NAME                     22: program.static_classes
        212     IMPORT_FROM                     27: memory_set_pid
        214     STORE_NAME                      27: memory_set_pid
        216     POP_TOP                         
        218     LOAD_CONST                      3: 0
        220     LOAD_CONST                      14: ('DelayOnline',)
        222     IMPORT_NAME                     28: program.telegram
        224     IMPORT_FROM                     29: DelayOnline
        226     STORE_NAME                      29: DelayOnline
        228     POP_TOP                         
        230     LOAD_CONST                      3: 0
        232     LOAD_CONST                      15: ('Disconnect',)
        234     IMPORT_NAME                     28: program.telegram
        236     IMPORT_FROM                     30: Disconnect
        238     STORE_NAME                      30: Disconnect
        240     POP_TOP                         
        242     LOAD_CONST                      3: 0
        244     LOAD_CONST                      16: ('Thread_wait',)
        246     IMPORT_NAME                     28: program.telegram
        248     IMPORT_FROM                     31: Thread_wait
        250     STORE_NAME                      31: Thread_wait
        252     POP_TOP                         
        254     LOAD_CONST                      3: 0
        256     LOAD_CONST                      17: ('account_works',)
        258     IMPORT_NAME                     28: program.telegram
        260     IMPORT_FROM                     32: account_works
        262     STORE_NAME                      32: account_works
        264     POP_TOP                         
        266     LOAD_CONST                      3: 0
        268     LOAD_CONST                      18: ('GetConfig',)
        270     IMPORT_NAME                     33: program.general
        272     IMPORT_FROM                     34: GetConfig
        274     STORE_NAME                      34: GetConfig
        276     POP_TOP                         
        278     LOAD_CONST                      3: 0
        280     LOAD_CONST                      19: ('GetProxy',)
        282     IMPORT_NAME                     33: program.general
        284     IMPORT_FROM                     35: GetProxy
        286     STORE_NAME                      35: GetProxy
        288     POP_TOP                         
        290     LOAD_CONST                      3: 0
        292     LOAD_CONST                      20: ('StopDetect',)
        294     IMPORT_NAME                     33: program.general
        296     IMPORT_FROM                     36: StopDetect
        298     STORE_NAME                      36: StopDetect
        300     POP_TOP                         
        302     LOAD_CONST                      3: 0
        304     LOAD_CONST                      21: ('del_task_manager',)
        306     IMPORT_NAME                     33: program.general
        308     IMPORT_FROM                     37: del_task_manager
        310     STORE_NAME                      37: del_task_manager
        312     POP_TOP                         
        314     LOAD_CONST                      3: 0
        316     LOAD_CONST                      22: ('set_task_manager',)
        318     IMPORT_NAME                     33: program.general
        320     IMPORT_FROM                     38: set_task_manager
        322     STORE_NAME                      38: set_task_manager
        324     POP_TOP                         
        326     LOAD_CONST                      3: 0
        328     LOAD_CONST                      23: ('db_create_bots',)
        330     IMPORT_NAME                     39: program.database
        332     IMPORT_FROM                     40: db_create_bots
        334     STORE_NAME                      40: db_create_bots
        336     POP_TOP                         
        338     LOAD_CONST                      24: <CODE> Create_bots
        340     MAKE_FUNCTION                   0
        342     STORE_NAME                      41: Create_bots
        344     LOAD_CONST                      25: <CODE> START
        346     MAKE_FUNCTION                   0
        348     STORE_NAME                      42: START
        350     LOAD_CONST                      26: <CODE> worker
        352     MAKE_FUNCTION                   0
        354     STORE_NAME                      43: worker
        356     LOAD_CONST                      27: <CODE> username_generator
        358     MAKE_FUNCTION                   0
        360     STORE_NAME                      44: username_generator
        362     LOAD_CONST                      28: <CODE> modify_username
        364     MAKE_FUNCTION                   0
        366     STORE_NAME                      45: modify_username
        368     LOAD_CONST                      32: (0,)
        370     LOAD_CONST                      29: <CODE> button_click
        372     MAKE_FUNCTION                   1
        374     STORE_NAME                      46: button_click
        376     LOAD_CONST                      30: <CODE> get_message
        378     MAKE_FUNCTION                   0
        380     STORE_NAME                      47: get_message
        382     LOAD_CONST                      4: None
        384     NOP                             
        386     NOP                             
        388     NOP                             
        390     JUMP_FORWARD                    19 (to 430)
        398     POP_TOP                         
        400     RETURN_CONST                    4: None
        402     PUSH_EXC_INFO                   
        404     PUSH_NULL                       
        406     LOAD_CONST                      31: '__pyarmor_exit_13409__'
        408     NOP                             
        410     LOAD_CONST                      2: b'<COAddr>\x05\x00\x00\x1ax\x01\x00\x00\x00\x00\x00\x00\x00\x00\x00\x00\x00\x00\x00\x00'
        412     CALL                            1
        420     POP_TOP                         
        422     RERAISE                         0
        424     COPY                            3
        426     POP_EXCEPT                      
        428     RERAISE                         1
        430     PUSH_NULL                       
        432     LOAD_CONST                      31: '__pyarmor_exit_13409__'
        434     LOAD_CONST                      2: b'<COAddr>\x05\x00\x00\x1ax\x01\x00\x00\x00\x00\x00\x00\x00\x00\x00\x00\x00\x00\x00\x00'
        436     BUILD_TUPLE                     1
        438     CALL_FUNCTION_EX                0
        440     POP_TOP                         
        442     RETURN_VALUE                    
    [Exception Table]
        26 to 382 -> 402 [0] 
        402 to 424 -> 424 [1] lasti
