#decoded by lolz.live/mrpenny / t.me/zeus_jackpot
# ================================
# Примечания по Pyarmor:
# - Байт-код и объекты кода Pyarmor соответствуют стандартному Python, но присутствуют специальные вызовы функций среды выполнения (runtime) Pyarmor.
# - Вызовы строк — это не ошибки, а маркеры, которые обрабатываются Pyarmor во время выполнения.
#
# Руководство по декомпиляции (без среды выполнения):
# 1. Игнорируйте зашифрованные байты после `#`; используйте только строку до `#`.
# 2. Удалите "__pyarmor_enter_xxx__"(b"<COAddr>...") и "__pyarmor_leave_xxx__"(b"<COAddr>...") (пролог/эпилог).
# 3. "__pyarmor_assert_xxx__"(A) не является настоящим оператором assert.
#    - Если A — это имя или читаемая строка: замените на A.
#    - Если A — это (X, "Y"): замените на X.Y.
#    - Если A — это (X, "Y", Z): замените на X.Y = Z.
#    - В противном случае: выберите наиболее подходящую/логичную замену.
# 4. "__pyarmor_bcc_xxx__"(...) указывает на машинный (нативный) код; тело функции недоступно. Добавьте комментарий.
# ================================

[Code]
    File Name: <frozen program.modules.Edit_messages>
    Object Name: <module>
    Qualified Name: <module>
    Arg Count: 0
    Pos Only Arg Count: 0
    KW Only Arg Count: 0
    Stack Size: 5
    Flags: 0x20000000 (CO_PYARMOR_OBFUSCATED)
    [Names]
        '__assert_armored__'
        'eel'
        'json'
        'time'
        'datetime'
        'concurrent.futures'
        'concurrent'
        'threading'
        'Thread'
        'Event'
        'multithon.sync'
        'functions'
        'errors'
        'multithon.errors'
        'StopProgram'
        'program.static_classes'
        'GetLang'
        'Logs'
        'check_module'
        'logging'
        'memory_check_switcher'
        'memory_set_pid'
        'program.telegram'
        'DelayOnline'
        'Disconnect'
        'Thread_wait'
        'account_works'
        'entity'
        'program.general'
        'GetConfig'
        'GetProxy'
        'StopDetect'
        'check_get_settings'
        'del_task_manager'
        'set_task_manager'
        'func.sender'
        'TelegramEditMessage'
        'program.database'
        'db_edit_message'
        'Edit_messages'
        'START'
        'worker'
        'get_full_channel'
    [Locals+Names]
    [Constants]
        '__pyarmor_assert_13602__'
        '__pyarmor_enter_13603__'
        b'<COAddr>\x07\x00\x00\x1ad\x01\x00\x00\x00\x00\x00\x00\x00\x00\x00\x00\x00\x00\x00\x00'
        0
        None
        (
            'Thread'
            'Event'
        )
        (
            'functions'
            'errors'
        )
        (
            'StopProgram'
        )
        (
            'GetLang'
        )
        (
            'Logs'
        )
        (
            'check_module'
        )
        (
            'logging'
        )
        (
            'memory_check_switcher'
        )
        (
            'memory_set_pid'
        )
        (
            'DelayOnline'
        )
        (
            'Disconnect'
        )
        (
            'Thread_wait'
        )
        (
            'account_works'
        )
        (
            'entity'
        )
        (
            'GetConfig'
        )
        (
            'GetProxy'
        )
        (
            'StopDetect'
        )
        (
            'check_get_settings'
        )
        (
            'del_task_manager'
        )
        (
            'set_task_manager'
        )
        1
        (
            'TelegramEditMessage'
        )
        (
            'db_edit_message'
        )
        [Code]
            File Name: <frozen program.modules.Edit_messages>
            Object Name: Edit_messages
            Qualified Name: Edit_messages
            Arg Count: 1
            Pos Only Arg Count: 0
            KW Only Arg Count: 0
            Stack Size: 8
            Flags: 0x20000003 (CO_OPTIMIZED | CO_NEWLOCALS | CO_PYARMOR_OBFUSCATED)
            [Names]
                'GetConfig'
                'config'
                'GetLang'
                'Lang'
                'GetProxy'
                'eel'
                'sendSuccessBox'
                'memory_check_switcher'
                'check_module'
                'sendErrorBox'
                'Event'
                'memory_set_pid'
                'Thread'
                'START'
                'start'
                'Logs'
                'WaitStopAnsfer'
                'UpdateLogInWindow'
                'BaseException'
                'logging'
            [Locals+Names]
                'data'
                '__assert_armored__'
                '_var_var_0'
                '_var_var_1'
                '_var_var_2'
                '_var_var_3'
            [Constants]
                None
                '__pyarmor_assert_13605__'
                '__pyarmor_enter_13606__'
                b'<COAddr>\x05\x00\x00\x1a\xe2\x02\x00\x00\x00\x00\x00\x00\x00\x00\x00\x00\x00\x00\x00\x00'
                'program_running'   # b'\x81\xf2\n\x1c4\xe8\xbf\xdf$\xe8\x18\xceb\xe5\xf6\x82'
                '__pyarmor_exit_13607__'
                False
                'gpt'
                True
                11
                'gpt_not_activate'   # b'\x81\xe5\x08\x07\x0c\xf4\xb1\xc6$\xfb\x0e\xd4e\xfa\xf9\x91\n'
                (
                    'target'
                    'args'
                )
                (
                    'target'
                    'args'
                    'daemon'
                )
            [Disassembly]
                0       NOP                             
                2       NOP                             
                4       PUSH_NULL                       
                6       LOAD_CONST                      2: '__pyarmor_enter_13606__'
                8       LOAD_CONST                      3: b'<COAddr>\x05\x00\x00\x1a\xe2\x02\x00\x00\x00\x00\x00\x00\x00\x00\x00\x00\x00\x00\x00\x00'
                10      BUILD_TUPLE                     1
                12      CALL_FUNCTION_EX                0
                14      POP_TOP                         
                16      RESUME                          0
                18      NOP                             
                20      NOP                             
                22      NOP                             
                24      NOP                             
                26      NOP                             
                28      NOP                             
                30      LOAD_GLOBAL                     1: NULL + GetConfig
                40      CALL                            0
                48      STORE_GLOBAL                    1: config
                50      LOAD_GLOBAL                     5: NULL + GetLang
                60      LOAD_GLOBAL                     2: config
                70      CALL                            1
                78      STORE_GLOBAL                    3: Lang
                80      LOAD_GLOBAL                     9: NULL + GetProxy
                90      CALL                            0
                98      STORE_FAST                      2: _var_var_0
                100     LOAD_GLOBAL                     11: NULL + eel
                110     LOAD_ATTR                       12: sendSuccessBox
                130     LOAD_GLOBAL                     6: Lang
                140     PUSH_NULL                       
                142     LOAD_CONST                      1: '__pyarmor_assert_13605__'
                144     LOAD_CONST                      4: 'program_running'   # b'\x81\xf2\n\x1c4\xe8\xbf\xdf$\xe8\x18\xceb\xe5\xf6\x82'
                146     CALL                            1
                154     BINARY_SUBSCR                   
                158     CALL                            1
                166     POP_TOP                         
                168     LOAD_GLOBAL                     15: NULL + memory_check_switcher
                178     CALL                            0
                186     POP_JUMP_IF_TRUE                11 (to 210)
                188     NOP                             
                190     LOAD_CONST                      6: False
                192     NOP                             
                194     NOP                             
                196     JUMP_FORWARD                    296 (to 792)
                206     POP_TOP                         
                208     RETURN_CONST                    6: False
                210     LOAD_GLOBAL                     2: config
                220     LOAD_CONST                      7: 'gpt'
                222     BINARY_SUBSCR                   
                226     LOAD_CONST                      8: True
                228     COMPARE_OP                      40 (==)
                232     POP_JUMP_IF_FALSE               59 (to 352)
                234     LOAD_GLOBAL                     17: NULL + check_module
                244     LOAD_CONST                      9: 11
                246     CALL                            1
                254     LOAD_CONST                      6: False
                256     COMPARE_OP                      40 (==)
                260     POP_JUMP_IF_FALSE               45 (to 352)
                262     LOAD_GLOBAL                     11: NULL + eel
                272     LOAD_ATTR                       18: sendErrorBox
                292     LOAD_GLOBAL                     6: Lang
                302     PUSH_NULL                       
                304     LOAD_CONST                      1: '__pyarmor_assert_13605__'
                306     LOAD_CONST                      10: 'gpt_not_activate'   # b'\x81\xe5\x08\x07\x0c\xf4\xb1\xc6$\xfb\x0e\xd4e\xfa\xf9\x91\n'
                308     CALL                            1
                316     BINARY_SUBSCR                   
                320     CALL                            1
                328     POP_TOP                         
                330     NOP                             
                332     LOAD_CONST                      6: False
                334     NOP                             
                336     NOP                             
                338     NOP                             
                340     JUMP_FORWARD                    225 (to 792)
                348     POP_TOP                         
                350     RETURN_CONST                    6: False
                352     LOAD_GLOBAL                     21: NULL + Event
                362     CALL                            0
                370     STORE_FAST                      3: _var_var_1
                372     LOAD_GLOBAL                     23: NULL + memory_set_pid
                382     CALL                            0
                390     STORE_FAST                      4: _var_var_2
                392     LOAD_GLOBAL                     25: NULL + Thread
                402     LOAD_GLOBAL                     26: START
                412     LOAD_FAST                       0: data
                414     LOAD_GLOBAL                     2: config
                424     LOAD_FAST                       4: _var_var_2
                426     LOAD_FAST                       2: _var_var_0
                428     LOAD_FAST                       3: _var_var_1
                430     BUILD_TUPLE                     5
                432     KW_NAMES                        11: ('target', 'args')
                434     CALL                            2
                442     LOAD_ATTR                       29: start
                462     CALL                            0
                470     POP_TOP                         
                472     LOAD_GLOBAL                     25: NULL + Thread
                482     LOAD_GLOBAL                     30: Logs
                492     LOAD_ATTR                       32: WaitStopAnsfer
                512     LOAD_GLOBAL                     2: config
                522     LOAD_FAST                       4: _var_var_2
                524     LOAD_FAST                       3: _var_var_1
                526     BUILD_TUPLE                     3
                528     LOAD_CONST                      8: True
                530     KW_NAMES                        12: ('target', 'args', 'daemon')
                532     CALL                            3
                540     LOAD_ATTR                       29: start
                560     CALL                            0
                568     POP_TOP                         
                570     LOAD_GLOBAL                     25: NULL + Thread
                580     LOAD_GLOBAL                     30: Logs
                590     LOAD_ATTR                       34: UpdateLogInWindow
                610     LOAD_GLOBAL                     2: config
                620     LOAD_FAST                       4: _var_var_2
                622     LOAD_FAST                       3: _var_var_1
                624     BUILD_TUPLE                     3
                626     LOAD_CONST                      8: True
                628     KW_NAMES                        12: ('target', 'args', 'daemon')
                630     CALL                            3
                638     LOAD_ATTR                       29: start
                658     CALL                            0
                666     POP_TOP                         
                668     LOAD_CONST                      0: None
                670     NOP                             
                672     NOP                             
                674     NOP                             
                676     JUMP_FORWARD                    57 (to 792)
                684     POP_TOP                         
                686     RETURN_CONST                    0: None
                688     PUSH_EXC_INFO                   
                690     LOAD_GLOBAL                     36: BaseException
                700     CHECK_EXC_MATCH                 
                702     POP_JUMP_IF_FALSE               26 (to 756)
                704     STORE_FAST                      5: _var_var_3
                706     PUSH_NULL                       
                708     LOAD_GLOBAL                     39: NULL + logging
                718     LOAD_FAST                       5: _var_var_3
                720     CALL                            1
                728     CALL                            0
                736     POP_TOP                         
                738     POP_EXCEPT                      
                740     LOAD_CONST                      0: None
                742     STORE_FAST                      5: _var_var_3
                744     DELETE_FAST                     5: _var_var_3
                746     JUMP_BACKWARD                   40 (to 668)
                748     LOAD_CONST                      0: None
                750     STORE_FAST                      5: _var_var_3
                752     DELETE_FAST                     5: _var_var_3
                754     RERAISE                         1
                756     RERAISE                         0
                758     COPY                            3
                760     POP_EXCEPT                      
                762     RERAISE                         1
                764     PUSH_EXC_INFO                   
                766     PUSH_NULL                       
                768     LOAD_CONST                      5: '__pyarmor_exit_13607__'
                770     NOP                             
                772     LOAD_CONST                      3: b'<COAddr>\x05\x00\x00\x1a\xe2\x02\x00\x00\x00\x00\x00\x00\x00\x00\x00\x00\x00\x00\x00\x00'
                774     CALL                            1
                782     POP_TOP                         
                784     RERAISE                         0
                786     COPY                            3
                788     POP_EXCEPT                      
                790     RERAISE                         1
                792     PUSH_NULL                       
                794     LOAD_CONST                      5: '__pyarmor_exit_13607__'
                796     LOAD_CONST                      3: b'<COAddr>\x05\x00\x00\x1a\xe2\x02\x00\x00\x00\x00\x00\x00\x00\x00\x00\x00\x00\x00\x00\x00'
                798     BUILD_TUPLE                     1
                800     CALL_FUNCTION_EX                0
                802     POP_TOP                         
                804     RETURN_VALUE                    
            [Exception Table]
                30 to 188 -> 688 [0] 
                210 to 330 -> 688 [0] 
                352 to 668 -> 688 [0] 
                688 to 706 -> 758 [1] lasti
                706 to 738 -> 748 [1] lasti
                738 to 748 -> 764 [0] 
                748 to 758 -> 758 [1] lasti
                758 to 764 -> 764 [0] 
                764 to 786 -> 786 [1] lasti
        [Code]
            File Name: <frozen program.modules.Edit_messages>
            Object Name: START
            Qualified Name: START
            Arg Count: 5
            Pos Only Arg Count: 0
            KW Only Arg Count: 0
            Stack Size: 14
            Flags: 0x20000003 (CO_OPTIMIZED | CO_NEWLOCALS | CO_PYARMOR_OBFUSCATED)
            [Names]
                'check_get_settings'
                'get'
                'isinstance'
                'list'
                'int'
                'len'
                'eel'
                'sendErrorBox'
                'Lang'
                'StopProgram'
                'datetime'
                'now'
                'strftime'
                'db_edit_message'
                'create'
                'WriteResult'
                'set_task_manager'
                'concurrent'
                'futures'
                'ThreadPoolExecutor'
                'StreamStat'
                'json'
                'dumps'
                'append'
                'submit'
                'worker'
                'as_completed'
                'BaseException'
                'logging'
                'del_task_manager'
                'StopDetect'
            [Locals+Names]
                'data'
                'config'
                'pid'
                'proxy'
                'stop_thread'
                '__assert_armored__'
                '_var_var_4'
                '_var_var_5'
                '_var_var_6'
                '_var_var_7'
                '_var_var_8'
                '_var_var_9'
                '_var_var_10'
                '_var_var_11'
                '_var_var_12'
                '_var_var_13'
                '_var_var_14'
                '_var_var_15'
                '_var_var_3'
            [Constants]
                None
                '__pyarmor_assert_13608__'
                '__pyarmor_enter_13609__'
                b'<COAddr>\x07\x00\x00\x1a\xce\x05\x00\x00\x00\x00\x00\x00\x00\x00\x00\x00\x00\x00\x00\x00'
                'Settings'
                'Accounts'
                1
                'select_accounts_works'   # b'\x81\xf1\x1d\x1f6\xf9\xaa\xed\x1a\xf9\x0e\xcfy\xe2\xec\x960J\xb4\xb5\xa1\xd8'
                'thread_rules'   # b'\x81\xf6\x10\x016\xfb\xba\xed\t\xef\x01\xc5\x7f'
                True
                'thread_count'   # b'\x81\xf6\x10\x016\xfb\xba\xed\x18\xf5\x18\xcex'
                '%Y-%m-%d_%H-%M-%S'   # b'\x81\xa7!^v\xf7\xf3\x97\x1f\xc5H\xe8!\xa9\xd5\xc8Jn'
                'additives/edit_messages/'   # b'\x81\xe3\x1c\x17:\xee\xb7\xc4\x1e\xe9B\xc5h\xe5\xec\xba\x02X\xa8\xb4\xab\xccK\xdfJ'
                '_edit_messages.db'   # b'\x81\xdd\x1d\x17:\xee\x81\xdf\x1e\xe9\x1e\xc1k\xe9\xeb\xcb\x0b_'
                'Statistic'   # b"\x81\xd1\x0c\x12'\xf3\xad\xc6\x12\xf9"
                'edit_messages'   # b"\x81\xe7\x1c\x1a'\xc5\xb3\xd7\x08\xe9\x0c\xc7i\xff"
                'stuff'
                (
                    'accounts'
                    'name'
                )
                (
                    'max_workers'
                )
                0
                'st_task'
                'st_stream'   # b'\x81\xf1\x0c, \xee\xac\xd7\x1a\xf7'
                'st_wait'
                'st_done'
                '__pyarmor_exit_13610__'
                'Done'
            [Disassembly]
                0       NOP                             
                2       NOP                             
                4       PUSH_NULL                       
                6       LOAD_CONST                      2: '__pyarmor_enter_13609__'
                8       LOAD_CONST                      3: b'<COAddr>\x07\x00\x00\x1a\xce\x05\x00\x00\x00\x00\x00\x00\x00\x00\x00\x00\x00\x00\x00\x00'
                10      BUILD_TUPLE                     1
                12      CALL_FUNCTION_EX                0
                14      POP_TOP                         
                16      RESUME                          0
                18      NOP                             
                20      NOP                             
                22      NOP                             
                24      NOP                             
                26      NOP                             
                28      NOP                             
                30      LOAD_GLOBAL                     1: NULL + check_get_settings
                40      LOAD_FAST                       0: data
                42      LOAD_ATTR                       3: get
                62      LOAD_CONST                      4: 'Settings'
                64      CALL                            1
                72      CALL                            1
                80      POP_TOP                         
                82      LOAD_FAST                       0: data
                84      LOAD_CONST                      5: 'Accounts'
                86      BINARY_SUBSCR                   
                90      STORE_FAST                      6: _var_var_4
                92      LOAD_GLOBAL                     5: NULL + isinstance
                102     LOAD_FAST                       6: _var_var_4
                104     LOAD_GLOBAL                     6: list
                114     CALL                            2
                122     POP_JUMP_IF_TRUE                3 (to 130)
                124     LOAD_FAST                       6: _var_var_4
                126     BUILD_LIST                      1
                128     STORE_FAST                      6: _var_var_4
                130     LOAD_GLOBAL                     9: NULL + int
                140     LOAD_GLOBAL                     11: NULL + len
                150     LOAD_FAST                       6: _var_var_4
                152     CALL                            1
                160     CALL                            1
                168     LOAD_CONST                      6: 1
                170     COMPARE_OP                      2 (<)
                174     POP_JUMP_IF_FALSE               44 (to 264)
                176     LOAD_GLOBAL                     13: NULL + eel
                186     LOAD_ATTR                       14: sendErrorBox
                206     LOAD_GLOBAL                     16: Lang
                216     PUSH_NULL                       
                218     LOAD_CONST                      1: '__pyarmor_assert_13608__'
                220     LOAD_CONST                      7: 'select_accounts_works'   # b'\x81\xf1\x1d\x1f6\xf9\xaa\xed\x1a\xf9\x0e\xcfy\xe2\xec\x960J\xb4\xb5\xa1\xd8'
                222     CALL                            1
                230     BINARY_SUBSCR                   
                234     CALL                            1
                242     POP_TOP                         
                244     LOAD_GLOBAL                     19: NULL + StopProgram
                254     CALL                            0
                262     RAISE_VARARGS                   1
                264     LOAD_FAST                       0: data
                266     LOAD_CONST                      4: 'Settings'
                268     BINARY_SUBSCR                   
                272     LOAD_ATTR                       3: get
                292     PUSH_NULL                       
                294     LOAD_CONST                      1: '__pyarmor_assert_13608__'
                296     LOAD_CONST                      8: 'thread_rules'   # b'\x81\xf6\x10\x016\xfb\xba\xed\t\xef\x01\xc5\x7f'
                298     CALL                            1
                306     CALL                            1
                314     LOAD_CONST                      9: True
                316     COMPARE_OP                      40 (==)
                320     POP_JUMP_IF_FALSE               36 (to 394)
                322     LOAD_GLOBAL                     9: NULL + int
                332     LOAD_FAST                       0: data
                334     LOAD_CONST                      4: 'Settings'
                336     BINARY_SUBSCR                   
                340     LOAD_ATTR                       3: get
                360     PUSH_NULL                       
                362     LOAD_CONST                      1: '__pyarmor_assert_13608__'
                364     LOAD_CONST                      10: 'thread_count'   # b'\x81\xf6\x10\x016\xfb\xba\xed\x18\xf5\x18\xcex'
                366     CALL                            1
                374     CALL                            1
                382     CALL                            1
                390     STORE_FAST                      7: _var_var_5
                392     JUMP_FORWARD                    11 (to 416)
                394     LOAD_FAST                       1: config
                396     PUSH_NULL                       
                398     LOAD_CONST                      1: '__pyarmor_assert_13608__'
                400     LOAD_CONST                      10: 'thread_count'   # b'\x81\xf6\x10\x016\xfb\xba\xed\x18\xf5\x18\xcex'
                402     CALL                            1
                410     BINARY_SUBSCR                   
                414     STORE_FAST                      7: _var_var_5
                416     LOAD_GLOBAL                     20: datetime
                426     LOAD_ATTR                       20: datetime
                446     LOAD_ATTR                       23: now
                466     CALL                            0
                474     LOAD_ATTR                       25: strftime
                494     PUSH_NULL                       
                496     LOAD_CONST                      1: '__pyarmor_assert_13608__'
                498     LOAD_CONST                      11: '%Y-%m-%d_%H-%M-%S'   # b'\x81\xa7!^v\xf7\xf3\x97\x1f\xc5H\xe8!\xa9\xd5\xc8Jn'
                500     CALL                            1
                508     CALL                            1
                516     STORE_FAST                      8: _var_var_6
                518     LOAD_GLOBAL                     27: NULL + db_edit_message
                528     PUSH_NULL                       
                530     LOAD_CONST                      1: '__pyarmor_assert_13608__'
                532     LOAD_CONST                      12: 'additives/edit_messages/'   # b'\x81\xe3\x1c\x17:\xee\xb7\xc4\x1e\xe9B\xc5h\xe5\xec\xba\x02X\xa8\xb4\xab\xccK\xdfJ'
                534     CALL                            1
                542     LOAD_FAST                       8: _var_var_6
                544     FORMAT_VALUE                    0 (FVC_NONE)
                546     PUSH_NULL                       
                548     LOAD_CONST                      1: '__pyarmor_assert_13608__'
                550     LOAD_CONST                      13: '_edit_messages.db'   # b'\x81\xdd\x1d\x17:\xee\x81\xdf\x1e\xe9\x1e\xc1k\xe9\xeb\xcb\x0b_'
                552     CALL                            1
                560     BUILD_STRING                    3
                562     CALL                            1
                570     LOAD_ATTR                       29: create
                590     CALL                            0
                598     STORE_FAST                      9: _var_var_7
                600     LOAD_GLOBAL                     13: NULL + eel
                610     LOAD_ATTR                       30: WriteResult
                630     PUSH_NULL                       
                632     LOAD_CONST                      1: '__pyarmor_assert_13608__'
                634     LOAD_CONST                      14: 'Statistic'   # b"\x81\xd1\x0c\x12'\xf3\xad\xc6\x12\xf9"
                636     CALL                            1
                644     PUSH_NULL                       
                646     LOAD_CONST                      1: '__pyarmor_assert_13608__'
                648     LOAD_CONST                      15: 'edit_messages'   # b"\x81\xe7\x1c\x1a'\xc5\xb3\xd7\x08\xe9\x0c\xc7i\xff"
                650     CALL                            1
                658     LOAD_FAST                       8: _var_var_6
                660     FORMAT_VALUE                    0 (FVC_NONE)
                662     PUSH_NULL                       
                664     LOAD_CONST                      1: '__pyarmor_assert_13608__'
                666     LOAD_CONST                      13: '_edit_messages.db'   # b'\x81\xdd\x1d\x17:\xee\x81\xdf\x1e\xe9\x1e\xc1k\xe9\xeb\xcb\x0b_'
                668     CALL                            1
                676     BUILD_STRING                    2
                678     CALL                            3
                686     POP_TOP                         
                688     LOAD_GLOBAL                     33: NULL + set_task_manager
                698     LOAD_FAST                       2: pid
                700     LOAD_FAST                       6: _var_var_4
                702     LOAD_FAST                       0: data
                704     LOAD_CONST                      16: 'stuff'
                706     BINARY_SUBSCR                   
                710     KW_NAMES                        17: ('accounts', 'name')
                712     CALL                            3
                720     POP_TOP                         
                722     LOAD_GLOBAL                     34: concurrent
                732     LOAD_ATTR                       36: futures
                752     LOAD_ATTR                       39: ThreadPoolExecutor
                772     LOAD_FAST                       7: _var_var_5
                774     KW_NAMES                        18: ('max_workers',)
                776     CALL                            1
                784     BEFORE_WITH                     
                786     STORE_FAST                      10: _var_var_8
                788     BUILD_LIST                      0
                790     STORE_FAST                      11: _var_var_9
                792     LOAD_GLOBAL                     11: NULL + len
                802     LOAD_FAST                       6: _var_var_4
                804     CALL                            1
                812     STORE_FAST                      12: _var_var_10
                814     LOAD_FAST                       7: _var_var_5
                816     STORE_FAST                      13: _var_var_11
                818     LOAD_FAST                       12: _var_var_10
                820     STORE_FAST                      14: _var_var_12
                822     LOAD_CONST                      19: 0
                824     STORE_FAST                      15: _var_var_13
                826     LOAD_GLOBAL                     13: NULL + eel
                836     LOAD_ATTR                       40: StreamStat
                856     LOAD_GLOBAL                     43: NULL + json
                866     LOAD_ATTR                       44: dumps
                886     LOAD_CONST                      20: 'st_task'
                888     LOAD_FAST                       12: _var_var_10
                890     PUSH_NULL                       
                892     LOAD_CONST                      1: '__pyarmor_assert_13608__'
                894     LOAD_CONST                      21: 'st_stream'   # b'\x81\xf1\x0c, \xee\xac\xd7\x1a\xf7'
                896     CALL                            1
                904     LOAD_FAST                       13: _var_var_11
                906     LOAD_CONST                      22: 'st_wait'
                908     LOAD_FAST                       14: _var_var_12
                910     LOAD_CONST                      23: 'st_done'
                912     LOAD_FAST                       15: _var_var_13
                914     BUILD_MAP                       4
                916     CALL                            1
                924     CALL                            1
                932     POP_TOP                         
                934     LOAD_FAST                       6: _var_var_4
                936     GET_ITER                        
                938     FOR_ITER                        44 (to 1028)
                942     STORE_FAST                      16: _var_var_14
                944     LOAD_FAST                       11: _var_var_9
                946     LOAD_ATTR                       47: append
                966     LOAD_FAST                       10: _var_var_8
                968     LOAD_ATTR                       49: submit
                988     LOAD_GLOBAL                     50: worker
                998     LOAD_FAST                       16: _var_var_14
                1000    LOAD_FAST                       1: config
                1002    LOAD_FAST                       3: proxy
                1004    LOAD_FAST                       0: data
                1006    LOAD_FAST                       9: _var_var_7
                1008    LOAD_FAST                       4: stop_thread
                1010    CALL                            7
                1018    CALL                            1
                1026    POP_TOP                         
                1028    JUMP_BACKWARD                   46 (to 938)
                1030    END_FOR                         
                1032    LOAD_GLOBAL                     34: concurrent
                1042    LOAD_ATTR                       36: futures
                1062    LOAD_ATTR                       53: as_completed
                1082    LOAD_FAST                       11: _var_var_9
                1084    CALL                            1
                1092    GET_ITER                        
                1094    FOR_ITER                        66 (to 1228)
                1098    STORE_FAST                      17: _var_var_15
                1100    LOAD_FAST                       15: _var_var_13
                1102    LOAD_CONST                      6: 1
                1104    BINARY_OP                       13 (+=)
                1108    STORE_FAST                      15: _var_var_13
                1110    LOAD_FAST                       14: _var_var_12
                1112    LOAD_CONST                      6: 1
                1114    BINARY_OP                       23 (-=)
                1118    STORE_FAST                      14: _var_var_12
                1120    LOAD_GLOBAL                     13: NULL + eel
                1130    LOAD_ATTR                       40: StreamStat
                1150    LOAD_GLOBAL                     43: NULL + json
                1160    LOAD_ATTR                       44: dumps
                1180    LOAD_CONST                      20: 'st_task'
                1182    LOAD_FAST                       12: _var_var_10
                1184    PUSH_NULL                       
                1186    LOAD_CONST                      1: '__pyarmor_assert_13608__'
                1188    LOAD_CONST                      21: 'st_stream'   # b'\x81\xf1\x0c, \xee\xac\xd7\x1a\xf7'
                1190    CALL                            1
                1198    LOAD_FAST                       13: _var_var_11
                1200    LOAD_CONST                      22: 'st_wait'
                1202    LOAD_FAST                       14: _var_var_12
                1204    LOAD_CONST                      23: 'st_done'
                1206    LOAD_FAST                       15: _var_var_13
                1208    BUILD_MAP                       4
                1210    CALL                            1
                1218    CALL                            1
                1226    POP_TOP                         
                1228    JUMP_BACKWARD                   68 (to 1094)
                1230    END_FOR                         
                1232    NOP                             
                1234    LOAD_CONST                      0: None
                1236    LOAD_CONST                      0: None
                1238    LOAD_CONST                      0: None
                1240    CALL                            2
                1248    POP_TOP                         
                1250    LOAD_GLOBAL                     59: NULL + del_task_manager
                1260    LOAD_FAST                       2: pid
                1262    CALL                            1
                1270    POP_TOP                         
                1272    LOAD_GLOBAL                     61: NULL + StopDetect
                1282    LOAD_FAST                       4: stop_thread
                1284    CALL                            1
                1292    POP_TOP                         
                1294    NOP                             
                1296    LOAD_CONST                      25: 'Done'
                1298    NOP                             
                1300    NOP                             
                1302    NOP                             
                1304    JUMP_FORWARD                    117 (to 1540)
                1312    POP_TOP                         
                1314    RETURN_CONST                    25: 'Done'
                1316    PUSH_EXC_INFO                   
                1318    WITH_EXCEPT_START               
                1320    POP_JUMP_IF_TRUE                1 (to 1324)
                1322    RERAISE                         2
                1324    POP_TOP                         
                1326    POP_EXCEPT                      
                1328    POP_TOP                         
                1330    POP_TOP                         
                1332    JUMP_BACKWARD                   42 (to 1250)
                1334    COPY                            3
                1336    POP_EXCEPT                      
                1338    RERAISE                         1
                1340    PUSH_EXC_INFO                   
                1342    LOAD_GLOBAL                     18: StopProgram
                1352    CHECK_EXC_MATCH                 
                1354    POP_JUMP_IF_FALSE               3 (to 1362)
                1356    POP_TOP                         
                1358    POP_EXCEPT                      
                1360    JUMP_BACKWARD                   56 (to 1250)
                1362    LOAD_GLOBAL                     54: BaseException
                1372    CHECK_EXC_MATCH                 
                1374    POP_JUMP_IF_FALSE               26 (to 1428)
                1376    STORE_FAST                      18: _var_var_3
                1378    PUSH_NULL                       
                1380    LOAD_GLOBAL                     57: NULL + logging
                1390    LOAD_FAST                       18: _var_var_3
                1392    CALL                            1
                1400    CALL                            0
                1408    POP_TOP                         
                1410    POP_EXCEPT                      
                1412    LOAD_CONST                      0: None
                1414    STORE_FAST                      18: _var_var_3
                1416    DELETE_FAST                     18: _var_var_3
                1418    JUMP_BACKWARD                   85 (to 1250)
                1420    LOAD_CONST                      0: None
                1422    STORE_FAST                      18: _var_var_3
                1424    DELETE_FAST                     18: _var_var_3
                1426    RERAISE                         1
                1428    RERAISE                         0
                1430    COPY                            3
                1432    POP_EXCEPT                      
                1434    RERAISE                         1
                1436    PUSH_EXC_INFO                   
                1438    LOAD_GLOBAL                     59: NULL + del_task_manager
                1448    LOAD_FAST                       2: pid
                1450    CALL                            1
                1458    POP_TOP                         
                1460    LOAD_GLOBAL                     61: NULL + StopDetect
                1470    LOAD_FAST                       4: stop_thread
                1472    CALL                            1
                1480    POP_TOP                         
                1482    POP_TOP                         
                1484    POP_EXCEPT                      
                1486    LOAD_CONST                      25: 'Done'
                1488    NOP                             
                1490    NOP                             
                1492    NOP                             
                1494    JUMP_FORWARD                    22 (to 1540)
                1502    POP_TOP                         
                1504    RETURN_CONST                    25: 'Done'
                1506    COPY                            3
                1508    POP_EXCEPT                      
                1510    RERAISE                         1
                1512    PUSH_EXC_INFO                   
                1514    PUSH_NULL                       
                1516    LOAD_CONST                      24: '__pyarmor_exit_13610__'
                1518    NOP                             
                1520    LOAD_CONST                      3: b'<COAddr>\x07\x00\x00\x1a\xce\x05\x00\x00\x00\x00\x00\x00\x00\x00\x00\x00\x00\x00\x00\x00'
                1522    CALL                            1
                1530    POP_TOP                         
                1532    RERAISE                         0
                1534    COPY                            3
                1536    POP_EXCEPT                      
                1538    RERAISE                         1
                1540    PUSH_NULL                       
                1542    LOAD_CONST                      24: '__pyarmor_exit_13610__'
                1544    LOAD_CONST                      3: b'<COAddr>\x07\x00\x00\x1a\xce\x05\x00\x00\x00\x00\x00\x00\x00\x00\x00\x00\x00\x00\x00\x00'
                1546    BUILD_TUPLE                     1
                1548    CALL_FUNCTION_EX                0
                1550    POP_TOP                         
                1552    RETURN_VALUE                    
            [Exception Table]
                30 to 786 -> 1340 [0] 
                786 to 1232 -> 1316 [1] lasti
                1234 to 1250 -> 1340 [0] 
                1250 to 1294 -> 1512 [0] 
                1316 to 1326 -> 1334 [3] lasti
                1326 to 1340 -> 1340 [0] 
                1340 to 1358 -> 1430 [1] lasti
                1358 to 1362 -> 1436 [0] 
                1362 to 1378 -> 1430 [1] lasti
                1378 to 1410 -> 1420 [1] lasti
                1410 to 1420 -> 1436 [0] 
                1420 to 1430 -> 1430 [1] lasti
                1430 to 1436 -> 1436 [0] 
                1436 to 1484 -> 1506 [1] lasti
                1484 to 1486 -> 1512 [0] 
                1506 to 1512 -> 1512 [0] 
                1512 to 1534 -> 1534 [1] lasti
        [Code]
            File Name: <frozen program.modules.Edit_messages>
            Object Name: worker
            Qualified Name: worker
            Arg Count: 6
            Pos Only Arg Count: 0
            KW Only Arg Count: 0
            Stack Size: 14
            Flags: 0x20000003 (CO_OPTIMIZED | CO_NEWLOCALS | CO_PYARMOR_OBFUSCATED)
            [Names]
                'Thread_wait'
                'account_works'
                'Lang'
                'get'
                'int'
                'get_me'
                'id'
                'TelegramEditMessage'
                'get_dialogs'
                'is_set'
                'StopProgram'
                'hasattr'
                'entity'
                'check'
                'get_full_channel'
                'chats'
                'iter_messages'
                'date'
                'datetime'
                'now'
                'timezone'
                'utc'
                'total_seconds'
                'sender_id'
                'edit'
                'db_edit_message'
                'insert'
                'raw_text'
                'Logs'
                'PrintLog'
                'DelayOnline'
                'BaseException'
                'logging'
                'Disconnect'
            [Locals+Names]
                'account'
                'config'
                'proxy'
                'data'
                'statistic'
                'stop_thread'
                '__assert_armored__'
                '_var_var_16'
                '_var_var_17'
                '_var_var_18'
                '_var_var_19'
                '_var_var_20'
                '_var_var_21'
                '_var_var_22'
                '_var_var_23'
                '_var_var_24'
                '_var_var_25'
                '_var_var_26'
                '_var_var_27'
                '_var_var_28'
                '_var_var_29'
                '_var_var_30'
                '_var_var_31'
                '_var_var_32'
                '_var_var_33'
                '_var_var_34'
                '_var_var_35'
                '_var_var_36'
                '_var_var_37'
                '_var_var_38'
                '_var_var_39'
                '_var_var_40'
                '_var_var_41'
                '_var_var_42'
                '_var_var_43'
                '_var_var_44'
                '_var_var_45'
                '_var_var_46'
                '_var_var_3'
            [Constants]
                None
                '__pyarmor_assert_13611__'
                '__pyarmor_enter_13612__'
                b'<COAddr>\x07\x00\x00\x1a\x1c\n\x00\x00\x00\x00\x00\x00\x00\x00\x00\x00\x00\x00\x00\x00'
                'Edit_messages'   # b"\x81\xc7\x1c\x1a'\xc5\xb3\xd7\x08\xe9\x0c\xc7i\xff"
                (
                    'module'
                )
                False
                'false'
                (
                    'account'
                    'status'
                )
                '__pyarmor_exit_13613__'
                'Settings'
                'option'
                'time_limit'   # b'\x81\xf6\x11\x1e6\xc5\xb2\xdb\x16\xf3\x19'
                60
                'wait_min'
                'wait_max'
                'max_flood'   # b'\x81\xef\x19\x0b\x0c\xfc\xb2\xdd\x14\xfe'
                'max_sms'
                'kol_max_sms'   # b'\x81\xe9\x17\x1f\x0c\xf7\xbf\xca$\xe9\x00\xd3'
                'pin_message'   # b'\x81\xf2\x11\x1d\x0c\xf7\xbb\xc1\x08\xfb\n\xc5'
                'link_preview'   # b'\x81\xee\x11\x1d8\xc5\xae\xc0\x1e\xec\x04\xc5{'
                'video_note'   # b'\x81\xf4\x11\x176\xf5\x81\xdc\x14\xee\x08'
                'message'
                500
                (
                    'limit'
                    'archived'
                )
                'entity'
                777000
                178220800
                0
                'all'
                'info'
                'types'
                'megagroup'   # b'\x81\xef\x1d\x142\xfd\xac\xdd\x0e\xea'
                'gigagroup'   # b'\x81\xe5\x11\x142\xfd\xac\xdd\x0e\xea'
                'chat'
                'groups'
                'channel'
                'channels'
                'user'
                'messages'
                'type'
                50
                'first_name'   # b'\x81\xe4\x11\x01 \xee\x81\xdc\x1a\xf7\x08'
                ' '
                'last_name'   # b"\x81\xee\x19\x00'\xc5\xb0\xd3\x16\xff"
                100
                'title'
                250
                (
                    'limit'
                )
                'date'
                (
                    'entity'
                    'message'
                    'message_id'
                    'pin_message'
                    'video_note'
                    'link_preview'
                    'flood_wait'
                )
                1
                'id'
                'username'
                'raw_message'   # b'\x81\xf0\x19\x04\x0c\xf7\xbb\xc1\x08\xfb\n\xc5'
                'status'
                (
                    'account'
                    'user_id'
                    'title'
                    'username'
                    'type'
                    'message'
                    'message_edit'
                    'status'
                )
                (
                    'config'
                    'account'
                    'message'
                    'end'
                )
                'stop'
                True
                'work_account_completed'   # b'\x81\xf5\x17\x018\xc5\xbf\xd1\x18\xf5\x18\xcex\xd3\xfb\x8a\x02M\xb7\xa2\xbe\xceJ'
                (
                    'config'
                    'account'
                    'message'
                )
                'done'
            [Disassembly]
                0       NOP                             
                2       NOP                             
                4       PUSH_NULL                       
                6       LOAD_CONST                      2: '__pyarmor_enter_13612__'
                8       LOAD_CONST                      3: b'<COAddr>\x07\x00\x00\x1a\x1c\n\x00\x00\x00\x00\x00\x00\x00\x00\x00\x00\x00\x00\x00\x00'
                10      BUILD_TUPLE                     1
                12      CALL_FUNCTION_EX                0
                14      POP_TOP                         
                16      RESUME                          0
                18      NOP                             
                20      NOP                             
                22      NOP                             
                24      NOP                             
                26      NOP                             
                28      NOP                             
                30      LOAD_GLOBAL                     1: NULL + Thread_wait
                40      LOAD_FAST                       3: data
                42      LOAD_FAST                       1: config
                44      LOAD_FAST                       5: stop_thread
                46      CALL                            3
                54      POP_TOP                         
                56      LOAD_GLOBAL                     3: NULL + account_works
                66      LOAD_FAST                       1: config
                68      LOAD_GLOBAL                     4: Lang
                78      LOAD_FAST                       2: proxy
                80      LOAD_FAST                       0: account
                82      LOAD_FAST                       5: stop_thread
                84      PUSH_NULL                       
                86      LOAD_CONST                      1: '__pyarmor_assert_13611__'
                88      LOAD_CONST                      4: 'Edit_messages'   # b"\x81\xc7\x1c\x1a'\xc5\xb3\xd7\x08\xe9\x0c\xc7i\xff"
                90      CALL                            1
                98      KW_NAMES                        5: ('module',)
                100     CALL                            6
                108     STORE_FAST                      7: _var_var_16
                110     LOAD_FAST                       7: _var_var_16
                112     LOAD_CONST                      6: False
                114     COMPARE_OP                      40 (==)
                118     POP_JUMP_IF_FALSE               14 (to 148)
                120     LOAD_FAST                       0: account
                122     LOAD_CONST                      7: 'false'
                124     LOAD_CONST                      8: ('account', 'status')
                126     BUILD_CONST_KEY_MAP             2
                128     NOP                             
                130     NOP                             
                132     JUMP_FORWARD                    1253 (to 2642)
                136     CALL                            1
                144     POP_TOP                         
                146     RETURN_VALUE                    
                148     LOAD_FAST                       3: data
                150     LOAD_CONST                      10: 'Settings'
                152     BINARY_SUBSCR                   
                156     LOAD_ATTR                       7: get
                176     LOAD_CONST                      11: 'option'
                178     CALL                            1
                186     STORE_FAST                      8: _var_var_17
                188     LOAD_GLOBAL                     9: NULL + int
                198     LOAD_FAST                       3: data
                200     LOAD_CONST                      10: 'Settings'
                202     BINARY_SUBSCR                   
                206     LOAD_ATTR                       7: get
                226     PUSH_NULL                       
                228     LOAD_CONST                      1: '__pyarmor_assert_13611__'
                230     LOAD_CONST                      12: 'time_limit'   # b'\x81\xf6\x11\x1e6\xc5\xb2\xdb\x16\xf3\x19'
                232     CALL                            1
                240     CALL                            1
                248     CALL                            1
                256     LOAD_CONST                      13: 60
                258     BINARY_OP                       5 (*)
                262     STORE_FAST                      9: _var_var_18
                264     LOAD_GLOBAL                     9: NULL + int
                274     LOAD_FAST                       3: data
                276     LOAD_CONST                      10: 'Settings'
                278     BINARY_SUBSCR                   
                282     LOAD_ATTR                       7: get
                302     LOAD_CONST                      14: 'wait_min'
                304     CALL                            1
                312     CALL                            1
                320     STORE_FAST                      10: _var_var_19
                322     LOAD_GLOBAL                     9: NULL + int
                332     LOAD_FAST                       3: data
                334     LOAD_CONST                      10: 'Settings'
                336     BINARY_SUBSCR                   
                340     LOAD_ATTR                       7: get
                360     LOAD_CONST                      15: 'wait_max'
                362     CALL                            1
                370     CALL                            1
                378     STORE_FAST                      11: _var_var_20
                380     LOAD_GLOBAL                     9: NULL + int
                390     LOAD_FAST                       3: data
                392     LOAD_CONST                      10: 'Settings'
                394     BINARY_SUBSCR                   
                398     LOAD_ATTR                       7: get
                418     PUSH_NULL                       
                420     LOAD_CONST                      1: '__pyarmor_assert_13611__'
                422     LOAD_CONST                      16: 'max_flood'   # b'\x81\xef\x19\x0b\x0c\xfc\xb2\xdd\x14\xfe'
                424     CALL                            1
                432     CALL                            1
                440     CALL                            1
                448     STORE_FAST                      12: _var_var_21
                450     LOAD_FAST                       3: data
                452     LOAD_CONST                      10: 'Settings'
                454     BINARY_SUBSCR                   
                458     LOAD_ATTR                       7: get
                478     LOAD_CONST                      17: 'max_sms'
                480     CALL                            1
                488     STORE_FAST                      13: _var_var_22
                490     LOAD_GLOBAL                     9: NULL + int
                500     LOAD_FAST                       3: data
                502     LOAD_CONST                      10: 'Settings'
                504     BINARY_SUBSCR                   
                508     LOAD_ATTR                       7: get
                528     PUSH_NULL                       
                530     LOAD_CONST                      1: '__pyarmor_assert_13611__'
                532     LOAD_CONST                      18: 'kol_max_sms'   # b'\x81\xe9\x17\x1f\x0c\xf7\xbf\xca$\xe9\x00\xd3'
                534     CALL                            1
                542     CALL                            1
                550     CALL                            1
                558     STORE_FAST                      14: _var_var_23
                560     LOAD_FAST                       3: data
                562     LOAD_CONST                      10: 'Settings'
                564     BINARY_SUBSCR                   
                568     LOAD_ATTR                       7: get
                588     PUSH_NULL                       
                590     LOAD_CONST                      1: '__pyarmor_assert_13611__'
                592     LOAD_CONST                      19: 'pin_message'   # b'\x81\xf2\x11\x1d\x0c\xf7\xbb\xc1\x08\xfb\n\xc5'
                594     CALL                            1
                602     CALL                            1
                610     STORE_FAST                      15: _var_var_24
                612     LOAD_FAST                       3: data
                614     LOAD_CONST                      10: 'Settings'
                616     BINARY_SUBSCR                   
                620     LOAD_ATTR                       7: get
                640     PUSH_NULL                       
                642     LOAD_CONST                      1: '__pyarmor_assert_13611__'
                644     LOAD_CONST                      20: 'link_preview'   # b'\x81\xee\x11\x1d8\xc5\xae\xc0\x1e\xec\x04\xc5{'
                646     CALL                            1
                654     CALL                            1
                662     STORE_FAST                      16: _var_var_25
                664     LOAD_FAST                       3: data
                666     LOAD_CONST                      10: 'Settings'
                668     BINARY_SUBSCR                   
                672     LOAD_ATTR                       7: get
                692     PUSH_NULL                       
                694     LOAD_CONST                      1: '__pyarmor_assert_13611__'
                696     LOAD_CONST                      21: 'video_note'   # b'\x81\xf4\x11\x176\xf5\x81\xdc\x14\xee\x08'
                698     CALL                            1
                706     CALL                            1
                714     STORE_FAST                      17: _var_var_26
                716     LOAD_FAST                       3: data
                718     LOAD_CONST                      10: 'Settings'
                720     BINARY_SUBSCR                   
                724     LOAD_ATTR                       7: get
                744     LOAD_CONST                      22: 'message'
                746     CALL                            1
                754     STORE_FAST                      18: _var_var_27
                756     LOAD_FAST                       7: _var_var_16
                758     LOAD_ATTR                       11: get_me
                778     CALL                            0
                786     STORE_FAST                      19: _var_var_28
                788     LOAD_FAST                       19: _var_var_28
                790     LOAD_ATTR                       12: id
                810     STORE_FAST                      20: _var_var_29
                812     LOAD_CONST                      6: False
                814     STORE_FAST                      21: _var_var_30
                816     LOAD_GLOBAL                     15: NULL + TelegramEditMessage
                826     LOAD_FAST                       1: config
                828     LOAD_GLOBAL                     4: Lang
                838     LOAD_FAST                       0: account
                840     LOAD_FAST                       7: _var_var_16
                842     LOAD_FAST                       5: stop_thread
                844     CALL                            5
                852     STORE_FAST                      22: _var_var_31
                854     LOAD_FAST                       7: _var_var_16
                856     LOAD_ATTR                       17: get_dialogs
                876     LOAD_CONST                      23: 500
                878     LOAD_CONST                      6: False
                880     KW_NAMES                        24: ('limit', 'archived')
                882     CALL                            2
                890     STORE_FAST                      23: _var_var_32
                892     LOAD_FAST                       23: _var_var_32
                894     GET_ITER                        
                896     FOR_ITER                        700 (to 2300)
                902     STORE_FAST                      24: _var_var_33
                904     LOAD_FAST                       5: stop_thread
                906     LOAD_ATTR                       19: is_set
                926     CALL                            0
                934     POP_JUMP_IF_FALSE               10 (to 956)
                936     LOAD_GLOBAL                     21: NULL + StopProgram
                946     CALL                            0
                954     RAISE_VARARGS                   1
                956     LOAD_GLOBAL                     23: NULL + hasattr
                966     LOAD_FAST                       24: _var_var_33
                968     LOAD_CONST                      25: 'entity'
                970     CALL                            2
                978     POP_JUMP_IF_TRUE                1 (to 982)
                980     JUMP_BACKWARD                   43 (to 896)
                982     LOAD_FAST                       24: _var_var_33
                984     LOAD_ATTR                       12: id
                1004    LOAD_CONST                      26: 777000
                1006    COMPARE_OP                      40 (==)
                1010    POP_JUMP_IF_TRUE                15 (to 1042)
                1012    LOAD_FAST                       24: _var_var_33
                1014    LOAD_ATTR                       12: id
                1034    LOAD_CONST                      27: 178220800
                1036    COMPARE_OP                      40 (==)
                1040    POP_JUMP_IF_FALSE               1 (to 1044)
                1042    JUMP_BACKWARD                   74 (to 896)
                1044    LOAD_CONST                      28: 0
                1046    STORE_FAST                      25: _var_var_34
                1048    NOP                             
                1050    LOAD_GLOBAL                     25: NULL + entity
                1060    CALL                            0
                1068    LOAD_ATTR                       27: check
                1088    LOAD_FAST                       24: _var_var_33
                1090    LOAD_ATTR                       24: entity
                1110    CALL                            1
                1118    STORE_FAST                      26: _var_var_35
                1120    LOAD_FAST                       26: _var_var_35
                1122    POP_JUMP_IF_TRUE                1 (to 1126)
                1124    JUMP_BACKWARD                   115 (to 896)
                1126    LOAD_FAST                       8: _var_var_17
                1128    LOAD_CONST                      29: 'all'
                1130    COMPARE_OP                      55 (!=)
                1134    POP_JUMP_IF_FALSE               85 (to 1306)
                1136    LOAD_FAST                       26: _var_var_35
                1138    LOAD_CONST                      30: 'info'
                1140    BINARY_SUBSCR                   
                1144    LOAD_CONST                      31: 'types'
                1146    BINARY_SUBSCR                   
                1150    PUSH_NULL                       
                1152    LOAD_CONST                      1: '__pyarmor_assert_13611__'
                1154    LOAD_CONST                      32: 'megagroup'   # b'\x81\xef\x1d\x142\xfd\xac\xdd\x0e\xea'
                1156    CALL                            1
                1164    COMPARE_OP                      40 (==)
                1168    POP_JUMP_IF_TRUE                28 (to 1226)
                1170    LOAD_FAST                       26: _var_var_35
                1172    LOAD_CONST                      30: 'info'
                1174    BINARY_SUBSCR                   
                1178    LOAD_CONST                      31: 'types'
                1180    BINARY_SUBSCR                   
                1184    PUSH_NULL                       
                1186    LOAD_CONST                      1: '__pyarmor_assert_13611__'
                1188    LOAD_CONST                      33: 'gigagroup'   # b'\x81\xe5\x11\x142\xfd\xac\xdd\x0e\xea'
                1190    CALL                            1
                1198    COMPARE_OP                      40 (==)
                1202    POP_JUMP_IF_TRUE                11 (to 1226)
                1204    LOAD_FAST                       26: _var_var_35
                1206    LOAD_CONST                      30: 'info'
                1208    BINARY_SUBSCR                   
                1212    LOAD_CONST                      31: 'types'
                1214    BINARY_SUBSCR                   
                1218    LOAD_CONST                      34: 'chat'
                1220    COMPARE_OP                      40 (==)
                1224    POP_JUMP_IF_FALSE               6 (to 1238)
                1226    LOAD_FAST                       8: _var_var_17
                1228    LOAD_CONST                      35: 'groups'
                1230    COMPARE_OP                      55 (!=)
                1234    POP_JUMP_IF_FALSE               1 (to 1238)
                1236    JUMP_BACKWARD                   171 (to 896)
                1238    LOAD_FAST                       26: _var_var_35
                1240    LOAD_CONST                      30: 'info'
                1242    BINARY_SUBSCR                   
                1246    LOAD_CONST                      31: 'types'
                1248    BINARY_SUBSCR                   
                1252    LOAD_CONST                      36: 'channel'
                1254    COMPARE_OP                      40 (==)
                1258    POP_JUMP_IF_FALSE               6 (to 1272)
                1260    LOAD_FAST                       8: _var_var_17
                1262    LOAD_CONST                      37: 'channels'
                1264    COMPARE_OP                      55 (!=)
                1268    POP_JUMP_IF_FALSE               1 (to 1272)
                1270    JUMP_BACKWARD                   188 (to 896)
                1272    LOAD_FAST                       26: _var_var_35
                1274    LOAD_CONST                      30: 'info'
                1276    BINARY_SUBSCR                   
                1280    LOAD_CONST                      31: 'types'
                1282    BINARY_SUBSCR                   
                1286    LOAD_CONST                      38: 'user'
                1288    COMPARE_OP                      40 (==)
                1292    POP_JUMP_IF_FALSE               6 (to 1306)
                1294    LOAD_FAST                       8: _var_var_17
                1296    LOAD_CONST                      39: 'messages'
                1298    COMPARE_OP                      55 (!=)
                1302    POP_JUMP_IF_FALSE               1 (to 1306)
                1304    JUMP_BACKWARD                   205 (to 896)
                1306    LOAD_FAST                       26: _var_var_35
                1308    LOAD_CONST                      40: 'type'
                1310    BINARY_SUBSCR                   
                1314    LOAD_CONST                      38: 'user'
                1316    COMPARE_OP                      40 (==)
                1320    POP_JUMP_IF_FALSE               34 (to 1390)
                1322    LOAD_CONST                      41: 50
                1324    STORE_FAST                      27: _var_var_36
                1326    LOAD_FAST                       26: _var_var_35
                1328    LOAD_CONST                      30: 'info'
                1330    BINARY_SUBSCR                   
                1334    PUSH_NULL                       
                1336    LOAD_CONST                      1: '__pyarmor_assert_13611__'
                1338    LOAD_CONST                      42: 'first_name'   # b'\x81\xe4\x11\x01 \xee\x81\xdc\x1a\xf7\x08'
                1340    CALL                            1
                1348    BINARY_SUBSCR                   
                1352    FORMAT_VALUE                    0 (FVC_NONE)
                1354    LOAD_CONST                      43: ' '
                1356    LOAD_FAST                       26: _var_var_35
                1358    LOAD_CONST                      30: 'info'
                1360    BINARY_SUBSCR                   
                1364    PUSH_NULL                       
                1366    LOAD_CONST                      1: '__pyarmor_assert_13611__'
                1368    LOAD_CONST                      44: 'last_name'   # b"\x81\xee\x19\x00'\xc5\xb0\xd3\x16\xff"
                1370    CALL                            1
                1378    BINARY_SUBSCR                   
                1382    FORMAT_VALUE                    0 (FVC_NONE)
                1384    BUILD_STRING                    3
                1386    STORE_FAST                      28: _var_var_37
                1388    JUMP_FORWARD                    10 (to 1410)
                1390    LOAD_CONST                      45: 100
                1392    STORE_FAST                      27: _var_var_36
                1394    LOAD_FAST                       26: _var_var_35
                1396    LOAD_CONST                      30: 'info'
                1398    BINARY_SUBSCR                   
                1402    LOAD_CONST                      46: 'title'
                1404    BINARY_SUBSCR                   
                1408    STORE_FAST                      28: _var_var_37
                1410    LOAD_FAST                       24: _var_var_33
                1412    LOAD_ATTR                       24: entity
                1432    STORE_FAST                      29: _var_var_38
                1434    LOAD_FAST                       26: _var_var_35
                1436    LOAD_CONST                      30: 'info'
                1438    BINARY_SUBSCR                   
                1442    LOAD_CONST                      31: 'types'
                1444    BINARY_SUBSCR                   
                1448    LOAD_CONST                      36: 'channel'
                1450    COMPARE_OP                      40 (==)
                1454    POP_JUMP_IF_FALSE               78 (to 1612)
                1456    LOAD_CONST                      47: 250
                1458    STORE_FAST                      27: _var_var_36
                1460    LOAD_GLOBAL                     29: NULL + get_full_channel
                1470    LOAD_FAST                       0: account
                1472    LOAD_FAST                       7: _var_var_16
                1474    LOAD_FAST                       29: _var_var_38
                1476    CALL                            3
                1484    STORE_FAST                      30: _var_var_39
                1486    LOAD_CONST                      0: None
                1488    STORE_FAST                      31: _var_var_40
                1490    LOAD_FAST                       30: _var_var_39
                1492    LOAD_ATTR                       30: chats
                1512    GET_ITER                        
                1514    FOR_ITER                        40 (to 1596)
                1518    STORE_FAST                      32: _var_var_41
                1520    LOAD_FAST                       24: _var_var_33
                1522    LOAD_ATTR                       24: entity
                1542    LOAD_ATTR                       12: id
                1562    LOAD_FAST                       32: _var_var_41
                1564    LOAD_ATTR                       12: id
                1584    COMPARE_OP                      55 (!=)
                1588    POP_JUMP_IF_TRUE                1 (to 1592)
                1590    JUMP_BACKWARD                   39 (to 1514)
                1592    LOAD_FAST                       32: _var_var_41
                1594    STORE_FAST                      31: _var_var_40
                1596    JUMP_BACKWARD                   42 (to 1514)
                1598    END_FOR                         
                1600    LOAD_FAST                       31: _var_var_40
                1602    POP_JUMP_IF_TRUE                2 (to 1608)
                1604    JUMP_BACKWARD                   356 (to 896)
                1608    LOAD_FAST                       31: _var_var_40
                1610    STORE_FAST                      29: _var_var_38
                1612    LOAD_FAST                       7: _var_var_16
                1614    LOAD_ATTR                       33: iter_messages
                1634    LOAD_FAST                       29: _var_var_38
                1636    LOAD_FAST                       27: _var_var_36
                1638    KW_NAMES                        48: ('limit',)
                1640    CALL                            2
                1648    GET_ITER                        
                1650    FOR_ITER                        316 (to 2286)
                1656    STORE_FAST                      33: _var_var_42
                1658    LOAD_GLOBAL                     23: NULL + hasattr
                1668    LOAD_FAST                       33: _var_var_42
                1670    LOAD_CONST                      49: 'date'
                1672    CALL                            2
                1680    POP_JUMP_IF_FALSE               111 (to 1904)
                1682    LOAD_FAST                       33: _var_var_42
                1684    LOAD_ATTR                       34: date
                1704    LOAD_CONST                      0: None
                1706    COMPARE_OP                      55 (!=)
                1710    POP_JUMP_IF_FALSE               96 (to 1904)
                1712    LOAD_GLOBAL                     36: datetime
                1722    LOAD_ATTR                       36: datetime
                1742    LOAD_ATTR                       39: now
                1762    LOAD_GLOBAL                     36: datetime
                1772    LOAD_ATTR                       40: timezone
                1792    LOAD_ATTR                       42: utc
                1812    CALL                            1
                1820    STORE_FAST                      34: _var_var_43
                1822    LOAD_FAST                       34: _var_var_43
                1824    LOAD_FAST                       33: _var_var_42
                1826    LOAD_ATTR                       34: date
                1846    BINARY_OP                       10 (-)
                1850    STORE_FAST                      35: _var_var_44
                1852    LOAD_FAST                       35: _var_var_44
                1854    LOAD_ATTR                       45: total_seconds
                1874    CALL                            0
                1882    LOAD_CONST                      13: 60
                1884    BINARY_OP                       11 (/)
                1888    STORE_FAST                      36: _var_var_45
                1890    LOAD_FAST                       36: _var_var_45
                1892    LOAD_FAST                       9: _var_var_18
                1894    COMPARE_OP                      92 (>=)
                1898    POP_JUMP_IF_FALSE               2 (to 1904)
                1900    POP_TOP                         
                1902    JUMP_FORWARD                    193 (to 2290)
                1904    LOAD_FAST                       33: _var_var_42
                1906    LOAD_ATTR                       46: sender_id
                1926    LOAD_FAST                       20: _var_var_29
                1928    COMPARE_OP                      55 (!=)
                1932    POP_JUMP_IF_FALSE               1 (to 1936)
                1934    JUMP_BACKWARD                   143 (to 1650)
                1936    LOAD_FAST                       22: _var_var_31
                1938    LOAD_ATTR                       49: edit
                1958    LOAD_FAST                       29: _var_var_38
                1960    LOAD_FAST                       18: _var_var_27
                1962    LOAD_FAST                       33: _var_var_42
                1964    LOAD_ATTR                       12: id
                1984    LOAD_FAST                       15: _var_var_24
                1986    LOAD_FAST                       17: _var_var_26
                1988    LOAD_FAST                       16: _var_var_25
                1990    LOAD_FAST                       12: _var_var_21
                1992    KW_NAMES                        50: ('entity', 'message', 'message_id', 'pin_message', 'video_note', 'link_preview', 'flood_wait')
                1994    CALL                            7
                2002    STORE_FAST                      37: _var_var_46
                2004    LOAD_FAST                       25: _var_var_34
                2006    LOAD_CONST                      51: 1
                2008    BINARY_OP                       13 (+=)
                2012    STORE_FAST                      25: _var_var_34
                2014    LOAD_GLOBAL                     51: NULL + db_edit_message
                2024    LOAD_FAST                       4: statistic
                2026    CALL                            1
                2034    LOAD_ATTR                       53: insert
                2054    LOAD_FAST                       0: account
                2056    LOAD_FAST                       26: _var_var_35
                2058    LOAD_CONST                      30: 'info'
                2060    BINARY_SUBSCR                   
                2064    LOAD_CONST                      52: 'id'
                2066    BINARY_SUBSCR                   
                2070    LOAD_FAST                       28: _var_var_37
                2072    LOAD_FAST                       26: _var_var_35
                2074    LOAD_CONST                      30: 'info'
                2076    BINARY_SUBSCR                   
                2080    LOAD_CONST                      53: 'username'
                2082    BINARY_SUBSCR                   
                2086    LOAD_FAST                       26: _var_var_35
                2088    LOAD_CONST                      30: 'info'
                2090    BINARY_SUBSCR                   
                2094    LOAD_CONST                      31: 'types'
                2096    BINARY_SUBSCR                   
                2100    LOAD_FAST                       33: _var_var_42
                2102    LOAD_ATTR                       54: raw_text
                2122    LOAD_FAST                       37: _var_var_46
                2124    PUSH_NULL                       
                2126    LOAD_CONST                      1: '__pyarmor_assert_13611__'
                2128    LOAD_CONST                      54: 'raw_message'   # b'\x81\xf0\x19\x04\x0c\xf7\xbb\xc1\x08\xfb\n\xc5'
                2130    CALL                            1
                2138    BINARY_SUBSCR                   
                2142    LOAD_FAST                       37: _var_var_46
                2144    LOAD_CONST                      55: 'status'
                2146    BINARY_SUBSCR                   
                2150    KW_NAMES                        56: ('account', 'user_id', 'title', 'username', 'type', 'message', 'message_edit', 'status')
                2152    CALL                            8
                2160    POP_TOP                         
                2162    LOAD_GLOBAL                     57: NULL + Logs
                2172    LOAD_ATTR                       58: PrintLog
                2192    LOAD_FAST                       1: config
                2194    LOAD_FAST                       0: account
                2196    LOAD_FAST                       28: _var_var_37
                2198    LOAD_FAST                       37: _var_var_46
                2200    LOAD_CONST                      55: 'status'
                2202    BINARY_SUBSCR                   
                2206    KW_NAMES                        57: ('config', 'account', 'message', 'end')
                2208    CALL                            4
                2216    POP_TOP                         
                2218    LOAD_FAST                       13: _var_var_22
                2220    POP_JUMP_IF_FALSE               7 (to 2236)
                2222    LOAD_FAST                       25: _var_var_34
                2224    LOAD_FAST                       14: _var_var_23
                2226    COMPARE_OP                      92 (>=)
                2230    POP_JUMP_IF_FALSE               2 (to 2236)
                2232    POP_TOP                         
                2234    JUMP_FORWARD                    27 (to 2290)
                2236    LOAD_FAST                       37: _var_var_46
                2238    LOAD_CONST                      58: 'stop'
                2240    BINARY_SUBSCR                   
                2244    POP_JUMP_IF_FALSE               4 (to 2254)
                2246    LOAD_CONST                      59: True
                2248    STORE_FAST                      21: _var_var_30
                2250    POP_TOP                         
                2252    JUMP_FORWARD                    18 (to 2290)
                2254    LOAD_GLOBAL                     61: NULL + DelayOnline
                2264    LOAD_FAST                       0: account
                2266    LOAD_FAST                       7: _var_var_16
                2268    LOAD_FAST                       10: _var_var_19
                2270    LOAD_FAST                       11: _var_var_20
                2272    LOAD_FAST                       5: stop_thread
                2274    CALL                            5
                2282    POP_TOP                         
                2284    JUMP_BACKWARD                   319 (to 1650)
                2288    END_FOR                         
                2290    LOAD_FAST                       21: _var_var_30
                2292    POP_JUMP_IF_TRUE                2 (to 2298)
                2294    JUMP_BACKWARD                   701 (to 896)
                2298    POP_TOP                         
                2300    JUMP_FORWARD                    1 (to 2304)
                2302    END_FOR                         
                2304    LOAD_GLOBAL                     67: NULL + Disconnect
                2314    LOAD_FAST_CHECK                 7: _var_var_16
                2316    CALL                            1
                2324    POP_TOP                         
                2326    LOAD_GLOBAL                     57: NULL + Logs
                2336    LOAD_ATTR                       58: PrintLog
                2356    LOAD_FAST                       1: config
                2358    LOAD_FAST                       0: account
                2360    LOAD_GLOBAL                     4: Lang
                2370    PUSH_NULL                       
                2372    LOAD_CONST                      1: '__pyarmor_assert_13611__'
                2374    LOAD_CONST                      60: 'work_account_completed'   # b'\x81\xf5\x17\x018\xc5\xbf\xd1\x18\xf5\x18\xcex\xd3\xfb\x8a\x02M\xb7\xa2\xbe\xceJ'
                2376    CALL                            1
                2384    BINARY_SUBSCR                   
                2388    KW_NAMES                        61: ('config', 'account', 'message')
                2390    CALL                            3
                2398    POP_TOP                         
                2400    LOAD_FAST                       0: account
                2402    LOAD_CONST                      62: 'done'
                2404    LOAD_CONST                      8: ('account', 'status')
                2406    BUILD_CONST_KEY_MAP             2
                2408    NOP                             
                2410    NOP                             
                2412    NOP                             
                2414    JUMP_FORWARD                    113 (to 2642)
                2416    CALL                            1
                2424    POP_TOP                         
                2426    RETURN_VALUE                    
                2428    PUSH_EXC_INFO                   
                2430    LOAD_GLOBAL                     62: BaseException
                2440    CHECK_EXC_MATCH                 
                2442    POP_JUMP_IF_FALSE               26 (to 2496)
                2444    STORE_FAST                      38: _var_var_3
                2446    PUSH_NULL                       
                2448    LOAD_GLOBAL                     65: NULL + logging
                2458    LOAD_FAST                       38: _var_var_3
                2460    CALL                            1
                2468    CALL                            0
                2476    POP_TOP                         
                2478    POP_EXCEPT                      
                2480    LOAD_CONST                      0: None
                2482    STORE_FAST                      38: _var_var_3
                2484    DELETE_FAST                     38: _var_var_3
                2486    JUMP_BACKWARD                   99 (to 2290)
                2488    LOAD_CONST                      0: None
                2490    STORE_FAST                      38: _var_var_3
                2492    DELETE_FAST                     38: _var_var_3
                2494    RERAISE                         1
                2496    RERAISE                         0
                2498    COPY                            3
                2500    POP_EXCEPT                      
                2502    RERAISE                         1
                2504    PUSH_EXC_INFO                   
                2506    LOAD_GLOBAL                     20: StopProgram
                2516    CHECK_EXC_MATCH                 
                2518    POP_JUMP_IF_FALSE               3 (to 2526)
                2520    POP_TOP                         
                2522    POP_EXCEPT                      
                2524    JUMP_BACKWARD                   111 (to 2304)
                2526    LOAD_GLOBAL                     62: BaseException
                2536    CHECK_EXC_MATCH                 
                2538    POP_JUMP_IF_FALSE               26 (to 2592)
                2540    STORE_FAST                      38: _var_var_3
                2542    PUSH_NULL                       
                2544    LOAD_GLOBAL                     65: NULL + logging
                2554    LOAD_FAST                       38: _var_var_3
                2556    CALL                            1
                2564    CALL                            0
                2572    POP_TOP                         
                2574    POP_EXCEPT                      
                2576    LOAD_CONST                      0: None
                2578    STORE_FAST                      38: _var_var_3
                2580    DELETE_FAST                     38: _var_var_3
                2582    JUMP_BACKWARD                   140 (to 2304)
                2584    LOAD_CONST                      0: None
                2586    STORE_FAST                      38: _var_var_3
                2588    DELETE_FAST                     38: _var_var_3
                2590    RERAISE                         1
                2592    RERAISE                         0
                2594    COPY                            3
                2596    POP_EXCEPT                      
                2598    RERAISE                         1
                2600    PUSH_EXC_INFO                   
                2602    POP_TOP                         
                2604    POP_EXCEPT                      
                2606    JUMP_BACKWARD                   141 (to 2326)
                2608    COPY                            3
                2610    POP_EXCEPT                      
                2612    RERAISE                         1
                2614    PUSH_EXC_INFO                   
                2616    PUSH_NULL                       
                2618    LOAD_CONST                      9: '__pyarmor_exit_13613__'
                2620    NOP                             
                2622    LOAD_CONST                      3: b'<COAddr>\x07\x00\x00\x1a\x1c\n\x00\x00\x00\x00\x00\x00\x00\x00\x00\x00\x00\x00\x00\x00'
                2624    CALL                            1
                2632    POP_TOP                         
                2634    RERAISE                         0
                2636    COPY                            3
                2638    POP_EXCEPT                      
                2640    RERAISE                         1
                2642    PUSH_NULL                       
                2644    LOAD_CONST                      9: '__pyarmor_exit_13613__'
                2646    LOAD_CONST                      3: b'<COAddr>\x07\x00\x00\x1a\x1c\n\x00\x00\x00\x00\x00\x00\x00\x00\x00\x00\x00\x00\x00\x00'
                2648    BUILD_TUPLE                     1
                2650    CALL_FUNCTION_EX                0
                2652    POP_TOP                         
                2654    RETURN_VALUE                    
            [Exception Table]
                30 to 128 -> 2504 [0] 
                148 to 1048 -> 2504 [0] 
                1050 to 1124 -> 2428 [1] 
                1124 to 1126 -> 2504 [0] 
                1126 to 1236 -> 2428 [1] 
                1236 to 1238 -> 2504 [0] 
                1238 to 1270 -> 2428 [1] 
                1270 to 1272 -> 2504 [0] 
                1272 to 1304 -> 2428 [1] 
                1304 to 1306 -> 2504 [0] 
                1306 to 1590 -> 2428 [1] 
                1592 to 1604 -> 2428 [1] 
                1604 to 1608 -> 2504 [0] 
                1608 to 2290 -> 2428 [1] 
                2290 to 2294 -> 2504 [0] 
                2298 to 2304 -> 2504 [0] 
                2304 to 2326 -> 2600 [0] 
                2326 to 2408 -> 2614 [0] 
                2428 to 2446 -> 2498 [2] lasti
                2446 to 2478 -> 2488 [2] lasti
                2478 to 2488 -> 2504 [0] 
                2488 to 2498 -> 2498 [2] lasti
                2498 to 2504 -> 2504 [0] 
                2504 to 2522 -> 2594 [1] lasti
                2522 to 2526 -> 2614 [0] 
                2526 to 2542 -> 2594 [1] lasti
                2542 to 2574 -> 2584 [1] lasti
                2574 to 2584 -> 2614 [0] 
                2584 to 2594 -> 2594 [1] lasti
                2594 to 2600 -> 2614 [0] 
                2600 to 2604 -> 2608 [1] lasti
                2604 to 2614 -> 2614 [0] 
                2614 to 2636 -> 2636 [1] lasti
        [Code]
            File Name: <frozen program.modules.Edit_messages>
            Object Name: get_full_channel
            Qualified Name: get_full_channel
            Arg Count: 3
            Pos Only Arg Count: 0
            KW Only Arg Count: 0
            Stack Size: 9
            Flags: 0x20000003 (CO_OPTIMIZED | CO_NEWLOCALS | CO_PYARMOR_OBFUSCATED)
            [Names]
                'functions'
                'channels'
                'GetFullChannelRequest'
                'errors'
                'FloodWaitError'
                'Logs'
                'PrintLog'
                'config'
                'Lang'
                'seconds'
                'time'
                'sleep'
                'int'
                'is_connected'
                'connect'
                'account'
                'UpdateStatusRequest'
                'get_full_channel'
                'ConnectionError'
                'Exception'
                'str'
            [Locals+Names]
                'account'
                'client'
                'entity'
                '__assert_armored__'
                '_var_var_47'
                '_var_var_3'
            [Constants]
                None
                '__pyarmor_assert_13614__'
                '__pyarmor_enter_13615__'
                b'<COAddr>\x07\x00\x00\x1a\xfa\x03\x00\x00\x00\x00\x00\x00\x00\x00\x00\x00\x00\x00\x00\x00'
                (
                    'channel'
                )
                '__pyarmor_exit_13616__'
                'restriction_detected'   # b"\x81\xf0\x1d\x00'\xe8\xb7\xd1\x0f\xf3\x02\xceS\xe8\xfd\x91\n^\xaf\xa2\xae"
                (
                    'config'
                    'account'
                    'message'
                )
                'flood_wait_sec'   # b'\x81\xe4\x14\x1c<\xfe\x81\xc5\x1a\xf3\x19\xff\x7f\xe9\xfb'
                (
                    'config'
                    'account'
                    'message'
                    'param'
                )
                'algorithm_running'   # b'\x81\xe3\x14\x14<\xe8\xb7\xc6\x13\xf72\xd2y\xe2\xf6\x8c\x01Z'
                10
                False
                (
                    'offline'
                )
                'EXCEPTION:'   # b'\x81\xc7 0\x16\xca\x8a\xfb4\xd4W'
                (
                    'config'
                    'account'
                    'message'
                    'end'
                )
            [Disassembly]
                0       NOP                             
                2       NOP                             
                4       PUSH_NULL                       
                6       LOAD_CONST                      2: '__pyarmor_enter_13615__'
                8       LOAD_CONST                      3: b'<COAddr>\x07\x00\x00\x1a\xfa\x03\x00\x00\x00\x00\x00\x00\x00\x00\x00\x00\x00\x00\x00\x00'
                10      BUILD_TUPLE                     1
                12      CALL_FUNCTION_EX                0
                14      POP_TOP                         
                16      RESUME                          0
                18      NOP                             
                20      NOP                             
                22      NOP                             
                24      NOP                             
                26      NOP                             
                28      NOP                             
                30      PUSH_NULL                       
                32      LOAD_FAST                       1: client
                34      LOAD_GLOBAL                     0: functions
                44      LOAD_ATTR                       2: channels
                64      LOAD_ATTR                       5: GetFullChannelRequest
                84      LOAD_FAST                       2: entity
                86      KW_NAMES                        4: ('channel',)
                88      CALL                            1
                96      CALL                            1
                104     STORE_FAST                      4: _var_var_47
                106     LOAD_FAST                       4: _var_var_47
                108     NOP                             
                110     NOP                             
                112     JUMP_FORWARD                    478 (to 1072)
                116     CALL                            1
                124     POP_TOP                         
                126     RETURN_VALUE                    
                128     PUSH_EXC_INFO                   
                130     LOAD_GLOBAL                     6: errors
                140     LOAD_ATTR                       8: FloodWaitError
                160     CHECK_EXC_MATCH                 
                162     POP_JUMP_IF_FALSE               279 (to 724)
                166     STORE_FAST                      5: _var_var_3
                168     LOAD_GLOBAL                     11: NULL + Logs
                178     LOAD_ATTR                       12: PrintLog
                198     LOAD_GLOBAL                     14: config
                208     LOAD_FAST                       0: account
                210     LOAD_GLOBAL                     16: Lang
                220     PUSH_NULL                       
                222     LOAD_CONST                      1: '__pyarmor_assert_13614__'
                224     LOAD_CONST                      6: 'restriction_detected'   # b"\x81\xf0\x1d\x00'\xe8\xb7\xd1\x0f\xf3\x02\xceS\xe8\xfd\x91\n^\xaf\xa2\xae"
                226     CALL                            1
                234     BINARY_SUBSCR                   
                238     KW_NAMES                        7: ('config', 'account', 'message')
                240     CALL                            3
                248     POP_TOP                         
                250     LOAD_GLOBAL                     11: NULL + Logs
                260     LOAD_ATTR                       12: PrintLog
                280     LOAD_GLOBAL                     14: config
                290     LOAD_FAST                       0: account
                292     LOAD_GLOBAL                     16: Lang
                302     PUSH_NULL                       
                304     LOAD_CONST                      1: '__pyarmor_assert_13614__'
                306     LOAD_CONST                      8: 'flood_wait_sec'   # b'\x81\xe4\x14\x1c<\xfe\x81\xc5\x1a\xf3\x19\xff\x7f\xe9\xfb'
                308     CALL                            1
                316     BINARY_SUBSCR                   
                320     LOAD_FAST                       5: _var_var_3
                322     LOAD_ATTR                       18: seconds
                342     KW_NAMES                        9: ('config', 'account', 'message', 'param')
                344     CALL                            4
                352     POP_TOP                         
                354     LOAD_GLOBAL                     11: NULL + Logs
                364     LOAD_ATTR                       12: PrintLog
                384     LOAD_GLOBAL                     14: config
                394     LOAD_FAST                       0: account
                396     LOAD_GLOBAL                     16: Lang
                406     PUSH_NULL                       
                408     LOAD_CONST                      1: '__pyarmor_assert_13614__'
                410     LOAD_CONST                      10: 'algorithm_running'   # b'\x81\xe3\x14\x14<\xe8\xb7\xc6\x13\xf72\xd2y\xe2\xf6\x8c\x01Z'
                412     CALL                            1
                420     BINARY_SUBSCR                   
                424     KW_NAMES                        7: ('config', 'account', 'message')
                426     CALL                            3
                434     POP_TOP                         
                436     LOAD_GLOBAL                     21: NULL + time
                446     LOAD_ATTR                       22: sleep
                466     LOAD_GLOBAL                     25: NULL + int
                476     LOAD_FAST                       5: _var_var_3
                478     LOAD_ATTR                       18: seconds
                498     CALL                            1
                506     LOAD_CONST                      11: 10
                508     BINARY_OP                       0 (+)
                512     CALL                            1
                520     POP_TOP                         
                522     LOAD_FAST                       1: client
                524     LOAD_ATTR                       27: is_connected
                544     CALL                            0
                552     POP_JUMP_IF_TRUE                54 (to 662)
                554     LOAD_FAST                       1: client
                556     LOAD_ATTR                       29: connect
                576     CALL                            0
                584     POP_TOP                         
                586     PUSH_NULL                       
                588     LOAD_FAST                       1: client
                590     LOAD_GLOBAL                     0: functions
                600     LOAD_ATTR                       30: account
                620     LOAD_ATTR                       33: UpdateStatusRequest
                640     LOAD_CONST                      12: False
                642     KW_NAMES                        13: ('offline',)
                644     CALL                            1
                652     CALL                            1
                660     POP_TOP                         
                662     LOAD_GLOBAL                     35: NULL + get_full_channel
                672     LOAD_FAST                       0: account
                674     LOAD_FAST                       1: client
                676     LOAD_FAST                       2: entity
                678     CALL                            3
                686     SWAP                            2
                688     POP_EXCEPT                      
                690     LOAD_CONST                      0: None
                692     STORE_FAST                      5: _var_var_3
                694     DELETE_FAST                     5: _var_var_3
                696     NOP                             
                698     NOP                             
                700     NOP                             
                702     JUMP_FORWARD                    184 (to 1072)
                704     CALL                            1
                712     POP_TOP                         
                714     RETURN_VALUE                    
                716     LOAD_CONST                      0: None
                718     STORE_FAST                      5: _var_var_3
                720     DELETE_FAST                     5: _var_var_3
                722     RERAISE                         1
                724     LOAD_GLOBAL                     36: ConnectionError
                734     CHECK_EXC_MATCH                 
                736     POP_JUMP_IF_FALSE               79 (to 896)
                738     POP_TOP                         
                740     LOAD_FAST                       1: client
                742     LOAD_ATTR                       29: connect
                762     CALL                            0
                770     POP_TOP                         
                772     PUSH_NULL                       
                774     LOAD_FAST                       1: client
                776     LOAD_GLOBAL                     0: functions
                786     LOAD_ATTR                       30: account
                806     LOAD_ATTR                       33: UpdateStatusRequest
                826     LOAD_CONST                      12: False
                828     KW_NAMES                        13: ('offline',)
                830     CALL                            1
                838     CALL                            1
                846     POP_TOP                         
                848     LOAD_GLOBAL                     35: NULL + get_full_channel
                858     LOAD_FAST                       0: account
                860     LOAD_FAST                       1: client
                862     LOAD_FAST                       2: entity
                864     CALL                            3
                872     SWAP                            2
                874     POP_EXCEPT                      
                876     NOP                             
                878     NOP                             
                880     NOP                             
                882     JUMP_FORWARD                    94 (to 1072)
                884     CALL                            1
                892     POP_TOP                         
                894     RETURN_VALUE                    
                896     LOAD_GLOBAL                     38: Exception
                906     CHECK_EXC_MATCH                 
                908     POP_JUMP_IF_FALSE               63 (to 1036)
                910     STORE_FAST                      5: _var_var_3
                912     LOAD_GLOBAL                     11: NULL + Logs
                922     LOAD_ATTR                       12: PrintLog
                942     LOAD_GLOBAL                     14: config
                952     LOAD_FAST                       0: account
                954     PUSH_NULL                       
                956     LOAD_CONST                      1: '__pyarmor_assert_13614__'
                958     LOAD_CONST                      14: 'EXCEPTION:'   # b'\x81\xc7 0\x16\xca\x8a\xfb4\xd4W'
                960     CALL                            1
                968     LOAD_GLOBAL                     41: NULL + str
                978     LOAD_FAST                       5: _var_var_3
                980     CALL                            1
                988     KW_NAMES                        15: ('config', 'account', 'message', 'end')
                990     CALL                            4
                998     POP_TOP                         
                1000    POP_EXCEPT                      
                1002    LOAD_CONST                      0: None
                1004    STORE_FAST                      5: _var_var_3
                1006    DELETE_FAST                     5: _var_var_3
                1008    LOAD_CONST                      0: None
                1010    NOP                             
                1012    NOP                             
                1014    NOP                             
                1016    JUMP_FORWARD                    27 (to 1072)
                1024    POP_TOP                         
                1026    RETURN_CONST                    0: None
                1028    LOAD_CONST                      0: None
                1030    STORE_FAST                      5: _var_var_3
                1032    DELETE_FAST                     5: _var_var_3
                1034    RERAISE                         1
                1036    RERAISE                         0
                1038    COPY                            3
                1040    POP_EXCEPT                      
                1042    RERAISE                         1
                1044    PUSH_EXC_INFO                   
                1046    PUSH_NULL                       
                1048    LOAD_CONST                      5: '__pyarmor_exit_13616__'
                1050    NOP                             
                1052    LOAD_CONST                      3: b'<COAddr>\x07\x00\x00\x1a\xfa\x03\x00\x00\x00\x00\x00\x00\x00\x00\x00\x00\x00\x00\x00\x00'
                1054    CALL                            1
                1062    POP_TOP                         
                1064    RERAISE                         0
                1066    COPY                            3
                1068    POP_EXCEPT                      
                1070    RERAISE                         1
                1072    PUSH_NULL                       
                1074    LOAD_CONST                      5: '__pyarmor_exit_13616__'
                1076    LOAD_CONST                      3: b'<COAddr>\x07\x00\x00\x1a\xfa\x03\x00\x00\x00\x00\x00\x00\x00\x00\x00\x00\x00\x00\x00\x00'
                1078    BUILD_TUPLE                     1
                1080    CALL_FUNCTION_EX                0
                1082    POP_TOP                         
                1084    RETURN_VALUE                    
            [Exception Table]
                30 to 108 -> 128 [0] 
                128 to 168 -> 1038 [1] lasti
                168 to 686 -> 716 [1] lasti
                686 to 688 -> 1038 [1] lasti
                688 to 696 -> 1044 [0] 
                716 to 874 -> 1038 [1] lasti
                874 to 876 -> 1044 [0] 
                896 to 912 -> 1038 [1] lasti
                912 to 1000 -> 1028 [1] lasti
                1000 to 1008 -> 1044 [0] 
                1028 to 1038 -> 1038 [1] lasti
                1038 to 1044 -> 1044 [0] 
                1044 to 1066 -> 1066 [1] lasti
        '__pyarmor_exit_13604__'
    [Disassembly]
        0       NOP                             
        2       NOP                             
        4       PUSH_NULL                       
        6       LOAD_CONST                      1: '__pyarmor_enter_13603__'
        8       LOAD_CONST                      2: b'<COAddr>\x07\x00\x00\x1ad\x01\x00\x00\x00\x00\x00\x00\x00\x00\x00\x00\x00\x00\x00\x00'
        10      BUILD_TUPLE                     1
        12      CALL_FUNCTION_EX                0
        14      POP_TOP                         
        16      RESUME                          0
        18      NOP                             
        20      NOP                             
        22      NOP                             
        24      NOP                             
        26      LOAD_CONST                      3: 0
        28      LOAD_CONST                      4: None
        30      IMPORT_NAME                     1: eel
        32      STORE_NAME                      1: eel
        34      LOAD_CONST                      3: 0
        36      LOAD_CONST                      4: None
        38      IMPORT_NAME                     2: json
        40      STORE_NAME                      2: json
        42      LOAD_CONST                      3: 0
        44      LOAD_CONST                      4: None
        46      IMPORT_NAME                     3: time
        48      STORE_NAME                      3: time
        50      LOAD_CONST                      3: 0
        52      LOAD_CONST                      4: None
        54      IMPORT_NAME                     4: datetime
        56      STORE_NAME                      4: datetime
        58      LOAD_CONST                      3: 0
        60      LOAD_CONST                      4: None
        62      IMPORT_NAME                     5: concurrent.futures
        64      STORE_NAME                      6: concurrent
        66      LOAD_CONST                      3: 0
        68      LOAD_CONST                      5: ('Thread', 'Event')
        70      IMPORT_NAME                     7: threading
        72      IMPORT_FROM                     8: Thread
        74      STORE_NAME                      8: Thread
        76      IMPORT_FROM                     9: Event
        78      STORE_NAME                      9: Event
        80      POP_TOP                         
        82      LOAD_CONST                      3: 0
        84      LOAD_CONST                      6: ('functions', 'errors')
        86      IMPORT_NAME                     10: multithon.sync
        88      IMPORT_FROM                     11: functions
        90      STORE_NAME                      11: functions
        92      IMPORT_FROM                     12: errors
        94      STORE_NAME                      12: errors
        96      POP_TOP                         
        98      LOAD_CONST                      3: 0
        100     LOAD_CONST                      7: ('StopProgram',)
        102     IMPORT_NAME                     13: multithon.errors
        104     IMPORT_FROM                     14: StopProgram
        106     STORE_NAME                      14: StopProgram
        108     POP_TOP                         
        110     LOAD_CONST                      3: 0
        112     LOAD_CONST                      8: ('GetLang',)
        114     IMPORT_NAME                     15: program.static_classes
        116     IMPORT_FROM                     16: GetLang
        118     STORE_NAME                      16: GetLang
        120     POP_TOP                         
        122     LOAD_CONST                      3: 0
        124     LOAD_CONST                      9: ('Logs',)
        126     IMPORT_NAME                     15: program.static_classes
        128     IMPORT_FROM                     17: Logs
        130     STORE_NAME                      17: Logs
        132     POP_TOP                         
        134     LOAD_CONST                      3: 0
        136     LOAD_CONST                      10: ('check_module',)
        138     IMPORT_NAME                     15: program.static_classes
        140     IMPORT_FROM                     18: check_module
        142     STORE_NAME                      18: check_module
        144     POP_TOP                         
        146     LOAD_CONST                      3: 0
        148     LOAD_CONST                      11: ('logging',)
        150     IMPORT_NAME                     15: program.static_classes
        152     IMPORT_FROM                     19: logging
        154     STORE_NAME                      19: logging
        156     POP_TOP                         
        158     LOAD_CONST                      3: 0
        160     LOAD_CONST                      12: ('memory_check_switcher',)
        162     IMPORT_NAME                     15: program.static_classes
        164     IMPORT_FROM                     20: memory_check_switcher
        166     STORE_NAME                      20: memory_check_switcher
        168     POP_TOP                         
        170     LOAD_CONST                      3: 0
        172     LOAD_CONST                      13: ('memory_set_pid',)
        174     IMPORT_NAME                     15: program.static_classes
        176     IMPORT_FROM                     21: memory_set_pid
        178     STORE_NAME                      21: memory_set_pid
        180     POP_TOP                         
        182     LOAD_CONST                      3: 0
        184     LOAD_CONST                      14: ('DelayOnline',)
        186     IMPORT_NAME                     22: program.telegram
        188     IMPORT_FROM                     23: DelayOnline
        190     STORE_NAME                      23: DelayOnline
        192     POP_TOP                         
        194     LOAD_CONST                      3: 0
        196     LOAD_CONST                      15: ('Disconnect',)
        198     IMPORT_NAME                     22: program.telegram
        200     IMPORT_FROM                     24: Disconnect
        202     STORE_NAME                      24: Disconnect
        204     POP_TOP                         
        206     LOAD_CONST                      3: 0
        208     LOAD_CONST                      16: ('Thread_wait',)
        210     IMPORT_NAME                     22: program.telegram
        212     IMPORT_FROM                     25: Thread_wait
        214     STORE_NAME                      25: Thread_wait
        216     POP_TOP                         
        218     LOAD_CONST                      3: 0
        220     LOAD_CONST                      17: ('account_works',)
        222     IMPORT_NAME                     22: program.telegram
        224     IMPORT_FROM                     26: account_works
        226     STORE_NAME                      26: account_works
        228     POP_TOP                         
        230     LOAD_CONST                      3: 0
        232     LOAD_CONST                      18: ('entity',)
        234     IMPORT_NAME                     22: program.telegram
        236     IMPORT_FROM                     27: entity
        238     STORE_NAME                      27: entity
        240     POP_TOP                         
        242     LOAD_CONST                      3: 0
        244     LOAD_CONST                      19: ('GetConfig',)
        246     IMPORT_NAME                     28: program.general
        248     IMPORT_FROM                     29: GetConfig
        250     STORE_NAME                      29: GetConfig
        252     POP_TOP                         
        254     LOAD_CONST                      3: 0
        256     LOAD_CONST                      20: ('GetProxy',)
        258     IMPORT_NAME                     28: program.general
        260     IMPORT_FROM                     30: GetProxy
        262     STORE_NAME                      30: GetProxy
        264     POP_TOP                         
        266     LOAD_CONST                      3: 0
        268     LOAD_CONST                      21: ('StopDetect',)
        270     IMPORT_NAME                     28: program.general
        272     IMPORT_FROM                     31: StopDetect
        274     STORE_NAME                      31: StopDetect
        276     POP_TOP                         
        278     LOAD_CONST                      3: 0
        280     LOAD_CONST                      22: ('check_get_settings',)
        282     IMPORT_NAME                     28: program.general
        284     IMPORT_FROM                     32: check_get_settings
        286     STORE_NAME                      32: check_get_settings
        288     POP_TOP                         
        290     LOAD_CONST                      3: 0
        292     LOAD_CONST                      23: ('del_task_manager',)
        294     IMPORT_NAME                     28: program.general
        296     IMPORT_FROM                     33: del_task_manager
        298     STORE_NAME                      33: del_task_manager
        300     POP_TOP                         
        302     LOAD_CONST                      3: 0
        304     LOAD_CONST                      24: ('set_task_manager',)
        306     IMPORT_NAME                     28: program.general
        308     IMPORT_FROM                     34: set_task_manager
        310     STORE_NAME                      34: set_task_manager
        312     POP_TOP                         
        314     LOAD_CONST                      25: 1
        316     LOAD_CONST                      26: ('TelegramEditMessage',)
        318     IMPORT_NAME                     35: func.sender
        320     IMPORT_FROM                     36: TelegramEditMessage
        322     STORE_NAME                      36: TelegramEditMessage
        324     POP_TOP                         
        326     LOAD_CONST                      3: 0
        328     LOAD_CONST                      27: ('db_edit_message',)
        330     IMPORT_NAME                     37: program.database
        332     IMPORT_FROM                     38: db_edit_message
        334     STORE_NAME                      38: db_edit_message
        336     POP_TOP                         
        338     LOAD_CONST                      28: <CODE> Edit_messages
        340     MAKE_FUNCTION                   0
        342     STORE_NAME                      39: Edit_messages
        344     LOAD_CONST                      29: <CODE> START
        346     MAKE_FUNCTION                   0
        348     STORE_NAME                      40: START
        350     LOAD_CONST                      30: <CODE> worker
        352     MAKE_FUNCTION                   0
        354     STORE_NAME                      41: worker
        356     LOAD_CONST                      31: <CODE> get_full_channel
        358     MAKE_FUNCTION                   0
        360     STORE_NAME                      42: get_full_channel
        362     LOAD_CONST                      4: None
        364     NOP                             
        366     NOP                             
        368     NOP                             
        370     JUMP_FORWARD                    19 (to 410)
        378     POP_TOP                         
        380     RETURN_CONST                    4: None
        382     PUSH_EXC_INFO                   
        384     PUSH_NULL                       
        386     LOAD_CONST                      32: '__pyarmor_exit_13604__'
        388     NOP                             
        390     LOAD_CONST                      2: b'<COAddr>\x07\x00\x00\x1ad\x01\x00\x00\x00\x00\x00\x00\x00\x00\x00\x00\x00\x00\x00\x00'
        392     CALL                            1
        400     POP_TOP                         
        402     RERAISE                         0
        404     COPY                            3
        406     POP_EXCEPT                      
        408     RERAISE                         1
        410     PUSH_NULL                       
        412     LOAD_CONST                      32: '__pyarmor_exit_13604__'
        414     LOAD_CONST                      2: b'<COAddr>\x07\x00\x00\x1ad\x01\x00\x00\x00\x00\x00\x00\x00\x00\x00\x00\x00\x00\x00\x00'
        416     BUILD_TUPLE                     1
        418     CALL_FUNCTION_EX                0
        420     POP_TOP                         
        422     RETURN_VALUE                    
    [Exception Table]
        26 to 362 -> 382 [0] 
        382 to 404 -> 404 [1] lasti
