#decoded by lolz.live/mrpenny / t.me/zeus_jackpot
# ================================
# Примечания по Pyarmor:
# - Байт-код и объекты кода Pyarmor соответствуют стандартному Python, но присутствуют специальные вызовы функций среды выполнения (runtime) Pyarmor.
# - Вызовы строк — это не ошибки, а маркеры, которые обрабатываются Pyarmor во время выполнения.
#
# Руководство по декомпиляции (без среды выполнения):
# 1. Игнорируйте зашифрованные байты после `#`; используйте только строку до `#`.
# 2. Удалите "__pyarmor_enter_xxx__"(b"<COAddr>...") и "__pyarmor_leave_xxx__"(b"<COAddr>...") (пролог/эпилог).
# 3. "__pyarmor_assert_xxx__"(A) не является настоящим оператором assert.
#    - Если A — это имя или читаемая строка: замените на A.
#    - Если A — это (X, "Y"): замените на X.Y.
#    - Если A — это (X, "Y", Z): замените на X.Y = Z.
#    - В противном случае: выберите наиболее подходящую/логичную замену.
# 4. "__pyarmor_bcc_xxx__"(...) указывает на машинный (нативный) код; тело функции недоступно. Добавьте комментарий.
# ================================

[Code]
    File Name: <frozen program.modules.Group_del_admin>
    Object Name: <module>
    Qualified Name: <module>
    Arg Count: 0
    Pos Only Arg Count: 0
    KW Only Arg Count: 0
    Stack Size: 5
    Flags: 0x20000000 (CO_PYARMOR_OBFUSCATED)
    [Names]
        '__assert_armored__'
        'eel'
        'threading'
        'Thread'
        'Event'
        'multithon.sync'
        'types'
        'multithon.errors'
        'StopProgram'
        'program.static_classes'
        'GetLang'
        'Logs'
        'logging'
        'memory_check_switcher'
        'memory_set_pid'
        'program.telegram'
        'Disconnect'
        'account_works'
        'program.general'
        'GetConfig'
        'GetProxy'
        'StopDetect'
        'del_task_manager'
        'getFile'
        'Group_del_admin'
        'START'
        'GetAdminGroups'
        'GetAdmins'
        'DelAdmins'
        'EntityCorrectGroup'
    [Locals+Names]
    [Constants]
        '__pyarmor_assert_13701__'
        '__pyarmor_enter_13702__'
        b'<COAddr>\x07\x00\x00\x1a\xf8\x00\x00\x00\x00\x00\x00\x00\x00\x00\x00\x00\x00\x00\x00\x00'
        0
        None
        (
            'Thread'
            'Event'
        )
        (
            'types'
        )
        (
            'StopProgram'
        )
        (
            'GetLang'
        )
        (
            'Logs'
        )
        (
            'logging'
        )
        (
            'memory_check_switcher'
        )
        (
            'memory_set_pid'
        )
        (
            'Disconnect'
        )
        (
            'account_works'
        )
        (
            'GetConfig'
        )
        (
            'GetProxy'
        )
        (
            'StopDetect'
        )
        (
            'del_task_manager'
        )
        (
            'getFile'
        )
        [Code]
            File Name: <frozen program.modules.Group_del_admin>
            Object Name: Group_del_admin
            Qualified Name: Group_del_admin
            Arg Count: 1
            Pos Only Arg Count: 0
            KW Only Arg Count: 0
            Stack Size: 8
            Flags: 0x20000003 (CO_OPTIMIZED | CO_NEWLOCALS | CO_PYARMOR_OBFUSCATED)
            [Names]
                'get'
                'getFile'
                'GetConfig'
                'config'
                'GetLang'
                'Lang'
                'GetProxy'
                'eel'
                'sendSuccessBox'
                'memory_check_switcher'
                'Event'
                'memory_set_pid'
                'Thread'
                'START'
                'start'
                'Logs'
                'WaitStopAnsfer'
                'UpdateLogInWindow'
                'BaseException'
                'logging'
            [Locals+Names]
                'data'
                '__assert_armored__'
                '_var_var_0'
                '_var_var_1'
                '_var_var_2'
                '_var_var_3'
            [Constants]
                None
                '__pyarmor_assert_13704__'
                '__pyarmor_enter_13705__'
                b'<COAddr>\x05\x00\x00\x1a\xae\x02\x00\x00\x00\x00\x00\x00\x00\x00\x00\x00\x00\x00\x00\x00'
                'action'
                'getFile'
                '__pyarmor_exit_13706__'
                'program_running'   # b'\x81\xf2\n\x1c4\xe8\xbf\xdf$\xe8\x18\xceb\xe5\xf6\x82'
                False
                (
                    'target'
                    'args'
                )
                True
                (
                    'target'
                    'args'
                    'daemon'
                )
            [Disassembly]
                0       NOP                             
                2       NOP                             
                4       PUSH_NULL                       
                6       LOAD_CONST                      2: '__pyarmor_enter_13705__'
                8       LOAD_CONST                      3: b'<COAddr>\x05\x00\x00\x1a\xae\x02\x00\x00\x00\x00\x00\x00\x00\x00\x00\x00\x00\x00\x00\x00'
                10      BUILD_TUPLE                     1
                12      CALL_FUNCTION_EX                0
                14      POP_TOP                         
                16      RESUME                          0
                18      NOP                             
                20      NOP                             
                22      NOP                             
                24      NOP                             
                26      NOP                             
                28      NOP                             
                30      LOAD_FAST                       0: data
                32      LOAD_ATTR                       1: get
                52      LOAD_CONST                      4: 'action'
                54      CALL                            1
                62      POP_JUMP_IF_NONE                28 (to 120)
                64      LOAD_FAST                       0: data
                66      LOAD_CONST                      4: 'action'
                68      BINARY_SUBSCR                   
                72      LOAD_CONST                      5: 'getFile'
                74      COMPARE_OP                      40 (==)
                78      POP_JUMP_IF_FALSE               20 (to 120)
                80      LOAD_GLOBAL                     3: NULL + getFile
                90      LOAD_FAST                       0: data
                92      CALL                            1
                100     NOP                             
                102     NOP                             
                104     JUMP_FORWARD                    316 (to 740)
                108     CALL                            1
                116     POP_TOP                         
                118     RETURN_VALUE                    
                120     LOAD_GLOBAL                     5: NULL + GetConfig
                130     CALL                            0
                138     STORE_GLOBAL                    3: config
                140     LOAD_GLOBAL                     9: NULL + GetLang
                150     LOAD_GLOBAL                     6: config
                160     CALL                            1
                168     STORE_GLOBAL                    5: Lang
                170     LOAD_GLOBAL                     13: NULL + GetProxy
                180     CALL                            0
                188     STORE_FAST                      2: _var_var_0
                190     LOAD_GLOBAL                     15: NULL + eel
                200     LOAD_ATTR                       16: sendSuccessBox
                220     LOAD_GLOBAL                     10: Lang
                230     PUSH_NULL                       
                232     LOAD_CONST                      1: '__pyarmor_assert_13704__'
                234     LOAD_CONST                      7: 'program_running'   # b'\x81\xf2\n\x1c4\xe8\xbf\xdf$\xe8\x18\xceb\xe5\xf6\x82'
                236     CALL                            1
                244     BINARY_SUBSCR                   
                248     CALL                            1
                256     POP_TOP                         
                258     LOAD_GLOBAL                     19: NULL + memory_check_switcher
                268     CALL                            0
                276     POP_JUMP_IF_TRUE                11 (to 300)
                278     NOP                             
                280     LOAD_CONST                      8: False
                282     NOP                             
                284     NOP                             
                286     NOP                             
                288     JUMP_FORWARD                    225 (to 740)
                296     POP_TOP                         
                298     RETURN_CONST                    8: False
                300     LOAD_GLOBAL                     21: NULL + Event
                310     CALL                            0
                318     STORE_FAST                      3: _var_var_1
                320     LOAD_GLOBAL                     23: NULL + memory_set_pid
                330     CALL                            0
                338     STORE_FAST                      4: _var_var_2
                340     LOAD_GLOBAL                     25: NULL + Thread
                350     LOAD_GLOBAL                     26: START
                360     LOAD_FAST                       0: data
                362     LOAD_GLOBAL                     6: config
                372     LOAD_FAST                       4: _var_var_2
                374     LOAD_FAST                       2: _var_var_0
                376     LOAD_FAST                       3: _var_var_1
                378     BUILD_TUPLE                     5
                380     KW_NAMES                        9: ('target', 'args')
                382     CALL                            2
                390     LOAD_ATTR                       29: start
                410     CALL                            0
                418     POP_TOP                         
                420     LOAD_GLOBAL                     25: NULL + Thread
                430     LOAD_GLOBAL                     30: Logs
                440     LOAD_ATTR                       32: WaitStopAnsfer
                460     LOAD_GLOBAL                     6: config
                470     LOAD_FAST                       4: _var_var_2
                472     LOAD_FAST                       3: _var_var_1
                474     BUILD_TUPLE                     3
                476     LOAD_CONST                      10: True
                478     KW_NAMES                        11: ('target', 'args', 'daemon')
                480     CALL                            3
                488     LOAD_ATTR                       29: start
                508     CALL                            0
                516     POP_TOP                         
                518     LOAD_GLOBAL                     25: NULL + Thread
                528     LOAD_GLOBAL                     30: Logs
                538     LOAD_ATTR                       34: UpdateLogInWindow
                558     LOAD_GLOBAL                     6: config
                568     LOAD_FAST                       4: _var_var_2
                570     LOAD_FAST                       3: _var_var_1
                572     BUILD_TUPLE                     3
                574     LOAD_CONST                      10: True
                576     KW_NAMES                        11: ('target', 'args', 'daemon')
                578     CALL                            3
                586     LOAD_ATTR                       29: start
                606     CALL                            0
                614     POP_TOP                         
                616     LOAD_CONST                      0: None
                618     NOP                             
                620     NOP                             
                622     NOP                             
                624     JUMP_FORWARD                    57 (to 740)
                632     POP_TOP                         
                634     RETURN_CONST                    0: None
                636     PUSH_EXC_INFO                   
                638     LOAD_GLOBAL                     36: BaseException
                648     CHECK_EXC_MATCH                 
                650     POP_JUMP_IF_FALSE               26 (to 704)
                652     STORE_FAST                      5: _var_var_3
                654     PUSH_NULL                       
                656     LOAD_GLOBAL                     39: NULL + logging
                666     LOAD_FAST                       5: _var_var_3
                668     CALL                            1
                676     CALL                            0
                684     POP_TOP                         
                686     POP_EXCEPT                      
                688     LOAD_CONST                      0: None
                690     STORE_FAST                      5: _var_var_3
                692     DELETE_FAST                     5: _var_var_3
                694     JUMP_BACKWARD                   40 (to 616)
                696     LOAD_CONST                      0: None
                698     STORE_FAST                      5: _var_var_3
                700     DELETE_FAST                     5: _var_var_3
                702     RERAISE                         1
                704     RERAISE                         0
                706     COPY                            3
                708     POP_EXCEPT                      
                710     RERAISE                         1
                712     PUSH_EXC_INFO                   
                714     PUSH_NULL                       
                716     LOAD_CONST                      6: '__pyarmor_exit_13706__'
                718     NOP                             
                720     LOAD_CONST                      3: b'<COAddr>\x05\x00\x00\x1a\xae\x02\x00\x00\x00\x00\x00\x00\x00\x00\x00\x00\x00\x00\x00\x00'
                722     CALL                            1
                730     POP_TOP                         
                732     RERAISE                         0
                734     COPY                            3
                736     POP_EXCEPT                      
                738     RERAISE                         1
                740     PUSH_NULL                       
                742     LOAD_CONST                      6: '__pyarmor_exit_13706__'
                744     LOAD_CONST                      3: b'<COAddr>\x05\x00\x00\x1a\xae\x02\x00\x00\x00\x00\x00\x00\x00\x00\x00\x00\x00\x00\x00\x00'
                746     BUILD_TUPLE                     1
                748     CALL_FUNCTION_EX                0
                750     POP_TOP                         
                752     RETURN_VALUE                    
            [Exception Table]
                30 to 100 -> 636 [0] 
                120 to 278 -> 636 [0] 
                300 to 616 -> 636 [0] 
                636 to 654 -> 706 [1] lasti
                654 to 686 -> 696 [1] lasti
                686 to 696 -> 712 [0] 
                696 to 706 -> 706 [1] lasti
                706 to 712 -> 712 [0] 
                712 to 734 -> 734 [1] lasti
        [Code]
            File Name: <frozen program.modules.Group_del_admin>
            Object Name: START
            Qualified Name: START
            Arg Count: 5
            Pos Only Arg Count: 0
            KW Only Arg Count: 0
            Stack Size: 7
            Flags: 0x20000003 (CO_OPTIMIZED | CO_NEWLOCALS | CO_PYARMOR_OBFUSCATED)
            [Names]
                'is_set'
                'StopProgram'
                'isinstance'
                'list'
                'len'
                'eel'
                'sendErrorBox'
                'Lang'
                'get'
                'GetAdminGroups'
                'GetAdmins'
                'DelAdmins'
                'BaseException'
                'logging'
                'del_task_manager'
                'StopDetect'
            [Locals+Names]
                'data'
                'config'
                'pid'
                'proxy'
                'stop_thread'
                '__assert_armored__'
                '_var_var_4'
                '_var_var_5'
                '_var_var_6'
                '_var_var_3'
            [Constants]
                None
                '__pyarmor_assert_13707__'
                '__pyarmor_enter_13708__'
                b'<COAddr>\x07\x00\x00\x1aZ\x05\x00\x00\x00\x00\x00\x00\x00\x00\x00\x00\x00\x00\x00\x00'
                'Accounts'
                1
                'select_accounts_works'   # b'\x81\xf1\x1d\x1f6\xf9\xaa\xed\x1a\xf9\x0e\xcfy\xe2\xec\x960J\xb4\xb5\xa1\xd8'
                'action'
                'getGroups'   # b'\x81\xe5\x1d\x07\x14\xe8\xb1\xc7\x0b\xe9'
                0
                'getAdmins'   # b'\x81\xe5\x1d\x07\x12\xfe\xb3\xdb\x15\xe9'
                'Settings'
                'source'
                'not_set_group_or_channel'   # b'\x81\xec\x17\x07\x0c\xe9\xbb\xc6$\xfd\x1f\xcfy\xfc\xc7\x8a\x1db\xb8\xaf\xab\xc5@\xc9\t'
                'users'
                'admins_not_set'   # b'\x81\xe3\x1c\x1e:\xf4\xad\xed\x15\xf5\x19\xff\x7f\xe9\xec'
                'change_rules'   # b'\x81\xe1\x10\x12=\xfd\xbb\xed\t\xef\x01\xc5\x7f'
                False
                'del_admins'   # b'\x81\xe6\x1d\x1f\x0c\xfb\xba\xdf\x12\xf4\x1e'
                'action_not_set'   # b'\x81\xe3\x1b\x07:\xf5\xb0\xed\x15\xf5\x19\xff\x7f\xe9\xec'
                '__pyarmor_exit_13709__'
                'Done'
            [Disassembly]
                0       NOP                             
                2       NOP                             
                4       PUSH_NULL                       
                6       LOAD_CONST                      2: '__pyarmor_enter_13708__'
                8       LOAD_CONST                      3: b'<COAddr>\x07\x00\x00\x1aZ\x05\x00\x00\x00\x00\x00\x00\x00\x00\x00\x00\x00\x00\x00\x00'
                10      BUILD_TUPLE                     1
                12      CALL_FUNCTION_EX                0
                14      POP_TOP                         
                16      RESUME                          0
                18      NOP                             
                20      NOP                             
                22      NOP                             
                24      NOP                             
                26      NOP                             
                28      NOP                             
                30      LOAD_FAST                       4: stop_thread
                32      LOAD_ATTR                       1: is_set
                52      CALL                            0
                60      POP_JUMP_IF_FALSE               10 (to 82)
                62      LOAD_GLOBAL                     3: NULL + StopProgram
                72      CALL                            0
                80      RAISE_VARARGS                   1
                82      LOAD_FAST                       0: data
                84      LOAD_CONST                      4: 'Accounts'
                86      BINARY_SUBSCR                   
                90      STORE_FAST                      6: _var_var_4
                92      LOAD_GLOBAL                     5: NULL + isinstance
                102     LOAD_FAST                       6: _var_var_4
                104     LOAD_GLOBAL                     6: list
                114     CALL                            2
                122     POP_JUMP_IF_TRUE                3 (to 130)
                124     LOAD_FAST                       6: _var_var_4
                126     BUILD_LIST                      1
                128     STORE_FAST                      6: _var_var_4
                130     LOAD_GLOBAL                     9: NULL + len
                140     LOAD_FAST                       6: _var_var_4
                142     CALL                            1
                150     LOAD_CONST                      5: 1
                152     COMPARE_OP                      2 (<)
                156     POP_JUMP_IF_FALSE               44 (to 246)
                158     LOAD_GLOBAL                     11: NULL + eel
                168     LOAD_ATTR                       12: sendErrorBox
                188     LOAD_GLOBAL                     14: Lang
                198     PUSH_NULL                       
                200     LOAD_CONST                      1: '__pyarmor_assert_13707__'
                202     LOAD_CONST                      6: 'select_accounts_works'   # b'\x81\xf1\x1d\x1f6\xf9\xaa\xed\x1a\xf9\x0e\xcfy\xe2\xec\x960J\xb4\xb5\xa1\xd8'
                204     CALL                            1
                212     BINARY_SUBSCR                   
                216     CALL                            1
                224     POP_TOP                         
                226     LOAD_GLOBAL                     3: NULL + StopProgram
                236     CALL                            0
                244     RAISE_VARARGS                   1
                246     LOAD_FAST                       0: data
                248     LOAD_ATTR                       17: get
                268     LOAD_CONST                      7: 'action'
                270     CALL                            1
                278     POP_JUMP_IF_NONE                34 (to 348)
                280     LOAD_FAST                       0: data
                282     LOAD_CONST                      7: 'action'
                284     BINARY_SUBSCR                   
                288     PUSH_NULL                       
                290     LOAD_CONST                      1: '__pyarmor_assert_13707__'
                292     LOAD_CONST                      8: 'getGroups'   # b'\x81\xe5\x1d\x07\x14\xe8\xb1\xc7\x0b\xe9'
                294     CALL                            1
                302     COMPARE_OP                      40 (==)
                306     POP_JUMP_IF_FALSE               20 (to 348)
                308     LOAD_GLOBAL                     19: NULL + GetAdminGroups
                318     LOAD_FAST                       6: _var_var_4
                320     LOAD_CONST                      9: 0
                322     BINARY_SUBSCR                   
                326     LOAD_FAST                       0: data
                328     LOAD_FAST                       1: config
                330     LOAD_FAST                       3: proxy
                332     LOAD_FAST                       4: stop_thread
                334     CALL                            5
                342     POP_TOP                         
                344     JUMP_FORWARD                    405 (to 1158)
                348     LOAD_FAST                       0: data
                350     LOAD_ATTR                       17: get
                370     LOAD_CONST                      7: 'action'
                372     CALL                            1
                380     POP_JUMP_IF_NONE                112 (to 606)
                382     LOAD_FAST                       0: data
                384     LOAD_CONST                      7: 'action'
                386     BINARY_SUBSCR                   
                390     PUSH_NULL                       
                392     LOAD_CONST                      1: '__pyarmor_assert_13707__'
                394     LOAD_CONST                      10: 'getAdmins'   # b'\x81\xe5\x1d\x07\x12\xfe\xb3\xdb\x15\xe9'
                396     CALL                            1
                404     COMPARE_OP                      40 (==)
                408     POP_JUMP_IF_FALSE               98 (to 606)
                410     LOAD_FAST                       0: data
                412     LOAD_CONST                      11: 'Settings'
                414     BINARY_SUBSCR                   
                418     LOAD_ATTR                       17: get
                438     LOAD_CONST                      12: 'source'
                440     CALL                            1
                448     STORE_FAST                      7: _var_var_5
                450     LOAD_GLOBAL                     9: NULL + len
                460     LOAD_FAST                       7: _var_var_5
                462     CALL                            1
                470     LOAD_CONST                      5: 1
                472     COMPARE_OP                      2 (<)
                476     POP_JUMP_IF_FALSE               44 (to 566)
                478     LOAD_GLOBAL                     11: NULL + eel
                488     LOAD_ATTR                       12: sendErrorBox
                508     LOAD_GLOBAL                     14: Lang
                518     PUSH_NULL                       
                520     LOAD_CONST                      1: '__pyarmor_assert_13707__'
                522     LOAD_CONST                      13: 'not_set_group_or_channel'   # b'\x81\xec\x17\x07\x0c\xe9\xbb\xc6$\xfd\x1f\xcfy\xfc\xc7\x8a\x1db\xb8\xaf\xab\xc5@\xc9\t'
                524     CALL                            1
                532     BINARY_SUBSCR                   
                536     CALL                            1
                544     POP_TOP                         
                546     LOAD_GLOBAL                     3: NULL + StopProgram
                556     CALL                            0
                564     RAISE_VARARGS                   1
                566     LOAD_GLOBAL                     21: NULL + GetAdmins
                576     LOAD_FAST                       6: _var_var_4
                578     LOAD_CONST                      9: 0
                580     BINARY_SUBSCR                   
                584     LOAD_FAST                       0: data
                586     LOAD_FAST                       1: config
                588     LOAD_FAST                       3: proxy
                590     LOAD_FAST                       4: stop_thread
                592     CALL                            5
                600     POP_TOP                         
                602     JUMP_FORWARD                    276 (to 1158)
                606     LOAD_FAST                       0: data
                608     LOAD_CONST                      11: 'Settings'
                610     BINARY_SUBSCR                   
                614     LOAD_ATTR                       17: get
                634     LOAD_CONST                      12: 'source'
                636     CALL                            1
                644     STORE_FAST                      7: _var_var_5
                646     LOAD_FAST                       0: data
                648     LOAD_CONST                      11: 'Settings'
                650     BINARY_SUBSCR                   
                654     LOAD_ATTR                       17: get
                674     LOAD_CONST                      14: 'users'
                676     CALL                            1
                684     STORE_FAST                      8: _var_var_6
                686     LOAD_GLOBAL                     9: NULL + len
                696     LOAD_FAST                       7: _var_var_5
                698     CALL                            1
                706     LOAD_CONST                      5: 1
                708     COMPARE_OP                      2 (<)
                712     POP_JUMP_IF_FALSE               44 (to 802)
                714     LOAD_GLOBAL                     11: NULL + eel
                724     LOAD_ATTR                       12: sendErrorBox
                744     LOAD_GLOBAL                     14: Lang
                754     PUSH_NULL                       
                756     LOAD_CONST                      1: '__pyarmor_assert_13707__'
                758     LOAD_CONST                      13: 'not_set_group_or_channel'   # b'\x81\xec\x17\x07\x0c\xe9\xbb\xc6$\xfd\x1f\xcfy\xfc\xc7\x8a\x1db\xb8\xaf\xab\xc5@\xc9\t'
                760     CALL                            1
                768     BINARY_SUBSCR                   
                772     CALL                            1
                780     POP_TOP                         
                782     LOAD_GLOBAL                     3: NULL + StopProgram
                792     CALL                            0
                800     RAISE_VARARGS                   1
                802     LOAD_GLOBAL                     9: NULL + len
                812     LOAD_FAST                       8: _var_var_6
                814     CALL                            1
                822     LOAD_CONST                      5: 1
                824     COMPARE_OP                      2 (<)
                828     POP_JUMP_IF_FALSE               44 (to 918)
                830     LOAD_GLOBAL                     11: NULL + eel
                840     LOAD_ATTR                       12: sendErrorBox
                860     LOAD_GLOBAL                     14: Lang
                870     PUSH_NULL                       
                872     LOAD_CONST                      1: '__pyarmor_assert_13707__'
                874     LOAD_CONST                      15: 'admins_not_set'   # b'\x81\xe3\x1c\x1e:\xf4\xad\xed\x15\xf5\x19\xff\x7f\xe9\xec'
                876     CALL                            1
                884     BINARY_SUBSCR                   
                888     CALL                            1
                896     POP_TOP                         
                898     LOAD_GLOBAL                     3: NULL + StopProgram
                908     CALL                            0
                916     RAISE_VARARGS                   1
                918     LOAD_FAST                       0: data
                920     LOAD_CONST                      11: 'Settings'
                922     BINARY_SUBSCR                   
                926     LOAD_ATTR                       17: get
                946     PUSH_NULL                       
                948     LOAD_CONST                      1: '__pyarmor_assert_13707__'
                950     LOAD_CONST                      16: 'change_rules'   # b'\x81\xe1\x10\x12=\xfd\xbb\xed\t\xef\x01\xc5\x7f'
                952     CALL                            1
                960     CALL                            1
                968     LOAD_CONST                      17: False
                970     COMPARE_OP                      40 (==)
                974     POP_JUMP_IF_FALSE               73 (to 1122)
                976     LOAD_FAST                       0: data
                978     LOAD_CONST                      11: 'Settings'
                980     BINARY_SUBSCR                   
                984     LOAD_ATTR                       17: get
                1004    PUSH_NULL                       
                1006    LOAD_CONST                      1: '__pyarmor_assert_13707__'
                1008    LOAD_CONST                      18: 'del_admins'   # b'\x81\xe6\x1d\x1f\x0c\xfb\xba\xdf\x12\xf4\x1e'
                1010    CALL                            1
                1018    CALL                            1
                1026    LOAD_CONST                      17: False
                1028    COMPARE_OP                      40 (==)
                1032    POP_JUMP_IF_FALSE               44 (to 1122)
                1034    LOAD_GLOBAL                     11: NULL + eel
                1044    LOAD_ATTR                       12: sendErrorBox
                1064    LOAD_GLOBAL                     14: Lang
                1074    PUSH_NULL                       
                1076    LOAD_CONST                      1: '__pyarmor_assert_13707__'
                1078    LOAD_CONST                      19: 'action_not_set'   # b'\x81\xe3\x1b\x07:\xf5\xb0\xed\x15\xf5\x19\xff\x7f\xe9\xec'
                1080    CALL                            1
                1088    BINARY_SUBSCR                   
                1092    CALL                            1
                1100    POP_TOP                         
                1102    LOAD_GLOBAL                     3: NULL + StopProgram
                1112    CALL                            0
                1120    RAISE_VARARGS                   1
                1122    LOAD_GLOBAL                     23: NULL + DelAdmins
                1132    LOAD_FAST                       6: _var_var_4
                1134    LOAD_CONST                      9: 0
                1136    BINARY_SUBSCR                   
                1140    LOAD_FAST                       0: data
                1142    LOAD_FAST                       1: config
                1144    LOAD_FAST                       3: proxy
                1146    LOAD_FAST                       4: stop_thread
                1148    CALL                            5
                1156    POP_TOP                         
                1158    LOAD_GLOBAL                     29: NULL + del_task_manager
                1168    LOAD_FAST                       2: pid
                1170    CALL                            1
                1178    POP_TOP                         
                1180    LOAD_GLOBAL                     31: NULL + StopDetect
                1190    LOAD_FAST                       4: stop_thread
                1192    CALL                            1
                1200    POP_TOP                         
                1202    NOP                             
                1204    LOAD_CONST                      21: 'Done'
                1206    NOP                             
                1208    NOP                             
                1210    NOP                             
                1212    JUMP_FORWARD                    105 (to 1424)
                1220    POP_TOP                         
                1222    RETURN_CONST                    21: 'Done'
                1224    PUSH_EXC_INFO                   
                1226    LOAD_GLOBAL                     2: StopProgram
                1236    CHECK_EXC_MATCH                 
                1238    POP_JUMP_IF_FALSE               3 (to 1246)
                1240    POP_TOP                         
                1242    POP_EXCEPT                      
                1244    JUMP_BACKWARD                   44 (to 1158)
                1246    LOAD_GLOBAL                     24: BaseException
                1256    CHECK_EXC_MATCH                 
                1258    POP_JUMP_IF_FALSE               26 (to 1312)
                1260    STORE_FAST                      9: _var_var_3
                1262    PUSH_NULL                       
                1264    LOAD_GLOBAL                     27: NULL + logging
                1274    LOAD_FAST                       9: _var_var_3
                1276    CALL                            1
                1284    CALL                            0
                1292    POP_TOP                         
                1294    POP_EXCEPT                      
                1296    LOAD_CONST                      0: None
                1298    STORE_FAST                      9: _var_var_3
                1300    DELETE_FAST                     9: _var_var_3
                1302    JUMP_BACKWARD                   73 (to 1158)
                1304    LOAD_CONST                      0: None
                1306    STORE_FAST                      9: _var_var_3
                1308    DELETE_FAST                     9: _var_var_3
                1310    RERAISE                         1
                1312    RERAISE                         0
                1314    COPY                            3
                1316    POP_EXCEPT                      
                1318    RERAISE                         1
                1320    PUSH_EXC_INFO                   
                1322    LOAD_GLOBAL                     29: NULL + del_task_manager
                1332    LOAD_FAST                       2: pid
                1334    CALL                            1
                1342    POP_TOP                         
                1344    LOAD_GLOBAL                     31: NULL + StopDetect
                1354    LOAD_FAST                       4: stop_thread
                1356    CALL                            1
                1364    POP_TOP                         
                1366    POP_TOP                         
                1368    POP_EXCEPT                      
                1370    LOAD_CONST                      21: 'Done'
                1372    NOP                             
                1374    NOP                             
                1376    NOP                             
                1378    JUMP_FORWARD                    22 (to 1424)
                1386    POP_TOP                         
                1388    RETURN_CONST                    21: 'Done'
                1390    COPY                            3
                1392    POP_EXCEPT                      
                1394    RERAISE                         1
                1396    PUSH_EXC_INFO                   
                1398    PUSH_NULL                       
                1400    LOAD_CONST                      20: '__pyarmor_exit_13709__'
                1402    NOP                             
                1404    LOAD_CONST                      3: b'<COAddr>\x07\x00\x00\x1aZ\x05\x00\x00\x00\x00\x00\x00\x00\x00\x00\x00\x00\x00\x00\x00'
                1406    CALL                            1
                1414    POP_TOP                         
                1416    RERAISE                         0
                1418    COPY                            3
                1420    POP_EXCEPT                      
                1422    RERAISE                         1
                1424    PUSH_NULL                       
                1426    LOAD_CONST                      20: '__pyarmor_exit_13709__'
                1428    LOAD_CONST                      3: b'<COAddr>\x07\x00\x00\x1aZ\x05\x00\x00\x00\x00\x00\x00\x00\x00\x00\x00\x00\x00\x00\x00'
                1430    BUILD_TUPLE                     1
                1432    CALL_FUNCTION_EX                0
                1434    POP_TOP                         
                1436    RETURN_VALUE                    
            [Exception Table]
                30 to 1158 -> 1224 [0] 
                1158 to 1202 -> 1396 [0] 
                1224 to 1242 -> 1314 [1] lasti
                1242 to 1246 -> 1320 [0] 
                1246 to 1262 -> 1314 [1] lasti
                1262 to 1294 -> 1304 [1] lasti
                1294 to 1304 -> 1320 [0] 
                1304 to 1314 -> 1314 [1] lasti
                1314 to 1320 -> 1320 [0] 
                1320 to 1368 -> 1390 [1] lasti
                1368 to 1370 -> 1396 [0] 
                1390 to 1396 -> 1396 [0] 
                1396 to 1418 -> 1418 [1] lasti
        [Code]
            File Name: <frozen program.modules.Group_del_admin>
            Object Name: GetAdminGroups
            Qualified Name: GetAdminGroups
            Arg Count: 5
            Pos Only Arg Count: 0
            KW Only Arg Count: 0
            Stack Size: 10
            Flags: 0x20000003 (CO_OPTIMIZED | CO_NEWLOCALS | CO_PYARMOR_OBFUSCATED)
            [Names]
                'account_works'
                'Lang'
                'Disconnect'
                'Logs'
                'PrintLog'
                'is_set'
                'StopProgram'
                'iter_dialogs'
                'hasattr'
                'entity'
                'creator'
                'admin_rights'
                'EntityCorrectGroup'
                'append'
                'id'
                'Exception'
                'eel'
                'ShowList'
                'BaseException'
                'logging'
            [Locals+Names]
                'account'
                'data'
                'config'
                'proxy'
                'stop_thread'
                '__assert_armored__'
                '_var_var_7'
                '_var_var_8'
                '_var_var_9'
                '_var_var_10'
                '_var_var_11'
                '_var_var_12'
                '_var_var_13'
                '_var_var_3'
            [Constants]
                None
                '__pyarmor_assert_13710__'
                '__pyarmor_enter_13711__'
                b'<COAddr>\x05\x00\x00\x1a\xae\x05\x00\x00\x00\x00\x00\x00\x00\x00\x00\x00\x00\x00\x00\x00'
                'DelAdmin'
                (
                    'module'
                )
                False
                'false'
                (
                    'account'
                    'status'
                )
                'work_account_completed'   # b'\x81\xf5\x17\x018\xc5\xbf\xd1\x18\xf5\x18\xcex\xd3\xfb\x8a\x02M\xb7\xa2\xbe\xceJ'
                (
                    'config'
                    'account'
                    'message'
                )
                'done'
                '__pyarmor_exit_13712__'
                500
                (
                    'limit'
                )
                'entity'
                'creator'
                'admin_rights'   # b'\x81\xe3\x1c\x1e:\xf4\x81\xc0\x12\xfd\x05\xd4\x7f'
                True
                'type'
                'MEGA_GROUP'   # b'\x81\xcf=4\x12\xc5\x99\xe04\xcf='
                'GIGA_GROUP'   # b'\x81\xc514\x12\xc5\x99\xe04\xcf='
                'title'
                'CHANNEL'
                'error_detected'   # b'\x81\xe7\n\x01<\xe8\x81\xd6\x1e\xee\x08\xc3x\xe9\xfc'
                (
                    'config'
                    'account'
                    'message'
                    'param'
                )
                'channels'
                'groups'
            [Disassembly]
                0       NOP                             
                2       NOP                             
                4       PUSH_NULL                       
                6       LOAD_CONST                      2: '__pyarmor_enter_13711__'
                8       LOAD_CONST                      3: b'<COAddr>\x05\x00\x00\x1a\xae\x05\x00\x00\x00\x00\x00\x00\x00\x00\x00\x00\x00\x00\x00\x00'
                10      BUILD_TUPLE                     1
                12      CALL_FUNCTION_EX                0
                14      POP_TOP                         
                16      RESUME                          0
                18      NOP                             
                20      NOP                             
                22      NOP                             
                24      NOP                             
                26      NOP                             
                28      NOP                             
                30      LOAD_GLOBAL                     1: NULL + account_works
                40      LOAD_FAST                       2: config
                42      LOAD_GLOBAL                     2: Lang
                52      LOAD_FAST                       3: proxy
                54      LOAD_FAST                       0: account
                56      LOAD_FAST                       4: stop_thread
                58      LOAD_CONST                      4: 'DelAdmin'
                60      KW_NAMES                        5: ('module',)
                62      CALL                            6
                70      STORE_FAST                      6: _var_var_7
                72      LOAD_FAST                       6: _var_var_7
                74      LOAD_CONST                      6: False
                76      COMPARE_OP                      40 (==)
                80      POP_JUMP_IF_FALSE               68 (to 218)
                82      LOAD_FAST                       0: account
                84      LOAD_CONST                      7: 'false'
                86      LOAD_CONST                      8: ('account', 'status')
                88      BUILD_CONST_KEY_MAP             2
                90      LOAD_GLOBAL                     5: NULL + Disconnect
                100     LOAD_FAST                       6: _var_var_7
                102     CALL                            1
                110     POP_TOP                         
                112     LOAD_GLOBAL                     7: NULL + Logs
                122     LOAD_ATTR                       8: PrintLog
                142     LOAD_FAST                       2: config
                144     LOAD_FAST                       0: account
                146     LOAD_GLOBAL                     2: Lang
                156     PUSH_NULL                       
                158     LOAD_CONST                      1: '__pyarmor_assert_13710__'
                160     LOAD_CONST                      9: 'work_account_completed'   # b'\x81\xf5\x17\x018\xc5\xbf\xd1\x18\xf5\x18\xcex\xd3\xfb\x8a\x02M\xb7\xa2\xbe\xceJ'
                162     CALL                            1
                170     BINARY_SUBSCR                   
                174     KW_NAMES                        10: ('config', 'account', 'message')
                176     CALL                            3
                184     POP_TOP                         
                186     LOAD_FAST                       0: account
                188     LOAD_CONST                      11: 'done'
                190     LOAD_CONST                      8: ('account', 'status')
                192     BUILD_CONST_KEY_MAP             2
                194     SWAP                            2
                196     POP_TOP                         
                198     NOP                             
                200     NOP                             
                202     JUMP_FORWARD                    651 (to 1508)
                206     CALL                            1
                214     POP_TOP                         
                216     RETURN_VALUE                    
                218     LOAD_FAST                       4: stop_thread
                220     LOAD_ATTR                       11: is_set
                240     CALL                            0
                248     POP_JUMP_IF_FALSE               10 (to 270)
                250     LOAD_GLOBAL                     13: NULL + StopProgram
                260     CALL                            0
                268     RAISE_VARARGS                   1
                270     BUILD_LIST                      0
                272     STORE_FAST                      7: _var_var_8
                274     BUILD_LIST                      0
                276     STORE_FAST                      8: _var_var_9
                278     BUILD_LIST                      0
                280     STORE_FAST                      9: _var_var_10
                282     LOAD_FAST                       6: _var_var_7
                284     LOAD_ATTR                       15: iter_dialogs
                304     LOAD_CONST                      13: 500
                306     KW_NAMES                        14: ('limit',)
                308     CALL                            1
                316     GET_ITER                        
                318     FOR_ITER                        269 (to 860)
                324     STORE_FAST                      10: _var_var_11
                326     LOAD_FAST                       4: stop_thread
                328     LOAD_ATTR                       11: is_set
                348     CALL                            0
                356     POP_JUMP_IF_FALSE               10 (to 378)
                358     LOAD_GLOBAL                     13: NULL + StopProgram
                368     CALL                            0
                376     RAISE_VARARGS                   1
                378     LOAD_GLOBAL                     17: NULL + hasattr
                388     LOAD_FAST                       10: _var_var_11
                390     LOAD_CONST                      15: 'entity'
                392     CALL                            2
                400     POP_JUMP_IF_TRUE                1 (to 404)
                402     JUMP_BACKWARD                   43 (to 318)
                404     LOAD_GLOBAL                     17: NULL + hasattr
                414     LOAD_FAST                       10: _var_var_11
                416     LOAD_ATTR                       18: entity
                436     LOAD_CONST                      16: 'creator'
                438     CALL                            2
                446     POP_JUMP_IF_TRUE                1 (to 450)
                448     JUMP_BACKWARD                   66 (to 318)
                450     LOAD_GLOBAL                     17: NULL + hasattr
                460     LOAD_FAST                       10: _var_var_11
                462     LOAD_ATTR                       18: entity
                482     PUSH_NULL                       
                484     LOAD_CONST                      1: '__pyarmor_assert_13710__'
                486     LOAD_CONST                      17: 'admin_rights'   # b'\x81\xe3\x1c\x1e:\xf4\x81\xc0\x12\xfd\x05\xd4\x7f'
                488     CALL                            1
                496     CALL                            2
                504     POP_JUMP_IF_TRUE                1 (to 508)
                506     JUMP_BACKWARD                   95 (to 318)
                508     LOAD_FAST                       10: _var_var_11
                510     LOAD_ATTR                       18: entity
                530     LOAD_ATTR                       20: creator
                550     LOAD_CONST                      18: True
                552     COMPARE_OP                      40 (==)
                556     POP_JUMP_IF_TRUE                23 (to 604)
                558     LOAD_FAST                       10: _var_var_11
                560     LOAD_ATTR                       18: entity
                580     LOAD_ATTR                       22: admin_rights
                600     POP_JUMP_IF_NOT_NONE            1 (to 604)
                602     JUMP_BACKWARD                   143 (to 318)
                604     NOP                             
                606     LOAD_GLOBAL                     25: NULL + EntityCorrectGroup
                616     LOAD_FAST                       10: _var_var_11
                618     LOAD_ATTR                       18: entity
                638     CALL                            1
                646     STORE_FAST                      11: _var_var_12
                648     LOAD_FAST                       11: _var_var_12
                650     LOAD_CONST                      6: False
                652     COMPARE_OP                      55 (!=)
                656     POP_JUMP_IF_FALSE               100 (to 858)
                658     LOAD_FAST                       11: _var_var_12
                660     LOAD_CONST                      19: 'type'
                662     BINARY_SUBSCR                   
                666     PUSH_NULL                       
                668     LOAD_CONST                      1: '__pyarmor_assert_13710__'
                670     LOAD_CONST                      20: 'MEGA_GROUP'   # b'\x81\xcf=4\x12\xc5\x99\xe04\xcf='
                672     CALL                            1
                680     COMPARE_OP                      40 (==)
                684     POP_JUMP_IF_TRUE                14 (to 714)
                686     LOAD_FAST                       11: _var_var_12
                688     LOAD_CONST                      19: 'type'
                690     BINARY_SUBSCR                   
                694     PUSH_NULL                       
                696     LOAD_CONST                      1: '__pyarmor_assert_13710__'
                698     LOAD_CONST                      21: 'GIGA_GROUP'   # b'\x81\xc514\x12\xc5\x99\xe04\xcf='
                700     CALL                            1
                708     COMPARE_OP                      40 (==)
                712     POP_JUMP_IF_FALSE               32 (to 778)
                714     LOAD_FAST                       8: _var_var_9
                716     LOAD_ATTR                       27: append
                736     LOAD_FAST                       10: _var_var_11
                738     LOAD_ATTR                       28: id
                758     LOAD_FAST                       11: _var_var_12
                760     LOAD_CONST                      22: 'title'
                762     BINARY_SUBSCR                   
                766     BUILD_LIST                      2
                768     CALL                            1
                776     POP_TOP                         
                778     LOAD_FAST                       11: _var_var_12
                780     LOAD_CONST                      19: 'type'
                782     BINARY_SUBSCR                   
                786     LOAD_CONST                      23: 'CHANNEL'
                788     COMPARE_OP                      40 (==)
                792     POP_JUMP_IF_FALSE               32 (to 858)
                794     LOAD_FAST                       7: _var_var_8
                796     LOAD_ATTR                       27: append
                816     LOAD_FAST                       10: _var_var_11
                818     LOAD_ATTR                       28: id
                838     LOAD_FAST                       11: _var_var_12
                840     LOAD_CONST                      22: 'title'
                842     BINARY_SUBSCR                   
                846     BUILD_LIST                      2
                848     CALL                            1
                856     POP_TOP                         
                858     JUMP_BACKWARD                   272 (to 318)
                862     END_FOR                         
                864     LOAD_GLOBAL                     33: NULL + eel
                874     LOAD_ATTR                       34: ShowList
                894     LOAD_CONST                      26: 'channels'
                896     LOAD_FAST                       7: _var_var_8
                898     CALL                            2
                906     POP_TOP                         
                908     LOAD_GLOBAL                     33: NULL + eel
                918     LOAD_ATTR                       34: ShowList
                938     LOAD_CONST                      27: 'groups'
                940     LOAD_FAST                       8: _var_var_9
                942     CALL                            2
                950     POP_TOP                         
                952     LOAD_GLOBAL                     5: NULL + Disconnect
                962     LOAD_FAST_CHECK                 6: _var_var_7
                964     CALL                            1
                972     POP_TOP                         
                974     LOAD_GLOBAL                     7: NULL + Logs
                984     LOAD_ATTR                       8: PrintLog
                1004    LOAD_FAST                       2: config
                1006    LOAD_FAST                       0: account
                1008    LOAD_GLOBAL                     2: Lang
                1018    PUSH_NULL                       
                1020    LOAD_CONST                      1: '__pyarmor_assert_13710__'
                1022    LOAD_CONST                      9: 'work_account_completed'   # b'\x81\xf5\x17\x018\xc5\xbf\xd1\x18\xf5\x18\xcex\xd3\xfb\x8a\x02M\xb7\xa2\xbe\xceJ'
                1024    CALL                            1
                1032    BINARY_SUBSCR                   
                1036    KW_NAMES                        10: ('config', 'account', 'message')
                1038    CALL                            3
                1046    POP_TOP                         
                1048    LOAD_FAST                       0: account
                1050    LOAD_CONST                      11: 'done'
                1052    LOAD_CONST                      8: ('account', 'status')
                1054    BUILD_CONST_KEY_MAP             2
                1056    NOP                             
                1058    NOP                             
                1060    NOP                             
                1062    JUMP_FORWARD                    222 (to 1508)
                1064    CALL                            1
                1072    POP_TOP                         
                1074    RETURN_VALUE                    
                1076    PUSH_EXC_INFO                   
                1078    POP_TOP                         
                1080    POP_EXCEPT                      
                1082    JUMP_BACKWARD                   487 (to 112)
                1086    COPY                            3
                1088    POP_EXCEPT                      
                1090    RERAISE                         1
                1092    PUSH_EXC_INFO                   
                1094    LOAD_GLOBAL                     30: Exception
                1104    CHECK_EXC_MATCH                 
                1106    POP_JUMP_IF_FALSE               49 (to 1206)
                1108    STORE_FAST                      12: _var_var_13
                1110    LOAD_GLOBAL                     7: NULL + Logs
                1120    LOAD_ATTR                       8: PrintLog
                1140    LOAD_FAST                       2: config
                1142    LOAD_FAST                       0: account
                1144    LOAD_GLOBAL                     2: Lang
                1154    PUSH_NULL                       
                1156    LOAD_CONST                      1: '__pyarmor_assert_13710__'
                1158    LOAD_CONST                      24: 'error_detected'   # b'\x81\xe7\n\x01<\xe8\x81\xd6\x1e\xee\x08\xc3x\xe9\xfc'
                1160    CALL                            1
                1168    BINARY_SUBSCR                   
                1172    LOAD_FAST                       12: _var_var_13
                1174    KW_NAMES                        25: ('config', 'account', 'message', 'param')
                1176    CALL                            4
                1184    POP_TOP                         
                1186    POP_EXCEPT                      
                1188    LOAD_CONST                      0: None
                1190    STORE_FAST                      12: _var_var_13
                1192    DELETE_FAST                     12: _var_var_13
                1194    JUMP_BACKWARD                   440 (to 318)
                1198    LOAD_CONST                      0: None
                1200    STORE_FAST                      12: _var_var_13
                1202    DELETE_FAST                     12: _var_var_13
                1204    RERAISE                         1
                1206    RERAISE                         0
                1208    COPY                            3
                1210    POP_EXCEPT                      
                1212    RERAISE                         1
                1214    PUSH_EXC_INFO                   
                1216    LOAD_GLOBAL                     12: StopProgram
                1226    CHECK_EXC_MATCH                 
                1228    POP_JUMP_IF_FALSE               3 (to 1236)
                1230    POP_TOP                         
                1232    POP_EXCEPT                      
                1234    JUMP_BACKWARD                   142 (to 952)
                1236    LOAD_GLOBAL                     36: BaseException
                1246    CHECK_EXC_MATCH                 
                1248    POP_JUMP_IF_FALSE               26 (to 1302)
                1250    STORE_FAST                      13: _var_var_3
                1252    PUSH_NULL                       
                1254    LOAD_GLOBAL                     39: NULL + logging
                1264    LOAD_FAST                       13: _var_var_3
                1266    CALL                            1
                1274    CALL                            0
                1282    POP_TOP                         
                1284    POP_EXCEPT                      
                1286    LOAD_CONST                      0: None
                1288    STORE_FAST                      13: _var_var_3
                1290    DELETE_FAST                     13: _var_var_3
                1292    JUMP_BACKWARD                   171 (to 952)
                1294    LOAD_CONST                      0: None
                1296    STORE_FAST                      13: _var_var_3
                1298    DELETE_FAST                     13: _var_var_3
                1300    RERAISE                         1
                1302    RERAISE                         0
                1304    COPY                            3
                1306    POP_EXCEPT                      
                1308    RERAISE                         1
                1310    PUSH_EXC_INFO                   
                1312    POP_TOP                         
                1314    POP_EXCEPT                      
                1316    JUMP_BACKWARD                   172 (to 974)
                1318    COPY                            3
                1320    POP_EXCEPT                      
                1322    RERAISE                         1
                1324    PUSH_EXC_INFO                   
                1326    LOAD_GLOBAL                     5: NULL + Disconnect
                1336    LOAD_FAST_CHECK                 6: _var_var_7
                1338    CALL                            1
                1346    POP_TOP                         
                1348    JUMP_FORWARD                    7 (to 1364)
                1350    PUSH_EXC_INFO                   
                1352    POP_TOP                         
                1354    POP_EXCEPT                      
                1356    JUMP_FORWARD                    3 (to 1364)
                1358    COPY                            3
                1360    POP_EXCEPT                      
                1362    RERAISE                         1
                1364    LOAD_GLOBAL                     7: NULL + Logs
                1374    LOAD_ATTR                       8: PrintLog
                1394    LOAD_FAST                       2: config
                1396    LOAD_FAST                       0: account
                1398    LOAD_GLOBAL                     2: Lang
                1408    PUSH_NULL                       
                1410    LOAD_CONST                      1: '__pyarmor_assert_13710__'
                1412    LOAD_CONST                      9: 'work_account_completed'   # b'\x81\xf5\x17\x018\xc5\xbf\xd1\x18\xf5\x18\xcex\xd3\xfb\x8a\x02M\xb7\xa2\xbe\xceJ'
                1414    CALL                            1
                1422    BINARY_SUBSCR                   
                1426    KW_NAMES                        10: ('config', 'account', 'message')
                1428    CALL                            3
                1436    POP_TOP                         
                1438    LOAD_FAST                       0: account
                1440    LOAD_CONST                      11: 'done'
                1442    LOAD_CONST                      8: ('account', 'status')
                1444    BUILD_CONST_KEY_MAP             2
                1446    SWAP                            2
                1448    POP_TOP                         
                1450    SWAP                            2
                1452    POP_EXCEPT                      
                1454    NOP                             
                1456    NOP                             
                1458    NOP                             
                1460    JUMP_FORWARD                    23 (to 1508)
                1462    CALL                            1
                1470    POP_TOP                         
                1472    RETURN_VALUE                    
                1474    COPY                            3
                1476    POP_EXCEPT                      
                1478    RERAISE                         1
                1480    PUSH_EXC_INFO                   
                1482    PUSH_NULL                       
                1484    LOAD_CONST                      12: '__pyarmor_exit_13712__'
                1486    NOP                             
                1488    LOAD_CONST                      3: b'<COAddr>\x05\x00\x00\x1a\xae\x05\x00\x00\x00\x00\x00\x00\x00\x00\x00\x00\x00\x00\x00\x00'
                1490    CALL                            1
                1498    POP_TOP                         
                1500    RERAISE                         0
                1502    COPY                            3
                1504    POP_EXCEPT                      
                1506    RERAISE                         1
                1508    PUSH_NULL                       
                1510    LOAD_CONST                      12: '__pyarmor_exit_13712__'
                1512    LOAD_CONST                      3: b'<COAddr>\x05\x00\x00\x1a\xae\x05\x00\x00\x00\x00\x00\x00\x00\x00\x00\x00\x00\x00\x00\x00'
                1514    BUILD_TUPLE                     1
                1516    CALL_FUNCTION_EX                0
                1518    POP_TOP                         
                1520    RETURN_VALUE                    
            [Exception Table]
                30 to 90 -> 1214 [0] 
                90 to 112 -> 1076 [1] 
                112 to 198 -> 1480 [0] 
                218 to 402 -> 1214 [0] 
                404 to 448 -> 1214 [0] 
                450 to 506 -> 1214 [0] 
                508 to 602 -> 1214 [0] 
                606 to 858 -> 1092 [1] 
                858 to 952 -> 1214 [0] 
                952 to 974 -> 1310 [0] 
                974 to 1056 -> 1480 [0] 
                1076 to 1080 -> 1086 [2] lasti
                1080 to 1092 -> 1480 [0] 
                1092 to 1110 -> 1208 [2] lasti
                1110 to 1186 -> 1198 [2] lasti
                1186 to 1198 -> 1214 [0] 
                1198 to 1208 -> 1208 [2] lasti
                1208 to 1214 -> 1214 [0] 
                1214 to 1232 -> 1304 [1] lasti
                1232 to 1236 -> 1324 [0] 
                1236 to 1252 -> 1304 [1] lasti
                1252 to 1284 -> 1294 [1] lasti
                1284 to 1294 -> 1324 [0] 
                1294 to 1304 -> 1304 [1] lasti
                1304 to 1310 -> 1324 [0] 
                1310 to 1314 -> 1318 [1] lasti
                1314 to 1324 -> 1480 [0] 
                1324 to 1326 -> 1474 [1] lasti
                1326 to 1348 -> 1350 [2] 
                1348 to 1350 -> 1474 [1] lasti
                1350 to 1354 -> 1358 [3] lasti
                1354 to 1452 -> 1474 [1] lasti
                1452 to 1454 -> 1480 [0] 
                1474 to 1480 -> 1480 [0] 
                1480 to 1502 -> 1502 [1] lasti
        [Code]
            File Name: <frozen program.modules.Group_del_admin>
            Object Name: GetAdmins
            Qualified Name: GetAdmins
            Arg Count: 5
            Pos Only Arg Count: 0
            KW Only Arg Count: 0
            Stack Size: 10
            Flags: 0x20000003 (CO_OPTIMIZED | CO_NEWLOCALS | CO_PYARMOR_OBFUSCATED)
            [Names]
                'account_works'
                'Lang'
                'Disconnect'
                'Logs'
                'PrintLog'
                'is_set'
                'StopProgram'
                'get'
                'iter_dialogs'
                'hasattr'
                'str'
                'id'
                'iter_participants'
                'entity'
                'types'
                'ChannelParticipantsAdmins'
                'last_name'
                'first_name'
                'append'
                'Exception'
                'eel'
                'ShowList'
                'BaseException'
                'logging'
            [Locals+Names]
                'account'
                'data'
                'config'
                'proxy'
                'stop_thread'
                '__assert_armored__'
                '_var_var_7'
                '_var_var_5'
                '_var_var_14'
                '_var_var_6'
                '_var_var_11'
                '_var_var_15'
                '_var_var_16'
                '_var_var_17'
                '_var_var_13'
                '_var_var_3'
            [Constants]
                None
                '__pyarmor_assert_13713__'
                '__pyarmor_enter_13714__'
                b'<COAddr>\x07\x00\x00\x1a\x82\x05\x00\x00\x00\x00\x00\x00\x00\x00\x00\x00\x00\x00\x00\x00'
                'DelAdmin'
                (
                    'module'
                )
                False
                'false'
                (
                    'account'
                    'status'
                )
                'work_account_completed'   # b'\x81\xf5\x17\x018\xc5\xbf\xd1\x18\xf5\x18\xcex\xd3\xfb\x8a\x02M\xb7\xa2\xbe\xceJ'
                (
                    'config'
                    'account'
                    'message'
                )
                'done'
                '__pyarmor_exit_13715__'
                'Settings'
                'source'
                500
                (
                    'limit'
                )
                'id'
                True
                'entity'
                (
                    'filter'
                )
                'last_name'   # b"\x81\xee\x19\x00'\xc5\xb0\xd3\x16\xff"
                ''
                'error_detected'   # b'\x81\xe7\n\x01<\xe8\x81\xd6\x1e\xee\x08\xc3x\xe9\xfc'
                (
                    'config'
                    'account'
                    'message'
                    'param'
                )
                'users'
            [Disassembly]
                0       NOP                             
                2       NOP                             
                4       PUSH_NULL                       
                6       LOAD_CONST                      2: '__pyarmor_enter_13714__'
                8       LOAD_CONST                      3: b'<COAddr>\x07\x00\x00\x1a\x82\x05\x00\x00\x00\x00\x00\x00\x00\x00\x00\x00\x00\x00\x00\x00'
                10      BUILD_TUPLE                     1
                12      CALL_FUNCTION_EX                0
                14      POP_TOP                         
                16      RESUME                          0
                18      NOP                             
                20      NOP                             
                22      NOP                             
                24      NOP                             
                26      NOP                             
                28      NOP                             
                30      LOAD_GLOBAL                     1: NULL + account_works
                40      LOAD_FAST                       2: config
                42      LOAD_GLOBAL                     2: Lang
                52      LOAD_FAST                       3: proxy
                54      LOAD_FAST                       0: account
                56      LOAD_FAST                       4: stop_thread
                58      LOAD_CONST                      4: 'DelAdmin'
                60      KW_NAMES                        5: ('module',)
                62      CALL                            6
                70      STORE_FAST                      6: _var_var_7
                72      LOAD_FAST                       6: _var_var_7
                74      LOAD_CONST                      6: False
                76      COMPARE_OP                      40 (==)
                80      POP_JUMP_IF_FALSE               68 (to 218)
                82      LOAD_FAST                       0: account
                84      LOAD_CONST                      7: 'false'
                86      LOAD_CONST                      8: ('account', 'status')
                88      BUILD_CONST_KEY_MAP             2
                90      LOAD_GLOBAL                     5: NULL + Disconnect
                100     LOAD_FAST                       6: _var_var_7
                102     CALL                            1
                110     POP_TOP                         
                112     LOAD_GLOBAL                     7: NULL + Logs
                122     LOAD_ATTR                       8: PrintLog
                142     LOAD_FAST                       2: config
                144     LOAD_FAST                       0: account
                146     LOAD_GLOBAL                     2: Lang
                156     PUSH_NULL                       
                158     LOAD_CONST                      1: '__pyarmor_assert_13713__'
                160     LOAD_CONST                      9: 'work_account_completed'   # b'\x81\xf5\x17\x018\xc5\xbf\xd1\x18\xf5\x18\xcex\xd3\xfb\x8a\x02M\xb7\xa2\xbe\xceJ'
                162     CALL                            1
                170     BINARY_SUBSCR                   
                174     KW_NAMES                        10: ('config', 'account', 'message')
                176     CALL                            3
                184     POP_TOP                         
                186     LOAD_FAST                       0: account
                188     LOAD_CONST                      11: 'done'
                190     LOAD_CONST                      8: ('account', 'status')
                192     BUILD_CONST_KEY_MAP             2
                194     SWAP                            2
                196     POP_TOP                         
                198     NOP                             
                200     NOP                             
                202     JUMP_FORWARD                    629 (to 1464)
                206     CALL                            1
                214     POP_TOP                         
                216     RETURN_VALUE                    
                218     LOAD_FAST                       4: stop_thread
                220     LOAD_ATTR                       11: is_set
                240     CALL                            0
                248     POP_JUMP_IF_FALSE               10 (to 270)
                250     LOAD_GLOBAL                     13: NULL + StopProgram
                260     CALL                            0
                268     RAISE_VARARGS                   1
                270     LOAD_FAST                       1: data
                272     LOAD_CONST                      13: 'Settings'
                274     BINARY_SUBSCR                   
                278     LOAD_ATTR                       15: get
                298     LOAD_CONST                      14: 'source'
                300     CALL                            1
                308     STORE_FAST                      7: _var_var_5
                310     BUILD_LIST                      0
                312     STORE_FAST                      8: _var_var_14
                314     BUILD_LIST                      0
                316     STORE_FAST                      9: _var_var_6
                318     LOAD_FAST                       6: _var_var_7
                320     LOAD_ATTR                       17: iter_dialogs
                340     LOAD_CONST                      15: 500
                342     KW_NAMES                        16: ('limit',)
                344     CALL                            1
                352     GET_ITER                        
                354     FOR_ITER                        245 (to 846)
                358     STORE_FAST                      10: _var_var_11
                360     LOAD_FAST                       4: stop_thread
                362     LOAD_ATTR                       11: is_set
                382     CALL                            0
                390     POP_JUMP_IF_FALSE               10 (to 412)
                392     LOAD_GLOBAL                     13: NULL + StopProgram
                402     CALL                            0
                410     RAISE_VARARGS                   1
                412     LOAD_GLOBAL                     19: NULL + hasattr
                422     LOAD_FAST                       10: _var_var_11
                424     LOAD_CONST                      17: 'id'
                426     CALL                            2
                434     LOAD_CONST                      18: True
                436     COMPARE_OP                      40 (==)
                440     POP_JUMP_IF_TRUE                1 (to 444)
                442     JUMP_BACKWARD                   45 (to 354)
                444     LOAD_GLOBAL                     19: NULL + hasattr
                454     LOAD_FAST                       10: _var_var_11
                456     LOAD_CONST                      19: 'entity'
                458     CALL                            2
                466     LOAD_CONST                      18: True
                468     COMPARE_OP                      40 (==)
                472     POP_JUMP_IF_TRUE                1 (to 476)
                474     JUMP_BACKWARD                   61 (to 354)
                476     NOP                             
                478     LOAD_GLOBAL                     21: NULL + str
                488     LOAD_FAST                       10: _var_var_11
                490     LOAD_ATTR                       22: id
                510     CALL                            1
                518     STORE_FAST                      11: _var_var_15
                520     LOAD_FAST                       11: _var_var_15
                522     LOAD_FAST                       7: _var_var_5
                524     CONTAINS_OP                     0 (in)
                526     POP_JUMP_IF_FALSE               159 (to 846)
                528     NOP                             
                530     LOAD_FAST                       6: _var_var_7
                532     LOAD_ATTR                       25: iter_participants
                552     LOAD_FAST                       10: _var_var_11
                554     LOAD_ATTR                       26: entity
                574     LOAD_GLOBAL                     28: types
                584     LOAD_ATTR                       30: ChannelParticipantsAdmins
                604     KW_NAMES                        20: ('filter',)
                606     CALL                            2
                614     GET_ITER                        
                616     FOR_ITER                        111 (to 840)
                620     STORE_FAST                      12: _var_var_16
                622     LOAD_GLOBAL                     19: NULL + hasattr
                632     LOAD_FAST                       12: _var_var_16
                634     PUSH_NULL                       
                636     LOAD_CONST                      1: '__pyarmor_assert_13713__'
                638     LOAD_CONST                      21: 'last_name'   # b"\x81\xee\x19\x00'\xc5\xb0\xd3\x16\xff"
                640     CALL                            1
                648     CALL                            2
                656     POP_JUMP_IF_FALSE               50 (to 758)
                658     LOAD_FAST                       12: _var_var_16
                660     LOAD_ATTR                       32: last_name
                680     POP_JUMP_IF_NONE                38 (to 758)
                682     LOAD_FAST                       12: _var_var_16
                684     LOAD_ATTR                       34: first_name
                704     LOAD_CONST                      22: ''
                706     BINARY_OP                       0 (+)
                710     LOAD_GLOBAL                     21: NULL + str
                720     LOAD_FAST                       12: _var_var_16
                722     LOAD_ATTR                       32: last_name
                742     CALL                            1
                750     BINARY_OP                       0 (+)
                754     STORE_FAST                      13: _var_var_17
                756     JUMP_FORWARD                    12 (to 782)
                758     LOAD_FAST                       12: _var_var_16
                760     LOAD_ATTR                       34: first_name
                780     STORE_FAST                      13: _var_var_17
                782     LOAD_FAST                       9: _var_var_6
                784     LOAD_ATTR                       37: append
                804     LOAD_FAST                       12: _var_var_16
                806     LOAD_ATTR                       22: id
                826     LOAD_FAST                       13: _var_var_17
                828     BUILD_LIST                      2
                830     CALL                            1
                838     POP_TOP                         
                840     JUMP_BACKWARD                   113 (to 616)
                842     END_FOR                         
                844     NOP                             
                846     JUMP_BACKWARD                   247 (to 354)
                848     END_FOR                         
                850     LOAD_GLOBAL                     41: NULL + eel
                860     LOAD_ATTR                       42: ShowList
                880     LOAD_CONST                      25: 'users'
                882     LOAD_FAST                       9: _var_var_6
                884     CALL                            2
                892     POP_TOP                         
                894     LOAD_GLOBAL                     5: NULL + Disconnect
                904     LOAD_FAST_CHECK                 6: _var_var_7
                906     CALL                            1
                914     POP_TOP                         
                916     LOAD_GLOBAL                     7: NULL + Logs
                926     LOAD_ATTR                       8: PrintLog
                946     LOAD_FAST                       2: config
                948     LOAD_FAST                       0: account
                950     LOAD_GLOBAL                     2: Lang
                960     PUSH_NULL                       
                962     LOAD_CONST                      1: '__pyarmor_assert_13713__'
                964     LOAD_CONST                      9: 'work_account_completed'   # b'\x81\xf5\x17\x018\xc5\xbf\xd1\x18\xf5\x18\xcex\xd3\xfb\x8a\x02M\xb7\xa2\xbe\xceJ'
                966     CALL                            1
                974     BINARY_SUBSCR                   
                978     KW_NAMES                        10: ('config', 'account', 'message')
                980     CALL                            3
                988     POP_TOP                         
                990     LOAD_FAST                       0: account
                992     LOAD_CONST                      11: 'done'
                994     LOAD_CONST                      8: ('account', 'status')
                996     BUILD_CONST_KEY_MAP             2
                998     NOP                             
                1000    NOP                             
                1002    NOP                             
                1004    JUMP_FORWARD                    229 (to 1464)
                1006    CALL                            1
                1014    POP_TOP                         
                1016    RETURN_VALUE                    
                1018    PUSH_EXC_INFO                   
                1020    POP_TOP                         
                1022    POP_EXCEPT                      
                1024    JUMP_BACKWARD                   458 (to 112)
                1028    COPY                            3
                1030    POP_EXCEPT                      
                1032    RERAISE                         1
                1034    PUSH_EXC_INFO                   
                1036    POP_TOP                         
                1038    POP_EXCEPT                      
                1040    JUMP_BACKWARD                   98 (to 846)
                1042    COPY                            3
                1044    POP_EXCEPT                      
                1046    RERAISE                         1
                1048    PUSH_EXC_INFO                   
                1050    LOAD_GLOBAL                     38: Exception
                1060    CHECK_EXC_MATCH                 
                1062    POP_JUMP_IF_FALSE               49 (to 1162)
                1064    STORE_FAST                      14: _var_var_13
                1066    LOAD_GLOBAL                     7: NULL + Logs
                1076    LOAD_ATTR                       8: PrintLog
                1096    LOAD_FAST                       2: config
                1098    LOAD_FAST                       0: account
                1100    LOAD_GLOBAL                     2: Lang
                1110    PUSH_NULL                       
                1112    LOAD_CONST                      1: '__pyarmor_assert_13713__'
                1114    LOAD_CONST                      23: 'error_detected'   # b'\x81\xe7\n\x01<\xe8\x81\xd6\x1e\xee\x08\xc3x\xe9\xfc'
                1116    CALL                            1
                1124    BINARY_SUBSCR                   
                1128    LOAD_FAST                       14: _var_var_13
                1130    KW_NAMES                        24: ('config', 'account', 'message', 'param')
                1132    CALL                            4
                1140    POP_TOP                         
                1142    POP_EXCEPT                      
                1144    LOAD_CONST                      0: None
                1146    STORE_FAST                      14: _var_var_13
                1148    DELETE_FAST                     14: _var_var_13
                1150    JUMP_BACKWARD                   400 (to 354)
                1154    LOAD_CONST                      0: None
                1156    STORE_FAST                      14: _var_var_13
                1158    DELETE_FAST                     14: _var_var_13
                1160    RERAISE                         1
                1162    RERAISE                         0
                1164    COPY                            3
                1166    POP_EXCEPT                      
                1168    RERAISE                         1
                1170    PUSH_EXC_INFO                   
                1172    LOAD_GLOBAL                     12: StopProgram
                1182    CHECK_EXC_MATCH                 
                1184    POP_JUMP_IF_FALSE               3 (to 1192)
                1186    POP_TOP                         
                1188    POP_EXCEPT                      
                1190    JUMP_BACKWARD                   149 (to 894)
                1192    LOAD_GLOBAL                     44: BaseException
                1202    CHECK_EXC_MATCH                 
                1204    POP_JUMP_IF_FALSE               26 (to 1258)
                1206    STORE_FAST                      15: _var_var_3
                1208    PUSH_NULL                       
                1210    LOAD_GLOBAL                     47: NULL + logging
                1220    LOAD_FAST                       15: _var_var_3
                1222    CALL                            1
                1230    CALL                            0
                1238    POP_TOP                         
                1240    POP_EXCEPT                      
                1242    LOAD_CONST                      0: None
                1244    STORE_FAST                      15: _var_var_3
                1246    DELETE_FAST                     15: _var_var_3
                1248    JUMP_BACKWARD                   178 (to 894)
                1250    LOAD_CONST                      0: None
                1252    STORE_FAST                      15: _var_var_3
                1254    DELETE_FAST                     15: _var_var_3
                1256    RERAISE                         1
                1258    RERAISE                         0
                1260    COPY                            3
                1262    POP_EXCEPT                      
                1264    RERAISE                         1
                1266    PUSH_EXC_INFO                   
                1268    POP_TOP                         
                1270    POP_EXCEPT                      
                1272    JUMP_BACKWARD                   179 (to 916)
                1274    COPY                            3
                1276    POP_EXCEPT                      
                1278    RERAISE                         1
                1280    PUSH_EXC_INFO                   
                1282    LOAD_GLOBAL                     5: NULL + Disconnect
                1292    LOAD_FAST_CHECK                 6: _var_var_7
                1294    CALL                            1
                1302    POP_TOP                         
                1304    JUMP_FORWARD                    7 (to 1320)
                1306    PUSH_EXC_INFO                   
                1308    POP_TOP                         
                1310    POP_EXCEPT                      
                1312    JUMP_FORWARD                    3 (to 1320)
                1314    COPY                            3
                1316    POP_EXCEPT                      
                1318    RERAISE                         1
                1320    LOAD_GLOBAL                     7: NULL + Logs
                1330    LOAD_ATTR                       8: PrintLog
                1350    LOAD_FAST                       2: config
                1352    LOAD_FAST                       0: account
                1354    LOAD_GLOBAL                     2: Lang
                1364    PUSH_NULL                       
                1366    LOAD_CONST                      1: '__pyarmor_assert_13713__'
                1368    LOAD_CONST                      9: 'work_account_completed'   # b'\x81\xf5\x17\x018\xc5\xbf\xd1\x18\xf5\x18\xcex\xd3\xfb\x8a\x02M\xb7\xa2\xbe\xceJ'
                1370    CALL                            1
                1378    BINARY_SUBSCR                   
                1382    KW_NAMES                        10: ('config', 'account', 'message')
                1384    CALL                            3
                1392    POP_TOP                         
                1394    LOAD_FAST                       0: account
                1396    LOAD_CONST                      11: 'done'
                1398    LOAD_CONST                      8: ('account', 'status')
                1400    BUILD_CONST_KEY_MAP             2
                1402    SWAP                            2
                1404    POP_TOP                         
                1406    SWAP                            2
                1408    POP_EXCEPT                      
                1410    NOP                             
                1412    NOP                             
                1414    NOP                             
                1416    JUMP_FORWARD                    23 (to 1464)
                1418    CALL                            1
                1426    POP_TOP                         
                1428    RETURN_VALUE                    
                1430    COPY                            3
                1432    POP_EXCEPT                      
                1434    RERAISE                         1
                1436    PUSH_EXC_INFO                   
                1438    PUSH_NULL                       
                1440    LOAD_CONST                      12: '__pyarmor_exit_13715__'
                1442    NOP                             
                1444    LOAD_CONST                      3: b'<COAddr>\x07\x00\x00\x1a\x82\x05\x00\x00\x00\x00\x00\x00\x00\x00\x00\x00\x00\x00\x00\x00'
                1446    CALL                            1
                1454    POP_TOP                         
                1456    RERAISE                         0
                1458    COPY                            3
                1460    POP_EXCEPT                      
                1462    RERAISE                         1
                1464    PUSH_NULL                       
                1466    LOAD_CONST                      12: '__pyarmor_exit_13715__'
                1468    LOAD_CONST                      3: b'<COAddr>\x07\x00\x00\x1a\x82\x05\x00\x00\x00\x00\x00\x00\x00\x00\x00\x00\x00\x00\x00\x00'
                1470    BUILD_TUPLE                     1
                1472    CALL_FUNCTION_EX                0
                1474    POP_TOP                         
                1476    RETURN_VALUE                    
            [Exception Table]
                30 to 90 -> 1170 [0] 
                90 to 112 -> 1018 [1] 
                112 to 198 -> 1436 [0] 
                218 to 442 -> 1170 [0] 
                444 to 474 -> 1170 [0] 
                478 to 528 -> 1048 [1] 
                530 to 844 -> 1034 [1] 
                844 to 846 -> 1048 [1] 
                846 to 894 -> 1170 [0] 
                894 to 916 -> 1266 [0] 
                916 to 998 -> 1436 [0] 
                1018 to 1022 -> 1028 [2] lasti
                1022 to 1034 -> 1436 [0] 
                1034 to 1038 -> 1042 [2] lasti
                1038 to 1048 -> 1048 [1] 
                1048 to 1066 -> 1164 [2] lasti
                1066 to 1142 -> 1154 [2] lasti
                1142 to 1154 -> 1170 [0] 
                1154 to 1164 -> 1164 [2] lasti
                1164 to 1170 -> 1170 [0] 
                1170 to 1188 -> 1260 [1] lasti
                1188 to 1192 -> 1280 [0] 
                1192 to 1208 -> 1260 [1] lasti
                1208 to 1240 -> 1250 [1] lasti
                1240 to 1250 -> 1280 [0] 
                1250 to 1260 -> 1260 [1] lasti
                1260 to 1266 -> 1280 [0] 
                1266 to 1270 -> 1274 [1] lasti
                1270 to 1280 -> 1436 [0] 
                1280 to 1282 -> 1430 [1] lasti
                1282 to 1304 -> 1306 [2] 
                1304 to 1306 -> 1430 [1] lasti
                1306 to 1310 -> 1314 [3] lasti
                1310 to 1408 -> 1430 [1] lasti
                1408 to 1410 -> 1436 [0] 
                1430 to 1436 -> 1436 [0] 
                1436 to 1458 -> 1458 [1] lasti
        [Code]
            File Name: <frozen program.modules.Group_del_admin>
            Object Name: DelAdmins
            Qualified Name: DelAdmins
            Arg Count: 5
            Pos Only Arg Count: 0
            KW Only Arg Count: 0
            Stack Size: 10
            Flags: 0x20000003 (CO_OPTIMIZED | CO_NEWLOCALS | CO_PYARMOR_OBFUSCATED)
            [Names]
                'account_works'
                'Lang'
                'Disconnect'
                'Logs'
                'PrintLog'
                'is_set'
                'StopProgram'
                'get'
                'iter_dialogs'
                'hasattr'
                'str'
                'id'
                'iter_participants'
                'entity'
                'types'
                'ChannelParticipantsAdmins'
                'append'
                'Exception'
                'edit_admin'
                'first_name'
                'edit_permissions'
                'BaseException'
                'logging'
            [Locals+Names]
                'account'
                'data'
                'config'
                'proxy'
                'stop_thread'
                '__assert_armored__'
                '_var_var_7'
                '_var_var_5'
                '_var_var_6'
                '_var_var_18'
                '_var_var_19'
                '_var_var_20'
                '_var_var_11'
                '_var_var_15'
                '_var_var_16'
                '_var_var_21'
                '_var_var_13'
                '_var_var_22'
                '_var_var_3'
            [Constants]
                None
                '__pyarmor_assert_13716__'
                '__pyarmor_enter_13717__'
                b'<COAddr>\x07\x00\x00\x1a\x90\x08\x00\x00\x00\x00\x00\x00\x00\x00\x00\x00\x00\x00\x00\x00'
                'DelAdmin'
                (
                    'module'
                )
                False
                'false'
                (
                    'account'
                    'status'
                )
                'work_account_completed'   # b'\x81\xf5\x17\x018\xc5\xbf\xd1\x18\xf5\x18\xcex\xd3\xfb\x8a\x02M\xb7\xa2\xbe\xceJ'
                (
                    'config'
                    'account'
                    'message'
                )
                'done'
                '__pyarmor_exit_13718__'
                'Settings'
                'source'
                'users'
                'change_rules'   # b'\x81\xe1\x10\x12=\xfd\xbb\xed\t\xef\x01\xc5\x7f'
                'del_admins'   # b'\x81\xe6\x1d\x1f\x0c\xfb\xba\xdf\x12\xf4\x1e'
                'Собираем админов'   # b'\x81R\xd9\xa3\xedJob\xc3K\xedp\xbc\\-5\xd3\x1d\x0bw\x1a\x1f\xfe\x10\xb5\xb7\x13\x81\xb0o\xae7'
                500
                (
                    'limit'
                )
                'id'
                True
                'entity'
                (
                    'filter'
                )
                'error_detected'   # b'\x81\xe7\n\x01<\xe8\x81\xd6\x1e\xee\x08\xc3x\xe9\xfc'
                (
                    'config'
                    'account'
                    'message'
                    'param'
                )
                0
                1
                (
                    'is_admin'
                )
                'first_name'   # b'\x81\xe4\x11\x01 \xee\x81\xdc\x1a\xf7\x08'
                'Удалил права администратора:'   # b'\x81R\xdb\xa3\xe7Jnb\xc0J\xd5p\xb7\xacHZ\xbe\xbd\x0bw\x1a\x19\xfe\x1cE\xdfs\xec\xd4\x01\xc2U\xe2\xe2\xfd\xbd@{U\x9f\xfaX\x18\xed\ri\xed\xf7\xe9\\\xb6KW*'
                (
                    'config'
                    'account'
                    'message'
                    'param'
                    'end'
                )
                (
                    'view_messages'
                )
                'Кикнул пользователя из группы:'   # b"\x81R\xe2\xa3\xebJdb\xc6K\xeep\xb7\xacHZ\xbf\x83\x0b|\x1b'\xfe\x1b\xb5\xb1\x13\x8e\xb0a\xaf\x07\x8a\x87\x90\xd6)%\xf4\x9e\xc0Y/\x1dm\x0b\xbe\xa7\x86\x0e\xe6$7\xaf\xb7\x06m"
            [Disassembly]
                0       NOP                             
                2       NOP                             
                4       PUSH_NULL                       
                6       LOAD_CONST                      2: '__pyarmor_enter_13717__'
                8       LOAD_CONST                      3: b'<COAddr>\x07\x00\x00\x1a\x90\x08\x00\x00\x00\x00\x00\x00\x00\x00\x00\x00\x00\x00\x00\x00'
                10      BUILD_TUPLE                     1
                12      CALL_FUNCTION_EX                0
                14      POP_TOP                         
                16      RESUME                          0
                18      NOP                             
                20      NOP                             
                22      NOP                             
                24      NOP                             
                26      NOP                             
                28      NOP                             
                30      LOAD_GLOBAL                     1: NULL + account_works
                40      LOAD_FAST                       2: config
                42      LOAD_GLOBAL                     2: Lang
                52      LOAD_FAST                       3: proxy
                54      LOAD_FAST                       0: account
                56      LOAD_FAST                       4: stop_thread
                58      LOAD_CONST                      4: 'DelAdmin'
                60      KW_NAMES                        5: ('module',)
                62      CALL                            6
                70      STORE_FAST                      6: _var_var_7
                72      LOAD_FAST                       6: _var_var_7
                74      LOAD_CONST                      6: False
                76      COMPARE_OP                      40 (==)
                80      POP_JUMP_IF_FALSE               68 (to 218)
                82      LOAD_FAST                       0: account
                84      LOAD_CONST                      7: 'false'
                86      LOAD_CONST                      8: ('account', 'status')
                88      BUILD_CONST_KEY_MAP             2
                90      LOAD_GLOBAL                     5: NULL + Disconnect
                100     LOAD_FAST                       6: _var_var_7
                102     CALL                            1
                110     POP_TOP                         
                112     LOAD_GLOBAL                     7: NULL + Logs
                122     LOAD_ATTR                       8: PrintLog
                142     LOAD_FAST                       2: config
                144     LOAD_FAST                       0: account
                146     LOAD_GLOBAL                     2: Lang
                156     PUSH_NULL                       
                158     LOAD_CONST                      1: '__pyarmor_assert_13716__'
                160     LOAD_CONST                      9: 'work_account_completed'   # b'\x81\xf5\x17\x018\xc5\xbf\xd1\x18\xf5\x18\xcex\xd3\xfb\x8a\x02M\xb7\xa2\xbe\xceJ'
                162     CALL                            1
                170     BINARY_SUBSCR                   
                174     KW_NAMES                        10: ('config', 'account', 'message')
                176     CALL                            3
                184     POP_TOP                         
                186     LOAD_FAST                       0: account
                188     LOAD_CONST                      11: 'done'
                190     LOAD_CONST                      8: ('account', 'status')
                192     BUILD_CONST_KEY_MAP             2
                194     SWAP                            2
                196     POP_TOP                         
                198     NOP                             
                200     NOP                             
                202     JUMP_FORWARD                    1020 (to 2246)
                206     CALL                            1
                214     POP_TOP                         
                216     RETURN_VALUE                    
                218     LOAD_FAST                       4: stop_thread
                220     LOAD_ATTR                       11: is_set
                240     CALL                            0
                248     POP_JUMP_IF_FALSE               10 (to 270)
                250     LOAD_GLOBAL                     13: NULL + StopProgram
                260     CALL                            0
                268     RAISE_VARARGS                   1
                270     LOAD_FAST                       1: data
                272     LOAD_CONST                      13: 'Settings'
                274     BINARY_SUBSCR                   
                278     LOAD_ATTR                       15: get
                298     LOAD_CONST                      14: 'source'
                300     CALL                            1
                308     STORE_FAST                      7: _var_var_5
                310     LOAD_FAST                       1: data
                312     LOAD_CONST                      13: 'Settings'
                314     BINARY_SUBSCR                   
                318     LOAD_ATTR                       15: get
                338     LOAD_CONST                      15: 'users'
                340     CALL                            1
                348     STORE_FAST                      8: _var_var_6
                350     LOAD_FAST                       1: data
                352     LOAD_CONST                      13: 'Settings'
                354     BINARY_SUBSCR                   
                358     LOAD_ATTR                       15: get
                378     PUSH_NULL                       
                380     LOAD_CONST                      1: '__pyarmor_assert_13716__'
                382     LOAD_CONST                      16: 'change_rules'   # b'\x81\xe1\x10\x12=\xfd\xbb\xed\t\xef\x01\xc5\x7f'
                384     CALL                            1
                392     CALL                            1
                400     STORE_FAST                      9: _var_var_18
                402     LOAD_FAST                       1: data
                404     LOAD_CONST                      13: 'Settings'
                406     BINARY_SUBSCR                   
                410     LOAD_ATTR                       15: get
                430     PUSH_NULL                       
                432     LOAD_CONST                      1: '__pyarmor_assert_13716__'
                434     LOAD_CONST                      17: 'del_admins'   # b'\x81\xe6\x1d\x1f\x0c\xfb\xba\xdf\x12\xf4\x1e'
                436     CALL                            1
                444     CALL                            1
                452     STORE_FAST                      10: _var_var_19
                454     LOAD_GLOBAL                     7: NULL + Logs
                464     LOAD_ATTR                       8: PrintLog
                484     LOAD_FAST                       2: config
                486     LOAD_FAST                       0: account
                488     PUSH_NULL                       
                490     LOAD_CONST                      1: '__pyarmor_assert_13716__'
                492     LOAD_CONST                      18: 'Собираем админов'   # b'\x81R\xd9\xa3\xedJob\xc3K\xedp\xbc\\-5\xd3\x1d\x0bw\x1a\x1f\xfe\x10\xb5\xb7\x13\x81\xb0o\xae7'
                494     CALL                            1
                502     KW_NAMES                        10: ('config', 'account', 'message')
                504     CALL                            3
                512     POP_TOP                         
                514     BUILD_LIST                      0
                516     STORE_FAST                      11: _var_var_20
                518     LOAD_FAST                       6: _var_var_7
                520     LOAD_ATTR                       17: iter_dialogs
                540     LOAD_CONST                      19: 500
                542     KW_NAMES                        20: ('limit',)
                544     CALL                            1
                552     GET_ITER                        
                554     FOR_ITER                        181 (to 918)
                558     STORE_FAST                      12: _var_var_11
                560     LOAD_FAST                       4: stop_thread
                562     LOAD_ATTR                       11: is_set
                582     CALL                            0
                590     POP_JUMP_IF_FALSE               10 (to 612)
                592     LOAD_GLOBAL                     13: NULL + StopProgram
                602     CALL                            0
                610     RAISE_VARARGS                   1
                612     LOAD_GLOBAL                     19: NULL + hasattr
                622     LOAD_FAST                       12: _var_var_11
                624     LOAD_CONST                      21: 'id'
                626     CALL                            2
                634     LOAD_CONST                      22: True
                636     COMPARE_OP                      40 (==)
                640     POP_JUMP_IF_TRUE                1 (to 644)
                642     JUMP_BACKWARD                   45 (to 554)
                644     LOAD_GLOBAL                     19: NULL + hasattr
                654     LOAD_FAST                       12: _var_var_11
                656     LOAD_CONST                      23: 'entity'
                658     CALL                            2
                666     LOAD_CONST                      22: True
                668     COMPARE_OP                      40 (==)
                672     POP_JUMP_IF_TRUE                1 (to 676)
                674     JUMP_BACKWARD                   61 (to 554)
                676     NOP                             
                678     LOAD_GLOBAL                     21: NULL + str
                688     LOAD_FAST                       12: _var_var_11
                690     LOAD_ATTR                       22: id
                710     CALL                            1
                718     STORE_FAST                      13: _var_var_15
                720     LOAD_FAST                       13: _var_var_15
                722     LOAD_FAST                       7: _var_var_5
                724     CONTAINS_OP                     0 (in)
                726     POP_JUMP_IF_FALSE               95 (to 918)
                728     NOP                             
                730     LOAD_FAST                       6: _var_var_7
                732     LOAD_ATTR                       25: iter_participants
                752     LOAD_FAST                       12: _var_var_11
                754     LOAD_ATTR                       26: entity
                774     LOAD_GLOBAL                     28: types
                784     LOAD_ATTR                       30: ChannelParticipantsAdmins
                804     KW_NAMES                        24: ('filter',)
                806     CALL                            2
                814     GET_ITER                        
                816     FOR_ITER                        47 (to 912)
                820     STORE_FAST                      14: _var_var_16
                822     LOAD_GLOBAL                     21: NULL + str
                832     LOAD_FAST                       14: _var_var_16
                834     LOAD_ATTR                       22: id
                854     CALL                            1
                862     STORE_FAST                      15: _var_var_21
                864     LOAD_FAST                       15: _var_var_21
                866     LOAD_FAST                       8: _var_var_6
                868     CONTAINS_OP                     0 (in)
                870     POP_JUMP_IF_TRUE                1 (to 874)
                872     JUMP_BACKWARD                   29 (to 816)
                874     LOAD_FAST                       11: _var_var_20
                876     LOAD_ATTR                       33: append
                896     LOAD_FAST                       12: _var_var_11
                898     LOAD_FAST                       14: _var_var_16
                900     BUILD_LIST                      2
                902     CALL                            1
                910     POP_TOP                         
                912     JUMP_BACKWARD                   49 (to 816)
                914     END_FOR                         
                916     NOP                             
                918     JUMP_BACKWARD                   183 (to 554)
                920     END_FOR                         
                922     LOAD_FAST                       11: _var_var_20
                924     GET_ITER                        
                926     FOR_ITER                        217 (to 1362)
                930     STORE_FAST                      17: _var_var_22
                932     LOAD_FAST                       4: stop_thread
                934     LOAD_ATTR                       11: is_set
                954     CALL                            0
                962     POP_JUMP_IF_FALSE               10 (to 984)
                964     LOAD_GLOBAL                     13: NULL + StopProgram
                974     CALL                            0
                982     RAISE_VARARGS                   1
                984     LOAD_FAST                       9: _var_var_18
                986     POP_JUMP_IF_FALSE               92 (to 1172)
                988     NOP                             
                990     LOAD_FAST                       6: _var_var_7
                992     LOAD_ATTR                       37: edit_admin
                1012    LOAD_FAST                       17: _var_var_22
                1014    LOAD_CONST                      27: 0
                1016    BINARY_SUBSCR                   
                1020    LOAD_FAST                       17: _var_var_22
                1022    LOAD_CONST                      28: 1
                1024    BINARY_SUBSCR                   
                1028    LOAD_CONST                      6: False
                1030    KW_NAMES                        29: ('is_admin',)
                1032    CALL                            3
                1040    POP_TOP                         
                1042    LOAD_GLOBAL                     19: NULL + hasattr
                1052    LOAD_FAST                       17: _var_var_22
                1054    LOAD_CONST                      28: 1
                1056    BINARY_SUBSCR                   
                1060    PUSH_NULL                       
                1062    LOAD_CONST                      1: '__pyarmor_assert_13716__'
                1064    LOAD_CONST                      30: 'first_name'   # b'\x81\xe4\x11\x01 \xee\x81\xdc\x1a\xf7\x08'
                1066    CALL                            1
                1074    CALL                            2
                1082    POP_JUMP_IF_FALSE               44 (to 1172)
                1084    LOAD_GLOBAL                     7: NULL + Logs
                1094    LOAD_ATTR                       8: PrintLog
                1114    LOAD_FAST                       2: config
                1116    LOAD_FAST                       0: account
                1118    PUSH_NULL                       
                1120    LOAD_CONST                      1: '__pyarmor_assert_13716__'
                1122    LOAD_CONST                      31: 'Удалил права администратора:'   # b'\x81R\xdb\xa3\xe7Jnb\xc0J\xd5p\xb7\xacHZ\xbe\xbd\x0bw\x1a\x19\xfe\x1cE\xdfs\xec\xd4\x01\xc2U\xe2\xe2\xfd\xbd@{U\x9f\xfaX\x18\xed\ri\xed\xf7\xe9\\\xb6KW*'
                1124    CALL                            1
                1132    LOAD_FAST                       17: _var_var_22
                1134    LOAD_CONST                      28: 1
                1136    BINARY_SUBSCR                   
                1140    LOAD_ATTR                       38: first_name
                1160    KW_NAMES                        26: ('config', 'account', 'message', 'param')
                1162    CALL                            4
                1170    POP_TOP                         
                1172    LOAD_FAST                       10: _var_var_19
                1174    POP_JUMP_IF_TRUE                1 (to 1178)
                1176    JUMP_BACKWARD                   126 (to 926)
                1178    NOP                             
                1180    LOAD_FAST                       6: _var_var_7
                1182    LOAD_ATTR                       41: edit_permissions
                1202    LOAD_FAST                       17: _var_var_22
                1204    LOAD_CONST                      27: 0
                1206    BINARY_SUBSCR                   
                1210    LOAD_FAST                       17: _var_var_22
                1212    LOAD_CONST                      28: 1
                1214    BINARY_SUBSCR                   
                1218    LOAD_CONST                      6: False
                1220    KW_NAMES                        33: ('view_messages',)
                1222    CALL                            3
                1230    POP_TOP                         
                1232    LOAD_GLOBAL                     19: NULL + hasattr
                1242    LOAD_FAST                       17: _var_var_22
                1244    LOAD_CONST                      28: 1
                1246    BINARY_SUBSCR                   
                1250    PUSH_NULL                       
                1252    LOAD_CONST                      1: '__pyarmor_assert_13716__'
                1254    LOAD_CONST                      30: 'first_name'   # b'\x81\xe4\x11\x01 \xee\x81\xdc\x1a\xf7\x08'
                1256    CALL                            1
                1264    CALL                            2
                1272    POP_JUMP_IF_FALSE               44 (to 1362)
                1274    LOAD_GLOBAL                     7: NULL + Logs
                1284    LOAD_ATTR                       8: PrintLog
                1304    LOAD_FAST                       2: config
                1306    LOAD_FAST                       0: account
                1308    PUSH_NULL                       
                1310    LOAD_CONST                      1: '__pyarmor_assert_13716__'
                1312    LOAD_CONST                      34: 'Кикнул пользователя из группы:'   # b"\x81R\xe2\xa3\xebJdb\xc6K\xeep\xb7\xacHZ\xbf\x83\x0b|\x1b'\xfe\x1b\xb5\xb1\x13\x8e\xb0a\xaf\x07\x8a\x87\x90\xd6)%\xf4\x9e\xc0Y/\x1dm\x0b\xbe\xa7\x86\x0e\xe6$7\xaf\xb7\x06m"
                1314    CALL                            1
                1322    LOAD_FAST                       17: _var_var_22
                1324    LOAD_CONST                      28: 1
                1326    BINARY_SUBSCR                   
                1330    LOAD_ATTR                       38: first_name
                1350    KW_NAMES                        26: ('config', 'account', 'message', 'param')
                1352    CALL                            4
                1360    POP_TOP                         
                1362    JUMP_BACKWARD                   219 (to 926)
                1364    END_FOR                         
                1366    NOP                             
                1368    LOAD_GLOBAL                     5: NULL + Disconnect
                1378    LOAD_FAST_CHECK                 6: _var_var_7
                1380    CALL                            1
                1388    POP_TOP                         
                1390    LOAD_GLOBAL                     7: NULL + Logs
                1400    LOAD_ATTR                       8: PrintLog
                1420    LOAD_FAST                       2: config
                1422    LOAD_FAST                       0: account
                1424    LOAD_GLOBAL                     2: Lang
                1434    PUSH_NULL                       
                1436    LOAD_CONST                      1: '__pyarmor_assert_13716__'
                1438    LOAD_CONST                      9: 'work_account_completed'   # b'\x81\xf5\x17\x018\xc5\xbf\xd1\x18\xf5\x18\xcex\xd3\xfb\x8a\x02M\xb7\xa2\xbe\xceJ'
                1440    CALL                            1
                1448    BINARY_SUBSCR                   
                1452    KW_NAMES                        10: ('config', 'account', 'message')
                1454    CALL                            3
                1462    POP_TOP                         
                1464    LOAD_FAST                       0: account
                1466    LOAD_CONST                      11: 'done'
                1468    LOAD_CONST                      8: ('account', 'status')
                1470    BUILD_CONST_KEY_MAP             2
                1472    NOP                             
                1474    NOP                             
                1476    JUMP_FORWARD                    383 (to 2246)
                1480    CALL                            1
                1488    POP_TOP                         
                1490    RETURN_VALUE                    
                1492    PUSH_EXC_INFO                   
                1494    POP_TOP                         
                1496    POP_EXCEPT                      
                1498    JUMP_BACKWARD                   695 (to 112)
                1502    COPY                            3
                1504    POP_EXCEPT                      
                1506    RERAISE                         1
                1508    PUSH_EXC_INFO                   
                1510    POP_TOP                         
                1512    POP_EXCEPT                      
                1514    JUMP_BACKWARD                   300 (to 918)
                1518    COPY                            3
                1520    POP_EXCEPT                      
                1522    RERAISE                         1
                1524    PUSH_EXC_INFO                   
                1526    LOAD_GLOBAL                     34: Exception
                1536    CHECK_EXC_MATCH                 
                1538    POP_JUMP_IF_FALSE               49 (to 1638)
                1540    STORE_FAST                      16: _var_var_13
                1542    LOAD_GLOBAL                     7: NULL + Logs
                1552    LOAD_ATTR                       8: PrintLog
                1572    LOAD_FAST                       2: config
                1574    LOAD_FAST                       0: account
                1576    LOAD_GLOBAL                     2: Lang
                1586    PUSH_NULL                       
                1588    LOAD_CONST                      1: '__pyarmor_assert_13716__'
                1590    LOAD_CONST                      25: 'error_detected'   # b'\x81\xe7\n\x01<\xe8\x81\xd6\x1e\xee\x08\xc3x\xe9\xfc'
                1592    CALL                            1
                1600    BINARY_SUBSCR                   
                1604    LOAD_FAST                       16: _var_var_13
                1606    KW_NAMES                        26: ('config', 'account', 'message', 'param')
                1608    CALL                            4
                1616    POP_TOP                         
                1618    POP_EXCEPT                      
                1620    LOAD_CONST                      0: None
                1622    STORE_FAST                      16: _var_var_13
                1624    DELETE_FAST                     16: _var_var_13
                1626    JUMP_BACKWARD                   538 (to 554)
                1630    LOAD_CONST                      0: None
                1632    STORE_FAST                      16: _var_var_13
                1634    DELETE_FAST                     16: _var_var_13
                1636    RERAISE                         1
                1638    RERAISE                         0
                1640    COPY                            3
                1642    POP_EXCEPT                      
                1644    RERAISE                         1
                1646    PUSH_EXC_INFO                   
                1648    LOAD_GLOBAL                     34: Exception
                1658    CHECK_EXC_MATCH                 
                1660    POP_JUMP_IF_FALSE               63 (to 1788)
                1662    STORE_FAST                      16: _var_var_13
                1664    LOAD_GLOBAL                     7: NULL + Logs
                1674    LOAD_ATTR                       8: PrintLog
                1694    LOAD_FAST                       2: config
                1696    LOAD_FAST                       0: account
                1698    LOAD_GLOBAL                     2: Lang
                1708    PUSH_NULL                       
                1710    LOAD_CONST                      1: '__pyarmor_assert_13716__'
                1712    LOAD_CONST                      25: 'error_detected'   # b'\x81\xe7\n\x01<\xe8\x81\xd6\x1e\xee\x08\xc3x\xe9\xfc'
                1714    CALL                            1
                1722    BINARY_SUBSCR                   
                1726    LOAD_FAST                       17: _var_var_22
                1728    LOAD_CONST                      28: 1
                1730    BINARY_SUBSCR                   
                1734    LOAD_ATTR                       38: first_name
                1754    LOAD_FAST                       16: _var_var_13
                1756    KW_NAMES                        32: ('config', 'account', 'message', 'param', 'end')
                1758    CALL                            5
                1766    POP_TOP                         
                1768    POP_EXCEPT                      
                1770    LOAD_CONST                      0: None
                1772    STORE_FAST                      16: _var_var_13
                1774    DELETE_FAST                     16: _var_var_13
                1776    JUMP_BACKWARD                   304 (to 1172)
                1780    LOAD_CONST                      0: None
                1782    STORE_FAST                      16: _var_var_13
                1784    DELETE_FAST                     16: _var_var_13
                1786    RERAISE                         1
                1788    RERAISE                         0
                1790    COPY                            3
                1792    POP_EXCEPT                      
                1794    RERAISE                         1
                1796    PUSH_EXC_INFO                   
                1798    LOAD_GLOBAL                     34: Exception
                1808    CHECK_EXC_MATCH                 
                1810    POP_JUMP_IF_FALSE               63 (to 1938)
                1812    STORE_FAST                      16: _var_var_13
                1814    LOAD_GLOBAL                     7: NULL + Logs
                1824    LOAD_ATTR                       8: PrintLog
                1844    LOAD_FAST                       2: config
                1846    LOAD_FAST                       0: account
                1848    LOAD_GLOBAL                     2: Lang
                1858    PUSH_NULL                       
                1860    LOAD_CONST                      1: '__pyarmor_assert_13716__'
                1862    LOAD_CONST                      25: 'error_detected'   # b'\x81\xe7\n\x01<\xe8\x81\xd6\x1e\xee\x08\xc3x\xe9\xfc'
                1864    CALL                            1
                1872    BINARY_SUBSCR                   
                1876    LOAD_FAST                       17: _var_var_22
                1878    LOAD_CONST                      28: 1
                1880    BINARY_SUBSCR                   
                1884    LOAD_ATTR                       38: first_name
                1904    LOAD_FAST                       16: _var_var_13
                1906    KW_NAMES                        32: ('config', 'account', 'message', 'param', 'end')
                1908    CALL                            5
                1916    POP_TOP                         
                1918    POP_EXCEPT                      
                1920    LOAD_CONST                      0: None
                1922    STORE_FAST                      16: _var_var_13
                1924    DELETE_FAST                     16: _var_var_13
                1926    JUMP_BACKWARD                   502 (to 926)
                1930    LOAD_CONST                      0: None
                1932    STORE_FAST                      16: _var_var_13
                1934    DELETE_FAST                     16: _var_var_13
                1936    RERAISE                         1
                1938    RERAISE                         0
                1940    COPY                            3
                1942    POP_EXCEPT                      
                1944    RERAISE                         1
                1946    PUSH_EXC_INFO                   
                1948    LOAD_GLOBAL                     12: StopProgram
                1958    CHECK_EXC_MATCH                 
                1960    POP_JUMP_IF_FALSE               4 (to 1970)
                1962    POP_TOP                         
                1964    POP_EXCEPT                      
                1966    JUMP_BACKWARD                   301 (to 1368)
                1970    LOAD_GLOBAL                     42: BaseException
                1980    CHECK_EXC_MATCH                 
                1982    POP_JUMP_IF_FALSE               27 (to 2038)
                1984    STORE_FAST                      18: _var_var_3
                1986    PUSH_NULL                       
                1988    LOAD_GLOBAL                     45: NULL + logging
                1998    LOAD_FAST                       18: _var_var_3
                2000    CALL                            1
                2008    CALL                            0
                2016    POP_TOP                         
                2018    POP_EXCEPT                      
                2020    LOAD_CONST                      0: None
                2022    STORE_FAST                      18: _var_var_3
                2024    DELETE_FAST                     18: _var_var_3
                2026    JUMP_BACKWARD                   331 (to 1368)
                2030    LOAD_CONST                      0: None
                2032    STORE_FAST                      18: _var_var_3
                2034    DELETE_FAST                     18: _var_var_3
                2036    RERAISE                         1
                2038    RERAISE                         0
                2040    COPY                            3
                2042    POP_EXCEPT                      
                2044    RERAISE                         1
                2046    PUSH_EXC_INFO                   
                2048    POP_TOP                         
                2050    POP_EXCEPT                      
                2052    JUMP_BACKWARD                   333 (to 1390)
                2056    COPY                            3
                2058    POP_EXCEPT                      
                2060    RERAISE                         1
                2062    PUSH_EXC_INFO                   
                2064    LOAD_GLOBAL                     5: NULL + Disconnect
                2074    LOAD_FAST_CHECK                 6: _var_var_7
                2076    CALL                            1
                2084    POP_TOP                         
                2086    JUMP_FORWARD                    7 (to 2102)
                2088    PUSH_EXC_INFO                   
                2090    POP_TOP                         
                2092    POP_EXCEPT                      
                2094    JUMP_FORWARD                    3 (to 2102)
                2096    COPY                            3
                2098    POP_EXCEPT                      
                2100    RERAISE                         1
                2102    LOAD_GLOBAL                     7: NULL + Logs
                2112    LOAD_ATTR                       8: PrintLog
                2132    LOAD_FAST                       2: config
                2134    LOAD_FAST                       0: account
                2136    LOAD_GLOBAL                     2: Lang
                2146    PUSH_NULL                       
                2148    LOAD_CONST                      1: '__pyarmor_assert_13716__'
                2150    LOAD_CONST                      9: 'work_account_completed'   # b'\x81\xf5\x17\x018\xc5\xbf\xd1\x18\xf5\x18\xcex\xd3\xfb\x8a\x02M\xb7\xa2\xbe\xceJ'
                2152    CALL                            1
                2160    BINARY_SUBSCR                   
                2164    KW_NAMES                        10: ('config', 'account', 'message')
                2166    CALL                            3
                2174    POP_TOP                         
                2176    LOAD_FAST                       0: account
                2178    LOAD_CONST                      11: 'done'
                2180    LOAD_CONST                      8: ('account', 'status')
                2182    BUILD_CONST_KEY_MAP             2
                2184    SWAP                            2
                2186    POP_TOP                         
                2188    SWAP                            2
                2190    POP_EXCEPT                      
                2192    NOP                             
                2194    NOP                             
                2196    NOP                             
                2198    JUMP_FORWARD                    23 (to 2246)
                2200    CALL                            1
                2208    POP_TOP                         
                2210    RETURN_VALUE                    
                2212    COPY                            3
                2214    POP_EXCEPT                      
                2216    RERAISE                         1
                2218    PUSH_EXC_INFO                   
                2220    PUSH_NULL                       
                2222    LOAD_CONST                      12: '__pyarmor_exit_13718__'
                2224    NOP                             
                2226    LOAD_CONST                      3: b'<COAddr>\x07\x00\x00\x1a\x90\x08\x00\x00\x00\x00\x00\x00\x00\x00\x00\x00\x00\x00\x00\x00'
                2228    CALL                            1
                2236    POP_TOP                         
                2238    RERAISE                         0
                2240    COPY                            3
                2242    POP_EXCEPT                      
                2244    RERAISE                         1
                2246    PUSH_NULL                       
                2248    LOAD_CONST                      12: '__pyarmor_exit_13718__'
                2250    LOAD_CONST                      3: b'<COAddr>\x07\x00\x00\x1a\x90\x08\x00\x00\x00\x00\x00\x00\x00\x00\x00\x00\x00\x00\x00\x00'
                2252    BUILD_TUPLE                     1
                2254    CALL_FUNCTION_EX                0
                2256    POP_TOP                         
                2258    RETURN_VALUE                    
            [Exception Table]
                30 to 90 -> 1946 [0] 
                90 to 112 -> 1492 [1] 
                112 to 198 -> 2218 [0] 
                218 to 642 -> 1946 [0] 
                644 to 674 -> 1946 [0] 
                678 to 728 -> 1524 [1] 
                730 to 872 -> 1508 [1] 
                874 to 916 -> 1508 [1] 
                916 to 918 -> 1524 [1] 
                918 to 988 -> 1946 [0] 
                990 to 1172 -> 1646 [1] 
                1172 to 1176 -> 1946 [0] 
                1180 to 1362 -> 1796 [1] 
                1362 to 1366 -> 1946 [0] 
                1366 to 1368 -> 2062 [0] 
                1368 to 1390 -> 2046 [0] 
                1390 to 1472 -> 2218 [0] 
                1492 to 1496 -> 1502 [2] lasti
                1496 to 1508 -> 2218 [0] 
                1508 to 1512 -> 1518 [2] lasti
                1512 to 1524 -> 1524 [1] 
                1524 to 1542 -> 1640 [2] lasti
                1542 to 1618 -> 1630 [2] lasti
                1618 to 1630 -> 1946 [0] 
                1630 to 1640 -> 1640 [2] lasti
                1640 to 1646 -> 1946 [0] 
                1646 to 1664 -> 1790 [2] lasti
                1664 to 1768 -> 1780 [2] lasti
                1768 to 1780 -> 1946 [0] 
                1780 to 1790 -> 1790 [2] lasti
                1790 to 1796 -> 1946 [0] 
                1796 to 1814 -> 1940 [2] lasti
                1814 to 1918 -> 1930 [2] lasti
                1918 to 1930 -> 1946 [0] 
                1930 to 1940 -> 1940 [2] lasti
                1940 to 1946 -> 1946 [0] 
                1946 to 1964 -> 2040 [1] lasti
                1964 to 1970 -> 2062 [0] 
                1970 to 1986 -> 2040 [1] lasti
                1986 to 2018 -> 2030 [1] lasti
                2018 to 2030 -> 2062 [0] 
                2030 to 2040 -> 2040 [1] lasti
                2040 to 2046 -> 2062 [0] 
                2046 to 2050 -> 2056 [1] lasti
                2050 to 2062 -> 2218 [0] 
                2062 to 2064 -> 2212 [1] lasti
                2064 to 2086 -> 2088 [2] 
                2086 to 2088 -> 2212 [1] lasti
                2088 to 2092 -> 2096 [3] lasti
                2092 to 2190 -> 2212 [1] lasti
                2190 to 2192 -> 2218 [0] 
                2212 to 2218 -> 2218 [0] 
                2218 to 2240 -> 2240 [1] lasti
        [Code]
            File Name: <frozen program.modules.Group_del_admin>
            Object Name: EntityCorrectGroup
            Qualified Name: EntityCorrectGroup
            Arg Count: 1
            Pos Only Arg Count: 0
            KW Only Arg Count: 0
            Stack Size: 12
            Flags: 0x20000003 (CO_OPTIMIZED | CO_NEWLOCALS | CO_PYARMOR_OBFUSCATED)
            [Names]
                'id'
                'hasattr'
                'username'
                'title'
                'participants_count'
                'isinstance'
                'types'
                'User'
                'User_L199'
                'User_L195'
                'User_L185'
                'User_L184'
                'User_L166'
                'User_L165'
                'User_L159'
                'last_name'
                'first_name'
                'Chat'
                'Channel'
                'Channel_L203'
                'Channel_L199'
                'Channel_L195'
                'Channel_L185'
                'Channel_L167'
                'Channel_L166'
                'Channel_L165'
                'Channel_L161'
                'megagroup'
                'gigagroup'
                'Exception'
                'print'
                'str'
            [Locals+Names]
                'entity'
                '__assert_armored__'
                '_var_var_12'
                '_var_var_13'
            [Constants]
                None
                '__pyarmor_assert_13719__'
                '__pyarmor_enter_13720__'
                b'<COAddr>\x05\x00\x00\x1a\x8e\x05\x00\x00\x00\x00\x00\x00\x00\x00\x00\x00\x00\x00\x00\x00'
                '__pyarmor_exit_13721__'
                False
                'id'
                'username'
                'title'
                'participants_count'   # b"\x81\xf2\x19\x01'\xf3\xbd\xdb\x0b\xfb\x03\xd4\x7f\xd3\xfb\x8a\x1aS\xaf"
                'count'
                ''
                'USER'
                'type'
                'CHAT'
                'megagroup'   # b'\x81\xef\x1d\x142\xfd\xac\xdd\x0e\xea'
                'gigagroup'   # b'\x81\xe5\x11\x142\xfd\xac\xdd\x0e\xea'
                'MEGA_GROUP'   # b'\x81\xcf=4\x12\xc5\x99\xe04\xcf='
                'GIGA_GROUP'   # b'\x81\xc514\x12\xc5\x99\xe04\xcf='
                'CHANNEL'
                'NotDefined'   # b'\x81\xcc\x17\x07\x17\xff\xb8\xdb\x15\xff\t'
                'EntityCorrectGroup: '   # b'\x81\xc7\x16\x07:\xee\xa7\xf1\x14\xe8\x1f\xc5o\xf8\xdf\x97\x00H\xab\xfd\xea'
            [Disassembly]
                0       NOP                             
                2       NOP                             
                4       PUSH_NULL                       
                6       LOAD_CONST                      2: '__pyarmor_enter_13720__'
                8       LOAD_CONST                      3: b'<COAddr>\x05\x00\x00\x1a\x8e\x05\x00\x00\x00\x00\x00\x00\x00\x00\x00\x00\x00\x00\x00\x00'
                10      BUILD_TUPLE                     1
                12      CALL_FUNCTION_EX                0
                14      POP_TOP                         
                16      RESUME                          0
                18      NOP                             
                20      NOP                             
                22      NOP                             
                24      NOP                             
                26      NOP                             
                28      NOP                             
                30      LOAD_FAST                       0: entity
                32      LOAD_CONST                      0: None
                34      COMPARE_OP                      40 (==)
                38      POP_JUMP_IF_FALSE               11 (to 62)
                40      NOP                             
                42      LOAD_CONST                      5: False
                44      NOP                             
                46      NOP                             
                48      JUMP_FORWARD                    712 (to 1476)
                58      POP_TOP                         
                60      RETURN_CONST                    5: False
                62      LOAD_FAST                       0: entity
                64      LOAD_CONST                      5: False
                66      COMPARE_OP                      40 (==)
                70      POP_JUMP_IF_FALSE               11 (to 94)
                72      NOP                             
                74      LOAD_CONST                      5: False
                76      NOP                             
                78      NOP                             
                80      JUMP_FORWARD                    696 (to 1476)
                90      POP_TOP                         
                92      RETURN_CONST                    5: False
                94      BUILD_MAP                       0
                96      STORE_FAST                      2: _var_var_12
                98      LOAD_FAST                       0: entity
                100     LOAD_ATTR                       0: id
                120     LOAD_FAST                       2: _var_var_12
                122     LOAD_CONST                      6: 'id'
                124     STORE_SUBSCR                    
                128     LOAD_GLOBAL                     3: NULL + hasattr
                138     LOAD_FAST                       0: entity
                140     LOAD_CONST                      7: 'username'
                142     CALL                            2
                150     POP_JUMP_IF_FALSE               16 (to 184)
                152     LOAD_FAST                       0: entity
                154     LOAD_ATTR                       4: username
                174     LOAD_FAST                       2: _var_var_12
                176     LOAD_CONST                      7: 'username'
                178     STORE_SUBSCR                    
                182     JUMP_FORWARD                    5 (to 194)
                184     LOAD_CONST                      0: None
                186     LOAD_FAST                       2: _var_var_12
                188     LOAD_CONST                      7: 'username'
                190     STORE_SUBSCR                    
                194     LOAD_GLOBAL                     3: NULL + hasattr
                204     LOAD_FAST                       0: entity
                206     LOAD_CONST                      8: 'title'
                208     CALL                            2
                216     POP_JUMP_IF_FALSE               16 (to 250)
                218     LOAD_FAST                       0: entity
                220     LOAD_ATTR                       6: title
                240     LOAD_FAST                       2: _var_var_12
                242     LOAD_CONST                      8: 'title'
                244     STORE_SUBSCR                    
                248     JUMP_FORWARD                    5 (to 260)
                250     LOAD_CONST                      0: None
                252     LOAD_FAST                       2: _var_var_12
                254     LOAD_CONST                      8: 'title'
                256     STORE_SUBSCR                    
                260     LOAD_GLOBAL                     3: NULL + hasattr
                270     LOAD_FAST                       0: entity
                272     PUSH_NULL                       
                274     LOAD_CONST                      1: '__pyarmor_assert_13719__'
                276     LOAD_CONST                      9: 'participants_count'   # b"\x81\xf2\x19\x01'\xf3\xbd\xdb\x0b\xfb\x03\xd4\x7f\xd3\xfb\x8a\x1aS\xaf"
                278     CALL                            1
                286     CALL                            2
                294     POP_JUMP_IF_FALSE               16 (to 328)
                296     LOAD_FAST                       0: entity
                298     LOAD_ATTR                       8: participants_count
                318     LOAD_FAST                       2: _var_var_12
                320     LOAD_CONST                      10: 'count'
                322     STORE_SUBSCR                    
                326     JUMP_FORWARD                    5 (to 338)
                328     LOAD_CONST                      0: None
                330     LOAD_FAST                       2: _var_var_12
                332     LOAD_CONST                      10: 'count'
                334     STORE_SUBSCR                    
                338     LOAD_GLOBAL                     11: NULL + isinstance
                348     LOAD_FAST                       0: entity
                350     LOAD_GLOBAL                     12: types
                360     LOAD_ATTR                       14: User
                380     LOAD_GLOBAL                     12: types
                390     LOAD_ATTR                       16: User_L199
                410     LOAD_GLOBAL                     12: types
                420     LOAD_ATTR                       18: User_L195
                440     LOAD_GLOBAL                     12: types
                450     LOAD_ATTR                       20: User_L185
                470     LOAD_GLOBAL                     12: types
                480     LOAD_ATTR                       22: User_L184
                500     LOAD_GLOBAL                     12: types
                510     LOAD_ATTR                       24: User_L166
                530     LOAD_GLOBAL                     12: types
                540     LOAD_ATTR                       26: User_L165
                560     LOAD_GLOBAL                     12: types
                570     LOAD_ATTR                       28: User_L159
                590     BUILD_TUPLE                     8
                592     CALL                            2
                600     POP_JUMP_IF_FALSE               66 (to 734)
                602     LOAD_FAST                       0: entity
                604     LOAD_ATTR                       30: last_name
                624     POP_JUMP_IF_NOT_NONE            16 (to 658)
                626     LOAD_FAST                       0: entity
                628     LOAD_ATTR                       32: first_name
                648     LOAD_FAST                       2: _var_var_12
                650     LOAD_CONST                      8: 'title'
                652     STORE_SUBSCR                    
                656     JUMP_FORWARD                    31 (to 720)
                658     LOAD_FAST                       0: entity
                660     LOAD_ATTR                       32: first_name
                680     LOAD_CONST                      11: ''
                682     BINARY_OP                       0 (+)
                686     LOAD_FAST                       0: entity
                688     LOAD_ATTR                       30: last_name
                708     BINARY_OP                       0 (+)
                712     LOAD_FAST                       2: _var_var_12
                714     LOAD_CONST                      8: 'title'
                716     STORE_SUBSCR                    
                720     LOAD_CONST                      12: 'USER'
                722     LOAD_FAST                       2: _var_var_12
                724     LOAD_CONST                      13: 'type'
                726     STORE_SUBSCR                    
                730     JUMP_FORWARD                    286 (to 1306)
                734     LOAD_GLOBAL                     11: NULL + isinstance
                744     LOAD_FAST                       0: entity
                746     LOAD_GLOBAL                     12: types
                756     LOAD_ATTR                       34: Chat
                776     CALL                            2
                784     POP_JUMP_IF_FALSE               6 (to 798)
                786     LOAD_CONST                      14: 'CHAT'
                788     LOAD_FAST                       2: _var_var_12
                790     LOAD_CONST                      13: 'type'
                792     STORE_SUBSCR                    
                796     JUMP_FORWARD                    254 (to 1306)
                798     LOAD_GLOBAL                     11: NULL + isinstance
                808     LOAD_FAST                       0: entity
                810     LOAD_GLOBAL                     12: types
                820     LOAD_ATTR                       36: Channel
                840     LOAD_GLOBAL                     12: types
                850     LOAD_ATTR                       38: Channel_L203
                870     LOAD_GLOBAL                     12: types
                880     LOAD_ATTR                       40: Channel_L199
                900     LOAD_GLOBAL                     12: types
                910     LOAD_ATTR                       42: Channel_L195
                930     LOAD_GLOBAL                     12: types
                940     LOAD_ATTR                       44: Channel_L185
                960     LOAD_GLOBAL                     12: types
                970     LOAD_ATTR                       46: Channel_L167
                990     LOAD_GLOBAL                     12: types
                1000    LOAD_ATTR                       48: Channel_L166
                1020    LOAD_GLOBAL                     12: types
                1030    LOAD_ATTR                       50: Channel_L165
                1050    LOAD_GLOBAL                     12: types
                1060    LOAD_ATTR                       52: Channel_L161
                1080    BUILD_TUPLE                     9
                1082    CALL                            2
                1090    POP_JUMP_IF_FALSE               96 (to 1284)
                1092    LOAD_GLOBAL                     3: NULL + hasattr
                1102    LOAD_FAST                       0: entity
                1104    PUSH_NULL                       
                1106    LOAD_CONST                      1: '__pyarmor_assert_13719__'
                1108    LOAD_CONST                      15: 'megagroup'   # b'\x81\xef\x1d\x142\xfd\xac\xdd\x0e\xea'
                1110    CALL                            1
                1118    CALL                            2
                1126    POP_JUMP_IF_FALSE               72 (to 1272)
                1128    LOAD_GLOBAL                     3: NULL + hasattr
                1138    LOAD_FAST                       0: entity
                1140    PUSH_NULL                       
                1142    LOAD_CONST                      1: '__pyarmor_assert_13719__'
                1144    LOAD_CONST                      16: 'gigagroup'   # b'\x81\xe5\x11\x142\xfd\xac\xdd\x0e\xea'
                1146    CALL                            1
                1154    CALL                            2
                1162    POP_JUMP_IF_FALSE               54 (to 1272)
                1164    LOAD_FAST                       0: entity
                1166    LOAD_ATTR                       54: megagroup
                1186    POP_JUMP_IF_FALSE               12 (to 1212)
                1188    PUSH_NULL                       
                1190    LOAD_CONST                      1: '__pyarmor_assert_13719__'
                1192    LOAD_CONST                      17: 'MEGA_GROUP'   # b'\x81\xcf=4\x12\xc5\x99\xe04\xcf='
                1194    CALL                            1
                1202    LOAD_FAST                       2: _var_var_12
                1204    LOAD_CONST                      13: 'type'
                1206    STORE_SUBSCR                    
                1210    JUMP_FORWARD                    47 (to 1306)
                1212    LOAD_FAST                       0: entity
                1214    LOAD_ATTR                       56: gigagroup
                1234    POP_JUMP_IF_FALSE               12 (to 1260)
                1236    PUSH_NULL                       
                1238    LOAD_CONST                      1: '__pyarmor_assert_13719__'
                1240    LOAD_CONST                      18: 'GIGA_GROUP'   # b'\x81\xc514\x12\xc5\x99\xe04\xcf='
                1242    CALL                            1
                1250    LOAD_FAST                       2: _var_var_12
                1252    LOAD_CONST                      13: 'type'
                1254    STORE_SUBSCR                    
                1258    JUMP_FORWARD                    23 (to 1306)
                1260    LOAD_CONST                      19: 'CHANNEL'
                1262    LOAD_FAST                       2: _var_var_12
                1264    LOAD_CONST                      13: 'type'
                1266    STORE_SUBSCR                    
                1270    JUMP_FORWARD                    17 (to 1306)
                1272    LOAD_CONST                      19: 'CHANNEL'
                1274    LOAD_FAST                       2: _var_var_12
                1276    LOAD_CONST                      13: 'type'
                1278    STORE_SUBSCR                    
                1282    JUMP_FORWARD                    11 (to 1306)
                1284    PUSH_NULL                       
                1286    LOAD_CONST                      1: '__pyarmor_assert_13719__'
                1288    LOAD_CONST                      20: 'NotDefined'   # b'\x81\xcc\x17\x07\x17\xff\xb8\xdb\x15\xff\t'
                1290    CALL                            1
                1298    LOAD_FAST                       2: _var_var_12
                1300    LOAD_CONST                      13: 'type'
                1302    STORE_SUBSCR                    
                1306    LOAD_FAST                       2: _var_var_12
                1308    NOP                             
                1310    NOP                             
                1312    NOP                             
                1314    JUMP_FORWARD                    80 (to 1476)
                1316    CALL                            1
                1324    POP_TOP                         
                1326    RETURN_VALUE                    
                1328    PUSH_EXC_INFO                   
                1330    LOAD_GLOBAL                     58: Exception
                1340    CHECK_EXC_MATCH                 
                1342    POP_JUMP_IF_FALSE               48 (to 1440)
                1344    STORE_FAST                      3: _var_var_13
                1346    LOAD_GLOBAL                     61: NULL + print
                1356    PUSH_NULL                       
                1358    LOAD_CONST                      1: '__pyarmor_assert_13719__'
                1360    LOAD_CONST                      21: 'EntityCorrectGroup: '   # b'\x81\xc7\x16\x07:\xee\xa7\xf1\x14\xe8\x1f\xc5o\xf8\xdf\x97\x00H\xab\xfd\xea'
                1362    CALL                            1
                1370    LOAD_GLOBAL                     63: NULL + str
                1380    LOAD_FAST                       3: _var_var_13
                1382    CALL                            1
                1390    BINARY_OP                       0 (+)
                1394    CALL                            1
                1402    POP_TOP                         
                1404    POP_EXCEPT                      
                1406    LOAD_CONST                      0: None
                1408    STORE_FAST                      3: _var_var_13
                1410    DELETE_FAST                     3: _var_var_13
                1412    LOAD_CONST                      5: False
                1414    NOP                             
                1416    NOP                             
                1418    NOP                             
                1420    JUMP_FORWARD                    27 (to 1476)
                1428    POP_TOP                         
                1430    RETURN_CONST                    5: False
                1432    LOAD_CONST                      0: None
                1434    STORE_FAST                      3: _var_var_13
                1436    DELETE_FAST                     3: _var_var_13
                1438    RERAISE                         1
                1440    RERAISE                         0
                1442    COPY                            3
                1444    POP_EXCEPT                      
                1446    RERAISE                         1
                1448    PUSH_EXC_INFO                   
                1450    PUSH_NULL                       
                1452    LOAD_CONST                      4: '__pyarmor_exit_13721__'
                1454    NOP                             
                1456    LOAD_CONST                      3: b'<COAddr>\x05\x00\x00\x1a\x8e\x05\x00\x00\x00\x00\x00\x00\x00\x00\x00\x00\x00\x00\x00\x00'
                1458    CALL                            1
                1466    POP_TOP                         
                1468    RERAISE                         0
                1470    COPY                            3
                1472    POP_EXCEPT                      
                1474    RERAISE                         1
                1476    PUSH_NULL                       
                1478    LOAD_CONST                      4: '__pyarmor_exit_13721__'
                1480    LOAD_CONST                      3: b'<COAddr>\x05\x00\x00\x1a\x8e\x05\x00\x00\x00\x00\x00\x00\x00\x00\x00\x00\x00\x00\x00\x00'
                1482    BUILD_TUPLE                     1
                1484    CALL_FUNCTION_EX                0
                1486    POP_TOP                         
                1488    RETURN_VALUE                    
            [Exception Table]
                30 to 40 -> 1328 [0] 
                62 to 72 -> 1328 [0] 
                94 to 1308 -> 1328 [0] 
                1328 to 1346 -> 1442 [1] lasti
                1346 to 1404 -> 1432 [1] lasti
                1404 to 1412 -> 1448 [0] 
                1432 to 1442 -> 1442 [1] lasti
                1442 to 1448 -> 1448 [0] 
                1448 to 1470 -> 1470 [1] lasti
        '__pyarmor_exit_13703__'
    [Disassembly]
        0       NOP                             
        2       NOP                             
        4       PUSH_NULL                       
        6       LOAD_CONST                      1: '__pyarmor_enter_13702__'
        8       LOAD_CONST                      2: b'<COAddr>\x07\x00\x00\x1a\xf8\x00\x00\x00\x00\x00\x00\x00\x00\x00\x00\x00\x00\x00\x00\x00'
        10      BUILD_TUPLE                     1
        12      CALL_FUNCTION_EX                0
        14      POP_TOP                         
        16      RESUME                          0
        18      NOP                             
        20      NOP                             
        22      NOP                             
        24      NOP                             
        26      LOAD_CONST                      3: 0
        28      LOAD_CONST                      4: None
        30      IMPORT_NAME                     1: eel
        32      STORE_NAME                      1: eel
        34      LOAD_CONST                      3: 0
        36      LOAD_CONST                      5: ('Thread', 'Event')
        38      IMPORT_NAME                     2: threading
        40      IMPORT_FROM                     3: Thread
        42      STORE_NAME                      3: Thread
        44      IMPORT_FROM                     4: Event
        46      STORE_NAME                      4: Event
        48      POP_TOP                         
        50      LOAD_CONST                      3: 0
        52      LOAD_CONST                      6: ('types',)
        54      IMPORT_NAME                     5: multithon.sync
        56      IMPORT_FROM                     6: types
        58      STORE_NAME                      6: types
        60      POP_TOP                         
        62      LOAD_CONST                      3: 0
        64      LOAD_CONST                      7: ('StopProgram',)
        66      IMPORT_NAME                     7: multithon.errors
        68      IMPORT_FROM                     8: StopProgram
        70      STORE_NAME                      8: StopProgram
        72      POP_TOP                         
        74      LOAD_CONST                      3: 0
        76      LOAD_CONST                      8: ('GetLang',)
        78      IMPORT_NAME                     9: program.static_classes
        80      IMPORT_FROM                     10: GetLang
        82      STORE_NAME                      10: GetLang
        84      POP_TOP                         
        86      LOAD_CONST                      3: 0
        88      LOAD_CONST                      9: ('Logs',)
        90      IMPORT_NAME                     9: program.static_classes
        92      IMPORT_FROM                     11: Logs
        94      STORE_NAME                      11: Logs
        96      POP_TOP                         
        98      LOAD_CONST                      3: 0
        100     LOAD_CONST                      10: ('logging',)
        102     IMPORT_NAME                     9: program.static_classes
        104     IMPORT_FROM                     12: logging
        106     STORE_NAME                      12: logging
        108     POP_TOP                         
        110     LOAD_CONST                      3: 0
        112     LOAD_CONST                      11: ('memory_check_switcher',)
        114     IMPORT_NAME                     9: program.static_classes
        116     IMPORT_FROM                     13: memory_check_switcher
        118     STORE_NAME                      13: memory_check_switcher
        120     POP_TOP                         
        122     LOAD_CONST                      3: 0
        124     LOAD_CONST                      12: ('memory_set_pid',)
        126     IMPORT_NAME                     9: program.static_classes
        128     IMPORT_FROM                     14: memory_set_pid
        130     STORE_NAME                      14: memory_set_pid
        132     POP_TOP                         
        134     LOAD_CONST                      3: 0
        136     LOAD_CONST                      13: ('Disconnect',)
        138     IMPORT_NAME                     15: program.telegram
        140     IMPORT_FROM                     16: Disconnect
        142     STORE_NAME                      16: Disconnect
        144     POP_TOP                         
        146     LOAD_CONST                      3: 0
        148     LOAD_CONST                      14: ('account_works',)
        150     IMPORT_NAME                     15: program.telegram
        152     IMPORT_FROM                     17: account_works
        154     STORE_NAME                      17: account_works
        156     POP_TOP                         
        158     LOAD_CONST                      3: 0
        160     LOAD_CONST                      15: ('GetConfig',)
        162     IMPORT_NAME                     18: program.general
        164     IMPORT_FROM                     19: GetConfig
        166     STORE_NAME                      19: GetConfig
        168     POP_TOP                         
        170     LOAD_CONST                      3: 0
        172     LOAD_CONST                      16: ('GetProxy',)
        174     IMPORT_NAME                     18: program.general
        176     IMPORT_FROM                     20: GetProxy
        178     STORE_NAME                      20: GetProxy
        180     POP_TOP                         
        182     LOAD_CONST                      3: 0
        184     LOAD_CONST                      17: ('StopDetect',)
        186     IMPORT_NAME                     18: program.general
        188     IMPORT_FROM                     21: StopDetect
        190     STORE_NAME                      21: StopDetect
        192     POP_TOP                         
        194     LOAD_CONST                      3: 0
        196     LOAD_CONST                      18: ('del_task_manager',)
        198     IMPORT_NAME                     18: program.general
        200     IMPORT_FROM                     22: del_task_manager
        202     STORE_NAME                      22: del_task_manager
        204     POP_TOP                         
        206     LOAD_CONST                      3: 0
        208     LOAD_CONST                      19: ('getFile',)
        210     IMPORT_NAME                     18: program.general
        212     IMPORT_FROM                     23: getFile
        214     STORE_NAME                      23: getFile
        216     POP_TOP                         
        218     LOAD_CONST                      20: <CODE> Group_del_admin
        220     MAKE_FUNCTION                   0
        222     STORE_NAME                      24: Group_del_admin
        224     LOAD_CONST                      21: <CODE> START
        226     MAKE_FUNCTION                   0
        228     STORE_NAME                      25: START
        230     LOAD_CONST                      22: <CODE> GetAdminGroups
        232     MAKE_FUNCTION                   0
        234     STORE_NAME                      26: GetAdminGroups
        236     LOAD_CONST                      23: <CODE> GetAdmins
        238     MAKE_FUNCTION                   0
        240     STORE_NAME                      27: GetAdmins
        242     LOAD_CONST                      24: <CODE> DelAdmins
        244     MAKE_FUNCTION                   0
        246     STORE_NAME                      28: DelAdmins
        248     LOAD_CONST                      25: <CODE> EntityCorrectGroup
        250     MAKE_FUNCTION                   0
        252     STORE_NAME                      29: EntityCorrectGroup
        254     LOAD_CONST                      4: None
        256     NOP                             
        258     NOP                             
        260     NOP                             
        262     JUMP_FORWARD                    19 (to 302)
        270     POP_TOP                         
        272     RETURN_CONST                    4: None
        274     PUSH_EXC_INFO                   
        276     PUSH_NULL                       
        278     LOAD_CONST                      26: '__pyarmor_exit_13703__'
        280     NOP                             
        282     LOAD_CONST                      2: b'<COAddr>\x07\x00\x00\x1a\xf8\x00\x00\x00\x00\x00\x00\x00\x00\x00\x00\x00\x00\x00\x00\x00'
        284     CALL                            1
        292     POP_TOP                         
        294     RERAISE                         0
        296     COPY                            3
        298     POP_EXCEPT                      
        300     RERAISE                         1
        302     PUSH_NULL                       
        304     LOAD_CONST                      26: '__pyarmor_exit_13703__'
        306     LOAD_CONST                      2: b'<COAddr>\x07\x00\x00\x1a\xf8\x00\x00\x00\x00\x00\x00\x00\x00\x00\x00\x00\x00\x00\x00\x00'
        308     BUILD_TUPLE                     1
        310     CALL_FUNCTION_EX                0
        312     POP_TOP                         
        314     RETURN_VALUE                    
    [Exception Table]
        26 to 254 -> 274 [0] 
        274 to 296 -> 296 [1] lasti
