#decoded by lolz.live/mrpenny / t.me/zeus_jackpot
# ================================
# Примечания по Pyarmor:
# - Байт-код и объекты кода Pyarmor соответствуют стандартному Python, но присутствуют специальные вызовы функций среды выполнения (runtime) Pyarmor.
# - Вызовы строк — это не ошибки, а маркеры, которые обрабатываются Pyarmor во время выполнения.
#
# Руководство по декомпиляции (без среды выполнения):
# 1. Игнорируйте зашифрованные байты после `#`; используйте только строку до `#`.
# 2. Удалите "__pyarmor_enter_xxx__"(b"<COAddr>...") и "__pyarmor_leave_xxx__"(b"<COAddr>...") (пролог/эпилог).
# 3. "__pyarmor_assert_xxx__"(A) не является настоящим оператором assert.
#    - Если A — это имя или читаемая строка: замените на A.
#    - Если A — это (X, "Y"): замените на X.Y.
#    - Если A — это (X, "Y", Z): замените на X.Y = Z.
#    - В противном случае: выберите наиболее подходящую/логичную замену.
# 4. "__pyarmor_bcc_xxx__"(...) указывает на машинный (нативный) код; тело функции недоступно. Добавьте комментарий.
# ================================

[Code]
    File Name: <frozen program.modules.Group_add_admin>
    Object Name: <module>
    Qualified Name: <module>
    Arg Count: 0
    Pos Only Arg Count: 0
    KW Only Arg Count: 0
    Stack Size: 5
    Flags: 0x20000000 (CO_PYARMOR_OBFUSCATED)
    [Names]
        '__assert_armored__'
        'eel'
        'time'
        'random'
        'threading'
        'Thread'
        'Event'
        'multithon.sync'
        'functions'
        'types'
        'errors'
        'multithon.errors'
        'StopProgram'
        'program.static_classes'
        'GetLang'
        'Logs'
        'logging'
        'memory_check_switcher'
        'memory_set_pid'
        'program.telegram'
        'DelayOnline'
        'Disconnect'
        'account_works'
        'program.general'
        'GetConfig'
        'GetProxy'
        'StopDetect'
        'del_task_manager'
        'getFile'
        'Group_add_admin'
        'START'
        'GetAdminGroups'
        'EntityCorrectGroup'
        'clear_array'
        'check_array_word'
        'replace_array_word'
        'get_user_entity'
        'SetAdminGroups'
    [Locals+Names]
    [Constants]
        '__pyarmor_assert_13671__'
        '__pyarmor_enter_13672__'
        b'<COAddr>\x07\x00\x00\x1a.\x01\x00\x00\x00\x00\x00\x00\x00\x00\x00\x00\x00\x00\x00\x00'
        0
        None
        (
            'Thread'
            'Event'
        )
        (
            'functions'
            'types'
            'errors'
        )
        (
            'StopProgram'
        )
        (
            'GetLang'
        )
        (
            'Logs'
        )
        (
            'logging'
        )
        (
            'memory_check_switcher'
        )
        (
            'memory_set_pid'
        )
        (
            'DelayOnline'
        )
        (
            'Disconnect'
        )
        (
            'account_works'
        )
        (
            'GetConfig'
        )
        (
            'GetProxy'
        )
        (
            'StopDetect'
        )
        (
            'del_task_manager'
        )
        (
            'getFile'
        )
        [Code]
            File Name: <frozen program.modules.Group_add_admin>
            Object Name: Group_add_admin
            Qualified Name: Group_add_admin
            Arg Count: 1
            Pos Only Arg Count: 0
            KW Only Arg Count: 0
            Stack Size: 8
            Flags: 0x20000003 (CO_OPTIMIZED | CO_NEWLOCALS | CO_PYARMOR_OBFUSCATED)
            [Names]
                'get'
                'getFile'
                'GetConfig'
                'config'
                'GetLang'
                'Lang'
                'GetProxy'
                'eel'
                'sendSuccessBox'
                'memory_check_switcher'
                'Event'
                'memory_set_pid'
                'Thread'
                'START'
                'start'
                'Logs'
                'WaitStopAnsfer'
                'UpdateLogInWindow'
                'LangCheck'
                'Exception'
                'print'
                'str'
            [Locals+Names]
                'data'
                '__assert_armored__'
                '_var_var_0'
                '_var_var_1'
                '_var_var_2'
                '_var_var_3'
            [Constants]
                None
                '__pyarmor_assert_13674__'
                '__pyarmor_enter_13675__'
                b'<COAddr>\x07\x00\x00\x1a\x04\x03\x00\x00\x00\x00\x00\x00\x00\x00\x00\x00\x00\x00\x00\x00'
                'action'
                'getFile'
                '__pyarmor_exit_13676__'
                'program_running'   # b'\x81\xf2\n\x1c4\xe8\xbf\xdf$\xe8\x18\xceb\xe5\xf6\x82'
                False
                (
                    'target'
                    'args'
                )
                True
                (
                    'target'
                    'args'
                    'daemon'
                )
                'Group_add_admin: '   # b'\x81\xc5\n\x1c&\xea\x81\xd3\x1f\xfe2\xc1h\xe1\xf1\x8bU\x1d'
            [Disassembly]
                0       NOP                             
                2       NOP                             
                4       PUSH_NULL                       
                6       LOAD_CONST                      2: '__pyarmor_enter_13675__'
                8       LOAD_CONST                      3: b'<COAddr>\x07\x00\x00\x1a\x04\x03\x00\x00\x00\x00\x00\x00\x00\x00\x00\x00\x00\x00\x00\x00'
                10      BUILD_TUPLE                     1
                12      CALL_FUNCTION_EX                0
                14      POP_TOP                         
                16      RESUME                          0
                18      NOP                             
                20      NOP                             
                22      NOP                             
                24      NOP                             
                26      NOP                             
                28      NOP                             
                30      LOAD_FAST                       0: data
                32      LOAD_ATTR                       1: get
                52      LOAD_CONST                      4: 'action'
                54      CALL                            1
                62      POP_JUMP_IF_NONE                28 (to 120)
                64      LOAD_FAST                       0: data
                66      LOAD_CONST                      4: 'action'
                68      BINARY_SUBSCR                   
                72      LOAD_CONST                      5: 'getFile'
                74      COMPARE_OP                      40 (==)
                78      POP_JUMP_IF_FALSE               20 (to 120)
                80      LOAD_GLOBAL                     3: NULL + getFile
                90      LOAD_FAST                       0: data
                92      CALL                            1
                100     NOP                             
                102     NOP                             
                104     JUMP_FORWARD                    359 (to 826)
                108     CALL                            1
                116     POP_TOP                         
                118     RETURN_VALUE                    
                120     LOAD_GLOBAL                     5: NULL + GetConfig
                130     CALL                            0
                138     STORE_GLOBAL                    3: config
                140     LOAD_GLOBAL                     9: NULL + GetLang
                150     LOAD_GLOBAL                     6: config
                160     CALL                            1
                168     STORE_GLOBAL                    5: Lang
                170     LOAD_GLOBAL                     13: NULL + GetProxy
                180     CALL                            0
                188     STORE_FAST                      2: _var_var_0
                190     LOAD_GLOBAL                     15: NULL + eel
                200     LOAD_ATTR                       16: sendSuccessBox
                220     LOAD_GLOBAL                     10: Lang
                230     PUSH_NULL                       
                232     LOAD_CONST                      1: '__pyarmor_assert_13674__'
                234     LOAD_CONST                      7: 'program_running'   # b'\x81\xf2\n\x1c4\xe8\xbf\xdf$\xe8\x18\xceb\xe5\xf6\x82'
                236     CALL                            1
                244     BINARY_SUBSCR                   
                248     CALL                            1
                256     POP_TOP                         
                258     LOAD_GLOBAL                     19: NULL + memory_check_switcher
                268     CALL                            0
                276     POP_JUMP_IF_TRUE                11 (to 300)
                278     NOP                             
                280     LOAD_CONST                      8: False
                282     NOP                             
                284     NOP                             
                286     JUMP_FORWARD                    268 (to 826)
                296     POP_TOP                         
                298     RETURN_CONST                    8: False
                300     LOAD_GLOBAL                     21: NULL + Event
                310     CALL                            0
                318     STORE_FAST                      3: _var_var_1
                320     LOAD_GLOBAL                     23: NULL + memory_set_pid
                330     CALL                            0
                338     STORE_FAST                      4: _var_var_2
                340     LOAD_GLOBAL                     25: NULL + Thread
                350     LOAD_GLOBAL                     26: START
                360     LOAD_FAST                       0: data
                362     LOAD_GLOBAL                     6: config
                372     LOAD_FAST                       4: _var_var_2
                374     LOAD_FAST                       2: _var_var_0
                376     LOAD_FAST                       3: _var_var_1
                378     BUILD_TUPLE                     5
                380     KW_NAMES                        9: ('target', 'args')
                382     CALL                            2
                390     LOAD_ATTR                       29: start
                410     CALL                            0
                418     POP_TOP                         
                420     LOAD_GLOBAL                     25: NULL + Thread
                430     LOAD_GLOBAL                     30: Logs
                440     LOAD_ATTR                       32: WaitStopAnsfer
                460     LOAD_GLOBAL                     6: config
                470     LOAD_FAST                       4: _var_var_2
                472     LOAD_FAST                       3: _var_var_1
                474     BUILD_TUPLE                     3
                476     LOAD_CONST                      10: True
                478     KW_NAMES                        11: ('target', 'args', 'daemon')
                480     CALL                            3
                488     LOAD_ATTR                       29: start
                508     CALL                            0
                516     POP_TOP                         
                518     LOAD_GLOBAL                     25: NULL + Thread
                528     LOAD_GLOBAL                     30: Logs
                538     LOAD_ATTR                       34: UpdateLogInWindow
                558     LOAD_GLOBAL                     6: config
                568     LOAD_FAST                       4: _var_var_2
                570     LOAD_FAST                       3: _var_var_1
                572     BUILD_TUPLE                     3
                574     LOAD_CONST                      10: True
                576     KW_NAMES                        11: ('target', 'args', 'daemon')
                578     CALL                            3
                586     LOAD_ATTR                       29: start
                606     CALL                            0
                614     POP_TOP                         
                616     LOAD_GLOBAL                     31: NULL + Logs
                626     LOAD_ATTR                       36: LangCheck
                646     CALL                            0
                654     POP_TOP                         
                656     NOP                             
                658     LOAD_CONST                      10: True
                660     NOP                             
                662     NOP                             
                664     NOP                             
                666     JUMP_FORWARD                    79 (to 826)
                674     POP_TOP                         
                676     RETURN_CONST                    10: True
                678     PUSH_EXC_INFO                   
                680     LOAD_GLOBAL                     38: Exception
                690     CHECK_EXC_MATCH                 
                692     POP_JUMP_IF_FALSE               48 (to 790)
                694     STORE_FAST                      5: _var_var_3
                696     LOAD_GLOBAL                     41: NULL + print
                706     PUSH_NULL                       
                708     LOAD_CONST                      1: '__pyarmor_assert_13674__'
                710     LOAD_CONST                      12: 'Group_add_admin: '   # b'\x81\xc5\n\x1c&\xea\x81\xd3\x1f\xfe2\xc1h\xe1\xf1\x8bU\x1d'
                712     CALL                            1
                720     LOAD_GLOBAL                     43: NULL + str
                730     LOAD_FAST                       5: _var_var_3
                732     CALL                            1
                740     BINARY_OP                       0 (+)
                744     CALL                            1
                752     POP_TOP                         
                754     POP_EXCEPT                      
                756     LOAD_CONST                      0: None
                758     STORE_FAST                      5: _var_var_3
                760     DELETE_FAST                     5: _var_var_3
                762     LOAD_CONST                      8: False
                764     NOP                             
                766     NOP                             
                768     NOP                             
                770     JUMP_FORWARD                    27 (to 826)
                778     POP_TOP                         
                780     RETURN_CONST                    8: False
                782     LOAD_CONST                      0: None
                784     STORE_FAST                      5: _var_var_3
                786     DELETE_FAST                     5: _var_var_3
                788     RERAISE                         1
                790     RERAISE                         0
                792     COPY                            3
                794     POP_EXCEPT                      
                796     RERAISE                         1
                798     PUSH_EXC_INFO                   
                800     PUSH_NULL                       
                802     LOAD_CONST                      6: '__pyarmor_exit_13676__'
                804     NOP                             
                806     LOAD_CONST                      3: b'<COAddr>\x07\x00\x00\x1a\x04\x03\x00\x00\x00\x00\x00\x00\x00\x00\x00\x00\x00\x00\x00\x00'
                808     CALL                            1
                816     POP_TOP                         
                818     RERAISE                         0
                820     COPY                            3
                822     POP_EXCEPT                      
                824     RERAISE                         1
                826     PUSH_NULL                       
                828     LOAD_CONST                      6: '__pyarmor_exit_13676__'
                830     LOAD_CONST                      3: b'<COAddr>\x07\x00\x00\x1a\x04\x03\x00\x00\x00\x00\x00\x00\x00\x00\x00\x00\x00\x00\x00\x00'
                832     BUILD_TUPLE                     1
                834     CALL_FUNCTION_EX                0
                836     POP_TOP                         
                838     RETURN_VALUE                    
            [Exception Table]
                30 to 100 -> 678 [0] 
                120 to 278 -> 678 [0] 
                300 to 656 -> 678 [0] 
                678 to 696 -> 792 [1] lasti
                696 to 754 -> 782 [1] lasti
                754 to 762 -> 798 [0] 
                782 to 792 -> 792 [1] lasti
                792 to 798 -> 798 [0] 
                798 to 820 -> 820 [1] lasti
        [Code]
            File Name: <frozen program.modules.Group_add_admin>
            Object Name: START
            Qualified Name: START
            Arg Count: 5
            Pos Only Arg Count: 0
            KW Only Arg Count: 0
            Stack Size: 7
            Flags: 0x20000003 (CO_OPTIMIZED | CO_NEWLOCALS | CO_PYARMOR_OBFUSCATED)
            [Names]
                'is_set'
                'StopProgram'
                'isinstance'
                'list'
                'len'
                'eel'
                'sendErrorBox'
                'Lang'
                'get'
                'clear_array'
                'GetAdminGroups'
                'SetAdminGroups'
                'BaseException'
                'logging'
                'del_task_manager'
                'StopDetect'
            [Locals+Names]
                'data'
                'config'
                'pid'
                'proxy'
                'stop_thread'
                '__assert_armored__'
                '_var_var_4'
                '_var_var_5'
                '_var_var_6'
                '_var_var_7'
            [Constants]
                None
                '__pyarmor_assert_13677__'
                '__pyarmor_enter_13678__'
                b'<COAddr>\x05\x00\x00\x1a\xd0\x03\x00\x00\x00\x00\x00\x00\x00\x00\x00\x00\x00\x00\x00\x00'
                'Accounts'
                1
                'select_accounts_works'   # b'\x81\xf1\x1d\x1f6\xf9\xaa\xed\x1a\xf9\x0e\xcfy\xe2\xec\x960J\xb4\xb5\xa1\xd8'
                'Settings'
                'source'
                'usernames'   # b'\x81\xf7\x0b\x16!\xf4\xbf\xdf\x1e\xe9'
                'not_set_group_or_channel'   # b'\x81\xec\x17\x07\x0c\xe9\xbb\xc6$\xfd\x1f\xcfy\xfc\xc7\x8a\x1db\xb8\xaf\xab\xc5@\xc9\t'
                'no_usernames'   # b'\x81\xec\x17,&\xe9\xbb\xc0\x15\xfb\x00\xc5\x7f'
                'action'
                'getGroups'   # b'\x81\xe5\x1d\x07\x14\xe8\xb1\xc7\x0b\xe9'
                0
                '__pyarmor_exit_13679__'
                'Done'
            [Disassembly]
                0       NOP                             
                2       NOP                             
                4       PUSH_NULL                       
                6       LOAD_CONST                      2: '__pyarmor_enter_13678__'
                8       LOAD_CONST                      3: b'<COAddr>\x05\x00\x00\x1a\xd0\x03\x00\x00\x00\x00\x00\x00\x00\x00\x00\x00\x00\x00\x00\x00'
                10      BUILD_TUPLE                     1
                12      CALL_FUNCTION_EX                0
                14      POP_TOP                         
                16      RESUME                          0
                18      NOP                             
                20      NOP                             
                22      NOP                             
                24      NOP                             
                26      NOP                             
                28      NOP                             
                30      LOAD_FAST                       4: stop_thread
                32      LOAD_ATTR                       1: is_set
                52      CALL                            0
                60      POP_JUMP_IF_FALSE               10 (to 82)
                62      LOAD_GLOBAL                     3: NULL + StopProgram
                72      CALL                            0
                80      RAISE_VARARGS                   1
                82      LOAD_FAST                       0: data
                84      LOAD_CONST                      4: 'Accounts'
                86      BINARY_SUBSCR                   
                90      STORE_FAST                      6: _var_var_4
                92      LOAD_GLOBAL                     5: NULL + isinstance
                102     LOAD_FAST                       6: _var_var_4
                104     LOAD_GLOBAL                     6: list
                114     CALL                            2
                122     POP_JUMP_IF_TRUE                3 (to 130)
                124     LOAD_FAST                       6: _var_var_4
                126     BUILD_LIST                      1
                128     STORE_FAST                      6: _var_var_4
                130     LOAD_GLOBAL                     9: NULL + len
                140     LOAD_FAST                       6: _var_var_4
                142     CALL                            1
                150     LOAD_CONST                      5: 1
                152     COMPARE_OP                      2 (<)
                156     POP_JUMP_IF_FALSE               44 (to 246)
                158     LOAD_GLOBAL                     11: NULL + eel
                168     LOAD_ATTR                       12: sendErrorBox
                188     LOAD_GLOBAL                     14: Lang
                198     PUSH_NULL                       
                200     LOAD_CONST                      1: '__pyarmor_assert_13677__'
                202     LOAD_CONST                      6: 'select_accounts_works'   # b'\x81\xf1\x1d\x1f6\xf9\xaa\xed\x1a\xf9\x0e\xcfy\xe2\xec\x960J\xb4\xb5\xa1\xd8'
                204     CALL                            1
                212     BINARY_SUBSCR                   
                216     CALL                            1
                224     POP_TOP                         
                226     LOAD_GLOBAL                     3: NULL + StopProgram
                236     CALL                            0
                244     RAISE_VARARGS                   1
                246     LOAD_FAST                       0: data
                248     LOAD_ATTR                       17: get
                268     LOAD_CONST                      7: 'Settings'
                270     CALL                            1
                278     LOAD_CONST                      0: None
                280     COMPARE_OP                      55 (!=)
                284     POP_JUMP_IF_FALSE               171 (to 628)
                286     LOAD_FAST                       0: data
                288     LOAD_CONST                      7: 'Settings'
                290     BINARY_SUBSCR                   
                294     LOAD_ATTR                       17: get
                314     LOAD_CONST                      8: 'source'
                316     CALL                            1
                324     STORE_FAST                      7: _var_var_5
                326     LOAD_GLOBAL                     19: NULL + clear_array
                336     LOAD_FAST                       0: data
                338     LOAD_CONST                      7: 'Settings'
                340     BINARY_SUBSCR                   
                344     LOAD_ATTR                       17: get
                364     PUSH_NULL                       
                366     LOAD_CONST                      1: '__pyarmor_assert_13677__'
                368     LOAD_CONST                      9: 'usernames'   # b'\x81\xf7\x0b\x16!\xf4\xbf\xdf\x1e\xe9'
                370     CALL                            1
                378     CALL                            1
                386     CALL                            1
                394     STORE_FAST                      8: _var_var_6
                396     LOAD_GLOBAL                     9: NULL + len
                406     LOAD_FAST                       7: _var_var_5
                408     CALL                            1
                416     LOAD_CONST                      5: 1
                418     COMPARE_OP                      2 (<)
                422     POP_JUMP_IF_FALSE               44 (to 512)
                424     LOAD_GLOBAL                     11: NULL + eel
                434     LOAD_ATTR                       12: sendErrorBox
                454     LOAD_GLOBAL                     14: Lang
                464     PUSH_NULL                       
                466     LOAD_CONST                      1: '__pyarmor_assert_13677__'
                468     LOAD_CONST                      10: 'not_set_group_or_channel'   # b'\x81\xec\x17\x07\x0c\xe9\xbb\xc6$\xfd\x1f\xcfy\xfc\xc7\x8a\x1db\xb8\xaf\xab\xc5@\xc9\t'
                470     CALL                            1
                478     BINARY_SUBSCR                   
                482     CALL                            1
                490     POP_TOP                         
                492     LOAD_GLOBAL                     3: NULL + StopProgram
                502     CALL                            0
                510     RAISE_VARARGS                   1
                512     LOAD_GLOBAL                     9: NULL + len
                522     LOAD_FAST                       8: _var_var_6
                524     CALL                            1
                532     LOAD_CONST                      5: 1
                534     COMPARE_OP                      2 (<)
                538     POP_JUMP_IF_FALSE               44 (to 628)
                540     LOAD_GLOBAL                     11: NULL + eel
                550     LOAD_ATTR                       12: sendErrorBox
                570     LOAD_GLOBAL                     14: Lang
                580     PUSH_NULL                       
                582     LOAD_CONST                      1: '__pyarmor_assert_13677__'
                584     LOAD_CONST                      11: 'no_usernames'   # b'\x81\xec\x17,&\xe9\xbb\xc0\x15\xfb\x00\xc5\x7f'
                586     CALL                            1
                594     BINARY_SUBSCR                   
                598     CALL                            1
                606     POP_TOP                         
                608     LOAD_GLOBAL                     3: NULL + StopProgram
                618     CALL                            0
                626     RAISE_VARARGS                   1
                628     LOAD_FAST                       0: data
                630     LOAD_ATTR                       17: get
                650     LOAD_CONST                      12: 'action'
                652     CALL                            1
                660     POP_JUMP_IF_NONE                33 (to 728)
                662     LOAD_FAST                       0: data
                664     LOAD_CONST                      12: 'action'
                666     BINARY_SUBSCR                   
                670     PUSH_NULL                       
                672     LOAD_CONST                      1: '__pyarmor_assert_13677__'
                674     LOAD_CONST                      13: 'getGroups'   # b'\x81\xe5\x1d\x07\x14\xe8\xb1\xc7\x0b\xe9'
                676     CALL                            1
                684     COMPARE_OP                      40 (==)
                688     POP_JUMP_IF_FALSE               19 (to 728)
                690     LOAD_GLOBAL                     21: NULL + GetAdminGroups
                700     LOAD_FAST                       6: _var_var_4
                702     LOAD_CONST                      14: 0
                704     BINARY_SUBSCR                   
                708     LOAD_FAST                       0: data
                710     LOAD_FAST                       1: config
                712     LOAD_FAST                       3: proxy
                714     LOAD_FAST                       4: stop_thread
                716     CALL                            5
                724     POP_TOP                         
                726     JUMP_FORWARD                    18 (to 764)
                728     LOAD_GLOBAL                     23: NULL + SetAdminGroups
                738     LOAD_FAST                       6: _var_var_4
                740     LOAD_CONST                      14: 0
                742     BINARY_SUBSCR                   
                746     LOAD_FAST                       0: data
                748     LOAD_FAST                       1: config
                750     LOAD_FAST                       3: proxy
                752     LOAD_FAST                       4: stop_thread
                754     CALL                            5
                762     POP_TOP                         
                764     LOAD_GLOBAL                     29: NULL + del_task_manager
                774     LOAD_FAST                       2: pid
                776     CALL                            1
                784     POP_TOP                         
                786     LOAD_GLOBAL                     31: NULL + StopDetect
                796     LOAD_FAST                       4: stop_thread
                798     CALL                            1
                806     POP_TOP                         
                808     NOP                             
                810     LOAD_CONST                      16: 'Done'
                812     NOP                             
                814     NOP                             
                816     NOP                             
                818     JUMP_FORWARD                    105 (to 1030)
                826     POP_TOP                         
                828     RETURN_CONST                    16: 'Done'
                830     PUSH_EXC_INFO                   
                832     LOAD_GLOBAL                     2: StopProgram
                842     CHECK_EXC_MATCH                 
                844     POP_JUMP_IF_FALSE               3 (to 852)
                846     POP_TOP                         
                848     POP_EXCEPT                      
                850     JUMP_BACKWARD                   44 (to 764)
                852     LOAD_GLOBAL                     24: BaseException
                862     CHECK_EXC_MATCH                 
                864     POP_JUMP_IF_FALSE               26 (to 918)
                866     STORE_FAST                      9: _var_var_7
                868     PUSH_NULL                       
                870     LOAD_GLOBAL                     27: NULL + logging
                880     LOAD_FAST                       9: _var_var_7
                882     CALL                            1
                890     CALL                            0
                898     POP_TOP                         
                900     POP_EXCEPT                      
                902     LOAD_CONST                      0: None
                904     STORE_FAST                      9: _var_var_7
                906     DELETE_FAST                     9: _var_var_7
                908     JUMP_BACKWARD                   73 (to 764)
                910     LOAD_CONST                      0: None
                912     STORE_FAST                      9: _var_var_7
                914     DELETE_FAST                     9: _var_var_7
                916     RERAISE                         1
                918     RERAISE                         0
                920     COPY                            3
                922     POP_EXCEPT                      
                924     RERAISE                         1
                926     PUSH_EXC_INFO                   
                928     LOAD_GLOBAL                     29: NULL + del_task_manager
                938     LOAD_FAST                       2: pid
                940     CALL                            1
                948     POP_TOP                         
                950     LOAD_GLOBAL                     31: NULL + StopDetect
                960     LOAD_FAST                       4: stop_thread
                962     CALL                            1
                970     POP_TOP                         
                972     POP_TOP                         
                974     POP_EXCEPT                      
                976     LOAD_CONST                      16: 'Done'
                978     NOP                             
                980     NOP                             
                982     NOP                             
                984     JUMP_FORWARD                    22 (to 1030)
                992     POP_TOP                         
                994     RETURN_CONST                    16: 'Done'
                996     COPY                            3
                998     POP_EXCEPT                      
                1000    RERAISE                         1
                1002    PUSH_EXC_INFO                   
                1004    PUSH_NULL                       
                1006    LOAD_CONST                      15: '__pyarmor_exit_13679__'
                1008    NOP                             
                1010    LOAD_CONST                      3: b'<COAddr>\x05\x00\x00\x1a\xd0\x03\x00\x00\x00\x00\x00\x00\x00\x00\x00\x00\x00\x00\x00\x00'
                1012    CALL                            1
                1020    POP_TOP                         
                1022    RERAISE                         0
                1024    COPY                            3
                1026    POP_EXCEPT                      
                1028    RERAISE                         1
                1030    PUSH_NULL                       
                1032    LOAD_CONST                      15: '__pyarmor_exit_13679__'
                1034    LOAD_CONST                      3: b'<COAddr>\x05\x00\x00\x1a\xd0\x03\x00\x00\x00\x00\x00\x00\x00\x00\x00\x00\x00\x00\x00\x00'
                1036    BUILD_TUPLE                     1
                1038    CALL_FUNCTION_EX                0
                1040    POP_TOP                         
                1042    RETURN_VALUE                    
            [Exception Table]
                30 to 764 -> 830 [0] 
                764 to 808 -> 1002 [0] 
                830 to 848 -> 920 [1] lasti
                848 to 852 -> 926 [0] 
                852 to 868 -> 920 [1] lasti
                868 to 900 -> 910 [1] lasti
                900 to 910 -> 926 [0] 
                910 to 920 -> 920 [1] lasti
                920 to 926 -> 926 [0] 
                926 to 974 -> 996 [1] lasti
                974 to 976 -> 1002 [0] 
                996 to 1002 -> 1002 [0] 
                1002 to 1024 -> 1024 [1] lasti
        [Code]
            File Name: <frozen program.modules.Group_add_admin>
            Object Name: GetAdminGroups
            Qualified Name: GetAdminGroups
            Arg Count: 5
            Pos Only Arg Count: 0
            KW Only Arg Count: 0
            Stack Size: 10
            Flags: 0x20000003 (CO_OPTIMIZED | CO_NEWLOCALS | CO_PYARMOR_OBFUSCATED)
            [Names]
                'account_works'
                'Lang'
                'Disconnect'
                'Logs'
                'PrintLog'
                'is_set'
                'StopProgram'
                'iter_dialogs'
                'hasattr'
                'entity'
                'creator'
                'admin_rights'
                'EntityCorrectGroup'
                'append'
                'id'
                'Exception'
                'eel'
                'ShowList'
                'BaseException'
                'logging'
            [Locals+Names]
                'account'
                'data'
                'config'
                'proxy'
                'stop_thread'
                '__assert_armored__'
                '_var_var_8'
                '_var_var_9'
                '_var_var_10'
                '_var_var_11'
                '_var_var_12'
                '_var_var_13'
                '_var_var_3'
                '_var_var_7'
            [Constants]
                None
                '__pyarmor_assert_13680__'
                '__pyarmor_enter_13681__'
                b'<COAddr>\x05\x00\x00\x1a\xae\x05\x00\x00\x00\x00\x00\x00\x00\x00\x00\x00\x00\x00\x00\x00'
                'AddAdmin'
                (
                    'module'
                )
                False
                'false'
                (
                    'account'
                    'status'
                )
                'work_account_completed'   # b'\x81\xf5\x17\x018\xc5\xbf\xd1\x18\xf5\x18\xcex\xd3\xfb\x8a\x02M\xb7\xa2\xbe\xceJ'
                (
                    'config'
                    'account'
                    'message'
                )
                'done'
                '__pyarmor_exit_13682__'
                500
                (
                    'limit'
                )
                'entity'
                'creator'
                'admin_rights'   # b'\x81\xe3\x1c\x1e:\xf4\x81\xc0\x12\xfd\x05\xd4\x7f'
                True
                'type'
                'MEGA_GROUP'   # b'\x81\xcf=4\x12\xc5\x99\xe04\xcf='
                'GIGA_GROUP'   # b'\x81\xc514\x12\xc5\x99\xe04\xcf='
                'title'
                'CHANNEL'
                'error_detected'   # b'\x81\xe7\n\x01<\xe8\x81\xd6\x1e\xee\x08\xc3x\xe9\xfc'
                (
                    'config'
                    'account'
                    'message'
                    'param'
                )
                'channels'
                'groups'
            [Disassembly]
                0       NOP                             
                2       NOP                             
                4       PUSH_NULL                       
                6       LOAD_CONST                      2: '__pyarmor_enter_13681__'
                8       LOAD_CONST                      3: b'<COAddr>\x05\x00\x00\x1a\xae\x05\x00\x00\x00\x00\x00\x00\x00\x00\x00\x00\x00\x00\x00\x00'
                10      BUILD_TUPLE                     1
                12      CALL_FUNCTION_EX                0
                14      POP_TOP                         
                16      RESUME                          0
                18      NOP                             
                20      NOP                             
                22      NOP                             
                24      NOP                             
                26      NOP                             
                28      NOP                             
                30      LOAD_GLOBAL                     1: NULL + account_works
                40      LOAD_FAST                       2: config
                42      LOAD_GLOBAL                     2: Lang
                52      LOAD_FAST                       3: proxy
                54      LOAD_FAST                       0: account
                56      LOAD_FAST                       4: stop_thread
                58      LOAD_CONST                      4: 'AddAdmin'
                60      KW_NAMES                        5: ('module',)
                62      CALL                            6
                70      STORE_FAST                      6: _var_var_8
                72      LOAD_FAST                       6: _var_var_8
                74      LOAD_CONST                      6: False
                76      COMPARE_OP                      40 (==)
                80      POP_JUMP_IF_FALSE               68 (to 218)
                82      LOAD_FAST                       0: account
                84      LOAD_CONST                      7: 'false'
                86      LOAD_CONST                      8: ('account', 'status')
                88      BUILD_CONST_KEY_MAP             2
                90      LOAD_GLOBAL                     5: NULL + Disconnect
                100     LOAD_FAST                       6: _var_var_8
                102     CALL                            1
                110     POP_TOP                         
                112     LOAD_GLOBAL                     7: NULL + Logs
                122     LOAD_ATTR                       8: PrintLog
                142     LOAD_FAST                       2: config
                144     LOAD_FAST                       0: account
                146     LOAD_GLOBAL                     2: Lang
                156     PUSH_NULL                       
                158     LOAD_CONST                      1: '__pyarmor_assert_13680__'
                160     LOAD_CONST                      9: 'work_account_completed'   # b'\x81\xf5\x17\x018\xc5\xbf\xd1\x18\xf5\x18\xcex\xd3\xfb\x8a\x02M\xb7\xa2\xbe\xceJ'
                162     CALL                            1
                170     BINARY_SUBSCR                   
                174     KW_NAMES                        10: ('config', 'account', 'message')
                176     CALL                            3
                184     POP_TOP                         
                186     LOAD_FAST                       0: account
                188     LOAD_CONST                      11: 'done'
                190     LOAD_CONST                      8: ('account', 'status')
                192     BUILD_CONST_KEY_MAP             2
                194     SWAP                            2
                196     POP_TOP                         
                198     NOP                             
                200     NOP                             
                202     JUMP_FORWARD                    651 (to 1508)
                206     CALL                            1
                214     POP_TOP                         
                216     RETURN_VALUE                    
                218     LOAD_FAST                       4: stop_thread
                220     LOAD_ATTR                       11: is_set
                240     CALL                            0
                248     POP_JUMP_IF_FALSE               10 (to 270)
                250     LOAD_GLOBAL                     13: NULL + StopProgram
                260     CALL                            0
                268     RAISE_VARARGS                   1
                270     BUILD_LIST                      0
                272     STORE_FAST                      7: _var_var_9
                274     BUILD_LIST                      0
                276     STORE_FAST                      8: _var_var_10
                278     BUILD_LIST                      0
                280     STORE_FAST                      9: _var_var_11
                282     LOAD_FAST                       6: _var_var_8
                284     LOAD_ATTR                       15: iter_dialogs
                304     LOAD_CONST                      13: 500
                306     KW_NAMES                        14: ('limit',)
                308     CALL                            1
                316     GET_ITER                        
                318     FOR_ITER                        269 (to 860)
                324     STORE_FAST                      10: _var_var_12
                326     LOAD_FAST                       4: stop_thread
                328     LOAD_ATTR                       11: is_set
                348     CALL                            0
                356     POP_JUMP_IF_FALSE               10 (to 378)
                358     LOAD_GLOBAL                     13: NULL + StopProgram
                368     CALL                            0
                376     RAISE_VARARGS                   1
                378     LOAD_GLOBAL                     17: NULL + hasattr
                388     LOAD_FAST                       10: _var_var_12
                390     LOAD_CONST                      15: 'entity'
                392     CALL                            2
                400     POP_JUMP_IF_TRUE                1 (to 404)
                402     JUMP_BACKWARD                   43 (to 318)
                404     LOAD_GLOBAL                     17: NULL + hasattr
                414     LOAD_FAST                       10: _var_var_12
                416     LOAD_ATTR                       18: entity
                436     LOAD_CONST                      16: 'creator'
                438     CALL                            2
                446     POP_JUMP_IF_TRUE                1 (to 450)
                448     JUMP_BACKWARD                   66 (to 318)
                450     LOAD_GLOBAL                     17: NULL + hasattr
                460     LOAD_FAST                       10: _var_var_12
                462     LOAD_ATTR                       18: entity
                482     PUSH_NULL                       
                484     LOAD_CONST                      1: '__pyarmor_assert_13680__'
                486     LOAD_CONST                      17: 'admin_rights'   # b'\x81\xe3\x1c\x1e:\xf4\x81\xc0\x12\xfd\x05\xd4\x7f'
                488     CALL                            1
                496     CALL                            2
                504     POP_JUMP_IF_TRUE                1 (to 508)
                506     JUMP_BACKWARD                   95 (to 318)
                508     LOAD_FAST                       10: _var_var_12
                510     LOAD_ATTR                       18: entity
                530     LOAD_ATTR                       20: creator
                550     LOAD_CONST                      18: True
                552     COMPARE_OP                      40 (==)
                556     POP_JUMP_IF_TRUE                23 (to 604)
                558     LOAD_FAST                       10: _var_var_12
                560     LOAD_ATTR                       18: entity
                580     LOAD_ATTR                       22: admin_rights
                600     POP_JUMP_IF_NOT_NONE            1 (to 604)
                602     JUMP_BACKWARD                   143 (to 318)
                604     NOP                             
                606     LOAD_GLOBAL                     25: NULL + EntityCorrectGroup
                616     LOAD_FAST                       10: _var_var_12
                618     LOAD_ATTR                       18: entity
                638     CALL                            1
                646     STORE_FAST                      11: _var_var_13
                648     LOAD_FAST                       11: _var_var_13
                650     LOAD_CONST                      6: False
                652     COMPARE_OP                      55 (!=)
                656     POP_JUMP_IF_FALSE               100 (to 858)
                658     LOAD_FAST                       11: _var_var_13
                660     LOAD_CONST                      19: 'type'
                662     BINARY_SUBSCR                   
                666     PUSH_NULL                       
                668     LOAD_CONST                      1: '__pyarmor_assert_13680__'
                670     LOAD_CONST                      20: 'MEGA_GROUP'   # b'\x81\xcf=4\x12\xc5\x99\xe04\xcf='
                672     CALL                            1
                680     COMPARE_OP                      40 (==)
                684     POP_JUMP_IF_TRUE                14 (to 714)
                686     LOAD_FAST                       11: _var_var_13
                688     LOAD_CONST                      19: 'type'
                690     BINARY_SUBSCR                   
                694     PUSH_NULL                       
                696     LOAD_CONST                      1: '__pyarmor_assert_13680__'
                698     LOAD_CONST                      21: 'GIGA_GROUP'   # b'\x81\xc514\x12\xc5\x99\xe04\xcf='
                700     CALL                            1
                708     COMPARE_OP                      40 (==)
                712     POP_JUMP_IF_FALSE               32 (to 778)
                714     LOAD_FAST                       8: _var_var_10
                716     LOAD_ATTR                       27: append
                736     LOAD_FAST                       10: _var_var_12
                738     LOAD_ATTR                       28: id
                758     LOAD_FAST                       11: _var_var_13
                760     LOAD_CONST                      22: 'title'
                762     BINARY_SUBSCR                   
                766     BUILD_LIST                      2
                768     CALL                            1
                776     POP_TOP                         
                778     LOAD_FAST                       11: _var_var_13
                780     LOAD_CONST                      19: 'type'
                782     BINARY_SUBSCR                   
                786     LOAD_CONST                      23: 'CHANNEL'
                788     COMPARE_OP                      40 (==)
                792     POP_JUMP_IF_FALSE               32 (to 858)
                794     LOAD_FAST                       7: _var_var_9
                796     LOAD_ATTR                       27: append
                816     LOAD_FAST                       10: _var_var_12
                818     LOAD_ATTR                       28: id
                838     LOAD_FAST                       11: _var_var_13
                840     LOAD_CONST                      22: 'title'
                842     BINARY_SUBSCR                   
                846     BUILD_LIST                      2
                848     CALL                            1
                856     POP_TOP                         
                858     JUMP_BACKWARD                   272 (to 318)
                862     END_FOR                         
                864     LOAD_GLOBAL                     33: NULL + eel
                874     LOAD_ATTR                       34: ShowList
                894     LOAD_CONST                      26: 'channels'
                896     LOAD_FAST                       7: _var_var_9
                898     CALL                            2
                906     POP_TOP                         
                908     LOAD_GLOBAL                     33: NULL + eel
                918     LOAD_ATTR                       34: ShowList
                938     LOAD_CONST                      27: 'groups'
                940     LOAD_FAST                       8: _var_var_10
                942     CALL                            2
                950     POP_TOP                         
                952     LOAD_GLOBAL                     5: NULL + Disconnect
                962     LOAD_FAST_CHECK                 6: _var_var_8
                964     CALL                            1
                972     POP_TOP                         
                974     LOAD_GLOBAL                     7: NULL + Logs
                984     LOAD_ATTR                       8: PrintLog
                1004    LOAD_FAST                       2: config
                1006    LOAD_FAST                       0: account
                1008    LOAD_GLOBAL                     2: Lang
                1018    PUSH_NULL                       
                1020    LOAD_CONST                      1: '__pyarmor_assert_13680__'
                1022    LOAD_CONST                      9: 'work_account_completed'   # b'\x81\xf5\x17\x018\xc5\xbf\xd1\x18\xf5\x18\xcex\xd3\xfb\x8a\x02M\xb7\xa2\xbe\xceJ'
                1024    CALL                            1
                1032    BINARY_SUBSCR                   
                1036    KW_NAMES                        10: ('config', 'account', 'message')
                1038    CALL                            3
                1046    POP_TOP                         
                1048    LOAD_FAST                       0: account
                1050    LOAD_CONST                      11: 'done'
                1052    LOAD_CONST                      8: ('account', 'status')
                1054    BUILD_CONST_KEY_MAP             2
                1056    NOP                             
                1058    NOP                             
                1060    NOP                             
                1062    JUMP_FORWARD                    222 (to 1508)
                1064    CALL                            1
                1072    POP_TOP                         
                1074    RETURN_VALUE                    
                1076    PUSH_EXC_INFO                   
                1078    POP_TOP                         
                1080    POP_EXCEPT                      
                1082    JUMP_BACKWARD                   487 (to 112)
                1086    COPY                            3
                1088    POP_EXCEPT                      
                1090    RERAISE                         1
                1092    PUSH_EXC_INFO                   
                1094    LOAD_GLOBAL                     30: Exception
                1104    CHECK_EXC_MATCH                 
                1106    POP_JUMP_IF_FALSE               49 (to 1206)
                1108    STORE_FAST                      12: _var_var_3
                1110    LOAD_GLOBAL                     7: NULL + Logs
                1120    LOAD_ATTR                       8: PrintLog
                1140    LOAD_FAST                       2: config
                1142    LOAD_FAST                       0: account
                1144    LOAD_GLOBAL                     2: Lang
                1154    PUSH_NULL                       
                1156    LOAD_CONST                      1: '__pyarmor_assert_13680__'
                1158    LOAD_CONST                      24: 'error_detected'   # b'\x81\xe7\n\x01<\xe8\x81\xd6\x1e\xee\x08\xc3x\xe9\xfc'
                1160    CALL                            1
                1168    BINARY_SUBSCR                   
                1172    LOAD_FAST                       12: _var_var_3
                1174    KW_NAMES                        25: ('config', 'account', 'message', 'param')
                1176    CALL                            4
                1184    POP_TOP                         
                1186    POP_EXCEPT                      
                1188    LOAD_CONST                      0: None
                1190    STORE_FAST                      12: _var_var_3
                1192    DELETE_FAST                     12: _var_var_3
                1194    JUMP_BACKWARD                   440 (to 318)
                1198    LOAD_CONST                      0: None
                1200    STORE_FAST                      12: _var_var_3
                1202    DELETE_FAST                     12: _var_var_3
                1204    RERAISE                         1
                1206    RERAISE                         0
                1208    COPY                            3
                1210    POP_EXCEPT                      
                1212    RERAISE                         1
                1214    PUSH_EXC_INFO                   
                1216    LOAD_GLOBAL                     12: StopProgram
                1226    CHECK_EXC_MATCH                 
                1228    POP_JUMP_IF_FALSE               3 (to 1236)
                1230    POP_TOP                         
                1232    POP_EXCEPT                      
                1234    JUMP_BACKWARD                   142 (to 952)
                1236    LOAD_GLOBAL                     36: BaseException
                1246    CHECK_EXC_MATCH                 
                1248    POP_JUMP_IF_FALSE               26 (to 1302)
                1250    STORE_FAST                      13: _var_var_7
                1252    PUSH_NULL                       
                1254    LOAD_GLOBAL                     39: NULL + logging
                1264    LOAD_FAST                       13: _var_var_7
                1266    CALL                            1
                1274    CALL                            0
                1282    POP_TOP                         
                1284    POP_EXCEPT                      
                1286    LOAD_CONST                      0: None
                1288    STORE_FAST                      13: _var_var_7
                1290    DELETE_FAST                     13: _var_var_7
                1292    JUMP_BACKWARD                   171 (to 952)
                1294    LOAD_CONST                      0: None
                1296    STORE_FAST                      13: _var_var_7
                1298    DELETE_FAST                     13: _var_var_7
                1300    RERAISE                         1
                1302    RERAISE                         0
                1304    COPY                            3
                1306    POP_EXCEPT                      
                1308    RERAISE                         1
                1310    PUSH_EXC_INFO                   
                1312    POP_TOP                         
                1314    POP_EXCEPT                      
                1316    JUMP_BACKWARD                   172 (to 974)
                1318    COPY                            3
                1320    POP_EXCEPT                      
                1322    RERAISE                         1
                1324    PUSH_EXC_INFO                   
                1326    LOAD_GLOBAL                     5: NULL + Disconnect
                1336    LOAD_FAST_CHECK                 6: _var_var_8
                1338    CALL                            1
                1346    POP_TOP                         
                1348    JUMP_FORWARD                    7 (to 1364)
                1350    PUSH_EXC_INFO                   
                1352    POP_TOP                         
                1354    POP_EXCEPT                      
                1356    JUMP_FORWARD                    3 (to 1364)
                1358    COPY                            3
                1360    POP_EXCEPT                      
                1362    RERAISE                         1
                1364    LOAD_GLOBAL                     7: NULL + Logs
                1374    LOAD_ATTR                       8: PrintLog
                1394    LOAD_FAST                       2: config
                1396    LOAD_FAST                       0: account
                1398    LOAD_GLOBAL                     2: Lang
                1408    PUSH_NULL                       
                1410    LOAD_CONST                      1: '__pyarmor_assert_13680__'
                1412    LOAD_CONST                      9: 'work_account_completed'   # b'\x81\xf5\x17\x018\xc5\xbf\xd1\x18\xf5\x18\xcex\xd3\xfb\x8a\x02M\xb7\xa2\xbe\xceJ'
                1414    CALL                            1
                1422    BINARY_SUBSCR                   
                1426    KW_NAMES                        10: ('config', 'account', 'message')
                1428    CALL                            3
                1436    POP_TOP                         
                1438    LOAD_FAST                       0: account
                1440    LOAD_CONST                      11: 'done'
                1442    LOAD_CONST                      8: ('account', 'status')
                1444    BUILD_CONST_KEY_MAP             2
                1446    SWAP                            2
                1448    POP_TOP                         
                1450    SWAP                            2
                1452    POP_EXCEPT                      
                1454    NOP                             
                1456    NOP                             
                1458    NOP                             
                1460    JUMP_FORWARD                    23 (to 1508)
                1462    CALL                            1
                1470    POP_TOP                         
                1472    RETURN_VALUE                    
                1474    COPY                            3
                1476    POP_EXCEPT                      
                1478    RERAISE                         1
                1480    PUSH_EXC_INFO                   
                1482    PUSH_NULL                       
                1484    LOAD_CONST                      12: '__pyarmor_exit_13682__'
                1486    NOP                             
                1488    LOAD_CONST                      3: b'<COAddr>\x05\x00\x00\x1a\xae\x05\x00\x00\x00\x00\x00\x00\x00\x00\x00\x00\x00\x00\x00\x00'
                1490    CALL                            1
                1498    POP_TOP                         
                1500    RERAISE                         0
                1502    COPY                            3
                1504    POP_EXCEPT                      
                1506    RERAISE                         1
                1508    PUSH_NULL                       
                1510    LOAD_CONST                      12: '__pyarmor_exit_13682__'
                1512    LOAD_CONST                      3: b'<COAddr>\x05\x00\x00\x1a\xae\x05\x00\x00\x00\x00\x00\x00\x00\x00\x00\x00\x00\x00\x00\x00'
                1514    BUILD_TUPLE                     1
                1516    CALL_FUNCTION_EX                0
                1518    POP_TOP                         
                1520    RETURN_VALUE                    
            [Exception Table]
                30 to 90 -> 1214 [0] 
                90 to 112 -> 1076 [1] 
                112 to 198 -> 1480 [0] 
                218 to 402 -> 1214 [0] 
                404 to 448 -> 1214 [0] 
                450 to 506 -> 1214 [0] 
                508 to 602 -> 1214 [0] 
                606 to 858 -> 1092 [1] 
                858 to 952 -> 1214 [0] 
                952 to 974 -> 1310 [0] 
                974 to 1056 -> 1480 [0] 
                1076 to 1080 -> 1086 [2] lasti
                1080 to 1092 -> 1480 [0] 
                1092 to 1110 -> 1208 [2] lasti
                1110 to 1186 -> 1198 [2] lasti
                1186 to 1198 -> 1214 [0] 
                1198 to 1208 -> 1208 [2] lasti
                1208 to 1214 -> 1214 [0] 
                1214 to 1232 -> 1304 [1] lasti
                1232 to 1236 -> 1324 [0] 
                1236 to 1252 -> 1304 [1] lasti
                1252 to 1284 -> 1294 [1] lasti
                1284 to 1294 -> 1324 [0] 
                1294 to 1304 -> 1304 [1] lasti
                1304 to 1310 -> 1324 [0] 
                1310 to 1314 -> 1318 [1] lasti
                1314 to 1324 -> 1480 [0] 
                1324 to 1326 -> 1474 [1] lasti
                1326 to 1348 -> 1350 [2] 
                1348 to 1350 -> 1474 [1] lasti
                1350 to 1354 -> 1358 [3] lasti
                1354 to 1452 -> 1474 [1] lasti
                1452 to 1454 -> 1480 [0] 
                1474 to 1480 -> 1480 [0] 
                1480 to 1502 -> 1502 [1] lasti
        [Code]
            File Name: <frozen program.modules.Group_add_admin>
            Object Name: EntityCorrectGroup
            Qualified Name: EntityCorrectGroup
            Arg Count: 1
            Pos Only Arg Count: 0
            KW Only Arg Count: 0
            Stack Size: 12
            Flags: 0x20000003 (CO_OPTIMIZED | CO_NEWLOCALS | CO_PYARMOR_OBFUSCATED)
            [Names]
                'id'
                'hasattr'
                'username'
                'title'
                'participants_count'
                'isinstance'
                'types'
                'User'
                'User_L199'
                'User_L195'
                'User_L185'
                'User_L184'
                'User_L166'
                'User_L165'
                'User_L159'
                'last_name'
                'first_name'
                'Chat'
                'Channel'
                'Channel_L203'
                'Channel_L199'
                'Channel_L195'
                'Channel_L185'
                'Channel_L167'
                'Channel_L166'
                'Channel_L165'
                'Channel_L161'
                'megagroup'
                'gigagroup'
                'Exception'
                'print'
                'str'
            [Locals+Names]
                'entity'
                '__assert_armored__'
                '_var_var_13'
                '_var_var_3'
            [Constants]
                None
                '__pyarmor_assert_13683__'
                '__pyarmor_enter_13684__'
                b'<COAddr>\x05\x00\x00\x1a\x8e\x05\x00\x00\x00\x00\x00\x00\x00\x00\x00\x00\x00\x00\x00\x00'
                '__pyarmor_exit_13685__'
                False
                'id'
                'username'
                'title'
                'participants_count'   # b"\x81\xf2\x19\x01'\xf3\xbd\xdb\x0b\xfb\x03\xd4\x7f\xd3\xfb\x8a\x1aS\xaf"
                'count'
                ''
                'USER'
                'type'
                'CHAT'
                'megagroup'   # b'\x81\xef\x1d\x142\xfd\xac\xdd\x0e\xea'
                'gigagroup'   # b'\x81\xe5\x11\x142\xfd\xac\xdd\x0e\xea'
                'MEGA_GROUP'   # b'\x81\xcf=4\x12\xc5\x99\xe04\xcf='
                'GIGA_GROUP'   # b'\x81\xc514\x12\xc5\x99\xe04\xcf='
                'CHANNEL'
                'NotDefined'   # b'\x81\xcc\x17\x07\x17\xff\xb8\xdb\x15\xff\t'
                'EntityCorrectGroup: '   # b'\x81\xc7\x16\x07:\xee\xa7\xf1\x14\xe8\x1f\xc5o\xf8\xdf\x97\x00H\xab\xfd\xea'
            [Disassembly]
                0       NOP                             
                2       NOP                             
                4       PUSH_NULL                       
                6       LOAD_CONST                      2: '__pyarmor_enter_13684__'
                8       LOAD_CONST                      3: b'<COAddr>\x05\x00\x00\x1a\x8e\x05\x00\x00\x00\x00\x00\x00\x00\x00\x00\x00\x00\x00\x00\x00'
                10      BUILD_TUPLE                     1
                12      CALL_FUNCTION_EX                0
                14      POP_TOP                         
                16      RESUME                          0
                18      NOP                             
                20      NOP                             
                22      NOP                             
                24      NOP                             
                26      NOP                             
                28      NOP                             
                30      LOAD_FAST                       0: entity
                32      LOAD_CONST                      0: None
                34      COMPARE_OP                      40 (==)
                38      POP_JUMP_IF_FALSE               11 (to 62)
                40      NOP                             
                42      LOAD_CONST                      5: False
                44      NOP                             
                46      NOP                             
                48      JUMP_FORWARD                    712 (to 1476)
                58      POP_TOP                         
                60      RETURN_CONST                    5: False
                62      LOAD_FAST                       0: entity
                64      LOAD_CONST                      5: False
                66      COMPARE_OP                      40 (==)
                70      POP_JUMP_IF_FALSE               11 (to 94)
                72      NOP                             
                74      LOAD_CONST                      5: False
                76      NOP                             
                78      NOP                             
                80      JUMP_FORWARD                    696 (to 1476)
                90      POP_TOP                         
                92      RETURN_CONST                    5: False
                94      BUILD_MAP                       0
                96      STORE_FAST                      2: _var_var_13
                98      LOAD_FAST                       0: entity
                100     LOAD_ATTR                       0: id
                120     LOAD_FAST                       2: _var_var_13
                122     LOAD_CONST                      6: 'id'
                124     STORE_SUBSCR                    
                128     LOAD_GLOBAL                     3: NULL + hasattr
                138     LOAD_FAST                       0: entity
                140     LOAD_CONST                      7: 'username'
                142     CALL                            2
                150     POP_JUMP_IF_FALSE               16 (to 184)
                152     LOAD_FAST                       0: entity
                154     LOAD_ATTR                       4: username
                174     LOAD_FAST                       2: _var_var_13
                176     LOAD_CONST                      7: 'username'
                178     STORE_SUBSCR                    
                182     JUMP_FORWARD                    5 (to 194)
                184     LOAD_CONST                      0: None
                186     LOAD_FAST                       2: _var_var_13
                188     LOAD_CONST                      7: 'username'
                190     STORE_SUBSCR                    
                194     LOAD_GLOBAL                     3: NULL + hasattr
                204     LOAD_FAST                       0: entity
                206     LOAD_CONST                      8: 'title'
                208     CALL                            2
                216     POP_JUMP_IF_FALSE               16 (to 250)
                218     LOAD_FAST                       0: entity
                220     LOAD_ATTR                       6: title
                240     LOAD_FAST                       2: _var_var_13
                242     LOAD_CONST                      8: 'title'
                244     STORE_SUBSCR                    
                248     JUMP_FORWARD                    5 (to 260)
                250     LOAD_CONST                      0: None
                252     LOAD_FAST                       2: _var_var_13
                254     LOAD_CONST                      8: 'title'
                256     STORE_SUBSCR                    
                260     LOAD_GLOBAL                     3: NULL + hasattr
                270     LOAD_FAST                       0: entity
                272     PUSH_NULL                       
                274     LOAD_CONST                      1: '__pyarmor_assert_13683__'
                276     LOAD_CONST                      9: 'participants_count'   # b"\x81\xf2\x19\x01'\xf3\xbd\xdb\x0b\xfb\x03\xd4\x7f\xd3\xfb\x8a\x1aS\xaf"
                278     CALL                            1
                286     CALL                            2
                294     POP_JUMP_IF_FALSE               16 (to 328)
                296     LOAD_FAST                       0: entity
                298     LOAD_ATTR                       8: participants_count
                318     LOAD_FAST                       2: _var_var_13
                320     LOAD_CONST                      10: 'count'
                322     STORE_SUBSCR                    
                326     JUMP_FORWARD                    5 (to 338)
                328     LOAD_CONST                      0: None
                330     LOAD_FAST                       2: _var_var_13
                332     LOAD_CONST                      10: 'count'
                334     STORE_SUBSCR                    
                338     LOAD_GLOBAL                     11: NULL + isinstance
                348     LOAD_FAST                       0: entity
                350     LOAD_GLOBAL                     12: types
                360     LOAD_ATTR                       14: User
                380     LOAD_GLOBAL                     12: types
                390     LOAD_ATTR                       16: User_L199
                410     LOAD_GLOBAL                     12: types
                420     LOAD_ATTR                       18: User_L195
                440     LOAD_GLOBAL                     12: types
                450     LOAD_ATTR                       20: User_L185
                470     LOAD_GLOBAL                     12: types
                480     LOAD_ATTR                       22: User_L184
                500     LOAD_GLOBAL                     12: types
                510     LOAD_ATTR                       24: User_L166
                530     LOAD_GLOBAL                     12: types
                540     LOAD_ATTR                       26: User_L165
                560     LOAD_GLOBAL                     12: types
                570     LOAD_ATTR                       28: User_L159
                590     BUILD_TUPLE                     8
                592     CALL                            2
                600     POP_JUMP_IF_FALSE               66 (to 734)
                602     LOAD_FAST                       0: entity
                604     LOAD_ATTR                       30: last_name
                624     POP_JUMP_IF_NOT_NONE            16 (to 658)
                626     LOAD_FAST                       0: entity
                628     LOAD_ATTR                       32: first_name
                648     LOAD_FAST                       2: _var_var_13
                650     LOAD_CONST                      8: 'title'
                652     STORE_SUBSCR                    
                656     JUMP_FORWARD                    31 (to 720)
                658     LOAD_FAST                       0: entity
                660     LOAD_ATTR                       32: first_name
                680     LOAD_CONST                      11: ''
                682     BINARY_OP                       0 (+)
                686     LOAD_FAST                       0: entity
                688     LOAD_ATTR                       30: last_name
                708     BINARY_OP                       0 (+)
                712     LOAD_FAST                       2: _var_var_13
                714     LOAD_CONST                      8: 'title'
                716     STORE_SUBSCR                    
                720     LOAD_CONST                      12: 'USER'
                722     LOAD_FAST                       2: _var_var_13
                724     LOAD_CONST                      13: 'type'
                726     STORE_SUBSCR                    
                730     JUMP_FORWARD                    286 (to 1306)
                734     LOAD_GLOBAL                     11: NULL + isinstance
                744     LOAD_FAST                       0: entity
                746     LOAD_GLOBAL                     12: types
                756     LOAD_ATTR                       34: Chat
                776     CALL                            2
                784     POP_JUMP_IF_FALSE               6 (to 798)
                786     LOAD_CONST                      14: 'CHAT'
                788     LOAD_FAST                       2: _var_var_13
                790     LOAD_CONST                      13: 'type'
                792     STORE_SUBSCR                    
                796     JUMP_FORWARD                    254 (to 1306)
                798     LOAD_GLOBAL                     11: NULL + isinstance
                808     LOAD_FAST                       0: entity
                810     LOAD_GLOBAL                     12: types
                820     LOAD_ATTR                       36: Channel
                840     LOAD_GLOBAL                     12: types
                850     LOAD_ATTR                       38: Channel_L203
                870     LOAD_GLOBAL                     12: types
                880     LOAD_ATTR                       40: Channel_L199
                900     LOAD_GLOBAL                     12: types
                910     LOAD_ATTR                       42: Channel_L195
                930     LOAD_GLOBAL                     12: types
                940     LOAD_ATTR                       44: Channel_L185
                960     LOAD_GLOBAL                     12: types
                970     LOAD_ATTR                       46: Channel_L167
                990     LOAD_GLOBAL                     12: types
                1000    LOAD_ATTR                       48: Channel_L166
                1020    LOAD_GLOBAL                     12: types
                1030    LOAD_ATTR                       50: Channel_L165
                1050    LOAD_GLOBAL                     12: types
                1060    LOAD_ATTR                       52: Channel_L161
                1080    BUILD_TUPLE                     9
                1082    CALL                            2
                1090    POP_JUMP_IF_FALSE               96 (to 1284)
                1092    LOAD_GLOBAL                     3: NULL + hasattr
                1102    LOAD_FAST                       0: entity
                1104    PUSH_NULL                       
                1106    LOAD_CONST                      1: '__pyarmor_assert_13683__'
                1108    LOAD_CONST                      15: 'megagroup'   # b'\x81\xef\x1d\x142\xfd\xac\xdd\x0e\xea'
                1110    CALL                            1
                1118    CALL                            2
                1126    POP_JUMP_IF_FALSE               72 (to 1272)
                1128    LOAD_GLOBAL                     3: NULL + hasattr
                1138    LOAD_FAST                       0: entity
                1140    PUSH_NULL                       
                1142    LOAD_CONST                      1: '__pyarmor_assert_13683__'
                1144    LOAD_CONST                      16: 'gigagroup'   # b'\x81\xe5\x11\x142\xfd\xac\xdd\x0e\xea'
                1146    CALL                            1
                1154    CALL                            2
                1162    POP_JUMP_IF_FALSE               54 (to 1272)
                1164    LOAD_FAST                       0: entity
                1166    LOAD_ATTR                       54: megagroup
                1186    POP_JUMP_IF_FALSE               12 (to 1212)
                1188    PUSH_NULL                       
                1190    LOAD_CONST                      1: '__pyarmor_assert_13683__'
                1192    LOAD_CONST                      17: 'MEGA_GROUP'   # b'\x81\xcf=4\x12\xc5\x99\xe04\xcf='
                1194    CALL                            1
                1202    LOAD_FAST                       2: _var_var_13
                1204    LOAD_CONST                      13: 'type'
                1206    STORE_SUBSCR                    
                1210    JUMP_FORWARD                    47 (to 1306)
                1212    LOAD_FAST                       0: entity
                1214    LOAD_ATTR                       56: gigagroup
                1234    POP_JUMP_IF_FALSE               12 (to 1260)
                1236    PUSH_NULL                       
                1238    LOAD_CONST                      1: '__pyarmor_assert_13683__'
                1240    LOAD_CONST                      18: 'GIGA_GROUP'   # b'\x81\xc514\x12\xc5\x99\xe04\xcf='
                1242    CALL                            1
                1250    LOAD_FAST                       2: _var_var_13
                1252    LOAD_CONST                      13: 'type'
                1254    STORE_SUBSCR                    
                1258    JUMP_FORWARD                    23 (to 1306)
                1260    LOAD_CONST                      19: 'CHANNEL'
                1262    LOAD_FAST                       2: _var_var_13
                1264    LOAD_CONST                      13: 'type'
                1266    STORE_SUBSCR                    
                1270    JUMP_FORWARD                    17 (to 1306)
                1272    LOAD_CONST                      19: 'CHANNEL'
                1274    LOAD_FAST                       2: _var_var_13
                1276    LOAD_CONST                      13: 'type'
                1278    STORE_SUBSCR                    
                1282    JUMP_FORWARD                    11 (to 1306)
                1284    PUSH_NULL                       
                1286    LOAD_CONST                      1: '__pyarmor_assert_13683__'
                1288    LOAD_CONST                      20: 'NotDefined'   # b'\x81\xcc\x17\x07\x17\xff\xb8\xdb\x15\xff\t'
                1290    CALL                            1
                1298    LOAD_FAST                       2: _var_var_13
                1300    LOAD_CONST                      13: 'type'
                1302    STORE_SUBSCR                    
                1306    LOAD_FAST                       2: _var_var_13
                1308    NOP                             
                1310    NOP                             
                1312    NOP                             
                1314    JUMP_FORWARD                    80 (to 1476)
                1316    CALL                            1
                1324    POP_TOP                         
                1326    RETURN_VALUE                    
                1328    PUSH_EXC_INFO                   
                1330    LOAD_GLOBAL                     58: Exception
                1340    CHECK_EXC_MATCH                 
                1342    POP_JUMP_IF_FALSE               48 (to 1440)
                1344    STORE_FAST                      3: _var_var_3
                1346    LOAD_GLOBAL                     61: NULL + print
                1356    PUSH_NULL                       
                1358    LOAD_CONST                      1: '__pyarmor_assert_13683__'
                1360    LOAD_CONST                      21: 'EntityCorrectGroup: '   # b'\x81\xc7\x16\x07:\xee\xa7\xf1\x14\xe8\x1f\xc5o\xf8\xdf\x97\x00H\xab\xfd\xea'
                1362    CALL                            1
                1370    LOAD_GLOBAL                     63: NULL + str
                1380    LOAD_FAST                       3: _var_var_3
                1382    CALL                            1
                1390    BINARY_OP                       0 (+)
                1394    CALL                            1
                1402    POP_TOP                         
                1404    POP_EXCEPT                      
                1406    LOAD_CONST                      0: None
                1408    STORE_FAST                      3: _var_var_3
                1410    DELETE_FAST                     3: _var_var_3
                1412    LOAD_CONST                      5: False
                1414    NOP                             
                1416    NOP                             
                1418    NOP                             
                1420    JUMP_FORWARD                    27 (to 1476)
                1428    POP_TOP                         
                1430    RETURN_CONST                    5: False
                1432    LOAD_CONST                      0: None
                1434    STORE_FAST                      3: _var_var_3
                1436    DELETE_FAST                     3: _var_var_3
                1438    RERAISE                         1
                1440    RERAISE                         0
                1442    COPY                            3
                1444    POP_EXCEPT                      
                1446    RERAISE                         1
                1448    PUSH_EXC_INFO                   
                1450    PUSH_NULL                       
                1452    LOAD_CONST                      4: '__pyarmor_exit_13685__'
                1454    NOP                             
                1456    LOAD_CONST                      3: b'<COAddr>\x05\x00\x00\x1a\x8e\x05\x00\x00\x00\x00\x00\x00\x00\x00\x00\x00\x00\x00\x00\x00'
                1458    CALL                            1
                1466    POP_TOP                         
                1468    RERAISE                         0
                1470    COPY                            3
                1472    POP_EXCEPT                      
                1474    RERAISE                         1
                1476    PUSH_NULL                       
                1478    LOAD_CONST                      4: '__pyarmor_exit_13685__'
                1480    LOAD_CONST                      3: b'<COAddr>\x05\x00\x00\x1a\x8e\x05\x00\x00\x00\x00\x00\x00\x00\x00\x00\x00\x00\x00\x00\x00'
                1482    BUILD_TUPLE                     1
                1484    CALL_FUNCTION_EX                0
                1486    POP_TOP                         
                1488    RETURN_VALUE                    
            [Exception Table]
                30 to 40 -> 1328 [0] 
                62 to 72 -> 1328 [0] 
                94 to 1308 -> 1328 [0] 
                1328 to 1346 -> 1442 [1] lasti
                1346 to 1404 -> 1432 [1] lasti
                1404 to 1412 -> 1448 [0] 
                1432 to 1442 -> 1442 [1] lasti
                1442 to 1448 -> 1448 [0] 
                1448 to 1470 -> 1470 [1] lasti
        [Code]
            File Name: <frozen program.modules.Group_add_admin>
            Object Name: clear_array
            Qualified Name: clear_array
            Arg Count: 1
            Pos Only Arg Count: 0
            KW Only Arg Count: 0
            Stack Size: 5
            Flags: 0x20000003 (CO_OPTIMIZED | CO_NEWLOCALS | CO_PYARMOR_OBFUSCATED)
            [Names]
                'append'
            [Locals+Names]
                'data'
                '__assert_armored__'
                '_var_var_14'
                '_var_var_15'
            [Constants]
                None
                '__pyarmor_assert_13686__'
                '__pyarmor_enter_13687__'
                b'<COAddr>\x05\x00\x00\x1ad\x00\x00\x00\x00\x00\x00\x00\x00\x00\x00\x00\x00\x00\x00\x00'
                ''
                '__pyarmor_exit_13688__'
            [Disassembly]
                0       NOP                             
                2       NOP                             
                4       PUSH_NULL                       
                6       LOAD_CONST                      2: '__pyarmor_enter_13687__'
                8       LOAD_CONST                      3: b'<COAddr>\x05\x00\x00\x1ad\x00\x00\x00\x00\x00\x00\x00\x00\x00\x00\x00\x00\x00\x00\x00'
                10      BUILD_TUPLE                     1
                12      CALL_FUNCTION_EX                0
                14      POP_TOP                         
                16      RESUME                          0
                18      NOP                             
                20      NOP                             
                22      NOP                             
                24      NOP                             
                26      NOP                             
                28      BUILD_LIST                      0
                30      STORE_FAST                      2: _var_var_14
                32      LOAD_FAST                       0: data
                34      GET_ITER                        
                36      FOR_ITER                        31 (to 100)
                40      STORE_FAST                      3: _var_var_15
                42      LOAD_FAST                       3: _var_var_15
                44      LOAD_CONST                      4: ''
                46      COMPARE_OP                      55 (!=)
                50      POP_JUMP_IF_TRUE                1 (to 54)
                52      JUMP_BACKWARD                   9 (to 36)
                54      LOAD_FAST                       3: _var_var_15
                56      LOAD_CONST                      0: None
                58      COMPARE_OP                      55 (!=)
                62      POP_JUMP_IF_TRUE                1 (to 66)
                64      JUMP_BACKWARD                   15 (to 36)
                66      LOAD_FAST                       2: _var_var_14
                68      LOAD_ATTR                       1: append
                88      LOAD_FAST                       3: _var_var_15
                90      CALL                            1
                98      POP_TOP                         
                100     JUMP_BACKWARD                   33 (to 36)
                102     END_FOR                         
                104     LOAD_FAST                       2: _var_var_14
                106     NOP                             
                108     NOP                             
                110     NOP                             
                112     JUMP_FORWARD                    20 (to 154)
                114     CALL                            1
                122     POP_TOP                         
                124     RETURN_VALUE                    
                126     PUSH_EXC_INFO                   
                128     PUSH_NULL                       
                130     LOAD_CONST                      5: '__pyarmor_exit_13688__'
                132     NOP                             
                134     LOAD_CONST                      3: b'<COAddr>\x05\x00\x00\x1ad\x00\x00\x00\x00\x00\x00\x00\x00\x00\x00\x00\x00\x00\x00\x00'
                136     CALL                            1
                144     POP_TOP                         
                146     RERAISE                         0
                148     COPY                            3
                150     POP_EXCEPT                      
                152     RERAISE                         1
                154     PUSH_NULL                       
                156     LOAD_CONST                      5: '__pyarmor_exit_13688__'
                158     LOAD_CONST                      3: b'<COAddr>\x05\x00\x00\x1ad\x00\x00\x00\x00\x00\x00\x00\x00\x00\x00\x00\x00\x00\x00\x00'
                160     BUILD_TUPLE                     1
                162     CALL_FUNCTION_EX                0
                164     POP_TOP                         
                166     RETURN_VALUE                    
            [Exception Table]
                28 to 52 -> 126 [0] 
                54 to 64 -> 126 [0] 
                66 to 106 -> 126 [0] 
                126 to 148 -> 148 [1] lasti
        [Code]
            File Name: <frozen program.modules.Group_add_admin>
            Object Name: check_array_word
            Qualified Name: check_array_word
            Arg Count: 2
            Pos Only Arg Count: 0
            KW Only Arg Count: 0
            Stack Size: 5
            Flags: 0x20000003 (CO_OPTIMIZED | CO_NEWLOCALS | CO_PYARMOR_OBFUSCATED)
            [Names]
                'lower'
            [Locals+Names]
                'text'
                'words'
                '__assert_armored__'
                '_var_var_16'
            [Constants]
                None
                '__pyarmor_assert_13689__'
                '__pyarmor_enter_13690__'
                b'<COAddr>\x05\x00\x00\x1az\x00\x00\x00\x00\x00\x00\x00\x00\x00\x00\x00\x00\x00\x00\x00'
                '__pyarmor_exit_13691__'
                True
                False
            [Disassembly]
                0       NOP                             
                2       NOP                             
                4       PUSH_NULL                       
                6       LOAD_CONST                      2: '__pyarmor_enter_13690__'
                8       LOAD_CONST                      3: b'<COAddr>\x05\x00\x00\x1az\x00\x00\x00\x00\x00\x00\x00\x00\x00\x00\x00\x00\x00\x00\x00'
                10      BUILD_TUPLE                     1
                12      CALL_FUNCTION_EX                0
                14      POP_TOP                         
                16      RESUME                          0
                18      NOP                             
                20      NOP                             
                22      NOP                             
                24      NOP                             
                26      NOP                             
                28      LOAD_FAST                       1: words
                30      GET_ITER                        
                32      FOR_ITER                        45 (to 124)
                36      STORE_FAST                      3: _var_var_16
                38      LOAD_FAST                       3: _var_var_16
                40      LOAD_ATTR                       1: lower
                60      CALL                            0
                68      LOAD_FAST                       0: text
                70      LOAD_ATTR                       1: lower
                90      CALL                            0
                98      CONTAINS_OP                     0 (in)
                100     POP_JUMP_IF_TRUE                1 (to 104)
                102     JUMP_BACKWARD                   36 (to 32)
                104     POP_TOP                         
                106     LOAD_CONST                      5: True
                108     NOP                             
                110     NOP                             
                112     NOP                             
                114     JUMP_FORWARD                    30 (to 176)
                122     POP_TOP                         
                124     RETURN_CONST                    5: True
                126     END_FOR                         
                128     LOAD_CONST                      6: False
                130     NOP                             
                132     NOP                             
                134     NOP                             
                136     JUMP_FORWARD                    19 (to 176)
                144     POP_TOP                         
                146     RETURN_CONST                    6: False
                148     PUSH_EXC_INFO                   
                150     PUSH_NULL                       
                152     LOAD_CONST                      4: '__pyarmor_exit_13691__'
                154     NOP                             
                156     LOAD_CONST                      3: b'<COAddr>\x05\x00\x00\x1az\x00\x00\x00\x00\x00\x00\x00\x00\x00\x00\x00\x00\x00\x00\x00'
                158     CALL                            1
                166     POP_TOP                         
                168     RERAISE                         0
                170     COPY                            3
                172     POP_EXCEPT                      
                174     RERAISE                         1
                176     PUSH_NULL                       
                178     LOAD_CONST                      4: '__pyarmor_exit_13691__'
                180     LOAD_CONST                      3: b'<COAddr>\x05\x00\x00\x1az\x00\x00\x00\x00\x00\x00\x00\x00\x00\x00\x00\x00\x00\x00\x00'
                182     BUILD_TUPLE                     1
                184     CALL_FUNCTION_EX                0
                186     POP_TOP                         
                188     RETURN_VALUE                    
            [Exception Table]
                28 to 102 -> 148 [0] 
                104 to 106 -> 148 [0] 
                126 to 128 -> 148 [0] 
                148 to 170 -> 170 [1] lasti
        [Code]
            File Name: <frozen program.modules.Group_add_admin>
            Object Name: replace_array_word
            Qualified Name: replace_array_word
            Arg Count: 2
            Pos Only Arg Count: 0
            KW Only Arg Count: 0
            Stack Size: 6
            Flags: 0x20000003 (CO_OPTIMIZED | CO_NEWLOCALS | CO_PYARMOR_OBFUSCATED)
            [Names]
                'len'
                'split'
                'replace'
            [Locals+Names]
                'text'
                'words'
                '__assert_armored__'
                '_var_var_16'
            [Constants]
                None
                '__pyarmor_assert_13692__'
                '__pyarmor_enter_13693__'
                b'<COAddr>\x05\x00\x00\x1a\x94\x00\x00\x00\x00\x00\x00\x00\x00\x00\x00\x00\x00\x00\x00\x00'
                0
                ':'
                1
                '__pyarmor_exit_13694__'
            [Disassembly]
                0       NOP                             
                2       NOP                             
                4       PUSH_NULL                       
                6       LOAD_CONST                      2: '__pyarmor_enter_13693__'
                8       LOAD_CONST                      3: b'<COAddr>\x05\x00\x00\x1a\x94\x00\x00\x00\x00\x00\x00\x00\x00\x00\x00\x00\x00\x00\x00\x00'
                10      BUILD_TUPLE                     1
                12      CALL_FUNCTION_EX                0
                14      POP_TOP                         
                16      RESUME                          0
                18      NOP                             
                20      NOP                             
                22      NOP                             
                24      NOP                             
                26      NOP                             
                28      LOAD_GLOBAL                     1: NULL + len
                38      LOAD_FAST                       1: words
                40      CALL                            1
                48      LOAD_CONST                      4: 0
                50      COMPARE_OP                      68 (>)
                54      POP_JUMP_IF_FALSE               48 (to 152)
                56      LOAD_FAST                       1: words
                58      GET_ITER                        
                60      FOR_ITER                        43 (to 148)
                64      STORE_FAST                      3: _var_var_16
                66      LOAD_FAST                       3: _var_var_16
                68      LOAD_ATTR                       3: split
                88      LOAD_CONST                      5: ':'
                90      CALL                            1
                98      STORE_FAST                      3: _var_var_16
                100     LOAD_FAST                       0: text
                102     LOAD_ATTR                       5: replace
                122     LOAD_FAST                       3: _var_var_16
                124     LOAD_CONST                      4: 0
                126     BINARY_SUBSCR                   
                130     LOAD_FAST                       3: _var_var_16
                132     LOAD_CONST                      6: 1
                134     BINARY_SUBSCR                   
                138     CALL                            2
                146     STORE_FAST                      0: text
                148     JUMP_BACKWARD                   45 (to 60)
                150     END_FOR                         
                152     LOAD_FAST                       0: text
                154     NOP                             
                156     NOP                             
                158     NOP                             
                160     JUMP_FORWARD                    20 (to 202)
                162     CALL                            1
                170     POP_TOP                         
                172     RETURN_VALUE                    
                174     PUSH_EXC_INFO                   
                176     PUSH_NULL                       
                178     LOAD_CONST                      7: '__pyarmor_exit_13694__'
                180     NOP                             
                182     LOAD_CONST                      3: b'<COAddr>\x05\x00\x00\x1a\x94\x00\x00\x00\x00\x00\x00\x00\x00\x00\x00\x00\x00\x00\x00\x00'
                184     CALL                            1
                192     POP_TOP                         
                194     RERAISE                         0
                196     COPY                            3
                198     POP_EXCEPT                      
                200     RERAISE                         1
                202     PUSH_NULL                       
                204     LOAD_CONST                      7: '__pyarmor_exit_13694__'
                206     LOAD_CONST                      3: b'<COAddr>\x05\x00\x00\x1a\x94\x00\x00\x00\x00\x00\x00\x00\x00\x00\x00\x00\x00\x00\x00\x00'
                208     BUILD_TUPLE                     1
                210     CALL_FUNCTION_EX                0
                212     POP_TOP                         
                214     RETURN_VALUE                    
            [Exception Table]
                28 to 154 -> 174 [0] 
                174 to 196 -> 196 [1] lasti
        [Code]
            File Name: <frozen program.modules.Group_add_admin>
            Object Name: get_user_entity
            Qualified Name: get_user_entity
            Arg Count: 6
            Pos Only Arg Count: 0
            KW Only Arg Count: 0
            Stack Size: 11
            Flags: 0x20000003 (CO_OPTIMIZED | CO_NEWLOCALS | CO_PYARMOR_OBFUSCATED)
            [Names]
                'get_entity'
                'isinstance'
                'types'
                'User'
                'User_L199'
                'User_L195'
                'User_L185'
                'User_L184'
                'User_L166'
                'User_L165'
                'User_L159'
                'ConnectionError'
                'get_user_entity'
                'ValueError'
                'errors'
                'UsernameInvalidError'
                'UsernameNotOccupiedError'
                'TypeNotFoundError'
                'FloodWaitError'
                'int'
                'seconds'
                'Logs'
                'PrintLog'
                'Lang'
                'random'
                'randint'
                'time'
                'sleep'
                'DelayOnline'
                'Exception'
            [Locals+Names]
                'account'
                'client'
                'username'
                'max_flood_wait'
                'config'
                'stop_thread'
                '__assert_armored__'
                '_var_var_17'
                '_var_var_3'
                '_var_var_18'
                '_var_var_19'
            [Constants]
                None
                '__pyarmor_assert_13695__'
                '__pyarmor_enter_13696__'
                b'<COAddr>\x07\x00\x00\x1a\xfa\x05\x00\x00\x00\x00\x00\x00\x00\x00\x00\x00\x00\x00\x00\x00'
                '__pyarmor_exit_13697__'
                False
                30
                'restriction_detected'   # b"\x81\xf0\x1d\x00'\xe8\xb7\xd1\x0f\xf3\x02\xceS\xe8\xfd\x91\n^\xaf\xa2\xae"
                (
                    'config'
                    'account'
                    'message'
                )
                'algorithm_running'   # b'\x81\xe3\x14\x14<\xe8\xb7\xc6\x13\xf72\xd2y\xe2\xf6\x8c\x01Z'
                10
                20
                'flood_wait_more_sec'   # b'\x81\xe4\x14\x1c<\xfe\x81\xc5\x1a\xf3\x19\xffa\xe3\xea\x800N\xbe\xa4'
                (
                    'config'
                    'account'
                    'message'
                    'param'
                )
                'invite_stopped'   # b'\x81\xeb\x16\x05:\xee\xbb\xed\x08\xee\x02\xd0|\xe9\xfc'
                'stop'
                'algorithm_running_wait'   # b'\x81\xe3\x14\x14<\xe8\xb7\xc6\x13\xf72\xd2y\xe2\xf6\x8c\x01Z\x84\xb0\xab\xc2Z'
                1
                2
                'back_in_ranks'   # b'\x81\xe0\x19\x108\xc5\xb7\xdc$\xe8\x0c\xceg\xff'
                'Warning: get_entity '   # b'\x81\xd5\x19\x01=\xf3\xb0\xd5A\xba\n\xc5x\xd3\xfd\x8b\x1bT\xaf\xbe\xea'
                (
                    'config'
                    'account'
                    'message'
                    'param'
                    'end'
                )
            [Disassembly]
                0       NOP                             
                2       NOP                             
                4       PUSH_NULL                       
                6       LOAD_CONST                      2: '__pyarmor_enter_13696__'
                8       LOAD_CONST                      3: b'<COAddr>\x07\x00\x00\x1a\xfa\x05\x00\x00\x00\x00\x00\x00\x00\x00\x00\x00\x00\x00\x00\x00'
                10      BUILD_TUPLE                     1
                12      CALL_FUNCTION_EX                0
                14      POP_TOP                         
                16      RESUME                          0
                18      NOP                             
                20      NOP                             
                22      NOP                             
                24      NOP                             
                26      NOP                             
                28      NOP                             
                30      LOAD_FAST                       1: client
                32      LOAD_ATTR                       1: get_entity
                52      LOAD_FAST                       2: username
                54      CALL                            1
                62      STORE_FAST                      7: _var_var_17
                64      LOAD_GLOBAL                     3: NULL + isinstance
                74      LOAD_FAST                       7: _var_var_17
                76      LOAD_GLOBAL                     4: types
                86      LOAD_ATTR                       6: User
                106     LOAD_GLOBAL                     4: types
                116     LOAD_ATTR                       8: User_L199
                136     LOAD_GLOBAL                     4: types
                146     LOAD_ATTR                       10: User_L195
                166     LOAD_GLOBAL                     4: types
                176     LOAD_ATTR                       12: User_L185
                196     LOAD_GLOBAL                     4: types
                206     LOAD_ATTR                       14: User_L184
                226     LOAD_GLOBAL                     4: types
                236     LOAD_ATTR                       16: User_L166
                256     LOAD_GLOBAL                     4: types
                266     LOAD_ATTR                       18: User_L165
                286     LOAD_GLOBAL                     4: types
                296     LOAD_ATTR                       20: User_L159
                316     BUILD_TUPLE                     8
                318     CALL                            2
                326     POP_JUMP_IF_FALSE               11 (to 350)
                328     LOAD_FAST                       7: _var_var_17
                330     NOP                             
                332     NOP                             
                334     JUMP_FORWARD                    623 (to 1584)
                338     CALL                            1
                346     POP_TOP                         
                348     RETURN_VALUE                    
                350     NOP                             
                352     LOAD_CONST                      5: False
                354     NOP                             
                356     NOP                             
                358     JUMP_FORWARD                    611 (to 1584)
                368     POP_TOP                         
                370     RETURN_CONST                    5: False
                372     PUSH_EXC_INFO                   
                374     LOAD_GLOBAL                     22: ConnectionError
                384     CHECK_EXC_MATCH                 
                386     POP_JUMP_IF_FALSE               28 (to 444)
                388     POP_TOP                         
                390     LOAD_GLOBAL                     25: NULL + get_user_entity
                400     LOAD_FAST                       0: account
                402     LOAD_FAST                       1: client
                404     LOAD_FAST                       2: username
                406     LOAD_FAST                       3: max_flood_wait
                408     LOAD_FAST                       4: config
                410     LOAD_FAST                       5: stop_thread
                412     CALL                            6
                420     SWAP                            2
                422     POP_EXCEPT                      
                424     NOP                             
                426     NOP                             
                428     JUMP_FORWARD                    576 (to 1584)
                432     CALL                            1
                440     POP_TOP                         
                442     RETURN_VALUE                    
                444     LOAD_GLOBAL                     26: ValueError
                454     CHECK_EXC_MATCH                 
                456     POP_JUMP_IF_FALSE               12 (to 482)
                458     POP_TOP                         
                460     POP_EXCEPT                      
                462     LOAD_CONST                      5: False
                464     NOP                             
                466     NOP                             
                468     JUMP_FORWARD                    556 (to 1584)
                478     POP_TOP                         
                480     RETURN_CONST                    5: False
                482     LOAD_GLOBAL                     28: errors
                492     LOAD_ATTR                       30: UsernameInvalidError
                512     CHECK_EXC_MATCH                 
                514     POP_JUMP_IF_FALSE               12 (to 540)
                516     POP_TOP                         
                518     POP_EXCEPT                      
                520     LOAD_CONST                      5: False
                522     NOP                             
                524     NOP                             
                526     JUMP_FORWARD                    527 (to 1584)
                536     POP_TOP                         
                538     RETURN_CONST                    5: False
                540     LOAD_GLOBAL                     28: errors
                550     LOAD_ATTR                       32: UsernameNotOccupiedError
                570     CHECK_EXC_MATCH                 
                572     POP_JUMP_IF_FALSE               12 (to 598)
                574     POP_TOP                         
                576     POP_EXCEPT                      
                578     LOAD_CONST                      5: False
                580     NOP                             
                582     NOP                             
                584     JUMP_FORWARD                    498 (to 1584)
                594     POP_TOP                         
                596     RETURN_CONST                    5: False
                598     LOAD_GLOBAL                     28: errors
                608     LOAD_ATTR                       34: TypeNotFoundError
                628     CHECK_EXC_MATCH                 
                630     POP_JUMP_IF_FALSE               12 (to 656)
                632     POP_TOP                         
                634     POP_EXCEPT                      
                636     LOAD_CONST                      5: False
                638     NOP                             
                640     NOP                             
                642     JUMP_FORWARD                    469 (to 1584)
                652     POP_TOP                         
                654     RETURN_CONST                    5: False
                656     LOAD_GLOBAL                     28: errors
                666     LOAD_ATTR                       36: FloodWaitError
                686     CHECK_EXC_MATCH                 
                688     POP_JUMP_IF_FALSE               370 (to 1432)
                692     STORE_FAST                      8: _var_var_3
                694     LOAD_GLOBAL                     39: NULL + int
                704     LOAD_FAST                       8: _var_var_3
                706     LOAD_ATTR                       40: seconds
                726     CALL                            1
                734     STORE_FAST                      9: _var_var_18
                736     JUMP_FORWARD                    9 (to 756)
                738     PUSH_EXC_INFO                   
                740     POP_TOP                         
                742     LOAD_CONST                      6: 30
                744     STORE_FAST                      9: _var_var_18
                746     POP_EXCEPT                      
                748     JUMP_FORWARD                    3 (to 756)
                750     COPY                            3
                752     POP_EXCEPT                      
                754     RERAISE                         1
                756     LOAD_GLOBAL                     43: NULL + Logs
                766     LOAD_ATTR                       44: PrintLog
                786     LOAD_FAST                       4: config
                788     LOAD_FAST                       0: account
                790     LOAD_GLOBAL                     46: Lang
                800     PUSH_NULL                       
                802     LOAD_CONST                      1: '__pyarmor_assert_13695__'
                804     LOAD_CONST                      7: 'restriction_detected'   # b"\x81\xf0\x1d\x00'\xe8\xb7\xd1\x0f\xf3\x02\xceS\xe8\xfd\x91\n^\xaf\xa2\xae"
                806     CALL                            1
                814     BINARY_SUBSCR                   
                818     KW_NAMES                        8: ('config', 'account', 'message')
                820     CALL                            3
                828     POP_TOP                         
                830     LOAD_GLOBAL                     43: NULL + Logs
                840     LOAD_ATTR                       44: PrintLog
                860     LOAD_FAST                       4: config
                862     LOAD_FAST                       0: account
                864     LOAD_GLOBAL                     46: Lang
                874     PUSH_NULL                       
                876     LOAD_CONST                      1: '__pyarmor_assert_13695__'
                878     LOAD_CONST                      9: 'algorithm_running'   # b'\x81\xe3\x14\x14<\xe8\xb7\xc6\x13\xf72\xd2y\xe2\xf6\x8c\x01Z'
                880     CALL                            1
                888     BINARY_SUBSCR                   
                892     KW_NAMES                        8: ('config', 'account', 'message')
                894     CALL                            3
                902     POP_TOP                         
                904     LOAD_FAST                       9: _var_var_18
                906     LOAD_GLOBAL                     49: NULL + random
                916     LOAD_ATTR                       50: randint
                936     LOAD_CONST                      10: 10
                938     LOAD_CONST                      11: 20
                940     CALL                            2
                948     BINARY_OP                       0 (+)
                952     STORE_FAST                      10: _var_var_19
                954     LOAD_FAST                       9: _var_var_18
                956     LOAD_FAST                       3: max_flood_wait
                958     COMPARE_OP                      68 (>)
                962     POP_JUMP_IF_FALSE               89 (to 1142)
                964     LOAD_GLOBAL                     43: NULL + Logs
                974     LOAD_ATTR                       44: PrintLog
                994     LOAD_FAST                       4: config
                996     LOAD_FAST                       0: account
                998     LOAD_GLOBAL                     46: Lang
                1008    PUSH_NULL                       
                1010    LOAD_CONST                      1: '__pyarmor_assert_13695__'
                1012    LOAD_CONST                      12: 'flood_wait_more_sec'   # b'\x81\xe4\x14\x1c<\xfe\x81\xc5\x1a\xf3\x19\xffa\xe3\xea\x800N\xbe\xa4'
                1014    CALL                            1
                1022    BINARY_SUBSCR                   
                1026    LOAD_FAST                       3: max_flood_wait
                1028    KW_NAMES                        13: ('config', 'account', 'message', 'param')
                1030    CALL                            4
                1038    POP_TOP                         
                1040    LOAD_GLOBAL                     43: NULL + Logs
                1050    LOAD_ATTR                       44: PrintLog
                1070    LOAD_FAST                       4: config
                1072    LOAD_FAST                       0: account
                1074    LOAD_GLOBAL                     46: Lang
                1084    PUSH_NULL                       
                1086    LOAD_CONST                      1: '__pyarmor_assert_13695__'
                1088    LOAD_CONST                      14: 'invite_stopped'   # b'\x81\xeb\x16\x05:\xee\xbb\xed\x08\xee\x02\xd0|\xe9\xfc'
                1090    CALL                            1
                1098    BINARY_SUBSCR                   
                1102    KW_NAMES                        8: ('config', 'account', 'message')
                1104    CALL                            3
                1112    POP_TOP                         
                1114    POP_EXCEPT                      
                1116    LOAD_CONST                      0: None
                1118    STORE_FAST                      8: _var_var_3
                1120    DELETE_FAST                     8: _var_var_3
                1122    LOAD_CONST                      15: 'stop'
                1124    NOP                             
                1126    NOP                             
                1128    NOP                             
                1130    JUMP_FORWARD                    226 (to 1584)
                1138    POP_TOP                         
                1140    RETURN_CONST                    15: 'stop'
                1142    LOAD_GLOBAL                     43: NULL + Logs
                1152    LOAD_ATTR                       44: PrintLog
                1172    LOAD_FAST                       4: config
                1174    LOAD_FAST                       0: account
                1176    LOAD_GLOBAL                     46: Lang
                1186    PUSH_NULL                       
                1188    LOAD_CONST                      1: '__pyarmor_assert_13695__'
                1190    LOAD_CONST                      16: 'algorithm_running_wait'   # b'\x81\xe3\x14\x14<\xe8\xb7\xc6\x13\xf72\xd2y\xe2\xf6\x8c\x01Z\x84\xb0\xab\xc2Z'
                1192    CALL                            1
                1200    BINARY_SUBSCR                   
                1204    LOAD_FAST                       10: _var_var_19
                1206    KW_NAMES                        13: ('config', 'account', 'message', 'param')
                1208    CALL                            4
                1216    POP_TOP                         
                1218    LOAD_GLOBAL                     53: NULL + time
                1228    LOAD_ATTR                       54: sleep
                1248    LOAD_FAST                       10: _var_var_19
                1250    CALL                            1
                1258    POP_TOP                         
                1260    LOAD_GLOBAL                     57: NULL + DelayOnline
                1270    LOAD_FAST                       0: account
                1272    LOAD_FAST                       1: client
                1274    LOAD_CONST                      17: 1
                1276    LOAD_CONST                      18: 2
                1278    LOAD_FAST                       5: stop_thread
                1280    CALL                            5
                1288    POP_TOP                         
                1290    LOAD_GLOBAL                     43: NULL + Logs
                1300    LOAD_ATTR                       44: PrintLog
                1320    LOAD_FAST                       4: config
                1322    LOAD_FAST                       0: account
                1324    LOAD_GLOBAL                     46: Lang
                1334    PUSH_NULL                       
                1336    LOAD_CONST                      1: '__pyarmor_assert_13695__'
                1338    LOAD_CONST                      19: 'back_in_ranks'   # b'\x81\xe0\x19\x108\xc5\xb7\xdc$\xe8\x0c\xceg\xff'
                1340    CALL                            1
                1348    BINARY_SUBSCR                   
                1352    KW_NAMES                        8: ('config', 'account', 'message')
                1354    CALL                            3
                1362    POP_TOP                         
                1364    LOAD_GLOBAL                     25: NULL + get_user_entity
                1374    LOAD_FAST                       0: account
                1376    LOAD_FAST                       1: client
                1378    LOAD_FAST                       2: username
                1380    LOAD_FAST                       3: max_flood_wait
                1382    LOAD_FAST                       4: config
                1384    LOAD_FAST                       5: stop_thread
                1386    CALL                            6
                1394    SWAP                            2
                1396    POP_EXCEPT                      
                1398    LOAD_CONST                      0: None
                1400    STORE_FAST                      8: _var_var_3
                1402    DELETE_FAST                     8: _var_var_3
                1404    NOP                             
                1406    NOP                             
                1408    NOP                             
                1410    JUMP_FORWARD                    86 (to 1584)
                1412    CALL                            1
                1420    POP_TOP                         
                1422    RETURN_VALUE                    
                1424    LOAD_CONST                      0: None
                1426    STORE_FAST                      8: _var_var_3
                1428    DELETE_FAST                     8: _var_var_3
                1430    RERAISE                         1
                1432    LOAD_GLOBAL                     58: Exception
                1442    CHECK_EXC_MATCH                 
                1444    POP_JUMP_IF_FALSE               51 (to 1548)
                1446    STORE_FAST                      8: _var_var_3
                1448    LOAD_GLOBAL                     43: NULL + Logs
                1458    LOAD_ATTR                       44: PrintLog
                1478    LOAD_FAST                       4: config
                1480    LOAD_FAST                       0: account
                1482    PUSH_NULL                       
                1484    LOAD_CONST                      1: '__pyarmor_assert_13695__'
                1486    LOAD_CONST                      20: 'Warning: get_entity '   # b'\x81\xd5\x19\x01=\xf3\xb0\xd5A\xba\n\xc5x\xd3\xfd\x8b\x1bT\xaf\xbe\xea'
                1488    CALL                            1
                1496    LOAD_FAST                       2: username
                1498    LOAD_FAST                       8: _var_var_3
                1500    KW_NAMES                        21: ('config', 'account', 'message', 'param', 'end')
                1502    CALL                            5
                1510    POP_TOP                         
                1512    POP_EXCEPT                      
                1514    LOAD_CONST                      0: None
                1516    STORE_FAST                      8: _var_var_3
                1518    DELETE_FAST                     8: _var_var_3
                1520    LOAD_CONST                      15: 'stop'
                1522    NOP                             
                1524    NOP                             
                1526    NOP                             
                1528    JUMP_FORWARD                    27 (to 1584)
                1536    POP_TOP                         
                1538    RETURN_CONST                    15: 'stop'
                1540    LOAD_CONST                      0: None
                1542    STORE_FAST                      8: _var_var_3
                1544    DELETE_FAST                     8: _var_var_3
                1546    RERAISE                         1
                1548    RERAISE                         0
                1550    COPY                            3
                1552    POP_EXCEPT                      
                1554    RERAISE                         1
                1556    PUSH_EXC_INFO                   
                1558    PUSH_NULL                       
                1560    LOAD_CONST                      4: '__pyarmor_exit_13697__'
                1562    NOP                             
                1564    LOAD_CONST                      3: b'<COAddr>\x07\x00\x00\x1a\xfa\x05\x00\x00\x00\x00\x00\x00\x00\x00\x00\x00\x00\x00\x00\x00'
                1566    CALL                            1
                1574    POP_TOP                         
                1576    RERAISE                         0
                1578    COPY                            3
                1580    POP_EXCEPT                      
                1582    RERAISE                         1
                1584    PUSH_NULL                       
                1586    LOAD_CONST                      4: '__pyarmor_exit_13697__'
                1588    LOAD_CONST                      3: b'<COAddr>\x07\x00\x00\x1a\xfa\x05\x00\x00\x00\x00\x00\x00\x00\x00\x00\x00\x00\x00\x00\x00'
                1590    BUILD_TUPLE                     1
                1592    CALL_FUNCTION_EX                0
                1594    POP_TOP                         
                1596    RETURN_VALUE                    
            [Exception Table]
                30 to 330 -> 372 [0] 
                372 to 422 -> 1550 [1] lasti
                422 to 424 -> 1556 [0] 
                444 to 460 -> 1550 [1] lasti
                460 to 462 -> 1556 [0] 
                482 to 518 -> 1550 [1] lasti
                518 to 520 -> 1556 [0] 
                540 to 576 -> 1550 [1] lasti
                576 to 578 -> 1556 [0] 
                598 to 634 -> 1550 [1] lasti
                634 to 636 -> 1556 [0] 
                656 to 694 -> 1550 [1] lasti
                694 to 736 -> 738 [1] 
                736 to 738 -> 1424 [1] lasti
                738 to 746 -> 750 [2] lasti
                746 to 1114 -> 1424 [1] lasti
                1114 to 1122 -> 1556 [0] 
                1142 to 1394 -> 1424 [1] lasti
                1394 to 1396 -> 1550 [1] lasti
                1396 to 1404 -> 1556 [0] 
                1424 to 1448 -> 1550 [1] lasti
                1448 to 1512 -> 1540 [1] lasti
                1512 to 1520 -> 1556 [0] 
                1540 to 1550 -> 1550 [1] lasti
                1550 to 1556 -> 1556 [0] 
                1556 to 1578 -> 1578 [1] lasti
        [Code]
            File Name: <frozen program.modules.Group_add_admin>
            Object Name: SetAdminGroups
            Qualified Name: SetAdminGroups
            Arg Count: 5
            Pos Only Arg Count: 0
            KW Only Arg Count: 0
            Stack Size: 22
            Flags: 0x20000003 (CO_OPTIMIZED | CO_NEWLOCALS | CO_PYARMOR_OBFUSCATED)
            [Names]
                'account_works'
                'Lang'
                'Disconnect'
                'Logs'
                'PrintLog'
                'get'
                'clear_array'
                'len'
                'iter_dialogs'
                'is_set'
                'StopProgram'
                'hasattr'
                'str'
                'id'
                'append'
                'entity'
                'Exception'
                'get_user_entity'
                'name'
                'first_name'
                'functions'
                'channels'
                'EditAdminRequest'
                'types'
                'ChatAdminRights'
                'username'
                'BaseException'
                'logging'
            [Locals+Names]
                'account'
                'data'
                'config'
                'proxy'
                'stop_thread'
                '__assert_armored__'
                '_var_var_8'
                '_var_var_5'
                '_var_var_6'
                '_var_var_20'
                '_var_var_21'
                '_var_var_22'
                '_var_var_23'
                '_var_var_24'
                '_var_var_25'
                '_var_var_26'
                '_var_var_27'
                '_var_var_28'
                '_var_var_29'
                '_var_var_30'
                '_var_var_31'
                '_var_var_32'
                '_var_var_12'
                '_var_var_33'
                '_var_var_3'
                '_var_var_34'
                '_var_var_35'
                '_var_var_36'
                '_var_var_37'
                '_var_var_7'
            [Constants]
                None
                '__pyarmor_assert_13698__'
                '__pyarmor_enter_13699__'
                b'<COAddr>\x05\x00\x00\x1a\xaa\n\x00\x00\x00\x00\x00\x00\x00\x00\x00\x00\x00\x00\x00\x00'
                'AddAdmin'
                (
                    'module'
                )
                False
                'false'
                (
                    'account'
                    'status'
                )
                'work_account_completed'   # b'\x81\xf5\x17\x018\xc5\xbf\xd1\x18\xf5\x18\xcex\xd3\xfb\x8a\x02M\xb7\xa2\xbe\xceJ'
                (
                    'config'
                    'account'
                    'message'
                )
                'done'
                '__pyarmor_exit_13700__'
                'Settings'
                'source'
                'usernames'   # b'\x81\xf7\x0b\x16!\xf4\xbf\xdf\x1e\xe9'
                'change_info'   # b'\x81\xe1\x10\x12=\xfd\xbb\xed\x12\xf4\x0b\xcf'
                'post_messages'   # b"\x81\xf2\x17\x00'\xc5\xb3\xd7\x08\xe9\x0c\xc7i\xff"
                'edit_messages'   # b"\x81\xe7\x1c\x1a'\xc5\xb3\xd7\x08\xe9\x0c\xc7i\xff"
                'delete_messages'   # b'\x81\xe6\x1d\x1f6\xee\xbb\xed\x16\xff\x1e\xd3m\xeb\xfd\x96'
                'ban_users'   # b'\x81\xe0\x19\x1d\x0c\xef\xad\xd7\t\xe9'
                'invite_users'   # b'\x81\xeb\x16\x05:\xee\xbb\xed\x0e\xe9\x08\xd2\x7f'
                'pin_messages'   # b'\x81\xf2\x11\x1d\x0c\xf7\xbb\xc1\x08\xfb\n\xc5\x7f'
                'manage_call'   # b'\x81\xef\x19\x1d2\xfd\xbb\xed\x18\xfb\x01\xcc'
                'anonymous'   # b'\x81\xe3\x16\x1c=\xe3\xb3\xdd\x0e\xe9'
                'add_admins'   # b'\x81\xe3\x1c\x17\x0c\xfb\xba\xdf\x12\xf4\x1e'
                0
                500
                (
                    'limit'
                )
                'id'
                True
                'entity'
                'error_detected'   # b'\x81\xe7\n\x01<\xe8\x81\xd6\x1e\xee\x08\xc3x\xe9\xfc'
                (
                    'config'
                    'account'
                    'message'
                    'param'
                )
                'Проверяю пользователя: '   # b'\x81R\xe7\xa2\xd3J`b\xc9J\xd8q\x8c]\x174\xe1\x1d\x0bx\x1a\x15\xfe\x17\xb4\x83\x13\x8b\xb0o\xae7\x8a\x82\x91\xef(\x1f\x04\xf5\xa9\x06\xa2\x1d'
                120
                'stop'
                'name'
                'Устанавливаю админов для группы:'   # b'\x81R\xdb\xa2\xd2K\\b\xcbJ\xd0p\xbc\\*5\xd4\xedc\x17x{\x9e}\xeb/\x13\x8c\xb0e\xae9\x8a\x8a\x90\xd0(\x14\x04\xfcXY,\xed\x06i\xe0\x07\x87>\xe7\x1b6\x93\xb62\x874*\xf6B'
                'first_name'   # b'\x81\xe4\x11\x01 \xee\x81\xdc\x1a\xf7\x08'
                'Добавляю пользователя:'   # b'\x81R\xec\xa3\xedJob\xcbJ\xdfp\xb7]\x174\xe1\x1d\x0bx\x1a\x15\xfe\x17\xb4\x83\x13\x8b\xb0o\xae7\x8a\x82\x91\xef(\x1f\x04\xf5\xa9\x06\xa2'
                (
                    'change_info'
                    'post_messages'
                    'edit_messages'
                    'delete_messages'
                    'ban_users'
                    'invite_users'
                    'pin_messages'
                    'add_admins'
                    'anonymous'
                    'manage_call'
                    'other'
                    'manage_topics'
                )
                ''
                (
                    'channel'
                    'user_id'
                    'admin_rights'
                    'rank'
                )
                1
                'Установил права администратора:'   # b'\x81R\xdb\xa2\xd2K\\b\xcbJ\xd0p\xb2\\*5\xd7\xed`\xe7\x1a\x14\xff,\xb5\xbf\x13\x8e\xb0a^U\xea\xe2\xf4\xbdDzl\x9e\xc5Y \xec<i\xed\xf6\xd7]\x86Je\xc0\xd8\\\xd7[KG'
                (
                    'config'
                    'account'
                    'message'
                    'param'
                    'end'
                )
                'Всего юзернеймов:'   # b'\x81R\xea\xa2\xd2Jkb\xc8J\xd3\x80\xdd\x02HR\xbf\x88\nG\x1a\x16\xfe\x19\xb5\xb6\x13\x80\xb0o\xae7`'
                'Успешно добавлено администраторов:'   # b'\x81R\xdb\xa2\xd2Jab\xceK\xe5p\xb1\\&\xc5\xbf\x89\x0by\x1a\x1a\xfe\x1c\xb5\xbd\x13\x87\xb0d\xae8\x8a\x8c`\xbdHz`\x9e\xc4Y \xed\x00h\xd7\xf6\xd6\\\xb4Jg\xc0\xd6\\\xd5[E\xac\xf8\xfb\xef\xe3\x85\x12'
                'Работа завершена'   # b'\x81R\xd8\xa3\xe3Job\xc5K\xefp\xbc\xacHR\xbf\x8d\x0bu\x1a\x1e\xff,\xb4\x87\x13\x89\xb0l\xae5'
            [Disassembly]
                0       NOP                             
                2       NOP                             
                4       PUSH_NULL                       
                6       LOAD_CONST                      2: '__pyarmor_enter_13699__'
                8       LOAD_CONST                      3: b'<COAddr>\x05\x00\x00\x1a\xaa\n\x00\x00\x00\x00\x00\x00\x00\x00\x00\x00\x00\x00\x00\x00'
                10      BUILD_TUPLE                     1
                12      CALL_FUNCTION_EX                0
                14      POP_TOP                         
                16      RESUME                          0
                18      NOP                             
                20      NOP                             
                22      NOP                             
                24      NOP                             
                26      NOP                             
                28      NOP                             
                30      LOAD_GLOBAL                     1: NULL + account_works
                40      LOAD_FAST                       2: config
                42      LOAD_GLOBAL                     2: Lang
                52      LOAD_FAST                       3: proxy
                54      LOAD_FAST                       0: account
                56      LOAD_FAST                       4: stop_thread
                58      LOAD_CONST                      4: 'AddAdmin'
                60      KW_NAMES                        5: ('module',)
                62      CALL                            6
                70      STORE_FAST                      6: _var_var_8
                72      LOAD_FAST                       6: _var_var_8
                74      LOAD_CONST                      6: False
                76      COMPARE_OP                      40 (==)
                80      POP_JUMP_IF_FALSE               68 (to 218)
                82      LOAD_FAST                       0: account
                84      LOAD_CONST                      7: 'false'
                86      LOAD_CONST                      8: ('account', 'status')
                88      BUILD_CONST_KEY_MAP             2
                90      LOAD_GLOBAL                     5: NULL + Disconnect
                100     LOAD_FAST                       6: _var_var_8
                102     CALL                            1
                110     POP_TOP                         
                112     LOAD_GLOBAL                     7: NULL + Logs
                122     LOAD_ATTR                       8: PrintLog
                142     LOAD_FAST                       2: config
                144     LOAD_FAST                       0: account
                146     LOAD_GLOBAL                     2: Lang
                156     PUSH_NULL                       
                158     LOAD_CONST                      1: '__pyarmor_assert_13698__'
                160     LOAD_CONST                      9: 'work_account_completed'   # b'\x81\xf5\x17\x018\xc5\xbf\xd1\x18\xf5\x18\xcex\xd3\xfb\x8a\x02M\xb7\xa2\xbe\xceJ'
                162     CALL                            1
                170     BINARY_SUBSCR                   
                174     KW_NAMES                        10: ('config', 'account', 'message')
                176     CALL                            3
                184     POP_TOP                         
                186     LOAD_FAST                       0: account
                188     LOAD_CONST                      11: 'done'
                190     LOAD_CONST                      8: ('account', 'status')
                192     BUILD_CONST_KEY_MAP             2
                194     SWAP                            2
                196     POP_TOP                         
                198     NOP                             
                200     NOP                             
                202     JUMP_FORWARD                    1289 (to 2784)
                206     CALL                            1
                214     POP_TOP                         
                216     RETURN_VALUE                    
                218     LOAD_FAST                       1: data
                220     LOAD_CONST                      13: 'Settings'
                222     BINARY_SUBSCR                   
                226     LOAD_ATTR                       11: get
                246     LOAD_CONST                      14: 'source'
                248     CALL                            1
                256     STORE_FAST                      7: _var_var_5
                258     LOAD_GLOBAL                     13: NULL + clear_array
                268     LOAD_FAST                       1: data
                270     LOAD_CONST                      13: 'Settings'
                272     BINARY_SUBSCR                   
                276     LOAD_ATTR                       11: get
                296     PUSH_NULL                       
                298     LOAD_CONST                      1: '__pyarmor_assert_13698__'
                300     LOAD_CONST                      15: 'usernames'   # b'\x81\xf7\x0b\x16!\xf4\xbf\xdf\x1e\xe9'
                302     CALL                            1
                310     CALL                            1
                318     CALL                            1
                326     STORE_FAST                      8: _var_var_6
                328     LOAD_FAST                       1: data
                330     LOAD_CONST                      13: 'Settings'
                332     BINARY_SUBSCR                   
                336     LOAD_ATTR                       11: get
                356     PUSH_NULL                       
                358     LOAD_CONST                      1: '__pyarmor_assert_13698__'
                360     LOAD_CONST                      16: 'change_info'   # b'\x81\xe1\x10\x12=\xfd\xbb\xed\x12\xf4\x0b\xcf'
                362     CALL                            1
                370     CALL                            1
                378     STORE_FAST                      9: _var_var_20
                380     LOAD_FAST                       1: data
                382     LOAD_CONST                      13: 'Settings'
                384     BINARY_SUBSCR                   
                388     LOAD_ATTR                       11: get
                408     PUSH_NULL                       
                410     LOAD_CONST                      1: '__pyarmor_assert_13698__'
                412     LOAD_CONST                      17: 'post_messages'   # b"\x81\xf2\x17\x00'\xc5\xb3\xd7\x08\xe9\x0c\xc7i\xff"
                414     CALL                            1
                422     CALL                            1
                430     STORE_FAST                      10: _var_var_21
                432     LOAD_FAST                       1: data
                434     LOAD_CONST                      13: 'Settings'
                436     BINARY_SUBSCR                   
                440     LOAD_ATTR                       11: get
                460     PUSH_NULL                       
                462     LOAD_CONST                      1: '__pyarmor_assert_13698__'
                464     LOAD_CONST                      18: 'edit_messages'   # b"\x81\xe7\x1c\x1a'\xc5\xb3\xd7\x08\xe9\x0c\xc7i\xff"
                466     CALL                            1
                474     CALL                            1
                482     STORE_FAST                      11: _var_var_22
                484     LOAD_FAST                       1: data
                486     LOAD_CONST                      13: 'Settings'
                488     BINARY_SUBSCR                   
                492     LOAD_ATTR                       11: get
                512     PUSH_NULL                       
                514     LOAD_CONST                      1: '__pyarmor_assert_13698__'
                516     LOAD_CONST                      19: 'delete_messages'   # b'\x81\xe6\x1d\x1f6\xee\xbb\xed\x16\xff\x1e\xd3m\xeb\xfd\x96'
                518     CALL                            1
                526     CALL                            1
                534     STORE_FAST                      12: _var_var_23
                536     LOAD_FAST                       1: data
                538     LOAD_CONST                      13: 'Settings'
                540     BINARY_SUBSCR                   
                544     LOAD_ATTR                       11: get
                564     PUSH_NULL                       
                566     LOAD_CONST                      1: '__pyarmor_assert_13698__'
                568     LOAD_CONST                      20: 'ban_users'   # b'\x81\xe0\x19\x1d\x0c\xef\xad\xd7\t\xe9'
                570     CALL                            1
                578     CALL                            1
                586     STORE_FAST                      13: _var_var_24
                588     LOAD_FAST                       1: data
                590     LOAD_CONST                      13: 'Settings'
                592     BINARY_SUBSCR                   
                596     LOAD_ATTR                       11: get
                616     PUSH_NULL                       
                618     LOAD_CONST                      1: '__pyarmor_assert_13698__'
                620     LOAD_CONST                      21: 'invite_users'   # b'\x81\xeb\x16\x05:\xee\xbb\xed\x0e\xe9\x08\xd2\x7f'
                622     CALL                            1
                630     CALL                            1
                638     STORE_FAST                      14: _var_var_25
                640     LOAD_FAST                       1: data
                642     LOAD_CONST                      13: 'Settings'
                644     BINARY_SUBSCR                   
                648     LOAD_ATTR                       11: get
                668     PUSH_NULL                       
                670     LOAD_CONST                      1: '__pyarmor_assert_13698__'
                672     LOAD_CONST                      22: 'pin_messages'   # b'\x81\xf2\x11\x1d\x0c\xf7\xbb\xc1\x08\xfb\n\xc5\x7f'
                674     CALL                            1
                682     CALL                            1
                690     STORE_FAST                      15: _var_var_26
                692     LOAD_FAST                       1: data
                694     LOAD_CONST                      13: 'Settings'
                696     BINARY_SUBSCR                   
                700     LOAD_ATTR                       11: get
                720     PUSH_NULL                       
                722     LOAD_CONST                      1: '__pyarmor_assert_13698__'
                724     LOAD_CONST                      23: 'manage_call'   # b'\x81\xef\x19\x1d2\xfd\xbb\xed\x18\xfb\x01\xcc'
                726     CALL                            1
                734     CALL                            1
                742     STORE_FAST                      16: _var_var_27
                744     LOAD_FAST                       1: data
                746     LOAD_CONST                      13: 'Settings'
                748     BINARY_SUBSCR                   
                752     LOAD_ATTR                       11: get
                772     PUSH_NULL                       
                774     LOAD_CONST                      1: '__pyarmor_assert_13698__'
                776     LOAD_CONST                      24: 'anonymous'   # b'\x81\xe3\x16\x1c=\xe3\xb3\xdd\x0e\xe9'
                778     CALL                            1
                786     CALL                            1
                794     STORE_FAST                      17: _var_var_28
                796     LOAD_FAST                       1: data
                798     LOAD_CONST                      13: 'Settings'
                800     BINARY_SUBSCR                   
                804     LOAD_ATTR                       11: get
                824     PUSH_NULL                       
                826     LOAD_CONST                      1: '__pyarmor_assert_13698__'
                828     LOAD_CONST                      25: 'add_admins'   # b'\x81\xe3\x1c\x17\x0c\xfb\xba\xdf\x12\xf4\x1e'
                830     CALL                            1
                838     CALL                            1
                846     STORE_FAST                      18: _var_var_29
                848     LOAD_GLOBAL                     15: NULL + len
                858     LOAD_FAST                       8: _var_var_6
                860     CALL                            1
                868     STORE_FAST                      19: _var_var_30
                870     LOAD_CONST                      26: 0
                872     STORE_FAST                      20: _var_var_31
                874     BUILD_LIST                      0
                876     STORE_FAST                      21: _var_var_32
                878     LOAD_FAST                       6: _var_var_8
                880     LOAD_ATTR                       17: iter_dialogs
                900     LOAD_CONST                      27: 500
                902     KW_NAMES                        28: ('limit',)
                904     CALL                            1
                912     GET_ITER                        
                914     FOR_ITER                        113 (to 1142)
                918     STORE_FAST                      22: _var_var_12
                920     LOAD_FAST                       4: stop_thread
                922     LOAD_ATTR                       19: is_set
                942     CALL                            0
                950     POP_JUMP_IF_FALSE               10 (to 972)
                952     LOAD_GLOBAL                     21: NULL + StopProgram
                962     CALL                            0
                970     RAISE_VARARGS                   1
                972     LOAD_GLOBAL                     23: NULL + hasattr
                982     LOAD_FAST                       22: _var_var_12
                984     LOAD_CONST                      29: 'id'
                986     CALL                            2
                994     LOAD_CONST                      30: True
                996     COMPARE_OP                      40 (==)
                1000    POP_JUMP_IF_TRUE                1 (to 1004)
                1002    JUMP_BACKWARD                   45 (to 914)
                1004    LOAD_GLOBAL                     23: NULL + hasattr
                1014    LOAD_FAST                       22: _var_var_12
                1016    LOAD_CONST                      31: 'entity'
                1018    CALL                            2
                1026    LOAD_CONST                      30: True
                1028    COMPARE_OP                      40 (==)
                1032    POP_JUMP_IF_TRUE                1 (to 1036)
                1034    JUMP_BACKWARD                   61 (to 914)
                1036    NOP                             
                1038    LOAD_GLOBAL                     25: NULL + str
                1048    LOAD_FAST                       22: _var_var_12
                1050    LOAD_ATTR                       26: id
                1070    CALL                            1
                1078    STORE_FAST                      23: _var_var_33
                1080    LOAD_FAST                       23: _var_var_33
                1082    LOAD_FAST                       7: _var_var_5
                1084    CONTAINS_OP                     0 (in)
                1086    POP_JUMP_IF_FALSE               27 (to 1142)
                1088    LOAD_FAST                       21: _var_var_32
                1090    LOAD_ATTR                       29: append
                1110    LOAD_FAST                       22: _var_var_12
                1112    LOAD_ATTR                       30: entity
                1132    CALL                            1
                1140    POP_TOP                         
                1142    JUMP_BACKWARD                   115 (to 914)
                1144    END_FOR                         
                1146    BUILD_LIST                      0
                1148    STORE_FAST                      25: _var_var_34
                1150    LOAD_FAST                       8: _var_var_6
                1152    GET_ITER                        
                1154    FOR_ITER                        105 (to 1366)
                1158    STORE_FAST                      26: _var_var_35
                1160    LOAD_FAST                       4: stop_thread
                1162    LOAD_ATTR                       19: is_set
                1182    CALL                            0
                1190    POP_JUMP_IF_FALSE               10 (to 1212)
                1192    LOAD_GLOBAL                     21: NULL + StopProgram
                1202    CALL                            0
                1210    RAISE_VARARGS                   1
                1212    LOAD_GLOBAL                     7: NULL + Logs
                1222    LOAD_ATTR                       8: PrintLog
                1242    LOAD_FAST                       2: config
                1244    LOAD_FAST                       0: account
                1246    PUSH_NULL                       
                1248    LOAD_CONST                      1: '__pyarmor_assert_13698__'
                1250    LOAD_CONST                      34: 'Проверяю пользователя: '   # b'\x81R\xe7\xa2\xd3J`b\xc9J\xd8q\x8c]\x174\xe1\x1d\x0bx\x1a\x15\xfe\x17\xb4\x83\x13\x8b\xb0o\xae7\x8a\x82\x91\xef(\x1f\x04\xf5\xa9\x06\xa2\x1d'
                1252    CALL                            1
                1260    LOAD_FAST                       26: _var_var_35
                1262    KW_NAMES                        33: ('config', 'account', 'message', 'param')
                1264    CALL                            4
                1272    POP_TOP                         
                1274    LOAD_GLOBAL                     35: NULL + get_user_entity
                1284    LOAD_FAST                       0: account
                1286    LOAD_FAST                       6: _var_var_8
                1288    LOAD_FAST                       26: _var_var_35
                1290    LOAD_CONST                      35: 120
                1292    LOAD_FAST                       2: config
                1294    LOAD_FAST                       4: stop_thread
                1296    CALL                            6
                1304    STORE_FAST                      27: _var_var_36
                1306    LOAD_FAST                       27: _var_var_36
                1308    LOAD_CONST                      36: 'stop'
                1310    COMPARE_OP                      40 (==)
                1314    POP_JUMP_IF_FALSE               2 (to 1320)
                1316    POP_TOP                         
                1318    JUMP_FORWARD                    25 (to 1370)
                1320    LOAD_FAST                       27: _var_var_36
                1322    LOAD_CONST                      6: False
                1324    COMPARE_OP                      55 (!=)
                1328    POP_JUMP_IF_TRUE                1 (to 1332)
                1330    JUMP_BACKWARD                   89 (to 1154)
                1332    LOAD_FAST                       25: _var_var_34
                1334    LOAD_ATTR                       29: append
                1354    LOAD_FAST                       27: _var_var_36
                1356    CALL                            1
                1364    POP_TOP                         
                1366    JUMP_BACKWARD                   107 (to 1154)
                1368    END_FOR                         
                1370    LOAD_FAST                       21: _var_var_32
                1372    GET_ITER                        
                1374    FOR_ITER                        259 (to 1896)
                1380    STORE_FAST                      28: _var_var_37
                1382    LOAD_GLOBAL                     23: NULL + hasattr
                1392    LOAD_FAST                       28: _var_var_37
                1394    LOAD_CONST                      37: 'name'
                1396    CALL                            2
                1404    POP_JUMP_IF_FALSE               41 (to 1488)
                1406    LOAD_GLOBAL                     7: NULL + Logs
                1416    LOAD_ATTR                       8: PrintLog
                1436    LOAD_FAST                       2: config
                1438    LOAD_FAST                       0: account
                1440    PUSH_NULL                       
                1442    LOAD_CONST                      1: '__pyarmor_assert_13698__'
                1444    LOAD_CONST                      38: 'Устанавливаю админов для группы:'   # b'\x81R\xdb\xa2\xd2K\\b\xcbJ\xd0p\xbc\\*5\xd4\xedc\x17x{\x9e}\xeb/\x13\x8c\xb0e\xae9\x8a\x8a\x90\xd0(\x14\x04\xfcXY,\xed\x06i\xe0\x07\x87>\xe7\x1b6\x93\xb62\x874*\xf6B'
                1446    CALL                            1
                1454    LOAD_FAST                       28: _var_var_37
                1456    LOAD_ATTR                       36: name
                1476    KW_NAMES                        33: ('config', 'account', 'message', 'param')
                1478    CALL                            4
                1486    POP_TOP                         
                1488    LOAD_FAST                       25: _var_var_34
                1490    GET_ITER                        
                1492    FOR_ITER                        198 (to 1890)
                1496    STORE_FAST                      27: _var_var_36
                1498    LOAD_GLOBAL                     23: NULL + hasattr
                1508    LOAD_FAST                       27: _var_var_36
                1510    PUSH_NULL                       
                1512    LOAD_CONST                      1: '__pyarmor_assert_13698__'
                1514    LOAD_CONST                      39: 'first_name'   # b'\x81\xe4\x11\x01 \xee\x81\xdc\x1a\xf7\x08'
                1516    CALL                            1
                1524    CALL                            2
                1532    POP_JUMP_IF_FALSE               41 (to 1616)
                1534    LOAD_GLOBAL                     7: NULL + Logs
                1544    LOAD_ATTR                       8: PrintLog
                1564    LOAD_FAST                       2: config
                1566    LOAD_FAST                       0: account
                1568    PUSH_NULL                       
                1570    LOAD_CONST                      1: '__pyarmor_assert_13698__'
                1572    LOAD_CONST                      40: 'Добавляю пользователя:'   # b'\x81R\xec\xa3\xedJob\xcbJ\xdfp\xb7]\x174\xe1\x1d\x0bx\x1a\x15\xfe\x17\xb4\x83\x13\x8b\xb0o\xae7\x8a\x82\x91\xef(\x1f\x04\xf5\xa9\x06\xa2'
                1574    CALL                            1
                1582    LOAD_FAST                       27: _var_var_36
                1584    LOAD_ATTR                       38: first_name
                1604    KW_NAMES                        33: ('config', 'account', 'message', 'param')
                1606    CALL                            4
                1614    POP_TOP                         
                1616    NOP                             
                1618    PUSH_NULL                       
                1620    LOAD_FAST                       6: _var_var_8
                1622    LOAD_GLOBAL                     40: functions
                1632    LOAD_ATTR                       42: channels
                1652    LOAD_ATTR                       45: EditAdminRequest
                1672    LOAD_FAST                       28: _var_var_37
                1674    LOAD_FAST                       27: _var_var_36
                1676    LOAD_GLOBAL                     47: NULL + types
                1686    LOAD_ATTR                       48: ChatAdminRights
                1706    LOAD_FAST                       9: _var_var_20
                1708    LOAD_FAST                       10: _var_var_21
                1710    LOAD_FAST                       11: _var_var_22
                1712    LOAD_FAST                       12: _var_var_23
                1714    LOAD_FAST                       13: _var_var_24
                1716    LOAD_FAST                       14: _var_var_25
                1718    LOAD_FAST                       15: _var_var_26
                1720    LOAD_FAST                       18: _var_var_29
                1722    LOAD_FAST                       17: _var_var_28
                1724    LOAD_FAST                       16: _var_var_27
                1726    LOAD_CONST                      6: False
                1728    LOAD_CONST                      6: False
                1730    KW_NAMES                        41: ('change_info', 'post_messages', 'edit_messages', 'delete_messages', 'ban_users', 'invite_users', 'pin_messages', 'add_admins', 'anonymous', 'manage_call', 'other', 'manage_topics')
                1732    CALL                            12
                1740    LOAD_CONST                      42: ''
                1742    KW_NAMES                        43: ('channel', 'user_id', 'admin_rights', 'rank')
                1744    CALL                            4
                1752    CALL                            1
                1760    POP_TOP                         
                1762    LOAD_FAST                       20: _var_var_31
                1764    LOAD_CONST                      44: 1
                1766    BINARY_OP                       13 (+=)
                1770    STORE_FAST                      20: _var_var_31
                1772    LOAD_GLOBAL                     23: NULL + hasattr
                1782    LOAD_FAST                       27: _var_var_36
                1784    PUSH_NULL                       
                1786    LOAD_CONST                      1: '__pyarmor_assert_13698__'
                1788    LOAD_CONST                      39: 'first_name'   # b'\x81\xe4\x11\x01 \xee\x81\xdc\x1a\xf7\x08'
                1790    CALL                            1
                1798    CALL                            2
                1806    POP_JUMP_IF_FALSE               41 (to 1890)
                1808    LOAD_GLOBAL                     7: NULL + Logs
                1818    LOAD_ATTR                       8: PrintLog
                1838    LOAD_FAST                       2: config
                1840    LOAD_FAST                       0: account
                1842    PUSH_NULL                       
                1844    LOAD_CONST                      1: '__pyarmor_assert_13698__'
                1846    LOAD_CONST                      45: 'Установил права администратора:'   # b'\x81R\xdb\xa2\xd2K\\b\xcbJ\xd0p\xb2\\*5\xd7\xed`\xe7\x1a\x14\xff,\xb5\xbf\x13\x8e\xb0a^U\xea\xe2\xf4\xbdDzl\x9e\xc5Y \xec<i\xed\xf6\xd7]\x86Je\xc0\xd8\\\xd7[KG'
                1848    CALL                            1
                1856    LOAD_FAST                       27: _var_var_36
                1858    LOAD_ATTR                       38: first_name
                1878    KW_NAMES                        33: ('config', 'account', 'message', 'param')
                1880    CALL                            4
                1888    POP_TOP                         
                1890    JUMP_BACKWARD                   200 (to 1492)
                1892    END_FOR                         
                1894    JUMP_BACKWARD                   262 (to 1374)
                1898    END_FOR                         
                1900    LOAD_GLOBAL                     7: NULL + Logs
                1910    LOAD_ATTR                       8: PrintLog
                1930    LOAD_FAST                       2: config
                1932    LOAD_FAST                       0: account
                1934    PUSH_NULL                       
                1936    LOAD_CONST                      1: '__pyarmor_assert_13698__'
                1938    LOAD_CONST                      47: 'Всего юзернеймов:'   # b'\x81R\xea\xa2\xd2Jkb\xc8J\xd3\x80\xdd\x02HR\xbf\x88\nG\x1a\x16\xfe\x19\xb5\xb6\x13\x80\xb0o\xae7`'
                1940    CALL                            1
                1948    LOAD_FAST                       19: _var_var_30
                1950    KW_NAMES                        33: ('config', 'account', 'message', 'param')
                1952    CALL                            4
                1960    POP_TOP                         
                1962    LOAD_GLOBAL                     7: NULL + Logs
                1972    LOAD_ATTR                       8: PrintLog
                1992    LOAD_FAST                       2: config
                1994    LOAD_FAST                       0: account
                1996    PUSH_NULL                       
                1998    LOAD_CONST                      1: '__pyarmor_assert_13698__'
                2000    LOAD_CONST                      48: 'Успешно добавлено администраторов:'   # b'\x81R\xdb\xa2\xd2Jab\xceK\xe5p\xb1\\&\xc5\xbf\x89\x0by\x1a\x1a\xfe\x1c\xb5\xbd\x13\x87\xb0d\xae8\x8a\x8c`\xbdHz`\x9e\xc4Y \xed\x00h\xd7\xf6\xd6\\\xb4Jg\xc0\xd6\\\xd5[E\xac\xf8\xfb\xef\xe3\x85\x12'
                2002    CALL                            1
                2010    LOAD_FAST                       20: _var_var_31
                2012    KW_NAMES                        33: ('config', 'account', 'message', 'param')
                2014    CALL                            4
                2022    POP_TOP                         
                2024    LOAD_GLOBAL                     7: NULL + Logs
                2034    LOAD_ATTR                       8: PrintLog
                2054    LOAD_FAST                       2: config
                2056    LOAD_FAST                       0: account
                2058    PUSH_NULL                       
                2060    LOAD_CONST                      1: '__pyarmor_assert_13698__'
                2062    LOAD_CONST                      49: 'Работа завершена'   # b'\x81R\xd8\xa3\xe3Job\xc5K\xefp\xbc\xacHR\xbf\x8d\x0bu\x1a\x1e\xff,\xb4\x87\x13\x89\xb0l\xae5'
                2064    CALL                            1
                2072    KW_NAMES                        10: ('config', 'account', 'message')
                2074    CALL                            3
                2082    POP_TOP                         
                2084    LOAD_GLOBAL                     5: NULL + Disconnect
                2094    LOAD_FAST_CHECK                 6: _var_var_8
                2096    CALL                            1
                2104    POP_TOP                         
                2106    LOAD_GLOBAL                     7: NULL + Logs
                2116    LOAD_ATTR                       8: PrintLog
                2136    LOAD_FAST                       2: config
                2138    LOAD_FAST                       0: account
                2140    LOAD_GLOBAL                     2: Lang
                2150    PUSH_NULL                       
                2152    LOAD_CONST                      1: '__pyarmor_assert_13698__'
                2154    LOAD_CONST                      9: 'work_account_completed'   # b'\x81\xf5\x17\x018\xc5\xbf\xd1\x18\xf5\x18\xcex\xd3\xfb\x8a\x02M\xb7\xa2\xbe\xceJ'
                2156    CALL                            1
                2164    BINARY_SUBSCR                   
                2168    KW_NAMES                        10: ('config', 'account', 'message')
                2170    CALL                            3
                2178    POP_TOP                         
                2180    LOAD_FAST                       0: account
                2182    LOAD_CONST                      11: 'done'
                2184    LOAD_CONST                      8: ('account', 'status')
                2186    BUILD_CONST_KEY_MAP             2
                2188    NOP                             
                2190    NOP                             
                2192    JUMP_FORWARD                    294 (to 2784)
                2196    CALL                            1
                2204    POP_TOP                         
                2206    RETURN_VALUE                    
                2208    PUSH_EXC_INFO                   
                2210    POP_TOP                         
                2212    POP_EXCEPT                      
                2214    JUMP_BACKWARD                   1053 (to 112)
                2218    COPY                            3
                2220    POP_EXCEPT                      
                2222    RERAISE                         1
                2224    PUSH_EXC_INFO                   
                2226    LOAD_GLOBAL                     32: Exception
                2236    CHECK_EXC_MATCH                 
                2238    POP_JUMP_IF_FALSE               49 (to 2338)
                2240    STORE_FAST                      24: _var_var_3
                2242    LOAD_GLOBAL                     7: NULL + Logs
                2252    LOAD_ATTR                       8: PrintLog
                2272    LOAD_FAST                       2: config
                2274    LOAD_FAST                       0: account
                2276    LOAD_GLOBAL                     2: Lang
                2286    PUSH_NULL                       
                2288    LOAD_CONST                      1: '__pyarmor_assert_13698__'
                2290    LOAD_CONST                      32: 'error_detected'   # b'\x81\xe7\n\x01<\xe8\x81\xd6\x1e\xee\x08\xc3x\xe9\xfc'
                2292    CALL                            1
                2300    BINARY_SUBSCR                   
                2304    LOAD_FAST                       24: _var_var_3
                2306    KW_NAMES                        33: ('config', 'account', 'message', 'param')
                2308    CALL                            4
                2316    POP_TOP                         
                2318    POP_EXCEPT                      
                2320    LOAD_CONST                      0: None
                2322    STORE_FAST                      24: _var_var_3
                2324    DELETE_FAST                     24: _var_var_3
                2326    JUMP_BACKWARD                   708 (to 914)
                2330    LOAD_CONST                      0: None
                2332    STORE_FAST                      24: _var_var_3
                2334    DELETE_FAST                     24: _var_var_3
                2336    RERAISE                         1
                2338    RERAISE                         0
                2340    COPY                            3
                2342    POP_EXCEPT                      
                2344    RERAISE                         1
                2346    PUSH_EXC_INFO                   
                2348    LOAD_GLOBAL                     32: Exception
                2358    CHECK_EXC_MATCH                 
                2360    POP_JUMP_IF_FALSE               60 (to 2482)
                2362    STORE_FAST                      24: _var_var_3
                2364    LOAD_GLOBAL                     7: NULL + Logs
                2374    LOAD_ATTR                       8: PrintLog
                2394    LOAD_FAST                       2: config
                2396    LOAD_FAST                       0: account
                2398    LOAD_GLOBAL                     2: Lang
                2408    PUSH_NULL                       
                2410    LOAD_CONST                      1: '__pyarmor_assert_13698__'
                2412    LOAD_CONST                      32: 'error_detected'   # b'\x81\xe7\n\x01<\xe8\x81\xd6\x1e\xee\x08\xc3x\xe9\xfc'
                2414    CALL                            1
                2422    BINARY_SUBSCR                   
                2426    LOAD_FAST                       27: _var_var_36
                2428    LOAD_ATTR                       50: username
                2448    LOAD_FAST                       24: _var_var_3
                2450    KW_NAMES                        46: ('config', 'account', 'message', 'param', 'end')
                2452    CALL                            5
                2460    POP_TOP                         
                2462    POP_EXCEPT                      
                2464    LOAD_CONST                      0: None
                2466    STORE_FAST                      24: _var_var_3
                2468    DELETE_FAST                     24: _var_var_3
                2470    JUMP_BACKWARD                   491 (to 1492)
                2474    LOAD_CONST                      0: None
                2476    STORE_FAST                      24: _var_var_3
                2478    DELETE_FAST                     24: _var_var_3
                2480    RERAISE                         1
                2482    RERAISE                         0
                2484    COPY                            3
                2486    POP_EXCEPT                      
                2488    RERAISE                         1
                2490    PUSH_EXC_INFO                   
                2492    LOAD_GLOBAL                     20: StopProgram
                2502    CHECK_EXC_MATCH                 
                2504    POP_JUMP_IF_FALSE               3 (to 2512)
                2506    POP_TOP                         
                2508    POP_EXCEPT                      
                2510    JUMP_BACKWARD                   214 (to 2084)
                2512    LOAD_GLOBAL                     52: BaseException
                2522    CHECK_EXC_MATCH                 
                2524    POP_JUMP_IF_FALSE               26 (to 2578)
                2526    STORE_FAST                      29: _var_var_7
                2528    PUSH_NULL                       
                2530    LOAD_GLOBAL                     55: NULL + logging
                2540    LOAD_FAST                       29: _var_var_7
                2542    CALL                            1
                2550    CALL                            0
                2558    POP_TOP                         
                2560    POP_EXCEPT                      
                2562    LOAD_CONST                      0: None
                2564    STORE_FAST                      29: _var_var_7
                2566    DELETE_FAST                     29: _var_var_7
                2568    JUMP_BACKWARD                   243 (to 2084)
                2570    LOAD_CONST                      0: None
                2572    STORE_FAST                      29: _var_var_7
                2574    DELETE_FAST                     29: _var_var_7
                2576    RERAISE                         1
                2578    RERAISE                         0
                2580    COPY                            3
                2582    POP_EXCEPT                      
                2584    RERAISE                         1
                2586    PUSH_EXC_INFO                   
                2588    POP_TOP                         
                2590    POP_EXCEPT                      
                2592    JUMP_BACKWARD                   244 (to 2106)
                2594    COPY                            3
                2596    POP_EXCEPT                      
                2598    RERAISE                         1
                2600    PUSH_EXC_INFO                   
                2602    LOAD_GLOBAL                     5: NULL + Disconnect
                2612    LOAD_FAST_CHECK                 6: _var_var_8
                2614    CALL                            1
                2622    POP_TOP                         
                2624    JUMP_FORWARD                    7 (to 2640)
                2626    PUSH_EXC_INFO                   
                2628    POP_TOP                         
                2630    POP_EXCEPT                      
                2632    JUMP_FORWARD                    3 (to 2640)
                2634    COPY                            3
                2636    POP_EXCEPT                      
                2638    RERAISE                         1
                2640    LOAD_GLOBAL                     7: NULL + Logs
                2650    LOAD_ATTR                       8: PrintLog
                2670    LOAD_FAST                       2: config
                2672    LOAD_FAST                       0: account
                2674    LOAD_GLOBAL                     2: Lang
                2684    PUSH_NULL                       
                2686    LOAD_CONST                      1: '__pyarmor_assert_13698__'
                2688    LOAD_CONST                      9: 'work_account_completed'   # b'\x81\xf5\x17\x018\xc5\xbf\xd1\x18\xf5\x18\xcex\xd3\xfb\x8a\x02M\xb7\xa2\xbe\xceJ'
                2690    CALL                            1
                2698    BINARY_SUBSCR                   
                2702    KW_NAMES                        10: ('config', 'account', 'message')
                2704    CALL                            3
                2712    POP_TOP                         
                2714    LOAD_FAST                       0: account
                2716    LOAD_CONST                      11: 'done'
                2718    LOAD_CONST                      8: ('account', 'status')
                2720    BUILD_CONST_KEY_MAP             2
                2722    SWAP                            2
                2724    POP_TOP                         
                2726    SWAP                            2
                2728    POP_EXCEPT                      
                2730    NOP                             
                2732    NOP                             
                2734    NOP                             
                2736    JUMP_FORWARD                    23 (to 2784)
                2738    CALL                            1
                2746    POP_TOP                         
                2748    RETURN_VALUE                    
                2750    COPY                            3
                2752    POP_EXCEPT                      
                2754    RERAISE                         1
                2756    PUSH_EXC_INFO                   
                2758    PUSH_NULL                       
                2760    LOAD_CONST                      12: '__pyarmor_exit_13700__'
                2762    NOP                             
                2764    LOAD_CONST                      3: b'<COAddr>\x05\x00\x00\x1a\xaa\n\x00\x00\x00\x00\x00\x00\x00\x00\x00\x00\x00\x00\x00\x00'
                2766    CALL                            1
                2774    POP_TOP                         
                2776    RERAISE                         0
                2778    COPY                            3
                2780    POP_EXCEPT                      
                2782    RERAISE                         1
                2784    PUSH_NULL                       
                2786    LOAD_CONST                      12: '__pyarmor_exit_13700__'
                2788    LOAD_CONST                      3: b'<COAddr>\x05\x00\x00\x1a\xaa\n\x00\x00\x00\x00\x00\x00\x00\x00\x00\x00\x00\x00\x00\x00'
                2790    BUILD_TUPLE                     1
                2792    CALL_FUNCTION_EX                0
                2794    POP_TOP                         
                2796    RETURN_VALUE                    
            [Exception Table]
                30 to 90 -> 2490 [0] 
                90 to 112 -> 2208 [1] 
                112 to 198 -> 2756 [0] 
                218 to 1002 -> 2490 [0] 
                1004 to 1034 -> 2490 [0] 
                1038 to 1142 -> 2224 [1] 
                1142 to 1330 -> 2490 [0] 
                1332 to 1616 -> 2490 [0] 
                1618 to 1890 -> 2346 [2] 
                1890 to 2084 -> 2490 [0] 
                2084 to 2106 -> 2586 [0] 
                2106 to 2188 -> 2756 [0] 
                2208 to 2212 -> 2218 [2] lasti
                2212 to 2224 -> 2756 [0] 
                2224 to 2242 -> 2340 [2] lasti
                2242 to 2318 -> 2330 [2] lasti
                2318 to 2330 -> 2490 [0] 
                2330 to 2340 -> 2340 [2] lasti
                2340 to 2346 -> 2490 [0] 
                2346 to 2364 -> 2484 [3] lasti
                2364 to 2462 -> 2474 [3] lasti
                2462 to 2474 -> 2490 [0] 
                2474 to 2484 -> 2484 [3] lasti
                2484 to 2490 -> 2490 [0] 
                2490 to 2508 -> 2580 [1] lasti
                2508 to 2512 -> 2600 [0] 
                2512 to 2528 -> 2580 [1] lasti
                2528 to 2560 -> 2570 [1] lasti
                2560 to 2570 -> 2600 [0] 
                2570 to 2580 -> 2580 [1] lasti
                2580 to 2586 -> 2600 [0] 
                2586 to 2590 -> 2594 [1] lasti
                2590 to 2600 -> 2756 [0] 
                2600 to 2602 -> 2750 [1] lasti
                2602 to 2624 -> 2626 [2] 
                2624 to 2626 -> 2750 [1] lasti
                2626 to 2630 -> 2634 [3] lasti
                2630 to 2728 -> 2750 [1] lasti
                2728 to 2730 -> 2756 [0] 
                2750 to 2756 -> 2756 [0] 
                2756 to 2778 -> 2778 [1] lasti
        '__pyarmor_exit_13673__'
    [Disassembly]
        0       NOP                             
        2       NOP                             
        4       PUSH_NULL                       
        6       LOAD_CONST                      1: '__pyarmor_enter_13672__'
        8       LOAD_CONST                      2: b'<COAddr>\x07\x00\x00\x1a.\x01\x00\x00\x00\x00\x00\x00\x00\x00\x00\x00\x00\x00\x00\x00'
        10      BUILD_TUPLE                     1
        12      CALL_FUNCTION_EX                0
        14      POP_TOP                         
        16      RESUME                          0
        18      NOP                             
        20      NOP                             
        22      NOP                             
        24      NOP                             
        26      LOAD_CONST                      3: 0
        28      LOAD_CONST                      4: None
        30      IMPORT_NAME                     1: eel
        32      STORE_NAME                      1: eel
        34      LOAD_CONST                      3: 0
        36      LOAD_CONST                      4: None
        38      IMPORT_NAME                     2: time
        40      STORE_NAME                      2: time
        42      LOAD_CONST                      3: 0
        44      LOAD_CONST                      4: None
        46      IMPORT_NAME                     3: random
        48      STORE_NAME                      3: random
        50      LOAD_CONST                      3: 0
        52      LOAD_CONST                      5: ('Thread', 'Event')
        54      IMPORT_NAME                     4: threading
        56      IMPORT_FROM                     5: Thread
        58      STORE_NAME                      5: Thread
        60      IMPORT_FROM                     6: Event
        62      STORE_NAME                      6: Event
        64      POP_TOP                         
        66      LOAD_CONST                      3: 0
        68      LOAD_CONST                      6: ('functions', 'types', 'errors')
        70      IMPORT_NAME                     7: multithon.sync
        72      IMPORT_FROM                     8: functions
        74      STORE_NAME                      8: functions
        76      IMPORT_FROM                     9: types
        78      STORE_NAME                      9: types
        80      IMPORT_FROM                     10: errors
        82      STORE_NAME                      10: errors
        84      POP_TOP                         
        86      LOAD_CONST                      3: 0
        88      LOAD_CONST                      7: ('StopProgram',)
        90      IMPORT_NAME                     11: multithon.errors
        92      IMPORT_FROM                     12: StopProgram
        94      STORE_NAME                      12: StopProgram
        96      POP_TOP                         
        98      LOAD_CONST                      3: 0
        100     LOAD_CONST                      8: ('GetLang',)
        102     IMPORT_NAME                     13: program.static_classes
        104     IMPORT_FROM                     14: GetLang
        106     STORE_NAME                      14: GetLang
        108     POP_TOP                         
        110     LOAD_CONST                      3: 0
        112     LOAD_CONST                      9: ('Logs',)
        114     IMPORT_NAME                     13: program.static_classes
        116     IMPORT_FROM                     15: Logs
        118     STORE_NAME                      15: Logs
        120     POP_TOP                         
        122     LOAD_CONST                      3: 0
        124     LOAD_CONST                      10: ('logging',)
        126     IMPORT_NAME                     13: program.static_classes
        128     IMPORT_FROM                     16: logging
        130     STORE_NAME                      16: logging
        132     POP_TOP                         
        134     LOAD_CONST                      3: 0
        136     LOAD_CONST                      11: ('memory_check_switcher',)
        138     IMPORT_NAME                     13: program.static_classes
        140     IMPORT_FROM                     17: memory_check_switcher
        142     STORE_NAME                      17: memory_check_switcher
        144     POP_TOP                         
        146     LOAD_CONST                      3: 0
        148     LOAD_CONST                      12: ('memory_set_pid',)
        150     IMPORT_NAME                     13: program.static_classes
        152     IMPORT_FROM                     18: memory_set_pid
        154     STORE_NAME                      18: memory_set_pid
        156     POP_TOP                         
        158     LOAD_CONST                      3: 0
        160     LOAD_CONST                      13: ('DelayOnline',)
        162     IMPORT_NAME                     19: program.telegram
        164     IMPORT_FROM                     20: DelayOnline
        166     STORE_NAME                      20: DelayOnline
        168     POP_TOP                         
        170     LOAD_CONST                      3: 0
        172     LOAD_CONST                      14: ('Disconnect',)
        174     IMPORT_NAME                     19: program.telegram
        176     IMPORT_FROM                     21: Disconnect
        178     STORE_NAME                      21: Disconnect
        180     POP_TOP                         
        182     LOAD_CONST                      3: 0
        184     LOAD_CONST                      15: ('account_works',)
        186     IMPORT_NAME                     19: program.telegram
        188     IMPORT_FROM                     22: account_works
        190     STORE_NAME                      22: account_works
        192     POP_TOP                         
        194     LOAD_CONST                      3: 0
        196     LOAD_CONST                      16: ('GetConfig',)
        198     IMPORT_NAME                     23: program.general
        200     IMPORT_FROM                     24: GetConfig
        202     STORE_NAME                      24: GetConfig
        204     POP_TOP                         
        206     LOAD_CONST                      3: 0
        208     LOAD_CONST                      17: ('GetProxy',)
        210     IMPORT_NAME                     23: program.general
        212     IMPORT_FROM                     25: GetProxy
        214     STORE_NAME                      25: GetProxy
        216     POP_TOP                         
        218     LOAD_CONST                      3: 0
        220     LOAD_CONST                      18: ('StopDetect',)
        222     IMPORT_NAME                     23: program.general
        224     IMPORT_FROM                     26: StopDetect
        226     STORE_NAME                      26: StopDetect
        228     POP_TOP                         
        230     LOAD_CONST                      3: 0
        232     LOAD_CONST                      19: ('del_task_manager',)
        234     IMPORT_NAME                     23: program.general
        236     IMPORT_FROM                     27: del_task_manager
        238     STORE_NAME                      27: del_task_manager
        240     POP_TOP                         
        242     LOAD_CONST                      3: 0
        244     LOAD_CONST                      20: ('getFile',)
        246     IMPORT_NAME                     23: program.general
        248     IMPORT_FROM                     28: getFile
        250     STORE_NAME                      28: getFile
        252     POP_TOP                         
        254     LOAD_CONST                      21: <CODE> Group_add_admin
        256     MAKE_FUNCTION                   0
        258     STORE_NAME                      29: Group_add_admin
        260     LOAD_CONST                      22: <CODE> START
        262     MAKE_FUNCTION                   0
        264     STORE_NAME                      30: START
        266     LOAD_CONST                      23: <CODE> GetAdminGroups
        268     MAKE_FUNCTION                   0
        270     STORE_NAME                      31: GetAdminGroups
        272     LOAD_CONST                      24: <CODE> EntityCorrectGroup
        274     MAKE_FUNCTION                   0
        276     STORE_NAME                      32: EntityCorrectGroup
        278     LOAD_CONST                      25: <CODE> clear_array
        280     MAKE_FUNCTION                   0
        282     STORE_NAME                      33: clear_array
        284     LOAD_CONST                      26: <CODE> check_array_word
        286     MAKE_FUNCTION                   0
        288     STORE_NAME                      34: check_array_word
        290     LOAD_CONST                      27: <CODE> replace_array_word
        292     MAKE_FUNCTION                   0
        294     STORE_NAME                      35: replace_array_word
        296     LOAD_CONST                      28: <CODE> get_user_entity
        298     MAKE_FUNCTION                   0
        300     STORE_NAME                      36: get_user_entity
        302     LOAD_CONST                      29: <CODE> SetAdminGroups
        304     MAKE_FUNCTION                   0
        306     STORE_NAME                      37: SetAdminGroups
        308     LOAD_CONST                      4: None
        310     NOP                             
        312     NOP                             
        314     NOP                             
        316     JUMP_FORWARD                    19 (to 356)
        324     POP_TOP                         
        326     RETURN_CONST                    4: None
        328     PUSH_EXC_INFO                   
        330     PUSH_NULL                       
        332     LOAD_CONST                      30: '__pyarmor_exit_13673__'
        334     NOP                             
        336     LOAD_CONST                      2: b'<COAddr>\x07\x00\x00\x1a.\x01\x00\x00\x00\x00\x00\x00\x00\x00\x00\x00\x00\x00\x00\x00'
        338     CALL                            1
        346     POP_TOP                         
        348     RERAISE                         0
        350     COPY                            3
        352     POP_EXCEPT                      
        354     RERAISE                         1
        356     PUSH_NULL                       
        358     LOAD_CONST                      30: '__pyarmor_exit_13673__'
        360     LOAD_CONST                      2: b'<COAddr>\x07\x00\x00\x1a.\x01\x00\x00\x00\x00\x00\x00\x00\x00\x00\x00\x00\x00\x00\x00'
        362     BUILD_TUPLE                     1
        364     CALL_FUNCTION_EX                0
        366     POP_TOP                         
        368     RETURN_VALUE                    
    [Exception Table]
        26 to 308 -> 328 [0] 
        328 to 350 -> 350 [1] lasti
