#decoded by lolz.live/mrpenny / t.me/zeus_jackpot
# ================================
# Примечания по Pyarmor:
# - Байт-код и объекты кода Pyarmor соответствуют стандартному Python, но присутствуют специальные вызовы функций среды выполнения (runtime) Pyarmor.
# - Вызовы строк — это не ошибки, а маркеры, которые обрабатываются Pyarmor во время выполнения.
#
# Руководство по декомпиляции (без среды выполнения):
# 1. Игнорируйте зашифрованные байты после `#`; используйте только строку до `#`.
# 2. Удалите "__pyarmor_enter_xxx__"(b"<COAddr>...") и "__pyarmor_leave_xxx__"(b"<COAddr>...") (пролог/эпилог).
# 3. "__pyarmor_assert_xxx__"(A) не является настоящим оператором assert.
#    - Если A — это имя или читаемая строка: замените на A.
#    - Если A — это (X, "Y"): замените на X.Y.
#    - Если A — это (X, "Y", Z): замените на X.Y = Z.
#    - В противном случае: выберите наиболее подходящую/логичную замену.
# 4. "__pyarmor_bcc_xxx__"(...) указывает на машинный (нативный) код; тело функции недоступно. Добавьте комментарий.
# ================================

[Code]
    File Name: <frozen program.modules.Invite_username_v2>
    Object Name: <module>
    Qualified Name: <module>
    Arg Count: 0
    Pos Only Arg Count: 0
    KW Only Arg Count: 0
    Stack Size: 5
    Flags: 0x20000000 (CO_PYARMOR_OBFUSCATED)
    [Names]
        '__assert_armored__'
        'eel'
        'json'
        'random'
        'datetime'
        'concurrent.futures'
        'concurrent'
        'threading'
        'Thread'
        'Event'
        'multithon.sync'
        'functions'
        'types'
        'multithon.errors'
        'StopProgram'
        'program.static_classes'
        'AutoStop'
        'BanAccount'
        'GetLang'
        'Logs'
        'MaxFlood'
        'PeerFlood'
        'StopAccount'
        'logging'
        'memory_check_switcher'
        'memory_set_pid'
        'program.telegram'
        'DelayOnline'
        'Disconnect'
        'TelegramRequest'
        'Thread_wait'
        'account_works'
        'entity'
        'tg_entity'
        'tg_group'
        'tg_links'
        'program.general'
        'GetConfig'
        'GetProxy'
        'StopDetect'
        'check_get_settings'
        'del_task_manager'
        'getFile'
        'set_task_manager'
        'program.database'
        'db_parsing'
        'db_statistic'
        'Invite_username_v2'
        'START'
        'worker'
        'invite'
    [Locals+Names]
    [Constants]
        '__pyarmor_assert_13926__'
        '__pyarmor_enter_13927__'
        b'<COAddr>\x05\x00\x00\x1a\xde\x01\x00\x00\x00\x00\x00\x00\x00\x00\x00\x00\x00\x00\x00\x00'
        0
        None
        (
            'Thread'
            'Event'
        )
        (
            'functions'
            'types'
        )
        (
            'StopProgram'
        )
        (
            'AutoStop'
        )
        (
            'BanAccount'
        )
        (
            'GetLang'
        )
        (
            'Logs'
        )
        (
            'MaxFlood'
        )
        (
            'PeerFlood'
        )
        (
            'StopAccount'
        )
        (
            'logging'
        )
        (
            'memory_check_switcher'
        )
        (
            'memory_set_pid'
        )
        (
            'DelayOnline'
        )
        (
            'Disconnect'
        )
        (
            'TelegramRequest'
        )
        (
            'Thread_wait'
        )
        (
            'account_works'
        )
        (
            'entity'
        )
        (
            'tg_entity'
        )
        (
            'tg_group'
        )
        (
            'tg_links'
        )
        (
            'GetConfig'
        )
        (
            'GetProxy'
        )
        (
            'StopDetect'
        )
        (
            'check_get_settings'
        )
        (
            'del_task_manager'
        )
        (
            'getFile'
        )
        (
            'set_task_manager'
        )
        (
            'db_parsing'
        )
        (
            'db_statistic'
        )
        [Code]
            File Name: <frozen program.modules.Invite_username_v2>
            Object Name: Invite_username_v2
            Qualified Name: Invite_username_v2
            Arg Count: 1
            Pos Only Arg Count: 0
            KW Only Arg Count: 0
            Stack Size: 8
            Flags: 0x20000003 (CO_OPTIMIZED | CO_NEWLOCALS | CO_PYARMOR_OBFUSCATED)
            [Names]
                'get'
                'getFile'
                'GetConfig'
                'config'
                'GetLang'
                'Lang'
                'GetProxy'
                'eel'
                'sendSuccessBox'
                'memory_check_switcher'
                'Event'
                'memory_set_pid'
                'Thread'
                'START'
                'start'
                'Logs'
                'WaitStopAnsfer'
                'UpdateLogInWindow'
                'BaseException'
                'logging'
            [Locals+Names]
                'data'
                '__assert_armored__'
                '_var_var_0'
                '_var_var_1'
                '_var_var_2'
                '_var_var_3'
            [Constants]
                None
                '__pyarmor_assert_13929__'
                '__pyarmor_enter_13930__'
                b'<COAddr>\x05\x00\x00\x1a\xae\x02\x00\x00\x00\x00\x00\x00\x00\x00\x00\x00\x00\x00\x00\x00'
                'action'
                'getFile'
                '__pyarmor_exit_13931__'
                'program_running'   # b'\x81\xf2\n\x1c4\xe8\xbf\xdf$\xe8\x18\xceb\xe5\xf6\x82'
                False
                (
                    'target'
                    'args'
                )
                True
                (
                    'target'
                    'args'
                    'daemon'
                )
            [Disassembly]
                0       NOP                             
                2       NOP                             
                4       PUSH_NULL                       
                6       LOAD_CONST                      2: '__pyarmor_enter_13930__'
                8       LOAD_CONST                      3: b'<COAddr>\x05\x00\x00\x1a\xae\x02\x00\x00\x00\x00\x00\x00\x00\x00\x00\x00\x00\x00\x00\x00'
                10      BUILD_TUPLE                     1
                12      CALL_FUNCTION_EX                0
                14      POP_TOP                         
                16      RESUME                          0
                18      NOP                             
                20      NOP                             
                22      NOP                             
                24      NOP                             
                26      NOP                             
                28      NOP                             
                30      LOAD_FAST                       0: data
                32      LOAD_ATTR                       1: get
                52      LOAD_CONST                      4: 'action'
                54      CALL                            1
                62      POP_JUMP_IF_NONE                28 (to 120)
                64      LOAD_FAST                       0: data
                66      LOAD_CONST                      4: 'action'
                68      BINARY_SUBSCR                   
                72      LOAD_CONST                      5: 'getFile'
                74      COMPARE_OP                      40 (==)
                78      POP_JUMP_IF_FALSE               20 (to 120)
                80      LOAD_GLOBAL                     3: NULL + getFile
                90      LOAD_FAST                       0: data
                92      CALL                            1
                100     NOP                             
                102     NOP                             
                104     JUMP_FORWARD                    316 (to 740)
                108     CALL                            1
                116     POP_TOP                         
                118     RETURN_VALUE                    
                120     LOAD_GLOBAL                     5: NULL + GetConfig
                130     CALL                            0
                138     STORE_GLOBAL                    3: config
                140     LOAD_GLOBAL                     9: NULL + GetLang
                150     LOAD_GLOBAL                     6: config
                160     CALL                            1
                168     STORE_GLOBAL                    5: Lang
                170     LOAD_GLOBAL                     13: NULL + GetProxy
                180     CALL                            0
                188     STORE_FAST                      2: _var_var_0
                190     LOAD_GLOBAL                     15: NULL + eel
                200     LOAD_ATTR                       16: sendSuccessBox
                220     LOAD_GLOBAL                     10: Lang
                230     PUSH_NULL                       
                232     LOAD_CONST                      1: '__pyarmor_assert_13929__'
                234     LOAD_CONST                      7: 'program_running'   # b'\x81\xf2\n\x1c4\xe8\xbf\xdf$\xe8\x18\xceb\xe5\xf6\x82'
                236     CALL                            1
                244     BINARY_SUBSCR                   
                248     CALL                            1
                256     POP_TOP                         
                258     LOAD_GLOBAL                     19: NULL + memory_check_switcher
                268     CALL                            0
                276     POP_JUMP_IF_TRUE                11 (to 300)
                278     NOP                             
                280     LOAD_CONST                      8: False
                282     NOP                             
                284     NOP                             
                286     NOP                             
                288     JUMP_FORWARD                    225 (to 740)
                296     POP_TOP                         
                298     RETURN_CONST                    8: False
                300     LOAD_GLOBAL                     21: NULL + Event
                310     CALL                            0
                318     STORE_FAST                      3: _var_var_1
                320     LOAD_GLOBAL                     23: NULL + memory_set_pid
                330     CALL                            0
                338     STORE_FAST                      4: _var_var_2
                340     LOAD_GLOBAL                     25: NULL + Thread
                350     LOAD_GLOBAL                     26: START
                360     LOAD_FAST                       0: data
                362     LOAD_GLOBAL                     6: config
                372     LOAD_FAST                       4: _var_var_2
                374     LOAD_FAST                       2: _var_var_0
                376     LOAD_FAST                       3: _var_var_1
                378     BUILD_TUPLE                     5
                380     KW_NAMES                        9: ('target', 'args')
                382     CALL                            2
                390     LOAD_ATTR                       29: start
                410     CALL                            0
                418     POP_TOP                         
                420     LOAD_GLOBAL                     25: NULL + Thread
                430     LOAD_GLOBAL                     30: Logs
                440     LOAD_ATTR                       32: WaitStopAnsfer
                460     LOAD_GLOBAL                     6: config
                470     LOAD_FAST                       4: _var_var_2
                472     LOAD_FAST                       3: _var_var_1
                474     BUILD_TUPLE                     3
                476     LOAD_CONST                      10: True
                478     KW_NAMES                        11: ('target', 'args', 'daemon')
                480     CALL                            3
                488     LOAD_ATTR                       29: start
                508     CALL                            0
                516     POP_TOP                         
                518     LOAD_GLOBAL                     25: NULL + Thread
                528     LOAD_GLOBAL                     30: Logs
                538     LOAD_ATTR                       34: UpdateLogInWindow
                558     LOAD_GLOBAL                     6: config
                568     LOAD_FAST                       4: _var_var_2
                570     LOAD_FAST                       3: _var_var_1
                572     BUILD_TUPLE                     3
                574     LOAD_CONST                      10: True
                576     KW_NAMES                        11: ('target', 'args', 'daemon')
                578     CALL                            3
                586     LOAD_ATTR                       29: start
                606     CALL                            0
                614     POP_TOP                         
                616     LOAD_CONST                      0: None
                618     NOP                             
                620     NOP                             
                622     NOP                             
                624     JUMP_FORWARD                    57 (to 740)
                632     POP_TOP                         
                634     RETURN_CONST                    0: None
                636     PUSH_EXC_INFO                   
                638     LOAD_GLOBAL                     36: BaseException
                648     CHECK_EXC_MATCH                 
                650     POP_JUMP_IF_FALSE               26 (to 704)
                652     STORE_FAST                      5: _var_var_3
                654     PUSH_NULL                       
                656     LOAD_GLOBAL                     39: NULL + logging
                666     LOAD_FAST                       5: _var_var_3
                668     CALL                            1
                676     CALL                            0
                684     POP_TOP                         
                686     POP_EXCEPT                      
                688     LOAD_CONST                      0: None
                690     STORE_FAST                      5: _var_var_3
                692     DELETE_FAST                     5: _var_var_3
                694     JUMP_BACKWARD                   40 (to 616)
                696     LOAD_CONST                      0: None
                698     STORE_FAST                      5: _var_var_3
                700     DELETE_FAST                     5: _var_var_3
                702     RERAISE                         1
                704     RERAISE                         0
                706     COPY                            3
                708     POP_EXCEPT                      
                710     RERAISE                         1
                712     PUSH_EXC_INFO                   
                714     PUSH_NULL                       
                716     LOAD_CONST                      6: '__pyarmor_exit_13931__'
                718     NOP                             
                720     LOAD_CONST                      3: b'<COAddr>\x05\x00\x00\x1a\xae\x02\x00\x00\x00\x00\x00\x00\x00\x00\x00\x00\x00\x00\x00\x00'
                722     CALL                            1
                730     POP_TOP                         
                732     RERAISE                         0
                734     COPY                            3
                736     POP_EXCEPT                      
                738     RERAISE                         1
                740     PUSH_NULL                       
                742     LOAD_CONST                      6: '__pyarmor_exit_13931__'
                744     LOAD_CONST                      3: b'<COAddr>\x05\x00\x00\x1a\xae\x02\x00\x00\x00\x00\x00\x00\x00\x00\x00\x00\x00\x00\x00\x00'
                746     BUILD_TUPLE                     1
                748     CALL_FUNCTION_EX                0
                750     POP_TOP                         
                752     RETURN_VALUE                    
            [Exception Table]
                30 to 100 -> 636 [0] 
                120 to 278 -> 636 [0] 
                300 to 616 -> 636 [0] 
                636 to 654 -> 706 [1] lasti
                654 to 686 -> 696 [1] lasti
                686 to 696 -> 712 [0] 
                696 to 706 -> 706 [1] lasti
                706 to 712 -> 712 [0] 
                712 to 734 -> 734 [1] lasti
        [Code]
            File Name: <frozen program.modules.Invite_username_v2>
            Object Name: START
            Qualified Name: START
            Arg Count: 5
            Pos Only Arg Count: 0
            KW Only Arg Count: 0
            Stack Size: 14
            Flags: 0x20000003 (CO_OPTIMIZED | CO_NEWLOCALS | CO_PYARMOR_OBFUSCATED)
            [Names]
                'is_set'
                'StopProgram'
                'check_get_settings'
                'get'
                'int'
                'isinstance'
                'list'
                'eel'
                'sendErrorBox'
                'Lang'
                'datetime'
                'now'
                'strftime'
                'db_parsing'
                'import_users'
                'Logs'
                'PrintLog'
                'WriteResult'
                'db_statistic'
                'create'
                'set_task_manager'
                'concurrent'
                'futures'
                'ThreadPoolExecutor'
                'len'
                'StreamStat'
                'json'
                'dumps'
                'append'
                'submit'
                'worker'
                'as_completed'
                'result'
                'AutoStop'
                'start'
                'BaseException'
                'logging'
                'del_task_manager'
                'StopDetect'
            [Locals+Names]
                'data'
                'config'
                'pid'
                'proxy'
                'stop_thread'
                '__assert_armored__'
                '_var_var_4'
                '_var_var_5'
                '_var_var_6'
                '_var_var_7'
                '_var_var_8'
                '_var_var_9'
                '_var_var_10'
                '_var_var_11'
                '_var_var_12'
                '_var_var_13'
                '_var_var_14'
                '_var_var_15'
                '_var_var_16'
                '_var_var_17'
                '_var_var_18'
                '_var_var_19'
                '_var_var_20'
                '_var_var_21'
                '_var_var_22'
                '_var_var_23'
                '_var_var_24'
                '_var_var_25'
                '_var_var_26'
                '_var_var_3'
            [Constants]
                None
                '__pyarmor_assert_13932__'
                '__pyarmor_enter_13933__'
                b'<COAddr>\x05\x00\x00\x1a\xfa\t\x00\x00\x00\x00\x00\x00\x00\x00\x00\x00\x00\x00\x00\x00'
                'Settings'
                'Accounts'
                'invitegroups'   # b'\x81\xeb\x16\x05:\xee\xbb\xd5\t\xf5\x18\xd0\x7f'
                'autostop_rules'   # b'\x81\xe3\r\x07<\xe9\xaa\xdd\x0b\xc5\x1f\xd5`\xe9\xeb'
                'autostop_ban'   # b'\x81\xe3\r\x07<\xe9\xaa\xdd\x0b\xc5\x0f\xc1b'
                'autostop_spamblock'   # b'\x81\xe3\r\x07<\xe9\xaa\xdd\x0b\xc5\x1e\xd0m\xe1\xfa\x89\x00^\xb0'
                'autostop_flood'   # b'\x81\xe3\r\x07<\xe9\xaa\xdd\x0b\xc5\x0b\xccc\xe3\xfc'
                'autostop_sequential'   # b'\x81\xe3\r\x07<\xe9\xaa\xdd\x0b\xc5\x1e\xc5}\xf9\xfd\x8b\x1bT\xba\xab'
                'select_accounts_works'   # b'\x81\xf1\x1d\x1f6\xf9\xaa\xed\x1a\xf9\x0e\xcfy\xe2\xec\x960J\xb4\xb5\xa1\xd8'
                0
                ''
                'add_groups_invite'   # b'\x81\xe3\x1c\x17\x0c\xfd\xac\xdd\x0e\xea\x1e\xffe\xe2\xee\x8c\x1bX'
                'thread_rules'   # b'\x81\xf6\x10\x016\xfb\xba\xed\t\xef\x01\xc5\x7f'
                True
                'thread_count'   # b'\x81\xf6\x10\x016\xfb\xba\xed\x18\xf5\x18\xcex'
                '%Y-%m-%d_%H-%M-%S'   # b'\x81\xa7!^v\xf7\xf3\x97\x1f\xc5H\xe8!\xa9\xd5\xc8Jn'
                'use_data_base'   # b'\x81\xf7\x0b\x16\x0c\xfe\xbf\xc6\x1a\xc5\x0f\xc1\x7f\xe9'
                False
                'additives/invite_username/'   # b'\x81\xe3\x1c\x17:\xee\xb7\xc4\x1e\xe9B\xc9b\xfa\xf1\x91\nb\xae\xb4\xaf\xd9@\xcd\x08j\xec'
                '_parsing.db'   # b'\x81\xdd\x08\x12!\xe9\xb7\xdc\x1c\xb4\t\xc2'
                'usernames'   # b'\x81\xf7\x0b\x16!\xf4\xbf\xdf\x1e\xe9'
                (
                    'users'
                )
                'Check usernames'   # b'\x81\xc1\x10\x160\xf1\xfe\xc7\x08\xff\x1f\xcem\xe1\xfd\x96'
                (
                    'message'
                )
                'file_db'
                'Database'
                'invite_username'   # b'\x81\xeb\x16\x05:\xee\xbb\xed\x0e\xe9\x08\xd2b\xed\xf5\x80'
                '_stat_invite_username.db'   # b'\x81\xdd\x0b\x072\xee\x81\xdb\x15\xec\x04\xd4i\xd3\xed\x96\nO\xb5\xa6\xa7\xce\x00\xc8\x07'
                'Statistic'   # b"\x81\xd1\x0c\x12'\xf3\xad\xc6\x12\xf9"
                (
                    'accounts'
                    'name'
                )
                (
                    'max_workers'
                )
                'st_task'
                'st_stream'   # b'\x81\xf1\x0c, \xee\xac\xd7\x1a\xf7'
                'st_wait'
                'st_done'
                1
                '__pyarmor_exit_13934__'
                'Done'
            [Disassembly]
                0       NOP                             
                2       NOP                             
                4       PUSH_NULL                       
                6       LOAD_CONST                      2: '__pyarmor_enter_13933__'
                8       LOAD_CONST                      3: b'<COAddr>\x05\x00\x00\x1a\xfa\t\x00\x00\x00\x00\x00\x00\x00\x00\x00\x00\x00\x00\x00\x00'
                10      BUILD_TUPLE                     1
                12      CALL_FUNCTION_EX                0
                14      POP_TOP                         
                16      RESUME                          0
                18      NOP                             
                20      NOP                             
                22      NOP                             
                24      NOP                             
                26      NOP                             
                28      NOP                             
                30      LOAD_FAST                       4: stop_thread
                32      LOAD_ATTR                       1: is_set
                52      CALL                            0
                60      POP_JUMP_IF_FALSE               10 (to 82)
                62      LOAD_GLOBAL                     3: NULL + StopProgram
                72      CALL                            0
                80      RAISE_VARARGS                   1
                82      LOAD_GLOBAL                     5: NULL + check_get_settings
                92      LOAD_FAST                       0: data
                94      LOAD_ATTR                       7: get
                114     LOAD_CONST                      4: 'Settings'
                116     CALL                            1
                124     CALL                            1
                132     POP_TOP                         
                134     LOAD_FAST                       0: data
                136     LOAD_CONST                      5: 'Accounts'
                138     BINARY_SUBSCR                   
                142     STORE_FAST                      6: _var_var_4
                144     LOAD_FAST                       0: data
                146     LOAD_CONST                      4: 'Settings'
                148     BINARY_SUBSCR                   
                152     LOAD_ATTR                       7: get
                172     PUSH_NULL                       
                174     LOAD_CONST                      1: '__pyarmor_assert_13932__'
                176     LOAD_CONST                      6: 'invitegroups'   # b'\x81\xeb\x16\x05:\xee\xbb\xd5\t\xf5\x18\xd0\x7f'
                178     CALL                            1
                186     CALL                            1
                194     STORE_FAST                      7: _var_var_5
                196     LOAD_FAST                       0: data
                198     LOAD_CONST                      4: 'Settings'
                200     BINARY_SUBSCR                   
                204     LOAD_ATTR                       7: get
                224     PUSH_NULL                       
                226     LOAD_CONST                      1: '__pyarmor_assert_13932__'
                228     LOAD_CONST                      7: 'autostop_rules'   # b'\x81\xe3\r\x07<\xe9\xaa\xdd\x0b\xc5\x1f\xd5`\xe9\xeb'
                230     CALL                            1
                238     CALL                            1
                246     STORE_FAST                      8: _var_var_6
                248     LOAD_GLOBAL                     9: NULL + int
                258     LOAD_FAST                       0: data
                260     LOAD_CONST                      4: 'Settings'
                262     BINARY_SUBSCR                   
                266     LOAD_ATTR                       7: get
                286     PUSH_NULL                       
                288     LOAD_CONST                      1: '__pyarmor_assert_13932__'
                290     LOAD_CONST                      8: 'autostop_ban'   # b'\x81\xe3\r\x07<\xe9\xaa\xdd\x0b\xc5\x0f\xc1b'
                292     CALL                            1
                300     CALL                            1
                308     CALL                            1
                316     STORE_FAST                      9: _var_var_7
                318     LOAD_GLOBAL                     9: NULL + int
                328     LOAD_FAST                       0: data
                330     LOAD_CONST                      4: 'Settings'
                332     BINARY_SUBSCR                   
                336     LOAD_ATTR                       7: get
                356     PUSH_NULL                       
                358     LOAD_CONST                      1: '__pyarmor_assert_13932__'
                360     LOAD_CONST                      9: 'autostop_spamblock'   # b'\x81\xe3\r\x07<\xe9\xaa\xdd\x0b\xc5\x1e\xd0m\xe1\xfa\x89\x00^\xb0'
                362     CALL                            1
                370     CALL                            1
                378     CALL                            1
                386     STORE_FAST                      10: _var_var_8
                388     LOAD_GLOBAL                     9: NULL + int
                398     LOAD_FAST                       0: data
                400     LOAD_CONST                      4: 'Settings'
                402     BINARY_SUBSCR                   
                406     LOAD_ATTR                       7: get
                426     PUSH_NULL                       
                428     LOAD_CONST                      1: '__pyarmor_assert_13932__'
                430     LOAD_CONST                      10: 'autostop_flood'   # b'\x81\xe3\r\x07<\xe9\xaa\xdd\x0b\xc5\x0b\xccc\xe3\xfc'
                432     CALL                            1
                440     CALL                            1
                448     CALL                            1
                456     STORE_FAST                      11: _var_var_9
                458     LOAD_FAST                       0: data
                460     LOAD_CONST                      4: 'Settings'
                462     BINARY_SUBSCR                   
                466     LOAD_ATTR                       7: get
                486     PUSH_NULL                       
                488     LOAD_CONST                      1: '__pyarmor_assert_13932__'
                490     LOAD_CONST                      11: 'autostop_sequential'   # b'\x81\xe3\r\x07<\xe9\xaa\xdd\x0b\xc5\x1e\xc5}\xf9\xfd\x8b\x1bT\xba\xab'
                492     CALL                            1
                500     CALL                            1
                508     STORE_FAST                      12: _var_var_10
                510     LOAD_GLOBAL                     11: NULL + isinstance
                520     LOAD_FAST                       6: _var_var_4
                522     LOAD_GLOBAL                     12: list
                532     CALL                            2
                540     POP_JUMP_IF_TRUE                3 (to 548)
                542     LOAD_FAST                       6: _var_var_4
                544     BUILD_LIST                      1
                546     STORE_FAST                      6: _var_var_4
                548     LOAD_GLOBAL                     11: NULL + isinstance
                558     LOAD_FAST                       7: _var_var_5
                560     LOAD_GLOBAL                     12: list
                570     CALL                            2
                578     POP_JUMP_IF_TRUE                3 (to 586)
                580     LOAD_FAST                       7: _var_var_5
                582     BUILD_LIST                      1
                584     STORE_FAST                      7: _var_var_5
                586     LOAD_FAST                       6: _var_var_4
                588     POP_JUMP_IF_TRUE                44 (to 678)
                590     LOAD_GLOBAL                     15: NULL + eel
                600     LOAD_ATTR                       16: sendErrorBox
                620     LOAD_GLOBAL                     18: Lang
                630     PUSH_NULL                       
                632     LOAD_CONST                      1: '__pyarmor_assert_13932__'
                634     LOAD_CONST                      12: 'select_accounts_works'   # b'\x81\xf1\x1d\x1f6\xf9\xaa\xed\x1a\xf9\x0e\xcfy\xe2\xec\x960J\xb4\xb5\xa1\xd8'
                636     CALL                            1
                644     BINARY_SUBSCR                   
                648     CALL                            1
                656     POP_TOP                         
                658     LOAD_GLOBAL                     3: NULL + StopProgram
                668     CALL                            0
                676     RAISE_VARARGS                   1
                678     LOAD_FAST                       7: _var_var_5
                680     LOAD_CONST                      13: 0
                682     BINARY_SUBSCR                   
                686     LOAD_CONST                      14: ''
                688     COMPARE_OP                      40 (==)
                692     POP_JUMP_IF_FALSE               44 (to 782)
                694     LOAD_GLOBAL                     15: NULL + eel
                704     LOAD_ATTR                       16: sendErrorBox
                724     LOAD_GLOBAL                     18: Lang
                734     PUSH_NULL                       
                736     LOAD_CONST                      1: '__pyarmor_assert_13932__'
                738     LOAD_CONST                      15: 'add_groups_invite'   # b'\x81\xe3\x1c\x17\x0c\xfd\xac\xdd\x0e\xea\x1e\xffe\xe2\xee\x8c\x1bX'
                740     CALL                            1
                748     BINARY_SUBSCR                   
                752     CALL                            1
                760     POP_TOP                         
                762     LOAD_GLOBAL                     3: NULL + StopProgram
                772     CALL                            0
                780     RAISE_VARARGS                   1
                782     LOAD_FAST                       0: data
                784     LOAD_CONST                      4: 'Settings'
                786     BINARY_SUBSCR                   
                790     LOAD_ATTR                       7: get
                810     PUSH_NULL                       
                812     LOAD_CONST                      1: '__pyarmor_assert_13932__'
                814     LOAD_CONST                      16: 'thread_rules'   # b'\x81\xf6\x10\x016\xfb\xba\xed\t\xef\x01\xc5\x7f'
                816     CALL                            1
                824     CALL                            1
                832     LOAD_CONST                      17: True
                834     COMPARE_OP                      40 (==)
                838     POP_JUMP_IF_FALSE               36 (to 912)
                840     LOAD_GLOBAL                     9: NULL + int
                850     LOAD_FAST                       0: data
                852     LOAD_CONST                      4: 'Settings'
                854     BINARY_SUBSCR                   
                858     LOAD_ATTR                       7: get
                878     PUSH_NULL                       
                880     LOAD_CONST                      1: '__pyarmor_assert_13932__'
                882     LOAD_CONST                      18: 'thread_count'   # b'\x81\xf6\x10\x016\xfb\xba\xed\x18\xf5\x18\xcex'
                884     CALL                            1
                892     CALL                            1
                900     CALL                            1
                908     STORE_FAST                      13: _var_var_11
                910     JUMP_FORWARD                    11 (to 934)
                912     LOAD_FAST                       1: config
                914     PUSH_NULL                       
                916     LOAD_CONST                      1: '__pyarmor_assert_13932__'
                918     LOAD_CONST                      18: 'thread_count'   # b'\x81\xf6\x10\x016\xfb\xba\xed\x18\xf5\x18\xcex'
                920     CALL                            1
                928     BINARY_SUBSCR                   
                932     STORE_FAST                      13: _var_var_11
                934     LOAD_GLOBAL                     20: datetime
                944     LOAD_ATTR                       20: datetime
                964     LOAD_ATTR                       23: now
                984     CALL                            0
                992     LOAD_ATTR                       25: strftime
                1012    PUSH_NULL                       
                1014    LOAD_CONST                      1: '__pyarmor_assert_13932__'
                1016    LOAD_CONST                      19: '%Y-%m-%d_%H-%M-%S'   # b'\x81\xa7!^v\xf7\xf3\x97\x1f\xc5H\xe8!\xa9\xd5\xc8Jn'
                1018    CALL                            1
                1026    CALL                            1
                1034    STORE_FAST                      14: _var_var_12
                1036    LOAD_FAST                       0: data
                1038    LOAD_CONST                      4: 'Settings'
                1040    BINARY_SUBSCR                   
                1044    PUSH_NULL                       
                1046    LOAD_CONST                      1: '__pyarmor_assert_13932__'
                1048    LOAD_CONST                      20: 'use_data_base'   # b'\x81\xf7\x0b\x16\x0c\xfe\xbf\xc6\x1a\xc5\x0f\xc1\x7f\xe9'
                1050    CALL                            1
                1058    BINARY_SUBSCR                   
                1062    LOAD_CONST                      21: False
                1064    COMPARE_OP                      40 (==)
                1068    POP_JUMP_IF_FALSE               156 (to 1382)
                1070    LOAD_GLOBAL                     27: NULL + db_parsing
                1080    PUSH_NULL                       
                1082    LOAD_CONST                      1: '__pyarmor_assert_13932__'
                1084    LOAD_CONST                      22: 'additives/invite_username/'   # b'\x81\xe3\x1c\x17:\xee\xb7\xc4\x1e\xe9B\xc9b\xfa\xf1\x91\nb\xae\xb4\xaf\xd9@\xcd\x08j\xec'
                1086    CALL                            1
                1094    LOAD_FAST                       14: _var_var_12
                1096    FORMAT_VALUE                    0 (FVC_NONE)
                1098    PUSH_NULL                       
                1100    LOAD_CONST                      1: '__pyarmor_assert_13932__'
                1102    LOAD_CONST                      23: '_parsing.db'   # b'\x81\xdd\x08\x12!\xe9\xb7\xdc\x1c\xb4\t\xc2'
                1104    CALL                            1
                1112    BUILD_STRING                    3
                1114    CALL                            1
                1122    LOAD_ATTR                       29: import_users
                1142    LOAD_FAST                       0: data
                1144    LOAD_CONST                      4: 'Settings'
                1146    BINARY_SUBSCR                   
                1150    LOAD_ATTR                       7: get
                1170    PUSH_NULL                       
                1172    LOAD_CONST                      1: '__pyarmor_assert_13932__'
                1174    LOAD_CONST                      24: 'usernames'   # b'\x81\xf7\x0b\x16!\xf4\xbf\xdf\x1e\xe9'
                1176    CALL                            1
                1184    CALL                            1
                1192    KW_NAMES                        25: ('users',)
                1194    CALL                            1
                1202    STORE_FAST                      15: _var_var_13
                1204    LOAD_FAST                       15: _var_var_13
                1206    LOAD_CONST                      21: False
                1208    COMPARE_OP                      40 (==)
                1212    POP_JUMP_IF_FALSE               38 (to 1290)
                1214    LOAD_GLOBAL                     31: NULL + Logs
                1224    LOAD_ATTR                       32: PrintLog
                1244    PUSH_NULL                       
                1246    LOAD_CONST                      1: '__pyarmor_assert_13932__'
                1248    LOAD_CONST                      26: 'Check usernames'   # b'\x81\xc1\x10\x160\xf1\xfe\xc7\x08\xff\x1f\xcem\xe1\xfd\x96'
                1250    CALL                            1
                1258    KW_NAMES                        27: ('message',)
                1260    CALL                            1
                1268    POP_TOP                         
                1270    LOAD_GLOBAL                     3: NULL + StopProgram
                1280    CALL                            0
                1288    RAISE_VARARGS                   1
                1290    LOAD_FAST                       15: _var_var_13
                1292    LOAD_FAST                       0: data
                1294    LOAD_CONST                      4: 'Settings'
                1296    BINARY_SUBSCR                   
                1300    LOAD_CONST                      28: 'file_db'
                1302    STORE_SUBSCR                    
                1306    LOAD_GLOBAL                     15: NULL + eel
                1316    LOAD_ATTR                       34: WriteResult
                1336    LOAD_CONST                      29: 'Database'
                1338    PUSH_NULL                       
                1340    LOAD_CONST                      1: '__pyarmor_assert_13932__'
                1342    LOAD_CONST                      30: 'invite_username'   # b'\x81\xeb\x16\x05:\xee\xbb\xed\x0e\xe9\x08\xd2b\xed\xf5\x80'
                1344    CALL                            1
                1352    LOAD_FAST                       14: _var_var_12
                1354    FORMAT_VALUE                    0 (FVC_NONE)
                1356    PUSH_NULL                       
                1358    LOAD_CONST                      1: '__pyarmor_assert_13932__'
                1360    LOAD_CONST                      23: '_parsing.db'   # b'\x81\xdd\x08\x12!\xe9\xb7\xdc\x1c\xb4\t\xc2'
                1362    CALL                            1
                1370    BUILD_STRING                    2
                1372    CALL                            3
                1380    POP_TOP                         
                1382    LOAD_GLOBAL                     37: NULL + db_statistic
                1392    PUSH_NULL                       
                1394    LOAD_CONST                      1: '__pyarmor_assert_13932__'
                1396    LOAD_CONST                      22: 'additives/invite_username/'   # b'\x81\xe3\x1c\x17:\xee\xb7\xc4\x1e\xe9B\xc9b\xfa\xf1\x91\nb\xae\xb4\xaf\xd9@\xcd\x08j\xec'
                1398    CALL                            1
                1406    LOAD_FAST                       14: _var_var_12
                1408    FORMAT_VALUE                    0 (FVC_NONE)
                1410    PUSH_NULL                       
                1412    LOAD_CONST                      1: '__pyarmor_assert_13932__'
                1414    LOAD_CONST                      31: '_stat_invite_username.db'   # b'\x81\xdd\x0b\x072\xee\x81\xdb\x15\xec\x04\xd4i\xd3\xed\x96\nO\xb5\xa6\xa7\xce\x00\xc8\x07'
                1416    CALL                            1
                1424    BUILD_STRING                    3
                1426    CALL                            1
                1434    LOAD_ATTR                       39: create
                1454    CALL                            0
                1462    STORE_FAST                      16: _var_var_14
                1464    LOAD_GLOBAL                     15: NULL + eel
                1474    LOAD_ATTR                       34: WriteResult
                1494    PUSH_NULL                       
                1496    LOAD_CONST                      1: '__pyarmor_assert_13932__'
                1498    LOAD_CONST                      32: 'Statistic'   # b"\x81\xd1\x0c\x12'\xf3\xad\xc6\x12\xf9"
                1500    CALL                            1
                1508    PUSH_NULL                       
                1510    LOAD_CONST                      1: '__pyarmor_assert_13932__'
                1512    LOAD_CONST                      30: 'invite_username'   # b'\x81\xeb\x16\x05:\xee\xbb\xed\x0e\xe9\x08\xd2b\xed\xf5\x80'
                1514    CALL                            1
                1522    LOAD_FAST                       14: _var_var_12
                1524    FORMAT_VALUE                    0 (FVC_NONE)
                1526    PUSH_NULL                       
                1528    LOAD_CONST                      1: '__pyarmor_assert_13932__'
                1530    LOAD_CONST                      31: '_stat_invite_username.db'   # b'\x81\xdd\x0b\x072\xee\x81\xdb\x15\xec\x04\xd4i\xd3\xed\x96\nO\xb5\xa6\xa7\xce\x00\xc8\x07'
                1532    CALL                            1
                1540    BUILD_STRING                    2
                1542    CALL                            3
                1550    POP_TOP                         
                1552    LOAD_GLOBAL                     41: NULL + set_task_manager
                1562    LOAD_FAST                       2: pid
                1564    LOAD_FAST                       6: _var_var_4
                1566    PUSH_NULL                       
                1568    LOAD_CONST                      1: '__pyarmor_assert_13932__'
                1570    LOAD_CONST                      30: 'invite_username'   # b'\x81\xeb\x16\x05:\xee\xbb\xed\x0e\xe9\x08\xd2b\xed\xf5\x80'
                1572    CALL                            1
                1580    KW_NAMES                        33: ('accounts', 'name')
                1582    CALL                            3
                1590    POP_TOP                         
                1592    LOAD_GLOBAL                     42: concurrent
                1602    LOAD_ATTR                       44: futures
                1622    LOAD_ATTR                       47: ThreadPoolExecutor
                1642    LOAD_FAST                       13: _var_var_11
                1644    KW_NAMES                        34: ('max_workers',)
                1646    CALL                            1
                1654    BEFORE_WITH                     
                1656    STORE_FAST                      17: _var_var_15
                1658    BUILD_LIST                      0
                1660    STORE_FAST                      18: _var_var_16
                1662    LOAD_GLOBAL                     49: NULL + len
                1672    LOAD_FAST                       6: _var_var_4
                1674    CALL                            1
                1682    STORE_FAST                      19: _var_var_17
                1684    LOAD_FAST                       13: _var_var_11
                1686    STORE_FAST                      20: _var_var_18
                1688    LOAD_FAST                       19: _var_var_17
                1690    STORE_FAST                      21: _var_var_19
                1692    LOAD_CONST                      13: 0
                1694    STORE_FAST                      22: _var_var_20
                1696    LOAD_CONST                      13: 0
                1698    STORE_FAST                      23: _var_var_21
                1700    LOAD_GLOBAL                     15: NULL + eel
                1710    LOAD_ATTR                       50: StreamStat
                1730    LOAD_GLOBAL                     53: NULL + json
                1740    LOAD_ATTR                       54: dumps
                1760    LOAD_CONST                      35: 'st_task'
                1762    LOAD_FAST                       19: _var_var_17
                1764    PUSH_NULL                       
                1766    LOAD_CONST                      1: '__pyarmor_assert_13932__'
                1768    LOAD_CONST                      36: 'st_stream'   # b'\x81\xf1\x0c, \xee\xac\xd7\x1a\xf7'
                1770    CALL                            1
                1778    LOAD_FAST                       20: _var_var_18
                1780    LOAD_CONST                      37: 'st_wait'
                1782    LOAD_FAST                       21: _var_var_19
                1784    LOAD_CONST                      38: 'st_done'
                1786    LOAD_FAST                       22: _var_var_20
                1788    BUILD_MAP                       4
                1790    CALL                            1
                1798    CALL                            1
                1806    POP_TOP                         
                1808    LOAD_FAST                       6: _var_var_4
                1810    GET_ITER                        
                1812    FOR_ITER                        94 (to 2002)
                1816    STORE_FAST                      24: _var_var_22
                1818    LOAD_GLOBAL                     49: NULL + len
                1828    LOAD_FAST                       7: _var_var_5
                1830    CALL                            1
                1838    LOAD_CONST                      39: 1
                1840    COMPARE_OP                      68 (>)
                1844    POP_JUMP_IF_FALSE               30 (to 1906)
                1846    LOAD_FAST                       23: _var_var_21
                1848    LOAD_GLOBAL                     49: NULL + len
                1858    LOAD_FAST                       7: _var_var_5
                1860    CALL                            1
                1868    LOAD_CONST                      39: 1
                1870    BINARY_OP                       10 (-)
                1874    COMPARE_OP                      68 (>)
                1878    POP_JUMP_IF_FALSE               2 (to 1884)
                1880    LOAD_CONST                      13: 0
                1882    STORE_FAST                      23: _var_var_21
                1884    LOAD_FAST                       7: _var_var_5
                1886    LOAD_FAST                       23: _var_var_21
                1888    BINARY_SUBSCR                   
                1892    STORE_FAST                      25: _var_var_23
                1894    LOAD_FAST                       23: _var_var_21
                1896    LOAD_CONST                      39: 1
                1898    BINARY_OP                       13 (+=)
                1902    STORE_FAST                      23: _var_var_21
                1904    JUMP_FORWARD                    5 (to 1916)
                1906    LOAD_FAST                       7: _var_var_5
                1908    LOAD_CONST                      13: 0
                1910    BINARY_SUBSCR                   
                1914    STORE_FAST                      25: _var_var_23
                1916    LOAD_FAST                       18: _var_var_16
                1918    LOAD_ATTR                       57: append
                1938    LOAD_FAST                       17: _var_var_15
                1940    LOAD_ATTR                       59: submit
                1960    LOAD_GLOBAL                     60: worker
                1970    LOAD_FAST                       25: _var_var_23
                1972    LOAD_FAST                       24: _var_var_22
                1974    LOAD_FAST                       1: config
                1976    LOAD_FAST                       3: proxy
                1978    LOAD_FAST                       0: data
                1980    LOAD_FAST                       16: _var_var_14
                1982    LOAD_FAST                       4: stop_thread
                1984    CALL                            8
                1992    CALL                            1
                2000    POP_TOP                         
                2002    JUMP_BACKWARD                   96 (to 1812)
                2004    END_FOR                         
                2006    BUILD_LIST                      0
                2008    STORE_FAST                      26: _var_var_24
                2010    LOAD_GLOBAL                     42: concurrent
                2020    LOAD_ATTR                       44: futures
                2040    LOAD_ATTR                       63: as_completed
                2060    LOAD_FAST                       18: _var_var_16
                2062    CALL                            1
                2070    GET_ITER                        
                2072    FOR_ITER                        110 (to 2294)
                2076    STORE_FAST                      27: _var_var_25
                2078    LOAD_FAST                       22: _var_var_20
                2080    LOAD_CONST                      39: 1
                2082    BINARY_OP                       13 (+=)
                2086    STORE_FAST                      22: _var_var_20
                2088    LOAD_FAST                       21: _var_var_19
                2090    LOAD_CONST                      39: 1
                2092    BINARY_OP                       23 (-=)
                2096    STORE_FAST                      21: _var_var_19
                2098    LOAD_GLOBAL                     15: NULL + eel
                2108    LOAD_ATTR                       50: StreamStat
                2128    LOAD_GLOBAL                     53: NULL + json
                2138    LOAD_ATTR                       54: dumps
                2158    LOAD_CONST                      35: 'st_task'
                2160    LOAD_FAST                       19: _var_var_17
                2162    PUSH_NULL                       
                2164    LOAD_CONST                      1: '__pyarmor_assert_13932__'
                2166    LOAD_CONST                      36: 'st_stream'   # b'\x81\xf1\x0c, \xee\xac\xd7\x1a\xf7'
                2168    CALL                            1
                2176    LOAD_FAST                       20: _var_var_18
                2178    LOAD_CONST                      37: 'st_wait'
                2180    LOAD_FAST                       21: _var_var_19
                2182    LOAD_CONST                      38: 'st_done'
                2184    LOAD_FAST                       22: _var_var_20
                2186    BUILD_MAP                       4
                2188    CALL                            1
                2196    CALL                            1
                2204    POP_TOP                         
                2206    LOAD_FAST                       27: _var_var_25
                2208    LOAD_ATTR                       65: result
                2228    CALL                            0
                2236    STORE_FAST                      28: _var_var_26
                2238    LOAD_GLOBAL                     67: NULL + AutoStop
                2248    LOAD_FAST                       28: _var_var_26
                2250    LOAD_FAST                       26: _var_var_24
                2252    LOAD_FAST                       0: data
                2254    LOAD_FAST                       4: stop_thread
                2256    CALL                            4
                2264    LOAD_ATTR                       69: start
                2284    CALL                            0
                2292    STORE_FAST                      26: _var_var_24
                2294    JUMP_BACKWARD                   112 (to 2072)
                2296    END_FOR                         
                2298    DELETE_FAST                     18: _var_var_16
                2300    DELETE_FAST                     0: data
                2302    LOAD_CONST                      0: None
                2304    LOAD_CONST                      0: None
                2306    LOAD_CONST                      0: None
                2308    CALL                            2
                2316    POP_TOP                         
                2318    LOAD_GLOBAL                     75: NULL + del_task_manager
                2328    LOAD_FAST                       2: pid
                2330    CALL                            1
                2338    POP_TOP                         
                2340    LOAD_GLOBAL                     77: NULL + StopDetect
                2350    LOAD_FAST                       4: stop_thread
                2352    CALL                            1
                2360    POP_TOP                         
                2362    NOP                             
                2364    LOAD_CONST                      41: 'Done'
                2366    NOP                             
                2368    NOP                             
                2370    NOP                             
                2372    JUMP_FORWARD                    117 (to 2608)
                2380    POP_TOP                         
                2382    RETURN_CONST                    41: 'Done'
                2384    PUSH_EXC_INFO                   
                2386    WITH_EXCEPT_START               
                2388    POP_JUMP_IF_TRUE                1 (to 2392)
                2390    RERAISE                         2
                2392    POP_TOP                         
                2394    POP_EXCEPT                      
                2396    POP_TOP                         
                2398    POP_TOP                         
                2400    JUMP_BACKWARD                   42 (to 2318)
                2402    COPY                            3
                2404    POP_EXCEPT                      
                2406    RERAISE                         1
                2408    PUSH_EXC_INFO                   
                2410    LOAD_GLOBAL                     2: StopProgram
                2420    CHECK_EXC_MATCH                 
                2422    POP_JUMP_IF_FALSE               3 (to 2430)
                2424    POP_TOP                         
                2426    POP_EXCEPT                      
                2428    JUMP_BACKWARD                   56 (to 2318)
                2430    LOAD_GLOBAL                     70: BaseException
                2440    CHECK_EXC_MATCH                 
                2442    POP_JUMP_IF_FALSE               26 (to 2496)
                2444    STORE_FAST                      29: _var_var_3
                2446    PUSH_NULL                       
                2448    LOAD_GLOBAL                     73: NULL + logging
                2458    LOAD_FAST                       29: _var_var_3
                2460    CALL                            1
                2468    CALL                            0
                2476    POP_TOP                         
                2478    POP_EXCEPT                      
                2480    LOAD_CONST                      0: None
                2482    STORE_FAST                      29: _var_var_3
                2484    DELETE_FAST                     29: _var_var_3
                2486    JUMP_BACKWARD                   85 (to 2318)
                2488    LOAD_CONST                      0: None
                2490    STORE_FAST                      29: _var_var_3
                2492    DELETE_FAST                     29: _var_var_3
                2494    RERAISE                         1
                2496    RERAISE                         0
                2498    COPY                            3
                2500    POP_EXCEPT                      
                2502    RERAISE                         1
                2504    PUSH_EXC_INFO                   
                2506    LOAD_GLOBAL                     75: NULL + del_task_manager
                2516    LOAD_FAST                       2: pid
                2518    CALL                            1
                2526    POP_TOP                         
                2528    LOAD_GLOBAL                     77: NULL + StopDetect
                2538    LOAD_FAST                       4: stop_thread
                2540    CALL                            1
                2548    POP_TOP                         
                2550    POP_TOP                         
                2552    POP_EXCEPT                      
                2554    LOAD_CONST                      41: 'Done'
                2556    NOP                             
                2558    NOP                             
                2560    NOP                             
                2562    JUMP_FORWARD                    22 (to 2608)
                2570    POP_TOP                         
                2572    RETURN_CONST                    41: 'Done'
                2574    COPY                            3
                2576    POP_EXCEPT                      
                2578    RERAISE                         1
                2580    PUSH_EXC_INFO                   
                2582    PUSH_NULL                       
                2584    LOAD_CONST                      40: '__pyarmor_exit_13934__'
                2586    NOP                             
                2588    LOAD_CONST                      3: b'<COAddr>\x05\x00\x00\x1a\xfa\t\x00\x00\x00\x00\x00\x00\x00\x00\x00\x00\x00\x00\x00\x00'
                2590    CALL                            1
                2598    POP_TOP                         
                2600    RERAISE                         0
                2602    COPY                            3
                2604    POP_EXCEPT                      
                2606    RERAISE                         1
                2608    PUSH_NULL                       
                2610    LOAD_CONST                      40: '__pyarmor_exit_13934__'
                2612    LOAD_CONST                      3: b'<COAddr>\x05\x00\x00\x1a\xfa\t\x00\x00\x00\x00\x00\x00\x00\x00\x00\x00\x00\x00\x00\x00'
                2614    BUILD_TUPLE                     1
                2616    CALL_FUNCTION_EX                0
                2618    POP_TOP                         
                2620    RETURN_VALUE                    
            [Exception Table]
                30 to 1656 -> 2408 [0] 
                1656 to 2302 -> 2384 [1] lasti
                2302 to 2318 -> 2408 [0] 
                2318 to 2362 -> 2580 [0] 
                2384 to 2394 -> 2402 [3] lasti
                2394 to 2408 -> 2408 [0] 
                2408 to 2426 -> 2498 [1] lasti
                2426 to 2430 -> 2504 [0] 
                2430 to 2446 -> 2498 [1] lasti
                2446 to 2478 -> 2488 [1] lasti
                2478 to 2488 -> 2504 [0] 
                2488 to 2498 -> 2498 [1] lasti
                2498 to 2504 -> 2504 [0] 
                2504 to 2552 -> 2574 [1] lasti
                2552 to 2554 -> 2580 [0] 
                2574 to 2580 -> 2580 [0] 
                2580 to 2602 -> 2602 [1] lasti
        [Code]
            File Name: <frozen program.modules.Invite_username_v2>
            Object Name: worker
            Qualified Name: worker
            Arg Count: 7
            Pos Only Arg Count: 0
            KW Only Arg Count: 0
            Stack Size: 9
            Flags: 0x20000003 (CO_OPTIMIZED | CO_NEWLOCALS | CO_PYARMOR_OBFUSCATED)
            [Names]
                'Thread_wait'
                'account_works'
                'Lang'
                'tg_links'
                '_correct'
                'get'
                'int'
                'is_set'
                'StopProgram'
                'tg_group'
                'go_to'
                'Logs'
                'PrintLog'
                'StopAccount'
                'entity'
                'check'
                'random'
                'randint'
                'invite'
                'start'
                'go_out'
                'PeerFlood'
                'MaxFlood'
                'BanAccount'
                'status'
                'Disconnect'
                'result'
                'BaseException'
                'logging'
            [Locals+Names]
                'group'
                'account'
                'config'
                'proxy'
                'data'
                'statistic'
                'stop_thread'
                '__assert_armored__'
                '_var_var_27'
                '_var_var_28'
                '_var_var_13'
                '_var_var_29'
                '_var_var_30'
                '_var_var_31'
                '_var_var_32'
                '_var_var_33'
                '_var_var_34'
                '_var_var_35'
                '_var_var_36'
                '_var_var_37'
                '_var_var_38'
                '_var_var_39'
                '_var_var_40'
                '_var_var_41'
                '_var_var_42'
                '_var_var_3'
            [Constants]
                None
                '__pyarmor_assert_13935__'
                '__pyarmor_enter_13936__'
                b'<COAddr>\x07\x00\x00\x1a\xe4\x08\x00\x00\x00\x00\x00\x00\x00\x00\x00\x00\x00\x00\x00\x00'
                'Invite'
                (
                    'module'
                )
                False
                'false'
                (
                    'account'
                    'status'
                )
                '__pyarmor_exit_13937__'
                'Settings'
                'file_db'
                'kol_users_from'   # b'\x81\xe9\x17\x1f\x0c\xef\xad\xd7\t\xe92\xc6~\xe3\xf5'
                'kol_users_to'   # b'\x81\xe9\x17\x1f\x0c\xef\xad\xd7\t\xe92\xd4c'
                'kol_req_from'   # b'\x81\xe9\x17\x1f\x0c\xe8\xbb\xc3$\xfc\x1f\xcfa'
                'kol_req_to'   # b'\x81\xe9\x17\x1f\x0c\xe8\xbb\xc3$\xee\x02'
                'wait_from'   # b"\x81\xf5\x19\x1a'\xc5\xb8\xc0\x14\xf7"
                'wait_to'
                'leave_chat'   # b'\x81\xee\x1d\x12%\xff\x81\xd1\x13\xfb\x19'
                'max_flood_wait'   # b'\x81\xef\x19\x0b\x0c\xfc\xb2\xdd\x14\xfe2\xd7m\xe5\xec'
                'force_mode'   # b'\x81\xe4\x17\x010\xff\x81\xdf\x14\xfe\x08'
                'check_users'   # b'\x81\xe1\x10\x160\xf1\x81\xc7\x08\xff\x1f\xd3'
                (
                    'config'
                    'client'
                    'account'
                    'group_link'
                    'max_flood_wait'
                    'lang'
                    'stop_thread'
                )
                'invite_enter_to_group_flood'   # b'\x81\xeb\x16\x05:\xee\xbb\xed\x1e\xf4\x19\xc5~\xd3\xec\x8a0Z\xa9\xa8\xbf\xdbq\xca\t`\xacX'
                (
                    'config'
                    'account'
                    'message'
                )
                'type'
                'chat'
                'cloner_chats_error_type_group'   # b'\x81\xe1\x14\x1c=\xff\xac\xed\x18\xf2\x0c\xd4\x7f\xd3\xfd\x97\x1dR\xa9\x98\xbe\xd2^\xc9:h\xb1S\x15\xa1'
                'config'
                'client'
                'account'
                'kol_users'
                'kol_req'
                'force_mode'
                'check_users'
                'group'
                'link'
                'statistic'
                'wait_from'
                'max_flood_wait'
                'lang'
                'stop_thread'
                'exit_groups_on_activated'   # b"\x81\xe7\x00\x1a'\xc5\xb9\xc0\x14\xef\x1d\xd3S\xe3\xf6\xba\x0e^\xaf\xae\xbc\xcaZ\xc9\x01"
                'leaving_group'   # b'\x81\xee\x1d\x12%\xf3\xb0\xd5$\xfd\x1f\xcfy\xfc'
                (
                    'config'
                    'client'
                    'account'
                    'max_flood_wait'
                    'lang'
                    'stop_thread'
                )
                (
                    'entity'
                )
                'work_account_completed'   # b'\x81\xf5\x17\x018\xc5\xbf\xd1\x18\xf5\x18\xcex\xd3\xfb\x8a\x02M\xb7\xa2\xbe\xceJ'
                (
                    'config'
                    'account'
                    'message'
                    'end'
                )
                'done'
                (
                )
            [Disassembly]
                0       NOP                             
                2       NOP                             
                4       PUSH_NULL                       
                6       LOAD_CONST                      2: '__pyarmor_enter_13936__'
                8       LOAD_CONST                      3: b'<COAddr>\x07\x00\x00\x1a\xe4\x08\x00\x00\x00\x00\x00\x00\x00\x00\x00\x00\x00\x00\x00\x00'
                10      BUILD_TUPLE                     1
                12      CALL_FUNCTION_EX                0
                14      POP_TOP                         
                16      RESUME                          0
                18      NOP                             
                20      NOP                             
                22      NOP                             
                24      NOP                             
                26      NOP                             
                28      NOP                             
                30      LOAD_GLOBAL                     1: NULL + Thread_wait
                40      LOAD_FAST                       4: data
                42      LOAD_FAST                       2: config
                44      LOAD_FAST                       6: stop_thread
                46      CALL                            3
                54      POP_TOP                         
                56      LOAD_GLOBAL                     3: NULL + account_works
                66      LOAD_FAST                       2: config
                68      LOAD_GLOBAL                     4: Lang
                78      LOAD_FAST                       3: proxy
                80      LOAD_FAST                       1: account
                82      LOAD_FAST                       6: stop_thread
                84      LOAD_CONST                      4: 'Invite'
                86      KW_NAMES                        5: ('module',)
                88      CALL                            6
                96      STORE_FAST                      8: _var_var_27
                98      LOAD_FAST                       8: _var_var_27
                100     LOAD_CONST                      6: False
                102     COMPARE_OP                      40 (==)
                106     POP_JUMP_IF_FALSE               14 (to 136)
                108     LOAD_FAST                       1: account
                110     LOAD_CONST                      7: 'false'
                112     LOAD_CONST                      8: ('account', 'status')
                114     BUILD_CONST_KEY_MAP             2
                116     NOP                             
                118     NOP                             
                120     JUMP_FORWARD                    1103 (to 2330)
                124     CALL                            1
                132     POP_TOP                         
                134     RETURN_VALUE                    
                136     LOAD_GLOBAL                     7: NULL + tg_links
                146     CALL                            0
                154     LOAD_ATTR                       9: _correct
                174     LOAD_FAST                       0: group
                176     CALL                            1
                184     STORE_FAST                      9: _var_var_28
                186     LOAD_FAST                       4: data
                188     LOAD_CONST                      10: 'Settings'
                190     BINARY_SUBSCR                   
                194     LOAD_ATTR                       11: get
                214     LOAD_CONST                      11: 'file_db'
                216     CALL                            1
                224     STORE_FAST                      10: _var_var_13
                226     LOAD_GLOBAL                     13: NULL + int
                236     LOAD_FAST                       4: data
                238     LOAD_CONST                      10: 'Settings'
                240     BINARY_SUBSCR                   
                244     LOAD_ATTR                       11: get
                264     PUSH_NULL                       
                266     LOAD_CONST                      1: '__pyarmor_assert_13935__'
                268     LOAD_CONST                      12: 'kol_users_from'   # b'\x81\xe9\x17\x1f\x0c\xef\xad\xd7\t\xe92\xc6~\xe3\xf5'
                270     CALL                            1
                278     CALL                            1
                286     CALL                            1
                294     STORE_FAST                      11: _var_var_29
                296     LOAD_GLOBAL                     13: NULL + int
                306     LOAD_FAST                       4: data
                308     LOAD_CONST                      10: 'Settings'
                310     BINARY_SUBSCR                   
                314     LOAD_ATTR                       11: get
                334     PUSH_NULL                       
                336     LOAD_CONST                      1: '__pyarmor_assert_13935__'
                338     LOAD_CONST                      13: 'kol_users_to'   # b'\x81\xe9\x17\x1f\x0c\xef\xad\xd7\t\xe92\xd4c'
                340     CALL                            1
                348     CALL                            1
                356     CALL                            1
                364     STORE_FAST                      12: _var_var_30
                366     LOAD_GLOBAL                     13: NULL + int
                376     LOAD_FAST                       4: data
                378     LOAD_CONST                      10: 'Settings'
                380     BINARY_SUBSCR                   
                384     LOAD_ATTR                       11: get
                404     PUSH_NULL                       
                406     LOAD_CONST                      1: '__pyarmor_assert_13935__'
                408     LOAD_CONST                      14: 'kol_req_from'   # b'\x81\xe9\x17\x1f\x0c\xe8\xbb\xc3$\xfc\x1f\xcfa'
                410     CALL                            1
                418     CALL                            1
                426     CALL                            1
                434     STORE_FAST                      13: _var_var_31
                436     LOAD_GLOBAL                     13: NULL + int
                446     LOAD_FAST                       4: data
                448     LOAD_CONST                      10: 'Settings'
                450     BINARY_SUBSCR                   
                454     LOAD_ATTR                       11: get
                474     PUSH_NULL                       
                476     LOAD_CONST                      1: '__pyarmor_assert_13935__'
                478     LOAD_CONST                      15: 'kol_req_to'   # b'\x81\xe9\x17\x1f\x0c\xe8\xbb\xc3$\xee\x02'
                480     CALL                            1
                488     CALL                            1
                496     CALL                            1
                504     STORE_FAST                      14: _var_var_32
                506     LOAD_GLOBAL                     13: NULL + int
                516     LOAD_FAST                       4: data
                518     LOAD_CONST                      10: 'Settings'
                520     BINARY_SUBSCR                   
                524     LOAD_ATTR                       11: get
                544     PUSH_NULL                       
                546     LOAD_CONST                      1: '__pyarmor_assert_13935__'
                548     LOAD_CONST                      16: 'wait_from'   # b"\x81\xf5\x19\x1a'\xc5\xb8\xc0\x14\xf7"
                550     CALL                            1
                558     CALL                            1
                566     CALL                            1
                574     STORE_FAST                      15: _var_var_33
                576     LOAD_GLOBAL                     13: NULL + int
                586     LOAD_FAST                       4: data
                588     LOAD_CONST                      10: 'Settings'
                590     BINARY_SUBSCR                   
                594     LOAD_ATTR                       11: get
                614     LOAD_CONST                      17: 'wait_to'
                616     CALL                            1
                624     CALL                            1
                632     STORE_FAST                      16: _var_var_34
                634     LOAD_FAST                       4: data
                636     LOAD_CONST                      10: 'Settings'
                638     BINARY_SUBSCR                   
                642     LOAD_ATTR                       11: get
                662     PUSH_NULL                       
                664     LOAD_CONST                      1: '__pyarmor_assert_13935__'
                666     LOAD_CONST                      18: 'leave_chat'   # b'\x81\xee\x1d\x12%\xff\x81\xd1\x13\xfb\x19'
                668     CALL                            1
                676     CALL                            1
                684     STORE_FAST                      17: _var_var_35
                686     LOAD_GLOBAL                     13: NULL + int
                696     LOAD_FAST                       4: data
                698     LOAD_CONST                      10: 'Settings'
                700     BINARY_SUBSCR                   
                704     LOAD_ATTR                       11: get
                724     PUSH_NULL                       
                726     LOAD_CONST                      1: '__pyarmor_assert_13935__'
                728     LOAD_CONST                      19: 'max_flood_wait'   # b'\x81\xef\x19\x0b\x0c\xfc\xb2\xdd\x14\xfe2\xd7m\xe5\xec'
                730     CALL                            1
                738     CALL                            1
                746     CALL                            1
                754     STORE_FAST                      18: _var_var_36
                756     LOAD_FAST                       4: data
                758     LOAD_CONST                      10: 'Settings'
                760     BINARY_SUBSCR                   
                764     LOAD_ATTR                       11: get
                784     PUSH_NULL                       
                786     LOAD_CONST                      1: '__pyarmor_assert_13935__'
                788     LOAD_CONST                      20: 'force_mode'   # b'\x81\xe4\x17\x010\xff\x81\xdf\x14\xfe\x08'
                790     CALL                            1
                798     CALL                            1
                806     STORE_FAST                      19: _var_var_37
                808     LOAD_FAST                       4: data
                810     LOAD_CONST                      10: 'Settings'
                812     BINARY_SUBSCR                   
                816     LOAD_ATTR                       11: get
                836     PUSH_NULL                       
                838     LOAD_CONST                      1: '__pyarmor_assert_13935__'
                840     LOAD_CONST                      21: 'check_users'   # b'\x81\xe1\x10\x160\xf1\x81\xc7\x08\xff\x1f\xd3'
                842     CALL                            1
                850     CALL                            1
                858     STORE_FAST                      20: _var_var_38
                860     LOAD_FAST                       11: _var_var_29
                862     LOAD_FAST                       12: _var_var_30
                864     COMPARE_OP                      68 (>)
                868     POP_JUMP_IF_FALSE               2 (to 874)
                870     LOAD_FAST                       11: _var_var_29
                872     STORE_FAST                      12: _var_var_30
                874     LOAD_FAST                       13: _var_var_31
                876     LOAD_FAST                       14: _var_var_32
                878     COMPARE_OP                      68 (>)
                882     POP_JUMP_IF_FALSE               2 (to 888)
                884     LOAD_FAST                       14: _var_var_32
                886     STORE_FAST                      13: _var_var_31
                888     LOAD_FAST                       15: _var_var_33
                890     LOAD_FAST                       16: _var_var_34
                892     COMPARE_OP                      68 (>)
                896     POP_JUMP_IF_FALSE               2 (to 902)
                898     LOAD_FAST                       15: _var_var_33
                900     STORE_FAST                      16: _var_var_34
                902     LOAD_FAST                       6: stop_thread
                904     LOAD_ATTR                       15: is_set
                924     CALL                            0
                932     POP_JUMP_IF_FALSE               10 (to 954)
                934     LOAD_GLOBAL                     17: NULL + StopProgram
                944     CALL                            0
                952     RAISE_VARARGS                   1
                954     LOAD_GLOBAL                     19: NULL + tg_group
                964     LOAD_FAST                       2: config
                966     LOAD_FAST                       8: _var_var_27
                968     LOAD_FAST                       1: account
                970     LOAD_FAST                       9: _var_var_28
                972     LOAD_FAST                       18: _var_var_36
                974     LOAD_GLOBAL                     4: Lang
                984     LOAD_FAST                       6: stop_thread
                986     KW_NAMES                        22: ('config', 'client', 'account', 'group_link', 'max_flood_wait', 'lang', 'stop_thread')
                988     CALL                            7
                996     LOAD_ATTR                       21: go_to
                1016    CALL                            0
                1024    STORE_FAST                      21: _var_var_39
                1026    LOAD_FAST                       21: _var_var_39
                1028    PUSH_NULL                       
                1030    LOAD_CONST                      1: '__pyarmor_assert_13935__'
                1032    LOAD_CONST                      19: 'max_flood_wait'   # b'\x81\xef\x19\x0b\x0c\xfc\xb2\xdd\x14\xfe2\xd7m\xe5\xec'
                1034    CALL                            1
                1042    COMPARE_OP                      40 (==)
                1046    POP_JUMP_IF_FALSE               48 (to 1144)
                1048    LOAD_GLOBAL                     23: NULL + Logs
                1058    LOAD_ATTR                       24: PrintLog
                1078    LOAD_FAST                       2: config
                1080    LOAD_FAST                       1: account
                1082    LOAD_GLOBAL                     4: Lang
                1092    PUSH_NULL                       
                1094    LOAD_CONST                      1: '__pyarmor_assert_13935__'
                1096    LOAD_CONST                      23: 'invite_enter_to_group_flood'   # b'\x81\xeb\x16\x05:\xee\xbb\xed\x1e\xf4\x19\xc5~\xd3\xec\x8a0Z\xa9\xa8\xbf\xdbq\xca\t`\xacX'
                1098    CALL                            1
                1106    BINARY_SUBSCR                   
                1110    KW_NAMES                        24: ('config', 'account', 'message')
                1112    CALL                            3
                1120    POP_TOP                         
                1122    LOAD_GLOBAL                     27: NULL + StopAccount
                1132    LOAD_FAST                       1: account
                1134    CALL                            1
                1142    RAISE_VARARGS                   1
                1144    LOAD_GLOBAL                     29: NULL + entity
                1154    CALL                            0
                1162    LOAD_ATTR                       31: check
                1182    LOAD_FAST                       21: _var_var_39
                1184    CALL                            1
                1192    STORE_FAST                      22: _var_var_40
                1194    LOAD_FAST                       22: _var_var_40
                1196    POP_JUMP_IF_NONE                8 (to 1214)
                1198    LOAD_FAST                       22: _var_var_40
                1200    LOAD_CONST                      25: 'type'
                1202    BINARY_SUBSCR                   
                1206    LOAD_CONST                      26: 'chat'
                1208    COMPARE_OP                      40 (==)
                1212    POP_JUMP_IF_FALSE               48 (to 1310)
                1214    LOAD_GLOBAL                     23: NULL + Logs
                1224    LOAD_ATTR                       24: PrintLog
                1244    LOAD_FAST                       2: config
                1246    LOAD_FAST                       1: account
                1248    LOAD_GLOBAL                     4: Lang
                1258    PUSH_NULL                       
                1260    LOAD_CONST                      1: '__pyarmor_assert_13935__'
                1262    LOAD_CONST                      27: 'cloner_chats_error_type_group'   # b'\x81\xe1\x14\x1c=\xff\xac\xed\x18\xf2\x0c\xd4\x7f\xd3\xfd\x97\x1dR\xa9\x98\xbe\xd2^\xc9:h\xb1S\x15\xa1'
                1264    CALL                            1
                1272    BINARY_SUBSCR                   
                1276    KW_NAMES                        24: ('config', 'account', 'message')
                1278    CALL                            3
                1286    POP_TOP                         
                1288    LOAD_GLOBAL                     27: NULL + StopAccount
                1298    LOAD_FAST                       1: account
                1300    CALL                            1
                1308    RAISE_VARARGS                   1
                1310    LOAD_GLOBAL                     33: NULL + random
                1320    LOAD_ATTR                       34: randint
                1340    LOAD_FAST                       11: _var_var_29
                1342    LOAD_FAST                       12: _var_var_30
                1344    CALL                            2
                1352    STORE_FAST                      23: _var_var_41
                1354    LOAD_GLOBAL                     33: NULL + random
                1364    LOAD_ATTR                       34: randint
                1384    LOAD_FAST                       13: _var_var_31
                1386    LOAD_FAST                       14: _var_var_32
                1388    CALL                            2
                1396    STORE_FAST                      24: _var_var_42
                1398    LOAD_FAST                       6: stop_thread
                1400    LOAD_ATTR                       15: is_set
                1420    CALL                            0
                1428    POP_JUMP_IF_FALSE               10 (to 1450)
                1430    LOAD_GLOBAL                     17: NULL + StopProgram
                1440    CALL                            0
                1448    RAISE_VARARGS                   1
                1450    LOAD_GLOBAL                     37: NULL + invite
                1460    LOAD_CONST                      49: ()
                1462    BUILD_MAP                       0
                1464    LOAD_CONST                      28: 'config'
                1466    LOAD_FAST                       2: config
                1468    MAP_ADD                         1
                1470    LOAD_CONST                      29: 'client'
                1472    LOAD_FAST                       8: _var_var_27
                1474    MAP_ADD                         1
                1476    LOAD_CONST                      30: 'account'
                1478    LOAD_FAST                       1: account
                1480    MAP_ADD                         1
                1482    LOAD_CONST                      31: 'kol_users'
                1484    LOAD_FAST                       23: _var_var_41
                1486    MAP_ADD                         1
                1488    LOAD_CONST                      32: 'kol_req'
                1490    LOAD_FAST                       24: _var_var_42
                1492    MAP_ADD                         1
                1494    LOAD_CONST                      33: 'force_mode'
                1496    LOAD_FAST                       19: _var_var_37
                1498    MAP_ADD                         1
                1500    LOAD_CONST                      34: 'check_users'
                1502    LOAD_FAST                       20: _var_var_38
                1504    MAP_ADD                         1
                1506    LOAD_CONST                      35: 'group'
                1508    LOAD_FAST                       21: _var_var_39
                1510    MAP_ADD                         1
                1512    LOAD_CONST                      36: 'link'
                1514    LOAD_FAST                       9: _var_var_28
                1516    MAP_ADD                         1
                1518    LOAD_CONST                      11: 'file_db'
                1520    LOAD_FAST                       10: _var_var_13
                1522    MAP_ADD                         1
                1524    LOAD_CONST                      37: 'statistic'
                1526    LOAD_FAST                       5: statistic
                1528    MAP_ADD                         1
                1530    LOAD_CONST                      38: 'wait_from'
                1532    LOAD_FAST                       15: _var_var_33
                1534    MAP_ADD                         1
                1536    LOAD_CONST                      17: 'wait_to'
                1538    LOAD_FAST                       16: _var_var_34
                1540    MAP_ADD                         1
                1542    LOAD_CONST                      39: 'max_flood_wait'
                1544    LOAD_FAST                       18: _var_var_36
                1546    MAP_ADD                         1
                1548    LOAD_CONST                      40: 'lang'
                1550    LOAD_GLOBAL                     4: Lang
                1560    MAP_ADD                         1
                1562    LOAD_CONST                      41: 'stop_thread'
                1564    LOAD_FAST                       6: stop_thread
                1566    MAP_ADD                         1
                1568    CALL_FUNCTION_EX                1
                1570    LOAD_ATTR                       39: start
                1590    CALL                            0
                1598    POP_TOP                         
                1600    LOAD_FAST                       17: _var_var_35
                1602    POP_JUMP_IF_FALSE               111 (to 1826)
                1604    LOAD_GLOBAL                     23: NULL + Logs
                1614    LOAD_ATTR                       24: PrintLog
                1634    LOAD_FAST                       2: config
                1636    LOAD_FAST                       1: account
                1638    LOAD_GLOBAL                     4: Lang
                1648    PUSH_NULL                       
                1650    LOAD_CONST                      1: '__pyarmor_assert_13935__'
                1652    LOAD_CONST                      42: 'exit_groups_on_activated'   # b"\x81\xe7\x00\x1a'\xc5\xb9\xc0\x14\xef\x1d\xd3S\xe3\xf6\xba\x0e^\xaf\xae\xbc\xcaZ\xc9\x01"
                1654    CALL                            1
                1662    BINARY_SUBSCR                   
                1666    KW_NAMES                        24: ('config', 'account', 'message')
                1668    CALL                            3
                1676    POP_TOP                         
                1678    LOAD_GLOBAL                     23: NULL + Logs
                1688    LOAD_ATTR                       24: PrintLog
                1708    LOAD_FAST                       2: config
                1710    LOAD_FAST                       1: account
                1712    LOAD_GLOBAL                     4: Lang
                1722    PUSH_NULL                       
                1724    LOAD_CONST                      1: '__pyarmor_assert_13935__'
                1726    LOAD_CONST                      43: 'leaving_group'   # b'\x81\xee\x1d\x12%\xf3\xb0\xd5$\xfd\x1f\xcfy\xfc'
                1728    CALL                            1
                1736    BINARY_SUBSCR                   
                1740    KW_NAMES                        24: ('config', 'account', 'message')
                1742    CALL                            3
                1750    POP_TOP                         
                1752    LOAD_GLOBAL                     19: NULL + tg_group
                1762    LOAD_FAST                       2: config
                1764    LOAD_FAST                       8: _var_var_27
                1766    LOAD_FAST                       1: account
                1768    LOAD_FAST                       18: _var_var_36
                1770    LOAD_GLOBAL                     4: Lang
                1780    LOAD_FAST                       6: stop_thread
                1782    KW_NAMES                        44: ('config', 'client', 'account', 'max_flood_wait', 'lang', 'stop_thread')
                1784    CALL                            6
                1792    LOAD_ATTR                       41: go_out
                1812    LOAD_FAST                       21: _var_var_39
                1814    KW_NAMES                        45: ('entity',)
                1816    CALL                            1
                1824    POP_TOP                         
                1826    LOAD_GLOBAL                     51: NULL + Disconnect
                1836    LOAD_FAST_CHECK                 8: _var_var_27
                1838    CALL                            1
                1846    POP_TOP                         
                1848    LOAD_GLOBAL                     23: NULL + Logs
                1858    LOAD_ATTR                       24: PrintLog
                1878    LOAD_FAST                       2: config
                1880    LOAD_FAST                       1: account
                1882    LOAD_GLOBAL                     4: Lang
                1892    PUSH_NULL                       
                1894    LOAD_CONST                      1: '__pyarmor_assert_13935__'
                1896    LOAD_CONST                      46: 'work_account_completed'   # b'\x81\xf5\x17\x018\xc5\xbf\xd1\x18\xf5\x18\xcex\xd3\xfb\x8a\x02M\xb7\xa2\xbe\xceJ'
                1898    CALL                            1
                1906    BINARY_SUBSCR                   
                1910    KW_NAMES                        24: ('config', 'account', 'message')
                1912    CALL                            3
                1920    POP_TOP                         
                1922    LOAD_FAST                       1: account
                1924    LOAD_CONST                      48: 'done'
                1926    LOAD_CONST                      8: ('account', 'status')
                1928    BUILD_CONST_KEY_MAP             2
                1930    NOP                             
                1932    NOP                             
                1934    NOP                             
                1936    JUMP_FORWARD                    196 (to 2330)
                1938    CALL                            1
                1946    POP_TOP                         
                1948    RETURN_VALUE                    
                1950    PUSH_EXC_INFO                   
                1952    LOAD_GLOBAL                     16: StopProgram
                1962    CHECK_EXC_MATCH                 
                1964    POP_JUMP_IF_FALSE               3 (to 1972)
                1966    POP_TOP                         
                1968    POP_EXCEPT                      
                1970    JUMP_BACKWARD                   73 (to 1826)
                1972    LOAD_GLOBAL                     26: StopAccount
                1982    LOAD_GLOBAL                     42: PeerFlood
                1992    LOAD_GLOBAL                     44: MaxFlood
                2002    LOAD_GLOBAL                     46: BanAccount
                2012    BUILD_TUPLE                     4
                2014    CHECK_EXC_MATCH                 
                2016    POP_JUMP_IF_FALSE               98 (to 2214)
                2018    STORE_FAST                      25: _var_var_3
                2020    LOAD_GLOBAL                     23: NULL + Logs
                2030    LOAD_ATTR                       24: PrintLog
                2050    LOAD_FAST                       2: config
                2052    LOAD_FAST                       1: account
                2054    LOAD_GLOBAL                     4: Lang
                2064    PUSH_NULL                       
                2066    LOAD_CONST                      1: '__pyarmor_assert_13935__'
                2068    LOAD_CONST                      46: 'work_account_completed'   # b'\x81\xf5\x17\x018\xc5\xbf\xd1\x18\xf5\x18\xcex\xd3\xfb\x8a\x02M\xb7\xa2\xbe\xceJ'
                2070    CALL                            1
                2078    BINARY_SUBSCR                   
                2082    LOAD_FAST                       25: _var_var_3
                2084    LOAD_ATTR                       48: status
                2104    KW_NAMES                        47: ('config', 'account', 'message', 'end')
                2106    CALL                            4
                2114    POP_TOP                         
                2116    LOAD_GLOBAL                     51: NULL + Disconnect
                2126    LOAD_FAST_CHECK                 8: _var_var_27
                2128    CALL                            1
                2136    POP_TOP                         
                2138    JUMP_FORWARD                    7 (to 2154)
                2140    PUSH_EXC_INFO                   
                2142    POP_TOP                         
                2144    POP_EXCEPT                      
                2146    JUMP_FORWARD                    3 (to 2154)
                2148    COPY                            3
                2150    POP_EXCEPT                      
                2152    RERAISE                         1
                2154    LOAD_FAST                       25: _var_var_3
                2156    LOAD_ATTR                       52: result
                2176    SWAP                            2
                2178    POP_EXCEPT                      
                2180    LOAD_CONST                      0: None
                2182    STORE_FAST                      25: _var_var_3
                2184    DELETE_FAST                     25: _var_var_3
                2186    NOP                             
                2188    NOP                             
                2190    NOP                             
                2192    JUMP_FORWARD                    68 (to 2330)
                2194    CALL                            1
                2202    POP_TOP                         
                2204    RETURN_VALUE                    
                2206    LOAD_CONST                      0: None
                2208    STORE_FAST                      25: _var_var_3
                2210    DELETE_FAST                     25: _var_var_3
                2212    RERAISE                         1
                2214    LOAD_GLOBAL                     54: BaseException
                2224    CHECK_EXC_MATCH                 
                2226    POP_JUMP_IF_FALSE               26 (to 2280)
                2228    STORE_FAST                      25: _var_var_3
                2230    PUSH_NULL                       
                2232    LOAD_GLOBAL                     57: NULL + logging
                2242    LOAD_FAST                       25: _var_var_3
                2244    CALL                            1
                2252    CALL                            0
                2260    POP_TOP                         
                2262    POP_EXCEPT                      
                2264    LOAD_CONST                      0: None
                2266    STORE_FAST                      25: _var_var_3
                2268    DELETE_FAST                     25: _var_var_3
                2270    JUMP_BACKWARD                   223 (to 1826)
                2272    LOAD_CONST                      0: None
                2274    STORE_FAST                      25: _var_var_3
                2276    DELETE_FAST                     25: _var_var_3
                2278    RERAISE                         1
                2280    RERAISE                         0
                2282    COPY                            3
                2284    POP_EXCEPT                      
                2286    RERAISE                         1
                2288    PUSH_EXC_INFO                   
                2290    POP_TOP                         
                2292    POP_EXCEPT                      
                2294    JUMP_BACKWARD                   224 (to 1848)
                2296    COPY                            3
                2298    POP_EXCEPT                      
                2300    RERAISE                         1
                2302    PUSH_EXC_INFO                   
                2304    PUSH_NULL                       
                2306    LOAD_CONST                      9: '__pyarmor_exit_13937__'
                2308    NOP                             
                2310    LOAD_CONST                      3: b'<COAddr>\x07\x00\x00\x1a\xe4\x08\x00\x00\x00\x00\x00\x00\x00\x00\x00\x00\x00\x00\x00\x00'
                2312    CALL                            1
                2320    POP_TOP                         
                2322    RERAISE                         0
                2324    COPY                            3
                2326    POP_EXCEPT                      
                2328    RERAISE                         1
                2330    PUSH_NULL                       
                2332    LOAD_CONST                      9: '__pyarmor_exit_13937__'
                2334    LOAD_CONST                      3: b'<COAddr>\x07\x00\x00\x1a\xe4\x08\x00\x00\x00\x00\x00\x00\x00\x00\x00\x00\x00\x00\x00\x00'
                2336    BUILD_TUPLE                     1
                2338    CALL_FUNCTION_EX                0
                2340    POP_TOP                         
                2342    RETURN_VALUE                    
            [Exception Table]
                30 to 116 -> 1950 [0] 
                136 to 1826 -> 1950 [0] 
                1826 to 1848 -> 2288 [0] 
                1848 to 1930 -> 2302 [0] 
                1950 to 1968 -> 2282 [1] lasti
                1968 to 1972 -> 2302 [0] 
                1972 to 2020 -> 2282 [1] lasti
                2020 to 2116 -> 2206 [1] lasti
                2116 to 2138 -> 2140 [1] 
                2138 to 2140 -> 2206 [1] lasti
                2140 to 2144 -> 2148 [2] lasti
                2144 to 2176 -> 2206 [1] lasti
                2176 to 2178 -> 2282 [1] lasti
                2178 to 2186 -> 2302 [0] 
                2206 to 2230 -> 2282 [1] lasti
                2230 to 2262 -> 2272 [1] lasti
                2262 to 2272 -> 2302 [0] 
                2272 to 2282 -> 2282 [1] lasti
                2282 to 2288 -> 2302 [0] 
                2288 to 2292 -> 2296 [1] lasti
                2292 to 2302 -> 2302 [0] 
                2302 to 2324 -> 2324 [1] lasti
        [Code]
            File Name: <frozen program.modules.Invite_username_v2>
            Object Name: invite
            Qualified Name: invite
            Arg Count: 0
            Pos Only Arg Count: 0
            KW Only Arg Count: 0
            Stack Size: 5
            Flags: 0x20000000 (CO_PYARMOR_OBFUSCATED)
            [Names]
                '__name__'
                '__module__'
                '__qualname__'
                '__assert_armored__'
                '__init__'
                'prepare_users'
                'start'
            [Locals+Names]
            [Constants]
                'invite'
                '__pyarmor_assert_13938__'
                '__pyarmor_enter_13939__'
                b'<COAddr>\x07\x00\x00"*\x00\x00\x00\x00\x00\x00\x00\x00\x00\x00\x00\x00\x00\x00\x00'
                None
                [Code]
                    File Name: <frozen program.modules.Invite_username_v2>
                    Object Name: __init__
                    Qualified Name: invite.__init__
                    Arg Count: 17
                    Pos Only Arg Count: 0
                    KW Only Arg Count: 0
                    Stack Size: 5
                    Flags: 0x20000003 (CO_OPTIMIZED | CO_NEWLOCALS | CO_PYARMOR_OBFUSCATED)
                    [Names]
                        'config'
                        'client'
                        'account'
                        'kol_users'
                        'kol_req'
                        'force_mode'
                        'check_users'
                        'group_entity'
                        'group_link'
                        'file_db'
                        'statistic'
                        'wait_from'
                        'wait_to'
                        'max_flood_wait'
                        'lang'
                        'stop_thread'
                        'flood_wait'
                        'count_request'
                        'count_users'
                        'total_users'
                        'peer_flood'
                        'users'
                    [Locals+Names]
                        'self'
                        'config'
                        'client'
                        'account'
                        'kol_users'
                        'kol_req'
                        'force_mode'
                        'check_users'
                        'group'
                        'link'
                        'file_db'
                        'statistic'
                        'wait_from'
                        'wait_to'
                        'max_flood_wait'
                        'lang'
                        'stop_thread'
                        '__assert_armored__'
                    [Constants]
                        None
                        '__pyarmor_assert_13941__'
                        '__pyarmor_enter_13942__'
                        b'<COAddr>\x07\x00\x00\x1a\\\x01\x00\x00\x00\x00\x00\x00\x00\x00\x00\x00\x00\x00\x00\x00'
                        0
                        'peer_flood'   # b'\x81\xf2\x1d\x16!\xc5\xb8\xde\x14\xf5\t'
                        '__pyarmor_exit_13943__'
                    [Disassembly]
                        0       NOP                             
                        2       NOP                             
                        4       PUSH_NULL                       
                        6       LOAD_CONST                      2: '__pyarmor_enter_13942__'
                        8       LOAD_CONST                      3: b'<COAddr>\x07\x00\x00\x1a\\\x01\x00\x00\x00\x00\x00\x00\x00\x00\x00\x00\x00\x00\x00\x00'
                        10      BUILD_TUPLE                     1
                        12      CALL_FUNCTION_EX                0
                        14      POP_TOP                         
                        16      RESUME                          0
                        18      NOP                             
                        20      NOP                             
                        22      NOP                             
                        24      NOP                             
                        26      NOP                             
                        28      LOAD_FAST                       1: config
                        30      LOAD_FAST                       0: self
                        32      STORE_ATTR                      0: config
                        42      LOAD_FAST                       2: client
                        44      LOAD_FAST                       0: self
                        46      STORE_ATTR                      1: client
                        56      LOAD_FAST                       3: account
                        58      LOAD_FAST                       0: self
                        60      STORE_ATTR                      2: account
                        70      LOAD_FAST                       4: kol_users
                        72      LOAD_FAST                       0: self
                        74      STORE_ATTR                      3: kol_users
                        84      LOAD_FAST                       5: kol_req
                        86      LOAD_FAST                       0: self
                        88      STORE_ATTR                      4: kol_req
                        98      LOAD_FAST                       6: force_mode
                        100     LOAD_FAST                       0: self
                        102     STORE_ATTR                      5: force_mode
                        112     LOAD_FAST                       7: check_users
                        114     LOAD_FAST                       0: self
                        116     STORE_ATTR                      6: check_users
                        126     LOAD_FAST                       8: group
                        128     LOAD_FAST                       0: self
                        130     STORE_ATTR                      7: group_entity
                        140     LOAD_FAST                       9: link
                        142     LOAD_FAST                       0: self
                        144     STORE_ATTR                      8: group_link
                        154     LOAD_FAST                       10: file_db
                        156     LOAD_FAST                       0: self
                        158     STORE_ATTR                      9: file_db
                        168     LOAD_FAST                       11: statistic
                        170     LOAD_FAST                       0: self
                        172     STORE_ATTR                      10: statistic
                        182     LOAD_FAST                       12: wait_from
                        184     LOAD_FAST                       0: self
                        186     STORE_ATTR                      11: wait_from
                        196     LOAD_FAST                       13: wait_to
                        198     LOAD_FAST                       0: self
                        200     STORE_ATTR                      12: wait_to
                        210     LOAD_FAST                       14: max_flood_wait
                        212     LOAD_FAST                       0: self
                        214     STORE_ATTR                      13: max_flood_wait
                        224     LOAD_FAST                       15: lang
                        226     LOAD_FAST                       0: self
                        228     STORE_ATTR                      14: lang
                        238     LOAD_FAST                       16: stop_thread
                        240     LOAD_FAST                       0: self
                        242     STORE_ATTR                      15: stop_thread
                        252     LOAD_CONST                      4: 0
                        254     LOAD_FAST                       0: self
                        256     STORE_ATTR                      16: flood_wait
                        266     LOAD_CONST                      4: 0
                        268     LOAD_FAST                       0: self
                        270     STORE_ATTR                      17: count_request
                        280     LOAD_CONST                      4: 0
                        282     LOAD_FAST                       0: self
                        284     STORE_ATTR                      18: count_users
                        294     LOAD_CONST                      4: 0
                        296     LOAD_FAST                       0: self
                        298     STORE_ATTR                      19: total_users
                        308     LOAD_FAST                       1: config
                        310     PUSH_NULL                       
                        312     LOAD_CONST                      1: '__pyarmor_assert_13941__'
                        314     LOAD_CONST                      5: 'peer_flood'   # b'\x81\xf2\x1d\x16!\xc5\xb8\xde\x14\xf5\t'
                        316     CALL                            1
                        324     BINARY_SUBSCR                   
                        328     LOAD_FAST                       0: self
                        330     STORE_ATTR                      20: peer_flood
                        340     BUILD_LIST                      0
                        342     LOAD_FAST                       0: self
                        344     STORE_ATTR                      21: users
                        354     LOAD_CONST                      0: None
                        356     NOP                             
                        358     NOP                             
                        360     NOP                             
                        362     JUMP_FORWARD                    19 (to 402)
                        370     POP_TOP                         
                        372     RETURN_CONST                    0: None
                        374     PUSH_EXC_INFO                   
                        376     PUSH_NULL                       
                        378     LOAD_CONST                      6: '__pyarmor_exit_13943__'
                        380     NOP                             
                        382     LOAD_CONST                      3: b'<COAddr>\x07\x00\x00\x1a\\\x01\x00\x00\x00\x00\x00\x00\x00\x00\x00\x00\x00\x00\x00\x00'
                        384     CALL                            1
                        392     POP_TOP                         
                        394     RERAISE                         0
                        396     COPY                            3
                        398     POP_EXCEPT                      
                        400     RERAISE                         1
                        402     PUSH_NULL                       
                        404     LOAD_CONST                      6: '__pyarmor_exit_13943__'
                        406     LOAD_CONST                      3: b'<COAddr>\x07\x00\x00\x1a\\\x01\x00\x00\x00\x00\x00\x00\x00\x00\x00\x00\x00\x00\x00\x00'
                        408     BUILD_TUPLE                     1
                        410     CALL_FUNCTION_EX                0
                        412     POP_TOP                         
                        414     RETURN_VALUE                    
                    [Exception Table]
                        28 to 354 -> 374 [0] 
                        374 to 396 -> 396 [1] lasti
                [Code]
                    File Name: <frozen program.modules.Invite_username_v2>
                    Object Name: prepare_users
                    Qualified Name: invite.prepare_users
                    Arg Count: 1
                    Pos Only Arg Count: 0
                    KW Only Arg Count: 0
                    Stack Size: 17
                    Flags: 0x20000003 (CO_OPTIMIZED | CO_NEWLOCALS | CO_PYARMOR_OBFUSCATED)
                    [Names]
                        'users'
                        'Logs'
                        'PrintLog'
                        'config'
                        'account'
                        'lang'
                        'db_parsing'
                        'file_db'
                        'get_user_with_username'
                        'update_user_status'
                        'tg_entity'
                        'client'
                        'max_flood_wait'
                        'stop_thread'
                        'check'
                        'type'
                        'dict'
                        'check_users'
                        'functions'
                        'messages'
                        'GetCommonChatsRequest'
                        'types'
                        'InputUser'
                        'TelegramRequest'
                        'req'
                        'chats'
                        'id'
                        'group_entity'
                        'update_user'
                        'append'
                        'len'
                        'kol_users'
                        'kol_req'
                    [Locals+Names]
                        'self'
                        '__assert_armored__'
                        '_var_var_43'
                        '_var_var_44'
                        '_var_var_45'
                        '_var_var_46'
                        '_var_var_47'
                        '_var_var_48'
                    [Constants]
                        None
                        '__pyarmor_assert_13944__'
                        '__pyarmor_enter_13945__'
                        b'<COAddr>\x05\x00\x00\x1aF\x08\x00\x00\x00\x00\x00\x00\x00\x00\x00\x00\x00\x00\x00\x00'
                        'prepare_users'   # b'\x81\xf2\n\x16#\xfb\xac\xd7$\xef\x1e\xc5~\xff'
                        (
                            'config'
                            'account'
                            'message'
                        )
                        (
                            'path'
                        )
                        'invite'
                        (
                            'mode'
                        )
                        'no_users_to_invite'   # b'\x81\xec\x17,&\xe9\xbb\xc0\x08\xc5\x19\xcfS\xe5\xf6\x93\x06I\xbe'
                        5
                        'Taken'
                        (
                            'username'
                            'mode'
                            'status'
                        )
                        (
                            'config'
                            'client'
                            'account'
                            'username'
                            'max_flood_wait'
                            'lang'
                            'stop_thread'
                        )
                        'max_flood_wait'   # b'\x81\xef\x19\x0b\x0c\xfc\xb2\xdd\x14\xfe2\xd7m\xe5\xec'
                        'FloodWaitError'   # b'\x81\xc4\x14\x1c<\xfe\x89\xd3\x12\xee(\xd2~\xe3\xea'
                        'type'
                        'user'
                        'NotUser'
                        'info'
                        'id'
                        'access_hash'   # b'\x81\xe3\x1b\x106\xe9\xad\xed\x13\xfb\x1e\xc8'
                        (
                            'user_id'
                            'access_hash'
                        )
                        0
                        100
                        (
                            'user_id'
                            'max_id'
                            'limit'
                        )
                        'username'
                        'phone'
                        'first_name'   # b'\x81\xe4\x11\x01 \xee\x81\xdc\x1a\xf7\x08'
                        'last_name'   # b"\x81\xee\x19\x00'\xc5\xb0\xd3\x16\xff"
                        'gender'
                        'photo'
                        'premium'
                        'status'
                        'time'
                        'AlreadyInGroup'   # b'\x81\xc3\x14\x016\xfb\xba\xcb2\xf4*\xd2c\xf9\xe8'
                        (
                            'mode'
                            'user_id'
                            'phone'
                            'username'
                            'first_name'
                            'last_name'
                            'gender'
                            'photo'
                            'premium'
                            'status'
                            'time'
                            'invite_status'
                        )
                        'invite_alrady_in_group'   # b'\x81\xeb\x16\x05:\xee\xbb\xed\x1a\xf6\x1f\xc1h\xf5\xc7\x8c\x01b\xbc\xb5\xa5\xde^'
                        (
                            'config'
                            'account'
                            'message'
                            'param'
                        )
                        '__pyarmor_exit_13946__'
                    [Disassembly]
                        0       NOP                             
                        2       NOP                             
                        4       PUSH_NULL                       
                        6       LOAD_CONST                      2: '__pyarmor_enter_13945__'
                        8       LOAD_CONST                      3: b'<COAddr>\x05\x00\x00\x1aF\x08\x00\x00\x00\x00\x00\x00\x00\x00\x00\x00\x00\x00\x00\x00'
                        10      BUILD_TUPLE                     1
                        12      CALL_FUNCTION_EX                0
                        14      POP_TOP                         
                        16      RESUME                          0
                        18      NOP                             
                        20      NOP                             
                        22      NOP                             
                        24      NOP                             
                        26      NOP                             
                        28      BUILD_LIST                      0
                        30      LOAD_FAST                       0: self
                        32      STORE_ATTR                      0: users
                        42      BUILD_LIST                      0
                        44      STORE_FAST                      2: _var_var_43
                        46      LOAD_GLOBAL                     3: NULL + Logs
                        56      LOAD_ATTR                       4: PrintLog
                        76      LOAD_FAST                       0: self
                        78      LOAD_ATTR                       6: config
                        98      LOAD_FAST                       0: self
                        100     LOAD_ATTR                       8: account
                        120     LOAD_FAST                       0: self
                        122     LOAD_ATTR                       10: lang
                        142     PUSH_NULL                       
                        144     LOAD_CONST                      1: '__pyarmor_assert_13944__'
                        146     LOAD_CONST                      4: 'prepare_users'   # b'\x81\xf2\n\x16#\xfb\xac\xd7$\xef\x1e\xc5~\xff'
                        148     CALL                            1
                        156     BINARY_SUBSCR                   
                        160     KW_NAMES                        5: ('config', 'account', 'message')
                        162     CALL                            3
                        170     POP_TOP                         
                        172     NOP                             
                        174     LOAD_GLOBAL                     13: NULL + db_parsing
                        184     LOAD_FAST                       0: self
                        186     LOAD_ATTR                       14: file_db
                        206     KW_NAMES                        6: ('path',)
                        208     CALL                            1
                        216     LOAD_ATTR                       17: get_user_with_username
                        236     LOAD_CONST                      7: 'invite'
                        238     KW_NAMES                        8: ('mode',)
                        240     CALL                            1
                        248     STORE_FAST                      3: _var_var_44
                        250     LOAD_FAST                       3: _var_var_44
                        252     POP_JUMP_IF_TRUE                65 (to 384)
                        254     LOAD_GLOBAL                     3: NULL + Logs
                        264     LOAD_ATTR                       4: PrintLog
                        284     LOAD_FAST                       0: self
                        286     LOAD_ATTR                       6: config
                        306     LOAD_FAST                       0: self
                        308     LOAD_ATTR                       8: account
                        328     LOAD_FAST                       0: self
                        330     LOAD_ATTR                       10: lang
                        350     PUSH_NULL                       
                        352     LOAD_CONST                      1: '__pyarmor_assert_13944__'
                        354     LOAD_CONST                      9: 'no_users_to_invite'   # b'\x81\xec\x17,&\xe9\xbb\xc0\x08\xc5\x19\xcfS\xe5\xf6\x93\x06I\xbe'
                        356     CALL                            1
                        364     BINARY_SUBSCR                   
                        368     KW_NAMES                        5: ('config', 'account', 'message')
                        370     CALL                            3
                        378     POP_TOP                         
                        380     JUMP_FORWARD                    738 (to 1860)
                        384     LOAD_GLOBAL                     13: NULL + db_parsing
                        394     LOAD_FAST                       0: self
                        396     LOAD_ATTR                       14: file_db
                        416     KW_NAMES                        6: ('path',)
                        418     CALL                            1
                        426     LOAD_ATTR                       19: update_user_status
                        446     LOAD_FAST                       3: _var_var_44
                        448     LOAD_CONST                      10: 5
                        450     BINARY_SUBSCR                   
                        454     LOAD_CONST                      7: 'invite'
                        456     LOAD_CONST                      11: 'Taken'
                        458     KW_NAMES                        12: ('username', 'mode', 'status')
                        460     CALL                            3
                        468     POP_TOP                         
                        470     LOAD_GLOBAL                     21: NULL + tg_entity
                        480     LOAD_FAST                       0: self
                        482     LOAD_ATTR                       6: config
                        502     LOAD_FAST                       0: self
                        504     LOAD_ATTR                       22: client
                        524     LOAD_FAST                       0: self
                        526     LOAD_ATTR                       8: account
                        546     LOAD_FAST                       3: _var_var_44
                        548     LOAD_CONST                      10: 5
                        550     BINARY_SUBSCR                   
                        554     LOAD_FAST                       0: self
                        556     LOAD_ATTR                       24: max_flood_wait
                        576     LOAD_FAST                       0: self
                        578     LOAD_ATTR                       10: lang
                        598     LOAD_FAST                       0: self
                        600     LOAD_ATTR                       26: stop_thread
                        620     KW_NAMES                        13: ('config', 'client', 'account', 'username', 'max_flood_wait', 'lang', 'stop_thread')
                        622     CALL                            7
                        630     LOAD_ATTR                       29: check
                        650     CALL                            0
                        658     STORE_FAST                      4: _var_var_45
                        660     LOAD_FAST                       4: _var_var_45
                        662     PUSH_NULL                       
                        664     LOAD_CONST                      1: '__pyarmor_assert_13944__'
                        666     LOAD_CONST                      14: 'max_flood_wait'   # b'\x81\xef\x19\x0b\x0c\xfc\xb2\xdd\x14\xfe2\xd7m\xe5\xec'
                        668     CALL                            1
                        676     COMPARE_OP                      40 (==)
                        680     POP_JUMP_IF_FALSE               51 (to 784)
                        682     LOAD_GLOBAL                     13: NULL + db_parsing
                        692     LOAD_FAST                       0: self
                        694     LOAD_ATTR                       14: file_db
                        714     KW_NAMES                        6: ('path',)
                        716     CALL                            1
                        724     LOAD_ATTR                       19: update_user_status
                        744     LOAD_FAST                       3: _var_var_44
                        746     LOAD_CONST                      10: 5
                        748     BINARY_SUBSCR                   
                        752     LOAD_CONST                      7: 'invite'
                        754     PUSH_NULL                       
                        756     LOAD_CONST                      1: '__pyarmor_assert_13944__'
                        758     LOAD_CONST                      15: 'FloodWaitError'   # b'\x81\xc4\x14\x1c<\xfe\x89\xd3\x12\xee(\xd2~\xe3\xea'
                        760     CALL                            1
                        768     KW_NAMES                        12: ('username', 'mode', 'status')
                        770     CALL                            3
                        778     POP_TOP                         
                        780     JUMP_FORWARD                    538 (to 1860)
                        784     LOAD_GLOBAL                     31: NULL + type
                        794     LOAD_FAST                       4: _var_var_45
                        796     CALL                            1
                        804     LOAD_GLOBAL                     32: dict
                        814     COMPARE_OP                      55 (!=)
                        818     POP_JUMP_IF_TRUE                8 (to 836)
                        820     LOAD_FAST                       4: _var_var_45
                        822     LOAD_CONST                      16: 'type'
                        824     BINARY_SUBSCR                   
                        828     LOAD_CONST                      17: 'user'
                        830     COMPARE_OP                      55 (!=)
                        834     POP_JUMP_IF_FALSE               45 (to 926)
                        836     LOAD_GLOBAL                     13: NULL + db_parsing
                        846     LOAD_FAST                       0: self
                        848     LOAD_ATTR                       14: file_db
                        868     KW_NAMES                        6: ('path',)
                        870     CALL                            1
                        878     LOAD_ATTR                       19: update_user_status
                        898     LOAD_FAST                       3: _var_var_44
                        900     LOAD_CONST                      10: 5
                        902     BINARY_SUBSCR                   
                        906     LOAD_CONST                      7: 'invite'
                        908     LOAD_CONST                      18: 'NotUser'
                        910     KW_NAMES                        12: ('username', 'mode', 'status')
                        912     CALL                            3
                        920     POP_TOP                         
                        922     JUMP_BACKWARD                   377 (to 172)
                        926     LOAD_FAST                       0: self
                        928     LOAD_ATTR                       34: check_users
                        948     POP_JUMP_IF_FALSE               410 (to 1772)
                        952     LOAD_GLOBAL                     36: functions
                        962     LOAD_ATTR                       38: messages
                        982     LOAD_ATTR                       41: GetCommonChatsRequest
                        1002    LOAD_GLOBAL                     43: NULL + types
                        1012    LOAD_ATTR                       44: InputUser
                        1032    LOAD_FAST                       4: _var_var_45
                        1034    LOAD_CONST                      19: 'info'
                        1036    BINARY_SUBSCR                   
                        1040    LOAD_CONST                      20: 'id'
                        1042    BINARY_SUBSCR                   
                        1046    LOAD_FAST                       4: _var_var_45
                        1048    LOAD_CONST                      19: 'info'
                        1050    BINARY_SUBSCR                   
                        1054    PUSH_NULL                       
                        1056    LOAD_CONST                      1: '__pyarmor_assert_13944__'
                        1058    LOAD_CONST                      21: 'access_hash'   # b'\x81\xe3\x1b\x106\xe9\xad\xed\x13\xfb\x1e\xc8'
                        1060    CALL                            1
                        1068    BINARY_SUBSCR                   
                        1072    KW_NAMES                        22: ('user_id', 'access_hash')
                        1074    CALL                            2
                        1082    LOAD_CONST                      23: 0
                        1084    LOAD_CONST                      24: 100
                        1086    KW_NAMES                        25: ('user_id', 'max_id', 'limit')
                        1088    CALL                            3
                        1096    STORE_FAST                      5: _var_var_46
                        1098    LOAD_GLOBAL                     47: NULL + TelegramRequest
                        1108    LOAD_FAST                       0: self
                        1110    LOAD_ATTR                       22: client
                        1130    LOAD_FAST                       0: self
                        1132    LOAD_ATTR                       8: account
                        1152    LOAD_FAST                       0: self
                        1154    LOAD_ATTR                       24: max_flood_wait
                        1174    LOAD_FAST                       0: self
                        1176    LOAD_ATTR                       6: config
                        1196    LOAD_FAST                       0: self
                        1198    LOAD_ATTR                       10: lang
                        1218    LOAD_FAST                       0: self
                        1220    LOAD_ATTR                       26: stop_thread
                        1240    CALL                            6
                        1248    LOAD_ATTR                       49: req
                        1268    LOAD_FAST                       5: _var_var_46
                        1270    CALL                            1
                        1278    STORE_FAST                      6: _var_var_47
                        1280    LOAD_FAST                       6: _var_var_47
                        1282    LOAD_ATTR                       50: chats
                        1302    GET_ITER                        
                        1304    FOR_ITER                        231 (to 1768)
                        1308    STORE_FAST                      7: _var_var_48
                        1310    LOAD_FAST                       7: _var_var_48
                        1312    LOAD_ATTR                       52: id
                        1332    LOAD_FAST                       0: self
                        1334    LOAD_ATTR                       54: group_entity
                        1354    LOAD_ATTR                       52: id
                        1374    COMPARE_OP                      40 (==)
                        1378    POP_JUMP_IF_TRUE                1 (to 1382)
                        1380    JUMP_BACKWARD                   39 (to 1304)
                        1382    LOAD_GLOBAL                     13: NULL + db_parsing
                        1392    LOAD_FAST                       0: self
                        1394    LOAD_ATTR                       14: file_db
                        1414    CALL                            1
                        1422    LOAD_ATTR                       57: update_user
                        1442    LOAD_CONST                      26: 'username'
                        1444    LOAD_FAST                       4: _var_var_45
                        1446    LOAD_CONST                      19: 'info'
                        1448    BINARY_SUBSCR                   
                        1452    LOAD_CONST                      20: 'id'
                        1454    BINARY_SUBSCR                   
                        1458    LOAD_FAST                       4: _var_var_45
                        1460    LOAD_CONST                      19: 'info'
                        1462    BINARY_SUBSCR                   
                        1466    LOAD_CONST                      27: 'phone'
                        1468    BINARY_SUBSCR                   
                        1472    LOAD_FAST                       4: _var_var_45
                        1474    LOAD_CONST                      19: 'info'
                        1476    BINARY_SUBSCR                   
                        1480    LOAD_CONST                      26: 'username'
                        1482    BINARY_SUBSCR                   
                        1486    LOAD_FAST                       4: _var_var_45
                        1488    LOAD_CONST                      19: 'info'
                        1490    BINARY_SUBSCR                   
                        1494    PUSH_NULL                       
                        1496    LOAD_CONST                      1: '__pyarmor_assert_13944__'
                        1498    LOAD_CONST                      28: 'first_name'   # b'\x81\xe4\x11\x01 \xee\x81\xdc\x1a\xf7\x08'
                        1500    CALL                            1
                        1508    BINARY_SUBSCR                   
                        1512    LOAD_FAST                       4: _var_var_45
                        1514    LOAD_CONST                      19: 'info'
                        1516    BINARY_SUBSCR                   
                        1520    PUSH_NULL                       
                        1522    LOAD_CONST                      1: '__pyarmor_assert_13944__'
                        1524    LOAD_CONST                      29: 'last_name'   # b"\x81\xee\x19\x00'\xc5\xb0\xd3\x16\xff"
                        1526    CALL                            1
                        1534    BINARY_SUBSCR                   
                        1538    LOAD_FAST                       4: _var_var_45
                        1540    LOAD_CONST                      19: 'info'
                        1542    BINARY_SUBSCR                   
                        1546    LOAD_CONST                      30: 'gender'
                        1548    BINARY_SUBSCR                   
                        1552    LOAD_FAST                       4: _var_var_45
                        1554    LOAD_CONST                      19: 'info'
                        1556    BINARY_SUBSCR                   
                        1560    LOAD_CONST                      31: 'photo'
                        1562    BINARY_SUBSCR                   
                        1566    LOAD_FAST                       4: _var_var_45
                        1568    LOAD_CONST                      19: 'info'
                        1570    BINARY_SUBSCR                   
                        1574    LOAD_CONST                      32: 'premium'
                        1576    BINARY_SUBSCR                   
                        1580    LOAD_FAST                       4: _var_var_45
                        1582    LOAD_CONST                      19: 'info'
                        1584    BINARY_SUBSCR                   
                        1588    LOAD_CONST                      33: 'status'
                        1590    BINARY_SUBSCR                   
                        1594    LOAD_FAST                       4: _var_var_45
                        1596    LOAD_CONST                      19: 'info'
                        1598    BINARY_SUBSCR                   
                        1602    LOAD_CONST                      34: 'time'
                        1604    BINARY_SUBSCR                   
                        1608    PUSH_NULL                       
                        1610    LOAD_CONST                      1: '__pyarmor_assert_13944__'
                        1612    LOAD_CONST                      35: 'AlreadyInGroup'   # b'\x81\xc3\x14\x016\xfb\xba\xcb2\xf4*\xd2c\xf9\xe8'
                        1614    CALL                            1
                        1622    KW_NAMES                        36: ('mode', 'user_id', 'phone', 'username', 'first_name', 'last_name', 'gender', 'photo', 'premium', 'status', 'time', 'invite_status')
                        1624    CALL                            12
                        1632    POP_TOP                         
                        1634    LOAD_GLOBAL                     3: NULL + Logs
                        1644    LOAD_ATTR                       4: PrintLog
                        1664    LOAD_FAST                       0: self
                        1666    LOAD_ATTR                       6: config
                        1686    LOAD_FAST                       0: self
                        1688    LOAD_ATTR                       8: account
                        1708    LOAD_FAST                       0: self
                        1710    LOAD_ATTR                       10: lang
                        1730    PUSH_NULL                       
                        1732    LOAD_CONST                      1: '__pyarmor_assert_13944__'
                        1734    LOAD_CONST                      37: 'invite_alrady_in_group'   # b'\x81\xeb\x16\x05:\xee\xbb\xed\x1a\xf6\x1f\xc1h\xf5\xc7\x8c\x01b\xbc\xb5\xa5\xde^'
                        1736    CALL                            1
                        1744    BINARY_SUBSCR                   
                        1748    LOAD_FAST                       3: _var_var_44
                        1750    LOAD_CONST                      10: 5
                        1752    BINARY_SUBSCR                   
                        1756    KW_NAMES                        38: ('config', 'account', 'message', 'param')
                        1758    CALL                            4
                        1766    POP_TOP                         
                        1768    JUMP_BACKWARD                   233 (to 1304)
                        1770    END_FOR                         
                        1772    LOAD_FAST                       2: _var_var_43
                        1774    LOAD_ATTR                       59: append
                        1794    LOAD_FAST                       4: _var_var_45
                        1796    CALL                            1
                        1804    POP_TOP                         
                        1806    LOAD_GLOBAL                     61: NULL + len
                        1816    LOAD_FAST                       2: _var_var_43
                        1818    CALL                            1
                        1826    LOAD_FAST                       0: self
                        1828    LOAD_ATTR                       62: kol_users
                        1848    COMPARE_OP                      92 (>=)
                        1852    POP_JUMP_IF_FALSE               1 (to 1856)
                        1854    JUMP_FORWARD                    2 (to 1860)
                        1856    JUMP_BACKWARD                   843 (to 174)
                        1860    LOAD_GLOBAL                     61: NULL + len
                        1870    LOAD_FAST                       2: _var_var_43
                        1872    CALL                            1
                        1880    LOAD_FAST                       0: self
                        1882    LOAD_ATTR                       64: kol_req
                        1902    COMPARE_OP                      68 (>)
                        1906    POP_JUMP_IF_FALSE               81 (to 2070)
                        1908    LOAD_FAST                       0: self
                        1910    LOAD_ATTR                       0: users
                        1930    LOAD_ATTR                       59: append
                        1950    LOAD_FAST                       2: _var_var_43
                        1952    LOAD_CONST                      0: None
                        1954    LOAD_FAST                       0: self
                        1956    LOAD_ATTR                       64: kol_req
                        1976    BINARY_SLICE                    
                        1978    CALL                            1
                        1986    POP_TOP                         
                        1988    LOAD_FAST                       0: self
                        1990    LOAD_ATTR                       0: users
                        2010    LOAD_ATTR                       59: append
                        2030    LOAD_FAST                       2: _var_var_43
                        2032    LOAD_FAST                       0: self
                        2034    LOAD_ATTR                       64: kol_req
                        2054    LOAD_CONST                      0: None
                        2056    BINARY_SLICE                    
                        2058    CALL                            1
                        2066    POP_TOP                         
                        2068    JUMP_FORWARD                    27 (to 2124)
                        2070    LOAD_FAST                       0: self
                        2072    LOAD_ATTR                       0: users
                        2092    LOAD_ATTR                       59: append
                        2112    LOAD_FAST                       2: _var_var_43
                        2114    CALL                            1
                        2122    POP_TOP                         
                        2124    LOAD_CONST                      0: None
                        2126    NOP                             
                        2128    NOP                             
                        2130    NOP                             
                        2132    JUMP_FORWARD                    19 (to 2172)
                        2140    POP_TOP                         
                        2142    RETURN_CONST                    0: None
                        2144    PUSH_EXC_INFO                   
                        2146    PUSH_NULL                       
                        2148    LOAD_CONST                      39: '__pyarmor_exit_13946__'
                        2150    NOP                             
                        2152    LOAD_CONST                      3: b'<COAddr>\x05\x00\x00\x1aF\x08\x00\x00\x00\x00\x00\x00\x00\x00\x00\x00\x00\x00\x00\x00'
                        2154    CALL                            1
                        2162    POP_TOP                         
                        2164    RERAISE                         0
                        2166    COPY                            3
                        2168    POP_EXCEPT                      
                        2170    RERAISE                         1
                        2172    PUSH_NULL                       
                        2174    LOAD_CONST                      39: '__pyarmor_exit_13946__'
                        2176    LOAD_CONST                      3: b'<COAddr>\x05\x00\x00\x1aF\x08\x00\x00\x00\x00\x00\x00\x00\x00\x00\x00\x00\x00\x00\x00'
                        2178    BUILD_TUPLE                     1
                        2180    CALL_FUNCTION_EX                0
                        2182    POP_TOP                         
                        2184    RETURN_VALUE                    
                    [Exception Table]
                        28 to 1380 -> 2144 [0] 
                        1382 to 2124 -> 2144 [0] 
                        2144 to 2166 -> 2166 [1] lasti
                [Code]
                    File Name: <frozen program.modules.Invite_username_v2>
                    Object Name: start
                    Qualified Name: invite.start
                    Arg Count: 1
                    Pos Only Arg Count: 0
                    KW Only Arg Count: 0
                    Stack Size: 16
                    Flags: 0x20000003 (CO_OPTIMIZED | CO_NEWLOCALS | CO_PYARMOR_OBFUSCATED)
                    [Names]
                        'prepare_users'
                        'users'
                        'append'
                        'types'
                        'InputUser'
                        'DelayOnline'
                        'account'
                        'client'
                        'wait_from'
                        'wait_to'
                        'stop_thread'
                        'count_request'
                        'tdlib'
                        'functions'
                        'channels'
                        'InviteToChannel_tdlib_Request'
                        'group_entity'
                        'InviteToChannelRequest'
                        'TelegramRequest'
                        'max_flood_wait'
                        'config'
                        'lang'
                        'req'
                        'StopProgram'
                        'Exception'
                        'type'
                        '__name__'
                        'Logs'
                        'PrintLog'
                        'messages'
                        'GetCommonChatsRequest'
                        'chats'
                        'id'
                        'count_users'
                        'total_users'
                        'db_parsing'
                        'file_db'
                        'update_user'
                        'db_statistic'
                        'statistic'
                        'insert'
                        'group_link'
                        'force_mode'
                        'kol_users'
                        'start'
                    [Locals+Names]
                        'self'
                        '__assert_armored__'
                        '_var_var_43'
                        '_var_var_49'
                        '_var_var_50'
                        '_var_var_45'
                        '_var_var_46'
                        '_var_var_3'
                        '_var_var_47'
                        '_var_var_48'
                        '_var_var_51'
                    [Constants]
                        None
                        '__pyarmor_assert_13947__'
                        '__pyarmor_enter_13948__'
                        b'<COAddr>\x07\x00\x00\x1aV\x0b\x00\x00\x00\x00\x00\x00\x00\x00\x00\x00\x00\x00\x00\x00'
                        'info'
                        'id'
                        'access_hash'   # b'\x81\xe3\x1b\x106\xe9\xad\xed\x13\xfb\x1e\xc8'
                        (
                            'user_id'
                            'access_hash'
                        )
                        1
                        (
                            'channel'
                            'users'
                        )
                        'Status:'
                        (
                            'config'
                            'account'
                            'message'
                            'param'
                        )
                        'NotInGroup'   # b'\x81\xcc\x17\x07\x1a\xf4\x99\xc0\x14\xef\x1d'
                        0
                        100
                        (
                            'user_id'
                            'max_id'
                            'limit'
                        )
                        'Done'
                        'updating_user_database'   # b'\x81\xf7\x08\x172\xee\xb7\xdc\x1c\xc5\x18\xd3i\xfe\xc7\x81\x0eI\xba\xa5\xab\xd8K'
                        'username'
                        'phone'
                        'first_name'   # b'\x81\xe4\x11\x01 \xee\x81\xdc\x1a\xf7\x08'
                        'last_name'   # b"\x81\xee\x19\x00'\xc5\xb0\xd3\x16\xff"
                        'gender'
                        'photo'
                        'premium'
                        'status'
                        'time'
                        (
                            'mode'
                            'user_id'
                            'phone'
                            'username'
                            'first_name'
                            'last_name'
                            'gender'
                            'photo'
                            'premium'
                            'status'
                            'time'
                            'invite_status'
                        )
                        (
                            'account'
                            'group_id'
                            'group_link'
                            'user_id'
                            'username'
                            'first_name'
                            'last_name'
                            'invite_status'
                        )
                        'invite_force_mode_activated'   # b'\x81\xeb\x16\x05:\xee\xbb\xed\x1d\xf5\x1f\xc3i\xd3\xf5\x8a\x0bX\x84\xa6\xa9\xdfG\xda\x04{\xa6X'
                        (
                            'config'
                            'account'
                            'message'
                        )
                        'invite_force_mode_done'   # b'\x81\xeb\x16\x05:\xee\xbb\xed\x1d\xf5\x1f\xc3i\xd3\xf5\x8a\x0bX\x84\xa3\xa5\xc5K'
                        'invite_force_mode_ost'   # b'\x81\xeb\x16\x05:\xee\xbb\xed\x1d\xf5\x1f\xc3i\xd3\xf5\x8a\x0bX\x84\xa8\xb9\xdf'
                        (
                            'config'
                            'account'
                            'message'
                            'end'
                        )
                        '__pyarmor_exit_13949__'
                        'completed_invitations'   # b'\x81\xe1\x17\x1e#\xf6\xbb\xc6\x1e\xfe2\xc9b\xfa\xf1\x91\x0eI\xb2\xa8\xa4\xd8'
                    [Disassembly]
                        0       NOP                             
                        2       NOP                             
                        4       PUSH_NULL                       
                        6       LOAD_CONST                      2: '__pyarmor_enter_13948__'
                        8       LOAD_CONST                      3: b'<COAddr>\x07\x00\x00\x1aV\x0b\x00\x00\x00\x00\x00\x00\x00\x00\x00\x00\x00\x00\x00\x00'
                        10      BUILD_TUPLE                     1
                        12      CALL_FUNCTION_EX                0
                        14      POP_TOP                         
                        16      RESUME                          0
                        18      NOP                             
                        20      NOP                             
                        22      NOP                             
                        24      NOP                             
                        26      NOP                             
                        28      LOAD_FAST                       0: self
                        30      LOAD_ATTR                       1: prepare_users
                        50      CALL                            0
                        58      POP_TOP                         
                        60      LOAD_FAST                       0: self
                        62      LOAD_ATTR                       2: users
                        82      GET_ITER                        
                        84      FOR_ITER                        943 (to 1974)
                        90      STORE_FAST                      2: _var_var_43
                        92      BUILD_LIST                      0
                        94      STORE_FAST                      3: _var_var_49
                        96      LOAD_CONST                      0: None
                        98      STORE_FAST                      4: _var_var_50
                        100     LOAD_FAST                       2: _var_var_43
                        102     GET_ITER                        
                        104     FOR_ITER                        58 (to 222)
                        108     STORE_FAST                      5: _var_var_45
                        110     LOAD_FAST                       3: _var_var_49
                        112     LOAD_ATTR                       5: append
                        132     LOAD_GLOBAL                     7: NULL + types
                        142     LOAD_ATTR                       8: InputUser
                        162     LOAD_FAST                       5: _var_var_45
                        164     LOAD_CONST                      4: 'info'
                        166     BINARY_SUBSCR                   
                        170     LOAD_CONST                      5: 'id'
                        172     BINARY_SUBSCR                   
                        176     LOAD_FAST                       5: _var_var_45
                        178     LOAD_CONST                      4: 'info'
                        180     BINARY_SUBSCR                   
                        184     PUSH_NULL                       
                        186     LOAD_CONST                      1: '__pyarmor_assert_13947__'
                        188     LOAD_CONST                      6: 'access_hash'   # b'\x81\xe3\x1b\x106\xe9\xad\xed\x13\xfb\x1e\xc8'
                        190     CALL                            1
                        198     BINARY_SUBSCR                   
                        202     KW_NAMES                        7: ('user_id', 'access_hash')
                        204     CALL                            2
                        212     CALL                            1
                        220     POP_TOP                         
                        222     JUMP_BACKWARD                   60 (to 104)
                        224     END_FOR                         
                        226     LOAD_GLOBAL                     11: NULL + DelayOnline
                        236     LOAD_FAST                       0: self
                        238     LOAD_ATTR                       12: account
                        258     LOAD_FAST                       0: self
                        260     LOAD_ATTR                       14: client
                        280     LOAD_FAST                       0: self
                        282     LOAD_ATTR                       16: wait_from
                        302     LOAD_FAST                       0: self
                        304     LOAD_ATTR                       18: wait_to
                        324     LOAD_FAST                       0: self
                        326     LOAD_ATTR                       20: stop_thread
                        346     CALL                            5
                        354     POP_TOP                         
                        356     NOP                             
                        358     LOAD_FAST                       0: self
                        360     COPY                            1
                        362     LOAD_ATTR                       22: count_request
                        382     LOAD_CONST                      8: 1
                        384     BINARY_OP                       13 (+=)
                        388     SWAP                            2
                        390     STORE_ATTR                      11: count_request
                        400     LOAD_FAST                       0: self
                        402     LOAD_ATTR                       14: client
                        422     LOAD_ATTR                       24: tdlib
                        442     POP_JUMP_IF_FALSE               44 (to 532)
                        444     LOAD_GLOBAL                     26: functions
                        454     LOAD_ATTR                       28: channels
                        474     LOAD_ATTR                       31: InviteToChannel_tdlib_Request
                        494     LOAD_FAST                       0: self
                        496     LOAD_ATTR                       32: group_entity
                        516     LOAD_FAST                       3: _var_var_49
                        518     KW_NAMES                        9: ('channel', 'users')
                        520     CALL                            2
                        528     STORE_FAST                      6: _var_var_46
                        530     JUMP_FORWARD                    43 (to 618)
                        532     LOAD_GLOBAL                     26: functions
                        542     LOAD_ATTR                       28: channels
                        562     LOAD_ATTR                       35: InviteToChannelRequest
                        582     LOAD_FAST                       0: self
                        584     LOAD_ATTR                       32: group_entity
                        604     LOAD_FAST                       3: _var_var_49
                        606     KW_NAMES                        9: ('channel', 'users')
                        608     CALL                            2
                        616     STORE_FAST                      6: _var_var_46
                        618     LOAD_GLOBAL                     37: NULL + TelegramRequest
                        628     LOAD_FAST                       0: self
                        630     LOAD_ATTR                       14: client
                        650     LOAD_FAST                       0: self
                        652     LOAD_ATTR                       12: account
                        672     LOAD_FAST                       0: self
                        674     LOAD_ATTR                       38: max_flood_wait
                        694     LOAD_FAST                       0: self
                        696     LOAD_ATTR                       40: config
                        716     LOAD_FAST                       0: self
                        718     LOAD_ATTR                       42: lang
                        738     LOAD_FAST                       0: self
                        740     LOAD_ATTR                       20: stop_thread
                        760     CALL                            6
                        768     LOAD_ATTR                       45: req
                        788     LOAD_FAST                       6: _var_var_46
                        790     CALL                            1
                        798     POP_TOP                         
                        800     LOAD_FAST                       2: _var_var_43
                        802     GET_ITER                        
                        804     FOR_ITER                        580 (to 1968)
                        810     STORE_FAST                      5: _var_var_45
                        812     LOAD_FAST                       4: _var_var_50
                        814     POP_JUMP_IF_NOT_NONE            8 (to 832)
                        816     PUSH_NULL                       
                        818     LOAD_CONST                      1: '__pyarmor_assert_13947__'
                        820     LOAD_CONST                      12: 'NotInGroup'   # b'\x81\xcc\x17\x07\x1a\xf4\x99\xc0\x14\xef\x1d'
                        822     CALL                            1
                        830     STORE_FAST                      4: _var_var_50
                        832     LOAD_GLOBAL                     26: functions
                        842     LOAD_ATTR                       58: messages
                        862     LOAD_ATTR                       61: GetCommonChatsRequest
                        882     LOAD_GLOBAL                     7: NULL + types
                        892     LOAD_ATTR                       8: InputUser
                        912     LOAD_FAST                       5: _var_var_45
                        914     LOAD_CONST                      4: 'info'
                        916     BINARY_SUBSCR                   
                        920     LOAD_CONST                      5: 'id'
                        922     BINARY_SUBSCR                   
                        926     LOAD_FAST                       5: _var_var_45
                        928     LOAD_CONST                      4: 'info'
                        930     BINARY_SUBSCR                   
                        934     PUSH_NULL                       
                        936     LOAD_CONST                      1: '__pyarmor_assert_13947__'
                        938     LOAD_CONST                      6: 'access_hash'   # b'\x81\xe3\x1b\x106\xe9\xad\xed\x13\xfb\x1e\xc8'
                        940     CALL                            1
                        948     BINARY_SUBSCR                   
                        952     KW_NAMES                        7: ('user_id', 'access_hash')
                        954     CALL                            2
                        962     LOAD_CONST                      13: 0
                        964     LOAD_CONST                      14: 100
                        966     KW_NAMES                        15: ('user_id', 'max_id', 'limit')
                        968     CALL                            3
                        976     STORE_FAST                      6: _var_var_46
                        978     LOAD_GLOBAL                     37: NULL + TelegramRequest
                        988     LOAD_FAST                       0: self
                        990     LOAD_ATTR                       14: client
                        1010    LOAD_FAST                       0: self
                        1012    LOAD_ATTR                       12: account
                        1032    LOAD_FAST                       0: self
                        1034    LOAD_ATTR                       38: max_flood_wait
                        1054    LOAD_FAST                       0: self
                        1056    LOAD_ATTR                       40: config
                        1076    LOAD_FAST                       0: self
                        1078    LOAD_ATTR                       42: lang
                        1098    LOAD_FAST                       0: self
                        1100    LOAD_ATTR                       20: stop_thread
                        1120    CALL                            6
                        1128    LOAD_ATTR                       45: req
                        1148    LOAD_FAST                       6: _var_var_46
                        1150    CALL                            1
                        1158    STORE_FAST                      8: _var_var_47
                        1160    LOAD_FAST                       8: _var_var_47
                        1162    LOAD_ATTR                       62: chats
                        1182    GET_ITER                        
                        1184    FOR_ITER                        82 (to 1350)
                        1188    STORE_FAST                      9: _var_var_48
                        1190    LOAD_FAST                       9: _var_var_48
                        1192    LOAD_ATTR                       64: id
                        1212    LOAD_FAST                       0: self
                        1214    LOAD_ATTR                       32: group_entity
                        1234    LOAD_ATTR                       64: id
                        1254    COMPARE_OP                      40 (==)
                        1258    POP_JUMP_IF_TRUE                1 (to 1262)
                        1260    JUMP_BACKWARD                   39 (to 1184)
                        1262    LOAD_CONST                      16: 'Done'
                        1264    STORE_FAST                      4: _var_var_50
                        1266    LOAD_FAST                       0: self
                        1268    COPY                            1
                        1270    LOAD_ATTR                       66: count_users
                        1290    LOAD_CONST                      8: 1
                        1292    BINARY_OP                       13 (+=)
                        1296    SWAP                            2
                        1298    STORE_ATTR                      33: count_users
                        1308    LOAD_FAST                       0: self
                        1310    COPY                            1
                        1312    LOAD_ATTR                       68: total_users
                        1332    LOAD_CONST                      8: 1
                        1334    BINARY_OP                       13 (+=)
                        1338    SWAP                            2
                        1340    STORE_ATTR                      34: total_users
                        1350    JUMP_BACKWARD                   84 (to 1184)
                        1352    END_FOR                         
                        1354    LOAD_GLOBAL                     55: NULL + Logs
                        1364    LOAD_ATTR                       56: PrintLog
                        1384    LOAD_GLOBAL                     40: config
                        1394    LOAD_FAST                       0: self
                        1396    LOAD_ATTR                       12: account
                        1416    LOAD_FAST                       0: self
                        1418    LOAD_ATTR                       42: lang
                        1438    PUSH_NULL                       
                        1440    LOAD_CONST                      1: '__pyarmor_assert_13947__'
                        1442    LOAD_CONST                      17: 'updating_user_database'   # b'\x81\xf7\x08\x172\xee\xb7\xdc\x1c\xc5\x18\xd3i\xfe\xc7\x81\x0eI\xba\xa5\xab\xd8K'
                        1444    CALL                            1
                        1452    BINARY_SUBSCR                   
                        1456    LOAD_FAST                       5: _var_var_45
                        1458    LOAD_CONST                      4: 'info'
                        1460    BINARY_SUBSCR                   
                        1464    LOAD_CONST                      18: 'username'
                        1466    BINARY_SUBSCR                   
                        1470    KW_NAMES                        11: ('config', 'account', 'message', 'param')
                        1472    CALL                            4
                        1480    POP_TOP                         
                        1482    LOAD_GLOBAL                     71: NULL + db_parsing
                        1492    LOAD_FAST                       0: self
                        1494    LOAD_ATTR                       72: file_db
                        1514    CALL                            1
                        1522    LOAD_ATTR                       75: update_user
                        1542    LOAD_CONST                      18: 'username'
                        1544    LOAD_FAST                       5: _var_var_45
                        1546    LOAD_CONST                      4: 'info'
                        1548    BINARY_SUBSCR                   
                        1552    LOAD_CONST                      5: 'id'
                        1554    BINARY_SUBSCR                   
                        1558    LOAD_FAST                       5: _var_var_45
                        1560    LOAD_CONST                      4: 'info'
                        1562    BINARY_SUBSCR                   
                        1566    LOAD_CONST                      19: 'phone'
                        1568    BINARY_SUBSCR                   
                        1572    LOAD_FAST                       5: _var_var_45
                        1574    LOAD_CONST                      4: 'info'
                        1576    BINARY_SUBSCR                   
                        1580    LOAD_CONST                      18: 'username'
                        1582    BINARY_SUBSCR                   
                        1586    LOAD_FAST                       5: _var_var_45
                        1588    LOAD_CONST                      4: 'info'
                        1590    BINARY_SUBSCR                   
                        1594    PUSH_NULL                       
                        1596    LOAD_CONST                      1: '__pyarmor_assert_13947__'
                        1598    LOAD_CONST                      20: 'first_name'   # b'\x81\xe4\x11\x01 \xee\x81\xdc\x1a\xf7\x08'
                        1600    CALL                            1
                        1608    BINARY_SUBSCR                   
                        1612    LOAD_FAST                       5: _var_var_45
                        1614    LOAD_CONST                      4: 'info'
                        1616    BINARY_SUBSCR                   
                        1620    PUSH_NULL                       
                        1622    LOAD_CONST                      1: '__pyarmor_assert_13947__'
                        1624    LOAD_CONST                      21: 'last_name'   # b"\x81\xee\x19\x00'\xc5\xb0\xd3\x16\xff"
                        1626    CALL                            1
                        1634    BINARY_SUBSCR                   
                        1638    LOAD_FAST                       5: _var_var_45
                        1640    LOAD_CONST                      4: 'info'
                        1642    BINARY_SUBSCR                   
                        1646    LOAD_CONST                      22: 'gender'
                        1648    BINARY_SUBSCR                   
                        1652    LOAD_FAST                       5: _var_var_45
                        1654    LOAD_CONST                      4: 'info'
                        1656    BINARY_SUBSCR                   
                        1660    LOAD_CONST                      23: 'photo'
                        1662    BINARY_SUBSCR                   
                        1666    LOAD_FAST                       5: _var_var_45
                        1668    LOAD_CONST                      4: 'info'
                        1670    BINARY_SUBSCR                   
                        1674    LOAD_CONST                      24: 'premium'
                        1676    BINARY_SUBSCR                   
                        1680    LOAD_FAST                       5: _var_var_45
                        1682    LOAD_CONST                      4: 'info'
                        1684    BINARY_SUBSCR                   
                        1688    LOAD_CONST                      25: 'status'
                        1690    BINARY_SUBSCR                   
                        1694    LOAD_FAST                       5: _var_var_45
                        1696    LOAD_CONST                      4: 'info'
                        1698    BINARY_SUBSCR                   
                        1702    LOAD_CONST                      26: 'time'
                        1704    BINARY_SUBSCR                   
                        1708    LOAD_FAST                       4: _var_var_50
                        1710    KW_NAMES                        27: ('mode', 'user_id', 'phone', 'username', 'first_name', 'last_name', 'gender', 'photo', 'premium', 'status', 'time', 'invite_status')
                        1712    CALL                            12
                        1720    POP_TOP                         
                        1722    LOAD_GLOBAL                     77: NULL + db_statistic
                        1732    LOAD_FAST                       0: self
                        1734    LOAD_ATTR                       78: statistic
                        1754    CALL                            1
                        1762    LOAD_ATTR                       81: insert
                        1782    LOAD_FAST                       0: self
                        1784    LOAD_ATTR                       12: account
                        1804    LOAD_FAST                       0: self
                        1806    LOAD_ATTR                       32: group_entity
                        1826    LOAD_ATTR                       64: id
                        1846    LOAD_FAST                       0: self
                        1848    LOAD_ATTR                       82: group_link
                        1868    LOAD_FAST                       5: _var_var_45
                        1870    LOAD_CONST                      4: 'info'
                        1872    BINARY_SUBSCR                   
                        1876    LOAD_CONST                      5: 'id'
                        1878    BINARY_SUBSCR                   
                        1882    LOAD_FAST                       5: _var_var_45
                        1884    LOAD_CONST                      4: 'info'
                        1886    BINARY_SUBSCR                   
                        1890    LOAD_CONST                      18: 'username'
                        1892    BINARY_SUBSCR                   
                        1896    LOAD_FAST                       5: _var_var_45
                        1898    LOAD_CONST                      4: 'info'
                        1900    BINARY_SUBSCR                   
                        1904    PUSH_NULL                       
                        1906    LOAD_CONST                      1: '__pyarmor_assert_13947__'
                        1908    LOAD_CONST                      20: 'first_name'   # b'\x81\xe4\x11\x01 \xee\x81\xdc\x1a\xf7\x08'
                        1910    CALL                            1
                        1918    BINARY_SUBSCR                   
                        1922    LOAD_FAST                       5: _var_var_45
                        1924    LOAD_CONST                      4: 'info'
                        1926    BINARY_SUBSCR                   
                        1930    PUSH_NULL                       
                        1932    LOAD_CONST                      1: '__pyarmor_assert_13947__'
                        1934    LOAD_CONST                      21: 'last_name'   # b"\x81\xee\x19\x00'\xc5\xb0\xd3\x16\xff"
                        1936    CALL                            1
                        1944    BINARY_SUBSCR                   
                        1948    LOAD_FAST                       4: _var_var_50
                        1950    KW_NAMES                        28: ('account', 'group_id', 'group_link', 'user_id', 'username', 'first_name', 'last_name', 'invite_status')
                        1952    CALL                            8
                        1960    POP_TOP                         
                        1962    LOAD_CONST                      0: None
                        1964    STORE_FAST                      4: _var_var_50
                        1966    JUMP_BACKWARD                   583 (to 804)
                        1970    END_FOR                         
                        1972    JUMP_BACKWARD                   946 (to 84)
                        1976    END_FOR                         
                        1978    LOAD_FAST                       0: self
                        1980    LOAD_ATTR                       84: force_mode
                        2000    POP_JUMP_IF_FALSE               280 (to 2564)
                        2004    LOAD_GLOBAL                     55: NULL + Logs
                        2014    LOAD_ATTR                       56: PrintLog
                        2034    LOAD_FAST                       0: self
                        2036    LOAD_ATTR                       40: config
                        2056    LOAD_FAST                       0: self
                        2058    LOAD_ATTR                       12: account
                        2078    LOAD_FAST                       0: self
                        2080    LOAD_ATTR                       42: lang
                        2100    PUSH_NULL                       
                        2102    LOAD_CONST                      1: '__pyarmor_assert_13947__'
                        2104    LOAD_CONST                      29: 'invite_force_mode_activated'   # b'\x81\xeb\x16\x05:\xee\xbb\xed\x1d\xf5\x1f\xc3i\xd3\xf5\x8a\x0bX\x84\xa6\xa9\xdfG\xda\x04{\xa6X'
                        2106    CALL                            1
                        2114    BINARY_SUBSCR                   
                        2118    KW_NAMES                        30: ('config', 'account', 'message')
                        2120    CALL                            3
                        2128    POP_TOP                         
                        2130    LOAD_FAST                       0: self
                        2132    LOAD_ATTR                       68: total_users
                        2152    LOAD_FAST                       0: self
                        2154    LOAD_ATTR                       86: kol_users
                        2174    COMPARE_OP                      92 (>=)
                        2178    POP_JUMP_IF_FALSE               64 (to 2308)
                        2180    LOAD_GLOBAL                     55: NULL + Logs
                        2190    LOAD_ATTR                       56: PrintLog
                        2210    LOAD_FAST                       0: self
                        2212    LOAD_ATTR                       40: config
                        2232    LOAD_FAST                       0: self
                        2234    LOAD_ATTR                       12: account
                        2254    LOAD_FAST                       0: self
                        2256    LOAD_ATTR                       42: lang
                        2276    PUSH_NULL                       
                        2278    LOAD_CONST                      1: '__pyarmor_assert_13947__'
                        2280    LOAD_CONST                      31: 'invite_force_mode_done'   # b'\x81\xeb\x16\x05:\xee\xbb\xed\x1d\xf5\x1f\xc3i\xd3\xf5\x8a\x0bX\x84\xa3\xa5\xc5K'
                        2282    CALL                            1
                        2290    BINARY_SUBSCR                   
                        2294    KW_NAMES                        30: ('config', 'account', 'message')
                        2296    CALL                            3
                        2304    POP_TOP                         
                        2306    JUMP_FORWARD                    128 (to 2564)
                        2308    LOAD_FAST                       0: self
                        2310    LOAD_ATTR                       86: kol_users
                        2330    LOAD_FAST                       0: self
                        2332    LOAD_ATTR                       68: total_users
                        2352    BINARY_OP                       10 (-)
                        2356    STORE_FAST                      10: _var_var_51
                        2358    LOAD_GLOBAL                     55: NULL + Logs
                        2368    LOAD_ATTR                       56: PrintLog
                        2388    LOAD_FAST                       0: self
                        2390    LOAD_ATTR                       40: config
                        2410    LOAD_FAST                       0: self
                        2412    LOAD_ATTR                       12: account
                        2432    LOAD_FAST                       0: self
                        2434    LOAD_ATTR                       42: lang
                        2454    PUSH_NULL                       
                        2456    LOAD_CONST                      1: '__pyarmor_assert_13947__'
                        2458    LOAD_CONST                      32: 'invite_force_mode_ost'   # b'\x81\xeb\x16\x05:\xee\xbb\xed\x1d\xf5\x1f\xc3i\xd3\xf5\x8a\x0bX\x84\xa8\xb9\xdf'
                        2460    CALL                            1
                        2468    BINARY_SUBSCR                   
                        2472    LOAD_FAST                       10: _var_var_51
                        2474    KW_NAMES                        33: ('config', 'account', 'message', 'end')
                        2476    CALL                            4
                        2484    POP_TOP                         
                        2486    LOAD_CONST                      13: 0
                        2488    LOAD_FAST                       0: self
                        2490    STORE_ATTR                      33: count_users
                        2500    LOAD_FAST                       10: _var_var_51
                        2502    LOAD_FAST                       0: self
                        2504    STORE_ATTR                      43: kol_users
                        2514    LOAD_FAST                       0: self
                        2516    LOAD_ATTR                       89: start
                        2536    CALL                            0
                        2544    NOP                             
                        2546    NOP                             
                        2548    NOP                             
                        2550    JUMP_FORWARD                    202 (to 2956)
                        2552    CALL                            1
                        2560    POP_TOP                         
                        2562    RETURN_VALUE                    
                        2564    LOAD_GLOBAL                     55: NULL + Logs
                        2574    LOAD_ATTR                       56: PrintLog
                        2594    LOAD_FAST                       0: self
                        2596    LOAD_ATTR                       40: config
                        2616    LOAD_FAST                       0: self
                        2618    LOAD_ATTR                       12: account
                        2638    LOAD_FAST                       0: self
                        2640    LOAD_ATTR                       42: lang
                        2660    PUSH_NULL                       
                        2662    LOAD_CONST                      1: '__pyarmor_assert_13947__'
                        2664    LOAD_CONST                      35: 'completed_invitations'   # b'\x81\xe1\x17\x1e#\xf6\xbb\xc6\x1e\xfe2\xc9b\xfa\xf1\x91\x0eI\xb2\xa8\xa4\xd8'
                        2666    CALL                            1
                        2674    BINARY_SUBSCR                   
                        2678    LOAD_FAST                       0: self
                        2680    LOAD_ATTR                       68: total_users
                        2700    KW_NAMES                        11: ('config', 'account', 'message', 'param')
                        2702    CALL                            4
                        2710    POP_TOP                         
                        2712    LOAD_CONST                      0: None
                        2714    NOP                             
                        2716    NOP                             
                        2718    NOP                             
                        2720    JUMP_FORWARD                    117 (to 2956)
                        2728    POP_TOP                         
                        2730    RETURN_CONST                    0: None
                        2732    PUSH_EXC_INFO                   
                        2734    LOAD_GLOBAL                     46: StopProgram
                        2744    CHECK_EXC_MATCH                 
                        2746    POP_JUMP_IF_FALSE               2 (to 2752)
                        2748    POP_TOP                         
                        2750    RAISE_VARARGS                   0
                        2752    LOAD_GLOBAL                     48: Exception
                        2762    CHECK_EXC_MATCH                 
                        2764    POP_JUMP_IF_FALSE               77 (to 2920)
                        2766    STORE_FAST                      7: _var_var_3
                        2768    LOAD_GLOBAL                     51: NULL + type
                        2778    LOAD_FAST                       7: _var_var_3
                        2780    CALL                            1
                        2788    LOAD_ATTR                       52: __name__
                        2808    STORE_FAST                      4: _var_var_50
                        2810    LOAD_GLOBAL                     55: NULL + Logs
                        2820    LOAD_ATTR                       56: PrintLog
                        2840    LOAD_FAST                       0: self
                        2842    LOAD_ATTR                       40: config
                        2862    LOAD_FAST                       0: self
                        2864    LOAD_ATTR                       12: account
                        2884    LOAD_CONST                      10: 'Status:'
                        2886    LOAD_FAST                       4: _var_var_50
                        2888    KW_NAMES                        11: ('config', 'account', 'message', 'param')
                        2890    CALL                            4
                        2898    POP_TOP                         
                        2900    POP_EXCEPT                      
                        2902    LOAD_CONST                      0: None
                        2904    STORE_FAST                      7: _var_var_3
                        2906    DELETE_FAST                     7: _var_var_3
                        2908    JUMP_BACKWARD                   1056 (to 800)
                        2912    LOAD_CONST                      0: None
                        2914    STORE_FAST                      7: _var_var_3
                        2916    DELETE_FAST                     7: _var_var_3
                        2918    RERAISE                         1
                        2920    RERAISE                         0
                        2922    COPY                            3
                        2924    POP_EXCEPT                      
                        2926    RERAISE                         1
                        2928    PUSH_EXC_INFO                   
                        2930    PUSH_NULL                       
                        2932    LOAD_CONST                      34: '__pyarmor_exit_13949__'
                        2934    NOP                             
                        2936    LOAD_CONST                      3: b'<COAddr>\x07\x00\x00\x1aV\x0b\x00\x00\x00\x00\x00\x00\x00\x00\x00\x00\x00\x00\x00\x00'
                        2938    CALL                            1
                        2946    POP_TOP                         
                        2948    RERAISE                         0
                        2950    COPY                            3
                        2952    POP_EXCEPT                      
                        2954    RERAISE                         1
                        2956    PUSH_NULL                       
                        2958    LOAD_CONST                      34: '__pyarmor_exit_13949__'
                        2960    LOAD_CONST                      3: b'<COAddr>\x07\x00\x00\x1aV\x0b\x00\x00\x00\x00\x00\x00\x00\x00\x00\x00\x00\x00\x00\x00'
                        2962    BUILD_TUPLE                     1
                        2964    CALL_FUNCTION_EX                0
                        2966    POP_TOP                         
                        2968    RETURN_VALUE                    
                    [Exception Table]
                        28 to 356 -> 2928 [0] 
                        358 to 800 -> 2732 [1] 
                        800 to 1260 -> 2928 [0] 
                        1262 to 2544 -> 2928 [0] 
                        2564 to 2712 -> 2928 [0] 
                        2732 to 2768 -> 2922 [2] lasti
                        2768 to 2900 -> 2912 [2] lasti
                        2900 to 2912 -> 2928 [0] 
                        2912 to 2922 -> 2922 [2] lasti
                        2922 to 2928 -> 2928 [0] 
                        2928 to 2950 -> 2950 [1] lasti
                '__pyarmor_exit_13940__'
                (
                    500
                    None
                    None
                )
            [Disassembly]
                0       NOP                             
                2       LOAD_NAME                       0: __name__
                4       STORE_NAME                      1: __module__
                6       LOAD_CONST                      0: 'invite'
                8       STORE_NAME                      2: __qualname__
                10      NOP                             
                12      PUSH_NULL                       
                14      LOAD_CONST                      2: '__pyarmor_enter_13939__'
                16      LOAD_CONST                      3: b'<COAddr>\x07\x00\x00"*\x00\x00\x00\x00\x00\x00\x00\x00\x00\x00\x00\x00\x00\x00\x00'
                18      BUILD_TUPLE                     1
                20      CALL_FUNCTION_EX                0
                22      POP_TOP                         
                24      RESUME                          0
                26      NOP                             
                28      NOP                             
                30      NOP                             
                32      NOP                             
                34      NOP                             
                36      LOAD_CONST                      9: (500, None, None)
                38      LOAD_CONST                      5: <CODE> __init__
                40      MAKE_FUNCTION                   1
                42      STORE_NAME                      4: __init__
                44      LOAD_CONST                      6: <CODE> prepare_users
                46      MAKE_FUNCTION                   0
                48      STORE_NAME                      5: prepare_users
                50      LOAD_CONST                      7: <CODE> start
                52      MAKE_FUNCTION                   0
                54      STORE_NAME                      6: start
                56      LOAD_CONST                      4: None
                58      NOP                             
                60      NOP                             
                62      NOP                             
                64      JUMP_FORWARD                    19 (to 104)
                72      POP_TOP                         
                74      RETURN_CONST                    4: None
                76      PUSH_EXC_INFO                   
                78      PUSH_NULL                       
                80      LOAD_CONST                      8: '__pyarmor_exit_13940__'
                82      NOP                             
                84      LOAD_CONST                      3: b'<COAddr>\x07\x00\x00"*\x00\x00\x00\x00\x00\x00\x00\x00\x00\x00\x00\x00\x00\x00\x00'
                86      CALL                            1
                94      POP_TOP                         
                96      RERAISE                         0
                98      COPY                            3
                100     POP_EXCEPT                      
                102     RERAISE                         1
                104     PUSH_NULL                       
                106     LOAD_CONST                      8: '__pyarmor_exit_13940__'
                108     LOAD_CONST                      3: b'<COAddr>\x07\x00\x00"*\x00\x00\x00\x00\x00\x00\x00\x00\x00\x00\x00\x00\x00\x00\x00'
                110     BUILD_TUPLE                     1
                112     CALL_FUNCTION_EX                0
                114     POP_TOP                         
                116     RETURN_VALUE                    
            [Exception Table]
                36 to 56 -> 76 [0] 
                76 to 98 -> 98 [1] lasti
        'invite'
        '__pyarmor_exit_13928__'
    [Disassembly]
        0       NOP                             
        2       NOP                             
        4       PUSH_NULL                       
        6       LOAD_CONST                      1: '__pyarmor_enter_13927__'
        8       LOAD_CONST                      2: b'<COAddr>\x05\x00\x00\x1a\xde\x01\x00\x00\x00\x00\x00\x00\x00\x00\x00\x00\x00\x00\x00\x00'
        10      BUILD_TUPLE                     1
        12      CALL_FUNCTION_EX                0
        14      POP_TOP                         
        16      RESUME                          0
        18      NOP                             
        20      NOP                             
        22      NOP                             
        24      NOP                             
        26      LOAD_CONST                      3: 0
        28      LOAD_CONST                      4: None
        30      IMPORT_NAME                     1: eel
        32      STORE_NAME                      1: eel
        34      LOAD_CONST                      3: 0
        36      LOAD_CONST                      4: None
        38      IMPORT_NAME                     2: json
        40      STORE_NAME                      2: json
        42      LOAD_CONST                      3: 0
        44      LOAD_CONST                      4: None
        46      IMPORT_NAME                     3: random
        48      STORE_NAME                      3: random
        50      LOAD_CONST                      3: 0
        52      LOAD_CONST                      4: None
        54      IMPORT_NAME                     4: datetime
        56      STORE_NAME                      4: datetime
        58      LOAD_CONST                      3: 0
        60      LOAD_CONST                      4: None
        62      IMPORT_NAME                     5: concurrent.futures
        64      STORE_NAME                      6: concurrent
        66      LOAD_CONST                      3: 0
        68      LOAD_CONST                      5: ('Thread', 'Event')
        70      IMPORT_NAME                     7: threading
        72      IMPORT_FROM                     8: Thread
        74      STORE_NAME                      8: Thread
        76      IMPORT_FROM                     9: Event
        78      STORE_NAME                      9: Event
        80      POP_TOP                         
        82      LOAD_CONST                      3: 0
        84      LOAD_CONST                      6: ('functions', 'types')
        86      IMPORT_NAME                     10: multithon.sync
        88      IMPORT_FROM                     11: functions
        90      STORE_NAME                      11: functions
        92      IMPORT_FROM                     12: types
        94      STORE_NAME                      12: types
        96      POP_TOP                         
        98      LOAD_CONST                      3: 0
        100     LOAD_CONST                      7: ('StopProgram',)
        102     IMPORT_NAME                     13: multithon.errors
        104     IMPORT_FROM                     14: StopProgram
        106     STORE_NAME                      14: StopProgram
        108     POP_TOP                         
        110     LOAD_CONST                      3: 0
        112     LOAD_CONST                      8: ('AutoStop',)
        114     IMPORT_NAME                     15: program.static_classes
        116     IMPORT_FROM                     16: AutoStop
        118     STORE_NAME                      16: AutoStop
        120     POP_TOP                         
        122     LOAD_CONST                      3: 0
        124     LOAD_CONST                      9: ('BanAccount',)
        126     IMPORT_NAME                     15: program.static_classes
        128     IMPORT_FROM                     17: BanAccount
        130     STORE_NAME                      17: BanAccount
        132     POP_TOP                         
        134     LOAD_CONST                      3: 0
        136     LOAD_CONST                      10: ('GetLang',)
        138     IMPORT_NAME                     15: program.static_classes
        140     IMPORT_FROM                     18: GetLang
        142     STORE_NAME                      18: GetLang
        144     POP_TOP                         
        146     LOAD_CONST                      3: 0
        148     LOAD_CONST                      11: ('Logs',)
        150     IMPORT_NAME                     15: program.static_classes
        152     IMPORT_FROM                     19: Logs
        154     STORE_NAME                      19: Logs
        156     POP_TOP                         
        158     LOAD_CONST                      3: 0
        160     LOAD_CONST                      12: ('MaxFlood',)
        162     IMPORT_NAME                     15: program.static_classes
        164     IMPORT_FROM                     20: MaxFlood
        166     STORE_NAME                      20: MaxFlood
        168     POP_TOP                         
        170     LOAD_CONST                      3: 0
        172     LOAD_CONST                      13: ('PeerFlood',)
        174     IMPORT_NAME                     15: program.static_classes
        176     IMPORT_FROM                     21: PeerFlood
        178     STORE_NAME                      21: PeerFlood
        180     POP_TOP                         
        182     LOAD_CONST                      3: 0
        184     LOAD_CONST                      14: ('StopAccount',)
        186     IMPORT_NAME                     15: program.static_classes
        188     IMPORT_FROM                     22: StopAccount
        190     STORE_NAME                      22: StopAccount
        192     POP_TOP                         
        194     LOAD_CONST                      3: 0
        196     LOAD_CONST                      15: ('logging',)
        198     IMPORT_NAME                     15: program.static_classes
        200     IMPORT_FROM                     23: logging
        202     STORE_NAME                      23: logging
        204     POP_TOP                         
        206     LOAD_CONST                      3: 0
        208     LOAD_CONST                      16: ('memory_check_switcher',)
        210     IMPORT_NAME                     15: program.static_classes
        212     IMPORT_FROM                     24: memory_check_switcher
        214     STORE_NAME                      24: memory_check_switcher
        216     POP_TOP                         
        218     LOAD_CONST                      3: 0
        220     LOAD_CONST                      17: ('memory_set_pid',)
        222     IMPORT_NAME                     15: program.static_classes
        224     IMPORT_FROM                     25: memory_set_pid
        226     STORE_NAME                      25: memory_set_pid
        228     POP_TOP                         
        230     LOAD_CONST                      3: 0
        232     LOAD_CONST                      18: ('DelayOnline',)
        234     IMPORT_NAME                     26: program.telegram
        236     IMPORT_FROM                     27: DelayOnline
        238     STORE_NAME                      27: DelayOnline
        240     POP_TOP                         
        242     LOAD_CONST                      3: 0
        244     LOAD_CONST                      19: ('Disconnect',)
        246     IMPORT_NAME                     26: program.telegram
        248     IMPORT_FROM                     28: Disconnect
        250     STORE_NAME                      28: Disconnect
        252     POP_TOP                         
        254     LOAD_CONST                      3: 0
        256     LOAD_CONST                      20: ('TelegramRequest',)
        258     IMPORT_NAME                     26: program.telegram
        260     IMPORT_FROM                     29: TelegramRequest
        262     STORE_NAME                      29: TelegramRequest
        264     POP_TOP                         
        266     LOAD_CONST                      3: 0
        268     LOAD_CONST                      21: ('Thread_wait',)
        270     IMPORT_NAME                     26: program.telegram
        272     IMPORT_FROM                     30: Thread_wait
        274     STORE_NAME                      30: Thread_wait
        276     POP_TOP                         
        278     LOAD_CONST                      3: 0
        280     LOAD_CONST                      22: ('account_works',)
        282     IMPORT_NAME                     26: program.telegram
        284     IMPORT_FROM                     31: account_works
        286     STORE_NAME                      31: account_works
        288     POP_TOP                         
        290     LOAD_CONST                      3: 0
        292     LOAD_CONST                      23: ('entity',)
        294     IMPORT_NAME                     26: program.telegram
        296     IMPORT_FROM                     32: entity
        298     STORE_NAME                      32: entity
        300     POP_TOP                         
        302     LOAD_CONST                      3: 0
        304     LOAD_CONST                      24: ('tg_entity',)
        306     IMPORT_NAME                     26: program.telegram
        308     IMPORT_FROM                     33: tg_entity
        310     STORE_NAME                      33: tg_entity
        312     POP_TOP                         
        314     LOAD_CONST                      3: 0
        316     LOAD_CONST                      25: ('tg_group',)
        318     IMPORT_NAME                     26: program.telegram
        320     IMPORT_FROM                     34: tg_group
        322     STORE_NAME                      34: tg_group
        324     POP_TOP                         
        326     LOAD_CONST                      3: 0
        328     LOAD_CONST                      26: ('tg_links',)
        330     IMPORT_NAME                     26: program.telegram
        332     IMPORT_FROM                     35: tg_links
        334     STORE_NAME                      35: tg_links
        336     POP_TOP                         
        338     LOAD_CONST                      3: 0
        340     LOAD_CONST                      27: ('GetConfig',)
        342     IMPORT_NAME                     36: program.general
        344     IMPORT_FROM                     37: GetConfig
        346     STORE_NAME                      37: GetConfig
        348     POP_TOP                         
        350     LOAD_CONST                      3: 0
        352     LOAD_CONST                      28: ('GetProxy',)
        354     IMPORT_NAME                     36: program.general
        356     IMPORT_FROM                     38: GetProxy
        358     STORE_NAME                      38: GetProxy
        360     POP_TOP                         
        362     LOAD_CONST                      3: 0
        364     LOAD_CONST                      29: ('StopDetect',)
        366     IMPORT_NAME                     36: program.general
        368     IMPORT_FROM                     39: StopDetect
        370     STORE_NAME                      39: StopDetect
        372     POP_TOP                         
        374     LOAD_CONST                      3: 0
        376     LOAD_CONST                      30: ('check_get_settings',)
        378     IMPORT_NAME                     36: program.general
        380     IMPORT_FROM                     40: check_get_settings
        382     STORE_NAME                      40: check_get_settings
        384     POP_TOP                         
        386     LOAD_CONST                      3: 0
        388     LOAD_CONST                      31: ('del_task_manager',)
        390     IMPORT_NAME                     36: program.general
        392     IMPORT_FROM                     41: del_task_manager
        394     STORE_NAME                      41: del_task_manager
        396     POP_TOP                         
        398     LOAD_CONST                      3: 0
        400     LOAD_CONST                      32: ('getFile',)
        402     IMPORT_NAME                     36: program.general
        404     IMPORT_FROM                     42: getFile
        406     STORE_NAME                      42: getFile
        408     POP_TOP                         
        410     LOAD_CONST                      3: 0
        412     LOAD_CONST                      33: ('set_task_manager',)
        414     IMPORT_NAME                     36: program.general
        416     IMPORT_FROM                     43: set_task_manager
        418     STORE_NAME                      43: set_task_manager
        420     POP_TOP                         
        422     LOAD_CONST                      3: 0
        424     LOAD_CONST                      34: ('db_parsing',)
        426     IMPORT_NAME                     44: program.database
        428     IMPORT_FROM                     45: db_parsing
        430     STORE_NAME                      45: db_parsing
        432     POP_TOP                         
        434     LOAD_CONST                      3: 0
        436     LOAD_CONST                      35: ('db_statistic',)
        438     IMPORT_NAME                     44: program.database
        440     IMPORT_FROM                     46: db_statistic
        442     STORE_NAME                      46: db_statistic
        444     POP_TOP                         
        446     LOAD_CONST                      36: <CODE> Invite_username_v2
        448     MAKE_FUNCTION                   0
        450     STORE_NAME                      47: Invite_username_v2
        452     LOAD_CONST                      37: <CODE> START
        454     MAKE_FUNCTION                   0
        456     STORE_NAME                      48: START
        458     LOAD_CONST                      38: <CODE> worker
        460     MAKE_FUNCTION                   0
        462     STORE_NAME                      49: worker
        464     PUSH_NULL                       
        466     LOAD_BUILD_CLASS                
        468     LOAD_CONST                      39: <CODE> invite
        470     MAKE_FUNCTION                   0
        472     LOAD_CONST                      40: 'invite'
        474     CALL                            2
        482     STORE_NAME                      50: invite
        484     LOAD_CONST                      4: None
        486     NOP                             
        488     NOP                             
        490     NOP                             
        492     JUMP_FORWARD                    19 (to 532)
        500     POP_TOP                         
        502     RETURN_CONST                    4: None
        504     PUSH_EXC_INFO                   
        506     PUSH_NULL                       
        508     LOAD_CONST                      41: '__pyarmor_exit_13928__'
        510     NOP                             
        512     LOAD_CONST                      2: b'<COAddr>\x05\x00\x00\x1a\xde\x01\x00\x00\x00\x00\x00\x00\x00\x00\x00\x00\x00\x00\x00\x00'
        514     CALL                            1
        522     POP_TOP                         
        524     RERAISE                         0
        526     COPY                            3
        528     POP_EXCEPT                      
        530     RERAISE                         1
        532     PUSH_NULL                       
        534     LOAD_CONST                      41: '__pyarmor_exit_13928__'
        536     LOAD_CONST                      2: b'<COAddr>\x05\x00\x00\x1a\xde\x01\x00\x00\x00\x00\x00\x00\x00\x00\x00\x00\x00\x00\x00\x00'
        538     BUILD_TUPLE                     1
        540     CALL_FUNCTION_EX                0
        542     POP_TOP                         
        544     RETURN_VALUE                    
    [Exception Table]
        26 to 484 -> 504 [0] 
        504 to 526 -> 526 [1] lasti
