#decoded by lolz.live/mrpenny / t.me/zeus_jackpot
# ================================
# Примечания по Pyarmor:
# - Байт-код и объекты кода Pyarmor соответствуют стандартному Python, но присутствуют специальные вызовы функций среды выполнения (runtime) Pyarmor.
# - Вызовы строк — это не ошибки, а маркеры, которые обрабатываются Pyarmor во время выполнения.
#
# Руководство по декомпиляции (без среды выполнения):
# 1. Игнорируйте зашифрованные байты после `#`; используйте только строку до `#`.
# 2. Удалите "__pyarmor_enter_xxx__"(b"<COAddr>...") и "__pyarmor_leave_xxx__"(b"<COAddr>...") (пролог/эпилог).
# 3. "__pyarmor_assert_xxx__"(A) не является настоящим оператором assert.
#    - Если A — это имя или читаемая строка: замените на A.
#    - Если A — это (X, "Y"): замените на X.Y.
#    - Если A — это (X, "Y", Z): замените на X.Y = Z.
#    - В противном случае: выберите наиболее подходящую/логичную замену.
# 4. "__pyarmor_bcc_xxx__"(...) указывает на машинный (нативный) код; тело функции недоступно. Добавьте комментарий.
# ================================

[Code]
    File Name: <frozen program.modules.Parsing>
    Object Name: <module>
    Qualified Name: <module>
    Arg Count: 0
    Pos Only Arg Count: 0
    KW Only Arg Count: 0
    Stack Size: 5
    Flags: 0x20000000 (CO_PYARMOR_OBFUSCATED)
    [Names]
        '__assert_armored__'
        'eel'
        'json'
        'time'
        'datetime'
        'concurrent.futures'
        'concurrent'
        'threading'
        'Thread'
        'Event'
        'multithon.sync'
        'functions'
        'types'
        'errors'
        'multithon.errors'
        'StopProgram'
        'program.static_classes'
        'GetLang'
        'Logs'
        'logging'
        'memory_check_switcher'
        'memory_set_pid'
        'program.telegram'
        'DelayOnline'
        'Disconnect'
        'Thread_wait'
        'account_works'
        'entity'
        'parsing_time'
        'tg_group'
        'tg_links'
        'txt_file'
        'program.general'
        'GetConfig'
        'GetProxy'
        'StopDetect'
        'check_get_settings'
        'del_task_manager'
        'getFile'
        'set_task_manager'
        'program.database'
        'db_parsing'
        'db_base'
        'db_parsing_res'
        'Exception'
        'Stop'
        'Parsing'
        'START'
        'worker'
    [Locals+Names]
    [Constants]
        '__pyarmor_assert_13950__'
        '__pyarmor_enter_13951__'
        b'<COAddr>\x05\x00\x00\x1a\xb4\x01\x00\x00\x00\x00\x00\x00\x00\x00\x00\x00\x00\x00\x00\x00'
        0
        None
        (
            'Thread'
            'Event'
        )
        (
            'functions'
            'types'
            'errors'
        )
        (
            'StopProgram'
        )
        (
            'GetLang'
        )
        (
            'Logs'
        )
        (
            'logging'
        )
        (
            'memory_check_switcher'
        )
        (
            'memory_set_pid'
        )
        (
            'DelayOnline'
        )
        (
            'Disconnect'
        )
        (
            'Thread_wait'
        )
        (
            'account_works'
        )
        (
            'entity'
        )
        (
            'parsing_time'
        )
        (
            'tg_group'
        )
        (
            'tg_links'
        )
        (
            'txt_file'
        )
        (
            'GetConfig'
        )
        (
            'GetProxy'
        )
        (
            'StopDetect'
        )
        (
            'check_get_settings'
        )
        (
            'del_task_manager'
        )
        (
            'getFile'
        )
        (
            'set_task_manager'
        )
        (
            'db_parsing'
        )
        (
            'db_base'
        )
        (
            'db_parsing_res'
        )
        [Code]
            File Name: <frozen program.modules.Parsing>
            Object Name: Stop
            Qualified Name: Stop
            Arg Count: 0
            Pos Only Arg Count: 0
            KW Only Arg Count: 0
            Stack Size: 5
            Flags: 0x20000000 (CO_PYARMOR_OBFUSCATED)
            [Names]
                '__name__'
                '__module__'
                '__qualname__'
                '__assert_armored__'
            [Locals+Names]
            [Constants]
                'Stop'
                '__pyarmor_assert_13953__'
                '__pyarmor_enter_13954__'
                b'<COAddr>\x07\x00\x00"\x14\x00\x00\x00\x00\x00\x00\x00\x00\x00\x00\x00\x00\x00\x00\x00'
                '__pyarmor_exit_13955__'
                None
            [Disassembly]
                0       NOP                             
                2       LOAD_NAME                       0: __name__
                4       STORE_NAME                      1: __module__
                6       LOAD_CONST                      0: 'Stop'
                8       STORE_NAME                      2: __qualname__
                10      NOP                             
                12      PUSH_NULL                       
                14      LOAD_CONST                      2: '__pyarmor_enter_13954__'
                16      LOAD_CONST                      3: b'<COAddr>\x07\x00\x00"\x14\x00\x00\x00\x00\x00\x00\x00\x00\x00\x00\x00\x00\x00\x00\x00'
                18      BUILD_TUPLE                     1
                20      CALL_FUNCTION_EX                0
                22      POP_TOP                         
                24      RESUME                          0
                26      NOP                             
                28      NOP                             
                30      NOP                             
                32      NOP                             
                34      LOAD_CONST                      5: None
                36      NOP                             
                38      NOP                             
                40      NOP                             
                42      JUMP_FORWARD                    19 (to 82)
                50      POP_TOP                         
                52      RETURN_CONST                    5: None
                54      PUSH_EXC_INFO                   
                56      PUSH_NULL                       
                58      LOAD_CONST                      4: '__pyarmor_exit_13955__'
                60      NOP                             
                62      LOAD_CONST                      3: b'<COAddr>\x07\x00\x00"\x14\x00\x00\x00\x00\x00\x00\x00\x00\x00\x00\x00\x00\x00\x00\x00'
                64      CALL                            1
                72      POP_TOP                         
                74      RERAISE                         0
                76      COPY                            3
                78      POP_EXCEPT                      
                80      RERAISE                         1
                82      PUSH_NULL                       
                84      LOAD_CONST                      4: '__pyarmor_exit_13955__'
                86      LOAD_CONST                      3: b'<COAddr>\x07\x00\x00"\x14\x00\x00\x00\x00\x00\x00\x00\x00\x00\x00\x00\x00\x00\x00\x00'
                88      BUILD_TUPLE                     1
                90      CALL_FUNCTION_EX                0
                92      POP_TOP                         
                94      RETURN_VALUE                    
            [Exception Table]
                54 to 76 -> 76 [1] lasti
        'Stop'
        [Code]
            File Name: <frozen program.modules.Parsing>
            Object Name: Parsing
            Qualified Name: Parsing
            Arg Count: 1
            Pos Only Arg Count: 0
            KW Only Arg Count: 0
            Stack Size: 8
            Flags: 0x20000003 (CO_OPTIMIZED | CO_NEWLOCALS | CO_PYARMOR_OBFUSCATED)
            [Names]
                'get'
                'getFile'
                'GetConfig'
                'config'
                'GetLang'
                'Lang'
                'GetProxy'
                'eel'
                'sendSuccessBox'
                'memory_check_switcher'
                'Event'
                'memory_set_pid'
                'Thread'
                'START'
                'start'
                'Logs'
                'WaitStopAnsfer'
                'UpdateLogInWindow'
                'Exception'
                'print'
            [Locals+Names]
                'data'
                '__assert_armored__'
                '_var_var_0'
                '_var_var_1'
                '_var_var_2'
                '_var_var_3'
            [Constants]
                None
                '__pyarmor_assert_13956__'
                '__pyarmor_enter_13957__'
                b'<COAddr>\x07\x00\x00\x1a\xb6\x02\x00\x00\x00\x00\x00\x00\x00\x00\x00\x00\x00\x00\x00\x00'
                'action'
                'getFile'
                '__pyarmor_exit_13958__'
                'program_running'   # b'\x81\xf2\n\x1c4\xe8\xbf\xdf$\xe8\x18\xceb\xe5\xf6\x82'
                False
                (
                    'target'
                    'args'
                )
                True
                (
                    'target'
                    'args'
                    'daemon'
                )
                'Parsing: '   # b'\x81\xd2\x19\x01 \xf3\xb0\xd5A\xba'
            [Disassembly]
                0       NOP                             
                2       NOP                             
                4       PUSH_NULL                       
                6       LOAD_CONST                      2: '__pyarmor_enter_13957__'
                8       LOAD_CONST                      3: b'<COAddr>\x07\x00\x00\x1a\xb6\x02\x00\x00\x00\x00\x00\x00\x00\x00\x00\x00\x00\x00\x00\x00'
                10      BUILD_TUPLE                     1
                12      CALL_FUNCTION_EX                0
                14      POP_TOP                         
                16      RESUME                          0
                18      NOP                             
                20      NOP                             
                22      NOP                             
                24      NOP                             
                26      NOP                             
                28      NOP                             
                30      LOAD_FAST                       0: data
                32      LOAD_ATTR                       1: get
                52      LOAD_CONST                      4: 'action'
                54      CALL                            1
                62      POP_JUMP_IF_NONE                28 (to 120)
                64      LOAD_FAST                       0: data
                66      LOAD_CONST                      4: 'action'
                68      BINARY_SUBSCR                   
                72      LOAD_CONST                      5: 'getFile'
                74      COMPARE_OP                      40 (==)
                78      POP_JUMP_IF_FALSE               20 (to 120)
                80      LOAD_GLOBAL                     3: NULL + getFile
                90      LOAD_FAST                       0: data
                92      CALL                            1
                100     NOP                             
                102     NOP                             
                104     JUMP_FORWARD                    320 (to 748)
                108     CALL                            1
                116     POP_TOP                         
                118     RETURN_VALUE                    
                120     LOAD_GLOBAL                     5: NULL + GetConfig
                130     CALL                            0
                138     STORE_GLOBAL                    3: config
                140     LOAD_GLOBAL                     9: NULL + GetLang
                150     LOAD_GLOBAL                     6: config
                160     CALL                            1
                168     STORE_GLOBAL                    5: Lang
                170     LOAD_GLOBAL                     13: NULL + GetProxy
                180     CALL                            0
                188     STORE_FAST                      2: _var_var_0
                190     LOAD_GLOBAL                     15: NULL + eel
                200     LOAD_ATTR                       16: sendSuccessBox
                220     LOAD_GLOBAL                     10: Lang
                230     PUSH_NULL                       
                232     LOAD_CONST                      1: '__pyarmor_assert_13956__'
                234     LOAD_CONST                      7: 'program_running'   # b'\x81\xf2\n\x1c4\xe8\xbf\xdf$\xe8\x18\xceb\xe5\xf6\x82'
                236     CALL                            1
                244     BINARY_SUBSCR                   
                248     CALL                            1
                256     POP_TOP                         
                258     LOAD_GLOBAL                     19: NULL + memory_check_switcher
                268     CALL                            0
                276     POP_JUMP_IF_TRUE                11 (to 300)
                278     NOP                             
                280     LOAD_CONST                      8: False
                282     NOP                             
                284     NOP                             
                286     NOP                             
                288     JUMP_FORWARD                    229 (to 748)
                296     POP_TOP                         
                298     RETURN_CONST                    8: False
                300     LOAD_GLOBAL                     21: NULL + Event
                310     CALL                            0
                318     STORE_FAST                      3: _var_var_1
                320     LOAD_GLOBAL                     23: NULL + memory_set_pid
                330     CALL                            0
                338     STORE_FAST                      4: _var_var_2
                340     LOAD_GLOBAL                     25: NULL + Thread
                350     LOAD_GLOBAL                     26: START
                360     LOAD_FAST                       0: data
                362     LOAD_GLOBAL                     6: config
                372     LOAD_FAST                       4: _var_var_2
                374     LOAD_FAST                       2: _var_var_0
                376     LOAD_FAST                       3: _var_var_1
                378     BUILD_TUPLE                     5
                380     KW_NAMES                        9: ('target', 'args')
                382     CALL                            2
                390     LOAD_ATTR                       29: start
                410     CALL                            0
                418     POP_TOP                         
                420     LOAD_GLOBAL                     25: NULL + Thread
                430     LOAD_GLOBAL                     30: Logs
                440     LOAD_ATTR                       32: WaitStopAnsfer
                460     LOAD_GLOBAL                     6: config
                470     LOAD_FAST                       4: _var_var_2
                472     LOAD_FAST                       3: _var_var_1
                474     BUILD_TUPLE                     3
                476     LOAD_CONST                      10: True
                478     KW_NAMES                        11: ('target', 'args', 'daemon')
                480     CALL                            3
                488     LOAD_ATTR                       29: start
                508     CALL                            0
                516     POP_TOP                         
                518     LOAD_GLOBAL                     25: NULL + Thread
                528     LOAD_GLOBAL                     30: Logs
                538     LOAD_ATTR                       34: UpdateLogInWindow
                558     LOAD_GLOBAL                     6: config
                568     LOAD_FAST                       4: _var_var_2
                570     LOAD_FAST                       3: _var_var_1
                572     BUILD_TUPLE                     3
                574     LOAD_CONST                      10: True
                576     KW_NAMES                        11: ('target', 'args', 'daemon')
                578     CALL                            3
                586     LOAD_ATTR                       29: start
                606     CALL                            0
                614     POP_TOP                         
                616     LOAD_CONST                      0: None
                618     NOP                             
                620     NOP                             
                622     NOP                             
                624     JUMP_FORWARD                    61 (to 748)
                632     POP_TOP                         
                634     RETURN_CONST                    0: None
                636     PUSH_EXC_INFO                   
                638     LOAD_GLOBAL                     36: Exception
                648     CHECK_EXC_MATCH                 
                650     POP_JUMP_IF_FALSE               30 (to 712)
                652     STORE_FAST                      5: _var_var_3
                654     LOAD_GLOBAL                     39: NULL + print
                664     PUSH_NULL                       
                666     LOAD_CONST                      1: '__pyarmor_assert_13956__'
                668     LOAD_CONST                      12: 'Parsing: '   # b'\x81\xd2\x19\x01 \xf3\xb0\xd5A\xba'
                670     CALL                            1
                678     LOAD_FAST                       5: _var_var_3
                680     FORMAT_VALUE                    0 (FVC_NONE)
                682     BUILD_STRING                    2
                684     CALL                            1
                692     POP_TOP                         
                694     POP_EXCEPT                      
                696     LOAD_CONST                      0: None
                698     STORE_FAST                      5: _var_var_3
                700     DELETE_FAST                     5: _var_var_3
                702     JUMP_BACKWARD                   44 (to 616)
                704     LOAD_CONST                      0: None
                706     STORE_FAST                      5: _var_var_3
                708     DELETE_FAST                     5: _var_var_3
                710     RERAISE                         1
                712     RERAISE                         0
                714     COPY                            3
                716     POP_EXCEPT                      
                718     RERAISE                         1
                720     PUSH_EXC_INFO                   
                722     PUSH_NULL                       
                724     LOAD_CONST                      6: '__pyarmor_exit_13958__'
                726     NOP                             
                728     LOAD_CONST                      3: b'<COAddr>\x07\x00\x00\x1a\xb6\x02\x00\x00\x00\x00\x00\x00\x00\x00\x00\x00\x00\x00\x00\x00'
                730     CALL                            1
                738     POP_TOP                         
                740     RERAISE                         0
                742     COPY                            3
                744     POP_EXCEPT                      
                746     RERAISE                         1
                748     PUSH_NULL                       
                750     LOAD_CONST                      6: '__pyarmor_exit_13958__'
                752     LOAD_CONST                      3: b'<COAddr>\x07\x00\x00\x1a\xb6\x02\x00\x00\x00\x00\x00\x00\x00\x00\x00\x00\x00\x00\x00\x00'
                754     BUILD_TUPLE                     1
                756     CALL_FUNCTION_EX                0
                758     POP_TOP                         
                760     RETURN_VALUE                    
            [Exception Table]
                30 to 100 -> 636 [0] 
                120 to 278 -> 636 [0] 
                300 to 616 -> 636 [0] 
                636 to 654 -> 714 [1] lasti
                654 to 694 -> 704 [1] lasti
                694 to 704 -> 720 [0] 
                704 to 714 -> 714 [1] lasti
                714 to 720 -> 720 [0] 
                720 to 742 -> 742 [1] lasti
        [Code]
            File Name: <frozen program.modules.Parsing>
            Object Name: START
            Qualified Name: START
            Arg Count: 5
            Pos Only Arg Count: 0
            KW Only Arg Count: 0
            Stack Size: 14
            Flags: 0x20000003 (CO_OPTIMIZED | CO_NEWLOCALS | CO_PYARMOR_OBFUSCATED)
            [Names]
                'is_set'
                'StopProgram'
                'check_get_settings'
                'get'
                'isinstance'
                'list'
                'int'
                'len'
                'eel'
                'sendErrorBox'
                'Lang'
                'datetime'
                'now'
                'strftime'
                'db_base'
                'import_list'
                'WriteResult'
                'db_parsing'
                'create'
                'open'
                'set_task_manager'
                'concurrent'
                'futures'
                'ThreadPoolExecutor'
                'StreamStat'
                'json'
                'dumps'
                'append'
                'submit'
                'worker'
                'as_completed'
                'Logs'
                'PrintLog'
                'txt_file'
                'unic'
                'get_users_count'
                'BaseException'
                'logging'
                'del_task_manager'
                'StopDetect'
            [Locals+Names]
                'data'
                'config'
                'pid'
                'proxy'
                'stop_thread'
                '__assert_armored__'
                '_var_var_4'
                '_var_var_5'
                '_var_var_6'
                '_var_var_7'
                '_var_var_8'
                '_var_var_9'
                '_var_var_10'
                '_var_var_11'
                '_var_var_12'
                '_var_var_13'
                '_var_var_14'
                '_var_var_15'
                '_var_var_16'
                '_var_var_17'
                '_var_var_18'
                '_var_var_3'
            [Constants]
                None
                '__pyarmor_assert_13959__'
                '__pyarmor_enter_13960__'
                b'<COAddr>\x07\x00\x00\x1aJ\t\x00\x00\x00\x00\x00\x00\x00\x00\x00\x00\x00\x00\x00\x00'
                'Settings'
                'Accounts'
                1
                'select_accounts_works'   # b'\x81\xf1\x1d\x1f6\xf9\xaa\xed\x1a\xf9\x0e\xcfy\xe2\xec\x960J\xb4\xb5\xa1\xd8'
                'thread_rules'   # b'\x81\xf6\x10\x016\xfb\xba\xed\t\xef\x01\xc5\x7f'
                True
                'thread_count'   # b'\x81\xf6\x10\x016\xfb\xba\xed\x18\xf5\x18\xcex'
                '%Y-%m-%d_%H-%M-%S'   # b'\x81\xa7!^v\xf7\xf3\x97\x1f\xc5H\xe8!\xa9\xd5\xc8Jn'
                'use_data_base'   # b'\x81\xf7\x0b\x16\x0c\xfe\xbf\xc6\x1a\xc5\x0f\xc1\x7f\xe9'
                False
                'additives/parsing/'   # b'\x81\xe3\x1c\x17:\xee\xb7\xc4\x1e\xe9B\xd0m\xfe\xeb\x8c\x01Z\xf4'
                '_base.db'
                'usernames'   # b'\x81\xf7\x0b\x16!\xf4\xbf\xdf\x1e\xe9'
                (
                    'users'
                )
                'file_db'
                'can_not_create_database'   # b'\x81\xe1\x19\x1d\x0c\xf4\xb1\xc6$\xf9\x1f\xc5m\xf8\xfd\xba\x0b\\\xaf\xa6\xa8\xca]\xc9'
                'Groups'
                'parsing'
                '_Base.db'
                '_Parsing.db'   # b'\x81\xdd(\x12!\xe9\xb7\xdc\x1c\xb4\t\xc2'
                'Общая база данных'   # b'\x81R\xe6\xa3\xe2KWb\xcbK\xe2\x80\xdc=HU\xbf\x8a\x0bw\xea{\x9a|\xd5\xdf~\xec\xdd\x00\xf5T\xdf'
                'create_txt'   # b'\x81\xe1\n\x162\xee\xbb\xed\x0f\xe2\x19'
                '_Parsing.txt'   # b'\x81\xdd(\x12!\xe9\xb7\xdc\x1c\xb4\x19\xd8x'
                'a'
                (
                    'accounts'
                    'name'
                )
                (
                    'max_workers'
                )
                0
                'st_task'
                'st_stream'   # b'\x81\xf1\x0c, \xee\xac\xd7\x1a\xf7'
                'st_wait'
                'st_done'
                'Выполняю проверку на уникальность текстового файла основной базы'   # b'\x81R\xea\xa2\xd8Jab\xc5J\xd6p\xb1]\x174\xe1\x1d\x0bx\x1b+\xfe\x12\xb5\xbd\x13\x89\xb1Q\xae?\x8b\xb1`\xbdEzdn\xa9\nH\x80m\x00\xbf\x9d\x87=\xe6 6\x9c\xb60\x875*\xfc\xa9\xa9\x80\xbf\x17\xf9\xe73\x08\x876\x0er\xd3\xde\x8e\x9e\t\xda!\x7f7W\x19aO\xb3\xa5tg=5/\xaaic\xa4\xe0c\xc2\xda\xb8\xf9\x8c\x91\xafj2\x90W#\x8bkz\x02\xc9\xc8$\xe5\xdc\xc2\xa7'
                (
                    'message'
                )
                'Проверка выполнена, работа с файлом завершена'   # b'\x81R\xe7\xa2\xd3J`b\xc9J\xd8q\x8c\\"5\xdf\x1d\x0bu\x1b \xfe\x13\xb5\xb1\x13\x87\xb0l\xae0\x8a\x8f\x90\xdd\xd4\x8a\x05\xce\xa89H\x8cm\x06\xbe\xa5\x87=\x16Jf0\xb7\t\x87;+\xc4\xa8\x90\x81\x8d\xe7\x94E3\n\x87<\x0fA\xd2\xe9\x8f\xa0\x08\xe0!t7Y\x19o'
                'Общий результат:'   # b'\x81R\xe6\xa3\xe2KWb\xc3J\xd4\x80\xdd\x0cHP\xbf\x8a\nD\x1a\x10\xff \xb4\x8d\x13\x8c\xb1SD'
                'уникальных пользователей'   # b'\x81S\xfb\xa3\xeeJfb\xc1J\xddp\xb7]\x145\xd2\xecP\x16O\x8b\xfe\x13\xb5\xb1\x13\x87\xb1]\xae2\x8a\x8c\x90\xdf(\x1a\x05\xcc\xa8<H\x86m\r\xbf\x9e'
                (
                    'message'
                    'param'
                    'end'
                )
                '__pyarmor_exit_13961__'
                'Done'
            [Disassembly]
                0       NOP                             
                2       NOP                             
                4       PUSH_NULL                       
                6       LOAD_CONST                      2: '__pyarmor_enter_13960__'
                8       LOAD_CONST                      3: b'<COAddr>\x07\x00\x00\x1aJ\t\x00\x00\x00\x00\x00\x00\x00\x00\x00\x00\x00\x00\x00\x00'
                10      BUILD_TUPLE                     1
                12      CALL_FUNCTION_EX                0
                14      POP_TOP                         
                16      RESUME                          0
                18      NOP                             
                20      NOP                             
                22      NOP                             
                24      NOP                             
                26      NOP                             
                28      NOP                             
                30      LOAD_FAST                       4: stop_thread
                32      LOAD_ATTR                       1: is_set
                52      CALL                            0
                60      POP_JUMP_IF_FALSE               10 (to 82)
                62      LOAD_GLOBAL                     3: NULL + StopProgram
                72      CALL                            0
                80      RAISE_VARARGS                   1
                82      LOAD_GLOBAL                     5: NULL + check_get_settings
                92      LOAD_FAST                       0: data
                94      LOAD_ATTR                       7: get
                114     LOAD_CONST                      4: 'Settings'
                116     CALL                            1
                124     CALL                            1
                132     POP_TOP                         
                134     LOAD_FAST                       0: data
                136     LOAD_CONST                      5: 'Accounts'
                138     BINARY_SUBSCR                   
                142     STORE_FAST                      6: _var_var_4
                144     LOAD_GLOBAL                     9: NULL + isinstance
                154     LOAD_FAST                       6: _var_var_4
                156     LOAD_GLOBAL                     10: list
                166     CALL                            2
                174     POP_JUMP_IF_TRUE                3 (to 182)
                176     LOAD_FAST                       6: _var_var_4
                178     BUILD_LIST                      1
                180     STORE_FAST                      6: _var_var_4
                182     LOAD_GLOBAL                     13: NULL + int
                192     LOAD_GLOBAL                     15: NULL + len
                202     LOAD_FAST                       6: _var_var_4
                204     CALL                            1
                212     CALL                            1
                220     LOAD_CONST                      6: 1
                222     COMPARE_OP                      2 (<)
                226     POP_JUMP_IF_FALSE               44 (to 316)
                228     LOAD_GLOBAL                     17: NULL + eel
                238     LOAD_ATTR                       18: sendErrorBox
                258     LOAD_GLOBAL                     20: Lang
                268     PUSH_NULL                       
                270     LOAD_CONST                      1: '__pyarmor_assert_13959__'
                272     LOAD_CONST                      7: 'select_accounts_works'   # b'\x81\xf1\x1d\x1f6\xf9\xaa\xed\x1a\xf9\x0e\xcfy\xe2\xec\x960J\xb4\xb5\xa1\xd8'
                274     CALL                            1
                282     BINARY_SUBSCR                   
                286     CALL                            1
                294     POP_TOP                         
                296     LOAD_GLOBAL                     3: NULL + StopProgram
                306     CALL                            0
                314     RAISE_VARARGS                   1
                316     LOAD_FAST                       0: data
                318     LOAD_CONST                      4: 'Settings'
                320     BINARY_SUBSCR                   
                324     LOAD_ATTR                       7: get
                344     PUSH_NULL                       
                346     LOAD_CONST                      1: '__pyarmor_assert_13959__'
                348     LOAD_CONST                      8: 'thread_rules'   # b'\x81\xf6\x10\x016\xfb\xba\xed\t\xef\x01\xc5\x7f'
                350     CALL                            1
                358     CALL                            1
                366     LOAD_CONST                      9: True
                368     COMPARE_OP                      40 (==)
                372     POP_JUMP_IF_FALSE               36 (to 446)
                374     LOAD_GLOBAL                     13: NULL + int
                384     LOAD_FAST                       0: data
                386     LOAD_CONST                      4: 'Settings'
                388     BINARY_SUBSCR                   
                392     LOAD_ATTR                       7: get
                412     PUSH_NULL                       
                414     LOAD_CONST                      1: '__pyarmor_assert_13959__'
                416     LOAD_CONST                      10: 'thread_count'   # b'\x81\xf6\x10\x016\xfb\xba\xed\x18\xf5\x18\xcex'
                418     CALL                            1
                426     CALL                            1
                434     CALL                            1
                442     STORE_FAST                      7: _var_var_5
                444     JUMP_FORWARD                    11 (to 468)
                446     LOAD_FAST                       1: config
                448     PUSH_NULL                       
                450     LOAD_CONST                      1: '__pyarmor_assert_13959__'
                452     LOAD_CONST                      10: 'thread_count'   # b'\x81\xf6\x10\x016\xfb\xba\xed\x18\xf5\x18\xcex'
                454     CALL                            1
                462     BINARY_SUBSCR                   
                466     STORE_FAST                      7: _var_var_5
                468     LOAD_GLOBAL                     22: datetime
                478     LOAD_ATTR                       22: datetime
                498     LOAD_ATTR                       25: now
                518     CALL                            0
                526     LOAD_ATTR                       27: strftime
                546     PUSH_NULL                       
                548     LOAD_CONST                      1: '__pyarmor_assert_13959__'
                550     LOAD_CONST                      11: '%Y-%m-%d_%H-%M-%S'   # b'\x81\xa7!^v\xf7\xf3\x97\x1f\xc5H\xe8!\xa9\xd5\xc8Jn'
                552     CALL                            1
                560     CALL                            1
                568     STORE_FAST                      8: _var_var_6
                570     LOAD_FAST                       0: data
                572     LOAD_CONST                      4: 'Settings'
                574     BINARY_SUBSCR                   
                578     PUSH_NULL                       
                580     LOAD_CONST                      1: '__pyarmor_assert_13959__'
                582     LOAD_CONST                      12: 'use_data_base'   # b'\x81\xf7\x0b\x16\x0c\xfe\xbf\xc6\x1a\xc5\x0f\xc1\x7f\xe9'
                584     CALL                            1
                592     BINARY_SUBSCR                   
                596     LOAD_CONST                      13: False
                598     COMPARE_OP                      40 (==)
                602     POP_JUMP_IF_FALSE               149 (to 902)
                604     LOAD_GLOBAL                     29: NULL + db_base
                614     PUSH_NULL                       
                616     LOAD_CONST                      1: '__pyarmor_assert_13959__'
                618     LOAD_CONST                      14: 'additives/parsing/'   # b'\x81\xe3\x1c\x17:\xee\xb7\xc4\x1e\xe9B\xd0m\xfe\xeb\x8c\x01Z\xf4'
                620     CALL                            1
                628     LOAD_FAST                       8: _var_var_6
                630     FORMAT_VALUE                    0 (FVC_NONE)
                632     LOAD_CONST                      15: '_base.db'
                634     BUILD_STRING                    3
                636     CALL                            1
                644     LOAD_ATTR                       31: import_list
                664     LOAD_FAST                       0: data
                666     LOAD_CONST                      4: 'Settings'
                668     BINARY_SUBSCR                   
                672     LOAD_ATTR                       7: get
                692     PUSH_NULL                       
                694     LOAD_CONST                      1: '__pyarmor_assert_13959__'
                696     LOAD_CONST                      16: 'usernames'   # b'\x81\xf7\x0b\x16!\xf4\xbf\xdf\x1e\xe9'
                698     CALL                            1
                706     BUILD_LIST                      0
                708     CALL                            2
                716     KW_NAMES                        17: ('users',)
                718     CALL                            1
                726     LOAD_FAST                       0: data
                728     LOAD_CONST                      4: 'Settings'
                730     BINARY_SUBSCR                   
                734     LOAD_CONST                      18: 'file_db'
                736     STORE_SUBSCR                    
                740     LOAD_FAST                       0: data
                742     LOAD_CONST                      4: 'Settings'
                744     BINARY_SUBSCR                   
                748     LOAD_CONST                      18: 'file_db'
                750     BINARY_SUBSCR                   
                754     LOAD_CONST                      13: False
                756     COMPARE_OP                      40 (==)
                760     POP_JUMP_IF_FALSE               44 (to 850)
                762     LOAD_GLOBAL                     17: NULL + eel
                772     LOAD_ATTR                       18: sendErrorBox
                792     LOAD_GLOBAL                     20: Lang
                802     PUSH_NULL                       
                804     LOAD_CONST                      1: '__pyarmor_assert_13959__'
                806     LOAD_CONST                      19: 'can_not_create_database'   # b'\x81\xe1\x19\x1d\x0c\xf4\xb1\xc6$\xf9\x1f\xc5m\xf8\xfd\xba\x0b\\\xaf\xa6\xa8\xca]\xc9'
                808     CALL                            1
                816     BINARY_SUBSCR                   
                820     CALL                            1
                828     POP_TOP                         
                830     LOAD_GLOBAL                     3: NULL + StopProgram
                840     CALL                            0
                848     RAISE_VARARGS                   1
                850     LOAD_GLOBAL                     17: NULL + eel
                860     LOAD_ATTR                       32: WriteResult
                880     LOAD_CONST                      20: 'Groups'
                882     LOAD_CONST                      21: 'parsing'
                884     LOAD_FAST                       8: _var_var_6
                886     LOAD_CONST                      22: '_Base.db'
                888     BINARY_OP                       0 (+)
                892     CALL                            3
                900     POP_TOP                         
                902     LOAD_GLOBAL                     35: NULL + db_parsing
                912     PUSH_NULL                       
                914     LOAD_CONST                      1: '__pyarmor_assert_13959__'
                916     LOAD_CONST                      14: 'additives/parsing/'   # b'\x81\xe3\x1c\x17:\xee\xb7\xc4\x1e\xe9B\xd0m\xfe\xeb\x8c\x01Z\xf4'
                918     CALL                            1
                926     LOAD_FAST                       8: _var_var_6
                928     FORMAT_VALUE                    0 (FVC_NONE)
                930     PUSH_NULL                       
                932     LOAD_CONST                      1: '__pyarmor_assert_13959__'
                934     LOAD_CONST                      23: '_Parsing.db'   # b'\x81\xdd(\x12!\xe9\xb7\xdc\x1c\xb4\t\xc2'
                936     CALL                            1
                944     BUILD_STRING                    3
                946     CALL                            1
                954     LOAD_ATTR                       37: create
                974     CALL                            0
                982     STORE_FAST                      9: _var_var_7
                984     LOAD_GLOBAL                     17: NULL + eel
                994     LOAD_ATTR                       32: WriteResult
                1014    PUSH_NULL                       
                1016    LOAD_CONST                      1: '__pyarmor_assert_13959__'
                1018    LOAD_CONST                      24: 'Общая база данных'   # b'\x81R\xe6\xa3\xe2KWb\xcbK\xe2\x80\xdc=HU\xbf\x8a\x0bw\xea{\x9a|\xd5\xdf~\xec\xdd\x00\xf5T\xdf'
                1020    CALL                            1
                1028    LOAD_CONST                      21: 'parsing'
                1030    LOAD_FAST                       8: _var_var_6
                1032    FORMAT_VALUE                    0 (FVC_NONE)
                1034    PUSH_NULL                       
                1036    LOAD_CONST                      1: '__pyarmor_assert_13959__'
                1038    LOAD_CONST                      23: '_Parsing.db'   # b'\x81\xdd(\x12!\xe9\xb7\xdc\x1c\xb4\t\xc2'
                1040    CALL                            1
                1048    BUILD_STRING                    2
                1050    CALL                            3
                1058    POP_TOP                         
                1060    LOAD_FAST                       0: data
                1062    LOAD_CONST                      4: 'Settings'
                1064    BINARY_SUBSCR                   
                1068    PUSH_NULL                       
                1070    LOAD_CONST                      1: '__pyarmor_assert_13959__'
                1072    LOAD_CONST                      25: 'create_txt'   # b'\x81\xe1\n\x162\xee\xbb\xed\x0f\xe2\x19'
                1074    CALL                            1
                1082    BINARY_SUBSCR                   
                1086    LOAD_CONST                      9: True
                1088    COMPARE_OP                      40 (==)
                1092    POP_JUMP_IF_FALSE               77 (to 1248)
                1094    PUSH_NULL                       
                1096    LOAD_CONST                      1: '__pyarmor_assert_13959__'
                1098    LOAD_CONST                      14: 'additives/parsing/'   # b'\x81\xe3\x1c\x17:\xee\xb7\xc4\x1e\xe9B\xd0m\xfe\xeb\x8c\x01Z\xf4'
                1100    CALL                            1
                1108    LOAD_FAST                       8: _var_var_6
                1110    FORMAT_VALUE                    0 (FVC_NONE)
                1112    PUSH_NULL                       
                1114    LOAD_CONST                      1: '__pyarmor_assert_13959__'
                1116    LOAD_CONST                      26: '_Parsing.txt'   # b'\x81\xdd(\x12!\xe9\xb7\xdc\x1c\xb4\x19\xd8x'
                1118    CALL                            1
                1126    BUILD_STRING                    3
                1128    STORE_FAST                      10: _var_var_8
                1130    LOAD_GLOBAL                     39: NULL + open
                1140    LOAD_FAST                       10: _var_var_8
                1142    LOAD_CONST                      27: 'a'
                1144    CALL                            2
                1152    BEFORE_WITH                     
                1154    STORE_FAST                      11: _var_var_9
                1156    LOAD_CONST                      0: None
                1158    LOAD_CONST                      0: None
                1160    LOAD_CONST                      0: None
                1162    CALL                            2
                1170    POP_TOP                         
                1172    LOAD_GLOBAL                     17: NULL + eel
                1182    LOAD_ATTR                       32: WriteResult
                1202    PUSH_NULL                       
                1204    LOAD_CONST                      1: '__pyarmor_assert_13959__'
                1206    LOAD_CONST                      24: 'Общая база данных'   # b'\x81R\xe6\xa3\xe2KWb\xcbK\xe2\x80\xdc=HU\xbf\x8a\x0bw\xea{\x9a|\xd5\xdf~\xec\xdd\x00\xf5T\xdf'
                1208    CALL                            1
                1216    LOAD_CONST                      21: 'parsing'
                1218    LOAD_FAST                       8: _var_var_6
                1220    FORMAT_VALUE                    0 (FVC_NONE)
                1222    PUSH_NULL                       
                1224    LOAD_CONST                      1: '__pyarmor_assert_13959__'
                1226    LOAD_CONST                      26: '_Parsing.txt'   # b'\x81\xdd(\x12!\xe9\xb7\xdc\x1c\xb4\x19\xd8x'
                1228    CALL                            1
                1236    BUILD_STRING                    2
                1238    CALL                            3
                1246    POP_TOP                         
                1248    LOAD_GLOBAL                     41: NULL + set_task_manager
                1258    LOAD_FAST                       2: pid
                1260    LOAD_FAST                       6: _var_var_4
                1262    LOAD_CONST                      21: 'parsing'
                1264    KW_NAMES                        28: ('accounts', 'name')
                1266    CALL                            3
                1274    POP_TOP                         
                1276    LOAD_GLOBAL                     42: concurrent
                1286    LOAD_ATTR                       44: futures
                1306    LOAD_ATTR                       47: ThreadPoolExecutor
                1326    LOAD_FAST                       7: _var_var_5
                1328    KW_NAMES                        29: ('max_workers',)
                1330    CALL                            1
                1338    BEFORE_WITH                     
                1340    STORE_FAST                      12: _var_var_10
                1342    BUILD_LIST                      0
                1344    STORE_FAST                      13: _var_var_11
                1346    LOAD_GLOBAL                     15: NULL + len
                1356    LOAD_FAST                       6: _var_var_4
                1358    CALL                            1
                1366    STORE_FAST                      14: _var_var_12
                1368    LOAD_FAST                       7: _var_var_5
                1370    STORE_FAST                      15: _var_var_13
                1372    LOAD_FAST                       14: _var_var_12
                1374    STORE_FAST                      16: _var_var_14
                1376    LOAD_CONST                      30: 0
                1378    STORE_FAST                      17: _var_var_15
                1380    LOAD_GLOBAL                     17: NULL + eel
                1390    LOAD_ATTR                       48: StreamStat
                1410    LOAD_GLOBAL                     51: NULL + json
                1420    LOAD_ATTR                       52: dumps
                1440    LOAD_CONST                      31: 'st_task'
                1442    LOAD_FAST                       14: _var_var_12
                1444    PUSH_NULL                       
                1446    LOAD_CONST                      1: '__pyarmor_assert_13959__'
                1448    LOAD_CONST                      32: 'st_stream'   # b'\x81\xf1\x0c, \xee\xac\xd7\x1a\xf7'
                1450    CALL                            1
                1458    LOAD_FAST                       15: _var_var_13
                1460    LOAD_CONST                      33: 'st_wait'
                1462    LOAD_FAST                       16: _var_var_14
                1464    LOAD_CONST                      34: 'st_done'
                1466    LOAD_FAST                       17: _var_var_15
                1468    BUILD_MAP                       4
                1470    CALL                            1
                1478    CALL                            1
                1486    POP_TOP                         
                1488    LOAD_FAST                       6: _var_var_4
                1490    GET_ITER                        
                1492    FOR_ITER                        45 (to 1584)
                1496    STORE_FAST                      18: _var_var_16
                1498    LOAD_FAST                       13: _var_var_11
                1500    LOAD_ATTR                       55: append
                1520    LOAD_FAST                       12: _var_var_10
                1522    LOAD_ATTR                       57: submit
                1542    LOAD_GLOBAL                     58: worker
                1552    LOAD_FAST                       18: _var_var_16
                1554    LOAD_FAST                       1: config
                1556    LOAD_FAST                       3: proxy
                1558    LOAD_FAST                       0: data
                1560    LOAD_FAST                       9: _var_var_7
                1562    LOAD_FAST                       8: _var_var_6
                1564    LOAD_FAST                       4: stop_thread
                1566    CALL                            8
                1574    CALL                            1
                1582    POP_TOP                         
                1584    JUMP_BACKWARD                   47 (to 1492)
                1586    END_FOR                         
                1588    LOAD_GLOBAL                     42: concurrent
                1598    LOAD_ATTR                       44: futures
                1618    LOAD_ATTR                       61: as_completed
                1638    LOAD_FAST                       13: _var_var_11
                1640    CALL                            1
                1648    GET_ITER                        
                1650    FOR_ITER                        66 (to 1784)
                1654    STORE_FAST                      19: _var_var_17
                1656    LOAD_FAST                       17: _var_var_15
                1658    LOAD_CONST                      6: 1
                1660    BINARY_OP                       13 (+=)
                1664    STORE_FAST                      17: _var_var_15
                1666    LOAD_FAST                       16: _var_var_14
                1668    LOAD_CONST                      6: 1
                1670    BINARY_OP                       23 (-=)
                1674    STORE_FAST                      16: _var_var_14
                1676    LOAD_GLOBAL                     17: NULL + eel
                1686    LOAD_ATTR                       48: StreamStat
                1706    LOAD_GLOBAL                     51: NULL + json
                1716    LOAD_ATTR                       52: dumps
                1736    LOAD_CONST                      31: 'st_task'
                1738    LOAD_FAST                       14: _var_var_12
                1740    PUSH_NULL                       
                1742    LOAD_CONST                      1: '__pyarmor_assert_13959__'
                1744    LOAD_CONST                      32: 'st_stream'   # b'\x81\xf1\x0c, \xee\xac\xd7\x1a\xf7'
                1746    CALL                            1
                1754    LOAD_FAST                       15: _var_var_13
                1756    LOAD_CONST                      33: 'st_wait'
                1758    LOAD_FAST                       16: _var_var_14
                1760    LOAD_CONST                      34: 'st_done'
                1762    LOAD_FAST                       17: _var_var_15
                1764    BUILD_MAP                       4
                1766    CALL                            1
                1774    CALL                            1
                1782    POP_TOP                         
                1784    JUMP_BACKWARD                   68 (to 1650)
                1786    END_FOR                         
                1788    NOP                             
                1790    LOAD_CONST                      0: None
                1792    LOAD_CONST                      0: None
                1794    LOAD_CONST                      0: None
                1796    CALL                            2
                1804    POP_TOP                         
                1806    LOAD_FAST                       0: data
                1808    LOAD_CONST                      4: 'Settings'
                1810    BINARY_SUBSCR                   
                1814    PUSH_NULL                       
                1816    LOAD_CONST                      1: '__pyarmor_assert_13959__'
                1818    LOAD_CONST                      25: 'create_txt'   # b'\x81\xe1\n\x162\xee\xbb\xed\x0f\xe2\x19'
                1820    CALL                            1
                1828    BINARY_SUBSCR                   
                1832    LOAD_CONST                      9: True
                1834    COMPARE_OP                      40 (==)
                1838    POP_JUMP_IF_FALSE               77 (to 1994)
                1840    LOAD_GLOBAL                     63: NULL + Logs
                1850    LOAD_ATTR                       64: PrintLog
                1870    PUSH_NULL                       
                1872    LOAD_CONST                      1: '__pyarmor_assert_13959__'
                1874    LOAD_CONST                      35: 'Выполняю проверку на уникальность текстового файла основной базы'   # b'\x81R\xea\xa2\xd8Jab\xc5J\xd6p\xb1]\x174\xe1\x1d\x0bx\x1b+\xfe\x12\xb5\xbd\x13\x89\xb1Q\xae?\x8b\xb1`\xbdEzdn\xa9\nH\x80m\x00\xbf\x9d\x87=\xe6 6\x9c\xb60\x875*\xfc\xa9\xa9\x80\xbf\x17\xf9\xe73\x08\x876\x0er\xd3\xde\x8e\x9e\t\xda!\x7f7W\x19aO\xb3\xa5tg=5/\xaaic\xa4\xe0c\xc2\xda\xb8\xf9\x8c\x91\xafj2\x90W#\x8bkz\x02\xc9\xc8$\xe5\xdc\xc2\xa7'
                1876    CALL                            1
                1884    KW_NAMES                        36: ('message',)
                1886    CALL                            1
                1894    POP_TOP                         
                1896    LOAD_GLOBAL                     67: NULL + txt_file
                1906    LOAD_ATTR                       68: unic
                1926    LOAD_FAST_CHECK                 10: _var_var_8
                1928    CALL                            1
                1936    STORE_FAST                      20: _var_var_18
                1938    LOAD_GLOBAL                     63: NULL + Logs
                1948    LOAD_ATTR                       64: PrintLog
                1968    PUSH_NULL                       
                1970    LOAD_CONST                      1: '__pyarmor_assert_13959__'
                1972    LOAD_CONST                      37: 'Проверка выполнена, работа с файлом завершена'   # b'\x81R\xe7\xa2\xd3J`b\xc9J\xd8q\x8c\\"5\xdf\x1d\x0bu\x1b \xfe\x13\xb5\xb1\x13\x87\xb0l\xae0\x8a\x8f\x90\xdd\xd4\x8a\x05\xce\xa89H\x8cm\x06\xbe\xa5\x87=\x16Jf0\xb7\t\x87;+\xc4\xa8\x90\x81\x8d\xe7\x94E3\n\x87<\x0fA\xd2\xe9\x8f\xa0\x08\xe0!t7Y\x19o'
                1974    CALL                            1
                1982    KW_NAMES                        36: ('message',)
                1984    CALL                            1
                1992    POP_TOP                         
                1994    LOAD_GLOBAL                     35: NULL + db_parsing
                2004    LOAD_FAST                       9: _var_var_7
                2006    CALL                            1
                2014    LOAD_ATTR                       71: get_users_count
                2034    CALL                            0
                2042    STORE_FAST                      20: _var_var_18
                2044    LOAD_GLOBAL                     63: NULL + Logs
                2054    LOAD_ATTR                       64: PrintLog
                2074    PUSH_NULL                       
                2076    LOAD_CONST                      1: '__pyarmor_assert_13959__'
                2078    LOAD_CONST                      38: 'Общий результат:'   # b'\x81R\xe6\xa3\xe2KWb\xc3J\xd4\x80\xdd\x0cHP\xbf\x8a\nD\x1a\x10\xff \xb4\x8d\x13\x8c\xb1SD'
                2080    CALL                            1
                2088    LOAD_FAST                       20: _var_var_18
                2090    PUSH_NULL                       
                2092    LOAD_CONST                      1: '__pyarmor_assert_13959__'
                2094    LOAD_CONST                      39: 'уникальных пользователей'   # b'\x81S\xfb\xa3\xeeJfb\xc1J\xddp\xb7]\x145\xd2\xecP\x16O\x8b\xfe\x13\xb5\xb1\x13\x87\xb1]\xae2\x8a\x8c\x90\xdf(\x1a\x05\xcc\xa8<H\x86m\r\xbf\x9e'
                2096    CALL                            1
                2104    KW_NAMES                        40: ('message', 'param', 'end')
                2106    CALL                            3
                2114    POP_TOP                         
                2116    LOAD_GLOBAL                     77: NULL + del_task_manager
                2126    LOAD_FAST                       2: pid
                2128    CALL                            1
                2136    POP_TOP                         
                2138    LOAD_GLOBAL                     79: NULL + StopDetect
                2148    LOAD_FAST                       4: stop_thread
                2150    CALL                            1
                2158    POP_TOP                         
                2160    NOP                             
                2162    LOAD_CONST                      42: 'Done'
                2164    NOP                             
                2166    NOP                             
                2168    NOP                             
                2170    JUMP_FORWARD                    130 (to 2432)
                2178    POP_TOP                         
                2180    RETURN_CONST                    42: 'Done'
                2182    PUSH_EXC_INFO                   
                2184    WITH_EXCEPT_START               
                2186    POP_JUMP_IF_TRUE                1 (to 2190)
                2188    RERAISE                         2
                2190    POP_TOP                         
                2192    POP_EXCEPT                      
                2194    POP_TOP                         
                2196    POP_TOP                         
                2198    JUMP_BACKWARD                   515 (to 1172)
                2202    COPY                            3
                2204    POP_EXCEPT                      
                2206    RERAISE                         1
                2208    PUSH_EXC_INFO                   
                2210    WITH_EXCEPT_START               
                2212    POP_JUMP_IF_TRUE                1 (to 2216)
                2214    RERAISE                         2
                2216    POP_TOP                         
                2218    POP_EXCEPT                      
                2220    POP_TOP                         
                2222    POP_TOP                         
                2224    JUMP_BACKWARD                   210 (to 1806)
                2226    COPY                            3
                2228    POP_EXCEPT                      
                2230    RERAISE                         1
                2232    PUSH_EXC_INFO                   
                2234    LOAD_GLOBAL                     2: StopProgram
                2244    CHECK_EXC_MATCH                 
                2246    POP_JUMP_IF_FALSE               3 (to 2254)
                2248    POP_TOP                         
                2250    POP_EXCEPT                      
                2252    JUMP_BACKWARD                   69 (to 2116)
                2254    LOAD_GLOBAL                     72: BaseException
                2264    CHECK_EXC_MATCH                 
                2266    POP_JUMP_IF_FALSE               26 (to 2320)
                2268    STORE_FAST                      21: _var_var_3
                2270    PUSH_NULL                       
                2272    LOAD_GLOBAL                     75: NULL + logging
                2282    LOAD_FAST                       21: _var_var_3
                2284    CALL                            1
                2292    CALL                            0
                2300    POP_TOP                         
                2302    POP_EXCEPT                      
                2304    LOAD_CONST                      0: None
                2306    STORE_FAST                      21: _var_var_3
                2308    DELETE_FAST                     21: _var_var_3
                2310    JUMP_BACKWARD                   98 (to 2116)
                2312    LOAD_CONST                      0: None
                2314    STORE_FAST                      21: _var_var_3
                2316    DELETE_FAST                     21: _var_var_3
                2318    RERAISE                         1
                2320    RERAISE                         0
                2322    COPY                            3
                2324    POP_EXCEPT                      
                2326    RERAISE                         1
                2328    PUSH_EXC_INFO                   
                2330    LOAD_GLOBAL                     77: NULL + del_task_manager
                2340    LOAD_FAST                       2: pid
                2342    CALL                            1
                2350    POP_TOP                         
                2352    LOAD_GLOBAL                     79: NULL + StopDetect
                2362    LOAD_FAST                       4: stop_thread
                2364    CALL                            1
                2372    POP_TOP                         
                2374    POP_TOP                         
                2376    POP_EXCEPT                      
                2378    LOAD_CONST                      42: 'Done'
                2380    NOP                             
                2382    NOP                             
                2384    NOP                             
                2386    JUMP_FORWARD                    22 (to 2432)
                2394    POP_TOP                         
                2396    RETURN_CONST                    42: 'Done'
                2398    COPY                            3
                2400    POP_EXCEPT                      
                2402    RERAISE                         1
                2404    PUSH_EXC_INFO                   
                2406    PUSH_NULL                       
                2408    LOAD_CONST                      41: '__pyarmor_exit_13961__'
                2410    NOP                             
                2412    LOAD_CONST                      3: b'<COAddr>\x07\x00\x00\x1aJ\t\x00\x00\x00\x00\x00\x00\x00\x00\x00\x00\x00\x00\x00\x00'
                2414    CALL                            1
                2422    POP_TOP                         
                2424    RERAISE                         0
                2426    COPY                            3
                2428    POP_EXCEPT                      
                2430    RERAISE                         1
                2432    PUSH_NULL                       
                2434    LOAD_CONST                      41: '__pyarmor_exit_13961__'
                2436    LOAD_CONST                      3: b'<COAddr>\x07\x00\x00\x1aJ\t\x00\x00\x00\x00\x00\x00\x00\x00\x00\x00\x00\x00\x00\x00'
                2438    BUILD_TUPLE                     1
                2440    CALL_FUNCTION_EX                0
                2442    POP_TOP                         
                2444    RETURN_VALUE                    
            [Exception Table]
                30 to 1154 -> 2232 [0] 
                1154 to 1156 -> 2182 [1] lasti
                1156 to 1340 -> 2232 [0] 
                1340 to 1788 -> 2208 [1] lasti
                1790 to 2116 -> 2232 [0] 
                2116 to 2160 -> 2404 [0] 
                2182 to 2192 -> 2202 [3] lasti
                2192 to 2208 -> 2232 [0] 
                2208 to 2218 -> 2226 [3] lasti
                2218 to 2232 -> 2232 [0] 
                2232 to 2250 -> 2322 [1] lasti
                2250 to 2254 -> 2328 [0] 
                2254 to 2270 -> 2322 [1] lasti
                2270 to 2302 -> 2312 [1] lasti
                2302 to 2312 -> 2328 [0] 
                2312 to 2322 -> 2322 [1] lasti
                2322 to 2328 -> 2328 [0] 
                2328 to 2376 -> 2398 [1] lasti
                2376 to 2378 -> 2404 [0] 
                2398 to 2404 -> 2404 [0] 
                2404 to 2426 -> 2426 [1] lasti
        [Code]
            File Name: <frozen program.modules.Parsing>
            Object Name: worker
            Qualified Name: worker
            Arg Count: 7
            Pos Only Arg Count: 0
            KW Only Arg Count: 0
            Stack Size: 17
            Flags: 0x20000003 (CO_OPTIMIZED | CO_NEWLOCALS | CO_PYARMOR_OBFUSCATED)
            [Names]
                'Thread_wait'
                'account_works'
                'Lang'
                'Disconnect'
                'db_parsing_res'
                'disconnect'
                'Logs'
                'PrintLog'
                'get'
                'int'
                'db_base'
                'tg_links'
                '_correct_private'
                'tg_group'
                'go_to'
                'update'
                'entity'
                'check'
                'type'
                'dict'
                'is_set'
                'StopProgram'
                'get_hash'
                'standart'
                'connect'
                'create'
                'eel'
                'WriteResult'
                'functions'
                'channels'
                'GetFullChannelRequest'
                'full_chat'
                'participants_count'
                'iter_participants'
                'types'
                'ChannelParticipantsAdmins'
                'append'
                'id'
                'insert_group'
                'InputChannel'
                'access_hash'
                'len'
                'time'
                'sleep'
                'GetParticipantsRequest'
                'ChannelParticipantsSearch'
                'users'
                'parsing_time'
                'insert_user'
                'errors'
                'ChannelPrivateError'
                'DelayOnline'
                'is_connected'
                'FloodWaitError'
                'seconds'
                'ConnectionError'
                'account'
                'UpdateStatusRequest'
                'round'
                'BaseException'
                'logging'
                'go_out'
                'db_parsing'
                'check_gender'
                'get_users_count'
                'union'
                'create_txt'
            [Locals+Names]
                'account'
                'config'
                'proxy'
                'data'
                'db_result'
                'timestamp'
                'stop_thread'
                '__assert_armored__'
                '_var_var_19'
                '_var_var_20'
                '_var_var_21'
                '_var_var_22'
                '_var_var_23'
                '_var_var_24'
                '_var_var_25'
                '_var_var_26'
                '_var_var_27'
                '_var_var_28'
                '_var_var_29'
                '_var_var_30'
                '_var_var_31'
                '_var_var_32'
                '_var_var_33'
                '_var_var_34'
                '_var_var_35'
                '_var_var_36'
                '_var_var_37'
                '_var_var_38'
                '_var_var_39'
                '_var_var_40'
                '_var_var_41'
                '_var_var_42'
                '_var_var_43'
                '_var_var_44'
                '_var_var_45'
                '_var_var_46'
                '_var_var_47'
                '_var_var_48'
                '_var_var_49'
                '_var_var_50'
                '_var_var_18'
                '_var_var_51'
                '_var_var_52'
                '_var_var_53'
                '_var_var_54'
                '_var_var_55'
                '_var_var_56'
                '_var_var_57'
                '_var_var_58'
                '_var_var_59'
                '_var_var_60'
                '_var_var_61'
                '_var_var_62'
                '_var_var_63'
                '_var_var_64'
                '_var_var_3'
                '_var_var_65'
                '_var_var_66'
            [Constants]
                None
                '__pyarmor_assert_13962__'
                '__pyarmor_enter_13963__'
                b'<COAddr>\x07\x00\x00\x1av"\x00\x00\x00\x00\x00\x00\x00\x00\x00\x00\x00\x00\x00\x00'
                'Parsing'
                (
                    'module'
                )
                False
                'Error'
                (
                    'account'
                    'status'
                )
                'work_account_completed'   # b'\x81\xf5\x17\x018\xc5\xbf\xd1\x18\xf5\x18\xcex\xd3\xfb\x8a\x02M\xb7\xa2\xbe\xceJ'
                (
                    'config'
                    'account'
                    'message'
                )
                'done'
                '__pyarmor_exit_13964__'
                'Settings'
                'file_db'
                'parsing_days'   # b'\x81\xf2\x19\x01 \xf3\xb0\xd5$\xfe\x0c\xd9\x7f'
                'users_en'
                'users_ru'
                'users_cn'
                'users_ar'
                'users_he'
                'users_fa'
                'users_add'   # b'\x81\xf7\x0b\x16!\xe9\x81\xd3\x1f\xfe'
                'leave_group'   # b'\x81\xee\x1d\x12%\xff\x81\xd5\t\xf5\x18\xd0'
                'check_gender'   # b'\x81\xe1\x10\x160\xf1\x81\xd5\x1e\xf4\t\xc5~'
                'create_txt'   # b'\x81\xe1\n\x162\xee\xbb\xed\x0f\xe2\x19'
                'max_flood_wait'   # b'\x81\xef\x19\x0b\x0c\xfc\xb2\xdd\x14\xfe2\xd7m\xe5\xec'
                'exclude_admins'   # b'\x81\xe7\x00\x10?\xef\xba\xd7$\xfb\t\xcde\xe2\xeb'
                'NO_GROUP'
                'database_none_groups'   # b'\x81\xe6\x19\x072\xf8\xbf\xc1\x1e\xc5\x03\xcfb\xe9\xc7\x82\x1dR\xae\xb7\xb9'
                'EmptyGroups'   # b"\x81\xc7\x15\x03'\xe3\x99\xc0\x14\xef\x1d\xd3"
                1
                (
                    'config'
                    'client'
                    'account'
                    'group_link'
                    'max_flood_wait'
                    'lang'
                    'stop_thread'
                )
                'FloodWait'   # b'\x81\xc4\x14\x1c<\xfe\x89\xd3\x12\xee'
                'channel_not_found'   # b'\x81\xe1\x10\x12=\xf4\xbb\xde$\xf4\x02\xd4S\xea\xf7\x90\x01Y'
                (
                    'config'
                    'account'
                    'message'
                    'param'
                )
                'NotFound'
                'type'
                'group'
                'pupsik_get_error'   # b'\x81\xf2\r\x03 \xf3\xb5\xed\x1c\xff\x19\xffi\xfe\xea\x8a\x1d'
                'pupsik_get_not_channel'   # b'\x81\xf2\r\x03 \xf3\xb5\xed\x1c\xff\x19\xffb\xe3\xec\xba\x0cU\xba\xa9\xa4\xceB'
                'pupsik_shutdown_account'   # b'\x81\xf2\r\x03 \xf3\xb5\xed\x08\xf2\x18\xd4h\xe3\xef\x8b0\\\xb8\xa4\xa5\xde@\xd8'
                'NotGroup'
                'success_joined_channel'   # b'\x81\xf1\r\x100\xff\xad\xc1$\xf0\x02\xc9b\xe9\xfc\xba\x0cU\xba\xa9\xa4\xceB'
                'Entered'
                '_'
                '.db'
                '.txt'
                'additives/parsing/'   # b'\x81\xe3\x1c\x17:\xee\xb7\xc4\x1e\xe9B\xd0m\xfe\xeb\x8c\x01Z\xf4'
                '_Parsing.txt'   # b'\x81\xdd(\x12!\xe9\xb7\xdc\x1c\xb4\x19\xd8x'
                0
                'Group'
                'parsing'
                'add_to_database'   # b'\x81\xe3\x1c\x17\x0c\xee\xb1\xed\x1f\xfb\x19\xc1n\xed\xeb\x80'
                (
                    'channel'
                )
                (
                    'filter'
                )
                'info'
                'id'
                'title'
                'photo'
                'invite'
                'send_messages'   # b'\x81\xf1\x1d\x1d7\xc5\xb3\xd7\x08\xe9\x0c\xc7i\xff'
                'send_media'   # b'\x81\xf1\x1d\x1d7\xc5\xb3\xd7\x1f\xf3\x0c'
                'send_stickers'   # b'\x81\xf1\x1d\x1d7\xc5\xad\xc6\x12\xf9\x06\xc5~\xff'
                'send_polls'   # b'\x81\xf1\x1d\x1d7\xc5\xae\xdd\x17\xf6\x1e'
                'slow_mode'   # b'\x81\xf1\x14\x1c$\xc5\xb3\xdd\x1f\xff'
                'scam'
                'types'
                'Ready'
                (
                    '_connect'
                    'group_id'
                    'username'
                    'title'
                    'count'
                    'photo'
                    'invite'
                    'send_messages'
                    'send_media'
                    'send_stickers'
                    'send_pools'
                    'slow_mode'
                    'scam'
                    'types'
                    'status'
                )
                'im_starting_to_gather'   # b'\x81\xeb\x15, \xee\xbf\xc0\x0f\xf3\x03\xc7S\xf8\xf7\xba\x08\\\xaf\xaf\xaf\xd9'
                (
                    'channel_id'
                    'access_hash'
                )
                (
                    'a'
                    'b'
                    'c'
                    'd'
                    'e'
                    'f'
                    'g'
                    'h'
                    'i'
                    'j'
                    'k'
                    'l'
                    'm'
                    'n'
                    'o'
                    'p'
                    'q'
                    'r'
                    's'
                    't'
                    'u'
                    'v'
                    'w'
                    'x'
                    'y'
                    'z'
                )
                (
                    'о'
                    'е'
                    'а'
                    'и'
                    'н'
                    'т'
                    'с'
                    'р'
                    'в'
                    'л'
                    'к'
                    'м'
                    'д'
                    'п'
                    'у'
                    'я'
                    'ы'
                )
                (
                    '的'
                    '一'
                    '是'
                    '不'
                    '了'
                    '人'
                    '我'
                    '在'
                    '有'
                    '他'
                    '这'
                    '中'
                    '大'
                    '来'
                    '上'
                    '国'
                    '个'
                    '到'
                    '说'
                    '们'
                    '为'
                    '子'
                    '和'
                    '你'
                    '地'
                    '出'
                    '道'
                    '也'
                    '时'
                    '年'
                    '得'
                    '就'
                    '那'
                    '要'
                    '下'
                    '以'
                    '生'
                    '会'
                    '自'
                    '着'
                    '去'
                    '之'
                    '过'
                    '家'
                    '学'
                    '对'
                    '可'
                    '她'
                    '里'
                    '后'
                )
                (
                    'ا'
                    'ب'
                    'ت'
                    'ث'
                    'ج'
                    'ح'
                    'خ'
                    'د'
                    'ذ'
                    'ر'
                    'ز'
                    'س'
                    'ش'
                    'ص'
                    'ض'
                    'ط'
                    'ظ'
                    'ع'
                    'غ'
                    'ف'
                    'ق'
                    'ك'
                    'ل'
                    'م'
                    'ن'
                    'ه'
                    'و'
                    'ي'
                )
                (
                    'א'
                    'ב'
                    'ג'
                    'ד'
                    'ה'
                    'ו'
                    'ז'
                    'ח'
                    'ט'
                    'ך'
                    'כ'
                    'ל'
                    'ם'
                    'מ'
                    'ן'
                    'נ'
                    'ס'
                    'ע'
                    'ף'
                    'פ'
                    'ץ'
                    'צ'
                    'ק'
                    'ר'
                    'ש'
                    'ת'
                )
                (
                    'همزه'
                    'الف'
                    'ب'
                    'پ'
                    'ت'
                    'ث'
                    'جیم'
                    'چ'
                    'ح'
                    'خ'
                    'دال'
                    'ذال'
                    'ر'
                    'ز'
                    'ژ'
                    'سین'
                    'شین'
                    'صاد'
                    'ضاد'
                    'طا'
                    'ظا'
                    'عین'
                    'غین'
                    'ف'
                    'قاف'
                    'کاف'
                    'گاف'
                    'لام'
                    'میم'
                    'نون'
                    'واو'
                    'ه'
                    'ی'
                )
                (
                    '😊'
                    '👍'
                    '😀'
                    '☺'
                    '🤓'
                    '😁'
                    '👌'
                    '🧐'
                    '🙈'
                    '😌'
                    '😉'
                    '👇'
                    '👉'
                    '😃'
                    '😀'
                    '😃'
                    '😄'
                    '😅'
                    '🙃'
                    '🙂'
                    '☺'
                    '️😊'
                    '😎'
                    '😏'
                    '🤔'
                    '🤭'
                    '👐'
                    '🤝'
                    '👍'
                    '🤟'
                    '✌'
                    '️👌'
                    '✋'
                    '🖐'
                    '🙏'
                    '🐰'
                    '🐹'
                    '🐭'
                    '🐱'
                    '🐯'
                    '🦁'
                    '🐮'
                    '🐷'
                    '🙈'
                    '🐵'
                    '🙊'
                    '🐶'
                    '☀'
                    '️🌤'
                    '☂'
                    '️🚗'
                    '🚕'
                    '🚙'
                    '📞'
                    '☎'
                    '️✡'
                    '️💟'
                    '❤'
                    '️✅'
                    '🕐'
                    '🕑'
                    '💲'
                    '🚬'
                )
                100
                200
                True
                30
                'circumventing_restriction'   # b'\x81\xe1\x11\x010\xef\xb3\xc4\x1e\xf4\x19\xc9b\xeb\xc7\x97\nN\xaf\xb5\xa3\xc8Z\xc5\na'
                5
                (
                    'channel'
                    'filter'
                    'offset'
                    'limit'
                    'hash'
                )
                (
                    'parsing_days'
                )
                'user'
                '_connect'
                'user_id'
                'group_id'
                'mess_id'
                'comm_id'
                'phone'
                'username'
                'first_name'
                'first_name'   # b'\x81\xe4\x11\x01 \xee\x81\xdc\x1a\xf7\x08'
                'last_name'
                'last_name'   # b"\x81\xee\x19\x00'\xc5\xb0\xd3\x16\xff"
                'bio'
                'gender'
                'premium'
                'status'
                'time'
                'invite_status'
                'invite_status'   # b'\x81\xeb\x16\x05:\xee\xbb\xed\x08\xee\x0c\xd4y\xff'
                'send_status'
                'send_status'   # b'\x81\xf1\x1d\x1d7\xc5\xad\xc6\x1a\xee\x18\xd3'
                'stumbled_restriction_bypass'   # b'\x81\xf1\x0c\x06>\xf8\xb2\xd7\x1f\xc5\x1f\xc5\x7f\xf8\xea\x8c\x0cI\xb2\xa8\xa4\xf4L\xd5\x15n\xb0O'
                45
                65
                3
                'algorithm_error'   # b'\x81\xe3\x14\x14<\xe8\xb7\xc6\x13\xf72\xc5~\xfe\xf7\x97'
                'restriction_detected'   # b"\x81\xf0\x1d\x00'\xe8\xb7\xd1\x0f\xf3\x02\xceS\xe8\xfd\x91\n^\xaf\xa2\xae"
                'flood_wait_sec'   # b'\x81\xe4\x14\x1c<\xfe\x81\xc5\x1a\xf3\x19\xff\x7f\xe9\xfb'
                'algorithm_running'   # b'\x81\xe3\x14\x14<\xe8\xb7\xc6\x13\xf72\xd2y\xe2\xf6\x8c\x01Z'
                'waiting_time_longer'   # b"\x81\xf5\x19\x1a'\xf3\xb0\xd5$\xee\x04\xcdi\xd3\xf4\x8a\x01Z\xbe\xb5"
                'shutting_down_my_account'   # b"\x81\xf1\x10\x06'\xee\xb7\xdc\x1c\xc5\t\xcf{\xe2\xc7\x88\x16b\xba\xa4\xa9\xc4[\xc2\x11"
                10
                'Wait'
                'sec'
                (
                    'config'
                    'account'
                    'message'
                    'param'
                    'end'
                )
                (
                    'offline'
                )
                'parsing_done'   # b'\x81\xf2\x19\x01 \xf3\xb0\xd5$\xfe\x02\xcei'
                'collection_users_stopped'   # b'\x81\xe1\x17\x1f?\xff\xbd\xc6\x12\xf5\x03\xffy\xff\xfd\x97\x1cb\xa8\xb3\xa5\xdb^\xc9\x01'
                'users_corresponding_database'   # b'\x81\xf7\x0b\x16!\xe9\x81\xd1\x14\xe8\x1f\xc5\x7f\xfc\xf7\x8b\x0bT\xb5\xa0\x95\xcfO\xd8\x04m\xa2O\x05'
                (
                    'config'
                    'client'
                    'account'
                    'max_flood_wait'
                    'lang'
                    'stop_thread'
                )
                (
                    'entity'
                )
                'left_group'   # b"\x81\xee\x1d\x15'\xc5\xb9\xc0\x14\xef\x1d"
                'parsing_check_gender'   # b'\x81\xf2\x19\x01 \xf3\xb0\xd5$\xf9\x05\xc5o\xe7\xc7\x82\nS\xbf\xa2\xb8'
                'parsing_gender_men'   # b'\x81\xf2\x19\x01 \xf3\xb0\xd5$\xfd\x08\xceh\xe9\xea\xba\x02X\xb5'
                'male'
                'parsing_gender_women'   # b'\x81\xf2\x19\x01 \xf3\xb0\xd5$\xfd\x08\xceh\xe9\xea\xba\x18R\xb6\xa2\xa4'
                'female'
                'parsing_gender_un'   # b'\x81\xf2\x19\x01 \xf3\xb0\xd5$\xfd\x08\xceh\xe9\xea\xba\x1aS'
                'un'
                'parsing_gender_total'   # b'\x81\xf2\x19\x01 \xf3\xb0\xd5$\xfd\x08\xceh\xe9\xea\xba\x1bR\xaf\xa6\xa6'
                'count'
                'parsing_collect_users'   # b'\x81\xf2\x19\x01 \xf3\xb0\xd5$\xf9\x02\xcc`\xe9\xfb\x910H\xa8\xa2\xb8\xd8'
                'parsing_add_gen_db'   # b'\x81\xf2\x19\x01 \xf3\xb0\xd5$\xfb\t\xc4S\xeb\xfd\x8b0Y\xb9'
                'users'
                'Done'
                'Группа'
                (
                )
            [Disassembly]
                0       NOP                             
                2       NOP                             
                4       PUSH_NULL                       
                6       LOAD_CONST                      2: '__pyarmor_enter_13963__'
                8       LOAD_CONST                      3: b'<COAddr>\x07\x00\x00\x1av"\x00\x00\x00\x00\x00\x00\x00\x00\x00\x00\x00\x00\x00\x00'
                10      BUILD_TUPLE                     1
                12      CALL_FUNCTION_EX                0
                14      POP_TOP                         
                16      RESUME                          0
                18      NOP                             
                20      NOP                             
                22      NOP                             
                24      NOP                             
                26      NOP                             
                28      NOP                             
                30      LOAD_GLOBAL                     1: NULL + Thread_wait
                40      LOAD_FAST                       3: data
                42      LOAD_FAST                       1: config
                44      LOAD_FAST                       6: stop_thread
                46      CALL                            3
                54      POP_TOP                         
                56      LOAD_GLOBAL                     3: NULL + account_works
                66      LOAD_FAST                       1: config
                68      LOAD_GLOBAL                     4: Lang
                78      LOAD_FAST                       2: proxy
                80      LOAD_FAST                       0: account
                82      LOAD_FAST                       6: stop_thread
                84      LOAD_CONST                      4: 'Parsing'
                86      KW_NAMES                        5: ('module',)
                88      CALL                            6
                96      STORE_FAST                      8: _var_var_19
                98      LOAD_FAST                       8: _var_var_19
                100     LOAD_CONST                      6: False
                102     COMPARE_OP                      40 (==)
                106     POP_JUMP_IF_FALSE               89 (to 286)
                108     LOAD_FAST                       0: account
                110     LOAD_CONST                      7: 'Error'
                112     LOAD_CONST                      8: ('account', 'status')
                114     BUILD_CONST_KEY_MAP             2
                116     LOAD_GLOBAL                     7: NULL + Disconnect
                126     LOAD_FAST                       8: _var_var_19
                128     CALL                            1
                136     POP_TOP                         
                138     LOAD_GLOBAL                     9: NULL + db_parsing_res
                148     LOAD_ATTR                       10: disconnect
                168     LOAD_FAST_CHECK                 9: _var_var_20
                170     CALL                            1
                178     POP_TOP                         
                180     LOAD_GLOBAL                     13: NULL + Logs
                190     LOAD_ATTR                       14: PrintLog
                210     LOAD_FAST                       1: config
                212     LOAD_FAST                       0: account
                214     LOAD_GLOBAL                     4: Lang
                224     PUSH_NULL                       
                226     LOAD_CONST                      1: '__pyarmor_assert_13962__'
                228     LOAD_CONST                      9: 'work_account_completed'   # b'\x81\xf5\x17\x018\xc5\xbf\xd1\x18\xf5\x18\xcex\xd3\xfb\x8a\x02M\xb7\xa2\xbe\xceJ'
                230     CALL                            1
                238     BINARY_SUBSCR                   
                242     KW_NAMES                        10: ('config', 'account', 'message')
                244     CALL                            3
                252     POP_TOP                         
                254     LOAD_FAST                       0: account
                256     LOAD_CONST                      11: 'done'
                258     LOAD_CONST                      8: ('account', 'status')
                260     BUILD_CONST_KEY_MAP             2
                262     SWAP                            2
                264     POP_TOP                         
                266     NOP                             
                268     NOP                             
                270     JUMP_FORWARD                    4301 (to 8876)
                274     CALL                            1
                282     POP_TOP                         
                284     RETURN_VALUE                    
                286     LOAD_FAST                       3: data
                288     LOAD_CONST                      13: 'Settings'
                290     BINARY_SUBSCR                   
                294     LOAD_ATTR                       17: get
                314     LOAD_CONST                      14: 'file_db'
                316     CALL                            1
                324     STORE_FAST                      10: _var_var_21
                326     LOAD_GLOBAL                     19: NULL + int
                336     LOAD_FAST                       3: data
                338     LOAD_CONST                      13: 'Settings'
                340     BINARY_SUBSCR                   
                344     LOAD_ATTR                       17: get
                364     PUSH_NULL                       
                366     LOAD_CONST                      1: '__pyarmor_assert_13962__'
                368     LOAD_CONST                      15: 'parsing_days'   # b'\x81\xf2\x19\x01 \xf3\xb0\xd5$\xfe\x0c\xd9\x7f'
                370     CALL                            1
                378     CALL                            1
                386     CALL                            1
                394     STORE_FAST                      11: _var_var_22
                396     LOAD_FAST                       3: data
                398     LOAD_CONST                      13: 'Settings'
                400     BINARY_SUBSCR                   
                404     LOAD_ATTR                       17: get
                424     LOAD_CONST                      16: 'users_en'
                426     CALL                            1
                434     STORE_FAST                      12: _var_var_23
                436     LOAD_FAST                       3: data
                438     LOAD_CONST                      13: 'Settings'
                440     BINARY_SUBSCR                   
                444     LOAD_ATTR                       17: get
                464     LOAD_CONST                      17: 'users_ru'
                466     CALL                            1
                474     STORE_FAST                      13: _var_var_24
                476     LOAD_FAST                       3: data
                478     LOAD_CONST                      13: 'Settings'
                480     BINARY_SUBSCR                   
                484     LOAD_ATTR                       17: get
                504     LOAD_CONST                      18: 'users_cn'
                506     CALL                            1
                514     STORE_FAST                      14: _var_var_25
                516     LOAD_FAST                       3: data
                518     LOAD_CONST                      13: 'Settings'
                520     BINARY_SUBSCR                   
                524     LOAD_ATTR                       17: get
                544     LOAD_CONST                      19: 'users_ar'
                546     CALL                            1
                554     STORE_FAST                      15: _var_var_26
                556     LOAD_FAST                       3: data
                558     LOAD_CONST                      13: 'Settings'
                560     BINARY_SUBSCR                   
                564     LOAD_ATTR                       17: get
                584     LOAD_CONST                      20: 'users_he'
                586     CALL                            1
                594     STORE_FAST                      16: _var_var_27
                596     LOAD_FAST                       3: data
                598     LOAD_CONST                      13: 'Settings'
                600     BINARY_SUBSCR                   
                604     LOAD_ATTR                       17: get
                624     LOAD_CONST                      21: 'users_fa'
                626     CALL                            1
                634     STORE_FAST                      17: _var_var_28
                636     LOAD_FAST                       3: data
                638     LOAD_CONST                      13: 'Settings'
                640     BINARY_SUBSCR                   
                644     LOAD_ATTR                       17: get
                664     PUSH_NULL                       
                666     LOAD_CONST                      1: '__pyarmor_assert_13962__'
                668     LOAD_CONST                      22: 'users_add'   # b'\x81\xf7\x0b\x16!\xe9\x81\xd3\x1f\xfe'
                670     CALL                            1
                678     CALL                            1
                686     STORE_FAST                      18: _var_var_29
                688     LOAD_FAST                       3: data
                690     LOAD_CONST                      13: 'Settings'
                692     BINARY_SUBSCR                   
                696     LOAD_ATTR                       17: get
                716     PUSH_NULL                       
                718     LOAD_CONST                      1: '__pyarmor_assert_13962__'
                720     LOAD_CONST                      23: 'leave_group'   # b'\x81\xee\x1d\x12%\xff\x81\xd5\t\xf5\x18\xd0'
                722     CALL                            1
                730     CALL                            1
                738     STORE_FAST                      19: _var_var_30
                740     LOAD_FAST                       3: data
                742     LOAD_CONST                      13: 'Settings'
                744     BINARY_SUBSCR                   
                748     LOAD_ATTR                       17: get
                768     PUSH_NULL                       
                770     LOAD_CONST                      1: '__pyarmor_assert_13962__'
                772     LOAD_CONST                      24: 'check_gender'   # b'\x81\xe1\x10\x160\xf1\x81\xd5\x1e\xf4\t\xc5~'
                774     CALL                            1
                782     CALL                            1
                790     STORE_FAST                      20: _var_var_31
                792     LOAD_FAST                       3: data
                794     LOAD_CONST                      13: 'Settings'
                796     BINARY_SUBSCR                   
                800     LOAD_ATTR                       17: get
                820     PUSH_NULL                       
                822     LOAD_CONST                      1: '__pyarmor_assert_13962__'
                824     LOAD_CONST                      25: 'create_txt'   # b'\x81\xe1\n\x162\xee\xbb\xed\x0f\xe2\x19'
                826     CALL                            1
                834     CALL                            1
                842     STORE_FAST                      21: _var_var_32
                844     LOAD_GLOBAL                     19: NULL + int
                854     LOAD_FAST                       3: data
                856     LOAD_CONST                      13: 'Settings'
                858     BINARY_SUBSCR                   
                862     LOAD_ATTR                       17: get
                882     PUSH_NULL                       
                884     LOAD_CONST                      1: '__pyarmor_assert_13962__'
                886     LOAD_CONST                      26: 'max_flood_wait'   # b'\x81\xef\x19\x0b\x0c\xfc\xb2\xdd\x14\xfe2\xd7m\xe5\xec'
                888     CALL                            1
                896     CALL                            1
                904     CALL                            1
                912     STORE_FAST                      22: _var_var_33
                914     LOAD_FAST                       3: data
                916     LOAD_CONST                      13: 'Settings'
                918     BINARY_SUBSCR                   
                922     LOAD_ATTR                       17: get
                942     PUSH_NULL                       
                944     LOAD_CONST                      1: '__pyarmor_assert_13962__'
                946     LOAD_CONST                      27: 'exclude_admins'   # b'\x81\xe7\x00\x10?\xef\xba\xd7$\xfb\t\xcde\xe2\xeb'
                948     CALL                            1
                956     CALL                            1
                964     STORE_FAST                      23: _var_var_34
                966     BUILD_LIST                      0
                968     STORE_FAST                      24: _var_var_35
                970     LOAD_GLOBAL                     21: NULL + db_base
                980     LOAD_FAST                       10: _var_var_21
                982     CALL                            1
                990     LOAD_ATTR                       17: get
                1010    LOAD_FAST                       0: account
                1012    CALL                            1
                1020    STORE_FAST                      25: _var_var_36
                1022    LOAD_FAST                       25: _var_var_36
                1024    LOAD_CONST                      28: 'NO_GROUP'
                1026    COMPARE_OP                      40 (==)
                1030    POP_JUMP_IF_FALSE               142 (to 1316)
                1032    LOAD_GLOBAL                     13: NULL + Logs
                1042    LOAD_ATTR                       14: PrintLog
                1062    LOAD_FAST                       1: config
                1064    LOAD_FAST                       0: account
                1066    LOAD_GLOBAL                     4: Lang
                1076    PUSH_NULL                       
                1078    LOAD_CONST                      1: '__pyarmor_assert_13962__'
                1080    LOAD_CONST                      29: 'database_none_groups'   # b'\x81\xe6\x19\x072\xf8\xbf\xc1\x1e\xc5\x03\xcfb\xe9\xc7\x82\x1dR\xae\xb7\xb9'
                1082    CALL                            1
                1090    BINARY_SUBSCR                   
                1094    KW_NAMES                        10: ('config', 'account', 'message')
                1096    CALL                            3
                1104    POP_TOP                         
                1106    LOAD_GLOBAL                     7: NULL + Disconnect
                1116    LOAD_FAST                       8: _var_var_19
                1118    CALL                            1
                1126    POP_TOP                         
                1128    LOAD_FAST                       0: account
                1130    PUSH_NULL                       
                1132    LOAD_CONST                      1: '__pyarmor_assert_13962__'
                1134    LOAD_CONST                      30: 'EmptyGroups'   # b"\x81\xc7\x15\x03'\xe3\x99\xc0\x14\xef\x1d\xd3"
                1136    CALL                            1
                1144    BUILD_LIST                      2
                1146    LOAD_GLOBAL                     7: NULL + Disconnect
                1156    LOAD_FAST                       8: _var_var_19
                1158    CALL                            1
                1166    POP_TOP                         
                1168    LOAD_GLOBAL                     9: NULL + db_parsing_res
                1178    LOAD_ATTR                       10: disconnect
                1198    LOAD_FAST_CHECK                 9: _var_var_20
                1200    CALL                            1
                1208    POP_TOP                         
                1210    LOAD_GLOBAL                     13: NULL + Logs
                1220    LOAD_ATTR                       14: PrintLog
                1240    LOAD_FAST                       1: config
                1242    LOAD_FAST                       0: account
                1244    LOAD_GLOBAL                     4: Lang
                1254    PUSH_NULL                       
                1256    LOAD_CONST                      1: '__pyarmor_assert_13962__'
                1258    LOAD_CONST                      9: 'work_account_completed'   # b'\x81\xf5\x17\x018\xc5\xbf\xd1\x18\xf5\x18\xcex\xd3\xfb\x8a\x02M\xb7\xa2\xbe\xceJ'
                1260    CALL                            1
                1268    BINARY_SUBSCR                   
                1272    KW_NAMES                        10: ('config', 'account', 'message')
                1274    CALL                            3
                1282    POP_TOP                         
                1284    LOAD_FAST                       0: account
                1286    LOAD_CONST                      11: 'done'
                1288    LOAD_CONST                      8: ('account', 'status')
                1290    BUILD_CONST_KEY_MAP             2
                1292    SWAP                            2
                1294    POP_TOP                         
                1296    NOP                             
                1298    NOP                             
                1300    JUMP_FORWARD                    3786 (to 8876)
                1304    CALL                            1
                1312    POP_TOP                         
                1314    RETURN_VALUE                    
                1316    LOAD_GLOBAL                     23: NULL + tg_links
                1326    CALL                            0
                1334    LOAD_ATTR                       25: _correct_private
                1354    LOAD_FAST                       25: _var_var_36
                1356    LOAD_CONST                      31: 1
                1358    BINARY_SUBSCR                   
                1362    CALL                            1
                1370    STORE_FAST                      26: _var_var_37
                1372    LOAD_GLOBAL                     27: NULL + tg_group
                1382    LOAD_FAST                       1: config
                1384    LOAD_FAST                       8: _var_var_19
                1386    LOAD_FAST                       0: account
                1388    LOAD_FAST                       26: _var_var_37
                1390    LOAD_FAST                       22: _var_var_33
                1392    LOAD_GLOBAL                     4: Lang
                1402    LOAD_FAST                       6: stop_thread
                1404    KW_NAMES                        32: ('config', 'client', 'account', 'group_link', 'max_flood_wait', 'lang', 'stop_thread')
                1406    CALL                            7
                1414    LOAD_ATTR                       29: go_to
                1434    CALL                            0
                1442    STORE_FAST                      27: _var_var_38
                1444    LOAD_FAST                       27: _var_var_38
                1446    PUSH_NULL                       
                1448    LOAD_CONST                      1: '__pyarmor_assert_13962__'
                1450    LOAD_CONST                      26: 'max_flood_wait'   # b'\x81\xef\x19\x0b\x0c\xfc\xb2\xdd\x14\xfe2\xd7m\xe5\xec'
                1452    CALL                            1
                1460    COMPARE_OP                      40 (==)
                1464    POP_JUMP_IF_FALSE               143 (to 1752)
                1466    LOAD_GLOBAL                     21: NULL + db_base
                1476    LOAD_FAST                       10: _var_var_21
                1478    CALL                            1
                1486    LOAD_ATTR                       31: update
                1506    LOAD_FAST                       0: account
                1508    LOAD_FAST                       25: _var_var_36
                1510    LOAD_CONST                      31: 1
                1512    BINARY_SUBSCR                   
                1516    PUSH_NULL                       
                1518    LOAD_CONST                      1: '__pyarmor_assert_13962__'
                1520    LOAD_CONST                      33: 'FloodWait'   # b'\x81\xc4\x14\x1c<\xfe\x89\xd3\x12\xee'
                1522    CALL                            1
                1530    CALL                            3
                1538    POP_TOP                         
                1540    LOAD_GLOBAL                     7: NULL + Disconnect
                1550    LOAD_FAST                       8: _var_var_19
                1552    CALL                            1
                1560    POP_TOP                         
                1562    LOAD_FAST                       0: account
                1564    PUSH_NULL                       
                1566    LOAD_CONST                      1: '__pyarmor_assert_13962__'
                1568    LOAD_CONST                      33: 'FloodWait'   # b'\x81\xc4\x14\x1c<\xfe\x89\xd3\x12\xee'
                1570    CALL                            1
                1578    LOAD_CONST                      8: ('account', 'status')
                1580    BUILD_CONST_KEY_MAP             2
                1582    LOAD_GLOBAL                     7: NULL + Disconnect
                1592    LOAD_FAST                       8: _var_var_19
                1594    CALL                            1
                1602    POP_TOP                         
                1604    LOAD_GLOBAL                     9: NULL + db_parsing_res
                1614    LOAD_ATTR                       10: disconnect
                1634    LOAD_FAST_CHECK                 9: _var_var_20
                1636    CALL                            1
                1644    POP_TOP                         
                1646    LOAD_GLOBAL                     13: NULL + Logs
                1656    LOAD_ATTR                       14: PrintLog
                1676    LOAD_FAST                       1: config
                1678    LOAD_FAST                       0: account
                1680    LOAD_GLOBAL                     4: Lang
                1690    PUSH_NULL                       
                1692    LOAD_CONST                      1: '__pyarmor_assert_13962__'
                1694    LOAD_CONST                      9: 'work_account_completed'   # b'\x81\xf5\x17\x018\xc5\xbf\xd1\x18\xf5\x18\xcex\xd3\xfb\x8a\x02M\xb7\xa2\xbe\xceJ'
                1696    CALL                            1
                1704    BINARY_SUBSCR                   
                1708    KW_NAMES                        10: ('config', 'account', 'message')
                1710    CALL                            3
                1718    POP_TOP                         
                1720    LOAD_FAST                       0: account
                1722    LOAD_CONST                      11: 'done'
                1724    LOAD_CONST                      8: ('account', 'status')
                1726    BUILD_CONST_KEY_MAP             2
                1728    SWAP                            2
                1730    POP_TOP                         
                1732    NOP                             
                1734    NOP                             
                1736    JUMP_FORWARD                    3568 (to 8876)
                1740    CALL                            1
                1748    POP_TOP                         
                1750    RETURN_VALUE                    
                1752    LOAD_FAST                       27: _var_var_38
                1754    POP_JUMP_IF_NOT_NONE            172 (to 2100)
                1756    LOAD_GLOBAL                     13: NULL + Logs
                1766    LOAD_ATTR                       14: PrintLog
                1786    LOAD_FAST                       1: config
                1788    LOAD_FAST                       0: account
                1790    LOAD_GLOBAL                     4: Lang
                1800    PUSH_NULL                       
                1802    LOAD_CONST                      1: '__pyarmor_assert_13962__'
                1804    LOAD_CONST                      34: 'channel_not_found'   # b'\x81\xe1\x10\x12=\xf4\xbb\xde$\xf4\x02\xd4S\xea\xf7\x90\x01Y'
                1806    CALL                            1
                1814    BINARY_SUBSCR                   
                1818    LOAD_FAST                       25: _var_var_36
                1820    LOAD_CONST                      31: 1
                1822    BINARY_SUBSCR                   
                1826    KW_NAMES                        35: ('config', 'account', 'message', 'param')
                1828    CALL                            4
                1836    POP_TOP                         
                1838    LOAD_GLOBAL                     21: NULL + db_base
                1848    LOAD_FAST                       10: _var_var_21
                1850    CALL                            1
                1858    LOAD_ATTR                       31: update
                1878    LOAD_FAST                       0: account
                1880    LOAD_FAST                       25: _var_var_36
                1882    LOAD_CONST                      31: 1
                1884    BINARY_SUBSCR                   
                1888    LOAD_CONST                      36: 'NotFound'
                1890    CALL                            3
                1898    POP_TOP                         
                1900    LOAD_GLOBAL                     7: NULL + Disconnect
                1910    LOAD_FAST                       8: _var_var_19
                1912    CALL                            1
                1920    POP_TOP                         
                1922    LOAD_FAST                       0: account
                1924    LOAD_CONST                      36: 'NotFound'
                1926    LOAD_CONST                      8: ('account', 'status')
                1928    BUILD_CONST_KEY_MAP             2
                1930    LOAD_GLOBAL                     7: NULL + Disconnect
                1940    LOAD_FAST                       8: _var_var_19
                1942    CALL                            1
                1950    POP_TOP                         
                1952    LOAD_GLOBAL                     9: NULL + db_parsing_res
                1962    LOAD_ATTR                       10: disconnect
                1982    LOAD_FAST_CHECK                 9: _var_var_20
                1984    CALL                            1
                1992    POP_TOP                         
                1994    LOAD_GLOBAL                     13: NULL + Logs
                2004    LOAD_ATTR                       14: PrintLog
                2024    LOAD_FAST                       1: config
                2026    LOAD_FAST                       0: account
                2028    LOAD_GLOBAL                     4: Lang
                2038    PUSH_NULL                       
                2040    LOAD_CONST                      1: '__pyarmor_assert_13962__'
                2042    LOAD_CONST                      9: 'work_account_completed'   # b'\x81\xf5\x17\x018\xc5\xbf\xd1\x18\xf5\x18\xcex\xd3\xfb\x8a\x02M\xb7\xa2\xbe\xceJ'
                2044    CALL                            1
                2052    BINARY_SUBSCR                   
                2056    KW_NAMES                        10: ('config', 'account', 'message')
                2058    CALL                            3
                2066    POP_TOP                         
                2068    LOAD_FAST                       0: account
                2070    LOAD_CONST                      11: 'done'
                2072    LOAD_CONST                      8: ('account', 'status')
                2074    BUILD_CONST_KEY_MAP             2
                2076    SWAP                            2
                2078    POP_TOP                         
                2080    NOP                             
                2082    NOP                             
                2084    JUMP_FORWARD                    3394 (to 8876)
                2088    CALL                            1
                2096    POP_TOP                         
                2098    RETURN_VALUE                    
                2100    LOAD_GLOBAL                     33: NULL + entity
                2110    CALL                            0
                2118    LOAD_ATTR                       35: check
                2138    LOAD_FAST                       27: _var_var_38
                2140    CALL                            1
                2148    STORE_FAST                      28: _var_var_39
                2150    LOAD_GLOBAL                     37: NULL + type
                2160    LOAD_FAST                       28: _var_var_39
                2162    CALL                            1
                2170    LOAD_GLOBAL                     38: dict
                2180    COMPARE_OP                      40 (==)
                2184    POP_JUMP_IF_FALSE               256 (to 2700)
                2188    LOAD_FAST                       28: _var_var_39
                2190    LOAD_CONST                      37: 'type'
                2192    BINARY_SUBSCR                   
                2196    LOAD_CONST                      38: 'group'
                2198    COMPARE_OP                      55 (!=)
                2202    POP_JUMP_IF_FALSE               248 (to 2700)
                2204    LOAD_GLOBAL                     13: NULL + Logs
                2214    LOAD_ATTR                       14: PrintLog
                2234    LOAD_FAST                       1: config
                2236    LOAD_FAST                       0: account
                2238    LOAD_GLOBAL                     4: Lang
                2248    PUSH_NULL                       
                2250    LOAD_CONST                      1: '__pyarmor_assert_13962__'
                2252    LOAD_CONST                      39: 'pupsik_get_error'   # b'\x81\xf2\r\x03 \xf3\xb5\xed\x1c\xff\x19\xffi\xfe\xea\x8a\x1d'
                2254    CALL                            1
                2262    BINARY_SUBSCR                   
                2266    KW_NAMES                        10: ('config', 'account', 'message')
                2268    CALL                            3
                2276    POP_TOP                         
                2278    LOAD_GLOBAL                     13: NULL + Logs
                2288    LOAD_ATTR                       14: PrintLog
                2308    LOAD_FAST                       1: config
                2310    LOAD_FAST                       0: account
                2312    LOAD_GLOBAL                     4: Lang
                2322    PUSH_NULL                       
                2324    LOAD_CONST                      1: '__pyarmor_assert_13962__'
                2326    LOAD_CONST                      40: 'pupsik_get_not_channel'   # b'\x81\xf2\r\x03 \xf3\xb5\xed\x1c\xff\x19\xffb\xe3\xec\xba\x0cU\xba\xa9\xa4\xceB'
                2328    CALL                            1
                2336    BINARY_SUBSCR                   
                2340    LOAD_FAST                       25: _var_var_36
                2342    LOAD_CONST                      31: 1
                2344    BINARY_SUBSCR                   
                2348    KW_NAMES                        35: ('config', 'account', 'message', 'param')
                2350    CALL                            4
                2358    POP_TOP                         
                2360    LOAD_GLOBAL                     21: NULL + db_base
                2370    LOAD_FAST                       10: _var_var_21
                2372    CALL                            1
                2380    LOAD_ATTR                       31: update
                2400    LOAD_FAST                       0: account
                2402    LOAD_FAST                       25: _var_var_36
                2404    LOAD_CONST                      31: 1
                2406    BINARY_SUBSCR                   
                2410    LOAD_FAST                       28: _var_var_39
                2412    LOAD_CONST                      37: 'type'
                2414    BINARY_SUBSCR                   
                2418    CALL                            3
                2426    POP_TOP                         
                2428    LOAD_GLOBAL                     13: NULL + Logs
                2438    LOAD_ATTR                       14: PrintLog
                2458    LOAD_FAST                       1: config
                2460    LOAD_FAST                       0: account
                2462    LOAD_GLOBAL                     4: Lang
                2472    PUSH_NULL                       
                2474    LOAD_CONST                      1: '__pyarmor_assert_13962__'
                2476    LOAD_CONST                      41: 'pupsik_shutdown_account'   # b'\x81\xf2\r\x03 \xf3\xb5\xed\x08\xf2\x18\xd4h\xe3\xef\x8b0\\\xb8\xa4\xa5\xde@\xd8'
                2478    CALL                            1
                2486    BINARY_SUBSCR                   
                2490    KW_NAMES                        10: ('config', 'account', 'message')
                2492    CALL                            3
                2500    POP_TOP                         
                2502    LOAD_GLOBAL                     7: NULL + Disconnect
                2512    LOAD_FAST                       8: _var_var_19
                2514    CALL                            1
                2522    POP_TOP                         
                2524    LOAD_FAST                       0: account
                2526    LOAD_CONST                      42: 'NotGroup'
                2528    BUILD_LIST                      2
                2530    LOAD_GLOBAL                     7: NULL + Disconnect
                2540    LOAD_FAST                       8: _var_var_19
                2542    CALL                            1
                2550    POP_TOP                         
                2552    LOAD_GLOBAL                     9: NULL + db_parsing_res
                2562    LOAD_ATTR                       10: disconnect
                2582    LOAD_FAST_CHECK                 9: _var_var_20
                2584    CALL                            1
                2592    POP_TOP                         
                2594    LOAD_GLOBAL                     13: NULL + Logs
                2604    LOAD_ATTR                       14: PrintLog
                2624    LOAD_FAST                       1: config
                2626    LOAD_FAST                       0: account
                2628    LOAD_GLOBAL                     4: Lang
                2638    PUSH_NULL                       
                2640    LOAD_CONST                      1: '__pyarmor_assert_13962__'
                2642    LOAD_CONST                      9: 'work_account_completed'   # b'\x81\xf5\x17\x018\xc5\xbf\xd1\x18\xf5\x18\xcex\xd3\xfb\x8a\x02M\xb7\xa2\xbe\xceJ'
                2644    CALL                            1
                2652    BINARY_SUBSCR                   
                2656    KW_NAMES                        10: ('config', 'account', 'message')
                2658    CALL                            3
                2666    POP_TOP                         
                2668    LOAD_FAST                       0: account
                2670    LOAD_CONST                      11: 'done'
                2672    LOAD_CONST                      8: ('account', 'status')
                2674    BUILD_CONST_KEY_MAP             2
                2676    SWAP                            2
                2678    POP_TOP                         
                2680    NOP                             
                2682    NOP                             
                2684    JUMP_FORWARD                    3094 (to 8876)
                2688    CALL                            1
                2696    POP_TOP                         
                2698    RETURN_VALUE                    
                2700    LOAD_GLOBAL                     13: NULL + Logs
                2710    LOAD_ATTR                       14: PrintLog
                2730    LOAD_FAST                       1: config
                2732    LOAD_FAST                       0: account
                2734    LOAD_GLOBAL                     4: Lang
                2744    PUSH_NULL                       
                2746    LOAD_CONST                      1: '__pyarmor_assert_13962__'
                2748    LOAD_CONST                      43: 'success_joined_channel'   # b'\x81\xf1\r\x100\xff\xad\xc1$\xf0\x02\xc9b\xe9\xfc\xba\x0cU\xba\xa9\xa4\xceB'
                2750    CALL                            1
                2758    BINARY_SUBSCR                   
                2762    LOAD_FAST                       25: _var_var_36
                2764    LOAD_CONST                      31: 1
                2766    BINARY_SUBSCR                   
                2770    KW_NAMES                        35: ('config', 'account', 'message', 'param')
                2772    CALL                            4
                2780    POP_TOP                         
                2782    LOAD_GLOBAL                     21: NULL + db_base
                2792    LOAD_FAST                       10: _var_var_21
                2794    CALL                            1
                2802    LOAD_ATTR                       31: update
                2822    LOAD_FAST                       0: account
                2824    LOAD_FAST                       25: _var_var_36
                2826    LOAD_CONST                      31: 1
                2828    BINARY_SUBSCR                   
                2832    LOAD_CONST                      44: 'Entered'
                2834    CALL                            3
                2842    POP_TOP                         
                2844    LOAD_FAST                       6: stop_thread
                2846    LOAD_ATTR                       41: is_set
                2866    CALL                            0
                2874    POP_JUMP_IF_FALSE               10 (to 2896)
                2876    LOAD_GLOBAL                     43: NULL + StopProgram
                2886    CALL                            0
                2894    RAISE_VARARGS                   1
                2896    LOAD_GLOBAL                     23: NULL + tg_links
                2906    LOAD_ATTR                       44: get_hash
                2926    LOAD_FAST                       25: _var_var_36
                2928    LOAD_CONST                      31: 1
                2930    BINARY_SUBSCR                   
                2934    CALL                            1
                2942    STORE_FAST                      29: _var_var_40
                2944    LOAD_FAST                       5: timestamp
                2946    FORMAT_VALUE                    0 (FVC_NONE)
                2948    LOAD_CONST                      45: '_'
                2950    LOAD_FAST                       29: _var_var_40
                2952    FORMAT_VALUE                    0 (FVC_NONE)
                2954    LOAD_CONST                      46: '.db'
                2956    BUILD_STRING                    4
                2958    STORE_FAST                      30: _var_var_41
                2960    LOAD_FAST                       5: timestamp
                2962    FORMAT_VALUE                    0 (FVC_NONE)
                2964    LOAD_CONST                      45: '_'
                2966    LOAD_FAST                       29: _var_var_40
                2968    FORMAT_VALUE                    0 (FVC_NONE)
                2970    LOAD_CONST                      47: '.txt'
                2972    BUILD_STRING                    4
                2974    STORE_FAST                      31: _var_var_42
                2976    PUSH_NULL                       
                2978    LOAD_CONST                      1: '__pyarmor_assert_13962__'
                2980    LOAD_CONST                      48: 'additives/parsing/'   # b'\x81\xe3\x1c\x17:\xee\xb7\xc4\x1e\xe9B\xd0m\xfe\xeb\x8c\x01Z\xf4'
                2982    CALL                            1
                2990    LOAD_FAST                       30: _var_var_41
                2992    FORMAT_VALUE                    0 (FVC_NONE)
                2994    BUILD_STRING                    2
                2996    STORE_FAST                      32: _var_var_43
                2998    PUSH_NULL                       
                3000    LOAD_CONST                      1: '__pyarmor_assert_13962__'
                3002    LOAD_CONST                      48: 'additives/parsing/'   # b'\x81\xe3\x1c\x17:\xee\xb7\xc4\x1e\xe9B\xd0m\xfe\xeb\x8c\x01Z\xf4'
                3004    CALL                            1
                3012    LOAD_FAST                       31: _var_var_42
                3014    FORMAT_VALUE                    0 (FVC_NONE)
                3016    BUILD_STRING                    2
                3018    STORE_FAST                      33: _var_var_44
                3020    PUSH_NULL                       
                3022    LOAD_CONST                      1: '__pyarmor_assert_13962__'
                3024    LOAD_CONST                      48: 'additives/parsing/'   # b'\x81\xe3\x1c\x17:\xee\xb7\xc4\x1e\xe9B\xd0m\xfe\xeb\x8c\x01Z\xf4'
                3026    CALL                            1
                3034    LOAD_FAST                       5: timestamp
                3036    FORMAT_VALUE                    0 (FVC_NONE)
                3038    PUSH_NULL                       
                3040    LOAD_CONST                      1: '__pyarmor_assert_13962__'
                3042    LOAD_CONST                      49: '_Parsing.txt'   # b'\x81\xdd(\x12!\xe9\xb7\xdc\x1c\xb4\x19\xd8x'
                3044    CALL                            1
                3052    BUILD_STRING                    3
                3054    STORE_FAST                      34: _var_var_45
                3056    LOAD_GLOBAL                     23: NULL + tg_links
                3066    LOAD_ATTR                       46: standart
                3086    LOAD_FAST                       25: _var_var_36
                3088    LOAD_CONST                      31: 1
                3090    BINARY_SUBSCR                   
                3094    CALL                            1
                3102    STORE_FAST                      35: _var_var_46
                3104    LOAD_CONST                      50: 0
                3106    STORE_FAST                      36: _var_var_47
                3108    LOAD_GLOBAL                     9: NULL + db_parsing_res
                3118    LOAD_ATTR                       48: connect
                3138    LOAD_FAST                       32: _var_var_43
                3140    CALL                            1
                3148    STORE_FAST                      9: _var_var_20
                3150    LOAD_GLOBAL                     9: NULL + db_parsing_res
                3160    LOAD_ATTR                       50: create
                3180    LOAD_FAST                       9: _var_var_20
                3182    CALL                            1
                3190    POP_TOP                         
                3192    LOAD_GLOBAL                     53: NULL + eel
                3202    LOAD_ATTR                       54: WriteResult
                3222    LOAD_CONST                      51: 'Group'
                3224    LOAD_CONST                      52: 'parsing'
                3226    LOAD_FAST                       30: _var_var_41
                3228    CALL                            3
                3236    POP_TOP                         
                3238    LOAD_GLOBAL                     13: NULL + Logs
                3248    LOAD_ATTR                       14: PrintLog
                3268    LOAD_FAST                       1: config
                3270    LOAD_FAST                       0: account
                3272    LOAD_GLOBAL                     4: Lang
                3282    PUSH_NULL                       
                3284    LOAD_CONST                      1: '__pyarmor_assert_13962__'
                3286    LOAD_CONST                      53: 'add_to_database'   # b'\x81\xe3\x1c\x17\x0c\xee\xb1\xed\x1f\xfb\x19\xc1n\xed\xeb\x80'
                3288    CALL                            1
                3296    BINARY_SUBSCR                   
                3300    LOAD_FAST                       30: _var_var_41
                3302    KW_NAMES                        35: ('config', 'account', 'message', 'param')
                3304    CALL                            4
                3312    POP_TOP                         
                3314    NOP                             
                3316    PUSH_NULL                       
                3318    LOAD_FAST                       8: _var_var_19
                3320    LOAD_GLOBAL                     56: functions
                3330    LOAD_ATTR                       58: channels
                3350    LOAD_ATTR                       61: GetFullChannelRequest
                3370    LOAD_FAST                       27: _var_var_38
                3372    KW_NAMES                        54: ('channel',)
                3374    CALL                            1
                3382    CALL                            1
                3390    STORE_FAST                      37: _var_var_48
                3392    LOAD_FAST                       37: _var_var_48
                3394    LOAD_ATTR                       62: full_chat
                3414    LOAD_ATTR                       64: participants_count
                3434    STORE_FAST                      36: _var_var_47
                3436    LOAD_FAST                       23: _var_var_34
                3438    POP_JUMP_IF_FALSE               67 (to 3574)
                3440    NOP                             
                3442    LOAD_FAST                       8: _var_var_19
                3444    LOAD_ATTR                       67: iter_participants
                3464    LOAD_FAST                       27: _var_var_38
                3466    LOAD_GLOBAL                     68: types
                3476    LOAD_ATTR                       70: ChannelParticipantsAdmins
                3496    KW_NAMES                        55: ('filter',)
                3498    CALL                            2
                3506    GET_ITER                        
                3508    FOR_ITER                        29 (to 3568)
                3512    STORE_FAST                      38: _var_var_49
                3514    LOAD_FAST                       24: _var_var_35
                3516    LOAD_ATTR                       73: append
                3536    LOAD_FAST                       38: _var_var_49
                3538    LOAD_ATTR                       74: id
                3558    CALL                            1
                3566    POP_TOP                         
                3568    JUMP_BACKWARD                   31 (to 3508)
                3570    END_FOR                         
                3572    NOP                             
                3574    LOAD_GLOBAL                     9: NULL + db_parsing_res
                3584    LOAD_ATTR                       76: insert_group
                3604    LOAD_FAST                       9: _var_var_20
                3606    LOAD_FAST                       28: _var_var_39
                3608    LOAD_CONST                      56: 'info'
                3610    BINARY_SUBSCR                   
                3614    LOAD_CONST                      57: 'id'
                3616    BINARY_SUBSCR                   
                3620    LOAD_FAST                       35: _var_var_46
                3622    LOAD_FAST                       28: _var_var_39
                3624    LOAD_CONST                      56: 'info'
                3626    BINARY_SUBSCR                   
                3630    LOAD_CONST                      58: 'title'
                3632    BINARY_SUBSCR                   
                3636    LOAD_FAST                       36: _var_var_47
                3638    LOAD_FAST                       28: _var_var_39
                3640    LOAD_CONST                      56: 'info'
                3642    BINARY_SUBSCR                   
                3646    LOAD_CONST                      59: 'photo'
                3648    BINARY_SUBSCR                   
                3652    LOAD_FAST                       28: _var_var_39
                3654    LOAD_CONST                      56: 'info'
                3656    BINARY_SUBSCR                   
                3660    LOAD_CONST                      60: 'invite'
                3662    BINARY_SUBSCR                   
                3666    LOAD_FAST                       28: _var_var_39
                3668    LOAD_CONST                      56: 'info'
                3670    BINARY_SUBSCR                   
                3674    PUSH_NULL                       
                3676    LOAD_CONST                      1: '__pyarmor_assert_13962__'
                3678    LOAD_CONST                      61: 'send_messages'   # b'\x81\xf1\x1d\x1d7\xc5\xb3\xd7\x08\xe9\x0c\xc7i\xff'
                3680    CALL                            1
                3688    BINARY_SUBSCR                   
                3692    LOAD_FAST                       28: _var_var_39
                3694    LOAD_CONST                      56: 'info'
                3696    BINARY_SUBSCR                   
                3700    PUSH_NULL                       
                3702    LOAD_CONST                      1: '__pyarmor_assert_13962__'
                3704    LOAD_CONST                      62: 'send_media'   # b'\x81\xf1\x1d\x1d7\xc5\xb3\xd7\x1f\xf3\x0c'
                3706    CALL                            1
                3714    BINARY_SUBSCR                   
                3718    LOAD_FAST                       28: _var_var_39
                3720    LOAD_CONST                      56: 'info'
                3722    BINARY_SUBSCR                   
                3726    PUSH_NULL                       
                3728    LOAD_CONST                      1: '__pyarmor_assert_13962__'
                3730    LOAD_CONST                      63: 'send_stickers'   # b'\x81\xf1\x1d\x1d7\xc5\xad\xc6\x12\xf9\x06\xc5~\xff'
                3732    CALL                            1
                3740    BINARY_SUBSCR                   
                3744    LOAD_FAST                       28: _var_var_39
                3746    LOAD_CONST                      56: 'info'
                3748    BINARY_SUBSCR                   
                3752    PUSH_NULL                       
                3754    LOAD_CONST                      1: '__pyarmor_assert_13962__'
                3756    LOAD_CONST                      64: 'send_polls'   # b'\x81\xf1\x1d\x1d7\xc5\xae\xdd\x17\xf6\x1e'
                3758    CALL                            1
                3766    BINARY_SUBSCR                   
                3770    LOAD_FAST                       28: _var_var_39
                3772    LOAD_CONST                      56: 'info'
                3774    BINARY_SUBSCR                   
                3778    PUSH_NULL                       
                3780    LOAD_CONST                      1: '__pyarmor_assert_13962__'
                3782    LOAD_CONST                      65: 'slow_mode'   # b'\x81\xf1\x14\x1c$\xc5\xb3\xdd\x1f\xff'
                3784    CALL                            1
                3792    BINARY_SUBSCR                   
                3796    LOAD_FAST                       28: _var_var_39
                3798    LOAD_CONST                      56: 'info'
                3800    BINARY_SUBSCR                   
                3804    LOAD_CONST                      66: 'scam'
                3806    BINARY_SUBSCR                   
                3810    LOAD_FAST                       28: _var_var_39
                3812    LOAD_CONST                      56: 'info'
                3814    BINARY_SUBSCR                   
                3818    LOAD_CONST                      67: 'types'
                3820    BINARY_SUBSCR                   
                3824    LOAD_CONST                      68: 'Ready'
                3826    KW_NAMES                        69: ('_connect', 'group_id', 'username', 'title', 'count', 'photo', 'invite', 'send_messages', 'send_media', 'send_stickers', 'send_pools', 'slow_mode', 'scam', 'types', 'status')
                3828    CALL                            15
                3836    POP_TOP                         
                3838    LOAD_FAST                       6: stop_thread
                3840    LOAD_ATTR                       41: is_set
                3860    CALL                            0
                3868    POP_JUMP_IF_FALSE               10 (to 3890)
                3870    LOAD_GLOBAL                     43: NULL + StopProgram
                3880    CALL                            0
                3888    RAISE_VARARGS                   1
                3890    LOAD_GLOBAL                     13: NULL + Logs
                3900    LOAD_ATTR                       14: PrintLog
                3920    LOAD_FAST                       1: config
                3922    LOAD_FAST                       0: account
                3924    LOAD_GLOBAL                     4: Lang
                3934    PUSH_NULL                       
                3936    LOAD_CONST                      1: '__pyarmor_assert_13962__'
                3938    LOAD_CONST                      70: 'im_starting_to_gather'   # b'\x81\xeb\x15, \xee\xbf\xc0\x0f\xf3\x03\xc7S\xf8\xf7\xba\x08\\\xaf\xaf\xaf\xd9'
                3940    CALL                            1
                3948    BINARY_SUBSCR                   
                3952    LOAD_FAST                       25: _var_var_36
                3954    LOAD_CONST                      31: 1
                3956    BINARY_SUBSCR                   
                3960    KW_NAMES                        35: ('config', 'account', 'message', 'param')
                3962    CALL                            4
                3970    POP_TOP                         
                3972    LOAD_GLOBAL                     69: NULL + types
                3982    LOAD_ATTR                       78: InputChannel
                4002    LOAD_FAST                       27: _var_var_38
                4004    LOAD_ATTR                       74: id
                4024    LOAD_FAST                       27: _var_var_38
                4026    LOAD_ATTR                       80: access_hash
                4046    KW_NAMES                        71: ('channel_id', 'access_hash')
                4048    CALL                            2
                4056    STORE_FAST                      39: _var_var_50
                4058    LOAD_CONST                      50: 0
                4060    STORE_FAST                      40: _var_var_18
                4062    BUILD_LIST                      0
                4064    STORE_FAST                      41: _var_var_51
                4066    BUILD_LIST                      0
                4068    STORE_FAST                      42: _var_var_52
                4070    LOAD_CONST                      50: 0
                4072    STORE_FAST                      43: _var_var_53
                4074    LOAD_CONST                      6: False
                4076    STORE_FAST                      44: _var_var_54
                4078    NOP                             
                4080    LOAD_FAST                       6: stop_thread
                4082    LOAD_ATTR                       41: is_set
                4102    CALL                            0
                4110    POP_JUMP_IF_FALSE               10 (to 4132)
                4112    LOAD_GLOBAL                     43: NULL + StopProgram
                4122    CALL                            0
                4130    RAISE_VARARGS                   1
                4132    LOAD_FAST                       12: _var_var_23
                4134    POP_JUMP_IF_FALSE               7 (to 4150)
                4136    LOAD_FAST                       42: _var_var_52
                4138    BUILD_LIST                      0
                4140    LOAD_CONST                      72: ('a', 'b', 'c', 'd', 'e', 'f', 'g', 'h', 'i', 'j', 'k', 'l', 'm', 'n', 'o', 'p', 'q', 'r', 's', 't', 'u', 'v', 'w', 'x', 'y', 'z')
                4142    LIST_EXTEND                     1
                4144    BINARY_OP                       0 (+)
                4148    STORE_FAST                      42: _var_var_52
                4150    LOAD_FAST                       13: _var_var_24
                4152    POP_JUMP_IF_FALSE               7 (to 4168)
                4154    LOAD_FAST                       42: _var_var_52
                4156    BUILD_LIST                      0
                4158    LOAD_CONST                      73: ('о', 'е', 'а', 'и', 'н', 'т', 'с', 'р', 'в', 'л', 'к', 'м', 'д', 'п', 'у', 'я', 'ы')
                4160    LIST_EXTEND                     1
                4162    BINARY_OP                       0 (+)
                4166    STORE_FAST                      42: _var_var_52
                4168    LOAD_FAST                       14: _var_var_25
                4170    POP_JUMP_IF_FALSE               7 (to 4186)
                4172    LOAD_FAST                       42: _var_var_52
                4174    BUILD_LIST                      0
                4176    LOAD_CONST                      74: ('的', '一', '是', '不', '了', '人', '我', '在', '有', '他', '这', '中', '大', '来', '上', '国', '个', '到', '说', '们', '为', '子', '和', '你', '地', '出', '道', '也', '时', '年', '得', '就', '那', '要', '下', '以', '生', '会', '自', '着', '去', '之', '过', '家', '学', '对', '可', '她', '里', '后')
                4178    LIST_EXTEND                     1
                4180    BINARY_OP                       0 (+)
                4184    STORE_FAST                      42: _var_var_52
                4186    LOAD_FAST                       15: _var_var_26
                4188    POP_JUMP_IF_FALSE               7 (to 4204)
                4190    LOAD_FAST                       42: _var_var_52
                4192    BUILD_LIST                      0
                4194    LOAD_CONST                      75: ('ا', 'ب', 'ت', 'ث', 'ج', 'ح', 'خ', 'د', 'ذ', 'ر', 'ز', 'س', 'ش', 'ص', 'ض', 'ط', 'ظ', 'ع', 'غ', 'ف', 'ق', 'ك', 'ل', 'م', 'ن', 'ه', 'و', 'ي')
                4196    LIST_EXTEND                     1
                4198    BINARY_OP                       0 (+)
                4202    STORE_FAST                      42: _var_var_52
                4204    LOAD_FAST                       16: _var_var_27
                4206    POP_JUMP_IF_FALSE               7 (to 4222)
                4208    LOAD_FAST                       42: _var_var_52
                4210    BUILD_LIST                      0
                4212    LOAD_CONST                      76: ('א', 'ב', 'ג', 'ד', 'ה', 'ו', 'ז', 'ח', 'ט', 'ך', 'כ', 'ל', 'ם', 'מ', 'ן', 'נ', 'ס', 'ע', 'ף', 'פ', 'ץ', 'צ', 'ק', 'ר', 'ש', 'ת')
                4214    LIST_EXTEND                     1
                4216    BINARY_OP                       0 (+)
                4220    STORE_FAST                      42: _var_var_52
                4222    LOAD_FAST                       17: _var_var_28
                4224    POP_JUMP_IF_FALSE               7 (to 4240)
                4226    LOAD_FAST                       42: _var_var_52
                4228    BUILD_LIST                      0
                4230    LOAD_CONST                      77: ('همزه', 'الف', 'ب', 'پ', 'ت', 'ث', 'جیم', 'چ', 'ح', 'خ', 'دال', 'ذال', 'ر', 'ز', 'ژ', 'سین', 'شین', 'صاد', 'ضاد', 'طا', 'ظا', 'عین', 'غین', 'ف', 'قاف', 'کاف', 'گاف', 'لام', 'میم', 'نون', 'واو', 'ه', 'ی')
                4232    LIST_EXTEND                     1
                4234    BINARY_OP                       0 (+)
                4238    STORE_FAST                      42: _var_var_52
                4240    LOAD_FAST                       18: _var_var_29
                4242    POP_JUMP_IF_FALSE               7 (to 4258)
                4244    LOAD_FAST                       42: _var_var_52
                4246    BUILD_LIST                      0
                4248    LOAD_CONST                      78: ('😊', '👍', '😀', '☺', '🤓', '😁', '👌', '🧐', '🙈', '😌', '😉', '👇', '👉', '😃', '😀', '😃', '😄', '😅', '🙃', '🙂', '☺', '️😊', '😎', '😏', '🤔', '🤭', '👐', '🤝', '👍', '🤟', '✌', '️👌', '✋', '🖐', '🙏', '🐰', '🐹', '🐭', '🐱', '🐯', '🦁', '🐮', '🐷', '🙈', '🐵', '🙊', '🐶', '☀', '️🌤', '☂', '️🚗', '🚕', '🚙', '📞', '☎', '️✡', '️💟', '❤', '️✅', '🕐', '🕑', '💲', '🚬')
                4250    LIST_EXTEND                     1
                4252    BINARY_OP                       0 (+)
                4256    STORE_FAST                      42: _var_var_52
                4258    LOAD_CONST                      79: 100
                4260    LOAD_GLOBAL                     83: NULL + len
                4270    LOAD_FAST                       42: _var_var_52
                4272    CALL                            1
                4280    BINARY_OP                       11 (/)
                4284    STORE_FAST                      45: _var_var_55
                4286    LOAD_CONST                      50: 0
                4288    STORE_FAST                      46: _var_var_56
                4290    LOAD_CONST                      50: 0
                4292    STORE_FAST                      47: _var_var_57
                4294    LOAD_FAST                       42: _var_var_52
                4296    GET_ITER                        
                4298    FOR_ITER                        581 (to 5464)
                4304    STORE_FAST                      48: _var_var_58
                4306    LOAD_FAST                       6: stop_thread
                4308    LOAD_ATTR                       41: is_set
                4328    CALL                            0
                4336    POP_JUMP_IF_FALSE               10 (to 4358)
                4338    LOAD_GLOBAL                     43: NULL + StopProgram
                4348    CALL                            0
                4356    RAISE_VARARGS                   1
                4358    LOAD_CONST                      50: 0
                4360    STORE_FAST                      49: _var_var_59
                4362    LOAD_CONST                      50: 0
                4364    STORE_FAST                      50: _var_var_60
                4366    LOAD_CONST                      80: 200
                4368    STORE_FAST                      51: _var_var_61
                4370    LOAD_CONST                      50: 0
                4372    STORE_FAST                      52: _var_var_62
                4374    NOP                             
                4376    LOAD_FAST                       6: stop_thread
                4378    LOAD_ATTR                       41: is_set
                4398    CALL                            0
                4406    POP_JUMP_IF_FALSE               10 (to 4428)
                4408    LOAD_GLOBAL                     43: NULL + StopProgram
                4418    CALL                            0
                4426    RAISE_VARARGS                   1
                4428    LOAD_FAST                       50: _var_var_60
                4430    LOAD_CONST                      82: 30
                4432    COMPARE_OP                      40 (==)
                4436    POP_JUMP_IF_FALSE               60 (to 4558)
                4438    LOAD_GLOBAL                     13: NULL + Logs
                4448    LOAD_ATTR                       14: PrintLog
                4468    LOAD_FAST                       1: config
                4470    LOAD_FAST                       0: account
                4472    LOAD_GLOBAL                     4: Lang
                4482    PUSH_NULL                       
                4484    LOAD_CONST                      1: '__pyarmor_assert_13962__'
                4486    LOAD_CONST                      83: 'circumventing_restriction'   # b'\x81\xe1\x11\x010\xef\xb3\xc4\x1e\xf4\x19\xc9b\xeb\xc7\x97\nN\xaf\xb5\xa3\xc8Z\xc5\na'
                4488    CALL                            1
                4496    BINARY_SUBSCR                   
                4500    KW_NAMES                        10: ('config', 'account', 'message')
                4502    CALL                            3
                4510    POP_TOP                         
                4512    LOAD_CONST                      50: 0
                4514    STORE_FAST                      50: _var_var_60
                4516    LOAD_GLOBAL                     85: NULL + time
                4526    LOAD_ATTR                       86: sleep
                4546    LOAD_CONST                      84: 5
                4548    CALL                            1
                4556    POP_TOP                         
                4558    NOP                             
                4560    PUSH_NULL                       
                4562    LOAD_FAST                       8: _var_var_19
                4564    LOAD_GLOBAL                     56: functions
                4574    LOAD_ATTR                       58: channels
                4594    LOAD_ATTR                       89: GetParticipantsRequest
                4614    LOAD_FAST                       39: _var_var_50
                4616    LOAD_GLOBAL                     69: NULL + types
                4626    LOAD_ATTR                       90: ChannelParticipantsSearch
                4646    LOAD_FAST                       48: _var_var_58
                4648    CALL                            1
                4656    LOAD_FAST                       49: _var_var_59
                4658    LOAD_FAST                       51: _var_var_61
                4660    LOAD_CONST                      50: 0
                4662    KW_NAMES                        85: ('channel', 'filter', 'offset', 'limit', 'hash')
                4664    CALL                            5
                4672    CALL                            1
                4680    STORE_FAST                      37: _var_var_48
                4682    LOAD_FAST                       50: _var_var_60
                4684    LOAD_CONST                      31: 1
                4686    BINARY_OP                       13 (+=)
                4690    STORE_FAST                      50: _var_var_60
                4692    LOAD_FAST                       49: _var_var_59
                4694    LOAD_FAST                       51: _var_var_61
                4696    BINARY_OP                       0 (+)
                4700    STORE_FAST                      49: _var_var_59
                4702    LOAD_GLOBAL                     83: NULL + len
                4712    LOAD_FAST                       37: _var_var_48
                4714    LOAD_ATTR                       92: users
                4734    CALL                            1
                4742    LOAD_CONST                      31: 1
                4744    COMPARE_OP                      2 (<)
                4748    POP_JUMP_IF_FALSE               2 (to 4754)
                4750    JUMP_FORWARD                    290 (to 5334)
                4754    LOAD_FAST                       37: _var_var_48
                4756    LOAD_ATTR                       92: users
                4776    GET_ITER                        
                4778    FOR_ITER                        271 (to 5324)
                4784    STORE_FAST                      53: _var_var_63
                4786    LOAD_FAST                       40: _var_var_18
                4788    LOAD_CONST                      31: 1
                4790    BINARY_OP                       13 (+=)
                4794    STORE_FAST                      40: _var_var_18
                4796    LOAD_FAST                       52: _var_var_62
                4798    LOAD_CONST                      31: 1
                4800    BINARY_OP                       13 (+=)
                4804    STORE_FAST                      52: _var_var_62
                4806    LOAD_GLOBAL                     95: NULL + parsing_time
                4816    CALL                            0
                4824    LOAD_ATTR                       35: check
                4844    LOAD_FAST                       53: _var_var_63
                4846    LOAD_FAST                       11: _var_var_22
                4848    KW_NAMES                        86: ('parsing_days',)
                4850    CALL                            2
                4858    STORE_FAST                      54: _var_var_64
                4860    LOAD_GLOBAL                     37: NULL + type
                4870    LOAD_FAST                       54: _var_var_64
                4872    CALL                            1
                4880    LOAD_GLOBAL                     38: dict
                4890    COMPARE_OP                      40 (==)
                4894    POP_JUMP_IF_TRUE                1 (to 4898)
                4896    JUMP_BACKWARD                   60 (to 4778)
                4898    LOAD_FAST                       54: _var_var_64
                4900    LOAD_CONST                      37: 'type'
                4902    BINARY_SUBSCR                   
                4906    LOAD_CONST                      87: 'user'
                4908    COMPARE_OP                      40 (==)
                4912    POP_JUMP_IF_TRUE                1 (to 4916)
                4914    JUMP_BACKWARD                   69 (to 4778)
                4916    LOAD_FAST                       23: _var_var_34
                4918    POP_JUMP_IF_FALSE               11 (to 4942)
                4920    LOAD_FAST                       54: _var_var_64
                4922    LOAD_CONST                      56: 'info'
                4924    BINARY_SUBSCR                   
                4928    LOAD_CONST                      57: 'id'
                4930    BINARY_SUBSCR                   
                4934    LOAD_FAST                       24: _var_var_35
                4936    CONTAINS_OP                     0 (in)
                4938    POP_JUMP_IF_FALSE               1 (to 4942)
                4940    JUMP_BACKWARD                   82 (to 4778)
                4942    LOAD_GLOBAL                     9: NULL + db_parsing_res
                4952    LOAD_ATTR                       96: insert_user
                4972    LOAD_CONST                      143: ()
                4974    BUILD_MAP                       0
                4976    LOAD_CONST                      88: '_connect'
                4978    LOAD_FAST                       9: _var_var_20
                4980    MAP_ADD                         1
                4982    LOAD_CONST                      89: 'user_id'
                4984    LOAD_FAST                       54: _var_var_64
                4986    LOAD_CONST                      56: 'info'
                4988    BINARY_SUBSCR                   
                4992    LOAD_CONST                      57: 'id'
                4994    BINARY_SUBSCR                   
                4998    MAP_ADD                         1
                5000    LOAD_CONST                      90: 'group_id'
                5002    LOAD_FAST                       28: _var_var_39
                5004    LOAD_CONST                      56: 'info'
                5006    BINARY_SUBSCR                   
                5010    LOAD_CONST                      57: 'id'
                5012    BINARY_SUBSCR                   
                5016    MAP_ADD                         1
                5018    LOAD_CONST                      91: 'mess_id'
                5020    LOAD_FAST                       54: _var_var_64
                5022    LOAD_CONST                      56: 'info'
                5024    BINARY_SUBSCR                   
                5028    LOAD_CONST                      91: 'mess_id'
                5030    BINARY_SUBSCR                   
                5034    MAP_ADD                         1
                5036    LOAD_CONST                      92: 'comm_id'
                5038    LOAD_FAST                       54: _var_var_64
                5040    LOAD_CONST                      56: 'info'
                5042    BINARY_SUBSCR                   
                5046    LOAD_CONST                      92: 'comm_id'
                5048    BINARY_SUBSCR                   
                5052    MAP_ADD                         1
                5054    LOAD_CONST                      93: 'phone'
                5056    LOAD_FAST                       54: _var_var_64
                5058    LOAD_CONST                      56: 'info'
                5060    BINARY_SUBSCR                   
                5064    LOAD_CONST                      93: 'phone'
                5066    BINARY_SUBSCR                   
                5070    MAP_ADD                         1
                5072    LOAD_CONST                      94: 'username'
                5074    LOAD_FAST                       54: _var_var_64
                5076    LOAD_CONST                      56: 'info'
                5078    BINARY_SUBSCR                   
                5082    LOAD_CONST                      94: 'username'
                5084    BINARY_SUBSCR                   
                5088    MAP_ADD                         1
                5090    LOAD_CONST                      95: 'first_name'
                5092    LOAD_FAST                       54: _var_var_64
                5094    LOAD_CONST                      56: 'info'
                5096    BINARY_SUBSCR                   
                5100    PUSH_NULL                       
                5102    LOAD_CONST                      1: '__pyarmor_assert_13962__'
                5104    LOAD_CONST                      96: 'first_name'   # b'\x81\xe4\x11\x01 \xee\x81\xdc\x1a\xf7\x08'
                5106    CALL                            1
                5114    BINARY_SUBSCR                   
                5118    MAP_ADD                         1
                5120    LOAD_CONST                      97: 'last_name'
                5122    LOAD_FAST                       54: _var_var_64
                5124    LOAD_CONST                      56: 'info'
                5126    BINARY_SUBSCR                   
                5130    PUSH_NULL                       
                5132    LOAD_CONST                      1: '__pyarmor_assert_13962__'
                5134    LOAD_CONST                      98: 'last_name'   # b"\x81\xee\x19\x00'\xc5\xb0\xd3\x16\xff"
                5136    CALL                            1
                5144    BINARY_SUBSCR                   
                5148    MAP_ADD                         1
                5150    LOAD_CONST                      99: 'bio'
                5152    LOAD_FAST                       54: _var_var_64
                5154    LOAD_CONST                      56: 'info'
                5156    BINARY_SUBSCR                   
                5160    LOAD_CONST                      99: 'bio'
                5162    BINARY_SUBSCR                   
                5166    MAP_ADD                         1
                5168    LOAD_CONST                      100: 'gender'
                5170    LOAD_FAST                       54: _var_var_64
                5172    LOAD_CONST                      56: 'info'
                5174    BINARY_SUBSCR                   
                5178    LOAD_CONST                      100: 'gender'
                5180    BINARY_SUBSCR                   
                5184    MAP_ADD                         1
                5186    LOAD_CONST                      59: 'photo'
                5188    LOAD_FAST                       54: _var_var_64
                5190    LOAD_CONST                      56: 'info'
                5192    BINARY_SUBSCR                   
                5196    LOAD_CONST                      59: 'photo'
                5198    BINARY_SUBSCR                   
                5202    MAP_ADD                         1
                5204    LOAD_CONST                      101: 'premium'
                5206    LOAD_FAST                       54: _var_var_64
                5208    LOAD_CONST                      56: 'info'
                5210    BINARY_SUBSCR                   
                5214    LOAD_CONST                      101: 'premium'
                5216    BINARY_SUBSCR                   
                5220    MAP_ADD                         1
                5222    LOAD_CONST                      102: 'status'
                5224    LOAD_FAST                       54: _var_var_64
                5226    LOAD_CONST                      56: 'info'
                5228    BINARY_SUBSCR                   
                5232    LOAD_CONST                      102: 'status'
                5234    BINARY_SUBSCR                   
                5238    MAP_ADD                         1
                5240    LOAD_CONST                      103: 'time'
                5242    LOAD_FAST                       54: _var_var_64
                5244    LOAD_CONST                      56: 'info'
                5246    BINARY_SUBSCR                   
                5250    LOAD_CONST                      103: 'time'
                5252    BINARY_SUBSCR                   
                5256    MAP_ADD                         1
                5258    LOAD_CONST                      104: 'invite_status'
                5260    LOAD_FAST                       54: _var_var_64
                5262    LOAD_CONST                      56: 'info'
                5264    BINARY_SUBSCR                   
                5268    PUSH_NULL                       
                5270    LOAD_CONST                      1: '__pyarmor_assert_13962__'
                5272    LOAD_CONST                      105: 'invite_status'   # b'\x81\xeb\x16\x05:\xee\xbb\xed\x08\xee\x0c\xd4y\xff'
                5274    CALL                            1
                5282    BINARY_SUBSCR                   
                5286    MAP_ADD                         1
                5288    LOAD_CONST                      106: 'send_status'
                5290    LOAD_FAST                       54: _var_var_64
                5292    LOAD_CONST                      56: 'info'
                5294    BINARY_SUBSCR                   
                5298    PUSH_NULL                       
                5300    LOAD_CONST                      1: '__pyarmor_assert_13962__'
                5302    LOAD_CONST                      107: 'send_status'   # b'\x81\xf1\x1d\x1d7\xc5\xad\xc6\x1a\xee\x18\xd3'
                5304    CALL                            1
                5312    BINARY_SUBSCR                   
                5316    MAP_ADD                         1
                5318    CALL_FUNCTION_EX                1
                5320    POP_TOP                         
                5322    JUMP_BACKWARD                   274 (to 4778)
                5326    END_FOR                         
                5328    NOP                             
                5330    JUMP_BACKWARD                   479 (to 4376)
                5334    LOAD_FAST                       46: _var_var_56
                5336    LOAD_FAST                       45: _var_var_55
                5338    BINARY_OP                       0 (+)
                5342    STORE_FAST                      46: _var_var_56
                5344    LOAD_GLOBAL                     13: NULL + Logs
                5354    LOAD_ATTR                       14: PrintLog
                5374    LOAD_FAST                       1: config
                5376    LOAD_FAST                       0: account
                5378    LOAD_FAST                       26: _var_var_37
                5380    LOAD_GLOBAL                     4: Lang
                5390    PUSH_NULL                       
                5392    LOAD_CONST                      1: '__pyarmor_assert_13962__'
                5394    LOAD_CONST                      123: 'parsing_done'   # b'\x81\xf2\x19\x01 \xf3\xb0\xd5$\xfe\x02\xcei'
                5396    CALL                            1
                5404    BINARY_SUBSCR                   
                5408    LOAD_GLOBAL                     117: NULL + round
                5418    LOAD_FAST                       46: _var_var_56
                5420    CALL                            1
                5428    KW_NAMES                        121: ('config', 'account', 'message', 'param', 'end')
                5430    CALL                            5
                5438    POP_TOP                         
                5440    LOAD_FAST                       47: _var_var_57
                5442    LOAD_CONST                      31: 1
                5444    COMPARE_OP                      40 (==)
                5448    POP_JUMP_IF_FALSE               2 (to 5454)
                5450    POP_TOP                         
                5452    JUMP_FORWARD                    7 (to 5468)
                5454    LOAD_FAST                       44: _var_var_54
                5456    POP_JUMP_IF_TRUE                2 (to 5462)
                5458    JUMP_BACKWARD                   582 (to 4298)
                5462    POP_TOP                         
                5464    JUMP_FORWARD                    1 (to 5468)
                5466    END_FOR                         
                5468    LOAD_FAST                       44: _var_var_54
                5470    POP_JUMP_IF_FALSE               74 (to 5620)
                5472    LOAD_GLOBAL                     13: NULL + Logs
                5482    LOAD_ATTR                       14: PrintLog
                5502    LOAD_FAST                       1: config
                5504    LOAD_FAST                       0: account
                5506    LOAD_GLOBAL                     4: Lang
                5516    PUSH_NULL                       
                5518    LOAD_CONST                      1: '__pyarmor_assert_13962__'
                5520    LOAD_CONST                      124: 'collection_users_stopped'   # b'\x81\xe1\x17\x1f?\xff\xbd\xc6\x12\xf5\x03\xffy\xff\xfd\x97\x1cb\xa8\xb3\xa5\xdb^\xc9\x01'
                5522    CALL                            1
                5530    BINARY_SUBSCR                   
                5534    KW_NAMES                        10: ('config', 'account', 'message')
                5536    CALL                            3
                5544    POP_TOP                         
                5546    LOAD_GLOBAL                     13: NULL + Logs
                5556    LOAD_ATTR                       14: PrintLog
                5576    LOAD_FAST                       1: config
                5578    LOAD_FAST                       0: account
                5580    LOAD_GLOBAL                     4: Lang
                5590    PUSH_NULL                       
                5592    LOAD_CONST                      1: '__pyarmor_assert_13962__'
                5594    LOAD_CONST                      125: 'users_corresponding_database'   # b'\x81\xf7\x0b\x16!\xe9\x81\xd1\x14\xe8\x1f\xc5\x7f\xfc\xf7\x8b\x0bT\xb5\xa0\x95\xcfO\xd8\x04m\xa2O\x05'
                5596    CALL                            1
                5604    BINARY_SUBSCR                   
                5608    KW_NAMES                        10: ('config', 'account', 'message')
                5610    CALL                            3
                5618    POP_TOP                         
                5620    LOAD_GLOBAL                     9: NULL + db_parsing_res
                5630    LOAD_ATTR                       10: disconnect
                5650    LOAD_FAST                       9: _var_var_20
                5652    CALL                            1
                5660    POP_TOP                         
                5662    LOAD_FAST                       19: _var_var_30
                5664    POP_JUMP_IF_FALSE               78 (to 5822)
                5666    LOAD_GLOBAL                     27: NULL + tg_group
                5676    LOAD_FAST                       1: config
                5678    LOAD_FAST                       8: _var_var_19
                5680    LOAD_FAST                       0: account
                5682    LOAD_FAST                       22: _var_var_33
                5684    LOAD_GLOBAL                     4: Lang
                5694    LOAD_FAST                       6: stop_thread
                5696    KW_NAMES                        126: ('config', 'client', 'account', 'max_flood_wait', 'lang', 'stop_thread')
                5698    CALL                            6
                5706    LOAD_ATTR                       123: go_out
                5726    LOAD_FAST                       27: _var_var_38
                5728    KW_NAMES                        127: ('entity',)
                5730    CALL                            1
                5738    POP_TOP                         
                5740    LOAD_GLOBAL                     13: NULL + Logs
                5750    LOAD_ATTR                       14: PrintLog
                5770    LOAD_FAST                       1: config
                5772    LOAD_FAST                       0: account
                5774    LOAD_GLOBAL                     4: Lang
                5784    PUSH_NULL                       
                5786    LOAD_CONST                      1: '__pyarmor_assert_13962__'
                5788    LOAD_CONST                      128: 'left_group'   # b"\x81\xee\x1d\x15'\xc5\xb9\xc0\x14\xef\x1d"
                5790    CALL                            1
                5798    BINARY_SUBSCR                   
                5802    LOAD_FAST                       25: _var_var_36
                5804    LOAD_CONST                      31: 1
                5806    BINARY_SUBSCR                   
                5810    KW_NAMES                        35: ('config', 'account', 'message', 'param')
                5812    CALL                            4
                5820    POP_TOP                         
                5822    LOAD_GLOBAL                     7: NULL + Disconnect
                5832    LOAD_FAST                       8: _var_var_19
                5834    CALL                            1
                5842    POP_TOP                         
                5844    LOAD_FAST                       20: _var_var_31
                5846    POP_JUMP_IF_FALSE               226 (to 6300)
                5848    LOAD_GLOBAL                     13: NULL + Logs
                5858    LOAD_ATTR                       14: PrintLog
                5878    LOAD_FAST                       1: config
                5880    LOAD_FAST                       0: account
                5882    LOAD_GLOBAL                     4: Lang
                5892    PUSH_NULL                       
                5894    LOAD_CONST                      1: '__pyarmor_assert_13962__'
                5896    LOAD_CONST                      129: 'parsing_check_gender'   # b'\x81\xf2\x19\x01 \xf3\xb0\xd5$\xf9\x05\xc5o\xe7\xc7\x82\nS\xbf\xa2\xb8'
                5898    CALL                            1
                5906    BINARY_SUBSCR                   
                5910    KW_NAMES                        10: ('config', 'account', 'message')
                5912    CALL                            3
                5920    POP_TOP                         
                5922    LOAD_GLOBAL                     125: NULL + db_parsing
                5932    LOAD_FAST                       32: _var_var_43
                5934    CALL                            1
                5942    LOAD_ATTR                       127: check_gender
                5962    CALL                            0
                5970    STORE_FAST                      57: _var_var_66
                5972    LOAD_GLOBAL                     13: NULL + Logs
                5982    LOAD_ATTR                       14: PrintLog
                6002    LOAD_FAST                       1: config
                6004    LOAD_FAST                       0: account
                6006    LOAD_GLOBAL                     4: Lang
                6016    PUSH_NULL                       
                6018    LOAD_CONST                      1: '__pyarmor_assert_13962__'
                6020    LOAD_CONST                      130: 'parsing_gender_men'   # b'\x81\xf2\x19\x01 \xf3\xb0\xd5$\xfd\x08\xceh\xe9\xea\xba\x02X\xb5'
                6022    CALL                            1
                6030    BINARY_SUBSCR                   
                6034    LOAD_FAST                       57: _var_var_66
                6036    LOAD_CONST                      131: 'male'
                6038    BINARY_SUBSCR                   
                6042    KW_NAMES                        35: ('config', 'account', 'message', 'param')
                6044    CALL                            4
                6052    POP_TOP                         
                6054    LOAD_GLOBAL                     13: NULL + Logs
                6064    LOAD_ATTR                       14: PrintLog
                6084    LOAD_FAST                       1: config
                6086    LOAD_FAST                       0: account
                6088    LOAD_GLOBAL                     4: Lang
                6098    PUSH_NULL                       
                6100    LOAD_CONST                      1: '__pyarmor_assert_13962__'
                6102    LOAD_CONST                      132: 'parsing_gender_women'   # b'\x81\xf2\x19\x01 \xf3\xb0\xd5$\xfd\x08\xceh\xe9\xea\xba\x18R\xb6\xa2\xa4'
                6104    CALL                            1
                6112    BINARY_SUBSCR                   
                6116    LOAD_FAST                       57: _var_var_66
                6118    LOAD_CONST                      133: 'female'
                6120    BINARY_SUBSCR                   
                6124    KW_NAMES                        35: ('config', 'account', 'message', 'param')
                6126    CALL                            4
                6134    POP_TOP                         
                6136    LOAD_GLOBAL                     13: NULL + Logs
                6146    LOAD_ATTR                       14: PrintLog
                6166    LOAD_FAST                       1: config
                6168    LOAD_FAST                       0: account
                6170    LOAD_GLOBAL                     4: Lang
                6180    PUSH_NULL                       
                6182    LOAD_CONST                      1: '__pyarmor_assert_13962__'
                6184    LOAD_CONST                      134: 'parsing_gender_un'   # b'\x81\xf2\x19\x01 \xf3\xb0\xd5$\xfd\x08\xceh\xe9\xea\xba\x1aS'
                6186    CALL                            1
                6194    BINARY_SUBSCR                   
                6198    LOAD_FAST                       57: _var_var_66
                6200    LOAD_CONST                      135: 'un'
                6202    BINARY_SUBSCR                   
                6206    KW_NAMES                        35: ('config', 'account', 'message', 'param')
                6208    CALL                            4
                6216    POP_TOP                         
                6218    LOAD_GLOBAL                     13: NULL + Logs
                6228    LOAD_ATTR                       14: PrintLog
                6248    LOAD_FAST                       1: config
                6250    LOAD_FAST                       0: account
                6252    LOAD_GLOBAL                     4: Lang
                6262    PUSH_NULL                       
                6264    LOAD_CONST                      1: '__pyarmor_assert_13962__'
                6266    LOAD_CONST                      136: 'parsing_gender_total'   # b'\x81\xf2\x19\x01 \xf3\xb0\xd5$\xfd\x08\xceh\xe9\xea\xba\x1bR\xaf\xa6\xa6'
                6268    CALL                            1
                6276    BINARY_SUBSCR                   
                6280    LOAD_FAST                       57: _var_var_66
                6282    LOAD_CONST                      137: 'count'
                6284    BINARY_SUBSCR                   
                6288    KW_NAMES                        35: ('config', 'account', 'message', 'param')
                6290    CALL                            4
                6298    POP_TOP                         
                6300    LOAD_GLOBAL                     125: NULL + db_parsing
                6310    LOAD_FAST                       32: _var_var_43
                6312    CALL                            1
                6320    LOAD_ATTR                       129: get_users_count
                6340    CALL                            0
                6348    STORE_FAST                      40: _var_var_18
                6350    LOAD_GLOBAL                     13: NULL + Logs
                6360    LOAD_ATTR                       14: PrintLog
                6380    LOAD_FAST                       1: config
                6382    LOAD_FAST                       0: account
                6384    LOAD_FAST                       35: _var_var_46
                6386    LOAD_GLOBAL                     4: Lang
                6396    PUSH_NULL                       
                6398    LOAD_CONST                      1: '__pyarmor_assert_13962__'
                6400    LOAD_CONST                      138: 'parsing_collect_users'   # b'\x81\xf2\x19\x01 \xf3\xb0\xd5$\xf9\x02\xcc`\xe9\xfb\x910H\xa8\xa2\xb8\xd8'
                6402    CALL                            1
                6410    BINARY_SUBSCR                   
                6414    LOAD_FAST                       40: _var_var_18
                6416    KW_NAMES                        121: ('config', 'account', 'message', 'param', 'end')
                6418    CALL                            5
                6426    POP_TOP                         
                6428    LOAD_GLOBAL                     125: NULL + db_parsing
                6438    LOAD_FAST                       4: db_result
                6440    CALL                            1
                6448    LOAD_ATTR                       131: union
                6468    LOAD_FAST                       32: _var_var_43
                6470    CALL                            1
                6478    STORE_FAST                      40: _var_var_18
                6480    LOAD_GLOBAL                     13: NULL + Logs
                6490    LOAD_ATTR                       14: PrintLog
                6510    LOAD_FAST                       1: config
                6512    LOAD_FAST                       0: account
                6514    LOAD_GLOBAL                     4: Lang
                6524    PUSH_NULL                       
                6526    LOAD_CONST                      1: '__pyarmor_assert_13962__'
                6528    LOAD_CONST                      139: 'parsing_add_gen_db'   # b'\x81\xf2\x19\x01 \xf3\xb0\xd5$\xfb\t\xc4S\xeb\xfd\x8b0Y\xb9'
                6530    CALL                            1
                6538    BINARY_SUBSCR                   
                6542    LOAD_FAST                       40: _var_var_18
                6544    LOAD_CONST                      140: 'users'
                6546    BINARY_SUBSCR                   
                6550    KW_NAMES                        35: ('config', 'account', 'message', 'param')
                6552    CALL                            4
                6560    POP_TOP                         
                6562    LOAD_GLOBAL                     21: NULL + db_base
                6572    LOAD_FAST                       10: _var_var_21
                6574    CALL                            1
                6582    LOAD_ATTR                       31: update
                6602    LOAD_FAST                       0: account
                6604    LOAD_FAST                       26: _var_var_37
                6606    LOAD_CONST                      141: 'Done'
                6608    CALL                            3
                6616    POP_TOP                         
                6618    LOAD_FAST                       21: _var_var_32
                6620    POP_JUMP_IF_FALSE               75 (to 6772)
                6622    LOAD_GLOBAL                     125: NULL + db_parsing
                6632    LOAD_FAST                       32: _var_var_43
                6634    CALL                            1
                6642    LOAD_ATTR                       133: create_txt
                6662    LOAD_FAST                       33: _var_var_44
                6664    CALL                            1
                6672    POP_TOP                         
                6674    LOAD_GLOBAL                     125: NULL + db_parsing
                6684    LOAD_FAST                       32: _var_var_43
                6686    CALL                            1
                6694    LOAD_ATTR                       133: create_txt
                6714    LOAD_FAST                       34: _var_var_45
                6716    CALL                            1
                6724    POP_TOP                         
                6726    LOAD_GLOBAL                     53: NULL + eel
                6736    LOAD_ATTR                       54: WriteResult
                6756    LOAD_CONST                      142: 'Группа'
                6758    LOAD_CONST                      52: 'parsing'
                6760    LOAD_FAST                       31: _var_var_42
                6762    CALL                            3
                6770    POP_TOP                         
                6772    LOAD_GLOBAL                     7: NULL + Disconnect
                6782    LOAD_FAST_CHECK                 8: _var_var_19
                6784    CALL                            1
                6792    POP_TOP                         
                6794    LOAD_GLOBAL                     9: NULL + db_parsing_res
                6804    LOAD_ATTR                       10: disconnect
                6824    LOAD_FAST_CHECK                 9: _var_var_20
                6826    CALL                            1
                6834    POP_TOP                         
                6836    LOAD_GLOBAL                     13: NULL + Logs
                6846    LOAD_ATTR                       14: PrintLog
                6866    LOAD_FAST                       1: config
                6868    LOAD_FAST                       0: account
                6870    LOAD_GLOBAL                     4: Lang
                6880    PUSH_NULL                       
                6882    LOAD_CONST                      1: '__pyarmor_assert_13962__'
                6884    LOAD_CONST                      9: 'work_account_completed'   # b'\x81\xf5\x17\x018\xc5\xbf\xd1\x18\xf5\x18\xcex\xd3\xfb\x8a\x02M\xb7\xa2\xbe\xceJ'
                6886    CALL                            1
                6894    BINARY_SUBSCR                   
                6898    KW_NAMES                        10: ('config', 'account', 'message')
                6900    CALL                            3
                6908    POP_TOP                         
                6910    LOAD_FAST                       0: account
                6912    LOAD_CONST                      11: 'done'
                6914    LOAD_CONST                      8: ('account', 'status')
                6916    BUILD_CONST_KEY_MAP             2
                6918    NOP                             
                6920    NOP                             
                6922    JUMP_FORWARD                    975 (to 8876)
                6926    CALL                            1
                6934    POP_TOP                         
                6936    RETURN_VALUE                    
                6938    PUSH_EXC_INFO                   
                6940    POP_TOP                         
                6942    POP_EXCEPT                      
                6944    JUMP_BACKWARD                   3405 (to 138)
                6948    COPY                            3
                6950    POP_EXCEPT                      
                6952    RERAISE                         1
                6954    PUSH_EXC_INFO                   
                6956    POP_TOP                         
                6958    POP_EXCEPT                      
                6960    JUMP_BACKWARD                   3392 (to 180)
                6964    COPY                            3
                6966    POP_EXCEPT                      
                6968    RERAISE                         1
                6970    PUSH_EXC_INFO                   
                6972    POP_TOP                         
                6974    POP_EXCEPT                      
                6976    JUMP_BACKWARD                   2926 (to 1128)
                6980    COPY                            3
                6982    POP_EXCEPT                      
                6984    RERAISE                         1
                6986    PUSH_EXC_INFO                   
                6988    POP_TOP                         
                6990    POP_EXCEPT                      
                6992    JUMP_BACKWARD                   2914 (to 1168)
                6996    COPY                            3
                6998    POP_EXCEPT                      
                7000    RERAISE                         1
                7002    PUSH_EXC_INFO                   
                7004    POP_TOP                         
                7006    POP_EXCEPT                      
                7008    JUMP_BACKWARD                   2901 (to 1210)
                7012    COPY                            3
                7014    POP_EXCEPT                      
                7016    RERAISE                         1
                7018    PUSH_EXC_INFO                   
                7020    POP_TOP                         
                7022    POP_EXCEPT                      
                7024    JUMP_BACKWARD                   2733 (to 1562)
                7028    COPY                            3
                7030    POP_EXCEPT                      
                7032    RERAISE                         1
                7034    PUSH_EXC_INFO                   
                7036    POP_TOP                         
                7038    POP_EXCEPT                      
                7040    JUMP_BACKWARD                   2720 (to 1604)
                7044    COPY                            3
                7046    POP_EXCEPT                      
                7048    RERAISE                         1
                7050    PUSH_EXC_INFO                   
                7052    POP_TOP                         
                7054    POP_EXCEPT                      
                7056    JUMP_BACKWARD                   2707 (to 1646)
                7060    COPY                            3
                7062    POP_EXCEPT                      
                7064    RERAISE                         1
                7066    PUSH_EXC_INFO                   
                7068    POP_TOP                         
                7070    POP_EXCEPT                      
                7072    JUMP_BACKWARD                   2577 (to 1922)
                7076    COPY                            3
                7078    POP_EXCEPT                      
                7080    RERAISE                         1
                7082    PUSH_EXC_INFO                   
                7084    POP_TOP                         
                7086    POP_EXCEPT                      
                7088    JUMP_BACKWARD                   2570 (to 1952)
                7092    COPY                            3
                7094    POP_EXCEPT                      
                7096    RERAISE                         1
                7098    PUSH_EXC_INFO                   
                7100    POP_TOP                         
                7102    POP_EXCEPT                      
                7104    JUMP_BACKWARD                   2557 (to 1994)
                7108    COPY                            3
                7110    POP_EXCEPT                      
                7112    RERAISE                         1
                7114    PUSH_EXC_INFO                   
                7116    POP_TOP                         
                7118    POP_EXCEPT                      
                7120    JUMP_BACKWARD                   2300 (to 2524)
                7124    COPY                            3
                7126    POP_EXCEPT                      
                7128    RERAISE                         1
                7130    PUSH_EXC_INFO                   
                7132    POP_TOP                         
                7134    POP_EXCEPT                      
                7136    JUMP_BACKWARD                   2294 (to 2552)
                7140    COPY                            3
                7142    POP_EXCEPT                      
                7144    RERAISE                         1
                7146    PUSH_EXC_INFO                   
                7148    POP_TOP                         
                7150    POP_EXCEPT                      
                7152    JUMP_BACKWARD                   2281 (to 2594)
                7156    COPY                            3
                7158    POP_EXCEPT                      
                7160    RERAISE                         1
                7162    PUSH_EXC_INFO                   
                7164    POP_TOP                         
                7166    POP_EXCEPT                      
                7168    JUMP_BACKWARD                   1868 (to 3436)
                7172    COPY                            3
                7174    POP_EXCEPT                      
                7176    RERAISE                         1
                7178    PUSH_EXC_INFO                   
                7180    POP_TOP                         
                7182    POP_EXCEPT                      
                7184    JUMP_BACKWARD                   1807 (to 3574)
                7188    COPY                            3
                7190    POP_EXCEPT                      
                7192    RERAISE                         1
                7194    PUSH_EXC_INFO                   
                7196    LOAD_GLOBAL                     98: errors
                7206    LOAD_ATTR                       100: ChannelPrivateError
                7226    CHECK_EXC_MATCH                 
                7228    POP_JUMP_IF_FALSE               140 (to 7510)
                7230    POP_TOP                         
                7232    LOAD_GLOBAL                     13: NULL + Logs
                7242    LOAD_ATTR                       14: PrintLog
                7262    LOAD_FAST                       1: config
                7264    LOAD_FAST                       0: account
                7266    LOAD_GLOBAL                     4: Lang
                7276    PUSH_NULL                       
                7278    LOAD_CONST                      1: '__pyarmor_assert_13962__'
                7280    LOAD_CONST                      108: 'stumbled_restriction_bypass'   # b'\x81\xf1\x0c\x06>\xf8\xb2\xd7\x1f\xc5\x1f\xc5\x7f\xf8\xea\x8c\x0cI\xb2\xa8\xa4\xf4L\xd5\x15n\xb0O'
                7282    CALL                            1
                7290    BINARY_SUBSCR                   
                7294    KW_NAMES                        10: ('config', 'account', 'message')
                7296    CALL                            3
                7304    POP_TOP                         
                7306    LOAD_GLOBAL                     103: NULL + DelayOnline
                7316    LOAD_FAST                       0: account
                7318    LOAD_FAST                       8: _var_var_19
                7320    LOAD_CONST                      109: 45
                7322    LOAD_CONST                      110: 65
                7324    LOAD_FAST                       6: stop_thread
                7326    CALL                            5
                7334    POP_TOP                         
                7336    LOAD_FAST                       43: _var_var_53
                7338    LOAD_CONST                      31: 1
                7340    BINARY_OP                       13 (+=)
                7344    STORE_FAST                      43: _var_var_53
                7346    LOAD_FAST                       43: _var_var_53
                7348    LOAD_CONST                      111: 3
                7350    COMPARE_OP                      68 (>)
                7354    POP_JUMP_IF_FALSE               42 (to 7440)
                7356    LOAD_GLOBAL                     13: NULL + Logs
                7366    LOAD_ATTR                       14: PrintLog
                7386    LOAD_FAST                       1: config
                7388    LOAD_FAST                       0: account
                7390    LOAD_GLOBAL                     4: Lang
                7400    PUSH_NULL                       
                7402    LOAD_CONST                      1: '__pyarmor_assert_13962__'
                7404    LOAD_CONST                      112: 'algorithm_error'   # b'\x81\xe3\x14\x14<\xe8\xb7\xc6\x13\xf72\xc5~\xfe\xf7\x97'
                7406    CALL                            1
                7414    BINARY_SUBSCR                   
                7418    KW_NAMES                        10: ('config', 'account', 'message')
                7420    CALL                            3
                7428    POP_TOP                         
                7430    LOAD_CONST                      81: True
                7432    STORE_FAST                      44: _var_var_54
                7434    POP_EXCEPT                      
                7436    JUMP_BACKWARD                   1053 (to 5334)
                7440    LOAD_FAST                       8: _var_var_19
                7442    LOAD_ATTR                       105: is_connected
                7462    CALL                            0
                7470    POP_JUMP_IF_TRUE                16 (to 7504)
                7472    LOAD_FAST                       8: _var_var_19
                7474    LOAD_ATTR                       49: connect
                7494    CALL                            0
                7502    POP_TOP                         
                7504    POP_EXCEPT                      
                7506    JUMP_BACKWARD                   1568 (to 4374)
                7510    LOAD_GLOBAL                     98: errors
                7520    LOAD_ATTR                       106: FloodWaitError
                7540    CHECK_EXC_MATCH                 
                7542    POP_JUMP_IF_FALSE               337 (to 8220)
                7546    STORE_FAST                      55: _var_var_3
                7548    LOAD_GLOBAL                     13: NULL + Logs
                7558    LOAD_ATTR                       14: PrintLog
                7578    LOAD_FAST                       1: config
                7580    LOAD_FAST                       0: account
                7582    LOAD_GLOBAL                     4: Lang
                7592    PUSH_NULL                       
                7594    LOAD_CONST                      1: '__pyarmor_assert_13962__'
                7596    LOAD_CONST                      113: 'restriction_detected'   # b"\x81\xf0\x1d\x00'\xe8\xb7\xd1\x0f\xf3\x02\xceS\xe8\xfd\x91\n^\xaf\xa2\xae"
                7598    CALL                            1
                7606    BINARY_SUBSCR                   
                7610    KW_NAMES                        10: ('config', 'account', 'message')
                7612    CALL                            3
                7620    POP_TOP                         
                7622    LOAD_GLOBAL                     13: NULL + Logs
                7632    LOAD_ATTR                       14: PrintLog
                7652    LOAD_FAST                       1: config
                7654    LOAD_FAST                       0: account
                7656    LOAD_GLOBAL                     4: Lang
                7666    PUSH_NULL                       
                7668    LOAD_CONST                      1: '__pyarmor_assert_13962__'
                7670    LOAD_CONST                      114: 'flood_wait_sec'   # b'\x81\xe4\x14\x1c<\xfe\x81\xc5\x1a\xf3\x19\xff\x7f\xe9\xfb'
                7672    CALL                            1
                7680    BINARY_SUBSCR                   
                7684    LOAD_FAST                       55: _var_var_3
                7686    LOAD_ATTR                       108: seconds
                7706    KW_NAMES                        35: ('config', 'account', 'message', 'param')
                7708    CALL                            4
                7716    POP_TOP                         
                7718    LOAD_GLOBAL                     13: NULL + Logs
                7728    LOAD_ATTR                       14: PrintLog
                7748    LOAD_FAST                       1: config
                7750    LOAD_FAST                       0: account
                7752    LOAD_GLOBAL                     4: Lang
                7762    PUSH_NULL                       
                7764    LOAD_CONST                      1: '__pyarmor_assert_13962__'
                7766    LOAD_CONST                      115: 'algorithm_running'   # b'\x81\xe3\x14\x14<\xe8\xb7\xc6\x13\xf72\xd2y\xe2\xf6\x8c\x01Z'
                7768    CALL                            1
                7776    BINARY_SUBSCR                   
                7780    KW_NAMES                        10: ('config', 'account', 'message')
                7782    CALL                            3
                7790    POP_TOP                         
                7792    LOAD_GLOBAL                     19: NULL + int
                7802    LOAD_FAST                       55: _var_var_3
                7804    LOAD_ATTR                       108: seconds
                7824    CALL                            1
                7832    LOAD_FAST                       22: _var_var_33
                7834    COMPARE_OP                      68 (>)
                7838    POP_JUMP_IF_FALSE               83 (to 8006)
                7840    LOAD_GLOBAL                     13: NULL + Logs
                7850    LOAD_ATTR                       14: PrintLog
                7870    LOAD_FAST                       1: config
                7872    LOAD_FAST                       0: account
                7874    LOAD_GLOBAL                     4: Lang
                7884    PUSH_NULL                       
                7886    LOAD_CONST                      1: '__pyarmor_assert_13962__'
                7888    LOAD_CONST                      116: 'waiting_time_longer'   # b"\x81\xf5\x19\x1a'\xf3\xb0\xd5$\xee\x04\xcdi\xd3\xf4\x8a\x01Z\xbe\xb5"
                7890    CALL                            1
                7898    BINARY_SUBSCR                   
                7902    LOAD_FAST                       22: _var_var_33
                7904    KW_NAMES                        35: ('config', 'account', 'message', 'param')
                7906    CALL                            4
                7914    POP_TOP                         
                7916    LOAD_GLOBAL                     13: NULL + Logs
                7926    LOAD_ATTR                       14: PrintLog
                7946    LOAD_FAST                       1: config
                7948    LOAD_FAST                       0: account
                7950    LOAD_GLOBAL                     4: Lang
                7960    PUSH_NULL                       
                7962    LOAD_CONST                      1: '__pyarmor_assert_13962__'
                7964    LOAD_CONST                      117: 'shutting_down_my_account'   # b"\x81\xf1\x10\x06'\xee\xb7\xdc\x1c\xc5\t\xcf{\xe2\xc7\x88\x16b\xba\xa4\xa9\xc4[\xc2\x11"
                7966    CALL                            1
                7974    BINARY_SUBSCR                   
                7978    KW_NAMES                        10: ('config', 'account', 'message')
                7980    CALL                            3
                7988    POP_TOP                         
                7990    LOAD_CONST                      31: 1
                7992    STORE_FAST                      47: _var_var_57
                7994    POP_EXCEPT                      
                7996    LOAD_CONST                      0: None
                7998    STORE_FAST                      55: _var_var_3
                8000    DELETE_FAST                     55: _var_var_3
                8002    JUMP_BACKWARD                   1336 (to 5334)
                8006    LOAD_GLOBAL                     19: NULL + int
                8016    LOAD_FAST                       55: _var_var_3
                8018    LOAD_ATTR                       108: seconds
                8038    CALL                            1
                8046    LOAD_CONST                      118: 10
                8048    BINARY_OP                       0 (+)
                8052    STORE_FAST                      56: _var_var_65
                8054    LOAD_GLOBAL                     13: NULL + Logs
                8064    LOAD_ATTR                       14: PrintLog
                8084    LOAD_FAST                       1: config
                8086    LOAD_FAST                       0: account
                8088    LOAD_CONST                      119: 'Wait'
                8090    LOAD_FAST                       56: _var_var_65
                8092    LOAD_CONST                      120: 'sec'
                8094    KW_NAMES                        121: ('config', 'account', 'message', 'param', 'end')
                8096    CALL                            5
                8104    POP_TOP                         
                8106    LOAD_GLOBAL                     103: NULL + DelayOnline
                8116    LOAD_FAST                       0: account
                8118    LOAD_FAST                       8: _var_var_19
                8120    LOAD_FAST                       56: _var_var_65
                8122    LOAD_FAST                       56: _var_var_65
                8124    LOAD_FAST                       6: stop_thread
                8126    CALL                            5
                8134    POP_TOP                         
                8136    LOAD_FAST                       8: _var_var_19
                8138    LOAD_ATTR                       105: is_connected
                8158    CALL                            0
                8166    POP_JUMP_IF_TRUE                16 (to 8200)
                8168    LOAD_FAST                       8: _var_var_19
                8170    LOAD_ATTR                       49: connect
                8190    CALL                            0
                8198    POP_TOP                         
                8200    POP_EXCEPT                      
                8202    LOAD_CONST                      0: None
                8204    STORE_FAST                      55: _var_var_3
                8206    DELETE_FAST                     55: _var_var_3
                8208    JUMP_BACKWARD                   1919 (to 4374)
                8212    LOAD_CONST                      0: None
                8214    STORE_FAST                      55: _var_var_3
                8216    DELETE_FAST                     55: _var_var_3
                8218    RERAISE                         1
                8220    LOAD_GLOBAL                     110: ConnectionError
                8230    CHECK_EXC_MATCH                 
                8232    POP_JUMP_IF_FALSE               74 (to 8382)
                8234    POP_TOP                         
                8236    LOAD_FAST                       8: _var_var_19
                8238    LOAD_ATTR                       105: is_connected
                8258    CALL                            0
                8266    POP_JUMP_IF_TRUE                16 (to 8300)
                8268    LOAD_FAST                       8: _var_var_19
                8270    LOAD_ATTR                       49: connect
                8290    CALL                            0
                8298    POP_TOP                         
                8300    PUSH_NULL                       
                8302    LOAD_FAST                       8: _var_var_19
                8304    LOAD_GLOBAL                     56: functions
                8314    LOAD_ATTR                       112: account
                8334    LOAD_ATTR                       115: UpdateStatusRequest
                8354    LOAD_CONST                      6: False
                8356    KW_NAMES                        122: ('offline',)
                8358    CALL                            1
                8366    CALL                            1
                8374    POP_TOP                         
                8376    POP_EXCEPT                      
                8378    JUMP_BACKWARD                   2004 (to 4374)
                8382    RERAISE                         0
                8384    COPY                            3
                8386    POP_EXCEPT                      
                8388    RERAISE                         1
                8390    PUSH_EXC_INFO                   
                8392    LOAD_GLOBAL                     42: StopProgram
                8402    CHECK_EXC_MATCH                 
                8404    POP_JUMP_IF_FALSE               2 (to 8410)
                8406    POP_TOP                         
                8408    RAISE_VARARGS                   0
                8410    LOAD_GLOBAL                     118: BaseException
                8420    CHECK_EXC_MATCH                 
                8422    POP_JUMP_IF_FALSE               27 (to 8478)
                8424    STORE_FAST                      55: _var_var_3
                8426    PUSH_NULL                       
                8428    LOAD_GLOBAL                     121: NULL + logging
                8438    LOAD_FAST                       55: _var_var_3
                8440    CALL                            1
                8448    CALL                            0
                8456    POP_TOP                         
                8458    POP_EXCEPT                      
                8460    LOAD_CONST                      0: None
                8462    STORE_FAST                      55: _var_var_3
                8464    DELETE_FAST                     55: _var_var_3
                8466    JUMP_BACKWARD                   1425 (to 5620)
                8470    LOAD_CONST                      0: None
                8472    STORE_FAST                      55: _var_var_3
                8474    DELETE_FAST                     55: _var_var_3
                8476    RERAISE                         1
                8478    RERAISE                         0
                8480    COPY                            3
                8482    POP_EXCEPT                      
                8484    RERAISE                         1
                8486    PUSH_EXC_INFO                   
                8488    POP_TOP                         
                8490    POP_EXCEPT                      
                8492    JUMP_BACKWARD                   1326 (to 5844)
                8496    COPY                            3
                8498    POP_EXCEPT                      
                8500    RERAISE                         1
                8502    PUSH_EXC_INFO                   
                8504    LOAD_GLOBAL                     42: StopProgram
                8514    CHECK_EXC_MATCH                 
                8516    POP_JUMP_IF_FALSE               4 (to 8526)
                8518    POP_TOP                         
                8520    POP_EXCEPT                      
                8522    JUMP_BACKWARD                   877 (to 6772)
                8526    LOAD_GLOBAL                     118: BaseException
                8536    CHECK_EXC_MATCH                 
                8538    POP_JUMP_IF_FALSE               27 (to 8594)
                8540    STORE_FAST                      55: _var_var_3
                8542    PUSH_NULL                       
                8544    LOAD_GLOBAL                     121: NULL + logging
                8554    LOAD_FAST                       55: _var_var_3
                8556    CALL                            1
                8564    CALL                            0
                8572    POP_TOP                         
                8574    POP_EXCEPT                      
                8576    LOAD_CONST                      0: None
                8578    STORE_FAST                      55: _var_var_3
                8580    DELETE_FAST                     55: _var_var_3
                8582    JUMP_BACKWARD                   907 (to 6772)
                8586    LOAD_CONST                      0: None
                8588    STORE_FAST                      55: _var_var_3
                8590    DELETE_FAST                     55: _var_var_3
                8592    RERAISE                         1
                8594    RERAISE                         0
                8596    COPY                            3
                8598    POP_EXCEPT                      
                8600    RERAISE                         1
                8602    PUSH_EXC_INFO                   
                8604    POP_TOP                         
                8606    POP_EXCEPT                      
                8608    JUMP_BACKWARD                   909 (to 6794)
                8612    COPY                            3
                8614    POP_EXCEPT                      
                8616    RERAISE                         1
                8618    PUSH_EXC_INFO                   
                8620    POP_TOP                         
                8622    POP_EXCEPT                      
                8624    JUMP_BACKWARD                   896 (to 6836)
                8628    COPY                            3
                8630    POP_EXCEPT                      
                8632    RERAISE                         1
                8634    PUSH_EXC_INFO                   
                8636    LOAD_GLOBAL                     7: NULL + Disconnect
                8646    LOAD_FAST_CHECK                 8: _var_var_19
                8648    CALL                            1
                8656    POP_TOP                         
                8658    JUMP_FORWARD                    7 (to 8674)
                8660    PUSH_EXC_INFO                   
                8662    POP_TOP                         
                8664    POP_EXCEPT                      
                8666    JUMP_FORWARD                    3 (to 8674)
                8668    COPY                            3
                8670    POP_EXCEPT                      
                8672    RERAISE                         1
                8674    LOAD_GLOBAL                     9: NULL + db_parsing_res
                8684    LOAD_ATTR                       10: disconnect
                8704    LOAD_FAST_CHECK                 9: _var_var_20
                8706    CALL                            1
                8714    POP_TOP                         
                8716    JUMP_FORWARD                    7 (to 8732)
                8718    PUSH_EXC_INFO                   
                8720    POP_TOP                         
                8722    POP_EXCEPT                      
                8724    JUMP_FORWARD                    3 (to 8732)
                8726    COPY                            3
                8728    POP_EXCEPT                      
                8730    RERAISE                         1
                8732    LOAD_GLOBAL                     13: NULL + Logs
                8742    LOAD_ATTR                       14: PrintLog
                8762    LOAD_FAST                       1: config
                8764    LOAD_FAST                       0: account
                8766    LOAD_GLOBAL                     4: Lang
                8776    PUSH_NULL                       
                8778    LOAD_CONST                      1: '__pyarmor_assert_13962__'
                8780    LOAD_CONST                      9: 'work_account_completed'   # b'\x81\xf5\x17\x018\xc5\xbf\xd1\x18\xf5\x18\xcex\xd3\xfb\x8a\x02M\xb7\xa2\xbe\xceJ'
                8782    CALL                            1
                8790    BINARY_SUBSCR                   
                8794    KW_NAMES                        10: ('config', 'account', 'message')
                8796    CALL                            3
                8804    POP_TOP                         
                8806    LOAD_FAST                       0: account
                8808    LOAD_CONST                      11: 'done'
                8810    LOAD_CONST                      8: ('account', 'status')
                8812    BUILD_CONST_KEY_MAP             2
                8814    SWAP                            2
                8816    POP_TOP                         
                8818    SWAP                            2
                8820    POP_EXCEPT                      
                8822    NOP                             
                8824    NOP                             
                8826    NOP                             
                8828    JUMP_FORWARD                    23 (to 8876)
                8830    CALL                            1
                8838    POP_TOP                         
                8840    RETURN_VALUE                    
                8842    COPY                            3
                8844    POP_EXCEPT                      
                8846    RERAISE                         1
                8848    PUSH_EXC_INFO                   
                8850    PUSH_NULL                       
                8852    LOAD_CONST                      12: '__pyarmor_exit_13964__'
                8854    NOP                             
                8856    LOAD_CONST                      3: b'<COAddr>\x07\x00\x00\x1av"\x00\x00\x00\x00\x00\x00\x00\x00\x00\x00\x00\x00\x00\x00'
                8858    CALL                            1
                8866    POP_TOP                         
                8868    RERAISE                         0
                8870    COPY                            3
                8872    POP_EXCEPT                      
                8874    RERAISE                         1
                8876    PUSH_NULL                       
                8878    LOAD_CONST                      12: '__pyarmor_exit_13964__'
                8880    LOAD_CONST                      3: b'<COAddr>\x07\x00\x00\x1av"\x00\x00\x00\x00\x00\x00\x00\x00\x00\x00\x00\x00\x00\x00'
                8882    BUILD_TUPLE                     1
                8884    CALL_FUNCTION_EX                0
                8886    POP_TOP                         
                8888    RETURN_VALUE                    
            [Exception Table]
                30 to 116 -> 8502 [0] 
                116 to 138 -> 6938 [1] 
                138 to 180 -> 6954 [1] 
                180 to 266 -> 8848 [0] 
                286 to 1106 -> 8502 [0] 
                1106 to 1128 -> 6970 [0] 
                1128 to 1146 -> 8502 [0] 
                1146 to 1168 -> 6986 [1] 
                1168 to 1210 -> 7002 [1] 
                1210 to 1296 -> 8848 [0] 
                1316 to 1540 -> 8502 [0] 
                1540 to 1562 -> 7018 [0] 
                1562 to 1582 -> 8502 [0] 
                1582 to 1604 -> 7034 [1] 
                1604 to 1646 -> 7050 [1] 
                1646 to 1732 -> 8848 [0] 
                1752 to 1900 -> 8502 [0] 
                1900 to 1922 -> 7066 [0] 
                1922 to 1930 -> 8502 [0] 
                1930 to 1952 -> 7082 [1] 
                1952 to 1994 -> 7098 [1] 
                1994 to 2080 -> 8848 [0] 
                2100 to 2502 -> 8502 [0] 
                2502 to 2524 -> 7114 [0] 
                2524 to 2530 -> 8502 [0] 
                2530 to 2552 -> 7130 [1] 
                2552 to 2594 -> 7146 [1] 
                2594 to 2680 -> 8848 [0] 
                2700 to 3314 -> 8502 [0] 
                3316 to 3436 -> 7162 [0] 
                3436 to 3440 -> 8502 [0] 
                3442 to 3572 -> 7178 [0] 
                3572 to 4078 -> 8502 [0] 
                4080 to 4558 -> 8390 [0] 
                4560 to 4750 -> 7194 [1] 
                4750 to 4754 -> 8390 [0] 
                4754 to 4896 -> 7194 [1] 
                4898 to 4914 -> 7194 [1] 
                4916 to 5328 -> 7194 [1] 
                5328 to 5458 -> 8390 [0] 
                5462 to 5620 -> 8390 [0] 
                5620 to 5822 -> 8502 [0] 
                5822 to 5844 -> 8486 [0] 
                5844 to 6772 -> 8502 [0] 
                6772 to 6794 -> 8602 [0] 
                6794 to 6836 -> 8618 [0] 
                6836 to 6918 -> 8848 [0] 
                6938 to 6942 -> 6948 [2] lasti
                6942 to 6954 -> 8848 [0] 
                6954 to 6958 -> 6964 [2] lasti
                6958 to 6970 -> 8848 [0] 
                6970 to 6974 -> 6980 [1] lasti
                6974 to 6986 -> 8502 [0] 
                6986 to 6990 -> 6996 [2] lasti
                6990 to 7002 -> 8848 [0] 
                7002 to 7006 -> 7012 [2] lasti
                7006 to 7018 -> 8848 [0] 
                7018 to 7022 -> 7028 [1] lasti
                7022 to 7034 -> 8502 [0] 
                7034 to 7038 -> 7044 [2] lasti
                7038 to 7050 -> 8848 [0] 
                7050 to 7054 -> 7060 [2] lasti
                7054 to 7066 -> 8848 [0] 
                7066 to 7070 -> 7076 [1] lasti
                7070 to 7082 -> 8502 [0] 
                7082 to 7086 -> 7092 [2] lasti
                7086 to 7098 -> 8848 [0] 
                7098 to 7102 -> 7108 [2] lasti
                7102 to 7114 -> 8848 [0] 
                7114 to 7118 -> 7124 [1] lasti
                7118 to 7130 -> 8502 [0] 
                7130 to 7134 -> 7140 [2] lasti
                7134 to 7146 -> 8848 [0] 
                7146 to 7150 -> 7156 [2] lasti
                7150 to 7162 -> 8848 [0] 
                7162 to 7166 -> 7172 [1] lasti
                7166 to 7178 -> 8502 [0] 
                7178 to 7182 -> 7188 [1] lasti
                7182 to 7194 -> 8502 [0] 
                7194 to 7434 -> 8384 [2] lasti
                7434 to 7440 -> 8390 [0] 
                7440 to 7504 -> 8384 [2] lasti
                7504 to 7510 -> 8390 [0] 
                7510 to 7548 -> 8384 [2] lasti
                7548 to 7994 -> 8212 [2] lasti
                7994 to 8006 -> 8390 [0] 
                8006 to 8200 -> 8212 [2] lasti
                8200 to 8212 -> 8390 [0] 
                8212 to 8376 -> 8384 [2] lasti
                8376 to 8382 -> 8390 [0] 
                8382 to 8384 -> 8384 [2] lasti
                8384 to 8390 -> 8390 [0] 
                8390 to 8426 -> 8480 [1] lasti
                8426 to 8458 -> 8470 [1] lasti
                8458 to 8470 -> 8502 [0] 
                8470 to 8480 -> 8480 [1] lasti
                8480 to 8486 -> 8502 [0] 
                8486 to 8490 -> 8496 [1] lasti
                8490 to 8502 -> 8502 [0] 
                8502 to 8520 -> 8596 [1] lasti
                8520 to 8526 -> 8634 [0] 
                8526 to 8542 -> 8596 [1] lasti
                8542 to 8574 -> 8586 [1] lasti
                8574 to 8586 -> 8634 [0] 
                8586 to 8596 -> 8596 [1] lasti
                8596 to 8602 -> 8634 [0] 
                8602 to 8606 -> 8612 [1] lasti
                8606 to 8618 -> 8848 [0] 
                8618 to 8622 -> 8628 [1] lasti
                8622 to 8634 -> 8848 [0] 
                8634 to 8636 -> 8842 [1] lasti
                8636 to 8658 -> 8660 [2] 
                8658 to 8660 -> 8842 [1] lasti
                8660 to 8664 -> 8668 [3] lasti
                8664 to 8674 -> 8842 [1] lasti
                8674 to 8716 -> 8718 [2] 
                8716 to 8718 -> 8842 [1] lasti
                8718 to 8722 -> 8726 [3] lasti
                8722 to 8820 -> 8842 [1] lasti
                8820 to 8822 -> 8848 [0] 
                8842 to 8848 -> 8848 [0] 
                8848 to 8870 -> 8870 [1] lasti
        '__pyarmor_exit_13952__'
    [Disassembly]
        0       NOP                             
        2       NOP                             
        4       PUSH_NULL                       
        6       LOAD_CONST                      1: '__pyarmor_enter_13951__'
        8       LOAD_CONST                      2: b'<COAddr>\x05\x00\x00\x1a\xb4\x01\x00\x00\x00\x00\x00\x00\x00\x00\x00\x00\x00\x00\x00\x00'
        10      BUILD_TUPLE                     1
        12      CALL_FUNCTION_EX                0
        14      POP_TOP                         
        16      RESUME                          0
        18      NOP                             
        20      NOP                             
        22      NOP                             
        24      NOP                             
        26      LOAD_CONST                      3: 0
        28      LOAD_CONST                      4: None
        30      IMPORT_NAME                     1: eel
        32      STORE_NAME                      1: eel
        34      LOAD_CONST                      3: 0
        36      LOAD_CONST                      4: None
        38      IMPORT_NAME                     2: json
        40      STORE_NAME                      2: json
        42      LOAD_CONST                      3: 0
        44      LOAD_CONST                      4: None
        46      IMPORT_NAME                     3: time
        48      STORE_NAME                      3: time
        50      LOAD_CONST                      3: 0
        52      LOAD_CONST                      4: None
        54      IMPORT_NAME                     4: datetime
        56      STORE_NAME                      4: datetime
        58      LOAD_CONST                      3: 0
        60      LOAD_CONST                      4: None
        62      IMPORT_NAME                     5: concurrent.futures
        64      STORE_NAME                      6: concurrent
        66      LOAD_CONST                      3: 0
        68      LOAD_CONST                      5: ('Thread', 'Event')
        70      IMPORT_NAME                     7: threading
        72      IMPORT_FROM                     8: Thread
        74      STORE_NAME                      8: Thread
        76      IMPORT_FROM                     9: Event
        78      STORE_NAME                      9: Event
        80      POP_TOP                         
        82      LOAD_CONST                      3: 0
        84      LOAD_CONST                      6: ('functions', 'types', 'errors')
        86      IMPORT_NAME                     10: multithon.sync
        88      IMPORT_FROM                     11: functions
        90      STORE_NAME                      11: functions
        92      IMPORT_FROM                     12: types
        94      STORE_NAME                      12: types
        96      IMPORT_FROM                     13: errors
        98      STORE_NAME                      13: errors
        100     POP_TOP                         
        102     LOAD_CONST                      3: 0
        104     LOAD_CONST                      7: ('StopProgram',)
        106     IMPORT_NAME                     14: multithon.errors
        108     IMPORT_FROM                     15: StopProgram
        110     STORE_NAME                      15: StopProgram
        112     POP_TOP                         
        114     LOAD_CONST                      3: 0
        116     LOAD_CONST                      8: ('GetLang',)
        118     IMPORT_NAME                     16: program.static_classes
        120     IMPORT_FROM                     17: GetLang
        122     STORE_NAME                      17: GetLang
        124     POP_TOP                         
        126     LOAD_CONST                      3: 0
        128     LOAD_CONST                      9: ('Logs',)
        130     IMPORT_NAME                     16: program.static_classes
        132     IMPORT_FROM                     18: Logs
        134     STORE_NAME                      18: Logs
        136     POP_TOP                         
        138     LOAD_CONST                      3: 0
        140     LOAD_CONST                      10: ('logging',)
        142     IMPORT_NAME                     16: program.static_classes
        144     IMPORT_FROM                     19: logging
        146     STORE_NAME                      19: logging
        148     POP_TOP                         
        150     LOAD_CONST                      3: 0
        152     LOAD_CONST                      11: ('memory_check_switcher',)
        154     IMPORT_NAME                     16: program.static_classes
        156     IMPORT_FROM                     20: memory_check_switcher
        158     STORE_NAME                      20: memory_check_switcher
        160     POP_TOP                         
        162     LOAD_CONST                      3: 0
        164     LOAD_CONST                      12: ('memory_set_pid',)
        166     IMPORT_NAME                     16: program.static_classes
        168     IMPORT_FROM                     21: memory_set_pid
        170     STORE_NAME                      21: memory_set_pid
        172     POP_TOP                         
        174     LOAD_CONST                      3: 0
        176     LOAD_CONST                      13: ('DelayOnline',)
        178     IMPORT_NAME                     22: program.telegram
        180     IMPORT_FROM                     23: DelayOnline
        182     STORE_NAME                      23: DelayOnline
        184     POP_TOP                         
        186     LOAD_CONST                      3: 0
        188     LOAD_CONST                      14: ('Disconnect',)
        190     IMPORT_NAME                     22: program.telegram
        192     IMPORT_FROM                     24: Disconnect
        194     STORE_NAME                      24: Disconnect
        196     POP_TOP                         
        198     LOAD_CONST                      3: 0
        200     LOAD_CONST                      15: ('Thread_wait',)
        202     IMPORT_NAME                     22: program.telegram
        204     IMPORT_FROM                     25: Thread_wait
        206     STORE_NAME                      25: Thread_wait
        208     POP_TOP                         
        210     LOAD_CONST                      3: 0
        212     LOAD_CONST                      16: ('account_works',)
        214     IMPORT_NAME                     22: program.telegram
        216     IMPORT_FROM                     26: account_works
        218     STORE_NAME                      26: account_works
        220     POP_TOP                         
        222     LOAD_CONST                      3: 0
        224     LOAD_CONST                      17: ('entity',)
        226     IMPORT_NAME                     22: program.telegram
        228     IMPORT_FROM                     27: entity
        230     STORE_NAME                      27: entity
        232     POP_TOP                         
        234     LOAD_CONST                      3: 0
        236     LOAD_CONST                      18: ('parsing_time',)
        238     IMPORT_NAME                     22: program.telegram
        240     IMPORT_FROM                     28: parsing_time
        242     STORE_NAME                      28: parsing_time
        244     POP_TOP                         
        246     LOAD_CONST                      3: 0
        248     LOAD_CONST                      19: ('tg_group',)
        250     IMPORT_NAME                     22: program.telegram
        252     IMPORT_FROM                     29: tg_group
        254     STORE_NAME                      29: tg_group
        256     POP_TOP                         
        258     LOAD_CONST                      3: 0
        260     LOAD_CONST                      20: ('tg_links',)
        262     IMPORT_NAME                     22: program.telegram
        264     IMPORT_FROM                     30: tg_links
        266     STORE_NAME                      30: tg_links
        268     POP_TOP                         
        270     LOAD_CONST                      3: 0
        272     LOAD_CONST                      21: ('txt_file',)
        274     IMPORT_NAME                     22: program.telegram
        276     IMPORT_FROM                     31: txt_file
        278     STORE_NAME                      31: txt_file
        280     POP_TOP                         
        282     LOAD_CONST                      3: 0
        284     LOAD_CONST                      22: ('GetConfig',)
        286     IMPORT_NAME                     32: program.general
        288     IMPORT_FROM                     33: GetConfig
        290     STORE_NAME                      33: GetConfig
        292     POP_TOP                         
        294     LOAD_CONST                      3: 0
        296     LOAD_CONST                      23: ('GetProxy',)
        298     IMPORT_NAME                     32: program.general
        300     IMPORT_FROM                     34: GetProxy
        302     STORE_NAME                      34: GetProxy
        304     POP_TOP                         
        306     LOAD_CONST                      3: 0
        308     LOAD_CONST                      24: ('StopDetect',)
        310     IMPORT_NAME                     32: program.general
        312     IMPORT_FROM                     35: StopDetect
        314     STORE_NAME                      35: StopDetect
        316     POP_TOP                         
        318     LOAD_CONST                      3: 0
        320     LOAD_CONST                      25: ('check_get_settings',)
        322     IMPORT_NAME                     32: program.general
        324     IMPORT_FROM                     36: check_get_settings
        326     STORE_NAME                      36: check_get_settings
        328     POP_TOP                         
        330     LOAD_CONST                      3: 0
        332     LOAD_CONST                      26: ('del_task_manager',)
        334     IMPORT_NAME                     32: program.general
        336     IMPORT_FROM                     37: del_task_manager
        338     STORE_NAME                      37: del_task_manager
        340     POP_TOP                         
        342     LOAD_CONST                      3: 0
        344     LOAD_CONST                      27: ('getFile',)
        346     IMPORT_NAME                     32: program.general
        348     IMPORT_FROM                     38: getFile
        350     STORE_NAME                      38: getFile
        352     POP_TOP                         
        354     LOAD_CONST                      3: 0
        356     LOAD_CONST                      28: ('set_task_manager',)
        358     IMPORT_NAME                     32: program.general
        360     IMPORT_FROM                     39: set_task_manager
        362     STORE_NAME                      39: set_task_manager
        364     POP_TOP                         
        366     LOAD_CONST                      3: 0
        368     LOAD_CONST                      29: ('db_parsing',)
        370     IMPORT_NAME                     40: program.database
        372     IMPORT_FROM                     41: db_parsing
        374     STORE_NAME                      41: db_parsing
        376     POP_TOP                         
        378     LOAD_CONST                      3: 0
        380     LOAD_CONST                      30: ('db_base',)
        382     IMPORT_NAME                     40: program.database
        384     IMPORT_FROM                     42: db_base
        386     STORE_NAME                      42: db_base
        388     POP_TOP                         
        390     LOAD_CONST                      3: 0
        392     LOAD_CONST                      31: ('db_parsing_res',)
        394     IMPORT_NAME                     40: program.database
        396     IMPORT_FROM                     43: db_parsing_res
        398     STORE_NAME                      43: db_parsing_res
        400     POP_TOP                         
        402     PUSH_NULL                       
        404     LOAD_BUILD_CLASS                
        406     LOAD_CONST                      32: <CODE> Stop
        408     MAKE_FUNCTION                   0
        410     LOAD_CONST                      33: 'Stop'
        412     LOAD_NAME                       44: Exception
        414     CALL                            3
        422     STORE_NAME                      45: Stop
        424     LOAD_CONST                      34: <CODE> Parsing
        426     MAKE_FUNCTION                   0
        428     STORE_NAME                      46: Parsing
        430     LOAD_CONST                      35: <CODE> START
        432     MAKE_FUNCTION                   0
        434     STORE_NAME                      47: START
        436     LOAD_CONST                      36: <CODE> worker
        438     MAKE_FUNCTION                   0
        440     STORE_NAME                      48: worker
        442     LOAD_CONST                      4: None
        444     NOP                             
        446     NOP                             
        448     NOP                             
        450     JUMP_FORWARD                    19 (to 490)
        458     POP_TOP                         
        460     RETURN_CONST                    4: None
        462     PUSH_EXC_INFO                   
        464     PUSH_NULL                       
        466     LOAD_CONST                      37: '__pyarmor_exit_13952__'
        468     NOP                             
        470     LOAD_CONST                      2: b'<COAddr>\x05\x00\x00\x1a\xb4\x01\x00\x00\x00\x00\x00\x00\x00\x00\x00\x00\x00\x00\x00\x00'
        472     CALL                            1
        480     POP_TOP                         
        482     RERAISE                         0
        484     COPY                            3
        486     POP_EXCEPT                      
        488     RERAISE                         1
        490     PUSH_NULL                       
        492     LOAD_CONST                      37: '__pyarmor_exit_13952__'
        494     LOAD_CONST                      2: b'<COAddr>\x05\x00\x00\x1a\xb4\x01\x00\x00\x00\x00\x00\x00\x00\x00\x00\x00\x00\x00\x00\x00'
        496     BUILD_TUPLE                     1
        498     CALL_FUNCTION_EX                0
        500     POP_TOP                         
        502     RETURN_VALUE                    
    [Exception Table]
        26 to 442 -> 462 [0] 
        462 to 484 -> 484 [1] lasti
