#decoded by lolz.live/mrpenny / t.me/zeus_jackpot
# ================================
# Примечания по Pyarmor:
# - Байт-код и объекты кода Pyarmor соответствуют стандартному Python, но присутствуют специальные вызовы функций среды выполнения (runtime) Pyarmor.
# - Вызовы строк — это не ошибки, а маркеры, которые обрабатываются Pyarmor во время выполнения.
#
# Руководство по декомпиляции (без среды выполнения):
# 1. Игнорируйте зашифрованные байты после `#`; используйте только строку до `#`.
# 2. Удалите "__pyarmor_enter_xxx__"(b"<COAddr>...") и "__pyarmor_leave_xxx__"(b"<COAddr>...") (пролог/эпилог).
# 3. "__pyarmor_assert_xxx__"(A) не является настоящим оператором assert.
#    - Если A — это имя или читаемая строка: замените на A.
#    - Если A — это (X, "Y"): замените на X.Y.
#    - Если A — это (X, "Y", Z): замените на X.Y = Z.
#    - В противном случае: выберите наиболее подходящую/логичную замену.
# 4. "__pyarmor_bcc_xxx__"(...) указывает на машинный (нативный) код; тело функции недоступно. Добавьте комментарий.
# ================================

[Code]
    File Name: <frozen program.modules.Proxy_checker>
    Object Name: <module>
    Qualified Name: <module>
    Arg Count: 0
    Pos Only Arg Count: 0
    KW Only Arg Count: 0
    Stack Size: 5
    Flags: 0x20000000 (CO_PYARMOR_OBFUSCATED)
    [Names]
        '__assert_armored__'
        'eel'
        'requests'
        'concurrent.futures'
        'concurrent'
        'threading'
        'Thread'
        'Event'
        'multithon.errors'
        'StopProgram'
        'program.static_classes'
        'GetLang'
        'Logs'
        'logging'
        'memory_check_switcher'
        'memory_set_pid'
        'program.general'
        'GetConfig'
        'GetProxy'
        'StopDetect'
        'del_task_manager'
        'Proxy_checker'
        'START'
        'worker'
    [Locals+Names]
    [Constants]
        '__pyarmor_assert_14034__'
        '__pyarmor_enter_14035__'
        b'<COAddr>\x07\x00\x00\x1a\xc6\x00\x00\x00\x00\x00\x00\x00\x00\x00\x00\x00\x00\x00\x00\x00'
        0
        None
        (
            'Thread'
            'Event'
        )
        (
            'StopProgram'
        )
        (
            'GetLang'
        )
        (
            'Logs'
        )
        (
            'logging'
        )
        (
            'memory_check_switcher'
        )
        (
            'memory_set_pid'
        )
        (
            'GetConfig'
        )
        (
            'GetProxy'
        )
        (
            'StopDetect'
        )
        (
            'del_task_manager'
        )
        [Code]
            File Name: <frozen program.modules.Proxy_checker>
            Object Name: Proxy_checker
            Qualified Name: Proxy_checker
            Arg Count: 1
            Pos Only Arg Count: 0
            KW Only Arg Count: 0
            Stack Size: 8
            Flags: 0x20000003 (CO_OPTIMIZED | CO_NEWLOCALS | CO_PYARMOR_OBFUSCATED)
            [Names]
                'GetConfig'
                'config'
                'GetLang'
                'Lang'
                'GetProxy'
                'eel'
                'sendSuccessBox'
                'memory_check_switcher'
                'Event'
                'memory_set_pid'
                'Thread'
                'START'
                'start'
                'Logs'
                'WaitStopAnsfer'
                'UpdateLogInWindow'
                'BaseException'
                'logging'
            [Locals+Names]
                'data'
                '__assert_armored__'
                '_var_var_0'
                '_var_var_1'
                '_var_var_2'
                '_var_var_3'
            [Constants]
                None
                '__pyarmor_assert_14037__'
                '__pyarmor_enter_14038__'
                b'<COAddr>\x07\x00\x00\x1aT\x02\x00\x00\x00\x00\x00\x00\x00\x00\x00\x00\x00\x00\x00\x00'
                'program_running'   # b'\x81\xf2\n\x1c4\xe8\xbf\xdf$\xe8\x18\xceb\xe5\xf6\x82'
                '__pyarmor_exit_14039__'
                False
                (
                    'target'
                    'args'
                )
                True
                (
                    'target'
                    'args'
                    'daemon'
                )
            [Disassembly]
                0       NOP                             
                2       NOP                             
                4       PUSH_NULL                       
                6       LOAD_CONST                      2: '__pyarmor_enter_14038__'
                8       LOAD_CONST                      3: b'<COAddr>\x07\x00\x00\x1aT\x02\x00\x00\x00\x00\x00\x00\x00\x00\x00\x00\x00\x00\x00\x00'
                10      BUILD_TUPLE                     1
                12      CALL_FUNCTION_EX                0
                14      POP_TOP                         
                16      RESUME                          0
                18      NOP                             
                20      NOP                             
                22      NOP                             
                24      NOP                             
                26      NOP                             
                28      NOP                             
                30      LOAD_GLOBAL                     1: NULL + GetConfig
                40      CALL                            0
                48      STORE_GLOBAL                    1: config
                50      LOAD_GLOBAL                     5: NULL + GetLang
                60      LOAD_GLOBAL                     2: config
                70      CALL                            1
                78      STORE_GLOBAL                    3: Lang
                80      LOAD_GLOBAL                     9: NULL + GetProxy
                90      CALL                            0
                98      STORE_FAST                      2: _var_var_0
                100     LOAD_GLOBAL                     11: NULL + eel
                110     LOAD_ATTR                       12: sendSuccessBox
                130     LOAD_GLOBAL                     6: Lang
                140     PUSH_NULL                       
                142     LOAD_CONST                      1: '__pyarmor_assert_14037__'
                144     LOAD_CONST                      4: 'program_running'   # b'\x81\xf2\n\x1c4\xe8\xbf\xdf$\xe8\x18\xceb\xe5\xf6\x82'
                146     CALL                            1
                154     BINARY_SUBSCR                   
                158     CALL                            1
                166     POP_TOP                         
                168     LOAD_GLOBAL                     15: NULL + memory_check_switcher
                178     CALL                            0
                186     POP_JUMP_IF_TRUE                11 (to 210)
                188     NOP                             
                190     LOAD_CONST                      6: False
                192     NOP                             
                194     NOP                             
                196     NOP                             
                198     JUMP_FORWARD                    225 (to 650)
                206     POP_TOP                         
                208     RETURN_CONST                    6: False
                210     LOAD_GLOBAL                     17: NULL + Event
                220     CALL                            0
                228     STORE_FAST                      3: _var_var_1
                230     LOAD_GLOBAL                     19: NULL + memory_set_pid
                240     CALL                            0
                248     STORE_FAST                      4: _var_var_2
                250     LOAD_GLOBAL                     21: NULL + Thread
                260     LOAD_GLOBAL                     22: START
                270     LOAD_FAST                       0: data
                272     LOAD_GLOBAL                     2: config
                282     LOAD_FAST                       4: _var_var_2
                284     LOAD_FAST                       2: _var_var_0
                286     LOAD_FAST                       3: _var_var_1
                288     BUILD_TUPLE                     5
                290     KW_NAMES                        7: ('target', 'args')
                292     CALL                            2
                300     LOAD_ATTR                       25: start
                320     CALL                            0
                328     POP_TOP                         
                330     LOAD_GLOBAL                     21: NULL + Thread
                340     LOAD_GLOBAL                     26: Logs
                350     LOAD_ATTR                       28: WaitStopAnsfer
                370     LOAD_GLOBAL                     2: config
                380     LOAD_FAST                       4: _var_var_2
                382     LOAD_FAST                       3: _var_var_1
                384     BUILD_TUPLE                     3
                386     LOAD_CONST                      8: True
                388     KW_NAMES                        9: ('target', 'args', 'daemon')
                390     CALL                            3
                398     LOAD_ATTR                       25: start
                418     CALL                            0
                426     POP_TOP                         
                428     LOAD_GLOBAL                     21: NULL + Thread
                438     LOAD_GLOBAL                     26: Logs
                448     LOAD_ATTR                       30: UpdateLogInWindow
                468     LOAD_GLOBAL                     2: config
                478     LOAD_FAST                       4: _var_var_2
                480     LOAD_FAST                       3: _var_var_1
                482     BUILD_TUPLE                     3
                484     LOAD_CONST                      8: True
                486     KW_NAMES                        9: ('target', 'args', 'daemon')
                488     CALL                            3
                496     LOAD_ATTR                       25: start
                516     CALL                            0
                524     POP_TOP                         
                526     LOAD_CONST                      0: None
                528     NOP                             
                530     NOP                             
                532     NOP                             
                534     JUMP_FORWARD                    57 (to 650)
                542     POP_TOP                         
                544     RETURN_CONST                    0: None
                546     PUSH_EXC_INFO                   
                548     LOAD_GLOBAL                     32: BaseException
                558     CHECK_EXC_MATCH                 
                560     POP_JUMP_IF_FALSE               26 (to 614)
                562     STORE_FAST                      5: _var_var_3
                564     PUSH_NULL                       
                566     LOAD_GLOBAL                     35: NULL + logging
                576     LOAD_FAST                       5: _var_var_3
                578     CALL                            1
                586     CALL                            0
                594     POP_TOP                         
                596     POP_EXCEPT                      
                598     LOAD_CONST                      0: None
                600     STORE_FAST                      5: _var_var_3
                602     DELETE_FAST                     5: _var_var_3
                604     JUMP_BACKWARD                   40 (to 526)
                606     LOAD_CONST                      0: None
                608     STORE_FAST                      5: _var_var_3
                610     DELETE_FAST                     5: _var_var_3
                612     RERAISE                         1
                614     RERAISE                         0
                616     COPY                            3
                618     POP_EXCEPT                      
                620     RERAISE                         1
                622     PUSH_EXC_INFO                   
                624     PUSH_NULL                       
                626     LOAD_CONST                      5: '__pyarmor_exit_14039__'
                628     NOP                             
                630     LOAD_CONST                      3: b'<COAddr>\x07\x00\x00\x1aT\x02\x00\x00\x00\x00\x00\x00\x00\x00\x00\x00\x00\x00\x00\x00'
                632     CALL                            1
                640     POP_TOP                         
                642     RERAISE                         0
                644     COPY                            3
                646     POP_EXCEPT                      
                648     RERAISE                         1
                650     PUSH_NULL                       
                652     LOAD_CONST                      5: '__pyarmor_exit_14039__'
                654     LOAD_CONST                      3: b'<COAddr>\x07\x00\x00\x1aT\x02\x00\x00\x00\x00\x00\x00\x00\x00\x00\x00\x00\x00\x00\x00'
                656     BUILD_TUPLE                     1
                658     CALL_FUNCTION_EX                0
                660     POP_TOP                         
                662     RETURN_VALUE                    
            [Exception Table]
                30 to 188 -> 546 [0] 
                210 to 526 -> 546 [0] 
                546 to 564 -> 616 [1] lasti
                564 to 596 -> 606 [1] lasti
                596 to 606 -> 622 [0] 
                606 to 616 -> 616 [1] lasti
                616 to 622 -> 622 [0] 
                622 to 644 -> 644 [1] lasti
        [Code]
            File Name: <frozen program.modules.Proxy_checker>
            Object Name: START
            Qualified Name: START
            Arg Count: 5
            Pos Only Arg Count: 0
            KW Only Arg Count: 0
            Stack Size: 9
            Flags: 0x20000003 (CO_OPTIMIZED | CO_NEWLOCALS | CO_PYARMOR_OBFUSCATED)
            [Names]
                'is_set'
                'StopProgram'
                'get'
                'split'
                'len'
                'format'
                'int'
                'append'
                'Logs'
                'PrintLog'
                'Lang'
                'concurrent'
                'futures'
                'ThreadPoolExecutor'
                'range'
                'submit'
                'worker'
                'as_completed'
                'result'
                'eel'
                'LoadProxyResult'
                'BaseException'
                'logging'
                'del_task_manager'
                'StopDetect'
            [Locals+Names]
                'data'
                'config'
                'pid'
                'proxy'
                'stop_thread'
                '__assert_armored__'
                '_var_var_4'
                '_var_var_5'
                '_var_var_6'
                '_var_var_7'
                '_var_var_8'
                '_var_var_9'
                '_var_var_10'
                '_var_var_11'
                '_var_var_12'
                '_var_var_13'
                '_var_var_14'
                '_var_var_15'
                '_var_var_16'
                '_var_var_17'
                '_var_var_18'
                '_var_var_3'
            [Constants]
                None
                '__pyarmor_assert_14040__'
                '__pyarmor_enter_14041__'
                b'<COAddr>\x07\x00\x00\x1a\x82\n\x00\x00\x00\x00\x00\x00\x00\x00\x00\x00\x00\x00\x00\x00'
                'Settings'
                'mode'
                'proxy_type'   # b'\x81\xf2\n\x1c+\xe3\x81\xc6\x02\xea\x08'
                'rotate'
                'proxy_rotate'   # b'\x81\xf2\n\x1c+\xe3\x81\xc0\x14\xee\x0c\xd4i'
                ':'
                2
                'http'
                'http://{}:{}/'   # b'\x81\xea\x0c\x07#\xa0\xf1\x9d\x00\xe7W\xdbq\xa3'
                0
                1
                (
                    'http'
                    'https'
                )
                (
                    'socks5h'
                    'socks5h'
                )
                'http://{}:{}@{}:{}/'   # b'\x81\xea\x0c\x07#\xa0\xf1\x9d\x00\xe7W\xdbq\xcc\xe3\x98UF\xa6\xe8'
                3
                'requests'
                'usernames'   # b'\x81\xf7\x0b\x16!\xf4\xbf\xdf\x1e\xe9'
                'program_running'   # b'\x81\xf2\n\x1c4\xe8\xbf\xdf$\xe8\x18\xceb\xe5\xf6\x82'
                (
                    'config'
                    'message'
                )
                50
                (
                    'max_workers'
                )
                'status'
                'ok'
                'ip'
                'job_done'
                '__pyarmor_exit_14042__'
                'Done'
            [Disassembly]
                0       NOP                             
                2       NOP                             
                4       PUSH_NULL                       
                6       LOAD_CONST                      2: '__pyarmor_enter_14041__'
                8       LOAD_CONST                      3: b'<COAddr>\x07\x00\x00\x1a\x82\n\x00\x00\x00\x00\x00\x00\x00\x00\x00\x00\x00\x00\x00\x00'
                10      BUILD_TUPLE                     1
                12      CALL_FUNCTION_EX                0
                14      POP_TOP                         
                16      RESUME                          0
                18      NOP                             
                20      NOP                             
                22      NOP                             
                24      NOP                             
                26      NOP                             
                28      NOP                             
                30      LOAD_FAST                       4: stop_thread
                32      LOAD_ATTR                       1: is_set
                52      CALL                            0
                60      POP_JUMP_IF_FALSE               10 (to 82)
                62      LOAD_GLOBAL                     3: NULL + StopProgram
                72      CALL                            0
                80      RAISE_VARARGS                   1
                82      LOAD_FAST                       0: data
                84      LOAD_CONST                      4: 'Settings'
                86      BINARY_SUBSCR                   
                90      LOAD_ATTR                       5: get
                110     LOAD_CONST                      5: 'mode'
                112     CALL                            1
                120     STORE_FAST                      6: _var_var_4
                122     LOAD_FAST                       0: data
                124     LOAD_CONST                      4: 'Settings'
                126     BINARY_SUBSCR                   
                130     LOAD_ATTR                       5: get
                150     PUSH_NULL                       
                152     LOAD_CONST                      1: '__pyarmor_assert_14040__'
                154     LOAD_CONST                      6: 'proxy_type'   # b'\x81\xf2\n\x1c+\xe3\x81\xc6\x02\xea\x08'
                156     CALL                            1
                164     CALL                            1
                172     STORE_FAST                      7: _var_var_5
                174     LOAD_FAST                       6: _var_var_4
                176     LOAD_CONST                      7: 'rotate'
                178     COMPARE_OP                      40 (==)
                182     POP_JUMP_IF_FALSE               377 (to 940)
                186     LOAD_FAST                       0: data
                188     LOAD_CONST                      4: 'Settings'
                190     BINARY_SUBSCR                   
                194     LOAD_ATTR                       5: get
                214     PUSH_NULL                       
                216     LOAD_CONST                      1: '__pyarmor_assert_14040__'
                218     LOAD_CONST                      8: 'proxy_rotate'   # b'\x81\xf2\n\x1c+\xe3\x81\xc0\x14\xee\x0c\xd4i'
                220     CALL                            1
                228     CALL                            1
                236     STORE_FAST                      8: _var_var_6
                238     LOAD_FAST                       8: _var_var_6
                240     LOAD_ATTR                       7: split
                260     LOAD_CONST                      9: ':'
                262     CALL                            1
                270     STORE_FAST                      3: proxy
                272     LOAD_GLOBAL                     9: NULL + len
                282     LOAD_FAST                       3: proxy
                284     CALL                            1
                292     LOAD_CONST                      10: 2
                294     COMPARE_OP                      40 (==)
                298     POP_JUMP_IF_FALSE               129 (to 558)
                300     LOAD_FAST                       7: _var_var_5
                302     LOAD_CONST                      11: 'http'
                304     COMPARE_OP                      40 (==)
                308     POP_JUMP_IF_FALSE               62 (to 434)
                310     PUSH_NULL                       
                312     LOAD_CONST                      1: '__pyarmor_assert_14040__'
                314     LOAD_CONST                      12: 'http://{}:{}/'   # b'\x81\xea\x0c\x07#\xa0\xf1\x9d\x00\xe7W\xdbq\xa3'
                316     CALL                            1
                324     LOAD_ATTR                       11: format
                344     LOAD_FAST                       3: proxy
                346     LOAD_CONST                      13: 0
                348     BINARY_SUBSCR                   
                352     LOAD_FAST                       3: proxy
                354     LOAD_CONST                      14: 1
                356     BINARY_SUBSCR                   
                360     CALL                            2
                368     PUSH_NULL                       
                370     LOAD_CONST                      1: '__pyarmor_assert_14040__'
                372     LOAD_CONST                      12: 'http://{}:{}/'   # b'\x81\xea\x0c\x07#\xa0\xf1\x9d\x00\xe7W\xdbq\xa3'
                374     CALL                            1
                382     LOAD_ATTR                       11: format
                402     LOAD_FAST                       3: proxy
                404     LOAD_CONST                      13: 0
                406     BINARY_SUBSCR                   
                410     LOAD_FAST                       3: proxy
                412     LOAD_CONST                      14: 1
                414     BINARY_SUBSCR                   
                418     CALL                            2
                426     LOAD_CONST                      15: ('http', 'https')
                428     BUILD_CONST_KEY_MAP             2
                430     STORE_FAST                      9: _var_var_7
                432     JUMP_FORWARD                    222 (to 878)
                434     PUSH_NULL                       
                436     LOAD_CONST                      1: '__pyarmor_assert_14040__'
                438     LOAD_CONST                      12: 'http://{}:{}/'   # b'\x81\xea\x0c\x07#\xa0\xf1\x9d\x00\xe7W\xdbq\xa3'
                440     CALL                            1
                448     LOAD_ATTR                       11: format
                468     LOAD_FAST                       3: proxy
                470     LOAD_CONST                      13: 0
                472     BINARY_SUBSCR                   
                476     LOAD_FAST                       3: proxy
                478     LOAD_CONST                      14: 1
                480     BINARY_SUBSCR                   
                484     CALL                            2
                492     PUSH_NULL                       
                494     LOAD_CONST                      1: '__pyarmor_assert_14040__'
                496     LOAD_CONST                      12: 'http://{}:{}/'   # b'\x81\xea\x0c\x07#\xa0\xf1\x9d\x00\xe7W\xdbq\xa3'
                498     CALL                            1
                506     LOAD_ATTR                       11: format
                526     LOAD_FAST                       3: proxy
                528     LOAD_CONST                      13: 0
                530     BINARY_SUBSCR                   
                534     LOAD_FAST                       3: proxy
                536     LOAD_CONST                      14: 1
                538     BINARY_SUBSCR                   
                542     CALL                            2
                550     LOAD_CONST                      16: ('socks5h', 'socks5h')
                552     BUILD_CONST_KEY_MAP             2
                554     STORE_FAST                      9: _var_var_7
                556     JUMP_FORWARD                    160 (to 878)
                558     LOAD_FAST                       7: _var_var_5
                560     LOAD_CONST                      11: 'http'
                562     COMPARE_OP                      40 (==)
                566     POP_JUMP_IF_FALSE               78 (to 724)
                568     PUSH_NULL                       
                570     LOAD_CONST                      1: '__pyarmor_assert_14040__'
                572     LOAD_CONST                      17: 'http://{}:{}@{}:{}/'   # b'\x81\xea\x0c\x07#\xa0\xf1\x9d\x00\xe7W\xdbq\xcc\xe3\x98UF\xa6\xe8'
                574     CALL                            1
                582     LOAD_ATTR                       11: format
                602     LOAD_FAST                       3: proxy
                604     LOAD_CONST                      10: 2
                606     BINARY_SUBSCR                   
                610     LOAD_FAST                       3: proxy
                612     LOAD_CONST                      18: 3
                614     BINARY_SUBSCR                   
                618     LOAD_FAST                       3: proxy
                620     LOAD_CONST                      13: 0
                622     BINARY_SUBSCR                   
                626     LOAD_FAST                       3: proxy
                628     LOAD_CONST                      14: 1
                630     BINARY_SUBSCR                   
                634     CALL                            4
                642     PUSH_NULL                       
                644     LOAD_CONST                      1: '__pyarmor_assert_14040__'
                646     LOAD_CONST                      17: 'http://{}:{}@{}:{}/'   # b'\x81\xea\x0c\x07#\xa0\xf1\x9d\x00\xe7W\xdbq\xcc\xe3\x98UF\xa6\xe8'
                648     CALL                            1
                656     LOAD_ATTR                       11: format
                676     LOAD_FAST                       3: proxy
                678     LOAD_CONST                      10: 2
                680     BINARY_SUBSCR                   
                684     LOAD_FAST                       3: proxy
                686     LOAD_CONST                      18: 3
                688     BINARY_SUBSCR                   
                692     LOAD_FAST                       3: proxy
                694     LOAD_CONST                      13: 0
                696     BINARY_SUBSCR                   
                700     LOAD_FAST                       3: proxy
                702     LOAD_CONST                      14: 1
                704     BINARY_SUBSCR                   
                708     CALL                            4
                716     LOAD_CONST                      15: ('http', 'https')
                718     BUILD_CONST_KEY_MAP             2
                720     STORE_FAST                      9: _var_var_7
                722     JUMP_FORWARD                    77 (to 878)
                724     PUSH_NULL                       
                726     LOAD_CONST                      1: '__pyarmor_assert_14040__'
                728     LOAD_CONST                      17: 'http://{}:{}@{}:{}/'   # b'\x81\xea\x0c\x07#\xa0\xf1\x9d\x00\xe7W\xdbq\xcc\xe3\x98UF\xa6\xe8'
                730     CALL                            1
                738     LOAD_ATTR                       11: format
                758     LOAD_FAST                       3: proxy
                760     LOAD_CONST                      10: 2
                762     BINARY_SUBSCR                   
                766     LOAD_FAST                       3: proxy
                768     LOAD_CONST                      18: 3
                770     BINARY_SUBSCR                   
                774     LOAD_FAST                       3: proxy
                776     LOAD_CONST                      13: 0
                778     BINARY_SUBSCR                   
                782     LOAD_FAST                       3: proxy
                784     LOAD_CONST                      14: 1
                786     BINARY_SUBSCR                   
                790     CALL                            4
                798     PUSH_NULL                       
                800     LOAD_CONST                      1: '__pyarmor_assert_14040__'
                802     LOAD_CONST                      17: 'http://{}:{}@{}:{}/'   # b'\x81\xea\x0c\x07#\xa0\xf1\x9d\x00\xe7W\xdbq\xcc\xe3\x98UF\xa6\xe8'
                804     CALL                            1
                812     LOAD_ATTR                       11: format
                832     LOAD_FAST                       3: proxy
                834     LOAD_CONST                      10: 2
                836     BINARY_SUBSCR                   
                840     LOAD_FAST                       3: proxy
                842     LOAD_CONST                      18: 3
                844     BINARY_SUBSCR                   
                848     LOAD_FAST                       3: proxy
                850     LOAD_CONST                      13: 0
                852     BINARY_SUBSCR                   
                856     LOAD_FAST                       3: proxy
                858     LOAD_CONST                      14: 1
                860     BINARY_SUBSCR                   
                864     CALL                            4
                872     LOAD_CONST                      16: ('socks5h', 'socks5h')
                874     BUILD_CONST_KEY_MAP             2
                876     STORE_FAST                      9: _var_var_7
                878     LOAD_GLOBAL                     13: NULL + int
                888     LOAD_FAST                       0: data
                890     LOAD_CONST                      4: 'Settings'
                892     BINARY_SUBSCR                   
                896     LOAD_ATTR                       5: get
                916     LOAD_CONST                      19: 'requests'
                918     CALL                            1
                926     CALL                            1
                934     STORE_FAST                      10: _var_var_8
                936     JUMP_FORWARD                    374 (to 1688)
                940     BUILD_LIST                      0
                942     STORE_FAST                      11: _var_var_9
                944     LOAD_FAST                       0: data
                946     LOAD_CONST                      4: 'Settings'
                948     BINARY_SUBSCR                   
                952     LOAD_ATTR                       5: get
                972     PUSH_NULL                       
                974     LOAD_CONST                      1: '__pyarmor_assert_14040__'
                976     LOAD_CONST                      20: 'usernames'   # b'\x81\xf7\x0b\x16!\xf4\xbf\xdf\x1e\xe9'
                978     CALL                            1
                986     CALL                            1
                994     STORE_FAST                      12: _var_var_10
                996     LOAD_FAST                       12: _var_var_10
                998     GET_ITER                        
                1000    FOR_ITER                        340 (to 1684)
                1006    STORE_FAST                      3: proxy
                1008    LOAD_FAST                       3: proxy
                1010    LOAD_ATTR                       7: split
                1030    LOAD_CONST                      9: ':'
                1032    CALL                            1
                1040    STORE_FAST                      3: proxy
                1042    LOAD_GLOBAL                     9: NULL + len
                1052    LOAD_FAST                       3: proxy
                1054    CALL                            1
                1062    LOAD_CONST                      10: 2
                1064    COMPARE_OP                      40 (==)
                1068    POP_JUMP_IF_FALSE               129 (to 1328)
                1070    LOAD_FAST                       7: _var_var_5
                1072    LOAD_CONST                      11: 'http'
                1074    COMPARE_OP                      40 (==)
                1078    POP_JUMP_IF_FALSE               62 (to 1204)
                1080    PUSH_NULL                       
                1082    LOAD_CONST                      1: '__pyarmor_assert_14040__'
                1084    LOAD_CONST                      12: 'http://{}:{}/'   # b'\x81\xea\x0c\x07#\xa0\xf1\x9d\x00\xe7W\xdbq\xa3'
                1086    CALL                            1
                1094    LOAD_ATTR                       11: format
                1114    LOAD_FAST                       3: proxy
                1116    LOAD_CONST                      13: 0
                1118    BINARY_SUBSCR                   
                1122    LOAD_FAST                       3: proxy
                1124    LOAD_CONST                      14: 1
                1126    BINARY_SUBSCR                   
                1130    CALL                            2
                1138    PUSH_NULL                       
                1140    LOAD_CONST                      1: '__pyarmor_assert_14040__'
                1142    LOAD_CONST                      12: 'http://{}:{}/'   # b'\x81\xea\x0c\x07#\xa0\xf1\x9d\x00\xe7W\xdbq\xa3'
                1144    CALL                            1
                1152    LOAD_ATTR                       11: format
                1172    LOAD_FAST                       3: proxy
                1174    LOAD_CONST                      13: 0
                1176    BINARY_SUBSCR                   
                1180    LOAD_FAST                       3: proxy
                1182    LOAD_CONST                      14: 1
                1184    BINARY_SUBSCR                   
                1188    CALL                            2
                1196    LOAD_CONST                      15: ('http', 'https')
                1198    BUILD_CONST_KEY_MAP             2
                1200    STORE_FAST                      9: _var_var_7
                1202    JUMP_FORWARD                    222 (to 1648)
                1204    PUSH_NULL                       
                1206    LOAD_CONST                      1: '__pyarmor_assert_14040__'
                1208    LOAD_CONST                      12: 'http://{}:{}/'   # b'\x81\xea\x0c\x07#\xa0\xf1\x9d\x00\xe7W\xdbq\xa3'
                1210    CALL                            1
                1218    LOAD_ATTR                       11: format
                1238    LOAD_FAST                       3: proxy
                1240    LOAD_CONST                      13: 0
                1242    BINARY_SUBSCR                   
                1246    LOAD_FAST                       3: proxy
                1248    LOAD_CONST                      14: 1
                1250    BINARY_SUBSCR                   
                1254    CALL                            2
                1262    PUSH_NULL                       
                1264    LOAD_CONST                      1: '__pyarmor_assert_14040__'
                1266    LOAD_CONST                      12: 'http://{}:{}/'   # b'\x81\xea\x0c\x07#\xa0\xf1\x9d\x00\xe7W\xdbq\xa3'
                1268    CALL                            1
                1276    LOAD_ATTR                       11: format
                1296    LOAD_FAST                       3: proxy
                1298    LOAD_CONST                      13: 0
                1300    BINARY_SUBSCR                   
                1304    LOAD_FAST                       3: proxy
                1306    LOAD_CONST                      14: 1
                1308    BINARY_SUBSCR                   
                1312    CALL                            2
                1320    LOAD_CONST                      16: ('socks5h', 'socks5h')
                1322    BUILD_CONST_KEY_MAP             2
                1324    STORE_FAST                      9: _var_var_7
                1326    JUMP_FORWARD                    160 (to 1648)
                1328    LOAD_FAST                       7: _var_var_5
                1330    LOAD_CONST                      11: 'http'
                1332    COMPARE_OP                      40 (==)
                1336    POP_JUMP_IF_FALSE               78 (to 1494)
                1338    PUSH_NULL                       
                1340    LOAD_CONST                      1: '__pyarmor_assert_14040__'
                1342    LOAD_CONST                      17: 'http://{}:{}@{}:{}/'   # b'\x81\xea\x0c\x07#\xa0\xf1\x9d\x00\xe7W\xdbq\xcc\xe3\x98UF\xa6\xe8'
                1344    CALL                            1
                1352    LOAD_ATTR                       11: format
                1372    LOAD_FAST                       3: proxy
                1374    LOAD_CONST                      10: 2
                1376    BINARY_SUBSCR                   
                1380    LOAD_FAST                       3: proxy
                1382    LOAD_CONST                      18: 3
                1384    BINARY_SUBSCR                   
                1388    LOAD_FAST                       3: proxy
                1390    LOAD_CONST                      13: 0
                1392    BINARY_SUBSCR                   
                1396    LOAD_FAST                       3: proxy
                1398    LOAD_CONST                      14: 1
                1400    BINARY_SUBSCR                   
                1404    CALL                            4
                1412    PUSH_NULL                       
                1414    LOAD_CONST                      1: '__pyarmor_assert_14040__'
                1416    LOAD_CONST                      17: 'http://{}:{}@{}:{}/'   # b'\x81\xea\x0c\x07#\xa0\xf1\x9d\x00\xe7W\xdbq\xcc\xe3\x98UF\xa6\xe8'
                1418    CALL                            1
                1426    LOAD_ATTR                       11: format
                1446    LOAD_FAST                       3: proxy
                1448    LOAD_CONST                      10: 2
                1450    BINARY_SUBSCR                   
                1454    LOAD_FAST                       3: proxy
                1456    LOAD_CONST                      18: 3
                1458    BINARY_SUBSCR                   
                1462    LOAD_FAST                       3: proxy
                1464    LOAD_CONST                      13: 0
                1466    BINARY_SUBSCR                   
                1470    LOAD_FAST                       3: proxy
                1472    LOAD_CONST                      14: 1
                1474    BINARY_SUBSCR                   
                1478    CALL                            4
                1486    LOAD_CONST                      15: ('http', 'https')
                1488    BUILD_CONST_KEY_MAP             2
                1490    STORE_FAST                      9: _var_var_7
                1492    JUMP_FORWARD                    77 (to 1648)
                1494    PUSH_NULL                       
                1496    LOAD_CONST                      1: '__pyarmor_assert_14040__'
                1498    LOAD_CONST                      17: 'http://{}:{}@{}:{}/'   # b'\x81\xea\x0c\x07#\xa0\xf1\x9d\x00\xe7W\xdbq\xcc\xe3\x98UF\xa6\xe8'
                1500    CALL                            1
                1508    LOAD_ATTR                       11: format
                1528    LOAD_FAST                       3: proxy
                1530    LOAD_CONST                      10: 2
                1532    BINARY_SUBSCR                   
                1536    LOAD_FAST                       3: proxy
                1538    LOAD_CONST                      18: 3
                1540    BINARY_SUBSCR                   
                1544    LOAD_FAST                       3: proxy
                1546    LOAD_CONST                      13: 0
                1548    BINARY_SUBSCR                   
                1552    LOAD_FAST                       3: proxy
                1554    LOAD_CONST                      14: 1
                1556    BINARY_SUBSCR                   
                1560    CALL                            4
                1568    PUSH_NULL                       
                1570    LOAD_CONST                      1: '__pyarmor_assert_14040__'
                1572    LOAD_CONST                      17: 'http://{}:{}@{}:{}/'   # b'\x81\xea\x0c\x07#\xa0\xf1\x9d\x00\xe7W\xdbq\xcc\xe3\x98UF\xa6\xe8'
                1574    CALL                            1
                1582    LOAD_ATTR                       11: format
                1602    LOAD_FAST                       3: proxy
                1604    LOAD_CONST                      10: 2
                1606    BINARY_SUBSCR                   
                1610    LOAD_FAST                       3: proxy
                1612    LOAD_CONST                      18: 3
                1614    BINARY_SUBSCR                   
                1618    LOAD_FAST                       3: proxy
                1620    LOAD_CONST                      13: 0
                1622    BINARY_SUBSCR                   
                1626    LOAD_FAST                       3: proxy
                1628    LOAD_CONST                      14: 1
                1630    BINARY_SUBSCR                   
                1634    CALL                            4
                1642    LOAD_CONST                      16: ('socks5h', 'socks5h')
                1644    BUILD_CONST_KEY_MAP             2
                1646    STORE_FAST                      9: _var_var_7
                1648    LOAD_FAST                       11: _var_var_9
                1650    LOAD_ATTR                       15: append
                1670    LOAD_FAST                       9: _var_var_7
                1672    CALL                            1
                1680    POP_TOP                         
                1682    JUMP_BACKWARD                   343 (to 1000)
                1686    END_FOR                         
                1688    LOAD_GLOBAL                     17: NULL + Logs
                1698    LOAD_ATTR                       18: PrintLog
                1718    LOAD_FAST                       1: config
                1720    LOAD_GLOBAL                     20: Lang
                1730    PUSH_NULL                       
                1732    LOAD_CONST                      1: '__pyarmor_assert_14040__'
                1734    LOAD_CONST                      21: 'program_running'   # b'\x81\xf2\n\x1c4\xe8\xbf\xdf$\xe8\x18\xceb\xe5\xf6\x82'
                1736    CALL                            1
                1744    BINARY_SUBSCR                   
                1748    KW_NAMES                        22: ('config', 'message')
                1750    CALL                            2
                1758    POP_TOP                         
                1760    LOAD_GLOBAL                     22: concurrent
                1770    LOAD_ATTR                       24: futures
                1790    LOAD_ATTR                       27: ThreadPoolExecutor
                1810    LOAD_CONST                      23: 50
                1812    KW_NAMES                        24: ('max_workers',)
                1814    CALL                            1
                1822    BEFORE_WITH                     
                1824    STORE_FAST                      13: _var_var_11
                1826    BUILD_LIST                      0
                1828    STORE_FAST                      14: _var_var_12
                1830    LOAD_FAST                       6: _var_var_4
                1832    LOAD_CONST                      7: 'rotate'
                1834    COMPARE_OP                      40 (==)
                1838    POP_JUMP_IF_FALSE               55 (to 1950)
                1840    LOAD_GLOBAL                     29: NULL + range
                1850    LOAD_FAST_CHECK                 10: _var_var_8
                1852    CALL                            1
                1860    GET_ITER                        
                1862    FOR_ITER                        40 (to 1944)
                1866    STORE_FAST                      15: _var_var_13
                1868    LOAD_FAST                       14: _var_var_12
                1870    LOAD_ATTR                       15: append
                1890    LOAD_FAST                       13: _var_var_11
                1892    LOAD_ATTR                       31: submit
                1912    LOAD_GLOBAL                     32: worker
                1922    LOAD_FAST_CHECK                 9: _var_var_7
                1924    LOAD_FAST                       4: stop_thread
                1926    CALL                            3
                1934    CALL                            1
                1942    POP_TOP                         
                1944    JUMP_BACKWARD                   42 (to 1862)
                1946    END_FOR                         
                1948    JUMP_FORWARD                    45 (to 2040)
                1950    LOAD_FAST_CHECK                 11: _var_var_9
                1952    GET_ITER                        
                1954    FOR_ITER                        40 (to 2036)
                1958    STORE_FAST                      9: _var_var_7
                1960    LOAD_FAST                       14: _var_var_12
                1962    LOAD_ATTR                       15: append
                1982    LOAD_FAST                       13: _var_var_11
                1984    LOAD_ATTR                       31: submit
                2004    LOAD_GLOBAL                     32: worker
                2014    LOAD_FAST                       9: _var_var_7
                2016    LOAD_FAST                       4: stop_thread
                2018    CALL                            3
                2026    CALL                            1
                2034    POP_TOP                         
                2036    JUMP_BACKWARD                   42 (to 1954)
                2038    END_FOR                         
                2040    BUILD_LIST                      0
                2042    STORE_FAST                      16: _var_var_14
                2044    LOAD_CONST                      13: 0
                2046    STORE_FAST                      17: _var_var_15
                2048    LOAD_CONST                      13: 0
                2050    STORE_FAST                      18: _var_var_16
                2052    LOAD_GLOBAL                     22: concurrent
                2062    LOAD_ATTR                       24: futures
                2082    LOAD_ATTR                       35: as_completed
                2102    LOAD_FAST                       14: _var_var_12
                2104    CALL                            1
                2112    GET_ITER                        
                2114    FOR_ITER                        128 (to 2372)
                2118    STORE_FAST                      19: _var_var_17
                2120    LOAD_FAST                       19: _var_var_17
                2122    LOAD_ATTR                       37: result
                2142    CALL                            0
                2150    STORE_FAST                      20: _var_var_18
                2152    LOAD_FAST                       20: _var_var_18
                2154    LOAD_CONST                      25: 'status'
                2156    BINARY_SUBSCR                   
                2160    LOAD_CONST                      26: 'ok'
                2162    COMPARE_OP                      40 (==)
                2166    POP_JUMP_IF_FALSE               34 (to 2236)
                2168    LOAD_FAST                       20: _var_var_18
                2170    LOAD_CONST                      27: 'ip'
                2172    BINARY_SUBSCR                   
                2176    LOAD_FAST                       16: _var_var_14
                2178    CONTAINS_OP                     0 (in)
                2180    POP_JUMP_IF_FALSE               6 (to 2194)
                2182    LOAD_FAST                       17: _var_var_15
                2184    LOAD_CONST                      14: 1
                2186    BINARY_OP                       13 (+=)
                2190    STORE_FAST                      17: _var_var_15
                2192    JUMP_FORWARD                    26 (to 2246)
                2194    LOAD_FAST                       16: _var_var_14
                2196    LOAD_ATTR                       15: append
                2216    LOAD_FAST                       20: _var_var_18
                2218    LOAD_CONST                      27: 'ip'
                2220    BINARY_SUBSCR                   
                2224    CALL                            1
                2232    POP_TOP                         
                2234    JUMP_FORWARD                    5 (to 2246)
                2236    LOAD_FAST                       18: _var_var_16
                2238    LOAD_CONST                      14: 1
                2240    BINARY_OP                       13 (+=)
                2244    STORE_FAST                      18: _var_var_16
                2246    PUSH_NULL                       
                2248    LOAD_GLOBAL                     39: NULL + eel
                2258    LOAD_ATTR                       40: LoadProxyResult
                2278    LOAD_GLOBAL                     9: NULL + len
                2288    LOAD_FAST                       16: _var_var_14
                2290    CALL                            1
                2298    LOAD_FAST                       17: _var_var_15
                2300    LOAD_FAST                       18: _var_var_16
                2302    CALL                            3
                2310    CALL                            0
                2318    POP_TOP                         
                2320    LOAD_FAST                       4: stop_thread
                2322    LOAD_ATTR                       1: is_set
                2342    CALL                            0
                2350    POP_JUMP_IF_TRUE                1 (to 2354)
                2352    JUMP_BACKWARD                   120 (to 2114)
                2354    LOAD_GLOBAL                     3: NULL + StopProgram
                2364    CALL                            0
                2372    RAISE_VARARGS                   1
                2374    END_FOR                         
                2376    NOP                             
                2378    LOAD_CONST                      0: None
                2380    LOAD_CONST                      0: None
                2382    LOAD_CONST                      0: None
                2384    CALL                            2
                2392    POP_TOP                         
                2394    LOAD_GLOBAL                     17: NULL + Logs
                2404    LOAD_ATTR                       18: PrintLog
                2424    LOAD_FAST                       1: config
                2426    LOAD_GLOBAL                     20: Lang
                2436    LOAD_CONST                      28: 'job_done'
                2438    BINARY_SUBSCR                   
                2442    KW_NAMES                        22: ('config', 'message')
                2444    CALL                            2
                2452    POP_TOP                         
                2454    LOAD_GLOBAL                     47: NULL + del_task_manager
                2464    LOAD_FAST                       2: pid
                2466    CALL                            1
                2474    POP_TOP                         
                2476    LOAD_GLOBAL                     49: NULL + StopDetect
                2486    LOAD_FAST                       4: stop_thread
                2488    CALL                            1
                2496    POP_TOP                         
                2498    NOP                             
                2500    LOAD_CONST                      30: 'Done'
                2502    NOP                             
                2504    NOP                             
                2506    NOP                             
                2508    JUMP_FORWARD                    117 (to 2744)
                2516    POP_TOP                         
                2518    RETURN_CONST                    30: 'Done'
                2520    PUSH_EXC_INFO                   
                2522    WITH_EXCEPT_START               
                2524    POP_JUMP_IF_TRUE                1 (to 2528)
                2526    RERAISE                         2
                2528    POP_TOP                         
                2530    POP_EXCEPT                      
                2532    POP_TOP                         
                2534    POP_TOP                         
                2536    JUMP_BACKWARD                   72 (to 2394)
                2538    COPY                            3
                2540    POP_EXCEPT                      
                2542    RERAISE                         1
                2544    PUSH_EXC_INFO                   
                2546    LOAD_GLOBAL                     2: StopProgram
                2556    CHECK_EXC_MATCH                 
                2558    POP_JUMP_IF_FALSE               3 (to 2566)
                2560    POP_TOP                         
                2562    POP_EXCEPT                      
                2564    JUMP_BACKWARD                   56 (to 2454)
                2566    LOAD_GLOBAL                     42: BaseException
                2576    CHECK_EXC_MATCH                 
                2578    POP_JUMP_IF_FALSE               26 (to 2632)
                2580    STORE_FAST                      21: _var_var_3
                2582    PUSH_NULL                       
                2584    LOAD_GLOBAL                     45: NULL + logging
                2594    LOAD_FAST                       21: _var_var_3
                2596    CALL                            1
                2604    CALL                            0
                2612    POP_TOP                         
                2614    POP_EXCEPT                      
                2616    LOAD_CONST                      0: None
                2618    STORE_FAST                      21: _var_var_3
                2620    DELETE_FAST                     21: _var_var_3
                2622    JUMP_BACKWARD                   85 (to 2454)
                2624    LOAD_CONST                      0: None
                2626    STORE_FAST                      21: _var_var_3
                2628    DELETE_FAST                     21: _var_var_3
                2630    RERAISE                         1
                2632    RERAISE                         0
                2634    COPY                            3
                2636    POP_EXCEPT                      
                2638    RERAISE                         1
                2640    PUSH_EXC_INFO                   
                2642    LOAD_GLOBAL                     47: NULL + del_task_manager
                2652    LOAD_FAST                       2: pid
                2654    CALL                            1
                2662    POP_TOP                         
                2664    LOAD_GLOBAL                     49: NULL + StopDetect
                2674    LOAD_FAST                       4: stop_thread
                2676    CALL                            1
                2684    POP_TOP                         
                2686    POP_TOP                         
                2688    POP_EXCEPT                      
                2690    LOAD_CONST                      30: 'Done'
                2692    NOP                             
                2694    NOP                             
                2696    NOP                             
                2698    JUMP_FORWARD                    22 (to 2744)
                2706    POP_TOP                         
                2708    RETURN_CONST                    30: 'Done'
                2710    COPY                            3
                2712    POP_EXCEPT                      
                2714    RERAISE                         1
                2716    PUSH_EXC_INFO                   
                2718    PUSH_NULL                       
                2720    LOAD_CONST                      29: '__pyarmor_exit_14042__'
                2722    NOP                             
                2724    LOAD_CONST                      3: b'<COAddr>\x07\x00\x00\x1a\x82\n\x00\x00\x00\x00\x00\x00\x00\x00\x00\x00\x00\x00\x00\x00'
                2726    CALL                            1
                2734    POP_TOP                         
                2736    RERAISE                         0
                2738    COPY                            3
                2740    POP_EXCEPT                      
                2742    RERAISE                         1
                2744    PUSH_NULL                       
                2746    LOAD_CONST                      29: '__pyarmor_exit_14042__'
                2748    LOAD_CONST                      3: b'<COAddr>\x07\x00\x00\x1a\x82\n\x00\x00\x00\x00\x00\x00\x00\x00\x00\x00\x00\x00\x00\x00'
                2750    BUILD_TUPLE                     1
                2752    CALL_FUNCTION_EX                0
                2754    POP_TOP                         
                2756    RETURN_VALUE                    
            [Exception Table]
                30 to 1824 -> 2544 [0] 
                1824 to 2352 -> 2520 [1] lasti
                2354 to 2376 -> 2520 [1] lasti
                2378 to 2454 -> 2544 [0] 
                2454 to 2498 -> 2716 [0] 
                2520 to 2530 -> 2538 [3] lasti
                2530 to 2544 -> 2544 [0] 
                2544 to 2562 -> 2634 [1] lasti
                2562 to 2566 -> 2640 [0] 
                2566 to 2582 -> 2634 [1] lasti
                2582 to 2614 -> 2624 [1] lasti
                2614 to 2624 -> 2640 [0] 
                2624 to 2634 -> 2634 [1] lasti
                2634 to 2640 -> 2640 [0] 
                2640 to 2688 -> 2710 [1] lasti
                2688 to 2690 -> 2716 [0] 
                2710 to 2716 -> 2716 [0] 
                2716 to 2738 -> 2738 [1] lasti
        [Code]
            File Name: <frozen program.modules.Proxy_checker>
            Object Name: worker
            Qualified Name: worker
            Arg Count: 2
            Pos Only Arg Count: 0
            KW Only Arg Count: 0
            Stack Size: 6
            Flags: 0x20000003 (CO_OPTIMIZED | CO_NEWLOCALS | CO_PYARMOR_OBFUSCATED)
            [Names]
                'is_set'
                'StopProgram'
                'requests'
                'get'
                'status_code'
                'text'
                'strip'
                'BaseException'
            [Locals+Names]
                'proxi'
                'stop_thread'
                '__assert_armored__'
                '_var_var_19'
                '_var_var_20'
            [Constants]
                None
                '__pyarmor_assert_14043__'
                '__pyarmor_enter_14044__'
                b'<COAddr>\x07\x00\x00\x1a4\x01\x00\x00\x00\x00\x00\x00\x00\x00\x00\x00\x00\x00\x00\x00'
                'http://api.ipify.org'   # b'\x81\xea\x0c\x07#\xa0\xf1\x9d\x1a\xea\x04\x8ee\xfc\xf1\x83\x16\x13\xb4\xb5\xad'
                25
                False
                (
                    'proxies'
                    'timeout'
                    'verify'
                )
                200
                'ok'
                (
                    'status'
                    'ip'
                )
                '__pyarmor_exit_14045__'
                'error'
            [Disassembly]
                0       NOP                             
                2       NOP                             
                4       PUSH_NULL                       
                6       LOAD_CONST                      2: '__pyarmor_enter_14044__'
                8       LOAD_CONST                      3: b'<COAddr>\x07\x00\x00\x1a4\x01\x00\x00\x00\x00\x00\x00\x00\x00\x00\x00\x00\x00\x00\x00'
                10      BUILD_TUPLE                     1
                12      CALL_FUNCTION_EX                0
                14      POP_TOP                         
                16      RESUME                          0
                18      NOP                             
                20      NOP                             
                22      NOP                             
                24      NOP                             
                26      NOP                             
                28      NOP                             
                30      LOAD_FAST                       1: stop_thread
                32      LOAD_ATTR                       1: is_set
                52      CALL                            0
                60      POP_JUMP_IF_FALSE               10 (to 82)
                62      LOAD_GLOBAL                     3: NULL + StopProgram
                72      CALL                            0
                80      RAISE_VARARGS                   1
                82      LOAD_GLOBAL                     5: NULL + requests
                92      LOAD_ATTR                       6: get
                112     PUSH_NULL                       
                114     LOAD_CONST                      1: '__pyarmor_assert_14043__'
                116     LOAD_CONST                      4: 'http://api.ipify.org'   # b'\x81\xea\x0c\x07#\xa0\xf1\x9d\x1a\xea\x04\x8ee\xfc\xf1\x83\x16\x13\xb4\xb5\xad'
                118     CALL                            1
                126     LOAD_FAST                       0: proxi
                128     LOAD_CONST                      5: 25
                130     LOAD_CONST                      6: False
                132     KW_NAMES                        7: ('proxies', 'timeout', 'verify')
                134     CALL                            4
                142     STORE_FAST                      3: _var_var_19
                144     LOAD_FAST                       3: _var_var_19
                146     LOAD_ATTR                       8: status_code
                166     LOAD_CONST                      8: 200
                168     COMPARE_OP                      40 (==)
                172     POP_JUMP_IF_FALSE               40 (to 254)
                174     LOAD_FAST                       3: _var_var_19
                176     LOAD_ATTR                       10: text
                196     LOAD_ATTR                       13: strip
                216     CALL                            0
                224     STORE_FAST                      4: _var_var_20
                226     LOAD_CONST                      9: 'ok'
                228     LOAD_FAST                       4: _var_var_20
                230     LOAD_CONST                      10: ('status', 'ip')
                232     BUILD_CONST_KEY_MAP             2
                234     NOP                             
                236     NOP                             
                238     NOP                             
                240     JUMP_FORWARD                    60 (to 362)
                242     CALL                            1
                250     POP_TOP                         
                252     RETURN_VALUE                    
                254     NOP                             
                256     LOAD_CONST                      12: 'error'
                258     LOAD_CONST                      0: None
                260     LOAD_CONST                      10: ('status', 'ip')
                262     BUILD_CONST_KEY_MAP             2
                264     NOP                             
                266     NOP                             
                268     NOP                             
                270     JUMP_FORWARD                    45 (to 362)
                272     CALL                            1
                280     POP_TOP                         
                282     RETURN_VALUE                    
                284     PUSH_EXC_INFO                   
                286     LOAD_GLOBAL                     2: StopProgram
                296     CHECK_EXC_MATCH                 
                298     POP_JUMP_IF_FALSE               3 (to 306)
                300     POP_TOP                         
                302     POP_EXCEPT                      
                304     JUMP_BACKWARD                   25 (to 256)
                306     LOAD_GLOBAL                     14: BaseException
                316     CHECK_EXC_MATCH                 
                318     POP_JUMP_IF_FALSE               3 (to 326)
                320     POP_TOP                         
                322     POP_EXCEPT                      
                324     JUMP_BACKWARD                   35 (to 256)
                326     RERAISE                         0
                328     COPY                            3
                330     POP_EXCEPT                      
                332     RERAISE                         1
                334     PUSH_EXC_INFO                   
                336     PUSH_NULL                       
                338     LOAD_CONST                      11: '__pyarmor_exit_14045__'
                340     NOP                             
                342     LOAD_CONST                      3: b'<COAddr>\x07\x00\x00\x1a4\x01\x00\x00\x00\x00\x00\x00\x00\x00\x00\x00\x00\x00\x00\x00'
                344     CALL                            1
                352     POP_TOP                         
                354     RERAISE                         0
                356     COPY                            3
                358     POP_EXCEPT                      
                360     RERAISE                         1
                362     PUSH_NULL                       
                364     LOAD_CONST                      11: '__pyarmor_exit_14045__'
                366     LOAD_CONST                      3: b'<COAddr>\x07\x00\x00\x1a4\x01\x00\x00\x00\x00\x00\x00\x00\x00\x00\x00\x00\x00\x00\x00'
                368     BUILD_TUPLE                     1
                370     CALL_FUNCTION_EX                0
                372     POP_TOP                         
                374     RETURN_VALUE                    
            [Exception Table]
                30 to 234 -> 284 [0] 
                254 to 264 -> 334 [0] 
                284 to 302 -> 328 [1] lasti
                302 to 306 -> 334 [0] 
                306 to 322 -> 328 [1] lasti
                322 to 326 -> 334 [0] 
                326 to 328 -> 328 [1] lasti
                328 to 334 -> 334 [0] 
                334 to 356 -> 356 [1] lasti
        '__pyarmor_exit_14036__'
    [Disassembly]
        0       NOP                             
        2       NOP                             
        4       PUSH_NULL                       
        6       LOAD_CONST                      1: '__pyarmor_enter_14035__'
        8       LOAD_CONST                      2: b'<COAddr>\x07\x00\x00\x1a\xc6\x00\x00\x00\x00\x00\x00\x00\x00\x00\x00\x00\x00\x00\x00\x00'
        10      BUILD_TUPLE                     1
        12      CALL_FUNCTION_EX                0
        14      POP_TOP                         
        16      RESUME                          0
        18      NOP                             
        20      NOP                             
        22      NOP                             
        24      NOP                             
        26      LOAD_CONST                      3: 0
        28      LOAD_CONST                      4: None
        30      IMPORT_NAME                     1: eel
        32      STORE_NAME                      1: eel
        34      LOAD_CONST                      3: 0
        36      LOAD_CONST                      4: None
        38      IMPORT_NAME                     2: requests
        40      STORE_NAME                      2: requests
        42      LOAD_CONST                      3: 0
        44      LOAD_CONST                      4: None
        46      IMPORT_NAME                     3: concurrent.futures
        48      STORE_NAME                      4: concurrent
        50      LOAD_CONST                      3: 0
        52      LOAD_CONST                      5: ('Thread', 'Event')
        54      IMPORT_NAME                     5: threading
        56      IMPORT_FROM                     6: Thread
        58      STORE_NAME                      6: Thread
        60      IMPORT_FROM                     7: Event
        62      STORE_NAME                      7: Event
        64      POP_TOP                         
        66      LOAD_CONST                      3: 0
        68      LOAD_CONST                      6: ('StopProgram',)
        70      IMPORT_NAME                     8: multithon.errors
        72      IMPORT_FROM                     9: StopProgram
        74      STORE_NAME                      9: StopProgram
        76      POP_TOP                         
        78      LOAD_CONST                      3: 0
        80      LOAD_CONST                      7: ('GetLang',)
        82      IMPORT_NAME                     10: program.static_classes
        84      IMPORT_FROM                     11: GetLang
        86      STORE_NAME                      11: GetLang
        88      POP_TOP                         
        90      LOAD_CONST                      3: 0
        92      LOAD_CONST                      8: ('Logs',)
        94      IMPORT_NAME                     10: program.static_classes
        96      IMPORT_FROM                     12: Logs
        98      STORE_NAME                      12: Logs
        100     POP_TOP                         
        102     LOAD_CONST                      3: 0
        104     LOAD_CONST                      9: ('logging',)
        106     IMPORT_NAME                     10: program.static_classes
        108     IMPORT_FROM                     13: logging
        110     STORE_NAME                      13: logging
        112     POP_TOP                         
        114     LOAD_CONST                      3: 0
        116     LOAD_CONST                      10: ('memory_check_switcher',)
        118     IMPORT_NAME                     10: program.static_classes
        120     IMPORT_FROM                     14: memory_check_switcher
        122     STORE_NAME                      14: memory_check_switcher
        124     POP_TOP                         
        126     LOAD_CONST                      3: 0
        128     LOAD_CONST                      11: ('memory_set_pid',)
        130     IMPORT_NAME                     10: program.static_classes
        132     IMPORT_FROM                     15: memory_set_pid
        134     STORE_NAME                      15: memory_set_pid
        136     POP_TOP                         
        138     LOAD_CONST                      3: 0
        140     LOAD_CONST                      12: ('GetConfig',)
        142     IMPORT_NAME                     16: program.general
        144     IMPORT_FROM                     17: GetConfig
        146     STORE_NAME                      17: GetConfig
        148     POP_TOP                         
        150     LOAD_CONST                      3: 0
        152     LOAD_CONST                      13: ('GetProxy',)
        154     IMPORT_NAME                     16: program.general
        156     IMPORT_FROM                     18: GetProxy
        158     STORE_NAME                      18: GetProxy
        160     POP_TOP                         
        162     LOAD_CONST                      3: 0
        164     LOAD_CONST                      14: ('StopDetect',)
        166     IMPORT_NAME                     16: program.general
        168     IMPORT_FROM                     19: StopDetect
        170     STORE_NAME                      19: StopDetect
        172     POP_TOP                         
        174     LOAD_CONST                      3: 0
        176     LOAD_CONST                      15: ('del_task_manager',)
        178     IMPORT_NAME                     16: program.general
        180     IMPORT_FROM                     20: del_task_manager
        182     STORE_NAME                      20: del_task_manager
        184     POP_TOP                         
        186     LOAD_CONST                      16: <CODE> Proxy_checker
        188     MAKE_FUNCTION                   0
        190     STORE_NAME                      21: Proxy_checker
        192     LOAD_CONST                      17: <CODE> START
        194     MAKE_FUNCTION                   0
        196     STORE_NAME                      22: START
        198     LOAD_CONST                      18: <CODE> worker
        200     MAKE_FUNCTION                   0
        202     STORE_NAME                      23: worker
        204     LOAD_CONST                      4: None
        206     NOP                             
        208     NOP                             
        210     NOP                             
        212     JUMP_FORWARD                    19 (to 252)
        220     POP_TOP                         
        222     RETURN_CONST                    4: None
        224     PUSH_EXC_INFO                   
        226     PUSH_NULL                       
        228     LOAD_CONST                      19: '__pyarmor_exit_14036__'
        230     NOP                             
        232     LOAD_CONST                      2: b'<COAddr>\x07\x00\x00\x1a\xc6\x00\x00\x00\x00\x00\x00\x00\x00\x00\x00\x00\x00\x00\x00\x00'
        234     CALL                            1
        242     POP_TOP                         
        244     RERAISE                         0
        246     COPY                            3
        248     POP_EXCEPT                      
        250     RERAISE                         1
        252     PUSH_NULL                       
        254     LOAD_CONST                      19: '__pyarmor_exit_14036__'
        256     LOAD_CONST                      2: b'<COAddr>\x07\x00\x00\x1a\xc6\x00\x00\x00\x00\x00\x00\x00\x00\x00\x00\x00\x00\x00\x00\x00'
        258     BUILD_TUPLE                     1
        260     CALL_FUNCTION_EX                0
        262     POP_TOP                         
        264     RETURN_VALUE                    
    [Exception Table]
        26 to 204 -> 224 [0] 
        224 to 246 -> 246 [1] lasti
