#decoded by lolz.live/mrpenny / t.me/zeus_jackpot
# ================================
# Примечания по Pyarmor:
# - Байт-код и объекты кода Pyarmor соответствуют стандартному Python, но присутствуют специальные вызовы функций среды выполнения (runtime) Pyarmor.
# - Вызовы строк — это не ошибки, а маркеры, которые обрабатываются Pyarmor во время выполнения.
#
# Руководство по декомпиляции (без среды выполнения):
# 1. Игнорируйте зашифрованные байты после `#`; используйте только строку до `#`.
# 2. Удалите "__pyarmor_enter_xxx__"(b"<COAddr>...") и "__pyarmor_leave_xxx__"(b"<COAddr>...") (пролог/эпилог).
# 3. "__pyarmor_assert_xxx__"(A) не является настоящим оператором assert.
#    - Если A — это имя или читаемая строка: замените на A.
#    - Если A — это (X, "Y"): замените на X.Y.
#    - Если A — это (X, "Y", Z): замените на X.Y = Z.
#    - В противном случае: выберите наиболее подходящую/логичную замену.
# 4. "__pyarmor_bcc_xxx__"(...) указывает на машинный (нативный) код; тело функции недоступно. Добавьте комментарий.
# ================================

[Code]
    File Name: <frozen program.modules.Reactions>
    Object Name: <module>
    Qualified Name: <module>
    Arg Count: 0
    Pos Only Arg Count: 0
    KW Only Arg Count: 0
    Stack Size: 5
    Flags: 0x20000000 (CO_PYARMOR_OBFUSCATED)
    [Names]
        '__assert_armored__'
        'eel'
        'json'
        'random'
        'concurrent.futures'
        'concurrent'
        'threading'
        'Thread'
        'Event'
        'multithon.sync'
        'functions'
        'types'
        'multithon.errors'
        'StopProgram'
        'program.static_classes'
        'GetLang'
        'Logs'
        'memory_check_switcher'
        'memory_set_pid'
        'program.telegram'
        'DelayOnline'
        'Disconnect'
        'Thread_wait'
        'account_works'
        'tg_group'
        'tg_links'
        'program.general'
        'GetConfig'
        'GetProxy'
        'StopDetect'
        'check_get_settings'
        'del_task_manager'
        'getFile'
        'set_task_manager'
        'program.database'
        'db_reactions'
        'Reactions'
        'START'
        'int'
        'str'
        'get_emoticon'
        'worker'
        'tg_search_group'
    [Locals+Names]
    [Constants]
        '__pyarmor_assert_14046__'
        '__pyarmor_enter_14047__'
        b'<COAddr>\x05\x00\x00\x1an\x01\x00\x00\x00\x00\x00\x00\x00\x00\x00\x00\x00\x00\x00\x00'
        0
        None
        (
            'Thread'
            'Event'
        )
        (
            'functions'
            'types'
        )
        (
            'StopProgram'
        )
        (
            'GetLang'
        )
        (
            'Logs'
        )
        (
            'memory_check_switcher'
        )
        (
            'memory_set_pid'
        )
        (
            'DelayOnline'
        )
        (
            'Disconnect'
        )
        (
            'Thread_wait'
        )
        (
            'account_works'
        )
        (
            'tg_group'
        )
        (
            'tg_links'
        )
        (
            'GetConfig'
        )
        (
            'GetProxy'
        )
        (
            'StopDetect'
        )
        (
            'check_get_settings'
        )
        (
            'del_task_manager'
        )
        (
            'getFile'
        )
        (
            'set_task_manager'
        )
        (
            'db_reactions'
        )
        [Code]
            File Name: <frozen program.modules.Reactions>
            Object Name: Reactions
            Qualified Name: Reactions
            Arg Count: 1
            Pos Only Arg Count: 0
            KW Only Arg Count: 0
            Stack Size: 8
            Flags: 0x20000003 (CO_OPTIMIZED | CO_NEWLOCALS | CO_PYARMOR_OBFUSCATED)
            [Names]
                'get'
                'getFile'
                'GetConfig'
                'config'
                'GetLang'
                'Lang'
                'GetProxy'
                'eel'
                'sendSuccessBox'
                'memory_check_switcher'
                'Event'
                'memory_set_pid'
                'Thread'
                'START'
                'start'
                'Logs'
                'WaitStopAnsfer'
                'UpdateLogInWindow'
                'LangCheck'
                'Exception'
                'print'
                'str'
            [Locals+Names]
                'data'
                '__assert_armored__'
                '_var_var_0'
                '_var_var_1'
                '_var_var_2'
                '_var_var_3'
            [Constants]
                None
                '__pyarmor_assert_14049__'
                '__pyarmor_enter_14050__'
                b'<COAddr>\x05\x00\x00\x1a\xf8\x02\x00\x00\x00\x00\x00\x00\x00\x00\x00\x00\x00\x00\x00\x00'
                'action'
                'getFile'
                '__pyarmor_exit_14051__'
                'program_running'   # b'\x81\xf2\n\x1c4\xe8\xbf\xdf$\xe8\x18\xceb\xe5\xf6\x82'
                False
                (
                    'target'
                    'args'
                )
                True
                (
                    'target'
                    'args'
                    'daemon'
                )
                'Invite: '
            [Disassembly]
                0       NOP                             
                2       NOP                             
                4       PUSH_NULL                       
                6       LOAD_CONST                      2: '__pyarmor_enter_14050__'
                8       LOAD_CONST                      3: b'<COAddr>\x05\x00\x00\x1a\xf8\x02\x00\x00\x00\x00\x00\x00\x00\x00\x00\x00\x00\x00\x00\x00'
                10      BUILD_TUPLE                     1
                12      CALL_FUNCTION_EX                0
                14      POP_TOP                         
                16      RESUME                          0
                18      NOP                             
                20      NOP                             
                22      NOP                             
                24      NOP                             
                26      NOP                             
                28      NOP                             
                30      LOAD_FAST                       0: data
                32      LOAD_ATTR                       1: get
                52      LOAD_CONST                      4: 'action'
                54      CALL                            1
                62      POP_JUMP_IF_NONE                28 (to 120)
                64      LOAD_FAST                       0: data
                66      LOAD_CONST                      4: 'action'
                68      BINARY_SUBSCR                   
                72      LOAD_CONST                      5: 'getFile'
                74      COMPARE_OP                      40 (==)
                78      POP_JUMP_IF_FALSE               20 (to 120)
                80      LOAD_GLOBAL                     3: NULL + getFile
                90      LOAD_FAST                       0: data
                92      CALL                            1
                100     NOP                             
                102     NOP                             
                104     JUMP_FORWARD                    353 (to 814)
                108     CALL                            1
                116     POP_TOP                         
                118     RETURN_VALUE                    
                120     LOAD_GLOBAL                     5: NULL + GetConfig
                130     CALL                            0
                138     STORE_GLOBAL                    3: config
                140     LOAD_GLOBAL                     9: NULL + GetLang
                150     LOAD_GLOBAL                     6: config
                160     CALL                            1
                168     STORE_GLOBAL                    5: Lang
                170     LOAD_GLOBAL                     13: NULL + GetProxy
                180     CALL                            0
                188     STORE_FAST                      2: _var_var_0
                190     LOAD_GLOBAL                     15: NULL + eel
                200     LOAD_ATTR                       16: sendSuccessBox
                220     LOAD_GLOBAL                     10: Lang
                230     PUSH_NULL                       
                232     LOAD_CONST                      1: '__pyarmor_assert_14049__'
                234     LOAD_CONST                      7: 'program_running'   # b'\x81\xf2\n\x1c4\xe8\xbf\xdf$\xe8\x18\xceb\xe5\xf6\x82'
                236     CALL                            1
                244     BINARY_SUBSCR                   
                248     CALL                            1
                256     POP_TOP                         
                258     LOAD_GLOBAL                     19: NULL + memory_check_switcher
                268     CALL                            0
                276     POP_JUMP_IF_TRUE                11 (to 300)
                278     NOP                             
                280     LOAD_CONST                      8: False
                282     NOP                             
                284     NOP                             
                286     JUMP_FORWARD                    262 (to 814)
                296     POP_TOP                         
                298     RETURN_CONST                    8: False
                300     LOAD_GLOBAL                     21: NULL + Event
                310     CALL                            0
                318     STORE_FAST                      3: _var_var_1
                320     LOAD_GLOBAL                     23: NULL + memory_set_pid
                330     CALL                            0
                338     STORE_FAST                      4: _var_var_2
                340     LOAD_GLOBAL                     25: NULL + Thread
                350     LOAD_GLOBAL                     26: START
                360     LOAD_FAST                       0: data
                362     LOAD_GLOBAL                     6: config
                372     LOAD_FAST                       4: _var_var_2
                374     LOAD_FAST                       2: _var_var_0
                376     LOAD_FAST                       3: _var_var_1
                378     BUILD_TUPLE                     5
                380     KW_NAMES                        9: ('target', 'args')
                382     CALL                            2
                390     LOAD_ATTR                       29: start
                410     CALL                            0
                418     POP_TOP                         
                420     LOAD_GLOBAL                     25: NULL + Thread
                430     LOAD_GLOBAL                     30: Logs
                440     LOAD_ATTR                       32: WaitStopAnsfer
                460     LOAD_GLOBAL                     6: config
                470     LOAD_FAST                       4: _var_var_2
                472     LOAD_FAST                       3: _var_var_1
                474     BUILD_TUPLE                     3
                476     LOAD_CONST                      10: True
                478     KW_NAMES                        11: ('target', 'args', 'daemon')
                480     CALL                            3
                488     LOAD_ATTR                       29: start
                508     CALL                            0
                516     POP_TOP                         
                518     LOAD_GLOBAL                     25: NULL + Thread
                528     LOAD_GLOBAL                     30: Logs
                538     LOAD_ATTR                       34: UpdateLogInWindow
                558     LOAD_GLOBAL                     6: config
                568     LOAD_FAST                       4: _var_var_2
                570     LOAD_FAST                       3: _var_var_1
                572     BUILD_TUPLE                     3
                574     LOAD_CONST                      10: True
                576     KW_NAMES                        11: ('target', 'args', 'daemon')
                578     CALL                            3
                586     LOAD_ATTR                       29: start
                606     CALL                            0
                614     POP_TOP                         
                616     LOAD_GLOBAL                     31: NULL + Logs
                626     LOAD_ATTR                       36: LangCheck
                646     CALL                            0
                654     POP_TOP                         
                656     NOP                             
                658     LOAD_CONST                      10: True
                660     NOP                             
                662     NOP                             
                664     NOP                             
                666     JUMP_FORWARD                    73 (to 814)
                674     POP_TOP                         
                676     RETURN_CONST                    10: True
                678     PUSH_EXC_INFO                   
                680     LOAD_GLOBAL                     38: Exception
                690     CHECK_EXC_MATCH                 
                692     POP_JUMP_IF_FALSE               42 (to 778)
                694     STORE_FAST                      5: _var_var_3
                696     LOAD_GLOBAL                     41: NULL + print
                706     LOAD_CONST                      12: 'Invite: '
                708     LOAD_GLOBAL                     43: NULL + str
                718     LOAD_FAST                       5: _var_var_3
                720     CALL                            1
                728     BINARY_OP                       0 (+)
                732     CALL                            1
                740     POP_TOP                         
                742     POP_EXCEPT                      
                744     LOAD_CONST                      0: None
                746     STORE_FAST                      5: _var_var_3
                748     DELETE_FAST                     5: _var_var_3
                750     LOAD_CONST                      8: False
                752     NOP                             
                754     NOP                             
                756     NOP                             
                758     JUMP_FORWARD                    27 (to 814)
                766     POP_TOP                         
                768     RETURN_CONST                    8: False
                770     LOAD_CONST                      0: None
                772     STORE_FAST                      5: _var_var_3
                774     DELETE_FAST                     5: _var_var_3
                776     RERAISE                         1
                778     RERAISE                         0
                780     COPY                            3
                782     POP_EXCEPT                      
                784     RERAISE                         1
                786     PUSH_EXC_INFO                   
                788     PUSH_NULL                       
                790     LOAD_CONST                      6: '__pyarmor_exit_14051__'
                792     NOP                             
                794     LOAD_CONST                      3: b'<COAddr>\x05\x00\x00\x1a\xf8\x02\x00\x00\x00\x00\x00\x00\x00\x00\x00\x00\x00\x00\x00\x00'
                796     CALL                            1
                804     POP_TOP                         
                806     RERAISE                         0
                808     COPY                            3
                810     POP_EXCEPT                      
                812     RERAISE                         1
                814     PUSH_NULL                       
                816     LOAD_CONST                      6: '__pyarmor_exit_14051__'
                818     LOAD_CONST                      3: b'<COAddr>\x05\x00\x00\x1a\xf8\x02\x00\x00\x00\x00\x00\x00\x00\x00\x00\x00\x00\x00\x00\x00'
                820     BUILD_TUPLE                     1
                822     CALL_FUNCTION_EX                0
                824     POP_TOP                         
                826     RETURN_VALUE                    
            [Exception Table]
                30 to 100 -> 678 [0] 
                120 to 278 -> 678 [0] 
                300 to 656 -> 678 [0] 
                678 to 696 -> 780 [1] lasti
                696 to 742 -> 770 [1] lasti
                742 to 750 -> 786 [0] 
                770 to 780 -> 780 [1] lasti
                780 to 786 -> 786 [0] 
                786 to 808 -> 808 [1] lasti
        [Code]
            File Name: <frozen program.modules.Reactions>
            Object Name: START
            Qualified Name: START
            Arg Count: 5
            Pos Only Arg Count: 0
            KW Only Arg Count: 0
            Stack Size: 14
            Flags: 0x20000003 (CO_OPTIMIZED | CO_NEWLOCALS | CO_PYARMOR_OBFUSCATED)
            [Names]
                'is_set'
                'StopProgram'
                'check_get_settings'
                'get'
                'isinstance'
                'list'
                'int'
                'len'
                'eel'
                'sendErrorBox'
                'Lang'
                'db_reactions'
                'create'
                'set_task_manager'
                'concurrent'
                'futures'
                'ThreadPoolExecutor'
                'StreamStat'
                'json'
                'dumps'
                'append'
                'submit'
                'worker'
                'as_completed'
                'del_task_manager'
                'StopDetect'
                'Exception'
                'print'
            [Locals+Names]
                'data'
                'config'
                'pid'
                'proxy'
                'stop_thread'
                '__assert_armored__'
                '_var_var_4'
                '_var_var_5'
                '_var_var_6'
                '_var_var_7'
                '_var_var_8'
                '_var_var_9'
                '_var_var_10'
                '_var_var_11'
                '_var_var_12'
                '_var_var_13'
                '_var_var_14'
                '_var_var_15'
                '_var_var_16'
                '_var_var_17'
                '_var_var_18'
                '_var_var_19'
                '_var_var_20'
            [Constants]
                None
                '__pyarmor_assert_14052__'
                '__pyarmor_enter_14053__'
                b'<COAddr>\x07\x00\x00\x1a\x98\x07\x00\x00\x00\x00\x00\x00\x00\x00\x00\x00\x00\x00\x00\x00'
                'Settings'
                'Accounts'
                'posts'
                'all_reactions'   # b'\x81\xe3\x14\x1f\x0c\xe8\xbb\xd3\x18\xee\x04\xcfb\xff'
                1
                'select_accounts_works'   # b'\x81\xf1\x1d\x1f6\xf9\xaa\xed\x1a\xf9\x0e\xcfy\xe2\xec\x960J\xb4\xb5\xa1\xd8'
                'insert_post_link'   # b'\x81\xeb\x16\x006\xe8\xaa\xed\x0b\xf5\x1e\xd4S\xe0\xf1\x8b\x04'
                'check_reactions'   # b'\x81\xe1\x10\x160\xf1\x81\xc0\x1e\xfb\x0e\xd4e\xe3\xf6\x96'
                'kol_reaction_from'   # b'\x81\xe9\x17\x1f\x0c\xe8\xbb\xd3\x18\xee\x04\xcfb\xd3\xfe\x97\x00P'
                'select_more_accounts'   # b'\x81\xf1\x1d\x1f6\xf9\xaa\xed\x16\xf5\x1f\xc5S\xed\xfb\x86\x00H\xb5\xb3\xb9'
                'thread_rules'   # b'\x81\xf6\x10\x016\xfb\xba\xed\t\xef\x01\xc5\x7f'
                True
                'thread_count'   # b'\x81\xf6\x10\x016\xfb\xba\xed\x18\xf5\x18\xcex'
                'stuff'
                (
                    'accounts'
                    'name'
                )
                (
                    'max_workers'
                )
                0
                'st_task'
                'st_stream'   # b'\x81\xf1\x0c, \xee\xac\xd7\x1a\xf7'
                'st_wait'
                'st_done'
                '__pyarmor_exit_14054__'
                'DONE'
                'STOP'
                'START: '
                'EXCEPTION'   # b'\x81\xc7 0\x16\xca\x8a\xfb4\xd4'
            [Disassembly]
                0       NOP                             
                2       NOP                             
                4       PUSH_NULL                       
                6       LOAD_CONST                      2: '__pyarmor_enter_14053__'
                8       LOAD_CONST                      3: b'<COAddr>\x07\x00\x00\x1a\x98\x07\x00\x00\x00\x00\x00\x00\x00\x00\x00\x00\x00\x00\x00\x00'
                10      BUILD_TUPLE                     1
                12      CALL_FUNCTION_EX                0
                14      POP_TOP                         
                16      RESUME                          0
                18      NOP                             
                20      NOP                             
                22      NOP                             
                24      NOP                             
                26      NOP                             
                28      NOP                             
                30      LOAD_FAST                       4: stop_thread
                32      LOAD_ATTR                       1: is_set
                52      CALL                            0
                60      POP_JUMP_IF_FALSE               10 (to 82)
                62      LOAD_GLOBAL                     3: NULL + StopProgram
                72      CALL                            0
                80      RAISE_VARARGS                   1
                82      LOAD_GLOBAL                     5: NULL + check_get_settings
                92      LOAD_FAST                       0: data
                94      LOAD_ATTR                       7: get
                114     LOAD_CONST                      4: 'Settings'
                116     CALL                            1
                124     CALL                            1
                132     POP_TOP                         
                134     LOAD_FAST                       0: data
                136     LOAD_CONST                      5: 'Accounts'
                138     BINARY_SUBSCR                   
                142     STORE_FAST                      6: _var_var_4
                144     LOAD_FAST                       0: data
                146     LOAD_CONST                      4: 'Settings'
                148     BINARY_SUBSCR                   
                152     LOAD_ATTR                       7: get
                172     LOAD_CONST                      6: 'posts'
                174     CALL                            1
                182     STORE_FAST                      7: _var_var_5
                184     LOAD_FAST                       0: data
                186     LOAD_CONST                      4: 'Settings'
                188     BINARY_SUBSCR                   
                192     LOAD_ATTR                       7: get
                212     PUSH_NULL                       
                214     LOAD_CONST                      1: '__pyarmor_assert_14052__'
                216     LOAD_CONST                      7: 'all_reactions'   # b'\x81\xe3\x14\x1f\x0c\xe8\xbb\xd3\x18\xee\x04\xcfb\xff'
                218     CALL                            1
                226     CALL                            1
                234     STORE_FAST                      8: _var_var_6
                236     LOAD_GLOBAL                     9: NULL + isinstance
                246     LOAD_FAST                       6: _var_var_4
                248     LOAD_GLOBAL                     10: list
                258     CALL                            2
                266     POP_JUMP_IF_TRUE                3 (to 274)
                268     LOAD_FAST                       6: _var_var_4
                270     BUILD_LIST                      1
                272     STORE_FAST                      6: _var_var_4
                274     LOAD_GLOBAL                     9: NULL + isinstance
                284     LOAD_FAST                       7: _var_var_5
                286     LOAD_GLOBAL                     10: list
                296     CALL                            2
                304     POP_JUMP_IF_TRUE                3 (to 312)
                306     LOAD_FAST                       7: _var_var_5
                308     BUILD_LIST                      1
                310     STORE_FAST                      7: _var_var_5
                312     LOAD_GLOBAL                     13: NULL + int
                322     LOAD_GLOBAL                     15: NULL + len
                332     LOAD_FAST                       6: _var_var_4
                334     CALL                            1
                342     CALL                            1
                350     LOAD_CONST                      8: 1
                352     COMPARE_OP                      2 (<)
                356     POP_JUMP_IF_FALSE               44 (to 446)
                358     LOAD_GLOBAL                     17: NULL + eel
                368     LOAD_ATTR                       18: sendErrorBox
                388     LOAD_GLOBAL                     20: Lang
                398     PUSH_NULL                       
                400     LOAD_CONST                      1: '__pyarmor_assert_14052__'
                402     LOAD_CONST                      9: 'select_accounts_works'   # b'\x81\xf1\x1d\x1f6\xf9\xaa\xed\x1a\xf9\x0e\xcfy\xe2\xec\x960J\xb4\xb5\xa1\xd8'
                404     CALL                            1
                412     BINARY_SUBSCR                   
                416     CALL                            1
                424     POP_TOP                         
                426     LOAD_GLOBAL                     3: NULL + StopProgram
                436     CALL                            0
                444     RAISE_VARARGS                   1
                446     LOAD_GLOBAL                     13: NULL + int
                456     LOAD_GLOBAL                     15: NULL + len
                466     LOAD_FAST                       7: _var_var_5
                468     CALL                            1
                476     CALL                            1
                484     LOAD_CONST                      8: 1
                486     COMPARE_OP                      2 (<)
                490     POP_JUMP_IF_FALSE               44 (to 580)
                492     LOAD_GLOBAL                     17: NULL + eel
                502     LOAD_ATTR                       18: sendErrorBox
                522     LOAD_GLOBAL                     20: Lang
                532     PUSH_NULL                       
                534     LOAD_CONST                      1: '__pyarmor_assert_14052__'
                536     LOAD_CONST                      10: 'insert_post_link'   # b'\x81\xeb\x16\x006\xe8\xaa\xed\x0b\xf5\x1e\xd4S\xe0\xf1\x8b\x04'
                538     CALL                            1
                546     BINARY_SUBSCR                   
                550     CALL                            1
                558     POP_TOP                         
                560     LOAD_GLOBAL                     3: NULL + StopProgram
                570     CALL                            0
                578     RAISE_VARARGS                   1
                580     LOAD_GLOBAL                     13: NULL + int
                590     LOAD_GLOBAL                     15: NULL + len
                600     LOAD_FAST                       8: _var_var_6
                602     CALL                            1
                610     CALL                            1
                618     LOAD_CONST                      8: 1
                620     COMPARE_OP                      2 (<)
                624     POP_JUMP_IF_FALSE               44 (to 714)
                626     LOAD_GLOBAL                     17: NULL + eel
                636     LOAD_ATTR                       18: sendErrorBox
                656     LOAD_GLOBAL                     20: Lang
                666     PUSH_NULL                       
                668     LOAD_CONST                      1: '__pyarmor_assert_14052__'
                670     LOAD_CONST                      11: 'check_reactions'   # b'\x81\xe1\x10\x160\xf1\x81\xc0\x1e\xfb\x0e\xd4e\xe3\xf6\x96'
                672     CALL                            1
                680     BINARY_SUBSCR                   
                684     CALL                            1
                692     POP_TOP                         
                694     LOAD_GLOBAL                     3: NULL + StopProgram
                704     CALL                            0
                712     RAISE_VARARGS                   1
                714     LOAD_GLOBAL                     13: NULL + int
                724     LOAD_GLOBAL                     15: NULL + len
                734     LOAD_FAST                       8: _var_var_6
                736     CALL                            1
                744     CALL                            1
                752     LOAD_GLOBAL                     13: NULL + int
                762     LOAD_FAST                       0: data
                764     LOAD_CONST                      4: 'Settings'
                766     BINARY_SUBSCR                   
                770     LOAD_ATTR                       7: get
                790     PUSH_NULL                       
                792     LOAD_CONST                      1: '__pyarmor_assert_14052__'
                794     LOAD_CONST                      12: 'kol_reaction_from'   # b'\x81\xe9\x17\x1f\x0c\xe8\xbb\xd3\x18\xee\x04\xcfb\xd3\xfe\x97\x00P'
                796     CALL                            1
                804     CALL                            1
                812     CALL                            1
                820     COMPARE_OP                      2 (<)
                824     POP_JUMP_IF_FALSE               44 (to 914)
                826     LOAD_GLOBAL                     17: NULL + eel
                836     LOAD_ATTR                       18: sendErrorBox
                856     LOAD_GLOBAL                     20: Lang
                866     PUSH_NULL                       
                868     LOAD_CONST                      1: '__pyarmor_assert_14052__'
                870     LOAD_CONST                      13: 'select_more_accounts'   # b'\x81\xf1\x1d\x1f6\xf9\xaa\xed\x16\xf5\x1f\xc5S\xed\xfb\x86\x00H\xb5\xb3\xb9'
                872     CALL                            1
                880     BINARY_SUBSCR                   
                884     CALL                            1
                892     POP_TOP                         
                894     LOAD_GLOBAL                     3: NULL + StopProgram
                904     CALL                            0
                912     RAISE_VARARGS                   1
                914     LOAD_FAST                       0: data
                916     LOAD_CONST                      4: 'Settings'
                918     BINARY_SUBSCR                   
                922     LOAD_ATTR                       7: get
                942     PUSH_NULL                       
                944     LOAD_CONST                      1: '__pyarmor_assert_14052__'
                946     LOAD_CONST                      14: 'thread_rules'   # b'\x81\xf6\x10\x016\xfb\xba\xed\t\xef\x01\xc5\x7f'
                948     CALL                            1
                956     CALL                            1
                964     LOAD_CONST                      15: True
                966     COMPARE_OP                      40 (==)
                970     POP_JUMP_IF_FALSE               36 (to 1044)
                972     LOAD_GLOBAL                     13: NULL + int
                982     LOAD_FAST                       0: data
                984     LOAD_CONST                      4: 'Settings'
                986     BINARY_SUBSCR                   
                990     LOAD_ATTR                       7: get
                1010    PUSH_NULL                       
                1012    LOAD_CONST                      1: '__pyarmor_assert_14052__'
                1014    LOAD_CONST                      16: 'thread_count'   # b'\x81\xf6\x10\x016\xfb\xba\xed\x18\xf5\x18\xcex'
                1016    CALL                            1
                1024    CALL                            1
                1032    CALL                            1
                1040    STORE_FAST                      9: _var_var_7
                1042    JUMP_FORWARD                    11 (to 1066)
                1044    LOAD_FAST                       1: config
                1046    PUSH_NULL                       
                1048    LOAD_CONST                      1: '__pyarmor_assert_14052__'
                1050    LOAD_CONST                      16: 'thread_count'   # b'\x81\xf6\x10\x016\xfb\xba\xed\x18\xf5\x18\xcex'
                1052    CALL                            1
                1060    BINARY_SUBSCR                   
                1064    STORE_FAST                      9: _var_var_7
                1066    LOAD_GLOBAL                     23: NULL + db_reactions
                1076    CALL                            0
                1084    LOAD_ATTR                       25: create
                1104    CALL                            0
                1112    STORE_FAST                      10: _var_var_8
                1114    LOAD_GLOBAL                     27: NULL + set_task_manager
                1124    LOAD_FAST                       2: pid
                1126    LOAD_FAST                       6: _var_var_4
                1128    LOAD_FAST                       0: data
                1130    LOAD_CONST                      17: 'stuff'
                1132    BINARY_SUBSCR                   
                1136    KW_NAMES                        18: ('accounts', 'name')
                1138    CALL                            3
                1146    POP_TOP                         
                1148    LOAD_GLOBAL                     28: concurrent
                1158    LOAD_ATTR                       30: futures
                1178    LOAD_ATTR                       33: ThreadPoolExecutor
                1198    LOAD_FAST                       9: _var_var_7
                1200    KW_NAMES                        19: ('max_workers',)
                1202    CALL                            1
                1210    BEFORE_WITH                     
                1212    STORE_FAST                      11: _var_var_9
                1214    BUILD_LIST                      0
                1216    STORE_FAST                      12: _var_var_10
                1218    LOAD_GLOBAL                     15: NULL + len
                1228    LOAD_FAST                       6: _var_var_4
                1230    CALL                            1
                1238    STORE_FAST                      13: _var_var_11
                1240    LOAD_FAST                       9: _var_var_7
                1242    STORE_FAST                      14: _var_var_12
                1244    LOAD_FAST                       13: _var_var_11
                1246    STORE_FAST                      15: _var_var_13
                1248    LOAD_CONST                      20: 0
                1250    STORE_FAST                      16: _var_var_14
                1252    LOAD_GLOBAL                     17: NULL + eel
                1262    LOAD_ATTR                       34: StreamStat
                1282    LOAD_GLOBAL                     37: NULL + json
                1292    LOAD_ATTR                       38: dumps
                1312    LOAD_CONST                      21: 'st_task'
                1314    LOAD_FAST                       13: _var_var_11
                1316    PUSH_NULL                       
                1318    LOAD_CONST                      1: '__pyarmor_assert_14052__'
                1320    LOAD_CONST                      22: 'st_stream'   # b'\x81\xf1\x0c, \xee\xac\xd7\x1a\xf7'
                1322    CALL                            1
                1330    LOAD_FAST                       14: _var_var_12
                1332    LOAD_CONST                      23: 'st_wait'
                1334    LOAD_FAST                       15: _var_var_13
                1336    LOAD_CONST                      24: 'st_done'
                1338    LOAD_FAST                       16: _var_var_14
                1340    BUILD_MAP                       4
                1342    CALL                            1
                1350    CALL                            1
                1358    POP_TOP                         
                1360    LOAD_FAST                       6: _var_var_4
                1362    GET_ITER                        
                1364    FOR_ITER                        45 (to 1456)
                1368    STORE_FAST                      17: _var_var_15
                1370    LOAD_FAST                       12: _var_var_10
                1372    LOAD_ATTR                       41: append
                1392    LOAD_FAST                       11: _var_var_9
                1394    LOAD_ATTR                       43: submit
                1414    LOAD_GLOBAL                     44: worker
                1424    LOAD_FAST                       17: _var_var_15
                1426    LOAD_FAST                       1: config
                1428    LOAD_FAST                       3: proxy
                1430    LOAD_FAST                       7: _var_var_5
                1432    LOAD_FAST                       0: data
                1434    LOAD_FAST                       10: _var_var_8
                1436    LOAD_FAST                       4: stop_thread
                1438    CALL                            8
                1446    CALL                            1
                1454    POP_TOP                         
                1456    JUMP_BACKWARD                   47 (to 1364)
                1458    END_FOR                         
                1460    LOAD_CONST                      20: 0
                1462    STORE_FAST                      18: _var_var_16
                1464    LOAD_CONST                      20: 0
                1466    STORE_FAST                      19: _var_var_17
                1468    LOAD_CONST                      20: 0
                1470    STORE_FAST                      20: _var_var_18
                1472    LOAD_GLOBAL                     28: concurrent
                1482    LOAD_ATTR                       30: futures
                1502    LOAD_ATTR                       47: as_completed
                1522    LOAD_FAST                       12: _var_var_10
                1524    CALL                            1
                1532    GET_ITER                        
                1534    FOR_ITER                        66 (to 1668)
                1538    STORE_FAST                      21: _var_var_19
                1540    LOAD_FAST                       16: _var_var_14
                1542    LOAD_CONST                      8: 1
                1544    BINARY_OP                       13 (+=)
                1548    STORE_FAST                      16: _var_var_14
                1550    LOAD_FAST                       15: _var_var_13
                1552    LOAD_CONST                      8: 1
                1554    BINARY_OP                       23 (-=)
                1558    STORE_FAST                      15: _var_var_13
                1560    LOAD_GLOBAL                     17: NULL + eel
                1570    LOAD_ATTR                       34: StreamStat
                1590    LOAD_GLOBAL                     37: NULL + json
                1600    LOAD_ATTR                       38: dumps
                1620    LOAD_CONST                      21: 'st_task'
                1622    LOAD_FAST                       13: _var_var_11
                1624    PUSH_NULL                       
                1626    LOAD_CONST                      1: '__pyarmor_assert_14052__'
                1628    LOAD_CONST                      22: 'st_stream'   # b'\x81\xf1\x0c, \xee\xac\xd7\x1a\xf7'
                1630    CALL                            1
                1638    LOAD_FAST                       14: _var_var_12
                1640    LOAD_CONST                      23: 'st_wait'
                1642    LOAD_FAST                       15: _var_var_13
                1644    LOAD_CONST                      24: 'st_done'
                1646    LOAD_FAST                       16: _var_var_14
                1648    BUILD_MAP                       4
                1650    CALL                            1
                1658    CALL                            1
                1666    POP_TOP                         
                1668    JUMP_BACKWARD                   68 (to 1534)
                1670    END_FOR                         
                1672    DELETE_FAST                     12: _var_var_10
                1674    DELETE_FAST                     0: data
                1676    LOAD_CONST                      0: None
                1678    LOAD_CONST                      0: None
                1680    LOAD_CONST                      0: None
                1682    CALL                            2
                1690    POP_TOP                         
                1692    LOAD_GLOBAL                     49: NULL + del_task_manager
                1702    LOAD_FAST                       2: pid
                1704    CALL                            1
                1712    POP_TOP                         
                1714    LOAD_GLOBAL                     51: NULL + StopDetect
                1724    LOAD_FAST                       4: stop_thread
                1726    CALL                            1
                1734    POP_TOP                         
                1736    NOP                             
                1738    LOAD_CONST                      26: 'DONE'
                1740    NOP                             
                1742    NOP                             
                1744    NOP                             
                1746    JUMP_FORWARD                    125 (to 1998)
                1754    POP_TOP                         
                1756    RETURN_CONST                    26: 'DONE'
                1758    PUSH_EXC_INFO                   
                1760    WITH_EXCEPT_START               
                1762    POP_JUMP_IF_TRUE                1 (to 1766)
                1764    RERAISE                         2
                1766    POP_TOP                         
                1768    POP_EXCEPT                      
                1770    POP_TOP                         
                1772    POP_TOP                         
                1774    JUMP_BACKWARD                   42 (to 1692)
                1776    COPY                            3
                1778    POP_EXCEPT                      
                1780    RERAISE                         1
                1782    PUSH_EXC_INFO                   
                1784    LOAD_GLOBAL                     2: StopProgram
                1794    CHECK_EXC_MATCH                 
                1796    POP_JUMP_IF_FALSE               34 (to 1866)
                1798    POP_TOP                         
                1800    LOAD_GLOBAL                     49: NULL + del_task_manager
                1810    LOAD_FAST                       2: pid
                1812    CALL                            1
                1820    POP_TOP                         
                1822    LOAD_GLOBAL                     51: NULL + StopDetect
                1832    LOAD_FAST                       4: stop_thread
                1834    CALL                            1
                1842    POP_TOP                         
                1844    POP_EXCEPT                      
                1846    LOAD_CONST                      27: 'STOP'
                1848    NOP                             
                1850    NOP                             
                1852    NOP                             
                1854    JUMP_FORWARD                    71 (to 1998)
                1862    POP_TOP                         
                1864    RETURN_CONST                    27: 'STOP'
                1866    LOAD_GLOBAL                     52: Exception
                1876    CHECK_EXC_MATCH                 
                1878    POP_JUMP_IF_FALSE               41 (to 1962)
                1880    STORE_FAST                      22: _var_var_20
                1882    LOAD_GLOBAL                     55: NULL + print
                1892    LOAD_CONST                      28: 'START: '
                1894    LOAD_FAST                       22: _var_var_20
                1896    FORMAT_VALUE                    0 (FVC_NONE)
                1898    BUILD_STRING                    2
                1900    CALL                            1
                1908    POP_TOP                         
                1910    PUSH_NULL                       
                1912    LOAD_CONST                      1: '__pyarmor_assert_14052__'
                1914    LOAD_CONST                      29: 'EXCEPTION'   # b'\x81\xc7 0\x16\xca\x8a\xfb4\xd4'
                1916    CALL                            1
                1924    SWAP                            2
                1926    POP_EXCEPT                      
                1928    LOAD_CONST                      0: None
                1930    STORE_FAST                      22: _var_var_20
                1932    DELETE_FAST                     22: _var_var_20
                1934    NOP                             
                1936    NOP                             
                1938    NOP                             
                1940    JUMP_FORWARD                    28 (to 1998)
                1942    CALL                            1
                1950    POP_TOP                         
                1952    RETURN_VALUE                    
                1954    LOAD_CONST                      0: None
                1956    STORE_FAST                      22: _var_var_20
                1958    DELETE_FAST                     22: _var_var_20
                1960    RERAISE                         1
                1962    RERAISE                         0
                1964    COPY                            3
                1966    POP_EXCEPT                      
                1968    RERAISE                         1
                1970    PUSH_EXC_INFO                   
                1972    PUSH_NULL                       
                1974    LOAD_CONST                      25: '__pyarmor_exit_14054__'
                1976    NOP                             
                1978    LOAD_CONST                      3: b'<COAddr>\x07\x00\x00\x1a\x98\x07\x00\x00\x00\x00\x00\x00\x00\x00\x00\x00\x00\x00\x00\x00'
                1980    CALL                            1
                1988    POP_TOP                         
                1990    RERAISE                         0
                1992    COPY                            3
                1994    POP_EXCEPT                      
                1996    RERAISE                         1
                1998    PUSH_NULL                       
                2000    LOAD_CONST                      25: '__pyarmor_exit_14054__'
                2002    LOAD_CONST                      3: b'<COAddr>\x07\x00\x00\x1a\x98\x07\x00\x00\x00\x00\x00\x00\x00\x00\x00\x00\x00\x00\x00\x00'
                2004    BUILD_TUPLE                     1
                2006    CALL_FUNCTION_EX                0
                2008    POP_TOP                         
                2010    RETURN_VALUE                    
            [Exception Table]
                30 to 1212 -> 1782 [0] 
                1212 to 1676 -> 1758 [1] lasti
                1676 to 1736 -> 1782 [0] 
                1758 to 1768 -> 1776 [3] lasti
                1768 to 1782 -> 1782 [0] 
                1782 to 1844 -> 1964 [1] lasti
                1844 to 1846 -> 1970 [0] 
                1866 to 1882 -> 1964 [1] lasti
                1882 to 1924 -> 1954 [1] lasti
                1924 to 1926 -> 1964 [1] lasti
                1926 to 1934 -> 1970 [0] 
                1954 to 1964 -> 1964 [1] lasti
                1964 to 1970 -> 1970 [0] 
                1970 to 1992 -> 1992 [1] lasti
        'uid'
        'return'
        [Code]
            File Name: <frozen program.modules.Reactions>
            Object Name: get_emoticon
            Qualified Name: get_emoticon
            Arg Count: 1
            Pos Only Arg Count: 0
            KW Only Arg Count: 0
            Stack Size: 8
            Flags: 0x20000003 (CO_OPTIMIZED | CO_NEWLOCALS | CO_PYARMOR_OBFUSCATED)
            [Names]
                'str'
            [Locals+Names]
                'uid'
                '__assert_armored__'
                '_var_var_6'
            [Constants]
                None
                '__pyarmor_assert_14055__'
                '__pyarmor_enter_14056__'
                b'<COAddr>\x07\x00\x00\x1a\xea\x01\x00\x00\x00\x00\x00\x00\x00\x00\x00\x00\x00\x00\x00\x00'
                '0'
                '👍'
                '1'
                '👎'
                '2'
                '❤'
                '3'
                '🔥'
                '4'
                '🥰'
                '5'
                '👏'
                '6'
                '😁'
                '7'
                '🤔'
                '8'
                '🤯'
                '9'
                '😱'
                '10'
                '🤬'
                '11'
                '😢'
                '12'
                '🎉'
                '13'
                '🤩'
                '14'
                '🤮'
                '15'
                '💩'
                '16'
                '🙏'
                '17'
                '👌'
                '18'
                '🕊'
                '19'
                '🤡'
                '20'
                '🥱'
                '21'
                '🥴'
                '22'
                '😍'
                '23'
                '🐳'
                '24'
                '❤‍🔥'
                '25'
                '🌚'
                '26'
                '🌭'
                '27'
                '💯'
                '28'
                '🤣'
                '29'
                '⚡'
                '30'
                '🍌'
                '31'
                '🏆'
                '32'
                '💔'
                '33'
                '🤨'
                '34'
                '😐'
                '35'
                '🍓'
                '36'
                '🍾'
                '37'
                '💋'
                '38'
                '🖕'
                '39'
                '😈'
                '40'
                '😴'
                '41'
                '😭'
                '42'
                '🤓'
                '43'
                '👻'
                '44'
                '👨‍💻'
                '45'
                '👀'
                '46'
                '🎃'
                '47'
                '🙈'
                '48'
                '😇'
                '49'
                '😨'
                '50'
                '🤝'
                '51'
                '✍'
                '52'
                '🤗'
                '53'
                '🫡'
                '54'
                '🎅'
                '55'
                '🎄'
                '56'
                '☃'
                '57'
                '💅'
                '58'
                '🤪'
                '59'
                '🗿'
                '60'
                '🆒'
                '61'
                '💘'
                '62'
                '🙉'
                '63'
                '🦄'
                '64'
                '😘'
                '65'
                '💊'
                '66'
                '🙊'
                '67'
                '😎'
                '👾'
                '🤷‍♂'
                '🤷'
                '🤷‍♀'
                '😡'
                '😂'
                (
                    '68'
                    '69'
                    '70'
                    '71'
                    '72'
                    '73'
                )
                '__pyarmor_exit_14057__'
            [Disassembly]
                0       NOP                             
                2       NOP                             
                4       PUSH_NULL                       
                6       LOAD_CONST                      2: '__pyarmor_enter_14056__'
                8       LOAD_CONST                      3: b'<COAddr>\x07\x00\x00\x1a\xea\x01\x00\x00\x00\x00\x00\x00\x00\x00\x00\x00\x00\x00\x00\x00'
                10      BUILD_TUPLE                     1
                12      CALL_FUNCTION_EX                0
                14      POP_TOP                         
                16      RESUME                          0
                18      NOP                             
                20      NOP                             
                22      NOP                             
                24      NOP                             
                26      NOP                             
                28      BUILD_MAP                       0
                30      LOAD_CONST                      4: '0'
                32      LOAD_CONST                      5: '👍'
                34      MAP_ADD                         1
                36      LOAD_CONST                      6: '1'
                38      LOAD_CONST                      7: '👎'
                40      MAP_ADD                         1
                42      LOAD_CONST                      8: '2'
                44      LOAD_CONST                      9: '❤'
                46      MAP_ADD                         1
                48      LOAD_CONST                      10: '3'
                50      LOAD_CONST                      11: '🔥'
                52      MAP_ADD                         1
                54      LOAD_CONST                      12: '4'
                56      LOAD_CONST                      13: '🥰'
                58      MAP_ADD                         1
                60      LOAD_CONST                      14: '5'
                62      LOAD_CONST                      15: '👏'
                64      MAP_ADD                         1
                66      LOAD_CONST                      16: '6'
                68      LOAD_CONST                      17: '😁'
                70      MAP_ADD                         1
                72      LOAD_CONST                      18: '7'
                74      LOAD_CONST                      19: '🤔'
                76      MAP_ADD                         1
                78      LOAD_CONST                      20: '8'
                80      LOAD_CONST                      21: '🤯'
                82      MAP_ADD                         1
                84      LOAD_CONST                      22: '9'
                86      LOAD_CONST                      23: '😱'
                88      MAP_ADD                         1
                90      LOAD_CONST                      24: '10'
                92      LOAD_CONST                      25: '🤬'
                94      MAP_ADD                         1
                96      LOAD_CONST                      26: '11'
                98      LOAD_CONST                      27: '😢'
                100     MAP_ADD                         1
                102     LOAD_CONST                      28: '12'
                104     LOAD_CONST                      29: '🎉'
                106     MAP_ADD                         1
                108     LOAD_CONST                      30: '13'
                110     LOAD_CONST                      31: '🤩'
                112     MAP_ADD                         1
                114     LOAD_CONST                      32: '14'
                116     LOAD_CONST                      33: '🤮'
                118     MAP_ADD                         1
                120     LOAD_CONST                      34: '15'
                122     LOAD_CONST                      35: '💩'
                124     MAP_ADD                         1
                126     LOAD_CONST                      36: '16'
                128     LOAD_CONST                      37: '🙏'
                130     MAP_ADD                         1
                132     BUILD_MAP                       0
                134     LOAD_CONST                      38: '17'
                136     LOAD_CONST                      39: '👌'
                138     MAP_ADD                         1
                140     LOAD_CONST                      40: '18'
                142     LOAD_CONST                      41: '🕊'
                144     MAP_ADD                         1
                146     LOAD_CONST                      42: '19'
                148     LOAD_CONST                      43: '🤡'
                150     MAP_ADD                         1
                152     LOAD_CONST                      44: '20'
                154     LOAD_CONST                      45: '🥱'
                156     MAP_ADD                         1
                158     LOAD_CONST                      46: '21'
                160     LOAD_CONST                      47: '🥴'
                162     MAP_ADD                         1
                164     LOAD_CONST                      48: '22'
                166     LOAD_CONST                      49: '😍'
                168     MAP_ADD                         1
                170     LOAD_CONST                      50: '23'
                172     LOAD_CONST                      51: '🐳'
                174     MAP_ADD                         1
                176     LOAD_CONST                      52: '24'
                178     LOAD_CONST                      53: '❤‍🔥'
                180     MAP_ADD                         1
                182     LOAD_CONST                      54: '25'
                184     LOAD_CONST                      55: '🌚'
                186     MAP_ADD                         1
                188     LOAD_CONST                      56: '26'
                190     LOAD_CONST                      57: '🌭'
                192     MAP_ADD                         1
                194     LOAD_CONST                      58: '27'
                196     LOAD_CONST                      59: '💯'
                198     MAP_ADD                         1
                200     LOAD_CONST                      60: '28'
                202     LOAD_CONST                      61: '🤣'
                204     MAP_ADD                         1
                206     LOAD_CONST                      62: '29'
                208     LOAD_CONST                      63: '⚡'
                210     MAP_ADD                         1
                212     LOAD_CONST                      64: '30'
                214     LOAD_CONST                      65: '🍌'
                216     MAP_ADD                         1
                218     LOAD_CONST                      66: '31'
                220     LOAD_CONST                      67: '🏆'
                222     MAP_ADD                         1
                224     LOAD_CONST                      68: '32'
                226     LOAD_CONST                      69: '💔'
                228     MAP_ADD                         1
                230     LOAD_CONST                      70: '33'
                232     LOAD_CONST                      71: '🤨'
                234     MAP_ADD                         1
                236     DICT_UPDATE                     1
                238     BUILD_MAP                       0
                240     LOAD_CONST                      72: '34'
                242     LOAD_CONST                      73: '😐'
                244     MAP_ADD                         1
                246     LOAD_CONST                      74: '35'
                248     LOAD_CONST                      75: '🍓'
                250     MAP_ADD                         1
                252     LOAD_CONST                      76: '36'
                254     LOAD_CONST                      77: '🍾'
                256     MAP_ADD                         1
                258     LOAD_CONST                      78: '37'
                260     LOAD_CONST                      79: '💋'
                262     MAP_ADD                         1
                264     LOAD_CONST                      80: '38'
                266     LOAD_CONST                      81: '🖕'
                268     MAP_ADD                         1
                270     LOAD_CONST                      82: '39'
                272     LOAD_CONST                      83: '😈'
                274     MAP_ADD                         1
                276     LOAD_CONST                      84: '40'
                278     LOAD_CONST                      85: '😴'
                280     MAP_ADD                         1
                282     LOAD_CONST                      86: '41'
                284     LOAD_CONST                      87: '😭'
                286     MAP_ADD                         1
                288     LOAD_CONST                      88: '42'
                290     LOAD_CONST                      89: '🤓'
                292     MAP_ADD                         1
                294     LOAD_CONST                      90: '43'
                296     LOAD_CONST                      91: '👻'
                298     MAP_ADD                         1
                300     LOAD_CONST                      92: '44'
                302     LOAD_CONST                      93: '👨‍💻'
                304     MAP_ADD                         1
                306     LOAD_CONST                      94: '45'
                308     LOAD_CONST                      95: '👀'
                310     MAP_ADD                         1
                312     LOAD_CONST                      96: '46'
                314     LOAD_CONST                      97: '🎃'
                316     MAP_ADD                         1
                318     LOAD_CONST                      98: '47'
                320     LOAD_CONST                      99: '🙈'
                322     MAP_ADD                         1
                324     LOAD_CONST                      100: '48'
                326     LOAD_CONST                      101: '😇'
                328     MAP_ADD                         1
                330     LOAD_CONST                      102: '49'
                332     LOAD_CONST                      103: '😨'
                334     MAP_ADD                         1
                336     LOAD_CONST                      104: '50'
                338     LOAD_CONST                      105: '🤝'
                340     MAP_ADD                         1
                342     DICT_UPDATE                     1
                344     BUILD_MAP                       0
                346     LOAD_CONST                      106: '51'
                348     LOAD_CONST                      107: '✍'
                350     MAP_ADD                         1
                352     LOAD_CONST                      108: '52'
                354     LOAD_CONST                      109: '🤗'
                356     MAP_ADD                         1
                358     LOAD_CONST                      110: '53'
                360     LOAD_CONST                      111: '🫡'
                362     MAP_ADD                         1
                364     LOAD_CONST                      112: '54'
                366     LOAD_CONST                      113: '🎅'
                368     MAP_ADD                         1
                370     LOAD_CONST                      114: '55'
                372     LOAD_CONST                      115: '🎄'
                374     MAP_ADD                         1
                376     LOAD_CONST                      116: '56'
                378     LOAD_CONST                      117: '☃'
                380     MAP_ADD                         1
                382     LOAD_CONST                      118: '57'
                384     LOAD_CONST                      119: '💅'
                386     MAP_ADD                         1
                388     LOAD_CONST                      120: '58'
                390     LOAD_CONST                      121: '🤪'
                392     MAP_ADD                         1
                394     LOAD_CONST                      122: '59'
                396     LOAD_CONST                      123: '🗿'
                398     MAP_ADD                         1
                400     LOAD_CONST                      124: '60'
                402     LOAD_CONST                      125: '🆒'
                404     MAP_ADD                         1
                406     LOAD_CONST                      126: '61'
                408     LOAD_CONST                      127: '💘'
                410     MAP_ADD                         1
                412     LOAD_CONST                      128: '62'
                414     LOAD_CONST                      129: '🙉'
                416     MAP_ADD                         1
                418     LOAD_CONST                      130: '63'
                420     LOAD_CONST                      131: '🦄'
                422     MAP_ADD                         1
                424     LOAD_CONST                      132: '64'
                426     LOAD_CONST                      133: '😘'
                428     MAP_ADD                         1
                430     LOAD_CONST                      134: '65'
                432     LOAD_CONST                      135: '💊'
                434     MAP_ADD                         1
                436     LOAD_CONST                      136: '66'
                438     LOAD_CONST                      137: '🙊'
                440     MAP_ADD                         1
                442     LOAD_CONST                      138: '67'
                444     LOAD_CONST                      139: '😎'
                446     MAP_ADD                         1
                448     DICT_UPDATE                     1
                450     LOAD_CONST                      140: '👾'
                452     LOAD_CONST                      141: '🤷‍♂'
                454     LOAD_CONST                      142: '🤷'
                456     LOAD_CONST                      143: '🤷‍♀'
                458     LOAD_CONST                      144: '😡'
                460     LOAD_CONST                      145: '😂'
                462     LOAD_CONST                      146: ('68', '69', '70', '71', '72', '73')
                464     BUILD_CONST_KEY_MAP             6
                466     DICT_UPDATE                     1
                468     STORE_FAST                      2: _var_var_6
                470     LOAD_FAST                       2: _var_var_6
                472     LOAD_GLOBAL                     1: NULL + str
                482     LOAD_FAST                       0: uid
                484     CALL                            1
                492     BINARY_SUBSCR                   
                496     NOP                             
                498     NOP                             
                500     NOP                             
                502     JUMP_FORWARD                    20 (to 544)
                504     CALL                            1
                512     POP_TOP                         
                514     RETURN_VALUE                    
                516     PUSH_EXC_INFO                   
                518     PUSH_NULL                       
                520     LOAD_CONST                      147: '__pyarmor_exit_14057__'
                522     NOP                             
                524     LOAD_CONST                      3: b'<COAddr>\x07\x00\x00\x1a\xea\x01\x00\x00\x00\x00\x00\x00\x00\x00\x00\x00\x00\x00\x00\x00'
                526     CALL                            1
                534     POP_TOP                         
                536     RERAISE                         0
                538     COPY                            3
                540     POP_EXCEPT                      
                542     RERAISE                         1
                544     PUSH_NULL                       
                546     LOAD_CONST                      147: '__pyarmor_exit_14057__'
                548     LOAD_CONST                      3: b'<COAddr>\x07\x00\x00\x1a\xea\x01\x00\x00\x00\x00\x00\x00\x00\x00\x00\x00\x00\x00\x00\x00'
                550     BUILD_TUPLE                     1
                552     CALL_FUNCTION_EX                0
                554     POP_TOP                         
                556     RETURN_VALUE                    
            [Exception Table]
                28 to 496 -> 516 [0] 
                516 to 538 -> 538 [1] lasti
        [Code]
            File Name: <frozen program.modules.Reactions>
            Object Name: worker
            Qualified Name: worker
            Arg Count: 7
            Pos Only Arg Count: 0
            KW Only Arg Count: 0
            Stack Size: 13
            Flags: 0x20000003 (CO_OPTIMIZED | CO_NEWLOCALS | CO_PYARMOR_OBFUSCATED)
            [Names]
                'Thread_wait'
                'account_works'
                'Lang'
                'get'
                'int'
                'is_set'
                'StopProgram'
                'random'
                'shuffle'
                'randint'
                'tg_links'
                'message_link_id_username'
                'DelayOnline'
                'tg_search_group'
                'dialogs'
                'Logs'
                'PrintLog'
                'tg_group'
                'go_to'
                'Disconnect'
                'append'
                'range'
                'get_emoticon'
                'functions'
                'messages'
                'SendReactionRequest'
                'types'
                'ReactionEmoji'
                'GetMessagesViewsRequest'
                'Exception'
                'type'
                '__name__'
                'seconds'
                'db_reactions'
                'insert'
                'delete_dialog'
                'print'
            [Locals+Names]
                'account'
                'config'
                'proxy'
                'posts'
                'data'
                'db_result'
                'stop_thread'
                '__assert_armored__'
                '_var_var_21'
                '_var_var_22'
                '_var_var_23'
                '_var_var_24'
                '_var_var_25'
                '_var_var_26'
                '_var_var_27'
                '_var_var_28'
                '_var_var_29'
                '_var_var_30'
                '_var_var_31'
                '_var_var_32'
                '_var_var_33'
                '_var_var_34'
                '_var_var_35'
                '_var_var_36'
                '_var_var_37'
                '_var_var_38'
                '_var_var_39'
                '_var_var_40'
                '_var_var_41'
                '_var_var_20'
                '_var_var_42'
                '_var_var_43'
            [Constants]
                None
                '__pyarmor_assert_14058__'
                '__pyarmor_enter_14059__'
                b'<COAddr>\x05\x00\x00\x1a2\x0e\x00\x00\x00\x00\x00\x00\x00\x00\x00\x00\x00\x00\x00\x00'
                'Reactions'   # b'\x81\xd0\x1d\x120\xee\xb7\xdd\x15\xe9'
                (
                    'module'
                )
                False
                'false'
                (
                    'account'
                    'status'
                )
                '__pyarmor_exit_14060__'
                'Settings'
                'all_reactions'   # b'\x81\xe3\x14\x1f\x0c\xe8\xbb\xd3\x18\xee\x04\xcfb\xff'
                'kol_reaction_from'   # b'\x81\xe9\x17\x1f\x0c\xe8\xbb\xd3\x18\xee\x04\xcfb\xd3\xfe\x97\x00P'
                'kol_reaction_to'   # b'\x81\xe9\x17\x1f\x0c\xe8\xbb\xd3\x18\xee\x04\xcfb\xd3\xec\x8a'
                'reactions_wait_from'   # b'\x81\xf0\x1d\x120\xee\xb7\xdd\x15\xe92\xd7m\xe5\xec\xba\tO\xb4\xaa'
                'reactions_wait_to'   # b'\x81\xf0\x1d\x120\xee\xb7\xdd\x15\xe92\xd7m\xe5\xec\xba\x1bR'
                'wait_from'   # b"\x81\xf5\x19\x1a'\xc5\xb8\xc0\x14\xf7"
                'wait_to'
                'max_flood_wait'   # b'\x81\xef\x19\x0b\x0c\xfc\xb2\xdd\x14\xfe2\xd7m\xe5\xec'
                'reactions_random'   # b'\x81\xf0\x1d\x120\xee\xb7\xdd\x15\xe92\xd2m\xe2\xfc\x8a\x02'
                'leave_chat'   # b'\x81\xee\x1d\x12%\xff\x81\xd1\x13\xfb\x19'
                ''
                'group_id'
                'username'
                'mess_id'
                (
                    'uid'
                    'username'
                    'mess_id'
                )
                'Аккаунт не в группе, пытаюсь вступить'   # b'\x81R\xe8\xa3\xe9Jdb\xcbK\xeep\xb1]\x1a\xc5\xbf\x80\x0br\xea{\x9c\x8c\xb5\xbc\x12\xbc\xb1R\xae:\x8a\x8d\x90\xd8\xd4\x8a\x04\xf1\xa9\x02I\xbfm\x08\xbe\xa9\x86\x0c\xe7\x17\xc7\xc0\xd4\\\xd6Zy\xac\xfb\xfb\xee\xe3\x8f\xf9\xe721'
                (
                    'config'
                    'account'
                    'message'
                    'end'
                )
                (
                    'config'
                    'client'
                    'account'
                    'group_link'
                    'max_flood_wait'
                    'lang'
                    'stop_thread'
                )
                True
                (
                    'emoticon'
                )
                (
                    'peer'
                    'msg_id'
                    'big'
                    'add_to_recent'
                    'reaction'
                )
                (
                    'peer'
                    'id'
                    'increment'
                )
                'Done'
                'Status:'
                (
                    'config'
                    'account'
                    'message'
                    'param'
                )
                'FloodWaitError'   # b'\x81\xc4\x14\x1c<\xfe\x89\xd3\x12\xee(\xd2~\xe3\xea'
                'restriction_detected'   # b"\x81\xf0\x1d\x00'\xe8\xb7\xd1\x0f\xf3\x02\xceS\xe8\xfd\x91\n^\xaf\xa2\xae"
                (
                    'config'
                    'account'
                    'message'
                )
                'algorithm_running'   # b'\x81\xe3\x14\x14<\xe8\xb7\xc6\x13\xf72\xd2y\xe2\xf6\x8c\x01Z'
                10
                20
                'flood_wait_more'   # b'\x81\xe4\x14\x1c<\xfe\x81\xc5\x1a\xf3\x19\xffa\xe3\xea\x80'
                'work_stopped'   # b'\x81\xf5\x17\x018\xc5\xad\xc6\x14\xea\x1d\xc5h'
                (
                    'status'
                )
                (
                    'config'
                    'account'
                    'message'
                    'param'
                    'end'
                )
                'flood_wait_bypass'   # b'\x81\xe4\x14\x1c<\xfe\x81\xc5\x1a\xf3\x19\xffn\xf5\xe8\x84\x1cN'
                'Не могу найти группу\\канал, если группа\\канал приватный, вступите в него предварительно'   # b'\x81R\xe5\xa3\xe6\xba\x0e\x0e\xab$\xbd\x13\xdd\x0f\xb85\xd2\xedk\x17sz\xac|\xdd/\x13\x8f\xb1Q\xaf\x06\x8a\x8d\x90\xd2))\x88\x9e\xc2Y(\xed\x00h\xdf\xf7\xec\xa1\x16KR\xc1\xe7]\xec[C]\xa8\x98\x80\xb3\xe6\xab\xb5\\m\xe8\\o\xaf\xd2\xe6\x8e\x90\t\xd5!q7_\xe9\x0f\xd0\xb3\xa1to=>/\xa1hQT\x8d\x0c\x98\x8b\xd1h|\xff\xcd\tc\xfc\x05L\xd8\x02\xe5\x02\xc0\xc9\x16\xe5\xde3\xfc\xb86I\x9f\x0f8[|\xa2~G\x06\xce=\xd1\xe5\xc1In\x8c\x8e\x08\xa8\x01\x06l\xbd\xe6+\xd0(Bv\xba\r\x7f!gI'
                'Данная ссылка не является постом или формат неверен'   # b'\x81R\xec\xa3\xe3Jcb\xc6J\xddq\x83\xacId\xbe\xbc\nL\x1a\x10\xfe\x16\xb5\xbf\xe3\xec\xdd\x01\xcb\xa5\x8b\xbd\x90\xdf(\x11\x05\xc1\xa8<I\xbfl9\xbe\xa8w]\x89KY\xc1\xe7\\\xd5[E\xad\xc4\x0b\x81\x8b\xe7\x93\xb5[\x9d\x86\x08\x0fM\xd3\xdc\x8e\x9c\t\xd8 C\xc74t\x0f\xda\xb2\x93tb<\x0c/\xa4in'
                'exit_groups_on_activated'   # b"\x81\xe7\x00\x1a'\xc5\xb9\xc0\x14\xef\x1d\xd3S\xe3\xf6\xba\x0e^\xaf\xae\xbc\xcaZ\xc9\x01"
                'leaving_group'   # b'\x81\xee\x1d\x12%\xf3\xb0\xd5$\xfd\x1f\xcfy\xfc'
                'STOP'
                'worker: '
                'EXCEPTION'   # b'\x81\xc7 0\x16\xca\x8a\xfb4\xd4'
            [Disassembly]
                0       NOP                             
                2       NOP                             
                4       PUSH_NULL                       
                6       LOAD_CONST                      2: '__pyarmor_enter_14059__'
                8       LOAD_CONST                      3: b'<COAddr>\x05\x00\x00\x1a2\x0e\x00\x00\x00\x00\x00\x00\x00\x00\x00\x00\x00\x00\x00\x00'
                10      BUILD_TUPLE                     1
                12      CALL_FUNCTION_EX                0
                14      POP_TOP                         
                16      RESUME                          0
                18      NOP                             
                20      NOP                             
                22      NOP                             
                24      NOP                             
                26      NOP                             
                28      NOP                             
                30      LOAD_GLOBAL                     1: NULL + Thread_wait
                40      LOAD_FAST                       4: data
                42      LOAD_FAST                       1: config
                44      LOAD_FAST                       6: stop_thread
                46      CALL                            3
                54      POP_TOP                         
                56      LOAD_GLOBAL                     3: NULL + account_works
                66      LOAD_FAST                       1: config
                68      LOAD_GLOBAL                     4: Lang
                78      LOAD_FAST                       2: proxy
                80      LOAD_FAST                       0: account
                82      LOAD_FAST                       6: stop_thread
                84      PUSH_NULL                       
                86      LOAD_CONST                      1: '__pyarmor_assert_14058__'
                88      LOAD_CONST                      4: 'Reactions'   # b'\x81\xd0\x1d\x120\xee\xb7\xdd\x15\xe9'
                90      CALL                            1
                98      KW_NAMES                        5: ('module',)
                100     CALL                            6
                108     STORE_FAST                      8: _var_var_21
                110     LOAD_FAST                       8: _var_var_21
                112     LOAD_CONST                      6: False
                114     COMPARE_OP                      40 (==)
                118     POP_JUMP_IF_FALSE               14 (to 148)
                120     LOAD_FAST                       0: account
                122     LOAD_CONST                      7: 'false'
                124     LOAD_CONST                      8: ('account', 'status')
                126     BUILD_CONST_KEY_MAP             2
                128     NOP                             
                130     NOP                             
                132     JUMP_FORWARD                    1776 (to 3688)
                136     CALL                            1
                144     POP_TOP                         
                146     RETURN_VALUE                    
                148     LOAD_FAST                       4: data
                150     LOAD_CONST                      10: 'Settings'
                152     BINARY_SUBSCR                   
                156     LOAD_ATTR                       7: get
                176     PUSH_NULL                       
                178     LOAD_CONST                      1: '__pyarmor_assert_14058__'
                180     LOAD_CONST                      11: 'all_reactions'   # b'\x81\xe3\x14\x1f\x0c\xe8\xbb\xd3\x18\xee\x04\xcfb\xff'
                182     CALL                            1
                190     CALL                            1
                198     STORE_FAST                      9: _var_var_22
                200     LOAD_GLOBAL                     9: NULL + int
                210     LOAD_FAST                       4: data
                212     LOAD_CONST                      10: 'Settings'
                214     BINARY_SUBSCR                   
                218     LOAD_ATTR                       7: get
                238     PUSH_NULL                       
                240     LOAD_CONST                      1: '__pyarmor_assert_14058__'
                242     LOAD_CONST                      12: 'kol_reaction_from'   # b'\x81\xe9\x17\x1f\x0c\xe8\xbb\xd3\x18\xee\x04\xcfb\xd3\xfe\x97\x00P'
                244     CALL                            1
                252     CALL                            1
                260     CALL                            1
                268     STORE_FAST                      10: _var_var_23
                270     LOAD_GLOBAL                     9: NULL + int
                280     LOAD_FAST                       4: data
                282     LOAD_CONST                      10: 'Settings'
                284     BINARY_SUBSCR                   
                288     LOAD_ATTR                       7: get
                308     PUSH_NULL                       
                310     LOAD_CONST                      1: '__pyarmor_assert_14058__'
                312     LOAD_CONST                      13: 'kol_reaction_to'   # b'\x81\xe9\x17\x1f\x0c\xe8\xbb\xd3\x18\xee\x04\xcfb\xd3\xec\x8a'
                314     CALL                            1
                322     CALL                            1
                330     CALL                            1
                338     STORE_FAST                      11: _var_var_24
                340     LOAD_GLOBAL                     9: NULL + int
                350     LOAD_FAST                       4: data
                352     LOAD_CONST                      10: 'Settings'
                354     BINARY_SUBSCR                   
                358     LOAD_ATTR                       7: get
                378     PUSH_NULL                       
                380     LOAD_CONST                      1: '__pyarmor_assert_14058__'
                382     LOAD_CONST                      14: 'reactions_wait_from'   # b'\x81\xf0\x1d\x120\xee\xb7\xdd\x15\xe92\xd7m\xe5\xec\xba\tO\xb4\xaa'
                384     CALL                            1
                392     CALL                            1
                400     CALL                            1
                408     STORE_FAST                      12: _var_var_25
                410     LOAD_GLOBAL                     9: NULL + int
                420     LOAD_FAST                       4: data
                422     LOAD_CONST                      10: 'Settings'
                424     BINARY_SUBSCR                   
                428     LOAD_ATTR                       7: get
                448     PUSH_NULL                       
                450     LOAD_CONST                      1: '__pyarmor_assert_14058__'
                452     LOAD_CONST                      15: 'reactions_wait_to'   # b'\x81\xf0\x1d\x120\xee\xb7\xdd\x15\xe92\xd7m\xe5\xec\xba\x1bR'
                454     CALL                            1
                462     CALL                            1
                470     CALL                            1
                478     STORE_FAST                      13: _var_var_26
                480     LOAD_GLOBAL                     9: NULL + int
                490     LOAD_FAST                       4: data
                492     LOAD_CONST                      10: 'Settings'
                494     BINARY_SUBSCR                   
                498     LOAD_ATTR                       7: get
                518     PUSH_NULL                       
                520     LOAD_CONST                      1: '__pyarmor_assert_14058__'
                522     LOAD_CONST                      16: 'wait_from'   # b"\x81\xf5\x19\x1a'\xc5\xb8\xc0\x14\xf7"
                524     CALL                            1
                532     CALL                            1
                540     CALL                            1
                548     STORE_FAST                      14: _var_var_27
                550     LOAD_GLOBAL                     9: NULL + int
                560     LOAD_FAST                       4: data
                562     LOAD_CONST                      10: 'Settings'
                564     BINARY_SUBSCR                   
                568     LOAD_ATTR                       7: get
                588     LOAD_CONST                      17: 'wait_to'
                590     CALL                            1
                598     CALL                            1
                606     STORE_FAST                      15: _var_var_28
                608     LOAD_GLOBAL                     9: NULL + int
                618     LOAD_FAST                       4: data
                620     LOAD_CONST                      10: 'Settings'
                622     BINARY_SUBSCR                   
                626     LOAD_ATTR                       7: get
                646     PUSH_NULL                       
                648     LOAD_CONST                      1: '__pyarmor_assert_14058__'
                650     LOAD_CONST                      18: 'max_flood_wait'   # b'\x81\xef\x19\x0b\x0c\xfc\xb2\xdd\x14\xfe2\xd7m\xe5\xec'
                652     CALL                            1
                660     CALL                            1
                668     CALL                            1
                676     STORE_FAST                      16: _var_var_29
                678     LOAD_FAST                       4: data
                680     LOAD_CONST                      10: 'Settings'
                682     BINARY_SUBSCR                   
                686     LOAD_ATTR                       7: get
                706     PUSH_NULL                       
                708     LOAD_CONST                      1: '__pyarmor_assert_14058__'
                710     LOAD_CONST                      19: 'reactions_random'   # b'\x81\xf0\x1d\x120\xee\xb7\xdd\x15\xe92\xd2m\xe2\xfc\x8a\x02'
                712     CALL                            1
                720     CALL                            1
                728     STORE_FAST                      17: _var_var_30
                730     LOAD_FAST                       4: data
                732     LOAD_CONST                      10: 'Settings'
                734     BINARY_SUBSCR                   
                738     LOAD_ATTR                       7: get
                758     PUSH_NULL                       
                760     LOAD_CONST                      1: '__pyarmor_assert_14058__'
                762     LOAD_CONST                      20: 'leave_chat'   # b'\x81\xee\x1d\x12%\xff\x81\xd1\x13\xfb\x19'
                764     CALL                            1
                772     CALL                            1
                780     STORE_FAST                      18: _var_var_31
                782     BUILD_LIST                      0
                784     STORE_FAST                      19: _var_var_32
                786     LOAD_FAST                       10: _var_var_23
                788     LOAD_FAST                       11: _var_var_24
                790     COMPARE_OP                      68 (>)
                794     POP_JUMP_IF_FALSE               2 (to 800)
                796     LOAD_FAST                       11: _var_var_24
                798     STORE_FAST                      10: _var_var_23
                800     LOAD_FAST                       12: _var_var_25
                802     LOAD_FAST                       13: _var_var_26
                804     COMPARE_OP                      68 (>)
                808     POP_JUMP_IF_FALSE               2 (to 814)
                810     LOAD_FAST                       12: _var_var_25
                812     STORE_FAST                      13: _var_var_26
                814     LOAD_FAST                       14: _var_var_27
                816     LOAD_FAST                       15: _var_var_28
                818     COMPARE_OP                      68 (>)
                822     POP_JUMP_IF_FALSE               2 (to 828)
                824     LOAD_FAST                       14: _var_var_27
                826     STORE_FAST                      15: _var_var_28
                828     LOAD_FAST                       6: stop_thread
                830     LOAD_ATTR                       11: is_set
                850     CALL                            0
                858     POP_JUMP_IF_FALSE               10 (to 880)
                860     LOAD_GLOBAL                     13: NULL + StopProgram
                870     CALL                            0
                878     RAISE_VARARGS                   1
                880     LOAD_FAST                       3: posts
                882     GET_ITER                        
                884     FOR_ITER                        595 (to 2078)
                890     STORE_FAST                      20: _var_var_33
                892     LOAD_FAST                       9: _var_var_22
                894     STORE_FAST                      21: _var_var_34
                896     LOAD_FAST                       17: _var_var_30
                898     POP_JUMP_IF_FALSE               21 (to 942)
                900     LOAD_GLOBAL                     15: NULL + random
                910     LOAD_ATTR                       16: shuffle
                930     LOAD_FAST                       21: _var_var_34
                932     CALL                            1
                940     POP_TOP                         
                942     LOAD_GLOBAL                     15: NULL + random
                952     LOAD_ATTR                       18: randint
                972     LOAD_FAST                       10: _var_var_23
                974     LOAD_FAST                       11: _var_var_24
                976     CALL                            2
                984     STORE_FAST                      22: _var_var_35
                986     LOAD_GLOBAL                     21: NULL + tg_links
                996     CALL                            0
                1004    LOAD_ATTR                       23: message_link_id_username
                1024    LOAD_FAST                       20: _var_var_33
                1026    CALL                            1
                1034    STORE_FAST                      23: _var_var_36
                1036    LOAD_CONST                      21: ''
                1038    STORE_FAST                      24: _var_var_37
                1040    LOAD_FAST                       23: _var_var_36
                1042    LOAD_CONST                      6: False
                1044    COMPARE_OP                      55 (!=)
                1048    POP_JUMP_IF_FALSE               481 (to 2014)
                1052    LOAD_GLOBAL                     25: NULL + DelayOnline
                1062    LOAD_FAST                       0: account
                1064    LOAD_FAST                       8: _var_var_21
                1066    LOAD_FAST                       14: _var_var_27
                1068    LOAD_FAST                       15: _var_var_28
                1070    LOAD_FAST                       6: stop_thread
                1072    CALL                            5
                1080    POP_TOP                         
                1082    LOAD_GLOBAL                     27: NULL + tg_search_group
                1092    LOAD_FAST                       1: config
                1094    LOAD_FAST                       8: _var_var_21
                1096    LOAD_FAST                       0: account
                1098    LOAD_FAST                       16: _var_var_29
                1100    LOAD_GLOBAL                     4: Lang
                1110    LOAD_FAST                       6: stop_thread
                1112    CALL                            6
                1120    LOAD_ATTR                       29: dialogs
                1140    LOAD_FAST                       23: _var_var_36
                1142    LOAD_CONST                      22: 'group_id'
                1144    BINARY_SUBSCR                   
                1148    LOAD_FAST                       23: _var_var_36
                1150    LOAD_CONST                      23: 'username'
                1152    BINARY_SUBSCR                   
                1156    LOAD_FAST                       23: _var_var_36
                1158    LOAD_CONST                      24: 'mess_id'
                1160    BINARY_SUBSCR                   
                1164    KW_NAMES                        25: ('uid', 'username', 'mess_id')
                1166    CALL                            3
                1174    STORE_FAST                      25: _var_var_38
                1176    LOAD_FAST                       25: _var_var_38
                1178    LOAD_CONST                      6: False
                1180    COMPARE_OP                      40 (==)
                1184    POP_JUMP_IF_FALSE               115 (to 1416)
                1186    LOAD_FAST                       23: _var_var_36
                1188    LOAD_CONST                      23: 'username'
                1190    BINARY_SUBSCR                   
                1194    LOAD_CONST                      0: None
                1196    COMPARE_OP                      55 (!=)
                1200    POP_JUMP_IF_FALSE               107 (to 1416)
                1202    LOAD_GLOBAL                     31: NULL + Logs
                1212    LOAD_ATTR                       32: PrintLog
                1232    LOAD_FAST                       1: config
                1234    LOAD_FAST                       0: account
                1236    PUSH_NULL                       
                1238    LOAD_CONST                      1: '__pyarmor_assert_14058__'
                1240    LOAD_CONST                      26: 'Аккаунт не в группе, пытаюсь вступить'   # b'\x81R\xe8\xa3\xe9Jdb\xcbK\xeep\xb1]\x1a\xc5\xbf\x80\x0br\xea{\x9c\x8c\xb5\xbc\x12\xbc\xb1R\xae:\x8a\x8d\x90\xd8\xd4\x8a\x04\xf1\xa9\x02I\xbfm\x08\xbe\xa9\x86\x0c\xe7\x17\xc7\xc0\xd4\\\xd6Zy\xac\xfb\xfb\xee\xe3\x8f\xf9\xe721'
                1242    CALL                            1
                1250    LOAD_FAST                       20: _var_var_33
                1252    KW_NAMES                        27: ('config', 'account', 'message', 'end')
                1254    CALL                            4
                1262    POP_TOP                         
                1264    LOAD_GLOBAL                     35: NULL + tg_group
                1274    LOAD_FAST                       1: config
                1276    LOAD_FAST                       8: _var_var_21
                1278    LOAD_FAST                       0: account
                1280    LOAD_FAST                       23: _var_var_36
                1282    LOAD_CONST                      23: 'username'
                1284    BINARY_SUBSCR                   
                1288    LOAD_FAST                       16: _var_var_29
                1290    LOAD_GLOBAL                     4: Lang
                1300    LOAD_FAST                       6: stop_thread
                1302    KW_NAMES                        28: ('config', 'client', 'account', 'group_link', 'max_flood_wait', 'lang', 'stop_thread')
                1304    CALL                            7
                1312    LOAD_ATTR                       37: go_to
                1332    CALL                            0
                1340    STORE_FAST                      25: _var_var_38
                1342    LOAD_FAST                       25: _var_var_38
                1344    PUSH_NULL                       
                1346    LOAD_CONST                      1: '__pyarmor_assert_14058__'
                1348    LOAD_CONST                      18: 'max_flood_wait'   # b'\x81\xef\x19\x0b\x0c\xfc\xb2\xdd\x14\xfe2\xd7m\xe5\xec'
                1350    CALL                            1
                1358    COMPARE_OP                      40 (==)
                1362    POP_JUMP_IF_FALSE               26 (to 1416)
                1364    LOAD_GLOBAL                     39: NULL + Disconnect
                1374    LOAD_FAST                       8: _var_var_21
                1376    CALL                            1
                1384    POP_TOP                         
                1386    LOAD_FAST                       0: account
                1388    LOAD_CONST                      6: False
                1390    BUILD_LIST                      2
                1392    SWAP                            2
                1394    POP_TOP                         
                1396    NOP                             
                1398    NOP                             
                1400    JUMP_FORWARD                    1142 (to 3688)
                1404    CALL                            1
                1412    POP_TOP                         
                1414    RETURN_VALUE                    
                1416    LOAD_FAST                       25: _var_var_38
                1418    LOAD_CONST                      0: None
                1420    COMPARE_OP                      55 (!=)
                1424    POP_JUMP_IF_FALSE               260 (to 1948)
                1428    LOAD_FAST                       19: _var_var_32
                1430    LOAD_ATTR                       41: append
                1450    LOAD_FAST                       25: _var_var_38
                1452    CALL                            1
                1460    POP_TOP                         
                1462    LOAD_GLOBAL                     43: NULL + range
                1472    LOAD_FAST                       22: _var_var_35
                1474    CALL                            1
                1482    GET_ITER                        
                1484    FOR_ITER                        227 (to 1940)
                1488    STORE_FAST                      26: _var_var_39
                1490    LOAD_FAST                       6: stop_thread
                1492    LOAD_ATTR                       11: is_set
                1512    CALL                            0
                1520    POP_JUMP_IF_FALSE               10 (to 1542)
                1522    LOAD_GLOBAL                     13: NULL + StopProgram
                1532    CALL                            0
                1540    RAISE_VARARGS                   1
                1542    LOAD_GLOBAL                     45: NULL + get_emoticon
                1552    LOAD_FAST                       21: _var_var_34
                1554    LOAD_FAST                       26: _var_var_39
                1556    BINARY_SUBSCR                   
                1560    CALL                            1
                1568    STORE_FAST                      27: _var_var_40
                1570    NOP                             
                1572    PUSH_NULL                       
                1574    LOAD_FAST                       8: _var_var_21
                1576    LOAD_GLOBAL                     46: functions
                1586    LOAD_ATTR                       48: messages
                1606    LOAD_ATTR                       51: SendReactionRequest
                1626    LOAD_FAST                       25: _var_var_38
                1628    LOAD_FAST                       23: _var_var_36
                1630    LOAD_CONST                      24: 'mess_id'
                1632    BINARY_SUBSCR                   
                1636    LOAD_CONST                      6: False
                1638    LOAD_CONST                      29: True
                1640    LOAD_GLOBAL                     53: NULL + types
                1650    LOAD_ATTR                       54: ReactionEmoji
                1670    LOAD_FAST                       27: _var_var_40
                1672    KW_NAMES                        30: ('emoticon',)
                1674    CALL                            1
                1682    BUILD_LIST                      1
                1684    KW_NAMES                        31: ('peer', 'msg_id', 'big', 'add_to_recent', 'reaction')
                1686    CALL                            5
                1694    CALL                            1
                1702    POP_TOP                         
                1704    NOP                             
                1706    PUSH_NULL                       
                1708    LOAD_FAST                       8: _var_var_21
                1710    LOAD_GLOBAL                     46: functions
                1720    LOAD_ATTR                       48: messages
                1740    LOAD_ATTR                       57: GetMessagesViewsRequest
                1760    LOAD_FAST                       25: _var_var_38
                1762    LOAD_FAST                       23: _var_var_36
                1764    LOAD_CONST                      24: 'mess_id'
                1766    BINARY_SUBSCR                   
                1770    BUILD_LIST                      1
                1772    LOAD_CONST                      29: True
                1774    KW_NAMES                        32: ('peer', 'id', 'increment')
                1776    CALL                            3
                1784    CALL                            1
                1792    STORE_FAST                      28: _var_var_41
                1794    LOAD_CONST                      33: 'Done'
                1796    STORE_FAST                      24: _var_var_37
                1798    LOAD_GLOBAL                     31: NULL + Logs
                1808    LOAD_ATTR                       32: PrintLog
                1828    LOAD_FAST                       1: config
                1830    LOAD_FAST                       0: account
                1832    LOAD_FAST                       20: _var_var_33
                1834    LOAD_FAST                       27: _var_var_40
                1836    LOAD_FAST                       24: _var_var_37
                1838    KW_NAMES                        45: ('config', 'account', 'message', 'param', 'end')
                1840    CALL                            5
                1848    POP_TOP                         
                1850    LOAD_GLOBAL                     67: NULL + db_reactions
                1860    LOAD_FAST                       5: db_result
                1862    CALL                            1
                1870    LOAD_ATTR                       69: insert
                1890    LOAD_FAST                       0: account
                1892    LOAD_FAST                       20: _var_var_33
                1894    LOAD_FAST                       27: _var_var_40
                1896    LOAD_FAST                       24: _var_var_37
                1898    KW_NAMES                        44: ('status',)
                1900    CALL                            4
                1908    POP_TOP                         
                1910    LOAD_GLOBAL                     25: NULL + DelayOnline
                1920    LOAD_FAST                       0: account
                1922    LOAD_FAST                       8: _var_var_21
                1924    LOAD_FAST                       12: _var_var_25
                1926    LOAD_FAST                       13: _var_var_26
                1928    LOAD_FAST                       6: stop_thread
                1930    CALL                            5
                1938    POP_TOP                         
                1940    JUMP_BACKWARD                   229 (to 1484)
                1942    END_FOR                         
                1944    JUMP_BACKWARD                   532 (to 884)
                1948    LOAD_GLOBAL                     31: NULL + Logs
                1958    LOAD_ATTR                       32: PrintLog
                1978    LOAD_FAST                       1: config
                1980    LOAD_FAST                       0: account
                1982    PUSH_NULL                       
                1984    LOAD_CONST                      1: '__pyarmor_assert_14058__'
                1986    LOAD_CONST                      47: 'Не могу найти группу\\канал, если группа\\канал приватный, вступите в него предварительно'   # b'\x81R\xe5\xa3\xe6\xba\x0e\x0e\xab$\xbd\x13\xdd\x0f\xb85\xd2\xedk\x17sz\xac|\xdd/\x13\x8f\xb1Q\xaf\x06\x8a\x8d\x90\xd2))\x88\x9e\xc2Y(\xed\x00h\xdf\xf7\xec\xa1\x16KR\xc1\xe7]\xec[C]\xa8\x98\x80\xb3\xe6\xab\xb5\\m\xe8\\o\xaf\xd2\xe6\x8e\x90\t\xd5!q7_\xe9\x0f\xd0\xb3\xa1to=>/\xa1hQT\x8d\x0c\x98\x8b\xd1h|\xff\xcd\tc\xfc\x05L\xd8\x02\xe5\x02\xc0\xc9\x16\xe5\xde3\xfc\xb86I\x9f\x0f8[|\xa2~G\x06\xce=\xd1\xe5\xc1In\x8c\x8e\x08\xa8\x01\x06l\xbd\xe6+\xd0(Bv\xba\r\x7f!gI'
                1988    CALL                            1
                1996    LOAD_FAST                       20: _var_var_33
                1998    KW_NAMES                        27: ('config', 'account', 'message', 'end')
                2000    CALL                            4
                2008    POP_TOP                         
                2010    JUMP_BACKWARD                   565 (to 884)
                2014    LOAD_GLOBAL                     31: NULL + Logs
                2024    LOAD_ATTR                       32: PrintLog
                2044    LOAD_FAST                       1: config
                2046    LOAD_FAST                       0: account
                2048    PUSH_NULL                       
                2050    LOAD_CONST                      1: '__pyarmor_assert_14058__'
                2052    LOAD_CONST                      48: 'Данная ссылка не является постом или формат неверен'   # b'\x81R\xec\xa3\xe3Jcb\xc6J\xddq\x83\xacId\xbe\xbc\nL\x1a\x10\xfe\x16\xb5\xbf\xe3\xec\xdd\x01\xcb\xa5\x8b\xbd\x90\xdf(\x11\x05\xc1\xa8<I\xbfl9\xbe\xa8w]\x89KY\xc1\xe7\\\xd5[E\xad\xc4\x0b\x81\x8b\xe7\x93\xb5[\x9d\x86\x08\x0fM\xd3\xdc\x8e\x9c\t\xd8 C\xc74t\x0f\xda\xb2\x93tb<\x0c/\xa4in'
                2054    CALL                            1
                2062    LOAD_FAST                       20: _var_var_33
                2064    KW_NAMES                        27: ('config', 'account', 'message', 'end')
                2066    CALL                            4
                2074    POP_TOP                         
                2076    JUMP_BACKWARD                   598 (to 884)
                2080    END_FOR                         
                2082    LOAD_FAST                       18: _var_var_31
                2084    POP_JUMP_IF_FALSE               98 (to 2282)
                2086    LOAD_GLOBAL                     31: NULL + Logs
                2096    LOAD_ATTR                       32: PrintLog
                2116    LOAD_FAST                       1: config
                2118    LOAD_FAST                       0: account
                2120    LOAD_GLOBAL                     4: Lang
                2130    PUSH_NULL                       
                2132    LOAD_CONST                      1: '__pyarmor_assert_14058__'
                2134    LOAD_CONST                      49: 'exit_groups_on_activated'   # b"\x81\xe7\x00\x1a'\xc5\xb9\xc0\x14\xef\x1d\xd3S\xe3\xf6\xba\x0e^\xaf\xae\xbc\xcaZ\xc9\x01"
                2136    CALL                            1
                2144    BINARY_SUBSCR                   
                2148    KW_NAMES                        38: ('config', 'account', 'message')
                2150    CALL                            3
                2158    POP_TOP                         
                2160    LOAD_GLOBAL                     31: NULL + Logs
                2170    LOAD_ATTR                       32: PrintLog
                2190    LOAD_FAST                       1: config
                2192    LOAD_FAST                       0: account
                2194    LOAD_GLOBAL                     4: Lang
                2204    PUSH_NULL                       
                2206    LOAD_CONST                      1: '__pyarmor_assert_14058__'
                2208    LOAD_CONST                      50: 'leaving_group'   # b'\x81\xee\x1d\x12%\xf3\xb0\xd5$\xfd\x1f\xcfy\xfc'
                2210    CALL                            1
                2218    BINARY_SUBSCR                   
                2222    KW_NAMES                        38: ('config', 'account', 'message')
                2224    CALL                            3
                2232    POP_TOP                         
                2234    LOAD_FAST                       19: _var_var_32
                2236    GET_ITER                        
                2238    FOR_ITER                        19 (to 2278)
                2242    STORE_FAST                      25: _var_var_38
                2244    LOAD_FAST                       8: _var_var_21
                2246    LOAD_ATTR                       71: delete_dialog
                2266    LOAD_FAST                       25: _var_var_38
                2268    CALL                            1
                2276    POP_TOP                         
                2278    JUMP_BACKWARD                   21 (to 2238)
                2280    END_FOR                         
                2282    LOAD_GLOBAL                     39: NULL + Disconnect
                2292    LOAD_FAST                       8: _var_var_21
                2294    CALL                            1
                2302    POP_TOP                         
                2304    LOAD_CONST                      0: None
                2306    NOP                             
                2308    NOP                             
                2310    JUMP_FORWARD                    687 (to 3688)
                2320    POP_TOP                         
                2322    RETURN_CONST                    0: None
                2324    PUSH_EXC_INFO                   
                2326    POP_TOP                         
                2328    POP_EXCEPT                      
                2330    JUMP_BACKWARD                   474 (to 1386)
                2334    COPY                            3
                2336    POP_EXCEPT                      
                2338    RERAISE                         1
                2340    PUSH_EXC_INFO                   
                2342    POP_TOP                         
                2344    POP_EXCEPT                      
                2346    JUMP_BACKWARD                   278 (to 1794)
                2350    COPY                            3
                2352    POP_EXCEPT                      
                2354    RERAISE                         1
                2356    PUSH_EXC_INFO                   
                2358    LOAD_GLOBAL                     58: Exception
                2368    CHECK_EXC_MATCH                 
                2370    POP_JUMP_IF_FALSE               446 (to 3266)
                2374    STORE_FAST                      29: _var_var_20
                2376    LOAD_GLOBAL                     61: NULL + type
                2386    LOAD_FAST                       29: _var_var_20
                2388    CALL                            1
                2396    LOAD_ATTR                       62: __name__
                2416    STORE_FAST                      24: _var_var_37
                2418    LOAD_GLOBAL                     31: NULL + Logs
                2428    LOAD_ATTR                       32: PrintLog
                2448    LOAD_FAST                       1: config
                2450    LOAD_FAST                       0: account
                2452    LOAD_CONST                      34: 'Status:'
                2454    LOAD_FAST                       24: _var_var_37
                2456    KW_NAMES                        35: ('config', 'account', 'message', 'param')
                2458    CALL                            4
                2466    POP_TOP                         
                2468    LOAD_FAST                       24: _var_var_37
                2470    PUSH_NULL                       
                2472    LOAD_CONST                      1: '__pyarmor_assert_14058__'
                2474    LOAD_CONST                      36: 'FloodWaitError'   # b'\x81\xc4\x14\x1c<\xfe\x89\xd3\x12\xee(\xd2~\xe3\xea'
                2476    CALL                            1
                2484    COMPARE_OP                      40 (==)
                2488    POP_JUMP_IF_FALSE               377 (to 3246)
                2492    LOAD_FAST                       29: _var_var_20
                2494    LOAD_ATTR                       64: seconds
                2514    STORE_FAST                      30: _var_var_42
                2516    LOAD_GLOBAL                     31: NULL + Logs
                2526    LOAD_ATTR                       32: PrintLog
                2546    LOAD_FAST                       1: config
                2548    LOAD_FAST                       0: account
                2550    LOAD_GLOBAL                     4: Lang
                2560    PUSH_NULL                       
                2562    LOAD_CONST                      1: '__pyarmor_assert_14058__'
                2564    LOAD_CONST                      37: 'restriction_detected'   # b"\x81\xf0\x1d\x00'\xe8\xb7\xd1\x0f\xf3\x02\xceS\xe8\xfd\x91\n^\xaf\xa2\xae"
                2566    CALL                            1
                2574    BINARY_SUBSCR                   
                2578    KW_NAMES                        38: ('config', 'account', 'message')
                2580    CALL                            3
                2588    POP_TOP                         
                2590    LOAD_GLOBAL                     31: NULL + Logs
                2600    LOAD_ATTR                       32: PrintLog
                2620    LOAD_FAST                       1: config
                2622    LOAD_FAST                       0: account
                2624    LOAD_GLOBAL                     4: Lang
                2634    PUSH_NULL                       
                2636    LOAD_CONST                      1: '__pyarmor_assert_14058__'
                2638    LOAD_CONST                      39: 'algorithm_running'   # b'\x81\xe3\x14\x14<\xe8\xb7\xc6\x13\xf72\xd2y\xe2\xf6\x8c\x01Z'
                2640    CALL                            1
                2648    BINARY_SUBSCR                   
                2652    KW_NAMES                        38: ('config', 'account', 'message')
                2654    CALL                            3
                2662    POP_TOP                         
                2664    LOAD_FAST                       30: _var_var_42
                2666    LOAD_GLOBAL                     15: NULL + random
                2676    LOAD_ATTR                       18: randint
                2696    LOAD_CONST                      40: 10
                2698    LOAD_CONST                      41: 20
                2700    CALL                            2
                2708    BINARY_OP                       0 (+)
                2712    STORE_FAST                      31: _var_var_43
                2714    LOAD_FAST                       30: _var_var_42
                2716    LOAD_FAST                       16: _var_var_29
                2718    COMPARE_OP                      68 (>)
                2722    POP_JUMP_IF_FALSE               208 (to 3140)
                2724    LOAD_GLOBAL                     31: NULL + Logs
                2734    LOAD_ATTR                       32: PrintLog
                2754    LOAD_FAST                       1: config
                2756    LOAD_FAST                       0: account
                2758    LOAD_GLOBAL                     4: Lang
                2768    PUSH_NULL                       
                2770    LOAD_CONST                      1: '__pyarmor_assert_14058__'
                2772    LOAD_CONST                      42: 'flood_wait_more'   # b'\x81\xe4\x14\x1c<\xfe\x81\xc5\x1a\xf3\x19\xffa\xe3\xea\x80'
                2774    CALL                            1
                2782    BINARY_SUBSCR                   
                2786    LOAD_FAST                       16: _var_var_29
                2788    KW_NAMES                        35: ('config', 'account', 'message', 'param')
                2790    CALL                            4
                2798    POP_TOP                         
                2800    LOAD_GLOBAL                     31: NULL + Logs
                2810    LOAD_ATTR                       32: PrintLog
                2830    LOAD_FAST                       1: config
                2832    LOAD_FAST                       0: account
                2834    LOAD_GLOBAL                     4: Lang
                2844    PUSH_NULL                       
                2846    LOAD_CONST                      1: '__pyarmor_assert_14058__'
                2848    LOAD_CONST                      43: 'work_stopped'   # b'\x81\xf5\x17\x018\xc5\xad\xc6\x14\xea\x1d\xc5h'
                2850    CALL                            1
                2858    BINARY_SUBSCR                   
                2862    KW_NAMES                        38: ('config', 'account', 'message')
                2864    CALL                            3
                2872    POP_TOP                         
                2874    LOAD_GLOBAL                     67: NULL + db_reactions
                2884    LOAD_FAST                       5: db_result
                2886    CALL                            1
                2894    LOAD_ATTR                       69: insert
                2914    LOAD_FAST                       0: account
                2916    LOAD_FAST                       20: _var_var_33
                2918    LOAD_FAST                       27: _var_var_40
                2920    LOAD_FAST                       24: _var_var_37
                2922    KW_NAMES                        44: ('status',)
                2924    CALL                            4
                2932    POP_TOP                         
                2934    LOAD_GLOBAL                     39: NULL + Disconnect
                2944    LOAD_FAST                       8: _var_var_21
                2946    CALL                            1
                2954    POP_TOP                         
                2956    JUMP_FORWARD                    7 (to 2972)
                2958    PUSH_EXC_INFO                   
                2960    POP_TOP                         
                2962    POP_EXCEPT                      
                2964    JUMP_FORWARD                    3 (to 2972)
                2966    COPY                            3
                2968    POP_EXCEPT                      
                2970    RERAISE                         1
                2972    LOAD_FAST                       0: account
                2974    PUSH_NULL                       
                2976    LOAD_CONST                      1: '__pyarmor_assert_14058__'
                2978    LOAD_CONST                      36: 'FloodWaitError'   # b'\x81\xc4\x14\x1c<\xfe\x89\xd3\x12\xee(\xd2~\xe3\xea'
                2980    CALL                            1
                2988    BUILD_LIST                      2
                2990    SWAP                            2
                2992    POP_EXCEPT                      
                2994    LOAD_CONST                      0: None
                2996    STORE_FAST                      29: _var_var_20
                2998    DELETE_FAST                     29: _var_var_20
                3000    LOAD_GLOBAL                     31: NULL + Logs
                3010    LOAD_ATTR                       32: PrintLog
                3030    LOAD_FAST                       1: config
                3032    LOAD_FAST                       0: account
                3034    LOAD_FAST                       20: _var_var_33
                3036    LOAD_FAST                       27: _var_var_40
                3038    LOAD_FAST                       24: _var_var_37
                3040    KW_NAMES                        45: ('config', 'account', 'message', 'param', 'end')
                3042    CALL                            5
                3050    POP_TOP                         
                3052    LOAD_GLOBAL                     67: NULL + db_reactions
                3062    LOAD_FAST                       5: db_result
                3064    CALL                            1
                3072    LOAD_ATTR                       69: insert
                3092    LOAD_FAST                       0: account
                3094    LOAD_FAST                       20: _var_var_33
                3096    LOAD_FAST                       27: _var_var_40
                3098    LOAD_FAST                       24: _var_var_37
                3100    KW_NAMES                        44: ('status',)
                3102    CALL                            4
                3110    POP_TOP                         
                3112    SWAP                            2
                3114    POP_TOP                         
                3116    SWAP                            2
                3118    POP_TOP                         
                3120    NOP                             
                3122    NOP                             
                3124    JUMP_FORWARD                    280 (to 3688)
                3128    CALL                            1
                3136    POP_TOP                         
                3138    RETURN_VALUE                    
                3140    LOAD_GLOBAL                     31: NULL + Logs
                3150    LOAD_ATTR                       32: PrintLog
                3170    LOAD_FAST                       1: config
                3172    LOAD_FAST                       0: account
                3174    LOAD_GLOBAL                     4: Lang
                3184    PUSH_NULL                       
                3186    LOAD_CONST                      1: '__pyarmor_assert_14058__'
                3188    LOAD_CONST                      46: 'flood_wait_bypass'   # b'\x81\xe4\x14\x1c<\xfe\x81\xc5\x1a\xf3\x19\xffn\xf5\xe8\x84\x1cN'
                3190    CALL                            1
                3198    BINARY_SUBSCR                   
                3202    LOAD_FAST                       31: _var_var_43
                3204    KW_NAMES                        35: ('config', 'account', 'message', 'param')
                3206    CALL                            4
                3214    POP_TOP                         
                3216    LOAD_GLOBAL                     25: NULL + DelayOnline
                3226    LOAD_FAST                       0: account
                3228    LOAD_FAST                       8: _var_var_21
                3230    LOAD_FAST                       31: _var_var_43
                3232    LOAD_FAST                       31: _var_var_43
                3234    LOAD_FAST                       6: stop_thread
                3236    CALL                            5
                3244    POP_TOP                         
                3246    POP_EXCEPT                      
                3248    LOAD_CONST                      0: None
                3250    STORE_FAST                      29: _var_var_20
                3252    DELETE_FAST                     29: _var_var_20
                3254    JUMP_BACKWARD                   730 (to 1798)
                3258    LOAD_CONST                      0: None
                3260    STORE_FAST                      29: _var_var_20
                3262    DELETE_FAST                     29: _var_var_20
                3264    RERAISE                         1
                3266    RERAISE                         0
                3268    COPY                            3
                3270    POP_EXCEPT                      
                3272    RERAISE                         1
                3274    PUSH_EXC_INFO                   
                3276    LOAD_GLOBAL                     31: NULL + Logs
                3286    LOAD_ATTR                       32: PrintLog
                3306    LOAD_FAST                       1: config
                3308    LOAD_FAST                       0: account
                3310    LOAD_FAST                       20: _var_var_33
                3312    LOAD_FAST                       27: _var_var_40
                3314    LOAD_FAST                       24: _var_var_37
                3316    KW_NAMES                        45: ('config', 'account', 'message', 'param', 'end')
                3318    CALL                            5
                3326    POP_TOP                         
                3328    LOAD_GLOBAL                     67: NULL + db_reactions
                3338    LOAD_FAST                       5: db_result
                3340    CALL                            1
                3348    LOAD_ATTR                       69: insert
                3368    LOAD_FAST                       0: account
                3370    LOAD_FAST                       20: _var_var_33
                3372    LOAD_FAST                       27: _var_var_40
                3374    LOAD_FAST                       24: _var_var_37
                3376    KW_NAMES                        44: ('status',)
                3378    CALL                            4
                3386    POP_TOP                         
                3388    RERAISE                         0
                3390    COPY                            3
                3392    POP_EXCEPT                      
                3394    RERAISE                         1
                3396    PUSH_EXC_INFO                   
                3398    POP_TOP                         
                3400    POP_EXCEPT                      
                3402    JUMP_BACKWARD                   584 (to 2238)
                3406    COPY                            3
                3408    POP_EXCEPT                      
                3410    RERAISE                         1
                3412    PUSH_EXC_INFO                   
                3414    POP_TOP                         
                3416    POP_EXCEPT                      
                3418    JUMP_BACKWARD                   559 (to 2304)
                3422    COPY                            3
                3424    POP_EXCEPT                      
                3426    RERAISE                         1
                3428    PUSH_EXC_INFO                   
                3430    LOAD_GLOBAL                     12: StopProgram
                3440    CHECK_EXC_MATCH                 
                3442    POP_JUMP_IF_FALSE               35 (to 3514)
                3444    POP_TOP                         
                3446    LOAD_GLOBAL                     39: NULL + Disconnect
                3456    LOAD_FAST_CHECK                 8: _var_var_21
                3458    CALL                            1
                3466    POP_TOP                         
                3468    JUMP_FORWARD                    7 (to 3484)
                3470    PUSH_EXC_INFO                   
                3472    POP_TOP                         
                3474    POP_EXCEPT                      
                3476    JUMP_FORWARD                    3 (to 3484)
                3478    COPY                            3
                3480    POP_EXCEPT                      
                3482    RERAISE                         1
                3484    LOAD_FAST                       0: account
                3486    LOAD_CONST                      51: 'STOP'
                3488    BUILD_LIST                      2
                3490    SWAP                            2
                3492    POP_EXCEPT                      
                3494    NOP                             
                3496    NOP                             
                3498    NOP                             
                3500    JUMP_FORWARD                    93 (to 3688)
                3502    CALL                            1
                3510    POP_TOP                         
                3512    RETURN_VALUE                    
                3514    LOAD_GLOBAL                     58: Exception
                3524    CHECK_EXC_MATCH                 
                3526    POP_JUMP_IF_FALSE               62 (to 3652)
                3528    STORE_FAST                      29: _var_var_20
                3530    LOAD_GLOBAL                     39: NULL + Disconnect
                3540    LOAD_FAST_CHECK                 8: _var_var_21
                3542    CALL                            1
                3550    POP_TOP                         
                3552    JUMP_FORWARD                    7 (to 3568)
                3554    PUSH_EXC_INFO                   
                3556    POP_TOP                         
                3558    POP_EXCEPT                      
                3560    JUMP_FORWARD                    3 (to 3568)
                3562    COPY                            3
                3564    POP_EXCEPT                      
                3566    RERAISE                         1
                3568    LOAD_GLOBAL                     73: NULL + print
                3578    LOAD_CONST                      52: 'worker: '
                3580    LOAD_FAST                       29: _var_var_20
                3582    FORMAT_VALUE                    0 (FVC_NONE)
                3584    BUILD_STRING                    2
                3586    CALL                            1
                3594    POP_TOP                         
                3596    LOAD_FAST                       0: account
                3598    PUSH_NULL                       
                3600    LOAD_CONST                      1: '__pyarmor_assert_14058__'
                3602    LOAD_CONST                      53: 'EXCEPTION'   # b'\x81\xc7 0\x16\xca\x8a\xfb4\xd4'
                3604    CALL                            1
                3612    BUILD_LIST                      2
                3614    SWAP                            2
                3616    POP_EXCEPT                      
                3618    LOAD_CONST                      0: None
                3620    STORE_FAST                      29: _var_var_20
                3622    DELETE_FAST                     29: _var_var_20
                3624    NOP                             
                3626    NOP                             
                3628    NOP                             
                3630    JUMP_FORWARD                    28 (to 3688)
                3632    CALL                            1
                3640    POP_TOP                         
                3642    RETURN_VALUE                    
                3644    LOAD_CONST                      0: None
                3646    STORE_FAST                      29: _var_var_20
                3648    DELETE_FAST                     29: _var_var_20
                3650    RERAISE                         1
                3652    RERAISE                         0
                3654    COPY                            3
                3656    POP_EXCEPT                      
                3658    RERAISE                         1
                3660    PUSH_EXC_INFO                   
                3662    PUSH_NULL                       
                3664    LOAD_CONST                      9: '__pyarmor_exit_14060__'
                3666    NOP                             
                3668    LOAD_CONST                      3: b'<COAddr>\x05\x00\x00\x1a2\x0e\x00\x00\x00\x00\x00\x00\x00\x00\x00\x00\x00\x00\x00\x00'
                3670    CALL                            1
                3678    POP_TOP                         
                3680    RERAISE                         0
                3682    COPY                            3
                3684    POP_EXCEPT                      
                3686    RERAISE                         1
                3688    PUSH_NULL                       
                3690    LOAD_CONST                      9: '__pyarmor_exit_14060__'
                3692    LOAD_CONST                      3: b'<COAddr>\x05\x00\x00\x1a2\x0e\x00\x00\x00\x00\x00\x00\x00\x00\x00\x00\x00\x00\x00\x00'
                3694    BUILD_TUPLE                     1
                3696    CALL_FUNCTION_EX                0
                3698    POP_TOP                         
                3700    RETURN_VALUE                    
            [Exception Table]
                30 to 128 -> 3428 [0] 
                148 to 1364 -> 3428 [0] 
                1364 to 1386 -> 2324 [1] 
                1386 to 1396 -> 3428 [0] 
                1416 to 1570 -> 3428 [0] 
                1572 to 1704 -> 2356 [2] 
                1706 to 1794 -> 2340 [2] 
                1794 to 1798 -> 2356 [2] 
                1798 to 2244 -> 3428 [0] 
                2244 to 2278 -> 3396 [1] 
                2278 to 2282 -> 3428 [0] 
                2282 to 2304 -> 3412 [0] 
                2324 to 2328 -> 2334 [2] lasti
                2328 to 2340 -> 3428 [0] 
                2340 to 2344 -> 2350 [3] lasti
                2344 to 2356 -> 2356 [2] 
                2356 to 2376 -> 3268 [3] lasti
                2376 to 2934 -> 3258 [3] lasti
                2934 to 2956 -> 2958 [3] 
                2956 to 2958 -> 3258 [3] lasti
                2958 to 2962 -> 2966 [4] lasti
                2962 to 2990 -> 3258 [3] lasti
                2990 to 2992 -> 3268 [3] lasti
                2992 to 3000 -> 3274 [2] 
                3000 to 3120 -> 3428 [0] 
                3140 to 3246 -> 3258 [3] lasti
                3246 to 3258 -> 3274 [2] 
                3258 to 3268 -> 3268 [3] lasti
                3268 to 3274 -> 3274 [2] 
                3274 to 3390 -> 3390 [3] lasti
                3390 to 3396 -> 3428 [0] 
                3396 to 3400 -> 3406 [2] lasti
                3400 to 3412 -> 3428 [0] 
                3412 to 3416 -> 3422 [1] lasti
                3416 to 3428 -> 3428 [0] 
                3428 to 3446 -> 3654 [1] lasti
                3446 to 3468 -> 3470 [1] 
                3468 to 3470 -> 3654 [1] lasti
                3470 to 3474 -> 3478 [2] lasti
                3474 to 3492 -> 3654 [1] lasti
                3492 to 3494 -> 3660 [0] 
                3514 to 3530 -> 3654 [1] lasti
                3530 to 3552 -> 3554 [1] 
                3552 to 3554 -> 3644 [1] lasti
                3554 to 3558 -> 3562 [2] lasti
                3558 to 3614 -> 3644 [1] lasti
                3614 to 3616 -> 3654 [1] lasti
                3616 to 3624 -> 3660 [0] 
                3644 to 3654 -> 3654 [1] lasti
                3654 to 3660 -> 3660 [0] 
                3660 to 3682 -> 3682 [1] lasti
        [Code]
            File Name: <frozen program.modules.Reactions>
            Object Name: tg_search_group
            Qualified Name: tg_search_group
            Arg Count: 0
            Pos Only Arg Count: 0
            KW Only Arg Count: 0
            Stack Size: 6
            Flags: 0x20000000 (CO_PYARMOR_OBFUSCATED)
            [Names]
                '__name__'
                '__module__'
                '__qualname__'
                '__doc__'
                '__assert_armored__'
                '__init__'
                'int'
                'str'
                'dialogs'
            [Locals+Names]
            [Constants]
                'tg_search_group'
                ' Поиск группы внутри диалогов для получения entity '
                '__pyarmor_assert_14061__'
                '__pyarmor_enter_14062__'
                b'<COAddr>\x07\x00\x00&2\x00\x00\x00\x00\x00\x00\x00\x00\x00\x00\x00\x00\x00\x00\x00'
                None
                [Code]
                    File Name: <frozen program.modules.Reactions>
                    Object Name: __init__
                    Qualified Name: tg_search_group.__init__
                    Arg Count: 7
                    Pos Only Arg Count: 0
                    KW Only Arg Count: 0
                    Stack Size: 5
                    Flags: 0x20000003 (CO_OPTIMIZED | CO_NEWLOCALS | CO_PYARMOR_OBFUSCATED)
                    [Names]
                        '_config'
                        '_client'
                        '_account'
                        '_max_flood_wait'
                        '_lang'
                        '_stop_thread'
                    [Locals+Names]
                        'self'
                        'config'
                        'client'
                        'account'
                        'max_flood_wait'
                        'lang'
                        'stop_thread'
                        '__assert_armored__'
                    [Constants]
                        None
                        '__pyarmor_assert_14064__'
                        '__pyarmor_enter_14065__'
                        b'<COAddr>\x07\x00\x00\x1aj\x00\x00\x00\x00\x00\x00\x00\x00\x00\x00\x00\x00\x00\x00\x00'
                        '__pyarmor_exit_14066__'
                    [Disassembly]
                        0       NOP                             
                        2       NOP                             
                        4       PUSH_NULL                       
                        6       LOAD_CONST                      2: '__pyarmor_enter_14065__'
                        8       LOAD_CONST                      3: b'<COAddr>\x07\x00\x00\x1aj\x00\x00\x00\x00\x00\x00\x00\x00\x00\x00\x00\x00\x00\x00\x00'
                        10      BUILD_TUPLE                     1
                        12      CALL_FUNCTION_EX                0
                        14      POP_TOP                         
                        16      RESUME                          0
                        18      NOP                             
                        20      NOP                             
                        22      NOP                             
                        24      NOP                             
                        26      NOP                             
                        28      LOAD_FAST                       1: config
                        30      LOAD_FAST                       0: self
                        32      STORE_ATTR                      0: _config
                        42      LOAD_FAST                       2: client
                        44      LOAD_FAST                       0: self
                        46      STORE_ATTR                      1: _client
                        56      LOAD_FAST                       3: account
                        58      LOAD_FAST                       0: self
                        60      STORE_ATTR                      2: _account
                        70      LOAD_FAST                       4: max_flood_wait
                        72      LOAD_FAST                       0: self
                        74      STORE_ATTR                      3: _max_flood_wait
                        84      LOAD_FAST                       5: lang
                        86      LOAD_FAST                       0: self
                        88      STORE_ATTR                      4: _lang
                        98      LOAD_FAST                       6: stop_thread
                        100     LOAD_FAST                       0: self
                        102     STORE_ATTR                      5: _stop_thread
                        112     LOAD_CONST                      0: None
                        114     NOP                             
                        116     NOP                             
                        118     NOP                             
                        120     JUMP_FORWARD                    19 (to 160)
                        128     POP_TOP                         
                        130     RETURN_CONST                    0: None
                        132     PUSH_EXC_INFO                   
                        134     PUSH_NULL                       
                        136     LOAD_CONST                      4: '__pyarmor_exit_14066__'
                        138     NOP                             
                        140     LOAD_CONST                      3: b'<COAddr>\x07\x00\x00\x1aj\x00\x00\x00\x00\x00\x00\x00\x00\x00\x00\x00\x00\x00\x00\x00'
                        142     CALL                            1
                        150     POP_TOP                         
                        152     RERAISE                         0
                        154     COPY                            3
                        156     POP_EXCEPT                      
                        158     RERAISE                         1
                        160     PUSH_NULL                       
                        162     LOAD_CONST                      4: '__pyarmor_exit_14066__'
                        164     LOAD_CONST                      3: b'<COAddr>\x07\x00\x00\x1aj\x00\x00\x00\x00\x00\x00\x00\x00\x00\x00\x00\x00\x00\x00\x00'
                        166     BUILD_TUPLE                     1
                        168     CALL_FUNCTION_EX                0
                        170     POP_TOP                         
                        172     RETURN_VALUE                    
                    [Exception Table]
                        28 to 112 -> 132 [0] 
                        132 to 154 -> 154 [1] lasti
                'uid'
                'username'
                'mess_id'
                [Code]
                    File Name: <frozen program.modules.Reactions>
                    Object Name: dialogs
                    Qualified Name: tg_search_group.dialogs
                    Arg Count: 4
                    Pos Only Arg Count: 0
                    KW Only Arg Count: 0
                    Stack Size: 7
                    Flags: 0x20000003 (CO_OPTIMIZED | CO_NEWLOCALS | CO_PYARMOR_OBFUSCATED)
                    [Names]
                        '_client'
                        'iter_dialogs'
                        'hasattr'
                        'entity'
                        'username'
                        'id'
                        'StopProgram'
                        'Exception'
                        'print'
                        'type'
                        '__name__'
                    [Locals+Names]
                        'self'
                        'uid'
                        'username'
                        'mess_id'
                        '__assert_armored__'
                        '_var_var_44'
                        '_var_var_45'
                        '_var_var_20'
                    [Constants]
                        ' Поиск группы в диалогах '
                        '__pyarmor_assert_14067__'
                        '__pyarmor_enter_14068__'
                        b'<COAddr>\x05\x00\x00\x1a,\x02\x00\x00\x00\x00\x00\x00\x00\x00\x00\x00\x00\x00\x00\x00'
                        200
                        (
                            'limit'
                        )
                        'entity'
                        0
                        None
                        'username'
                        '__pyarmor_exit_14069__'
                        'id'
                        'Name: '
                        ' Error: '
                        False
                    [Disassembly]
                        0       NOP                             
                        2       NOP                             
                        4       PUSH_NULL                       
                        6       LOAD_CONST                      2: '__pyarmor_enter_14068__'
                        8       LOAD_CONST                      3: b'<COAddr>\x05\x00\x00\x1a,\x02\x00\x00\x00\x00\x00\x00\x00\x00\x00\x00\x00\x00\x00\x00'
                        10      BUILD_TUPLE                     1
                        12      CALL_FUNCTION_EX                0
                        14      POP_TOP                         
                        16      RESUME                          0
                        18      NOP                             
                        20      NOP                             
                        22      NOP                             
                        24      NOP                             
                        26      NOP                             
                        28      NOP                             
                        30      LOAD_FAST                       0: self
                        32      LOAD_ATTR                       0: _client
                        52      LOAD_ATTR                       3: iter_dialogs
                        72      LOAD_CONST                      4: 200
                        74      KW_NAMES                        5: ('limit',)
                        76      CALL                            1
                        84      STORE_FAST                      5: _var_var_44
                        86      LOAD_FAST                       5: _var_var_44
                        88      GET_ITER                        
                        90      FOR_ITER                        165 (to 422)
                        94      STORE_FAST                      6: _var_var_45
                        96      LOAD_GLOBAL                     5: NULL + hasattr
                        106     LOAD_FAST                       6: _var_var_45
                        108     LOAD_CONST                      6: 'entity'
                        110     CALL                            2
                        118     POP_JUMP_IF_TRUE                1 (to 122)
                        120     JUMP_BACKWARD                   16 (to 90)
                        122     LOAD_FAST                       1: uid
                        124     LOAD_CONST                      7: 0
                        126     COMPARE_OP                      40 (==)
                        130     POP_JUMP_IF_FALSE               74 (to 280)
                        132     LOAD_FAST                       2: username
                        134     POP_JUMP_IF_NONE                72 (to 280)
                        136     LOAD_GLOBAL                     5: NULL + hasattr
                        146     LOAD_FAST                       6: _var_var_45
                        148     LOAD_ATTR                       6: entity
                        168     LOAD_CONST                      9: 'username'
                        170     CALL                            2
                        178     POP_JUMP_IF_TRUE                1 (to 182)
                        180     JUMP_BACKWARD                   46 (to 90)
                        182     LOAD_FAST                       6: _var_var_45
                        184     LOAD_ATTR                       6: entity
                        204     LOAD_ATTR                       8: username
                        224     LOAD_FAST                       2: username
                        226     COMPARE_OP                      40 (==)
                        230     POP_JUMP_IF_TRUE                1 (to 234)
                        232     JUMP_BACKWARD                   72 (to 90)
                        234     LOAD_FAST                       6: _var_var_45
                        236     LOAD_ATTR                       6: entity
                        256     SWAP                            2
                        258     POP_TOP                         
                        260     NOP                             
                        262     NOP                             
                        264     NOP                             
                        266     JUMP_FORWARD                    171 (to 610)
                        268     CALL                            1
                        276     POP_TOP                         
                        278     RETURN_VALUE                    
                        280     LOAD_GLOBAL                     5: NULL + hasattr
                        290     LOAD_FAST                       6: _var_var_45
                        292     LOAD_ATTR                       6: entity
                        312     LOAD_CONST                      11: 'id'
                        314     CALL                            2
                        322     POP_JUMP_IF_TRUE                1 (to 326)
                        324     JUMP_BACKWARD                   118 (to 90)
                        326     LOAD_FAST                       6: _var_var_45
                        328     LOAD_ATTR                       6: entity
                        348     LOAD_ATTR                       10: id
                        368     LOAD_FAST                       1: uid
                        370     COMPARE_OP                      40 (==)
                        374     POP_JUMP_IF_TRUE                1 (to 378)
                        376     JUMP_BACKWARD                   144 (to 90)
                        378     LOAD_FAST                       6: _var_var_45
                        380     LOAD_ATTR                       6: entity
                        400     SWAP                            2
                        402     POP_TOP                         
                        404     NOP                             
                        406     NOP                             
                        408     NOP                             
                        410     JUMP_FORWARD                    99 (to 610)
                        412     CALL                            1
                        420     POP_TOP                         
                        422     RETURN_VALUE                    
                        424     END_FOR                         
                        426     NOP                             
                        428     LOAD_CONST                      14: False
                        430     NOP                             
                        432     NOP                             
                        434     NOP                             
                        436     JUMP_FORWARD                    86 (to 610)
                        444     POP_TOP                         
                        446     RETURN_CONST                    14: False
                        448     PUSH_EXC_INFO                   
                        450     LOAD_GLOBAL                     12: StopProgram
                        460     CHECK_EXC_MATCH                 
                        462     POP_JUMP_IF_FALSE               2 (to 468)
                        464     POP_TOP                         
                        466     RAISE_VARARGS                   0
                        468     LOAD_GLOBAL                     14: Exception
                        478     CHECK_EXC_MATCH                 
                        480     POP_JUMP_IF_FALSE               46 (to 574)
                        482     STORE_FAST                      7: _var_var_20
                        484     LOAD_GLOBAL                     17: NULL + print
                        494     LOAD_CONST                      12: 'Name: '
                        496     LOAD_GLOBAL                     19: NULL + type
                        506     LOAD_FAST                       7: _var_var_20
                        508     CALL                            1
                        516     LOAD_ATTR                       20: __name__
                        536     FORMAT_VALUE                    0 (FVC_NONE)
                        538     LOAD_CONST                      13: ' Error: '
                        540     LOAD_FAST                       7: _var_var_20
                        542     FORMAT_VALUE                    0 (FVC_NONE)
                        544     BUILD_STRING                    4
                        546     CALL                            1
                        554     POP_TOP                         
                        556     POP_EXCEPT                      
                        558     LOAD_CONST                      8: None
                        560     STORE_FAST                      7: _var_var_20
                        562     DELETE_FAST                     7: _var_var_20
                        564     JUMP_BACKWARD                   69 (to 428)
                        566     LOAD_CONST                      8: None
                        568     STORE_FAST                      7: _var_var_20
                        570     DELETE_FAST                     7: _var_var_20
                        572     RERAISE                         1
                        574     RERAISE                         0
                        576     COPY                            3
                        578     POP_EXCEPT                      
                        580     RERAISE                         1
                        582     PUSH_EXC_INFO                   
                        584     PUSH_NULL                       
                        586     LOAD_CONST                      10: '__pyarmor_exit_14069__'
                        588     NOP                             
                        590     LOAD_CONST                      3: b'<COAddr>\x05\x00\x00\x1a,\x02\x00\x00\x00\x00\x00\x00\x00\x00\x00\x00\x00\x00\x00\x00'
                        592     CALL                            1
                        600     POP_TOP                         
                        602     RERAISE                         0
                        604     COPY                            3
                        606     POP_EXCEPT                      
                        608     RERAISE                         1
                        610     PUSH_NULL                       
                        612     LOAD_CONST                      10: '__pyarmor_exit_14069__'
                        614     LOAD_CONST                      3: b'<COAddr>\x05\x00\x00\x1a,\x02\x00\x00\x00\x00\x00\x00\x00\x00\x00\x00\x00\x00\x00\x00'
                        616     BUILD_TUPLE                     1
                        618     CALL_FUNCTION_EX                0
                        620     POP_TOP                         
                        622     RETURN_VALUE                    
                    [Exception Table]
                        30 to 120 -> 448 [0] 
                        122 to 180 -> 448 [0] 
                        182 to 232 -> 448 [0] 
                        234 to 260 -> 448 [0] 
                        280 to 324 -> 448 [0] 
                        326 to 376 -> 448 [0] 
                        378 to 404 -> 448 [0] 
                        424 to 426 -> 448 [0] 
                        426 to 428 -> 582 [0] 
                        448 to 484 -> 576 [1] lasti
                        484 to 556 -> 566 [1] lasti
                        556 to 566 -> 582 [0] 
                        566 to 576 -> 576 [1] lasti
                        576 to 582 -> 582 [0] 
                        582 to 604 -> 604 [1] lasti
                '__pyarmor_exit_14063__'
                (
                    None
                    None
                    None
                )
            [Disassembly]
                0       NOP                             
                2       LOAD_NAME                       0: __name__
                4       STORE_NAME                      1: __module__
                6       LOAD_CONST                      0: 'tg_search_group'
                8       STORE_NAME                      2: __qualname__
                10      LOAD_CONST                      1: ' Поиск группы внутри диалогов для получения entity '
                12      STORE_NAME                      3: __doc__
                14      NOP                             
                16      PUSH_NULL                       
                18      LOAD_CONST                      3: '__pyarmor_enter_14062__'
                20      LOAD_CONST                      4: b'<COAddr>\x07\x00\x00&2\x00\x00\x00\x00\x00\x00\x00\x00\x00\x00\x00\x00\x00\x00\x00'
                22      BUILD_TUPLE                     1
                24      CALL_FUNCTION_EX                0
                26      POP_TOP                         
                28      RESUME                          0
                30      NOP                             
                32      NOP                             
                34      NOP                             
                36      NOP                             
                38      NOP                             
                40      LOAD_CONST                      12: (None, None, None)
                42      LOAD_CONST                      6: <CODE> __init__
                44      MAKE_FUNCTION                   1
                46      STORE_NAME                      5: __init__
                48      LOAD_CONST                      7: 'uid'
                50      LOAD_NAME                       6: int
                52      LOAD_CONST                      8: 'username'
                54      LOAD_NAME                       7: str
                56      LOAD_CONST                      9: 'mess_id'
                58      LOAD_NAME                       6: int
                60      BUILD_TUPLE                     6
                62      LOAD_CONST                      10: <CODE> dialogs
                64      MAKE_FUNCTION                   4
                66      STORE_NAME                      8: dialogs
                68      LOAD_CONST                      5: None
                70      NOP                             
                72      NOP                             
                74      NOP                             
                76      JUMP_FORWARD                    19 (to 116)
                84      POP_TOP                         
                86      RETURN_CONST                    5: None
                88      PUSH_EXC_INFO                   
                90      PUSH_NULL                       
                92      LOAD_CONST                      11: '__pyarmor_exit_14063__'
                94      NOP                             
                96      LOAD_CONST                      4: b'<COAddr>\x07\x00\x00&2\x00\x00\x00\x00\x00\x00\x00\x00\x00\x00\x00\x00\x00\x00\x00'
                98      CALL                            1
                106     POP_TOP                         
                108     RERAISE                         0
                110     COPY                            3
                112     POP_EXCEPT                      
                114     RERAISE                         1
                116     PUSH_NULL                       
                118     LOAD_CONST                      11: '__pyarmor_exit_14063__'
                120     LOAD_CONST                      4: b'<COAddr>\x07\x00\x00&2\x00\x00\x00\x00\x00\x00\x00\x00\x00\x00\x00\x00\x00\x00\x00'
                122     BUILD_TUPLE                     1
                124     CALL_FUNCTION_EX                0
                126     POP_TOP                         
                128     RETURN_VALUE                    
            [Exception Table]
                40 to 68 -> 88 [0] 
                88 to 110 -> 110 [1] lasti
        'tg_search_group'
        '__pyarmor_exit_14048__'
    [Disassembly]
        0       NOP                             
        2       NOP                             
        4       PUSH_NULL                       
        6       LOAD_CONST                      1: '__pyarmor_enter_14047__'
        8       LOAD_CONST                      2: b'<COAddr>\x05\x00\x00\x1an\x01\x00\x00\x00\x00\x00\x00\x00\x00\x00\x00\x00\x00\x00\x00'
        10      BUILD_TUPLE                     1
        12      CALL_FUNCTION_EX                0
        14      POP_TOP                         
        16      RESUME                          0
        18      NOP                             
        20      NOP                             
        22      NOP                             
        24      NOP                             
        26      LOAD_CONST                      3: 0
        28      LOAD_CONST                      4: None
        30      IMPORT_NAME                     1: eel
        32      STORE_NAME                      1: eel
        34      LOAD_CONST                      3: 0
        36      LOAD_CONST                      4: None
        38      IMPORT_NAME                     2: json
        40      STORE_NAME                      2: json
        42      LOAD_CONST                      3: 0
        44      LOAD_CONST                      4: None
        46      IMPORT_NAME                     3: random
        48      STORE_NAME                      3: random
        50      LOAD_CONST                      3: 0
        52      LOAD_CONST                      4: None
        54      IMPORT_NAME                     4: concurrent.futures
        56      STORE_NAME                      5: concurrent
        58      LOAD_CONST                      3: 0
        60      LOAD_CONST                      5: ('Thread', 'Event')
        62      IMPORT_NAME                     6: threading
        64      IMPORT_FROM                     7: Thread
        66      STORE_NAME                      7: Thread
        68      IMPORT_FROM                     8: Event
        70      STORE_NAME                      8: Event
        72      POP_TOP                         
        74      LOAD_CONST                      3: 0
        76      LOAD_CONST                      6: ('functions', 'types')
        78      IMPORT_NAME                     9: multithon.sync
        80      IMPORT_FROM                     10: functions
        82      STORE_NAME                      10: functions
        84      IMPORT_FROM                     11: types
        86      STORE_NAME                      11: types
        88      POP_TOP                         
        90      LOAD_CONST                      3: 0
        92      LOAD_CONST                      7: ('StopProgram',)
        94      IMPORT_NAME                     12: multithon.errors
        96      IMPORT_FROM                     13: StopProgram
        98      STORE_NAME                      13: StopProgram
        100     POP_TOP                         
        102     LOAD_CONST                      3: 0
        104     LOAD_CONST                      8: ('GetLang',)
        106     IMPORT_NAME                     14: program.static_classes
        108     IMPORT_FROM                     15: GetLang
        110     STORE_NAME                      15: GetLang
        112     POP_TOP                         
        114     LOAD_CONST                      3: 0
        116     LOAD_CONST                      9: ('Logs',)
        118     IMPORT_NAME                     14: program.static_classes
        120     IMPORT_FROM                     16: Logs
        122     STORE_NAME                      16: Logs
        124     POP_TOP                         
        126     LOAD_CONST                      3: 0
        128     LOAD_CONST                      10: ('memory_check_switcher',)
        130     IMPORT_NAME                     14: program.static_classes
        132     IMPORT_FROM                     17: memory_check_switcher
        134     STORE_NAME                      17: memory_check_switcher
        136     POP_TOP                         
        138     LOAD_CONST                      3: 0
        140     LOAD_CONST                      11: ('memory_set_pid',)
        142     IMPORT_NAME                     14: program.static_classes
        144     IMPORT_FROM                     18: memory_set_pid
        146     STORE_NAME                      18: memory_set_pid
        148     POP_TOP                         
        150     LOAD_CONST                      3: 0
        152     LOAD_CONST                      12: ('DelayOnline',)
        154     IMPORT_NAME                     19: program.telegram
        156     IMPORT_FROM                     20: DelayOnline
        158     STORE_NAME                      20: DelayOnline
        160     POP_TOP                         
        162     LOAD_CONST                      3: 0
        164     LOAD_CONST                      13: ('Disconnect',)
        166     IMPORT_NAME                     19: program.telegram
        168     IMPORT_FROM                     21: Disconnect
        170     STORE_NAME                      21: Disconnect
        172     POP_TOP                         
        174     LOAD_CONST                      3: 0
        176     LOAD_CONST                      14: ('Thread_wait',)
        178     IMPORT_NAME                     19: program.telegram
        180     IMPORT_FROM                     22: Thread_wait
        182     STORE_NAME                      22: Thread_wait
        184     POP_TOP                         
        186     LOAD_CONST                      3: 0
        188     LOAD_CONST                      15: ('account_works',)
        190     IMPORT_NAME                     19: program.telegram
        192     IMPORT_FROM                     23: account_works
        194     STORE_NAME                      23: account_works
        196     POP_TOP                         
        198     LOAD_CONST                      3: 0
        200     LOAD_CONST                      16: ('tg_group',)
        202     IMPORT_NAME                     19: program.telegram
        204     IMPORT_FROM                     24: tg_group
        206     STORE_NAME                      24: tg_group
        208     POP_TOP                         
        210     LOAD_CONST                      3: 0
        212     LOAD_CONST                      17: ('tg_links',)
        214     IMPORT_NAME                     19: program.telegram
        216     IMPORT_FROM                     25: tg_links
        218     STORE_NAME                      25: tg_links
        220     POP_TOP                         
        222     LOAD_CONST                      3: 0
        224     LOAD_CONST                      18: ('GetConfig',)
        226     IMPORT_NAME                     26: program.general
        228     IMPORT_FROM                     27: GetConfig
        230     STORE_NAME                      27: GetConfig
        232     POP_TOP                         
        234     LOAD_CONST                      3: 0
        236     LOAD_CONST                      19: ('GetProxy',)
        238     IMPORT_NAME                     26: program.general
        240     IMPORT_FROM                     28: GetProxy
        242     STORE_NAME                      28: GetProxy
        244     POP_TOP                         
        246     LOAD_CONST                      3: 0
        248     LOAD_CONST                      20: ('StopDetect',)
        250     IMPORT_NAME                     26: program.general
        252     IMPORT_FROM                     29: StopDetect
        254     STORE_NAME                      29: StopDetect
        256     POP_TOP                         
        258     LOAD_CONST                      3: 0
        260     LOAD_CONST                      21: ('check_get_settings',)
        262     IMPORT_NAME                     26: program.general
        264     IMPORT_FROM                     30: check_get_settings
        266     STORE_NAME                      30: check_get_settings
        268     POP_TOP                         
        270     LOAD_CONST                      3: 0
        272     LOAD_CONST                      22: ('del_task_manager',)
        274     IMPORT_NAME                     26: program.general
        276     IMPORT_FROM                     31: del_task_manager
        278     STORE_NAME                      31: del_task_manager
        280     POP_TOP                         
        282     LOAD_CONST                      3: 0
        284     LOAD_CONST                      23: ('getFile',)
        286     IMPORT_NAME                     26: program.general
        288     IMPORT_FROM                     32: getFile
        290     STORE_NAME                      32: getFile
        292     POP_TOP                         
        294     LOAD_CONST                      3: 0
        296     LOAD_CONST                      24: ('set_task_manager',)
        298     IMPORT_NAME                     26: program.general
        300     IMPORT_FROM                     33: set_task_manager
        302     STORE_NAME                      33: set_task_manager
        304     POP_TOP                         
        306     LOAD_CONST                      3: 0
        308     LOAD_CONST                      25: ('db_reactions',)
        310     IMPORT_NAME                     34: program.database
        312     IMPORT_FROM                     35: db_reactions
        314     STORE_NAME                      35: db_reactions
        316     POP_TOP                         
        318     LOAD_CONST                      26: <CODE> Reactions
        320     MAKE_FUNCTION                   0
        322     STORE_NAME                      36: Reactions
        324     LOAD_CONST                      27: <CODE> START
        326     MAKE_FUNCTION                   0
        328     STORE_NAME                      37: START
        330     LOAD_CONST                      28: 'uid'
        332     LOAD_NAME                       38: int
        334     LOAD_CONST                      29: 'return'
        336     LOAD_NAME                       39: str
        338     BUILD_TUPLE                     4
        340     LOAD_CONST                      30: <CODE> get_emoticon
        342     MAKE_FUNCTION                   4
        344     STORE_NAME                      40: get_emoticon
        346     LOAD_CONST                      31: <CODE> worker
        348     MAKE_FUNCTION                   0
        350     STORE_NAME                      41: worker
        352     PUSH_NULL                       
        354     LOAD_BUILD_CLASS                
        356     LOAD_CONST                      32: <CODE> tg_search_group
        358     MAKE_FUNCTION                   0
        360     LOAD_CONST                      33: 'tg_search_group'
        362     CALL                            2
        370     STORE_NAME                      42: tg_search_group
        372     LOAD_CONST                      4: None
        374     NOP                             
        376     NOP                             
        378     NOP                             
        380     JUMP_FORWARD                    19 (to 420)
        388     POP_TOP                         
        390     RETURN_CONST                    4: None
        392     PUSH_EXC_INFO                   
        394     PUSH_NULL                       
        396     LOAD_CONST                      34: '__pyarmor_exit_14048__'
        398     NOP                             
        400     LOAD_CONST                      2: b'<COAddr>\x05\x00\x00\x1an\x01\x00\x00\x00\x00\x00\x00\x00\x00\x00\x00\x00\x00\x00\x00'
        402     CALL                            1
        410     POP_TOP                         
        412     RERAISE                         0
        414     COPY                            3
        416     POP_EXCEPT                      
        418     RERAISE                         1
        420     PUSH_NULL                       
        422     LOAD_CONST                      34: '__pyarmor_exit_14048__'
        424     LOAD_CONST                      2: b'<COAddr>\x05\x00\x00\x1an\x01\x00\x00\x00\x00\x00\x00\x00\x00\x00\x00\x00\x00\x00\x00'
        426     BUILD_TUPLE                     1
        428     CALL_FUNCTION_EX                0
        430     POP_TOP                         
        432     RETURN_VALUE                    
    [Exception Table]
        26 to 372 -> 392 [0] 
        392 to 414 -> 414 [1] lasti
