#decoded by lolz.live/mrpenny / t.me/zeus_jackpot
# ================================
# Примечания по Pyarmor:
# - Байт-код и объекты кода Pyarmor соответствуют стандартному Python, но присутствуют специальные вызовы функций среды выполнения (runtime) Pyarmor.
# - Вызовы строк — это не ошибки, а маркеры, которые обрабатываются Pyarmor во время выполнения.
#
# Руководство по декомпиляции (без среды выполнения):
# 1. Игнорируйте зашифрованные байты после `#`; используйте только строку до `#`.
# 2. Удалите "__pyarmor_enter_xxx__"(b"<COAddr>...") и "__pyarmor_leave_xxx__"(b"<COAddr>...") (пролог/эпилог).
# 3. "__pyarmor_assert_xxx__"(A) не является настоящим оператором assert.
#    - Если A — это имя или читаемая строка: замените на A.
#    - Если A — это (X, "Y"): замените на X.Y.
#    - Если A — это (X, "Y", Z): замените на X.Y = Z.
#    - В противном случае: выберите наиболее подходящую/логичную замену.
# 4. "__pyarmor_bcc_xxx__"(...) указывает на машинный (нативный) код; тело функции недоступно. Добавьте комментарий.
# ================================

[Code]
    File Name: <frozen program.modules.Registrator_tokens>
    Object Name: <module>
    Qualified Name: <module>
    Arg Count: 0
    Pos Only Arg Count: 0
    KW Only Arg Count: 0
    Stack Size: 5
    Flags: 0x20000000 (CO_PYARMOR_OBFUSCATED)
    [Names]
        '__assert_armored__'
        'os'
        'eel'
        'json'
        'base64'
        'asyncio'
        'concurrent.futures'
        'concurrent'
        'threading'
        'Thread'
        'Event'
        'multithon'
        'TelegramClient'
        'functions'
        'multithon.errors'
        'StopProgram'
        'program.static_classes'
        'GetLang'
        'Logs'
        'VersionControl'
        'get_logger'
        'logging'
        'memory_check_switcher'
        'memory_set_pid'
        'proxy_hide'
        'program.telegram'
        'Disconnect'
        'Thread_wait'
        'get_account_json'
        'get_account_proxy'
        'json_file'
        'program.general'
        'GetConfig'
        'GetProxy'
        'StopDetect'
        'del_task_manager'
        'set_task_manager'
        'func.api.antisafety'
        'AntiSafety'
        'AntiSafetyMail'
        'program.database'
        'db_reg_statistic'
        'Registrator_tokens'
        'GetSafetyNetBalance'
        'get_anti_safety_key'
        'START'
        'worker'
    [Locals+Names]
    [Constants]
        '__pyarmor_assert_14376__'
        '__pyarmor_enter_14377__'
        b'<COAddr>\x07\x00\x00\x1a\x82\x01\x00\x00\x00\x00\x00\x00\x00\x00\x00\x00\x00\x00\x00\x00'
        0
        None
        (
            'Thread'
            'Event'
        )
        (
            'TelegramClient'
            'functions'
        )
        (
            'StopProgram'
        )
        (
            'GetLang'
        )
        (
            'Logs'
        )
        (
            'VersionControl'
        )
        (
            'get_logger'
        )
        (
            'logging'
        )
        (
            'memory_check_switcher'
        )
        (
            'memory_set_pid'
        )
        (
            'proxy_hide'
        )
        (
            'Disconnect'
        )
        (
            'Thread_wait'
        )
        (
            'get_account_json'
        )
        (
            'get_account_proxy'
        )
        (
            'json_file'
        )
        (
            'GetConfig'
        )
        (
            'GetProxy'
        )
        (
            'StopDetect'
        )
        (
            'del_task_manager'
        )
        (
            'set_task_manager'
        )
        1
        (
            'AntiSafety'
            'AntiSafetyMail'
        )
        (
            'db_reg_statistic'
        )
        [Code]
            File Name: <frozen program.modules.Registrator_tokens>
            Object Name: Registrator_tokens
            Qualified Name: Registrator_tokens
            Arg Count: 1
            Pos Only Arg Count: 0
            KW Only Arg Count: 0
            Stack Size: 8
            Flags: 0x20000003 (CO_OPTIMIZED | CO_NEWLOCALS | CO_PYARMOR_OBFUSCATED)
            [Names]
                'GetConfig'
                'config'
                'GetLang'
                'Lang'
                'GetProxy'
                'get'
                'GetSafetyNetBalance'
                'eel'
                'sendSuccessBox'
                'memory_check_switcher'
                'Event'
                'memory_set_pid'
                'Thread'
                'START'
                'start'
                'Logs'
                'WaitStopAnsfer'
                'UpdateLogInWindow'
                'BaseException'
                'logging'
            [Locals+Names]
                'data'
                '__assert_armored__'
                '_var_var_0'
                '_var_var_1'
                '_var_var_2'
                '_var_var_3'
            [Constants]
                None
                '__pyarmor_assert_14379__'
                '__pyarmor_enter_14380__'
                b'<COAddr>\x05\x00\x00\x1a\xb2\x02\x00\x00\x00\x00\x00\x00\x00\x00\x00\x00\x00\x00\x00\x00'
                'action'
                ''
                'GetSafetyNetBalance'   # b'\x81\xc5\x1d\x07\x00\xfb\xb8\xd7\x0f\xe3#\xc5x\xce\xf9\x89\x0eS\xb8\xa2'
                '__pyarmor_exit_14381__'
                'program_running'   # b'\x81\xf2\n\x1c4\xe8\xbf\xdf$\xe8\x18\xceb\xe5\xf6\x82'
                False
                (
                    'target'
                    'args'
                )
                True
                (
                    'target'
                    'args'
                    'daemon'
                )
            [Disassembly]
                0       NOP                             
                2       NOP                             
                4       PUSH_NULL                       
                6       LOAD_CONST                      2: '__pyarmor_enter_14380__'
                8       LOAD_CONST                      3: b'<COAddr>\x05\x00\x00\x1a\xb2\x02\x00\x00\x00\x00\x00\x00\x00\x00\x00\x00\x00\x00\x00\x00'
                10      BUILD_TUPLE                     1
                12      CALL_FUNCTION_EX                0
                14      POP_TOP                         
                16      RESUME                          0
                18      NOP                             
                20      NOP                             
                22      NOP                             
                24      NOP                             
                26      NOP                             
                28      NOP                             
                30      LOAD_GLOBAL                     1: NULL + GetConfig
                40      CALL                            0
                48      STORE_GLOBAL                    1: config
                50      LOAD_GLOBAL                     5: NULL + GetLang
                60      LOAD_GLOBAL                     2: config
                70      CALL                            1
                78      STORE_GLOBAL                    3: Lang
                80      LOAD_GLOBAL                     9: NULL + GetProxy
                90      CALL                            0
                98      STORE_FAST                      2: _var_var_0
                100     LOAD_FAST                       0: data
                102     LOAD_ATTR                       11: get
                122     LOAD_CONST                      4: 'action'
                124     LOAD_CONST                      5: ''
                126     CALL                            2
                134     PUSH_NULL                       
                136     LOAD_CONST                      1: '__pyarmor_assert_14379__'
                138     LOAD_CONST                      6: 'GetSafetyNetBalance'   # b'\x81\xc5\x1d\x07\x00\xfb\xb8\xd7\x0f\xe3#\xc5x\xce\xf9\x89\x0eS\xb8\xa2'
                140     CALL                            1
                148     COMPARE_OP                      40 (==)
                152     POP_JUMP_IF_FALSE               20 (to 194)
                154     LOAD_GLOBAL                     13: NULL + GetSafetyNetBalance
                164     LOAD_FAST                       0: data
                166     CALL                            1
                174     NOP                             
                176     NOP                             
                178     JUMP_FORWARD                    281 (to 744)
                182     CALL                            1
                190     POP_TOP                         
                192     RETURN_VALUE                    
                194     LOAD_GLOBAL                     15: NULL + eel
                204     LOAD_ATTR                       16: sendSuccessBox
                224     LOAD_GLOBAL                     6: Lang
                234     PUSH_NULL                       
                236     LOAD_CONST                      1: '__pyarmor_assert_14379__'
                238     LOAD_CONST                      8: 'program_running'   # b'\x81\xf2\n\x1c4\xe8\xbf\xdf$\xe8\x18\xceb\xe5\xf6\x82'
                240     CALL                            1
                248     BINARY_SUBSCR                   
                252     CALL                            1
                260     POP_TOP                         
                262     LOAD_GLOBAL                     19: NULL + memory_check_switcher
                272     CALL                            0
                280     POP_JUMP_IF_TRUE                11 (to 304)
                282     NOP                             
                284     LOAD_CONST                      9: False
                286     NOP                             
                288     NOP                             
                290     NOP                             
                292     JUMP_FORWARD                    225 (to 744)
                300     POP_TOP                         
                302     RETURN_CONST                    9: False
                304     LOAD_GLOBAL                     21: NULL + Event
                314     CALL                            0
                322     STORE_FAST                      3: _var_var_1
                324     LOAD_GLOBAL                     23: NULL + memory_set_pid
                334     CALL                            0
                342     STORE_FAST                      4: _var_var_2
                344     LOAD_GLOBAL                     25: NULL + Thread
                354     LOAD_GLOBAL                     26: START
                364     LOAD_FAST                       0: data
                366     LOAD_GLOBAL                     2: config
                376     LOAD_FAST                       4: _var_var_2
                378     LOAD_FAST                       2: _var_var_0
                380     LOAD_FAST                       3: _var_var_1
                382     BUILD_TUPLE                     5
                384     KW_NAMES                        10: ('target', 'args')
                386     CALL                            2
                394     LOAD_ATTR                       29: start
                414     CALL                            0
                422     POP_TOP                         
                424     LOAD_GLOBAL                     25: NULL + Thread
                434     LOAD_GLOBAL                     30: Logs
                444     LOAD_ATTR                       32: WaitStopAnsfer
                464     LOAD_GLOBAL                     2: config
                474     LOAD_FAST                       4: _var_var_2
                476     LOAD_FAST                       3: _var_var_1
                478     BUILD_TUPLE                     3
                480     LOAD_CONST                      11: True
                482     KW_NAMES                        12: ('target', 'args', 'daemon')
                484     CALL                            3
                492     LOAD_ATTR                       29: start
                512     CALL                            0
                520     POP_TOP                         
                522     LOAD_GLOBAL                     25: NULL + Thread
                532     LOAD_GLOBAL                     30: Logs
                542     LOAD_ATTR                       34: UpdateLogInWindow
                562     LOAD_GLOBAL                     2: config
                572     LOAD_FAST                       4: _var_var_2
                574     LOAD_FAST                       3: _var_var_1
                576     BUILD_TUPLE                     3
                578     LOAD_CONST                      11: True
                580     KW_NAMES                        12: ('target', 'args', 'daemon')
                582     CALL                            3
                590     LOAD_ATTR                       29: start
                610     CALL                            0
                618     POP_TOP                         
                620     LOAD_CONST                      0: None
                622     NOP                             
                624     NOP                             
                626     NOP                             
                628     JUMP_FORWARD                    57 (to 744)
                636     POP_TOP                         
                638     RETURN_CONST                    0: None
                640     PUSH_EXC_INFO                   
                642     LOAD_GLOBAL                     36: BaseException
                652     CHECK_EXC_MATCH                 
                654     POP_JUMP_IF_FALSE               26 (to 708)
                656     STORE_FAST                      5: _var_var_3
                658     PUSH_NULL                       
                660     LOAD_GLOBAL                     39: NULL + logging
                670     LOAD_FAST                       5: _var_var_3
                672     CALL                            1
                680     CALL                            0
                688     POP_TOP                         
                690     POP_EXCEPT                      
                692     LOAD_CONST                      0: None
                694     STORE_FAST                      5: _var_var_3
                696     DELETE_FAST                     5: _var_var_3
                698     JUMP_BACKWARD                   40 (to 620)
                700     LOAD_CONST                      0: None
                702     STORE_FAST                      5: _var_var_3
                704     DELETE_FAST                     5: _var_var_3
                706     RERAISE                         1
                708     RERAISE                         0
                710     COPY                            3
                712     POP_EXCEPT                      
                714     RERAISE                         1
                716     PUSH_EXC_INFO                   
                718     PUSH_NULL                       
                720     LOAD_CONST                      7: '__pyarmor_exit_14381__'
                722     NOP                             
                724     LOAD_CONST                      3: b'<COAddr>\x05\x00\x00\x1a\xb2\x02\x00\x00\x00\x00\x00\x00\x00\x00\x00\x00\x00\x00\x00\x00'
                726     CALL                            1
                734     POP_TOP                         
                736     RERAISE                         0
                738     COPY                            3
                740     POP_EXCEPT                      
                742     RERAISE                         1
                744     PUSH_NULL                       
                746     LOAD_CONST                      7: '__pyarmor_exit_14381__'
                748     LOAD_CONST                      3: b'<COAddr>\x05\x00\x00\x1a\xb2\x02\x00\x00\x00\x00\x00\x00\x00\x00\x00\x00\x00\x00\x00\x00'
                750     BUILD_TUPLE                     1
                752     CALL_FUNCTION_EX                0
                754     POP_TOP                         
                756     RETURN_VALUE                    
            [Exception Table]
                30 to 174 -> 640 [0] 
                194 to 282 -> 640 [0] 
                304 to 620 -> 640 [0] 
                640 to 658 -> 710 [1] lasti
                658 to 690 -> 700 [1] lasti
                690 to 700 -> 716 [0] 
                700 to 710 -> 710 [1] lasti
                710 to 716 -> 716 [0] 
                716 to 738 -> 738 [1] lasti
        [Code]
            File Name: <frozen program.modules.Registrator_tokens>
            Object Name: GetSafetyNetBalance
            Qualified Name: GetSafetyNetBalance
            Arg Count: 1
            Pos Only Arg Count: 0
            KW Only Arg Count: 0
            Stack Size: 7
            Flags: 0x20000003 (CO_OPTIMIZED | CO_NEWLOCALS | CO_PYARMOR_OBFUSCATED)
            [Names]
                'AntiSafetyMail'
                'get_domains'
                'eel'
                'LoadAntiSafetyEmail'
            [Locals+Names]
                'data'
                '__assert_armored__'
                '_var_var_4'
                '_var_var_5'
            [Constants]
                None
                '__pyarmor_assert_14382__'
                '__pyarmor_enter_14383__'
                b'<COAddr>\x07\x00\x00\x1a\xf0\x00\x00\x00\x00\x00\x00\x00\x00\x00\x00\x00\x00\x00\x00\x00'
                'Settings'
                'antisafetynet_key_1'   # b'\x81\xe3\x16\x07:\xe9\xbf\xd4\x1e\xee\x14\xcei\xf8\xc7\x8e\nD\x84\xf6'
                ''
                'antisafetynet_key_2'   # b'\x81\xe3\x16\x07:\xe9\xbf\xd4\x1e\xee\x14\xcei\xf8\xc7\x8e\nD\x84\xf5'
                'balance'
                'balance_reserve'   # b'\x81\xe0\x19\x1f2\xf4\xbd\xd7$\xe8\x08\xd3i\xfe\xee\x80'
                'email'
                '__pyarmor_exit_14384__'
            [Disassembly]
                0       NOP                             
                2       NOP                             
                4       PUSH_NULL                       
                6       LOAD_CONST                      2: '__pyarmor_enter_14383__'
                8       LOAD_CONST                      3: b'<COAddr>\x07\x00\x00\x1a\xf0\x00\x00\x00\x00\x00\x00\x00\x00\x00\x00\x00\x00\x00\x00\x00'
                10      BUILD_TUPLE                     1
                12      CALL_FUNCTION_EX                0
                14      POP_TOP                         
                16      RESUME                          0
                18      NOP                             
                20      NOP                             
                22      NOP                             
                24      NOP                             
                26      NOP                             
                28      LOAD_FAST                       0: data
                30      LOAD_CONST                      4: 'Settings'
                32      BINARY_SUBSCR                   
                36      PUSH_NULL                       
                38      LOAD_CONST                      1: '__pyarmor_assert_14382__'
                40      LOAD_CONST                      5: 'antisafetynet_key_1'   # b'\x81\xe3\x16\x07:\xe9\xbf\xd4\x1e\xee\x14\xcei\xf8\xc7\x8e\nD\x84\xf6'
                42      CALL                            1
                50      BINARY_SUBSCR                   
                54      LOAD_CONST                      6: ''
                56      COMPARE_OP                      55 (!=)
                60      POP_JUMP_IF_FALSE               15 (to 92)
                62      LOAD_FAST                       0: data
                64      LOAD_CONST                      4: 'Settings'
                66      BINARY_SUBSCR                   
                70      PUSH_NULL                       
                72      LOAD_CONST                      1: '__pyarmor_assert_14382__'
                74      LOAD_CONST                      5: 'antisafetynet_key_1'   # b'\x81\xe3\x16\x07:\xe9\xbf\xd4\x1e\xee\x14\xcei\xf8\xc7\x8e\nD\x84\xf6'
                76      CALL                            1
                84      BINARY_SUBSCR                   
                88      STORE_FAST                      2: _var_var_4
                90      JUMP_FORWARD                    14 (to 120)
                92      LOAD_FAST                       0: data
                94      LOAD_CONST                      4: 'Settings'
                96      BINARY_SUBSCR                   
                100     PUSH_NULL                       
                102     LOAD_CONST                      1: '__pyarmor_assert_14382__'
                104     LOAD_CONST                      7: 'antisafetynet_key_2'   # b'\x81\xe3\x16\x07:\xe9\xbf\xd4\x1e\xee\x14\xcei\xf8\xc7\x8e\nD\x84\xf5'
                106     CALL                            1
                114     BINARY_SUBSCR                   
                118     STORE_FAST                      2: _var_var_4
                120     LOAD_GLOBAL                     1: NULL + AntiSafetyMail
                130     LOAD_FAST                       2: _var_var_4
                132     CALL                            1
                140     LOAD_ATTR                       3: get_domains
                160     CALL                            0
                168     STORE_FAST                      3: _var_var_5
                170     LOAD_GLOBAL                     5: NULL + eel
                180     LOAD_ATTR                       6: LoadAntiSafetyEmail
                200     LOAD_FAST                       3: _var_var_5
                202     LOAD_CONST                      8: 'balance'
                204     BINARY_SUBSCR                   
                208     LOAD_FAST                       3: _var_var_5
                210     PUSH_NULL                       
                212     LOAD_CONST                      1: '__pyarmor_assert_14382__'
                214     LOAD_CONST                      9: 'balance_reserve'   # b'\x81\xe0\x19\x1f2\xf4\xbd\xd7$\xe8\x08\xd3i\xfe\xee\x80'
                216     CALL                            1
                224     BINARY_SUBSCR                   
                228     LOAD_FAST                       3: _var_var_5
                230     LOAD_CONST                      10: 'email'
                232     BINARY_SUBSCR                   
                236     CALL                            3
                244     POP_TOP                         
                246     LOAD_CONST                      0: None
                248     NOP                             
                250     NOP                             
                252     NOP                             
                254     JUMP_FORWARD                    19 (to 294)
                262     POP_TOP                         
                264     RETURN_CONST                    0: None
                266     PUSH_EXC_INFO                   
                268     PUSH_NULL                       
                270     LOAD_CONST                      11: '__pyarmor_exit_14384__'
                272     NOP                             
                274     LOAD_CONST                      3: b'<COAddr>\x07\x00\x00\x1a\xf0\x00\x00\x00\x00\x00\x00\x00\x00\x00\x00\x00\x00\x00\x00\x00'
                276     CALL                            1
                284     POP_TOP                         
                286     RERAISE                         0
                288     COPY                            3
                290     POP_EXCEPT                      
                292     RERAISE                         1
                294     PUSH_NULL                       
                296     LOAD_CONST                      11: '__pyarmor_exit_14384__'
                298     LOAD_CONST                      3: b'<COAddr>\x07\x00\x00\x1a\xf0\x00\x00\x00\x00\x00\x00\x00\x00\x00\x00\x00\x00\x00\x00\x00'
                300     BUILD_TUPLE                     1
                302     CALL_FUNCTION_EX                0
                304     POP_TOP                         
                306     RETURN_VALUE                    
            [Exception Table]
                28 to 246 -> 266 [0] 
                266 to 288 -> 288 [1] lasti
        [Code]
            File Name: <frozen program.modules.Registrator_tokens>
            Object Name: get_anti_safety_key
            Qualified Name: get_anti_safety_key
            Arg Count: 3
            Pos Only Arg Count: 0
            KW Only Arg Count: 0
            Stack Size: 5
            Flags: 0x20000003 (CO_OPTIMIZED | CO_NEWLOCALS | CO_PYARMOR_OBFUSCATED)
            [Names]
            [Locals+Names]
                'app_id'
                'safetynet_key_1'
                'safetynet_key_2'
                '__assert_armored__'
            [Constants]
                None
                '__pyarmor_assert_14385__'
                '__pyarmor_enter_14386__'
                b'<COAddr>\x05\x00\x00\x1a\xa0\x00\x00\x00\x00\x00\x00\x00\x00\x00\x00\x00\x00\x00\x00\x00'
                4
                6
                ''
                '__pyarmor_exit_14387__'
                False
                21724
            [Disassembly]
                0       NOP                             
                2       NOP                             
                4       PUSH_NULL                       
                6       LOAD_CONST                      2: '__pyarmor_enter_14386__'
                8       LOAD_CONST                      3: b'<COAddr>\x05\x00\x00\x1a\xa0\x00\x00\x00\x00\x00\x00\x00\x00\x00\x00\x00\x00\x00\x00\x00'
                10      BUILD_TUPLE                     1
                12      CALL_FUNCTION_EX                0
                14      POP_TOP                         
                16      RESUME                          0
                18      NOP                             
                20      NOP                             
                22      NOP                             
                24      NOP                             
                26      NOP                             
                28      LOAD_FAST                       0: app_id
                30      LOAD_CONST                      4: 4
                32      COMPARE_OP                      40 (==)
                36      POP_JUMP_IF_TRUE                5 (to 48)
                38      LOAD_FAST                       0: app_id
                40      LOAD_CONST                      5: 6
                42      COMPARE_OP                      40 (==)
                46      POP_JUMP_IF_FALSE               27 (to 102)
                48      LOAD_FAST                       1: safetynet_key_1
                50      LOAD_CONST                      6: ''
                52      COMPARE_OP                      40 (==)
                56      POP_JUMP_IF_FALSE               11 (to 80)
                58      NOP                             
                60      LOAD_CONST                      8: False
                62      NOP                             
                64      NOP                             
                66      NOP                             
                68      JUMP_FORWARD                    72 (to 214)
                76      POP_TOP                         
                78      RETURN_CONST                    8: False
                80      LOAD_FAST                       1: safetynet_key_1
                82      NOP                             
                84      NOP                             
                86      NOP                             
                88      JUMP_FORWARD                    62 (to 214)
                90      CALL                            1
                98      POP_TOP                         
                100     RETURN_VALUE                    
                102     LOAD_FAST                       0: app_id
                104     LOAD_CONST                      9: 21724
                106     COMPARE_OP                      40 (==)
                110     POP_JUMP_IF_FALSE               27 (to 166)
                112     LOAD_FAST                       2: safetynet_key_2
                114     LOAD_CONST                      6: ''
                116     COMPARE_OP                      40 (==)
                120     POP_JUMP_IF_FALSE               11 (to 144)
                122     NOP                             
                124     LOAD_CONST                      8: False
                126     NOP                             
                128     NOP                             
                130     NOP                             
                132     JUMP_FORWARD                    40 (to 214)
                140     POP_TOP                         
                142     RETURN_CONST                    8: False
                144     LOAD_FAST                       2: safetynet_key_2
                146     NOP                             
                148     NOP                             
                150     NOP                             
                152     JUMP_FORWARD                    30 (to 214)
                154     CALL                            1
                162     POP_TOP                         
                164     RETURN_VALUE                    
                166     LOAD_CONST                      8: False
                168     NOP                             
                170     NOP                             
                172     NOP                             
                174     JUMP_FORWARD                    19 (to 214)
                182     POP_TOP                         
                184     RETURN_CONST                    8: False
                186     PUSH_EXC_INFO                   
                188     PUSH_NULL                       
                190     LOAD_CONST                      7: '__pyarmor_exit_14387__'
                192     NOP                             
                194     LOAD_CONST                      3: b'<COAddr>\x05\x00\x00\x1a\xa0\x00\x00\x00\x00\x00\x00\x00\x00\x00\x00\x00\x00\x00\x00\x00'
                196     CALL                            1
                204     POP_TOP                         
                206     RERAISE                         0
                208     COPY                            3
                210     POP_EXCEPT                      
                212     RERAISE                         1
                214     PUSH_NULL                       
                216     LOAD_CONST                      7: '__pyarmor_exit_14387__'
                218     LOAD_CONST                      3: b'<COAddr>\x05\x00\x00\x1a\xa0\x00\x00\x00\x00\x00\x00\x00\x00\x00\x00\x00\x00\x00\x00\x00'
                220     BUILD_TUPLE                     1
                222     CALL_FUNCTION_EX                0
                224     POP_TOP                         
                226     RETURN_VALUE                    
            [Exception Table]
                28 to 58 -> 186 [0] 
                80 to 82 -> 186 [0] 
                102 to 122 -> 186 [0] 
                144 to 146 -> 186 [0] 
                186 to 208 -> 208 [1] lasti
        [Code]
            File Name: <frozen program.modules.Registrator_tokens>
            Object Name: START
            Qualified Name: START
            Arg Count: 5
            Pos Only Arg Count: 0
            KW Only Arg Count: 0
            Stack Size: 14
            Flags: 0x20000003 (CO_OPTIMIZED | CO_NEWLOCALS | CO_PYARMOR_OBFUSCATED)
            [Names]
                'is_set'
                'StopProgram'
                'isinstance'
                'list'
                'int'
                'len'
                'eel'
                'sendErrorBox'
                'Lang'
                'get'
                'db_reg_statistic'
                'create'
                'Logs'
                'LangCheck'
                'set_task_manager'
                'concurrent'
                'futures'
                'ThreadPoolExecutor'
                'StreamStat'
                'json'
                'dumps'
                'append'
                'submit'
                'worker'
                'as_completed'
                'BaseException'
                'logging'
                'del_task_manager'
                'StopDetect'
            [Locals+Names]
                'data'
                'config'
                'pid'
                'proxy'
                'stop_thread'
                '__assert_armored__'
                '_var_var_6'
                '_var_var_7'
                '_var_var_8'
                '_var_var_9'
                '_var_var_10'
                '_var_var_11'
                '_var_var_12'
                '_var_var_13'
                '_var_var_14'
                '_var_var_15'
                '_var_var_16'
                '_var_var_3'
            [Constants]
                None
                '__pyarmor_assert_14388__'
                '__pyarmor_enter_14389__'
                b'<COAddr>\x07\x00\x00\x1a\x10\x05\x00\x00\x00\x00\x00\x00\x00\x00\x00\x00\x00\x00\x00\x00'
                'Accounts'
                1
                'select_accounts_works'   # b'\x81\xf1\x1d\x1f6\xf9\xaa\xed\x1a\xf9\x0e\xcfy\xe2\xec\x960J\xb4\xb5\xa1\xd8'
                'Settings'
                'thread_rules'   # b'\x81\xf6\x10\x016\xfb\xba\xed\t\xef\x01\xc5\x7f'
                True
                'thread_count'   # b'\x81\xf6\x10\x016\xfb\xba\xed\x18\xf5\x18\xcex'
                'Tokens'
                (
                    'accounts'
                    'name'
                )
                (
                    'max_workers'
                )
                0
                'st_task'
                'st_stream'   # b'\x81\xf1\x0c, \xee\xac\xd7\x1a\xf7'
                'st_wait'
                'st_done'
                '__pyarmor_exit_14390__'
                'Done'
            [Disassembly]
                0       NOP                             
                2       NOP                             
                4       PUSH_NULL                       
                6       LOAD_CONST                      2: '__pyarmor_enter_14389__'
                8       LOAD_CONST                      3: b'<COAddr>\x07\x00\x00\x1a\x10\x05\x00\x00\x00\x00\x00\x00\x00\x00\x00\x00\x00\x00\x00\x00'
                10      BUILD_TUPLE                     1
                12      CALL_FUNCTION_EX                0
                14      POP_TOP                         
                16      RESUME                          0
                18      NOP                             
                20      NOP                             
                22      NOP                             
                24      NOP                             
                26      NOP                             
                28      NOP                             
                30      LOAD_FAST                       4: stop_thread
                32      LOAD_ATTR                       1: is_set
                52      CALL                            0
                60      POP_JUMP_IF_FALSE               10 (to 82)
                62      LOAD_GLOBAL                     3: NULL + StopProgram
                72      CALL                            0
                80      RAISE_VARARGS                   1
                82      LOAD_FAST                       0: data
                84      LOAD_CONST                      4: 'Accounts'
                86      BINARY_SUBSCR                   
                90      STORE_FAST                      6: _var_var_6
                92      LOAD_GLOBAL                     5: NULL + isinstance
                102     LOAD_FAST                       6: _var_var_6
                104     LOAD_GLOBAL                     6: list
                114     CALL                            2
                122     POP_JUMP_IF_TRUE                3 (to 130)
                124     LOAD_FAST                       6: _var_var_6
                126     BUILD_LIST                      1
                128     STORE_FAST                      6: _var_var_6
                130     LOAD_GLOBAL                     9: NULL + int
                140     LOAD_GLOBAL                     11: NULL + len
                150     LOAD_FAST                       6: _var_var_6
                152     CALL                            1
                160     CALL                            1
                168     LOAD_CONST                      5: 1
                170     COMPARE_OP                      2 (<)
                174     POP_JUMP_IF_FALSE               44 (to 264)
                176     LOAD_GLOBAL                     13: NULL + eel
                186     LOAD_ATTR                       14: sendErrorBox
                206     LOAD_GLOBAL                     16: Lang
                216     PUSH_NULL                       
                218     LOAD_CONST                      1: '__pyarmor_assert_14388__'
                220     LOAD_CONST                      6: 'select_accounts_works'   # b'\x81\xf1\x1d\x1f6\xf9\xaa\xed\x1a\xf9\x0e\xcfy\xe2\xec\x960J\xb4\xb5\xa1\xd8'
                222     CALL                            1
                230     BINARY_SUBSCR                   
                234     CALL                            1
                242     POP_TOP                         
                244     LOAD_GLOBAL                     3: NULL + StopProgram
                254     CALL                            0
                262     RAISE_VARARGS                   1
                264     LOAD_FAST                       0: data
                266     LOAD_CONST                      7: 'Settings'
                268     BINARY_SUBSCR                   
                272     LOAD_ATTR                       19: get
                292     PUSH_NULL                       
                294     LOAD_CONST                      1: '__pyarmor_assert_14388__'
                296     LOAD_CONST                      8: 'thread_rules'   # b'\x81\xf6\x10\x016\xfb\xba\xed\t\xef\x01\xc5\x7f'
                298     CALL                            1
                306     CALL                            1
                314     LOAD_CONST                      9: True
                316     COMPARE_OP                      40 (==)
                320     POP_JUMP_IF_FALSE               36 (to 394)
                322     LOAD_GLOBAL                     9: NULL + int
                332     LOAD_FAST                       0: data
                334     LOAD_CONST                      7: 'Settings'
                336     BINARY_SUBSCR                   
                340     LOAD_ATTR                       19: get
                360     PUSH_NULL                       
                362     LOAD_CONST                      1: '__pyarmor_assert_14388__'
                364     LOAD_CONST                      10: 'thread_count'   # b'\x81\xf6\x10\x016\xfb\xba\xed\x18\xf5\x18\xcex'
                366     CALL                            1
                374     CALL                            1
                382     CALL                            1
                390     STORE_FAST                      7: _var_var_7
                392     JUMP_FORWARD                    11 (to 416)
                394     LOAD_FAST                       1: config
                396     PUSH_NULL                       
                398     LOAD_CONST                      1: '__pyarmor_assert_14388__'
                400     LOAD_CONST                      10: 'thread_count'   # b'\x81\xf6\x10\x016\xfb\xba\xed\x18\xf5\x18\xcex'
                402     CALL                            1
                410     BINARY_SUBSCR                   
                414     STORE_FAST                      7: _var_var_7
                416     LOAD_GLOBAL                     21: NULL + db_reg_statistic
                426     CALL                            0
                434     LOAD_ATTR                       23: create
                454     CALL                            0
                462     STORE_FAST                      8: _var_var_8
                464     LOAD_GLOBAL                     25: NULL + Logs
                474     LOAD_ATTR                       26: LangCheck
                494     CALL                            0
                502     POP_TOP                         
                504     LOAD_GLOBAL                     29: NULL + set_task_manager
                514     LOAD_FAST                       2: pid
                516     BUILD_LIST                      0
                518     LOAD_CONST                      11: 'Tokens'
                520     KW_NAMES                        12: ('accounts', 'name')
                522     CALL                            3
                530     POP_TOP                         
                532     LOAD_GLOBAL                     30: concurrent
                542     LOAD_ATTR                       32: futures
                562     LOAD_ATTR                       35: ThreadPoolExecutor
                582     LOAD_FAST                       7: _var_var_7
                584     KW_NAMES                        13: ('max_workers',)
                586     CALL                            1
                594     BEFORE_WITH                     
                596     STORE_FAST                      9: _var_var_9
                598     BUILD_LIST                      0
                600     STORE_FAST                      10: _var_var_10
                602     LOAD_GLOBAL                     11: NULL + len
                612     LOAD_FAST                       6: _var_var_6
                614     CALL                            1
                622     STORE_FAST                      11: _var_var_11
                624     LOAD_FAST                       7: _var_var_7
                626     STORE_FAST                      12: _var_var_12
                628     LOAD_FAST                       11: _var_var_11
                630     STORE_FAST                      13: _var_var_13
                632     LOAD_CONST                      14: 0
                634     STORE_FAST                      14: _var_var_14
                636     LOAD_GLOBAL                     13: NULL + eel
                646     LOAD_ATTR                       36: StreamStat
                666     LOAD_GLOBAL                     39: NULL + json
                676     LOAD_ATTR                       40: dumps
                696     LOAD_CONST                      15: 'st_task'
                698     LOAD_FAST                       11: _var_var_11
                700     PUSH_NULL                       
                702     LOAD_CONST                      1: '__pyarmor_assert_14388__'
                704     LOAD_CONST                      16: 'st_stream'   # b'\x81\xf1\x0c, \xee\xac\xd7\x1a\xf7'
                706     CALL                            1
                714     LOAD_FAST                       12: _var_var_12
                716     LOAD_CONST                      17: 'st_wait'
                718     LOAD_FAST                       13: _var_var_13
                720     LOAD_CONST                      18: 'st_done'
                722     LOAD_FAST                       14: _var_var_14
                724     BUILD_MAP                       4
                726     CALL                            1
                734     CALL                            1
                742     POP_TOP                         
                744     LOAD_FAST                       6: _var_var_6
                746     GET_ITER                        
                748     FOR_ITER                        44 (to 838)
                752     STORE_FAST                      15: _var_var_15
                754     LOAD_FAST                       10: _var_var_10
                756     LOAD_ATTR                       43: append
                776     LOAD_FAST                       9: _var_var_9
                778     LOAD_ATTR                       45: submit
                798     LOAD_GLOBAL                     46: worker
                808     LOAD_FAST                       15: _var_var_15
                810     LOAD_FAST                       1: config
                812     LOAD_FAST                       3: proxy
                814     LOAD_FAST                       0: data
                816     LOAD_FAST                       8: _var_var_8
                818     LOAD_FAST                       4: stop_thread
                820     CALL                            7
                828     CALL                            1
                836     POP_TOP                         
                838     JUMP_BACKWARD                   46 (to 748)
                840     END_FOR                         
                842     LOAD_GLOBAL                     30: concurrent
                852     LOAD_ATTR                       32: futures
                872     LOAD_ATTR                       49: as_completed
                892     LOAD_FAST                       10: _var_var_10
                894     CALL                            1
                902     GET_ITER                        
                904     FOR_ITER                        66 (to 1038)
                908     STORE_FAST                      16: _var_var_16
                910     LOAD_FAST                       14: _var_var_14
                912     LOAD_CONST                      5: 1
                914     BINARY_OP                       13 (+=)
                918     STORE_FAST                      14: _var_var_14
                920     LOAD_FAST                       13: _var_var_13
                922     LOAD_CONST                      5: 1
                924     BINARY_OP                       23 (-=)
                928     STORE_FAST                      13: _var_var_13
                930     LOAD_GLOBAL                     13: NULL + eel
                940     LOAD_ATTR                       36: StreamStat
                960     LOAD_GLOBAL                     39: NULL + json
                970     LOAD_ATTR                       40: dumps
                990     LOAD_CONST                      15: 'st_task'
                992     LOAD_FAST                       11: _var_var_11
                994     PUSH_NULL                       
                996     LOAD_CONST                      1: '__pyarmor_assert_14388__'
                998     LOAD_CONST                      16: 'st_stream'   # b'\x81\xf1\x0c, \xee\xac\xd7\x1a\xf7'
                1000    CALL                            1
                1008    LOAD_FAST                       12: _var_var_12
                1010    LOAD_CONST                      17: 'st_wait'
                1012    LOAD_FAST                       13: _var_var_13
                1014    LOAD_CONST                      18: 'st_done'
                1016    LOAD_FAST                       14: _var_var_14
                1018    BUILD_MAP                       4
                1020    CALL                            1
                1028    CALL                            1
                1036    POP_TOP                         
                1038    JUMP_BACKWARD                   68 (to 904)
                1040    END_FOR                         
                1042    NOP                             
                1044    LOAD_CONST                      0: None
                1046    LOAD_CONST                      0: None
                1048    LOAD_CONST                      0: None
                1050    CALL                            2
                1058    POP_TOP                         
                1060    LOAD_GLOBAL                     55: NULL + del_task_manager
                1070    LOAD_FAST                       2: pid
                1072    CALL                            1
                1080    POP_TOP                         
                1082    LOAD_GLOBAL                     57: NULL + StopDetect
                1092    LOAD_FAST                       4: stop_thread
                1094    CALL                            1
                1102    POP_TOP                         
                1104    NOP                             
                1106    LOAD_CONST                      20: 'Done'
                1108    NOP                             
                1110    NOP                             
                1112    NOP                             
                1114    JUMP_FORWARD                    117 (to 1350)
                1122    POP_TOP                         
                1124    RETURN_CONST                    20: 'Done'
                1126    PUSH_EXC_INFO                   
                1128    WITH_EXCEPT_START               
                1130    POP_JUMP_IF_TRUE                1 (to 1134)
                1132    RERAISE                         2
                1134    POP_TOP                         
                1136    POP_EXCEPT                      
                1138    POP_TOP                         
                1140    POP_TOP                         
                1142    JUMP_BACKWARD                   42 (to 1060)
                1144    COPY                            3
                1146    POP_EXCEPT                      
                1148    RERAISE                         1
                1150    PUSH_EXC_INFO                   
                1152    LOAD_GLOBAL                     2: StopProgram
                1162    CHECK_EXC_MATCH                 
                1164    POP_JUMP_IF_FALSE               3 (to 1172)
                1166    POP_TOP                         
                1168    POP_EXCEPT                      
                1170    JUMP_BACKWARD                   56 (to 1060)
                1172    LOAD_GLOBAL                     50: BaseException
                1182    CHECK_EXC_MATCH                 
                1184    POP_JUMP_IF_FALSE               26 (to 1238)
                1186    STORE_FAST                      17: _var_var_3
                1188    PUSH_NULL                       
                1190    LOAD_GLOBAL                     53: NULL + logging
                1200    LOAD_FAST                       17: _var_var_3
                1202    CALL                            1
                1210    CALL                            0
                1218    POP_TOP                         
                1220    POP_EXCEPT                      
                1222    LOAD_CONST                      0: None
                1224    STORE_FAST                      17: _var_var_3
                1226    DELETE_FAST                     17: _var_var_3
                1228    JUMP_BACKWARD                   85 (to 1060)
                1230    LOAD_CONST                      0: None
                1232    STORE_FAST                      17: _var_var_3
                1234    DELETE_FAST                     17: _var_var_3
                1236    RERAISE                         1
                1238    RERAISE                         0
                1240    COPY                            3
                1242    POP_EXCEPT                      
                1244    RERAISE                         1
                1246    PUSH_EXC_INFO                   
                1248    LOAD_GLOBAL                     55: NULL + del_task_manager
                1258    LOAD_FAST                       2: pid
                1260    CALL                            1
                1268    POP_TOP                         
                1270    LOAD_GLOBAL                     57: NULL + StopDetect
                1280    LOAD_FAST                       4: stop_thread
                1282    CALL                            1
                1290    POP_TOP                         
                1292    POP_TOP                         
                1294    POP_EXCEPT                      
                1296    LOAD_CONST                      20: 'Done'
                1298    NOP                             
                1300    NOP                             
                1302    NOP                             
                1304    JUMP_FORWARD                    22 (to 1350)
                1312    POP_TOP                         
                1314    RETURN_CONST                    20: 'Done'
                1316    COPY                            3
                1318    POP_EXCEPT                      
                1320    RERAISE                         1
                1322    PUSH_EXC_INFO                   
                1324    PUSH_NULL                       
                1326    LOAD_CONST                      19: '__pyarmor_exit_14390__'
                1328    NOP                             
                1330    LOAD_CONST                      3: b'<COAddr>\x07\x00\x00\x1a\x10\x05\x00\x00\x00\x00\x00\x00\x00\x00\x00\x00\x00\x00\x00\x00'
                1332    CALL                            1
                1340    POP_TOP                         
                1342    RERAISE                         0
                1344    COPY                            3
                1346    POP_EXCEPT                      
                1348    RERAISE                         1
                1350    PUSH_NULL                       
                1352    LOAD_CONST                      19: '__pyarmor_exit_14390__'
                1354    LOAD_CONST                      3: b'<COAddr>\x07\x00\x00\x1a\x10\x05\x00\x00\x00\x00\x00\x00\x00\x00\x00\x00\x00\x00\x00\x00'
                1356    BUILD_TUPLE                     1
                1358    CALL_FUNCTION_EX                0
                1360    POP_TOP                         
                1362    RETURN_VALUE                    
            [Exception Table]
                30 to 596 -> 1150 [0] 
                596 to 1042 -> 1126 [1] lasti
                1044 to 1060 -> 1150 [0] 
                1060 to 1104 -> 1322 [0] 
                1126 to 1136 -> 1144 [3] lasti
                1136 to 1150 -> 1150 [0] 
                1150 to 1168 -> 1240 [1] lasti
                1168 to 1172 -> 1246 [0] 
                1172 to 1188 -> 1240 [1] lasti
                1188 to 1220 -> 1230 [1] lasti
                1220 to 1230 -> 1246 [0] 
                1230 to 1240 -> 1240 [1] lasti
                1240 to 1246 -> 1246 [0] 
                1246 to 1294 -> 1316 [1] lasti
                1294 to 1296 -> 1322 [0] 
                1316 to 1322 -> 1322 [0] 
                1322 to 1344 -> 1344 [1] lasti
        [Code]
            File Name: <frozen program.modules.Registrator_tokens>
            Object Name: worker
            Qualified Name: worker
            Arg Count: 6
            Pos Only Arg Count: 0
            KW Only Arg Count: 0
            Stack Size: 10
            Flags: 0x20000003 (CO_OPTIMIZED | CO_NEWLOCALS | CO_PYARMOR_OBFUSCATED)
            [Names]
                'Thread_wait'
                'get_account_json'
                'get_account_proxy'
                'is_set'
                'StopProgram'
                'Logs'
                'PrintLog'
                'db_reg_statistic'
                'insert'
                'get_anti_safety_key'
                'Lang'
                'AntiSafety'
                'apikey'
                'token'
                'asyncio'
                'new_event_loop'
                'set_event_loop'
                'VersionControl'
                'check'
                'proxy_hide'
                'TelegramClient'
                'get_logger'
                'connect'
                'functions'
                'contacts'
                'GetBirthdaysRequest'
                'BaseException'
                'os'
                'urandom'
                'account'
                'RegisterDeviceRequest'
                'get_me'
                'id'
                'base64'
                'b64encode'
                'decode'
                'json_file'
                'write'
                'Disconnect'
                'Exception'
                'type'
                '__name__'
                'logging'
            [Locals+Names]
                'account'
                'config'
                'proxy'
                'data'
                'statistic'
                'stop_thread'
                '__assert_armored__'
                '_var_var_17'
                '_var_var_18'
                '_var_var_19'
                '_var_var_20'
                '_var_var_21'
                '_var_var_22'
                '_var_var_23'
                '_var_var_24'
                '_var_var_25'
                '_var_var_26'
                '_var_var_27'
                '_var_var_28'
                '_var_var_29'
                '_var_var_30'
                '_var_var_31'
                '_var_var_32'
                '_var_var_33'
                '_var_var_34'
                '_var_var_35'
                '_var_var_36'
                '_var_var_37'
                '_var_var_3'
            [Constants]
                None
                '__pyarmor_assert_14391__'
                '__pyarmor_enter_14392__'
                b'<COAddr>\x07\x00\x00\x1a\xba\x0f\x00\x00\x00\x00\x00\x00\x00\x00\x00\x00\x00\x00\x00\x00'
                'sessions/active'   # b'\x81\xf1\x1d\x00 \xf3\xb1\xdc\x08\xb5\x0c\xc3x\xe5\xee\x80'
                'proxy'
                'ipv6'
                '/'
                '.json'
                '.session'
                'Settings'
                'antisafetynet_key_1'   # b'\x81\xe3\x16\x07:\xe9\xbf\xd4\x1e\xee\x14\xcei\xf8\xc7\x8e\nD\x84\xf6'
                'antisafetynet_key_2'   # b'\x81\xe3\x16\x07:\xe9\xbf\xd4\x1e\xee\x14\xcei\xf8\xc7\x8e\nD\x84\xf5'
                'reg_reserve_time'   # b'\x81\xf0\x1d\x14\x0c\xe8\xbb\xc1\x1e\xe8\x1b\xc5S\xf8\xf1\x88\n'
                'Done'
                'app_id'
                (
                    4
                    6
                    21724
                )
                'На этот аккаунт нельзя привязать токен'   # b'\x81R\xe5\xa3\xe3\xba\x0f?\xaa\x18\xbd\x1e\xdd\x0e\xb85\xdf\xeda\x17p{\x9e}\xe6\xdf~\xed\xe2\xf1\xae8\x8a\x87\x90\xd6)&\x04\xf9\xa9\x06\xb8\xed\x02i\xef\xf7\xef]\x84Jh\xc0\xd1]\xe7Zy\xac\xf4\x0b\x80\xb1\xe7\x96\xb5Ym\xe2\\b'
                (
                    'config'
                    'account'
                    'message'
                )
                'done'
                (
                    'account'
                    'status'
                )
                ''
                '__pyarmor_exit_14393__'
                'device_token'   # b'\x81\xe6\x1d\x05:\xf9\xbb\xed\x0f\xf5\x06\xc5b'
                'На аккаунте уже есть push токен'   # b'\x81R\xe5\xa3\xe3\xba\x0e\x02\xab \xbd\x1a\xdc<If\xbf\x80\nE\x1a\x1e\x0e}\xe6\xdfu\xec\xd5\xf1\xae0\x8b\xb3\x91\xef)&\xf4>\r\xfa\xf0\x1dl:\xbf\x99\x877\xe6.7\xad'
                'reg_app_id_and_antisafety'   # b'\x81\xf0\x1d\x14\x0c\xfb\xae\xc2$\xf3\t\xffm\xe2\xfc\xba\x0eS\xaf\xae\xb9\xcaH\xc9\x11v'
                (
                    'reserve_time'
                    'stop_thread'
                )
                'get_push_token'   # b'\x81\xe5\x1d\x07\x0c\xea\xab\xc1\x13\xc5\x19\xcfg\xe9\xf6'
                True
                'app_version'   # b'\x81\xe3\x08\x03\x0c\xec\xbb\xc0\x08\xf3\x02\xce'
                (
                    'config'
                    'account'
                    'message'
                    'param'
                )
                'session'
                'api_id'
                'api_hash'
                'app_hash'
                'device_model'
                'device'
                'system_version'
                'sdk'
                'app_version'
                'lang_code'
                'lang_code'   # b'\x81\xee\x19\x1d4\xc5\xbd\xdd\x1f\xff'
                'system_lang_code'
                'system_lang_code'   # b"\x81\xf1\x01\x00'\xff\xb3\xed\x17\xfb\x03\xc7S\xef\xf7\x81\n"
                'lang_pack'
                'lang_pack'   # b'\x81\xee\x19\x1d4\xc5\xae\xd3\x18\xf1'
                'device_token'
                'tz_offset'
                'tz_offset'   # b'\x81\xf6\x02,<\xfc\xb8\xc1\x1e\xee'
                'perf_cat'
                0
                'use_ipv6'
                1
                'timeout'
                'request_retries'
                'connection_retries'
                60
                'retry_delay'
                2
                'flood_sleep_threshold'
                'flood_wait'   # b'\x81\xe4\x14\x1c<\xfe\x81\xc5\x1a\xf3\x19'
                'auto_reconnect'
                'sequential_updates'
                'receive_updates'
                'raise_last_call_error'
                'stop_thread'
                'base_logger'
                'loop'
                'connected'   # b'\x81\xe1\x17\x1d=\xff\xbd\xc6\x1e\xfe'
                256
                False
                (
                    'token_type'
                    'token'
                    'app_sandbox'
                    'secret'
                    'other_uids'
                    'no_muted'
                )
                'Ошибка привязки токена'   # b'\x81R\xe6\xa2\xdbJfb\xcaJ\xd7p\xbc\xacHZ\xbe\xbd\x0b\x7f\x1a\x19\xff#\xb5\xb8\x13\x86\xb0i^T\xd8\xe2\xfe\xbdBza\x9e\xc5Y('
                'session_file'   # b'\x81\xf1\x1d\x00 \xf3\xb1\xdc$\xfc\x04\xcci'
                'phone'
                'user_id'
                'device_token_secret'   # b'\x81\xe6\x1d\x05:\xf9\xbb\xed\x0f\xf5\x06\xc5b\xd3\xeb\x80\x0cO\xbe\xb3'
                'device_secret'   # b'\x81\xe6\x1d\x05:\xf9\xbb\xed\x08\xff\x0e\xd2i\xf8'
                'signature'   # b'\x81\xf1\x11\x14=\xfb\xaa\xc7\t\xff'
                'certificate'   # b"\x81\xe1\x1d\x01'\xf3\xb8\xdb\x18\xfb\x19\xc5"
                512
                'safetynet'   # b'\x81\xf1\x19\x156\xee\xa7\xdc\x1e\xee'
                'register_time'   # b'\x81\xf0\x1d\x14:\xe9\xaa\xd7\t\xc5\x19\xc9a\xe9'
                'last_check_time'   # b"\x81\xee\x19\x00'\xc5\xbd\xda\x1e\xf9\x06\xffx\xe5\xf5\x80"
                'avatar'
                'first_name'   # b'\x81\xe4\x11\x01 \xee\x81\xdc\x1a\xf7\x08'
                'last_name'   # b"\x81\xee\x19\x00'\xc5\xb0\xd3\x16\xff"
                'username'
                'sex'
                'twoFA'
                'Tokens'
                'module'
                'TelegramExpert.pro'   # b'\x81\xd6\x1d\x1f6\xfd\xac\xd3\x16\xdf\x15\xd0i\xfe\xec\xcb\x1fO\xb4'
                'program'
                'Stop'
                (
                )
            [Disassembly]
                0       NOP                             
                2       NOP                             
                4       PUSH_NULL                       
                6       LOAD_CONST                      2: '__pyarmor_enter_14392__'
                8       LOAD_CONST                      3: b'<COAddr>\x07\x00\x00\x1a\xba\x0f\x00\x00\x00\x00\x00\x00\x00\x00\x00\x00\x00\x00\x00\x00'
                10      BUILD_TUPLE                     1
                12      CALL_FUNCTION_EX                0
                14      POP_TOP                         
                16      RESUME                          0
                18      NOP                             
                20      NOP                             
                22      NOP                             
                24      NOP                             
                26      NOP                             
                28      NOP                             
                30      LOAD_GLOBAL                     1: NULL + Thread_wait
                40      LOAD_FAST                       3: data
                42      LOAD_FAST                       1: config
                44      LOAD_FAST                       5: stop_thread
                46      CALL                            3
                54      POP_TOP                         
                56      PUSH_NULL                       
                58      LOAD_CONST                      1: '__pyarmor_assert_14391__'
                60      LOAD_CONST                      4: 'sessions/active'   # b'\x81\xf1\x1d\x00 \xf3\xb1\xdc\x08\xb5\x0c\xc3x\xe5\xee\x80'
                62      CALL                            1
                70      STORE_FAST                      7: _var_var_17
                72      LOAD_GLOBAL                     3: NULL + get_account_json
                82      LOAD_FAST                       0: account
                84      LOAD_FAST                       7: _var_var_17
                86      CALL                            2
                94      STORE_FAST                      8: _var_var_18
                96      LOAD_GLOBAL                     5: NULL + get_account_proxy
                106     LOAD_FAST                       1: config
                108     LOAD_FAST                       2: proxy
                110     LOAD_FAST                       8: _var_var_18
                112     LOAD_CONST                      5: 'proxy'
                114     BINARY_SUBSCR                   
                118     LOAD_FAST                       8: _var_var_18
                120     LOAD_CONST                      6: 'ipv6'
                122     BINARY_SUBSCR                   
                126     CALL                            4
                134     STORE_FAST                      9: _var_var_19
                136     LOAD_FAST                       7: _var_var_17
                138     FORMAT_VALUE                    0 (FVC_NONE)
                140     LOAD_CONST                      7: '/'
                142     LOAD_FAST                       0: account
                144     FORMAT_VALUE                    0 (FVC_NONE)
                146     LOAD_CONST                      8: '.json'
                148     BUILD_STRING                    4
                150     STORE_FAST                      10: _var_var_20
                152     LOAD_FAST                       7: _var_var_17
                154     FORMAT_VALUE                    0 (FVC_NONE)
                156     LOAD_CONST                      7: '/'
                158     LOAD_FAST                       0: account
                160     FORMAT_VALUE                    0 (FVC_NONE)
                162     LOAD_CONST                      9: '.session'
                164     BUILD_STRING                    4
                166     STORE_FAST                      11: _var_var_21
                168     LOAD_FAST                       3: data
                170     LOAD_CONST                      10: 'Settings'
                172     BINARY_SUBSCR                   
                176     PUSH_NULL                       
                178     LOAD_CONST                      1: '__pyarmor_assert_14391__'
                180     LOAD_CONST                      11: 'antisafetynet_key_1'   # b'\x81\xe3\x16\x07:\xe9\xbf\xd4\x1e\xee\x14\xcei\xf8\xc7\x8e\nD\x84\xf6'
                182     CALL                            1
                190     BINARY_SUBSCR                   
                194     STORE_FAST                      12: _var_var_22
                196     LOAD_FAST                       3: data
                198     LOAD_CONST                      10: 'Settings'
                200     BINARY_SUBSCR                   
                204     PUSH_NULL                       
                206     LOAD_CONST                      1: '__pyarmor_assert_14391__'
                208     LOAD_CONST                      12: 'antisafetynet_key_2'   # b'\x81\xe3\x16\x07:\xe9\xbf\xd4\x1e\xee\x14\xcei\xf8\xc7\x8e\nD\x84\xf5'
                210     CALL                            1
                218     BINARY_SUBSCR                   
                222     STORE_FAST                      13: _var_var_23
                224     LOAD_FAST                       3: data
                226     LOAD_CONST                      10: 'Settings'
                228     BINARY_SUBSCR                   
                232     PUSH_NULL                       
                234     LOAD_CONST                      1: '__pyarmor_assert_14391__'
                236     LOAD_CONST                      13: 'reg_reserve_time'   # b'\x81\xf0\x1d\x14\x0c\xe8\xbb\xc1\x1e\xe8\x1b\xc5S\xf8\xf1\x88\n'
                238     CALL                            1
                246     BINARY_SUBSCR                   
                250     STORE_FAST                      14: _var_var_24
                252     LOAD_CONST                      14: 'Done'
                254     STORE_FAST                      15: _var_var_25
                256     LOAD_FAST                       5: stop_thread
                258     LOAD_ATTR                       7: is_set
                278     CALL                            0
                286     POP_JUMP_IF_FALSE               10 (to 308)
                288     LOAD_GLOBAL                     9: NULL + StopProgram
                298     CALL                            0
                306     RAISE_VARARGS                   1
                308     LOAD_FAST                       8: _var_var_18
                310     LOAD_CONST                      15: 'app_id'
                312     BINARY_SUBSCR                   
                316     LOAD_CONST                      16: (4, 6, 21724)
                318     CONTAINS_OP                     1 (not in)
                320     POP_JUMP_IF_FALSE               101 (to 524)
                322     LOAD_GLOBAL                     11: NULL + Logs
                332     LOAD_ATTR                       12: PrintLog
                352     LOAD_FAST                       1: config
                354     LOAD_FAST                       0: account
                356     PUSH_NULL                       
                358     LOAD_CONST                      1: '__pyarmor_assert_14391__'
                360     LOAD_CONST                      17: 'На этот аккаунт нельзя привязать токен'   # b'\x81R\xe5\xa3\xe3\xba\x0f?\xaa\x18\xbd\x1e\xdd\x0e\xb85\xdf\xeda\x17p{\x9e}\xe6\xdf~\xed\xe2\xf1\xae8\x8a\x87\x90\xd6)&\x04\xf9\xa9\x06\xb8\xed\x02i\xef\xf7\xef]\x84Jh\xc0\xd1]\xe7Zy\xac\xf4\x0b\x80\xb1\xe7\x96\xb5Ym\xe2\\b'
                362     CALL                            1
                370     KW_NAMES                        18: ('config', 'account', 'message')
                372     CALL                            3
                380     POP_TOP                         
                382     LOAD_FAST                       0: account
                384     LOAD_CONST                      19: 'done'
                386     LOAD_CONST                      20: ('account', 'status')
                388     BUILD_CONST_KEY_MAP             2
                390     LOAD_GLOBAL                     11: NULL + Logs
                400     LOAD_ATTR                       12: PrintLog
                420     LOAD_FAST                       1: config
                422     LOAD_FAST                       0: account
                424     LOAD_FAST                       15: _var_var_25
                426     KW_NAMES                        18: ('config', 'account', 'message')
                428     CALL                            3
                436     POP_TOP                         
                438     LOAD_GLOBAL                     15: NULL + db_reg_statistic
                448     LOAD_FAST                       4: statistic
                450     CALL                            1
                458     LOAD_ATTR                       17: insert
                478     LOAD_FAST                       0: account
                480     LOAD_FAST                       15: _var_var_25
                482     CALL                            2
                490     POP_TOP                         
                492     LOAD_CONST                      21: ''
                494     LOAD_CONST                      19: 'done'
                496     LOAD_CONST                      20: ('account', 'status')
                498     BUILD_CONST_KEY_MAP             2
                500     SWAP                            2
                502     POP_TOP                         
                504     NOP                             
                506     NOP                             
                508     JUMP_FORWARD                    1784 (to 4080)
                512     CALL                            1
                520     POP_TOP                         
                522     RETURN_VALUE                    
                524     LOAD_FAST                       8: _var_var_18
                526     PUSH_NULL                       
                528     LOAD_CONST                      1: '__pyarmor_assert_14391__'
                530     LOAD_CONST                      23: 'device_token'   # b'\x81\xe6\x1d\x05:\xf9\xbb\xed\x0f\xf5\x06\xc5b'
                532     CALL                            1
                540     BINARY_SUBSCR                   
                544     POP_JUMP_IF_FALSE               101 (to 748)
                546     LOAD_GLOBAL                     11: NULL + Logs
                556     LOAD_ATTR                       12: PrintLog
                576     LOAD_FAST                       1: config
                578     LOAD_FAST                       0: account
                580     PUSH_NULL                       
                582     LOAD_CONST                      1: '__pyarmor_assert_14391__'
                584     LOAD_CONST                      24: 'На аккаунте уже есть push токен'   # b'\x81R\xe5\xa3\xe3\xba\x0e\x02\xab \xbd\x1a\xdc<If\xbf\x80\nE\x1a\x1e\x0e}\xe6\xdfu\xec\xd5\xf1\xae0\x8b\xb3\x91\xef)&\xf4>\r\xfa\xf0\x1dl:\xbf\x99\x877\xe6.7\xad'
                586     CALL                            1
                594     KW_NAMES                        18: ('config', 'account', 'message')
                596     CALL                            3
                604     POP_TOP                         
                606     LOAD_FAST                       0: account
                608     LOAD_CONST                      19: 'done'
                610     LOAD_CONST                      20: ('account', 'status')
                612     BUILD_CONST_KEY_MAP             2
                614     LOAD_GLOBAL                     11: NULL + Logs
                624     LOAD_ATTR                       12: PrintLog
                644     LOAD_FAST                       1: config
                646     LOAD_FAST                       0: account
                648     LOAD_FAST                       15: _var_var_25
                650     KW_NAMES                        18: ('config', 'account', 'message')
                652     CALL                            3
                660     POP_TOP                         
                662     LOAD_GLOBAL                     15: NULL + db_reg_statistic
                672     LOAD_FAST                       4: statistic
                674     CALL                            1
                682     LOAD_ATTR                       17: insert
                702     LOAD_FAST                       0: account
                704     LOAD_FAST                       15: _var_var_25
                706     CALL                            2
                714     POP_TOP                         
                716     LOAD_CONST                      21: ''
                718     LOAD_CONST                      19: 'done'
                720     LOAD_CONST                      20: ('account', 'status')
                722     BUILD_CONST_KEY_MAP             2
                724     SWAP                            2
                726     POP_TOP                         
                728     NOP                             
                730     NOP                             
                732     JUMP_FORWARD                    1672 (to 4080)
                736     CALL                            1
                744     POP_TOP                         
                746     RETURN_VALUE                    
                748     LOAD_GLOBAL                     19: NULL + get_anti_safety_key
                758     LOAD_FAST                       8: _var_var_18
                760     LOAD_CONST                      15: 'app_id'
                762     BINARY_SUBSCR                   
                766     LOAD_FAST                       12: _var_var_22
                768     LOAD_FAST                       13: _var_var_23
                770     CALL                            3
                778     STORE_FAST                      16: _var_var_26
                780     LOAD_FAST                       16: _var_var_26
                782     POP_JUMP_IF_TRUE                108 (to 1000)
                784     LOAD_GLOBAL                     11: NULL + Logs
                794     LOAD_ATTR                       12: PrintLog
                814     LOAD_FAST                       1: config
                816     LOAD_FAST                       0: account
                818     LOAD_GLOBAL                     20: Lang
                828     PUSH_NULL                       
                830     LOAD_CONST                      1: '__pyarmor_assert_14391__'
                832     LOAD_CONST                      25: 'reg_app_id_and_antisafety'   # b'\x81\xf0\x1d\x14\x0c\xfb\xae\xc2$\xf3\t\xffm\xe2\xfc\xba\x0eS\xaf\xae\xb9\xcaH\xc9\x11v'
                834     CALL                            1
                842     BINARY_SUBSCR                   
                846     KW_NAMES                        18: ('config', 'account', 'message')
                848     CALL                            3
                856     POP_TOP                         
                858     LOAD_FAST                       0: account
                860     LOAD_CONST                      19: 'done'
                862     LOAD_CONST                      20: ('account', 'status')
                864     BUILD_CONST_KEY_MAP             2
                866     LOAD_GLOBAL                     11: NULL + Logs
                876     LOAD_ATTR                       12: PrintLog
                896     LOAD_FAST                       1: config
                898     LOAD_FAST                       0: account
                900     LOAD_FAST                       15: _var_var_25
                902     KW_NAMES                        18: ('config', 'account', 'message')
                904     CALL                            3
                912     POP_TOP                         
                914     LOAD_GLOBAL                     15: NULL + db_reg_statistic
                924     LOAD_FAST                       4: statistic
                926     CALL                            1
                934     LOAD_ATTR                       17: insert
                954     LOAD_FAST                       0: account
                956     LOAD_FAST                       15: _var_var_25
                958     CALL                            2
                966     POP_TOP                         
                968     LOAD_CONST                      21: ''
                970     LOAD_CONST                      19: 'done'
                972     LOAD_CONST                      20: ('account', 'status')
                974     BUILD_CONST_KEY_MAP             2
                976     SWAP                            2
                978     POP_TOP                         
                980     NOP                             
                982     NOP                             
                984     JUMP_FORWARD                    1546 (to 4080)
                988     CALL                            1
                996     POP_TOP                         
                998     RETURN_VALUE                    
                1000    LOAD_GLOBAL                     23: NULL + AntiSafety
                1010    LOAD_FAST                       14: _var_var_24
                1012    LOAD_FAST                       5: stop_thread
                1014    KW_NAMES                        26: ('reserve_time', 'stop_thread')
                1016    CALL                            2
                1024    STORE_FAST                      17: _var_var_27
                1026    LOAD_FAST                       16: _var_var_26
                1028    LOAD_FAST                       17: _var_var_27
                1030    STORE_ATTR                      12: apikey
                1040    LOAD_GLOBAL                     11: NULL + Logs
                1050    LOAD_ATTR                       12: PrintLog
                1070    LOAD_FAST                       1: config
                1072    LOAD_FAST                       0: account
                1074    LOAD_GLOBAL                     20: Lang
                1084    PUSH_NULL                       
                1086    LOAD_CONST                      1: '__pyarmor_assert_14391__'
                1088    LOAD_CONST                      27: 'get_push_token'   # b'\x81\xe5\x1d\x07\x0c\xea\xab\xc1\x13\xc5\x19\xcfg\xe9\xf6'
                1090    CALL                            1
                1098    BINARY_SUBSCR                   
                1102    KW_NAMES                        18: ('config', 'account', 'message')
                1104    CALL                            3
                1112    POP_TOP                         
                1114    LOAD_FAST                       17: _var_var_27
                1116    LOAD_ATTR                       27: token
                1136    CALL                            0
                1144    UNPACK_SEQUENCE                 2
                1148    STORE_FAST                      18: _var_var_28
                1150    STORE_FAST                      19: _var_var_29
                1152    LOAD_GLOBAL                     29: NULL + asyncio
                1162    LOAD_ATTR                       30: new_event_loop
                1182    CALL                            0
                1190    STORE_FAST                      20: _var_var_30
                1192    LOAD_GLOBAL                     29: NULL + asyncio
                1202    LOAD_ATTR                       32: set_event_loop
                1222    LOAD_FAST                       20: _var_var_30
                1224    CALL                            1
                1232    POP_TOP                         
                1234    LOAD_GLOBAL                     35: NULL + VersionControl
                1244    LOAD_FAST                       1: config
                1246    LOAD_GLOBAL                     20: Lang
                1256    LOAD_CONST                      28: True
                1258    CALL                            3
                1266    LOAD_ATTR                       37: check
                1286    LOAD_FAST                       0: account
                1288    LOAD_FAST                       8: _var_var_18
                1290    LOAD_CONST                      15: 'app_id'
                1292    BINARY_SUBSCR                   
                1296    LOAD_FAST                       8: _var_var_18
                1298    PUSH_NULL                       
                1300    LOAD_CONST                      1: '__pyarmor_assert_14391__'
                1302    LOAD_CONST                      29: 'app_version'   # b'\x81\xe3\x08\x03\x0c\xec\xbb\xc0\x08\xf3\x02\xce'
                1304    CALL                            1
                1312    BINARY_SUBSCR                   
                1316    CALL                            3
                1324    STORE_FAST                      21: _var_var_31
                1326    LOAD_FAST                       21: _var_var_31
                1328    POP_JUMP_IF_TRUE                71 (to 1472)
                1330    LOAD_FAST                       0: account
                1332    LOAD_CONST                      19: 'done'
                1334    LOAD_CONST                      20: ('account', 'status')
                1336    BUILD_CONST_KEY_MAP             2
                1338    LOAD_GLOBAL                     11: NULL + Logs
                1348    LOAD_ATTR                       12: PrintLog
                1368    LOAD_FAST                       1: config
                1370    LOAD_FAST                       0: account
                1372    LOAD_FAST                       15: _var_var_25
                1374    KW_NAMES                        18: ('config', 'account', 'message')
                1376    CALL                            3
                1384    POP_TOP                         
                1386    LOAD_GLOBAL                     15: NULL + db_reg_statistic
                1396    LOAD_FAST                       4: statistic
                1398    CALL                            1
                1406    LOAD_ATTR                       17: insert
                1426    LOAD_FAST                       0: account
                1428    LOAD_FAST                       15: _var_var_25
                1430    CALL                            2
                1438    POP_TOP                         
                1440    LOAD_CONST                      21: ''
                1442    LOAD_CONST                      19: 'done'
                1444    LOAD_CONST                      20: ('account', 'status')
                1446    BUILD_CONST_KEY_MAP             2
                1448    SWAP                            2
                1450    POP_TOP                         
                1452    NOP                             
                1454    NOP                             
                1456    JUMP_FORWARD                    1310 (to 4080)
                1460    CALL                            1
                1468    POP_TOP                         
                1470    RETURN_VALUE                    
                1472    LOAD_GLOBAL                     11: NULL + Logs
                1482    LOAD_ATTR                       12: PrintLog
                1502    LOAD_FAST                       1: config
                1504    LOAD_FAST                       0: account
                1506    LOAD_CONST                      5: 'proxy'
                1508    LOAD_GLOBAL                     39: NULL + proxy_hide
                1518    LOAD_FAST                       9: _var_var_19
                1520    CALL                            1
                1528    KW_NAMES                        30: ('config', 'account', 'message', 'param')
                1530    CALL                            4
                1538    POP_TOP                         
                1540    LOAD_GLOBAL                     41: NULL + TelegramClient
                1550    LOAD_CONST                      95: ()
                1552    BUILD_MAP                       0
                1554    LOAD_CONST                      31: 'session'
                1556    LOAD_FAST                       11: _var_var_21
                1558    MAP_ADD                         1
                1560    LOAD_CONST                      32: 'api_id'
                1562    LOAD_FAST                       8: _var_var_18
                1564    LOAD_CONST                      15: 'app_id'
                1566    BINARY_SUBSCR                   
                1570    MAP_ADD                         1
                1572    LOAD_CONST                      33: 'api_hash'
                1574    LOAD_FAST                       8: _var_var_18
                1576    LOAD_CONST                      34: 'app_hash'
                1578    BINARY_SUBSCR                   
                1582    MAP_ADD                         1
                1584    LOAD_CONST                      35: 'device_model'
                1586    LOAD_FAST                       8: _var_var_18
                1588    LOAD_CONST                      36: 'device'
                1590    BINARY_SUBSCR                   
                1594    MAP_ADD                         1
                1596    LOAD_CONST                      37: 'system_version'
                1598    LOAD_FAST                       8: _var_var_18
                1600    LOAD_CONST                      38: 'sdk'
                1602    BINARY_SUBSCR                   
                1606    MAP_ADD                         1
                1608    LOAD_CONST                      39: 'app_version'
                1610    LOAD_FAST                       8: _var_var_18
                1612    PUSH_NULL                       
                1614    LOAD_CONST                      1: '__pyarmor_assert_14391__'
                1616    LOAD_CONST                      29: 'app_version'   # b'\x81\xe3\x08\x03\x0c\xec\xbb\xc0\x08\xf3\x02\xce'
                1618    CALL                            1
                1626    BINARY_SUBSCR                   
                1630    MAP_ADD                         1
                1632    LOAD_CONST                      40: 'lang_code'
                1634    LOAD_FAST                       8: _var_var_18
                1636    PUSH_NULL                       
                1638    LOAD_CONST                      1: '__pyarmor_assert_14391__'
                1640    LOAD_CONST                      41: 'lang_code'   # b'\x81\xee\x19\x1d4\xc5\xbd\xdd\x1f\xff'
                1642    CALL                            1
                1650    BINARY_SUBSCR                   
                1654    MAP_ADD                         1
                1656    LOAD_CONST                      42: 'system_lang_code'
                1658    LOAD_FAST                       8: _var_var_18
                1660    PUSH_NULL                       
                1662    LOAD_CONST                      1: '__pyarmor_assert_14391__'
                1664    LOAD_CONST                      43: 'system_lang_code'   # b"\x81\xf1\x01\x00'\xff\xb3\xed\x17\xfb\x03\xc7S\xef\xf7\x81\n"
                1666    CALL                            1
                1674    BINARY_SUBSCR                   
                1678    MAP_ADD                         1
                1680    LOAD_CONST                      44: 'lang_pack'
                1682    LOAD_FAST                       8: _var_var_18
                1684    PUSH_NULL                       
                1686    LOAD_CONST                      1: '__pyarmor_assert_14391__'
                1688    LOAD_CONST                      45: 'lang_pack'   # b'\x81\xee\x19\x1d4\xc5\xae\xd3\x18\xf1'
                1690    CALL                            1
                1698    BINARY_SUBSCR                   
                1702    MAP_ADD                         1
                1704    LOAD_CONST                      46: 'device_token'
                1706    LOAD_FAST                       18: _var_var_28
                1708    MAP_ADD                         1
                1710    LOAD_CONST                      47: 'tz_offset'
                1712    LOAD_FAST                       8: _var_var_18
                1714    PUSH_NULL                       
                1716    LOAD_CONST                      1: '__pyarmor_assert_14391__'
                1718    LOAD_CONST                      48: 'tz_offset'   # b'\x81\xf6\x02,<\xfc\xb8\xc1\x1e\xee'
                1720    CALL                            1
                1728    BINARY_SUBSCR                   
                1732    MAP_ADD                         1
                1734    LOAD_CONST                      49: 'perf_cat'
                1736    LOAD_FAST                       8: _var_var_18
                1738    LOAD_CONST                      49: 'perf_cat'
                1740    BINARY_SUBSCR                   
                1744    MAP_ADD                         1
                1746    LOAD_CONST                      5: 'proxy'
                1748    LOAD_FAST                       9: _var_var_19
                1750    LOAD_CONST                      50: 0
                1752    BINARY_SUBSCR                   
                1756    MAP_ADD                         1
                1758    LOAD_CONST                      51: 'use_ipv6'
                1760    LOAD_FAST                       9: _var_var_19
                1762    LOAD_CONST                      52: 1
                1764    BINARY_SUBSCR                   
                1768    MAP_ADD                         1
                1770    LOAD_CONST                      53: 'timeout'
                1772    LOAD_FAST                       1: config
                1774    LOAD_CONST                      53: 'timeout'
                1776    BINARY_SUBSCR                   
                1780    MAP_ADD                         1
                1782    LOAD_CONST                      54: 'request_retries'
                1784    LOAD_CONST                      52: 1
                1786    MAP_ADD                         1
                1788    LOAD_CONST                      55: 'connection_retries'
                1790    LOAD_CONST                      56: 60
                1792    MAP_ADD                         1
                1794    LOAD_CONST                      57: 'retry_delay'
                1796    LOAD_CONST                      58: 2
                1798    MAP_ADD                         1
                1800    LOAD_CONST                      59: 'flood_sleep_threshold'
                1802    LOAD_FAST                       1: config
                1804    PUSH_NULL                       
                1806    LOAD_CONST                      1: '__pyarmor_assert_14391__'
                1808    LOAD_CONST                      60: 'flood_wait'   # b'\x81\xe4\x14\x1c<\xfe\x81\xc5\x1a\xf3\x19'
                1810    CALL                            1
                1818    BINARY_SUBSCR                   
                1822    MAP_ADD                         1
                1824    LOAD_CONST                      61: 'auto_reconnect'
                1826    LOAD_CONST                      28: True
                1828    MAP_ADD                         1
                1830    LOAD_CONST                      62: 'sequential_updates'
                1832    LOAD_CONST                      28: True
                1834    MAP_ADD                         1
                1836    LOAD_CONST                      63: 'receive_updates'
                1838    LOAD_CONST                      28: True
                1840    MAP_ADD                         1
                1842    LOAD_CONST                      64: 'raise_last_call_error'
                1844    LOAD_CONST                      28: True
                1846    MAP_ADD                         1
                1848    LOAD_CONST                      65: 'stop_thread'
                1850    LOAD_FAST                       5: stop_thread
                1852    MAP_ADD                         1
                1854    LOAD_CONST                      66: 'base_logger'
                1856    LOAD_GLOBAL                     43: NULL + get_logger
                1866    LOAD_FAST                       0: account
                1868    CALL                            1
                1876    MAP_ADD                         1
                1878    LOAD_CONST                      67: 'loop'
                1880    LOAD_FAST                       20: _var_var_30
                1882    MAP_ADD                         1
                1884    CALL_FUNCTION_EX                1
                1886    STORE_FAST                      22: _var_var_32
                1888    LOAD_FAST                       22: _var_var_32
                1890    LOAD_ATTR                       45: connect
                1910    CALL                            0
                1918    POP_TOP                         
                1920    LOAD_GLOBAL                     11: NULL + Logs
                1930    LOAD_ATTR                       12: PrintLog
                1950    LOAD_FAST                       1: config
                1952    LOAD_FAST                       0: account
                1954    LOAD_GLOBAL                     20: Lang
                1964    PUSH_NULL                       
                1966    LOAD_CONST                      1: '__pyarmor_assert_14391__'
                1968    LOAD_CONST                      68: 'connected'   # b'\x81\xe1\x17\x1d=\xff\xbd\xc6\x1e\xfe'
                1970    CALL                            1
                1978    BINARY_SUBSCR                   
                1982    KW_NAMES                        18: ('config', 'account', 'message')
                1984    CALL                            3
                1992    POP_TOP                         
                1994    NOP                             
                1996    PUSH_NULL                       
                1998    LOAD_FAST                       22: _var_var_32
                2000    LOAD_GLOBAL                     46: functions
                2010    LOAD_ATTR                       48: contacts
                2030    LOAD_ATTR                       51: GetBirthdaysRequest
                2050    CALL                            0
                2058    CALL                            1
                2066    POP_TOP                         
                2068    LOAD_GLOBAL                     55: NULL + os
                2078    LOAD_ATTR                       56: urandom
                2098    LOAD_CONST                      69: 256
                2100    CALL                            1
                2108    STORE_FAST                      23: _var_var_33
                2110    PUSH_NULL                       
                2112    LOAD_FAST                       22: _var_var_32
                2114    LOAD_GLOBAL                     46: functions
                2124    LOAD_ATTR                       58: account
                2144    LOAD_ATTR                       61: RegisterDeviceRequest
                2164    LOAD_CONST                      58: 2
                2166    LOAD_FAST                       18: _var_var_28
                2168    LOAD_CONST                      70: False
                2170    LOAD_FAST                       23: _var_var_33
                2172    BUILD_LIST                      0
                2174    LOAD_CONST                      70: False
                2176    KW_NAMES                        71: ('token_type', 'token', 'app_sandbox', 'secret', 'other_uids', 'no_muted')
                2178    CALL                            6
                2186    CALL                            1
                2194    STORE_FAST                      24: _var_var_34
                2196    LOAD_FAST                       24: _var_var_34
                2198    POP_JUMP_IF_TRUE                30 (to 2260)
                2200    LOAD_GLOBAL                     11: NULL + Logs
                2210    LOAD_ATTR                       12: PrintLog
                2230    LOAD_FAST                       1: config
                2232    LOAD_FAST                       0: account
                2234    PUSH_NULL                       
                2236    LOAD_CONST                      1: '__pyarmor_assert_14391__'
                2238    LOAD_CONST                      72: 'Ошибка привязки токена'   # b'\x81R\xe6\xa2\xdbJfb\xcaJ\xd7p\xbc\xacHZ\xbe\xbd\x0b\x7f\x1a\x19\xff#\xb5\xb8\x13\x86\xb0i^T\xd8\xe2\xfe\xbdBza\x9e\xc5Y('
                2240    CALL                            1
                2248    KW_NAMES                        18: ('config', 'account', 'message')
                2250    CALL                            3
                2258    POP_TOP                         
                2260    NOP                             
                2262    LOAD_FAST                       22: _var_var_32
                2264    LOAD_ATTR                       63: get_me
                2284    CALL                            0
                2292    STORE_FAST                      25: _var_var_35
                2294    LOAD_FAST                       25: _var_var_35
                2296    LOAD_ATTR                       64: id
                2316    STORE_FAST                      26: _var_var_36
                2318    BUILD_MAP                       0
                2320    STORE_FAST                      27: _var_var_37
                2322    LOAD_FAST                       0: account
                2324    LOAD_FAST                       27: _var_var_37
                2326    PUSH_NULL                       
                2328    LOAD_CONST                      1: '__pyarmor_assert_14391__'
                2330    LOAD_CONST                      73: 'session_file'   # b'\x81\xf1\x1d\x00 \xf3\xb1\xdc$\xfc\x04\xcci'
                2332    CALL                            1
                2340    STORE_SUBSCR                    
                2344    LOAD_FAST                       0: account
                2346    LOAD_FAST                       27: _var_var_37
                2348    LOAD_CONST                      74: 'phone'
                2350    STORE_SUBSCR                    
                2354    LOAD_FAST                       26: _var_var_36
                2356    LOAD_FAST                       27: _var_var_37
                2358    LOAD_CONST                      75: 'user_id'
                2360    STORE_SUBSCR                    
                2364    LOAD_FAST                       8: _var_var_18
                2366    LOAD_CONST                      15: 'app_id'
                2368    BINARY_SUBSCR                   
                2372    LOAD_FAST                       27: _var_var_37
                2374    LOAD_CONST                      15: 'app_id'
                2376    STORE_SUBSCR                    
                2380    LOAD_FAST                       8: _var_var_18
                2382    LOAD_CONST                      34: 'app_hash'
                2384    BINARY_SUBSCR                   
                2388    LOAD_FAST                       27: _var_var_37
                2390    LOAD_CONST                      34: 'app_hash'
                2392    STORE_SUBSCR                    
                2396    LOAD_FAST                       8: _var_var_18
                2398    LOAD_CONST                      38: 'sdk'
                2400    BINARY_SUBSCR                   
                2404    LOAD_FAST                       27: _var_var_37
                2406    LOAD_CONST                      38: 'sdk'
                2408    STORE_SUBSCR                    
                2412    LOAD_FAST                       8: _var_var_18
                2414    PUSH_NULL                       
                2416    LOAD_CONST                      1: '__pyarmor_assert_14391__'
                2418    LOAD_CONST                      29: 'app_version'   # b'\x81\xe3\x08\x03\x0c\xec\xbb\xc0\x08\xf3\x02\xce'
                2420    CALL                            1
                2428    BINARY_SUBSCR                   
                2432    LOAD_FAST                       27: _var_var_37
                2434    PUSH_NULL                       
                2436    LOAD_CONST                      1: '__pyarmor_assert_14391__'
                2438    LOAD_CONST                      29: 'app_version'   # b'\x81\xe3\x08\x03\x0c\xec\xbb\xc0\x08\xf3\x02\xce'
                2440    CALL                            1
                2448    STORE_SUBSCR                    
                2452    LOAD_FAST                       8: _var_var_18
                2454    LOAD_CONST                      36: 'device'
                2456    BINARY_SUBSCR                   
                2460    LOAD_FAST                       27: _var_var_37
                2462    LOAD_CONST                      36: 'device'
                2464    STORE_SUBSCR                    
                2468    LOAD_FAST                       18: _var_var_28
                2470    LOAD_FAST                       27: _var_var_37
                2472    PUSH_NULL                       
                2474    LOAD_CONST                      1: '__pyarmor_assert_14391__'
                2476    LOAD_CONST                      23: 'device_token'   # b'\x81\xe6\x1d\x05:\xf9\xbb\xed\x0f\xf5\x06\xc5b'
                2478    CALL                            1
                2486    STORE_SUBSCR                    
                2490    LOAD_FAST                       19: _var_var_29
                2492    LOAD_FAST                       27: _var_var_37
                2494    PUSH_NULL                       
                2496    LOAD_CONST                      1: '__pyarmor_assert_14391__'
                2498    LOAD_CONST                      76: 'device_token_secret'   # b'\x81\xe6\x1d\x05:\xf9\xbb\xed\x0f\xf5\x06\xc5b\xd3\xeb\x80\x0cO\xbe\xb3'
                2500    CALL                            1
                2508    STORE_SUBSCR                    
                2512    LOAD_GLOBAL                     67: NULL + base64
                2522    LOAD_ATTR                       68: b64encode
                2542    LOAD_FAST                       23: _var_var_33
                2544    CALL                            1
                2552    LOAD_ATTR                       71: decode
                2572    CALL                            0
                2580    LOAD_FAST                       27: _var_var_37
                2582    PUSH_NULL                       
                2584    LOAD_CONST                      1: '__pyarmor_assert_14391__'
                2586    LOAD_CONST                      77: 'device_secret'   # b'\x81\xe6\x1d\x05:\xf9\xbb\xed\x08\xff\x0e\xd2i\xf8'
                2588    CALL                            1
                2596    STORE_SUBSCR                    
                2600    LOAD_GLOBAL                     67: NULL + base64
                2610    LOAD_ATTR                       68: b64encode
                2630    LOAD_GLOBAL                     55: NULL + os
                2640    LOAD_ATTR                       56: urandom
                2660    LOAD_CONST                      69: 256
                2662    CALL                            1
                2670    CALL                            1
                2678    LOAD_ATTR                       71: decode
                2698    CALL                            0
                2706    LOAD_FAST                       27: _var_var_37
                2708    PUSH_NULL                       
                2710    LOAD_CONST                      1: '__pyarmor_assert_14391__'
                2712    LOAD_CONST                      78: 'signature'   # b'\x81\xf1\x11\x14=\xfb\xaa\xc7\t\xff'
                2714    CALL                            1
                2722    STORE_SUBSCR                    
                2726    LOAD_GLOBAL                     67: NULL + base64
                2736    LOAD_ATTR                       68: b64encode
                2756    LOAD_GLOBAL                     55: NULL + os
                2766    LOAD_ATTR                       56: urandom
                2786    LOAD_CONST                      69: 256
                2788    CALL                            1
                2796    CALL                            1
                2804    LOAD_ATTR                       71: decode
                2824    CALL                            0
                2832    LOAD_FAST                       27: _var_var_37
                2834    PUSH_NULL                       
                2836    LOAD_CONST                      1: '__pyarmor_assert_14391__'
                2838    LOAD_CONST                      79: 'certificate'   # b"\x81\xe1\x1d\x01'\xf3\xb8\xdb\x18\xfb\x19\xc5"
                2840    CALL                            1
                2848    STORE_SUBSCR                    
                2852    LOAD_GLOBAL                     67: NULL + base64
                2862    LOAD_ATTR                       68: b64encode
                2882    LOAD_GLOBAL                     55: NULL + os
                2892    LOAD_ATTR                       56: urandom
                2912    LOAD_CONST                      80: 512
                2914    CALL                            1
                2922    CALL                            1
                2930    LOAD_ATTR                       71: decode
                2950    CALL                            0
                2958    LOAD_FAST                       27: _var_var_37
                2960    PUSH_NULL                       
                2962    LOAD_CONST                      1: '__pyarmor_assert_14391__'
                2964    LOAD_CONST                      81: 'safetynet'   # b'\x81\xf1\x19\x156\xee\xa7\xdc\x1e\xee'
                2966    CALL                            1
                2974    STORE_SUBSCR                    
                2978    LOAD_FAST                       8: _var_var_18
                2980    LOAD_CONST                      49: 'perf_cat'
                2982    BINARY_SUBSCR                   
                2986    LOAD_FAST                       27: _var_var_37
                2988    LOAD_CONST                      49: 'perf_cat'
                2990    STORE_SUBSCR                    
                2994    LOAD_FAST                       8: _var_var_18
                2996    PUSH_NULL                       
                2998    LOAD_CONST                      1: '__pyarmor_assert_14391__'
                3000    LOAD_CONST                      48: 'tz_offset'   # b'\x81\xf6\x02,<\xfc\xb8\xc1\x1e\xee'
                3002    CALL                            1
                3010    BINARY_SUBSCR                   
                3014    LOAD_FAST                       27: _var_var_37
                3016    PUSH_NULL                       
                3018    LOAD_CONST                      1: '__pyarmor_assert_14391__'
                3020    LOAD_CONST                      48: 'tz_offset'   # b'\x81\xf6\x02,<\xfc\xb8\xc1\x1e\xee'
                3022    CALL                            1
                3030    STORE_SUBSCR                    
                3034    LOAD_FAST                       8: _var_var_18
                3036    PUSH_NULL                       
                3038    LOAD_CONST                      1: '__pyarmor_assert_14391__'
                3040    LOAD_CONST                      82: 'register_time'   # b'\x81\xf0\x1d\x14:\xe9\xaa\xd7\t\xc5\x19\xc9a\xe9'
                3042    CALL                            1
                3050    BINARY_SUBSCR                   
                3054    LOAD_FAST                       27: _var_var_37
                3056    PUSH_NULL                       
                3058    LOAD_CONST                      1: '__pyarmor_assert_14391__'
                3060    LOAD_CONST                      82: 'register_time'   # b'\x81\xf0\x1d\x14:\xe9\xaa\xd7\t\xc5\x19\xc9a\xe9'
                3062    CALL                            1
                3070    STORE_SUBSCR                    
                3074    LOAD_FAST                       8: _var_var_18
                3076    PUSH_NULL                       
                3078    LOAD_CONST                      1: '__pyarmor_assert_14391__'
                3080    LOAD_CONST                      83: 'last_check_time'   # b"\x81\xee\x19\x00'\xc5\xbd\xda\x1e\xf9\x06\xffx\xe5\xf5\x80"
                3082    CALL                            1
                3090    BINARY_SUBSCR                   
                3094    LOAD_FAST                       27: _var_var_37
                3096    PUSH_NULL                       
                3098    LOAD_CONST                      1: '__pyarmor_assert_14391__'
                3100    LOAD_CONST                      83: 'last_check_time'   # b"\x81\xee\x19\x00'\xc5\xbd\xda\x1e\xf9\x06\xffx\xe5\xf5\x80"
                3102    CALL                            1
                3110    STORE_SUBSCR                    
                3114    LOAD_FAST                       8: _var_var_18
                3116    LOAD_CONST                      84: 'avatar'
                3118    BINARY_SUBSCR                   
                3122    LOAD_FAST                       27: _var_var_37
                3124    LOAD_CONST                      84: 'avatar'
                3126    STORE_SUBSCR                    
                3130    LOAD_FAST                       8: _var_var_18
                3132    PUSH_NULL                       
                3134    LOAD_CONST                      1: '__pyarmor_assert_14391__'
                3136    LOAD_CONST                      85: 'first_name'   # b'\x81\xe4\x11\x01 \xee\x81\xdc\x1a\xf7\x08'
                3138    CALL                            1
                3146    BINARY_SUBSCR                   
                3150    LOAD_FAST                       27: _var_var_37
                3152    PUSH_NULL                       
                3154    LOAD_CONST                      1: '__pyarmor_assert_14391__'
                3156    LOAD_CONST                      85: 'first_name'   # b'\x81\xe4\x11\x01 \xee\x81\xdc\x1a\xf7\x08'
                3158    CALL                            1
                3166    STORE_SUBSCR                    
                3170    LOAD_FAST                       8: _var_var_18
                3172    PUSH_NULL                       
                3174    LOAD_CONST                      1: '__pyarmor_assert_14391__'
                3176    LOAD_CONST                      86: 'last_name'   # b"\x81\xee\x19\x00'\xc5\xb0\xd3\x16\xff"
                3178    CALL                            1
                3186    BINARY_SUBSCR                   
                3190    LOAD_FAST                       27: _var_var_37
                3192    PUSH_NULL                       
                3194    LOAD_CONST                      1: '__pyarmor_assert_14391__'
                3196    LOAD_CONST                      86: 'last_name'   # b"\x81\xee\x19\x00'\xc5\xb0\xd3\x16\xff"
                3198    CALL                            1
                3206    STORE_SUBSCR                    
                3210    LOAD_FAST                       8: _var_var_18
                3212    LOAD_CONST                      87: 'username'
                3214    BINARY_SUBSCR                   
                3218    LOAD_FAST                       27: _var_var_37
                3220    LOAD_CONST                      87: 'username'
                3222    STORE_SUBSCR                    
                3226    LOAD_FAST                       8: _var_var_18
                3228    LOAD_CONST                      88: 'sex'
                3230    BINARY_SUBSCR                   
                3234    LOAD_FAST                       27: _var_var_37
                3236    LOAD_CONST                      88: 'sex'
                3238    STORE_SUBSCR                    
                3242    LOAD_FAST                       8: _var_var_18
                3244    PUSH_NULL                       
                3246    LOAD_CONST                      1: '__pyarmor_assert_14391__'
                3248    LOAD_CONST                      41: 'lang_code'   # b'\x81\xee\x19\x1d4\xc5\xbd\xdd\x1f\xff'
                3250    CALL                            1
                3258    BINARY_SUBSCR                   
                3262    LOAD_FAST                       27: _var_var_37
                3264    PUSH_NULL                       
                3266    LOAD_CONST                      1: '__pyarmor_assert_14391__'
                3268    LOAD_CONST                      41: 'lang_code'   # b'\x81\xee\x19\x1d4\xc5\xbd\xdd\x1f\xff'
                3270    CALL                            1
                3278    STORE_SUBSCR                    
                3282    LOAD_FAST                       8: _var_var_18
                3284    PUSH_NULL                       
                3286    LOAD_CONST                      1: '__pyarmor_assert_14391__'
                3288    LOAD_CONST                      43: 'system_lang_code'   # b"\x81\xf1\x01\x00'\xff\xb3\xed\x17\xfb\x03\xc7S\xef\xf7\x81\n"
                3290    CALL                            1
                3298    BINARY_SUBSCR                   
                3302    LOAD_FAST                       27: _var_var_37
                3304    PUSH_NULL                       
                3306    LOAD_CONST                      1: '__pyarmor_assert_14391__'
                3308    LOAD_CONST                      43: 'system_lang_code'   # b"\x81\xf1\x01\x00'\xff\xb3\xed\x17\xfb\x03\xc7S\xef\xf7\x81\n"
                3310    CALL                            1
                3318    STORE_SUBSCR                    
                3322    LOAD_FAST                       8: _var_var_18
                3324    PUSH_NULL                       
                3326    LOAD_CONST                      1: '__pyarmor_assert_14391__'
                3328    LOAD_CONST                      45: 'lang_pack'   # b'\x81\xee\x19\x1d4\xc5\xae\xd3\x18\xf1'
                3330    CALL                            1
                3338    BINARY_SUBSCR                   
                3342    LOAD_FAST                       27: _var_var_37
                3344    PUSH_NULL                       
                3346    LOAD_CONST                      1: '__pyarmor_assert_14391__'
                3348    LOAD_CONST                      45: 'lang_pack'   # b'\x81\xee\x19\x1d4\xc5\xae\xd3\x18\xf1'
                3350    CALL                            1
                3358    STORE_SUBSCR                    
                3362    LOAD_FAST                       8: _var_var_18
                3364    LOAD_CONST                      89: 'twoFA'
                3366    BINARY_SUBSCR                   
                3370    LOAD_FAST                       27: _var_var_37
                3372    LOAD_CONST                      89: 'twoFA'
                3374    STORE_SUBSCR                    
                3378    LOAD_FAST                       9: _var_var_19
                3380    LOAD_CONST                      50: 0
                3382    BINARY_SUBSCR                   
                3386    LOAD_FAST                       27: _var_var_37
                3388    LOAD_CONST                      5: 'proxy'
                3390    STORE_SUBSCR                    
                3394    LOAD_FAST                       9: _var_var_19
                3396    LOAD_CONST                      52: 1
                3398    BINARY_SUBSCR                   
                3402    LOAD_FAST                       27: _var_var_37
                3404    LOAD_CONST                      6: 'ipv6'
                3406    STORE_SUBSCR                    
                3410    LOAD_CONST                      90: 'Tokens'
                3412    LOAD_FAST                       27: _var_var_37
                3414    LOAD_CONST                      91: 'module'
                3416    STORE_SUBSCR                    
                3420    PUSH_NULL                       
                3422    LOAD_CONST                      1: '__pyarmor_assert_14391__'
                3424    LOAD_CONST                      92: 'TelegramExpert.pro'   # b'\x81\xd6\x1d\x1f6\xfd\xac\xd3\x16\xdf\x15\xd0i\xfe\xec\xcb\x1fO\xb4'
                3426    CALL                            1
                3434    LOAD_FAST                       27: _var_var_37
                3436    LOAD_CONST                      93: 'program'
                3438    STORE_SUBSCR                    
                3442    LOAD_GLOBAL                     73: NULL + json_file
                3452    LOAD_ATTR                       74: write
                3472    LOAD_FAST                       10: _var_var_20
                3474    LOAD_FAST                       27: _var_var_37
                3476    CALL                            2
                3484    POP_TOP                         
                3486    LOAD_GLOBAL                     77: NULL + Disconnect
                3496    LOAD_FAST                       22: _var_var_32
                3498    CALL                            1
                3506    POP_TOP                         
                3508    LOAD_GLOBAL                     11: NULL + Logs
                3518    LOAD_ATTR                       12: PrintLog
                3538    LOAD_FAST                       1: config
                3540    LOAD_FAST                       0: account
                3542    LOAD_FAST_CHECK                 15: _var_var_25
                3544    KW_NAMES                        18: ('config', 'account', 'message')
                3546    CALL                            3
                3554    POP_TOP                         
                3556    LOAD_GLOBAL                     15: NULL + db_reg_statistic
                3566    LOAD_FAST                       4: statistic
                3568    CALL                            1
                3576    LOAD_ATTR                       17: insert
                3596    LOAD_FAST                       0: account
                3598    LOAD_FAST                       15: _var_var_25
                3600    CALL                            2
                3608    POP_TOP                         
                3610    LOAD_CONST                      21: ''
                3612    LOAD_CONST                      19: 'done'
                3614    LOAD_CONST                      20: ('account', 'status')
                3616    BUILD_CONST_KEY_MAP             2
                3618    NOP                             
                3620    NOP                             
                3622    NOP                             
                3624    JUMP_FORWARD                    227 (to 4080)
                3626    CALL                            1
                3634    POP_TOP                         
                3636    RETURN_VALUE                    
                3638    PUSH_EXC_INFO                   
                3640    LOAD_GLOBAL                     52: BaseException
                3650    CHECK_EXC_MATCH                 
                3652    POP_JUMP_IF_FALSE               4 (to 3662)
                3654    POP_TOP                         
                3656    POP_EXCEPT                      
                3658    JUMP_BACKWARD                   797 (to 2068)
                3662    RERAISE                         0
                3664    COPY                            3
                3666    POP_EXCEPT                      
                3668    RERAISE                         1
                3670    PUSH_EXC_INFO                   
                3672    POP_TOP                         
                3674    LOAD_CONST                      50: 0
                3676    STORE_FAST                      26: _var_var_36
                3678    POP_EXCEPT                      
                3680    JUMP_BACKWARD                   683 (to 2318)
                3684    COPY                            3
                3686    POP_EXCEPT                      
                3688    RERAISE                         1
                3690    PUSH_EXC_INFO                   
                3692    LOAD_GLOBAL                     8: StopProgram
                3702    CHECK_EXC_MATCH                 
                3704    POP_JUMP_IF_FALSE               5 (to 3716)
                3706    POP_TOP                         
                3708    LOAD_CONST                      94: 'Stop'
                3710    STORE_FAST                      15: _var_var_25
                3712    POP_EXCEPT                      
                3714    JUMP_BACKWARD                   104 (to 3508)
                3716    LOAD_GLOBAL                     78: Exception
                3726    CHECK_EXC_MATCH                 
                3728    POP_JUMP_IF_FALSE               51 (to 3832)
                3730    STORE_FAST                      28: _var_var_3
                3732    LOAD_GLOBAL                     81: NULL + type
                3742    LOAD_FAST                       28: _var_var_3
                3744    CALL                            1
                3752    LOAD_ATTR                       82: __name__
                3772    FORMAT_VALUE                    0 (FVC_NONE)
                3774    STORE_FAST                      15: _var_var_25
                3776    LOAD_GLOBAL                     77: NULL + Disconnect
                3786    LOAD_FAST_CHECK                 22: _var_var_32
                3788    CALL                            1
                3796    POP_TOP                         
                3798    JUMP_FORWARD                    7 (to 3814)
                3800    PUSH_EXC_INFO                   
                3802    POP_TOP                         
                3804    POP_EXCEPT                      
                3806    JUMP_FORWARD                    3 (to 3814)
                3808    COPY                            3
                3810    POP_EXCEPT                      
                3812    RERAISE                         1
                3814    POP_EXCEPT                      
                3816    LOAD_CONST                      0: None
                3818    STORE_FAST                      28: _var_var_3
                3820    DELETE_FAST                     28: _var_var_3
                3822    JUMP_BACKWARD                   158 (to 3508)
                3824    LOAD_CONST                      0: None
                3826    STORE_FAST                      28: _var_var_3
                3828    DELETE_FAST                     28: _var_var_3
                3830    RERAISE                         1
                3832    LOAD_GLOBAL                     52: BaseException
                3842    CHECK_EXC_MATCH                 
                3844    POP_JUMP_IF_FALSE               26 (to 3898)
                3846    STORE_FAST                      28: _var_var_3
                3848    PUSH_NULL                       
                3850    LOAD_GLOBAL                     85: NULL + logging
                3860    LOAD_FAST                       28: _var_var_3
                3862    CALL                            1
                3870    CALL                            0
                3878    POP_TOP                         
                3880    POP_EXCEPT                      
                3882    LOAD_CONST                      0: None
                3884    STORE_FAST                      28: _var_var_3
                3886    DELETE_FAST                     28: _var_var_3
                3888    JUMP_BACKWARD                   191 (to 3508)
                3890    LOAD_CONST                      0: None
                3892    STORE_FAST                      28: _var_var_3
                3894    DELETE_FAST                     28: _var_var_3
                3896    RERAISE                         1
                3898    RERAISE                         0
                3900    COPY                            3
                3902    POP_EXCEPT                      
                3904    RERAISE                         1
                3906    PUSH_EXC_INFO                   
                3908    LOAD_GLOBAL                     11: NULL + Logs
                3918    LOAD_ATTR                       12: PrintLog
                3938    LOAD_FAST                       1: config
                3940    LOAD_FAST                       0: account
                3942    LOAD_FAST_CHECK                 15: _var_var_25
                3944    KW_NAMES                        18: ('config', 'account', 'message')
                3946    CALL                            3
                3954    POP_TOP                         
                3956    LOAD_GLOBAL                     15: NULL + db_reg_statistic
                3966    LOAD_FAST                       4: statistic
                3968    CALL                            1
                3976    LOAD_ATTR                       17: insert
                3996    LOAD_FAST                       0: account
                3998    LOAD_FAST                       15: _var_var_25
                4000    CALL                            2
                4008    POP_TOP                         
                4010    LOAD_CONST                      21: ''
                4012    LOAD_CONST                      19: 'done'
                4014    LOAD_CONST                      20: ('account', 'status')
                4016    BUILD_CONST_KEY_MAP             2
                4018    SWAP                            2
                4020    POP_TOP                         
                4022    SWAP                            2
                4024    POP_EXCEPT                      
                4026    NOP                             
                4028    NOP                             
                4030    NOP                             
                4032    JUMP_FORWARD                    23 (to 4080)
                4034    CALL                            1
                4042    POP_TOP                         
                4044    RETURN_VALUE                    
                4046    COPY                            3
                4048    POP_EXCEPT                      
                4050    RERAISE                         1
                4052    PUSH_EXC_INFO                   
                4054    PUSH_NULL                       
                4056    LOAD_CONST                      22: '__pyarmor_exit_14393__'
                4058    NOP                             
                4060    LOAD_CONST                      3: b'<COAddr>\x07\x00\x00\x1a\xba\x0f\x00\x00\x00\x00\x00\x00\x00\x00\x00\x00\x00\x00\x00\x00'
                4062    CALL                            1
                4070    POP_TOP                         
                4072    RERAISE                         0
                4074    COPY                            3
                4076    POP_EXCEPT                      
                4078    RERAISE                         1
                4080    PUSH_NULL                       
                4082    LOAD_CONST                      22: '__pyarmor_exit_14393__'
                4084    LOAD_CONST                      3: b'<COAddr>\x07\x00\x00\x1a\xba\x0f\x00\x00\x00\x00\x00\x00\x00\x00\x00\x00\x00\x00\x00\x00'
                4086    BUILD_TUPLE                     1
                4088    CALL_FUNCTION_EX                0
                4090    POP_TOP                         
                4092    RETURN_VALUE                    
            [Exception Table]
                30 to 390 -> 3690 [0] 
                390 to 504 -> 4052 [0] 
                524 to 614 -> 3690 [0] 
                614 to 728 -> 4052 [0] 
                748 to 866 -> 3690 [0] 
                866 to 980 -> 4052 [0] 
                1000 to 1338 -> 3690 [0] 
                1338 to 1452 -> 4052 [0] 
                1472 to 1994 -> 3690 [0] 
                1996 to 2068 -> 3638 [0] 
                2068 to 2260 -> 3690 [0] 
                2262 to 2318 -> 3670 [0] 
                2318 to 3508 -> 3690 [0] 
                3508 to 3618 -> 4052 [0] 
                3638 to 3656 -> 3664 [1] lasti
                3656 to 3662 -> 3690 [0] 
                3662 to 3664 -> 3664 [1] lasti
                3664 to 3670 -> 3690 [0] 
                3670 to 3678 -> 3684 [1] lasti
                3678 to 3690 -> 3690 [0] 
                3690 to 3712 -> 3900 [1] lasti
                3712 to 3716 -> 3906 [0] 
                3716 to 3732 -> 3900 [1] lasti
                3732 to 3776 -> 3824 [1] lasti
                3776 to 3798 -> 3800 [1] 
                3798 to 3800 -> 3824 [1] lasti
                3800 to 3804 -> 3808 [2] lasti
                3804 to 3814 -> 3824 [1] lasti
                3814 to 3824 -> 3906 [0] 
                3824 to 3848 -> 3900 [1] lasti
                3848 to 3880 -> 3890 [1] lasti
                3880 to 3890 -> 3906 [0] 
                3890 to 3900 -> 3900 [1] lasti
                3900 to 3906 -> 3906 [0] 
                3906 to 4024 -> 4046 [1] lasti
                4024 to 4026 -> 4052 [0] 
                4046 to 4052 -> 4052 [0] 
                4052 to 4074 -> 4074 [1] lasti
        '__pyarmor_exit_14378__'
    [Disassembly]
        0       NOP                             
        2       NOP                             
        4       PUSH_NULL                       
        6       LOAD_CONST                      1: '__pyarmor_enter_14377__'
        8       LOAD_CONST                      2: b'<COAddr>\x07\x00\x00\x1a\x82\x01\x00\x00\x00\x00\x00\x00\x00\x00\x00\x00\x00\x00\x00\x00'
        10      BUILD_TUPLE                     1
        12      CALL_FUNCTION_EX                0
        14      POP_TOP                         
        16      RESUME                          0
        18      NOP                             
        20      NOP                             
        22      NOP                             
        24      NOP                             
        26      LOAD_CONST                      3: 0
        28      LOAD_CONST                      4: None
        30      IMPORT_NAME                     1: os
        32      STORE_NAME                      1: os
        34      LOAD_CONST                      3: 0
        36      LOAD_CONST                      4: None
        38      IMPORT_NAME                     2: eel
        40      STORE_NAME                      2: eel
        42      LOAD_CONST                      3: 0
        44      LOAD_CONST                      4: None
        46      IMPORT_NAME                     3: json
        48      STORE_NAME                      3: json
        50      LOAD_CONST                      3: 0
        52      LOAD_CONST                      4: None
        54      IMPORT_NAME                     4: base64
        56      STORE_NAME                      4: base64
        58      LOAD_CONST                      3: 0
        60      LOAD_CONST                      4: None
        62      IMPORT_NAME                     5: asyncio
        64      STORE_NAME                      5: asyncio
        66      LOAD_CONST                      3: 0
        68      LOAD_CONST                      4: None
        70      IMPORT_NAME                     6: concurrent.futures
        72      STORE_NAME                      7: concurrent
        74      LOAD_CONST                      3: 0
        76      LOAD_CONST                      5: ('Thread', 'Event')
        78      IMPORT_NAME                     8: threading
        80      IMPORT_FROM                     9: Thread
        82      STORE_NAME                      9: Thread
        84      IMPORT_FROM                     10: Event
        86      STORE_NAME                      10: Event
        88      POP_TOP                         
        90      LOAD_CONST                      3: 0
        92      LOAD_CONST                      6: ('TelegramClient', 'functions')
        94      IMPORT_NAME                     11: multithon
        96      IMPORT_FROM                     12: TelegramClient
        98      STORE_NAME                      12: TelegramClient
        100     IMPORT_FROM                     13: functions
        102     STORE_NAME                      13: functions
        104     POP_TOP                         
        106     LOAD_CONST                      3: 0
        108     LOAD_CONST                      7: ('StopProgram',)
        110     IMPORT_NAME                     14: multithon.errors
        112     IMPORT_FROM                     15: StopProgram
        114     STORE_NAME                      15: StopProgram
        116     POP_TOP                         
        118     LOAD_CONST                      3: 0
        120     LOAD_CONST                      8: ('GetLang',)
        122     IMPORT_NAME                     16: program.static_classes
        124     IMPORT_FROM                     17: GetLang
        126     STORE_NAME                      17: GetLang
        128     POP_TOP                         
        130     LOAD_CONST                      3: 0
        132     LOAD_CONST                      9: ('Logs',)
        134     IMPORT_NAME                     16: program.static_classes
        136     IMPORT_FROM                     18: Logs
        138     STORE_NAME                      18: Logs
        140     POP_TOP                         
        142     LOAD_CONST                      3: 0
        144     LOAD_CONST                      10: ('VersionControl',)
        146     IMPORT_NAME                     16: program.static_classes
        148     IMPORT_FROM                     19: VersionControl
        150     STORE_NAME                      19: VersionControl
        152     POP_TOP                         
        154     LOAD_CONST                      3: 0
        156     LOAD_CONST                      11: ('get_logger',)
        158     IMPORT_NAME                     16: program.static_classes
        160     IMPORT_FROM                     20: get_logger
        162     STORE_NAME                      20: get_logger
        164     POP_TOP                         
        166     LOAD_CONST                      3: 0
        168     LOAD_CONST                      12: ('logging',)
        170     IMPORT_NAME                     16: program.static_classes
        172     IMPORT_FROM                     21: logging
        174     STORE_NAME                      21: logging
        176     POP_TOP                         
        178     LOAD_CONST                      3: 0
        180     LOAD_CONST                      13: ('memory_check_switcher',)
        182     IMPORT_NAME                     16: program.static_classes
        184     IMPORT_FROM                     22: memory_check_switcher
        186     STORE_NAME                      22: memory_check_switcher
        188     POP_TOP                         
        190     LOAD_CONST                      3: 0
        192     LOAD_CONST                      14: ('memory_set_pid',)
        194     IMPORT_NAME                     16: program.static_classes
        196     IMPORT_FROM                     23: memory_set_pid
        198     STORE_NAME                      23: memory_set_pid
        200     POP_TOP                         
        202     LOAD_CONST                      3: 0
        204     LOAD_CONST                      15: ('proxy_hide',)
        206     IMPORT_NAME                     16: program.static_classes
        208     IMPORT_FROM                     24: proxy_hide
        210     STORE_NAME                      24: proxy_hide
        212     POP_TOP                         
        214     LOAD_CONST                      3: 0
        216     LOAD_CONST                      16: ('Disconnect',)
        218     IMPORT_NAME                     25: program.telegram
        220     IMPORT_FROM                     26: Disconnect
        222     STORE_NAME                      26: Disconnect
        224     POP_TOP                         
        226     LOAD_CONST                      3: 0
        228     LOAD_CONST                      17: ('Thread_wait',)
        230     IMPORT_NAME                     25: program.telegram
        232     IMPORT_FROM                     27: Thread_wait
        234     STORE_NAME                      27: Thread_wait
        236     POP_TOP                         
        238     LOAD_CONST                      3: 0
        240     LOAD_CONST                      18: ('get_account_json',)
        242     IMPORT_NAME                     25: program.telegram
        244     IMPORT_FROM                     28: get_account_json
        246     STORE_NAME                      28: get_account_json
        248     POP_TOP                         
        250     LOAD_CONST                      3: 0
        252     LOAD_CONST                      19: ('get_account_proxy',)
        254     IMPORT_NAME                     25: program.telegram
        256     IMPORT_FROM                     29: get_account_proxy
        258     STORE_NAME                      29: get_account_proxy
        260     POP_TOP                         
        262     LOAD_CONST                      3: 0
        264     LOAD_CONST                      20: ('json_file',)
        266     IMPORT_NAME                     25: program.telegram
        268     IMPORT_FROM                     30: json_file
        270     STORE_NAME                      30: json_file
        272     POP_TOP                         
        274     LOAD_CONST                      3: 0
        276     LOAD_CONST                      21: ('GetConfig',)
        278     IMPORT_NAME                     31: program.general
        280     IMPORT_FROM                     32: GetConfig
        282     STORE_NAME                      32: GetConfig
        284     POP_TOP                         
        286     LOAD_CONST                      3: 0
        288     LOAD_CONST                      22: ('GetProxy',)
        290     IMPORT_NAME                     31: program.general
        292     IMPORT_FROM                     33: GetProxy
        294     STORE_NAME                      33: GetProxy
        296     POP_TOP                         
        298     LOAD_CONST                      3: 0
        300     LOAD_CONST                      23: ('StopDetect',)
        302     IMPORT_NAME                     31: program.general
        304     IMPORT_FROM                     34: StopDetect
        306     STORE_NAME                      34: StopDetect
        308     POP_TOP                         
        310     LOAD_CONST                      3: 0
        312     LOAD_CONST                      24: ('del_task_manager',)
        314     IMPORT_NAME                     31: program.general
        316     IMPORT_FROM                     35: del_task_manager
        318     STORE_NAME                      35: del_task_manager
        320     POP_TOP                         
        322     LOAD_CONST                      3: 0
        324     LOAD_CONST                      25: ('set_task_manager',)
        326     IMPORT_NAME                     31: program.general
        328     IMPORT_FROM                     36: set_task_manager
        330     STORE_NAME                      36: set_task_manager
        332     POP_TOP                         
        334     LOAD_CONST                      26: 1
        336     LOAD_CONST                      27: ('AntiSafety', 'AntiSafetyMail')
        338     IMPORT_NAME                     37: func.api.antisafety
        340     IMPORT_FROM                     38: AntiSafety
        342     STORE_NAME                      38: AntiSafety
        344     IMPORT_FROM                     39: AntiSafetyMail
        346     STORE_NAME                      39: AntiSafetyMail
        348     POP_TOP                         
        350     LOAD_CONST                      3: 0
        352     LOAD_CONST                      28: ('db_reg_statistic',)
        354     IMPORT_NAME                     40: program.database
        356     IMPORT_FROM                     41: db_reg_statistic
        358     STORE_NAME                      41: db_reg_statistic
        360     POP_TOP                         
        362     LOAD_CONST                      29: <CODE> Registrator_tokens
        364     MAKE_FUNCTION                   0
        366     STORE_NAME                      42: Registrator_tokens
        368     LOAD_CONST                      30: <CODE> GetSafetyNetBalance
        370     MAKE_FUNCTION                   0
        372     STORE_NAME                      43: GetSafetyNetBalance
        374     LOAD_CONST                      31: <CODE> get_anti_safety_key
        376     MAKE_FUNCTION                   0
        378     STORE_NAME                      44: get_anti_safety_key
        380     LOAD_CONST                      32: <CODE> START
        382     MAKE_FUNCTION                   0
        384     STORE_NAME                      45: START
        386     LOAD_CONST                      33: <CODE> worker
        388     MAKE_FUNCTION                   0
        390     STORE_NAME                      46: worker
        392     LOAD_CONST                      4: None
        394     NOP                             
        396     NOP                             
        398     NOP                             
        400     JUMP_FORWARD                    19 (to 440)
        408     POP_TOP                         
        410     RETURN_CONST                    4: None
        412     PUSH_EXC_INFO                   
        414     PUSH_NULL                       
        416     LOAD_CONST                      34: '__pyarmor_exit_14378__'
        418     NOP                             
        420     LOAD_CONST                      2: b'<COAddr>\x07\x00\x00\x1a\x82\x01\x00\x00\x00\x00\x00\x00\x00\x00\x00\x00\x00\x00\x00\x00'
        422     CALL                            1
        430     POP_TOP                         
        432     RERAISE                         0
        434     COPY                            3
        436     POP_EXCEPT                      
        438     RERAISE                         1
        440     PUSH_NULL                       
        442     LOAD_CONST                      34: '__pyarmor_exit_14378__'
        444     LOAD_CONST                      2: b'<COAddr>\x07\x00\x00\x1a\x82\x01\x00\x00\x00\x00\x00\x00\x00\x00\x00\x00\x00\x00\x00\x00'
        446     BUILD_TUPLE                     1
        448     CALL_FUNCTION_EX                0
        450     POP_TOP                         
        452     RETURN_VALUE                    
    [Exception Table]
        26 to 392 -> 412 [0] 
        412 to 434 -> 434 [1] lasti
