#decoded by lolz.live/mrpenny / t.me/zeus_jackpot
# ================================
# Примечания по Pyarmor:
# - Байт-код и объекты кода Pyarmor соответствуют стандартному Python, но присутствуют специальные вызовы функций среды выполнения (runtime) Pyarmor.
# - Вызовы строк — это не ошибки, а маркеры, которые обрабатываются Pyarmor во время выполнения.
#
# Руководство по декомпиляции (без среды выполнения):
# 1. Игнорируйте зашифрованные байты после `#`; используйте только строку до `#`.
# 2. Удалите "__pyarmor_enter_xxx__"(b"<COAddr>...") и "__pyarmor_leave_xxx__"(b"<COAddr>...") (пролог/эпилог).
# 3. "__pyarmor_assert_xxx__"(A) не является настоящим оператором assert.
#    - Если A — это имя или читаемая строка: замените на A.
#    - Если A — это (X, "Y"): замените на X.Y.
#    - Если A — это (X, "Y", Z): замените на X.Y = Z.
#    - В противном случае: выберите наиболее подходящую/логичную замену.
# 4. "__pyarmor_bcc_xxx__"(...) указывает на машинный (нативный) код; тело функции недоступно. Добавьте комментарий.
# ================================

[Code]
    File Name: <frozen program.modules.Registrator_add_account>
    Object Name: <module>
    Qualified Name: <module>
    Arg Count: 0
    Pos Only Arg Count: 0
    KW Only Arg Count: 0
    Stack Size: 5
    Flags: 0x20000000 (CO_PYARMOR_OBFUSCATED)
    [Names]
        '__assert_armored__'
        'os'
        'eel'
        'json'
        'time'
        'asyncio'
        'datetime'
        'concurrent.futures'
        'concurrent'
        'pathlib'
        'Path'
        'threading'
        'Thread'
        'Event'
        'multithon.sync'
        'TelegramClient'
        'functions'
        'types'
        'errors'
        'multithon.errors'
        'StopProgram'
        'program.static_classes'
        'GetLang'
        'Logs'
        'get_logger'
        'logging'
        'memory_check_switcher'
        'memory_set_pid'
        'proxy_hide'
        'program.telegram'
        'Disconnect'
        'Thread_wait'
        'get_account_proxy'
        'json_file'
        'program.general'
        'GetConfig'
        'GetProxy'
        'StopDetect'
        'check_get_settings'
        'del_task_manager'
        'getFile'
        'set_task_manager'
        'program.database'
        'db_param_accounts'
        'Registrator_add_account'
        'START'
        'destroy_empty_session'
        'get_code'
        'get_twofa'
        'add_account'
        'TELEGRAM_SEND_CODE'
        'SIGN_IN'
    [Locals+Names]
    [Constants]
        '__pyarmor_assert_14151__'
        '__pyarmor_enter_14152__'
        b'<COAddr>\x05\x00\x00\x1a\xa4\x01\x00\x00\x00\x00\x00\x00\x00\x00\x00\x00\x00\x00\x00\x00'
        0
        None
        (
            'Path'
        )
        (
            'Thread'
            'Event'
        )
        (
            'TelegramClient'
            'functions'
            'types'
            'errors'
        )
        (
            'StopProgram'
        )
        (
            'GetLang'
        )
        (
            'Logs'
        )
        (
            'get_logger'
        )
        (
            'logging'
        )
        (
            'memory_check_switcher'
        )
        (
            'memory_set_pid'
        )
        (
            'proxy_hide'
        )
        (
            'Disconnect'
        )
        (
            'Thread_wait'
        )
        (
            'get_account_proxy'
        )
        (
            'json_file'
        )
        (
            'GetConfig'
        )
        (
            'GetProxy'
        )
        (
            'StopDetect'
        )
        (
            'check_get_settings'
        )
        (
            'del_task_manager'
        )
        (
            'getFile'
        )
        (
            'set_task_manager'
        )
        (
            'db_param_accounts'
        )
        [Code]
            File Name: <frozen program.modules.Registrator_add_account>
            Object Name: Registrator_add_account
            Qualified Name: Registrator_add_account
            Arg Count: 1
            Pos Only Arg Count: 0
            KW Only Arg Count: 0
            Stack Size: 8
            Flags: 0x20000003 (CO_OPTIMIZED | CO_NEWLOCALS | CO_PYARMOR_OBFUSCATED)
            [Names]
                'get'
                'getFile'
                'GetConfig'
                'config'
                'GetLang'
                'Lang'
                'GetProxy'
                'eel'
                'sendSuccessBox'
                'memory_check_switcher'
                'Event'
                'memory_set_pid'
                'Thread'
                'START'
                'start'
                'Logs'
                'WaitStopAnsfer'
                'UpdateLogInWindow'
                'BaseException'
                'logging'
            [Locals+Names]
                'data'
                '__assert_armored__'
                '_var_var_0'
                '_var_var_1'
                '_var_var_2'
                '_var_var_3'
            [Constants]
                None
                '__pyarmor_assert_14154__'
                '__pyarmor_enter_14155__'
                b'<COAddr>\x07\x00\x00\x1a\xae\x02\x00\x00\x00\x00\x00\x00\x00\x00\x00\x00\x00\x00\x00\x00'
                'action'
                'getFile'
                '__pyarmor_exit_14156__'
                'program_running'   # b'\x81\xf2\n\x1c4\xe8\xbf\xdf$\xe8\x18\xceb\xe5\xf6\x82'
                False
                (
                    'target'
                    'args'
                )
                True
                (
                    'target'
                    'args'
                    'daemon'
                )
            [Disassembly]
                0       NOP                             
                2       NOP                             
                4       PUSH_NULL                       
                6       LOAD_CONST                      2: '__pyarmor_enter_14155__'
                8       LOAD_CONST                      3: b'<COAddr>\x07\x00\x00\x1a\xae\x02\x00\x00\x00\x00\x00\x00\x00\x00\x00\x00\x00\x00\x00\x00'
                10      BUILD_TUPLE                     1
                12      CALL_FUNCTION_EX                0
                14      POP_TOP                         
                16      RESUME                          0
                18      NOP                             
                20      NOP                             
                22      NOP                             
                24      NOP                             
                26      NOP                             
                28      NOP                             
                30      LOAD_FAST                       0: data
                32      LOAD_ATTR                       1: get
                52      LOAD_CONST                      4: 'action'
                54      CALL                            1
                62      POP_JUMP_IF_NONE                28 (to 120)
                64      LOAD_FAST                       0: data
                66      LOAD_CONST                      4: 'action'
                68      BINARY_SUBSCR                   
                72      LOAD_CONST                      5: 'getFile'
                74      COMPARE_OP                      40 (==)
                78      POP_JUMP_IF_FALSE               20 (to 120)
                80      LOAD_GLOBAL                     3: NULL + getFile
                90      LOAD_FAST                       0: data
                92      CALL                            1
                100     NOP                             
                102     NOP                             
                104     JUMP_FORWARD                    316 (to 740)
                108     CALL                            1
                116     POP_TOP                         
                118     RETURN_VALUE                    
                120     LOAD_GLOBAL                     5: NULL + GetConfig
                130     CALL                            0
                138     STORE_GLOBAL                    3: config
                140     LOAD_GLOBAL                     9: NULL + GetLang
                150     LOAD_GLOBAL                     6: config
                160     CALL                            1
                168     STORE_GLOBAL                    5: Lang
                170     LOAD_GLOBAL                     13: NULL + GetProxy
                180     CALL                            0
                188     STORE_FAST                      2: _var_var_0
                190     LOAD_GLOBAL                     15: NULL + eel
                200     LOAD_ATTR                       16: sendSuccessBox
                220     LOAD_GLOBAL                     10: Lang
                230     PUSH_NULL                       
                232     LOAD_CONST                      1: '__pyarmor_assert_14154__'
                234     LOAD_CONST                      7: 'program_running'   # b'\x81\xf2\n\x1c4\xe8\xbf\xdf$\xe8\x18\xceb\xe5\xf6\x82'
                236     CALL                            1
                244     BINARY_SUBSCR                   
                248     CALL                            1
                256     POP_TOP                         
                258     LOAD_GLOBAL                     19: NULL + memory_check_switcher
                268     CALL                            0
                276     POP_JUMP_IF_TRUE                11 (to 300)
                278     NOP                             
                280     LOAD_CONST                      8: False
                282     NOP                             
                284     NOP                             
                286     NOP                             
                288     JUMP_FORWARD                    225 (to 740)
                296     POP_TOP                         
                298     RETURN_CONST                    8: False
                300     LOAD_GLOBAL                     21: NULL + Event
                310     CALL                            0
                318     STORE_FAST                      3: _var_var_1
                320     LOAD_GLOBAL                     23: NULL + memory_set_pid
                330     CALL                            0
                338     STORE_FAST                      4: _var_var_2
                340     LOAD_GLOBAL                     25: NULL + Thread
                350     LOAD_GLOBAL                     26: START
                360     LOAD_FAST                       0: data
                362     LOAD_GLOBAL                     6: config
                372     LOAD_FAST                       4: _var_var_2
                374     LOAD_FAST                       2: _var_var_0
                376     LOAD_FAST                       3: _var_var_1
                378     BUILD_TUPLE                     5
                380     KW_NAMES                        9: ('target', 'args')
                382     CALL                            2
                390     LOAD_ATTR                       29: start
                410     CALL                            0
                418     POP_TOP                         
                420     LOAD_GLOBAL                     25: NULL + Thread
                430     LOAD_GLOBAL                     30: Logs
                440     LOAD_ATTR                       32: WaitStopAnsfer
                460     LOAD_GLOBAL                     6: config
                470     LOAD_FAST                       4: _var_var_2
                472     LOAD_FAST                       3: _var_var_1
                474     BUILD_TUPLE                     3
                476     LOAD_CONST                      10: True
                478     KW_NAMES                        11: ('target', 'args', 'daemon')
                480     CALL                            3
                488     LOAD_ATTR                       29: start
                508     CALL                            0
                516     POP_TOP                         
                518     LOAD_GLOBAL                     25: NULL + Thread
                528     LOAD_GLOBAL                     30: Logs
                538     LOAD_ATTR                       34: UpdateLogInWindow
                558     LOAD_GLOBAL                     6: config
                568     LOAD_FAST                       4: _var_var_2
                570     LOAD_FAST                       3: _var_var_1
                572     BUILD_TUPLE                     3
                574     LOAD_CONST                      10: True
                576     KW_NAMES                        11: ('target', 'args', 'daemon')
                578     CALL                            3
                586     LOAD_ATTR                       29: start
                606     CALL                            0
                614     POP_TOP                         
                616     LOAD_CONST                      0: None
                618     NOP                             
                620     NOP                             
                622     NOP                             
                624     JUMP_FORWARD                    57 (to 740)
                632     POP_TOP                         
                634     RETURN_CONST                    0: None
                636     PUSH_EXC_INFO                   
                638     LOAD_GLOBAL                     36: BaseException
                648     CHECK_EXC_MATCH                 
                650     POP_JUMP_IF_FALSE               26 (to 704)
                652     STORE_FAST                      5: _var_var_3
                654     PUSH_NULL                       
                656     LOAD_GLOBAL                     39: NULL + logging
                666     LOAD_FAST                       5: _var_var_3
                668     CALL                            1
                676     CALL                            0
                684     POP_TOP                         
                686     POP_EXCEPT                      
                688     LOAD_CONST                      0: None
                690     STORE_FAST                      5: _var_var_3
                692     DELETE_FAST                     5: _var_var_3
                694     JUMP_BACKWARD                   40 (to 616)
                696     LOAD_CONST                      0: None
                698     STORE_FAST                      5: _var_var_3
                700     DELETE_FAST                     5: _var_var_3
                702     RERAISE                         1
                704     RERAISE                         0
                706     COPY                            3
                708     POP_EXCEPT                      
                710     RERAISE                         1
                712     PUSH_EXC_INFO                   
                714     PUSH_NULL                       
                716     LOAD_CONST                      6: '__pyarmor_exit_14156__'
                718     NOP                             
                720     LOAD_CONST                      3: b'<COAddr>\x07\x00\x00\x1a\xae\x02\x00\x00\x00\x00\x00\x00\x00\x00\x00\x00\x00\x00\x00\x00'
                722     CALL                            1
                730     POP_TOP                         
                732     RERAISE                         0
                734     COPY                            3
                736     POP_EXCEPT                      
                738     RERAISE                         1
                740     PUSH_NULL                       
                742     LOAD_CONST                      6: '__pyarmor_exit_14156__'
                744     LOAD_CONST                      3: b'<COAddr>\x07\x00\x00\x1a\xae\x02\x00\x00\x00\x00\x00\x00\x00\x00\x00\x00\x00\x00\x00\x00'
                746     BUILD_TUPLE                     1
                748     CALL_FUNCTION_EX                0
                750     POP_TOP                         
                752     RETURN_VALUE                    
            [Exception Table]
                30 to 100 -> 636 [0] 
                120 to 278 -> 636 [0] 
                300 to 616 -> 636 [0] 
                636 to 654 -> 706 [1] lasti
                654 to 686 -> 696 [1] lasti
                686 to 696 -> 712 [0] 
                696 to 706 -> 706 [1] lasti
                706 to 712 -> 712 [0] 
                712 to 734 -> 734 [1] lasti
        [Code]
            File Name: <frozen program.modules.Registrator_add_account>
            Object Name: START
            Qualified Name: START
            Arg Count: 5
            Pos Only Arg Count: 0
            KW Only Arg Count: 0
            Stack Size: 14
            Flags: 0x20000003 (CO_OPTIMIZED | CO_NEWLOCALS | CO_PYARMOR_OBFUSCATED)
            [Names]
                'is_set'
                'StopProgram'
                'check_get_settings'
                'get'
                'int'
                'set_task_manager'
                'concurrent'
                'futures'
                'ThreadPoolExecutor'
                'eel'
                'StreamStat'
                'json'
                'dumps'
                'append'
                'submit'
                'add_account'
                'as_completed'
                'BaseException'
                'logging'
                'del_task_manager'
                'StopDetect'
            [Locals+Names]
                'data'
                'config'
                'pid'
                'proxy'
                'stop_thread'
                '__assert_armored__'
                '_var_var_4'
                '_var_var_5'
                '_var_var_6'
                '_var_var_7'
                '_var_var_8'
                '_var_var_9'
                '_var_var_10'
                '_var_var_11'
                '_var_var_3'
            [Constants]
                None
                '__pyarmor_assert_14157__'
                '__pyarmor_enter_14158__'
                b'<COAddr>\x05\x00\x00\x1a\x1a\x04\x00\x00\x00\x00\x00\x00\x00\x00\x00\x00\x00\x00\x00\x00'
                'Settings'
                'thread_rules'   # b'\x81\xf6\x10\x016\xfb\xba\xed\t\xef\x01\xc5\x7f'
                True
                'thread_count'   # b'\x81\xf6\x10\x016\xfb\xba\xed\x18\xf5\x18\xcex'
                'stuff'
                (
                    'accounts'
                    'name'
                )
                (
                    'max_workers'
                )
                1
                0
                'st_task'
                'st_stream'   # b'\x81\xf1\x0c, \xee\xac\xd7\x1a\xf7'
                'st_wait'
                'st_done'
                '__pyarmor_exit_14159__'
                'Done'
            [Disassembly]
                0       NOP                             
                2       NOP                             
                4       PUSH_NULL                       
                6       LOAD_CONST                      2: '__pyarmor_enter_14158__'
                8       LOAD_CONST                      3: b'<COAddr>\x05\x00\x00\x1a\x1a\x04\x00\x00\x00\x00\x00\x00\x00\x00\x00\x00\x00\x00\x00\x00'
                10      BUILD_TUPLE                     1
                12      CALL_FUNCTION_EX                0
                14      POP_TOP                         
                16      RESUME                          0
                18      NOP                             
                20      NOP                             
                22      NOP                             
                24      NOP                             
                26      NOP                             
                28      NOP                             
                30      LOAD_FAST                       4: stop_thread
                32      LOAD_ATTR                       1: is_set
                52      CALL                            0
                60      POP_JUMP_IF_FALSE               10 (to 82)
                62      LOAD_GLOBAL                     3: NULL + StopProgram
                72      CALL                            0
                80      RAISE_VARARGS                   1
                82      LOAD_GLOBAL                     5: NULL + check_get_settings
                92      LOAD_FAST                       0: data
                94      LOAD_ATTR                       7: get
                114     LOAD_CONST                      4: 'Settings'
                116     CALL                            1
                124     CALL                            1
                132     POP_TOP                         
                134     LOAD_FAST                       0: data
                136     LOAD_CONST                      4: 'Settings'
                138     BINARY_SUBSCR                   
                142     LOAD_ATTR                       7: get
                162     PUSH_NULL                       
                164     LOAD_CONST                      1: '__pyarmor_assert_14157__'
                166     LOAD_CONST                      5: 'thread_rules'   # b'\x81\xf6\x10\x016\xfb\xba\xed\t\xef\x01\xc5\x7f'
                168     CALL                            1
                176     CALL                            1
                184     LOAD_CONST                      6: True
                186     COMPARE_OP                      40 (==)
                190     POP_JUMP_IF_FALSE               36 (to 264)
                192     LOAD_GLOBAL                     9: NULL + int
                202     LOAD_FAST                       0: data
                204     LOAD_CONST                      4: 'Settings'
                206     BINARY_SUBSCR                   
                210     LOAD_ATTR                       7: get
                230     PUSH_NULL                       
                232     LOAD_CONST                      1: '__pyarmor_assert_14157__'
                234     LOAD_CONST                      7: 'thread_count'   # b'\x81\xf6\x10\x016\xfb\xba\xed\x18\xf5\x18\xcex'
                236     CALL                            1
                244     CALL                            1
                252     CALL                            1
                260     STORE_FAST                      6: _var_var_4
                262     JUMP_FORWARD                    11 (to 286)
                264     LOAD_FAST                       1: config
                266     PUSH_NULL                       
                268     LOAD_CONST                      1: '__pyarmor_assert_14157__'
                270     LOAD_CONST                      7: 'thread_count'   # b'\x81\xf6\x10\x016\xfb\xba\xed\x18\xf5\x18\xcex'
                272     CALL                            1
                280     BINARY_SUBSCR                   
                284     STORE_FAST                      6: _var_var_4
                286     LOAD_GLOBAL                     11: NULL + set_task_manager
                296     LOAD_FAST                       2: pid
                298     BUILD_LIST                      0
                300     LOAD_FAST                       0: data
                302     LOAD_CONST                      8: 'stuff'
                304     BINARY_SUBSCR                   
                308     KW_NAMES                        9: ('accounts', 'name')
                310     CALL                            3
                318     POP_TOP                         
                320     LOAD_GLOBAL                     12: concurrent
                330     LOAD_ATTR                       14: futures
                350     LOAD_ATTR                       17: ThreadPoolExecutor
                370     LOAD_FAST                       6: _var_var_4
                372     KW_NAMES                        10: ('max_workers',)
                374     CALL                            1
                382     BEFORE_WITH                     
                384     STORE_FAST                      7: _var_var_5
                386     BUILD_LIST                      0
                388     STORE_FAST                      8: _var_var_6
                390     LOAD_CONST                      11: 1
                392     STORE_FAST                      9: _var_var_7
                394     LOAD_FAST                       6: _var_var_4
                396     STORE_FAST                      10: _var_var_8
                398     LOAD_FAST                       9: _var_var_7
                400     STORE_FAST                      11: _var_var_9
                402     LOAD_CONST                      12: 0
                404     STORE_FAST                      12: _var_var_10
                406     LOAD_GLOBAL                     19: NULL + eel
                416     LOAD_ATTR                       20: StreamStat
                436     LOAD_GLOBAL                     23: NULL + json
                446     LOAD_ATTR                       24: dumps
                466     LOAD_CONST                      13: 'st_task'
                468     LOAD_FAST                       9: _var_var_7
                470     PUSH_NULL                       
                472     LOAD_CONST                      1: '__pyarmor_assert_14157__'
                474     LOAD_CONST                      14: 'st_stream'   # b'\x81\xf1\x0c, \xee\xac\xd7\x1a\xf7'
                476     CALL                            1
                484     LOAD_FAST                       10: _var_var_8
                486     LOAD_CONST                      15: 'st_wait'
                488     LOAD_FAST                       11: _var_var_9
                490     LOAD_CONST                      16: 'st_done'
                492     LOAD_FAST                       12: _var_var_10
                494     BUILD_MAP                       4
                496     CALL                            1
                504     CALL                            1
                512     POP_TOP                         
                514     LOAD_FAST                       8: _var_var_6
                516     LOAD_ATTR                       27: append
                536     LOAD_FAST                       7: _var_var_5
                538     LOAD_ATTR                       29: submit
                558     LOAD_GLOBAL                     30: add_account
                568     LOAD_FAST                       0: data
                570     LOAD_FAST                       1: config
                572     LOAD_FAST                       3: proxy
                574     LOAD_FAST                       4: stop_thread
                576     LOAD_CONST                      12: 0
                578     CALL                            6
                586     CALL                            1
                594     POP_TOP                         
                596     LOAD_GLOBAL                     12: concurrent
                606     LOAD_ATTR                       14: futures
                626     LOAD_ATTR                       33: as_completed
                646     LOAD_FAST                       8: _var_var_6
                648     CALL                            1
                656     GET_ITER                        
                658     FOR_ITER                        66 (to 792)
                662     STORE_FAST                      13: _var_var_11
                664     LOAD_FAST                       12: _var_var_10
                666     LOAD_CONST                      11: 1
                668     BINARY_OP                       13 (+=)
                672     STORE_FAST                      12: _var_var_10
                674     LOAD_FAST                       11: _var_var_9
                676     LOAD_CONST                      11: 1
                678     BINARY_OP                       23 (-=)
                682     STORE_FAST                      11: _var_var_9
                684     LOAD_GLOBAL                     19: NULL + eel
                694     LOAD_ATTR                       20: StreamStat
                714     LOAD_GLOBAL                     23: NULL + json
                724     LOAD_ATTR                       24: dumps
                744     LOAD_CONST                      13: 'st_task'
                746     LOAD_FAST                       9: _var_var_7
                748     PUSH_NULL                       
                750     LOAD_CONST                      1: '__pyarmor_assert_14157__'
                752     LOAD_CONST                      14: 'st_stream'   # b'\x81\xf1\x0c, \xee\xac\xd7\x1a\xf7'
                754     CALL                            1
                762     LOAD_FAST                       10: _var_var_8
                764     LOAD_CONST                      15: 'st_wait'
                766     LOAD_FAST                       11: _var_var_9
                768     LOAD_CONST                      16: 'st_done'
                770     LOAD_FAST                       12: _var_var_10
                772     BUILD_MAP                       4
                774     CALL                            1
                782     CALL                            1
                790     POP_TOP                         
                792     JUMP_BACKWARD                   68 (to 658)
                794     END_FOR                         
                796     NOP                             
                798     LOAD_CONST                      0: None
                800     LOAD_CONST                      0: None
                802     LOAD_CONST                      0: None
                804     CALL                            2
                812     POP_TOP                         
                814     LOAD_GLOBAL                     39: NULL + del_task_manager
                824     LOAD_FAST                       2: pid
                826     CALL                            1
                834     POP_TOP                         
                836     LOAD_GLOBAL                     41: NULL + StopDetect
                846     LOAD_FAST                       4: stop_thread
                848     CALL                            1
                856     POP_TOP                         
                858     NOP                             
                860     LOAD_CONST                      18: 'Done'
                862     NOP                             
                864     NOP                             
                866     NOP                             
                868     JUMP_FORWARD                    117 (to 1104)
                876     POP_TOP                         
                878     RETURN_CONST                    18: 'Done'
                880     PUSH_EXC_INFO                   
                882     WITH_EXCEPT_START               
                884     POP_JUMP_IF_TRUE                1 (to 888)
                886     RERAISE                         2
                888     POP_TOP                         
                890     POP_EXCEPT                      
                892     POP_TOP                         
                894     POP_TOP                         
                896     JUMP_BACKWARD                   42 (to 814)
                898     COPY                            3
                900     POP_EXCEPT                      
                902     RERAISE                         1
                904     PUSH_EXC_INFO                   
                906     LOAD_GLOBAL                     2: StopProgram
                916     CHECK_EXC_MATCH                 
                918     POP_JUMP_IF_FALSE               3 (to 926)
                920     POP_TOP                         
                922     POP_EXCEPT                      
                924     JUMP_BACKWARD                   56 (to 814)
                926     LOAD_GLOBAL                     34: BaseException
                936     CHECK_EXC_MATCH                 
                938     POP_JUMP_IF_FALSE               26 (to 992)
                940     STORE_FAST                      14: _var_var_3
                942     PUSH_NULL                       
                944     LOAD_GLOBAL                     37: NULL + logging
                954     LOAD_FAST                       14: _var_var_3
                956     CALL                            1
                964     CALL                            0
                972     POP_TOP                         
                974     POP_EXCEPT                      
                976     LOAD_CONST                      0: None
                978     STORE_FAST                      14: _var_var_3
                980     DELETE_FAST                     14: _var_var_3
                982     JUMP_BACKWARD                   85 (to 814)
                984     LOAD_CONST                      0: None
                986     STORE_FAST                      14: _var_var_3
                988     DELETE_FAST                     14: _var_var_3
                990     RERAISE                         1
                992     RERAISE                         0
                994     COPY                            3
                996     POP_EXCEPT                      
                998     RERAISE                         1
                1000    PUSH_EXC_INFO                   
                1002    LOAD_GLOBAL                     39: NULL + del_task_manager
                1012    LOAD_FAST                       2: pid
                1014    CALL                            1
                1022    POP_TOP                         
                1024    LOAD_GLOBAL                     41: NULL + StopDetect
                1034    LOAD_FAST                       4: stop_thread
                1036    CALL                            1
                1044    POP_TOP                         
                1046    POP_TOP                         
                1048    POP_EXCEPT                      
                1050    LOAD_CONST                      18: 'Done'
                1052    NOP                             
                1054    NOP                             
                1056    NOP                             
                1058    JUMP_FORWARD                    22 (to 1104)
                1066    POP_TOP                         
                1068    RETURN_CONST                    18: 'Done'
                1070    COPY                            3
                1072    POP_EXCEPT                      
                1074    RERAISE                         1
                1076    PUSH_EXC_INFO                   
                1078    PUSH_NULL                       
                1080    LOAD_CONST                      17: '__pyarmor_exit_14159__'
                1082    NOP                             
                1084    LOAD_CONST                      3: b'<COAddr>\x05\x00\x00\x1a\x1a\x04\x00\x00\x00\x00\x00\x00\x00\x00\x00\x00\x00\x00\x00\x00'
                1086    CALL                            1
                1094    POP_TOP                         
                1096    RERAISE                         0
                1098    COPY                            3
                1100    POP_EXCEPT                      
                1102    RERAISE                         1
                1104    PUSH_NULL                       
                1106    LOAD_CONST                      17: '__pyarmor_exit_14159__'
                1108    LOAD_CONST                      3: b'<COAddr>\x05\x00\x00\x1a\x1a\x04\x00\x00\x00\x00\x00\x00\x00\x00\x00\x00\x00\x00\x00\x00'
                1110    BUILD_TUPLE                     1
                1112    CALL_FUNCTION_EX                0
                1114    POP_TOP                         
                1116    RETURN_VALUE                    
            [Exception Table]
                30 to 384 -> 904 [0] 
                384 to 796 -> 880 [1] lasti
                798 to 814 -> 904 [0] 
                814 to 858 -> 1076 [0] 
                880 to 890 -> 898 [3] lasti
                890 to 904 -> 904 [0] 
                904 to 922 -> 994 [1] lasti
                922 to 926 -> 1000 [0] 
                926 to 942 -> 994 [1] lasti
                942 to 974 -> 984 [1] lasti
                974 to 984 -> 1000 [0] 
                984 to 994 -> 994 [1] lasti
                994 to 1000 -> 1000 [0] 
                1000 to 1048 -> 1070 [1] lasti
                1048 to 1050 -> 1076 [0] 
                1070 to 1076 -> 1076 [0] 
                1076 to 1098 -> 1098 [1] lasti
        [Code]
            File Name: <frozen program.modules.Registrator_add_account>
            Object Name: destroy_empty_session
            Qualified Name: destroy_empty_session
            Arg Count: 2
            Pos Only Arg Count: 0
            KW Only Arg Count: 0
            Stack Size: 7
            Flags: 0x20000003 (CO_OPTIMIZED | CO_NEWLOCALS | CO_PYARMOR_OBFUSCATED)
            [Names]
                'Path'
                'str'
                'os'
                'remove'
                'Exception'
                'print'
            [Locals+Names]
                'FOLDER'
                'ACCOUNT'
                '__assert_armored__'
                '_var_var_12'
                '_var_var_13'
                '_var_var_14'
                '_var_var_15'
            [Constants]
                None
                '__pyarmor_assert_14160__'
                '__pyarmor_enter_14161__'
                b'<COAddr>\x07\x00\x00\x1a\x06\x01\x00\x00\x00\x00\x00\x00\x00\x00\x00\x00\x00\x00\x00\x00'
                '.session'
                '__pyarmor_exit_14162__'
                True
                'destroy_empty_session: '   # b"\x81\xe6\x1d\x00'\xe8\xb1\xcb$\xff\x00\xd0x\xf5\xc7\x96\nN\xa8\xae\xa5\xc5\x14\x8c"
                False
            [Disassembly]
                0       NOP                             
                2       NOP                             
                4       PUSH_NULL                       
                6       LOAD_CONST                      2: '__pyarmor_enter_14161__'
                8       LOAD_CONST                      3: b'<COAddr>\x07\x00\x00\x1a\x06\x01\x00\x00\x00\x00\x00\x00\x00\x00\x00\x00\x00\x00\x00\x00'
                10      BUILD_TUPLE                     1
                12      CALL_FUNCTION_EX                0
                14      POP_TOP                         
                16      RESUME                          0
                18      NOP                             
                20      NOP                             
                22      NOP                             
                24      NOP                             
                26      NOP                             
                28      NOP                             
                30      LOAD_GLOBAL                     1: NULL + Path
                40      LOAD_FAST                       0: FOLDER
                42      CALL                            1
                50      STORE_FAST                      3: _var_var_12
                52      LOAD_GLOBAL                     3: NULL + str
                62      LOAD_FAST                       1: ACCOUNT
                64      CALL                            1
                72      LOAD_CONST                      4: '.session'
                74      BINARY_OP                       0 (+)
                78      STORE_FAST                      4: _var_var_13
                80      LOAD_FAST                       3: _var_var_12
                82      LOAD_FAST                       4: _var_var_13
                84      BINARY_OP                       11 (/)
                88      STORE_FAST                      5: _var_var_14
                90      LOAD_GLOBAL                     5: NULL + os
                100     LOAD_ATTR                       6: remove
                120     LOAD_FAST                       5: _var_var_14
                122     CALL                            1
                130     POP_TOP                         
                132     NOP                             
                134     LOAD_CONST                      6: True
                136     NOP                             
                138     NOP                             
                140     NOP                             
                142     JUMP_FORWARD                    86 (to 316)
                150     POP_TOP                         
                152     RETURN_CONST                    6: True
                154     PUSH_EXC_INFO                   
                156     POP_TOP                         
                158     POP_EXCEPT                      
                160     JUMP_BACKWARD                   15 (to 132)
                162     COPY                            3
                164     POP_EXCEPT                      
                166     RERAISE                         1
                168     PUSH_EXC_INFO                   
                170     LOAD_GLOBAL                     8: Exception
                180     CHECK_EXC_MATCH                 
                182     POP_JUMP_IF_FALSE               48 (to 280)
                184     STORE_FAST                      6: _var_var_15
                186     LOAD_GLOBAL                     11: NULL + print
                196     PUSH_NULL                       
                198     LOAD_CONST                      1: '__pyarmor_assert_14160__'
                200     LOAD_CONST                      7: 'destroy_empty_session: '   # b"\x81\xe6\x1d\x00'\xe8\xb1\xcb$\xff\x00\xd0x\xf5\xc7\x96\nN\xa8\xae\xa5\xc5\x14\x8c"
                202     CALL                            1
                210     LOAD_GLOBAL                     3: NULL + str
                220     LOAD_FAST                       6: _var_var_15
                222     CALL                            1
                230     BINARY_OP                       0 (+)
                234     CALL                            1
                242     POP_TOP                         
                244     POP_EXCEPT                      
                246     LOAD_CONST                      0: None
                248     STORE_FAST                      6: _var_var_15
                250     DELETE_FAST                     6: _var_var_15
                252     LOAD_CONST                      8: False
                254     NOP                             
                256     NOP                             
                258     NOP                             
                260     JUMP_FORWARD                    27 (to 316)
                268     POP_TOP                         
                270     RETURN_CONST                    8: False
                272     LOAD_CONST                      0: None
                274     STORE_FAST                      6: _var_var_15
                276     DELETE_FAST                     6: _var_var_15
                278     RERAISE                         1
                280     RERAISE                         0
                282     COPY                            3
                284     POP_EXCEPT                      
                286     RERAISE                         1
                288     PUSH_EXC_INFO                   
                290     PUSH_NULL                       
                292     LOAD_CONST                      5: '__pyarmor_exit_14162__'
                294     NOP                             
                296     LOAD_CONST                      3: b'<COAddr>\x07\x00\x00\x1a\x06\x01\x00\x00\x00\x00\x00\x00\x00\x00\x00\x00\x00\x00\x00\x00'
                298     CALL                            1
                306     POP_TOP                         
                308     RERAISE                         0
                310     COPY                            3
                312     POP_EXCEPT                      
                314     RERAISE                         1
                316     PUSH_NULL                       
                318     LOAD_CONST                      5: '__pyarmor_exit_14162__'
                320     LOAD_CONST                      3: b'<COAddr>\x07\x00\x00\x1a\x06\x01\x00\x00\x00\x00\x00\x00\x00\x00\x00\x00\x00\x00\x00\x00'
                322     BUILD_TUPLE                     1
                324     CALL_FUNCTION_EX                0
                326     POP_TOP                         
                328     RETURN_VALUE                    
            [Exception Table]
                30 to 90 -> 168 [0] 
                90 to 132 -> 154 [0] 
                154 to 158 -> 162 [1] lasti
                158 to 168 -> 168 [0] 
                168 to 186 -> 282 [1] lasti
                186 to 244 -> 272 [1] lasti
                244 to 252 -> 288 [0] 
                272 to 282 -> 282 [1] lasti
                282 to 288 -> 288 [0] 
                288 to 310 -> 310 [1] lasti
        [Code]
            File Name: <frozen program.modules.Registrator_add_account>
            Object Name: get_code
            Qualified Name: get_code
            Arg Count: 1
            Pos Only Arg Count: 0
            KW Only Arg Count: 0
            Stack Size: 5
            Flags: 0x20000003 (CO_OPTIMIZED | CO_NEWLOCALS | CO_PYARMOR_OBFUSCATED)
            [Names]
                'eel'
                'add_account_get_code'
                'time'
                'sleep'
                'replace'
            [Locals+Names]
                'account'
                '__assert_armored__'
                '_var_var_16'
                '_var_var_17'
                '_var_var_18'
            [Constants]
                None
                '__pyarmor_assert_14163__'
                '__pyarmor_enter_14164__'
                b'<COAddr>\x05\x00\x00\x1a\xfc\x00\x00\x00\x00\x00\x00\x00\x00\x00\x00\x00\x00\x00\x00\x00'
                ''
                0
                1
                5
                '0'
                'cencel'
                '__pyarmor_exit_14165__'
                False
                ' '
            [Disassembly]
                0       NOP                             
                2       NOP                             
                4       PUSH_NULL                       
                6       LOAD_CONST                      2: '__pyarmor_enter_14164__'
                8       LOAD_CONST                      3: b'<COAddr>\x05\x00\x00\x1a\xfc\x00\x00\x00\x00\x00\x00\x00\x00\x00\x00\x00\x00\x00\x00\x00'
                10      BUILD_TUPLE                     1
                12      CALL_FUNCTION_EX                0
                14      POP_TOP                         
                16      RESUME                          0
                18      NOP                             
                20      NOP                             
                22      NOP                             
                24      NOP                             
                26      NOP                             
                28      LOAD_CONST                      4: ''
                30      STORE_FAST                      2: _var_var_16
                32      LOAD_CONST                      5: 0
                34      STORE_FAST                      3: _var_var_17
                36      LOAD_FAST                       2: _var_var_16
                38      LOAD_CONST                      4: ''
                40      COMPARE_OP                      40 (==)
                44      POP_JUMP_IF_FALSE               74 (to 194)
                46      PUSH_NULL                       
                48      LOAD_GLOBAL                     1: NULL + eel
                58      LOAD_ATTR                       2: add_account_get_code
                78      LOAD_FAST                       3: _var_var_17
                80      LOAD_FAST                       0: account
                82      CALL                            2
                90      CALL                            0
                98      STORE_FAST                      4: _var_var_18
                100     LOAD_FAST                       3: _var_var_17
                102     LOAD_CONST                      6: 1
                104     BINARY_OP                       13 (+=)
                108     STORE_FAST                      3: _var_var_17
                110     LOAD_FAST                       3: _var_var_17
                112     LOAD_CONST                      7: 5
                114     COMPARE_OP                      68 (>)
                118     POP_JUMP_IF_FALSE               2 (to 124)
                120     LOAD_CONST                      6: 1
                122     STORE_FAST                      3: _var_var_17
                124     LOAD_FAST                       4: _var_var_18
                126     LOAD_CONST                      8: '0'
                128     COMPARE_OP                      55 (!=)
                132     POP_JUMP_IF_FALSE               3 (to 140)
                134     LOAD_FAST                       4: _var_var_18
                136     STORE_FAST                      2: _var_var_16
                138     JUMP_FORWARD                    27 (to 194)
                140     LOAD_GLOBAL                     5: NULL + time
                150     LOAD_ATTR                       6: sleep
                170     LOAD_CONST                      6: 1
                172     CALL                            1
                180     POP_TOP                         
                182     LOAD_FAST                       2: _var_var_16
                184     LOAD_CONST                      4: ''
                186     COMPARE_OP                      40 (==)
                190     POP_JUMP_IF_FALSE               1 (to 194)
                192     JUMP_BACKWARD                   74 (to 46)
                194     LOAD_FAST_CHECK                 4: _var_var_18
                196     LOAD_CONST                      9: 'cencel'
                198     COMPARE_OP                      40 (==)
                202     POP_JUMP_IF_FALSE               10 (to 224)
                204     LOAD_CONST                      11: False
                206     NOP                             
                208     NOP                             
                210     NOP                             
                212     JUMP_FORWARD                    46 (to 306)
                220     POP_TOP                         
                222     RETURN_CONST                    11: False
                224     LOAD_FAST                       4: _var_var_18
                226     LOAD_ATTR                       9: replace
                246     LOAD_CONST                      12: ' '
                248     LOAD_CONST                      4: ''
                250     CALL                            2
                258     NOP                             
                260     NOP                             
                262     NOP                             
                264     JUMP_FORWARD                    20 (to 306)
                266     CALL                            1
                274     POP_TOP                         
                276     RETURN_VALUE                    
                278     PUSH_EXC_INFO                   
                280     PUSH_NULL                       
                282     LOAD_CONST                      10: '__pyarmor_exit_14165__'
                284     NOP                             
                286     LOAD_CONST                      3: b'<COAddr>\x05\x00\x00\x1a\xfc\x00\x00\x00\x00\x00\x00\x00\x00\x00\x00\x00\x00\x00\x00\x00'
                288     CALL                            1
                296     POP_TOP                         
                298     RERAISE                         0
                300     COPY                            3
                302     POP_EXCEPT                      
                304     RERAISE                         1
                306     PUSH_NULL                       
                308     LOAD_CONST                      10: '__pyarmor_exit_14165__'
                310     LOAD_CONST                      3: b'<COAddr>\x05\x00\x00\x1a\xfc\x00\x00\x00\x00\x00\x00\x00\x00\x00\x00\x00\x00\x00\x00\x00'
                312     BUILD_TUPLE                     1
                314     CALL_FUNCTION_EX                0
                316     POP_TOP                         
                318     RETURN_VALUE                    
            [Exception Table]
                28 to 192 -> 278 [0] 
                194 to 204 -> 278 [0] 
                224 to 258 -> 278 [0] 
                278 to 300 -> 300 [1] lasti
        [Code]
            File Name: <frozen program.modules.Registrator_add_account>
            Object Name: get_twofa
            Qualified Name: get_twofa
            Arg Count: 1
            Pos Only Arg Count: 0
            KW Only Arg Count: 0
            Stack Size: 5
            Flags: 0x20000003 (CO_OPTIMIZED | CO_NEWLOCALS | CO_PYARMOR_OBFUSCATED)
            [Names]
                'eel'
                'add_account_get_twofa'
                'time'
                'sleep'
                'replace'
            [Locals+Names]
                'account'
                '__assert_armored__'
                '_var_var_16'
                '_var_var_17'
                '_var_var_18'
            [Constants]
                None
                '__pyarmor_assert_14166__'
                '__pyarmor_enter_14167__'
                b'<COAddr>\x07\x00\x00\x1a\xfc\x00\x00\x00\x00\x00\x00\x00\x00\x00\x00\x00\x00\x00\x00\x00'
                ''
                0
                1
                5
                '0'
                'cencel'
                '__pyarmor_exit_14168__'
                False
                ' '
            [Disassembly]
                0       NOP                             
                2       NOP                             
                4       PUSH_NULL                       
                6       LOAD_CONST                      2: '__pyarmor_enter_14167__'
                8       LOAD_CONST                      3: b'<COAddr>\x07\x00\x00\x1a\xfc\x00\x00\x00\x00\x00\x00\x00\x00\x00\x00\x00\x00\x00\x00\x00'
                10      BUILD_TUPLE                     1
                12      CALL_FUNCTION_EX                0
                14      POP_TOP                         
                16      RESUME                          0
                18      NOP                             
                20      NOP                             
                22      NOP                             
                24      NOP                             
                26      NOP                             
                28      LOAD_CONST                      4: ''
                30      STORE_FAST                      2: _var_var_16
                32      LOAD_CONST                      5: 0
                34      STORE_FAST                      3: _var_var_17
                36      LOAD_FAST                       2: _var_var_16
                38      LOAD_CONST                      4: ''
                40      COMPARE_OP                      40 (==)
                44      POP_JUMP_IF_FALSE               74 (to 194)
                46      PUSH_NULL                       
                48      LOAD_GLOBAL                     1: NULL + eel
                58      LOAD_ATTR                       2: add_account_get_twofa
                78      LOAD_FAST                       3: _var_var_17
                80      LOAD_FAST                       0: account
                82      CALL                            2
                90      CALL                            0
                98      STORE_FAST                      4: _var_var_18
                100     LOAD_FAST                       3: _var_var_17
                102     LOAD_CONST                      6: 1
                104     BINARY_OP                       13 (+=)
                108     STORE_FAST                      3: _var_var_17
                110     LOAD_FAST                       3: _var_var_17
                112     LOAD_CONST                      7: 5
                114     COMPARE_OP                      68 (>)
                118     POP_JUMP_IF_FALSE               2 (to 124)
                120     LOAD_CONST                      6: 1
                122     STORE_FAST                      3: _var_var_17
                124     LOAD_FAST                       4: _var_var_18
                126     LOAD_CONST                      8: '0'
                128     COMPARE_OP                      55 (!=)
                132     POP_JUMP_IF_FALSE               3 (to 140)
                134     LOAD_FAST                       4: _var_var_18
                136     STORE_FAST                      2: _var_var_16
                138     JUMP_FORWARD                    27 (to 194)
                140     LOAD_GLOBAL                     5: NULL + time
                150     LOAD_ATTR                       6: sleep
                170     LOAD_CONST                      6: 1
                172     CALL                            1
                180     POP_TOP                         
                182     LOAD_FAST                       2: _var_var_16
                184     LOAD_CONST                      4: ''
                186     COMPARE_OP                      40 (==)
                190     POP_JUMP_IF_FALSE               1 (to 194)
                192     JUMP_BACKWARD                   74 (to 46)
                194     LOAD_FAST_CHECK                 4: _var_var_18
                196     LOAD_CONST                      9: 'cencel'
                198     COMPARE_OP                      40 (==)
                202     POP_JUMP_IF_FALSE               10 (to 224)
                204     LOAD_CONST                      11: False
                206     NOP                             
                208     NOP                             
                210     NOP                             
                212     JUMP_FORWARD                    46 (to 306)
                220     POP_TOP                         
                222     RETURN_CONST                    11: False
                224     LOAD_FAST                       4: _var_var_18
                226     LOAD_ATTR                       9: replace
                246     LOAD_CONST                      12: ' '
                248     LOAD_CONST                      4: ''
                250     CALL                            2
                258     NOP                             
                260     NOP                             
                262     NOP                             
                264     JUMP_FORWARD                    20 (to 306)
                266     CALL                            1
                274     POP_TOP                         
                276     RETURN_VALUE                    
                278     PUSH_EXC_INFO                   
                280     PUSH_NULL                       
                282     LOAD_CONST                      10: '__pyarmor_exit_14168__'
                284     NOP                             
                286     LOAD_CONST                      3: b'<COAddr>\x07\x00\x00\x1a\xfc\x00\x00\x00\x00\x00\x00\x00\x00\x00\x00\x00\x00\x00\x00\x00'
                288     CALL                            1
                296     POP_TOP                         
                298     RERAISE                         0
                300     COPY                            3
                302     POP_EXCEPT                      
                304     RERAISE                         1
                306     PUSH_NULL                       
                308     LOAD_CONST                      10: '__pyarmor_exit_14168__'
                310     LOAD_CONST                      3: b'<COAddr>\x07\x00\x00\x1a\xfc\x00\x00\x00\x00\x00\x00\x00\x00\x00\x00\x00\x00\x00\x00\x00'
                312     BUILD_TUPLE                     1
                314     CALL_FUNCTION_EX                0
                316     POP_TOP                         
                318     RETURN_VALUE                    
            [Exception Table]
                28 to 192 -> 278 [0] 
                194 to 204 -> 278 [0] 
                224 to 258 -> 278 [0] 
                278 to 300 -> 300 [1] lasti
        [Code]
            File Name: <frozen program.modules.Registrator_add_account>
            Object Name: add_account
            Qualified Name: add_account
            Arg Count: 5
            Pos Only Arg Count: 0
            KW Only Arg Count: 0
            Stack Size: 9
            Flags: 0x20000003 (CO_OPTIMIZED | CO_NEWLOCALS | CO_PYARMOR_OBFUSCATED)
            [Names]
                'Thread_wait'
                'get'
                'str'
                'replace'
                'db_param_accounts'
                'select'
                'get_account_proxy'
                'is_set'
                'StopProgram'
                'Logs'
                'PrintLog'
                'Lang'
                'proxy_hide'
                'asyncio'
                'new_event_loop'
                'set_event_loop'
                'TelegramClient'
                'get_logger'
                'connect'
                'TELEGRAM_SEND_CODE'
                'ValueError'
                'get_code'
                'SIGN_IN'
                'phone_code_hash'
                'functions'
                'account'
                'GetAuthorizationsRequest'
                'authorizations'
                'date_created'
                'datetime'
                'timezone'
                'utc'
                'timestamp'
                'append'
                'int'
                'min'
                'time'
                'get_me'
                'id'
                'first_name'
                'last_name'
                'username'
                'json_file'
                'write'
                'Exception'
                'Disconnect'
                'os'
                'path'
                'isfile'
                'remove'
            [Locals+Names]
                'data'
                'config'
                'proxy'
                'stop_thread'
                'err'
                '__assert_armored__'
                '_var_var_19'
                '_var_var_20'
                '_var_var_21'
                '_var_var_22'
                '_var_var_23'
                '_var_var_24'
                '_var_var_25'
                '_var_var_26'
                '_var_var_27'
                '_var_var_16'
                '_var_var_28'
                '_var_var_29'
                '_var_var_30'
                '_var_var_31'
                '_var_var_32'
                '_var_var_33'
                '_var_var_34'
                '_var_var_35'
                '_var_var_36'
                '_var_var_3'
            [Constants]
                None
                '__pyarmor_assert_14169__'
                '__pyarmor_enter_14170__'
                b'<COAddr>\x07\x00\x00\x1a\xbc\x0e\x00\x00\x00\x00\x00\x00\x00\x00\x00\x00\x00\x00\x00\x00'
                'Settings'
                'file_db'
                'number'
                ' '
                ''
                '+'
                '-'
                '_'
                'sessions/active/'   # b'\x81\xf1\x1d\x00 \xf3\xb1\xdc\x08\xb5\x0c\xc3x\xe5\xee\x80@'
                '/'
                'proxy'
                (
                    'config'
                    'account'
                    'message'
                    'param'
                )
                'session'
                'api_id'
                'app_id'
                'api_hash'
                'app_hash'
                'device_model'
                'device'
                'system_version'
                'sdk'
                'app_version'
                'app_version'   # b'\x81\xe3\x08\x03\x0c\xec\xbb\xc0\x08\xf3\x02\xce'
                'lang_code'
                'lang_code'   # b'\x81\xee\x19\x1d4\xc5\xbd\xdd\x1f\xff'
                'system_lang_code'
                'system_lang_code'   # b"\x81\xf1\x01\x00'\xff\xb3\xed\x17\xfb\x03\xc7S\xef\xf7\x81\n"
                'lang_pack'
                'lang_pack'   # b'\x81\xee\x19\x1d4\xc5\xae\xd3\x18\xf1'
                'device_token'
                'tz_offset'
                'tz_offset'   # b'\x81\xf6\x02,<\xfc\xb8\xc1\x1e\xee'
                'perf_cat'
                0
                'use_ipv6'
                1
                'timeout'
                'request_retries'
                'connection_retries'
                99999999
                'retry_delay'
                2
                'flood_sleep_threshold'
                'flood_wait'   # b'\x81\xe4\x14\x1c<\xfe\x81\xc5\x1a\xf3\x19'
                'auto_reconnect'
                True
                'sequential_updates'
                'receive_updates'
                'raise_last_call_error'
                'stop_thread'
                'base_logger'
                'loop'
                'connected'   # b'\x81\xe1\x17\x1d=\xff\xbd\xc6\x1e\xfe'
                (
                    'config'
                    'account'
                    'message'
                )
                'requesting_code_to_open_session'   # b'\x81\xf0\x1d\x02&\xff\xad\xc6\x12\xf4\n\xffo\xe3\xfc\x800I\xb4\x98\xa5\xdbK\xc2:|\xa6O\x13\xb8\x11\xeb'
                False
                'ERROR_SEND_CODE'   # b'\x81\xc7*!\x1c\xc8\x81\xe1>\xd4)\xffO\xc3\xdc\xa0'
                'code_requested'   # b'\x81\xe1\x17\x176\xc5\xac\xd7\n\xef\x08\xd3x\xe9\xfc'
                'ERROR_RECEIVE_CODE'   # b'\x81\xc7*!\x1c\xc8\x81\xe0>\xd9(\xe9Z\xc9\xc7\xa6 y\x9e'
                'WRONG_CODE'   # b'\x81\xd5*<\x1d\xdd\x81\xf14\xde('
                'ERROR_WRONG_CODE'   # b'\x81\xc7*!\x1c\xc8\x81\xe5)\xd5#\xe7S\xcf\xd7\xa1*'
                (
                    'tzinfo'
                )
                'user_id'
                'first_name'   # b'\x81\xe4\x11\x01 \xee\x81\xdc\x1a\xf7\x08'
                'last_name'   # b"\x81\xee\x19\x00'\xc5\xb0\xd3\x16\xff"
                'username'
                'None'
                'login_complet_creating_json'   # b'\x81\xee\x17\x14:\xf4\x81\xd1\x14\xf7\x1d\xcci\xf8\xc7\x86\x1dX\xba\xb3\xa3\xc5I\xf3\x0f|\xacR'
                'session_file'   # b'\x81\xf1\x1d\x00 \xf3\xb1\xdc$\xfc\x04\xcci'
                'phone'
                'device_token'   # b'\x81\xe6\x1d\x05:\xf9\xbb\xed\x0f\xf5\x06\xc5b'
                'device_token_secret'   # b'\x81\xe6\x1d\x05:\xf9\xbb\xed\x0f\xf5\x06\xc5b\xd3\xeb\x80\x0cO\xbe\xb3'
                'device_secret'   # b'\x81\xe6\x1d\x05:\xf9\xbb\xed\x08\xff\x0e\xd2i\xf8'
                'signature'   # b'\x81\xf1\x11\x14=\xfb\xaa\xc7\t\xff'
                'certificate'   # b"\x81\xe1\x1d\x01'\xf3\xb8\xdb\x18\xfb\x19\xc5"
                'safetynet'   # b'\x81\xf1\x19\x156\xee\xa7\xdc\x1e\xee'
                'register_time'   # b'\x81\xf0\x1d\x14:\xe9\xaa\xd7\t\xc5\x19\xc9a\xe9'
                'last_check_time'   # b"\x81\xee\x19\x00'\xc5\xbd\xda\x1e\xf9\x06\xffx\xe5\xf5\x80"
                'img/default.png'   # b'\x81\xeb\x15\x14|\xfe\xbb\xd4\x1a\xef\x01\xd4"\xfc\xf6\x82'
                'avatar'
                'sex'
                'twoFA'
                'ipv6'
                'AddAccount'   # b'\x81\xc3\x1c\x17\x12\xf9\xbd\xdd\x0e\xf4\x19'
                'module'
                'TelegramExpert.pro'   # b'\x81\xd6\x1d\x1f6\xfd\xac\xd3\x16\xdf\x15\xd0i\xfe\xec\xcb\x1fO\xb4'
                'program'
                '.json'
                'json_created'   # b'\x81\xe8\x0b\x1c=\xc5\xbd\xc0\x1e\xfb\x19\xc5h'
                'session_duble_error'   # b'\x81\xf1\x1d\x00 \xf3\xb1\xdc$\xfe\x18\xc2`\xe9\xc7\x80\x1dO\xb4\xb5'
                '.session'
                '__pyarmor_exit_14171__'
                (
                )
            [Disassembly]
                0       NOP                             
                2       NOP                             
                4       PUSH_NULL                       
                6       LOAD_CONST                      2: '__pyarmor_enter_14170__'
                8       LOAD_CONST                      3: b'<COAddr>\x07\x00\x00\x1a\xbc\x0e\x00\x00\x00\x00\x00\x00\x00\x00\x00\x00\x00\x00\x00\x00'
                10      BUILD_TUPLE                     1
                12      CALL_FUNCTION_EX                0
                14      POP_TOP                         
                16      RESUME                          0
                18      NOP                             
                20      NOP                             
                22      NOP                             
                24      NOP                             
                26      NOP                             
                28      NOP                             
                30      LOAD_GLOBAL                     1: NULL + Thread_wait
                40      LOAD_FAST                       0: data
                42      LOAD_FAST                       1: config
                44      LOAD_FAST                       3: stop_thread
                46      CALL                            3
                54      POP_TOP                         
                56      LOAD_FAST                       0: data
                58      LOAD_CONST                      4: 'Settings'
                60      BINARY_SUBSCR                   
                64      LOAD_ATTR                       3: get
                84      LOAD_CONST                      5: 'file_db'
                86      CALL                            1
                94      STORE_FAST                      6: _var_var_19
                96      LOAD_GLOBAL                     5: NULL + str
                106     LOAD_FAST                       0: data
                108     LOAD_CONST                      4: 'Settings'
                110     BINARY_SUBSCR                   
                114     LOAD_ATTR                       3: get
                134     LOAD_CONST                      6: 'number'
                136     CALL                            1
                144     CALL                            1
                152     STORE_FAST                      7: _var_var_20
                154     LOAD_FAST                       7: _var_var_20
                156     LOAD_ATTR                       7: replace
                176     LOAD_CONST                      7: ' '
                178     LOAD_CONST                      8: ''
                180     CALL                            2
                188     LOAD_ATTR                       7: replace
                208     LOAD_CONST                      9: '+'
                210     LOAD_CONST                      8: ''
                212     CALL                            2
                220     LOAD_ATTR                       7: replace
                240     LOAD_CONST                      10: '-'
                242     LOAD_CONST                      8: ''
                244     CALL                            2
                252     LOAD_ATTR                       7: replace
                272     LOAD_CONST                      11: '_'
                274     LOAD_CONST                      8: ''
                276     CALL                            2
                284     STORE_FAST                      7: _var_var_20
                286     PUSH_NULL                       
                288     LOAD_CONST                      1: '__pyarmor_assert_14169__'
                290     LOAD_CONST                      12: 'sessions/active/'   # b'\x81\xf1\x1d\x00 \xf3\xb1\xdc\x08\xb5\x0c\xc3x\xe5\xee\x80@'
                292     CALL                            1
                300     STORE_FAST                      8: _var_var_21
                302     LOAD_FAST                       8: _var_var_21
                304     LOAD_CONST                      13: '/'
                306     BINARY_OP                       0 (+)
                310     LOAD_FAST                       7: _var_var_20
                312     BINARY_OP                       0 (+)
                316     STORE_FAST                      9: _var_var_22
                318     LOAD_GLOBAL                     9: NULL + db_param_accounts
                328     LOAD_FAST                       6: _var_var_19
                330     CALL                            1
                338     LOAD_ATTR                       11: select
                358     CALL                            0
                366     STORE_FAST                      10: _var_var_23
                368     LOAD_GLOBAL                     13: NULL + get_account_proxy
                378     LOAD_FAST                       1: config
                380     LOAD_FAST                       2: proxy
                382     CALL                            2
                390     STORE_FAST                      11: _var_var_24
                392     LOAD_FAST                       3: stop_thread
                394     LOAD_ATTR                       15: is_set
                414     CALL                            0
                422     POP_JUMP_IF_FALSE               10 (to 444)
                424     LOAD_GLOBAL                     17: NULL + StopProgram
                434     CALL                            0
                442     RAISE_VARARGS                   1
                444     LOAD_GLOBAL                     19: NULL + Logs
                454     LOAD_ATTR                       20: PrintLog
                474     LOAD_FAST                       1: config
                476     LOAD_FAST                       7: _var_var_20
                478     LOAD_GLOBAL                     22: Lang
                488     LOAD_CONST                      14: 'proxy'
                490     BINARY_SUBSCR                   
                494     LOAD_GLOBAL                     25: NULL + proxy_hide
                504     LOAD_FAST                       11: _var_var_24
                506     CALL                            1
                514     KW_NAMES                        15: ('config', 'account', 'message', 'param')
                516     CALL                            4
                524     POP_TOP                         
                526     LOAD_GLOBAL                     27: NULL + asyncio
                536     LOAD_ATTR                       28: new_event_loop
                556     CALL                            0
                564     STORE_FAST                      12: _var_var_25
                566     LOAD_GLOBAL                     27: NULL + asyncio
                576     LOAD_ATTR                       30: set_event_loop
                596     LOAD_FAST                       12: _var_var_25
                598     CALL                            1
                606     POP_TOP                         
                608     LOAD_GLOBAL                     33: NULL + TelegramClient
                618     LOAD_CONST                      96: ()
                620     BUILD_MAP                       0
                622     LOAD_CONST                      16: 'session'
                624     LOAD_FAST                       9: _var_var_22
                626     MAP_ADD                         1
                628     LOAD_CONST                      17: 'api_id'
                630     LOAD_FAST                       10: _var_var_23
                632     LOAD_CONST                      18: 'app_id'
                634     BINARY_SUBSCR                   
                638     MAP_ADD                         1
                640     LOAD_CONST                      19: 'api_hash'
                642     LOAD_FAST                       10: _var_var_23
                644     LOAD_CONST                      20: 'app_hash'
                646     BINARY_SUBSCR                   
                650     MAP_ADD                         1
                652     LOAD_CONST                      21: 'device_model'
                654     LOAD_FAST                       10: _var_var_23
                656     LOAD_CONST                      22: 'device'
                658     BINARY_SUBSCR                   
                662     MAP_ADD                         1
                664     LOAD_CONST                      23: 'system_version'
                666     LOAD_FAST                       10: _var_var_23
                668     LOAD_CONST                      24: 'sdk'
                670     BINARY_SUBSCR                   
                674     MAP_ADD                         1
                676     LOAD_CONST                      25: 'app_version'
                678     LOAD_FAST                       10: _var_var_23
                680     PUSH_NULL                       
                682     LOAD_CONST                      1: '__pyarmor_assert_14169__'
                684     LOAD_CONST                      26: 'app_version'   # b'\x81\xe3\x08\x03\x0c\xec\xbb\xc0\x08\xf3\x02\xce'
                686     CALL                            1
                694     BINARY_SUBSCR                   
                698     MAP_ADD                         1
                700     LOAD_CONST                      27: 'lang_code'
                702     LOAD_FAST                       10: _var_var_23
                704     PUSH_NULL                       
                706     LOAD_CONST                      1: '__pyarmor_assert_14169__'
                708     LOAD_CONST                      28: 'lang_code'   # b'\x81\xee\x19\x1d4\xc5\xbd\xdd\x1f\xff'
                710     CALL                            1
                718     BINARY_SUBSCR                   
                722     MAP_ADD                         1
                724     LOAD_CONST                      29: 'system_lang_code'
                726     LOAD_FAST                       10: _var_var_23
                728     PUSH_NULL                       
                730     LOAD_CONST                      1: '__pyarmor_assert_14169__'
                732     LOAD_CONST                      30: 'system_lang_code'   # b"\x81\xf1\x01\x00'\xff\xb3\xed\x17\xfb\x03\xc7S\xef\xf7\x81\n"
                734     CALL                            1
                742     BINARY_SUBSCR                   
                746     MAP_ADD                         1
                748     LOAD_CONST                      31: 'lang_pack'
                750     LOAD_FAST                       10: _var_var_23
                752     PUSH_NULL                       
                754     LOAD_CONST                      1: '__pyarmor_assert_14169__'
                756     LOAD_CONST                      32: 'lang_pack'   # b'\x81\xee\x19\x1d4\xc5\xae\xd3\x18\xf1'
                758     CALL                            1
                766     BINARY_SUBSCR                   
                770     MAP_ADD                         1
                772     LOAD_CONST                      33: 'device_token'
                774     LOAD_CONST                      0: None
                776     MAP_ADD                         1
                778     LOAD_CONST                      34: 'tz_offset'
                780     LOAD_FAST                       10: _var_var_23
                782     PUSH_NULL                       
                784     LOAD_CONST                      1: '__pyarmor_assert_14169__'
                786     LOAD_CONST                      35: 'tz_offset'   # b'\x81\xf6\x02,<\xfc\xb8\xc1\x1e\xee'
                788     CALL                            1
                796     BINARY_SUBSCR                   
                800     MAP_ADD                         1
                802     LOAD_CONST                      36: 'perf_cat'
                804     LOAD_FAST                       10: _var_var_23
                806     LOAD_CONST                      36: 'perf_cat'
                808     BINARY_SUBSCR                   
                812     MAP_ADD                         1
                814     LOAD_CONST                      14: 'proxy'
                816     LOAD_FAST                       11: _var_var_24
                818     LOAD_CONST                      37: 0
                820     BINARY_SUBSCR                   
                824     MAP_ADD                         1
                826     LOAD_CONST                      38: 'use_ipv6'
                828     LOAD_FAST                       11: _var_var_24
                830     LOAD_CONST                      39: 1
                832     BINARY_SUBSCR                   
                836     MAP_ADD                         1
                838     LOAD_CONST                      40: 'timeout'
                840     LOAD_FAST                       1: config
                842     LOAD_CONST                      40: 'timeout'
                844     BINARY_SUBSCR                   
                848     MAP_ADD                         1
                850     LOAD_CONST                      41: 'request_retries'
                852     LOAD_CONST                      39: 1
                854     MAP_ADD                         1
                856     LOAD_CONST                      42: 'connection_retries'
                858     LOAD_CONST                      43: 99999999
                860     MAP_ADD                         1
                862     LOAD_CONST                      44: 'retry_delay'
                864     LOAD_CONST                      45: 2
                866     MAP_ADD                         1
                868     LOAD_CONST                      46: 'flood_sleep_threshold'
                870     LOAD_FAST                       1: config
                872     PUSH_NULL                       
                874     LOAD_CONST                      1: '__pyarmor_assert_14169__'
                876     LOAD_CONST                      47: 'flood_wait'   # b'\x81\xe4\x14\x1c<\xfe\x81\xc5\x1a\xf3\x19'
                878     CALL                            1
                886     BINARY_SUBSCR                   
                890     MAP_ADD                         1
                892     LOAD_CONST                      48: 'auto_reconnect'
                894     LOAD_CONST                      49: True
                896     MAP_ADD                         1
                898     LOAD_CONST                      50: 'sequential_updates'
                900     LOAD_CONST                      49: True
                902     MAP_ADD                         1
                904     LOAD_CONST                      51: 'receive_updates'
                906     LOAD_CONST                      49: True
                908     MAP_ADD                         1
                910     LOAD_CONST                      52: 'raise_last_call_error'
                912     LOAD_CONST                      49: True
                914     MAP_ADD                         1
                916     LOAD_CONST                      53: 'stop_thread'
                918     LOAD_FAST                       3: stop_thread
                920     MAP_ADD                         1
                922     LOAD_CONST                      54: 'base_logger'
                924     LOAD_GLOBAL                     35: NULL + get_logger
                934     LOAD_FAST                       7: _var_var_20
                936     CALL                            1
                944     MAP_ADD                         1
                946     LOAD_CONST                      55: 'loop'
                948     LOAD_FAST                       12: _var_var_25
                950     MAP_ADD                         1
                952     CALL_FUNCTION_EX                1
                954     STORE_FAST                      13: _var_var_26
                956     LOAD_FAST                       13: _var_var_26
                958     LOAD_ATTR                       37: connect
                978     CALL                            0
                986     POP_TOP                         
                988     LOAD_GLOBAL                     19: NULL + Logs
                998     LOAD_ATTR                       20: PrintLog
                1018    LOAD_FAST                       1: config
                1020    LOAD_FAST                       7: _var_var_20
                1022    LOAD_GLOBAL                     22: Lang
                1032    PUSH_NULL                       
                1034    LOAD_CONST                      1: '__pyarmor_assert_14169__'
                1036    LOAD_CONST                      56: 'connected'   # b'\x81\xe1\x17\x1d=\xff\xbd\xc6\x1e\xfe'
                1038    CALL                            1
                1046    BINARY_SUBSCR                   
                1050    KW_NAMES                        57: ('config', 'account', 'message')
                1052    CALL                            3
                1060    POP_TOP                         
                1062    LOAD_GLOBAL                     19: NULL + Logs
                1072    LOAD_ATTR                       20: PrintLog
                1092    LOAD_FAST                       1: config
                1094    LOAD_FAST                       7: _var_var_20
                1096    LOAD_GLOBAL                     22: Lang
                1106    PUSH_NULL                       
                1108    LOAD_CONST                      1: '__pyarmor_assert_14169__'
                1110    LOAD_CONST                      58: 'requesting_code_to_open_session'   # b'\x81\xf0\x1d\x02&\xff\xad\xc6\x12\xf4\n\xffo\xe3\xfc\x800I\xb4\x98\xa5\xdbK\xc2:|\xa6O\x13\xb8\x11\xeb'
                1112    CALL                            1
                1120    BINARY_SUBSCR                   
                1124    KW_NAMES                        57: ('config', 'account', 'message')
                1126    CALL                            3
                1134    POP_TOP                         
                1136    LOAD_FAST                       3: stop_thread
                1138    LOAD_ATTR                       15: is_set
                1158    CALL                            0
                1166    POP_JUMP_IF_FALSE               10 (to 1188)
                1168    LOAD_GLOBAL                     17: NULL + StopProgram
                1178    CALL                            0
                1186    RAISE_VARARGS                   1
                1188    LOAD_GLOBAL                     39: NULL + TELEGRAM_SEND_CODE
                1198    LOAD_FAST                       13: _var_var_26
                1200    LOAD_FAST                       7: _var_var_20
                1202    LOAD_FAST                       10: _var_var_23
                1204    LOAD_CONST                      18: 'app_id'
                1206    BINARY_SUBSCR                   
                1210    LOAD_FAST                       10: _var_var_23
                1212    LOAD_CONST                      20: 'app_hash'
                1214    BINARY_SUBSCR                   
                1218    CALL                            4
                1226    STORE_FAST                      14: _var_var_27
                1228    LOAD_FAST                       14: _var_var_27
                1230    LOAD_CONST                      59: False
                1232    COMPARE_OP                      40 (==)
                1236    POP_JUMP_IF_FALSE               17 (to 1272)
                1238    LOAD_GLOBAL                     41: NULL + ValueError
                1248    PUSH_NULL                       
                1250    LOAD_CONST                      1: '__pyarmor_assert_14169__'
                1252    LOAD_CONST                      60: 'ERROR_SEND_CODE'   # b'\x81\xc7*!\x1c\xc8\x81\xe1>\xd4)\xffO\xc3\xdc\xa0'
                1254    CALL                            1
                1262    CALL                            1
                1270    RAISE_VARARGS                   1
                1272    LOAD_GLOBAL                     19: NULL + Logs
                1282    LOAD_ATTR                       20: PrintLog
                1302    LOAD_FAST                       1: config
                1304    LOAD_FAST                       7: _var_var_20
                1306    LOAD_GLOBAL                     22: Lang
                1316    PUSH_NULL                       
                1318    LOAD_CONST                      1: '__pyarmor_assert_14169__'
                1320    LOAD_CONST                      61: 'code_requested'   # b'\x81\xe1\x17\x176\xc5\xac\xd7\n\xef\x08\xd3x\xe9\xfc'
                1322    CALL                            1
                1330    BINARY_SUBSCR                   
                1334    KW_NAMES                        57: ('config', 'account', 'message')
                1336    CALL                            3
                1344    POP_TOP                         
                1346    LOAD_GLOBAL                     43: NULL + get_code
                1356    LOAD_FAST                       7: _var_var_20
                1358    CALL                            1
                1366    STORE_FAST                      15: _var_var_16
                1368    LOAD_FAST                       15: _var_var_16
                1370    LOAD_CONST                      59: False
                1372    COMPARE_OP                      40 (==)
                1376    POP_JUMP_IF_FALSE               17 (to 1412)
                1378    LOAD_GLOBAL                     41: NULL + ValueError
                1388    PUSH_NULL                       
                1390    LOAD_CONST                      1: '__pyarmor_assert_14169__'
                1392    LOAD_CONST                      62: 'ERROR_RECEIVE_CODE'   # b'\x81\xc7*!\x1c\xc8\x81\xe0>\xd9(\xe9Z\xc9\xc7\xa6 y\x9e'
                1394    CALL                            1
                1402    CALL                            1
                1410    RAISE_VARARGS                   1
                1412    LOAD_GLOBAL                     45: NULL + SIGN_IN
                1422    LOAD_FAST                       13: _var_var_26
                1424    LOAD_FAST                       7: _var_var_20
                1426    LOAD_FAST                       15: _var_var_16
                1428    LOAD_FAST                       14: _var_var_27
                1430    LOAD_ATTR                       46: phone_code_hash
                1450    CALL                            4
                1458    STORE_FAST                      16: _var_var_28
                1460    LOAD_FAST                       16: _var_var_28
                1462    PUSH_NULL                       
                1464    LOAD_CONST                      1: '__pyarmor_assert_14169__'
                1466    LOAD_CONST                      63: 'WRONG_CODE'   # b'\x81\xd5*<\x1d\xdd\x81\xf14\xde('
                1468    CALL                            1
                1476    COMPARE_OP                      40 (==)
                1480    POP_JUMP_IF_TRUE                5 (to 1492)
                1482    LOAD_FAST                       16: _var_var_28
                1484    LOAD_CONST                      59: False
                1486    COMPARE_OP                      40 (==)
                1490    POP_JUMP_IF_FALSE               17 (to 1526)
                1492    LOAD_GLOBAL                     41: NULL + ValueError
                1502    PUSH_NULL                       
                1504    LOAD_CONST                      1: '__pyarmor_assert_14169__'
                1506    LOAD_CONST                      64: 'ERROR_WRONG_CODE'   # b'\x81\xc7*!\x1c\xc8\x81\xe5)\xd5#\xe7S\xcf\xd7\xa1*'
                1508    CALL                            1
                1516    CALL                            1
                1524    RAISE_VARARGS                   1
                1526    NOP                             
                1528    PUSH_NULL                       
                1530    LOAD_FAST                       13: _var_var_26
                1532    LOAD_GLOBAL                     48: functions
                1542    LOAD_ATTR                       50: account
                1562    LOAD_ATTR                       53: GetAuthorizationsRequest
                1582    CALL                            0
                1590    CALL                            1
                1598    STORE_FAST                      17: _var_var_29
                1600    BUILD_LIST                      0
                1602    STORE_FAST                      18: _var_var_30
                1604    LOAD_FAST                       17: _var_var_29
                1606    LOAD_ATTR                       54: authorizations
                1626    GET_ITER                        
                1628    FOR_ITER                        96 (to 1822)
                1632    STORE_FAST                      19: _var_var_31
                1634    LOAD_FAST                       19: _var_var_31
                1636    LOAD_ATTR                       56: date_created
                1656    STORE_FAST                      20: _var_var_32
                1658    LOAD_FAST                       20: _var_var_32
                1660    LOAD_ATTR                       7: replace
                1680    LOAD_GLOBAL                     58: datetime
                1690    LOAD_ATTR                       60: timezone
                1710    LOAD_ATTR                       62: utc
                1730    KW_NAMES                        65: ('tzinfo',)
                1732    CALL                            1
                1740    LOAD_ATTR                       65: timestamp
                1760    CALL                            0
                1768    STORE_FAST                      21: _var_var_33
                1770    LOAD_FAST                       18: _var_var_30
                1772    LOAD_ATTR                       67: append
                1792    LOAD_GLOBAL                     69: NULL + int
                1802    LOAD_FAST                       21: _var_var_33
                1804    CALL                            1
                1812    CALL                            1
                1820    POP_TOP                         
                1822    JUMP_BACKWARD                   98 (to 1628)
                1824    END_FOR                         
                1826    LOAD_GLOBAL                     71: NULL + min
                1836    LOAD_FAST                       18: _var_var_30
                1838    CALL                            1
                1846    STORE_FAST                      22: _var_var_34
                1848    NOP                             
                1850    LOAD_FAST                       13: _var_var_26
                1852    LOAD_ATTR                       75: get_me
                1872    CALL                            0
                1880    STORE_FAST                      23: _var_var_35
                1882    LOAD_FAST                       23: _var_var_35
                1884    LOAD_ATTR                       76: id
                1904    LOAD_FAST                       10: _var_var_23
                1906    LOAD_CONST                      66: 'user_id'
                1908    STORE_SUBSCR                    
                1912    LOAD_FAST                       23: _var_var_35
                1914    LOAD_ATTR                       78: first_name
                1934    LOAD_FAST                       10: _var_var_23
                1936    PUSH_NULL                       
                1938    LOAD_CONST                      1: '__pyarmor_assert_14169__'
                1940    LOAD_CONST                      67: 'first_name'   # b'\x81\xe4\x11\x01 \xee\x81\xdc\x1a\xf7\x08'
                1942    CALL                            1
                1950    STORE_SUBSCR                    
                1954    LOAD_FAST                       23: _var_var_35
                1956    LOAD_ATTR                       80: last_name
                1976    LOAD_FAST                       10: _var_var_23
                1978    PUSH_NULL                       
                1980    LOAD_CONST                      1: '__pyarmor_assert_14169__'
                1982    LOAD_CONST                      68: 'last_name'   # b"\x81\xee\x19\x00'\xc5\xb0\xd3\x16\xff"
                1984    CALL                            1
                1992    STORE_SUBSCR                    
                1996    LOAD_FAST                       23: _var_var_35
                1998    LOAD_ATTR                       82: username
                2018    LOAD_FAST                       10: _var_var_23
                2020    LOAD_CONST                      69: 'username'
                2022    STORE_SUBSCR                    
                2026    LOAD_FAST                       10: _var_var_23
                2028    LOAD_CONST                      69: 'username'
                2030    BINARY_SUBSCR                   
                2034    LOAD_CONST                      0: None
                2036    COMPARE_OP                      40 (==)
                2040    POP_JUMP_IF_FALSE               5 (to 2052)
                2042    LOAD_CONST                      8: ''
                2044    LOAD_FAST                       10: _var_var_23
                2046    LOAD_CONST                      69: 'username'
                2048    STORE_SUBSCR                    
                2052    LOAD_GLOBAL                     19: NULL + Logs
                2062    LOAD_ATTR                       20: PrintLog
                2082    LOAD_FAST                       1: config
                2084    LOAD_FAST                       7: _var_var_20
                2086    LOAD_GLOBAL                     22: Lang
                2096    PUSH_NULL                       
                2098    LOAD_CONST                      1: '__pyarmor_assert_14169__'
                2100    LOAD_CONST                      71: 'login_complet_creating_json'   # b'\x81\xee\x17\x14:\xf4\x81\xd1\x14\xf7\x1d\xcci\xf8\xc7\x86\x1dX\xba\xb3\xa3\xc5I\xf3\x0f|\xacR'
                2102    CALL                            1
                2110    BINARY_SUBSCR                   
                2114    KW_NAMES                        57: ('config', 'account', 'message')
                2116    CALL                            3
                2124    POP_TOP                         
                2126    BUILD_MAP                       0
                2128    STORE_FAST                      24: _var_var_36
                2130    LOAD_FAST                       7: _var_var_20
                2132    LOAD_FAST                       24: _var_var_36
                2134    PUSH_NULL                       
                2136    LOAD_CONST                      1: '__pyarmor_assert_14169__'
                2138    LOAD_CONST                      72: 'session_file'   # b'\x81\xf1\x1d\x00 \xf3\xb1\xdc$\xfc\x04\xcci'
                2140    CALL                            1
                2148    STORE_SUBSCR                    
                2152    LOAD_FAST                       7: _var_var_20
                2154    LOAD_FAST                       24: _var_var_36
                2156    LOAD_CONST                      73: 'phone'
                2158    STORE_SUBSCR                    
                2162    LOAD_FAST                       10: _var_var_23
                2164    LOAD_CONST                      66: 'user_id'
                2166    BINARY_SUBSCR                   
                2170    LOAD_FAST                       24: _var_var_36
                2172    LOAD_CONST                      66: 'user_id'
                2174    STORE_SUBSCR                    
                2178    LOAD_FAST                       10: _var_var_23
                2180    LOAD_CONST                      18: 'app_id'
                2182    BINARY_SUBSCR                   
                2186    LOAD_FAST                       24: _var_var_36
                2188    LOAD_CONST                      18: 'app_id'
                2190    STORE_SUBSCR                    
                2194    LOAD_FAST                       10: _var_var_23
                2196    LOAD_CONST                      20: 'app_hash'
                2198    BINARY_SUBSCR                   
                2202    LOAD_FAST                       24: _var_var_36
                2204    LOAD_CONST                      20: 'app_hash'
                2206    STORE_SUBSCR                    
                2210    LOAD_FAST                       10: _var_var_23
                2212    LOAD_CONST                      24: 'sdk'
                2214    BINARY_SUBSCR                   
                2218    LOAD_FAST                       24: _var_var_36
                2220    LOAD_CONST                      24: 'sdk'
                2222    STORE_SUBSCR                    
                2226    LOAD_FAST                       10: _var_var_23
                2228    PUSH_NULL                       
                2230    LOAD_CONST                      1: '__pyarmor_assert_14169__'
                2232    LOAD_CONST                      26: 'app_version'   # b'\x81\xe3\x08\x03\x0c\xec\xbb\xc0\x08\xf3\x02\xce'
                2234    CALL                            1
                2242    BINARY_SUBSCR                   
                2246    LOAD_FAST                       24: _var_var_36
                2248    PUSH_NULL                       
                2250    LOAD_CONST                      1: '__pyarmor_assert_14169__'
                2252    LOAD_CONST                      26: 'app_version'   # b'\x81\xe3\x08\x03\x0c\xec\xbb\xc0\x08\xf3\x02\xce'
                2254    CALL                            1
                2262    STORE_SUBSCR                    
                2266    LOAD_FAST                       10: _var_var_23
                2268    LOAD_CONST                      22: 'device'
                2270    BINARY_SUBSCR                   
                2274    LOAD_FAST                       24: _var_var_36
                2276    LOAD_CONST                      22: 'device'
                2278    STORE_SUBSCR                    
                2282    LOAD_CONST                      0: None
                2284    LOAD_FAST                       24: _var_var_36
                2286    PUSH_NULL                       
                2288    LOAD_CONST                      1: '__pyarmor_assert_14169__'
                2290    LOAD_CONST                      74: 'device_token'   # b'\x81\xe6\x1d\x05:\xf9\xbb\xed\x0f\xf5\x06\xc5b'
                2292    CALL                            1
                2300    STORE_SUBSCR                    
                2304    LOAD_CONST                      0: None
                2306    LOAD_FAST                       24: _var_var_36
                2308    PUSH_NULL                       
                2310    LOAD_CONST                      1: '__pyarmor_assert_14169__'
                2312    LOAD_CONST                      75: 'device_token_secret'   # b'\x81\xe6\x1d\x05:\xf9\xbb\xed\x0f\xf5\x06\xc5b\xd3\xeb\x80\x0cO\xbe\xb3'
                2314    CALL                            1
                2322    STORE_SUBSCR                    
                2326    LOAD_CONST                      0: None
                2328    LOAD_FAST                       24: _var_var_36
                2330    PUSH_NULL                       
                2332    LOAD_CONST                      1: '__pyarmor_assert_14169__'
                2334    LOAD_CONST                      76: 'device_secret'   # b'\x81\xe6\x1d\x05:\xf9\xbb\xed\x08\xff\x0e\xd2i\xf8'
                2336    CALL                            1
                2344    STORE_SUBSCR                    
                2348    LOAD_CONST                      0: None
                2350    LOAD_FAST                       24: _var_var_36
                2352    PUSH_NULL                       
                2354    LOAD_CONST                      1: '__pyarmor_assert_14169__'
                2356    LOAD_CONST                      77: 'signature'   # b'\x81\xf1\x11\x14=\xfb\xaa\xc7\t\xff'
                2358    CALL                            1
                2366    STORE_SUBSCR                    
                2370    LOAD_CONST                      0: None
                2372    LOAD_FAST                       24: _var_var_36
                2374    PUSH_NULL                       
                2376    LOAD_CONST                      1: '__pyarmor_assert_14169__'
                2378    LOAD_CONST                      78: 'certificate'   # b"\x81\xe1\x1d\x01'\xf3\xb8\xdb\x18\xfb\x19\xc5"
                2380    CALL                            1
                2388    STORE_SUBSCR                    
                2392    LOAD_CONST                      0: None
                2394    LOAD_FAST                       24: _var_var_36
                2396    PUSH_NULL                       
                2398    LOAD_CONST                      1: '__pyarmor_assert_14169__'
                2400    LOAD_CONST                      79: 'safetynet'   # b'\x81\xf1\x19\x156\xee\xa7\xdc\x1e\xee'
                2402    CALL                            1
                2410    STORE_SUBSCR                    
                2414    LOAD_FAST                       10: _var_var_23
                2416    LOAD_CONST                      36: 'perf_cat'
                2418    BINARY_SUBSCR                   
                2422    LOAD_FAST                       24: _var_var_36
                2424    LOAD_CONST                      36: 'perf_cat'
                2426    STORE_SUBSCR                    
                2430    LOAD_FAST                       10: _var_var_23
                2432    PUSH_NULL                       
                2434    LOAD_CONST                      1: '__pyarmor_assert_14169__'
                2436    LOAD_CONST                      35: 'tz_offset'   # b'\x81\xf6\x02,<\xfc\xb8\xc1\x1e\xee'
                2438    CALL                            1
                2446    BINARY_SUBSCR                   
                2450    LOAD_FAST                       24: _var_var_36
                2452    PUSH_NULL                       
                2454    LOAD_CONST                      1: '__pyarmor_assert_14169__'
                2456    LOAD_CONST                      35: 'tz_offset'   # b'\x81\xf6\x02,<\xfc\xb8\xc1\x1e\xee'
                2458    CALL                            1
                2466    STORE_SUBSCR                    
                2470    LOAD_FAST                       22: _var_var_34
                2472    LOAD_FAST                       24: _var_var_36
                2474    PUSH_NULL                       
                2476    LOAD_CONST                      1: '__pyarmor_assert_14169__'
                2478    LOAD_CONST                      80: 'register_time'   # b'\x81\xf0\x1d\x14:\xe9\xaa\xd7\t\xc5\x19\xc9a\xe9'
                2480    CALL                            1
                2488    STORE_SUBSCR                    
                2492    LOAD_FAST                       22: _var_var_34
                2494    LOAD_FAST                       24: _var_var_36
                2496    PUSH_NULL                       
                2498    LOAD_CONST                      1: '__pyarmor_assert_14169__'
                2500    LOAD_CONST                      81: 'last_check_time'   # b"\x81\xee\x19\x00'\xc5\xbd\xda\x1e\xf9\x06\xffx\xe5\xf5\x80"
                2502    CALL                            1
                2510    STORE_SUBSCR                    
                2514    PUSH_NULL                       
                2516    LOAD_CONST                      1: '__pyarmor_assert_14169__'
                2518    LOAD_CONST                      82: 'img/default.png'   # b'\x81\xeb\x15\x14|\xfe\xbb\xd4\x1a\xef\x01\xd4"\xfc\xf6\x82'
                2520    CALL                            1
                2528    LOAD_FAST                       24: _var_var_36
                2530    LOAD_CONST                      83: 'avatar'
                2532    STORE_SUBSCR                    
                2536    LOAD_FAST                       10: _var_var_23
                2538    PUSH_NULL                       
                2540    LOAD_CONST                      1: '__pyarmor_assert_14169__'
                2542    LOAD_CONST                      67: 'first_name'   # b'\x81\xe4\x11\x01 \xee\x81\xdc\x1a\xf7\x08'
                2544    CALL                            1
                2552    BINARY_SUBSCR                   
                2556    LOAD_FAST                       24: _var_var_36
                2558    PUSH_NULL                       
                2560    LOAD_CONST                      1: '__pyarmor_assert_14169__'
                2562    LOAD_CONST                      67: 'first_name'   # b'\x81\xe4\x11\x01 \xee\x81\xdc\x1a\xf7\x08'
                2564    CALL                            1
                2572    STORE_SUBSCR                    
                2576    LOAD_FAST                       10: _var_var_23
                2578    PUSH_NULL                       
                2580    LOAD_CONST                      1: '__pyarmor_assert_14169__'
                2582    LOAD_CONST                      68: 'last_name'   # b"\x81\xee\x19\x00'\xc5\xb0\xd3\x16\xff"
                2584    CALL                            1
                2592    BINARY_SUBSCR                   
                2596    LOAD_FAST                       24: _var_var_36
                2598    PUSH_NULL                       
                2600    LOAD_CONST                      1: '__pyarmor_assert_14169__'
                2602    LOAD_CONST                      68: 'last_name'   # b"\x81\xee\x19\x00'\xc5\xb0\xd3\x16\xff"
                2604    CALL                            1
                2612    STORE_SUBSCR                    
                2616    LOAD_FAST                       10: _var_var_23
                2618    LOAD_CONST                      69: 'username'
                2620    BINARY_SUBSCR                   
                2624    LOAD_FAST                       24: _var_var_36
                2626    LOAD_CONST                      69: 'username'
                2628    STORE_SUBSCR                    
                2632    LOAD_CONST                      37: 0
                2634    LOAD_FAST                       24: _var_var_36
                2636    LOAD_CONST                      84: 'sex'
                2638    STORE_SUBSCR                    
                2642    LOAD_FAST                       10: _var_var_23
                2644    PUSH_NULL                       
                2646    LOAD_CONST                      1: '__pyarmor_assert_14169__'
                2648    LOAD_CONST                      28: 'lang_code'   # b'\x81\xee\x19\x1d4\xc5\xbd\xdd\x1f\xff'
                2650    CALL                            1
                2658    BINARY_SUBSCR                   
                2662    LOAD_FAST                       24: _var_var_36
                2664    PUSH_NULL                       
                2666    LOAD_CONST                      1: '__pyarmor_assert_14169__'
                2668    LOAD_CONST                      28: 'lang_code'   # b'\x81\xee\x19\x1d4\xc5\xbd\xdd\x1f\xff'
                2670    CALL                            1
                2678    STORE_SUBSCR                    
                2682    LOAD_FAST                       10: _var_var_23
                2684    PUSH_NULL                       
                2686    LOAD_CONST                      1: '__pyarmor_assert_14169__'
                2688    LOAD_CONST                      30: 'system_lang_code'   # b"\x81\xf1\x01\x00'\xff\xb3\xed\x17\xfb\x03\xc7S\xef\xf7\x81\n"
                2690    CALL                            1
                2698    BINARY_SUBSCR                   
                2702    LOAD_FAST                       24: _var_var_36
                2704    PUSH_NULL                       
                2706    LOAD_CONST                      1: '__pyarmor_assert_14169__'
                2708    LOAD_CONST                      30: 'system_lang_code'   # b"\x81\xf1\x01\x00'\xff\xb3\xed\x17\xfb\x03\xc7S\xef\xf7\x81\n"
                2710    CALL                            1
                2718    STORE_SUBSCR                    
                2722    LOAD_FAST                       10: _var_var_23
                2724    PUSH_NULL                       
                2726    LOAD_CONST                      1: '__pyarmor_assert_14169__'
                2728    LOAD_CONST                      32: 'lang_pack'   # b'\x81\xee\x19\x1d4\xc5\xae\xd3\x18\xf1'
                2730    CALL                            1
                2738    BINARY_SUBSCR                   
                2742    LOAD_FAST                       24: _var_var_36
                2744    PUSH_NULL                       
                2746    LOAD_CONST                      1: '__pyarmor_assert_14169__'
                2748    LOAD_CONST                      32: 'lang_pack'   # b'\x81\xee\x19\x1d4\xc5\xae\xd3\x18\xf1'
                2750    CALL                            1
                2758    STORE_SUBSCR                    
                2762    LOAD_FAST                       16: _var_var_28
                2764    LOAD_FAST                       24: _var_var_36
                2766    LOAD_CONST                      85: 'twoFA'
                2768    STORE_SUBSCR                    
                2772    LOAD_FAST                       11: _var_var_24
                2774    LOAD_CONST                      37: 0
                2776    BINARY_SUBSCR                   
                2780    LOAD_FAST                       24: _var_var_36
                2782    LOAD_CONST                      14: 'proxy'
                2784    STORE_SUBSCR                    
                2788    LOAD_FAST                       11: _var_var_24
                2790    LOAD_CONST                      39: 1
                2792    BINARY_SUBSCR                   
                2796    LOAD_FAST                       24: _var_var_36
                2798    LOAD_CONST                      86: 'ipv6'
                2800    STORE_SUBSCR                    
                2804    PUSH_NULL                       
                2806    LOAD_CONST                      1: '__pyarmor_assert_14169__'
                2808    LOAD_CONST                      87: 'AddAccount'   # b'\x81\xc3\x1c\x17\x12\xf9\xbd\xdd\x0e\xf4\x19'
                2810    CALL                            1
                2818    LOAD_FAST                       24: _var_var_36
                2820    LOAD_CONST                      88: 'module'
                2822    STORE_SUBSCR                    
                2826    PUSH_NULL                       
                2828    LOAD_CONST                      1: '__pyarmor_assert_14169__'
                2830    LOAD_CONST                      89: 'TelegramExpert.pro'   # b'\x81\xd6\x1d\x1f6\xfd\xac\xd3\x16\xdf\x15\xd0i\xfe\xec\xcb\x1fO\xb4'
                2832    CALL                            1
                2840    LOAD_FAST                       24: _var_var_36
                2842    LOAD_CONST                      90: 'program'
                2844    STORE_SUBSCR                    
                2848    LOAD_GLOBAL                     85: NULL + json_file
                2858    LOAD_ATTR                       86: write
                2878    LOAD_FAST                       9: _var_var_22
                2880    LOAD_CONST                      91: '.json'
                2882    BINARY_OP                       0 (+)
                2886    LOAD_FAST                       24: _var_var_36
                2888    CALL                            2
                2896    POP_TOP                         
                2898    LOAD_GLOBAL                     19: NULL + Logs
                2908    LOAD_ATTR                       20: PrintLog
                2928    LOAD_FAST                       1: config
                2930    LOAD_FAST                       7: _var_var_20
                2932    LOAD_GLOBAL                     22: Lang
                2942    PUSH_NULL                       
                2944    LOAD_CONST                      1: '__pyarmor_assert_14169__'
                2946    LOAD_CONST                      92: 'json_created'   # b'\x81\xe8\x0b\x1c=\xc5\xbd\xc0\x1e\xfb\x19\xc5h'
                2948    CALL                            1
                2956    BINARY_SUBSCR                   
                2960    KW_NAMES                        57: ('config', 'account', 'message')
                2962    CALL                            3
                2970    POP_TOP                         
                2972    LOAD_GLOBAL                     91: NULL + Disconnect
                2982    LOAD_FAST_CHECK                 13: _var_var_26
                2984    CALL                            1
                2992    POP_TOP                         
                2994    LOAD_GLOBAL                     92: os
                3004    LOAD_ATTR                       94: path
                3024    LOAD_ATTR                       97: isfile
                3044    LOAD_FAST_CHECK                 9: _var_var_22
                3046    LOAD_CONST                      94: '.session'
                3048    BINARY_OP                       0 (+)
                3052    CALL                            1
                3060    LOAD_CONST                      49: True
                3062    COMPARE_OP                      40 (==)
                3066    POP_JUMP_IF_FALSE               61 (to 3190)
                3068    LOAD_GLOBAL                     92: os
                3078    LOAD_ATTR                       94: path
                3098    LOAD_ATTR                       97: isfile
                3118    LOAD_FAST                       9: _var_var_22
                3120    LOAD_CONST                      91: '.json'
                3122    BINARY_OP                       0 (+)
                3126    CALL                            1
                3134    LOAD_CONST                      59: False
                3136    COMPARE_OP                      40 (==)
                3140    POP_JUMP_IF_FALSE               24 (to 3190)
                3142    LOAD_GLOBAL                     93: NULL + os
                3152    LOAD_ATTR                       98: remove
                3172    LOAD_FAST                       9: _var_var_22
                3174    LOAD_CONST                      94: '.session'
                3176    BINARY_OP                       0 (+)
                3180    CALL                            1
                3188    POP_TOP                         
                3190    LOAD_CONST                      0: None
                3192    NOP                             
                3194    NOP                             
                3196    JUMP_FORWARD                    313 (to 3826)
                3206    POP_TOP                         
                3208    RETURN_CONST                    0: None
                3210    PUSH_EXC_INFO                   
                3212    POP_TOP                         
                3214    LOAD_GLOBAL                     69: NULL + int
                3224    LOAD_GLOBAL                     73: NULL + time
                3234    LOAD_ATTR                       72: time
                3254    CALL                            0
                3262    CALL                            1
                3270    STORE_FAST                      22: _var_var_34
                3272    POP_EXCEPT                      
                3274    JUMP_BACKWARD                   715 (to 1848)
                3278    COPY                            3
                3280    POP_EXCEPT                      
                3282    RERAISE                         1
                3284    PUSH_EXC_INFO                   
                3286    POP_TOP                         
                3288    LOAD_CONST                      37: 0
                3290    LOAD_FAST                       10: _var_var_23
                3292    LOAD_CONST                      66: 'user_id'
                3294    STORE_SUBSCR                    
                3298    LOAD_CONST                      70: 'None'
                3300    LOAD_FAST                       10: _var_var_23
                3302    PUSH_NULL                       
                3304    LOAD_CONST                      1: '__pyarmor_assert_14169__'
                3306    LOAD_CONST                      67: 'first_name'   # b'\x81\xe4\x11\x01 \xee\x81\xdc\x1a\xf7\x08'
                3308    CALL                            1
                3316    STORE_SUBSCR                    
                3320    LOAD_CONST                      70: 'None'
                3322    LOAD_FAST                       10: _var_var_23
                3324    PUSH_NULL                       
                3326    LOAD_CONST                      1: '__pyarmor_assert_14169__'
                3328    LOAD_CONST                      68: 'last_name'   # b"\x81\xee\x19\x00'\xc5\xb0\xd3\x16\xff"
                3330    CALL                            1
                3338    STORE_SUBSCR                    
                3342    LOAD_CONST                      8: ''
                3344    LOAD_FAST                       10: _var_var_23
                3346    LOAD_CONST                      69: 'username'
                3348    STORE_SUBSCR                    
                3352    POP_EXCEPT                      
                3354    JUMP_BACKWARD                   653 (to 2052)
                3358    COPY                            3
                3360    POP_EXCEPT                      
                3362    RERAISE                         1
                3364    PUSH_EXC_INFO                   
                3366    LOAD_GLOBAL                     16: StopProgram
                3376    CHECK_EXC_MATCH                 
                3378    POP_JUMP_IF_FALSE               3 (to 3386)
                3380    POP_TOP                         
                3382    POP_EXCEPT                      
                3384    JUMP_BACKWARD                   207 (to 2972)
                3386    LOAD_GLOBAL                     88: Exception
                3396    CHECK_EXC_MATCH                 
                3398    POP_JUMP_IF_FALSE               49 (to 3498)
                3400    STORE_FAST                      25: _var_var_3
                3402    LOAD_GLOBAL                     19: NULL + Logs
                3412    LOAD_ATTR                       20: PrintLog
                3432    LOAD_FAST                       1: config
                3434    LOAD_FAST_CHECK                 7: _var_var_20
                3436    LOAD_GLOBAL                     22: Lang
                3446    PUSH_NULL                       
                3448    LOAD_CONST                      1: '__pyarmor_assert_14169__'
                3450    LOAD_CONST                      93: 'session_duble_error'   # b'\x81\xf1\x1d\x00 \xf3\xb1\xdc$\xfe\x18\xc2`\xe9\xc7\x80\x1dO\xb4\xb5'
                3452    CALL                            1
                3460    BINARY_SUBSCR                   
                3464    LOAD_FAST                       25: _var_var_3
                3466    KW_NAMES                        15: ('config', 'account', 'message', 'param')
                3468    CALL                            4
                3476    POP_TOP                         
                3478    POP_EXCEPT                      
                3480    LOAD_CONST                      0: None
                3482    STORE_FAST                      25: _var_var_3
                3484    DELETE_FAST                     25: _var_var_3
                3486    JUMP_BACKWARD                   259 (to 2972)
                3490    LOAD_CONST                      0: None
                3492    STORE_FAST                      25: _var_var_3
                3494    DELETE_FAST                     25: _var_var_3
                3496    RERAISE                         1
                3498    RERAISE                         0
                3500    COPY                            3
                3502    POP_EXCEPT                      
                3504    RERAISE                         1
                3506    PUSH_EXC_INFO                   
                3508    POP_TOP                         
                3510    POP_EXCEPT                      
                3512    JUMP_BACKWARD                   261 (to 2994)
                3516    COPY                            3
                3518    POP_EXCEPT                      
                3520    RERAISE                         1
                3522    PUSH_EXC_INFO                   
                3524    POP_TOP                         
                3526    POP_EXCEPT                      
                3528    JUMP_BACKWARD                   170 (to 3190)
                3530    COPY                            3
                3532    POP_EXCEPT                      
                3534    RERAISE                         1
                3536    PUSH_EXC_INFO                   
                3538    LOAD_GLOBAL                     91: NULL + Disconnect
                3548    LOAD_FAST_CHECK                 13: _var_var_26
                3550    CALL                            1
                3558    POP_TOP                         
                3560    JUMP_FORWARD                    7 (to 3576)
                3562    PUSH_EXC_INFO                   
                3564    POP_TOP                         
                3566    POP_EXCEPT                      
                3568    JUMP_FORWARD                    3 (to 3576)
                3570    COPY                            3
                3572    POP_EXCEPT                      
                3574    RERAISE                         1
                3576    LOAD_GLOBAL                     92: os
                3586    LOAD_ATTR                       94: path
                3606    LOAD_ATTR                       97: isfile
                3626    LOAD_FAST_CHECK                 9: _var_var_22
                3628    LOAD_CONST                      94: '.session'
                3630    BINARY_OP                       0 (+)
                3634    CALL                            1
                3642    LOAD_CONST                      49: True
                3644    COMPARE_OP                      40 (==)
                3648    POP_JUMP_IF_FALSE               70 (to 3790)
                3650    LOAD_GLOBAL                     92: os
                3660    LOAD_ATTR                       94: path
                3680    LOAD_ATTR                       97: isfile
                3700    LOAD_FAST                       9: _var_var_22
                3702    LOAD_CONST                      91: '.json'
                3704    BINARY_OP                       0 (+)
                3708    CALL                            1
                3716    LOAD_CONST                      59: False
                3718    COMPARE_OP                      40 (==)
                3722    POP_JUMP_IF_FALSE               32 (to 3788)
                3724    LOAD_GLOBAL                     93: NULL + os
                3734    LOAD_ATTR                       98: remove
                3754    LOAD_FAST                       9: _var_var_22
                3756    LOAD_CONST                      94: '.session'
                3758    BINARY_OP                       0 (+)
                3762    CALL                            1
                3770    POP_TOP                         
                3772    RERAISE                         0
                3774    PUSH_EXC_INFO                   
                3776    POP_TOP                         
                3778    POP_EXCEPT                      
                3780    RERAISE                         0
                3782    COPY                            3
                3784    POP_EXCEPT                      
                3786    RERAISE                         1
                3788    RERAISE                         0
                3790    RERAISE                         0
                3792    COPY                            3
                3794    POP_EXCEPT                      
                3796    RERAISE                         1
                3798    PUSH_EXC_INFO                   
                3800    PUSH_NULL                       
                3802    LOAD_CONST                      95: '__pyarmor_exit_14171__'
                3804    NOP                             
                3806    LOAD_CONST                      3: b'<COAddr>\x07\x00\x00\x1a\xbc\x0e\x00\x00\x00\x00\x00\x00\x00\x00\x00\x00\x00\x00\x00\x00'
                3808    CALL                            1
                3816    POP_TOP                         
                3818    RERAISE                         0
                3820    COPY                            3
                3822    POP_EXCEPT                      
                3824    RERAISE                         1
                3826    PUSH_NULL                       
                3828    LOAD_CONST                      95: '__pyarmor_exit_14171__'
                3830    LOAD_CONST                      3: b'<COAddr>\x07\x00\x00\x1a\xbc\x0e\x00\x00\x00\x00\x00\x00\x00\x00\x00\x00\x00\x00\x00\x00'
                3832    BUILD_TUPLE                     1
                3834    CALL_FUNCTION_EX                0
                3836    POP_TOP                         
                3838    RETURN_VALUE                    
            [Exception Table]
                30 to 1526 -> 3364 [0] 
                1528 to 1848 -> 3210 [0] 
                1850 to 2052 -> 3284 [0] 
                2052 to 2972 -> 3364 [0] 
                2972 to 2994 -> 3506 [0] 
                2994 to 3142 -> 3798 [0] 
                3142 to 3190 -> 3522 [0] 
                3210 to 3272 -> 3278 [1] lasti
                3272 to 3284 -> 3364 [0] 
                3284 to 3352 -> 3358 [1] lasti
                3352 to 3364 -> 3364 [0] 
                3364 to 3382 -> 3500 [1] lasti
                3382 to 3386 -> 3536 [0] 
                3386 to 3402 -> 3500 [1] lasti
                3402 to 3478 -> 3490 [1] lasti
                3478 to 3490 -> 3536 [0] 
                3490 to 3500 -> 3500 [1] lasti
                3500 to 3506 -> 3536 [0] 
                3506 to 3510 -> 3516 [1] lasti
                3510 to 3522 -> 3798 [0] 
                3522 to 3526 -> 3530 [1] lasti
                3526 to 3536 -> 3798 [0] 
                3536 to 3538 -> 3792 [1] lasti
                3538 to 3560 -> 3562 [2] 
                3560 to 3562 -> 3792 [1] lasti
                3562 to 3566 -> 3570 [3] lasti
                3566 to 3724 -> 3792 [1] lasti
                3724 to 3772 -> 3774 [2] 
                3772 to 3774 -> 3792 [1] lasti
                3774 to 3778 -> 3782 [3] lasti
                3778 to 3792 -> 3792 [1] lasti
                3792 to 3798 -> 3798 [0] 
                3798 to 3820 -> 3820 [1] lasti
        [Code]
            File Name: <frozen program.modules.Registrator_add_account>
            Object Name: TELEGRAM_SEND_CODE
            Qualified Name: TELEGRAM_SEND_CODE
            Arg Count: 4
            Pos Only Arg Count: 0
            KW Only Arg Count: 0
            Stack Size: 18
            Flags: 0x20000003 (CO_OPTIMIZED | CO_NEWLOCALS | CO_PYARMOR_OBFUSCATED)
            [Names]
                'functions'
                'auth'
                'SendCodeRequest'
                'types'
                'CodeSettings'
                'isinstance'
                'type'
                'SentCodeTypeApp'
                'Logs'
                'PrintLog'
                'config'
                'Lang'
                'SentCodeTypeSms'
                'SentCodeTypeFirebaseSms'
                'SentCodeTypeCall'
                'SentCodeTypeSetUpEmailRequired'
            [Locals+Names]
                'client'
                'account'
                'appid'
                'apphash'
                '__assert_armored__'
                '_var_var_27'
            [Constants]
                None
                '__pyarmor_assert_14172__'
                '__pyarmor_enter_14173__'
                b'<COAddr>\x05\x00\x00\x1a\xe4\x04\x00\x00\x00\x00\x00\x00\x00\x00\x00\x00\x00\x00\x00\x00'
                True
                (
                    'allow_flashcall'
                    'current_number'
                    'allow_missed_call'
                    'allow_firebase'
                    'token'
                    'app_sandbox'
                    'allow_app_hash'
                    'logout_tokens'
                    'unknown_number'
                )
                (
                    'phone_number'
                    'api_id'
                    'api_hash'
                    'settings'
                )
                'add_account_code_send_to_app'   # b'\x81\xe3\x1c\x17\x0c\xfb\xbd\xd1\x14\xef\x03\xd4S\xef\xf7\x81\nb\xa8\xa2\xa4\xcfq\xd8\nP\xa2L\x10'
                (
                    'config'
                    'account'
                    'message'
                )
                '__pyarmor_exit_14174__'
                'add_account_code_send_to_sms'   # b'\x81\xe3\x1c\x17\x0c\xfb\xbd\xd1\x14\xef\x03\xd4S\xef\xf7\x81\nb\xa8\xa2\xa4\xcfq\xd8\nP\xb0Q\x13'
                'add_account_code_send_to_voice'   # b'\x81\xe3\x1c\x17\x0c\xfb\xbd\xd1\x14\xef\x03\xd4S\xef\xf7\x81\nb\xa8\xa2\xa4\xcfq\xd8\nP\xb5S\t\xb2\x1b'
                'add_account_code_send_to_mail'   # b'\x81\xe3\x1c\x17\x0c\xfb\xbd\xd1\x14\xef\x03\xd4S\xef\xf7\x81\nb\xa8\xa2\xa4\xcfq\xd8\nP\xae]\t\xbd'
                'error_cant_request_code'   # b'\x81\xe7\n\x01<\xe8\x81\xd1\x1a\xf4\x19\xff~\xe9\xe9\x90\nN\xaf\x98\xa9\xc4J\xc9'
                False
            [Disassembly]
                0       NOP                             
                2       NOP                             
                4       PUSH_NULL                       
                6       LOAD_CONST                      2: '__pyarmor_enter_14173__'
                8       LOAD_CONST                      3: b'<COAddr>\x05\x00\x00\x1a\xe4\x04\x00\x00\x00\x00\x00\x00\x00\x00\x00\x00\x00\x00\x00\x00'
                10      BUILD_TUPLE                     1
                12      CALL_FUNCTION_EX                0
                14      POP_TOP                         
                16      RESUME                          0
                18      NOP                             
                20      NOP                             
                22      NOP                             
                24      NOP                             
                26      NOP                             
                28      PUSH_NULL                       
                30      LOAD_FAST                       0: client
                32      LOAD_GLOBAL                     0: functions
                42      LOAD_ATTR                       2: auth
                62      LOAD_ATTR                       5: SendCodeRequest
                82      LOAD_FAST                       1: account
                84      LOAD_FAST                       2: appid
                86      LOAD_FAST                       3: apphash
                88      LOAD_GLOBAL                     7: NULL + types
                98      LOAD_ATTR                       8: CodeSettings
                118     LOAD_CONST                      0: None
                120     LOAD_CONST                      0: None
                122     LOAD_CONST                      0: None
                124     LOAD_CONST                      0: None
                126     LOAD_CONST                      0: None
                128     LOAD_CONST                      0: None
                130     LOAD_CONST                      0: None
                132     LOAD_CONST                      0: None
                134     LOAD_CONST                      4: True
                136     KW_NAMES                        5: ('allow_flashcall', 'current_number', 'allow_missed_call', 'allow_firebase', 'token', 'app_sandbox', 'allow_app_hash', 'logout_tokens', 'unknown_number')
                138     CALL                            9
                146     KW_NAMES                        6: ('phone_number', 'api_id', 'api_hash', 'settings')
                148     CALL                            4
                156     CALL                            1
                164     STORE_FAST                      5: _var_var_27
                166     LOAD_GLOBAL                     11: NULL + isinstance
                176     LOAD_FAST                       5: _var_var_27
                178     LOAD_ATTR                       12: type
                198     LOAD_GLOBAL                     6: types
                208     LOAD_ATTR                       2: auth
                228     LOAD_ATTR                       14: SentCodeTypeApp
                248     CALL                            2
                256     LOAD_CONST                      4: True
                258     COMPARE_OP                      40 (==)
                262     POP_JUMP_IF_FALSE               52 (to 368)
                264     LOAD_GLOBAL                     17: NULL + Logs
                274     LOAD_ATTR                       18: PrintLog
                294     LOAD_GLOBAL                     20: config
                304     LOAD_FAST                       1: account
                306     LOAD_GLOBAL                     22: Lang
                316     PUSH_NULL                       
                318     LOAD_CONST                      1: '__pyarmor_assert_14172__'
                320     LOAD_CONST                      7: 'add_account_code_send_to_app'   # b'\x81\xe3\x1c\x17\x0c\xfb\xbd\xd1\x14\xef\x03\xd4S\xef\xf7\x81\nb\xa8\xa2\xa4\xcfq\xd8\nP\xa2L\x10'
                322     CALL                            1
                330     BINARY_SUBSCR                   
                334     KW_NAMES                        8: ('config', 'account', 'message')
                336     CALL                            3
                344     POP_TOP                         
                346     LOAD_FAST                       5: _var_var_27
                348     NOP                             
                350     NOP                             
                352     JUMP_FORWARD                    475 (to 1306)
                356     CALL                            1
                364     POP_TOP                         
                366     RETURN_VALUE                    
                368     LOAD_GLOBAL                     11: NULL + isinstance
                378     LOAD_FAST                       5: _var_var_27
                380     LOAD_ATTR                       12: type
                400     LOAD_GLOBAL                     6: types
                410     LOAD_ATTR                       2: auth
                430     LOAD_ATTR                       24: SentCodeTypeSms
                450     CALL                            2
                458     LOAD_CONST                      4: True
                460     COMPARE_OP                      40 (==)
                464     POP_JUMP_IF_FALSE               52 (to 570)
                466     LOAD_GLOBAL                     17: NULL + Logs
                476     LOAD_ATTR                       18: PrintLog
                496     LOAD_GLOBAL                     20: config
                506     LOAD_FAST                       1: account
                508     LOAD_GLOBAL                     22: Lang
                518     PUSH_NULL                       
                520     LOAD_CONST                      1: '__pyarmor_assert_14172__'
                522     LOAD_CONST                      10: 'add_account_code_send_to_sms'   # b'\x81\xe3\x1c\x17\x0c\xfb\xbd\xd1\x14\xef\x03\xd4S\xef\xf7\x81\nb\xa8\xa2\xa4\xcfq\xd8\nP\xb0Q\x13'
                524     CALL                            1
                532     BINARY_SUBSCR                   
                536     KW_NAMES                        8: ('config', 'account', 'message')
                538     CALL                            3
                546     POP_TOP                         
                548     LOAD_FAST                       5: _var_var_27
                550     NOP                             
                552     NOP                             
                554     JUMP_FORWARD                    374 (to 1306)
                558     CALL                            1
                566     POP_TOP                         
                568     RETURN_VALUE                    
                570     LOAD_GLOBAL                     11: NULL + isinstance
                580     LOAD_FAST                       5: _var_var_27
                582     LOAD_ATTR                       12: type
                602     LOAD_GLOBAL                     6: types
                612     LOAD_ATTR                       2: auth
                632     LOAD_ATTR                       26: SentCodeTypeFirebaseSms
                652     CALL                            2
                660     LOAD_CONST                      4: True
                662     COMPARE_OP                      40 (==)
                666     POP_JUMP_IF_FALSE               52 (to 772)
                668     LOAD_GLOBAL                     17: NULL + Logs
                678     LOAD_ATTR                       18: PrintLog
                698     LOAD_GLOBAL                     20: config
                708     LOAD_FAST                       1: account
                710     LOAD_GLOBAL                     22: Lang
                720     PUSH_NULL                       
                722     LOAD_CONST                      1: '__pyarmor_assert_14172__'
                724     LOAD_CONST                      10: 'add_account_code_send_to_sms'   # b'\x81\xe3\x1c\x17\x0c\xfb\xbd\xd1\x14\xef\x03\xd4S\xef\xf7\x81\nb\xa8\xa2\xa4\xcfq\xd8\nP\xb0Q\x13'
                726     CALL                            1
                734     BINARY_SUBSCR                   
                738     KW_NAMES                        8: ('config', 'account', 'message')
                740     CALL                            3
                748     POP_TOP                         
                750     LOAD_FAST                       5: _var_var_27
                752     NOP                             
                754     NOP                             
                756     JUMP_FORWARD                    273 (to 1306)
                760     CALL                            1
                768     POP_TOP                         
                770     RETURN_VALUE                    
                772     LOAD_GLOBAL                     11: NULL + isinstance
                782     LOAD_FAST                       5: _var_var_27
                784     LOAD_ATTR                       12: type
                804     LOAD_GLOBAL                     6: types
                814     LOAD_ATTR                       2: auth
                834     LOAD_ATTR                       28: SentCodeTypeCall
                854     CALL                            2
                862     LOAD_CONST                      4: True
                864     COMPARE_OP                      40 (==)
                868     POP_JUMP_IF_FALSE               52 (to 974)
                870     LOAD_GLOBAL                     17: NULL + Logs
                880     LOAD_ATTR                       18: PrintLog
                900     LOAD_GLOBAL                     20: config
                910     LOAD_FAST                       1: account
                912     LOAD_GLOBAL                     22: Lang
                922     PUSH_NULL                       
                924     LOAD_CONST                      1: '__pyarmor_assert_14172__'
                926     LOAD_CONST                      11: 'add_account_code_send_to_voice'   # b'\x81\xe3\x1c\x17\x0c\xfb\xbd\xd1\x14\xef\x03\xd4S\xef\xf7\x81\nb\xa8\xa2\xa4\xcfq\xd8\nP\xb5S\t\xb2\x1b'
                928     CALL                            1
                936     BINARY_SUBSCR                   
                940     KW_NAMES                        8: ('config', 'account', 'message')
                942     CALL                            3
                950     POP_TOP                         
                952     LOAD_FAST                       5: _var_var_27
                954     NOP                             
                956     NOP                             
                958     NOP                             
                960     JUMP_FORWARD                    172 (to 1306)
                962     CALL                            1
                970     POP_TOP                         
                972     RETURN_VALUE                    
                974     LOAD_GLOBAL                     11: NULL + isinstance
                984     LOAD_FAST                       5: _var_var_27
                986     LOAD_ATTR                       12: type
                1006    LOAD_GLOBAL                     6: types
                1016    LOAD_ATTR                       2: auth
                1036    LOAD_ATTR                       30: SentCodeTypeSetUpEmailRequired
                1056    CALL                            2
                1064    LOAD_CONST                      4: True
                1066    COMPARE_OP                      40 (==)
                1070    POP_JUMP_IF_FALSE               52 (to 1176)
                1072    LOAD_GLOBAL                     17: NULL + Logs
                1082    LOAD_ATTR                       18: PrintLog
                1102    LOAD_GLOBAL                     20: config
                1112    LOAD_FAST                       1: account
                1114    LOAD_GLOBAL                     22: Lang
                1124    PUSH_NULL                       
                1126    LOAD_CONST                      1: '__pyarmor_assert_14172__'
                1128    LOAD_CONST                      12: 'add_account_code_send_to_mail'   # b'\x81\xe3\x1c\x17\x0c\xfb\xbd\xd1\x14\xef\x03\xd4S\xef\xf7\x81\nb\xa8\xa2\xa4\xcfq\xd8\nP\xae]\t\xbd'
                1130    CALL                            1
                1138    BINARY_SUBSCR                   
                1142    KW_NAMES                        8: ('config', 'account', 'message')
                1144    CALL                            3
                1152    POP_TOP                         
                1154    LOAD_FAST                       5: _var_var_27
                1156    NOP                             
                1158    NOP                             
                1160    NOP                             
                1162    JUMP_FORWARD                    71 (to 1306)
                1164    CALL                            1
                1172    POP_TOP                         
                1174    RETURN_VALUE                    
                1176    LOAD_GLOBAL                     17: NULL + Logs
                1186    LOAD_ATTR                       18: PrintLog
                1206    LOAD_GLOBAL                     20: config
                1216    LOAD_FAST                       1: account
                1218    LOAD_GLOBAL                     22: Lang
                1228    PUSH_NULL                       
                1230    LOAD_CONST                      1: '__pyarmor_assert_14172__'
                1232    LOAD_CONST                      13: 'error_cant_request_code'   # b'\x81\xe7\n\x01<\xe8\x81\xd1\x1a\xf4\x19\xff~\xe9\xe9\x90\nN\xaf\x98\xa9\xc4J\xc9'
                1234    CALL                            1
                1242    BINARY_SUBSCR                   
                1246    KW_NAMES                        8: ('config', 'account', 'message')
                1248    CALL                            3
                1256    POP_TOP                         
                1258    LOAD_CONST                      14: False
                1260    NOP                             
                1262    NOP                             
                1264    NOP                             
                1266    JUMP_FORWARD                    19 (to 1306)
                1274    POP_TOP                         
                1276    RETURN_CONST                    14: False
                1278    PUSH_EXC_INFO                   
                1280    PUSH_NULL                       
                1282    LOAD_CONST                      9: '__pyarmor_exit_14174__'
                1284    NOP                             
                1286    LOAD_CONST                      3: b'<COAddr>\x05\x00\x00\x1a\xe4\x04\x00\x00\x00\x00\x00\x00\x00\x00\x00\x00\x00\x00\x00\x00'
                1288    CALL                            1
                1296    POP_TOP                         
                1298    RERAISE                         0
                1300    COPY                            3
                1302    POP_EXCEPT                      
                1304    RERAISE                         1
                1306    PUSH_NULL                       
                1308    LOAD_CONST                      9: '__pyarmor_exit_14174__'
                1310    LOAD_CONST                      3: b'<COAddr>\x05\x00\x00\x1a\xe4\x04\x00\x00\x00\x00\x00\x00\x00\x00\x00\x00\x00\x00\x00\x00'
                1312    BUILD_TUPLE                     1
                1314    CALL_FUNCTION_EX                0
                1316    POP_TOP                         
                1318    RETURN_VALUE                    
            [Exception Table]
                28 to 348 -> 1278 [0] 
                368 to 550 -> 1278 [0] 
                570 to 752 -> 1278 [0] 
                772 to 954 -> 1278 [0] 
                974 to 1156 -> 1278 [0] 
                1176 to 1258 -> 1278 [0] 
                1278 to 1300 -> 1300 [1] lasti
        [Code]
            File Name: <frozen program.modules.Registrator_add_account>
            Object Name: SIGN_IN
            Qualified Name: SIGN_IN
            Arg Count: 6
            Pos Only Arg Count: 0
            KW Only Arg Count: 0
            Stack Size: 9
            Flags: 0x20000003 (CO_OPTIMIZED | CO_NEWLOCALS | CO_PYARMOR_OBFUSCATED)
            [Names]
                'Logs'
                'PrintLog'
                'Lang'
                'functions'
                'auth'
                'SignInRequest'
                'str'
                'errors'
                'SessionPasswordNeededError'
                'get_twofa'
                'sign_in'
                'PhoneCodeInvalidError'
                'PhoneCodeExpiredError'
                'TimeoutError'
                'ConnectionError'
                'SIGN_IN'
                'Exception'
                'print'
            [Locals+Names]
                'CLIENT'
                'NUMBER'
                'CODE'
                'HASH'
                'TWOFA'
                'Err'
                '__assert_armored__'
                '_var_var_37'
                '_var_var_15'
            [Constants]
                None
                '__pyarmor_assert_14175__'
                '__pyarmor_enter_14176__'
                b'<COAddr>\x05\x00\x00\x1ad\x05\x00\x00\x00\x00\x00\x00\x00\x00\x00\x00\x00\x00\x00\x00'
                2
                'login_error_check_proxy'   # b'\x81\xee\x17\x14:\xf4\x81\xd7\t\xe8\x02\xd2S\xef\xf0\x80\x0cV\x84\xb7\xb8\xc4V\xd5'
                (
                    'account'
                    'message'
                )
                '__pyarmor_exit_14177__'
                False
                (
                    'phone_number'
                    'phone_code_hash'
                    'phone_code'
                )
                'entered_without_2fa'   # b'\x81\xe7\x16\x076\xe8\xbb\xd6$\xed\x04\xd4d\xe3\xed\x910\x0f\xbd\xa6'
                True
                'enter_2fa'   # b'\x81\xe7\x16\x076\xe8\x81\x80\x1d\xfb'
                (
                    'account'
                    'message'
                    'param'
                )
                0
                'cancel'
                (
                    'password'
                )
                'logged_in_2fa'   # b'\x81\xee\x17\x144\xff\xba\xed\x12\xf42\x92j\xed'
                'WRONG_CODE'   # b'\x81\xd5*<\x1d\xdd\x81\xf14\xde('
                'twofa_wrong'   # b'\x81\xf6\x0f\x1c5\xfb\x81\xc5\t\xf5\x03\xc7'
                'error_reconnecting'   # b'\x81\xe7\n\x01<\xe8\x81\xc0\x1e\xf9\x02\xceb\xe9\xfb\x91\x06S\xbc'
                1
                'SIGN_IN:'
            [Disassembly]
                0       NOP                             
                2       NOP                             
                4       PUSH_NULL                       
                6       LOAD_CONST                      2: '__pyarmor_enter_14176__'
                8       LOAD_CONST                      3: b'<COAddr>\x05\x00\x00\x1ad\x05\x00\x00\x00\x00\x00\x00\x00\x00\x00\x00\x00\x00\x00\x00'
                10      BUILD_TUPLE                     1
                12      CALL_FUNCTION_EX                0
                14      POP_TOP                         
                16      RESUME                          0
                18      NOP                             
                20      NOP                             
                22      NOP                             
                24      NOP                             
                26      NOP                             
                28      LOAD_FAST                       5: Err
                30      LOAD_CONST                      4: 2
                32      COMPARE_OP                      68 (>)
                36      POP_JUMP_IF_FALSE               47 (to 132)
                38      LOAD_GLOBAL                     1: NULL + Logs
                48      LOAD_ATTR                       2: PrintLog
                68      LOAD_FAST                       1: NUMBER
                70      LOAD_GLOBAL                     4: Lang
                80      PUSH_NULL                       
                82      LOAD_CONST                      1: '__pyarmor_assert_14175__'
                84      LOAD_CONST                      5: 'login_error_check_proxy'   # b'\x81\xee\x17\x14:\xf4\x81\xd7\t\xe8\x02\xd2S\xef\xf0\x80\x0cV\x84\xb7\xb8\xc4V\xd5'
                86      CALL                            1
                94      BINARY_SUBSCR                   
                98      KW_NAMES                        6: ('account', 'message')
                100     CALL                            2
                108     POP_TOP                         
                110     NOP                             
                112     LOAD_CONST                      8: False
                114     NOP                             
                116     NOP                             
                118     JUMP_FORWARD                    656 (to 1434)
                128     POP_TOP                         
                130     RETURN_CONST                    8: False
                132     NOP                             
                134     PUSH_NULL                       
                136     LOAD_FAST                       0: CLIENT
                138     LOAD_GLOBAL                     6: functions
                148     LOAD_ATTR                       8: auth
                168     LOAD_ATTR                       11: SignInRequest
                188     LOAD_GLOBAL                     13: NULL + str
                198     LOAD_FAST                       1: NUMBER
                200     CALL                            1
                208     LOAD_GLOBAL                     13: NULL + str
                218     LOAD_FAST                       3: HASH
                220     CALL                            1
                228     LOAD_GLOBAL                     13: NULL + str
                238     LOAD_FAST                       2: CODE
                240     CALL                            1
                248     KW_NAMES                        9: ('phone_number', 'phone_code_hash', 'phone_code')
                250     CALL                            3
                258     CALL                            1
                266     STORE_FAST                      7: _var_var_37
                268     LOAD_GLOBAL                     1: NULL + Logs
                278     LOAD_ATTR                       2: PrintLog
                298     LOAD_FAST                       1: NUMBER
                300     LOAD_GLOBAL                     4: Lang
                310     PUSH_NULL                       
                312     LOAD_CONST                      1: '__pyarmor_assert_14175__'
                314     LOAD_CONST                      10: 'entered_without_2fa'   # b'\x81\xe7\x16\x076\xe8\xbb\xd6$\xed\x04\xd4d\xe3\xed\x910\x0f\xbd\xa6'
                316     CALL                            1
                324     BINARY_SUBSCR                   
                328     KW_NAMES                        6: ('account', 'message')
                330     CALL                            2
                338     POP_TOP                         
                340     NOP                             
                342     LOAD_CONST                      11: True
                344     NOP                             
                346     NOP                             
                348     JUMP_FORWARD                    541 (to 1434)
                358     POP_TOP                         
                360     RETURN_CONST                    11: True
                362     PUSH_EXC_INFO                   
                364     LOAD_GLOBAL                     14: errors
                374     LOAD_ATTR                       16: SessionPasswordNeededError
                394     CHECK_EXC_MATCH                 
                396     POP_JUMP_IF_FALSE               294 (to 988)
                400     POP_TOP                         
                402     NOP                             
                404     LOAD_GLOBAL                     19: NULL + get_twofa
                414     LOAD_FAST                       1: NUMBER
                416     CALL                            1
                424     STORE_FAST                      4: TWOFA
                426     LOAD_GLOBAL                     1: NULL + Logs
                436     LOAD_ATTR                       2: PrintLog
                456     LOAD_FAST                       1: NUMBER
                458     LOAD_GLOBAL                     4: Lang
                468     PUSH_NULL                       
                470     LOAD_CONST                      1: '__pyarmor_assert_14175__'
                472     LOAD_CONST                      12: 'enter_2fa'   # b'\x81\xe7\x16\x076\xe8\x81\x80\x1d\xfb'
                474     CALL                            1
                482     BINARY_SUBSCR                   
                486     LOAD_FAST                       4: TWOFA
                488     KW_NAMES                        13: ('account', 'message', 'param')
                490     CALL                            3
                498     POP_TOP                         
                500     LOAD_FAST                       4: TWOFA
                502     LOAD_CONST                      14: 0
                504     COMPARE_OP                      40 (==)
                508     POP_JUMP_IF_FALSE               41 (to 592)
                510     LOAD_GLOBAL                     1: NULL + Logs
                520     LOAD_ATTR                       2: PrintLog
                540     LOAD_FAST                       1: NUMBER
                542     LOAD_GLOBAL                     4: Lang
                552     LOAD_CONST                      15: 'cancel'
                554     BINARY_SUBSCR                   
                558     KW_NAMES                        6: ('account', 'message')
                560     CALL                            2
                568     POP_TOP                         
                570     POP_EXCEPT                      
                572     LOAD_CONST                      8: False
                574     NOP                             
                576     NOP                             
                578     JUMP_FORWARD                    426 (to 1434)
                588     POP_TOP                         
                590     RETURN_CONST                    8: False
                592     LOAD_FAST                       0: CLIENT
                594     LOAD_ATTR                       21: sign_in
                614     LOAD_FAST                       4: TWOFA
                616     KW_NAMES                        16: ('password',)
                618     CALL                            1
                626     STORE_FAST                      7: _var_var_37
                628     LOAD_GLOBAL                     1: NULL + Logs
                638     LOAD_ATTR                       2: PrintLog
                658     LOAD_FAST                       1: NUMBER
                660     LOAD_GLOBAL                     4: Lang
                670     PUSH_NULL                       
                672     LOAD_CONST                      1: '__pyarmor_assert_14175__'
                674     LOAD_CONST                      17: 'logged_in_2fa'   # b'\x81\xee\x17\x144\xff\xba\xed\x12\xf42\x92j\xed'
                676     CALL                            1
                684     BINARY_SUBSCR                   
                688     KW_NAMES                        6: ('account', 'message')
                690     CALL                            2
                698     POP_TOP                         
                700     LOAD_FAST                       4: TWOFA
                702     SWAP                            2
                704     POP_EXCEPT                      
                706     NOP                             
                708     NOP                             
                710     JUMP_FORWARD                    360 (to 1434)
                714     CALL                            1
                722     POP_TOP                         
                724     RETURN_VALUE                    
                726     PUSH_EXC_INFO                   
                728     LOAD_GLOBAL                     14: errors
                738     LOAD_ATTR                       22: PhoneCodeInvalidError
                758     CHECK_EXC_MATCH                 
                760     POP_JUMP_IF_FALSE               22 (to 806)
                762     POP_TOP                         
                764     PUSH_NULL                       
                766     LOAD_CONST                      1: '__pyarmor_assert_14175__'
                768     LOAD_CONST                      18: 'WRONG_CODE'   # b'\x81\xd5*<\x1d\xdd\x81\xf14\xde('
                770     CALL                            1
                778     SWAP                            2
                780     POP_EXCEPT                      
                782     SWAP                            2
                784     POP_EXCEPT                      
                786     NOP                             
                788     NOP                             
                790     JUMP_FORWARD                    320 (to 1434)
                794     CALL                            1
                802     POP_TOP                         
                804     RETURN_VALUE                    
                806     LOAD_GLOBAL                     14: errors
                816     LOAD_ATTR                       24: PhoneCodeExpiredError
                836     CHECK_EXC_MATCH                 
                838     POP_JUMP_IF_FALSE               22 (to 884)
                840     POP_TOP                         
                842     PUSH_NULL                       
                844     LOAD_CONST                      1: '__pyarmor_assert_14175__'
                846     LOAD_CONST                      18: 'WRONG_CODE'   # b'\x81\xd5*<\x1d\xdd\x81\xf14\xde('
                848     CALL                            1
                856     SWAP                            2
                858     POP_EXCEPT                      
                860     SWAP                            2
                862     POP_EXCEPT                      
                864     NOP                             
                866     NOP                             
                868     JUMP_FORWARD                    281 (to 1434)
                872     CALL                            1
                880     POP_TOP                         
                882     RETURN_VALUE                    
                884     POP_TOP                         
                886     LOAD_GLOBAL                     1: NULL + Logs
                896     LOAD_ATTR                       2: PrintLog
                916     LOAD_FAST                       1: NUMBER
                918     LOAD_GLOBAL                     4: Lang
                928     PUSH_NULL                       
                930     LOAD_CONST                      1: '__pyarmor_assert_14175__'
                932     LOAD_CONST                      19: 'twofa_wrong'   # b'\x81\xf6\x0f\x1c5\xfb\x81\xc5\t\xf5\x03\xc7'
                934     CALL                            1
                942     BINARY_SUBSCR                   
                946     KW_NAMES                        6: ('account', 'message')
                948     CALL                            2
                956     POP_TOP                         
                958     POP_EXCEPT                      
                960     POP_EXCEPT                      
                962     LOAD_CONST                      8: False
                964     NOP                             
                966     NOP                             
                968     NOP                             
                970     JUMP_FORWARD                    231 (to 1434)
                978     POP_TOP                         
                980     RETURN_CONST                    8: False
                982     COPY                            3
                984     POP_EXCEPT                      
                986     RERAISE                         1
                988     LOAD_GLOBAL                     14: errors
                998     LOAD_ATTR                       22: PhoneCodeInvalidError
                1018    CHECK_EXC_MATCH                 
                1020    POP_JUMP_IF_FALSE               20 (to 1062)
                1022    POP_TOP                         
                1024    PUSH_NULL                       
                1026    LOAD_CONST                      1: '__pyarmor_assert_14175__'
                1028    LOAD_CONST                      18: 'WRONG_CODE'   # b'\x81\xd5*<\x1d\xdd\x81\xf14\xde('
                1030    CALL                            1
                1038    SWAP                            2
                1040    POP_EXCEPT                      
                1042    NOP                             
                1044    NOP                             
                1046    NOP                             
                1048    JUMP_FORWARD                    192 (to 1434)
                1050    CALL                            1
                1058    POP_TOP                         
                1060    RETURN_VALUE                    
                1062    LOAD_GLOBAL                     14: errors
                1072    LOAD_ATTR                       24: PhoneCodeExpiredError
                1092    CHECK_EXC_MATCH                 
                1094    POP_JUMP_IF_FALSE               20 (to 1136)
                1096    POP_TOP                         
                1098    PUSH_NULL                       
                1100    LOAD_CONST                      1: '__pyarmor_assert_14175__'
                1102    LOAD_CONST                      18: 'WRONG_CODE'   # b'\x81\xd5*<\x1d\xdd\x81\xf14\xde('
                1104    CALL                            1
                1112    SWAP                            2
                1114    POP_EXCEPT                      
                1116    NOP                             
                1118    NOP                             
                1120    NOP                             
                1122    JUMP_FORWARD                    155 (to 1434)
                1124    CALL                            1
                1132    POP_TOP                         
                1134    RETURN_VALUE                    
                1136    LOAD_GLOBAL                     26: TimeoutError
                1146    LOAD_GLOBAL                     28: ConnectionError
                1156    BUILD_TUPLE                     2
                1158    CHECK_EXC_MATCH                 
                1160    POP_JUMP_IF_FALSE               69 (to 1300)
                1162    POP_TOP                         
                1164    LOAD_GLOBAL                     1: NULL + Logs
                1174    LOAD_ATTR                       2: PrintLog
                1194    LOAD_FAST                       1: NUMBER
                1196    LOAD_GLOBAL                     4: Lang
                1206    PUSH_NULL                       
                1208    LOAD_CONST                      1: '__pyarmor_assert_14175__'
                1210    LOAD_CONST                      20: 'error_reconnecting'   # b'\x81\xe7\n\x01<\xe8\x81\xc0\x1e\xf9\x02\xceb\xe9\xfb\x91\x06S\xbc'
                1212    CALL                            1
                1220    BINARY_SUBSCR                   
                1224    KW_NAMES                        6: ('account', 'message')
                1226    CALL                            2
                1234    POP_TOP                         
                1236    LOAD_FAST                       5: Err
                1238    LOAD_CONST                      21: 1
                1240    BINARY_OP                       13 (+=)
                1244    STORE_FAST                      5: Err
                1246    LOAD_GLOBAL                     31: NULL + SIGN_IN
                1256    LOAD_FAST                       0: CLIENT
                1258    LOAD_FAST                       1: NUMBER
                1260    LOAD_FAST                       2: CODE
                1262    LOAD_FAST                       3: HASH
                1264    LOAD_FAST                       4: TWOFA
                1266    LOAD_FAST                       5: Err
                1268    CALL                            6
                1276    SWAP                            2
                1278    POP_EXCEPT                      
                1280    NOP                             
                1282    NOP                             
                1284    NOP                             
                1286    JUMP_FORWARD                    73 (to 1434)
                1288    CALL                            1
                1296    POP_TOP                         
                1298    RETURN_VALUE                    
                1300    LOAD_GLOBAL                     32: Exception
                1310    CHECK_EXC_MATCH                 
                1312    POP_JUMP_IF_FALSE               42 (to 1398)
                1314    STORE_FAST                      8: _var_var_15
                1316    LOAD_GLOBAL                     35: NULL + print
                1326    LOAD_CONST                      22: 'SIGN_IN:'
                1328    LOAD_GLOBAL                     13: NULL + str
                1338    LOAD_FAST                       8: _var_var_15
                1340    CALL                            1
                1348    BINARY_OP                       0 (+)
                1352    CALL                            1
                1360    POP_TOP                         
                1362    POP_EXCEPT                      
                1364    LOAD_CONST                      0: None
                1366    STORE_FAST                      8: _var_var_15
                1368    DELETE_FAST                     8: _var_var_15
                1370    LOAD_CONST                      8: False
                1372    NOP                             
                1374    NOP                             
                1376    NOP                             
                1378    JUMP_FORWARD                    27 (to 1434)
                1386    POP_TOP                         
                1388    RETURN_CONST                    8: False
                1390    LOAD_CONST                      0: None
                1392    STORE_FAST                      8: _var_var_15
                1394    DELETE_FAST                     8: _var_var_15
                1396    RERAISE                         1
                1398    RERAISE                         0
                1400    COPY                            3
                1402    POP_EXCEPT                      
                1404    RERAISE                         1
                1406    PUSH_EXC_INFO                   
                1408    PUSH_NULL                       
                1410    LOAD_CONST                      7: '__pyarmor_exit_14177__'
                1412    NOP                             
                1414    LOAD_CONST                      3: b'<COAddr>\x05\x00\x00\x1ad\x05\x00\x00\x00\x00\x00\x00\x00\x00\x00\x00\x00\x00\x00\x00'
                1416    CALL                            1
                1424    POP_TOP                         
                1426    RERAISE                         0
                1428    COPY                            3
                1430    POP_EXCEPT                      
                1432    RERAISE                         1
                1434    PUSH_NULL                       
                1436    LOAD_CONST                      7: '__pyarmor_exit_14177__'
                1438    LOAD_CONST                      3: b'<COAddr>\x05\x00\x00\x1ad\x05\x00\x00\x00\x00\x00\x00\x00\x00\x00\x00\x00\x00\x00\x00'
                1440    BUILD_TUPLE                     1
                1442    CALL_FUNCTION_EX                0
                1444    POP_TOP                         
                1446    RETURN_VALUE                    
            [Exception Table]
                28 to 110 -> 1406 [0] 
                134 to 340 -> 362 [0] 
                362 to 402 -> 1400 [1] lasti
                404 to 570 -> 726 [1] 
                570 to 572 -> 1406 [0] 
                592 to 702 -> 726 [1] 
                702 to 704 -> 1400 [1] lasti
                704 to 706 -> 1406 [0] 
                726 to 780 -> 982 [2] lasti
                780 to 784 -> 1400 [1] lasti
                784 to 786 -> 1406 [0] 
                806 to 858 -> 982 [2] lasti
                858 to 862 -> 1400 [1] lasti
                862 to 864 -> 1406 [0] 
                884 to 958 -> 982 [2] lasti
                958 to 960 -> 1400 [1] lasti
                960 to 962 -> 1406 [0] 
                982 to 1040 -> 1400 [1] lasti
                1040 to 1042 -> 1406 [0] 
                1062 to 1114 -> 1400 [1] lasti
                1114 to 1116 -> 1406 [0] 
                1136 to 1278 -> 1400 [1] lasti
                1278 to 1280 -> 1406 [0] 
                1300 to 1316 -> 1400 [1] lasti
                1316 to 1362 -> 1390 [1] lasti
                1362 to 1370 -> 1406 [0] 
                1390 to 1400 -> 1400 [1] lasti
                1400 to 1406 -> 1406 [0] 
                1406 to 1428 -> 1428 [1] lasti
        '__pyarmor_exit_14153__'
        (
            0
        )
        (
            None
            0
        )
    [Disassembly]
        0       NOP                             
        2       NOP                             
        4       PUSH_NULL                       
        6       LOAD_CONST                      1: '__pyarmor_enter_14152__'
        8       LOAD_CONST                      2: b'<COAddr>\x05\x00\x00\x1a\xa4\x01\x00\x00\x00\x00\x00\x00\x00\x00\x00\x00\x00\x00\x00\x00'
        10      BUILD_TUPLE                     1
        12      CALL_FUNCTION_EX                0
        14      POP_TOP                         
        16      RESUME                          0
        18      NOP                             
        20      NOP                             
        22      NOP                             
        24      NOP                             
        26      LOAD_CONST                      3: 0
        28      LOAD_CONST                      4: None
        30      IMPORT_NAME                     1: os
        32      STORE_NAME                      1: os
        34      LOAD_CONST                      3: 0
        36      LOAD_CONST                      4: None
        38      IMPORT_NAME                     2: eel
        40      STORE_NAME                      2: eel
        42      LOAD_CONST                      3: 0
        44      LOAD_CONST                      4: None
        46      IMPORT_NAME                     3: json
        48      STORE_NAME                      3: json
        50      LOAD_CONST                      3: 0
        52      LOAD_CONST                      4: None
        54      IMPORT_NAME                     4: time
        56      STORE_NAME                      4: time
        58      LOAD_CONST                      3: 0
        60      LOAD_CONST                      4: None
        62      IMPORT_NAME                     5: asyncio
        64      STORE_NAME                      5: asyncio
        66      LOAD_CONST                      3: 0
        68      LOAD_CONST                      4: None
        70      IMPORT_NAME                     6: datetime
        72      STORE_NAME                      6: datetime
        74      LOAD_CONST                      3: 0
        76      LOAD_CONST                      4: None
        78      IMPORT_NAME                     7: concurrent.futures
        80      STORE_NAME                      8: concurrent
        82      LOAD_CONST                      3: 0
        84      LOAD_CONST                      5: ('Path',)
        86      IMPORT_NAME                     9: pathlib
        88      IMPORT_FROM                     10: Path
        90      STORE_NAME                      10: Path
        92      POP_TOP                         
        94      LOAD_CONST                      3: 0
        96      LOAD_CONST                      6: ('Thread', 'Event')
        98      IMPORT_NAME                     11: threading
        100     IMPORT_FROM                     12: Thread
        102     STORE_NAME                      12: Thread
        104     IMPORT_FROM                     13: Event
        106     STORE_NAME                      13: Event
        108     POP_TOP                         
        110     LOAD_CONST                      3: 0
        112     LOAD_CONST                      7: ('TelegramClient', 'functions', 'types', 'errors')
        114     IMPORT_NAME                     14: multithon.sync
        116     IMPORT_FROM                     15: TelegramClient
        118     STORE_NAME                      15: TelegramClient
        120     IMPORT_FROM                     16: functions
        122     STORE_NAME                      16: functions
        124     IMPORT_FROM                     17: types
        126     STORE_NAME                      17: types
        128     IMPORT_FROM                     18: errors
        130     STORE_NAME                      18: errors
        132     POP_TOP                         
        134     LOAD_CONST                      3: 0
        136     LOAD_CONST                      8: ('StopProgram',)
        138     IMPORT_NAME                     19: multithon.errors
        140     IMPORT_FROM                     20: StopProgram
        142     STORE_NAME                      20: StopProgram
        144     POP_TOP                         
        146     LOAD_CONST                      3: 0
        148     LOAD_CONST                      9: ('GetLang',)
        150     IMPORT_NAME                     21: program.static_classes
        152     IMPORT_FROM                     22: GetLang
        154     STORE_NAME                      22: GetLang
        156     POP_TOP                         
        158     LOAD_CONST                      3: 0
        160     LOAD_CONST                      10: ('Logs',)
        162     IMPORT_NAME                     21: program.static_classes
        164     IMPORT_FROM                     23: Logs
        166     STORE_NAME                      23: Logs
        168     POP_TOP                         
        170     LOAD_CONST                      3: 0
        172     LOAD_CONST                      11: ('get_logger',)
        174     IMPORT_NAME                     21: program.static_classes
        176     IMPORT_FROM                     24: get_logger
        178     STORE_NAME                      24: get_logger
        180     POP_TOP                         
        182     LOAD_CONST                      3: 0
        184     LOAD_CONST                      12: ('logging',)
        186     IMPORT_NAME                     21: program.static_classes
        188     IMPORT_FROM                     25: logging
        190     STORE_NAME                      25: logging
        192     POP_TOP                         
        194     LOAD_CONST                      3: 0
        196     LOAD_CONST                      13: ('memory_check_switcher',)
        198     IMPORT_NAME                     21: program.static_classes
        200     IMPORT_FROM                     26: memory_check_switcher
        202     STORE_NAME                      26: memory_check_switcher
        204     POP_TOP                         
        206     LOAD_CONST                      3: 0
        208     LOAD_CONST                      14: ('memory_set_pid',)
        210     IMPORT_NAME                     21: program.static_classes
        212     IMPORT_FROM                     27: memory_set_pid
        214     STORE_NAME                      27: memory_set_pid
        216     POP_TOP                         
        218     LOAD_CONST                      3: 0
        220     LOAD_CONST                      15: ('proxy_hide',)
        222     IMPORT_NAME                     21: program.static_classes
        224     IMPORT_FROM                     28: proxy_hide
        226     STORE_NAME                      28: proxy_hide
        228     POP_TOP                         
        230     LOAD_CONST                      3: 0
        232     LOAD_CONST                      16: ('Disconnect',)
        234     IMPORT_NAME                     29: program.telegram
        236     IMPORT_FROM                     30: Disconnect
        238     STORE_NAME                      30: Disconnect
        240     POP_TOP                         
        242     LOAD_CONST                      3: 0
        244     LOAD_CONST                      17: ('Thread_wait',)
        246     IMPORT_NAME                     29: program.telegram
        248     IMPORT_FROM                     31: Thread_wait
        250     STORE_NAME                      31: Thread_wait
        252     POP_TOP                         
        254     LOAD_CONST                      3: 0
        256     LOAD_CONST                      18: ('get_account_proxy',)
        258     IMPORT_NAME                     29: program.telegram
        260     IMPORT_FROM                     32: get_account_proxy
        262     STORE_NAME                      32: get_account_proxy
        264     POP_TOP                         
        266     LOAD_CONST                      3: 0
        268     LOAD_CONST                      19: ('json_file',)
        270     IMPORT_NAME                     29: program.telegram
        272     IMPORT_FROM                     33: json_file
        274     STORE_NAME                      33: json_file
        276     POP_TOP                         
        278     LOAD_CONST                      3: 0
        280     LOAD_CONST                      20: ('GetConfig',)
        282     IMPORT_NAME                     34: program.general
        284     IMPORT_FROM                     35: GetConfig
        286     STORE_NAME                      35: GetConfig
        288     POP_TOP                         
        290     LOAD_CONST                      3: 0
        292     LOAD_CONST                      21: ('GetProxy',)
        294     IMPORT_NAME                     34: program.general
        296     IMPORT_FROM                     36: GetProxy
        298     STORE_NAME                      36: GetProxy
        300     POP_TOP                         
        302     LOAD_CONST                      3: 0
        304     LOAD_CONST                      22: ('StopDetect',)
        306     IMPORT_NAME                     34: program.general
        308     IMPORT_FROM                     37: StopDetect
        310     STORE_NAME                      37: StopDetect
        312     POP_TOP                         
        314     LOAD_CONST                      3: 0
        316     LOAD_CONST                      23: ('check_get_settings',)
        318     IMPORT_NAME                     34: program.general
        320     IMPORT_FROM                     38: check_get_settings
        322     STORE_NAME                      38: check_get_settings
        324     POP_TOP                         
        326     LOAD_CONST                      3: 0
        328     LOAD_CONST                      24: ('del_task_manager',)
        330     IMPORT_NAME                     34: program.general
        332     IMPORT_FROM                     39: del_task_manager
        334     STORE_NAME                      39: del_task_manager
        336     POP_TOP                         
        338     LOAD_CONST                      3: 0
        340     LOAD_CONST                      25: ('getFile',)
        342     IMPORT_NAME                     34: program.general
        344     IMPORT_FROM                     40: getFile
        346     STORE_NAME                      40: getFile
        348     POP_TOP                         
        350     LOAD_CONST                      3: 0
        352     LOAD_CONST                      26: ('set_task_manager',)
        354     IMPORT_NAME                     34: program.general
        356     IMPORT_FROM                     41: set_task_manager
        358     STORE_NAME                      41: set_task_manager
        360     POP_TOP                         
        362     LOAD_CONST                      3: 0
        364     LOAD_CONST                      27: ('db_param_accounts',)
        366     IMPORT_NAME                     42: program.database
        368     IMPORT_FROM                     43: db_param_accounts
        370     STORE_NAME                      43: db_param_accounts
        372     POP_TOP                         
        374     LOAD_CONST                      28: <CODE> Registrator_add_account
        376     MAKE_FUNCTION                   0
        378     STORE_NAME                      44: Registrator_add_account
        380     LOAD_CONST                      29: <CODE> START
        382     MAKE_FUNCTION                   0
        384     STORE_NAME                      45: START
        386     LOAD_CONST                      30: <CODE> destroy_empty_session
        388     MAKE_FUNCTION                   0
        390     STORE_NAME                      46: destroy_empty_session
        392     LOAD_CONST                      31: <CODE> get_code
        394     MAKE_FUNCTION                   0
        396     STORE_NAME                      47: get_code
        398     LOAD_CONST                      32: <CODE> get_twofa
        400     MAKE_FUNCTION                   0
        402     STORE_NAME                      48: get_twofa
        404     LOAD_CONST                      37: (0,)
        406     LOAD_CONST                      33: <CODE> add_account
        408     MAKE_FUNCTION                   1
        410     STORE_NAME                      49: add_account
        412     LOAD_CONST                      34: <CODE> TELEGRAM_SEND_CODE
        414     MAKE_FUNCTION                   0
        416     STORE_NAME                      50: TELEGRAM_SEND_CODE
        418     LOAD_CONST                      38: (None, 0)
        420     LOAD_CONST                      35: <CODE> SIGN_IN
        422     MAKE_FUNCTION                   1
        424     STORE_NAME                      51: SIGN_IN
        426     LOAD_CONST                      4: None
        428     NOP                             
        430     NOP                             
        432     NOP                             
        434     JUMP_FORWARD                    19 (to 474)
        442     POP_TOP                         
        444     RETURN_CONST                    4: None
        446     PUSH_EXC_INFO                   
        448     PUSH_NULL                       
        450     LOAD_CONST                      36: '__pyarmor_exit_14153__'
        452     NOP                             
        454     LOAD_CONST                      2: b'<COAddr>\x05\x00\x00\x1a\xa4\x01\x00\x00\x00\x00\x00\x00\x00\x00\x00\x00\x00\x00\x00\x00'
        456     CALL                            1
        464     POP_TOP                         
        466     RERAISE                         0
        468     COPY                            3
        470     POP_EXCEPT                      
        472     RERAISE                         1
        474     PUSH_NULL                       
        476     LOAD_CONST                      36: '__pyarmor_exit_14153__'
        478     LOAD_CONST                      2: b'<COAddr>\x05\x00\x00\x1a\xa4\x01\x00\x00\x00\x00\x00\x00\x00\x00\x00\x00\x00\x00\x00\x00'
        480     BUILD_TUPLE                     1
        482     CALL_FUNCTION_EX                0
        484     POP_TOP                         
        486     RETURN_VALUE                    
    [Exception Table]
        26 to 426 -> 446 [0] 
        446 to 468 -> 468 [1] lasti
