#decoded by lolz.live/mrpenny / t.me/zeus_jackpot
# ================================
# Примечания по Pyarmor:
# - Байт-код и объекты кода Pyarmor соответствуют стандартному Python, но присутствуют специальные вызовы функций среды выполнения (runtime) Pyarmor.
# - Вызовы строк — это не ошибки, а маркеры, которые обрабатываются Pyarmor во время выполнения.
#
# Руководство по декомпиляции (без среды выполнения):
# 1. Игнорируйте зашифрованные байты после `#`; используйте только строку до `#`.
# 2. Удалите "__pyarmor_enter_xxx__"(b"<COAddr>...") и "__pyarmor_leave_xxx__"(b"<COAddr>...") (пролог/эпилог).
# 3. "__pyarmor_assert_xxx__"(A) не является настоящим оператором assert.
#    - Если A — это имя или читаемая строка: замените на A.
#    - Если A — это (X, "Y"): замените на X.Y.
#    - Если A — это (X, "Y", Z): замените на X.Y = Z.
#    - В противном случае: выберите наиболее подходящую/логичную замену.
# 4. "__pyarmor_bcc_xxx__"(...) указывает на машинный (нативный) код; тело функции недоступно. Добавьте комментарий.
# ================================

[Code]
    File Name: <frozen program.modules.Registrator_converter>
    Object Name: <module>
    Qualified Name: <module>
    Arg Count: 0
    Pos Only Arg Count: 0
    KW Only Arg Count: 0
    Stack Size: 5
    Flags: 0x20000000 (CO_PYARMOR_OBFUSCATED)
    [Names]
        '__assert_armored__'
        'os'
        'eel'
        'asyncio'
        'threading'
        'Thread'
        'Event'
        'opentele.tl'
        'TelegramClient'
        'TelegramClientConverter'
        'opentele.api'
        'UseCurrentSession'
        'multithon'
        'multithon.errors'
        'StopProgram'
        'program.static_classes'
        'GetLang'
        'Logs'
        'check_module'
        'logging'
        'memory_check_switcher'
        'memory_set_pid'
        'proxy_hide'
        'program.telegram'
        'Disconnect'
        'Thread_wait'
        'get_account_json'
        'get_account_proxy'
        'rewrite_proxy_and_status'
        'program.general'
        'GetConfig'
        'GetProxy'
        'StopDetect'
        'check_get_settings'
        'del_task_manager'
        'getPath'
        'set_task_manager'
        'Registrator_converter'
        'START'
        'worker'
        'async_worker'
    [Locals+Names]
    [Constants]
        '__pyarmor_assert_14178__'
        '__pyarmor_enter_14179__'
        b'<COAddr>\x07\x00\x00\x1ax\x01\x00\x00\x00\x00\x00\x00\x00\x00\x00\x00\x00\x00\x00\x00'
        0
        None
        (
            'Thread'
            'Event'
        )
        (
            'TelegramClient'
        )
        (
            'UseCurrentSession'
        )
        (
            'StopProgram'
        )
        (
            'GetLang'
        )
        (
            'Logs'
        )
        (
            'check_module'
        )
        (
            'logging'
        )
        (
            'memory_check_switcher'
        )
        (
            'memory_set_pid'
        )
        (
            'proxy_hide'
        )
        (
            'Disconnect'
        )
        (
            'Thread_wait'
        )
        (
            'get_account_json'
        )
        (
            'get_account_proxy'
        )
        (
            'rewrite_proxy_and_status'
        )
        (
            'GetConfig'
        )
        (
            'GetProxy'
        )
        (
            'StopDetect'
        )
        (
            'check_get_settings'
        )
        (
            'del_task_manager'
        )
        (
            'getPath'
        )
        (
            'set_task_manager'
        )
        [Code]
            File Name: <frozen program.modules.Registrator_converter>
            Object Name: Registrator_converter
            Qualified Name: Registrator_converter
            Arg Count: 1
            Pos Only Arg Count: 0
            KW Only Arg Count: 0
            Stack Size: 8
            Flags: 0x20000003 (CO_OPTIMIZED | CO_NEWLOCALS | CO_PYARMOR_OBFUSCATED)
            [Names]
                'get'
                'getPath'
                'GetConfig'
                'config'
                'GetLang'
                'Lang'
                'GetProxy'
                'eel'
                'sendSuccessBox'
                'memory_check_switcher'
                'check_module'
                'Event'
                'memory_set_pid'
                'Thread'
                'START'
                'start'
                'Logs'
                'WaitStopAnsfer'
                'UpdateLogInWindow'
                'BaseException'
                'logging'
            [Locals+Names]
                'data'
                '__assert_armored__'
                '_var_var_0'
                '_var_var_1'
                '_var_var_2'
                '_var_var_3'
            [Constants]
                None
                '__pyarmor_assert_14181__'
                '__pyarmor_enter_14182__'
                b'<COAddr>\x07\x00\x00\x1a\xda\x02\x00\x00\x00\x00\x00\x00\x00\x00\x00\x00\x00\x00\x00\x00'
                'action'
                'getPath'
                '__pyarmor_exit_14183__'
                'program_running'   # b'\x81\xf2\n\x1c4\xe8\xbf\xdf$\xe8\x18\xceb\xe5\xf6\x82'
                False
                10
                (
                    'target'
                    'args'
                )
                True
                (
                    'target'
                    'args'
                    'daemon'
                )
            [Disassembly]
                0       NOP                             
                2       NOP                             
                4       PUSH_NULL                       
                6       LOAD_CONST                      2: '__pyarmor_enter_14182__'
                8       LOAD_CONST                      3: b'<COAddr>\x07\x00\x00\x1a\xda\x02\x00\x00\x00\x00\x00\x00\x00\x00\x00\x00\x00\x00\x00\x00'
                10      BUILD_TUPLE                     1
                12      CALL_FUNCTION_EX                0
                14      POP_TOP                         
                16      RESUME                          0
                18      NOP                             
                20      NOP                             
                22      NOP                             
                24      NOP                             
                26      NOP                             
                28      NOP                             
                30      LOAD_FAST                       0: data
                32      LOAD_ATTR                       1: get
                52      LOAD_CONST                      4: 'action'
                54      CALL                            1
                62      POP_JUMP_IF_NONE                28 (to 120)
                64      LOAD_FAST                       0: data
                66      LOAD_CONST                      4: 'action'
                68      BINARY_SUBSCR                   
                72      LOAD_CONST                      5: 'getPath'
                74      COMPARE_OP                      40 (==)
                78      POP_JUMP_IF_FALSE               20 (to 120)
                80      LOAD_GLOBAL                     3: NULL + getPath
                90      LOAD_FAST                       0: data
                92      CALL                            1
                100     NOP                             
                102     NOP                             
                104     JUMP_FORWARD                    338 (to 784)
                108     CALL                            1
                116     POP_TOP                         
                118     RETURN_VALUE                    
                120     LOAD_GLOBAL                     5: NULL + GetConfig
                130     CALL                            0
                138     STORE_GLOBAL                    3: config
                140     LOAD_GLOBAL                     9: NULL + GetLang
                150     LOAD_GLOBAL                     6: config
                160     CALL                            1
                168     STORE_GLOBAL                    5: Lang
                170     LOAD_GLOBAL                     13: NULL + GetProxy
                180     CALL                            0
                188     STORE_FAST                      2: _var_var_0
                190     LOAD_GLOBAL                     15: NULL + eel
                200     LOAD_ATTR                       16: sendSuccessBox
                220     LOAD_GLOBAL                     10: Lang
                230     PUSH_NULL                       
                232     LOAD_CONST                      1: '__pyarmor_assert_14181__'
                234     LOAD_CONST                      7: 'program_running'   # b'\x81\xf2\n\x1c4\xe8\xbf\xdf$\xe8\x18\xceb\xe5\xf6\x82'
                236     CALL                            1
                244     BINARY_SUBSCR                   
                248     CALL                            1
                256     POP_TOP                         
                258     LOAD_GLOBAL                     19: NULL + memory_check_switcher
                268     CALL                            0
                276     POP_JUMP_IF_TRUE                11 (to 300)
                278     NOP                             
                280     LOAD_CONST                      8: False
                282     NOP                             
                284     NOP                             
                286     NOP                             
                288     JUMP_FORWARD                    247 (to 784)
                296     POP_TOP                         
                298     RETURN_CONST                    8: False
                300     LOAD_GLOBAL                     21: NULL + check_module
                310     LOAD_CONST                      9: 10
                312     CALL                            1
                320     POP_JUMP_IF_TRUE                11 (to 344)
                322     NOP                             
                324     LOAD_CONST                      8: False
                326     NOP                             
                328     NOP                             
                330     NOP                             
                332     JUMP_FORWARD                    225 (to 784)
                340     POP_TOP                         
                342     RETURN_CONST                    8: False
                344     LOAD_GLOBAL                     23: NULL + Event
                354     CALL                            0
                362     STORE_FAST                      3: _var_var_1
                364     LOAD_GLOBAL                     25: NULL + memory_set_pid
                374     CALL                            0
                382     STORE_FAST                      4: _var_var_2
                384     LOAD_GLOBAL                     27: NULL + Thread
                394     LOAD_GLOBAL                     28: START
                404     LOAD_FAST                       0: data
                406     LOAD_GLOBAL                     6: config
                416     LOAD_FAST                       4: _var_var_2
                418     LOAD_FAST                       2: _var_var_0
                420     LOAD_FAST                       3: _var_var_1
                422     BUILD_TUPLE                     5
                424     KW_NAMES                        10: ('target', 'args')
                426     CALL                            2
                434     LOAD_ATTR                       31: start
                454     CALL                            0
                462     POP_TOP                         
                464     LOAD_GLOBAL                     27: NULL + Thread
                474     LOAD_GLOBAL                     32: Logs
                484     LOAD_ATTR                       34: WaitStopAnsfer
                504     LOAD_GLOBAL                     6: config
                514     LOAD_FAST                       4: _var_var_2
                516     LOAD_FAST                       3: _var_var_1
                518     BUILD_TUPLE                     3
                520     LOAD_CONST                      11: True
                522     KW_NAMES                        12: ('target', 'args', 'daemon')
                524     CALL                            3
                532     LOAD_ATTR                       31: start
                552     CALL                            0
                560     POP_TOP                         
                562     LOAD_GLOBAL                     27: NULL + Thread
                572     LOAD_GLOBAL                     32: Logs
                582     LOAD_ATTR                       36: UpdateLogInWindow
                602     LOAD_GLOBAL                     6: config
                612     LOAD_FAST                       4: _var_var_2
                614     LOAD_FAST                       3: _var_var_1
                616     BUILD_TUPLE                     3
                618     LOAD_CONST                      11: True
                620     KW_NAMES                        12: ('target', 'args', 'daemon')
                622     CALL                            3
                630     LOAD_ATTR                       31: start
                650     CALL                            0
                658     POP_TOP                         
                660     LOAD_CONST                      0: None
                662     NOP                             
                664     NOP                             
                666     NOP                             
                668     JUMP_FORWARD                    57 (to 784)
                676     POP_TOP                         
                678     RETURN_CONST                    0: None
                680     PUSH_EXC_INFO                   
                682     LOAD_GLOBAL                     38: BaseException
                692     CHECK_EXC_MATCH                 
                694     POP_JUMP_IF_FALSE               26 (to 748)
                696     STORE_FAST                      5: _var_var_3
                698     PUSH_NULL                       
                700     LOAD_GLOBAL                     41: NULL + logging
                710     LOAD_FAST                       5: _var_var_3
                712     CALL                            1
                720     CALL                            0
                728     POP_TOP                         
                730     POP_EXCEPT                      
                732     LOAD_CONST                      0: None
                734     STORE_FAST                      5: _var_var_3
                736     DELETE_FAST                     5: _var_var_3
                738     JUMP_BACKWARD                   40 (to 660)
                740     LOAD_CONST                      0: None
                742     STORE_FAST                      5: _var_var_3
                744     DELETE_FAST                     5: _var_var_3
                746     RERAISE                         1
                748     RERAISE                         0
                750     COPY                            3
                752     POP_EXCEPT                      
                754     RERAISE                         1
                756     PUSH_EXC_INFO                   
                758     PUSH_NULL                       
                760     LOAD_CONST                      6: '__pyarmor_exit_14183__'
                762     NOP                             
                764     LOAD_CONST                      3: b'<COAddr>\x07\x00\x00\x1a\xda\x02\x00\x00\x00\x00\x00\x00\x00\x00\x00\x00\x00\x00\x00\x00'
                766     CALL                            1
                774     POP_TOP                         
                776     RERAISE                         0
                778     COPY                            3
                780     POP_EXCEPT                      
                782     RERAISE                         1
                784     PUSH_NULL                       
                786     LOAD_CONST                      6: '__pyarmor_exit_14183__'
                788     LOAD_CONST                      3: b'<COAddr>\x07\x00\x00\x1a\xda\x02\x00\x00\x00\x00\x00\x00\x00\x00\x00\x00\x00\x00\x00\x00'
                790     BUILD_TUPLE                     1
                792     CALL_FUNCTION_EX                0
                794     POP_TOP                         
                796     RETURN_VALUE                    
            [Exception Table]
                30 to 100 -> 680 [0] 
                120 to 278 -> 680 [0] 
                300 to 322 -> 680 [0] 
                344 to 660 -> 680 [0] 
                680 to 698 -> 750 [1] lasti
                698 to 730 -> 740 [1] lasti
                730 to 740 -> 756 [0] 
                740 to 750 -> 750 [1] lasti
                750 to 756 -> 756 [0] 
                756 to 778 -> 778 [1] lasti
        [Code]
            File Name: <frozen program.modules.Registrator_converter>
            Object Name: START
            Qualified Name: START
            Arg Count: 5
            Pos Only Arg Count: 0
            KW Only Arg Count: 0
            Stack Size: 10
            Flags: 0x20000003 (CO_OPTIMIZED | CO_NEWLOCALS | CO_PYARMOR_OBFUSCATED)
            [Names]
                'is_set'
                'StopProgram'
                'check_get_settings'
                'get'
                'os'
                'listdir'
                'path'
                'exists'
                'replace'
                'append'
                'isinstance'
                'list'
                'len'
                'eel'
                'sendErrorBox'
                'Lang'
                'set_task_manager'
                'asyncio'
                'run'
                'worker'
                'BaseException'
                'logging'
                'del_task_manager'
                'StopDetect'
            [Locals+Names]
                'data'
                'config'
                'pid'
                'proxy'
                'stop_thread'
                '__assert_armored__'
                '_var_var_4'
                '_var_var_5'
                '_var_var_6'
                '_var_var_3'
            [Constants]
                None
                '__pyarmor_assert_14184__'
                '__pyarmor_enter_14185__'
                b'<COAddr>\x07\x00\x00\x1ah\x04\x00\x00\x00\x00\x00\x00\x00\x00\x00\x00\x00\x00\x00\x00'
                'Settings'
                'accounts_choose_all'   # b'\x81\xe3\x1b\x10<\xef\xb0\xc6\x08\xc5\x0e\xc8c\xe3\xeb\x800\\\xb7\xab'
                'sessions/active'   # b'\x81\xf1\x1d\x00 \xf3\xb1\xdc\x08\xb5\x0c\xc3x\xe5\xee\x80'
                '.json'
                'sessions/active//'   # b'\x81\xf1\x1d\x00 \xf3\xb1\xdc\x08\xb5\x0c\xc3x\xe5\xee\x80@\x12'
                '.session'
                ''
                'Accounts'
                1
                'select_accounts_works'   # b'\x81\xf1\x1d\x1f6\xf9\xaa\xed\x1a\xf9\x0e\xcfy\xe2\xec\x960J\xb4\xb5\xa1\xd8'
                'folder_path'   # b'\x81\xe4\x17\x1f7\xff\xac\xed\x0b\xfb\x19\xc8'
                'check_folder_path'   # b'\x81\xe1\x10\x160\xf1\x81\xd4\x14\xf6\t\xc5~\xd3\xe8\x84\x1bU'
                'stuff'
                (
                    'accounts'
                    'name'
                )
                '__pyarmor_exit_14186__'
                'Done'
            [Disassembly]
                0       NOP                             
                2       NOP                             
                4       PUSH_NULL                       
                6       LOAD_CONST                      2: '__pyarmor_enter_14185__'
                8       LOAD_CONST                      3: b'<COAddr>\x07\x00\x00\x1ah\x04\x00\x00\x00\x00\x00\x00\x00\x00\x00\x00\x00\x00\x00\x00'
                10      BUILD_TUPLE                     1
                12      CALL_FUNCTION_EX                0
                14      POP_TOP                         
                16      RESUME                          0
                18      NOP                             
                20      NOP                             
                22      NOP                             
                24      NOP                             
                26      NOP                             
                28      NOP                             
                30      LOAD_FAST                       4: stop_thread
                32      LOAD_ATTR                       1: is_set
                52      CALL                            0
                60      POP_JUMP_IF_FALSE               10 (to 82)
                62      LOAD_GLOBAL                     3: NULL + StopProgram
                72      CALL                            0
                80      RAISE_VARARGS                   1
                82      LOAD_GLOBAL                     5: NULL + check_get_settings
                92      LOAD_FAST                       0: data
                94      LOAD_ATTR                       7: get
                114     LOAD_CONST                      4: 'Settings'
                116     CALL                            1
                124     CALL                            1
                132     POP_TOP                         
                134     LOAD_FAST                       0: data
                136     LOAD_CONST                      4: 'Settings'
                138     BINARY_SUBSCR                   
                142     LOAD_ATTR                       7: get
                162     PUSH_NULL                       
                164     LOAD_CONST                      1: '__pyarmor_assert_14184__'
                166     LOAD_CONST                      5: 'accounts_choose_all'   # b'\x81\xe3\x1b\x10<\xef\xb0\xc6\x08\xc5\x0e\xc8c\xe3\xeb\x800\\\xb7\xab'
                168     CALL                            1
                176     CALL                            1
                184     POP_JUMP_IF_FALSE               130 (to 446)
                186     BUILD_LIST                      0
                188     STORE_FAST                      6: _var_var_4
                190     LOAD_GLOBAL                     9: NULL + os
                200     LOAD_ATTR                       10: listdir
                220     PUSH_NULL                       
                222     LOAD_CONST                      1: '__pyarmor_assert_14184__'
                224     LOAD_CONST                      6: 'sessions/active'   # b'\x81\xf1\x1d\x00 \xf3\xb1\xdc\x08\xb5\x0c\xc3x\xe5\xee\x80'
                226     CALL                            1
                234     CALL                            1
                242     GET_ITER                        
                244     FOR_ITER                        97 (to 440)
                248     STORE_FAST                      7: _var_var_5
                250     LOAD_CONST                      7: '.json'
                252     LOAD_FAST                       7: _var_var_5
                254     CONTAINS_OP                     0 (in)
                256     POP_JUMP_IF_TRUE                1 (to 260)
                258     JUMP_BACKWARD                   8 (to 244)
                260     LOAD_GLOBAL                     8: os
                270     LOAD_ATTR                       12: path
                290     LOAD_ATTR                       15: exists
                310     PUSH_NULL                       
                312     LOAD_CONST                      1: '__pyarmor_assert_14184__'
                314     LOAD_CONST                      8: 'sessions/active//'   # b'\x81\xf1\x1d\x00 \xf3\xb1\xdc\x08\xb5\x0c\xc3x\xe5\xee\x80@\x12'
                316     CALL                            1
                324     LOAD_FAST                       7: _var_var_5
                326     LOAD_ATTR                       17: replace
                346     LOAD_CONST                      7: '.json'
                348     LOAD_CONST                      9: '.session'
                350     CALL                            2
                358     FORMAT_VALUE                    0 (FVC_NONE)
                360     BUILD_STRING                    2
                362     CALL                            1
                370     POP_JUMP_IF_TRUE                1 (to 374)
                372     JUMP_BACKWARD                   65 (to 244)
                374     LOAD_FAST                       6: _var_var_4
                376     LOAD_ATTR                       19: append
                396     LOAD_FAST                       7: _var_var_5
                398     LOAD_ATTR                       17: replace
                418     LOAD_CONST                      7: '.json'
                420     LOAD_CONST                      10: ''
                422     CALL                            2
                430     CALL                            1
                438     POP_TOP                         
                440     JUMP_BACKWARD                   99 (to 244)
                442     END_FOR                         
                444     JUMP_FORWARD                    24 (to 494)
                446     LOAD_FAST                       0: data
                448     LOAD_CONST                      11: 'Accounts'
                450     BINARY_SUBSCR                   
                454     STORE_FAST                      6: _var_var_4
                456     LOAD_GLOBAL                     21: NULL + isinstance
                466     LOAD_FAST                       6: _var_var_4
                468     LOAD_GLOBAL                     22: list
                478     CALL                            2
                486     POP_JUMP_IF_TRUE                3 (to 494)
                488     LOAD_FAST                       6: _var_var_4
                490     BUILD_LIST                      1
                492     STORE_FAST                      6: _var_var_4
                494     LOAD_GLOBAL                     25: NULL + len
                504     LOAD_FAST                       6: _var_var_4
                506     CALL                            1
                514     LOAD_CONST                      12: 1
                516     COMPARE_OP                      2 (<)
                520     POP_JUMP_IF_FALSE               44 (to 610)
                522     LOAD_GLOBAL                     27: NULL + eel
                532     LOAD_ATTR                       28: sendErrorBox
                552     LOAD_GLOBAL                     30: Lang
                562     PUSH_NULL                       
                564     LOAD_CONST                      1: '__pyarmor_assert_14184__'
                566     LOAD_CONST                      13: 'select_accounts_works'   # b'\x81\xf1\x1d\x1f6\xf9\xaa\xed\x1a\xf9\x0e\xcfy\xe2\xec\x960J\xb4\xb5\xa1\xd8'
                568     CALL                            1
                576     BINARY_SUBSCR                   
                580     CALL                            1
                588     POP_TOP                         
                590     LOAD_GLOBAL                     3: NULL + StopProgram
                600     CALL                            0
                608     RAISE_VARARGS                   1
                610     LOAD_FAST                       0: data
                612     LOAD_CONST                      4: 'Settings'
                614     BINARY_SUBSCR                   
                618     LOAD_ATTR                       7: get
                638     PUSH_NULL                       
                640     LOAD_CONST                      1: '__pyarmor_assert_14184__'
                642     LOAD_CONST                      14: 'folder_path'   # b'\x81\xe4\x17\x1f7\xff\xac\xed\x0b\xfb\x19\xc8'
                644     CALL                            1
                652     CALL                            1
                660     STORE_FAST                      8: _var_var_6
                662     LOAD_GLOBAL                     8: os
                672     LOAD_ATTR                       12: path
                692     LOAD_ATTR                       15: exists
                712     LOAD_FAST                       8: _var_var_6
                714     CALL                            1
                722     POP_JUMP_IF_TRUE                44 (to 812)
                724     LOAD_GLOBAL                     27: NULL + eel
                734     LOAD_ATTR                       28: sendErrorBox
                754     LOAD_GLOBAL                     30: Lang
                764     PUSH_NULL                       
                766     LOAD_CONST                      1: '__pyarmor_assert_14184__'
                768     LOAD_CONST                      15: 'check_folder_path'   # b'\x81\xe1\x10\x160\xf1\x81\xd4\x14\xf6\t\xc5~\xd3\xe8\x84\x1bU'
                770     CALL                            1
                778     BINARY_SUBSCR                   
                782     CALL                            1
                790     POP_TOP                         
                792     LOAD_GLOBAL                     3: NULL + StopProgram
                802     CALL                            0
                810     RAISE_VARARGS                   1
                812     LOAD_GLOBAL                     33: NULL + set_task_manager
                822     LOAD_FAST                       2: pid
                824     LOAD_FAST                       6: _var_var_4
                826     LOAD_FAST                       0: data
                828     LOAD_CONST                      16: 'stuff'
                830     BINARY_SUBSCR                   
                834     KW_NAMES                        17: ('accounts', 'name')
                836     CALL                            3
                844     POP_TOP                         
                846     LOAD_GLOBAL                     35: NULL + asyncio
                856     LOAD_ATTR                       36: run
                876     LOAD_GLOBAL                     39: NULL + worker
                886     LOAD_FAST                       0: data
                888     LOAD_FAST                       6: _var_var_4
                890     LOAD_FAST                       1: config
                892     LOAD_FAST                       2: pid
                894     LOAD_FAST                       3: proxy
                896     LOAD_FAST                       4: stop_thread
                898     CALL                            6
                906     CALL                            1
                914     POP_TOP                         
                916     LOAD_GLOBAL                     45: NULL + del_task_manager
                926     LOAD_FAST                       2: pid
                928     CALL                            1
                936     POP_TOP                         
                938     LOAD_GLOBAL                     47: NULL + StopDetect
                948     LOAD_FAST                       4: stop_thread
                950     CALL                            1
                958     POP_TOP                         
                960     NOP                             
                962     LOAD_CONST                      19: 'Done'
                964     NOP                             
                966     NOP                             
                968     NOP                             
                970     JUMP_FORWARD                    105 (to 1182)
                978     POP_TOP                         
                980     RETURN_CONST                    19: 'Done'
                982     PUSH_EXC_INFO                   
                984     LOAD_GLOBAL                     2: StopProgram
                994     CHECK_EXC_MATCH                 
                996     POP_JUMP_IF_FALSE               3 (to 1004)
                998     POP_TOP                         
                1000    POP_EXCEPT                      
                1002    JUMP_BACKWARD                   44 (to 916)
                1004    LOAD_GLOBAL                     40: BaseException
                1014    CHECK_EXC_MATCH                 
                1016    POP_JUMP_IF_FALSE               26 (to 1070)
                1018    STORE_FAST                      9: _var_var_3
                1020    PUSH_NULL                       
                1022    LOAD_GLOBAL                     43: NULL + logging
                1032    LOAD_FAST                       9: _var_var_3
                1034    CALL                            1
                1042    CALL                            0
                1050    POP_TOP                         
                1052    POP_EXCEPT                      
                1054    LOAD_CONST                      0: None
                1056    STORE_FAST                      9: _var_var_3
                1058    DELETE_FAST                     9: _var_var_3
                1060    JUMP_BACKWARD                   73 (to 916)
                1062    LOAD_CONST                      0: None
                1064    STORE_FAST                      9: _var_var_3
                1066    DELETE_FAST                     9: _var_var_3
                1068    RERAISE                         1
                1070    RERAISE                         0
                1072    COPY                            3
                1074    POP_EXCEPT                      
                1076    RERAISE                         1
                1078    PUSH_EXC_INFO                   
                1080    LOAD_GLOBAL                     45: NULL + del_task_manager
                1090    LOAD_FAST                       2: pid
                1092    CALL                            1
                1100    POP_TOP                         
                1102    LOAD_GLOBAL                     47: NULL + StopDetect
                1112    LOAD_FAST                       4: stop_thread
                1114    CALL                            1
                1122    POP_TOP                         
                1124    POP_TOP                         
                1126    POP_EXCEPT                      
                1128    LOAD_CONST                      19: 'Done'
                1130    NOP                             
                1132    NOP                             
                1134    NOP                             
                1136    JUMP_FORWARD                    22 (to 1182)
                1144    POP_TOP                         
                1146    RETURN_CONST                    19: 'Done'
                1148    COPY                            3
                1150    POP_EXCEPT                      
                1152    RERAISE                         1
                1154    PUSH_EXC_INFO                   
                1156    PUSH_NULL                       
                1158    LOAD_CONST                      18: '__pyarmor_exit_14186__'
                1160    NOP                             
                1162    LOAD_CONST                      3: b'<COAddr>\x07\x00\x00\x1ah\x04\x00\x00\x00\x00\x00\x00\x00\x00\x00\x00\x00\x00\x00\x00'
                1164    CALL                            1
                1172    POP_TOP                         
                1174    RERAISE                         0
                1176    COPY                            3
                1178    POP_EXCEPT                      
                1180    RERAISE                         1
                1182    PUSH_NULL                       
                1184    LOAD_CONST                      18: '__pyarmor_exit_14186__'
                1186    LOAD_CONST                      3: b'<COAddr>\x07\x00\x00\x1ah\x04\x00\x00\x00\x00\x00\x00\x00\x00\x00\x00\x00\x00\x00\x00'
                1188    BUILD_TUPLE                     1
                1190    CALL_FUNCTION_EX                0
                1192    POP_TOP                         
                1194    RETURN_VALUE                    
            [Exception Table]
                30 to 258 -> 982 [0] 
                260 to 372 -> 982 [0] 
                374 to 916 -> 982 [0] 
                916 to 960 -> 1154 [0] 
                982 to 1000 -> 1072 [1] lasti
                1000 to 1004 -> 1078 [0] 
                1004 to 1020 -> 1072 [1] lasti
                1020 to 1052 -> 1062 [1] lasti
                1052 to 1062 -> 1078 [0] 
                1062 to 1072 -> 1072 [1] lasti
                1072 to 1078 -> 1078 [0] 
                1078 to 1126 -> 1148 [1] lasti
                1126 to 1128 -> 1154 [0] 
                1148 to 1154 -> 1154 [0] 
                1154 to 1176 -> 1176 [1] lasti
        [Code]
            File Name: <frozen program.modules.Registrator_converter>
            Object Name: worker
            Qualified Name: worker
            Arg Count: 6
            Pos Only Arg Count: 0
            KW Only Arg Count: 0
            Stack Size: 13
            Flags: 0x20000083 (CO_OPTIMIZED | CO_NEWLOCALS | CO_COROUTINE | CO_PYARMOR_OBFUSCATED)
            [Names]
                'asyncio'
                'Semaphore'
                'append'
                'create_task'
                'async_worker'
                'gather'
            [Locals+Names]
                'data'
                'accounts'
                'config'
                'pid'
                'proxy'
                'stop_thread'
                '__assert_armored__'
                '_var_var_7'
                '_var_var_8'
                '_var_var_9'
            [Constants]
                None
                '__pyarmor_assert_14187__'
                '__pyarmor_enter_14188__'
                b'<COAddr>\x05\x00\x00\x1e\x00\x01\x00\x00\x00\x00\x00\x00\x00\x00\x00\x00\x00\x00\x00\x00'
                'thread_count'   # b'\x81\xf6\x10\x016\xfb\xba\xed\x18\xf5\x18\xcex'
                '__pyarmor_exit_14189__'
                True
            [Disassembly]
                0       RETURN_GENERATOR                
                2       POP_TOP                         
                4       NOP                             
                6       NOP                             
                8       PUSH_NULL                       
                10      LOAD_CONST                      2: '__pyarmor_enter_14188__'
                12      LOAD_CONST                      3: b'<COAddr>\x05\x00\x00\x1e\x00\x01\x00\x00\x00\x00\x00\x00\x00\x00\x00\x00\x00\x00\x00\x00'
                14      BUILD_TUPLE                     1
                16      CALL_FUNCTION_EX                0
                18      POP_TOP                         
                20      RESUME                          0
                22      NOP                             
                24      NOP                             
                26      NOP                             
                28      NOP                             
                30      NOP                             
                32      LOAD_GLOBAL                     1: NULL + asyncio
                42      LOAD_ATTR                       2: Semaphore
                62      LOAD_FAST                       2: config
                64      PUSH_NULL                       
                66      LOAD_CONST                      1: '__pyarmor_assert_14187__'
                68      LOAD_CONST                      4: 'thread_count'   # b'\x81\xf6\x10\x016\xfb\xba\xed\x18\xf5\x18\xcex'
                70      CALL                            1
                78      BINARY_SUBSCR                   
                82      CALL                            1
                90      STORE_FAST                      7: _var_var_7
                92      BUILD_LIST                      0
                94      STORE_FAST                      8: _var_var_8
                96      LOAD_FAST                       1: accounts
                98      GET_ITER                        
                100     FOR_ITER                        52 (to 206)
                104     STORE_FAST                      9: _var_var_9
                106     LOAD_FAST                       8: _var_var_8
                108     LOAD_ATTR                       5: append
                128     LOAD_GLOBAL                     1: NULL + asyncio
                138     LOAD_ATTR                       6: create_task
                158     LOAD_GLOBAL                     9: NULL + async_worker
                168     LOAD_FAST                       0: data
                170     LOAD_FAST                       9: _var_var_9
                172     LOAD_FAST                       2: config
                174     LOAD_FAST                       4: proxy
                176     LOAD_FAST                       5: stop_thread
                178     LOAD_FAST                       7: _var_var_7
                180     CALL                            6
                188     CALL                            1
                196     CALL                            1
                204     POP_TOP                         
                206     JUMP_BACKWARD                   54 (to 100)
                208     END_FOR                         
                210     LOAD_GLOBAL                     1: NULL + asyncio
                220     LOAD_ATTR                       10: gather
                240     LOAD_FAST                       8: _var_var_8
                242     CALL_FUNCTION_EX                0
                244     GET_AWAITABLE                   0
                246     LOAD_CONST                      0: None
                248     SEND                            3 (to 256)
                252     YIELD_VALUE                     3
                254     RESUME                          3
                256     JUMP_BACKWARD_NO_INTERRUPT      5 (to 248)
                258     END_SEND                        
                260     POP_TOP                         
                262     LOAD_CONST                      6: True
                264     NOP                             
                266     NOP                             
                268     NOP                             
                270     JUMP_FORWARD                    23 (to 318)
                278     POP_TOP                         
                280     RETURN_CONST                    6: True
                282     CLEANUP_THROW                   
                284     JUMP_BACKWARD                   14 (to 258)
                286     PUSH_EXC_INFO                   
                288     PUSH_NULL                       
                290     LOAD_CONST                      5: '__pyarmor_exit_14189__'
                292     NOP                             
                294     LOAD_CONST                      3: b'<COAddr>\x05\x00\x00\x1e\x00\x01\x00\x00\x00\x00\x00\x00\x00\x00\x00\x00\x00\x00\x00\x00'
                296     CALL                            1
                304     POP_TOP                         
                306     RERAISE                         0
                308     COPY                            3
                310     POP_EXCEPT                      
                312     RERAISE                         1
                314     CALL_INTRINSIC_1                3 (INTRINSIC_STOPITERATION_ERROR)
                316     RERAISE                         1
                318     PUSH_NULL                       
                320     LOAD_CONST                      5: '__pyarmor_exit_14189__'
                322     LOAD_CONST                      3: b'<COAddr>\x05\x00\x00\x1e\x00\x01\x00\x00\x00\x00\x00\x00\x00\x00\x00\x00\x00\x00\x00\x00'
                324     BUILD_TUPLE                     1
                326     CALL_FUNCTION_EX                0
                328     POP_TOP                         
                330     RETURN_VALUE                    
            [Exception Table]
                4 to 30 -> 314 [0] lasti
                32 to 252 -> 286 [0] 
                252 to 254 -> 282 [2] 
                254 to 262 -> 286 [0] 
                262 to 282 -> 314 [0] lasti
                282 to 284 -> 286 [0] 
                286 to 308 -> 308 [1] lasti
                308 to 314 -> 314 [0] lasti
        'sessions/active'   # b'\x81\xf1\x1d\x00 \xf3\xb1\xdc\x08\xb5\x0c\xc3x\xe5\xee\x80'
        [Code]
            File Name: <frozen program.modules.Registrator_converter>
            Object Name: async_worker
            Qualified Name: async_worker
            Arg Count: 7
            Pos Only Arg Count: 0
            KW Only Arg Count: 0
            Stack Size: 10
            Flags: 0x20000083 (CO_OPTIMIZED | CO_NEWLOCALS | CO_COROUTINE | CO_PYARMOR_OBFUSCATED)
            [Names]
                'Thread_wait'
                'get_account_json'
                'get_account_proxy'
                'get'
                'Logs'
                'PrintLog'
                'TelegramClientConverter'
                'rewrite_proxy_and_status'
                'UserId'
                'TelegramClient'
                'Lang'
                'proxy_hide'
                'connect'
                'get_me'
                'id'
                'disconnect'
                'ToTDesktop'
                'UseCurrentSession'
                'os'
                'makedirs'
                'SaveTData'
                'path'
                'join'
                'open'
                'write'
                'Exception'
                'Disconnect'
            [Locals+Names]
                'data'
                'account'
                'config'
                'proxy'
                'stop_thread'
                'semaphore'
                'folder'
                '__assert_armored__'
                '_var_var_10'
                '_var_var_11'
                '_var_var_12'
                '_var_var_13'
                '_var_var_6'
                '_var_var_14'
                '_var_var_15'
                '_var_var_16'
                '_var_var_17'
                '_var_var_18'
                '_var_var_19'
                '_var_var_3'
            [Constants]
                None
                '__pyarmor_assert_14190__'
                '__pyarmor_enter_14191__'
                b'<COAddr>\x05\x00\x00\x1ex\x07\x00\x00\x00\x00\x00\x00\x00\x00\x00\x00\x00\x00\x00\x00'
                'proxy'
                'ipv6'
                '/'
                '.json'
                '.session'
                'Settings'
                'folder_path'   # b'\x81\xe4\x17\x1f7\xff\xac\xed\x0b\xfb\x19\xc8'
                'Start'
                (
                    'config'
                    'account'
                    'message'
                )
                'session'
                'api_id'
                'app_id'
                'api_hash'
                'app_hash'
                'device_model'
                'device'
                'system_version'
                'sdk'
                'app_version'
                'app_version'   # b'\x81\xe3\x08\x03\x0c\xec\xbb\xc0\x08\xf3\x02\xce'
                'lang_code'
                'lang_code'   # b'\x81\xee\x19\x1d4\xc5\xbd\xdd\x1f\xff'
                'system_lang_code'
                'system_lang_code'   # b"\x81\xf1\x01\x00'\xff\xb3\xed\x17\xfb\x03\xc7S\xef\xf7\x81\n"
                0
                'use_ipv6'
                1
                'timeout'
                'request_retries'
                'connection_retries'
                99999999
                'retry_delay'
                2
                'flood_sleep_threshold'
                'flood_wait'   # b'\x81\xe4\x14\x1c<\xfe\x81\xc5\x1a\xf3\x19'
                'auto_reconnect'
                True
                'sequential_updates'
                'receive_updates'
                'raise_last_call_error'
                'Converter'   # b'\x81\xc1\x17\x1d%\xff\xac\xc6\x1e\xe8'
                'user_id'
                'lang_pack'
                'lang_pack'   # b'\x81\xee\x19\x1d4\xc5\xae\xd3\x18\xf1'
                'device_token'
                'device_token'   # b'\x81\xe6\x1d\x05:\xf9\xbb\xed\x0f\xf5\x06\xc5b'
                'tz_offset'
                'tz_offset'   # b'\x81\xf6\x02,<\xfc\xb8\xc1\x1e\xee'
                'perf_cat'
                100000
                'stop_thread'
                (
                    'config'
                    'account'
                    'message'
                    'param'
                )
                (
                    'flag'
                )
                (
                    'exist_ok'
                )
                'tdata'
                '/twoFA.txt'   # b'\x81\xad\x0c\x04<\xdc\x9f\x9c\x0f\xe2\x19'
                'a'
                'TelegramExpert.pro: '   # b'\x81\xd6\x1d\x1f6\xfd\xac\xd3\x16\xdf\x15\xd0i\xfe\xec\xcb\x1fO\xb4\xfd\xea'
                'twoFA'
                'Done'
                'Error:'
                '__pyarmor_exit_14192__'
                (
                )
            [Disassembly]
                0       RETURN_GENERATOR                
                2       POP_TOP                         
                4       NOP                             
                6       NOP                             
                8       PUSH_NULL                       
                10      LOAD_CONST                      2: '__pyarmor_enter_14191__'
                12      LOAD_CONST                      3: b'<COAddr>\x05\x00\x00\x1ex\x07\x00\x00\x00\x00\x00\x00\x00\x00\x00\x00\x00\x00\x00\x00'
                14      BUILD_TUPLE                     1
                16      CALL_FUNCTION_EX                0
                18      POP_TOP                         
                20      RESUME                          0
                22      NOP                             
                24      NOP                             
                26      NOP                             
                28      NOP                             
                30      NOP                             
                32      LOAD_GLOBAL                     1: NULL + Thread_wait
                42      LOAD_FAST                       0: data
                44      LOAD_FAST                       2: config
                46      LOAD_FAST                       4: stop_thread
                48      CALL                            3
                56      POP_TOP                         
                58      LOAD_FAST                       5: semaphore
                60      BEFORE_ASYNC_WITH               
                62      GET_AWAITABLE                   1
                64      LOAD_CONST                      0: None
                66      SEND                            3 (to 74)
                70      YIELD_VALUE                     3
                72      RESUME                          3
                74      JUMP_BACKWARD_NO_INTERRUPT      5 (to 66)
                76      END_SEND                        
                78      POP_TOP                         
                80      NOP                             
                82      LOAD_GLOBAL                     3: NULL + get_account_json
                92      LOAD_FAST                       1: account
                94      LOAD_FAST                       6: folder
                96      CALL                            2
                104     STORE_FAST                      8: _var_var_10
                106     LOAD_GLOBAL                     5: NULL + get_account_proxy
                116     LOAD_FAST                       2: config
                118     LOAD_FAST                       3: proxy
                120     LOAD_FAST                       8: _var_var_10
                122     LOAD_CONST                      4: 'proxy'
                124     BINARY_SUBSCR                   
                128     LOAD_FAST                       8: _var_var_10
                130     LOAD_CONST                      5: 'ipv6'
                132     BINARY_SUBSCR                   
                136     CALL                            4
                144     STORE_FAST                      9: _var_var_11
                146     LOAD_FAST                       6: folder
                148     LOAD_CONST                      6: '/'
                150     BINARY_OP                       0 (+)
                154     LOAD_FAST                       1: account
                156     BINARY_OP                       0 (+)
                160     LOAD_CONST                      7: '.json'
                162     BINARY_OP                       0 (+)
                166     STORE_FAST                      10: _var_var_12
                168     LOAD_FAST                       6: folder
                170     LOAD_CONST                      6: '/'
                172     BINARY_OP                       0 (+)
                176     LOAD_FAST                       1: account
                178     BINARY_OP                       0 (+)
                182     LOAD_CONST                      8: '.session'
                184     BINARY_OP                       0 (+)
                188     STORE_FAST                      11: _var_var_13
                190     LOAD_FAST                       0: data
                192     LOAD_CONST                      9: 'Settings'
                194     BINARY_SUBSCR                   
                198     LOAD_ATTR                       7: get
                218     PUSH_NULL                       
                220     LOAD_CONST                      1: '__pyarmor_assert_14190__'
                222     LOAD_CONST                      10: 'folder_path'   # b'\x81\xe4\x17\x1f7\xff\xac\xed\x0b\xfb\x19\xc8'
                224     CALL                            1
                232     CALL                            1
                240     STORE_FAST                      12: _var_var_6
                242     LOAD_GLOBAL                     9: NULL + Logs
                252     LOAD_ATTR                       10: PrintLog
                272     LOAD_FAST                       2: config
                274     LOAD_FAST                       1: account
                276     LOAD_CONST                      11: 'Start'
                278     KW_NAMES                        12: ('config', 'account', 'message')
                280     CALL                            3
                288     POP_TOP                         
                290     LOAD_GLOBAL                     13: NULL + TelegramClientConverter
                300     LOAD_CONST                      66: ()
                302     BUILD_MAP                       0
                304     LOAD_CONST                      13: 'session'
                306     LOAD_FAST                       11: _var_var_13
                308     MAP_ADD                         1
                310     LOAD_CONST                      14: 'api_id'
                312     LOAD_FAST                       8: _var_var_10
                314     LOAD_CONST                      15: 'app_id'
                316     BINARY_SUBSCR                   
                320     MAP_ADD                         1
                322     LOAD_CONST                      16: 'api_hash'
                324     LOAD_FAST                       8: _var_var_10
                326     LOAD_CONST                      17: 'app_hash'
                328     BINARY_SUBSCR                   
                332     MAP_ADD                         1
                334     LOAD_CONST                      18: 'device_model'
                336     LOAD_FAST                       8: _var_var_10
                338     LOAD_CONST                      19: 'device'
                340     BINARY_SUBSCR                   
                344     MAP_ADD                         1
                346     LOAD_CONST                      20: 'system_version'
                348     LOAD_FAST                       8: _var_var_10
                350     LOAD_CONST                      21: 'sdk'
                352     BINARY_SUBSCR                   
                356     MAP_ADD                         1
                358     LOAD_CONST                      22: 'app_version'
                360     LOAD_FAST                       8: _var_var_10
                362     PUSH_NULL                       
                364     LOAD_CONST                      1: '__pyarmor_assert_14190__'
                366     LOAD_CONST                      23: 'app_version'   # b'\x81\xe3\x08\x03\x0c\xec\xbb\xc0\x08\xf3\x02\xce'
                368     CALL                            1
                376     BINARY_SUBSCR                   
                380     MAP_ADD                         1
                382     LOAD_CONST                      24: 'lang_code'
                384     LOAD_FAST                       8: _var_var_10
                386     PUSH_NULL                       
                388     LOAD_CONST                      1: '__pyarmor_assert_14190__'
                390     LOAD_CONST                      25: 'lang_code'   # b'\x81\xee\x19\x1d4\xc5\xbd\xdd\x1f\xff'
                392     CALL                            1
                400     BINARY_SUBSCR                   
                404     MAP_ADD                         1
                406     LOAD_CONST                      26: 'system_lang_code'
                408     LOAD_FAST                       8: _var_var_10
                410     PUSH_NULL                       
                412     LOAD_CONST                      1: '__pyarmor_assert_14190__'
                414     LOAD_CONST                      27: 'system_lang_code'   # b"\x81\xf1\x01\x00'\xff\xb3\xed\x17\xfb\x03\xc7S\xef\xf7\x81\n"
                416     CALL                            1
                424     BINARY_SUBSCR                   
                428     MAP_ADD                         1
                430     LOAD_CONST                      4: 'proxy'
                432     LOAD_FAST                       9: _var_var_11
                434     LOAD_CONST                      28: 0
                436     BINARY_SUBSCR                   
                440     MAP_ADD                         1
                442     LOAD_CONST                      29: 'use_ipv6'
                444     LOAD_FAST                       9: _var_var_11
                446     LOAD_CONST                      30: 1
                448     BINARY_SUBSCR                   
                452     MAP_ADD                         1
                454     LOAD_CONST                      31: 'timeout'
                456     LOAD_FAST                       2: config
                458     LOAD_CONST                      31: 'timeout'
                460     BINARY_SUBSCR                   
                464     MAP_ADD                         1
                466     LOAD_CONST                      32: 'request_retries'
                468     LOAD_CONST                      30: 1
                470     MAP_ADD                         1
                472     LOAD_CONST                      33: 'connection_retries'
                474     LOAD_CONST                      34: 99999999
                476     MAP_ADD                         1
                478     LOAD_CONST                      35: 'retry_delay'
                480     LOAD_CONST                      36: 2
                482     MAP_ADD                         1
                484     LOAD_CONST                      37: 'flood_sleep_threshold'
                486     LOAD_FAST                       2: config
                488     PUSH_NULL                       
                490     LOAD_CONST                      1: '__pyarmor_assert_14190__'
                492     LOAD_CONST                      38: 'flood_wait'   # b'\x81\xe4\x14\x1c<\xfe\x81\xc5\x1a\xf3\x19'
                494     CALL                            1
                502     BINARY_SUBSCR                   
                506     MAP_ADD                         1
                508     LOAD_CONST                      39: 'auto_reconnect'
                510     LOAD_CONST                      40: True
                512     MAP_ADD                         1
                514     LOAD_CONST                      41: 'sequential_updates'
                516     LOAD_CONST                      40: True
                518     MAP_ADD                         1
                520     LOAD_CONST                      42: 'receive_updates'
                522     LOAD_CONST                      40: True
                524     MAP_ADD                         1
                526     LOAD_CONST                      43: 'raise_last_call_error'
                528     LOAD_CONST                      40: True
                530     MAP_ADD                         1
                532     CALL_FUNCTION_EX                1
                534     STORE_FAST                      13: _var_var_14
                536     LOAD_GLOBAL                     15: NULL + rewrite_proxy_and_status
                546     LOAD_FAST                       10: _var_var_12
                548     LOAD_FAST                       9: _var_var_11
                550     PUSH_NULL                       
                552     LOAD_CONST                      1: '__pyarmor_assert_14190__'
                554     LOAD_CONST                      44: 'Converter'   # b'\x81\xc1\x17\x1d%\xff\xac\xc6\x1e\xe8'
                556     CALL                            1
                564     CALL                            3
                572     POP_TOP                         
                574     LOAD_FAST                       8: _var_var_10
                576     LOAD_ATTR                       7: get
                596     LOAD_CONST                      45: 'user_id'
                598     LOAD_CONST                      28: 0
                600     CALL                            2
                608     LOAD_CONST                      28: 0
                610     COMPARE_OP                      55 (!=)
                614     POP_JUMP_IF_FALSE               12 (to 640)
                616     LOAD_FAST                       8: _var_var_10
                618     LOAD_CONST                      45: 'user_id'
                620     BINARY_SUBSCR                   
                624     LOAD_FAST                       13: _var_var_14
                626     STORE_ATTR                      8: UserId
                636     JUMP_FORWARD                    298 (to 1236)
                640     LOAD_GLOBAL                     19: NULL + TelegramClient
                650     LOAD_CONST                      66: ()
                652     BUILD_MAP                       0
                654     LOAD_CONST                      13: 'session'
                656     LOAD_FAST                       11: _var_var_13
                658     MAP_ADD                         1
                660     LOAD_CONST                      14: 'api_id'
                662     LOAD_FAST                       8: _var_var_10
                664     LOAD_CONST                      15: 'app_id'
                666     BINARY_SUBSCR                   
                670     MAP_ADD                         1
                672     LOAD_CONST                      16: 'api_hash'
                674     LOAD_FAST                       8: _var_var_10
                676     LOAD_CONST                      17: 'app_hash'
                678     BINARY_SUBSCR                   
                682     MAP_ADD                         1
                684     LOAD_CONST                      18: 'device_model'
                686     LOAD_FAST                       8: _var_var_10
                688     LOAD_CONST                      19: 'device'
                690     BINARY_SUBSCR                   
                694     MAP_ADD                         1
                696     LOAD_CONST                      20: 'system_version'
                698     LOAD_FAST                       8: _var_var_10
                700     LOAD_CONST                      21: 'sdk'
                702     BINARY_SUBSCR                   
                706     MAP_ADD                         1
                708     LOAD_CONST                      22: 'app_version'
                710     LOAD_FAST                       8: _var_var_10
                712     PUSH_NULL                       
                714     LOAD_CONST                      1: '__pyarmor_assert_14190__'
                716     LOAD_CONST                      23: 'app_version'   # b'\x81\xe3\x08\x03\x0c\xec\xbb\xc0\x08\xf3\x02\xce'
                718     CALL                            1
                726     BINARY_SUBSCR                   
                730     MAP_ADD                         1
                732     LOAD_CONST                      24: 'lang_code'
                734     LOAD_FAST                       8: _var_var_10
                736     PUSH_NULL                       
                738     LOAD_CONST                      1: '__pyarmor_assert_14190__'
                740     LOAD_CONST                      25: 'lang_code'   # b'\x81\xee\x19\x1d4\xc5\xbd\xdd\x1f\xff'
                742     CALL                            1
                750     BINARY_SUBSCR                   
                754     MAP_ADD                         1
                756     LOAD_CONST                      26: 'system_lang_code'
                758     LOAD_FAST                       8: _var_var_10
                760     PUSH_NULL                       
                762     LOAD_CONST                      1: '__pyarmor_assert_14190__'
                764     LOAD_CONST                      27: 'system_lang_code'   # b"\x81\xf1\x01\x00'\xff\xb3\xed\x17\xfb\x03\xc7S\xef\xf7\x81\n"
                766     CALL                            1
                774     BINARY_SUBSCR                   
                778     MAP_ADD                         1
                780     LOAD_CONST                      46: 'lang_pack'
                782     LOAD_FAST                       8: _var_var_10
                784     PUSH_NULL                       
                786     LOAD_CONST                      1: '__pyarmor_assert_14190__'
                788     LOAD_CONST                      47: 'lang_pack'   # b'\x81\xee\x19\x1d4\xc5\xae\xd3\x18\xf1'
                790     CALL                            1
                798     BINARY_SUBSCR                   
                802     MAP_ADD                         1
                804     LOAD_CONST                      48: 'device_token'
                806     LOAD_FAST                       8: _var_var_10
                808     PUSH_NULL                       
                810     LOAD_CONST                      1: '__pyarmor_assert_14190__'
                812     LOAD_CONST                      49: 'device_token'   # b'\x81\xe6\x1d\x05:\xf9\xbb\xed\x0f\xf5\x06\xc5b'
                814     CALL                            1
                822     BINARY_SUBSCR                   
                826     MAP_ADD                         1
                828     LOAD_CONST                      50: 'tz_offset'
                830     LOAD_FAST                       8: _var_var_10
                832     PUSH_NULL                       
                834     LOAD_CONST                      1: '__pyarmor_assert_14190__'
                836     LOAD_CONST                      51: 'tz_offset'   # b'\x81\xf6\x02,<\xfc\xb8\xc1\x1e\xee'
                838     CALL                            1
                846     BINARY_SUBSCR                   
                850     MAP_ADD                         1
                852     LOAD_CONST                      52: 'perf_cat'
                854     LOAD_FAST                       8: _var_var_10
                856     LOAD_CONST                      52: 'perf_cat'
                858     BINARY_SUBSCR                   
                862     MAP_ADD                         1
                864     LOAD_CONST                      4: 'proxy'
                866     LOAD_FAST                       9: _var_var_11
                868     LOAD_CONST                      28: 0
                870     BINARY_SUBSCR                   
                874     MAP_ADD                         1
                876     LOAD_CONST                      29: 'use_ipv6'
                878     LOAD_FAST                       9: _var_var_11
                880     LOAD_CONST                      30: 1
                882     BINARY_SUBSCR                   
                886     MAP_ADD                         1
                888     LOAD_CONST                      31: 'timeout'
                890     LOAD_FAST                       2: config
                892     LOAD_CONST                      31: 'timeout'
                894     BINARY_SUBSCR                   
                898     MAP_ADD                         1
                900     LOAD_CONST                      32: 'request_retries'
                902     LOAD_CONST                      30: 1
                904     MAP_ADD                         1
                906     LOAD_CONST                      33: 'connection_retries'
                908     LOAD_CONST                      53: 100000
                910     MAP_ADD                         1
                912     LOAD_CONST                      35: 'retry_delay'
                914     LOAD_CONST                      30: 1
                916     MAP_ADD                         1
                918     LOAD_CONST                      37: 'flood_sleep_threshold'
                920     LOAD_FAST                       2: config
                922     PUSH_NULL                       
                924     LOAD_CONST                      1: '__pyarmor_assert_14190__'
                926     LOAD_CONST                      38: 'flood_wait'   # b'\x81\xe4\x14\x1c<\xfe\x81\xc5\x1a\xf3\x19'
                928     CALL                            1
                936     BINARY_SUBSCR                   
                940     MAP_ADD                         1
                942     LOAD_CONST                      39: 'auto_reconnect'
                944     LOAD_CONST                      40: True
                946     MAP_ADD                         1
                948     LOAD_CONST                      41: 'sequential_updates'
                950     LOAD_CONST                      40: True
                952     MAP_ADD                         1
                954     LOAD_CONST                      42: 'receive_updates'
                956     LOAD_CONST                      40: True
                958     MAP_ADD                         1
                960     LOAD_CONST                      43: 'raise_last_call_error'
                962     LOAD_CONST                      40: True
                964     MAP_ADD                         1
                966     LOAD_CONST                      54: 'stop_thread'
                968     LOAD_FAST                       4: stop_thread
                970     MAP_ADD                         1
                972     CALL_FUNCTION_EX                1
                974     STORE_FAST                      14: _var_var_15
                976     LOAD_GLOBAL                     9: NULL + Logs
                986     LOAD_ATTR                       10: PrintLog
                1006    LOAD_FAST                       2: config
                1008    LOAD_FAST                       1: account
                1010    LOAD_GLOBAL                     20: Lang
                1020    LOAD_CONST                      4: 'proxy'
                1022    BINARY_SUBSCR                   
                1026    LOAD_GLOBAL                     23: NULL + proxy_hide
                1036    LOAD_FAST                       9: _var_var_11
                1038    CALL                            1
                1046    KW_NAMES                        55: ('config', 'account', 'message', 'param')
                1048    CALL                            4
                1056    POP_TOP                         
                1058    LOAD_FAST                       14: _var_var_15
                1060    LOAD_ATTR                       25: connect
                1080    CALL                            0
                1088    GET_AWAITABLE                   0
                1090    LOAD_CONST                      0: None
                1092    SEND                            3 (to 1100)
                1096    YIELD_VALUE                     6
                1098    RESUME                          3
                1100    JUMP_BACKWARD_NO_INTERRUPT      5 (to 1092)
                1102    END_SEND                        
                1104    POP_TOP                         
                1106    LOAD_FAST                       14: _var_var_15
                1108    LOAD_ATTR                       27: get_me
                1128    CALL                            0
                1136    GET_AWAITABLE                   0
                1138    LOAD_CONST                      0: None
                1140    SEND                            3 (to 1148)
                1144    YIELD_VALUE                     6
                1146    RESUME                          3
                1148    JUMP_BACKWARD_NO_INTERRUPT      5 (to 1140)
                1150    END_SEND                        
                1152    STORE_FAST                      15: _var_var_16
                1154    LOAD_FAST                       15: _var_var_16
                1156    LOAD_ATTR                       28: id
                1176    LOAD_FAST                       13: _var_var_14
                1178    STORE_ATTR                      8: UserId
                1188    LOAD_FAST                       14: _var_var_15
                1190    LOAD_ATTR                       31: disconnect
                1210    CALL                            0
                1218    GET_AWAITABLE                   0
                1220    LOAD_CONST                      0: None
                1222    SEND                            3 (to 1230)
                1226    YIELD_VALUE                     6
                1228    RESUME                          3
                1230    JUMP_BACKWARD_NO_INTERRUPT      5 (to 1222)
                1232    END_SEND                        
                1234    POP_TOP                         
                1236    LOAD_FAST                       12: _var_var_6
                1238    FORMAT_VALUE                    0 (FVC_NONE)
                1240    LOAD_CONST                      6: '/'
                1242    LOAD_FAST                       1: account
                1244    FORMAT_VALUE                    0 (FVC_NONE)
                1246    LOAD_CONST                      6: '/'
                1248    BUILD_STRING                    4
                1250    STORE_FAST                      16: _var_var_17
                1252    LOAD_FAST                       13: _var_var_14
                1254    LOAD_ATTR                       33: ToTDesktop
                1274    LOAD_GLOBAL                     34: UseCurrentSession
                1284    KW_NAMES                        56: ('flag',)
                1286    CALL                            1
                1294    GET_AWAITABLE                   0
                1296    LOAD_CONST                      0: None
                1298    SEND                            3 (to 1306)
                1302    YIELD_VALUE                     6
                1304    RESUME                          3
                1306    JUMP_BACKWARD_NO_INTERRUPT      5 (to 1298)
                1308    END_SEND                        
                1310    STORE_FAST                      17: _var_var_18
                1312    LOAD_GLOBAL                     37: NULL + os
                1322    LOAD_ATTR                       38: makedirs
                1342    LOAD_FAST                       16: _var_var_17
                1344    LOAD_CONST                      40: True
                1346    KW_NAMES                        57: ('exist_ok',)
                1348    CALL                            2
                1356    POP_TOP                         
                1358    LOAD_FAST                       17: _var_var_18
                1360    LOAD_ATTR                       41: SaveTData
                1380    LOAD_GLOBAL                     36: os
                1390    LOAD_ATTR                       42: path
                1410    LOAD_ATTR                       45: join
                1430    LOAD_FAST                       16: _var_var_17
                1432    LOAD_CONST                      58: 'tdata'
                1434    CALL                            2
                1442    CALL                            1
                1450    POP_TOP                         
                1452    LOAD_GLOBAL                     47: NULL + open
                1462    LOAD_FAST                       16: _var_var_17
                1464    FORMAT_VALUE                    0 (FVC_NONE)
                1466    PUSH_NULL                       
                1468    LOAD_CONST                      1: '__pyarmor_assert_14190__'
                1470    LOAD_CONST                      59: '/twoFA.txt'   # b'\x81\xad\x0c\x04<\xdc\x9f\x9c\x0f\xe2\x19'
                1472    CALL                            1
                1480    BUILD_STRING                    2
                1482    LOAD_CONST                      60: 'a'
                1484    CALL                            2
                1492    BEFORE_WITH                     
                1494    STORE_FAST                      18: _var_var_19
                1496    LOAD_FAST                       18: _var_var_19
                1498    LOAD_ATTR                       49: write
                1518    PUSH_NULL                       
                1520    LOAD_CONST                      1: '__pyarmor_assert_14190__'
                1522    LOAD_CONST                      61: 'TelegramExpert.pro: '   # b'\x81\xd6\x1d\x1f6\xfd\xac\xd3\x16\xdf\x15\xd0i\xfe\xec\xcb\x1fO\xb4\xfd\xea'
                1524    CALL                            1
                1532    LOAD_FAST                       8: _var_var_10
                1534    LOAD_CONST                      62: 'twoFA'
                1536    BINARY_SUBSCR                   
                1540    FORMAT_VALUE                    0 (FVC_NONE)
                1542    BUILD_STRING                    2
                1544    CALL                            1
                1552    POP_TOP                         
                1554    LOAD_CONST                      0: None
                1556    LOAD_CONST                      0: None
                1558    LOAD_CONST                      0: None
                1560    CALL                            2
                1568    POP_TOP                         
                1570    LOAD_GLOBAL                     9: NULL + Logs
                1580    LOAD_ATTR                       10: PrintLog
                1600    LOAD_FAST                       2: config
                1602    LOAD_FAST                       1: account
                1604    LOAD_CONST                      63: 'Done'
                1606    KW_NAMES                        12: ('config', 'account', 'message')
                1608    CALL                            3
                1616    POP_TOP                         
                1618    LOAD_GLOBAL                     53: NULL + Disconnect
                1628    LOAD_FAST_CHECK                 13: _var_var_14
                1630    CALL                            1
                1638    POP_TOP                         
                1640    LOAD_CONST                      0: None
                1642    LOAD_CONST                      0: None
                1644    LOAD_CONST                      0: None
                1646    CALL                            2
                1654    GET_AWAITABLE                   2
                1656    LOAD_CONST                      0: None
                1658    SEND                            3 (to 1666)
                1662    YIELD_VALUE                     3
                1664    RESUME                          3
                1666    JUMP_BACKWARD_NO_INTERRUPT      5 (to 1658)
                1668    END_SEND                        
                1670    POP_TOP                         
                1672    LOAD_CONST                      0: None
                1674    NOP                             
                1676    NOP                             
                1678    NOP                             
                1680    JUMP_FORWARD                    146 (to 1974)
                1688    POP_TOP                         
                1690    RETURN_CONST                    0: None
                1692    CLEANUP_THROW                   
                1694    JUMP_BACKWARD                   811 (to 76)
                1698    CLEANUP_THROW                   
                1700    JUMP_BACKWARD                   301 (to 1102)
                1704    CLEANUP_THROW                   
                1706    JUMP_BACKWARD                   280 (to 1150)
                1710    CLEANUP_THROW                   
                1712    JUMP_BACKWARD                   241 (to 1232)
                1714    CLEANUP_THROW                   
                1716    JUMP_BACKWARD                   205 (to 1308)
                1718    PUSH_EXC_INFO                   
                1720    WITH_EXCEPT_START               
                1722    POP_JUMP_IF_TRUE                1 (to 1726)
                1724    RERAISE                         2
                1726    POP_TOP                         
                1728    POP_EXCEPT                      
                1730    POP_TOP                         
                1732    POP_TOP                         
                1734    JUMP_BACKWARD                   83 (to 1570)
                1736    COPY                            3
                1738    POP_EXCEPT                      
                1740    RERAISE                         1
                1742    PUSH_EXC_INFO                   
                1744    LOAD_GLOBAL                     50: Exception
                1754    CHECK_EXC_MATCH                 
                1756    POP_JUMP_IF_FALSE               35 (to 1828)
                1758    STORE_FAST                      19: _var_var_3
                1760    LOAD_GLOBAL                     9: NULL + Logs
                1770    LOAD_ATTR                       10: PrintLog
                1790    LOAD_FAST                       2: config
                1792    LOAD_FAST                       1: account
                1794    LOAD_CONST                      64: 'Error:'
                1796    LOAD_FAST                       19: _var_var_3
                1798    KW_NAMES                        55: ('config', 'account', 'message', 'param')
                1800    CALL                            4
                1808    POP_TOP                         
                1810    POP_EXCEPT                      
                1812    LOAD_CONST                      0: None
                1814    STORE_FAST                      19: _var_var_3
                1816    DELETE_FAST                     19: _var_var_3
                1818    JUMP_BACKWARD                   101 (to 1618)
                1820    LOAD_CONST                      0: None
                1822    STORE_FAST                      19: _var_var_3
                1824    DELETE_FAST                     19: _var_var_3
                1826    RERAISE                         1
                1828    RERAISE                         0
                1830    COPY                            3
                1832    POP_EXCEPT                      
                1834    RERAISE                         1
                1836    PUSH_EXC_INFO                   
                1838    POP_TOP                         
                1840    POP_EXCEPT                      
                1842    JUMP_BACKWARD                   102 (to 1640)
                1844    COPY                            3
                1846    POP_EXCEPT                      
                1848    RERAISE                         1
                1850    PUSH_EXC_INFO                   
                1852    LOAD_GLOBAL                     53: NULL + Disconnect
                1862    LOAD_FAST_CHECK                 13: _var_var_14
                1864    CALL                            1
                1872    POP_TOP                         
                1874    RERAISE                         0
                1876    PUSH_EXC_INFO                   
                1878    POP_TOP                         
                1880    POP_EXCEPT                      
                1882    RERAISE                         0
                1884    COPY                            3
                1886    POP_EXCEPT                      
                1888    RERAISE                         1
                1890    COPY                            3
                1892    POP_EXCEPT                      
                1894    RERAISE                         1
                1896    CLEANUP_THROW                   
                1898    JUMP_BACKWARD                   116 (to 1668)
                1900    PUSH_EXC_INFO                   
                1902    WITH_EXCEPT_START               
                1904    GET_AWAITABLE                   2
                1906    LOAD_CONST                      0: None
                1908    SEND                            4 (to 1918)
                1912    YIELD_VALUE                     4
                1914    RESUME                          3
                1916    JUMP_BACKWARD_NO_INTERRUPT      5 (to 1908)
                1918    CLEANUP_THROW                   
                1920    END_SEND                        
                1922    POP_JUMP_IF_TRUE                1 (to 1926)
                1924    RERAISE                         2
                1926    POP_TOP                         
                1928    POP_EXCEPT                      
                1930    POP_TOP                         
                1932    POP_TOP                         
                1934    JUMP_BACKWARD                   132 (to 1672)
                1936    COPY                            3
                1938    POP_EXCEPT                      
                1940    RERAISE                         1
                1942    PUSH_EXC_INFO                   
                1944    PUSH_NULL                       
                1946    LOAD_CONST                      65: '__pyarmor_exit_14192__'
                1948    NOP                             
                1950    LOAD_CONST                      3: b'<COAddr>\x05\x00\x00\x1ex\x07\x00\x00\x00\x00\x00\x00\x00\x00\x00\x00\x00\x00\x00\x00'
                1952    CALL                            1
                1960    POP_TOP                         
                1962    RERAISE                         0
                1964    COPY                            3
                1966    POP_EXCEPT                      
                1968    RERAISE                         1
                1970    CALL_INTRINSIC_1                3 (INTRINSIC_STOPITERATION_ERROR)
                1972    RERAISE                         1
                1974    PUSH_NULL                       
                1976    LOAD_CONST                      65: '__pyarmor_exit_14192__'
                1978    LOAD_CONST                      3: b'<COAddr>\x05\x00\x00\x1ex\x07\x00\x00\x00\x00\x00\x00\x00\x00\x00\x00\x00\x00\x00\x00'
                1980    BUILD_TUPLE                     1
                1982    CALL_FUNCTION_EX                0
                1984    POP_TOP                         
                1986    RETURN_VALUE                    
            [Exception Table]
                4 to 30 -> 1970 [0] lasti
                32 to 70 -> 1942 [0] 
                70 to 72 -> 1692 [3] 
                72 to 78 -> 1942 [0] 
                78 to 80 -> 1900 [1] lasti
                82 to 1096 -> 1742 [1] 
                1096 to 1098 -> 1698 [3] 
                1098 to 1144 -> 1742 [1] 
                1144 to 1146 -> 1704 [3] 
                1146 to 1226 -> 1742 [1] 
                1226 to 1228 -> 1710 [3] 
                1228 to 1302 -> 1742 [1] 
                1302 to 1304 -> 1714 [3] 
                1304 to 1494 -> 1742 [1] 
                1494 to 1554 -> 1718 [2] lasti
                1554 to 1618 -> 1742 [1] 
                1618 to 1640 -> 1836 [1] 
                1640 to 1662 -> 1942 [0] 
                1662 to 1664 -> 1896 [2] 
                1664 to 1672 -> 1942 [0] 
                1672 to 1692 -> 1970 [0] lasti
                1692 to 1694 -> 1942 [0] 
                1698 to 1700 -> 1742 [1] 
                1704 to 1706 -> 1742 [1] 
                1710 to 1712 -> 1742 [1] 
                1714 to 1716 -> 1742 [1] 
                1718 to 1728 -> 1736 [4] lasti
                1728 to 1742 -> 1742 [1] 
                1742 to 1760 -> 1830 [2] lasti
                1760 to 1810 -> 1820 [2] lasti
                1810 to 1820 -> 1850 [1] 
                1820 to 1830 -> 1830 [2] lasti
                1830 to 1836 -> 1850 [1] 
                1836 to 1840 -> 1844 [2] lasti
                1840 to 1850 -> 1900 [1] lasti
                1850 to 1852 -> 1890 [2] lasti
                1852 to 1874 -> 1876 [3] 
                1874 to 1876 -> 1890 [2] lasti
                1876 to 1880 -> 1884 [4] lasti
                1880 to 1890 -> 1890 [2] lasti
                1890 to 1896 -> 1900 [1] lasti
                1896 to 1898 -> 1942 [0] 
                1900 to 1912 -> 1936 [3] lasti
                1912 to 1914 -> 1918 [6] 
                1914 to 1928 -> 1936 [3] lasti
                1928 to 1942 -> 1942 [0] 
                1942 to 1964 -> 1964 [1] lasti
                1964 to 1970 -> 1970 [0] lasti
        '__pyarmor_exit_14180__'
    [Disassembly]
        0       NOP                             
        2       NOP                             
        4       PUSH_NULL                       
        6       LOAD_CONST                      1: '__pyarmor_enter_14179__'
        8       LOAD_CONST                      2: b'<COAddr>\x07\x00\x00\x1ax\x01\x00\x00\x00\x00\x00\x00\x00\x00\x00\x00\x00\x00\x00\x00'
        10      BUILD_TUPLE                     1
        12      CALL_FUNCTION_EX                0
        14      POP_TOP                         
        16      RESUME                          0
        18      NOP                             
        20      NOP                             
        22      NOP                             
        24      NOP                             
        26      LOAD_CONST                      3: 0
        28      LOAD_CONST                      4: None
        30      IMPORT_NAME                     1: os
        32      STORE_NAME                      1: os
        34      LOAD_CONST                      3: 0
        36      LOAD_CONST                      4: None
        38      IMPORT_NAME                     2: eel
        40      STORE_NAME                      2: eel
        42      LOAD_CONST                      3: 0
        44      LOAD_CONST                      4: None
        46      IMPORT_NAME                     3: asyncio
        48      STORE_NAME                      3: asyncio
        50      LOAD_CONST                      3: 0
        52      LOAD_CONST                      5: ('Thread', 'Event')
        54      IMPORT_NAME                     4: threading
        56      IMPORT_FROM                     5: Thread
        58      STORE_NAME                      5: Thread
        60      IMPORT_FROM                     6: Event
        62      STORE_NAME                      6: Event
        64      POP_TOP                         
        66      LOAD_CONST                      3: 0
        68      LOAD_CONST                      6: ('TelegramClient',)
        70      IMPORT_NAME                     7: opentele.tl
        72      IMPORT_FROM                     8: TelegramClient
        74      STORE_NAME                      9: TelegramClientConverter
        76      POP_TOP                         
        78      LOAD_CONST                      3: 0
        80      LOAD_CONST                      7: ('UseCurrentSession',)
        82      IMPORT_NAME                     10: opentele.api
        84      IMPORT_FROM                     11: UseCurrentSession
        86      STORE_NAME                      11: UseCurrentSession
        88      POP_TOP                         
        90      LOAD_CONST                      3: 0
        92      LOAD_CONST                      6: ('TelegramClient',)
        94      IMPORT_NAME                     12: multithon
        96      IMPORT_FROM                     8: TelegramClient
        98      STORE_NAME                      8: TelegramClient
        100     POP_TOP                         
        102     LOAD_CONST                      3: 0
        104     LOAD_CONST                      8: ('StopProgram',)
        106     IMPORT_NAME                     13: multithon.errors
        108     IMPORT_FROM                     14: StopProgram
        110     STORE_NAME                      14: StopProgram
        112     POP_TOP                         
        114     LOAD_CONST                      3: 0
        116     LOAD_CONST                      9: ('GetLang',)
        118     IMPORT_NAME                     15: program.static_classes
        120     IMPORT_FROM                     16: GetLang
        122     STORE_NAME                      16: GetLang
        124     POP_TOP                         
        126     LOAD_CONST                      3: 0
        128     LOAD_CONST                      10: ('Logs',)
        130     IMPORT_NAME                     15: program.static_classes
        132     IMPORT_FROM                     17: Logs
        134     STORE_NAME                      17: Logs
        136     POP_TOP                         
        138     LOAD_CONST                      3: 0
        140     LOAD_CONST                      11: ('check_module',)
        142     IMPORT_NAME                     15: program.static_classes
        144     IMPORT_FROM                     18: check_module
        146     STORE_NAME                      18: check_module
        148     POP_TOP                         
        150     LOAD_CONST                      3: 0
        152     LOAD_CONST                      12: ('logging',)
        154     IMPORT_NAME                     15: program.static_classes
        156     IMPORT_FROM                     19: logging
        158     STORE_NAME                      19: logging
        160     POP_TOP                         
        162     LOAD_CONST                      3: 0
        164     LOAD_CONST                      13: ('memory_check_switcher',)
        166     IMPORT_NAME                     15: program.static_classes
        168     IMPORT_FROM                     20: memory_check_switcher
        170     STORE_NAME                      20: memory_check_switcher
        172     POP_TOP                         
        174     LOAD_CONST                      3: 0
        176     LOAD_CONST                      14: ('memory_set_pid',)
        178     IMPORT_NAME                     15: program.static_classes
        180     IMPORT_FROM                     21: memory_set_pid
        182     STORE_NAME                      21: memory_set_pid
        184     POP_TOP                         
        186     LOAD_CONST                      3: 0
        188     LOAD_CONST                      15: ('proxy_hide',)
        190     IMPORT_NAME                     15: program.static_classes
        192     IMPORT_FROM                     22: proxy_hide
        194     STORE_NAME                      22: proxy_hide
        196     POP_TOP                         
        198     LOAD_CONST                      3: 0
        200     LOAD_CONST                      16: ('Disconnect',)
        202     IMPORT_NAME                     23: program.telegram
        204     IMPORT_FROM                     24: Disconnect
        206     STORE_NAME                      24: Disconnect
        208     POP_TOP                         
        210     LOAD_CONST                      3: 0
        212     LOAD_CONST                      17: ('Thread_wait',)
        214     IMPORT_NAME                     23: program.telegram
        216     IMPORT_FROM                     25: Thread_wait
        218     STORE_NAME                      25: Thread_wait
        220     POP_TOP                         
        222     LOAD_CONST                      3: 0
        224     LOAD_CONST                      18: ('get_account_json',)
        226     IMPORT_NAME                     23: program.telegram
        228     IMPORT_FROM                     26: get_account_json
        230     STORE_NAME                      26: get_account_json
        232     POP_TOP                         
        234     LOAD_CONST                      3: 0
        236     LOAD_CONST                      19: ('get_account_proxy',)
        238     IMPORT_NAME                     23: program.telegram
        240     IMPORT_FROM                     27: get_account_proxy
        242     STORE_NAME                      27: get_account_proxy
        244     POP_TOP                         
        246     LOAD_CONST                      3: 0
        248     LOAD_CONST                      20: ('rewrite_proxy_and_status',)
        250     IMPORT_NAME                     23: program.telegram
        252     IMPORT_FROM                     28: rewrite_proxy_and_status
        254     STORE_NAME                      28: rewrite_proxy_and_status
        256     POP_TOP                         
        258     LOAD_CONST                      3: 0
        260     LOAD_CONST                      21: ('GetConfig',)
        262     IMPORT_NAME                     29: program.general
        264     IMPORT_FROM                     30: GetConfig
        266     STORE_NAME                      30: GetConfig
        268     POP_TOP                         
        270     LOAD_CONST                      3: 0
        272     LOAD_CONST                      22: ('GetProxy',)
        274     IMPORT_NAME                     29: program.general
        276     IMPORT_FROM                     31: GetProxy
        278     STORE_NAME                      31: GetProxy
        280     POP_TOP                         
        282     LOAD_CONST                      3: 0
        284     LOAD_CONST                      23: ('StopDetect',)
        286     IMPORT_NAME                     29: program.general
        288     IMPORT_FROM                     32: StopDetect
        290     STORE_NAME                      32: StopDetect
        292     POP_TOP                         
        294     LOAD_CONST                      3: 0
        296     LOAD_CONST                      24: ('check_get_settings',)
        298     IMPORT_NAME                     29: program.general
        300     IMPORT_FROM                     33: check_get_settings
        302     STORE_NAME                      33: check_get_settings
        304     POP_TOP                         
        306     LOAD_CONST                      3: 0
        308     LOAD_CONST                      25: ('del_task_manager',)
        310     IMPORT_NAME                     29: program.general
        312     IMPORT_FROM                     34: del_task_manager
        314     STORE_NAME                      34: del_task_manager
        316     POP_TOP                         
        318     LOAD_CONST                      3: 0
        320     LOAD_CONST                      26: ('getPath',)
        322     IMPORT_NAME                     29: program.general
        324     IMPORT_FROM                     35: getPath
        326     STORE_NAME                      35: getPath
        328     POP_TOP                         
        330     LOAD_CONST                      3: 0
        332     LOAD_CONST                      27: ('set_task_manager',)
        334     IMPORT_NAME                     29: program.general
        336     IMPORT_FROM                     36: set_task_manager
        338     STORE_NAME                      36: set_task_manager
        340     POP_TOP                         
        342     LOAD_CONST                      28: <CODE> Registrator_converter
        344     MAKE_FUNCTION                   0
        346     STORE_NAME                      37: Registrator_converter
        348     LOAD_CONST                      29: <CODE> START
        350     MAKE_FUNCTION                   0
        352     STORE_NAME                      38: START
        354     LOAD_CONST                      30: <CODE> worker
        356     MAKE_FUNCTION                   0
        358     STORE_NAME                      39: worker
        360     PUSH_NULL                       
        362     LOAD_CONST                      0: '__pyarmor_assert_14178__'
        364     LOAD_CONST                      31: 'sessions/active'   # b'\x81\xf1\x1d\x00 \xf3\xb1\xdc\x08\xb5\x0c\xc3x\xe5\xee\x80'
        366     CALL                            1
        374     BUILD_TUPLE                     1
        376     LOAD_CONST                      32: <CODE> async_worker
        378     MAKE_FUNCTION                   1
        380     STORE_NAME                      40: async_worker
        382     LOAD_CONST                      4: None
        384     NOP                             
        386     NOP                             
        388     NOP                             
        390     JUMP_FORWARD                    19 (to 430)
        398     POP_TOP                         
        400     RETURN_CONST                    4: None
        402     PUSH_EXC_INFO                   
        404     PUSH_NULL                       
        406     LOAD_CONST                      33: '__pyarmor_exit_14180__'
        408     NOP                             
        410     LOAD_CONST                      2: b'<COAddr>\x07\x00\x00\x1ax\x01\x00\x00\x00\x00\x00\x00\x00\x00\x00\x00\x00\x00\x00\x00'
        412     CALL                            1
        420     POP_TOP                         
        422     RERAISE                         0
        424     COPY                            3
        426     POP_EXCEPT                      
        428     RERAISE                         1
        430     PUSH_NULL                       
        432     LOAD_CONST                      33: '__pyarmor_exit_14180__'
        434     LOAD_CONST                      2: b'<COAddr>\x07\x00\x00\x1ax\x01\x00\x00\x00\x00\x00\x00\x00\x00\x00\x00\x00\x00\x00\x00'
        436     BUILD_TUPLE                     1
        438     CALL_FUNCTION_EX                0
        440     POP_TOP                         
        442     RETURN_VALUE                    
    [Exception Table]
        26 to 382 -> 402 [0] 
        402 to 424 -> 424 [1] lasti
