#decoded by lolz.live/mrpenny / t.me/zeus_jackpot
# ================================
# Примечания по Pyarmor:
# - Байт-код и объекты кода Pyarmor соответствуют стандартному Python, но присутствуют специальные вызовы функций среды выполнения (runtime) Pyarmor.
# - Вызовы строк — это не ошибки, а маркеры, которые обрабатываются Pyarmor во время выполнения.
#
# Руководство по декомпиляции (без среды выполнения):
# 1. Игнорируйте зашифрованные байты после `#`; используйте только строку до `#`.
# 2. Удалите "__pyarmor_enter_xxx__"(b"<COAddr>...") и "__pyarmor_leave_xxx__"(b"<COAddr>...") (пролог/эпилог).
# 3. "__pyarmor_assert_xxx__"(A) не является настоящим оператором assert.
#    - Если A — это имя или читаемая строка: замените на A.
#    - Если A — это (X, "Y"): замените на X.Y.
#    - Если A — это (X, "Y", Z): замените на X.Y = Z.
#    - В противном случае: выберите наиболее подходящую/логичную замену.
# 4. "__pyarmor_bcc_xxx__"(...) указывает на машинный (нативный) код; тело функции недоступно. Добавьте комментарий.
# ================================

[Code]
    File Name: <frozen program.modules.Reporter>
    Object Name: <module>
    Qualified Name: <module>
    Arg Count: 0
    Pos Only Arg Count: 0
    KW Only Arg Count: 0
    Stack Size: 5
    Flags: 0x20000000 (CO_PYARMOR_OBFUSCATED)
    [Names]
        '__assert_armored__'
        'eel'
        'json'
        'random'
        'spintax'
        'concurrent.futures'
        'concurrent'
        'threading'
        'Thread'
        'Event'
        'multithon'
        'functions'
        'errors'
        'types'
        'multithon.errors'
        'StopProgram'
        'program.static_classes'
        'GetLang'
        'Logs'
        'check_module'
        'logging'
        'memory_check_switcher'
        'memory_set_pid'
        'program.telegram'
        'DelayOnline'
        'Disconnect'
        'Thread_wait'
        'account_works'
        'tg_links'
        'program.general'
        'GetConfig'
        'GetProxy'
        'StopDetect'
        'del_task_manager'
        'getFile'
        'getPath'
        'set_task_manager'
        'program.database'
        'db_reporter'
        'program.telegram.func_static'
        'Reporter'
        'START'
        'str'
        'get_reason_name'
        'get_reason_photo_name'
        'send_report'
        'send_report_photo'
        'worker_mess'
        'worker_photo'
    [Locals+Names]
    [Constants]
        '__pyarmor_assert_14460__'
        '__pyarmor_enter_14461__'
        b'<COAddr>\x05\x00\x00\x1a\x98\x01\x00\x00\x00\x00\x00\x00\x00\x00\x00\x00\x00\x00\x00\x00'
        0
        None
        (
            'Thread'
            'Event'
        )
        (
            'functions'
            'errors'
            'types'
        )
        (
            'StopProgram'
        )
        (
            'GetLang'
        )
        (
            'Logs'
        )
        (
            'check_module'
        )
        (
            'logging'
        )
        (
            'memory_check_switcher'
        )
        (
            'memory_set_pid'
        )
        (
            'DelayOnline'
        )
        (
            'Disconnect'
        )
        (
            'Thread_wait'
        )
        (
            'account_works'
        )
        (
            'tg_links'
        )
        (
            'GetConfig'
        )
        (
            'GetProxy'
        )
        (
            'StopDetect'
        )
        (
            'del_task_manager'
        )
        (
            'getFile'
        )
        (
            'getPath'
        )
        (
            'set_task_manager'
        )
        (
            'db_reporter'
        )
        [Code]
            File Name: <frozen program.modules.Reporter>
            Object Name: Reporter
            Qualified Name: Reporter
            Arg Count: 1
            Pos Only Arg Count: 0
            KW Only Arg Count: 0
            Stack Size: 8
            Flags: 0x20000003 (CO_OPTIMIZED | CO_NEWLOCALS | CO_PYARMOR_OBFUSCATED)
            [Names]
                'get'
                'getFile'
                'getPath'
                'GetConfig'
                'config'
                'GetLang'
                'Lang'
                'GetProxy'
                'eel'
                'sendSuccessBox'
                'memory_check_switcher'
                'check_module'
                'Event'
                'memory_set_pid'
                'Thread'
                'START'
                'start'
                'Logs'
                'WaitStopAnsfer'
                'UpdateLogInWindow'
                'BaseException'
                'logging'
            [Locals+Names]
                'data'
                '__assert_armored__'
                '_var_var_0'
                '_var_var_1'
                '_var_var_2'
                '_var_var_3'
            [Constants]
                None
                '__pyarmor_assert_14463__'
                '__pyarmor_enter_14464__'
                b'<COAddr>\x07\x00\x00\x1a4\x03\x00\x00\x00\x00\x00\x00\x00\x00\x00\x00\x00\x00\x00\x00'
                'action'
                'getFile'
                '__pyarmor_exit_14465__'
                'getPath'
                'program_running'   # b'\x81\xf2\n\x1c4\xe8\xbf\xdf$\xe8\x18\xceb\xe5\xf6\x82'
                False
                5
                (
                    'target'
                    'args'
                )
                True
                (
                    'target'
                    'args'
                    'daemon'
                )
            [Disassembly]
                0       NOP                             
                2       NOP                             
                4       PUSH_NULL                       
                6       LOAD_CONST                      2: '__pyarmor_enter_14464__'
                8       LOAD_CONST                      3: b'<COAddr>\x07\x00\x00\x1a4\x03\x00\x00\x00\x00\x00\x00\x00\x00\x00\x00\x00\x00\x00\x00'
                10      BUILD_TUPLE                     1
                12      CALL_FUNCTION_EX                0
                14      POP_TOP                         
                16      RESUME                          0
                18      NOP                             
                20      NOP                             
                22      NOP                             
                24      NOP                             
                26      NOP                             
                28      NOP                             
                30      LOAD_FAST                       0: data
                32      LOAD_ATTR                       1: get
                52      LOAD_CONST                      4: 'action'
                54      CALL                            1
                62      POP_JUMP_IF_NONE                28 (to 120)
                64      LOAD_FAST                       0: data
                66      LOAD_CONST                      4: 'action'
                68      BINARY_SUBSCR                   
                72      LOAD_CONST                      5: 'getFile'
                74      COMPARE_OP                      40 (==)
                78      POP_JUMP_IF_FALSE               20 (to 120)
                80      LOAD_GLOBAL                     3: NULL + getFile
                90      LOAD_FAST                       0: data
                92      CALL                            1
                100     NOP                             
                102     NOP                             
                104     JUMP_FORWARD                    383 (to 874)
                108     CALL                            1
                116     POP_TOP                         
                118     RETURN_VALUE                    
                120     LOAD_FAST                       0: data
                122     LOAD_ATTR                       1: get
                142     LOAD_CONST                      4: 'action'
                144     CALL                            1
                152     POP_JUMP_IF_NONE                28 (to 210)
                154     LOAD_FAST                       0: data
                156     LOAD_CONST                      4: 'action'
                158     BINARY_SUBSCR                   
                162     LOAD_CONST                      7: 'getPath'
                164     COMPARE_OP                      40 (==)
                168     POP_JUMP_IF_FALSE               20 (to 210)
                170     LOAD_GLOBAL                     5: NULL + getPath
                180     LOAD_FAST                       0: data
                182     CALL                            1
                190     NOP                             
                192     NOP                             
                194     JUMP_FORWARD                    338 (to 874)
                198     CALL                            1
                206     POP_TOP                         
                208     RETURN_VALUE                    
                210     LOAD_GLOBAL                     7: NULL + GetConfig
                220     CALL                            0
                228     STORE_GLOBAL                    4: config
                230     LOAD_GLOBAL                     11: NULL + GetLang
                240     LOAD_GLOBAL                     8: config
                250     CALL                            1
                258     STORE_GLOBAL                    6: Lang
                260     LOAD_GLOBAL                     15: NULL + GetProxy
                270     CALL                            0
                278     STORE_FAST                      2: _var_var_0
                280     LOAD_GLOBAL                     17: NULL + eel
                290     LOAD_ATTR                       18: sendSuccessBox
                310     LOAD_GLOBAL                     12: Lang
                320     PUSH_NULL                       
                322     LOAD_CONST                      1: '__pyarmor_assert_14463__'
                324     LOAD_CONST                      8: 'program_running'   # b'\x81\xf2\n\x1c4\xe8\xbf\xdf$\xe8\x18\xceb\xe5\xf6\x82'
                326     CALL                            1
                334     BINARY_SUBSCR                   
                338     CALL                            1
                346     POP_TOP                         
                348     LOAD_GLOBAL                     21: NULL + memory_check_switcher
                358     CALL                            0
                366     POP_JUMP_IF_TRUE                11 (to 390)
                368     NOP                             
                370     LOAD_CONST                      9: False
                372     NOP                             
                374     NOP                             
                376     NOP                             
                378     JUMP_FORWARD                    247 (to 874)
                386     POP_TOP                         
                388     RETURN_CONST                    9: False
                390     LOAD_GLOBAL                     23: NULL + check_module
                400     LOAD_CONST                      10: 5
                402     CALL                            1
                410     POP_JUMP_IF_TRUE                11 (to 434)
                412     NOP                             
                414     LOAD_CONST                      9: False
                416     NOP                             
                418     NOP                             
                420     NOP                             
                422     JUMP_FORWARD                    225 (to 874)
                430     POP_TOP                         
                432     RETURN_CONST                    9: False
                434     LOAD_GLOBAL                     25: NULL + Event
                444     CALL                            0
                452     STORE_FAST                      3: _var_var_1
                454     LOAD_GLOBAL                     27: NULL + memory_set_pid
                464     CALL                            0
                472     STORE_FAST                      4: _var_var_2
                474     LOAD_GLOBAL                     29: NULL + Thread
                484     LOAD_GLOBAL                     30: START
                494     LOAD_FAST                       0: data
                496     LOAD_GLOBAL                     8: config
                506     LOAD_FAST                       4: _var_var_2
                508     LOAD_FAST                       2: _var_var_0
                510     LOAD_FAST                       3: _var_var_1
                512     BUILD_TUPLE                     5
                514     KW_NAMES                        11: ('target', 'args')
                516     CALL                            2
                524     LOAD_ATTR                       33: start
                544     CALL                            0
                552     POP_TOP                         
                554     LOAD_GLOBAL                     29: NULL + Thread
                564     LOAD_GLOBAL                     34: Logs
                574     LOAD_ATTR                       36: WaitStopAnsfer
                594     LOAD_GLOBAL                     8: config
                604     LOAD_FAST                       4: _var_var_2
                606     LOAD_FAST                       3: _var_var_1
                608     BUILD_TUPLE                     3
                610     LOAD_CONST                      12: True
                612     KW_NAMES                        13: ('target', 'args', 'daemon')
                614     CALL                            3
                622     LOAD_ATTR                       33: start
                642     CALL                            0
                650     POP_TOP                         
                652     LOAD_GLOBAL                     29: NULL + Thread
                662     LOAD_GLOBAL                     34: Logs
                672     LOAD_ATTR                       38: UpdateLogInWindow
                692     LOAD_GLOBAL                     8: config
                702     LOAD_FAST                       4: _var_var_2
                704     LOAD_FAST                       3: _var_var_1
                706     BUILD_TUPLE                     3
                708     LOAD_CONST                      12: True
                710     KW_NAMES                        13: ('target', 'args', 'daemon')
                712     CALL                            3
                720     LOAD_ATTR                       33: start
                740     CALL                            0
                748     POP_TOP                         
                750     LOAD_CONST                      0: None
                752     NOP                             
                754     NOP                             
                756     NOP                             
                758     JUMP_FORWARD                    57 (to 874)
                766     POP_TOP                         
                768     RETURN_CONST                    0: None
                770     PUSH_EXC_INFO                   
                772     LOAD_GLOBAL                     40: BaseException
                782     CHECK_EXC_MATCH                 
                784     POP_JUMP_IF_FALSE               26 (to 838)
                786     STORE_FAST                      5: _var_var_3
                788     PUSH_NULL                       
                790     LOAD_GLOBAL                     43: NULL + logging
                800     LOAD_FAST                       5: _var_var_3
                802     CALL                            1
                810     CALL                            0
                818     POP_TOP                         
                820     POP_EXCEPT                      
                822     LOAD_CONST                      0: None
                824     STORE_FAST                      5: _var_var_3
                826     DELETE_FAST                     5: _var_var_3
                828     JUMP_BACKWARD                   40 (to 750)
                830     LOAD_CONST                      0: None
                832     STORE_FAST                      5: _var_var_3
                834     DELETE_FAST                     5: _var_var_3
                836     RERAISE                         1
                838     RERAISE                         0
                840     COPY                            3
                842     POP_EXCEPT                      
                844     RERAISE                         1
                846     PUSH_EXC_INFO                   
                848     PUSH_NULL                       
                850     LOAD_CONST                      6: '__pyarmor_exit_14465__'
                852     NOP                             
                854     LOAD_CONST                      3: b'<COAddr>\x07\x00\x00\x1a4\x03\x00\x00\x00\x00\x00\x00\x00\x00\x00\x00\x00\x00\x00\x00'
                856     CALL                            1
                864     POP_TOP                         
                866     RERAISE                         0
                868     COPY                            3
                870     POP_EXCEPT                      
                872     RERAISE                         1
                874     PUSH_NULL                       
                876     LOAD_CONST                      6: '__pyarmor_exit_14465__'
                878     LOAD_CONST                      3: b'<COAddr>\x07\x00\x00\x1a4\x03\x00\x00\x00\x00\x00\x00\x00\x00\x00\x00\x00\x00\x00\x00'
                880     BUILD_TUPLE                     1
                882     CALL_FUNCTION_EX                0
                884     POP_TOP                         
                886     RETURN_VALUE                    
            [Exception Table]
                30 to 100 -> 770 [0] 
                120 to 190 -> 770 [0] 
                210 to 368 -> 770 [0] 
                390 to 412 -> 770 [0] 
                434 to 750 -> 770 [0] 
                770 to 788 -> 840 [1] lasti
                788 to 820 -> 830 [1] lasti
                820 to 830 -> 846 [0] 
                830 to 840 -> 840 [1] lasti
                840 to 846 -> 846 [0] 
                846 to 868 -> 868 [1] lasti
        [Code]
            File Name: <frozen program.modules.Reporter>
            Object Name: START
            Qualified Name: START
            Arg Count: 5
            Pos Only Arg Count: 0
            KW Only Arg Count: 0
            Stack Size: 14
            Flags: 0x20000003 (CO_OPTIMIZED | CO_NEWLOCALS | CO_PYARMOR_OBFUSCATED)
            [Names]
                'is_set'
                'StopProgram'
                'isinstance'
                'list'
                'int'
                'len'
                'eel'
                'sendErrorBox'
                'Lang'
                'get'
                'db_reporter'
                'create'
                'set_task_manager'
                'concurrent'
                'futures'
                'ThreadPoolExecutor'
                'StreamStat'
                'json'
                'dumps'
                'append'
                'submit'
                'worker_photo'
                'worker_mess'
                'as_completed'
                'BaseException'
                'logging'
                'del_task_manager'
                'StopDetect'
            [Locals+Names]
                'data'
                'config'
                'pid'
                'proxy'
                'stop_thread'
                '__assert_armored__'
                '_var_var_4'
                '_var_var_5'
                '_var_var_6'
                '_var_var_7'
                '_var_var_8'
                '_var_var_9'
                '_var_var_10'
                '_var_var_11'
                '_var_var_12'
                '_var_var_13'
                '_var_var_14'
                '_var_var_15'
                '_var_var_3'
            [Constants]
                None
                '__pyarmor_assert_14466__'
                '__pyarmor_enter_14467__'
                b'<COAddr>\x05\x00\x00\x1ax\x05\x00\x00\x00\x00\x00\x00\x00\x00\x00\x00\x00\x00\x00\x00'
                'Accounts'
                1
                'select_accounts_works'   # b'\x81\xf1\x1d\x1f6\xf9\xaa\xed\x1a\xf9\x0e\xcfy\xe2\xec\x960J\xb4\xb5\xa1\xd8'
                'Settings'
                'target'
                'thread_rules'   # b'\x81\xf6\x10\x016\xfb\xba\xed\t\xef\x01\xc5\x7f'
                True
                'thread_count'   # b'\x81\xf6\x10\x016\xfb\xba\xed\x18\xf5\x18\xcex'
                'stuff'
                (
                    'accounts'
                    'name'
                )
                (
                    'max_workers'
                )
                0
                'st_task'
                'st_stream'   # b'\x81\xf1\x0c, \xee\xac\xd7\x1a\xf7'
                'st_wait'
                'st_done'
                'photo'
                '__pyarmor_exit_14468__'
                'Done'
            [Disassembly]
                0       NOP                             
                2       NOP                             
                4       PUSH_NULL                       
                6       LOAD_CONST                      2: '__pyarmor_enter_14467__'
                8       LOAD_CONST                      3: b'<COAddr>\x05\x00\x00\x1ax\x05\x00\x00\x00\x00\x00\x00\x00\x00\x00\x00\x00\x00\x00\x00'
                10      BUILD_TUPLE                     1
                12      CALL_FUNCTION_EX                0
                14      POP_TOP                         
                16      RESUME                          0
                18      NOP                             
                20      NOP                             
                22      NOP                             
                24      NOP                             
                26      NOP                             
                28      NOP                             
                30      LOAD_FAST                       4: stop_thread
                32      LOAD_ATTR                       1: is_set
                52      CALL                            0
                60      POP_JUMP_IF_FALSE               10 (to 82)
                62      LOAD_GLOBAL                     3: NULL + StopProgram
                72      CALL                            0
                80      RAISE_VARARGS                   1
                82      LOAD_FAST                       0: data
                84      LOAD_CONST                      4: 'Accounts'
                86      BINARY_SUBSCR                   
                90      STORE_FAST                      6: _var_var_4
                92      LOAD_GLOBAL                     5: NULL + isinstance
                102     LOAD_FAST                       6: _var_var_4
                104     LOAD_GLOBAL                     6: list
                114     CALL                            2
                122     POP_JUMP_IF_TRUE                3 (to 130)
                124     LOAD_FAST                       6: _var_var_4
                126     BUILD_LIST                      1
                128     STORE_FAST                      6: _var_var_4
                130     LOAD_GLOBAL                     9: NULL + int
                140     LOAD_GLOBAL                     11: NULL + len
                150     LOAD_FAST                       6: _var_var_4
                152     CALL                            1
                160     CALL                            1
                168     LOAD_CONST                      5: 1
                170     COMPARE_OP                      2 (<)
                174     POP_JUMP_IF_FALSE               44 (to 264)
                176     LOAD_GLOBAL                     13: NULL + eel
                186     LOAD_ATTR                       14: sendErrorBox
                206     LOAD_GLOBAL                     16: Lang
                216     PUSH_NULL                       
                218     LOAD_CONST                      1: '__pyarmor_assert_14466__'
                220     LOAD_CONST                      6: 'select_accounts_works'   # b'\x81\xf1\x1d\x1f6\xf9\xaa\xed\x1a\xf9\x0e\xcfy\xe2\xec\x960J\xb4\xb5\xa1\xd8'
                222     CALL                            1
                230     BINARY_SUBSCR                   
                234     CALL                            1
                242     POP_TOP                         
                244     LOAD_GLOBAL                     3: NULL + StopProgram
                254     CALL                            0
                262     RAISE_VARARGS                   1
                264     LOAD_FAST                       0: data
                266     LOAD_CONST                      7: 'Settings'
                268     BINARY_SUBSCR                   
                272     LOAD_ATTR                       19: get
                292     LOAD_CONST                      8: 'target'
                294     CALL                            1
                302     STORE_FAST                      7: _var_var_5
                304     LOAD_FAST                       0: data
                306     LOAD_CONST                      7: 'Settings'
                308     BINARY_SUBSCR                   
                312     LOAD_ATTR                       19: get
                332     PUSH_NULL                       
                334     LOAD_CONST                      1: '__pyarmor_assert_14466__'
                336     LOAD_CONST                      9: 'thread_rules'   # b'\x81\xf6\x10\x016\xfb\xba\xed\t\xef\x01\xc5\x7f'
                338     CALL                            1
                346     CALL                            1
                354     LOAD_CONST                      10: True
                356     COMPARE_OP                      40 (==)
                360     POP_JUMP_IF_FALSE               36 (to 434)
                362     LOAD_GLOBAL                     9: NULL + int
                372     LOAD_FAST                       0: data
                374     LOAD_CONST                      7: 'Settings'
                376     BINARY_SUBSCR                   
                380     LOAD_ATTR                       19: get
                400     PUSH_NULL                       
                402     LOAD_CONST                      1: '__pyarmor_assert_14466__'
                404     LOAD_CONST                      11: 'thread_count'   # b'\x81\xf6\x10\x016\xfb\xba\xed\x18\xf5\x18\xcex'
                406     CALL                            1
                414     CALL                            1
                422     CALL                            1
                430     STORE_FAST                      8: _var_var_6
                432     JUMP_FORWARD                    11 (to 456)
                434     LOAD_FAST                       1: config
                436     PUSH_NULL                       
                438     LOAD_CONST                      1: '__pyarmor_assert_14466__'
                440     LOAD_CONST                      11: 'thread_count'   # b'\x81\xf6\x10\x016\xfb\xba\xed\x18\xf5\x18\xcex'
                442     CALL                            1
                450     BINARY_SUBSCR                   
                454     STORE_FAST                      8: _var_var_6
                456     LOAD_GLOBAL                     21: NULL + db_reporter
                466     CALL                            0
                474     LOAD_ATTR                       23: create
                494     CALL                            0
                502     STORE_FAST                      9: _var_var_7
                504     LOAD_GLOBAL                     25: NULL + set_task_manager
                514     LOAD_FAST                       2: pid
                516     LOAD_FAST                       6: _var_var_4
                518     LOAD_FAST                       0: data
                520     LOAD_CONST                      12: 'stuff'
                522     BINARY_SUBSCR                   
                526     KW_NAMES                        13: ('accounts', 'name')
                528     CALL                            3
                536     POP_TOP                         
                538     LOAD_GLOBAL                     26: concurrent
                548     LOAD_ATTR                       28: futures
                568     LOAD_ATTR                       31: ThreadPoolExecutor
                588     LOAD_FAST                       8: _var_var_6
                590     KW_NAMES                        14: ('max_workers',)
                592     CALL                            1
                600     BEFORE_WITH                     
                602     STORE_FAST                      10: _var_var_8
                604     BUILD_LIST                      0
                606     STORE_FAST                      11: _var_var_9
                608     LOAD_GLOBAL                     11: NULL + len
                618     LOAD_FAST                       6: _var_var_4
                620     CALL                            1
                628     STORE_FAST                      12: _var_var_10
                630     LOAD_FAST                       8: _var_var_6
                632     STORE_FAST                      13: _var_var_11
                634     LOAD_FAST                       12: _var_var_10
                636     STORE_FAST                      14: _var_var_12
                638     LOAD_CONST                      15: 0
                640     STORE_FAST                      15: _var_var_13
                642     LOAD_GLOBAL                     13: NULL + eel
                652     LOAD_ATTR                       32: StreamStat
                672     LOAD_GLOBAL                     35: NULL + json
                682     LOAD_ATTR                       36: dumps
                702     LOAD_CONST                      16: 'st_task'
                704     LOAD_FAST                       12: _var_var_10
                706     PUSH_NULL                       
                708     LOAD_CONST                      1: '__pyarmor_assert_14466__'
                710     LOAD_CONST                      17: 'st_stream'   # b'\x81\xf1\x0c, \xee\xac\xd7\x1a\xf7'
                712     CALL                            1
                720     LOAD_FAST                       13: _var_var_11
                722     LOAD_CONST                      18: 'st_wait'
                724     LOAD_FAST                       14: _var_var_12
                726     LOAD_CONST                      19: 'st_done'
                728     LOAD_FAST                       15: _var_var_13
                730     BUILD_MAP                       4
                732     CALL                            1
                740     CALL                            1
                748     POP_TOP                         
                750     LOAD_FAST                       6: _var_var_4
                752     GET_ITER                        
                754     FOR_ITER                        92 (to 940)
                758     STORE_FAST                      16: _var_var_14
                760     LOAD_FAST                       7: _var_var_5
                762     LOAD_CONST                      20: 'photo'
                764     COMPARE_OP                      40 (==)
                768     POP_JUMP_IF_FALSE               43 (to 856)
                770     LOAD_FAST                       11: _var_var_9
                772     LOAD_ATTR                       39: append
                792     LOAD_FAST                       10: _var_var_8
                794     LOAD_ATTR                       41: submit
                814     LOAD_GLOBAL                     42: worker_photo
                824     LOAD_FAST                       16: _var_var_14
                826     LOAD_FAST                       1: config
                828     LOAD_FAST                       3: proxy
                830     LOAD_FAST                       0: data
                832     LOAD_FAST                       9: _var_var_7
                834     LOAD_FAST                       4: stop_thread
                836     CALL                            7
                844     CALL                            1
                852     POP_TOP                         
                854     JUMP_BACKWARD                   51 (to 754)
                856     LOAD_FAST                       11: _var_var_9
                858     LOAD_ATTR                       39: append
                878     LOAD_FAST                       10: _var_var_8
                880     LOAD_ATTR                       41: submit
                900     LOAD_GLOBAL                     44: worker_mess
                910     LOAD_FAST                       16: _var_var_14
                912     LOAD_FAST                       1: config
                914     LOAD_FAST                       3: proxy
                916     LOAD_FAST                       0: data
                918     LOAD_FAST                       9: _var_var_7
                920     LOAD_FAST                       4: stop_thread
                922     CALL                            7
                930     CALL                            1
                938     POP_TOP                         
                940     JUMP_BACKWARD                   94 (to 754)
                942     END_FOR                         
                944     LOAD_GLOBAL                     26: concurrent
                954     LOAD_ATTR                       28: futures
                974     LOAD_ATTR                       47: as_completed
                994     LOAD_FAST                       11: _var_var_9
                996     CALL                            1
                1004    GET_ITER                        
                1006    FOR_ITER                        66 (to 1140)
                1010    STORE_FAST                      17: _var_var_15
                1012    LOAD_FAST                       15: _var_var_13
                1014    LOAD_CONST                      5: 1
                1016    BINARY_OP                       13 (+=)
                1020    STORE_FAST                      15: _var_var_13
                1022    LOAD_FAST                       14: _var_var_12
                1024    LOAD_CONST                      5: 1
                1026    BINARY_OP                       23 (-=)
                1030    STORE_FAST                      14: _var_var_12
                1032    LOAD_GLOBAL                     13: NULL + eel
                1042    LOAD_ATTR                       32: StreamStat
                1062    LOAD_GLOBAL                     35: NULL + json
                1072    LOAD_ATTR                       36: dumps
                1092    LOAD_CONST                      16: 'st_task'
                1094    LOAD_FAST                       12: _var_var_10
                1096    PUSH_NULL                       
                1098    LOAD_CONST                      1: '__pyarmor_assert_14466__'
                1100    LOAD_CONST                      17: 'st_stream'   # b'\x81\xf1\x0c, \xee\xac\xd7\x1a\xf7'
                1102    CALL                            1
                1110    LOAD_FAST                       13: _var_var_11
                1112    LOAD_CONST                      18: 'st_wait'
                1114    LOAD_FAST                       14: _var_var_12
                1116    LOAD_CONST                      19: 'st_done'
                1118    LOAD_FAST                       15: _var_var_13
                1120    BUILD_MAP                       4
                1122    CALL                            1
                1130    CALL                            1
                1138    POP_TOP                         
                1140    JUMP_BACKWARD                   68 (to 1006)
                1142    END_FOR                         
                1144    DELETE_FAST                     11: _var_var_9
                1146    DELETE_FAST                     0: data
                1148    LOAD_CONST                      0: None
                1150    LOAD_CONST                      0: None
                1152    LOAD_CONST                      0: None
                1154    CALL                            2
                1162    POP_TOP                         
                1164    LOAD_GLOBAL                     53: NULL + del_task_manager
                1174    LOAD_FAST                       2: pid
                1176    CALL                            1
                1184    POP_TOP                         
                1186    LOAD_GLOBAL                     55: NULL + StopDetect
                1196    LOAD_FAST                       4: stop_thread
                1198    CALL                            1
                1206    POP_TOP                         
                1208    NOP                             
                1210    LOAD_CONST                      22: 'Done'
                1212    NOP                             
                1214    NOP                             
                1216    NOP                             
                1218    JUMP_FORWARD                    117 (to 1454)
                1226    POP_TOP                         
                1228    RETURN_CONST                    22: 'Done'
                1230    PUSH_EXC_INFO                   
                1232    WITH_EXCEPT_START               
                1234    POP_JUMP_IF_TRUE                1 (to 1238)
                1236    RERAISE                         2
                1238    POP_TOP                         
                1240    POP_EXCEPT                      
                1242    POP_TOP                         
                1244    POP_TOP                         
                1246    JUMP_BACKWARD                   42 (to 1164)
                1248    COPY                            3
                1250    POP_EXCEPT                      
                1252    RERAISE                         1
                1254    PUSH_EXC_INFO                   
                1256    LOAD_GLOBAL                     2: StopProgram
                1266    CHECK_EXC_MATCH                 
                1268    POP_JUMP_IF_FALSE               3 (to 1276)
                1270    POP_TOP                         
                1272    POP_EXCEPT                      
                1274    JUMP_BACKWARD                   56 (to 1164)
                1276    LOAD_GLOBAL                     48: BaseException
                1286    CHECK_EXC_MATCH                 
                1288    POP_JUMP_IF_FALSE               26 (to 1342)
                1290    STORE_FAST                      18: _var_var_3
                1292    PUSH_NULL                       
                1294    LOAD_GLOBAL                     51: NULL + logging
                1304    LOAD_FAST                       18: _var_var_3
                1306    CALL                            1
                1314    CALL                            0
                1322    POP_TOP                         
                1324    POP_EXCEPT                      
                1326    LOAD_CONST                      0: None
                1328    STORE_FAST                      18: _var_var_3
                1330    DELETE_FAST                     18: _var_var_3
                1332    JUMP_BACKWARD                   85 (to 1164)
                1334    LOAD_CONST                      0: None
                1336    STORE_FAST                      18: _var_var_3
                1338    DELETE_FAST                     18: _var_var_3
                1340    RERAISE                         1
                1342    RERAISE                         0
                1344    COPY                            3
                1346    POP_EXCEPT                      
                1348    RERAISE                         1
                1350    PUSH_EXC_INFO                   
                1352    LOAD_GLOBAL                     53: NULL + del_task_manager
                1362    LOAD_FAST                       2: pid
                1364    CALL                            1
                1372    POP_TOP                         
                1374    LOAD_GLOBAL                     55: NULL + StopDetect
                1384    LOAD_FAST                       4: stop_thread
                1386    CALL                            1
                1394    POP_TOP                         
                1396    POP_TOP                         
                1398    POP_EXCEPT                      
                1400    LOAD_CONST                      22: 'Done'
                1402    NOP                             
                1404    NOP                             
                1406    NOP                             
                1408    JUMP_FORWARD                    22 (to 1454)
                1416    POP_TOP                         
                1418    RETURN_CONST                    22: 'Done'
                1420    COPY                            3
                1422    POP_EXCEPT                      
                1424    RERAISE                         1
                1426    PUSH_EXC_INFO                   
                1428    PUSH_NULL                       
                1430    LOAD_CONST                      21: '__pyarmor_exit_14468__'
                1432    NOP                             
                1434    LOAD_CONST                      3: b'<COAddr>\x05\x00\x00\x1ax\x05\x00\x00\x00\x00\x00\x00\x00\x00\x00\x00\x00\x00\x00\x00'
                1436    CALL                            1
                1444    POP_TOP                         
                1446    RERAISE                         0
                1448    COPY                            3
                1450    POP_EXCEPT                      
                1452    RERAISE                         1
                1454    PUSH_NULL                       
                1456    LOAD_CONST                      21: '__pyarmor_exit_14468__'
                1458    LOAD_CONST                      3: b'<COAddr>\x05\x00\x00\x1ax\x05\x00\x00\x00\x00\x00\x00\x00\x00\x00\x00\x00\x00\x00\x00'
                1460    BUILD_TUPLE                     1
                1462    CALL_FUNCTION_EX                0
                1464    POP_TOP                         
                1466    RETURN_VALUE                    
            [Exception Table]
                30 to 602 -> 1254 [0] 
                602 to 1148 -> 1230 [1] lasti
                1148 to 1164 -> 1254 [0] 
                1164 to 1208 -> 1426 [0] 
                1230 to 1240 -> 1248 [3] lasti
                1240 to 1254 -> 1254 [0] 
                1254 to 1272 -> 1344 [1] lasti
                1272 to 1276 -> 1350 [0] 
                1276 to 1292 -> 1344 [1] lasti
                1292 to 1324 -> 1334 [1] lasti
                1324 to 1334 -> 1350 [0] 
                1334 to 1344 -> 1344 [1] lasti
                1344 to 1350 -> 1350 [0] 
                1350 to 1398 -> 1420 [1] lasti
                1398 to 1400 -> 1426 [0] 
                1420 to 1426 -> 1426 [0] 
                1426 to 1448 -> 1448 [1] lasti
        'ids'
        [Code]
            File Name: <frozen program.modules.Reporter>
            Object Name: get_reason_name
            Qualified Name: get_reason_name
            Arg Count: 1
            Pos Only Arg Count: 0
            KW Only Arg Count: 0
            Stack Size: 9
            Flags: 0x20000003 (CO_OPTIMIZED | CO_NEWLOCALS | CO_PYARMOR_OBFUSCATED)
            [Names]
                'int'
            [Locals+Names]
                'ids'
                '__assert_armored__'
                '_var_var_16'
            [Constants]
                None
                '__pyarmor_assert_14469__'
                '__pyarmor_enter_14470__'
                b'<COAddr>\x07\x00\x00\x1a\xac\x01\x00\x00\x00\x00\x00\x00\x00\x00\x00\x00\x00\x00\x00\x00'
                1
                'I don’t like it'   # b'\x81\xcbX\x17<\xf4<2\xe2\xeeM\xcce\xe7\xfd\xc5\x06I'
                2
                'Child abuse'   # b'\x81\xc1\x10\x1a?\xfe\xfe\xd3\x19\xef\x1e\xc5'
                3
                'Violence'
                41
                'Illegal goods - Weapons'   # b'\x81\xcb\x14\x1f6\xfd\xbf\xde[\xfd\x02\xcfh\xff\xb8\xc8Oj\xbe\xa6\xba\xc4@\xdf'
                42
                'Illegal goods - Drugs'   # b'\x81\xcb\x14\x1f6\xfd\xbf\xde[\xfd\x02\xcfh\xff\xb8\xc8Oy\xa9\xb2\xad\xd8'
                43
                'Illegal goods - Fake Documents'   # b'\x81\xcb\x14\x1f6\xfd\xbf\xde[\xfd\x02\xcfh\xff\xb8\xc8O{\xba\xac\xaf\x8bj\xc3\x06z\xaeY\x0e\xa5\r'
                44
                'Illegal goods - Counterfeit money'   # b'\x81\xcb\x14\x1f6\xfd\xbf\xde[\xfd\x02\xcfh\xff\xb8\xc8O~\xb4\xb2\xa4\xdfK\xde\x03j\xaaH@\xbc\x11\xeb?K'
                45
                'Illegal goods - Other'   # b'\x81\xcb\x14\x1f6\xfd\xbf\xde[\xfd\x02\xcfh\xff\xb8\xc8Or\xaf\xaf\xaf\xd9'
                51
                'Illegal adult content - Child abuse'   # b'\x81\xcb\x14\x1f6\xfd\xbf\xde[\xfb\t\xd5`\xf8\xb8\x86\x00S\xaf\xa2\xa4\xdf\x0e\x81EL\xabU\x0c\xb5^\xe48G3\x08'
                52
                'Illegal adult content - Non-consensual sexual imagery'   # b'\x81\xcb\x14\x1f6\xfd\xbf\xde[\xfb\t\xd5`\xf8\xb8\x86\x00S\xaf\xa2\xa4\xdf\x0e\x81EA\xacRM\xb2\x11\xeb)W.\x1e\x8d\xcb\xb8n\x0b\xec\xe0H\xdc\xd4ON:\xecQ\xfe\x95i'
                53
                'Illegal adult content - Other illegal sexual content'   # b'\x81\xcb\x14\x1f6\xfd\xbf\xde[\xfb\t\xd5`\xf8\xb8\x86\x00S\xaf\xa2\xa4\xdf\x0e\x81E@\xb7T\x05\xa3^\xec6^%\n\x99\xc6\xf4=\x1d\xf1\xed\\\xd1\x98\x0cH9\xf9S\xf5\x93'
                61
                'Personal data - Private images'   # b'\x81\xd2\x1d\x01 \xf5\xb0\xd3\x17\xba\t\xc1x\xed\xb8\xc8Om\xa9\xae\xbc\xcaZ\xc9Ef\xae]\x07\xb4\r'
                62
                'Personal data - Phone number'   # b'\x81\xd2\x1d\x01 \xf5\xb0\xd3\x17\xba\t\xc1x\xed\xb8\xc8Om\xb3\xa8\xa4\xce\x0e\xc2\x10b\xa1Y\x12'
                63
                'Personal data - Address'   # b'\x81\xd2\x1d\x01 \xf5\xb0\xd3\x17\xba\t\xc1x\xed\xb8\xc8O|\xbf\xa3\xb8\xce]\xdf'
                64
                'Personal data - Other personal information'   # b'\x81\xd2\x1d\x01 \xf5\xb0\xd3\x17\xba\t\xc1x\xed\xb8\xc8Or\xaf\xaf\xaf\xd9\x0e\xdc\x00}\xb0S\x0e\xb0\x12\xa53\\&\x02\x8a\xc7\xb5:\x11\xe6\xf6'
                7
                'Terrorism'   # b'\x81\xd6\x1d\x01!\xf5\xac\xdb\x08\xf7'
                81
                'Scam or spam - Phishing'   # b'\x81\xd1\x1b\x12>\xba\xb1\xc0[\xe9\x1d\xc1a\xac\xb5\xc5?U\xb2\xb4\xa2\xc2@\xcb'
                'Scam or spam - Impersonation'   # b'\x81\xd1\x1b\x12>\xba\xb1\xc0[\xe9\x1d\xc1a\xac\xb5\xc5&P\xab\xa2\xb8\xd8A\xc2\x04{\xaaS\x0e'
                'Scam or spam - Fraudulent sales'   # b'\x81\xd1\x1b\x12>\xba\xb1\xc0[\xe9\x1d\xc1a\xac\xb5\xc5)O\xba\xb2\xae\xdeB\xc9\x0b{\xe3O\x01\xbd\x1b\xf6'
                'Scam or spam - Spam'   # b'\x81\xd1\x1b\x12>\xba\xb1\xc0[\xe9\x1d\xc1a\xac\xb5\xc5<M\xba\xaa'
                'Copyright'   # b'\x81\xc1\x17\x03*\xe8\xb7\xd5\x13\xee'
                'Other'
                'It’s not illegal, but it must be taken down'   # b'\x81\xcb\x0c\x91\xd3\x03\xad\x92\x15\xf5\x19\x80e\xe0\xf4\x80\x08\\\xb7\xeb\xea\xc9[\xd8Ef\xb7\x1c\r\xa4\r\xf1zP%M\x8c\xcb\xbf+\x16\xa9\xfcR\xca\xd6'
                (
                    82
                    83
                    84
                    9
                    10
                    11
                )
                '__pyarmor_exit_14471__'
            [Disassembly]
                0       NOP                             
                2       NOP                             
                4       PUSH_NULL                       
                6       LOAD_CONST                      2: '__pyarmor_enter_14470__'
                8       LOAD_CONST                      3: b'<COAddr>\x07\x00\x00\x1a\xac\x01\x00\x00\x00\x00\x00\x00\x00\x00\x00\x00\x00\x00\x00\x00'
                10      BUILD_TUPLE                     1
                12      CALL_FUNCTION_EX                0
                14      POP_TOP                         
                16      RESUME                          0
                18      NOP                             
                20      NOP                             
                22      NOP                             
                24      NOP                             
                26      NOP                             
                28      LOAD_GLOBAL                     1: NULL + int
                38      LOAD_FAST                       0: ids
                40      CALL                            1
                48      STORE_FAST                      0: ids
                50      BUILD_MAP                       0
                52      LOAD_CONST                      4: 1
                54      PUSH_NULL                       
                56      LOAD_CONST                      1: '__pyarmor_assert_14469__'
                58      LOAD_CONST                      5: 'I don’t like it'   # b'\x81\xcbX\x17<\xf4<2\xe2\xeeM\xcce\xe7\xfd\xc5\x06I'
                60      CALL                            1
                68      MAP_ADD                         1
                70      LOAD_CONST                      6: 2
                72      PUSH_NULL                       
                74      LOAD_CONST                      1: '__pyarmor_assert_14469__'
                76      LOAD_CONST                      7: 'Child abuse'   # b'\x81\xc1\x10\x1a?\xfe\xfe\xd3\x19\xef\x1e\xc5'
                78      CALL                            1
                86      MAP_ADD                         1
                88      LOAD_CONST                      8: 3
                90      LOAD_CONST                      9: 'Violence'
                92      MAP_ADD                         1
                94      LOAD_CONST                      10: 41
                96      PUSH_NULL                       
                98      LOAD_CONST                      1: '__pyarmor_assert_14469__'
                100     LOAD_CONST                      11: 'Illegal goods - Weapons'   # b'\x81\xcb\x14\x1f6\xfd\xbf\xde[\xfd\x02\xcfh\xff\xb8\xc8Oj\xbe\xa6\xba\xc4@\xdf'
                102     CALL                            1
                110     MAP_ADD                         1
                112     LOAD_CONST                      12: 42
                114     PUSH_NULL                       
                116     LOAD_CONST                      1: '__pyarmor_assert_14469__'
                118     LOAD_CONST                      13: 'Illegal goods - Drugs'   # b'\x81\xcb\x14\x1f6\xfd\xbf\xde[\xfd\x02\xcfh\xff\xb8\xc8Oy\xa9\xb2\xad\xd8'
                120     CALL                            1
                128     MAP_ADD                         1
                130     LOAD_CONST                      14: 43
                132     PUSH_NULL                       
                134     LOAD_CONST                      1: '__pyarmor_assert_14469__'
                136     LOAD_CONST                      15: 'Illegal goods - Fake Documents'   # b'\x81\xcb\x14\x1f6\xfd\xbf\xde[\xfd\x02\xcfh\xff\xb8\xc8O{\xba\xac\xaf\x8bj\xc3\x06z\xaeY\x0e\xa5\r'
                138     CALL                            1
                146     MAP_ADD                         1
                148     LOAD_CONST                      16: 44
                150     PUSH_NULL                       
                152     LOAD_CONST                      1: '__pyarmor_assert_14469__'
                154     LOAD_CONST                      17: 'Illegal goods - Counterfeit money'   # b'\x81\xcb\x14\x1f6\xfd\xbf\xde[\xfd\x02\xcfh\xff\xb8\xc8O~\xb4\xb2\xa4\xdfK\xde\x03j\xaaH@\xbc\x11\xeb?K'
                156     CALL                            1
                164     MAP_ADD                         1
                166     LOAD_CONST                      18: 45
                168     PUSH_NULL                       
                170     LOAD_CONST                      1: '__pyarmor_assert_14469__'
                172     LOAD_CONST                      19: 'Illegal goods - Other'   # b'\x81\xcb\x14\x1f6\xfd\xbf\xde[\xfd\x02\xcfh\xff\xb8\xc8Or\xaf\xaf\xaf\xd9'
                174     CALL                            1
                182     MAP_ADD                         1
                184     LOAD_CONST                      20: 51
                186     PUSH_NULL                       
                188     LOAD_CONST                      1: '__pyarmor_assert_14469__'
                190     LOAD_CONST                      21: 'Illegal adult content - Child abuse'   # b'\x81\xcb\x14\x1f6\xfd\xbf\xde[\xfb\t\xd5`\xf8\xb8\x86\x00S\xaf\xa2\xa4\xdf\x0e\x81EL\xabU\x0c\xb5^\xe48G3\x08'
                192     CALL                            1
                200     MAP_ADD                         1
                202     LOAD_CONST                      22: 52
                204     PUSH_NULL                       
                206     LOAD_CONST                      1: '__pyarmor_assert_14469__'
                208     LOAD_CONST                      23: 'Illegal adult content - Non-consensual sexual imagery'   # b'\x81\xcb\x14\x1f6\xfd\xbf\xde[\xfb\t\xd5`\xf8\xb8\x86\x00S\xaf\xa2\xa4\xdf\x0e\x81EA\xacRM\xb2\x11\xeb)W.\x1e\x8d\xcb\xb8n\x0b\xec\xe0H\xdc\xd4ON:\xecQ\xfe\x95i'
                210     CALL                            1
                218     MAP_ADD                         1
                220     LOAD_CONST                      24: 53
                222     PUSH_NULL                       
                224     LOAD_CONST                      1: '__pyarmor_assert_14469__'
                226     LOAD_CONST                      25: 'Illegal adult content - Other illegal sexual content'   # b'\x81\xcb\x14\x1f6\xfd\xbf\xde[\xfb\t\xd5`\xf8\xb8\x86\x00S\xaf\xa2\xa4\xdf\x0e\x81E@\xb7T\x05\xa3^\xec6^%\n\x99\xc6\xf4=\x1d\xf1\xed\\\xd1\x98\x0cH9\xf9S\xf5\x93'
                228     CALL                            1
                236     MAP_ADD                         1
                238     LOAD_CONST                      26: 61
                240     PUSH_NULL                       
                242     LOAD_CONST                      1: '__pyarmor_assert_14469__'
                244     LOAD_CONST                      27: 'Personal data - Private images'   # b'\x81\xd2\x1d\x01 \xf5\xb0\xd3\x17\xba\t\xc1x\xed\xb8\xc8Om\xa9\xae\xbc\xcaZ\xc9Ef\xae]\x07\xb4\r'
                246     CALL                            1
                254     MAP_ADD                         1
                256     LOAD_CONST                      28: 62
                258     PUSH_NULL                       
                260     LOAD_CONST                      1: '__pyarmor_assert_14469__'
                262     LOAD_CONST                      29: 'Personal data - Phone number'   # b'\x81\xd2\x1d\x01 \xf5\xb0\xd3\x17\xba\t\xc1x\xed\xb8\xc8Om\xb3\xa8\xa4\xce\x0e\xc2\x10b\xa1Y\x12'
                264     CALL                            1
                272     MAP_ADD                         1
                274     LOAD_CONST                      30: 63
                276     PUSH_NULL                       
                278     LOAD_CONST                      1: '__pyarmor_assert_14469__'
                280     LOAD_CONST                      31: 'Personal data - Address'   # b'\x81\xd2\x1d\x01 \xf5\xb0\xd3\x17\xba\t\xc1x\xed\xb8\xc8O|\xbf\xa3\xb8\xce]\xdf'
                282     CALL                            1
                290     MAP_ADD                         1
                292     LOAD_CONST                      32: 64
                294     PUSH_NULL                       
                296     LOAD_CONST                      1: '__pyarmor_assert_14469__'
                298     LOAD_CONST                      33: 'Personal data - Other personal information'   # b'\x81\xd2\x1d\x01 \xf5\xb0\xd3\x17\xba\t\xc1x\xed\xb8\xc8Or\xaf\xaf\xaf\xd9\x0e\xdc\x00}\xb0S\x0e\xb0\x12\xa53\\&\x02\x8a\xc7\xb5:\x11\xe6\xf6'
                300     CALL                            1
                308     MAP_ADD                         1
                310     LOAD_CONST                      34: 7
                312     PUSH_NULL                       
                314     LOAD_CONST                      1: '__pyarmor_assert_14469__'
                316     LOAD_CONST                      35: 'Terrorism'   # b'\x81\xd6\x1d\x01!\xf5\xac\xdb\x08\xf7'
                318     CALL                            1
                326     MAP_ADD                         1
                328     LOAD_CONST                      36: 81
                330     PUSH_NULL                       
                332     LOAD_CONST                      1: '__pyarmor_assert_14469__'
                334     LOAD_CONST                      37: 'Scam or spam - Phishing'   # b'\x81\xd1\x1b\x12>\xba\xb1\xc0[\xe9\x1d\xc1a\xac\xb5\xc5?U\xb2\xb4\xa2\xc2@\xcb'
                336     CALL                            1
                344     MAP_ADD                         1
                346     PUSH_NULL                       
                348     LOAD_CONST                      1: '__pyarmor_assert_14469__'
                350     LOAD_CONST                      38: 'Scam or spam - Impersonation'   # b'\x81\xd1\x1b\x12>\xba\xb1\xc0[\xe9\x1d\xc1a\xac\xb5\xc5&P\xab\xa2\xb8\xd8A\xc2\x04{\xaaS\x0e'
                352     CALL                            1
                360     PUSH_NULL                       
                362     LOAD_CONST                      1: '__pyarmor_assert_14469__'
                364     LOAD_CONST                      39: 'Scam or spam - Fraudulent sales'   # b'\x81\xd1\x1b\x12>\xba\xb1\xc0[\xe9\x1d\xc1a\xac\xb5\xc5)O\xba\xb2\xae\xdeB\xc9\x0b{\xe3O\x01\xbd\x1b\xf6'
                366     CALL                            1
                374     PUSH_NULL                       
                376     LOAD_CONST                      1: '__pyarmor_assert_14469__'
                378     LOAD_CONST                      40: 'Scam or spam - Spam'   # b'\x81\xd1\x1b\x12>\xba\xb1\xc0[\xe9\x1d\xc1a\xac\xb5\xc5<M\xba\xaa'
                380     CALL                            1
                388     PUSH_NULL                       
                390     LOAD_CONST                      1: '__pyarmor_assert_14469__'
                392     LOAD_CONST                      41: 'Copyright'   # b'\x81\xc1\x17\x03*\xe8\xb7\xd5\x13\xee'
                394     CALL                            1
                402     LOAD_CONST                      42: 'Other'
                404     PUSH_NULL                       
                406     LOAD_CONST                      1: '__pyarmor_assert_14469__'
                408     LOAD_CONST                      43: 'It’s not illegal, but it must be taken down'   # b'\x81\xcb\x0c\x91\xd3\x03\xad\x92\x15\xf5\x19\x80e\xe0\xf4\x80\x08\\\xb7\xeb\xea\xc9[\xd8Ef\xb7\x1c\r\xa4\r\xf1zP%M\x8c\xcb\xbf+\x16\xa9\xfcR\xca\xd6'
                410     CALL                            1
                418     LOAD_CONST                      44: (82, 83, 84, 9, 10, 11)
                420     BUILD_CONST_KEY_MAP             6
                422     DICT_UPDATE                     1
                424     STORE_FAST                      2: _var_var_16
                426     LOAD_FAST                       2: _var_var_16
                428     LOAD_FAST                       0: ids
                430     BINARY_SUBSCR                   
                434     NOP                             
                436     NOP                             
                438     NOP                             
                440     JUMP_FORWARD                    20 (to 482)
                442     CALL                            1
                450     POP_TOP                         
                452     RETURN_VALUE                    
                454     PUSH_EXC_INFO                   
                456     PUSH_NULL                       
                458     LOAD_CONST                      45: '__pyarmor_exit_14471__'
                460     NOP                             
                462     LOAD_CONST                      3: b'<COAddr>\x07\x00\x00\x1a\xac\x01\x00\x00\x00\x00\x00\x00\x00\x00\x00\x00\x00\x00\x00\x00'
                464     CALL                            1
                472     POP_TOP                         
                474     RERAISE                         0
                476     COPY                            3
                478     POP_EXCEPT                      
                480     RERAISE                         1
                482     PUSH_NULL                       
                484     LOAD_CONST                      45: '__pyarmor_exit_14471__'
                486     LOAD_CONST                      3: b'<COAddr>\x07\x00\x00\x1a\xac\x01\x00\x00\x00\x00\x00\x00\x00\x00\x00\x00\x00\x00\x00\x00'
                488     BUILD_TUPLE                     1
                490     CALL_FUNCTION_EX                0
                492     POP_TOP                         
                494     RETURN_VALUE                    
            [Exception Table]
                28 to 434 -> 454 [0] 
                454 to 476 -> 476 [1] lasti
        [Code]
            File Name: <frozen program.modules.Reporter>
            Object Name: get_reason_photo_name
            Qualified Name: get_reason_photo_name
            Arg Count: 1
            Pos Only Arg Count: 0
            KW Only Arg Count: 0
            Stack Size: 9
            Flags: 0x20000003 (CO_OPTIMIZED | CO_NEWLOCALS | CO_PYARMOR_OBFUSCATED)
            [Names]
                'int'
            [Locals+Names]
                'ids'
                '__assert_armored__'
                '_var_var_16'
            [Constants]
                None
                '__pyarmor_assert_14472__'
                '__pyarmor_enter_14473__'
                b'<COAddr>\x05\x00\x00\x1a\x86\x00\x00\x00\x00\x00\x00\x00\x00\x00\x00\x00\x00\x00\x00\x00'
                'Spam'
                'Fake Accounts'   # b'\x81\xc4\x19\x186\xba\x9f\xd1\x18\xf5\x18\xcex\xff'
                'Violence'
                'Child Abuse'   # b'\x81\xc1\x10\x1a?\xfe\xfe\xf3\x19\xef\x1e\xc5'
                'Illegal Drugs'   # b'\x81\xcb\x14\x1f6\xfd\xbf\xde[\xde\x1f\xd5k\xff'
                'Personal Details'   # b'\x81\xd2\x1d\x01 \xf5\xb0\xd3\x17\xba)\xc5x\xed\xf1\x89\x1c'
                'Pornography'   # b'\x81\xd2\x17\x01=\xf5\xb9\xc0\x1a\xea\x05\xd9'
                'Other'
                (
                    1
                    2
                    3
                    4
                    5
                    6
                    7
                    8
                )
                '__pyarmor_exit_14474__'
            [Disassembly]
                0       NOP                             
                2       NOP                             
                4       PUSH_NULL                       
                6       LOAD_CONST                      2: '__pyarmor_enter_14473__'
                8       LOAD_CONST                      3: b'<COAddr>\x05\x00\x00\x1a\x86\x00\x00\x00\x00\x00\x00\x00\x00\x00\x00\x00\x00\x00\x00\x00'
                10      BUILD_TUPLE                     1
                12      CALL_FUNCTION_EX                0
                14      POP_TOP                         
                16      RESUME                          0
                18      NOP                             
                20      NOP                             
                22      NOP                             
                24      NOP                             
                26      NOP                             
                28      LOAD_GLOBAL                     1: NULL + int
                38      LOAD_FAST                       0: ids
                40      CALL                            1
                48      STORE_FAST                      0: ids
                50      LOAD_CONST                      4: 'Spam'
                52      PUSH_NULL                       
                54      LOAD_CONST                      1: '__pyarmor_assert_14472__'
                56      LOAD_CONST                      5: 'Fake Accounts'   # b'\x81\xc4\x19\x186\xba\x9f\xd1\x18\xf5\x18\xcex\xff'
                58      CALL                            1
                66      LOAD_CONST                      6: 'Violence'
                68      PUSH_NULL                       
                70      LOAD_CONST                      1: '__pyarmor_assert_14472__'
                72      LOAD_CONST                      7: 'Child Abuse'   # b'\x81\xc1\x10\x1a?\xfe\xfe\xf3\x19\xef\x1e\xc5'
                74      CALL                            1
                82      PUSH_NULL                       
                84      LOAD_CONST                      1: '__pyarmor_assert_14472__'
                86      LOAD_CONST                      8: 'Illegal Drugs'   # b'\x81\xcb\x14\x1f6\xfd\xbf\xde[\xde\x1f\xd5k\xff'
                88      CALL                            1
                96      PUSH_NULL                       
                98      LOAD_CONST                      1: '__pyarmor_assert_14472__'
                100     LOAD_CONST                      9: 'Personal Details'   # b'\x81\xd2\x1d\x01 \xf5\xb0\xd3\x17\xba)\xc5x\xed\xf1\x89\x1c'
                102     CALL                            1
                110     PUSH_NULL                       
                112     LOAD_CONST                      1: '__pyarmor_assert_14472__'
                114     LOAD_CONST                      10: 'Pornography'   # b'\x81\xd2\x17\x01=\xf5\xb9\xc0\x1a\xea\x05\xd9'
                116     CALL                            1
                124     LOAD_CONST                      11: 'Other'
                126     LOAD_CONST                      12: (1, 2, 3, 4, 5, 6, 7, 8)
                128     BUILD_CONST_KEY_MAP             8
                130     STORE_FAST                      2: _var_var_16
                132     LOAD_FAST                       2: _var_var_16
                134     LOAD_FAST                       0: ids
                136     BINARY_SUBSCR                   
                140     NOP                             
                142     NOP                             
                144     NOP                             
                146     JUMP_FORWARD                    20 (to 188)
                148     CALL                            1
                156     POP_TOP                         
                158     RETURN_VALUE                    
                160     PUSH_EXC_INFO                   
                162     PUSH_NULL                       
                164     LOAD_CONST                      13: '__pyarmor_exit_14474__'
                166     NOP                             
                168     LOAD_CONST                      3: b'<COAddr>\x05\x00\x00\x1a\x86\x00\x00\x00\x00\x00\x00\x00\x00\x00\x00\x00\x00\x00\x00\x00'
                170     CALL                            1
                178     POP_TOP                         
                180     RERAISE                         0
                182     COPY                            3
                184     POP_EXCEPT                      
                186     RERAISE                         1
                188     PUSH_NULL                       
                190     LOAD_CONST                      13: '__pyarmor_exit_14474__'
                192     LOAD_CONST                      3: b'<COAddr>\x05\x00\x00\x1a\x86\x00\x00\x00\x00\x00\x00\x00\x00\x00\x00\x00\x00\x00\x00\x00'
                194     BUILD_TUPLE                     1
                196     CALL_FUNCTION_EX                0
                198     POP_TOP                         
                200     RETURN_VALUE                    
            [Exception Table]
                28 to 140 -> 160 [0] 
                160 to 182 -> 182 [1] lasti
        [Code]
            File Name: <frozen program.modules.Reporter>
            Object Name: send_report
            Qualified Name: send_report
            Arg Count: 5
            Pos Only Arg Count: 0
            KW Only Arg Count: 0
            Stack Size: 8
            Flags: 0x20000003 (CO_OPTIMIZED | CO_NEWLOCALS | CO_PYARMOR_OBFUSCATED)
            [Names]
                'functions'
                'messages'
                'ReportRequest'
                'int'
                'encode'
                'option'
                'Exception'
            [Locals+Names]
                'client'
                'target_peer'
                'mess_id'
                'reason_send'
                'reason_mess_send'
                '__assert_armored__'
                '_var_var_17'
                '_var_var_18'
                '_var_var_19'
                '_var_var_3'
            [Constants]
                None
                '__pyarmor_assert_14475__'
                '__pyarmor_enter_14476__'
                b'<COAddr>\x07\x00\x00\x1a\xca\x04\x00\x00\x00\x00\x00\x00\x00\x00\x00\x00\x00\x00\x00\x00'
                False
                b''
                ''
                (
                    'peer'
                    'id'
                    'option'
                    'message'
                )
                10
                b'a'
                11
                b'b'
                1
                'utf-8'
                0
                '__pyarmor_exit_14477__'
                'Done'
                'NotDone'
            [Disassembly]
                0       NOP                             
                2       NOP                             
                4       PUSH_NULL                       
                6       LOAD_CONST                      2: '__pyarmor_enter_14476__'
                8       LOAD_CONST                      3: b'<COAddr>\x07\x00\x00\x1a\xca\x04\x00\x00\x00\x00\x00\x00\x00\x00\x00\x00\x00\x00\x00\x00'
                10      BUILD_TUPLE                     1
                12      CALL_FUNCTION_EX                0
                14      POP_TOP                         
                16      RESUME                          0
                18      NOP                             
                20      NOP                             
                22      NOP                             
                24      NOP                             
                26      NOP                             
                28      NOP                             
                30      LOAD_FAST                       2: mess_id
                32      POP_JUMP_IF_FALSE               4 (to 42)
                34      LOAD_FAST                       2: mess_id
                36      BUILD_LIST                      1
                38      STORE_FAST                      2: mess_id
                40      JUMP_FORWARD                    2 (to 46)
                42      BUILD_LIST                      0
                44      STORE_FAST                      2: mess_id
                46      LOAD_CONST                      4: False
                48      STORE_FAST                      6: _var_var_17
                50      PUSH_NULL                       
                52      LOAD_FAST                       0: client
                54      LOAD_GLOBAL                     0: functions
                64      LOAD_ATTR                       2: messages
                84      LOAD_ATTR                       5: ReportRequest
                104     LOAD_FAST                       1: target_peer
                106     LOAD_FAST                       2: mess_id
                108     LOAD_CONST                      5: b''
                110     LOAD_CONST                      6: ''
                112     KW_NAMES                        7: ('peer', 'id', 'option', 'message')
                114     CALL                            4
                122     CALL                            1
                130     STORE_FAST                      7: _var_var_18
                132     LOAD_GLOBAL                     7: NULL + int
                142     LOAD_FAST                       3: reason_send
                144     CALL                            1
                152     LOAD_CONST                      8: 10
                154     COMPARE_OP                      40 (==)
                158     POP_JUMP_IF_FALSE               43 (to 246)
                160     PUSH_NULL                       
                162     LOAD_FAST                       0: client
                164     LOAD_GLOBAL                     0: functions
                174     LOAD_ATTR                       2: messages
                194     LOAD_ATTR                       5: ReportRequest
                214     LOAD_FAST                       1: target_peer
                216     LOAD_FAST                       2: mess_id
                218     LOAD_CONST                      9: b'a'
                220     LOAD_FAST                       4: reason_mess_send
                222     KW_NAMES                        7: ('peer', 'id', 'option', 'message')
                224     CALL                            4
                232     CALL                            1
                240     STORE_FAST                      6: _var_var_17
                242     JUMP_FORWARD                    457 (to 1160)
                246     LOAD_GLOBAL                     7: NULL + int
                256     LOAD_FAST                       3: reason_send
                258     CALL                            1
                266     LOAD_CONST                      10: 11
                268     COMPARE_OP                      40 (==)
                272     POP_JUMP_IF_FALSE               43 (to 360)
                274     PUSH_NULL                       
                276     LOAD_FAST                       0: client
                278     LOAD_GLOBAL                     0: functions
                288     LOAD_ATTR                       2: messages
                308     LOAD_ATTR                       5: ReportRequest
                328     LOAD_FAST                       1: target_peer
                330     LOAD_FAST                       2: mess_id
                332     LOAD_CONST                      11: b'b'
                334     LOAD_FAST                       4: reason_mess_send
                336     KW_NAMES                        7: ('peer', 'id', 'option', 'message')
                338     CALL                            4
                346     CALL                            1
                354     STORE_FAST                      6: _var_var_17
                356     JUMP_FORWARD                    400 (to 1160)
                360     LOAD_GLOBAL                     7: NULL + int
                370     LOAD_FAST                       3: reason_send
                372     CALL                            1
                380     LOAD_CONST                      12: 1
                382     COMPARE_OP                      40 (==)
                386     POP_JUMP_IF_FALSE               60 (to 508)
                388     LOAD_FAST                       3: reason_send
                390     LOAD_ATTR                       9: encode
                410     LOAD_CONST                      13: 'utf-8'
                412     CALL                            1
                420     STORE_FAST                      8: _var_var_19
                422     PUSH_NULL                       
                424     LOAD_FAST                       0: client
                426     LOAD_GLOBAL                     0: functions
                436     LOAD_ATTR                       2: messages
                456     LOAD_ATTR                       5: ReportRequest
                476     LOAD_FAST                       1: target_peer
                478     LOAD_FAST                       2: mess_id
                480     LOAD_FAST                       8: _var_var_19
                482     LOAD_CONST                      6: ''
                484     KW_NAMES                        7: ('peer', 'id', 'option', 'message')
                486     CALL                            4
                494     CALL                            1
                502     STORE_FAST                      6: _var_var_17
                504     JUMP_FORWARD                    326 (to 1160)
                508     LOAD_GLOBAL                     7: NULL + int
                518     LOAD_FAST                       3: reason_send
                520     CALL                            1
                528     LOAD_CONST                      8: 10
                530     COMPARE_OP                      2 (<)
                534     POP_JUMP_IF_FALSE               126 (to 788)
                536     LOAD_GLOBAL                     7: NULL + int
                546     LOAD_FAST                       3: reason_send
                548     CALL                            1
                556     LOAD_CONST                      12: 1
                558     COMPARE_OP                      55 (!=)
                562     POP_JUMP_IF_FALSE               112 (to 788)
                564     LOAD_FAST                       3: reason_send
                566     LOAD_ATTR                       9: encode
                586     LOAD_CONST                      13: 'utf-8'
                588     CALL                            1
                596     STORE_FAST                      8: _var_var_19
                598     PUSH_NULL                       
                600     LOAD_FAST                       0: client
                602     LOAD_GLOBAL                     0: functions
                612     LOAD_ATTR                       2: messages
                632     LOAD_ATTR                       5: ReportRequest
                652     LOAD_FAST                       1: target_peer
                654     LOAD_FAST                       2: mess_id
                656     LOAD_FAST                       8: _var_var_19
                658     LOAD_CONST                      6: ''
                660     KW_NAMES                        7: ('peer', 'id', 'option', 'message')
                662     CALL                            4
                670     CALL                            1
                678     STORE_FAST                      7: _var_var_18
                680     LOAD_FAST                       7: _var_var_18
                682     LOAD_ATTR                       10: option
                702     STORE_FAST                      8: _var_var_19
                704     PUSH_NULL                       
                706     LOAD_FAST                       0: client
                708     LOAD_GLOBAL                     0: functions
                718     LOAD_ATTR                       2: messages
                738     LOAD_ATTR                       5: ReportRequest
                758     LOAD_FAST                       1: target_peer
                760     LOAD_FAST                       2: mess_id
                762     LOAD_FAST                       8: _var_var_19
                764     LOAD_FAST                       4: reason_mess_send
                766     KW_NAMES                        7: ('peer', 'id', 'option', 'message')
                768     CALL                            4
                776     CALL                            1
                784     STORE_FAST                      6: _var_var_17
                786     JUMP_FORWARD                    186 (to 1160)
                788     LOAD_GLOBAL                     7: NULL + int
                798     LOAD_FAST                       3: reason_send
                800     CALL                            1
                808     LOAD_CONST                      10: 11
                810     COMPARE_OP                      68 (>)
                814     POP_JUMP_IF_FALSE               172 (to 1160)
                816     LOAD_FAST                       3: reason_send
                818     LOAD_CONST                      14: 0
                820     BINARY_SUBSCR                   
                824     LOAD_ATTR                       9: encode
                844     LOAD_CONST                      13: 'utf-8'
                846     CALL                            1
                854     STORE_FAST                      8: _var_var_19
                856     PUSH_NULL                       
                858     LOAD_FAST                       0: client
                860     LOAD_GLOBAL                     0: functions
                870     LOAD_ATTR                       2: messages
                890     LOAD_ATTR                       5: ReportRequest
                910     LOAD_FAST                       1: target_peer
                912     LOAD_FAST                       2: mess_id
                914     LOAD_FAST                       8: _var_var_19
                916     LOAD_CONST                      6: ''
                918     KW_NAMES                        7: ('peer', 'id', 'option', 'message')
                920     CALL                            4
                928     CALL                            1
                936     STORE_FAST                      7: _var_var_18
                938     LOAD_FAST                       3: reason_send
                940     LOAD_ATTR                       9: encode
                960     LOAD_CONST                      13: 'utf-8'
                962     CALL                            1
                970     STORE_FAST                      8: _var_var_19
                972     PUSH_NULL                       
                974     LOAD_FAST                       0: client
                976     LOAD_GLOBAL                     0: functions
                986     LOAD_ATTR                       2: messages
                1006    LOAD_ATTR                       5: ReportRequest
                1026    LOAD_FAST                       1: target_peer
                1028    LOAD_FAST                       2: mess_id
                1030    LOAD_FAST                       8: _var_var_19
                1032    LOAD_CONST                      6: ''
                1034    KW_NAMES                        7: ('peer', 'id', 'option', 'message')
                1036    CALL                            4
                1044    CALL                            1
                1052    STORE_FAST                      7: _var_var_18
                1054    LOAD_FAST                       7: _var_var_18
                1056    LOAD_ATTR                       10: option
                1076    STORE_FAST                      8: _var_var_19
                1078    PUSH_NULL                       
                1080    LOAD_FAST                       0: client
                1082    LOAD_GLOBAL                     0: functions
                1092    LOAD_ATTR                       2: messages
                1112    LOAD_ATTR                       5: ReportRequest
                1132    LOAD_FAST                       1: target_peer
                1134    LOAD_FAST                       2: mess_id
                1136    LOAD_FAST                       8: _var_var_19
                1138    LOAD_FAST                       4: reason_mess_send
                1140    KW_NAMES                        7: ('peer', 'id', 'option', 'message')
                1142    CALL                            4
                1150    CALL                            1
                1158    STORE_FAST                      6: _var_var_17
                1160    LOAD_FAST                       6: _var_var_17
                1162    POP_JUMP_IF_FALSE               11 (to 1186)
                1164    NOP                             
                1166    LOAD_CONST                      16: 'Done'
                1168    NOP                             
                1170    NOP                             
                1172    NOP                             
                1174    JUMP_FORWARD                    52 (to 1280)
                1182    POP_TOP                         
                1184    RETURN_CONST                    16: 'Done'
                1186    NOP                             
                1188    LOAD_CONST                      17: 'NotDone'
                1190    NOP                             
                1192    NOP                             
                1194    NOP                             
                1196    JUMP_FORWARD                    41 (to 1280)
                1204    POP_TOP                         
                1206    RETURN_CONST                    17: 'NotDone'
                1208    PUSH_EXC_INFO                   
                1210    LOAD_GLOBAL                     12: Exception
                1220    CHECK_EXC_MATCH                 
                1222    POP_JUMP_IF_FALSE               10 (to 1244)
                1224    STORE_FAST                      9: _var_var_3
                1226    POP_EXCEPT                      
                1228    LOAD_CONST                      0: None
                1230    STORE_FAST                      9: _var_var_3
                1232    DELETE_FAST                     9: _var_var_3
                1234    JUMP_BACKWARD                   24 (to 1188)
                1236    LOAD_CONST                      0: None
                1238    STORE_FAST                      9: _var_var_3
                1240    DELETE_FAST                     9: _var_var_3
                1242    RERAISE                         1
                1244    RERAISE                         0
                1246    COPY                            3
                1248    POP_EXCEPT                      
                1250    RERAISE                         1
                1252    PUSH_EXC_INFO                   
                1254    PUSH_NULL                       
                1256    LOAD_CONST                      15: '__pyarmor_exit_14477__'
                1258    NOP                             
                1260    LOAD_CONST                      3: b'<COAddr>\x07\x00\x00\x1a\xca\x04\x00\x00\x00\x00\x00\x00\x00\x00\x00\x00\x00\x00\x00\x00'
                1262    CALL                            1
                1270    POP_TOP                         
                1272    RERAISE                         0
                1274    COPY                            3
                1276    POP_EXCEPT                      
                1278    RERAISE                         1
                1280    PUSH_NULL                       
                1282    LOAD_CONST                      15: '__pyarmor_exit_14477__'
                1284    LOAD_CONST                      3: b'<COAddr>\x07\x00\x00\x1a\xca\x04\x00\x00\x00\x00\x00\x00\x00\x00\x00\x00\x00\x00\x00\x00'
                1286    BUILD_TUPLE                     1
                1288    CALL_FUNCTION_EX                0
                1290    POP_TOP                         
                1292    RETURN_VALUE                    
            [Exception Table]
                30 to 1164 -> 1208 [0] 
                1186 to 1188 -> 1252 [0] 
                1208 to 1226 -> 1246 [1] lasti
                1226 to 1236 -> 1252 [0] 
                1236 to 1246 -> 1246 [1] lasti
                1246 to 1252 -> 1252 [0] 
                1252 to 1274 -> 1274 [1] lasti
        [Code]
            File Name: <frozen program.modules.Reporter>
            Object Name: send_report_photo
            Qualified Name: send_report_photo
            Arg Count: 5
            Pos Only Arg Count: 0
            KW Only Arg Count: 0
            Stack Size: 8
            Flags: 0x20000003 (CO_OPTIMIZED | CO_NEWLOCALS | CO_PYARMOR_OBFUSCATED)
            [Names]
                'int'
                'types'
                'InputReportReasonSpam'
                'InputReportReasonFake'
                'InputReportReasonViolence'
                'InputReportReasonChildAbuse'
                'InputReportReasonIllegalDrugs'
                'InputReportReasonPersonalDetails'
                'InputReportReasonPornography'
                'InputReportReasonOther'
                'functions'
                'account'
                'ReportProfilePhotoRequest'
                'Exception'
            [Locals+Names]
                'client'
                'target_peer'
                'user_photo'
                'reason_send'
                'reason_mess_send'
                '__assert_armored__'
                '_var_var_20'
                '_var_var_17'
                '_var_var_3'
            [Constants]
                None
                '__pyarmor_assert_14478__'
                '__pyarmor_enter_14479__'
                b'<COAddr>\x05\x00\x00\x1a\\\x02\x00\x00\x00\x00\x00\x00\x00\x00\x00\x00\x00\x00\x00\x00'
                1
                2
                3
                4
                5
                6
                7
                (
                    'peer'
                    'photo_id'
                    'reason'
                    'message'
                )
                '__pyarmor_exit_14480__'
                'Done'
                'NotDone'
            [Disassembly]
                0       NOP                             
                2       NOP                             
                4       PUSH_NULL                       
                6       LOAD_CONST                      2: '__pyarmor_enter_14479__'
                8       LOAD_CONST                      3: b'<COAddr>\x05\x00\x00\x1a\\\x02\x00\x00\x00\x00\x00\x00\x00\x00\x00\x00\x00\x00\x00\x00'
                10      BUILD_TUPLE                     1
                12      CALL_FUNCTION_EX                0
                14      POP_TOP                         
                16      RESUME                          0
                18      NOP                             
                20      NOP                             
                22      NOP                             
                24      NOP                             
                26      NOP                             
                28      NOP                             
                30      LOAD_GLOBAL                     1: NULL + int
                40      LOAD_FAST                       3: reason_send
                42      CALL                            1
                50      STORE_FAST                      3: reason_send
                52      LOAD_FAST                       3: reason_send
                54      LOAD_CONST                      4: 1
                56      COMPARE_OP                      40 (==)
                60      POP_JUMP_IF_FALSE               21 (to 104)
                62      LOAD_GLOBAL                     3: NULL + types
                72      LOAD_ATTR                       4: InputReportReasonSpam
                92      CALL                            0
                100     STORE_FAST                      6: _var_var_20
                102     JUMP_FORWARD                    176 (to 456)
                104     LOAD_FAST                       3: reason_send
                106     LOAD_CONST                      5: 2
                108     COMPARE_OP                      40 (==)
                112     POP_JUMP_IF_FALSE               21 (to 156)
                114     LOAD_GLOBAL                     3: NULL + types
                124     LOAD_ATTR                       6: InputReportReasonFake
                144     CALL                            0
                152     STORE_FAST                      6: _var_var_20
                154     JUMP_FORWARD                    150 (to 456)
                156     LOAD_FAST                       3: reason_send
                158     LOAD_CONST                      6: 3
                160     COMPARE_OP                      40 (==)
                164     POP_JUMP_IF_FALSE               21 (to 208)
                166     LOAD_GLOBAL                     3: NULL + types
                176     LOAD_ATTR                       8: InputReportReasonViolence
                196     CALL                            0
                204     STORE_FAST                      6: _var_var_20
                206     JUMP_FORWARD                    124 (to 456)
                208     LOAD_FAST                       3: reason_send
                210     LOAD_CONST                      7: 4
                212     COMPARE_OP                      40 (==)
                216     POP_JUMP_IF_FALSE               21 (to 260)
                218     LOAD_GLOBAL                     3: NULL + types
                228     LOAD_ATTR                       10: InputReportReasonChildAbuse
                248     CALL                            0
                256     STORE_FAST                      6: _var_var_20
                258     JUMP_FORWARD                    98 (to 456)
                260     LOAD_FAST                       3: reason_send
                262     LOAD_CONST                      8: 5
                264     COMPARE_OP                      40 (==)
                268     POP_JUMP_IF_FALSE               21 (to 312)
                270     LOAD_GLOBAL                     3: NULL + types
                280     LOAD_ATTR                       12: InputReportReasonIllegalDrugs
                300     CALL                            0
                308     STORE_FAST                      6: _var_var_20
                310     JUMP_FORWARD                    72 (to 456)
                312     LOAD_FAST                       3: reason_send
                314     LOAD_CONST                      9: 6
                316     COMPARE_OP                      40 (==)
                320     POP_JUMP_IF_FALSE               21 (to 364)
                322     LOAD_GLOBAL                     3: NULL + types
                332     LOAD_ATTR                       14: InputReportReasonPersonalDetails
                352     CALL                            0
                360     STORE_FAST                      6: _var_var_20
                362     JUMP_FORWARD                    46 (to 456)
                364     LOAD_FAST                       3: reason_send
                366     LOAD_CONST                      10: 7
                368     COMPARE_OP                      40 (==)
                372     POP_JUMP_IF_FALSE               21 (to 416)
                374     LOAD_GLOBAL                     3: NULL + types
                384     LOAD_ATTR                       16: InputReportReasonPornography
                404     CALL                            0
                412     STORE_FAST                      6: _var_var_20
                414     JUMP_FORWARD                    20 (to 456)
                416     LOAD_GLOBAL                     3: NULL + types
                426     LOAD_ATTR                       18: InputReportReasonOther
                446     CALL                            0
                454     STORE_FAST                      6: _var_var_20
                456     PUSH_NULL                       
                458     LOAD_FAST                       0: client
                460     LOAD_GLOBAL                     20: functions
                470     LOAD_ATTR                       22: account
                490     LOAD_ATTR                       25: ReportProfilePhotoRequest
                510     LOAD_FAST                       1: target_peer
                512     LOAD_FAST                       2: user_photo
                514     LOAD_FAST                       6: _var_var_20
                516     LOAD_FAST                       4: reason_mess_send
                518     KW_NAMES                        11: ('peer', 'photo_id', 'reason', 'message')
                520     CALL                            4
                528     CALL                            1
                536     STORE_FAST                      7: _var_var_17
                538     LOAD_FAST                       7: _var_var_17
                540     POP_JUMP_IF_FALSE               11 (to 564)
                542     NOP                             
                544     LOAD_CONST                      13: 'Done'
                546     NOP                             
                548     NOP                             
                550     NOP                             
                552     JUMP_FORWARD                    52 (to 658)
                560     POP_TOP                         
                562     RETURN_CONST                    13: 'Done'
                564     NOP                             
                566     LOAD_CONST                      14: 'NotDone'
                568     NOP                             
                570     NOP                             
                572     NOP                             
                574     JUMP_FORWARD                    41 (to 658)
                582     POP_TOP                         
                584     RETURN_CONST                    14: 'NotDone'
                586     PUSH_EXC_INFO                   
                588     LOAD_GLOBAL                     26: Exception
                598     CHECK_EXC_MATCH                 
                600     POP_JUMP_IF_FALSE               10 (to 622)
                602     STORE_FAST                      8: _var_var_3
                604     POP_EXCEPT                      
                606     LOAD_CONST                      0: None
                608     STORE_FAST                      8: _var_var_3
                610     DELETE_FAST                     8: _var_var_3
                612     JUMP_BACKWARD                   24 (to 566)
                614     LOAD_CONST                      0: None
                616     STORE_FAST                      8: _var_var_3
                618     DELETE_FAST                     8: _var_var_3
                620     RERAISE                         1
                622     RERAISE                         0
                624     COPY                            3
                626     POP_EXCEPT                      
                628     RERAISE                         1
                630     PUSH_EXC_INFO                   
                632     PUSH_NULL                       
                634     LOAD_CONST                      12: '__pyarmor_exit_14480__'
                636     NOP                             
                638     LOAD_CONST                      3: b'<COAddr>\x05\x00\x00\x1a\\\x02\x00\x00\x00\x00\x00\x00\x00\x00\x00\x00\x00\x00\x00\x00'
                640     CALL                            1
                648     POP_TOP                         
                650     RERAISE                         0
                652     COPY                            3
                654     POP_EXCEPT                      
                656     RERAISE                         1
                658     PUSH_NULL                       
                660     LOAD_CONST                      12: '__pyarmor_exit_14480__'
                662     LOAD_CONST                      3: b'<COAddr>\x05\x00\x00\x1a\\\x02\x00\x00\x00\x00\x00\x00\x00\x00\x00\x00\x00\x00\x00\x00'
                664     BUILD_TUPLE                     1
                666     CALL_FUNCTION_EX                0
                668     POP_TOP                         
                670     RETURN_VALUE                    
            [Exception Table]
                30 to 542 -> 586 [0] 
                564 to 566 -> 630 [0] 
                586 to 604 -> 624 [1] lasti
                604 to 614 -> 630 [0] 
                614 to 624 -> 624 [1] lasti
                624 to 630 -> 630 [0] 
                630 to 652 -> 652 [1] lasti
        [Code]
            File Name: <frozen program.modules.Reporter>
            Object Name: worker_mess
            Qualified Name: worker_mess
            Arg Count: 6
            Pos Only Arg Count: 0
            KW Only Arg Count: 0
            Stack Size: 10
            Flags: 0x20000003 (CO_OPTIMIZED | CO_NEWLOCALS | CO_PYARMOR_OBFUSCATED)
            [Names]
                'Thread_wait'
                'account_works'
                'Lang'
                'Disconnect'
                'Logs'
                'PrintLog'
                'get'
                'int'
                'db_reporter'
                'is_set'
                'StopProgram'
                'is_connected'
                'connect'
                'tg_links'
                'get_data'
                'get_entity'
                'hasattr'
                'bot'
                'send_message'
                'random'
                'choice'
                'get_reason_name'
                'spintax'
                'spin'
                'send_report'
                'functions'
                'messages'
                'GetMessagesViewsRequest'
                'insert'
                'DelayOnline'
                'iter_messages'
                'id'
                'errors'
                'FloodWaitError'
                'seconds'
                'randint'
                'Exception'
                'logging'
                'type'
                '__name__'
                'BaseException'
            [Locals+Names]
                'account'
                'config'
                'proxy'
                'data'
                'db_result'
                'stop_thread'
                '__assert_armored__'
                '_var_var_21'
                '_var_var_22'
                '_var_var_5'
                '_var_var_23'
                '_var_var_20'
                '_var_var_24'
                '_var_var_25'
                '_var_var_26'
                '_var_var_27'
                '_var_var_28'
                '_var_var_29'
                '_var_var_30'
                '_var_var_31'
                '_var_var_32'
                '_var_var_33'
                '_var_var_34'
                '_var_var_35'
                '_var_var_36'
                '_var_var_37'
                '_var_var_38'
                '_var_var_3'
                '_var_var_39'
            [Constants]
                None
                '__pyarmor_assert_14481__'
                '__pyarmor_enter_14482__'
                b'<COAddr>\x05\x00\x00\x1ab\r\x00\x00\x00\x00\x00\x00\x00\x00\x00\x00\x00\x00\x00\x00'
                'Reporter'
                (
                    'module'
                )
                False
                'error'
                (
                    'account'
                    'status'
                )
                'work_account_completed'   # b'\x81\xf5\x17\x018\xc5\xbf\xd1\x18\xf5\x18\xcex\xd3\xfb\x8a\x02M\xb7\xa2\xbe\xceJ'
                (
                    'config'
                    'account'
                    'message'
                )
                'done'
                '__pyarmor_exit_14483__'
                'Settings'
                'usernames'   # b'\x81\xf7\x0b\x16!\xf4\xbf\xdf\x1e\xe9'
                'target'
                'option'
                'reason'
                'reason_message'   # b'\x81\xf0\x1d\x12 \xf5\xb0\xed\x16\xff\x1e\xd3m\xeb\xfd'
                ''
                'mess_count'   # b'\x81\xef\x1d\x00 \xc5\xbd\xdd\x0e\xf4\x19'
                1
                'wait_from'   # b"\x81\xf5\x19\x1a'\xc5\xb8\xc0\x14\xf7"
                'wait_to'
                'max_flood_wait'   # b'\x81\xef\x19\x0b\x0c\xfc\xb2\xdd\x14\xfe2\xd7m\xe5\xec'
                'all'
                'last'
                'NotDone'
                'username'
                'id'
                'bot'
                '/start'
                'mess_id'
                True
                (
                    'peer'
                    'id'
                    'increment'
                )
                'status: '
                (
                    'config'
                    'account'
                    'message'
                    'param'
                    'end'
                )
                (
                    'entity'
                    'limit'
                    'filter'
                )
                '/'
                'restriction_detected'   # b"\x81\xf0\x1d\x00'\xe8\xb7\xd1\x0f\xf3\x02\xceS\xe8\xfd\x91\n^\xaf\xa2\xae"
                'algorithm_running'   # b'\x81\xe3\x14\x14<\xe8\xb7\xc6\x13\xf72\xd2y\xe2\xf6\x8c\x01Z'
                'flood_wait_more'   # b'\x81\xe4\x14\x1c<\xfe\x81\xc5\x1a\xf3\x19\xffa\xe3\xea\x80'
                (
                    'config'
                    'account'
                    'message'
                    'param'
                )
                'work_stopped'   # b'\x81\xf5\x17\x018\xc5\xad\xc6\x14\xea\x1d\xc5h'
                5
                15
                'flood_wait_bypass'   # b'\x81\xe4\x14\x1c<\xfe\x81\xc5\x1a\xf3\x19\xffn\xf5\xe8\x84\x1cN'
            [Disassembly]
                0       NOP                             
                2       NOP                             
                4       PUSH_NULL                       
                6       LOAD_CONST                      2: '__pyarmor_enter_14482__'
                8       LOAD_CONST                      3: b'<COAddr>\x05\x00\x00\x1ab\r\x00\x00\x00\x00\x00\x00\x00\x00\x00\x00\x00\x00\x00\x00'
                10      BUILD_TUPLE                     1
                12      CALL_FUNCTION_EX                0
                14      POP_TOP                         
                16      RESUME                          0
                18      NOP                             
                20      NOP                             
                22      NOP                             
                24      NOP                             
                26      NOP                             
                28      NOP                             
                30      LOAD_GLOBAL                     1: NULL + Thread_wait
                40      LOAD_FAST                       3: data
                42      LOAD_FAST                       1: config
                44      LOAD_FAST                       5: stop_thread
                46      CALL                            3
                54      POP_TOP                         
                56      LOAD_GLOBAL                     3: NULL + account_works
                66      LOAD_FAST                       1: config
                68      LOAD_GLOBAL                     4: Lang
                78      LOAD_FAST                       2: proxy
                80      LOAD_FAST                       0: account
                82      LOAD_FAST                       5: stop_thread
                84      LOAD_CONST                      4: 'Reporter'
                86      KW_NAMES                        5: ('module',)
                88      CALL                            6
                96      STORE_FAST                      7: _var_var_21
                98      LOAD_FAST                       7: _var_var_21
                100     LOAD_CONST                      6: False
                102     COMPARE_OP                      40 (==)
                106     POP_JUMP_IF_FALSE               68 (to 244)
                108     LOAD_FAST                       0: account
                110     LOAD_CONST                      7: 'error'
                112     LOAD_CONST                      8: ('account', 'status')
                114     BUILD_CONST_KEY_MAP             2
                116     LOAD_GLOBAL                     7: NULL + Disconnect
                126     LOAD_FAST                       7: _var_var_21
                128     CALL                            1
                136     POP_TOP                         
                138     LOAD_GLOBAL                     9: NULL + Logs
                148     LOAD_ATTR                       10: PrintLog
                168     LOAD_FAST                       1: config
                170     LOAD_FAST                       0: account
                172     LOAD_GLOBAL                     4: Lang
                182     PUSH_NULL                       
                184     LOAD_CONST                      1: '__pyarmor_assert_14481__'
                186     LOAD_CONST                      9: 'work_account_completed'   # b'\x81\xf5\x17\x018\xc5\xbf\xd1\x18\xf5\x18\xcex\xd3\xfb\x8a\x02M\xb7\xa2\xbe\xceJ'
                188     CALL                            1
                196     BINARY_SUBSCR                   
                200     KW_NAMES                        10: ('config', 'account', 'message')
                202     CALL                            3
                210     POP_TOP                         
                212     LOAD_FAST                       0: account
                214     LOAD_CONST                      11: 'done'
                216     LOAD_CONST                      8: ('account', 'status')
                218     BUILD_CONST_KEY_MAP             2
                220     SWAP                            2
                222     POP_TOP                         
                224     NOP                             
                226     NOP                             
                228     JUMP_FORWARD                    1624 (to 3480)
                232     CALL                            1
                240     POP_TOP                         
                242     RETURN_VALUE                    
                244     LOAD_FAST                       3: data
                246     LOAD_CONST                      13: 'Settings'
                248     BINARY_SUBSCR                   
                252     LOAD_ATTR                       13: get
                272     PUSH_NULL                       
                274     LOAD_CONST                      1: '__pyarmor_assert_14481__'
                276     LOAD_CONST                      14: 'usernames'   # b'\x81\xf7\x0b\x16!\xf4\xbf\xdf\x1e\xe9'
                278     CALL                            1
                286     BUILD_LIST                      0
                288     CALL                            2
                296     STORE_FAST                      8: _var_var_22
                298     LOAD_FAST                       3: data
                300     LOAD_CONST                      13: 'Settings'
                302     BINARY_SUBSCR                   
                306     LOAD_ATTR                       13: get
                326     LOAD_CONST                      15: 'target'
                328     CALL                            1
                336     STORE_FAST                      9: _var_var_5
                338     LOAD_FAST                       3: data
                340     LOAD_CONST                      13: 'Settings'
                342     BINARY_SUBSCR                   
                346     LOAD_ATTR                       13: get
                366     LOAD_CONST                      16: 'option'
                368     BUILD_LIST                      0
                370     CALL                            2
                378     STORE_FAST                      10: _var_var_23
                380     LOAD_FAST                       3: data
                382     LOAD_CONST                      13: 'Settings'
                384     BINARY_SUBSCR                   
                388     LOAD_ATTR                       13: get
                408     LOAD_CONST                      17: 'reason'
                410     BUILD_LIST                      0
                412     CALL                            2
                420     STORE_FAST                      11: _var_var_20
                422     LOAD_FAST                       3: data
                424     LOAD_CONST                      13: 'Settings'
                426     BINARY_SUBSCR                   
                430     LOAD_ATTR                       13: get
                450     PUSH_NULL                       
                452     LOAD_CONST                      1: '__pyarmor_assert_14481__'
                454     LOAD_CONST                      18: 'reason_message'   # b'\x81\xf0\x1d\x12 \xf5\xb0\xed\x16\xff\x1e\xd3m\xeb\xfd'
                456     CALL                            1
                464     LOAD_CONST                      19: ''
                466     CALL                            2
                474     STORE_FAST                      12: _var_var_24
                476     LOAD_FAST                       3: data
                478     LOAD_CONST                      13: 'Settings'
                480     BINARY_SUBSCR                   
                484     LOAD_ATTR                       13: get
                504     PUSH_NULL                       
                506     LOAD_CONST                      1: '__pyarmor_assert_14481__'
                508     LOAD_CONST                      20: 'mess_count'   # b'\x81\xef\x1d\x00 \xc5\xbd\xdd\x0e\xf4\x19'
                510     CALL                            1
                518     LOAD_CONST                      21: 1
                520     CALL                            2
                528     STORE_FAST                      13: _var_var_25
                530     LOAD_FAST                       3: data
                532     LOAD_CONST                      13: 'Settings'
                534     BINARY_SUBSCR                   
                538     LOAD_ATTR                       13: get
                558     PUSH_NULL                       
                560     LOAD_CONST                      1: '__pyarmor_assert_14481__'
                562     LOAD_CONST                      22: 'wait_from'   # b"\x81\xf5\x19\x1a'\xc5\xb8\xc0\x14\xf7"
                564     CALL                            1
                572     CALL                            1
                580     STORE_FAST                      14: _var_var_26
                582     LOAD_FAST                       3: data
                584     LOAD_CONST                      13: 'Settings'
                586     BINARY_SUBSCR                   
                590     LOAD_ATTR                       13: get
                610     LOAD_CONST                      23: 'wait_to'
                612     CALL                            1
                620     STORE_FAST                      15: _var_var_27
                622     LOAD_FAST                       3: data
                624     LOAD_CONST                      13: 'Settings'
                626     BINARY_SUBSCR                   
                630     LOAD_ATTR                       13: get
                650     PUSH_NULL                       
                652     LOAD_CONST                      1: '__pyarmor_assert_14481__'
                654     LOAD_CONST                      24: 'max_flood_wait'   # b'\x81\xef\x19\x0b\x0c\xfc\xb2\xdd\x14\xfe2\xd7m\xe5\xec'
                656     CALL                            1
                664     CALL                            1
                672     STORE_FAST                      16: _var_var_28
                674     LOAD_FAST                       10: _var_var_23
                676     LOAD_CONST                      25: 'all'
                678     COMPARE_OP                      40 (==)
                682     POP_JUMP_IF_FALSE               11 (to 706)
                684     LOAD_GLOBAL                     15: NULL + int
                694     LOAD_FAST                       13: _var_var_25
                696     CALL                            1
                704     STORE_FAST                      17: _var_var_29
                706     LOAD_FAST                       10: _var_var_23
                708     LOAD_CONST                      26: 'last'
                710     COMPARE_OP                      40 (==)
                714     POP_JUMP_IF_FALSE               2 (to 720)
                716     LOAD_CONST                      21: 1
                718     STORE_FAST                      17: _var_var_29
                720     LOAD_GLOBAL                     17: NULL + db_reporter
                730     LOAD_FAST                       4: db_result
                732     CALL                            1
                740     STORE_FAST                      18: _var_var_30
                742     LOAD_FAST                       8: _var_var_22
                744     GET_ITER                        
                746     FOR_ITER                        741 (to 2232)
                752     STORE_FAST                      19: _var_var_31
                754     LOAD_FAST                       5: stop_thread
                756     LOAD_ATTR                       19: is_set
                776     CALL                            0
                784     POP_JUMP_IF_FALSE               10 (to 806)
                786     LOAD_GLOBAL                     21: NULL + StopProgram
                796     CALL                            0
                804     RAISE_VARARGS                   1
                806     LOAD_FAST                       7: _var_var_21
                808     LOAD_ATTR                       23: is_connected
                828     CALL                            0
                836     POP_JUMP_IF_TRUE                16 (to 870)
                838     LOAD_FAST                       7: _var_var_21
                840     LOAD_ATTR                       25: connect
                860     CALL                            0
                868     POP_TOP                         
                870     LOAD_CONST                      27: 'NotDone'
                872     STORE_FAST                      20: _var_var_32
                874     LOAD_CONST                      19: ''
                876     STORE_FAST                      21: _var_var_33
                878     LOAD_CONST                      19: ''
                880     STORE_FAST                      22: _var_var_34
                882     NOP                             
                884     LOAD_GLOBAL                     27: NULL + tg_links
                894     LOAD_ATTR                       28: get_data
                914     LOAD_FAST                       19: _var_var_31
                916     CALL                            1
                924     STORE_FAST                      23: _var_var_35
                926     LOAD_FAST                       23: _var_var_35
                928     LOAD_CONST                      28: 'username'
                930     BINARY_SUBSCR                   
                934     POP_JUMP_IF_FALSE               21 (to 978)
                936     LOAD_FAST                       7: _var_var_21
                938     LOAD_ATTR                       31: get_entity
                958     LOAD_FAST                       23: _var_var_35
                960     LOAD_CONST                      28: 'username'
                962     BINARY_SUBSCR                   
                966     CALL                            1
                974     STORE_FAST                      24: _var_var_36
                976     JUMP_FORWARD                    20 (to 1018)
                978     LOAD_FAST                       7: _var_var_21
                980     LOAD_ATTR                       31: get_entity
                1000    LOAD_FAST                       23: _var_var_35
                1002    LOAD_CONST                      29: 'id'
                1004    BINARY_SUBSCR                   
                1008    CALL                            1
                1016    STORE_FAST                      24: _var_var_36
                1018    LOAD_FAST                       24: _var_var_36
                1020    POP_JUMP_IF_TRUE                1 (to 1024)
                1022    JUMP_BACKWARD                   139 (to 746)
                1024    LOAD_GLOBAL                     33: NULL + hasattr
                1034    LOAD_FAST                       24: _var_var_36
                1036    LOAD_CONST                      30: 'bot'
                1038    CALL                            2
                1046    POP_JUMP_IF_FALSE               36 (to 1120)
                1048    LOAD_FAST                       24: _var_var_36
                1050    LOAD_ATTR                       34: bot
                1070    POP_JUMP_IF_FALSE               24 (to 1120)
                1072    LOAD_FAST                       9: _var_var_5
                1074    LOAD_CONST                      30: 'bot'
                1076    COMPARE_OP                      55 (!=)
                1080    POP_JUMP_IF_FALSE               19 (to 1120)
                1082    NOP                             
                1084    LOAD_FAST                       7: _var_var_21
                1086    LOAD_ATTR                       37: send_message
                1106    LOAD_FAST                       19: _var_var_31
                1108    LOAD_CONST                      31: '/start'
                1110    CALL                            2
                1118    POP_TOP                         
                1120    LOAD_GLOBAL                     39: NULL + random
                1130    LOAD_ATTR                       40: choice
                1150    LOAD_FAST                       11: _var_var_20
                1152    CALL                            1
                1160    STORE_FAST                      25: _var_var_37
                1162    LOAD_GLOBAL                     43: NULL + get_reason_name
                1172    LOAD_FAST                       25: _var_var_37
                1174    CALL                            1
                1182    STORE_FAST                      21: _var_var_33
                1184    LOAD_GLOBAL                     45: NULL + spintax
                1194    LOAD_ATTR                       46: spin
                1214    LOAD_FAST                       12: _var_var_24
                1216    CALL                            1
                1224    STORE_FAST                      22: _var_var_34
                1226    LOAD_FAST                       23: _var_var_35
                1228    LOAD_CONST                      32: 'mess_id'
                1230    BINARY_SUBSCR                   
                1234    LOAD_CONST                      0: None
                1236    COMPARE_OP                      55 (!=)
                1240    POP_JUMP_IF_FALSE               129 (to 1500)
                1242    LOAD_GLOBAL                     49: NULL + send_report
                1252    LOAD_FAST                       7: _var_var_21
                1254    LOAD_FAST                       24: _var_var_36
                1256    LOAD_FAST                       23: _var_var_35
                1258    LOAD_CONST                      32: 'mess_id'
                1260    BINARY_SUBSCR                   
                1264    LOAD_FAST                       25: _var_var_37
                1266    LOAD_FAST                       22: _var_var_34
                1268    CALL                            5
                1276    STORE_FAST                      20: _var_var_32
                1278    NOP                             
                1280    PUSH_NULL                       
                1282    LOAD_FAST                       7: _var_var_21
                1284    LOAD_GLOBAL                     50: functions
                1294    LOAD_ATTR                       52: messages
                1314    LOAD_ATTR                       55: GetMessagesViewsRequest
                1334    LOAD_FAST                       24: _var_var_36
                1336    LOAD_FAST                       23: _var_var_35
                1338    LOAD_CONST                      32: 'mess_id'
                1340    BINARY_SUBSCR                   
                1344    LOAD_CONST                      33: True
                1346    KW_NAMES                        34: ('peer', 'id', 'increment')
                1348    CALL                            3
                1356    CALL                            1
                1364    POP_TOP                         
                1366    LOAD_GLOBAL                     9: NULL + Logs
                1376    LOAD_ATTR                       10: PrintLog
                1396    LOAD_FAST                       1: config
                1398    LOAD_FAST                       0: account
                1400    LOAD_FAST                       19: _var_var_31
                1402    LOAD_FAST                       21: _var_var_33
                1404    LOAD_CONST                      35: 'status: '
                1406    LOAD_FAST                       20: _var_var_32
                1408    FORMAT_VALUE                    0 (FVC_NONE)
                1410    BUILD_STRING                    2
                1412    KW_NAMES                        36: ('config', 'account', 'message', 'param', 'end')
                1414    CALL                            5
                1422    POP_TOP                         
                1424    LOAD_FAST                       18: _var_var_30
                1426    LOAD_ATTR                       57: insert
                1446    LOAD_FAST                       0: account
                1448    LOAD_FAST                       19: _var_var_31
                1450    LOAD_FAST                       21: _var_var_33
                1452    LOAD_FAST                       22: _var_var_34
                1454    LOAD_FAST                       20: _var_var_32
                1456    CALL                            5
                1464    POP_TOP                         
                1466    LOAD_GLOBAL                     59: NULL + DelayOnline
                1476    LOAD_FAST                       0: account
                1478    LOAD_FAST                       7: _var_var_21
                1480    LOAD_FAST                       14: _var_var_26
                1482    LOAD_FAST                       15: _var_var_27
                1484    LOAD_FAST                       5: stop_thread
                1486    CALL                            5
                1494    POP_TOP                         
                1496    JUMP_FORWARD                    365 (to 2230)
                1500    LOAD_FAST                       9: _var_var_5
                1502    LOAD_CONST                      30: 'bot'
                1504    COMPARE_OP                      40 (==)
                1508    POP_JUMP_IF_FALSE               84 (to 1678)
                1510    LOAD_GLOBAL                     49: NULL + send_report
                1520    LOAD_FAST                       7: _var_var_21
                1522    LOAD_FAST                       24: _var_var_36
                1524    LOAD_CONST                      0: None
                1526    LOAD_FAST                       25: _var_var_37
                1528    LOAD_FAST                       22: _var_var_34
                1530    CALL                            5
                1538    STORE_FAST                      20: _var_var_32
                1540    LOAD_GLOBAL                     9: NULL + Logs
                1550    LOAD_ATTR                       10: PrintLog
                1570    LOAD_FAST                       1: config
                1572    LOAD_FAST                       0: account
                1574    LOAD_FAST                       19: _var_var_31
                1576    FORMAT_VALUE                    0 (FVC_NONE)
                1578    LOAD_FAST                       21: _var_var_33
                1580    LOAD_CONST                      35: 'status: '
                1582    LOAD_FAST                       20: _var_var_32
                1584    FORMAT_VALUE                    0 (FVC_NONE)
                1586    BUILD_STRING                    2
                1588    KW_NAMES                        36: ('config', 'account', 'message', 'param', 'end')
                1590    CALL                            5
                1598    POP_TOP                         
                1600    LOAD_FAST                       18: _var_var_30
                1602    LOAD_ATTR                       57: insert
                1622    LOAD_FAST                       0: account
                1624    LOAD_FAST                       19: _var_var_31
                1626    FORMAT_VALUE                    0 (FVC_NONE)
                1628    LOAD_FAST                       21: _var_var_33
                1630    LOAD_FAST                       22: _var_var_34
                1632    LOAD_FAST                       20: _var_var_32
                1634    CALL                            5
                1642    POP_TOP                         
                1644    LOAD_GLOBAL                     59: NULL + DelayOnline
                1654    LOAD_FAST                       0: account
                1656    LOAD_FAST                       7: _var_var_21
                1658    LOAD_FAST                       14: _var_var_26
                1660    LOAD_FAST                       15: _var_var_27
                1662    LOAD_FAST                       5: stop_thread
                1664    CALL                            5
                1672    POP_TOP                         
                1674    JUMP_FORWARD                    276 (to 2230)
                1678    LOAD_FAST                       7: _var_var_21
                1680    LOAD_ATTR                       61: iter_messages
                1700    LOAD_FAST                       24: _var_var_36
                1702    LOAD_FAST_CHECK                 17: _var_var_29
                1704    LOAD_CONST                      0: None
                1706    KW_NAMES                        37: ('entity', 'limit', 'filter')
                1708    CALL                            3
                1716    GET_ITER                        
                1718    FOR_ITER                        253 (to 2226)
                1722    STORE_FAST                      26: _var_var_38
                1724    LOAD_FAST                       5: stop_thread
                1726    LOAD_ATTR                       19: is_set
                1746    CALL                            0
                1754    POP_JUMP_IF_FALSE               10 (to 1776)
                1756    LOAD_GLOBAL                     21: NULL + StopProgram
                1766    CALL                            0
                1774    RAISE_VARARGS                   1
                1776    LOAD_GLOBAL                     39: NULL + random
                1786    LOAD_ATTR                       40: choice
                1806    LOAD_FAST                       11: _var_var_20
                1808    CALL                            1
                1816    STORE_FAST                      25: _var_var_37
                1818    LOAD_GLOBAL                     43: NULL + get_reason_name
                1828    LOAD_FAST                       25: _var_var_37
                1830    CALL                            1
                1838    STORE_FAST                      21: _var_var_33
                1840    LOAD_GLOBAL                     45: NULL + spintax
                1850    LOAD_ATTR                       46: spin
                1870    LOAD_FAST                       12: _var_var_24
                1872    CALL                            1
                1880    STORE_FAST                      22: _var_var_34
                1882    LOAD_GLOBAL                     49: NULL + send_report
                1892    LOAD_FAST                       7: _var_var_21
                1894    LOAD_FAST                       24: _var_var_36
                1896    LOAD_FAST                       26: _var_var_38
                1898    LOAD_ATTR                       62: id
                1918    LOAD_FAST                       25: _var_var_37
                1920    LOAD_FAST                       22: _var_var_34
                1922    CALL                            5
                1930    STORE_FAST                      20: _var_var_32
                1932    NOP                             
                1934    PUSH_NULL                       
                1936    LOAD_FAST                       7: _var_var_21
                1938    LOAD_GLOBAL                     50: functions
                1948    LOAD_ATTR                       52: messages
                1968    LOAD_ATTR                       55: GetMessagesViewsRequest
                1988    LOAD_FAST                       24: _var_var_36
                1990    LOAD_FAST                       26: _var_var_38
                1992    LOAD_ATTR                       62: id
                2012    BUILD_LIST                      1
                2014    LOAD_CONST                      33: True
                2016    KW_NAMES                        34: ('peer', 'id', 'increment')
                2018    CALL                            3
                2026    CALL                            1
                2034    POP_TOP                         
                2036    LOAD_GLOBAL                     9: NULL + Logs
                2046    LOAD_ATTR                       10: PrintLog
                2066    LOAD_FAST                       1: config
                2068    LOAD_FAST                       0: account
                2070    LOAD_FAST                       19: _var_var_31
                2072    FORMAT_VALUE                    0 (FVC_NONE)
                2074    LOAD_CONST                      38: '/'
                2076    LOAD_FAST                       26: _var_var_38
                2078    LOAD_ATTR                       62: id
                2098    FORMAT_VALUE                    0 (FVC_NONE)
                2100    BUILD_STRING                    3
                2102    LOAD_FAST                       21: _var_var_33
                2104    LOAD_CONST                      35: 'status: '
                2106    LOAD_FAST                       20: _var_var_32
                2108    FORMAT_VALUE                    0 (FVC_NONE)
                2110    BUILD_STRING                    2
                2112    KW_NAMES                        36: ('config', 'account', 'message', 'param', 'end')
                2114    CALL                            5
                2122    POP_TOP                         
                2124    LOAD_FAST                       18: _var_var_30
                2126    LOAD_ATTR                       57: insert
                2146    LOAD_FAST                       0: account
                2148    LOAD_FAST                       19: _var_var_31
                2150    FORMAT_VALUE                    0 (FVC_NONE)
                2152    LOAD_CONST                      38: '/'
                2154    LOAD_FAST                       26: _var_var_38
                2156    LOAD_ATTR                       62: id
                2176    FORMAT_VALUE                    0 (FVC_NONE)
                2178    BUILD_STRING                    3
                2180    LOAD_FAST                       21: _var_var_33
                2182    LOAD_FAST                       22: _var_var_34
                2184    LOAD_FAST                       20: _var_var_32
                2186    CALL                            5
                2194    POP_TOP                         
                2196    LOAD_GLOBAL                     59: NULL + DelayOnline
                2206    LOAD_FAST                       0: account
                2208    LOAD_FAST                       7: _var_var_21
                2210    LOAD_FAST                       14: _var_var_26
                2212    LOAD_FAST                       15: _var_var_27
                2214    LOAD_FAST                       5: stop_thread
                2216    CALL                            5
                2224    POP_TOP                         
                2226    JUMP_BACKWARD                   255 (to 1718)
                2228    END_FOR                         
                2230    JUMP_BACKWARD                   744 (to 746)
                2234    END_FOR                         
                2236    LOAD_GLOBAL                     7: NULL + Disconnect
                2246    LOAD_FAST_CHECK                 7: _var_var_21
                2248    CALL                            1
                2256    POP_TOP                         
                2258    LOAD_GLOBAL                     9: NULL + Logs
                2268    LOAD_ATTR                       10: PrintLog
                2288    LOAD_FAST                       1: config
                2290    LOAD_FAST                       0: account
                2292    LOAD_GLOBAL                     4: Lang
                2302    PUSH_NULL                       
                2304    LOAD_CONST                      1: '__pyarmor_assert_14481__'
                2306    LOAD_CONST                      9: 'work_account_completed'   # b'\x81\xf5\x17\x018\xc5\xbf\xd1\x18\xf5\x18\xcex\xd3\xfb\x8a\x02M\xb7\xa2\xbe\xceJ'
                2308    CALL                            1
                2316    BINARY_SUBSCR                   
                2320    KW_NAMES                        10: ('config', 'account', 'message')
                2322    CALL                            3
                2330    POP_TOP                         
                2332    LOAD_FAST                       0: account
                2334    LOAD_CONST                      11: 'done'
                2336    LOAD_CONST                      8: ('account', 'status')
                2338    BUILD_CONST_KEY_MAP             2
                2340    NOP                             
                2342    NOP                             
                2344    JUMP_FORWARD                    566 (to 3480)
                2348    CALL                            1
                2356    POP_TOP                         
                2358    RETURN_VALUE                    
                2360    PUSH_EXC_INFO                   
                2362    POP_TOP                         
                2364    POP_EXCEPT                      
                2366    JUMP_BACKWARD                   1116 (to 138)
                2370    COPY                            3
                2372    POP_EXCEPT                      
                2374    RERAISE                         1
                2376    PUSH_EXC_INFO                   
                2378    POP_TOP                         
                2380    POP_EXCEPT                      
                2382    JUMP_BACKWARD                   633 (to 1120)
                2386    COPY                            3
                2388    POP_EXCEPT                      
                2390    RERAISE                         1
                2392    PUSH_EXC_INFO                   
                2394    POP_TOP                         
                2396    POP_EXCEPT                      
                2398    JUMP_BACKWARD                   518 (to 1366)
                2402    COPY                            3
                2404    POP_EXCEPT                      
                2406    RERAISE                         1
                2408    PUSH_EXC_INFO                   
                2410    POP_TOP                         
                2412    POP_EXCEPT                      
                2414    JUMP_BACKWARD                   190 (to 2036)
                2416    COPY                            3
                2418    POP_EXCEPT                      
                2420    RERAISE                         1
                2422    PUSH_EXC_INFO                   
                2424    LOAD_GLOBAL                     20: StopProgram
                2434    CHECK_EXC_MATCH                 
                2436    POP_JUMP_IF_FALSE               2 (to 2442)
                2438    POP_TOP                         
                2440    RAISE_VARARGS                   0
                2442    LOAD_GLOBAL                     64: errors
                2452    LOAD_ATTR                       66: FloodWaitError
                2472    CHECK_EXC_MATCH                 
                2474    POP_JUMP_IF_FALSE               270 (to 3018)
                2478    STORE_FAST                      27: _var_var_3
                2480    LOAD_GLOBAL                     9: NULL + Logs
                2490    LOAD_ATTR                       10: PrintLog
                2510    LOAD_FAST                       1: config
                2512    LOAD_FAST                       0: account
                2514    LOAD_GLOBAL                     4: Lang
                2524    PUSH_NULL                       
                2526    LOAD_CONST                      1: '__pyarmor_assert_14481__'
                2528    LOAD_CONST                      39: 'restriction_detected'   # b"\x81\xf0\x1d\x00'\xe8\xb7\xd1\x0f\xf3\x02\xceS\xe8\xfd\x91\n^\xaf\xa2\xae"
                2530    CALL                            1
                2538    BINARY_SUBSCR                   
                2542    KW_NAMES                        10: ('config', 'account', 'message')
                2544    CALL                            3
                2552    POP_TOP                         
                2554    LOAD_GLOBAL                     9: NULL + Logs
                2564    LOAD_ATTR                       10: PrintLog
                2584    LOAD_FAST                       1: config
                2586    LOAD_FAST                       0: account
                2588    LOAD_GLOBAL                     4: Lang
                2598    PUSH_NULL                       
                2600    LOAD_CONST                      1: '__pyarmor_assert_14481__'
                2602    LOAD_CONST                      40: 'algorithm_running'   # b'\x81\xe3\x14\x14<\xe8\xb7\xc6\x13\xf72\xd2y\xe2\xf6\x8c\x01Z'
                2604    CALL                            1
                2612    BINARY_SUBSCR                   
                2616    KW_NAMES                        10: ('config', 'account', 'message')
                2618    CALL                            3
                2626    POP_TOP                         
                2628    LOAD_FAST                       27: _var_var_3
                2630    LOAD_ATTR                       68: seconds
                2650    LOAD_FAST                       16: _var_var_28
                2652    COMPARE_OP                      68 (>)
                2656    POP_JUMP_IF_FALSE               82 (to 2822)
                2658    LOAD_GLOBAL                     9: NULL + Logs
                2668    LOAD_ATTR                       10: PrintLog
                2688    LOAD_FAST                       1: config
                2690    LOAD_FAST                       0: account
                2692    LOAD_GLOBAL                     4: Lang
                2702    PUSH_NULL                       
                2704    LOAD_CONST                      1: '__pyarmor_assert_14481__'
                2706    LOAD_CONST                      41: 'flood_wait_more'   # b'\x81\xe4\x14\x1c<\xfe\x81\xc5\x1a\xf3\x19\xffa\xe3\xea\x80'
                2708    CALL                            1
                2716    BINARY_SUBSCR                   
                2720    LOAD_FAST                       16: _var_var_28
                2722    KW_NAMES                        42: ('config', 'account', 'message', 'param')
                2724    CALL                            4
                2732    POP_TOP                         
                2734    LOAD_GLOBAL                     9: NULL + Logs
                2744    LOAD_ATTR                       10: PrintLog
                2764    LOAD_FAST                       1: config
                2766    LOAD_FAST                       0: account
                2768    LOAD_GLOBAL                     4: Lang
                2778    PUSH_NULL                       
                2780    LOAD_CONST                      1: '__pyarmor_assert_14481__'
                2782    LOAD_CONST                      43: 'work_stopped'   # b'\x81\xf5\x17\x018\xc5\xad\xc6\x14\xea\x1d\xc5h'
                2784    CALL                            1
                2792    BINARY_SUBSCR                   
                2796    KW_NAMES                        10: ('config', 'account', 'message')
                2798    CALL                            3
                2806    POP_TOP                         
                2808    POP_EXCEPT                      
                2810    LOAD_CONST                      0: None
                2812    STORE_FAST                      27: _var_var_3
                2814    DELETE_FAST                     27: _var_var_3
                2816    POP_TOP                         
                2818    JUMP_BACKWARD                   293 (to 2236)
                2822    LOAD_FAST                       27: _var_var_3
                2824    LOAD_ATTR                       68: seconds
                2844    LOAD_GLOBAL                     39: NULL + random
                2854    LOAD_ATTR                       70: randint
                2874    LOAD_CONST                      44: 5
                2876    LOAD_CONST                      45: 15
                2878    CALL                            2
                2886    BINARY_OP                       0 (+)
                2890    STORE_FAST                      28: _var_var_39
                2892    LOAD_GLOBAL                     9: NULL + Logs
                2902    LOAD_ATTR                       10: PrintLog
                2922    LOAD_FAST                       1: config
                2924    LOAD_FAST                       0: account
                2926    LOAD_GLOBAL                     4: Lang
                2936    PUSH_NULL                       
                2938    LOAD_CONST                      1: '__pyarmor_assert_14481__'
                2940    LOAD_CONST                      46: 'flood_wait_bypass'   # b'\x81\xe4\x14\x1c<\xfe\x81\xc5\x1a\xf3\x19\xffn\xf5\xe8\x84\x1cN'
                2942    CALL                            1
                2950    BINARY_SUBSCR                   
                2954    LOAD_FAST                       28: _var_var_39
                2956    KW_NAMES                        42: ('config', 'account', 'message', 'param')
                2958    CALL                            4
                2966    POP_TOP                         
                2968    LOAD_GLOBAL                     59: NULL + DelayOnline
                2978    LOAD_FAST                       0: account
                2980    LOAD_FAST                       7: _var_var_21
                2982    LOAD_FAST                       28: _var_var_39
                2984    LOAD_FAST                       28: _var_var_39
                2986    LOAD_FAST                       5: stop_thread
                2988    CALL                            5
                2996    POP_TOP                         
                2998    POP_EXCEPT                      
                3000    LOAD_CONST                      0: None
                3002    STORE_FAST                      27: _var_var_3
                3004    DELETE_FAST                     27: _var_var_3
                3006    JUMP_BACKWARD                   1132 (to 746)
                3010    LOAD_CONST                      0: None
                3012    STORE_FAST                      27: _var_var_3
                3014    DELETE_FAST                     27: _var_var_3
                3016    RERAISE                         1
                3018    LOAD_GLOBAL                     72: Exception
                3028    CHECK_EXC_MATCH                 
                3030    POP_JUMP_IF_FALSE               70 (to 3172)
                3032    STORE_FAST                      27: _var_var_3
                3034    PUSH_NULL                       
                3036    LOAD_GLOBAL                     75: NULL + logging
                3046    LOAD_FAST                       27: _var_var_3
                3048    CALL                            1
                3056    CALL                            0
                3064    POP_TOP                         
                3066    LOAD_GLOBAL                     77: NULL + type
                3076    LOAD_FAST                       27: _var_var_3
                3078    CALL                            1
                3086    LOAD_ATTR                       78: __name__
                3106    FORMAT_VALUE                    0 (FVC_NONE)
                3108    STORE_FAST                      20: _var_var_32
                3110    LOAD_FAST                       18: _var_var_30
                3112    LOAD_ATTR                       57: insert
                3132    LOAD_FAST                       0: account
                3134    LOAD_FAST                       19: _var_var_31
                3136    LOAD_FAST                       21: _var_var_33
                3138    LOAD_FAST                       22: _var_var_34
                3140    LOAD_FAST                       20: _var_var_32
                3142    CALL                            5
                3150    POP_TOP                         
                3152    POP_EXCEPT                      
                3154    LOAD_CONST                      0: None
                3156    STORE_FAST                      27: _var_var_3
                3158    DELETE_FAST                     27: _var_var_3
                3160    JUMP_BACKWARD                   1209 (to 746)
                3164    LOAD_CONST                      0: None
                3166    STORE_FAST                      27: _var_var_3
                3168    DELETE_FAST                     27: _var_var_3
                3170    RERAISE                         1
                3172    RERAISE                         0
                3174    COPY                            3
                3176    POP_EXCEPT                      
                3178    RERAISE                         1
                3180    PUSH_EXC_INFO                   
                3182    LOAD_GLOBAL                     20: StopProgram
                3192    CHECK_EXC_MATCH                 
                3194    POP_JUMP_IF_FALSE               4 (to 3204)
                3196    POP_TOP                         
                3198    POP_EXCEPT                      
                3200    JUMP_BACKWARD                   484 (to 2236)
                3204    LOAD_GLOBAL                     80: BaseException
                3214    CHECK_EXC_MATCH                 
                3216    POP_JUMP_IF_FALSE               27 (to 3272)
                3218    STORE_FAST                      27: _var_var_3
                3220    PUSH_NULL                       
                3222    LOAD_GLOBAL                     75: NULL + logging
                3232    LOAD_FAST                       27: _var_var_3
                3234    CALL                            1
                3242    CALL                            0
                3250    POP_TOP                         
                3252    POP_EXCEPT                      
                3254    LOAD_CONST                      0: None
                3256    STORE_FAST                      27: _var_var_3
                3258    DELETE_FAST                     27: _var_var_3
                3260    JUMP_BACKWARD                   514 (to 2236)
                3264    LOAD_CONST                      0: None
                3266    STORE_FAST                      27: _var_var_3
                3268    DELETE_FAST                     27: _var_var_3
                3270    RERAISE                         1
                3272    RERAISE                         0
                3274    COPY                            3
                3276    POP_EXCEPT                      
                3278    RERAISE                         1
                3280    PUSH_EXC_INFO                   
                3282    POP_TOP                         
                3284    POP_EXCEPT                      
                3286    JUMP_BACKWARD                   516 (to 2258)
                3290    COPY                            3
                3292    POP_EXCEPT                      
                3294    RERAISE                         1
                3296    PUSH_EXC_INFO                   
                3298    LOAD_GLOBAL                     7: NULL + Disconnect
                3308    LOAD_FAST_CHECK                 7: _var_var_21
                3310    CALL                            1
                3318    POP_TOP                         
                3320    JUMP_FORWARD                    7 (to 3336)
                3322    PUSH_EXC_INFO                   
                3324    POP_TOP                         
                3326    POP_EXCEPT                      
                3328    JUMP_FORWARD                    3 (to 3336)
                3330    COPY                            3
                3332    POP_EXCEPT                      
                3334    RERAISE                         1
                3336    LOAD_GLOBAL                     9: NULL + Logs
                3346    LOAD_ATTR                       10: PrintLog
                3366    LOAD_FAST                       1: config
                3368    LOAD_FAST                       0: account
                3370    LOAD_GLOBAL                     4: Lang
                3380    PUSH_NULL                       
                3382    LOAD_CONST                      1: '__pyarmor_assert_14481__'
                3384    LOAD_CONST                      9: 'work_account_completed'   # b'\x81\xf5\x17\x018\xc5\xbf\xd1\x18\xf5\x18\xcex\xd3\xfb\x8a\x02M\xb7\xa2\xbe\xceJ'
                3386    CALL                            1
                3394    BINARY_SUBSCR                   
                3398    KW_NAMES                        10: ('config', 'account', 'message')
                3400    CALL                            3
                3408    POP_TOP                         
                3410    LOAD_FAST                       0: account
                3412    LOAD_CONST                      11: 'done'
                3414    LOAD_CONST                      8: ('account', 'status')
                3416    BUILD_CONST_KEY_MAP             2
                3418    SWAP                            2
                3420    POP_TOP                         
                3422    SWAP                            2
                3424    POP_EXCEPT                      
                3426    NOP                             
                3428    NOP                             
                3430    NOP                             
                3432    JUMP_FORWARD                    23 (to 3480)
                3434    CALL                            1
                3442    POP_TOP                         
                3444    RETURN_VALUE                    
                3446    COPY                            3
                3448    POP_EXCEPT                      
                3450    RERAISE                         1
                3452    PUSH_EXC_INFO                   
                3454    PUSH_NULL                       
                3456    LOAD_CONST                      12: '__pyarmor_exit_14483__'
                3458    NOP                             
                3460    LOAD_CONST                      3: b'<COAddr>\x05\x00\x00\x1ab\r\x00\x00\x00\x00\x00\x00\x00\x00\x00\x00\x00\x00\x00\x00'
                3462    CALL                            1
                3470    POP_TOP                         
                3472    RERAISE                         0
                3474    COPY                            3
                3476    POP_EXCEPT                      
                3478    RERAISE                         1
                3480    PUSH_NULL                       
                3482    LOAD_CONST                      12: '__pyarmor_exit_14483__'
                3484    LOAD_CONST                      3: b'<COAddr>\x05\x00\x00\x1ab\r\x00\x00\x00\x00\x00\x00\x00\x00\x00\x00\x00\x00\x00\x00'
                3486    BUILD_TUPLE                     1
                3488    CALL_FUNCTION_EX                0
                3490    POP_TOP                         
                3492    RETURN_VALUE                    
            [Exception Table]
                30 to 116 -> 3180 [0] 
                116 to 138 -> 2360 [1] 
                138 to 224 -> 3452 [0] 
                244 to 882 -> 3180 [0] 
                884 to 1022 -> 2422 [1] 
                1022 to 1024 -> 3180 [0] 
                1024 to 1082 -> 2422 [1] 
                1084 to 1120 -> 2376 [1] 
                1120 to 1278 -> 2422 [1] 
                1280 to 1366 -> 2392 [1] 
                1366 to 1932 -> 2422 [1] 
                1934 to 2036 -> 2408 [2] 
                2036 to 2230 -> 2422 [1] 
                2230 to 2236 -> 3180 [0] 
                2236 to 2258 -> 3280 [0] 
                2258 to 2340 -> 3452 [0] 
                2360 to 2364 -> 2370 [2] lasti
                2364 to 2376 -> 3452 [0] 
                2376 to 2380 -> 2386 [2] lasti
                2380 to 2392 -> 2422 [1] 
                2392 to 2396 -> 2402 [2] lasti
                2396 to 2408 -> 2422 [1] 
                2408 to 2412 -> 2416 [3] lasti
                2412 to 2422 -> 2422 [1] 
                2422 to 2480 -> 3174 [2] lasti
                2480 to 2808 -> 3010 [2] lasti
                2808 to 2822 -> 3180 [0] 
                2822 to 2998 -> 3010 [2] lasti
                2998 to 3010 -> 3180 [0] 
                3010 to 3034 -> 3174 [2] lasti
                3034 to 3152 -> 3164 [2] lasti
                3152 to 3164 -> 3180 [0] 
                3164 to 3174 -> 3174 [2] lasti
                3174 to 3180 -> 3180 [0] 
                3180 to 3198 -> 3274 [1] lasti
                3198 to 3204 -> 3296 [0] 
                3204 to 3220 -> 3274 [1] lasti
                3220 to 3252 -> 3264 [1] lasti
                3252 to 3264 -> 3296 [0] 
                3264 to 3274 -> 3274 [1] lasti
                3274 to 3280 -> 3296 [0] 
                3280 to 3284 -> 3290 [1] lasti
                3284 to 3296 -> 3452 [0] 
                3296 to 3298 -> 3446 [1] lasti
                3298 to 3320 -> 3322 [2] 
                3320 to 3322 -> 3446 [1] lasti
                3322 to 3326 -> 3330 [3] lasti
                3326 to 3424 -> 3446 [1] lasti
                3424 to 3426 -> 3452 [0] 
                3446 to 3452 -> 3452 [0] 
                3452 to 3474 -> 3474 [1] lasti
        [Code]
            File Name: <frozen program.modules.Reporter>
            Object Name: worker_photo
            Qualified Name: worker_photo
            Arg Count: 6
            Pos Only Arg Count: 0
            KW Only Arg Count: 0
            Stack Size: 10
            Flags: 0x20000003 (CO_OPTIMIZED | CO_NEWLOCALS | CO_PYARMOR_OBFUSCATED)
            [Names]
                'Thread_wait'
                'account_works'
                'Lang'
                'Disconnect'
                'Logs'
                'PrintLog'
                'get'
                'db_reporter'
                'is_set'
                'StopProgram'
                'is_connected'
                'connect'
                'tg_links'
                'get_data'
                'get_entity'
                'get_profile_photos'
                'int'
                'random'
                'choice'
                'get_reason_photo_name'
                'spintax'
                'spin'
                'send_report_photo'
                'insert'
                'DelayOnline'
                'errors'
                'FloodWaitError'
                'seconds'
                'randint'
                'Exception'
                'logging'
                'type'
                '__name__'
                'BaseException'
            [Locals+Names]
                'account'
                'config'
                'proxy'
                'data'
                'db_result'
                'stop_thread'
                '__assert_armored__'
                '_var_var_21'
                '_var_var_22'
                '_var_var_20'
                '_var_var_24'
                '_var_var_23'
                '_var_var_26'
                '_var_var_27'
                '_var_var_28'
                '_var_var_30'
                '_var_var_31'
                '_var_var_32'
                '_var_var_33'
                '_var_var_34'
                '_var_var_36'
                '_var_var_35'
                '_var_var_40'
                '_var_var_41'
                '_var_var_37'
                '_var_var_3'
                '_var_var_39'
            [Constants]
                None
                '__pyarmor_assert_14484__'
                '__pyarmor_enter_14485__'
                b'<COAddr>\x07\x00\x00\x1aB\t\x00\x00\x00\x00\x00\x00\x00\x00\x00\x00\x00\x00\x00\x00'
                'Reporter'
                (
                    'module'
                )
                False
                'error'
                (
                    'account'
                    'status'
                )
                'work_account_completed'   # b'\x81\xf5\x17\x018\xc5\xbf\xd1\x18\xf5\x18\xcex\xd3\xfb\x8a\x02M\xb7\xa2\xbe\xceJ'
                (
                    'config'
                    'account'
                    'message'
                )
                'done'
                '__pyarmor_exit_14486__'
                'Settings'
                'usernames'   # b'\x81\xf7\x0b\x16!\xf4\xbf\xdf\x1e\xe9'
                'reason_photo'   # b'\x81\xf0\x1d\x12 \xf5\xb0\xed\x0b\xf2\x02\xd4c'
                'reason_message'   # b'\x81\xf0\x1d\x12 \xf5\xb0\xed\x16\xff\x1e\xd3m\xeb\xfd'
                ''
                'option_photo'   # b'\x81\xed\x08\x07:\xf5\xb0\xed\x0b\xf2\x02\xd4c'
                'wait_from'   # b"\x81\xf5\x19\x1a'\xc5\xb8\xc0\x14\xf7"
                'wait_to'
                'max_flood_wait'   # b'\x81\xef\x19\x0b\x0c\xfc\xb2\xdd\x14\xfe2\xd7m\xe5\xec'
                'NotDone'
                'username'
                20
                (
                    'limit'
                )
                'status: '
                (
                    'config'
                    'account'
                    'message'
                    'param'
                    'end'
                )
                'one'
                'restriction_detected'   # b"\x81\xf0\x1d\x00'\xe8\xb7\xd1\x0f\xf3\x02\xceS\xe8\xfd\x91\n^\xaf\xa2\xae"
                'algorithm_running'   # b'\x81\xe3\x14\x14<\xe8\xb7\xc6\x13\xf72\xd2y\xe2\xf6\x8c\x01Z'
                'flood_wait_more'   # b'\x81\xe4\x14\x1c<\xfe\x81\xc5\x1a\xf3\x19\xffa\xe3\xea\x80'
                (
                    'config'
                    'account'
                    'message'
                    'param'
                )
                'work_stopped'   # b'\x81\xf5\x17\x018\xc5\xad\xc6\x14\xea\x1d\xc5h'
                5
                15
                'flood_wait_bypass'   # b'\x81\xe4\x14\x1c<\xfe\x81\xc5\x1a\xf3\x19\xffn\xf5\xe8\x84\x1cN'
            [Disassembly]
                0       NOP                             
                2       NOP                             
                4       PUSH_NULL                       
                6       LOAD_CONST                      2: '__pyarmor_enter_14485__'
                8       LOAD_CONST                      3: b'<COAddr>\x07\x00\x00\x1aB\t\x00\x00\x00\x00\x00\x00\x00\x00\x00\x00\x00\x00\x00\x00'
                10      BUILD_TUPLE                     1
                12      CALL_FUNCTION_EX                0
                14      POP_TOP                         
                16      RESUME                          0
                18      NOP                             
                20      NOP                             
                22      NOP                             
                24      NOP                             
                26      NOP                             
                28      NOP                             
                30      LOAD_GLOBAL                     1: NULL + Thread_wait
                40      LOAD_FAST                       3: data
                42      LOAD_FAST                       1: config
                44      LOAD_FAST                       5: stop_thread
                46      CALL                            3
                54      POP_TOP                         
                56      LOAD_GLOBAL                     3: NULL + account_works
                66      LOAD_FAST                       1: config
                68      LOAD_GLOBAL                     4: Lang
                78      LOAD_FAST                       2: proxy
                80      LOAD_FAST                       0: account
                82      LOAD_FAST                       5: stop_thread
                84      LOAD_CONST                      4: 'Reporter'
                86      KW_NAMES                        5: ('module',)
                88      CALL                            6
                96      STORE_FAST                      7: _var_var_21
                98      LOAD_FAST                       7: _var_var_21
                100     LOAD_CONST                      6: False
                102     COMPARE_OP                      40 (==)
                106     POP_JUMP_IF_FALSE               68 (to 244)
                108     LOAD_FAST                       0: account
                110     LOAD_CONST                      7: 'error'
                112     LOAD_CONST                      8: ('account', 'status')
                114     BUILD_CONST_KEY_MAP             2
                116     LOAD_GLOBAL                     7: NULL + Disconnect
                126     LOAD_FAST                       7: _var_var_21
                128     CALL                            1
                136     POP_TOP                         
                138     LOAD_GLOBAL                     9: NULL + Logs
                148     LOAD_ATTR                       10: PrintLog
                168     LOAD_FAST                       1: config
                170     LOAD_FAST                       0: account
                172     LOAD_GLOBAL                     4: Lang
                182     PUSH_NULL                       
                184     LOAD_CONST                      1: '__pyarmor_assert_14484__'
                186     LOAD_CONST                      9: 'work_account_completed'   # b'\x81\xf5\x17\x018\xc5\xbf\xd1\x18\xf5\x18\xcex\xd3\xfb\x8a\x02M\xb7\xa2\xbe\xceJ'
                188     CALL                            1
                196     BINARY_SUBSCR                   
                200     KW_NAMES                        10: ('config', 'account', 'message')
                202     CALL                            3
                210     POP_TOP                         
                212     LOAD_FAST                       0: account
                214     LOAD_CONST                      11: 'done'
                216     LOAD_CONST                      8: ('account', 'status')
                218     BUILD_CONST_KEY_MAP             2
                220     SWAP                            2
                222     POP_TOP                         
                224     NOP                             
                226     NOP                             
                228     JUMP_FORWARD                    1096 (to 2424)
                232     CALL                            1
                240     POP_TOP                         
                242     RETURN_VALUE                    
                244     LOAD_FAST                       3: data
                246     LOAD_CONST                      13: 'Settings'
                248     BINARY_SUBSCR                   
                252     LOAD_ATTR                       13: get
                272     PUSH_NULL                       
                274     LOAD_CONST                      1: '__pyarmor_assert_14484__'
                276     LOAD_CONST                      14: 'usernames'   # b'\x81\xf7\x0b\x16!\xf4\xbf\xdf\x1e\xe9'
                278     CALL                            1
                286     BUILD_LIST                      0
                288     CALL                            2
                296     STORE_FAST                      8: _var_var_22
                298     LOAD_FAST                       3: data
                300     LOAD_CONST                      13: 'Settings'
                302     BINARY_SUBSCR                   
                306     LOAD_ATTR                       13: get
                326     PUSH_NULL                       
                328     LOAD_CONST                      1: '__pyarmor_assert_14484__'
                330     LOAD_CONST                      15: 'reason_photo'   # b'\x81\xf0\x1d\x12 \xf5\xb0\xed\x0b\xf2\x02\xd4c'
                332     CALL                            1
                340     BUILD_LIST                      0
                342     CALL                            2
                350     STORE_FAST                      9: _var_var_20
                352     LOAD_FAST                       3: data
                354     LOAD_CONST                      13: 'Settings'
                356     BINARY_SUBSCR                   
                360     LOAD_ATTR                       13: get
                380     PUSH_NULL                       
                382     LOAD_CONST                      1: '__pyarmor_assert_14484__'
                384     LOAD_CONST                      16: 'reason_message'   # b'\x81\xf0\x1d\x12 \xf5\xb0\xed\x16\xff\x1e\xd3m\xeb\xfd'
                386     CALL                            1
                394     LOAD_CONST                      17: ''
                396     CALL                            2
                404     STORE_FAST                      10: _var_var_24
                406     LOAD_FAST                       3: data
                408     LOAD_CONST                      13: 'Settings'
                410     BINARY_SUBSCR                   
                414     LOAD_ATTR                       13: get
                434     PUSH_NULL                       
                436     LOAD_CONST                      1: '__pyarmor_assert_14484__'
                438     LOAD_CONST                      18: 'option_photo'   # b'\x81\xed\x08\x07:\xf5\xb0\xed\x0b\xf2\x02\xd4c'
                440     CALL                            1
                448     LOAD_CONST                      17: ''
                450     CALL                            2
                458     STORE_FAST                      11: _var_var_23
                460     LOAD_FAST                       3: data
                462     LOAD_CONST                      13: 'Settings'
                464     BINARY_SUBSCR                   
                468     LOAD_ATTR                       13: get
                488     PUSH_NULL                       
                490     LOAD_CONST                      1: '__pyarmor_assert_14484__'
                492     LOAD_CONST                      19: 'wait_from'   # b"\x81\xf5\x19\x1a'\xc5\xb8\xc0\x14\xf7"
                494     CALL                            1
                502     CALL                            1
                510     STORE_FAST                      12: _var_var_26
                512     LOAD_FAST                       3: data
                514     LOAD_CONST                      13: 'Settings'
                516     BINARY_SUBSCR                   
                520     LOAD_ATTR                       13: get
                540     LOAD_CONST                      20: 'wait_to'
                542     CALL                            1
                550     STORE_FAST                      13: _var_var_27
                552     LOAD_FAST                       3: data
                554     LOAD_CONST                      13: 'Settings'
                556     BINARY_SUBSCR                   
                560     LOAD_ATTR                       13: get
                580     PUSH_NULL                       
                582     LOAD_CONST                      1: '__pyarmor_assert_14484__'
                584     LOAD_CONST                      21: 'max_flood_wait'   # b'\x81\xef\x19\x0b\x0c\xfc\xb2\xdd\x14\xfe2\xd7m\xe5\xec'
                586     CALL                            1
                594     CALL                            1
                602     STORE_FAST                      14: _var_var_28
                604     LOAD_GLOBAL                     15: NULL + db_reporter
                614     LOAD_FAST                       4: db_result
                616     CALL                            1
                624     STORE_FAST                      15: _var_var_30
                626     LOAD_FAST                       8: _var_var_22
                628     GET_ITER                        
                630     FOR_ITER                        294 (to 1222)
                636     STORE_FAST                      16: _var_var_31
                638     LOAD_FAST                       5: stop_thread
                640     LOAD_ATTR                       17: is_set
                660     CALL                            0
                668     POP_JUMP_IF_FALSE               10 (to 690)
                670     LOAD_GLOBAL                     19: NULL + StopProgram
                680     CALL                            0
                688     RAISE_VARARGS                   1
                690     LOAD_FAST                       7: _var_var_21
                692     LOAD_ATTR                       21: is_connected
                712     CALL                            0
                720     POP_JUMP_IF_TRUE                16 (to 754)
                722     LOAD_FAST                       7: _var_var_21
                724     LOAD_ATTR                       23: connect
                744     CALL                            0
                752     POP_TOP                         
                754     LOAD_CONST                      22: 'NotDone'
                756     STORE_FAST                      17: _var_var_32
                758     LOAD_CONST                      17: ''
                760     STORE_FAST                      18: _var_var_33
                762     LOAD_CONST                      17: ''
                764     STORE_FAST                      19: _var_var_34
                766     LOAD_CONST                      0: None
                768     STORE_FAST                      20: _var_var_36
                770     NOP                             
                772     LOAD_GLOBAL                     25: NULL + tg_links
                782     LOAD_ATTR                       26: get_data
                802     LOAD_FAST                       16: _var_var_31
                804     CALL                            1
                812     STORE_FAST                      21: _var_var_35
                814     LOAD_FAST                       21: _var_var_35
                816     LOAD_CONST                      23: 'username'
                818     BINARY_SUBSCR                   
                822     POP_JUMP_IF_FALSE               20 (to 864)
                824     LOAD_FAST                       7: _var_var_21
                826     LOAD_ATTR                       29: get_entity
                846     LOAD_FAST                       21: _var_var_35
                848     LOAD_CONST                      23: 'username'
                850     BINARY_SUBSCR                   
                854     CALL                            1
                862     STORE_FAST                      20: _var_var_36
                864     LOAD_FAST                       20: _var_var_36
                866     POP_JUMP_IF_TRUE                1 (to 870)
                868     JUMP_BACKWARD                   120 (to 630)
                870     LOAD_FAST                       7: _var_var_21
                872     LOAD_ATTR                       31: get_profile_photos
                892     LOAD_FAST                       20: _var_var_36
                894     LOAD_CONST                      24: 20
                896     KW_NAMES                        25: ('limit',)
                898     CALL                            2
                906     STORE_FAST                      22: _var_var_40
                908     LOAD_FAST                       22: _var_var_40
                910     GET_ITER                        
                912     FOR_ITER                        151 (to 1216)
                916     STORE_FAST                      23: _var_var_41
                918     LOAD_GLOBAL                     33: NULL + int
                928     LOAD_GLOBAL                     35: NULL + random
                938     LOAD_ATTR                       36: choice
                958     LOAD_FAST                       9: _var_var_20
                960     CALL                            1
                968     CALL                            1
                976     STORE_FAST                      24: _var_var_37
                978     LOAD_GLOBAL                     39: NULL + get_reason_photo_name
                988     LOAD_FAST                       24: _var_var_37
                990     CALL                            1
                998     STORE_FAST                      18: _var_var_33
                1000    LOAD_GLOBAL                     41: NULL + spintax
                1010    LOAD_ATTR                       42: spin
                1030    LOAD_FAST                       10: _var_var_24
                1032    CALL                            1
                1040    STORE_FAST                      19: _var_var_34
                1042    LOAD_GLOBAL                     45: NULL + send_report_photo
                1052    LOAD_FAST                       7: _var_var_21
                1054    LOAD_FAST                       20: _var_var_36
                1056    LOAD_FAST                       23: _var_var_41
                1058    LOAD_FAST                       24: _var_var_37
                1060    LOAD_FAST                       19: _var_var_34
                1062    CALL                            5
                1070    STORE_FAST                      17: _var_var_32
                1072    LOAD_GLOBAL                     9: NULL + Logs
                1082    LOAD_ATTR                       10: PrintLog
                1102    LOAD_FAST                       1: config
                1104    LOAD_FAST                       0: account
                1106    LOAD_FAST                       16: _var_var_31
                1108    LOAD_FAST                       18: _var_var_33
                1110    LOAD_CONST                      26: 'status: '
                1112    LOAD_FAST                       17: _var_var_32
                1114    FORMAT_VALUE                    0 (FVC_NONE)
                1116    BUILD_STRING                    2
                1118    KW_NAMES                        27: ('config', 'account', 'message', 'param', 'end')
                1120    CALL                            5
                1128    POP_TOP                         
                1130    LOAD_FAST                       15: _var_var_30
                1132    LOAD_ATTR                       47: insert
                1152    LOAD_FAST                       0: account
                1154    LOAD_FAST                       16: _var_var_31
                1156    LOAD_FAST                       18: _var_var_33
                1158    LOAD_FAST                       19: _var_var_34
                1160    LOAD_FAST                       17: _var_var_32
                1162    CALL                            5
                1170    POP_TOP                         
                1172    LOAD_FAST                       11: _var_var_23
                1174    LOAD_CONST                      28: 'one'
                1176    COMPARE_OP                      40 (==)
                1180    POP_JUMP_IF_FALSE               2 (to 1186)
                1182    POP_TOP                         
                1184    JUMP_FORWARD                    17 (to 1220)
                1186    LOAD_GLOBAL                     49: NULL + DelayOnline
                1196    LOAD_FAST                       0: account
                1198    LOAD_FAST                       7: _var_var_21
                1200    LOAD_FAST                       12: _var_var_26
                1202    LOAD_FAST                       13: _var_var_27
                1204    LOAD_FAST                       5: stop_thread
                1206    CALL                            5
                1214    POP_TOP                         
                1216    JUMP_BACKWARD                   153 (to 912)
                1218    END_FOR                         
                1220    JUMP_BACKWARD                   297 (to 630)
                1224    END_FOR                         
                1226    LOAD_GLOBAL                     7: NULL + Disconnect
                1236    LOAD_FAST_CHECK                 7: _var_var_21
                1238    CALL                            1
                1246    POP_TOP                         
                1248    LOAD_GLOBAL                     9: NULL + Logs
                1258    LOAD_ATTR                       10: PrintLog
                1278    LOAD_FAST                       1: config
                1280    LOAD_FAST                       0: account
                1282    LOAD_GLOBAL                     4: Lang
                1292    PUSH_NULL                       
                1294    LOAD_CONST                      1: '__pyarmor_assert_14484__'
                1296    LOAD_CONST                      9: 'work_account_completed'   # b'\x81\xf5\x17\x018\xc5\xbf\xd1\x18\xf5\x18\xcex\xd3\xfb\x8a\x02M\xb7\xa2\xbe\xceJ'
                1298    CALL                            1
                1306    BINARY_SUBSCR                   
                1310    KW_NAMES                        10: ('config', 'account', 'message')
                1312    CALL                            3
                1320    POP_TOP                         
                1322    LOAD_FAST                       0: account
                1324    LOAD_CONST                      11: 'done'
                1326    LOAD_CONST                      8: ('account', 'status')
                1328    BUILD_CONST_KEY_MAP             2
                1330    NOP                             
                1332    NOP                             
                1334    JUMP_FORWARD                    543 (to 2424)
                1338    CALL                            1
                1346    POP_TOP                         
                1348    RETURN_VALUE                    
                1350    PUSH_EXC_INFO                   
                1352    POP_TOP                         
                1354    POP_EXCEPT                      
                1356    JUMP_BACKWARD                   611 (to 138)
                1360    COPY                            3
                1362    POP_EXCEPT                      
                1364    RERAISE                         1
                1366    PUSH_EXC_INFO                   
                1368    LOAD_GLOBAL                     18: StopProgram
                1378    CHECK_EXC_MATCH                 
                1380    POP_JUMP_IF_FALSE               2 (to 1386)
                1382    POP_TOP                         
                1384    RAISE_VARARGS                   0
                1386    LOAD_GLOBAL                     50: errors
                1396    LOAD_ATTR                       52: FloodWaitError
                1416    CHECK_EXC_MATCH                 
                1418    POP_JUMP_IF_FALSE               270 (to 1962)
                1422    STORE_FAST                      25: _var_var_3
                1424    LOAD_GLOBAL                     9: NULL + Logs
                1434    LOAD_ATTR                       10: PrintLog
                1454    LOAD_FAST                       1: config
                1456    LOAD_FAST                       0: account
                1458    LOAD_GLOBAL                     4: Lang
                1468    PUSH_NULL                       
                1470    LOAD_CONST                      1: '__pyarmor_assert_14484__'
                1472    LOAD_CONST                      29: 'restriction_detected'   # b"\x81\xf0\x1d\x00'\xe8\xb7\xd1\x0f\xf3\x02\xceS\xe8\xfd\x91\n^\xaf\xa2\xae"
                1474    CALL                            1
                1482    BINARY_SUBSCR                   
                1486    KW_NAMES                        10: ('config', 'account', 'message')
                1488    CALL                            3
                1496    POP_TOP                         
                1498    LOAD_GLOBAL                     9: NULL + Logs
                1508    LOAD_ATTR                       10: PrintLog
                1528    LOAD_FAST                       1: config
                1530    LOAD_FAST                       0: account
                1532    LOAD_GLOBAL                     4: Lang
                1542    PUSH_NULL                       
                1544    LOAD_CONST                      1: '__pyarmor_assert_14484__'
                1546    LOAD_CONST                      30: 'algorithm_running'   # b'\x81\xe3\x14\x14<\xe8\xb7\xc6\x13\xf72\xd2y\xe2\xf6\x8c\x01Z'
                1548    CALL                            1
                1556    BINARY_SUBSCR                   
                1560    KW_NAMES                        10: ('config', 'account', 'message')
                1562    CALL                            3
                1570    POP_TOP                         
                1572    LOAD_FAST                       25: _var_var_3
                1574    LOAD_ATTR                       54: seconds
                1594    LOAD_FAST                       14: _var_var_28
                1596    COMPARE_OP                      68 (>)
                1600    POP_JUMP_IF_FALSE               82 (to 1766)
                1602    LOAD_GLOBAL                     9: NULL + Logs
                1612    LOAD_ATTR                       10: PrintLog
                1632    LOAD_FAST                       1: config
                1634    LOAD_FAST                       0: account
                1636    LOAD_GLOBAL                     4: Lang
                1646    PUSH_NULL                       
                1648    LOAD_CONST                      1: '__pyarmor_assert_14484__'
                1650    LOAD_CONST                      31: 'flood_wait_more'   # b'\x81\xe4\x14\x1c<\xfe\x81\xc5\x1a\xf3\x19\xffa\xe3\xea\x80'
                1652    CALL                            1
                1660    BINARY_SUBSCR                   
                1664    LOAD_FAST                       14: _var_var_28
                1666    KW_NAMES                        32: ('config', 'account', 'message', 'param')
                1668    CALL                            4
                1676    POP_TOP                         
                1678    LOAD_GLOBAL                     9: NULL + Logs
                1688    LOAD_ATTR                       10: PrintLog
                1708    LOAD_FAST                       1: config
                1710    LOAD_FAST                       0: account
                1712    LOAD_GLOBAL                     4: Lang
                1722    PUSH_NULL                       
                1724    LOAD_CONST                      1: '__pyarmor_assert_14484__'
                1726    LOAD_CONST                      33: 'work_stopped'   # b'\x81\xf5\x17\x018\xc5\xad\xc6\x14\xea\x1d\xc5h'
                1728    CALL                            1
                1736    BINARY_SUBSCR                   
                1740    KW_NAMES                        10: ('config', 'account', 'message')
                1742    CALL                            3
                1750    POP_TOP                         
                1752    POP_EXCEPT                      
                1754    LOAD_CONST                      0: None
                1756    STORE_FAST                      25: _var_var_3
                1758    DELETE_FAST                     25: _var_var_3
                1760    POP_TOP                         
                1762    JUMP_BACKWARD                   270 (to 1226)
                1766    LOAD_FAST                       25: _var_var_3
                1768    LOAD_ATTR                       54: seconds
                1788    LOAD_GLOBAL                     35: NULL + random
                1798    LOAD_ATTR                       56: randint
                1818    LOAD_CONST                      34: 5
                1820    LOAD_CONST                      35: 15
                1822    CALL                            2
                1830    BINARY_OP                       0 (+)
                1834    STORE_FAST                      26: _var_var_39
                1836    LOAD_GLOBAL                     9: NULL + Logs
                1846    LOAD_ATTR                       10: PrintLog
                1866    LOAD_FAST                       1: config
                1868    LOAD_FAST                       0: account
                1870    LOAD_GLOBAL                     4: Lang
                1880    PUSH_NULL                       
                1882    LOAD_CONST                      1: '__pyarmor_assert_14484__'
                1884    LOAD_CONST                      36: 'flood_wait_bypass'   # b'\x81\xe4\x14\x1c<\xfe\x81\xc5\x1a\xf3\x19\xffn\xf5\xe8\x84\x1cN'
                1886    CALL                            1
                1894    BINARY_SUBSCR                   
                1898    LOAD_FAST                       26: _var_var_39
                1900    KW_NAMES                        32: ('config', 'account', 'message', 'param')
                1902    CALL                            4
                1910    POP_TOP                         
                1912    LOAD_GLOBAL                     49: NULL + DelayOnline
                1922    LOAD_FAST                       0: account
                1924    LOAD_FAST                       7: _var_var_21
                1926    LOAD_FAST                       26: _var_var_39
                1928    LOAD_FAST                       26: _var_var_39
                1930    LOAD_FAST                       5: stop_thread
                1932    CALL                            5
                1940    POP_TOP                         
                1942    POP_EXCEPT                      
                1944    LOAD_CONST                      0: None
                1946    STORE_FAST                      25: _var_var_3
                1948    DELETE_FAST                     25: _var_var_3
                1950    JUMP_BACKWARD                   662 (to 630)
                1954    LOAD_CONST                      0: None
                1956    STORE_FAST                      25: _var_var_3
                1958    DELETE_FAST                     25: _var_var_3
                1960    RERAISE                         1
                1962    LOAD_GLOBAL                     58: Exception
                1972    CHECK_EXC_MATCH                 
                1974    POP_JUMP_IF_FALSE               70 (to 2116)
                1976    STORE_FAST                      25: _var_var_3
                1978    PUSH_NULL                       
                1980    LOAD_GLOBAL                     61: NULL + logging
                1990    LOAD_FAST                       25: _var_var_3
                1992    CALL                            1
                2000    CALL                            0
                2008    POP_TOP                         
                2010    LOAD_GLOBAL                     63: NULL + type
                2020    LOAD_FAST                       25: _var_var_3
                2022    CALL                            1
                2030    LOAD_ATTR                       64: __name__
                2050    FORMAT_VALUE                    0 (FVC_NONE)
                2052    STORE_FAST                      17: _var_var_32
                2054    LOAD_FAST                       15: _var_var_30
                2056    LOAD_ATTR                       47: insert
                2076    LOAD_FAST                       0: account
                2078    LOAD_FAST                       16: _var_var_31
                2080    LOAD_FAST                       18: _var_var_33
                2082    LOAD_FAST                       19: _var_var_34
                2084    LOAD_FAST                       17: _var_var_32
                2086    CALL                            5
                2094    POP_TOP                         
                2096    POP_EXCEPT                      
                2098    LOAD_CONST                      0: None
                2100    STORE_FAST                      25: _var_var_3
                2102    DELETE_FAST                     25: _var_var_3
                2104    JUMP_BACKWARD                   739 (to 630)
                2108    LOAD_CONST                      0: None
                2110    STORE_FAST                      25: _var_var_3
                2112    DELETE_FAST                     25: _var_var_3
                2114    RERAISE                         1
                2116    RERAISE                         0
                2118    COPY                            3
                2120    POP_EXCEPT                      
                2122    RERAISE                         1
                2124    PUSH_EXC_INFO                   
                2126    LOAD_GLOBAL                     18: StopProgram
                2136    CHECK_EXC_MATCH                 
                2138    POP_JUMP_IF_FALSE               4 (to 2148)
                2140    POP_TOP                         
                2142    POP_EXCEPT                      
                2144    JUMP_BACKWARD                   461 (to 1226)
                2148    LOAD_GLOBAL                     66: BaseException
                2158    CHECK_EXC_MATCH                 
                2160    POP_JUMP_IF_FALSE               27 (to 2216)
                2162    STORE_FAST                      25: _var_var_3
                2164    PUSH_NULL                       
                2166    LOAD_GLOBAL                     61: NULL + logging
                2176    LOAD_FAST                       25: _var_var_3
                2178    CALL                            1
                2186    CALL                            0
                2194    POP_TOP                         
                2196    POP_EXCEPT                      
                2198    LOAD_CONST                      0: None
                2200    STORE_FAST                      25: _var_var_3
                2202    DELETE_FAST                     25: _var_var_3
                2204    JUMP_BACKWARD                   491 (to 1226)
                2208    LOAD_CONST                      0: None
                2210    STORE_FAST                      25: _var_var_3
                2212    DELETE_FAST                     25: _var_var_3
                2214    RERAISE                         1
                2216    RERAISE                         0
                2218    COPY                            3
                2220    POP_EXCEPT                      
                2222    RERAISE                         1
                2224    PUSH_EXC_INFO                   
                2226    POP_TOP                         
                2228    POP_EXCEPT                      
                2230    JUMP_BACKWARD                   493 (to 1248)
                2234    COPY                            3
                2236    POP_EXCEPT                      
                2238    RERAISE                         1
                2240    PUSH_EXC_INFO                   
                2242    LOAD_GLOBAL                     7: NULL + Disconnect
                2252    LOAD_FAST_CHECK                 7: _var_var_21
                2254    CALL                            1
                2262    POP_TOP                         
                2264    JUMP_FORWARD                    7 (to 2280)
                2266    PUSH_EXC_INFO                   
                2268    POP_TOP                         
                2270    POP_EXCEPT                      
                2272    JUMP_FORWARD                    3 (to 2280)
                2274    COPY                            3
                2276    POP_EXCEPT                      
                2278    RERAISE                         1
                2280    LOAD_GLOBAL                     9: NULL + Logs
                2290    LOAD_ATTR                       10: PrintLog
                2310    LOAD_FAST                       1: config
                2312    LOAD_FAST                       0: account
                2314    LOAD_GLOBAL                     4: Lang
                2324    PUSH_NULL                       
                2326    LOAD_CONST                      1: '__pyarmor_assert_14484__'
                2328    LOAD_CONST                      9: 'work_account_completed'   # b'\x81\xf5\x17\x018\xc5\xbf\xd1\x18\xf5\x18\xcex\xd3\xfb\x8a\x02M\xb7\xa2\xbe\xceJ'
                2330    CALL                            1
                2338    BINARY_SUBSCR                   
                2342    KW_NAMES                        10: ('config', 'account', 'message')
                2344    CALL                            3
                2352    POP_TOP                         
                2354    LOAD_FAST                       0: account
                2356    LOAD_CONST                      11: 'done'
                2358    LOAD_CONST                      8: ('account', 'status')
                2360    BUILD_CONST_KEY_MAP             2
                2362    SWAP                            2
                2364    POP_TOP                         
                2366    SWAP                            2
                2368    POP_EXCEPT                      
                2370    NOP                             
                2372    NOP                             
                2374    NOP                             
                2376    JUMP_FORWARD                    23 (to 2424)
                2378    CALL                            1
                2386    POP_TOP                         
                2388    RETURN_VALUE                    
                2390    COPY                            3
                2392    POP_EXCEPT                      
                2394    RERAISE                         1
                2396    PUSH_EXC_INFO                   
                2398    PUSH_NULL                       
                2400    LOAD_CONST                      12: '__pyarmor_exit_14486__'
                2402    NOP                             
                2404    LOAD_CONST                      3: b'<COAddr>\x07\x00\x00\x1aB\t\x00\x00\x00\x00\x00\x00\x00\x00\x00\x00\x00\x00\x00\x00'
                2406    CALL                            1
                2414    POP_TOP                         
                2416    RERAISE                         0
                2418    COPY                            3
                2420    POP_EXCEPT                      
                2422    RERAISE                         1
                2424    PUSH_NULL                       
                2426    LOAD_CONST                      12: '__pyarmor_exit_14486__'
                2428    LOAD_CONST                      3: b'<COAddr>\x07\x00\x00\x1aB\t\x00\x00\x00\x00\x00\x00\x00\x00\x00\x00\x00\x00\x00\x00'
                2430    BUILD_TUPLE                     1
                2432    CALL_FUNCTION_EX                0
                2434    POP_TOP                         
                2436    RETURN_VALUE                    
            [Exception Table]
                30 to 116 -> 2124 [0] 
                116 to 138 -> 1350 [1] 
                138 to 224 -> 2396 [0] 
                244 to 770 -> 2124 [0] 
                772 to 868 -> 1366 [1] 
                868 to 870 -> 2124 [0] 
                870 to 1220 -> 1366 [1] 
                1220 to 1226 -> 2124 [0] 
                1226 to 1248 -> 2224 [0] 
                1248 to 1330 -> 2396 [0] 
                1350 to 1354 -> 1360 [2] lasti
                1354 to 1366 -> 2396 [0] 
                1366 to 1424 -> 2118 [2] lasti
                1424 to 1752 -> 1954 [2] lasti
                1752 to 1766 -> 2124 [0] 
                1766 to 1942 -> 1954 [2] lasti
                1942 to 1954 -> 2124 [0] 
                1954 to 1978 -> 2118 [2] lasti
                1978 to 2096 -> 2108 [2] lasti
                2096 to 2108 -> 2124 [0] 
                2108 to 2118 -> 2118 [2] lasti
                2118 to 2124 -> 2124 [0] 
                2124 to 2142 -> 2218 [1] lasti
                2142 to 2148 -> 2240 [0] 
                2148 to 2164 -> 2218 [1] lasti
                2164 to 2196 -> 2208 [1] lasti
                2196 to 2208 -> 2240 [0] 
                2208 to 2218 -> 2218 [1] lasti
                2218 to 2224 -> 2240 [0] 
                2224 to 2228 -> 2234 [1] lasti
                2228 to 2240 -> 2396 [0] 
                2240 to 2242 -> 2390 [1] lasti
                2242 to 2264 -> 2266 [2] 
                2264 to 2266 -> 2390 [1] lasti
                2266 to 2270 -> 2274 [3] lasti
                2270 to 2368 -> 2390 [1] lasti
                2368 to 2370 -> 2396 [0] 
                2390 to 2396 -> 2396 [0] 
                2396 to 2418 -> 2418 [1] lasti
        '__pyarmor_exit_14462__'
    [Disassembly]
        0       NOP                             
        2       NOP                             
        4       PUSH_NULL                       
        6       LOAD_CONST                      1: '__pyarmor_enter_14461__'
        8       LOAD_CONST                      2: b'<COAddr>\x05\x00\x00\x1a\x98\x01\x00\x00\x00\x00\x00\x00\x00\x00\x00\x00\x00\x00\x00\x00'
        10      BUILD_TUPLE                     1
        12      CALL_FUNCTION_EX                0
        14      POP_TOP                         
        16      RESUME                          0
        18      NOP                             
        20      NOP                             
        22      NOP                             
        24      NOP                             
        26      LOAD_CONST                      3: 0
        28      LOAD_CONST                      4: None
        30      IMPORT_NAME                     1: eel
        32      STORE_NAME                      1: eel
        34      LOAD_CONST                      3: 0
        36      LOAD_CONST                      4: None
        38      IMPORT_NAME                     2: json
        40      STORE_NAME                      2: json
        42      LOAD_CONST                      3: 0
        44      LOAD_CONST                      4: None
        46      IMPORT_NAME                     3: random
        48      STORE_NAME                      3: random
        50      LOAD_CONST                      3: 0
        52      LOAD_CONST                      4: None
        54      IMPORT_NAME                     4: spintax
        56      STORE_NAME                      4: spintax
        58      LOAD_CONST                      3: 0
        60      LOAD_CONST                      4: None
        62      IMPORT_NAME                     5: concurrent.futures
        64      STORE_NAME                      6: concurrent
        66      LOAD_CONST                      3: 0
        68      LOAD_CONST                      5: ('Thread', 'Event')
        70      IMPORT_NAME                     7: threading
        72      IMPORT_FROM                     8: Thread
        74      STORE_NAME                      8: Thread
        76      IMPORT_FROM                     9: Event
        78      STORE_NAME                      9: Event
        80      POP_TOP                         
        82      LOAD_CONST                      3: 0
        84      LOAD_CONST                      6: ('functions', 'errors', 'types')
        86      IMPORT_NAME                     10: multithon
        88      IMPORT_FROM                     11: functions
        90      STORE_NAME                      11: functions
        92      IMPORT_FROM                     12: errors
        94      STORE_NAME                      12: errors
        96      IMPORT_FROM                     13: types
        98      STORE_NAME                      13: types
        100     POP_TOP                         
        102     LOAD_CONST                      3: 0
        104     LOAD_CONST                      7: ('StopProgram',)
        106     IMPORT_NAME                     14: multithon.errors
        108     IMPORT_FROM                     15: StopProgram
        110     STORE_NAME                      15: StopProgram
        112     POP_TOP                         
        114     LOAD_CONST                      3: 0
        116     LOAD_CONST                      8: ('GetLang',)
        118     IMPORT_NAME                     16: program.static_classes
        120     IMPORT_FROM                     17: GetLang
        122     STORE_NAME                      17: GetLang
        124     POP_TOP                         
        126     LOAD_CONST                      3: 0
        128     LOAD_CONST                      9: ('Logs',)
        130     IMPORT_NAME                     16: program.static_classes
        132     IMPORT_FROM                     18: Logs
        134     STORE_NAME                      18: Logs
        136     POP_TOP                         
        138     LOAD_CONST                      3: 0
        140     LOAD_CONST                      10: ('check_module',)
        142     IMPORT_NAME                     16: program.static_classes
        144     IMPORT_FROM                     19: check_module
        146     STORE_NAME                      19: check_module
        148     POP_TOP                         
        150     LOAD_CONST                      3: 0
        152     LOAD_CONST                      11: ('logging',)
        154     IMPORT_NAME                     16: program.static_classes
        156     IMPORT_FROM                     20: logging
        158     STORE_NAME                      20: logging
        160     POP_TOP                         
        162     LOAD_CONST                      3: 0
        164     LOAD_CONST                      12: ('memory_check_switcher',)
        166     IMPORT_NAME                     16: program.static_classes
        168     IMPORT_FROM                     21: memory_check_switcher
        170     STORE_NAME                      21: memory_check_switcher
        172     POP_TOP                         
        174     LOAD_CONST                      3: 0
        176     LOAD_CONST                      13: ('memory_set_pid',)
        178     IMPORT_NAME                     16: program.static_classes
        180     IMPORT_FROM                     22: memory_set_pid
        182     STORE_NAME                      22: memory_set_pid
        184     POP_TOP                         
        186     LOAD_CONST                      3: 0
        188     LOAD_CONST                      14: ('DelayOnline',)
        190     IMPORT_NAME                     23: program.telegram
        192     IMPORT_FROM                     24: DelayOnline
        194     STORE_NAME                      24: DelayOnline
        196     POP_TOP                         
        198     LOAD_CONST                      3: 0
        200     LOAD_CONST                      15: ('Disconnect',)
        202     IMPORT_NAME                     23: program.telegram
        204     IMPORT_FROM                     25: Disconnect
        206     STORE_NAME                      25: Disconnect
        208     POP_TOP                         
        210     LOAD_CONST                      3: 0
        212     LOAD_CONST                      16: ('Thread_wait',)
        214     IMPORT_NAME                     23: program.telegram
        216     IMPORT_FROM                     26: Thread_wait
        218     STORE_NAME                      26: Thread_wait
        220     POP_TOP                         
        222     LOAD_CONST                      3: 0
        224     LOAD_CONST                      17: ('account_works',)
        226     IMPORT_NAME                     23: program.telegram
        228     IMPORT_FROM                     27: account_works
        230     STORE_NAME                      27: account_works
        232     POP_TOP                         
        234     LOAD_CONST                      3: 0
        236     LOAD_CONST                      18: ('tg_links',)
        238     IMPORT_NAME                     23: program.telegram
        240     IMPORT_FROM                     28: tg_links
        242     STORE_NAME                      28: tg_links
        244     POP_TOP                         
        246     LOAD_CONST                      3: 0
        248     LOAD_CONST                      19: ('GetConfig',)
        250     IMPORT_NAME                     29: program.general
        252     IMPORT_FROM                     30: GetConfig
        254     STORE_NAME                      30: GetConfig
        256     POP_TOP                         
        258     LOAD_CONST                      3: 0
        260     LOAD_CONST                      20: ('GetProxy',)
        262     IMPORT_NAME                     29: program.general
        264     IMPORT_FROM                     31: GetProxy
        266     STORE_NAME                      31: GetProxy
        268     POP_TOP                         
        270     LOAD_CONST                      3: 0
        272     LOAD_CONST                      21: ('StopDetect',)
        274     IMPORT_NAME                     29: program.general
        276     IMPORT_FROM                     32: StopDetect
        278     STORE_NAME                      32: StopDetect
        280     POP_TOP                         
        282     LOAD_CONST                      3: 0
        284     LOAD_CONST                      22: ('del_task_manager',)
        286     IMPORT_NAME                     29: program.general
        288     IMPORT_FROM                     33: del_task_manager
        290     STORE_NAME                      33: del_task_manager
        292     POP_TOP                         
        294     LOAD_CONST                      3: 0
        296     LOAD_CONST                      23: ('getFile',)
        298     IMPORT_NAME                     29: program.general
        300     IMPORT_FROM                     34: getFile
        302     STORE_NAME                      34: getFile
        304     POP_TOP                         
        306     LOAD_CONST                      3: 0
        308     LOAD_CONST                      24: ('getPath',)
        310     IMPORT_NAME                     29: program.general
        312     IMPORT_FROM                     35: getPath
        314     STORE_NAME                      35: getPath
        316     POP_TOP                         
        318     LOAD_CONST                      3: 0
        320     LOAD_CONST                      25: ('set_task_manager',)
        322     IMPORT_NAME                     29: program.general
        324     IMPORT_FROM                     36: set_task_manager
        326     STORE_NAME                      36: set_task_manager
        328     POP_TOP                         
        330     LOAD_CONST                      3: 0
        332     LOAD_CONST                      26: ('db_reporter',)
        334     IMPORT_NAME                     37: program.database
        336     IMPORT_FROM                     38: db_reporter
        338     STORE_NAME                      38: db_reporter
        340     POP_TOP                         
        342     LOAD_CONST                      3: 0
        344     LOAD_CONST                      18: ('tg_links',)
        346     IMPORT_NAME                     39: program.telegram.func_static
        348     IMPORT_FROM                     28: tg_links
        350     STORE_NAME                      28: tg_links
        352     POP_TOP                         
        354     LOAD_CONST                      27: <CODE> Reporter
        356     MAKE_FUNCTION                   0
        358     STORE_NAME                      40: Reporter
        360     LOAD_CONST                      28: <CODE> START
        362     MAKE_FUNCTION                   0
        364     STORE_NAME                      41: START
        366     LOAD_CONST                      29: 'ids'
        368     LOAD_NAME                       42: str
        370     BUILD_TUPLE                     2
        372     LOAD_CONST                      30: <CODE> get_reason_name
        374     MAKE_FUNCTION                   4
        376     STORE_NAME                      43: get_reason_name
        378     LOAD_CONST                      29: 'ids'
        380     LOAD_NAME                       42: str
        382     BUILD_TUPLE                     2
        384     LOAD_CONST                      31: <CODE> get_reason_photo_name
        386     MAKE_FUNCTION                   4
        388     STORE_NAME                      44: get_reason_photo_name
        390     LOAD_CONST                      32: <CODE> send_report
        392     MAKE_FUNCTION                   0
        394     STORE_NAME                      45: send_report
        396     LOAD_CONST                      33: <CODE> send_report_photo
        398     MAKE_FUNCTION                   0
        400     STORE_NAME                      46: send_report_photo
        402     LOAD_CONST                      34: <CODE> worker_mess
        404     MAKE_FUNCTION                   0
        406     STORE_NAME                      47: worker_mess
        408     LOAD_CONST                      35: <CODE> worker_photo
        410     MAKE_FUNCTION                   0
        412     STORE_NAME                      48: worker_photo
        414     LOAD_CONST                      4: None
        416     NOP                             
        418     NOP                             
        420     NOP                             
        422     JUMP_FORWARD                    19 (to 462)
        430     POP_TOP                         
        432     RETURN_CONST                    4: None
        434     PUSH_EXC_INFO                   
        436     PUSH_NULL                       
        438     LOAD_CONST                      36: '__pyarmor_exit_14462__'
        440     NOP                             
        442     LOAD_CONST                      2: b'<COAddr>\x05\x00\x00\x1a\x98\x01\x00\x00\x00\x00\x00\x00\x00\x00\x00\x00\x00\x00\x00\x00'
        444     CALL                            1
        452     POP_TOP                         
        454     RERAISE                         0
        456     COPY                            3
        458     POP_EXCEPT                      
        460     RERAISE                         1
        462     PUSH_NULL                       
        464     LOAD_CONST                      36: '__pyarmor_exit_14462__'
        466     LOAD_CONST                      2: b'<COAddr>\x05\x00\x00\x1a\x98\x01\x00\x00\x00\x00\x00\x00\x00\x00\x00\x00\x00\x00\x00\x00'
        468     BUILD_TUPLE                     1
        470     CALL_FUNCTION_EX                0
        472     POP_TOP                         
        474     RETURN_VALUE                    
    [Exception Table]
        26 to 414 -> 434 [0] 
        434 to 456 -> 456 [1] lasti
