#decoded by lolz.live/mrpenny / t.me/zeus_jackpot
# ================================
# Примечания по Pyarmor:
# - Байт-код и объекты кода Pyarmor соответствуют стандартному Python, но присутствуют специальные вызовы функций среды выполнения (runtime) Pyarmor.
# - Вызовы строк — это не ошибки, а маркеры, которые обрабатываются Pyarmor во время выполнения.
#
# Руководство по декомпиляции (без среды выполнения):
# 1. Игнорируйте зашифрованные байты после `#`; используйте только строку до `#`.
# 2. Удалите "__pyarmor_enter_xxx__"(b"<COAddr>...") и "__pyarmor_leave_xxx__"(b"<COAddr>...") (пролог/эпилог).
# 3. "__pyarmor_assert_xxx__"(A) не является настоящим оператором assert.
#    - Если A — это имя или читаемая строка: замените на A.
#    - Если A — это (X, "Y"): замените на X.Y.
#    - Если A — это (X, "Y", Z): замените на X.Y = Z.
#    - В противном случае: выберите наиболее подходящую/логичную замену.
# 4. "__pyarmor_bcc_xxx__"(...) указывает на машинный (нативный) код; тело функции недоступно. Добавьте комментарий.
# ================================

[Code]
    File Name: <frozen program.modules.Search_groups>
    Object Name: <module>
    Qualified Name: <module>
    Arg Count: 0
    Pos Only Arg Count: 0
    KW Only Arg Count: 0
    Stack Size: 5
    Flags: 0x20000000 (CO_PYARMOR_OBFUSCATED)
    [Names]
        '__assert_armored__'
        'eel'
        'time'
        'json'
        'concurrent.futures'
        'concurrent'
        'threading'
        'Thread'
        'Event'
        'multithon'
        'functions'
        'password'
        'pwd_mod'
        'multithon.errors'
        'StopProgram'
        'program.static_classes'
        'GetLang'
        'Logs'
        'logging'
        'memory_check_switcher'
        'memory_set_pid'
        'program.telegram'
        'Disconnect'
        'Thread_wait'
        'account_works'
        'get_account_json'
        'program.general'
        'GetConfig'
        'GetProxy'
        'StopDetect'
        'check_get_settings'
        'del_task_manager'
        'set_task_manager'
        'program.database'
        'db_search_groups'
        'Search_groups'
        'generator_list'
        'START'
        'channel_transfer_group'
        'channel_get_link'
        'worker'
    [Locals+Names]
    [Constants]
        '__pyarmor_assert_14505__'
        '__pyarmor_enter_14506__'
        b'<COAddr>\x05\x00\x00\x1aL\x01\x00\x00\x00\x00\x00\x00\x00\x00\x00\x00\x00\x00\x00\x00'
        0
        None
        (
            'Thread'
            'Event'
        )
        (
            'functions'
        )
        (
            'password'
        )
        (
            'StopProgram'
        )
        (
            'GetLang'
        )
        (
            'Logs'
        )
        (
            'logging'
        )
        (
            'memory_check_switcher'
        )
        (
            'memory_set_pid'
        )
        (
            'Disconnect'
        )
        (
            'Thread_wait'
        )
        (
            'account_works'
        )
        (
            'get_account_json'
        )
        (
            'GetConfig'
        )
        (
            'GetProxy'
        )
        (
            'StopDetect'
        )
        (
            'check_get_settings'
        )
        (
            'del_task_manager'
        )
        (
            'set_task_manager'
        )
        (
            'db_search_groups'
        )
        [Code]
            File Name: <frozen program.modules.Search_groups>
            Object Name: Search_groups
            Qualified Name: Search_groups
            Arg Count: 1
            Pos Only Arg Count: 0
            KW Only Arg Count: 0
            Stack Size: 8
            Flags: 0x20000003 (CO_OPTIMIZED | CO_NEWLOCALS | CO_PYARMOR_OBFUSCATED)
            [Names]
                'GetConfig'
                'config'
                'GetLang'
                'Lang'
                'GetProxy'
                'eel'
                'sendSuccessBox'
                'memory_check_switcher'
                'Event'
                'memory_set_pid'
                'Thread'
                'START'
                'start'
                'Logs'
                'WaitStopAnsfer'
                'UpdateLogInWindow'
                'BaseException'
                'logging'
            [Locals+Names]
                'data'
                '__assert_armored__'
                '_var_var_0'
                '_var_var_1'
                '_var_var_2'
                '_var_var_3'
            [Constants]
                None
                '__pyarmor_assert_14508__'
                '__pyarmor_enter_14509__'
                b'<COAddr>\x07\x00\x00\x1aT\x02\x00\x00\x00\x00\x00\x00\x00\x00\x00\x00\x00\x00\x00\x00'
                'program_running'   # b'\x81\xf2\n\x1c4\xe8\xbf\xdf$\xe8\x18\xceb\xe5\xf6\x82'
                '__pyarmor_exit_14510__'
                False
                (
                    'target'
                    'args'
                )
                True
                (
                    'target'
                    'args'
                    'daemon'
                )
            [Disassembly]
                0       NOP                             
                2       NOP                             
                4       PUSH_NULL                       
                6       LOAD_CONST                      2: '__pyarmor_enter_14509__'
                8       LOAD_CONST                      3: b'<COAddr>\x07\x00\x00\x1aT\x02\x00\x00\x00\x00\x00\x00\x00\x00\x00\x00\x00\x00\x00\x00'
                10      BUILD_TUPLE                     1
                12      CALL_FUNCTION_EX                0
                14      POP_TOP                         
                16      RESUME                          0
                18      NOP                             
                20      NOP                             
                22      NOP                             
                24      NOP                             
                26      NOP                             
                28      NOP                             
                30      LOAD_GLOBAL                     1: NULL + GetConfig
                40      CALL                            0
                48      STORE_GLOBAL                    1: config
                50      LOAD_GLOBAL                     5: NULL + GetLang
                60      LOAD_GLOBAL                     2: config
                70      CALL                            1
                78      STORE_GLOBAL                    3: Lang
                80      LOAD_GLOBAL                     9: NULL + GetProxy
                90      CALL                            0
                98      STORE_FAST                      2: _var_var_0
                100     LOAD_GLOBAL                     11: NULL + eel
                110     LOAD_ATTR                       12: sendSuccessBox
                130     LOAD_GLOBAL                     6: Lang
                140     PUSH_NULL                       
                142     LOAD_CONST                      1: '__pyarmor_assert_14508__'
                144     LOAD_CONST                      4: 'program_running'   # b'\x81\xf2\n\x1c4\xe8\xbf\xdf$\xe8\x18\xceb\xe5\xf6\x82'
                146     CALL                            1
                154     BINARY_SUBSCR                   
                158     CALL                            1
                166     POP_TOP                         
                168     LOAD_GLOBAL                     15: NULL + memory_check_switcher
                178     CALL                            0
                186     POP_JUMP_IF_TRUE                11 (to 210)
                188     NOP                             
                190     LOAD_CONST                      6: False
                192     NOP                             
                194     NOP                             
                196     NOP                             
                198     JUMP_FORWARD                    225 (to 650)
                206     POP_TOP                         
                208     RETURN_CONST                    6: False
                210     LOAD_GLOBAL                     17: NULL + Event
                220     CALL                            0
                228     STORE_FAST                      3: _var_var_1
                230     LOAD_GLOBAL                     19: NULL + memory_set_pid
                240     CALL                            0
                248     STORE_FAST                      4: _var_var_2
                250     LOAD_GLOBAL                     21: NULL + Thread
                260     LOAD_GLOBAL                     22: START
                270     LOAD_FAST                       0: data
                272     LOAD_GLOBAL                     2: config
                282     LOAD_FAST                       4: _var_var_2
                284     LOAD_FAST                       2: _var_var_0
                286     LOAD_FAST                       3: _var_var_1
                288     BUILD_TUPLE                     5
                290     KW_NAMES                        7: ('target', 'args')
                292     CALL                            2
                300     LOAD_ATTR                       25: start
                320     CALL                            0
                328     POP_TOP                         
                330     LOAD_GLOBAL                     21: NULL + Thread
                340     LOAD_GLOBAL                     26: Logs
                350     LOAD_ATTR                       28: WaitStopAnsfer
                370     LOAD_GLOBAL                     2: config
                380     LOAD_FAST                       4: _var_var_2
                382     LOAD_FAST                       3: _var_var_1
                384     BUILD_TUPLE                     3
                386     LOAD_CONST                      8: True
                388     KW_NAMES                        9: ('target', 'args', 'daemon')
                390     CALL                            3
                398     LOAD_ATTR                       25: start
                418     CALL                            0
                426     POP_TOP                         
                428     LOAD_GLOBAL                     21: NULL + Thread
                438     LOAD_GLOBAL                     26: Logs
                448     LOAD_ATTR                       30: UpdateLogInWindow
                468     LOAD_GLOBAL                     2: config
                478     LOAD_FAST                       4: _var_var_2
                480     LOAD_FAST                       3: _var_var_1
                482     BUILD_TUPLE                     3
                484     LOAD_CONST                      8: True
                486     KW_NAMES                        9: ('target', 'args', 'daemon')
                488     CALL                            3
                496     LOAD_ATTR                       25: start
                516     CALL                            0
                524     POP_TOP                         
                526     LOAD_CONST                      0: None
                528     NOP                             
                530     NOP                             
                532     NOP                             
                534     JUMP_FORWARD                    57 (to 650)
                542     POP_TOP                         
                544     RETURN_CONST                    0: None
                546     PUSH_EXC_INFO                   
                548     LOAD_GLOBAL                     32: BaseException
                558     CHECK_EXC_MATCH                 
                560     POP_JUMP_IF_FALSE               26 (to 614)
                562     STORE_FAST                      5: _var_var_3
                564     PUSH_NULL                       
                566     LOAD_GLOBAL                     35: NULL + logging
                576     LOAD_FAST                       5: _var_var_3
                578     CALL                            1
                586     CALL                            0
                594     POP_TOP                         
                596     POP_EXCEPT                      
                598     LOAD_CONST                      0: None
                600     STORE_FAST                      5: _var_var_3
                602     DELETE_FAST                     5: _var_var_3
                604     JUMP_BACKWARD                   40 (to 526)
                606     LOAD_CONST                      0: None
                608     STORE_FAST                      5: _var_var_3
                610     DELETE_FAST                     5: _var_var_3
                612     RERAISE                         1
                614     RERAISE                         0
                616     COPY                            3
                618     POP_EXCEPT                      
                620     RERAISE                         1
                622     PUSH_EXC_INFO                   
                624     PUSH_NULL                       
                626     LOAD_CONST                      5: '__pyarmor_exit_14510__'
                628     NOP                             
                630     LOAD_CONST                      3: b'<COAddr>\x07\x00\x00\x1aT\x02\x00\x00\x00\x00\x00\x00\x00\x00\x00\x00\x00\x00\x00\x00'
                632     CALL                            1
                640     POP_TOP                         
                642     RERAISE                         0
                644     COPY                            3
                646     POP_EXCEPT                      
                648     RERAISE                         1
                650     PUSH_NULL                       
                652     LOAD_CONST                      5: '__pyarmor_exit_14510__'
                654     LOAD_CONST                      3: b'<COAddr>\x07\x00\x00\x1aT\x02\x00\x00\x00\x00\x00\x00\x00\x00\x00\x00\x00\x00\x00\x00'
                656     BUILD_TUPLE                     1
                658     CALL_FUNCTION_EX                0
                660     POP_TOP                         
                662     RETURN_VALUE                    
            [Exception Table]
                30 to 188 -> 546 [0] 
                210 to 526 -> 546 [0] 
                546 to 564 -> 616 [1] lasti
                564 to 596 -> 606 [1] lasti
                596 to 606 -> 622 [0] 
                606 to 616 -> 616 [1] lasti
                616 to 622 -> 622 [0] 
                622 to 644 -> 644 [1] lasti
        [Code]
            File Name: <frozen program.modules.Search_groups>
            Object Name: generator_list
            Qualified Name: generator_list
            Arg Count: 1
            Pos Only Arg Count: 0
            KW Only Arg Count: 0
            Stack Size: 5
            Flags: 0x20000023 (CO_OPTIMIZED | CO_NEWLOCALS | CO_GENERATOR | CO_PYARMOR_OBFUSCATED)
            [Names]
                'len'
            [Locals+Names]
                'datalist'
                '__assert_armored__'
                '_var_var_4'
                '_var_var_5'
            [Constants]
                ' Генератор юзернеймов '
                '__pyarmor_assert_14511__'
                '__pyarmor_enter_14512__'
                b'<COAddr>\x07\x00\x00\x1e\x90\x00\x00\x00\x00\x00\x00\x00\x00\x00\x00\x00\x00\x00\x00\x00'
                0
                1
                '__pyarmor_exit_14513__'
                None
            [Disassembly]
                0       RETURN_GENERATOR                
                2       POP_TOP                         
                4       NOP                             
                6       NOP                             
                8       PUSH_NULL                       
                10      LOAD_CONST                      2: '__pyarmor_enter_14512__'
                12      LOAD_CONST                      3: b'<COAddr>\x07\x00\x00\x1e\x90\x00\x00\x00\x00\x00\x00\x00\x00\x00\x00\x00\x00\x00\x00\x00'
                14      BUILD_TUPLE                     1
                16      CALL_FUNCTION_EX                0
                18      POP_TOP                         
                20      RESUME                          0
                22      NOP                             
                24      NOP                             
                26      NOP                             
                28      NOP                             
                30      NOP                             
                32      LOAD_CONST                      4: 0
                34      STORE_FAST                      2: _var_var_4
                36      LOAD_GLOBAL                     1: NULL + len
                46      LOAD_FAST                       0: datalist
                48      CALL                            1
                56      STORE_FAST                      3: _var_var_5
                58      LOAD_FAST                       2: _var_var_4
                60      LOAD_GLOBAL                     1: NULL + len
                70      LOAD_FAST                       0: datalist
                72      CALL                            1
                80      COMPARE_OP                      2 (<)
                84      POP_JUMP_IF_FALSE               34 (to 154)
                86      LOAD_FAST                       0: datalist
                88      LOAD_FAST                       2: _var_var_4
                90      BINARY_SUBSCR                   
                94      YIELD_VALUE                     2
                96      RESUME                          1
                98      POP_TOP                         
                100     LOAD_FAST                       2: _var_var_4
                102     LOAD_CONST                      5: 1
                104     BINARY_OP                       13 (+=)
                108     STORE_FAST                      2: _var_var_4
                110     LOAD_FAST                       3: _var_var_5
                112     LOAD_FAST                       2: _var_var_4
                114     COMPARE_OP                      40 (==)
                118     POP_JUMP_IF_FALSE               2 (to 124)
                120     LOAD_CONST                      4: 0
                122     STORE_FAST                      2: _var_var_4
                124     LOAD_FAST                       2: _var_var_4
                126     LOAD_GLOBAL                     1: NULL + len
                136     LOAD_FAST                       0: datalist
                138     CALL                            1
                146     COMPARE_OP                      2 (<)
                150     POP_JUMP_IF_FALSE               1 (to 154)
                152     JUMP_BACKWARD                   34 (to 86)
                154     LOAD_CONST                      7: None
                156     NOP                             
                158     NOP                             
                160     NOP                             
                162     JUMP_FORWARD                    21 (to 206)
                170     POP_TOP                         
                172     RETURN_CONST                    7: None
                174     PUSH_EXC_INFO                   
                176     PUSH_NULL                       
                178     LOAD_CONST                      6: '__pyarmor_exit_14513__'
                180     NOP                             
                182     LOAD_CONST                      3: b'<COAddr>\x07\x00\x00\x1e\x90\x00\x00\x00\x00\x00\x00\x00\x00\x00\x00\x00\x00\x00\x00\x00'
                184     CALL                            1
                192     POP_TOP                         
                194     RERAISE                         0
                196     COPY                            3
                198     POP_EXCEPT                      
                200     RERAISE                         1
                202     CALL_INTRINSIC_1                3 (INTRINSIC_STOPITERATION_ERROR)
                204     RERAISE                         1
                206     PUSH_NULL                       
                208     LOAD_CONST                      6: '__pyarmor_exit_14513__'
                210     LOAD_CONST                      3: b'<COAddr>\x07\x00\x00\x1e\x90\x00\x00\x00\x00\x00\x00\x00\x00\x00\x00\x00\x00\x00\x00\x00'
                212     BUILD_TUPLE                     1
                214     CALL_FUNCTION_EX                0
                216     POP_TOP                         
                218     RETURN_VALUE                    
            [Exception Table]
                4 to 30 -> 202 [0] lasti
                32 to 152 -> 174 [0] 
                154 to 174 -> 202 [0] lasti
                174 to 196 -> 196 [1] lasti
                196 to 202 -> 202 [0] lasti
        [Code]
            File Name: <frozen program.modules.Search_groups>
            Object Name: START
            Qualified Name: START
            Arg Count: 5
            Pos Only Arg Count: 0
            KW Only Arg Count: 0
            Stack Size: 14
            Flags: 0x20000003 (CO_OPTIMIZED | CO_NEWLOCALS | CO_PYARMOR_OBFUSCATED)
            [Names]
                'is_set'
                'StopProgram'
                'check_get_settings'
                'get'
                'isinstance'
                'list'
                'int'
                'len'
                'eel'
                'sendErrorBox'
                'Lang'
                'db_search_groups'
                'create'
                'generator_list'
                'set_task_manager'
                'concurrent'
                'futures'
                'ThreadPoolExecutor'
                'StreamStat'
                'json'
                'dumps'
                'append'
                'submit'
                'worker'
                'as_completed'
                'BaseException'
                'logging'
                'del_task_manager'
                'StopDetect'
            [Locals+Names]
                'data'
                'config'
                'pid'
                'proxy'
                'stop_thread'
                '__assert_armored__'
                '_var_var_6'
                '_var_var_7'
                '_var_var_8'
                '_var_var_9'
                '_var_var_10'
                '_var_var_11'
                '_var_var_12'
                '_var_var_13'
                '_var_var_14'
                '_var_var_15'
                '_var_var_16'
                '_var_var_17'
                '_var_var_18'
                '_var_var_3'
            [Constants]
                None
                '__pyarmor_assert_14514__'
                '__pyarmor_enter_14515__'
                b'<COAddr>\x05\x00\x00\x1a\x1c\x06\x00\x00\x00\x00\x00\x00\x00\x00\x00\x00\x00\x00\x00\x00'
                'Settings'
                'Accounts'
                1
                'select_accounts_works'   # b'\x81\xf1\x1d\x1f6\xf9\xaa\xed\x1a\xf9\x0e\xcfy\xe2\xec\x960J\xb4\xb5\xa1\xd8'
                'thread_rules'   # b'\x81\xf6\x10\x016\xfb\xba\xed\t\xef\x01\xc5\x7f'
                True
                'thread_count'   # b'\x81\xf6\x10\x016\xfb\xba\xed\x18\xf5\x18\xcex'
                'list_admins'   # b"\x81\xee\x11\x00'\xc5\xbf\xd6\x16\xf3\x03\xd3"
                'No admins in list'   # b'\x81\xcc\x17S2\xfe\xb3\xdb\x15\xe9M\xc9b\xac\xf4\x8c\x1cI'
                'stuff'
                (
                    'accounts'
                    'name'
                )
                (
                    'max_workers'
                )
                0
                'st_task'
                'st_stream'   # b'\x81\xf1\x0c, \xee\xac\xd7\x1a\xf7'
                'st_wait'
                'st_done'
                '__pyarmor_exit_14516__'
                'Done'
            [Disassembly]
                0       NOP                             
                2       NOP                             
                4       PUSH_NULL                       
                6       LOAD_CONST                      2: '__pyarmor_enter_14515__'
                8       LOAD_CONST                      3: b'<COAddr>\x05\x00\x00\x1a\x1c\x06\x00\x00\x00\x00\x00\x00\x00\x00\x00\x00\x00\x00\x00\x00'
                10      BUILD_TUPLE                     1
                12      CALL_FUNCTION_EX                0
                14      POP_TOP                         
                16      RESUME                          0
                18      NOP                             
                20      NOP                             
                22      NOP                             
                24      NOP                             
                26      NOP                             
                28      NOP                             
                30      LOAD_FAST                       4: stop_thread
                32      LOAD_ATTR                       1: is_set
                52      CALL                            0
                60      POP_JUMP_IF_FALSE               10 (to 82)
                62      LOAD_GLOBAL                     3: NULL + StopProgram
                72      CALL                            0
                80      RAISE_VARARGS                   1
                82      LOAD_GLOBAL                     5: NULL + check_get_settings
                92      LOAD_FAST                       0: data
                94      LOAD_ATTR                       7: get
                114     LOAD_CONST                      4: 'Settings'
                116     CALL                            1
                124     CALL                            1
                132     POP_TOP                         
                134     LOAD_FAST                       0: data
                136     LOAD_CONST                      5: 'Accounts'
                138     BINARY_SUBSCR                   
                142     STORE_FAST                      6: _var_var_6
                144     LOAD_GLOBAL                     9: NULL + isinstance
                154     LOAD_FAST                       6: _var_var_6
                156     LOAD_GLOBAL                     10: list
                166     CALL                            2
                174     POP_JUMP_IF_TRUE                3 (to 182)
                176     LOAD_FAST                       6: _var_var_6
                178     BUILD_LIST                      1
                180     STORE_FAST                      6: _var_var_6
                182     LOAD_GLOBAL                     13: NULL + int
                192     LOAD_GLOBAL                     15: NULL + len
                202     LOAD_FAST                       6: _var_var_6
                204     CALL                            1
                212     CALL                            1
                220     LOAD_CONST                      6: 1
                222     COMPARE_OP                      2 (<)
                226     POP_JUMP_IF_FALSE               44 (to 316)
                228     LOAD_GLOBAL                     17: NULL + eel
                238     LOAD_ATTR                       18: sendErrorBox
                258     LOAD_GLOBAL                     20: Lang
                268     PUSH_NULL                       
                270     LOAD_CONST                      1: '__pyarmor_assert_14514__'
                272     LOAD_CONST                      7: 'select_accounts_works'   # b'\x81\xf1\x1d\x1f6\xf9\xaa\xed\x1a\xf9\x0e\xcfy\xe2\xec\x960J\xb4\xb5\xa1\xd8'
                274     CALL                            1
                282     BINARY_SUBSCR                   
                286     CALL                            1
                294     POP_TOP                         
                296     LOAD_GLOBAL                     3: NULL + StopProgram
                306     CALL                            0
                314     RAISE_VARARGS                   1
                316     LOAD_FAST                       0: data
                318     LOAD_CONST                      4: 'Settings'
                320     BINARY_SUBSCR                   
                324     LOAD_ATTR                       7: get
                344     PUSH_NULL                       
                346     LOAD_CONST                      1: '__pyarmor_assert_14514__'
                348     LOAD_CONST                      8: 'thread_rules'   # b'\x81\xf6\x10\x016\xfb\xba\xed\t\xef\x01\xc5\x7f'
                350     CALL                            1
                358     CALL                            1
                366     LOAD_CONST                      9: True
                368     COMPARE_OP                      40 (==)
                372     POP_JUMP_IF_FALSE               36 (to 446)
                374     LOAD_GLOBAL                     13: NULL + int
                384     LOAD_FAST                       0: data
                386     LOAD_CONST                      4: 'Settings'
                388     BINARY_SUBSCR                   
                392     LOAD_ATTR                       7: get
                412     PUSH_NULL                       
                414     LOAD_CONST                      1: '__pyarmor_assert_14514__'
                416     LOAD_CONST                      10: 'thread_count'   # b'\x81\xf6\x10\x016\xfb\xba\xed\x18\xf5\x18\xcex'
                418     CALL                            1
                426     CALL                            1
                434     CALL                            1
                442     STORE_FAST                      7: _var_var_7
                444     JUMP_FORWARD                    11 (to 468)
                446     LOAD_FAST                       1: config
                448     PUSH_NULL                       
                450     LOAD_CONST                      1: '__pyarmor_assert_14514__'
                452     LOAD_CONST                      10: 'thread_count'   # b'\x81\xf6\x10\x016\xfb\xba\xed\x18\xf5\x18\xcex'
                454     CALL                            1
                462     BINARY_SUBSCR                   
                466     STORE_FAST                      7: _var_var_7
                468     LOAD_GLOBAL                     23: NULL + db_search_groups
                478     CALL                            0
                486     LOAD_ATTR                       25: create
                506     CALL                            0
                514     STORE_FAST                      8: _var_var_8
                516     LOAD_FAST                       0: data
                518     LOAD_CONST                      4: 'Settings'
                520     BINARY_SUBSCR                   
                524     LOAD_ATTR                       7: get
                544     PUSH_NULL                       
                546     LOAD_CONST                      1: '__pyarmor_assert_14514__'
                548     LOAD_CONST                      11: 'list_admins'   # b"\x81\xee\x11\x00'\xc5\xbf\xd6\x16\xf3\x03\xd3"
                550     CALL                            1
                558     CALL                            1
                566     STORE_FAST                      9: _var_var_9
                568     LOAD_GLOBAL                     9: NULL + isinstance
                578     LOAD_FAST                       9: _var_var_9
                580     LOAD_GLOBAL                     10: list
                590     CALL                            2
                598     POP_JUMP_IF_TRUE                3 (to 606)
                600     LOAD_FAST                       9: _var_var_9
                602     BUILD_LIST                      1
                604     STORE_FAST                      9: _var_var_9
                606     LOAD_GLOBAL                     9: NULL + isinstance
                616     LOAD_FAST                       9: _var_var_9
                618     LOAD_GLOBAL                     10: list
                628     CALL                            2
                636     POP_JUMP_IF_FALSE               14 (to 666)
                638     LOAD_GLOBAL                     15: NULL + len
                648     LOAD_FAST                       9: _var_var_9
                650     CALL                            1
                658     LOAD_CONST                      6: 1
                660     COMPARE_OP                      2 (<)
                664     POP_JUMP_IF_FALSE               37 (to 740)
                666     LOAD_GLOBAL                     17: NULL + eel
                676     LOAD_ATTR                       18: sendErrorBox
                696     PUSH_NULL                       
                698     LOAD_CONST                      1: '__pyarmor_assert_14514__'
                700     LOAD_CONST                      12: 'No admins in list'   # b'\x81\xcc\x17S2\xfe\xb3\xdb\x15\xe9M\xc9b\xac\xf4\x8c\x1cI'
                702     CALL                            1
                710     CALL                            1
                718     POP_TOP                         
                720     LOAD_GLOBAL                     3: NULL + StopProgram
                730     CALL                            0
                738     RAISE_VARARGS                   1
                740     LOAD_GLOBAL                     27: NULL + generator_list
                750     LOAD_FAST                       9: _var_var_9
                752     CALL                            1
                760     STORE_FAST                      10: _var_var_10
                762     LOAD_GLOBAL                     29: NULL + set_task_manager
                772     LOAD_FAST                       2: pid
                774     LOAD_FAST                       6: _var_var_6
                776     LOAD_FAST                       0: data
                778     LOAD_CONST                      13: 'stuff'
                780     BINARY_SUBSCR                   
                784     KW_NAMES                        14: ('accounts', 'name')
                786     CALL                            3
                794     POP_TOP                         
                796     LOAD_GLOBAL                     30: concurrent
                806     LOAD_ATTR                       32: futures
                826     LOAD_ATTR                       35: ThreadPoolExecutor
                846     LOAD_FAST                       7: _var_var_7
                848     KW_NAMES                        15: ('max_workers',)
                850     CALL                            1
                858     BEFORE_WITH                     
                860     STORE_FAST                      11: _var_var_11
                862     BUILD_LIST                      0
                864     STORE_FAST                      12: _var_var_12
                866     LOAD_GLOBAL                     15: NULL + len
                876     LOAD_FAST                       6: _var_var_6
                878     CALL                            1
                886     STORE_FAST                      13: _var_var_13
                888     LOAD_FAST                       7: _var_var_7
                890     STORE_FAST                      14: _var_var_14
                892     LOAD_FAST                       13: _var_var_13
                894     STORE_FAST                      15: _var_var_15
                896     LOAD_CONST                      16: 0
                898     STORE_FAST                      16: _var_var_16
                900     LOAD_GLOBAL                     17: NULL + eel
                910     LOAD_ATTR                       36: StreamStat
                930     LOAD_GLOBAL                     39: NULL + json
                940     LOAD_ATTR                       40: dumps
                960     LOAD_CONST                      17: 'st_task'
                962     LOAD_FAST                       13: _var_var_13
                964     PUSH_NULL                       
                966     LOAD_CONST                      1: '__pyarmor_assert_14514__'
                968     LOAD_CONST                      18: 'st_stream'   # b'\x81\xf1\x0c, \xee\xac\xd7\x1a\xf7'
                970     CALL                            1
                978     LOAD_FAST                       14: _var_var_14
                980     LOAD_CONST                      19: 'st_wait'
                982     LOAD_FAST                       15: _var_var_15
                984     LOAD_CONST                      20: 'st_done'
                986     LOAD_FAST                       16: _var_var_16
                988     BUILD_MAP                       4
                990     CALL                            1
                998     CALL                            1
                1006    POP_TOP                         
                1008    LOAD_FAST                       6: _var_var_6
                1010    GET_ITER                        
                1012    FOR_ITER                        45 (to 1104)
                1016    STORE_FAST                      17: _var_var_17
                1018    LOAD_FAST                       12: _var_var_12
                1020    LOAD_ATTR                       43: append
                1040    LOAD_FAST                       11: _var_var_11
                1042    LOAD_ATTR                       45: submit
                1062    LOAD_GLOBAL                     46: worker
                1072    LOAD_FAST                       17: _var_var_17
                1074    LOAD_FAST                       1: config
                1076    LOAD_FAST                       3: proxy
                1078    LOAD_FAST                       0: data
                1080    LOAD_FAST                       10: _var_var_10
                1082    LOAD_FAST                       8: _var_var_8
                1084    LOAD_FAST                       4: stop_thread
                1086    CALL                            8
                1094    CALL                            1
                1102    POP_TOP                         
                1104    JUMP_BACKWARD                   47 (to 1012)
                1106    END_FOR                         
                1108    LOAD_GLOBAL                     30: concurrent
                1118    LOAD_ATTR                       32: futures
                1138    LOAD_ATTR                       49: as_completed
                1158    LOAD_FAST                       12: _var_var_12
                1160    CALL                            1
                1168    GET_ITER                        
                1170    FOR_ITER                        66 (to 1304)
                1174    STORE_FAST                      18: _var_var_18
                1176    LOAD_FAST                       16: _var_var_16
                1178    LOAD_CONST                      6: 1
                1180    BINARY_OP                       13 (+=)
                1184    STORE_FAST                      16: _var_var_16
                1186    LOAD_FAST                       15: _var_var_15
                1188    LOAD_CONST                      6: 1
                1190    BINARY_OP                       23 (-=)
                1194    STORE_FAST                      15: _var_var_15
                1196    LOAD_GLOBAL                     17: NULL + eel
                1206    LOAD_ATTR                       36: StreamStat
                1226    LOAD_GLOBAL                     39: NULL + json
                1236    LOAD_ATTR                       40: dumps
                1256    LOAD_CONST                      17: 'st_task'
                1258    LOAD_FAST                       13: _var_var_13
                1260    PUSH_NULL                       
                1262    LOAD_CONST                      1: '__pyarmor_assert_14514__'
                1264    LOAD_CONST                      18: 'st_stream'   # b'\x81\xf1\x0c, \xee\xac\xd7\x1a\xf7'
                1266    CALL                            1
                1274    LOAD_FAST                       14: _var_var_14
                1276    LOAD_CONST                      19: 'st_wait'
                1278    LOAD_FAST                       15: _var_var_15
                1280    LOAD_CONST                      20: 'st_done'
                1282    LOAD_FAST                       16: _var_var_16
                1284    BUILD_MAP                       4
                1286    CALL                            1
                1294    CALL                            1
                1302    POP_TOP                         
                1304    JUMP_BACKWARD                   68 (to 1170)
                1306    END_FOR                         
                1308    DELETE_FAST                     12: _var_var_12
                1310    DELETE_FAST                     0: data
                1312    LOAD_CONST                      0: None
                1314    LOAD_CONST                      0: None
                1316    LOAD_CONST                      0: None
                1318    CALL                            2
                1326    POP_TOP                         
                1328    LOAD_GLOBAL                     55: NULL + del_task_manager
                1338    LOAD_FAST                       2: pid
                1340    CALL                            1
                1348    POP_TOP                         
                1350    LOAD_GLOBAL                     57: NULL + StopDetect
                1360    LOAD_FAST                       4: stop_thread
                1362    CALL                            1
                1370    POP_TOP                         
                1372    NOP                             
                1374    LOAD_CONST                      22: 'Done'
                1376    NOP                             
                1378    NOP                             
                1380    NOP                             
                1382    JUMP_FORWARD                    117 (to 1618)
                1390    POP_TOP                         
                1392    RETURN_CONST                    22: 'Done'
                1394    PUSH_EXC_INFO                   
                1396    WITH_EXCEPT_START               
                1398    POP_JUMP_IF_TRUE                1 (to 1402)
                1400    RERAISE                         2
                1402    POP_TOP                         
                1404    POP_EXCEPT                      
                1406    POP_TOP                         
                1408    POP_TOP                         
                1410    JUMP_BACKWARD                   42 (to 1328)
                1412    COPY                            3
                1414    POP_EXCEPT                      
                1416    RERAISE                         1
                1418    PUSH_EXC_INFO                   
                1420    LOAD_GLOBAL                     2: StopProgram
                1430    CHECK_EXC_MATCH                 
                1432    POP_JUMP_IF_FALSE               3 (to 1440)
                1434    POP_TOP                         
                1436    POP_EXCEPT                      
                1438    JUMP_BACKWARD                   56 (to 1328)
                1440    LOAD_GLOBAL                     50: BaseException
                1450    CHECK_EXC_MATCH                 
                1452    POP_JUMP_IF_FALSE               26 (to 1506)
                1454    STORE_FAST                      19: _var_var_3
                1456    PUSH_NULL                       
                1458    LOAD_GLOBAL                     53: NULL + logging
                1468    LOAD_FAST                       19: _var_var_3
                1470    CALL                            1
                1478    CALL                            0
                1486    POP_TOP                         
                1488    POP_EXCEPT                      
                1490    LOAD_CONST                      0: None
                1492    STORE_FAST                      19: _var_var_3
                1494    DELETE_FAST                     19: _var_var_3
                1496    JUMP_BACKWARD                   85 (to 1328)
                1498    LOAD_CONST                      0: None
                1500    STORE_FAST                      19: _var_var_3
                1502    DELETE_FAST                     19: _var_var_3
                1504    RERAISE                         1
                1506    RERAISE                         0
                1508    COPY                            3
                1510    POP_EXCEPT                      
                1512    RERAISE                         1
                1514    PUSH_EXC_INFO                   
                1516    LOAD_GLOBAL                     55: NULL + del_task_manager
                1526    LOAD_FAST                       2: pid
                1528    CALL                            1
                1536    POP_TOP                         
                1538    LOAD_GLOBAL                     57: NULL + StopDetect
                1548    LOAD_FAST                       4: stop_thread
                1550    CALL                            1
                1558    POP_TOP                         
                1560    POP_TOP                         
                1562    POP_EXCEPT                      
                1564    LOAD_CONST                      22: 'Done'
                1566    NOP                             
                1568    NOP                             
                1570    NOP                             
                1572    JUMP_FORWARD                    22 (to 1618)
                1580    POP_TOP                         
                1582    RETURN_CONST                    22: 'Done'
                1584    COPY                            3
                1586    POP_EXCEPT                      
                1588    RERAISE                         1
                1590    PUSH_EXC_INFO                   
                1592    PUSH_NULL                       
                1594    LOAD_CONST                      21: '__pyarmor_exit_14516__'
                1596    NOP                             
                1598    LOAD_CONST                      3: b'<COAddr>\x05\x00\x00\x1a\x1c\x06\x00\x00\x00\x00\x00\x00\x00\x00\x00\x00\x00\x00\x00\x00'
                1600    CALL                            1
                1608    POP_TOP                         
                1610    RERAISE                         0
                1612    COPY                            3
                1614    POP_EXCEPT                      
                1616    RERAISE                         1
                1618    PUSH_NULL                       
                1620    LOAD_CONST                      21: '__pyarmor_exit_14516__'
                1622    LOAD_CONST                      3: b'<COAddr>\x05\x00\x00\x1a\x1c\x06\x00\x00\x00\x00\x00\x00\x00\x00\x00\x00\x00\x00\x00\x00'
                1624    BUILD_TUPLE                     1
                1626    CALL_FUNCTION_EX                0
                1628    POP_TOP                         
                1630    RETURN_VALUE                    
            [Exception Table]
                30 to 860 -> 1418 [0] 
                860 to 1312 -> 1394 [1] lasti
                1312 to 1328 -> 1418 [0] 
                1328 to 1372 -> 1590 [0] 
                1394 to 1404 -> 1412 [3] lasti
                1404 to 1418 -> 1418 [0] 
                1418 to 1436 -> 1508 [1] lasti
                1436 to 1440 -> 1514 [0] 
                1440 to 1456 -> 1508 [1] lasti
                1456 to 1488 -> 1498 [1] lasti
                1488 to 1498 -> 1514 [0] 
                1498 to 1508 -> 1508 [1] lasti
                1508 to 1514 -> 1514 [0] 
                1514 to 1562 -> 1584 [1] lasti
                1562 to 1564 -> 1590 [0] 
                1584 to 1590 -> 1590 [0] 
                1590 to 1612 -> 1612 [1] lasti
        [Code]
            File Name: <frozen program.modules.Search_groups>
            Object Name: channel_transfer_group
            Qualified Name: channel_transfer_group
            Arg Count: 4
            Pos Only Arg Count: 0
            KW Only Arg Count: 0
            Stack Size: 9
            Flags: 0x20000003 (CO_OPTIMIZED | CO_NEWLOCALS | CO_PYARMOR_OBFUSCATED)
            [Names]
                'get_account_json'
                'Logs'
                'PrintLog'
                'config'
                'title'
                'functions'
                'account'
                'GetPasswordRequest'
                'pwd_mod'
                'compute_check'
                'channels'
                'EditCreatorRequest'
                'time'
                'sleep'
                'Exception'
                'type'
                '__name__'
            [Locals+Names]
                'account'
                'client'
                'channel'
                'admin'
                '__assert_armored__'
                '_var_var_19'
                '_var_var_20'
                '_var_var_21'
                '_var_var_22'
                '_var_var_23'
                '_var_var_3'
            [Constants]
                None
                '__pyarmor_assert_14517__'
                '__pyarmor_enter_14518__'
                b'<COAddr>\x05\x00\x00\x1ah\x02\x00\x00\x00\x00\x00\x00\x00\x00\x00\x00\x00\x00\x00\x00'
                'twoFA'
                'Transfer group'   # b'\x81\xd6\n\x12=\xe9\xb8\xd7\t\xba\n\xd2c\xf9\xe8'
                (
                    'config'
                    'account'
                    'message'
                    'end'
                )
                (
                    'channel'
                    'user_id'
                    'password'
                )
                'Done, wait 3 sec...'   # b'\x81\xc6\x17\x1d6\xb6\xfe\xc5\x1a\xf3\x19\x80?\xac\xeb\x80\x0c\x13\xf5\xe9'
                (
                    'config'
                    'account'
                    'message'
                )
                3
                '__pyarmor_exit_14519__'
                True
                'Error'
                (
                    'config'
                    'account'
                    'message'
                    'param'
                    'end'
                )
                False
            [Disassembly]
                0       NOP                             
                2       NOP                             
                4       PUSH_NULL                       
                6       LOAD_CONST                      2: '__pyarmor_enter_14518__'
                8       LOAD_CONST                      3: b'<COAddr>\x05\x00\x00\x1ah\x02\x00\x00\x00\x00\x00\x00\x00\x00\x00\x00\x00\x00\x00\x00'
                10      BUILD_TUPLE                     1
                12      CALL_FUNCTION_EX                0
                14      POP_TOP                         
                16      RESUME                          0
                18      NOP                             
                20      NOP                             
                22      NOP                             
                24      NOP                             
                26      NOP                             
                28      NOP                             
                30      LOAD_GLOBAL                     1: NULL + get_account_json
                40      LOAD_FAST                       0: account
                42      CALL                            1
                50      STORE_FAST                      5: _var_var_19
                52      LOAD_FAST                       5: _var_var_19
                54      LOAD_CONST                      4: 'twoFA'
                56      BINARY_SUBSCR                   
                60      STORE_FAST                      6: _var_var_20
                62      LOAD_GLOBAL                     3: NULL + Logs
                72      LOAD_ATTR                       4: PrintLog
                92      LOAD_GLOBAL                     6: config
                102     LOAD_FAST                       0: account
                104     PUSH_NULL                       
                106     LOAD_CONST                      1: '__pyarmor_assert_14517__'
                108     LOAD_CONST                      5: 'Transfer group'   # b'\x81\xd6\n\x12=\xe9\xb8\xd7\t\xba\n\xd2c\xf9\xe8'
                110     CALL                            1
                118     LOAD_FAST                       2: channel
                120     LOAD_ATTR                       8: title
                140     KW_NAMES                        6: ('config', 'account', 'message', 'end')
                142     CALL                            4
                150     POP_TOP                         
                152     PUSH_NULL                       
                154     LOAD_FAST                       1: client
                156     LOAD_GLOBAL                     10: functions
                166     LOAD_ATTR                       12: account
                186     LOAD_ATTR                       15: GetPasswordRequest
                206     CALL                            0
                214     CALL                            1
                222     STORE_FAST                      7: _var_var_21
                224     LOAD_GLOBAL                     17: NULL + pwd_mod
                234     LOAD_ATTR                       18: compute_check
                254     LOAD_FAST                       7: _var_var_21
                256     LOAD_FAST                       6: _var_var_20
                258     CALL                            2
                266     STORE_FAST                      8: _var_var_22
                268     PUSH_NULL                       
                270     LOAD_FAST                       1: client
                272     LOAD_GLOBAL                     10: functions
                282     LOAD_ATTR                       20: channels
                302     LOAD_ATTR                       23: EditCreatorRequest
                322     LOAD_FAST                       2: channel
                324     LOAD_FAST                       3: admin
                326     LOAD_FAST                       8: _var_var_22
                328     KW_NAMES                        7: ('channel', 'user_id', 'password')
                330     CALL                            3
                338     CALL                            1
                346     STORE_FAST                      9: _var_var_23
                348     LOAD_GLOBAL                     3: NULL + Logs
                358     LOAD_ATTR                       4: PrintLog
                378     LOAD_GLOBAL                     6: config
                388     LOAD_FAST                       0: account
                390     PUSH_NULL                       
                392     LOAD_CONST                      1: '__pyarmor_assert_14517__'
                394     LOAD_CONST                      8: 'Done, wait 3 sec...'   # b'\x81\xc6\x17\x1d6\xb6\xfe\xc5\x1a\xf3\x19\x80?\xac\xeb\x80\x0c\x13\xf5\xe9'
                396     CALL                            1
                404     KW_NAMES                        9: ('config', 'account', 'message')
                406     CALL                            3
                414     POP_TOP                         
                416     LOAD_GLOBAL                     25: NULL + time
                426     LOAD_ATTR                       26: sleep
                446     LOAD_CONST                      10: 3
                448     CALL                            1
                456     POP_TOP                         
                458     NOP                             
                460     LOAD_CONST                      12: True
                462     NOP                             
                464     NOP                             
                466     NOP                             
                468     JUMP_FORWARD                    100 (to 670)
                476     POP_TOP                         
                478     RETURN_CONST                    12: True
                480     PUSH_EXC_INFO                   
                482     LOAD_GLOBAL                     28: Exception
                492     CHECK_EXC_MATCH                 
                494     POP_JUMP_IF_FALSE               59 (to 614)
                496     STORE_FAST                      10: _var_var_3
                498     LOAD_GLOBAL                     3: NULL + Logs
                508     LOAD_ATTR                       4: PrintLog
                528     LOAD_GLOBAL                     6: config
                538     LOAD_FAST                       0: account
                540     LOAD_CONST                      13: 'Error'
                542     LOAD_GLOBAL                     31: NULL + type
                552     LOAD_FAST                       10: _var_var_3
                554     CALL                            1
                562     LOAD_ATTR                       32: __name__
                582     LOAD_FAST                       10: _var_var_3
                584     KW_NAMES                        14: ('config', 'account', 'message', 'param', 'end')
                586     CALL                            5
                594     POP_TOP                         
                596     POP_EXCEPT                      
                598     LOAD_CONST                      0: None
                600     STORE_FAST                      10: _var_var_3
                602     DELETE_FAST                     10: _var_var_3
                604     JUMP_FORWARD                    8 (to 622)
                606     LOAD_CONST                      0: None
                608     STORE_FAST                      10: _var_var_3
                610     DELETE_FAST                     10: _var_var_3
                612     RERAISE                         1
                614     RERAISE                         0
                616     COPY                            3
                618     POP_EXCEPT                      
                620     RERAISE                         1
                622     LOAD_CONST                      15: False
                624     NOP                             
                626     NOP                             
                628     NOP                             
                630     JUMP_FORWARD                    19 (to 670)
                638     POP_TOP                         
                640     RETURN_CONST                    15: False
                642     PUSH_EXC_INFO                   
                644     PUSH_NULL                       
                646     LOAD_CONST                      11: '__pyarmor_exit_14519__'
                648     NOP                             
                650     LOAD_CONST                      3: b'<COAddr>\x05\x00\x00\x1ah\x02\x00\x00\x00\x00\x00\x00\x00\x00\x00\x00\x00\x00\x00\x00'
                652     CALL                            1
                660     POP_TOP                         
                662     RERAISE                         0
                664     COPY                            3
                666     POP_EXCEPT                      
                668     RERAISE                         1
                670     PUSH_NULL                       
                672     LOAD_CONST                      11: '__pyarmor_exit_14519__'
                674     LOAD_CONST                      3: b'<COAddr>\x05\x00\x00\x1ah\x02\x00\x00\x00\x00\x00\x00\x00\x00\x00\x00\x00\x00\x00\x00'
                676     BUILD_TUPLE                     1
                678     CALL_FUNCTION_EX                0
                680     POP_TOP                         
                682     RETURN_VALUE                    
            [Exception Table]
                30 to 458 -> 480 [0] 
                480 to 498 -> 616 [1] lasti
                498 to 596 -> 606 [1] lasti
                596 to 606 -> 642 [0] 
                606 to 616 -> 616 [1] lasti
                616 to 622 -> 642 [0] 
                642 to 664 -> 664 [1] lasti
        [Code]
            File Name: <frozen program.modules.Search_groups>
            Object Name: channel_get_link
            Qualified Name: channel_get_link
            Arg Count: 3
            Pos Only Arg Count: 0
            KW Only Arg Count: 0
            Stack Size: 8
            Flags: 0x20000003 (CO_OPTIMIZED | CO_NEWLOCALS | CO_PYARMOR_OBFUSCATED)
            [Names]
                'functions'
                'messages'
                'ExportChatInviteRequest'
                'Logs'
                'PrintLog'
                'config'
                'link'
                'Exception'
            [Locals+Names]
                'account'
                'client'
                'channel'
                '__assert_armored__'
                '_var_var_24'
                '_var_var_3'
            [Constants]
                None
                '__pyarmor_assert_14520__'
                '__pyarmor_enter_14521__'
                b'<COAddr>\x07\x00\x00\x1a\\\x01\x00\x00\x00\x00\x00\x00\x00\x00\x00\x00\x00\x00\x00\x00'
                ''
                (
                    'peer'
                    'title'
                )
                'Get link:'   # b'\x81\xc5\x1d\x07s\xf6\xb7\xdc\x10\xa0'
                (
                    'config'
                    'account'
                    'message'
                    'end'
                )
                '__pyarmor_exit_14522__'
                'channel_get_link'   # b'\x81\xe1\x10\x12=\xf4\xbb\xde$\xfd\x08\xd4S\xe0\xf1\x8b\x04'
                (
                    'config'
                    'account'
                    'message'
                    'param'
                )
                False
            [Disassembly]
                0       NOP                             
                2       NOP                             
                4       PUSH_NULL                       
                6       LOAD_CONST                      2: '__pyarmor_enter_14521__'
                8       LOAD_CONST                      3: b'<COAddr>\x07\x00\x00\x1a\\\x01\x00\x00\x00\x00\x00\x00\x00\x00\x00\x00\x00\x00\x00\x00'
                10      BUILD_TUPLE                     1
                12      CALL_FUNCTION_EX                0
                14      POP_TOP                         
                16      RESUME                          0
                18      NOP                             
                20      NOP                             
                22      NOP                             
                24      NOP                             
                26      NOP                             
                28      NOP                             
                30      PUSH_NULL                       
                32      LOAD_FAST                       1: client
                34      LOAD_GLOBAL                     0: functions
                44      LOAD_ATTR                       2: messages
                64      LOAD_ATTR                       5: ExportChatInviteRequest
                84      LOAD_FAST                       2: channel
                86      LOAD_CONST                      4: ''
                88      KW_NAMES                        5: ('peer', 'title')
                90      CALL                            2
                98      CALL                            1
                106     STORE_FAST                      4: _var_var_24
                108     LOAD_GLOBAL                     7: NULL + Logs
                118     LOAD_ATTR                       8: PrintLog
                138     LOAD_GLOBAL                     10: config
                148     LOAD_FAST                       0: account
                150     PUSH_NULL                       
                152     LOAD_CONST                      1: '__pyarmor_assert_14520__'
                154     LOAD_CONST                      6: 'Get link:'   # b'\x81\xc5\x1d\x07s\xf6\xb7\xdc\x10\xa0'
                156     CALL                            1
                164     LOAD_FAST                       4: _var_var_24
                166     LOAD_ATTR                       12: link
                186     KW_NAMES                        7: ('config', 'account', 'message', 'end')
                188     CALL                            4
                196     POP_TOP                         
                198     LOAD_FAST                       4: _var_var_24
                200     LOAD_ATTR                       12: link
                220     NOP                             
                222     NOP                             
                224     NOP                             
                226     JUMP_FORWARD                    87 (to 402)
                228     CALL                            1
                236     POP_TOP                         
                238     RETURN_VALUE                    
                240     PUSH_EXC_INFO                   
                242     LOAD_GLOBAL                     14: Exception
                252     CHECK_EXC_MATCH                 
                254     POP_JUMP_IF_FALSE               45 (to 346)
                256     STORE_FAST                      5: _var_var_3
                258     LOAD_GLOBAL                     7: NULL + Logs
                268     LOAD_ATTR                       8: PrintLog
                288     LOAD_GLOBAL                     10: config
                298     LOAD_FAST                       0: account
                300     PUSH_NULL                       
                302     LOAD_CONST                      1: '__pyarmor_assert_14520__'
                304     LOAD_CONST                      9: 'channel_get_link'   # b'\x81\xe1\x10\x12=\xf4\xbb\xde$\xfd\x08\xd4S\xe0\xf1\x8b\x04'
                306     CALL                            1
                314     LOAD_FAST                       5: _var_var_3
                316     KW_NAMES                        10: ('config', 'account', 'message', 'param')
                318     CALL                            4
                326     POP_TOP                         
                328     POP_EXCEPT                      
                330     LOAD_CONST                      0: None
                332     STORE_FAST                      5: _var_var_3
                334     DELETE_FAST                     5: _var_var_3
                336     JUMP_FORWARD                    8 (to 354)
                338     LOAD_CONST                      0: None
                340     STORE_FAST                      5: _var_var_3
                342     DELETE_FAST                     5: _var_var_3
                344     RERAISE                         1
                346     RERAISE                         0
                348     COPY                            3
                350     POP_EXCEPT                      
                352     RERAISE                         1
                354     LOAD_CONST                      11: False
                356     NOP                             
                358     NOP                             
                360     NOP                             
                362     JUMP_FORWARD                    19 (to 402)
                370     POP_TOP                         
                372     RETURN_CONST                    11: False
                374     PUSH_EXC_INFO                   
                376     PUSH_NULL                       
                378     LOAD_CONST                      8: '__pyarmor_exit_14522__'
                380     NOP                             
                382     LOAD_CONST                      3: b'<COAddr>\x07\x00\x00\x1a\\\x01\x00\x00\x00\x00\x00\x00\x00\x00\x00\x00\x00\x00\x00\x00'
                384     CALL                            1
                392     POP_TOP                         
                394     RERAISE                         0
                396     COPY                            3
                398     POP_EXCEPT                      
                400     RERAISE                         1
                402     PUSH_NULL                       
                404     LOAD_CONST                      8: '__pyarmor_exit_14522__'
                406     LOAD_CONST                      3: b'<COAddr>\x07\x00\x00\x1a\\\x01\x00\x00\x00\x00\x00\x00\x00\x00\x00\x00\x00\x00\x00\x00'
                408     BUILD_TUPLE                     1
                410     CALL_FUNCTION_EX                0
                412     POP_TOP                         
                414     RETURN_VALUE                    
            [Exception Table]
                30 to 220 -> 240 [0] 
                240 to 258 -> 348 [1] lasti
                258 to 328 -> 338 [1] lasti
                328 to 338 -> 374 [0] 
                338 to 348 -> 348 [1] lasti
                348 to 354 -> 374 [0] 
                374 to 396 -> 396 [1] lasti
        [Code]
            File Name: <frozen program.modules.Search_groups>
            Object Name: worker
            Qualified Name: worker
            Arg Count: 7
            Pos Only Arg Count: 0
            KW Only Arg Count: 0
            Stack Size: 10
            Flags: 0x20000003 (CO_OPTIMIZED | CO_NEWLOCALS | CO_PYARMOR_OBFUSCATED)
            [Names]
                'Thread_wait'
                'account_works'
                'Lang'
                'Disconnect'
                'Logs'
                'PrintLog'
                'int'
                'get'
                'is_set'
                'StopProgram'
                'iter_dialogs'
                'hasattr'
                'entity'
                'creator'
                'next'
                'channel_transfer_group'
                'getattr'
                'channel_get_link'
                'db_search_groups'
                'insert'
                'id'
                'title'
                'BaseException'
                'logging'
            [Locals+Names]
                'account'
                'config'
                'proxy'
                'data'
                'admins'
                'db_result'
                'stop_thread'
                '__assert_armored__'
                '_var_var_25'
                '_var_var_26'
                '_var_var_27'
                '_var_var_28'
                '_var_var_29'
                '_var_var_30'
                '_var_var_31'
                '_var_var_32'
                '_var_var_3'
            [Constants]
                None
                '__pyarmor_assert_14523__'
                '__pyarmor_enter_14524__'
                b'<COAddr>\x05\x00\x00\x1a\xec\x05\x00\x00\x00\x00\x00\x00\x00\x00\x00\x00\x00\x00\x00\x00'
                'CreateChannel'   # b'\x81\xc1\n\x162\xee\xbb\xf1\x13\xfb\x03\xcei\xe0'
                (
                    'module'
                )
                False
                'false'
                (
                    'account'
                    'status'
                )
                'work_account_completed'   # b'\x81\xf5\x17\x018\xc5\xbf\xd1\x18\xf5\x18\xcex\xd3\xfb\x8a\x02M\xb7\xa2\xbe\xceJ'
                (
                    'config'
                    'account'
                    'message'
                )
                'done'
                '__pyarmor_exit_14525__'
                'Settings'
                'max_flood_wait'   # b'\x81\xef\x19\x0b\x0c\xfc\xb2\xdd\x14\xfe2\xd7m\xe5\xec'
                'add_admins'   # b'\x81\xe3\x1c\x17\x0c\xfb\xba\xdf\x12\xf4\x1e'
                250
                (
                    'limit'
                )
                'entity'
                'creator'
                'Owner changed'   # b'\x81\xcd\x0f\x1d6\xe8\xfe\xd1\x13\xfb\x03\xc7i\xe8'
                'Done'
                'username'
                'Unknow'
                0
                (
                    'account'
                    'uid'
                    'link'
                    'title'
                    'count'
                    'new_owner'
                    'status'
                )
            [Disassembly]
                0       NOP                             
                2       NOP                             
                4       PUSH_NULL                       
                6       LOAD_CONST                      2: '__pyarmor_enter_14524__'
                8       LOAD_CONST                      3: b'<COAddr>\x05\x00\x00\x1a\xec\x05\x00\x00\x00\x00\x00\x00\x00\x00\x00\x00\x00\x00\x00\x00'
                10      BUILD_TUPLE                     1
                12      CALL_FUNCTION_EX                0
                14      POP_TOP                         
                16      RESUME                          0
                18      NOP                             
                20      NOP                             
                22      NOP                             
                24      NOP                             
                26      NOP                             
                28      NOP                             
                30      LOAD_GLOBAL                     1: NULL + Thread_wait
                40      LOAD_FAST                       3: data
                42      LOAD_FAST                       1: config
                44      LOAD_FAST                       6: stop_thread
                46      CALL                            3
                54      POP_TOP                         
                56      LOAD_GLOBAL                     3: NULL + account_works
                66      LOAD_FAST                       1: config
                68      LOAD_GLOBAL                     4: Lang
                78      LOAD_FAST                       2: proxy
                80      LOAD_FAST                       0: account
                82      LOAD_FAST                       6: stop_thread
                84      PUSH_NULL                       
                86      LOAD_CONST                      1: '__pyarmor_assert_14523__'
                88      LOAD_CONST                      4: 'CreateChannel'   # b'\x81\xc1\n\x162\xee\xbb\xf1\x13\xfb\x03\xcei\xe0'
                90      CALL                            1
                98      KW_NAMES                        5: ('module',)
                100     CALL                            6
                108     STORE_FAST                      8: _var_var_25
                110     LOAD_FAST                       8: _var_var_25
                112     LOAD_CONST                      6: False
                114     COMPARE_OP                      40 (==)
                118     POP_JUMP_IF_FALSE               68 (to 256)
                120     LOAD_FAST                       0: account
                122     LOAD_CONST                      7: 'false'
                124     LOAD_CONST                      8: ('account', 'status')
                126     BUILD_CONST_KEY_MAP             2
                128     LOAD_GLOBAL                     7: NULL + Disconnect
                138     LOAD_FAST                       8: _var_var_25
                140     CALL                            1
                148     POP_TOP                         
                150     LOAD_GLOBAL                     9: NULL + Logs
                160     LOAD_ATTR                       10: PrintLog
                180     LOAD_FAST                       1: config
                182     LOAD_FAST                       0: account
                184     LOAD_GLOBAL                     4: Lang
                194     PUSH_NULL                       
                196     LOAD_CONST                      1: '__pyarmor_assert_14523__'
                198     LOAD_CONST                      9: 'work_account_completed'   # b'\x81\xf5\x17\x018\xc5\xbf\xd1\x18\xf5\x18\xcex\xd3\xfb\x8a\x02M\xb7\xa2\xbe\xceJ'
                200     CALL                            1
                208     BINARY_SUBSCR                   
                212     KW_NAMES                        10: ('config', 'account', 'message')
                214     CALL                            3
                222     POP_TOP                         
                224     LOAD_FAST                       0: account
                226     LOAD_CONST                      11: 'done'
                228     LOAD_CONST                      8: ('account', 'status')
                230     BUILD_CONST_KEY_MAP             2
                232     SWAP                            2
                234     POP_TOP                         
                236     NOP                             
                238     NOP                             
                240     JUMP_FORWARD                    663 (to 1570)
                244     CALL                            1
                252     POP_TOP                         
                254     RETURN_VALUE                    
                256     LOAD_GLOBAL                     13: NULL + int
                266     LOAD_FAST                       3: data
                268     LOAD_CONST                      13: 'Settings'
                270     BINARY_SUBSCR                   
                274     LOAD_ATTR                       15: get
                294     PUSH_NULL                       
                296     LOAD_CONST                      1: '__pyarmor_assert_14523__'
                298     LOAD_CONST                      14: 'max_flood_wait'   # b'\x81\xef\x19\x0b\x0c\xfc\xb2\xdd\x14\xfe2\xd7m\xe5\xec'
                300     CALL                            1
                308     CALL                            1
                316     CALL                            1
                324     STORE_FAST                      9: _var_var_26
                326     LOAD_GLOBAL                     13: NULL + int
                336     LOAD_FAST                       3: data
                338     LOAD_CONST                      13: 'Settings'
                340     BINARY_SUBSCR                   
                344     LOAD_ATTR                       15: get
                364     PUSH_NULL                       
                366     LOAD_CONST                      1: '__pyarmor_assert_14523__'
                368     LOAD_CONST                      15: 'add_admins'   # b'\x81\xe3\x1c\x17\x0c\xfb\xba\xdf\x12\xf4\x1e'
                370     CALL                            1
                378     CALL                            1
                386     CALL                            1
                394     STORE_FAST                      10: _var_var_27
                396     LOAD_FAST                       6: stop_thread
                398     LOAD_ATTR                       17: is_set
                418     CALL                            0
                426     POP_JUMP_IF_FALSE               10 (to 448)
                428     LOAD_GLOBAL                     19: NULL + StopProgram
                438     CALL                            0
                446     RAISE_VARARGS                   1
                448     NOP                             
                450     LOAD_FAST                       8: _var_var_25
                452     LOAD_ATTR                       21: iter_dialogs
                472     LOAD_CONST                      16: 250
                474     KW_NAMES                        17: ('limit',)
                476     CALL                            1
                484     STORE_FAST                      11: _var_var_28
                486     LOAD_FAST                       11: _var_var_28
                488     GET_ITER                        
                490     FOR_ITER                        271 (to 1036)
                496     STORE_FAST                      12: _var_var_29
                498     LOAD_FAST                       6: stop_thread
                500     LOAD_ATTR                       17: is_set
                520     CALL                            0
                528     POP_JUMP_IF_FALSE               10 (to 550)
                530     LOAD_GLOBAL                     19: NULL + StopProgram
                540     CALL                            0
                548     RAISE_VARARGS                   1
                550     LOAD_GLOBAL                     23: NULL + hasattr
                560     LOAD_FAST                       12: _var_var_29
                562     LOAD_CONST                      18: 'entity'
                564     CALL                            2
                572     POP_JUMP_IF_TRUE                1 (to 576)
                574     JUMP_BACKWARD                   43 (to 490)
                576     LOAD_GLOBAL                     23: NULL + hasattr
                586     LOAD_FAST                       12: _var_var_29
                588     LOAD_ATTR                       24: entity
                608     LOAD_CONST                      19: 'creator'
                610     CALL                            2
                618     POP_JUMP_IF_TRUE                1 (to 622)
                620     JUMP_BACKWARD                   66 (to 490)
                622     LOAD_FAST                       12: _var_var_29
                624     LOAD_ATTR                       24: entity
                644     LOAD_ATTR                       26: creator
                664     POP_JUMP_IF_TRUE                1 (to 668)
                666     JUMP_BACKWARD                   89 (to 490)
                668     LOAD_FAST                       10: _var_var_27
                670     POP_JUMP_IF_FALSE               49 (to 770)
                672     LOAD_GLOBAL                     29: NULL + next
                682     LOAD_FAST                       4: admins
                684     CALL                            1
                692     STORE_FAST                      13: _var_var_30
                694     LOAD_GLOBAL                     31: NULL + channel_transfer_group
                704     LOAD_FAST                       0: account
                706     LOAD_FAST                       8: _var_var_25
                708     LOAD_FAST                       12: _var_var_29
                710     LOAD_ATTR                       24: entity
                730     LOAD_FAST                       13: _var_var_30
                732     CALL                            4
                740     POP_JUMP_IF_FALSE               9 (to 760)
                742     PUSH_NULL                       
                744     LOAD_CONST                      1: '__pyarmor_assert_14523__'
                746     LOAD_CONST                      20: 'Owner changed'   # b'\x81\xcd\x0f\x1d6\xe8\xfe\xd1\x13\xfb\x03\xc7i\xe8'
                748     CALL                            1
                756     STORE_FAST                      14: _var_var_31
                758     JUMP_FORWARD                    9 (to 778)
                760     LOAD_CONST                      21: 'Done'
                762     STORE_FAST                      14: _var_var_31
                764     LOAD_CONST                      0: None
                766     STORE_FAST                      13: _var_var_30
                768     JUMP_FORWARD                    4 (to 778)
                770     LOAD_CONST                      21: 'Done'
                772     STORE_FAST                      14: _var_var_31
                774     LOAD_CONST                      0: None
                776     STORE_FAST                      13: _var_var_30
                778     LOAD_GLOBAL                     33: NULL + getattr
                788     LOAD_FAST                       12: _var_var_29
                790     LOAD_ATTR                       24: entity
                810     LOAD_CONST                      22: 'username'
                812     LOAD_CONST                      0: None
                814     CALL                            3
                822     STORE_FAST                      15: _var_var_32
                824     LOAD_FAST                       15: _var_var_32
                826     POP_JUMP_IF_NOT_NONE            30 (to 888)
                828     LOAD_GLOBAL                     35: NULL + channel_get_link
                838     LOAD_FAST                       0: account
                840     LOAD_FAST                       8: _var_var_25
                842     LOAD_FAST                       12: _var_var_29
                844     LOAD_ATTR                       24: entity
                864     CALL                            3
                872     STORE_FAST                      15: _var_var_32
                874     LOAD_FAST                       15: _var_var_32
                876     LOAD_CONST                      6: False
                878     COMPARE_OP                      40 (==)
                882     POP_JUMP_IF_FALSE               2 (to 888)
                884     LOAD_CONST                      23: 'Unknow'
                886     STORE_FAST                      15: _var_var_32
                888     LOAD_GLOBAL                     37: NULL + db_search_groups
                898     LOAD_FAST                       5: db_result
                900     CALL                            1
                908     LOAD_ATTR                       39: insert
                928     LOAD_FAST                       0: account
                930     LOAD_FAST                       12: _var_var_29
                932     LOAD_ATTR                       24: entity
                952     LOAD_ATTR                       40: id
                972     LOAD_FAST                       15: _var_var_32
                974     LOAD_FAST                       12: _var_var_29
                976     LOAD_ATTR                       24: entity
                996     LOAD_ATTR                       42: title
                1016    LOAD_CONST                      24: 0
                1018    LOAD_FAST                       13: _var_var_30
                1020    LOAD_FAST                       14: _var_var_31
                1022    KW_NAMES                        25: ('account', 'uid', 'link', 'title', 'count', 'new_owner', 'status')
                1024    CALL                            7
                1032    POP_TOP                         
                1034    JUMP_BACKWARD                   274 (to 490)
                1038    END_FOR                         
                1040    NOP                             
                1042    LOAD_GLOBAL                     7: NULL + Disconnect
                1052    LOAD_FAST_CHECK                 8: _var_var_25
                1054    CALL                            1
                1062    POP_TOP                         
                1064    LOAD_GLOBAL                     9: NULL + Logs
                1074    LOAD_ATTR                       10: PrintLog
                1094    LOAD_FAST                       1: config
                1096    LOAD_FAST                       0: account
                1098    LOAD_GLOBAL                     4: Lang
                1108    PUSH_NULL                       
                1110    LOAD_CONST                      1: '__pyarmor_assert_14523__'
                1112    LOAD_CONST                      9: 'work_account_completed'   # b'\x81\xf5\x17\x018\xc5\xbf\xd1\x18\xf5\x18\xcex\xd3\xfb\x8a\x02M\xb7\xa2\xbe\xceJ'
                1114    CALL                            1
                1122    BINARY_SUBSCR                   
                1126    KW_NAMES                        10: ('config', 'account', 'message')
                1128    CALL                            3
                1136    POP_TOP                         
                1138    LOAD_FAST                       0: account
                1140    LOAD_CONST                      11: 'done'
                1142    LOAD_CONST                      8: ('account', 'status')
                1144    BUILD_CONST_KEY_MAP             2
                1146    NOP                             
                1148    NOP                             
                1150    NOP                             
                1152    JUMP_FORWARD                    208 (to 1570)
                1154    CALL                            1
                1162    POP_TOP                         
                1164    RETURN_VALUE                    
                1166    PUSH_EXC_INFO                   
                1168    POP_TOP                         
                1170    POP_EXCEPT                      
                1172    JUMP_BACKWARD                   513 (to 150)
                1176    COPY                            3
                1178    POP_EXCEPT                      
                1180    RERAISE                         1
                1182    PUSH_EXC_INFO                   
                1184    LOAD_GLOBAL                     18: StopProgram
                1194    CHECK_EXC_MATCH                 
                1196    POP_JUMP_IF_FALSE               2 (to 1202)
                1198    POP_TOP                         
                1200    RAISE_VARARGS                   0
                1202    LOAD_GLOBAL                     44: BaseException
                1212    CHECK_EXC_MATCH                 
                1214    POP_JUMP_IF_FALSE               26 (to 1268)
                1216    STORE_FAST                      16: _var_var_3
                1218    PUSH_NULL                       
                1220    LOAD_GLOBAL                     47: NULL + logging
                1230    LOAD_FAST                       16: _var_var_3
                1232    CALL                            1
                1240    CALL                            0
                1248    POP_TOP                         
                1250    POP_EXCEPT                      
                1252    LOAD_CONST                      0: None
                1254    STORE_FAST                      16: _var_var_3
                1256    DELETE_FAST                     16: _var_var_3
                1258    JUMP_BACKWARD                   109 (to 1042)
                1260    LOAD_CONST                      0: None
                1262    STORE_FAST                      16: _var_var_3
                1264    DELETE_FAST                     16: _var_var_3
                1266    RERAISE                         1
                1268    RERAISE                         0
                1270    COPY                            3
                1272    POP_EXCEPT                      
                1274    RERAISE                         1
                1276    PUSH_EXC_INFO                   
                1278    LOAD_GLOBAL                     18: StopProgram
                1288    CHECK_EXC_MATCH                 
                1290    POP_JUMP_IF_FALSE               3 (to 1298)
                1292    POP_TOP                         
                1294    POP_EXCEPT                      
                1296    JUMP_BACKWARD                   128 (to 1042)
                1298    LOAD_GLOBAL                     44: BaseException
                1308    CHECK_EXC_MATCH                 
                1310    POP_JUMP_IF_FALSE               26 (to 1364)
                1312    STORE_FAST                      16: _var_var_3
                1314    PUSH_NULL                       
                1316    LOAD_GLOBAL                     47: NULL + logging
                1326    LOAD_FAST                       16: _var_var_3
                1328    CALL                            1
                1336    CALL                            0
                1344    POP_TOP                         
                1346    POP_EXCEPT                      
                1348    LOAD_CONST                      0: None
                1350    STORE_FAST                      16: _var_var_3
                1352    DELETE_FAST                     16: _var_var_3
                1354    JUMP_BACKWARD                   157 (to 1042)
                1356    LOAD_CONST                      0: None
                1358    STORE_FAST                      16: _var_var_3
                1360    DELETE_FAST                     16: _var_var_3
                1362    RERAISE                         1
                1364    RERAISE                         0
                1366    COPY                            3
                1368    POP_EXCEPT                      
                1370    RERAISE                         1
                1372    PUSH_EXC_INFO                   
                1374    POP_TOP                         
                1376    POP_EXCEPT                      
                1378    JUMP_BACKWARD                   158 (to 1064)
                1380    COPY                            3
                1382    POP_EXCEPT                      
                1384    RERAISE                         1
                1386    PUSH_EXC_INFO                   
                1388    LOAD_GLOBAL                     7: NULL + Disconnect
                1398    LOAD_FAST_CHECK                 8: _var_var_25
                1400    CALL                            1
                1408    POP_TOP                         
                1410    JUMP_FORWARD                    7 (to 1426)
                1412    PUSH_EXC_INFO                   
                1414    POP_TOP                         
                1416    POP_EXCEPT                      
                1418    JUMP_FORWARD                    3 (to 1426)
                1420    COPY                            3
                1422    POP_EXCEPT                      
                1424    RERAISE                         1
                1426    LOAD_GLOBAL                     9: NULL + Logs
                1436    LOAD_ATTR                       10: PrintLog
                1456    LOAD_FAST                       1: config
                1458    LOAD_FAST                       0: account
                1460    LOAD_GLOBAL                     4: Lang
                1470    PUSH_NULL                       
                1472    LOAD_CONST                      1: '__pyarmor_assert_14523__'
                1474    LOAD_CONST                      9: 'work_account_completed'   # b'\x81\xf5\x17\x018\xc5\xbf\xd1\x18\xf5\x18\xcex\xd3\xfb\x8a\x02M\xb7\xa2\xbe\xceJ'
                1476    CALL                            1
                1484    BINARY_SUBSCR                   
                1488    KW_NAMES                        10: ('config', 'account', 'message')
                1490    CALL                            3
                1498    POP_TOP                         
                1500    LOAD_FAST                       0: account
                1502    LOAD_CONST                      11: 'done'
                1504    LOAD_CONST                      8: ('account', 'status')
                1506    BUILD_CONST_KEY_MAP             2
                1508    SWAP                            2
                1510    POP_TOP                         
                1512    SWAP                            2
                1514    POP_EXCEPT                      
                1516    NOP                             
                1518    NOP                             
                1520    NOP                             
                1522    JUMP_FORWARD                    23 (to 1570)
                1524    CALL                            1
                1532    POP_TOP                         
                1534    RETURN_VALUE                    
                1536    COPY                            3
                1538    POP_EXCEPT                      
                1540    RERAISE                         1
                1542    PUSH_EXC_INFO                   
                1544    PUSH_NULL                       
                1546    LOAD_CONST                      12: '__pyarmor_exit_14525__'
                1548    NOP                             
                1550    LOAD_CONST                      3: b'<COAddr>\x05\x00\x00\x1a\xec\x05\x00\x00\x00\x00\x00\x00\x00\x00\x00\x00\x00\x00\x00\x00'
                1552    CALL                            1
                1560    POP_TOP                         
                1562    RERAISE                         0
                1564    COPY                            3
                1566    POP_EXCEPT                      
                1568    RERAISE                         1
                1570    PUSH_NULL                       
                1572    LOAD_CONST                      12: '__pyarmor_exit_14525__'
                1574    LOAD_CONST                      3: b'<COAddr>\x05\x00\x00\x1a\xec\x05\x00\x00\x00\x00\x00\x00\x00\x00\x00\x00\x00\x00\x00\x00'
                1576    BUILD_TUPLE                     1
                1578    CALL_FUNCTION_EX                0
                1580    POP_TOP                         
                1582    RETURN_VALUE                    
            [Exception Table]
                30 to 128 -> 1276 [0] 
                128 to 150 -> 1166 [1] 
                150 to 236 -> 1542 [0] 
                256 to 448 -> 1276 [0] 
                450 to 574 -> 1182 [0] 
                576 to 620 -> 1182 [0] 
                622 to 666 -> 1182 [0] 
                668 to 1040 -> 1182 [0] 
                1040 to 1042 -> 1276 [0] 
                1042 to 1064 -> 1372 [0] 
                1064 to 1146 -> 1542 [0] 
                1166 to 1170 -> 1176 [2] lasti
                1170 to 1182 -> 1542 [0] 
                1182 to 1218 -> 1270 [1] lasti
                1218 to 1250 -> 1260 [1] lasti
                1250 to 1260 -> 1276 [0] 
                1260 to 1270 -> 1270 [1] lasti
                1270 to 1276 -> 1276 [0] 
                1276 to 1294 -> 1366 [1] lasti
                1294 to 1298 -> 1386 [0] 
                1298 to 1314 -> 1366 [1] lasti
                1314 to 1346 -> 1356 [1] lasti
                1346 to 1356 -> 1386 [0] 
                1356 to 1366 -> 1366 [1] lasti
                1366 to 1372 -> 1386 [0] 
                1372 to 1376 -> 1380 [1] lasti
                1376 to 1386 -> 1542 [0] 
                1386 to 1388 -> 1536 [1] lasti
                1388 to 1410 -> 1412 [2] 
                1410 to 1412 -> 1536 [1] lasti
                1412 to 1416 -> 1420 [3] lasti
                1416 to 1514 -> 1536 [1] lasti
                1514 to 1516 -> 1542 [0] 
                1536 to 1542 -> 1542 [0] 
                1542 to 1564 -> 1564 [1] lasti
        '__pyarmor_exit_14507__'
    [Disassembly]
        0       NOP                             
        2       NOP                             
        4       PUSH_NULL                       
        6       LOAD_CONST                      1: '__pyarmor_enter_14506__'
        8       LOAD_CONST                      2: b'<COAddr>\x05\x00\x00\x1aL\x01\x00\x00\x00\x00\x00\x00\x00\x00\x00\x00\x00\x00\x00\x00'
        10      BUILD_TUPLE                     1
        12      CALL_FUNCTION_EX                0
        14      POP_TOP                         
        16      RESUME                          0
        18      NOP                             
        20      NOP                             
        22      NOP                             
        24      NOP                             
        26      LOAD_CONST                      3: 0
        28      LOAD_CONST                      4: None
        30      IMPORT_NAME                     1: eel
        32      STORE_NAME                      1: eel
        34      LOAD_CONST                      3: 0
        36      LOAD_CONST                      4: None
        38      IMPORT_NAME                     2: time
        40      STORE_NAME                      2: time
        42      LOAD_CONST                      3: 0
        44      LOAD_CONST                      4: None
        46      IMPORT_NAME                     3: json
        48      STORE_NAME                      3: json
        50      LOAD_CONST                      3: 0
        52      LOAD_CONST                      4: None
        54      IMPORT_NAME                     4: concurrent.futures
        56      STORE_NAME                      5: concurrent
        58      LOAD_CONST                      3: 0
        60      LOAD_CONST                      5: ('Thread', 'Event')
        62      IMPORT_NAME                     6: threading
        64      IMPORT_FROM                     7: Thread
        66      STORE_NAME                      7: Thread
        68      IMPORT_FROM                     8: Event
        70      STORE_NAME                      8: Event
        72      POP_TOP                         
        74      LOAD_CONST                      3: 0
        76      LOAD_CONST                      6: ('functions',)
        78      IMPORT_NAME                     9: multithon
        80      IMPORT_FROM                     10: functions
        82      STORE_NAME                      10: functions
        84      POP_TOP                         
        86      LOAD_CONST                      3: 0
        88      LOAD_CONST                      7: ('password',)
        90      IMPORT_NAME                     9: multithon
        92      IMPORT_FROM                     11: password
        94      STORE_NAME                      12: pwd_mod
        96      POP_TOP                         
        98      LOAD_CONST                      3: 0
        100     LOAD_CONST                      8: ('StopProgram',)
        102     IMPORT_NAME                     13: multithon.errors
        104     IMPORT_FROM                     14: StopProgram
        106     STORE_NAME                      14: StopProgram
        108     POP_TOP                         
        110     LOAD_CONST                      3: 0
        112     LOAD_CONST                      9: ('GetLang',)
        114     IMPORT_NAME                     15: program.static_classes
        116     IMPORT_FROM                     16: GetLang
        118     STORE_NAME                      16: GetLang
        120     POP_TOP                         
        122     LOAD_CONST                      3: 0
        124     LOAD_CONST                      10: ('Logs',)
        126     IMPORT_NAME                     15: program.static_classes
        128     IMPORT_FROM                     17: Logs
        130     STORE_NAME                      17: Logs
        132     POP_TOP                         
        134     LOAD_CONST                      3: 0
        136     LOAD_CONST                      11: ('logging',)
        138     IMPORT_NAME                     15: program.static_classes
        140     IMPORT_FROM                     18: logging
        142     STORE_NAME                      18: logging
        144     POP_TOP                         
        146     LOAD_CONST                      3: 0
        148     LOAD_CONST                      12: ('memory_check_switcher',)
        150     IMPORT_NAME                     15: program.static_classes
        152     IMPORT_FROM                     19: memory_check_switcher
        154     STORE_NAME                      19: memory_check_switcher
        156     POP_TOP                         
        158     LOAD_CONST                      3: 0
        160     LOAD_CONST                      13: ('memory_set_pid',)
        162     IMPORT_NAME                     15: program.static_classes
        164     IMPORT_FROM                     20: memory_set_pid
        166     STORE_NAME                      20: memory_set_pid
        168     POP_TOP                         
        170     LOAD_CONST                      3: 0
        172     LOAD_CONST                      14: ('Disconnect',)
        174     IMPORT_NAME                     21: program.telegram
        176     IMPORT_FROM                     22: Disconnect
        178     STORE_NAME                      22: Disconnect
        180     POP_TOP                         
        182     LOAD_CONST                      3: 0
        184     LOAD_CONST                      15: ('Thread_wait',)
        186     IMPORT_NAME                     21: program.telegram
        188     IMPORT_FROM                     23: Thread_wait
        190     STORE_NAME                      23: Thread_wait
        192     POP_TOP                         
        194     LOAD_CONST                      3: 0
        196     LOAD_CONST                      16: ('account_works',)
        198     IMPORT_NAME                     21: program.telegram
        200     IMPORT_FROM                     24: account_works
        202     STORE_NAME                      24: account_works
        204     POP_TOP                         
        206     LOAD_CONST                      3: 0
        208     LOAD_CONST                      17: ('get_account_json',)
        210     IMPORT_NAME                     21: program.telegram
        212     IMPORT_FROM                     25: get_account_json
        214     STORE_NAME                      25: get_account_json
        216     POP_TOP                         
        218     LOAD_CONST                      3: 0
        220     LOAD_CONST                      18: ('GetConfig',)
        222     IMPORT_NAME                     26: program.general
        224     IMPORT_FROM                     27: GetConfig
        226     STORE_NAME                      27: GetConfig
        228     POP_TOP                         
        230     LOAD_CONST                      3: 0
        232     LOAD_CONST                      19: ('GetProxy',)
        234     IMPORT_NAME                     26: program.general
        236     IMPORT_FROM                     28: GetProxy
        238     STORE_NAME                      28: GetProxy
        240     POP_TOP                         
        242     LOAD_CONST                      3: 0
        244     LOAD_CONST                      20: ('StopDetect',)
        246     IMPORT_NAME                     26: program.general
        248     IMPORT_FROM                     29: StopDetect
        250     STORE_NAME                      29: StopDetect
        252     POP_TOP                         
        254     LOAD_CONST                      3: 0
        256     LOAD_CONST                      21: ('check_get_settings',)
        258     IMPORT_NAME                     26: program.general
        260     IMPORT_FROM                     30: check_get_settings
        262     STORE_NAME                      30: check_get_settings
        264     POP_TOP                         
        266     LOAD_CONST                      3: 0
        268     LOAD_CONST                      22: ('del_task_manager',)
        270     IMPORT_NAME                     26: program.general
        272     IMPORT_FROM                     31: del_task_manager
        274     STORE_NAME                      31: del_task_manager
        276     POP_TOP                         
        278     LOAD_CONST                      3: 0
        280     LOAD_CONST                      23: ('set_task_manager',)
        282     IMPORT_NAME                     26: program.general
        284     IMPORT_FROM                     32: set_task_manager
        286     STORE_NAME                      32: set_task_manager
        288     POP_TOP                         
        290     LOAD_CONST                      3: 0
        292     LOAD_CONST                      24: ('db_search_groups',)
        294     IMPORT_NAME                     33: program.database
        296     IMPORT_FROM                     34: db_search_groups
        298     STORE_NAME                      34: db_search_groups
        300     POP_TOP                         
        302     LOAD_CONST                      25: <CODE> Search_groups
        304     MAKE_FUNCTION                   0
        306     STORE_NAME                      35: Search_groups
        308     LOAD_CONST                      26: <CODE> generator_list
        310     MAKE_FUNCTION                   0
        312     STORE_NAME                      36: generator_list
        314     LOAD_CONST                      27: <CODE> START
        316     MAKE_FUNCTION                   0
        318     STORE_NAME                      37: START
        320     LOAD_CONST                      28: <CODE> channel_transfer_group
        322     MAKE_FUNCTION                   0
        324     STORE_NAME                      38: channel_transfer_group
        326     LOAD_CONST                      29: <CODE> channel_get_link
        328     MAKE_FUNCTION                   0
        330     STORE_NAME                      39: channel_get_link
        332     LOAD_CONST                      30: <CODE> worker
        334     MAKE_FUNCTION                   0
        336     STORE_NAME                      40: worker
        338     LOAD_CONST                      4: None
        340     NOP                             
        342     NOP                             
        344     NOP                             
        346     JUMP_FORWARD                    19 (to 386)
        354     POP_TOP                         
        356     RETURN_CONST                    4: None
        358     PUSH_EXC_INFO                   
        360     PUSH_NULL                       
        362     LOAD_CONST                      31: '__pyarmor_exit_14507__'
        364     NOP                             
        366     LOAD_CONST                      2: b'<COAddr>\x05\x00\x00\x1aL\x01\x00\x00\x00\x00\x00\x00\x00\x00\x00\x00\x00\x00\x00\x00'
        368     CALL                            1
        376     POP_TOP                         
        378     RERAISE                         0
        380     COPY                            3
        382     POP_EXCEPT                      
        384     RERAISE                         1
        386     PUSH_NULL                       
        388     LOAD_CONST                      31: '__pyarmor_exit_14507__'
        390     LOAD_CONST                      2: b'<COAddr>\x05\x00\x00\x1aL\x01\x00\x00\x00\x00\x00\x00\x00\x00\x00\x00\x00\x00\x00\x00'
        392     BUILD_TUPLE                     1
        394     CALL_FUNCTION_EX                0
        396     POP_TOP                         
        398     RETURN_VALUE                    
    [Exception Table]
        26 to 338 -> 358 [0] 
        358 to 380 -> 380 [1] lasti
