#decoded by lolz.live/mrpenny / t.me/zeus_jackpot
# ================================
# Примечания по Pyarmor:
# - Байт-код и объекты кода Pyarmor соответствуют стандартному Python, но присутствуют специальные вызовы функций среды выполнения (runtime) Pyarmor.
# - Вызовы строк — это не ошибки, а маркеры, которые обрабатываются Pyarmor во время выполнения.
#
# Руководство по декомпиляции (без среды выполнения):
# 1. Игнорируйте зашифрованные байты после `#`; используйте только строку до `#`.
# 2. Удалите "__pyarmor_enter_xxx__"(b"<COAddr>...") и "__pyarmor_leave_xxx__"(b"<COAddr>...") (пролог/эпилог).
# 3. "__pyarmor_assert_xxx__"(A) не является настоящим оператором assert.
#    - Если A — это имя или читаемая строка: замените на A.
#    - Если A — это (X, "Y"): замените на X.Y.
#    - Если A — это (X, "Y", Z): замените на X.Y = Z.
#    - В противном случае: выберите наиболее подходящую/логичную замену.
# 4. "__pyarmor_bcc_xxx__"(...) указывает на машинный (нативный) код; тело функции недоступно. Добавьте комментарий.
# ================================

[Code]
    File Name: <frozen program.modules.Search_global>
    Object Name: <module>
    Qualified Name: <module>
    Arg Count: 0
    Pos Only Arg Count: 0
    KW Only Arg Count: 0
    Stack Size: 5
    Flags: 0x20000000 (CO_PYARMOR_OBFUSCATED)
    [Names]
        '__assert_armored__'
        'eel'
        'time'
        'json'
        'random'
        'datetime'
        'concurrent.futures'
        'concurrent'
        'threading'
        'Thread'
        'Event'
        'multithon'
        'functions'
        'types'
        'multithon.errors'
        'StopProgram'
        'program.static_classes'
        'GetLang'
        'Logs'
        'logging'
        'memory_check_switcher'
        'memory_set_pid'
        'program.telegram'
        'DelayOnline'
        'Disconnect'
        'Thread_wait'
        'account_works'
        'entity'
        'program.general'
        'GetConfig'
        'GetProxy'
        'StopDetect'
        'check_get_settings'
        'del_task_manager'
        'getFile'
        'set_task_manager'
        'program.database'
        'db_parsing'
        'db_search_global'
        'Search_global'
        'START'
        'worker'
    [Locals+Names]
    [Constants]
        '__pyarmor_assert_14493__'
        '__pyarmor_enter_14494__'
        b'<COAddr>\x05\x00\x00\x1af\x01\x00\x00\x00\x00\x00\x00\x00\x00\x00\x00\x00\x00\x00\x00'
        0
        None
        (
            'Thread'
            'Event'
        )
        (
            'functions'
            'types'
        )
        (
            'StopProgram'
        )
        (
            'GetLang'
        )
        (
            'Logs'
        )
        (
            'logging'
        )
        (
            'memory_check_switcher'
        )
        (
            'memory_set_pid'
        )
        (
            'DelayOnline'
        )
        (
            'Disconnect'
        )
        (
            'Thread_wait'
        )
        (
            'account_works'
        )
        (
            'entity'
        )
        (
            'GetConfig'
        )
        (
            'GetProxy'
        )
        (
            'StopDetect'
        )
        (
            'check_get_settings'
        )
        (
            'del_task_manager'
        )
        (
            'getFile'
        )
        (
            'set_task_manager'
        )
        (
            'db_parsing'
        )
        (
            'db_search_global'
        )
        [Code]
            File Name: <frozen program.modules.Search_global>
            Object Name: Search_global
            Qualified Name: Search_global
            Arg Count: 1
            Pos Only Arg Count: 0
            KW Only Arg Count: 0
            Stack Size: 8
            Flags: 0x20000003 (CO_OPTIMIZED | CO_NEWLOCALS | CO_PYARMOR_OBFUSCATED)
            [Names]
                'get'
                'getFile'
                'GetConfig'
                'config'
                'GetLang'
                'Lang'
                'GetProxy'
                'eel'
                'sendSuccessBox'
                'memory_check_switcher'
                'Event'
                'memory_set_pid'
                'Thread'
                'START'
                'start'
                'Logs'
                'WaitStopAnsfer'
                'UpdateLogInWindow'
                'BaseException'
                'logging'
            [Locals+Names]
                'data'
                '__assert_armored__'
                '_var_var_0'
                '_var_var_1'
                '_var_var_2'
                '_var_var_3'
            [Constants]
                None
                '__pyarmor_assert_14496__'
                '__pyarmor_enter_14497__'
                b'<COAddr>\x07\x00\x00\x1a\xae\x02\x00\x00\x00\x00\x00\x00\x00\x00\x00\x00\x00\x00\x00\x00'
                'action'
                'getFile'
                '__pyarmor_exit_14498__'
                'program_running'   # b'\x81\xf2\n\x1c4\xe8\xbf\xdf$\xe8\x18\xceb\xe5\xf6\x82'
                False
                (
                    'target'
                    'args'
                )
                True
                (
                    'target'
                    'args'
                    'daemon'
                )
            [Disassembly]
                0       NOP                             
                2       NOP                             
                4       PUSH_NULL                       
                6       LOAD_CONST                      2: '__pyarmor_enter_14497__'
                8       LOAD_CONST                      3: b'<COAddr>\x07\x00\x00\x1a\xae\x02\x00\x00\x00\x00\x00\x00\x00\x00\x00\x00\x00\x00\x00\x00'
                10      BUILD_TUPLE                     1
                12      CALL_FUNCTION_EX                0
                14      POP_TOP                         
                16      RESUME                          0
                18      NOP                             
                20      NOP                             
                22      NOP                             
                24      NOP                             
                26      NOP                             
                28      NOP                             
                30      LOAD_FAST                       0: data
                32      LOAD_ATTR                       1: get
                52      LOAD_CONST                      4: 'action'
                54      CALL                            1
                62      POP_JUMP_IF_NONE                28 (to 120)
                64      LOAD_FAST                       0: data
                66      LOAD_CONST                      4: 'action'
                68      BINARY_SUBSCR                   
                72      LOAD_CONST                      5: 'getFile'
                74      COMPARE_OP                      40 (==)
                78      POP_JUMP_IF_FALSE               20 (to 120)
                80      LOAD_GLOBAL                     3: NULL + getFile
                90      LOAD_FAST                       0: data
                92      CALL                            1
                100     NOP                             
                102     NOP                             
                104     JUMP_FORWARD                    316 (to 740)
                108     CALL                            1
                116     POP_TOP                         
                118     RETURN_VALUE                    
                120     LOAD_GLOBAL                     5: NULL + GetConfig
                130     CALL                            0
                138     STORE_GLOBAL                    3: config
                140     LOAD_GLOBAL                     9: NULL + GetLang
                150     LOAD_GLOBAL                     6: config
                160     CALL                            1
                168     STORE_GLOBAL                    5: Lang
                170     LOAD_GLOBAL                     13: NULL + GetProxy
                180     CALL                            0
                188     STORE_FAST                      2: _var_var_0
                190     LOAD_GLOBAL                     15: NULL + eel
                200     LOAD_ATTR                       16: sendSuccessBox
                220     LOAD_GLOBAL                     10: Lang
                230     PUSH_NULL                       
                232     LOAD_CONST                      1: '__pyarmor_assert_14496__'
                234     LOAD_CONST                      7: 'program_running'   # b'\x81\xf2\n\x1c4\xe8\xbf\xdf$\xe8\x18\xceb\xe5\xf6\x82'
                236     CALL                            1
                244     BINARY_SUBSCR                   
                248     CALL                            1
                256     POP_TOP                         
                258     LOAD_GLOBAL                     19: NULL + memory_check_switcher
                268     CALL                            0
                276     POP_JUMP_IF_TRUE                11 (to 300)
                278     NOP                             
                280     LOAD_CONST                      8: False
                282     NOP                             
                284     NOP                             
                286     NOP                             
                288     JUMP_FORWARD                    225 (to 740)
                296     POP_TOP                         
                298     RETURN_CONST                    8: False
                300     LOAD_GLOBAL                     21: NULL + Event
                310     CALL                            0
                318     STORE_FAST                      3: _var_var_1
                320     LOAD_GLOBAL                     23: NULL + memory_set_pid
                330     CALL                            0
                338     STORE_FAST                      4: _var_var_2
                340     LOAD_GLOBAL                     25: NULL + Thread
                350     LOAD_GLOBAL                     26: START
                360     LOAD_FAST                       0: data
                362     LOAD_GLOBAL                     6: config
                372     LOAD_FAST                       4: _var_var_2
                374     LOAD_FAST                       2: _var_var_0
                376     LOAD_FAST                       3: _var_var_1
                378     BUILD_TUPLE                     5
                380     KW_NAMES                        9: ('target', 'args')
                382     CALL                            2
                390     LOAD_ATTR                       29: start
                410     CALL                            0
                418     POP_TOP                         
                420     LOAD_GLOBAL                     25: NULL + Thread
                430     LOAD_GLOBAL                     30: Logs
                440     LOAD_ATTR                       32: WaitStopAnsfer
                460     LOAD_GLOBAL                     6: config
                470     LOAD_FAST                       4: _var_var_2
                472     LOAD_FAST                       3: _var_var_1
                474     BUILD_TUPLE                     3
                476     LOAD_CONST                      10: True
                478     KW_NAMES                        11: ('target', 'args', 'daemon')
                480     CALL                            3
                488     LOAD_ATTR                       29: start
                508     CALL                            0
                516     POP_TOP                         
                518     LOAD_GLOBAL                     25: NULL + Thread
                528     LOAD_GLOBAL                     30: Logs
                538     LOAD_ATTR                       34: UpdateLogInWindow
                558     LOAD_GLOBAL                     6: config
                568     LOAD_FAST                       4: _var_var_2
                570     LOAD_FAST                       3: _var_var_1
                572     BUILD_TUPLE                     3
                574     LOAD_CONST                      10: True
                576     KW_NAMES                        11: ('target', 'args', 'daemon')
                578     CALL                            3
                586     LOAD_ATTR                       29: start
                606     CALL                            0
                614     POP_TOP                         
                616     LOAD_CONST                      0: None
                618     NOP                             
                620     NOP                             
                622     NOP                             
                624     JUMP_FORWARD                    57 (to 740)
                632     POP_TOP                         
                634     RETURN_CONST                    0: None
                636     PUSH_EXC_INFO                   
                638     LOAD_GLOBAL                     36: BaseException
                648     CHECK_EXC_MATCH                 
                650     POP_JUMP_IF_FALSE               26 (to 704)
                652     STORE_FAST                      5: _var_var_3
                654     PUSH_NULL                       
                656     LOAD_GLOBAL                     39: NULL + logging
                666     LOAD_FAST                       5: _var_var_3
                668     CALL                            1
                676     CALL                            0
                684     POP_TOP                         
                686     POP_EXCEPT                      
                688     LOAD_CONST                      0: None
                690     STORE_FAST                      5: _var_var_3
                692     DELETE_FAST                     5: _var_var_3
                694     JUMP_BACKWARD                   40 (to 616)
                696     LOAD_CONST                      0: None
                698     STORE_FAST                      5: _var_var_3
                700     DELETE_FAST                     5: _var_var_3
                702     RERAISE                         1
                704     RERAISE                         0
                706     COPY                            3
                708     POP_EXCEPT                      
                710     RERAISE                         1
                712     PUSH_EXC_INFO                   
                714     PUSH_NULL                       
                716     LOAD_CONST                      6: '__pyarmor_exit_14498__'
                718     NOP                             
                720     LOAD_CONST                      3: b'<COAddr>\x07\x00\x00\x1a\xae\x02\x00\x00\x00\x00\x00\x00\x00\x00\x00\x00\x00\x00\x00\x00'
                722     CALL                            1
                730     POP_TOP                         
                732     RERAISE                         0
                734     COPY                            3
                736     POP_EXCEPT                      
                738     RERAISE                         1
                740     PUSH_NULL                       
                742     LOAD_CONST                      6: '__pyarmor_exit_14498__'
                744     LOAD_CONST                      3: b'<COAddr>\x07\x00\x00\x1a\xae\x02\x00\x00\x00\x00\x00\x00\x00\x00\x00\x00\x00\x00\x00\x00'
                746     BUILD_TUPLE                     1
                748     CALL_FUNCTION_EX                0
                750     POP_TOP                         
                752     RETURN_VALUE                    
            [Exception Table]
                30 to 100 -> 636 [0] 
                120 to 278 -> 636 [0] 
                300 to 616 -> 636 [0] 
                636 to 654 -> 706 [1] lasti
                654 to 686 -> 696 [1] lasti
                686 to 696 -> 712 [0] 
                696 to 706 -> 706 [1] lasti
                706 to 712 -> 712 [0] 
                712 to 734 -> 734 [1] lasti
        [Code]
            File Name: <frozen program.modules.Search_global>
            Object Name: START
            Qualified Name: START
            Arg Count: 5
            Pos Only Arg Count: 0
            KW Only Arg Count: 0
            Stack Size: 14
            Flags: 0x20000003 (CO_OPTIMIZED | CO_NEWLOCALS | CO_PYARMOR_OBFUSCATED)
            [Names]
                'is_set'
                'StopProgram'
                'check_get_settings'
                'get'
                'isinstance'
                'list'
                'eel'
                'sendErrorBox'
                'Lang'
                'int'
                'datetime'
                'now'
                'strftime'
                'db_search_global'
                'import_list'
                'WriteResult'
                'Logs'
                'LangCheck'
                'db_parsing'
                'create'
                'set_task_manager'
                'concurrent'
                'futures'
                'ThreadPoolExecutor'
                'len'
                'StreamStat'
                'json'
                'dumps'
                'append'
                'submit'
                'worker'
                'as_completed'
                'BaseException'
                'logging'
                'del_task_manager'
                'StopDetect'
            [Locals+Names]
                'data'
                'config'
                'pid'
                'proxy'
                'stop_thread'
                '__assert_armored__'
                '_var_var_4'
                '_var_var_5'
                '_var_var_6'
                '_var_var_7'
                '_var_var_8'
                '_var_var_9'
                '_var_var_10'
                '_var_var_11'
                '_var_var_12'
                '_var_var_13'
                '_var_var_14'
                '_var_var_15'
                '_var_var_3'
            [Constants]
                None
                '__pyarmor_assert_14499__'
                '__pyarmor_enter_14500__'
                b'<COAddr>\x07\x00\x00\x1aL\x07\x00\x00\x00\x00\x00\x00\x00\x00\x00\x00\x00\x00\x00\x00'
                'Settings'
                'Accounts'
                'select_accounts_works'   # b'\x81\xf1\x1d\x1f6\xf9\xaa\xed\x1a\xf9\x0e\xcfy\xe2\xec\x960J\xb4\xb5\xa1\xd8'
                'thread_rules'   # b'\x81\xf6\x10\x016\xfb\xba\xed\t\xef\x01\xc5\x7f'
                True
                'thread_count'   # b'\x81\xf6\x10\x016\xfb\xba\xed\x18\xf5\x18\xcex'
                '%Y-%m-%d_%H-%M-%S'   # b'\x81\xa7!^v\xf7\xf3\x97\x1f\xc5H\xe8!\xa9\xd5\xc8Jn'
                'use_data_base'   # b'\x81\xf7\x0b\x16\x0c\xfe\xbf\xc6\x1a\xc5\x0f\xc1\x7f\xe9'
                False
                'additives/search_global/'   # b'\x81\xe3\x1c\x17:\xee\xb7\xc4\x1e\xe9B\xd3i\xed\xea\x86\x07b\xbc\xab\xa5\xc9O\xc0J'
                '_base.db'
                'words'
                (
                    'words'
                )
                'file_db'
                'can_not_create_database'   # b'\x81\xe1\x19\x1d\x0c\xf4\xb1\xc6$\xf9\x1f\xc5m\xf8\xfd\xba\x0b\\\xaf\xa6\xa8\xca]\xc9'
                'Contacts'
                'search_global'   # b'\x81\xf1\x1d\x12!\xf9\xb6\xed\x1c\xf6\x02\xc2m\xe0'
                '_Parsing.db'   # b'\x81\xdd(\x12!\xe9\xb7\xdc\x1c\xb4\t\xc2'
                'Общая база данных'   # b'\x81R\xe6\xa3\xe2KWb\xcbK\xe2\x80\xdc=HU\xbf\x8a\x0bw\xea{\x9a|\xd5\xdf~\xec\xdd\x00\xf5T\xdf'
                'stuff'
                (
                    'accounts'
                    'name'
                )
                (
                    'max_workers'
                )
                0
                'st_task'
                'st_stream'   # b'\x81\xf1\x0c, \xee\xac\xd7\x1a\xf7'
                'st_wait'
                'st_done'
                1
                '__pyarmor_exit_14501__'
                'Done'
            [Disassembly]
                0       NOP                             
                2       NOP                             
                4       PUSH_NULL                       
                6       LOAD_CONST                      2: '__pyarmor_enter_14500__'
                8       LOAD_CONST                      3: b'<COAddr>\x07\x00\x00\x1aL\x07\x00\x00\x00\x00\x00\x00\x00\x00\x00\x00\x00\x00\x00\x00'
                10      BUILD_TUPLE                     1
                12      CALL_FUNCTION_EX                0
                14      POP_TOP                         
                16      RESUME                          0
                18      NOP                             
                20      NOP                             
                22      NOP                             
                24      NOP                             
                26      NOP                             
                28      NOP                             
                30      LOAD_FAST                       4: stop_thread
                32      LOAD_ATTR                       1: is_set
                52      CALL                            0
                60      POP_JUMP_IF_FALSE               10 (to 82)
                62      LOAD_GLOBAL                     3: NULL + StopProgram
                72      CALL                            0
                80      RAISE_VARARGS                   1
                82      LOAD_GLOBAL                     5: NULL + check_get_settings
                92      LOAD_FAST                       0: data
                94      LOAD_ATTR                       7: get
                114     LOAD_CONST                      4: 'Settings'
                116     CALL                            1
                124     CALL                            1
                132     POP_TOP                         
                134     LOAD_FAST                       0: data
                136     LOAD_CONST                      5: 'Accounts'
                138     BINARY_SUBSCR                   
                142     STORE_FAST                      6: _var_var_4
                144     LOAD_GLOBAL                     9: NULL + isinstance
                154     LOAD_FAST                       6: _var_var_4
                156     LOAD_GLOBAL                     10: list
                166     CALL                            2
                174     POP_JUMP_IF_TRUE                3 (to 182)
                176     LOAD_FAST                       6: _var_var_4
                178     BUILD_LIST                      1
                180     STORE_FAST                      6: _var_var_4
                182     LOAD_FAST                       6: _var_var_4
                184     POP_JUMP_IF_TRUE                44 (to 274)
                186     LOAD_GLOBAL                     13: NULL + eel
                196     LOAD_ATTR                       14: sendErrorBox
                216     LOAD_GLOBAL                     16: Lang
                226     PUSH_NULL                       
                228     LOAD_CONST                      1: '__pyarmor_assert_14499__'
                230     LOAD_CONST                      6: 'select_accounts_works'   # b'\x81\xf1\x1d\x1f6\xf9\xaa\xed\x1a\xf9\x0e\xcfy\xe2\xec\x960J\xb4\xb5\xa1\xd8'
                232     CALL                            1
                240     BINARY_SUBSCR                   
                244     CALL                            1
                252     POP_TOP                         
                254     LOAD_GLOBAL                     3: NULL + StopProgram
                264     CALL                            0
                272     RAISE_VARARGS                   1
                274     LOAD_FAST                       0: data
                276     LOAD_CONST                      4: 'Settings'
                278     BINARY_SUBSCR                   
                282     LOAD_ATTR                       7: get
                302     PUSH_NULL                       
                304     LOAD_CONST                      1: '__pyarmor_assert_14499__'
                306     LOAD_CONST                      7: 'thread_rules'   # b'\x81\xf6\x10\x016\xfb\xba\xed\t\xef\x01\xc5\x7f'
                308     CALL                            1
                316     CALL                            1
                324     LOAD_CONST                      8: True
                326     COMPARE_OP                      40 (==)
                330     POP_JUMP_IF_FALSE               36 (to 404)
                332     LOAD_GLOBAL                     19: NULL + int
                342     LOAD_FAST                       0: data
                344     LOAD_CONST                      4: 'Settings'
                346     BINARY_SUBSCR                   
                350     LOAD_ATTR                       7: get
                370     PUSH_NULL                       
                372     LOAD_CONST                      1: '__pyarmor_assert_14499__'
                374     LOAD_CONST                      9: 'thread_count'   # b'\x81\xf6\x10\x016\xfb\xba\xed\x18\xf5\x18\xcex'
                376     CALL                            1
                384     CALL                            1
                392     CALL                            1
                400     STORE_FAST                      7: _var_var_5
                402     JUMP_FORWARD                    11 (to 426)
                404     LOAD_FAST                       1: config
                406     PUSH_NULL                       
                408     LOAD_CONST                      1: '__pyarmor_assert_14499__'
                410     LOAD_CONST                      9: 'thread_count'   # b'\x81\xf6\x10\x016\xfb\xba\xed\x18\xf5\x18\xcex'
                412     CALL                            1
                420     BINARY_SUBSCR                   
                424     STORE_FAST                      7: _var_var_5
                426     LOAD_GLOBAL                     20: datetime
                436     LOAD_ATTR                       20: datetime
                456     LOAD_ATTR                       23: now
                476     CALL                            0
                484     LOAD_ATTR                       25: strftime
                504     PUSH_NULL                       
                506     LOAD_CONST                      1: '__pyarmor_assert_14499__'
                508     LOAD_CONST                      10: '%Y-%m-%d_%H-%M-%S'   # b'\x81\xa7!^v\xf7\xf3\x97\x1f\xc5H\xe8!\xa9\xd5\xc8Jn'
                510     CALL                            1
                518     CALL                            1
                526     STORE_FAST                      8: _var_var_6
                528     LOAD_FAST                       0: data
                530     LOAD_CONST                      4: 'Settings'
                532     BINARY_SUBSCR                   
                536     PUSH_NULL                       
                538     LOAD_CONST                      1: '__pyarmor_assert_14499__'
                540     LOAD_CONST                      11: 'use_data_base'   # b'\x81\xf7\x0b\x16\x0c\xfe\xbf\xc6\x1a\xc5\x0f\xc1\x7f\xe9'
                542     CALL                            1
                550     BINARY_SUBSCR                   
                554     LOAD_CONST                      12: False
                556     COMPARE_OP                      40 (==)
                560     POP_JUMP_IF_FALSE               149 (to 860)
                562     LOAD_GLOBAL                     27: NULL + db_search_global
                572     PUSH_NULL                       
                574     LOAD_CONST                      1: '__pyarmor_assert_14499__'
                576     LOAD_CONST                      13: 'additives/search_global/'   # b'\x81\xe3\x1c\x17:\xee\xb7\xc4\x1e\xe9B\xd3i\xed\xea\x86\x07b\xbc\xab\xa5\xc9O\xc0J'
                578     CALL                            1
                586     LOAD_FAST                       8: _var_var_6
                588     FORMAT_VALUE                    0 (FVC_NONE)
                590     LOAD_CONST                      14: '_base.db'
                592     BUILD_STRING                    3
                594     CALL                            1
                602     LOAD_ATTR                       29: import_list
                622     LOAD_FAST                       0: data
                624     LOAD_CONST                      4: 'Settings'
                626     BINARY_SUBSCR                   
                630     LOAD_ATTR                       7: get
                650     LOAD_CONST                      15: 'words'
                652     BUILD_LIST                      0
                654     CALL                            2
                662     KW_NAMES                        16: ('words',)
                664     CALL                            1
                672     LOAD_FAST                       0: data
                674     LOAD_CONST                      4: 'Settings'
                676     BINARY_SUBSCR                   
                680     LOAD_CONST                      17: 'file_db'
                682     STORE_SUBSCR                    
                686     LOAD_FAST                       0: data
                688     LOAD_CONST                      4: 'Settings'
                690     BINARY_SUBSCR                   
                694     LOAD_CONST                      17: 'file_db'
                696     BINARY_SUBSCR                   
                700     LOAD_CONST                      12: False
                702     COMPARE_OP                      40 (==)
                706     POP_JUMP_IF_FALSE               44 (to 796)
                708     LOAD_GLOBAL                     13: NULL + eel
                718     LOAD_ATTR                       14: sendErrorBox
                738     LOAD_GLOBAL                     16: Lang
                748     PUSH_NULL                       
                750     LOAD_CONST                      1: '__pyarmor_assert_14499__'
                752     LOAD_CONST                      18: 'can_not_create_database'   # b'\x81\xe1\x19\x1d\x0c\xf4\xb1\xc6$\xf9\x1f\xc5m\xf8\xfd\xba\x0b\\\xaf\xa6\xa8\xca]\xc9'
                754     CALL                            1
                762     BINARY_SUBSCR                   
                766     CALL                            1
                774     POP_TOP                         
                776     LOAD_GLOBAL                     3: NULL + StopProgram
                786     CALL                            0
                794     RAISE_VARARGS                   1
                796     LOAD_GLOBAL                     13: NULL + eel
                806     LOAD_ATTR                       30: WriteResult
                826     LOAD_CONST                      19: 'Contacts'
                828     PUSH_NULL                       
                830     LOAD_CONST                      1: '__pyarmor_assert_14499__'
                832     LOAD_CONST                      20: 'search_global'   # b'\x81\xf1\x1d\x12!\xf9\xb6\xed\x1c\xf6\x02\xc2m\xe0'
                834     CALL                            1
                842     LOAD_FAST                       8: _var_var_6
                844     FORMAT_VALUE                    0 (FVC_NONE)
                846     LOAD_CONST                      14: '_base.db'
                848     BUILD_STRING                    2
                850     CALL                            3
                858     POP_TOP                         
                860     LOAD_GLOBAL                     33: NULL + Logs
                870     LOAD_ATTR                       34: LangCheck
                890     CALL                            0
                898     POP_TOP                         
                900     LOAD_GLOBAL                     37: NULL + db_parsing
                910     PUSH_NULL                       
                912     LOAD_CONST                      1: '__pyarmor_assert_14499__'
                914     LOAD_CONST                      13: 'additives/search_global/'   # b'\x81\xe3\x1c\x17:\xee\xb7\xc4\x1e\xe9B\xd3i\xed\xea\x86\x07b\xbc\xab\xa5\xc9O\xc0J'
                916     CALL                            1
                924     LOAD_FAST                       8: _var_var_6
                926     FORMAT_VALUE                    0 (FVC_NONE)
                928     PUSH_NULL                       
                930     LOAD_CONST                      1: '__pyarmor_assert_14499__'
                932     LOAD_CONST                      21: '_Parsing.db'   # b'\x81\xdd(\x12!\xe9\xb7\xdc\x1c\xb4\t\xc2'
                934     CALL                            1
                942     BUILD_STRING                    3
                944     CALL                            1
                952     LOAD_ATTR                       39: create
                972     CALL                            0
                980     STORE_FAST                      9: _var_var_7
                982     LOAD_GLOBAL                     13: NULL + eel
                992     LOAD_ATTR                       30: WriteResult
                1012    PUSH_NULL                       
                1014    LOAD_CONST                      1: '__pyarmor_assert_14499__'
                1016    LOAD_CONST                      22: 'Общая база данных'   # b'\x81R\xe6\xa3\xe2KWb\xcbK\xe2\x80\xdc=HU\xbf\x8a\x0bw\xea{\x9a|\xd5\xdf~\xec\xdd\x00\xf5T\xdf'
                1018    CALL                            1
                1026    PUSH_NULL                       
                1028    LOAD_CONST                      1: '__pyarmor_assert_14499__'
                1030    LOAD_CONST                      20: 'search_global'   # b'\x81\xf1\x1d\x12!\xf9\xb6\xed\x1c\xf6\x02\xc2m\xe0'
                1032    CALL                            1
                1040    LOAD_FAST                       8: _var_var_6
                1042    FORMAT_VALUE                    0 (FVC_NONE)
                1044    PUSH_NULL                       
                1046    LOAD_CONST                      1: '__pyarmor_assert_14499__'
                1048    LOAD_CONST                      21: '_Parsing.db'   # b'\x81\xdd(\x12!\xe9\xb7\xdc\x1c\xb4\t\xc2'
                1050    CALL                            1
                1058    BUILD_STRING                    2
                1060    CALL                            3
                1068    POP_TOP                         
                1070    LOAD_GLOBAL                     41: NULL + set_task_manager
                1080    LOAD_FAST                       2: pid
                1082    LOAD_FAST                       6: _var_var_4
                1084    LOAD_FAST                       0: data
                1086    LOAD_CONST                      23: 'stuff'
                1088    BINARY_SUBSCR                   
                1092    KW_NAMES                        24: ('accounts', 'name')
                1094    CALL                            3
                1102    POP_TOP                         
                1104    LOAD_GLOBAL                     42: concurrent
                1114    LOAD_ATTR                       44: futures
                1134    LOAD_ATTR                       47: ThreadPoolExecutor
                1154    LOAD_FAST                       7: _var_var_5
                1156    KW_NAMES                        25: ('max_workers',)
                1158    CALL                            1
                1166    BEFORE_WITH                     
                1168    STORE_FAST                      10: _var_var_8
                1170    BUILD_LIST                      0
                1172    STORE_FAST                      11: _var_var_9
                1174    LOAD_GLOBAL                     49: NULL + len
                1184    LOAD_FAST                       6: _var_var_4
                1186    CALL                            1
                1194    STORE_FAST                      12: _var_var_10
                1196    LOAD_FAST                       7: _var_var_5
                1198    STORE_FAST                      13: _var_var_11
                1200    LOAD_FAST                       12: _var_var_10
                1202    STORE_FAST                      14: _var_var_12
                1204    LOAD_CONST                      26: 0
                1206    STORE_FAST                      15: _var_var_13
                1208    LOAD_GLOBAL                     13: NULL + eel
                1218    LOAD_ATTR                       50: StreamStat
                1238    LOAD_GLOBAL                     53: NULL + json
                1248    LOAD_ATTR                       54: dumps
                1268    LOAD_CONST                      27: 'st_task'
                1270    LOAD_FAST                       12: _var_var_10
                1272    PUSH_NULL                       
                1274    LOAD_CONST                      1: '__pyarmor_assert_14499__'
                1276    LOAD_CONST                      28: 'st_stream'   # b'\x81\xf1\x0c, \xee\xac\xd7\x1a\xf7'
                1278    CALL                            1
                1286    LOAD_FAST                       13: _var_var_11
                1288    LOAD_CONST                      29: 'st_wait'
                1290    LOAD_FAST                       14: _var_var_12
                1292    LOAD_CONST                      30: 'st_done'
                1294    LOAD_FAST                       15: _var_var_13
                1296    BUILD_MAP                       4
                1298    CALL                            1
                1306    CALL                            1
                1314    POP_TOP                         
                1316    LOAD_FAST                       6: _var_var_4
                1318    GET_ITER                        
                1320    FOR_ITER                        44 (to 1410)
                1324    STORE_FAST                      16: _var_var_14
                1326    LOAD_FAST                       11: _var_var_9
                1328    LOAD_ATTR                       57: append
                1348    LOAD_FAST                       10: _var_var_8
                1350    LOAD_ATTR                       59: submit
                1370    LOAD_GLOBAL                     60: worker
                1380    LOAD_FAST                       16: _var_var_14
                1382    LOAD_FAST                       1: config
                1384    LOAD_FAST                       3: proxy
                1386    LOAD_FAST                       0: data
                1388    LOAD_FAST                       9: _var_var_7
                1390    LOAD_FAST                       4: stop_thread
                1392    CALL                            7
                1400    CALL                            1
                1408    POP_TOP                         
                1410    JUMP_BACKWARD                   46 (to 1320)
                1412    END_FOR                         
                1414    LOAD_GLOBAL                     42: concurrent
                1424    LOAD_ATTR                       44: futures
                1444    LOAD_ATTR                       63: as_completed
                1464    LOAD_FAST                       11: _var_var_9
                1466    CALL                            1
                1474    GET_ITER                        
                1476    FOR_ITER                        66 (to 1610)
                1480    STORE_FAST                      17: _var_var_15
                1482    LOAD_FAST                       15: _var_var_13
                1484    LOAD_CONST                      31: 1
                1486    BINARY_OP                       13 (+=)
                1490    STORE_FAST                      15: _var_var_13
                1492    LOAD_FAST                       14: _var_var_12
                1494    LOAD_CONST                      31: 1
                1496    BINARY_OP                       23 (-=)
                1500    STORE_FAST                      14: _var_var_12
                1502    LOAD_GLOBAL                     13: NULL + eel
                1512    LOAD_ATTR                       50: StreamStat
                1532    LOAD_GLOBAL                     53: NULL + json
                1542    LOAD_ATTR                       54: dumps
                1562    LOAD_CONST                      27: 'st_task'
                1564    LOAD_FAST                       12: _var_var_10
                1566    PUSH_NULL                       
                1568    LOAD_CONST                      1: '__pyarmor_assert_14499__'
                1570    LOAD_CONST                      28: 'st_stream'   # b'\x81\xf1\x0c, \xee\xac\xd7\x1a\xf7'
                1572    CALL                            1
                1580    LOAD_FAST                       13: _var_var_11
                1582    LOAD_CONST                      29: 'st_wait'
                1584    LOAD_FAST                       14: _var_var_12
                1586    LOAD_CONST                      30: 'st_done'
                1588    LOAD_FAST                       15: _var_var_13
                1590    BUILD_MAP                       4
                1592    CALL                            1
                1600    CALL                            1
                1608    POP_TOP                         
                1610    JUMP_BACKWARD                   68 (to 1476)
                1612    END_FOR                         
                1614    NOP                             
                1616    LOAD_CONST                      0: None
                1618    LOAD_CONST                      0: None
                1620    LOAD_CONST                      0: None
                1622    CALL                            2
                1630    POP_TOP                         
                1632    LOAD_GLOBAL                     69: NULL + del_task_manager
                1642    LOAD_FAST                       2: pid
                1644    CALL                            1
                1652    POP_TOP                         
                1654    LOAD_GLOBAL                     71: NULL + StopDetect
                1664    LOAD_FAST                       4: stop_thread
                1666    CALL                            1
                1674    POP_TOP                         
                1676    NOP                             
                1678    LOAD_CONST                      33: 'Done'
                1680    NOP                             
                1682    NOP                             
                1684    NOP                             
                1686    JUMP_FORWARD                    117 (to 1922)
                1694    POP_TOP                         
                1696    RETURN_CONST                    33: 'Done'
                1698    PUSH_EXC_INFO                   
                1700    WITH_EXCEPT_START               
                1702    POP_JUMP_IF_TRUE                1 (to 1706)
                1704    RERAISE                         2
                1706    POP_TOP                         
                1708    POP_EXCEPT                      
                1710    POP_TOP                         
                1712    POP_TOP                         
                1714    JUMP_BACKWARD                   42 (to 1632)
                1716    COPY                            3
                1718    POP_EXCEPT                      
                1720    RERAISE                         1
                1722    PUSH_EXC_INFO                   
                1724    LOAD_GLOBAL                     2: StopProgram
                1734    CHECK_EXC_MATCH                 
                1736    POP_JUMP_IF_FALSE               3 (to 1744)
                1738    POP_TOP                         
                1740    POP_EXCEPT                      
                1742    JUMP_BACKWARD                   56 (to 1632)
                1744    LOAD_GLOBAL                     64: BaseException
                1754    CHECK_EXC_MATCH                 
                1756    POP_JUMP_IF_FALSE               26 (to 1810)
                1758    STORE_FAST                      18: _var_var_3
                1760    PUSH_NULL                       
                1762    LOAD_GLOBAL                     67: NULL + logging
                1772    LOAD_FAST                       18: _var_var_3
                1774    CALL                            1
                1782    CALL                            0
                1790    POP_TOP                         
                1792    POP_EXCEPT                      
                1794    LOAD_CONST                      0: None
                1796    STORE_FAST                      18: _var_var_3
                1798    DELETE_FAST                     18: _var_var_3
                1800    JUMP_BACKWARD                   85 (to 1632)
                1802    LOAD_CONST                      0: None
                1804    STORE_FAST                      18: _var_var_3
                1806    DELETE_FAST                     18: _var_var_3
                1808    RERAISE                         1
                1810    RERAISE                         0
                1812    COPY                            3
                1814    POP_EXCEPT                      
                1816    RERAISE                         1
                1818    PUSH_EXC_INFO                   
                1820    LOAD_GLOBAL                     69: NULL + del_task_manager
                1830    LOAD_FAST                       2: pid
                1832    CALL                            1
                1840    POP_TOP                         
                1842    LOAD_GLOBAL                     71: NULL + StopDetect
                1852    LOAD_FAST                       4: stop_thread
                1854    CALL                            1
                1862    POP_TOP                         
                1864    POP_TOP                         
                1866    POP_EXCEPT                      
                1868    LOAD_CONST                      33: 'Done'
                1870    NOP                             
                1872    NOP                             
                1874    NOP                             
                1876    JUMP_FORWARD                    22 (to 1922)
                1884    POP_TOP                         
                1886    RETURN_CONST                    33: 'Done'
                1888    COPY                            3
                1890    POP_EXCEPT                      
                1892    RERAISE                         1
                1894    PUSH_EXC_INFO                   
                1896    PUSH_NULL                       
                1898    LOAD_CONST                      32: '__pyarmor_exit_14501__'
                1900    NOP                             
                1902    LOAD_CONST                      3: b'<COAddr>\x07\x00\x00\x1aL\x07\x00\x00\x00\x00\x00\x00\x00\x00\x00\x00\x00\x00\x00\x00'
                1904    CALL                            1
                1912    POP_TOP                         
                1914    RERAISE                         0
                1916    COPY                            3
                1918    POP_EXCEPT                      
                1920    RERAISE                         1
                1922    PUSH_NULL                       
                1924    LOAD_CONST                      32: '__pyarmor_exit_14501__'
                1926    LOAD_CONST                      3: b'<COAddr>\x07\x00\x00\x1aL\x07\x00\x00\x00\x00\x00\x00\x00\x00\x00\x00\x00\x00\x00\x00'
                1928    BUILD_TUPLE                     1
                1930    CALL_FUNCTION_EX                0
                1932    POP_TOP                         
                1934    RETURN_VALUE                    
            [Exception Table]
                30 to 1168 -> 1722 [0] 
                1168 to 1614 -> 1698 [1] lasti
                1616 to 1632 -> 1722 [0] 
                1632 to 1676 -> 1894 [0] 
                1698 to 1708 -> 1716 [3] lasti
                1708 to 1722 -> 1722 [0] 
                1722 to 1740 -> 1812 [1] lasti
                1740 to 1744 -> 1818 [0] 
                1744 to 1760 -> 1812 [1] lasti
                1760 to 1792 -> 1802 [1] lasti
                1792 to 1802 -> 1818 [0] 
                1802 to 1812 -> 1812 [1] lasti
                1812 to 1818 -> 1818 [0] 
                1818 to 1866 -> 1888 [1] lasti
                1866 to 1868 -> 1894 [0] 
                1888 to 1894 -> 1894 [0] 
                1894 to 1916 -> 1916 [1] lasti
        [Code]
            File Name: <frozen program.modules.Search_global>
            Object Name: worker
            Qualified Name: worker
            Arg Count: 6
            Pos Only Arg Count: 0
            KW Only Arg Count: 0
            Stack Size: 25
            Flags: 0x20000003 (CO_OPTIMIZED | CO_NEWLOCALS | CO_PYARMOR_OBFUSCATED)
            [Names]
                'Thread_wait'
                'account_works'
                'Lang'
                'Disconnect'
                'Logs'
                'PrintLog'
                'get'
                'int'
                'range'
                'db_search_global'
                'append'
                'get_all'
                'ValueError'
                'len'
                'capitalize'
                'functions'
                'contacts'
                'SearchRequest'
                'messages'
                'SearchGlobalRequest'
                'types'
                'InputMessagesFilterEmpty'
                'InputPeerEmpty'
                'chats'
                'entity'
                'check'
                'db_parsing'
                'insert_group'
                'users'
                'insert_user'
                'time'
                'sleep'
                'random'
                'uniform'
                'BaseException'
                'logging'
                'DelayOnline'
                'StopProgram'
            [Locals+Names]
                'account'
                'config'
                'proxy'
                'data'
                'parsing'
                'stop_thread'
                '__assert_armored__'
                '_var_var_16'
                '_var_var_17'
                '_var_var_18'
                '_var_var_19'
                '_var_var_20'
                '_var_var_21'
                '_var_var_22'
                '_var_var_23'
                '_var_var_15'
                '_var_var_24'
                '_var_var_25'
                '_var_var_26'
                '_var_var_27'
                '_var_var_28'
                '_var_var_29'
                '_var_var_30'
                '_var_var_31'
                '_var_var_32'
                '_var_var_3'
            [Constants]
                None
                '__pyarmor_assert_14502__'
                '__pyarmor_enter_14503__'
                b'<COAddr>\x05\x00\x00\x1a\xa2\n\x00\x00\x00\x00\x00\x00\x00\x00\x00\x00\x00\x00\x00\x00'
                'Search_global'   # b'\x81\xd1\x1d\x12!\xf9\xb6\xed\x1c\xf6\x02\xc2m\xe0'
                (
                    'module'
                )
                False
                'false'
                (
                    'account'
                    'status'
                )
                'work_account_completed'   # b'\x81\xf5\x17\x018\xc5\xbf\xd1\x18\xf5\x18\xcex\xd3\xfb\x8a\x02M\xb7\xa2\xbe\xceJ'
                (
                    'config'
                    'account'
                    'message'
                )
                'done'
                '__pyarmor_exit_14504__'
                'Settings'
                'file_db'
                'wait_from'   # b"\x81\xf5\x19\x1a'\xc5\xb8\xc0\x14\xf7"
                'wait_to'
                'kol_per_acc'   # b'\x81\xe9\x17\x1f\x0c\xea\xbb\xc0$\xfb\x0e\xc3'
                'option_list'   # b'\x81\xed\x08\x07:\xf5\xb0\xed\x17\xf3\x1e\xd4'
                'option'
                'unic'
                'No words in database'   # b'\x81\xcc\x17S$\xf5\xac\xd6\x08\xba\x04\xce,\xe8\xf9\x91\x0e_\xba\xb4\xaf'
                'took_from_database'   # b'\x81\xf6\x17\x1c8\xc5\xb8\xc0\x14\xf72\xc4m\xf8\xf9\x87\x0eN\xbe'
                (
                    'config'
                    'account'
                    'message'
                    'param'
                )
                ''
                20
                (
                    'q'
                    'limit'
                )
                0
                (
                    'q'
                    'filter'
                    'min_date'
                    'max_date'
                    'offset_rate'
                    'offset_peer'
                    'offset_id'
                    'limit'
                    'broadcasts_only'
                    'folder_id'
                )
                'all'
                'channels'
                'info'
                'id'
                'username'
                'title'
                'count'
                'photo'
                'invite'
                'send_messages'   # b'\x81\xf1\x1d\x1d7\xc5\xb3\xd7\x08\xe9\x0c\xc7i\xff'
                'send_media'   # b'\x81\xf1\x1d\x1d7\xc5\xb3\xd7\x1f\xf3\x0c'
                'send_stickers'   # b'\x81\xf1\x1d\x1d7\xc5\xad\xc6\x12\xf9\x06\xc5~\xff'
                'send_polls'   # b'\x81\xf1\x1d\x1d7\xc5\xae\xdd\x17\xf6\x1e'
                'slow_mode'   # b'\x81\xf1\x14\x1c$\xc5\xb3\xdd\x1f\xff'
                'scam'
                'types'
                'status'
                (
                    'group_id'
                    'username'
                    'title'
                    'count'
                    'photo'
                    'invite'
                    'send_messages'
                    'send_media'
                    'send_stickers'
                    'send_pools'
                    'slow_mode'
                    'scam'
                    'types'
                    'status'
                )
                'users'
                'group_id'
                'mess_id'
                'comm_id'
                'phone'
                'first_name'   # b'\x81\xe4\x11\x01 \xee\x81\xdc\x1a\xf7\x08'
                'last_name'   # b"\x81\xee\x19\x00'\xc5\xb0\xd3\x16\xff"
                'bio'
                'gender'
                'premium'
                'time'
                'invite_status'   # b'\x81\xeb\x16\x05:\xee\xbb\xed\x08\xee\x0c\xd4y\xff'
                'send_status'   # b'\x81\xf1\x1d\x1d7\xc5\xad\xc6\x1a\xee\x18\xd3'
                (
                    'user_id'
                    'group_id'
                    'mess_id'
                    'comm_id'
                    'phone'
                    'username'
                    'first_name'
                    'last_name'
                    'bio'
                    'gender'
                    'photo'
                    'premium'
                    'status'
                    'time'
                    'invite_status'
                    'send_status'
                )
                1
                2
            [Disassembly]
                0       NOP                             
                2       NOP                             
                4       PUSH_NULL                       
                6       LOAD_CONST                      2: '__pyarmor_enter_14503__'
                8       LOAD_CONST                      3: b'<COAddr>\x05\x00\x00\x1a\xa2\n\x00\x00\x00\x00\x00\x00\x00\x00\x00\x00\x00\x00\x00\x00'
                10      BUILD_TUPLE                     1
                12      CALL_FUNCTION_EX                0
                14      POP_TOP                         
                16      RESUME                          0
                18      NOP                             
                20      NOP                             
                22      NOP                             
                24      NOP                             
                26      NOP                             
                28      NOP                             
                30      LOAD_GLOBAL                     1: NULL + Thread_wait
                40      LOAD_FAST                       3: data
                42      LOAD_FAST                       1: config
                44      LOAD_FAST                       5: stop_thread
                46      CALL                            3
                54      POP_TOP                         
                56      LOAD_GLOBAL                     3: NULL + account_works
                66      LOAD_FAST                       1: config
                68      LOAD_GLOBAL                     4: Lang
                78      LOAD_FAST                       2: proxy
                80      LOAD_FAST                       0: account
                82      LOAD_FAST                       5: stop_thread
                84      PUSH_NULL                       
                86      LOAD_CONST                      1: '__pyarmor_assert_14502__'
                88      LOAD_CONST                      4: 'Search_global'   # b'\x81\xd1\x1d\x12!\xf9\xb6\xed\x1c\xf6\x02\xc2m\xe0'
                90      CALL                            1
                98      KW_NAMES                        5: ('module',)
                100     CALL                            6
                108     STORE_FAST                      7: _var_var_16
                110     LOAD_FAST                       7: _var_var_16
                112     LOAD_CONST                      6: False
                114     COMPARE_OP                      40 (==)
                118     POP_JUMP_IF_FALSE               68 (to 256)
                120     LOAD_FAST                       0: account
                122     LOAD_CONST                      7: 'false'
                124     LOAD_CONST                      8: ('account', 'status')
                126     BUILD_CONST_KEY_MAP             2
                128     LOAD_GLOBAL                     7: NULL + Disconnect
                138     LOAD_FAST                       7: _var_var_16
                140     CALL                            1
                148     POP_TOP                         
                150     LOAD_GLOBAL                     9: NULL + Logs
                160     LOAD_ATTR                       10: PrintLog
                180     LOAD_FAST                       1: config
                182     LOAD_FAST                       0: account
                184     LOAD_GLOBAL                     4: Lang
                194     PUSH_NULL                       
                196     LOAD_CONST                      1: '__pyarmor_assert_14502__'
                198     LOAD_CONST                      9: 'work_account_completed'   # b'\x81\xf5\x17\x018\xc5\xbf\xd1\x18\xf5\x18\xcex\xd3\xfb\x8a\x02M\xb7\xa2\xbe\xceJ'
                200     CALL                            1
                208     BINARY_SUBSCR                   
                212     KW_NAMES                        10: ('config', 'account', 'message')
                214     CALL                            3
                222     POP_TOP                         
                224     LOAD_FAST                       0: account
                226     LOAD_CONST                      11: 'done'
                228     LOAD_CONST                      8: ('account', 'status')
                230     BUILD_CONST_KEY_MAP             2
                232     SWAP                            2
                234     POP_TOP                         
                236     NOP                             
                238     NOP                             
                240     JUMP_FORWARD                    1266 (to 2776)
                244     CALL                            1
                252     POP_TOP                         
                254     RETURN_VALUE                    
                256     LOAD_FAST                       3: data
                258     LOAD_CONST                      13: 'Settings'
                260     BINARY_SUBSCR                   
                264     LOAD_ATTR                       13: get
                284     LOAD_CONST                      14: 'file_db'
                286     CALL                            1
                294     STORE_FAST                      8: _var_var_17
                296     LOAD_GLOBAL                     15: NULL + int
                306     LOAD_FAST                       3: data
                308     LOAD_CONST                      13: 'Settings'
                310     BINARY_SUBSCR                   
                314     LOAD_ATTR                       13: get
                334     PUSH_NULL                       
                336     LOAD_CONST                      1: '__pyarmor_assert_14502__'
                338     LOAD_CONST                      15: 'wait_from'   # b"\x81\xf5\x19\x1a'\xc5\xb8\xc0\x14\xf7"
                340     CALL                            1
                348     CALL                            1
                356     CALL                            1
                364     STORE_FAST                      9: _var_var_18
                366     LOAD_GLOBAL                     15: NULL + int
                376     LOAD_FAST                       3: data
                378     LOAD_CONST                      13: 'Settings'
                380     BINARY_SUBSCR                   
                384     LOAD_ATTR                       13: get
                404     LOAD_CONST                      16: 'wait_to'
                406     CALL                            1
                414     CALL                            1
                422     STORE_FAST                      10: _var_var_19
                424     LOAD_GLOBAL                     15: NULL + int
                434     LOAD_FAST                       3: data
                436     LOAD_CONST                      13: 'Settings'
                438     BINARY_SUBSCR                   
                442     LOAD_ATTR                       13: get
                462     PUSH_NULL                       
                464     LOAD_CONST                      1: '__pyarmor_assert_14502__'
                466     LOAD_CONST                      17: 'kol_per_acc'   # b'\x81\xe9\x17\x1f\x0c\xea\xbb\xc0$\xfb\x0e\xc3'
                468     CALL                            1
                476     CALL                            1
                484     CALL                            1
                492     STORE_FAST                      11: _var_var_20
                494     LOAD_FAST                       3: data
                496     LOAD_CONST                      13: 'Settings'
                498     BINARY_SUBSCR                   
                502     LOAD_ATTR                       13: get
                522     PUSH_NULL                       
                524     LOAD_CONST                      1: '__pyarmor_assert_14502__'
                526     LOAD_CONST                      18: 'option_list'   # b'\x81\xed\x08\x07:\xf5\xb0\xed\x17\xf3\x1e\xd4'
                528     CALL                            1
                536     CALL                            1
                544     STORE_FAST                      12: _var_var_21
                546     LOAD_FAST                       3: data
                548     LOAD_CONST                      13: 'Settings'
                550     BINARY_SUBSCR                   
                554     LOAD_ATTR                       13: get
                574     LOAD_CONST                      19: 'option'
                576     CALL                            1
                584     STORE_FAST                      13: _var_var_22
                586     BUILD_LIST                      0
                588     STORE_FAST                      14: _var_var_23
                590     LOAD_FAST                       12: _var_var_21
                592     LOAD_CONST                      20: 'unic'
                594     COMPARE_OP                      40 (==)
                598     POP_JUMP_IF_FALSE               63 (to 726)
                600     LOAD_GLOBAL                     17: NULL + range
                610     LOAD_FAST                       11: _var_var_20
                612     CALL                            1
                620     GET_ITER                        
                622     FOR_ITER                        48 (to 720)
                626     STORE_FAST                      15: _var_var_15
                628     LOAD_GLOBAL                     19: NULL + db_search_global
                638     LOAD_FAST                       8: _var_var_17
                640     CALL                            1
                648     LOAD_ATTR                       13: get
                668     CALL                            0
                676     STORE_FAST                      16: _var_var_24
                678     LOAD_FAST                       16: _var_var_24
                680     POP_JUMP_IF_NOT_NONE            2 (to 686)
                682     POP_TOP                         
                684     JUMP_FORWARD                    65 (to 816)
                686     LOAD_FAST                       14: _var_var_23
                688     LOAD_ATTR                       21: append
                708     LOAD_FAST                       16: _var_var_24
                710     CALL                            1
                718     POP_TOP                         
                720     JUMP_BACKWARD                   50 (to 622)
                722     END_FOR                         
                724     JUMP_FORWARD                    45 (to 816)
                726     LOAD_GLOBAL                     19: NULL + db_search_global
                736     LOAD_FAST                       8: _var_var_17
                738     CALL                            1
                746     LOAD_ATTR                       23: get_all
                766     LOAD_FAST                       11: _var_var_20
                768     CALL                            1
                776     STORE_FAST                      14: _var_var_23
                778     LOAD_FAST                       14: _var_var_23
                780     POP_JUMP_IF_NOT_NONE            17 (to 816)
                782     LOAD_GLOBAL                     25: NULL + ValueError
                792     PUSH_NULL                       
                794     LOAD_CONST                      1: '__pyarmor_assert_14502__'
                796     LOAD_CONST                      21: 'No words in database'   # b'\x81\xcc\x17S$\xf5\xac\xd6\x08\xba\x04\xce,\xe8\xf9\x91\x0e_\xba\xb4\xaf'
                798     CALL                            1
                806     CALL                            1
                814     RAISE_VARARGS                   1
                816     LOAD_GLOBAL                     9: NULL + Logs
                826     LOAD_ATTR                       10: PrintLog
                846     LOAD_FAST                       1: config
                848     LOAD_FAST                       0: account
                850     LOAD_GLOBAL                     4: Lang
                860     PUSH_NULL                       
                862     LOAD_CONST                      1: '__pyarmor_assert_14502__'
                864     LOAD_CONST                      22: 'took_from_database'   # b'\x81\xf6\x17\x1c8\xc5\xb8\xc0\x14\xf72\xc4m\xf8\xf9\x87\x0eN\xbe'
                866     CALL                            1
                874     BINARY_SUBSCR                   
                878     LOAD_GLOBAL                     27: NULL + len
                888     LOAD_FAST                       14: _var_var_23
                890     CALL                            1
                898     KW_NAMES                        23: ('config', 'account', 'message', 'param')
                900     CALL                            4
                908     POP_TOP                         
                910     LOAD_FAST                       14: _var_var_23
                912     GET_ITER                        
                914     FOR_ITER                        670 (to 2258)
                920     STORE_FAST                      16: _var_var_24
                922     LOAD_GLOBAL                     9: NULL + Logs
                932     LOAD_ATTR                       10: PrintLog
                952     LOAD_FAST                       1: config
                954     LOAD_FAST                       0: account
                956     LOAD_FAST                       16: _var_var_24
                958     KW_NAMES                        10: ('config', 'account', 'message')
                960     CALL                            3
                968     POP_TOP                         
                970     LOAD_FAST                       16: _var_var_24
                972     LOAD_ATTR                       29: capitalize
                992     CALL                            0
                1000    STORE_FAST                      16: _var_var_24
                1002    LOAD_CONST                      24: ''
                1004    STORE_FAST                      17: _var_var_25
                1006    LOAD_FAST                       16: _var_var_24
                1008    GET_ITER                        
                1010    FOR_ITER                        604 (to 2222)
                1016    STORE_FAST                      18: _var_var_26
                1018    NOP                             
                1020    LOAD_FAST                       17: _var_var_25
                1022    LOAD_FAST                       18: _var_var_26
                1024    BINARY_OP                       13 (+=)
                1028    STORE_FAST                      17: _var_var_25
                1030    LOAD_GLOBAL                     30: functions
                1040    LOAD_ATTR                       32: contacts
                1060    LOAD_ATTR                       35: SearchRequest
                1080    LOAD_FAST                       17: _var_var_25
                1082    LOAD_CONST                      25: 20
                1084    KW_NAMES                        26: ('q', 'limit')
                1086    CALL                            2
                1094    LOAD_GLOBAL                     30: functions
                1104    LOAD_ATTR                       36: messages
                1124    LOAD_ATTR                       39: SearchGlobalRequest
                1144    LOAD_FAST                       17: _var_var_25
                1146    LOAD_GLOBAL                     41: NULL + types
                1156    LOAD_ATTR                       42: InputMessagesFilterEmpty
                1176    CALL                            0
                1184    LOAD_CONST                      27: 0
                1186    LOAD_CONST                      27: 0
                1188    LOAD_CONST                      27: 0
                1190    LOAD_GLOBAL                     41: NULL + types
                1200    LOAD_ATTR                       44: InputPeerEmpty
                1220    CALL                            0
                1228    LOAD_CONST                      27: 0
                1230    LOAD_CONST                      25: 20
                1232    LOAD_CONST                      6: False
                1234    LOAD_CONST                      27: 0
                1236    KW_NAMES                        28: ('q', 'filter', 'min_date', 'max_date', 'offset_rate', 'offset_peer', 'offset_id', 'limit', 'broadcasts_only', 'folder_id')
                1238    CALL                            10
                1246    BUILD_LIST                      2
                1248    STORE_FAST                      19: _var_var_27
                1250    PUSH_NULL                       
                1252    LOAD_FAST                       7: _var_var_16
                1254    LOAD_FAST                       19: _var_var_27
                1256    CALL                            1
                1264    STORE_FAST                      20: _var_var_28
                1266    LOAD_FAST                       20: _var_var_28
                1268    GET_ITER                        
                1270    FOR_ITER                        430 (to 2134)
                1276    STORE_FAST                      21: _var_var_29
                1278    LOAD_FAST                       13: _var_var_22
                1280    LOAD_CONST                      29: 'all'
                1282    COMPARE_OP                      40 (==)
                1286    POP_JUMP_IF_TRUE                5 (to 1298)
                1288    LOAD_FAST                       13: _var_var_22
                1290    LOAD_CONST                      30: 'channels'
                1292    COMPARE_OP                      40 (==)
                1296    POP_JUMP_IF_FALSE               199 (to 1696)
                1298    LOAD_FAST                       21: _var_var_29
                1300    LOAD_ATTR                       46: chats
                1320    GET_ITER                        
                1322    FOR_ITER                        184 (to 1692)
                1326    STORE_FAST                      22: _var_var_30
                1328    LOAD_GLOBAL                     49: NULL + entity
                1338    CALL                            0
                1346    LOAD_ATTR                       51: check
                1366    LOAD_FAST                       22: _var_var_30
                1368    CALL                            1
                1376    STORE_FAST                      23: _var_var_31
                1378    LOAD_FAST                       23: _var_var_31
                1380    POP_JUMP_IF_TRUE                1 (to 1384)
                1382    JUMP_BACKWARD                   31 (to 1322)
                1384    LOAD_GLOBAL                     53: NULL + db_parsing
                1394    LOAD_FAST                       4: parsing
                1396    CALL                            1
                1404    LOAD_ATTR                       55: insert_group
                1424    LOAD_FAST                       23: _var_var_31
                1426    LOAD_CONST                      31: 'info'
                1428    BINARY_SUBSCR                   
                1432    LOAD_CONST                      32: 'id'
                1434    BINARY_SUBSCR                   
                1438    LOAD_FAST                       23: _var_var_31
                1440    LOAD_CONST                      31: 'info'
                1442    BINARY_SUBSCR                   
                1446    LOAD_CONST                      33: 'username'
                1448    BINARY_SUBSCR                   
                1452    LOAD_FAST                       23: _var_var_31
                1454    LOAD_CONST                      31: 'info'
                1456    BINARY_SUBSCR                   
                1460    LOAD_CONST                      34: 'title'
                1462    BINARY_SUBSCR                   
                1466    LOAD_FAST                       23: _var_var_31
                1468    LOAD_CONST                      31: 'info'
                1470    BINARY_SUBSCR                   
                1474    LOAD_CONST                      35: 'count'
                1476    BINARY_SUBSCR                   
                1480    LOAD_FAST                       23: _var_var_31
                1482    LOAD_CONST                      31: 'info'
                1484    BINARY_SUBSCR                   
                1488    LOAD_CONST                      36: 'photo'
                1490    BINARY_SUBSCR                   
                1494    LOAD_FAST                       23: _var_var_31
                1496    LOAD_CONST                      31: 'info'
                1498    BINARY_SUBSCR                   
                1502    LOAD_CONST                      37: 'invite'
                1504    BINARY_SUBSCR                   
                1508    LOAD_FAST                       23: _var_var_31
                1510    LOAD_CONST                      31: 'info'
                1512    BINARY_SUBSCR                   
                1516    PUSH_NULL                       
                1518    LOAD_CONST                      1: '__pyarmor_assert_14502__'
                1520    LOAD_CONST                      38: 'send_messages'   # b'\x81\xf1\x1d\x1d7\xc5\xb3\xd7\x08\xe9\x0c\xc7i\xff'
                1522    CALL                            1
                1530    BINARY_SUBSCR                   
                1534    LOAD_FAST                       23: _var_var_31
                1536    LOAD_CONST                      31: 'info'
                1538    BINARY_SUBSCR                   
                1542    PUSH_NULL                       
                1544    LOAD_CONST                      1: '__pyarmor_assert_14502__'
                1546    LOAD_CONST                      39: 'send_media'   # b'\x81\xf1\x1d\x1d7\xc5\xb3\xd7\x1f\xf3\x0c'
                1548    CALL                            1
                1556    BINARY_SUBSCR                   
                1560    LOAD_FAST                       23: _var_var_31
                1562    LOAD_CONST                      31: 'info'
                1564    BINARY_SUBSCR                   
                1568    PUSH_NULL                       
                1570    LOAD_CONST                      1: '__pyarmor_assert_14502__'
                1572    LOAD_CONST                      40: 'send_stickers'   # b'\x81\xf1\x1d\x1d7\xc5\xad\xc6\x12\xf9\x06\xc5~\xff'
                1574    CALL                            1
                1582    BINARY_SUBSCR                   
                1586    LOAD_FAST                       23: _var_var_31
                1588    LOAD_CONST                      31: 'info'
                1590    BINARY_SUBSCR                   
                1594    PUSH_NULL                       
                1596    LOAD_CONST                      1: '__pyarmor_assert_14502__'
                1598    LOAD_CONST                      41: 'send_polls'   # b'\x81\xf1\x1d\x1d7\xc5\xae\xdd\x17\xf6\x1e'
                1600    CALL                            1
                1608    BINARY_SUBSCR                   
                1612    LOAD_FAST                       23: _var_var_31
                1614    LOAD_CONST                      31: 'info'
                1616    BINARY_SUBSCR                   
                1620    PUSH_NULL                       
                1622    LOAD_CONST                      1: '__pyarmor_assert_14502__'
                1624    LOAD_CONST                      42: 'slow_mode'   # b'\x81\xf1\x14\x1c$\xc5\xb3\xdd\x1f\xff'
                1626    CALL                            1
                1634    BINARY_SUBSCR                   
                1638    LOAD_FAST                       23: _var_var_31
                1640    LOAD_CONST                      31: 'info'
                1642    BINARY_SUBSCR                   
                1646    LOAD_CONST                      43: 'scam'
                1648    BINARY_SUBSCR                   
                1652    LOAD_FAST                       23: _var_var_31
                1654    LOAD_CONST                      31: 'info'
                1656    BINARY_SUBSCR                   
                1660    LOAD_CONST                      44: 'types'
                1662    BINARY_SUBSCR                   
                1666    LOAD_FAST                       23: _var_var_31
                1668    LOAD_CONST                      31: 'info'
                1670    BINARY_SUBSCR                   
                1674    LOAD_CONST                      45: 'status'
                1676    BINARY_SUBSCR                   
                1680    KW_NAMES                        46: ('group_id', 'username', 'title', 'count', 'photo', 'invite', 'send_messages', 'send_media', 'send_stickers', 'send_pools', 'slow_mode', 'scam', 'types', 'status')
                1682    CALL                            14
                1690    POP_TOP                         
                1692    JUMP_BACKWARD                   186 (to 1322)
                1694    END_FOR                         
                1696    LOAD_FAST                       13: _var_var_22
                1698    LOAD_CONST                      29: 'all'
                1700    COMPARE_OP                      40 (==)
                1704    POP_JUMP_IF_TRUE                6 (to 1718)
                1706    LOAD_FAST                       13: _var_var_22
                1708    LOAD_CONST                      47: 'users'
                1710    COMPARE_OP                      40 (==)
                1714    POP_JUMP_IF_TRUE                1 (to 1718)
                1716    JUMP_BACKWARD                   224 (to 1270)
                1718    LOAD_FAST                       21: _var_var_29
                1720    LOAD_ATTR                       56: users
                1740    GET_ITER                        
                1742    FOR_ITER                        192 (to 2128)
                1746    STORE_FAST                      24: _var_var_32
                1748    LOAD_GLOBAL                     49: NULL + entity
                1758    CALL                            0
                1766    LOAD_ATTR                       51: check
                1786    LOAD_FAST                       24: _var_var_32
                1788    CALL                            1
                1796    STORE_FAST                      23: _var_var_31
                1798    LOAD_FAST                       23: _var_var_31
                1800    POP_JUMP_IF_TRUE                1 (to 1804)
                1802    JUMP_BACKWARD                   31 (to 1742)
                1804    LOAD_GLOBAL                     53: NULL + db_parsing
                1814    LOAD_FAST                       4: parsing
                1816    CALL                            1
                1824    LOAD_ATTR                       59: insert_user
                1844    LOAD_FAST                       23: _var_var_31
                1846    LOAD_CONST                      31: 'info'
                1848    BINARY_SUBSCR                   
                1852    LOAD_CONST                      32: 'id'
                1854    BINARY_SUBSCR                   
                1858    LOAD_FAST                       23: _var_var_31
                1860    LOAD_CONST                      31: 'info'
                1862    BINARY_SUBSCR                   
                1866    LOAD_CONST                      48: 'group_id'
                1868    BINARY_SUBSCR                   
                1872    LOAD_FAST                       23: _var_var_31
                1874    LOAD_CONST                      31: 'info'
                1876    BINARY_SUBSCR                   
                1880    LOAD_CONST                      49: 'mess_id'
                1882    BINARY_SUBSCR                   
                1886    LOAD_FAST                       23: _var_var_31
                1888    LOAD_CONST                      31: 'info'
                1890    BINARY_SUBSCR                   
                1894    LOAD_CONST                      50: 'comm_id'
                1896    BINARY_SUBSCR                   
                1900    LOAD_FAST                       23: _var_var_31
                1902    LOAD_CONST                      31: 'info'
                1904    BINARY_SUBSCR                   
                1908    LOAD_CONST                      51: 'phone'
                1910    BINARY_SUBSCR                   
                1914    LOAD_FAST                       23: _var_var_31
                1916    LOAD_CONST                      31: 'info'
                1918    BINARY_SUBSCR                   
                1922    LOAD_CONST                      33: 'username'
                1924    BINARY_SUBSCR                   
                1928    LOAD_FAST                       23: _var_var_31
                1930    LOAD_CONST                      31: 'info'
                1932    BINARY_SUBSCR                   
                1936    PUSH_NULL                       
                1938    LOAD_CONST                      1: '__pyarmor_assert_14502__'
                1940    LOAD_CONST                      52: 'first_name'   # b'\x81\xe4\x11\x01 \xee\x81\xdc\x1a\xf7\x08'
                1942    CALL                            1
                1950    BINARY_SUBSCR                   
                1954    LOAD_FAST                       23: _var_var_31
                1956    LOAD_CONST                      31: 'info'
                1958    BINARY_SUBSCR                   
                1962    PUSH_NULL                       
                1964    LOAD_CONST                      1: '__pyarmor_assert_14502__'
                1966    LOAD_CONST                      53: 'last_name'   # b"\x81\xee\x19\x00'\xc5\xb0\xd3\x16\xff"
                1968    CALL                            1
                1976    BINARY_SUBSCR                   
                1980    LOAD_FAST                       23: _var_var_31
                1982    LOAD_CONST                      31: 'info'
                1984    BINARY_SUBSCR                   
                1988    LOAD_CONST                      54: 'bio'
                1990    BINARY_SUBSCR                   
                1994    LOAD_FAST                       23: _var_var_31
                1996    LOAD_CONST                      31: 'info'
                1998    BINARY_SUBSCR                   
                2002    LOAD_CONST                      55: 'gender'
                2004    BINARY_SUBSCR                   
                2008    LOAD_FAST                       23: _var_var_31
                2010    LOAD_CONST                      31: 'info'
                2012    BINARY_SUBSCR                   
                2016    LOAD_CONST                      36: 'photo'
                2018    BINARY_SUBSCR                   
                2022    LOAD_FAST                       23: _var_var_31
                2024    LOAD_CONST                      31: 'info'
                2026    BINARY_SUBSCR                   
                2030    LOAD_CONST                      56: 'premium'
                2032    BINARY_SUBSCR                   
                2036    LOAD_FAST                       23: _var_var_31
                2038    LOAD_CONST                      31: 'info'
                2040    BINARY_SUBSCR                   
                2044    LOAD_CONST                      45: 'status'
                2046    BINARY_SUBSCR                   
                2050    LOAD_FAST                       23: _var_var_31
                2052    LOAD_CONST                      31: 'info'
                2054    BINARY_SUBSCR                   
                2058    LOAD_CONST                      57: 'time'
                2060    BINARY_SUBSCR                   
                2064    LOAD_FAST                       23: _var_var_31
                2066    LOAD_CONST                      31: 'info'
                2068    BINARY_SUBSCR                   
                2072    PUSH_NULL                       
                2074    LOAD_CONST                      1: '__pyarmor_assert_14502__'
                2076    LOAD_CONST                      58: 'invite_status'   # b'\x81\xeb\x16\x05:\xee\xbb\xed\x08\xee\x0c\xd4y\xff'
                2078    CALL                            1
                2086    BINARY_SUBSCR                   
                2090    LOAD_FAST                       23: _var_var_31
                2092    LOAD_CONST                      31: 'info'
                2094    BINARY_SUBSCR                   
                2098    PUSH_NULL                       
                2100    LOAD_CONST                      1: '__pyarmor_assert_14502__'
                2102    LOAD_CONST                      59: 'send_status'   # b'\x81\xf1\x1d\x1d7\xc5\xad\xc6\x1a\xee\x18\xd3'
                2104    CALL                            1
                2112    BINARY_SUBSCR                   
                2116    KW_NAMES                        60: ('user_id', 'group_id', 'mess_id', 'comm_id', 'phone', 'username', 'first_name', 'last_name', 'bio', 'gender', 'photo', 'premium', 'status', 'time', 'invite_status', 'send_status')
                2118    CALL                            16
                2126    POP_TOP                         
                2128    JUMP_BACKWARD                   194 (to 1742)
                2130    END_FOR                         
                2132    JUMP_BACKWARD                   433 (to 1270)
                2136    END_FOR                         
                2138    LOAD_GLOBAL                     61: NULL + time
                2148    LOAD_ATTR                       62: sleep
                2168    LOAD_GLOBAL                     65: NULL + random
                2178    LOAD_ATTR                       66: uniform
                2198    LOAD_CONST                      61: 1
                2200    LOAD_CONST                      62: 2
                2202    CALL                            2
                2210    CALL                            1
                2218    POP_TOP                         
                2220    JUMP_BACKWARD                   607 (to 1010)
                2224    END_FOR                         
                2226    LOAD_GLOBAL                     73: NULL + DelayOnline
                2236    LOAD_FAST                       0: account
                2238    LOAD_FAST                       7: _var_var_16
                2240    LOAD_FAST                       9: _var_var_18
                2242    LOAD_FAST                       10: _var_var_19
                2244    LOAD_FAST                       5: stop_thread
                2246    CALL                            5
                2254    POP_TOP                         
                2256    JUMP_BACKWARD                   673 (to 914)
                2260    END_FOR                         
                2262    NOP                             
                2264    LOAD_GLOBAL                     7: NULL + Disconnect
                2274    LOAD_FAST_CHECK                 7: _var_var_16
                2276    CALL                            1
                2284    POP_TOP                         
                2286    LOAD_GLOBAL                     9: NULL + Logs
                2296    LOAD_ATTR                       10: PrintLog
                2316    LOAD_FAST                       1: config
                2318    LOAD_FAST                       0: account
                2320    LOAD_GLOBAL                     4: Lang
                2330    PUSH_NULL                       
                2332    LOAD_CONST                      1: '__pyarmor_assert_14502__'
                2334    LOAD_CONST                      9: 'work_account_completed'   # b'\x81\xf5\x17\x018\xc5\xbf\xd1\x18\xf5\x18\xcex\xd3\xfb\x8a\x02M\xb7\xa2\xbe\xceJ'
                2336    CALL                            1
                2344    BINARY_SUBSCR                   
                2348    KW_NAMES                        10: ('config', 'account', 'message')
                2350    CALL                            3
                2358    POP_TOP                         
                2360    LOAD_FAST                       0: account
                2362    LOAD_CONST                      11: 'done'
                2364    LOAD_CONST                      8: ('account', 'status')
                2366    BUILD_CONST_KEY_MAP             2
                2368    NOP                             
                2370    NOP                             
                2372    NOP                             
                2374    JUMP_FORWARD                    200 (to 2776)
                2376    CALL                            1
                2384    POP_TOP                         
                2386    RETURN_VALUE                    
                2388    PUSH_EXC_INFO                   
                2390    POP_TOP                         
                2392    POP_EXCEPT                      
                2394    JUMP_BACKWARD                   1124 (to 150)
                2398    COPY                            3
                2400    POP_EXCEPT                      
                2402    RERAISE                         1
                2404    PUSH_EXC_INFO                   
                2406    LOAD_GLOBAL                     68: BaseException
                2416    CHECK_EXC_MATCH                 
                2418    POP_JUMP_IF_FALSE               27 (to 2474)
                2420    STORE_FAST                      25: _var_var_3
                2422    PUSH_NULL                       
                2424    LOAD_GLOBAL                     71: NULL + logging
                2434    LOAD_FAST                       25: _var_var_3
                2436    CALL                            1
                2444    CALL                            0
                2452    POP_TOP                         
                2454    POP_EXCEPT                      
                2456    LOAD_CONST                      0: None
                2458    STORE_FAST                      25: _var_var_3
                2460    DELETE_FAST                     25: _var_var_3
                2462    JUMP_BACKWARD                   728 (to 1010)
                2466    LOAD_CONST                      0: None
                2468    STORE_FAST                      25: _var_var_3
                2470    DELETE_FAST                     25: _var_var_3
                2472    RERAISE                         1
                2474    RERAISE                         0
                2476    COPY                            3
                2478    POP_EXCEPT                      
                2480    RERAISE                         1
                2482    PUSH_EXC_INFO                   
                2484    LOAD_GLOBAL                     74: StopProgram
                2494    CHECK_EXC_MATCH                 
                2496    POP_JUMP_IF_FALSE               3 (to 2504)
                2498    POP_TOP                         
                2500    POP_EXCEPT                      
                2502    JUMP_BACKWARD                   120 (to 2264)
                2504    LOAD_GLOBAL                     68: BaseException
                2514    CHECK_EXC_MATCH                 
                2516    POP_JUMP_IF_FALSE               26 (to 2570)
                2518    STORE_FAST                      25: _var_var_3
                2520    PUSH_NULL                       
                2522    LOAD_GLOBAL                     71: NULL + logging
                2532    LOAD_FAST                       25: _var_var_3
                2534    CALL                            1
                2542    CALL                            0
                2550    POP_TOP                         
                2552    POP_EXCEPT                      
                2554    LOAD_CONST                      0: None
                2556    STORE_FAST                      25: _var_var_3
                2558    DELETE_FAST                     25: _var_var_3
                2560    JUMP_BACKWARD                   149 (to 2264)
                2562    LOAD_CONST                      0: None
                2564    STORE_FAST                      25: _var_var_3
                2566    DELETE_FAST                     25: _var_var_3
                2568    RERAISE                         1
                2570    RERAISE                         0
                2572    COPY                            3
                2574    POP_EXCEPT                      
                2576    RERAISE                         1
                2578    PUSH_EXC_INFO                   
                2580    POP_TOP                         
                2582    POP_EXCEPT                      
                2584    JUMP_BACKWARD                   150 (to 2286)
                2586    COPY                            3
                2588    POP_EXCEPT                      
                2590    RERAISE                         1
                2592    PUSH_EXC_INFO                   
                2594    LOAD_GLOBAL                     7: NULL + Disconnect
                2604    LOAD_FAST_CHECK                 7: _var_var_16
                2606    CALL                            1
                2614    POP_TOP                         
                2616    JUMP_FORWARD                    7 (to 2632)
                2618    PUSH_EXC_INFO                   
                2620    POP_TOP                         
                2622    POP_EXCEPT                      
                2624    JUMP_FORWARD                    3 (to 2632)
                2626    COPY                            3
                2628    POP_EXCEPT                      
                2630    RERAISE                         1
                2632    LOAD_GLOBAL                     9: NULL + Logs
                2642    LOAD_ATTR                       10: PrintLog
                2662    LOAD_FAST                       1: config
                2664    LOAD_FAST                       0: account
                2666    LOAD_GLOBAL                     4: Lang
                2676    PUSH_NULL                       
                2678    LOAD_CONST                      1: '__pyarmor_assert_14502__'
                2680    LOAD_CONST                      9: 'work_account_completed'   # b'\x81\xf5\x17\x018\xc5\xbf\xd1\x18\xf5\x18\xcex\xd3\xfb\x8a\x02M\xb7\xa2\xbe\xceJ'
                2682    CALL                            1
                2690    BINARY_SUBSCR                   
                2694    KW_NAMES                        10: ('config', 'account', 'message')
                2696    CALL                            3
                2704    POP_TOP                         
                2706    LOAD_FAST                       0: account
                2708    LOAD_CONST                      11: 'done'
                2710    LOAD_CONST                      8: ('account', 'status')
                2712    BUILD_CONST_KEY_MAP             2
                2714    SWAP                            2
                2716    POP_TOP                         
                2718    SWAP                            2
                2720    POP_EXCEPT                      
                2722    NOP                             
                2724    NOP                             
                2726    NOP                             
                2728    JUMP_FORWARD                    23 (to 2776)
                2730    CALL                            1
                2738    POP_TOP                         
                2740    RETURN_VALUE                    
                2742    COPY                            3
                2744    POP_EXCEPT                      
                2746    RERAISE                         1
                2748    PUSH_EXC_INFO                   
                2750    PUSH_NULL                       
                2752    LOAD_CONST                      12: '__pyarmor_exit_14504__'
                2754    NOP                             
                2756    LOAD_CONST                      3: b'<COAddr>\x05\x00\x00\x1a\xa2\n\x00\x00\x00\x00\x00\x00\x00\x00\x00\x00\x00\x00\x00\x00'
                2758    CALL                            1
                2766    POP_TOP                         
                2768    RERAISE                         0
                2770    COPY                            3
                2772    POP_EXCEPT                      
                2774    RERAISE                         1
                2776    PUSH_NULL                       
                2778    LOAD_CONST                      12: '__pyarmor_exit_14504__'
                2780    LOAD_CONST                      3: b'<COAddr>\x05\x00\x00\x1a\xa2\n\x00\x00\x00\x00\x00\x00\x00\x00\x00\x00\x00\x00\x00\x00'
                2782    BUILD_TUPLE                     1
                2784    CALL_FUNCTION_EX                0
                2786    POP_TOP                         
                2788    RETURN_VALUE                    
            [Exception Table]
                30 to 128 -> 2482 [0] 
                128 to 150 -> 2388 [1] 
                150 to 236 -> 2748 [0] 
                256 to 1018 -> 2482 [0] 
                1020 to 1716 -> 2404 [2] 
                1718 to 2220 -> 2404 [2] 
                2220 to 2262 -> 2482 [0] 
                2262 to 2264 -> 2592 [0] 
                2264 to 2286 -> 2578 [0] 
                2286 to 2368 -> 2748 [0] 
                2388 to 2392 -> 2398 [2] lasti
                2392 to 2404 -> 2748 [0] 
                2404 to 2422 -> 2476 [3] lasti
                2422 to 2454 -> 2466 [3] lasti
                2454 to 2466 -> 2482 [0] 
                2466 to 2476 -> 2476 [3] lasti
                2476 to 2482 -> 2482 [0] 
                2482 to 2500 -> 2572 [1] lasti
                2500 to 2504 -> 2592 [0] 
                2504 to 2520 -> 2572 [1] lasti
                2520 to 2552 -> 2562 [1] lasti
                2552 to 2562 -> 2592 [0] 
                2562 to 2572 -> 2572 [1] lasti
                2572 to 2578 -> 2592 [0] 
                2578 to 2582 -> 2586 [1] lasti
                2582 to 2592 -> 2748 [0] 
                2592 to 2594 -> 2742 [1] lasti
                2594 to 2616 -> 2618 [2] 
                2616 to 2618 -> 2742 [1] lasti
                2618 to 2622 -> 2626 [3] lasti
                2622 to 2720 -> 2742 [1] lasti
                2720 to 2722 -> 2748 [0] 
                2742 to 2748 -> 2748 [0] 
                2748 to 2770 -> 2770 [1] lasti
        '__pyarmor_exit_14495__'
    [Disassembly]
        0       NOP                             
        2       NOP                             
        4       PUSH_NULL                       
        6       LOAD_CONST                      1: '__pyarmor_enter_14494__'
        8       LOAD_CONST                      2: b'<COAddr>\x05\x00\x00\x1af\x01\x00\x00\x00\x00\x00\x00\x00\x00\x00\x00\x00\x00\x00\x00'
        10      BUILD_TUPLE                     1
        12      CALL_FUNCTION_EX                0
        14      POP_TOP                         
        16      RESUME                          0
        18      NOP                             
        20      NOP                             
        22      NOP                             
        24      NOP                             
        26      LOAD_CONST                      3: 0
        28      LOAD_CONST                      4: None
        30      IMPORT_NAME                     1: eel
        32      STORE_NAME                      1: eel
        34      LOAD_CONST                      3: 0
        36      LOAD_CONST                      4: None
        38      IMPORT_NAME                     2: time
        40      STORE_NAME                      2: time
        42      LOAD_CONST                      3: 0
        44      LOAD_CONST                      4: None
        46      IMPORT_NAME                     3: json
        48      STORE_NAME                      3: json
        50      LOAD_CONST                      3: 0
        52      LOAD_CONST                      4: None
        54      IMPORT_NAME                     4: random
        56      STORE_NAME                      4: random
        58      LOAD_CONST                      3: 0
        60      LOAD_CONST                      4: None
        62      IMPORT_NAME                     5: datetime
        64      STORE_NAME                      5: datetime
        66      LOAD_CONST                      3: 0
        68      LOAD_CONST                      4: None
        70      IMPORT_NAME                     6: concurrent.futures
        72      STORE_NAME                      7: concurrent
        74      LOAD_CONST                      3: 0
        76      LOAD_CONST                      5: ('Thread', 'Event')
        78      IMPORT_NAME                     8: threading
        80      IMPORT_FROM                     9: Thread
        82      STORE_NAME                      9: Thread
        84      IMPORT_FROM                     10: Event
        86      STORE_NAME                      10: Event
        88      POP_TOP                         
        90      LOAD_CONST                      3: 0
        92      LOAD_CONST                      6: ('functions', 'types')
        94      IMPORT_NAME                     11: multithon
        96      IMPORT_FROM                     12: functions
        98      STORE_NAME                      12: functions
        100     IMPORT_FROM                     13: types
        102     STORE_NAME                      13: types
        104     POP_TOP                         
        106     LOAD_CONST                      3: 0
        108     LOAD_CONST                      7: ('StopProgram',)
        110     IMPORT_NAME                     14: multithon.errors
        112     IMPORT_FROM                     15: StopProgram
        114     STORE_NAME                      15: StopProgram
        116     POP_TOP                         
        118     LOAD_CONST                      3: 0
        120     LOAD_CONST                      8: ('GetLang',)
        122     IMPORT_NAME                     16: program.static_classes
        124     IMPORT_FROM                     17: GetLang
        126     STORE_NAME                      17: GetLang
        128     POP_TOP                         
        130     LOAD_CONST                      3: 0
        132     LOAD_CONST                      9: ('Logs',)
        134     IMPORT_NAME                     16: program.static_classes
        136     IMPORT_FROM                     18: Logs
        138     STORE_NAME                      18: Logs
        140     POP_TOP                         
        142     LOAD_CONST                      3: 0
        144     LOAD_CONST                      10: ('logging',)
        146     IMPORT_NAME                     16: program.static_classes
        148     IMPORT_FROM                     19: logging
        150     STORE_NAME                      19: logging
        152     POP_TOP                         
        154     LOAD_CONST                      3: 0
        156     LOAD_CONST                      11: ('memory_check_switcher',)
        158     IMPORT_NAME                     16: program.static_classes
        160     IMPORT_FROM                     20: memory_check_switcher
        162     STORE_NAME                      20: memory_check_switcher
        164     POP_TOP                         
        166     LOAD_CONST                      3: 0
        168     LOAD_CONST                      12: ('memory_set_pid',)
        170     IMPORT_NAME                     16: program.static_classes
        172     IMPORT_FROM                     21: memory_set_pid
        174     STORE_NAME                      21: memory_set_pid
        176     POP_TOP                         
        178     LOAD_CONST                      3: 0
        180     LOAD_CONST                      13: ('DelayOnline',)
        182     IMPORT_NAME                     22: program.telegram
        184     IMPORT_FROM                     23: DelayOnline
        186     STORE_NAME                      23: DelayOnline
        188     POP_TOP                         
        190     LOAD_CONST                      3: 0
        192     LOAD_CONST                      14: ('Disconnect',)
        194     IMPORT_NAME                     22: program.telegram
        196     IMPORT_FROM                     24: Disconnect
        198     STORE_NAME                      24: Disconnect
        200     POP_TOP                         
        202     LOAD_CONST                      3: 0
        204     LOAD_CONST                      15: ('Thread_wait',)
        206     IMPORT_NAME                     22: program.telegram
        208     IMPORT_FROM                     25: Thread_wait
        210     STORE_NAME                      25: Thread_wait
        212     POP_TOP                         
        214     LOAD_CONST                      3: 0
        216     LOAD_CONST                      16: ('account_works',)
        218     IMPORT_NAME                     22: program.telegram
        220     IMPORT_FROM                     26: account_works
        222     STORE_NAME                      26: account_works
        224     POP_TOP                         
        226     LOAD_CONST                      3: 0
        228     LOAD_CONST                      17: ('entity',)
        230     IMPORT_NAME                     22: program.telegram
        232     IMPORT_FROM                     27: entity
        234     STORE_NAME                      27: entity
        236     POP_TOP                         
        238     LOAD_CONST                      3: 0
        240     LOAD_CONST                      18: ('GetConfig',)
        242     IMPORT_NAME                     28: program.general
        244     IMPORT_FROM                     29: GetConfig
        246     STORE_NAME                      29: GetConfig
        248     POP_TOP                         
        250     LOAD_CONST                      3: 0
        252     LOAD_CONST                      19: ('GetProxy',)
        254     IMPORT_NAME                     28: program.general
        256     IMPORT_FROM                     30: GetProxy
        258     STORE_NAME                      30: GetProxy
        260     POP_TOP                         
        262     LOAD_CONST                      3: 0
        264     LOAD_CONST                      20: ('StopDetect',)
        266     IMPORT_NAME                     28: program.general
        268     IMPORT_FROM                     31: StopDetect
        270     STORE_NAME                      31: StopDetect
        272     POP_TOP                         
        274     LOAD_CONST                      3: 0
        276     LOAD_CONST                      21: ('check_get_settings',)
        278     IMPORT_NAME                     28: program.general
        280     IMPORT_FROM                     32: check_get_settings
        282     STORE_NAME                      32: check_get_settings
        284     POP_TOP                         
        286     LOAD_CONST                      3: 0
        288     LOAD_CONST                      22: ('del_task_manager',)
        290     IMPORT_NAME                     28: program.general
        292     IMPORT_FROM                     33: del_task_manager
        294     STORE_NAME                      33: del_task_manager
        296     POP_TOP                         
        298     LOAD_CONST                      3: 0
        300     LOAD_CONST                      23: ('getFile',)
        302     IMPORT_NAME                     28: program.general
        304     IMPORT_FROM                     34: getFile
        306     STORE_NAME                      34: getFile
        308     POP_TOP                         
        310     LOAD_CONST                      3: 0
        312     LOAD_CONST                      24: ('set_task_manager',)
        314     IMPORT_NAME                     28: program.general
        316     IMPORT_FROM                     35: set_task_manager
        318     STORE_NAME                      35: set_task_manager
        320     POP_TOP                         
        322     LOAD_CONST                      3: 0
        324     LOAD_CONST                      25: ('db_parsing',)
        326     IMPORT_NAME                     36: program.database
        328     IMPORT_FROM                     37: db_parsing
        330     STORE_NAME                      37: db_parsing
        332     POP_TOP                         
        334     LOAD_CONST                      3: 0
        336     LOAD_CONST                      26: ('db_search_global',)
        338     IMPORT_NAME                     36: program.database
        340     IMPORT_FROM                     38: db_search_global
        342     STORE_NAME                      38: db_search_global
        344     POP_TOP                         
        346     LOAD_CONST                      27: <CODE> Search_global
        348     MAKE_FUNCTION                   0
        350     STORE_NAME                      39: Search_global
        352     LOAD_CONST                      28: <CODE> START
        354     MAKE_FUNCTION                   0
        356     STORE_NAME                      40: START
        358     LOAD_CONST                      29: <CODE> worker
        360     MAKE_FUNCTION                   0
        362     STORE_NAME                      41: worker
        364     LOAD_CONST                      4: None
        366     NOP                             
        368     NOP                             
        370     NOP                             
        372     JUMP_FORWARD                    19 (to 412)
        380     POP_TOP                         
        382     RETURN_CONST                    4: None
        384     PUSH_EXC_INFO                   
        386     PUSH_NULL                       
        388     LOAD_CONST                      30: '__pyarmor_exit_14495__'
        390     NOP                             
        392     LOAD_CONST                      2: b'<COAddr>\x05\x00\x00\x1af\x01\x00\x00\x00\x00\x00\x00\x00\x00\x00\x00\x00\x00\x00\x00'
        394     CALL                            1
        402     POP_TOP                         
        404     RERAISE                         0
        406     COPY                            3
        408     POP_EXCEPT                      
        410     RERAISE                         1
        412     PUSH_NULL                       
        414     LOAD_CONST                      30: '__pyarmor_exit_14495__'
        416     LOAD_CONST                      2: b'<COAddr>\x05\x00\x00\x1af\x01\x00\x00\x00\x00\x00\x00\x00\x00\x00\x00\x00\x00\x00\x00'
        418     BUILD_TUPLE                     1
        420     CALL_FUNCTION_EX                0
        422     POP_TOP                         
        424     RETURN_VALUE                    
    [Exception Table]
        26 to 364 -> 384 [0] 
        384 to 406 -> 406 [1] lasti
