#decoded by lolz.live/mrpenny / t.me/zeus_jackpot
# ================================
# Примечания по Pyarmor:
# - Байт-код и объекты кода Pyarmor соответствуют стандартному Python, но присутствуют специальные вызовы функций среды выполнения (runtime) Pyarmor.
# - Вызовы строк — это не ошибки, а маркеры, которые обрабатываются Pyarmor во время выполнения.
#
# Руководство по декомпиляции (без среды выполнения):
# 1. Игнорируйте зашифрованные байты после `#`; используйте только строку до `#`.
# 2. Удалите "__pyarmor_enter_xxx__"(b"<COAddr>...") и "__pyarmor_leave_xxx__"(b"<COAddr>...") (пролог/эпилог).
# 3. "__pyarmor_assert_xxx__"(A) не является настоящим оператором assert.
#    - Если A — это имя или читаемая строка: замените на A.
#    - Если A — это (X, "Y"): замените на X.Y.
#    - Если A — это (X, "Y", Z): замените на X.Y = Z.
#    - В противном случае: выберите наиболее подходящую/логичную замену.
# 4. "__pyarmor_bcc_xxx__"(...) указывает на машинный (нативный) код; тело функции недоступно. Добавьте комментарий.
# ================================

[Code]
    File Name: <frozen program.modules.Send_groups>
    Object Name: <module>
    Qualified Name: <module>
    Arg Count: 0
    Pos Only Arg Count: 0
    KW Only Arg Count: 0
    Stack Size: 5
    Flags: 0x20000000 (CO_PYARMOR_OBFUSCATED)
    [Names]
        '__assert_armored__'
        'os'
        'eel'
        'json'
        'random'
        'datetime'
        'concurrent.futures'
        'concurrent'
        'threading'
        'Thread'
        'Event'
        'multithon.errors'
        'StopProgram'
        'program.static_classes'
        'AutoStop'
        'BanAccount'
        'GetLang'
        'Logs'
        'MaxFlood'
        'PeerFlood'
        'StopAccount'
        'check_module'
        'logging'
        'memory_check_switcher'
        'memory_set_pid'
        'program.telegram'
        'DelayOnline'
        'Disconnect'
        'Restart_wait'
        'Thread_wait'
        'account_works'
        'entity'
        'tg_group'
        'tg_links'
        'program.general'
        'GetConfig'
        'GetProxy'
        'StopDetect'
        'check_get_settings'
        'del_task_manager'
        'getFile'
        'set_task_manager'
        'program.database'
        'db_parsing'
        'db_statistic'
        'func.sender'
        'sender'
        'temp_group'
        'Send_groups'
        'START'
        'worker'
    [Locals+Names]
    [Constants]
        '__pyarmor_assert_14550__'
        '__pyarmor_enter_14551__'
        b'<COAddr>\x05\x00\x00\x1a\xd2\x01\x00\x00\x00\x00\x00\x00\x00\x00\x00\x00\x00\x00\x00\x00'
        0
        None
        (
            'Thread'
            'Event'
        )
        (
            'StopProgram'
        )
        (
            'AutoStop'
        )
        (
            'BanAccount'
        )
        (
            'GetLang'
        )
        (
            'Logs'
        )
        (
            'MaxFlood'
        )
        (
            'PeerFlood'
        )
        (
            'StopAccount'
        )
        (
            'check_module'
        )
        (
            'logging'
        )
        (
            'memory_check_switcher'
        )
        (
            'memory_set_pid'
        )
        (
            'DelayOnline'
        )
        (
            'Disconnect'
        )
        (
            'Restart_wait'
        )
        (
            'Thread_wait'
        )
        (
            'account_works'
        )
        (
            'entity'
        )
        (
            'tg_group'
        )
        (
            'tg_links'
        )
        (
            'GetConfig'
        )
        (
            'GetProxy'
        )
        (
            'StopDetect'
        )
        (
            'check_get_settings'
        )
        (
            'del_task_manager'
        )
        (
            'getFile'
        )
        (
            'set_task_manager'
        )
        (
            'db_parsing'
        )
        (
            'db_statistic'
        )
        1
        (
            'sender'
            'temp_group'
        )
        [Code]
            File Name: <frozen program.modules.Send_groups>
            Object Name: Send_groups
            Qualified Name: Send_groups
            Arg Count: 1
            Pos Only Arg Count: 0
            KW Only Arg Count: 0
            Stack Size: 8
            Flags: 0x20000003 (CO_OPTIMIZED | CO_NEWLOCALS | CO_PYARMOR_OBFUSCATED)
            [Names]
                'get'
                'getFile'
                'GetConfig'
                'config'
                'GetLang'
                'Lang'
                'GetProxy'
                'eel'
                'sendSuccessBox'
                'memory_check_switcher'
                'check_module'
                'sendErrorBox'
                'Event'
                'memory_set_pid'
                'Thread'
                'START'
                'start'
                'Logs'
                'WaitStopAnsfer'
                'UpdateLogInWindow'
                'BaseException'
                'logging'
            [Locals+Names]
                'data'
                '__assert_armored__'
                '_var_var_0'
                '_var_var_1'
                '_var_var_2'
                '_var_var_3'
            [Constants]
                None
                '__pyarmor_assert_14553__'
                '__pyarmor_enter_14554__'
                b'<COAddr>\x07\x00\x00\x1a<\x03\x00\x00\x00\x00\x00\x00\x00\x00\x00\x00\x00\x00\x00\x00'
                'action'
                'getFile'
                '__pyarmor_exit_14555__'
                'program_running'   # b'\x81\xf2\n\x1c4\xe8\xbf\xdf$\xe8\x18\xceb\xe5\xf6\x82'
                False
                'gpt'
                True
                11
                'gpt_not_activate'   # b'\x81\xe5\x08\x07\x0c\xf4\xb1\xc6$\xfb\x0e\xd4e\xfa\xf9\x91\n'
                (
                    'target'
                    'args'
                )
                (
                    'target'
                    'args'
                    'daemon'
                )
            [Disassembly]
                0       NOP                             
                2       NOP                             
                4       PUSH_NULL                       
                6       LOAD_CONST                      2: '__pyarmor_enter_14554__'
                8       LOAD_CONST                      3: b'<COAddr>\x07\x00\x00\x1a<\x03\x00\x00\x00\x00\x00\x00\x00\x00\x00\x00\x00\x00\x00\x00'
                10      BUILD_TUPLE                     1
                12      CALL_FUNCTION_EX                0
                14      POP_TOP                         
                16      RESUME                          0
                18      NOP                             
                20      NOP                             
                22      NOP                             
                24      NOP                             
                26      NOP                             
                28      NOP                             
                30      LOAD_FAST                       0: data
                32      LOAD_ATTR                       1: get
                52      LOAD_CONST                      4: 'action'
                54      CALL                            1
                62      POP_JUMP_IF_NONE                28 (to 120)
                64      LOAD_FAST                       0: data
                66      LOAD_CONST                      4: 'action'
                68      BINARY_SUBSCR                   
                72      LOAD_CONST                      5: 'getFile'
                74      COMPARE_OP                      40 (==)
                78      POP_JUMP_IF_FALSE               20 (to 120)
                80      LOAD_GLOBAL                     3: NULL + getFile
                90      LOAD_FAST                       0: data
                92      CALL                            1
                100     NOP                             
                102     NOP                             
                104     JUMP_FORWARD                    387 (to 882)
                108     CALL                            1
                116     POP_TOP                         
                118     RETURN_VALUE                    
                120     LOAD_GLOBAL                     5: NULL + GetConfig
                130     CALL                            0
                138     STORE_GLOBAL                    3: config
                140     LOAD_GLOBAL                     9: NULL + GetLang
                150     LOAD_GLOBAL                     6: config
                160     CALL                            1
                168     STORE_GLOBAL                    5: Lang
                170     LOAD_GLOBAL                     13: NULL + GetProxy
                180     CALL                            0
                188     STORE_FAST                      2: _var_var_0
                190     LOAD_GLOBAL                     15: NULL + eel
                200     LOAD_ATTR                       16: sendSuccessBox
                220     LOAD_GLOBAL                     10: Lang
                230     PUSH_NULL                       
                232     LOAD_CONST                      1: '__pyarmor_assert_14553__'
                234     LOAD_CONST                      7: 'program_running'   # b'\x81\xf2\n\x1c4\xe8\xbf\xdf$\xe8\x18\xceb\xe5\xf6\x82'
                236     CALL                            1
                244     BINARY_SUBSCR                   
                248     CALL                            1
                256     POP_TOP                         
                258     LOAD_GLOBAL                     19: NULL + memory_check_switcher
                268     CALL                            0
                276     POP_JUMP_IF_TRUE                11 (to 300)
                278     NOP                             
                280     LOAD_CONST                      8: False
                282     NOP                             
                284     NOP                             
                286     JUMP_FORWARD                    296 (to 882)
                296     POP_TOP                         
                298     RETURN_CONST                    8: False
                300     LOAD_GLOBAL                     6: config
                310     LOAD_CONST                      9: 'gpt'
                312     BINARY_SUBSCR                   
                316     LOAD_CONST                      10: True
                318     COMPARE_OP                      40 (==)
                322     POP_JUMP_IF_FALSE               59 (to 442)
                324     LOAD_GLOBAL                     21: NULL + check_module
                334     LOAD_CONST                      11: 11
                336     CALL                            1
                344     LOAD_CONST                      8: False
                346     COMPARE_OP                      40 (==)
                350     POP_JUMP_IF_FALSE               45 (to 442)
                352     LOAD_GLOBAL                     15: NULL + eel
                362     LOAD_ATTR                       22: sendErrorBox
                382     LOAD_GLOBAL                     10: Lang
                392     PUSH_NULL                       
                394     LOAD_CONST                      1: '__pyarmor_assert_14553__'
                396     LOAD_CONST                      12: 'gpt_not_activate'   # b'\x81\xe5\x08\x07\x0c\xf4\xb1\xc6$\xfb\x0e\xd4e\xfa\xf9\x91\n'
                398     CALL                            1
                406     BINARY_SUBSCR                   
                410     CALL                            1
                418     POP_TOP                         
                420     NOP                             
                422     LOAD_CONST                      8: False
                424     NOP                             
                426     NOP                             
                428     NOP                             
                430     JUMP_FORWARD                    225 (to 882)
                438     POP_TOP                         
                440     RETURN_CONST                    8: False
                442     LOAD_GLOBAL                     25: NULL + Event
                452     CALL                            0
                460     STORE_FAST                      3: _var_var_1
                462     LOAD_GLOBAL                     27: NULL + memory_set_pid
                472     CALL                            0
                480     STORE_FAST                      4: _var_var_2
                482     LOAD_GLOBAL                     29: NULL + Thread
                492     LOAD_GLOBAL                     30: START
                502     LOAD_FAST                       0: data
                504     LOAD_GLOBAL                     6: config
                514     LOAD_FAST                       4: _var_var_2
                516     LOAD_FAST                       2: _var_var_0
                518     LOAD_FAST                       3: _var_var_1
                520     BUILD_TUPLE                     5
                522     KW_NAMES                        13: ('target', 'args')
                524     CALL                            2
                532     LOAD_ATTR                       33: start
                552     CALL                            0
                560     POP_TOP                         
                562     LOAD_GLOBAL                     29: NULL + Thread
                572     LOAD_GLOBAL                     34: Logs
                582     LOAD_ATTR                       36: WaitStopAnsfer
                602     LOAD_GLOBAL                     6: config
                612     LOAD_FAST                       4: _var_var_2
                614     LOAD_FAST                       3: _var_var_1
                616     BUILD_TUPLE                     3
                618     LOAD_CONST                      10: True
                620     KW_NAMES                        14: ('target', 'args', 'daemon')
                622     CALL                            3
                630     LOAD_ATTR                       33: start
                650     CALL                            0
                658     POP_TOP                         
                660     LOAD_GLOBAL                     29: NULL + Thread
                670     LOAD_GLOBAL                     34: Logs
                680     LOAD_ATTR                       38: UpdateLogInWindow
                700     LOAD_GLOBAL                     6: config
                710     LOAD_FAST                       4: _var_var_2
                712     LOAD_FAST                       3: _var_var_1
                714     BUILD_TUPLE                     3
                716     LOAD_CONST                      10: True
                718     KW_NAMES                        14: ('target', 'args', 'daemon')
                720     CALL                            3
                728     LOAD_ATTR                       33: start
                748     CALL                            0
                756     POP_TOP                         
                758     LOAD_CONST                      0: None
                760     NOP                             
                762     NOP                             
                764     NOP                             
                766     JUMP_FORWARD                    57 (to 882)
                774     POP_TOP                         
                776     RETURN_CONST                    0: None
                778     PUSH_EXC_INFO                   
                780     LOAD_GLOBAL                     40: BaseException
                790     CHECK_EXC_MATCH                 
                792     POP_JUMP_IF_FALSE               26 (to 846)
                794     STORE_FAST                      5: _var_var_3
                796     PUSH_NULL                       
                798     LOAD_GLOBAL                     43: NULL + logging
                808     LOAD_FAST                       5: _var_var_3
                810     CALL                            1
                818     CALL                            0
                826     POP_TOP                         
                828     POP_EXCEPT                      
                830     LOAD_CONST                      0: None
                832     STORE_FAST                      5: _var_var_3
                834     DELETE_FAST                     5: _var_var_3
                836     JUMP_BACKWARD                   40 (to 758)
                838     LOAD_CONST                      0: None
                840     STORE_FAST                      5: _var_var_3
                842     DELETE_FAST                     5: _var_var_3
                844     RERAISE                         1
                846     RERAISE                         0
                848     COPY                            3
                850     POP_EXCEPT                      
                852     RERAISE                         1
                854     PUSH_EXC_INFO                   
                856     PUSH_NULL                       
                858     LOAD_CONST                      6: '__pyarmor_exit_14555__'
                860     NOP                             
                862     LOAD_CONST                      3: b'<COAddr>\x07\x00\x00\x1a<\x03\x00\x00\x00\x00\x00\x00\x00\x00\x00\x00\x00\x00\x00\x00'
                864     CALL                            1
                872     POP_TOP                         
                874     RERAISE                         0
                876     COPY                            3
                878     POP_EXCEPT                      
                880     RERAISE                         1
                882     PUSH_NULL                       
                884     LOAD_CONST                      6: '__pyarmor_exit_14555__'
                886     LOAD_CONST                      3: b'<COAddr>\x07\x00\x00\x1a<\x03\x00\x00\x00\x00\x00\x00\x00\x00\x00\x00\x00\x00\x00\x00'
                888     BUILD_TUPLE                     1
                890     CALL_FUNCTION_EX                0
                892     POP_TOP                         
                894     RETURN_VALUE                    
            [Exception Table]
                30 to 100 -> 778 [0] 
                120 to 278 -> 778 [0] 
                300 to 420 -> 778 [0] 
                442 to 758 -> 778 [0] 
                778 to 796 -> 848 [1] lasti
                796 to 828 -> 838 [1] lasti
                828 to 838 -> 854 [0] 
                838 to 848 -> 848 [1] lasti
                848 to 854 -> 854 [0] 
                854 to 876 -> 876 [1] lasti
        [Code]
            File Name: <frozen program.modules.Send_groups>
            Object Name: START
            Qualified Name: START
            Arg Count: 5
            Pos Only Arg Count: 0
            KW Only Arg Count: 0
            Stack Size: 14
            Flags: 0x20000003 (CO_OPTIMIZED | CO_NEWLOCALS | CO_PYARMOR_OBFUSCATED)
            [Names]
                'is_set'
                'StopProgram'
                'check_get_settings'
                'get'
                'os'
                'listdir'
                'path'
                'exists'
                'replace'
                'append'
                'isinstance'
                'list'
                'len'
                'eel'
                'sendErrorBox'
                'Lang'
                'Logs'
                'PrintLog'
                'int'
                'set_task_manager'
                'datetime'
                'now'
                'strftime'
                'db_parsing'
                'import_groups'
                'WriteResult'
                'db_statistic'
                'create'
                'concurrent'
                'futures'
                'ThreadPoolExecutor'
                'StreamStat'
                'json'
                'dumps'
                'submit'
                'worker'
                'as_completed'
                'result'
                'AutoStop'
                'start'
                'Restart_wait'
                'BaseException'
                'logging'
                'del_task_manager'
                'StopDetect'
            [Locals+Names]
                'data'
                'config'
                'pid'
                'proxy'
                'stop_thread'
                '__assert_armored__'
                '_var_var_4'
                '_var_var_5'
                '_var_var_6'
                '_var_var_7'
                '_var_var_8'
                '_var_var_9'
                '_var_var_10'
                '_var_var_11'
                '_var_var_12'
                '_var_var_13'
                '_var_var_14'
                '_var_var_15'
                '_var_var_16'
                '_var_var_17'
                '_var_var_18'
                '_var_var_19'
                '_var_var_20'
                '_var_var_21'
                '_var_var_22'
                '_var_var_23'
                '_var_var_24'
                '_var_var_3'
            [Constants]
                None
                '__pyarmor_assert_14556__'
                '__pyarmor_enter_14557__'
                b'<COAddr>\x05\x00\x00\x1a\xa0\r\x00\x00\x00\x00\x00\x00\x00\x00\x00\x00\x00\x00\x00\x00'
                'Settings'
                'accounts_choose_all'   # b'\x81\xe3\x1b\x10<\xef\xb0\xc6\x08\xc5\x0e\xc8c\xe3\xeb\x800\\\xb7\xab'
                'sessions/active'   # b'\x81\xf1\x1d\x00 \xf3\xb1\xdc\x08\xb5\x0c\xc3x\xe5\xee\x80'
                '.json'
                'sessions/active//'   # b'\x81\xf1\x1d\x00 \xf3\xb1\xdc\x08\xb5\x0c\xc3x\xe5\xee\x80@\x12'
                '.session'
                ''
                'Accounts'
                1
                'select_accounts_works'   # b'\x81\xf1\x1d\x1f6\xf9\xaa\xed\x1a\xf9\x0e\xcfy\xe2\xec\x960J\xb4\xb5\xa1\xd8'
                'sending_time'   # b'\x81\xf1\x1d\x1d7\xf3\xb0\xd5$\xee\x04\xcdi'
                True
                'leave_group'   # b'\x81\xee\x1d\x12%\xff\x81\xd5\t\xf5\x18\xd0'
                'pupsik_settings_error'   # b'\x81\xf2\r\x03 \xf3\xb5\xed\x08\xff\x19\xd4e\xe2\xff\x960X\xa9\xb5\xa5\xd9'
                (
                    'message'
                )
                'pupsik_time_exit'   # b'\x81\xf2\r\x03 \xf3\xb5\xed\x0f\xf3\x00\xc5S\xe9\xe0\x8c\x1b'
                'pupsik_exit_groups'   # b'\x81\xf2\r\x03 \xf3\xb5\xed\x1e\xe2\x04\xd4S\xeb\xea\x8a\x1aM\xa8'
                'pupsik_continue_to_work'   # b'\x81\xf2\r\x03 \xf3\xb5\xed\x18\xf5\x03\xd4e\xe2\xed\x800I\xb4\x98\xbd\xc4\\\xc7'
                False
                'thread_count'   # b'\x81\xf6\x10\x016\xfb\xba\xed\x18\xf5\x18\xcex'
                'thread_rules'   # b'\x81\xf6\x10\x016\xfb\xba\xed\t\xef\x01\xc5\x7f'
                'start_rules'   # b'\x81\xf1\x0c\x12!\xee\x81\xc0\x0e\xf6\x08\xd3'
                'start_count'   # b'\x81\xf1\x0c\x12!\xee\x81\xd1\x14\xef\x03\xd4'
                0
                'stuff'
                (
                    'accounts'
                    'name'
                )
                'launch_no'   # b'\x81\xee\x19\x06=\xf9\xb6\xed\x15\xf5'
                (
                    'message'
                    'param'
                )
                '%Y-%m-%d_%H-%M-%S'   # b'\x81\xa7!^v\xf7\xf3\x97\x1f\xc5H\xe8!\xa9\xd5\xc8Jn'
                'use_data_base'   # b'\x81\xf7\x0b\x16\x0c\xfe\xbf\xc6\x1a\xc5\x0f\xc1\x7f\xe9'
                'additives/send_groups/'   # b'\x81\xe3\x1c\x17:\xee\xb7\xc4\x1e\xe9B\xd3i\xe2\xfc\xba\x08O\xb4\xb2\xba\xd8\x01'
                '_parsing.db'   # b'\x81\xdd\x08\x12!\xe9\xb7\xdc\x1c\xb4\t\xc2'
                'usernames'   # b'\x81\xf7\x0b\x16!\xf4\xbf\xdf\x1e\xe9'
                (
                    'groups'
                )
                'file_db'
                'Database'
                'send_groups'   # b'\x81\xf1\x1d\x1d7\xc5\xb9\xc0\x14\xef\x1d\xd3'
                '_stat_send_groups.db'   # b'\x81\xdd\x0b\x072\xee\x81\xc1\x1e\xf4\t\xffk\xfe\xf7\x90\x1fN\xf5\xa3\xa8'
                'Statistic'   # b"\x81\xd1\x0c\x12'\xf3\xad\xc6\x12\xf9"
                'message'
                'forward'
                'bots'
                'bot'
                'posts'
                'Username @PostBot is not set!'   # b'\x81\xd7\x0b\x16!\xf4\xbf\xdf\x1e\xba-\xf0c\xff\xec\xa7\x00I\xfb\xae\xb9\x8b@\xc3\x11/\xb0Y\x14\xf0'
                (
                    'max_workers'
                )
                'st_task'
                'st_stream'   # b'\x81\xf1\x0c, \xee\xac\xd7\x1a\xf7'
                'st_wait'
                'st_done'
                'completed'   # b'\x81\xe1\x17\x1e#\xf6\xbb\xc6\x1e\xfe'
                (
                    'message'
                    'param'
                    'end'
                )
                'delay_between_launches_activated'   # b'\x81\xe6\x1d\x1f2\xe3\x81\xd0\x1e\xee\x1a\xc5i\xe2\xc7\x89\x0eH\xb5\xa4\xa2\xce]\xf3\x04l\xb7U\x16\xb0\n\xe0>'
                '__pyarmor_exit_14558__'
                'Done'
            [Disassembly]
                0       NOP                             
                2       NOP                             
                4       PUSH_NULL                       
                6       LOAD_CONST                      2: '__pyarmor_enter_14557__'
                8       LOAD_CONST                      3: b'<COAddr>\x05\x00\x00\x1a\xa0\r\x00\x00\x00\x00\x00\x00\x00\x00\x00\x00\x00\x00\x00\x00'
                10      BUILD_TUPLE                     1
                12      CALL_FUNCTION_EX                0
                14      POP_TOP                         
                16      RESUME                          0
                18      NOP                             
                20      NOP                             
                22      NOP                             
                24      NOP                             
                26      NOP                             
                28      NOP                             
                30      LOAD_FAST                       4: stop_thread
                32      LOAD_ATTR                       1: is_set
                52      CALL                            0
                60      POP_JUMP_IF_FALSE               10 (to 82)
                62      LOAD_GLOBAL                     3: NULL + StopProgram
                72      CALL                            0
                80      RAISE_VARARGS                   1
                82      LOAD_GLOBAL                     5: NULL + check_get_settings
                92      LOAD_FAST                       0: data
                94      LOAD_ATTR                       7: get
                114     LOAD_CONST                      4: 'Settings'
                116     CALL                            1
                124     CALL                            1
                132     POP_TOP                         
                134     LOAD_FAST                       0: data
                136     LOAD_CONST                      4: 'Settings'
                138     BINARY_SUBSCR                   
                142     LOAD_ATTR                       7: get
                162     PUSH_NULL                       
                164     LOAD_CONST                      1: '__pyarmor_assert_14556__'
                166     LOAD_CONST                      5: 'accounts_choose_all'   # b'\x81\xe3\x1b\x10<\xef\xb0\xc6\x08\xc5\x0e\xc8c\xe3\xeb\x800\\\xb7\xab'
                168     CALL                            1
                176     CALL                            1
                184     POP_JUMP_IF_FALSE               130 (to 446)
                186     BUILD_LIST                      0
                188     STORE_FAST                      6: _var_var_4
                190     LOAD_GLOBAL                     9: NULL + os
                200     LOAD_ATTR                       10: listdir
                220     PUSH_NULL                       
                222     LOAD_CONST                      1: '__pyarmor_assert_14556__'
                224     LOAD_CONST                      6: 'sessions/active'   # b'\x81\xf1\x1d\x00 \xf3\xb1\xdc\x08\xb5\x0c\xc3x\xe5\xee\x80'
                226     CALL                            1
                234     CALL                            1
                242     GET_ITER                        
                244     FOR_ITER                        97 (to 440)
                248     STORE_FAST                      7: _var_var_5
                250     LOAD_CONST                      7: '.json'
                252     LOAD_FAST                       7: _var_var_5
                254     CONTAINS_OP                     0 (in)
                256     POP_JUMP_IF_TRUE                1 (to 260)
                258     JUMP_BACKWARD                   8 (to 244)
                260     LOAD_GLOBAL                     8: os
                270     LOAD_ATTR                       12: path
                290     LOAD_ATTR                       15: exists
                310     PUSH_NULL                       
                312     LOAD_CONST                      1: '__pyarmor_assert_14556__'
                314     LOAD_CONST                      8: 'sessions/active//'   # b'\x81\xf1\x1d\x00 \xf3\xb1\xdc\x08\xb5\x0c\xc3x\xe5\xee\x80@\x12'
                316     CALL                            1
                324     LOAD_FAST                       7: _var_var_5
                326     LOAD_ATTR                       17: replace
                346     LOAD_CONST                      7: '.json'
                348     LOAD_CONST                      9: '.session'
                350     CALL                            2
                358     FORMAT_VALUE                    0 (FVC_NONE)
                360     BUILD_STRING                    2
                362     CALL                            1
                370     POP_JUMP_IF_TRUE                1 (to 374)
                372     JUMP_BACKWARD                   65 (to 244)
                374     LOAD_FAST                       6: _var_var_4
                376     LOAD_ATTR                       19: append
                396     LOAD_FAST                       7: _var_var_5
                398     LOAD_ATTR                       17: replace
                418     LOAD_CONST                      7: '.json'
                420     LOAD_CONST                      10: ''
                422     CALL                            2
                430     CALL                            1
                438     POP_TOP                         
                440     JUMP_BACKWARD                   99 (to 244)
                442     END_FOR                         
                444     JUMP_FORWARD                    24 (to 494)
                446     LOAD_FAST                       0: data
                448     LOAD_CONST                      11: 'Accounts'
                450     BINARY_SUBSCR                   
                454     STORE_FAST                      6: _var_var_4
                456     LOAD_GLOBAL                     21: NULL + isinstance
                466     LOAD_FAST                       6: _var_var_4
                468     LOAD_GLOBAL                     22: list
                478     CALL                            2
                486     POP_JUMP_IF_TRUE                3 (to 494)
                488     LOAD_FAST                       6: _var_var_4
                490     BUILD_LIST                      1
                492     STORE_FAST                      6: _var_var_4
                494     LOAD_GLOBAL                     25: NULL + len
                504     LOAD_FAST                       6: _var_var_4
                506     CALL                            1
                514     LOAD_CONST                      12: 1
                516     COMPARE_OP                      2 (<)
                520     POP_JUMP_IF_FALSE               44 (to 610)
                522     LOAD_GLOBAL                     27: NULL + eel
                532     LOAD_ATTR                       28: sendErrorBox
                552     LOAD_GLOBAL                     30: Lang
                562     PUSH_NULL                       
                564     LOAD_CONST                      1: '__pyarmor_assert_14556__'
                566     LOAD_CONST                      13: 'select_accounts_works'   # b'\x81\xf1\x1d\x1f6\xf9\xaa\xed\x1a\xf9\x0e\xcfy\xe2\xec\x960J\xb4\xb5\xa1\xd8'
                568     CALL                            1
                576     BINARY_SUBSCR                   
                580     CALL                            1
                588     POP_TOP                         
                590     LOAD_GLOBAL                     3: NULL + StopProgram
                600     CALL                            0
                608     RAISE_VARARGS                   1
                610     LOAD_FAST                       0: data
                612     LOAD_CONST                      4: 'Settings'
                614     BINARY_SUBSCR                   
                618     LOAD_ATTR                       7: get
                638     PUSH_NULL                       
                640     LOAD_CONST                      1: '__pyarmor_assert_14556__'
                642     LOAD_CONST                      14: 'sending_time'   # b'\x81\xf1\x1d\x1d7\xf3\xb0\xd5$\xee\x04\xcdi'
                644     CALL                            1
                652     CALL                            1
                660     LOAD_CONST                      15: True
                662     COMPARE_OP                      40 (==)
                666     POP_JUMP_IF_FALSE               183 (to 1034)
                668     LOAD_FAST                       0: data
                670     LOAD_CONST                      4: 'Settings'
                672     BINARY_SUBSCR                   
                676     LOAD_ATTR                       7: get
                696     PUSH_NULL                       
                698     LOAD_CONST                      1: '__pyarmor_assert_14556__'
                700     LOAD_CONST                      16: 'leave_group'   # b'\x81\xee\x1d\x12%\xff\x81\xd5\t\xf5\x18\xd0'
                702     CALL                            1
                710     CALL                            1
                718     LOAD_CONST                      15: True
                720     COMPARE_OP                      40 (==)
                724     POP_JUMP_IF_FALSE               154 (to 1034)
                726     LOAD_GLOBAL                     33: NULL + Logs
                736     LOAD_ATTR                       34: PrintLog
                756     LOAD_GLOBAL                     30: Lang
                766     PUSH_NULL                       
                768     LOAD_CONST                      1: '__pyarmor_assert_14556__'
                770     LOAD_CONST                      17: 'pupsik_settings_error'   # b'\x81\xf2\r\x03 \xf3\xb5\xed\x08\xff\x19\xd4e\xe2\xff\x960X\xa9\xb5\xa5\xd9'
                772     CALL                            1
                780     BINARY_SUBSCR                   
                784     KW_NAMES                        18: ('message',)
                786     CALL                            1
                794     POP_TOP                         
                796     LOAD_GLOBAL                     33: NULL + Logs
                806     LOAD_ATTR                       34: PrintLog
                826     LOAD_GLOBAL                     30: Lang
                836     PUSH_NULL                       
                838     LOAD_CONST                      1: '__pyarmor_assert_14556__'
                840     LOAD_CONST                      19: 'pupsik_time_exit'   # b'\x81\xf2\r\x03 \xf3\xb5\xed\x0f\xf3\x00\xc5S\xe9\xe0\x8c\x1b'
                842     CALL                            1
                850     BINARY_SUBSCR                   
                854     KW_NAMES                        18: ('message',)
                856     CALL                            1
                864     POP_TOP                         
                866     LOAD_GLOBAL                     33: NULL + Logs
                876     LOAD_ATTR                       34: PrintLog
                896     LOAD_GLOBAL                     30: Lang
                906     PUSH_NULL                       
                908     LOAD_CONST                      1: '__pyarmor_assert_14556__'
                910     LOAD_CONST                      20: 'pupsik_exit_groups'   # b'\x81\xf2\r\x03 \xf3\xb5\xed\x1e\xe2\x04\xd4S\xeb\xea\x8a\x1aM\xa8'
                912     CALL                            1
                920     BINARY_SUBSCR                   
                924     KW_NAMES                        18: ('message',)
                926     CALL                            1
                934     POP_TOP                         
                936     LOAD_GLOBAL                     33: NULL + Logs
                946     LOAD_ATTR                       34: PrintLog
                966     LOAD_GLOBAL                     30: Lang
                976     PUSH_NULL                       
                978     LOAD_CONST                      1: '__pyarmor_assert_14556__'
                980     LOAD_CONST                      21: 'pupsik_continue_to_work'   # b'\x81\xf2\r\x03 \xf3\xb5\xed\x18\xf5\x03\xd4e\xe2\xed\x800I\xb4\x98\xbd\xc4\\\xc7'
                982     CALL                            1
                990     BINARY_SUBSCR                   
                994     KW_NAMES                        18: ('message',)
                996     CALL                            1
                1004    POP_TOP                         
                1006    LOAD_CONST                      22: False
                1008    LOAD_FAST                       0: data
                1010    LOAD_CONST                      4: 'Settings'
                1012    BINARY_SUBSCR                   
                1016    PUSH_NULL                       
                1018    LOAD_CONST                      1: '__pyarmor_assert_14556__'
                1020    LOAD_CONST                      16: 'leave_group'   # b'\x81\xee\x1d\x12%\xff\x81\xd5\t\xf5\x18\xd0'
                1022    CALL                            1
                1030    STORE_SUBSCR                    
                1034    LOAD_FAST                       1: config
                1036    PUSH_NULL                       
                1038    LOAD_CONST                      1: '__pyarmor_assert_14556__'
                1040    LOAD_CONST                      23: 'thread_count'   # b'\x81\xf6\x10\x016\xfb\xba\xed\x18\xf5\x18\xcex'
                1042    CALL                            1
                1050    BINARY_SUBSCR                   
                1054    STORE_FAST                      8: _var_var_6
                1056    LOAD_FAST                       0: data
                1058    LOAD_CONST                      4: 'Settings'
                1060    BINARY_SUBSCR                   
                1064    LOAD_ATTR                       7: get
                1084    PUSH_NULL                       
                1086    LOAD_CONST                      1: '__pyarmor_assert_14556__'
                1088    LOAD_CONST                      24: 'thread_rules'   # b'\x81\xf6\x10\x016\xfb\xba\xed\t\xef\x01\xc5\x7f'
                1090    CALL                            1
                1098    CALL                            1
                1106    POP_JUMP_IF_FALSE               35 (to 1178)
                1108    LOAD_GLOBAL                     37: NULL + int
                1118    LOAD_FAST                       0: data
                1120    LOAD_CONST                      4: 'Settings'
                1122    BINARY_SUBSCR                   
                1126    LOAD_ATTR                       7: get
                1146    PUSH_NULL                       
                1148    LOAD_CONST                      1: '__pyarmor_assert_14556__'
                1150    LOAD_CONST                      23: 'thread_count'   # b'\x81\xf6\x10\x016\xfb\xba\xed\x18\xf5\x18\xcex'
                1152    CALL                            1
                1160    CALL                            1
                1168    CALL                            1
                1176    STORE_FAST                      8: _var_var_6
                1178    LOAD_CONST                      12: 1
                1180    STORE_FAST                      9: _var_var_7
                1182    LOAD_FAST                       0: data
                1184    LOAD_CONST                      4: 'Settings'
                1186    BINARY_SUBSCR                   
                1190    LOAD_ATTR                       7: get
                1210    PUSH_NULL                       
                1212    LOAD_CONST                      1: '__pyarmor_assert_14556__'
                1214    LOAD_CONST                      25: 'start_rules'   # b'\x81\xf1\x0c\x12!\xee\x81\xc0\x0e\xf6\x08\xd3'
                1216    CALL                            1
                1224    CALL                            1
                1232    POP_JUMP_IF_FALSE               35 (to 1304)
                1234    LOAD_GLOBAL                     37: NULL + int
                1244    LOAD_FAST                       0: data
                1246    LOAD_CONST                      4: 'Settings'
                1248    BINARY_SUBSCR                   
                1252    LOAD_ATTR                       7: get
                1272    PUSH_NULL                       
                1274    LOAD_CONST                      1: '__pyarmor_assert_14556__'
                1276    LOAD_CONST                      26: 'start_count'   # b'\x81\xf1\x0c\x12!\xee\x81\xd1\x14\xef\x03\xd4'
                1278    CALL                            1
                1286    CALL                            1
                1294    CALL                            1
                1302    STORE_FAST                      9: _var_var_7
                1304    LOAD_CONST                      27: 0
                1306    STORE_FAST                      10: _var_var_8
                1308    LOAD_GLOBAL                     39: NULL + set_task_manager
                1318    LOAD_FAST                       2: pid
                1320    LOAD_FAST                       6: _var_var_4
                1322    LOAD_FAST                       0: data
                1324    LOAD_CONST                      28: 'stuff'
                1326    BINARY_SUBSCR                   
                1330    KW_NAMES                        29: ('accounts', 'name')
                1332    CALL                            3
                1340    POP_TOP                         
                1342    LOAD_FAST                       10: _var_var_8
                1344    LOAD_FAST                       9: _var_var_7
                1346    COMPARE_OP                      2 (<)
                1350    POP_JUMP_IF_FALSE               949 (to 3252)
                1354    LOAD_FAST                       10: _var_var_8
                1356    LOAD_CONST                      12: 1
                1358    BINARY_OP                       13 (+=)
                1362    STORE_FAST                      10: _var_var_8
                1364    LOAD_FAST                       4: stop_thread
                1366    LOAD_ATTR                       1: is_set
                1386    CALL                            0
                1394    POP_JUMP_IF_FALSE               10 (to 1416)
                1396    LOAD_GLOBAL                     3: NULL + StopProgram
                1406    CALL                            0
                1414    RAISE_VARARGS                   1
                1416    LOAD_FAST                       9: _var_var_7
                1418    LOAD_CONST                      12: 1
                1420    COMPARE_OP                      68 (>)
                1424    POP_JUMP_IF_FALSE               36 (to 1498)
                1426    LOAD_GLOBAL                     33: NULL + Logs
                1436    LOAD_ATTR                       34: PrintLog
                1456    LOAD_GLOBAL                     30: Lang
                1466    PUSH_NULL                       
                1468    LOAD_CONST                      1: '__pyarmor_assert_14556__'
                1470    LOAD_CONST                      30: 'launch_no'   # b'\x81\xee\x19\x06=\xf9\xb6\xed\x15\xf5'
                1472    CALL                            1
                1480    BINARY_SUBSCR                   
                1484    LOAD_FAST                       10: _var_var_8
                1486    KW_NAMES                        31: ('message', 'param')
                1488    CALL                            2
                1496    POP_TOP                         
                1498    LOAD_GLOBAL                     40: datetime
                1508    LOAD_ATTR                       40: datetime
                1528    LOAD_ATTR                       43: now
                1548    CALL                            0
                1556    LOAD_ATTR                       45: strftime
                1576    PUSH_NULL                       
                1578    LOAD_CONST                      1: '__pyarmor_assert_14556__'
                1580    LOAD_CONST                      32: '%Y-%m-%d_%H-%M-%S'   # b'\x81\xa7!^v\xf7\xf3\x97\x1f\xc5H\xe8!\xa9\xd5\xc8Jn'
                1582    CALL                            1
                1590    CALL                            1
                1598    STORE_FAST                      11: _var_var_9
                1600    LOAD_FAST                       0: data
                1602    LOAD_CONST                      4: 'Settings'
                1604    BINARY_SUBSCR                   
                1608    PUSH_NULL                       
                1610    LOAD_CONST                      1: '__pyarmor_assert_14556__'
                1612    LOAD_CONST                      33: 'use_data_base'   # b'\x81\xf7\x0b\x16\x0c\xfe\xbf\xc6\x1a\xc5\x0f\xc1\x7f\xe9'
                1614    CALL                            1
                1622    BINARY_SUBSCR                   
                1626    LOAD_CONST                      22: False
                1628    COMPARE_OP                      40 (==)
                1632    POP_JUMP_IF_FALSE               159 (to 1952)
                1634    LOAD_GLOBAL                     47: NULL + db_parsing
                1644    PUSH_NULL                       
                1646    LOAD_CONST                      1: '__pyarmor_assert_14556__'
                1648    LOAD_CONST                      34: 'additives/send_groups/'   # b'\x81\xe3\x1c\x17:\xee\xb7\xc4\x1e\xe9B\xd3i\xe2\xfc\xba\x08O\xb4\xb2\xba\xd8\x01'
                1650    CALL                            1
                1658    LOAD_FAST                       11: _var_var_9
                1660    FORMAT_VALUE                    0 (FVC_NONE)
                1662    PUSH_NULL                       
                1664    LOAD_CONST                      1: '__pyarmor_assert_14556__'
                1666    LOAD_CONST                      35: '_parsing.db'   # b'\x81\xdd\x08\x12!\xe9\xb7\xdc\x1c\xb4\t\xc2'
                1668    CALL                            1
                1676    BUILD_STRING                    3
                1678    CALL                            1
                1686    LOAD_ATTR                       49: import_groups
                1706    LOAD_FAST                       0: data
                1708    LOAD_CONST                      4: 'Settings'
                1710    BINARY_SUBSCR                   
                1714    LOAD_ATTR                       7: get
                1734    PUSH_NULL                       
                1736    LOAD_CONST                      1: '__pyarmor_assert_14556__'
                1738    LOAD_CONST                      36: 'usernames'   # b'\x81\xf7\x0b\x16!\xf4\xbf\xdf\x1e\xe9'
                1740    CALL                            1
                1748    CALL                            1
                1756    KW_NAMES                        37: ('groups',)
                1758    CALL                            1
                1766    STORE_FAST                      12: _var_var_10
                1768    LOAD_FAST                       12: _var_var_10
                1770    POP_JUMP_IF_TRUE                44 (to 1860)
                1772    LOAD_GLOBAL                     27: NULL + eel
                1782    LOAD_ATTR                       28: sendErrorBox
                1802    LOAD_GLOBAL                     30: Lang
                1812    PUSH_NULL                       
                1814    LOAD_CONST                      1: '__pyarmor_assert_14556__'
                1816    LOAD_CONST                      13: 'select_accounts_works'   # b'\x81\xf1\x1d\x1f6\xf9\xaa\xed\x1a\xf9\x0e\xcfy\xe2\xec\x960J\xb4\xb5\xa1\xd8'
                1818    CALL                            1
                1826    BINARY_SUBSCR                   
                1830    CALL                            1
                1838    POP_TOP                         
                1840    LOAD_GLOBAL                     3: NULL + StopProgram
                1850    CALL                            0
                1858    RAISE_VARARGS                   1
                1860    LOAD_FAST                       12: _var_var_10
                1862    LOAD_FAST                       0: data
                1864    LOAD_CONST                      4: 'Settings'
                1866    BINARY_SUBSCR                   
                1870    LOAD_CONST                      38: 'file_db'
                1872    STORE_SUBSCR                    
                1876    LOAD_GLOBAL                     27: NULL + eel
                1886    LOAD_ATTR                       50: WriteResult
                1906    LOAD_CONST                      39: 'Database'
                1908    PUSH_NULL                       
                1910    LOAD_CONST                      1: '__pyarmor_assert_14556__'
                1912    LOAD_CONST                      40: 'send_groups'   # b'\x81\xf1\x1d\x1d7\xc5\xb9\xc0\x14\xef\x1d\xd3'
                1914    CALL                            1
                1922    LOAD_FAST                       11: _var_var_9
                1924    FORMAT_VALUE                    0 (FVC_NONE)
                1926    PUSH_NULL                       
                1928    LOAD_CONST                      1: '__pyarmor_assert_14556__'
                1930    LOAD_CONST                      35: '_parsing.db'   # b'\x81\xdd\x08\x12!\xe9\xb7\xdc\x1c\xb4\t\xc2'
                1932    CALL                            1
                1940    BUILD_STRING                    2
                1942    CALL                            3
                1950    POP_TOP                         
                1952    LOAD_GLOBAL                     53: NULL + db_statistic
                1962    PUSH_NULL                       
                1964    LOAD_CONST                      1: '__pyarmor_assert_14556__'
                1966    LOAD_CONST                      34: 'additives/send_groups/'   # b'\x81\xe3\x1c\x17:\xee\xb7\xc4\x1e\xe9B\xd3i\xe2\xfc\xba\x08O\xb4\xb2\xba\xd8\x01'
                1968    CALL                            1
                1976    LOAD_FAST                       11: _var_var_9
                1978    FORMAT_VALUE                    0 (FVC_NONE)
                1980    PUSH_NULL                       
                1982    LOAD_CONST                      1: '__pyarmor_assert_14556__'
                1984    LOAD_CONST                      41: '_stat_send_groups.db'   # b'\x81\xdd\x0b\x072\xee\x81\xc1\x1e\xf4\t\xffk\xfe\xf7\x90\x1fN\xf5\xa3\xa8'
                1986    CALL                            1
                1994    BUILD_STRING                    3
                1996    CALL                            1
                2004    LOAD_ATTR                       55: create
                2024    CALL                            0
                2032    STORE_FAST                      13: _var_var_11
                2034    LOAD_GLOBAL                     27: NULL + eel
                2044    LOAD_ATTR                       50: WriteResult
                2064    PUSH_NULL                       
                2066    LOAD_CONST                      1: '__pyarmor_assert_14556__'
                2068    LOAD_CONST                      42: 'Statistic'   # b"\x81\xd1\x0c\x12'\xf3\xad\xc6\x12\xf9"
                2070    CALL                            1
                2078    PUSH_NULL                       
                2080    LOAD_CONST                      1: '__pyarmor_assert_14556__'
                2082    LOAD_CONST                      40: 'send_groups'   # b'\x81\xf1\x1d\x1d7\xc5\xb9\xc0\x14\xef\x1d\xd3'
                2084    CALL                            1
                2092    LOAD_FAST                       11: _var_var_9
                2094    FORMAT_VALUE                    0 (FVC_NONE)
                2096    PUSH_NULL                       
                2098    LOAD_CONST                      1: '__pyarmor_assert_14556__'
                2100    LOAD_CONST                      41: '_stat_send_groups.db'   # b'\x81\xdd\x0b\x072\xee\x81\xc1\x1e\xf4\t\xffk\xfe\xf7\x90\x1fN\xf5\xa3\xa8'
                2102    CALL                            1
                2110    BUILD_STRING                    2
                2112    CALL                            3
                2120    POP_TOP                         
                2122    LOAD_FAST                       0: data
                2124    LOAD_CONST                      4: 'Settings'
                2126    BINARY_SUBSCR                   
                2130    LOAD_CONST                      43: 'message'
                2132    BINARY_SUBSCR                   
                2136    LOAD_ATTR                       7: get
                2156    LOAD_CONST                      44: 'forward'
                2158    CALL                            1
                2166    STORE_FAST                      14: _var_var_12
                2168    LOAD_GLOBAL                     25: NULL + len
                2178    LOAD_FAST                       14: _var_var_12
                2180    CALL                            1
                2188    LOAD_CONST                      27: 0
                2190    COMPARE_OP                      68 (>)
                2194    POP_JUMP_IF_FALSE               3 (to 2202)
                2196    LOAD_CONST                      15: True
                2198    STORE_FAST                      14: _var_var_12
                2200    JUMP_FORWARD                    2 (to 2206)
                2202    LOAD_CONST                      22: False
                2204    STORE_FAST                      14: _var_var_12
                2206    LOAD_FAST                       0: data
                2208    LOAD_CONST                      4: 'Settings'
                2210    BINARY_SUBSCR                   
                2214    LOAD_CONST                      43: 'message'
                2216    BINARY_SUBSCR                   
                2220    LOAD_CONST                      45: 'bots'
                2222    BINARY_SUBSCR                   
                2226    LOAD_ATTR                       7: get
                2246    LOAD_CONST                      46: 'bot'
                2248    CALL                            1
                2256    STORE_FAST                      15: _var_var_13
                2258    LOAD_FAST                       0: data
                2260    LOAD_CONST                      4: 'Settings'
                2262    BINARY_SUBSCR                   
                2266    LOAD_CONST                      43: 'message'
                2268    BINARY_SUBSCR                   
                2272    LOAD_CONST                      45: 'bots'
                2274    BINARY_SUBSCR                   
                2278    LOAD_ATTR                       7: get
                2298    LOAD_CONST                      47: 'posts'
                2300    CALL                            1
                2308    STORE_FAST                      16: _var_var_14
                2310    LOAD_GLOBAL                     25: NULL + len
                2320    LOAD_FAST                       16: _var_var_14
                2322    CALL                            1
                2330    LOAD_CONST                      27: 0
                2332    COMPARE_OP                      68 (>)
                2336    POP_JUMP_IF_FALSE               40 (to 2418)
                2338    LOAD_FAST                       15: _var_var_13
                2340    POP_JUMP_IF_TRUE                38 (to 2418)
                2342    LOAD_GLOBAL                     33: NULL + Logs
                2352    LOAD_ATTR                       34: PrintLog
                2372    PUSH_NULL                       
                2374    LOAD_CONST                      1: '__pyarmor_assert_14556__'
                2376    LOAD_CONST                      48: 'Username @PostBot is not set!'   # b'\x81\xd7\x0b\x16!\xf4\xbf\xdf\x1e\xba-\xf0c\xff\xec\xa7\x00I\xfb\xae\xb9\x8b@\xc3\x11/\xb0Y\x14\xf0'
                2378    CALL                            1
                2386    KW_NAMES                        18: ('message',)
                2388    CALL                            1
                2396    POP_TOP                         
                2398    LOAD_GLOBAL                     3: NULL + StopProgram
                2408    CALL                            0
                2416    RAISE_VARARGS                   1
                2418    LOAD_GLOBAL                     56: concurrent
                2428    LOAD_ATTR                       58: futures
                2448    LOAD_ATTR                       61: ThreadPoolExecutor
                2468    LOAD_FAST                       8: _var_var_6
                2470    KW_NAMES                        49: ('max_workers',)
                2472    CALL                            1
                2480    BEFORE_WITH                     
                2482    STORE_FAST                      17: _var_var_15
                2484    LOAD_GLOBAL                     25: NULL + len
                2494    LOAD_FAST                       6: _var_var_4
                2496    CALL                            1
                2504    STORE_FAST                      18: _var_var_16
                2506    LOAD_FAST                       8: _var_var_6
                2508    STORE_FAST                      19: _var_var_17
                2510    LOAD_FAST                       18: _var_var_16
                2512    STORE_FAST                      20: _var_var_18
                2514    LOAD_CONST                      27: 0
                2516    STORE_FAST                      21: _var_var_19
                2518    LOAD_GLOBAL                     27: NULL + eel
                2528    LOAD_ATTR                       62: StreamStat
                2548    LOAD_GLOBAL                     65: NULL + json
                2558    LOAD_ATTR                       66: dumps
                2578    LOAD_CONST                      50: 'st_task'
                2580    LOAD_FAST                       18: _var_var_16
                2582    PUSH_NULL                       
                2584    LOAD_CONST                      1: '__pyarmor_assert_14556__'
                2586    LOAD_CONST                      51: 'st_stream'   # b'\x81\xf1\x0c, \xee\xac\xd7\x1a\xf7'
                2588    CALL                            1
                2596    LOAD_FAST                       19: _var_var_17
                2598    LOAD_CONST                      52: 'st_wait'
                2600    LOAD_FAST                       20: _var_var_18
                2602    LOAD_CONST                      53: 'st_done'
                2604    LOAD_FAST                       21: _var_var_19
                2606    BUILD_MAP                       4
                2608    CALL                            1
                2616    CALL                            1
                2624    POP_TOP                         
                2626    BUILD_LIST                      0
                2628    STORE_FAST                      22: _var_var_20
                2630    LOAD_FAST                       6: _var_var_4
                2632    GET_ITER                        
                2634    FOR_ITER                        44 (to 2724)
                2638    STORE_FAST                      23: _var_var_21
                2640    LOAD_FAST                       22: _var_var_20
                2642    LOAD_ATTR                       19: append
                2662    LOAD_FAST                       17: _var_var_15
                2664    LOAD_ATTR                       69: submit
                2684    LOAD_GLOBAL                     70: worker
                2694    LOAD_FAST                       23: _var_var_21
                2696    LOAD_FAST                       1: config
                2698    LOAD_FAST                       3: proxy
                2700    LOAD_FAST                       0: data
                2702    LOAD_FAST                       13: _var_var_11
                2704    LOAD_FAST                       4: stop_thread
                2706    CALL                            7
                2714    CALL                            1
                2722    POP_TOP                         
                2724    JUMP_BACKWARD                   46 (to 2634)
                2726    END_FOR                         
                2728    BUILD_LIST                      0
                2730    STORE_FAST                      24: _var_var_22
                2732    LOAD_GLOBAL                     56: concurrent
                2742    LOAD_ATTR                       58: futures
                2762    LOAD_ATTR                       73: as_completed
                2782    LOAD_FAST                       22: _var_var_20
                2784    CALL                            1
                2792    GET_ITER                        
                2794    FOR_ITER                        110 (to 3016)
                2798    STORE_FAST                      25: _var_var_23
                2800    LOAD_FAST                       21: _var_var_19
                2802    LOAD_CONST                      12: 1
                2804    BINARY_OP                       13 (+=)
                2808    STORE_FAST                      21: _var_var_19
                2810    LOAD_FAST                       20: _var_var_18
                2812    LOAD_CONST                      12: 1
                2814    BINARY_OP                       23 (-=)
                2818    STORE_FAST                      20: _var_var_18
                2820    LOAD_GLOBAL                     27: NULL + eel
                2830    LOAD_ATTR                       62: StreamStat
                2850    LOAD_GLOBAL                     65: NULL + json
                2860    LOAD_ATTR                       66: dumps
                2880    LOAD_CONST                      50: 'st_task'
                2882    LOAD_FAST                       18: _var_var_16
                2884    PUSH_NULL                       
                2886    LOAD_CONST                      1: '__pyarmor_assert_14556__'
                2888    LOAD_CONST                      51: 'st_stream'   # b'\x81\xf1\x0c, \xee\xac\xd7\x1a\xf7'
                2890    CALL                            1
                2898    LOAD_FAST                       19: _var_var_17
                2900    LOAD_CONST                      52: 'st_wait'
                2902    LOAD_FAST                       20: _var_var_18
                2904    LOAD_CONST                      53: 'st_done'
                2906    LOAD_FAST                       21: _var_var_19
                2908    BUILD_MAP                       4
                2910    CALL                            1
                2918    CALL                            1
                2926    POP_TOP                         
                2928    LOAD_FAST                       25: _var_var_23
                2930    LOAD_ATTR                       75: result
                2950    CALL                            0
                2958    STORE_FAST                      26: _var_var_24
                2960    LOAD_GLOBAL                     77: NULL + AutoStop
                2970    LOAD_FAST                       26: _var_var_24
                2972    LOAD_FAST                       24: _var_var_22
                2974    LOAD_FAST                       0: data
                2976    LOAD_FAST                       4: stop_thread
                2978    CALL                            4
                2986    LOAD_ATTR                       79: start
                3006    CALL                            0
                3014    STORE_FAST                      24: _var_var_22
                3016    JUMP_BACKWARD                   112 (to 2794)
                3018    END_FOR                         
                3020    NOP                             
                3022    LOAD_CONST                      0: None
                3024    LOAD_CONST                      0: None
                3026    LOAD_CONST                      0: None
                3028    CALL                            2
                3036    POP_TOP                         
                3038    LOAD_FAST                       9: _var_var_7
                3040    LOAD_CONST                      12: 1
                3042    COMPARE_OP                      68 (>)
                3046    POP_JUMP_IF_FALSE               95 (to 3238)
                3048    LOAD_GLOBAL                     33: NULL + Logs
                3058    LOAD_ATTR                       34: PrintLog
                3078    LOAD_GLOBAL                     30: Lang
                3088    PUSH_NULL                       
                3090    LOAD_CONST                      1: '__pyarmor_assert_14556__'
                3092    LOAD_CONST                      30: 'launch_no'   # b'\x81\xee\x19\x06=\xf9\xb6\xed\x15\xf5'
                3094    CALL                            1
                3102    BINARY_SUBSCR                   
                3106    LOAD_FAST                       10: _var_var_8
                3108    PUSH_NULL                       
                3110    LOAD_CONST                      1: '__pyarmor_assert_14556__'
                3112    LOAD_CONST                      54: 'completed'   # b'\x81\xe1\x17\x1e#\xf6\xbb\xc6\x1e\xfe'
                3114    CALL                            1
                3122    KW_NAMES                        55: ('message', 'param', 'end')
                3124    CALL                            3
                3132    POP_TOP                         
                3134    LOAD_FAST                       10: _var_var_8
                3136    LOAD_FAST                       9: _var_var_7
                3138    COMPARE_OP                      55 (!=)
                3142    POP_JUMP_IF_FALSE               47 (to 3238)
                3144    LOAD_GLOBAL                     33: NULL + Logs
                3154    LOAD_ATTR                       34: PrintLog
                3174    LOAD_GLOBAL                     30: Lang
                3184    PUSH_NULL                       
                3186    LOAD_CONST                      1: '__pyarmor_assert_14556__'
                3188    LOAD_CONST                      56: 'delay_between_launches_activated'   # b'\x81\xe6\x1d\x1f2\xe3\x81\xd0\x1e\xee\x1a\xc5i\xe2\xc7\x89\x0eH\xb5\xa4\xa2\xce]\xf3\x04l\xb7U\x16\xb0\n\xe0>'
                3190    CALL                            1
                3198    BINARY_SUBSCR                   
                3202    KW_NAMES                        18: ('message',)
                3204    CALL                            1
                3212    POP_TOP                         
                3214    LOAD_GLOBAL                     81: NULL + Restart_wait
                3224    LOAD_FAST                       0: data
                3226    LOAD_FAST                       4: stop_thread
                3228    CALL                            2
                3236    POP_TOP                         
                3238    LOAD_FAST                       10: _var_var_8
                3240    LOAD_FAST                       9: _var_var_7
                3242    COMPARE_OP                      2 (<)
                3246    POP_JUMP_IF_FALSE               2 (to 3252)
                3248    JUMP_BACKWARD                   949 (to 1354)
                3252    LOAD_GLOBAL                     87: NULL + del_task_manager
                3262    LOAD_FAST                       2: pid
                3264    CALL                            1
                3272    POP_TOP                         
                3274    LOAD_GLOBAL                     89: NULL + StopDetect
                3284    LOAD_FAST                       4: stop_thread
                3286    CALL                            1
                3294    POP_TOP                         
                3296    NOP                             
                3298    LOAD_CONST                      58: 'Done'
                3300    NOP                             
                3302    NOP                             
                3304    NOP                             
                3306    JUMP_FORWARD                    117 (to 3542)
                3314    POP_TOP                         
                3316    RETURN_CONST                    58: 'Done'
                3318    PUSH_EXC_INFO                   
                3320    WITH_EXCEPT_START               
                3322    POP_JUMP_IF_TRUE                1 (to 3326)
                3324    RERAISE                         2
                3326    POP_TOP                         
                3328    POP_EXCEPT                      
                3330    POP_TOP                         
                3332    POP_TOP                         
                3334    JUMP_BACKWARD                   149 (to 3038)
                3336    COPY                            3
                3338    POP_EXCEPT                      
                3340    RERAISE                         1
                3342    PUSH_EXC_INFO                   
                3344    LOAD_GLOBAL                     2: StopProgram
                3354    CHECK_EXC_MATCH                 
                3356    POP_JUMP_IF_FALSE               3 (to 3364)
                3358    POP_TOP                         
                3360    POP_EXCEPT                      
                3362    JUMP_BACKWARD                   56 (to 3252)
                3364    LOAD_GLOBAL                     82: BaseException
                3374    CHECK_EXC_MATCH                 
                3376    POP_JUMP_IF_FALSE               26 (to 3430)
                3378    STORE_FAST                      27: _var_var_3
                3380    PUSH_NULL                       
                3382    LOAD_GLOBAL                     85: NULL + logging
                3392    LOAD_FAST                       27: _var_var_3
                3394    CALL                            1
                3402    CALL                            0
                3410    POP_TOP                         
                3412    POP_EXCEPT                      
                3414    LOAD_CONST                      0: None
                3416    STORE_FAST                      27: _var_var_3
                3418    DELETE_FAST                     27: _var_var_3
                3420    JUMP_BACKWARD                   85 (to 3252)
                3422    LOAD_CONST                      0: None
                3424    STORE_FAST                      27: _var_var_3
                3426    DELETE_FAST                     27: _var_var_3
                3428    RERAISE                         1
                3430    RERAISE                         0
                3432    COPY                            3
                3434    POP_EXCEPT                      
                3436    RERAISE                         1
                3438    PUSH_EXC_INFO                   
                3440    LOAD_GLOBAL                     87: NULL + del_task_manager
                3450    LOAD_FAST                       2: pid
                3452    CALL                            1
                3460    POP_TOP                         
                3462    LOAD_GLOBAL                     89: NULL + StopDetect
                3472    LOAD_FAST                       4: stop_thread
                3474    CALL                            1
                3482    POP_TOP                         
                3484    POP_TOP                         
                3486    POP_EXCEPT                      
                3488    LOAD_CONST                      58: 'Done'
                3490    NOP                             
                3492    NOP                             
                3494    NOP                             
                3496    JUMP_FORWARD                    22 (to 3542)
                3504    POP_TOP                         
                3506    RETURN_CONST                    58: 'Done'
                3508    COPY                            3
                3510    POP_EXCEPT                      
                3512    RERAISE                         1
                3514    PUSH_EXC_INFO                   
                3516    PUSH_NULL                       
                3518    LOAD_CONST                      57: '__pyarmor_exit_14558__'
                3520    NOP                             
                3522    LOAD_CONST                      3: b'<COAddr>\x05\x00\x00\x1a\xa0\r\x00\x00\x00\x00\x00\x00\x00\x00\x00\x00\x00\x00\x00\x00'
                3524    CALL                            1
                3532    POP_TOP                         
                3534    RERAISE                         0
                3536    COPY                            3
                3538    POP_EXCEPT                      
                3540    RERAISE                         1
                3542    PUSH_NULL                       
                3544    LOAD_CONST                      57: '__pyarmor_exit_14558__'
                3546    LOAD_CONST                      3: b'<COAddr>\x05\x00\x00\x1a\xa0\r\x00\x00\x00\x00\x00\x00\x00\x00\x00\x00\x00\x00\x00\x00'
                3548    BUILD_TUPLE                     1
                3550    CALL_FUNCTION_EX                0
                3552    POP_TOP                         
                3554    RETURN_VALUE                    
            [Exception Table]
                30 to 258 -> 3342 [0] 
                260 to 372 -> 3342 [0] 
                374 to 2482 -> 3342 [0] 
                2482 to 3020 -> 3318 [1] lasti
                3022 to 3248 -> 3342 [0] 
                3252 to 3296 -> 3514 [0] 
                3318 to 3328 -> 3336 [3] lasti
                3328 to 3342 -> 3342 [0] 
                3342 to 3360 -> 3432 [1] lasti
                3360 to 3364 -> 3438 [0] 
                3364 to 3380 -> 3432 [1] lasti
                3380 to 3412 -> 3422 [1] lasti
                3412 to 3422 -> 3438 [0] 
                3422 to 3432 -> 3432 [1] lasti
                3432 to 3438 -> 3438 [0] 
                3438 to 3486 -> 3508 [1] lasti
                3486 to 3488 -> 3514 [0] 
                3508 to 3514 -> 3514 [0] 
                3514 to 3536 -> 3536 [1] lasti
        [Code]
            File Name: <frozen program.modules.Send_groups>
            Object Name: worker
            Qualified Name: worker
            Arg Count: 6
            Pos Only Arg Count: 0
            KW Only Arg Count: 0
            Stack Size: 20
            Flags: 0x20000003 (CO_OPTIMIZED | CO_NEWLOCALS | CO_PYARMOR_OBFUSCATED)
            [Names]
                'Thread_wait'
                'account_works'
                'Lang'
                'Disconnect'
                'get'
                'int'
                'strip'
                'random'
                'randint'
                'Logs'
                'PrintLog'
                'is_set'
                'StopProgram'
                'db_parsing'
                'get_group'
                'tg_links'
                'standart'
                'tg_group'
                'go_to'
                'update_group'
                'entity'
                'check'
                'type'
                'dict'
                'append'
                'DelayOnline'
                'len'
                'temp_group'
                'create'
                'sender'
                'direct'
                'repost'
                'db_statistic'
                'insert'
                'go_out'
                'delete'
                'StopAccount'
                'PeerFlood'
                'MaxFlood'
                'BanAccount'
                'status'
                'result'
                'Exception'
                'logging'
            [Locals+Names]
                'account'
                'config'
                'proxy'
                'data'
                'statistic'
                'stop_thread'
                '__assert_armored__'
                '_var_var_25'
                '_var_var_26'
                '_var_var_27'
                '_var_var_28'
                '_var_var_29'
                '_var_var_30'
                '_var_var_31'
                '_var_var_32'
                '_var_var_33'
                '_var_var_34'
                '_var_var_35'
                '_var_var_36'
                '_var_var_37'
                '_var_var_38'
                '_var_var_39'
                '_var_var_40'
                '_var_var_41'
                '_var_var_42'
                '_var_var_43'
                '_var_var_44'
                '_var_var_45'
                '_var_var_46'
                '_var_var_47'
                '_var_var_48'
                '_var_var_49'
                '_var_var_50'
                '_var_var_51'
                '_var_var_52'
                '_var_var_53'
                '_var_var_54'
                '_var_var_55'
                '_var_var_56'
                '_var_var_57'
                '_var_var_3'
            [Constants]
                None
                '__pyarmor_assert_14559__'
                '__pyarmor_enter_14560__'
                b'<COAddr>\x07\x00\x00\x1al\x13\x00\x00\x00\x00\x00\x00\x00\x00\x00\x00\x00\x00\x00\x00'
                'SendGroups'   # b'\x81\xd1\x1d\x1d7\xdd\xac\xdd\x0e\xea\x1e'
                (
                    'module'
                )
                False
                'false'
                (
                    'account'
                    'status'
                )
                '__pyarmor_exit_14561__'
                'Settings'
                'file_db'
                'kol_group_from'   # b'\x81\xe9\x17\x1f\x0c\xfd\xac\xdd\x0e\xea2\xc6~\xe3\xf5'
                1
                'kol_group_to'   # b'\x81\xe9\x17\x1f\x0c\xfd\xac\xdd\x0e\xea2\xd4c'
                'wait_from'   # b"\x81\xf5\x19\x1a'\xc5\xb8\xc0\x14\xf7"
                0
                'wait_to'
                'wait_go_form'   # b"\x81\xf5\x19\x1a'\xc5\xb9\xdd$\xfc\x02\xd2a"
                'wait_go_to'   # b"\x81\xf5\x19\x1a'\xc5\xb9\xdd$\xee\x02"
                'max_flood_wait'   # b'\x81\xef\x19\x0b\x0c\xfc\xb2\xdd\x14\xfe2\xd7m\xe5\xec'
                700
                'auto_repost'   # b'\x81\xe3\r\x07<\xc5\xac\xd7\x0b\xf5\x1e\xd4'
                'leave_group'   # b'\x81\xee\x1d\x12%\xff\x81\xd5\t\xf5\x18\xd0'
                'link_preview'   # b'\x81\xee\x11\x1d8\xc5\xae\xc0\x1e\xec\x04\xc5{'
                'ignore_ubic'   # b'\x81\xeb\x1f\x1d<\xe8\xbb\xed\x0e\xf8\x04\xc3'
                'sending_time'   # b'\x81\xf1\x1d\x1d7\xf3\xb0\xd5$\xee\x04\xcdi'
                'active'
                'st_day'
                'day'
                'st_month'
                'month'
                'st_year'
                'year'
                'st_hour'
                'hour'
                'st_minute'   # b'\x81\xf1\x0c,>\xf3\xb0\xc7\x0f\xff'
                'minute'
                'st_second'   # b'\x81\xf1\x0c, \xff\xbd\xdd\x15\xfe'
                'second'
                '-'
                'str'
                'silent'
                'message'
                'video_note'   # b'\x81\xf4\x11\x176\xf5\x81\xdc\x14\xee\x08'
                'peer_flood'   # b'\x81\xf2\x1d\x16!\xc5\xb8\xde\x14\xf5\t'
                True
                'time_sending_activated'   # b'\x81\xf6\x11\x1e6\xc5\xad\xd7\x15\xfe\x04\xcek\xd3\xf9\x86\x1bT\xad\xa6\xbe\xceJ'
                (
                    'config'
                    'account'
                    'message'
                    'param'
                )
                'username'
                (
                    'mode'
                )
                'database_none_groups'   # b'\x81\xe6\x19\x072\xf8\xbf\xc1\x1e\xc5\x03\xcfb\xe9\xc7\x82\x1dR\xae\xb7\xb9'
                (
                    'config'
                    'account'
                    'message'
                )
                (
                    'config'
                    'client'
                    'account'
                    'group_link'
                    'max_flood_wait'
                    'lang'
                    'stop_thread'
                )
                'MaxFloodWait'   # b'\x81\xcf\x19\x0b\x15\xf6\xb1\xdd\x1f\xcd\x0c\xc9x'
                (
                    'username'
                    'status'
                    'mode'
                )
                'type'
                'group'
                'info'
                'id'
                'title'
                'count'
                'photo'
                'invite'
                'send_messages'   # b'\x81\xf1\x1d\x1d7\xc5\xb3\xd7\x08\xe9\x0c\xc7i\xff'
                'send_media'   # b'\x81\xf1\x1d\x1d7\xc5\xb3\xd7\x1f\xf3\x0c'
                'send_stickers'   # b'\x81\xf1\x1d\x1d7\xc5\xad\xc6\x12\xf9\x06\xc5~\xff'
                'send_polls'   # b'\x81\xf1\x1d\x1d7\xc5\xae\xdd\x17\xf6\x1e'
                'slow_mode'   # b'\x81\xf1\x14\x1c$\xc5\xb3\xdd\x1f\xff'
                'scam'
                'types'
                'Done'
                (
                    'group_id'
                    'username'
                    'title'
                    'count'
                    'photo'
                    'invite'
                    'send_messages'
                    'send_media'
                    'send_stickers'
                    'send_pools'
                    'slow_mode'
                    'scam'
                    'types'
                    'status'
                    'mode'
                )
                'success_joined_channel'   # b'\x81\xf1\r\x100\xff\xad\xc1$\xf0\x02\xc9b\xe9\xfc\xba\x0cU\xba\xa9\xa4\xceB'
                'group_not_found'   # b'\x81\xe5\n\x1c&\xea\x81\xdc\x14\xee2\xc6c\xf9\xf6\x81'
                'NotFound'
                'Error: Groups is empty'   # b'\x81\xc7\n\x01<\xe8\xe4\x92<\xe8\x02\xd5|\xff\xb8\x8c\x1c\x1d\xbe\xaa\xba\xdfW'
                'Error'
                'Error: Temp group is not created. Stop account'   # b'\x81\xc7\n\x01<\xe8\xe4\x92/\xff\x00\xd0,\xeb\xea\x8a\x1aM\xfb\xae\xb9\x8b@\xc3\x11/\xa0N\x05\xb0\n\xe0>\x1c`>\x8c\xc5\xa4n\x19\xea\xfbR\xc8\xd6\x1b'
                'chat_created'   # b"\x81\xe1\x10\x12'\xc5\xbd\xc0\x1e\xfb\x19\xc5h"
                (
                    'config'
                    'lang'
                    'client'
                    'account'
                    'entity'
                    'message'
                    'silent'
                    'sending_time'
                    'link_preview'
                    'max_flood'
                    'delete_dialog'
                    'video_note'
                    'stop_thread'
                )
                'entity'
                'forward_drop_author'   # b'\x81\xe4\x17\x01$\xfb\xac\xd6$\xfe\x1f\xcf|\xd3\xf9\x90\x1bU\xb4\xb5'
                (
                    'config'
                    'lang'
                    'client'
                    'account'
                    'entity'
                    'message'
                    'silent'
                    'sending_time'
                    'link_preview'
                    'max_flood'
                    'delete_dialog'
                    'video_note'
                    'forward_drop_author'
                    'stop_thread'
                )
                2
                3
                'UserBannedInChannelError'   # b'\x81\xd7\x0b\x16!\xd8\xbf\xdc\x15\xff\t\xe9b\xcf\xf0\x84\x01S\xbe\xab\x8f\xd9\\\xc3\x17'
                'PeerFloodError'   # b'\x81\xd2\x1d\x16!\xdc\xb2\xdd\x14\xfe(\xd2~\xe3\xea'
                (
                    'account'
                    'group_id'
                    'group_link'
                    'send_status'
                    'message'
                )
                'Send - '
                ':'
                'Status: '
                (
                    'config'
                    'account'
                    'message'
                    'end'
                )
                (
                    'config'
                    'client'
                    'account'
                    'max_flood_wait'
                    'lang'
                    'stop_thread'
                )
                (
                    'entity'
                )
                'Left group:'   # b"\x81\xce\x1d\x15'\xba\xb9\xc0\x14\xef\x1d\x9a"
                'work_account_completed'   # b'\x81\xf5\x17\x018\xc5\xbf\xd1\x18\xf5\x18\xcex\xd3\xfb\x8a\x02M\xb7\xa2\xbe\xceJ'
                'done'
            [Disassembly]
                0       NOP                             
                2       NOP                             
                4       PUSH_NULL                       
                6       LOAD_CONST                      2: '__pyarmor_enter_14560__'
                8       LOAD_CONST                      3: b'<COAddr>\x07\x00\x00\x1al\x13\x00\x00\x00\x00\x00\x00\x00\x00\x00\x00\x00\x00\x00\x00'
                10      BUILD_TUPLE                     1
                12      CALL_FUNCTION_EX                0
                14      POP_TOP                         
                16      RESUME                          0
                18      NOP                             
                20      NOP                             
                22      NOP                             
                24      NOP                             
                26      NOP                             
                28      NOP                             
                30      LOAD_GLOBAL                     1: NULL + Thread_wait
                40      LOAD_FAST                       3: data
                42      LOAD_FAST                       1: config
                44      LOAD_FAST                       5: stop_thread
                46      CALL                            3
                54      POP_TOP                         
                56      LOAD_GLOBAL                     3: NULL + account_works
                66      LOAD_FAST                       1: config
                68      LOAD_GLOBAL                     4: Lang
                78      LOAD_FAST                       2: proxy
                80      LOAD_FAST                       0: account
                82      LOAD_FAST                       5: stop_thread
                84      PUSH_NULL                       
                86      LOAD_CONST                      1: '__pyarmor_assert_14559__'
                88      LOAD_CONST                      4: 'SendGroups'   # b'\x81\xd1\x1d\x1d7\xdd\xac\xdd\x0e\xea\x1e'
                90      CALL                            1
                98      KW_NAMES                        5: ('module',)
                100     CALL                            6
                108     STORE_FAST                      7: _var_var_25
                110     LOAD_FAST                       7: _var_var_25
                112     LOAD_CONST                      6: False
                114     COMPARE_OP                      40 (==)
                118     POP_JUMP_IF_FALSE               25 (to 170)
                120     LOAD_FAST                       0: account
                122     LOAD_CONST                      7: 'false'
                124     LOAD_CONST                      8: ('account', 'status')
                126     BUILD_CONST_KEY_MAP             2
                128     LOAD_GLOBAL                     7: NULL + Disconnect
                138     LOAD_FAST                       7: _var_var_25
                140     CALL                            1
                148     POP_TOP                         
                150     NOP                             
                152     NOP                             
                154     JUMP_FORWARD                    2434 (to 5026)
                158     CALL                            1
                166     POP_TOP                         
                168     RETURN_VALUE                    
                170     LOAD_FAST                       3: data
                172     LOAD_CONST                      10: 'Settings'
                174     BINARY_SUBSCR                   
                178     LOAD_ATTR                       9: get
                198     LOAD_CONST                      11: 'file_db'
                200     CALL                            1
                208     STORE_FAST                      8: _var_var_26
                210     LOAD_GLOBAL                     11: NULL + int
                220     LOAD_FAST                       3: data
                222     LOAD_CONST                      10: 'Settings'
                224     BINARY_SUBSCR                   
                228     LOAD_ATTR                       9: get
                248     PUSH_NULL                       
                250     LOAD_CONST                      1: '__pyarmor_assert_14559__'
                252     LOAD_CONST                      12: 'kol_group_from'   # b'\x81\xe9\x17\x1f\x0c\xfd\xac\xdd\x0e\xea2\xc6~\xe3\xf5'
                254     CALL                            1
                262     LOAD_CONST                      13: 1
                264     CALL                            2
                272     CALL                            1
                280     STORE_FAST                      9: _var_var_27
                282     LOAD_GLOBAL                     11: NULL + int
                292     LOAD_FAST                       3: data
                294     LOAD_CONST                      10: 'Settings'
                296     BINARY_SUBSCR                   
                300     LOAD_ATTR                       9: get
                320     PUSH_NULL                       
                322     LOAD_CONST                      1: '__pyarmor_assert_14559__'
                324     LOAD_CONST                      14: 'kol_group_to'   # b'\x81\xe9\x17\x1f\x0c\xfd\xac\xdd\x0e\xea2\xd4c'
                326     CALL                            1
                334     LOAD_CONST                      13: 1
                336     CALL                            2
                344     CALL                            1
                352     STORE_FAST                      10: _var_var_28
                354     LOAD_GLOBAL                     11: NULL + int
                364     LOAD_FAST                       3: data
                366     LOAD_CONST                      10: 'Settings'
                368     BINARY_SUBSCR                   
                372     LOAD_ATTR                       9: get
                392     PUSH_NULL                       
                394     LOAD_CONST                      1: '__pyarmor_assert_14559__'
                396     LOAD_CONST                      15: 'wait_from'   # b"\x81\xf5\x19\x1a'\xc5\xb8\xc0\x14\xf7"
                398     CALL                            1
                406     LOAD_CONST                      16: 0
                408     CALL                            2
                416     CALL                            1
                424     STORE_FAST                      11: _var_var_29
                426     LOAD_GLOBAL                     11: NULL + int
                436     LOAD_FAST                       3: data
                438     LOAD_CONST                      10: 'Settings'
                440     BINARY_SUBSCR                   
                444     LOAD_ATTR                       9: get
                464     LOAD_CONST                      17: 'wait_to'
                466     LOAD_CONST                      16: 0
                468     CALL                            2
                476     CALL                            1
                484     STORE_FAST                      12: _var_var_30
                486     LOAD_GLOBAL                     11: NULL + int
                496     LOAD_FAST                       3: data
                498     LOAD_CONST                      10: 'Settings'
                500     BINARY_SUBSCR                   
                504     LOAD_ATTR                       9: get
                524     PUSH_NULL                       
                526     LOAD_CONST                      1: '__pyarmor_assert_14559__'
                528     LOAD_CONST                      18: 'wait_go_form'   # b"\x81\xf5\x19\x1a'\xc5\xb9\xdd$\xfc\x02\xd2a"
                530     CALL                            1
                538     LOAD_CONST                      16: 0
                540     CALL                            2
                548     CALL                            1
                556     STORE_FAST                      13: _var_var_31
                558     LOAD_GLOBAL                     11: NULL + int
                568     LOAD_FAST                       3: data
                570     LOAD_CONST                      10: 'Settings'
                572     BINARY_SUBSCR                   
                576     LOAD_ATTR                       9: get
                596     PUSH_NULL                       
                598     LOAD_CONST                      1: '__pyarmor_assert_14559__'
                600     LOAD_CONST                      19: 'wait_go_to'   # b"\x81\xf5\x19\x1a'\xc5\xb9\xdd$\xee\x02"
                602     CALL                            1
                610     LOAD_CONST                      16: 0
                612     CALL                            2
                620     CALL                            1
                628     STORE_FAST                      14: _var_var_32
                630     LOAD_GLOBAL                     11: NULL + int
                640     LOAD_FAST                       3: data
                642     LOAD_CONST                      10: 'Settings'
                644     BINARY_SUBSCR                   
                648     LOAD_ATTR                       9: get
                668     PUSH_NULL                       
                670     LOAD_CONST                      1: '__pyarmor_assert_14559__'
                672     LOAD_CONST                      20: 'max_flood_wait'   # b'\x81\xef\x19\x0b\x0c\xfc\xb2\xdd\x14\xfe2\xd7m\xe5\xec'
                674     CALL                            1
                682     LOAD_CONST                      21: 700
                684     CALL                            2
                692     CALL                            1
                700     STORE_FAST                      15: _var_var_33
                702     LOAD_FAST                       3: data
                704     LOAD_CONST                      10: 'Settings'
                706     BINARY_SUBSCR                   
                710     LOAD_ATTR                       9: get
                730     PUSH_NULL                       
                732     LOAD_CONST                      1: '__pyarmor_assert_14559__'
                734     LOAD_CONST                      22: 'auto_repost'   # b'\x81\xe3\r\x07<\xc5\xac\xd7\x0b\xf5\x1e\xd4'
                736     CALL                            1
                744     LOAD_CONST                      6: False
                746     CALL                            2
                754     STORE_FAST                      16: _var_var_34
                756     LOAD_FAST                       3: data
                758     LOAD_CONST                      10: 'Settings'
                760     BINARY_SUBSCR                   
                764     LOAD_ATTR                       9: get
                784     PUSH_NULL                       
                786     LOAD_CONST                      1: '__pyarmor_assert_14559__'
                788     LOAD_CONST                      23: 'leave_group'   # b'\x81\xee\x1d\x12%\xff\x81\xd5\t\xf5\x18\xd0'
                790     CALL                            1
                798     LOAD_CONST                      6: False
                800     CALL                            2
                808     STORE_FAST                      17: _var_var_35
                810     LOAD_FAST                       3: data
                812     LOAD_CONST                      10: 'Settings'
                814     BINARY_SUBSCR                   
                818     LOAD_ATTR                       9: get
                838     PUSH_NULL                       
                840     LOAD_CONST                      1: '__pyarmor_assert_14559__'
                842     LOAD_CONST                      24: 'link_preview'   # b'\x81\xee\x11\x1d8\xc5\xae\xc0\x1e\xec\x04\xc5{'
                844     CALL                            1
                852     LOAD_CONST                      6: False
                854     CALL                            2
                862     STORE_FAST                      18: _var_var_36
                864     LOAD_FAST                       3: data
                866     LOAD_CONST                      10: 'Settings'
                868     BINARY_SUBSCR                   
                872     LOAD_ATTR                       9: get
                892     PUSH_NULL                       
                894     LOAD_CONST                      1: '__pyarmor_assert_14559__'
                896     LOAD_CONST                      25: 'ignore_ubic'   # b'\x81\xeb\x1f\x1d<\xe8\xbb\xed\x0e\xf8\x04\xc3'
                898     CALL                            1
                906     CALL                            1
                914     STORE_FAST                      19: _var_var_37
                916     BUILD_MAP                       0
                918     STORE_FAST                      20: _var_var_38
                920     LOAD_FAST                       3: data
                922     LOAD_CONST                      10: 'Settings'
                924     BINARY_SUBSCR                   
                928     LOAD_ATTR                       9: get
                948     PUSH_NULL                       
                950     LOAD_CONST                      1: '__pyarmor_assert_14559__'
                952     LOAD_CONST                      26: 'sending_time'   # b'\x81\xf1\x1d\x1d7\xf3\xb0\xd5$\xee\x04\xcdi'
                954     CALL                            1
                962     LOAD_CONST                      6: False
                964     CALL                            2
                972     LOAD_FAST                       20: _var_var_38
                974     LOAD_CONST                      27: 'active'
                976     STORE_SUBSCR                    
                980     LOAD_FAST                       3: data
                982     LOAD_CONST                      10: 'Settings'
                984     BINARY_SUBSCR                   
                988     LOAD_ATTR                       9: get
                1008    LOAD_CONST                      28: 'st_day'
                1010    CALL                            1
                1018    LOAD_ATTR                       13: strip
                1038    CALL                            0
                1046    LOAD_FAST                       20: _var_var_38
                1048    LOAD_CONST                      29: 'day'
                1050    STORE_SUBSCR                    
                1054    LOAD_FAST                       3: data
                1056    LOAD_CONST                      10: 'Settings'
                1058    BINARY_SUBSCR                   
                1062    LOAD_ATTR                       9: get
                1082    LOAD_CONST                      30: 'st_month'
                1084    CALL                            1
                1092    LOAD_ATTR                       13: strip
                1112    CALL                            0
                1120    LOAD_FAST                       20: _var_var_38
                1122    LOAD_CONST                      31: 'month'
                1124    STORE_SUBSCR                    
                1128    LOAD_FAST                       3: data
                1130    LOAD_CONST                      10: 'Settings'
                1132    BINARY_SUBSCR                   
                1136    LOAD_ATTR                       9: get
                1156    LOAD_CONST                      32: 'st_year'
                1158    CALL                            1
                1166    LOAD_ATTR                       13: strip
                1186    CALL                            0
                1194    LOAD_FAST                       20: _var_var_38
                1196    LOAD_CONST                      33: 'year'
                1198    STORE_SUBSCR                    
                1202    LOAD_FAST                       3: data
                1204    LOAD_CONST                      10: 'Settings'
                1206    BINARY_SUBSCR                   
                1210    LOAD_ATTR                       9: get
                1230    LOAD_CONST                      34: 'st_hour'
                1232    CALL                            1
                1240    LOAD_ATTR                       13: strip
                1260    CALL                            0
                1268    LOAD_FAST                       20: _var_var_38
                1270    LOAD_CONST                      35: 'hour'
                1272    STORE_SUBSCR                    
                1276    LOAD_FAST                       3: data
                1278    LOAD_CONST                      10: 'Settings'
                1280    BINARY_SUBSCR                   
                1284    LOAD_ATTR                       9: get
                1304    PUSH_NULL                       
                1306    LOAD_CONST                      1: '__pyarmor_assert_14559__'
                1308    LOAD_CONST                      36: 'st_minute'   # b'\x81\xf1\x0c,>\xf3\xb0\xc7\x0f\xff'
                1310    CALL                            1
                1318    CALL                            1
                1326    LOAD_ATTR                       13: strip
                1346    CALL                            0
                1354    LOAD_FAST                       20: _var_var_38
                1356    LOAD_CONST                      37: 'minute'
                1358    STORE_SUBSCR                    
                1362    LOAD_FAST                       3: data
                1364    LOAD_CONST                      10: 'Settings'
                1366    BINARY_SUBSCR                   
                1370    LOAD_ATTR                       9: get
                1390    PUSH_NULL                       
                1392    LOAD_CONST                      1: '__pyarmor_assert_14559__'
                1394    LOAD_CONST                      38: 'st_second'   # b'\x81\xf1\x0c, \xff\xbd\xdd\x15\xfe'
                1396    CALL                            1
                1404    CALL                            1
                1412    LOAD_ATTR                       13: strip
                1432    CALL                            0
                1440    LOAD_FAST                       20: _var_var_38
                1442    LOAD_CONST                      39: 'second'
                1444    STORE_SUBSCR                    
                1448    LOAD_FAST                       20: _var_var_38
                1450    LOAD_CONST                      33: 'year'
                1452    BINARY_SUBSCR                   
                1456    FORMAT_VALUE                    0 (FVC_NONE)
                1458    LOAD_CONST                      40: '-'
                1460    LOAD_FAST                       20: _var_var_38
                1462    LOAD_CONST                      31: 'month'
                1464    BINARY_SUBSCR                   
                1468    FORMAT_VALUE                    0 (FVC_NONE)
                1470    LOAD_CONST                      40: '-'
                1472    LOAD_FAST                       20: _var_var_38
                1474    LOAD_CONST                      29: 'day'
                1476    BINARY_SUBSCR                   
                1480    FORMAT_VALUE                    0 (FVC_NONE)
                1482    LOAD_CONST                      40: '-'
                1484    LOAD_FAST                       20: _var_var_38
                1486    LOAD_CONST                      35: 'hour'
                1488    BINARY_SUBSCR                   
                1492    FORMAT_VALUE                    0 (FVC_NONE)
                1494    LOAD_CONST                      40: '-'
                1496    LOAD_FAST                       20: _var_var_38
                1498    LOAD_CONST                      37: 'minute'
                1500    BINARY_SUBSCR                   
                1504    FORMAT_VALUE                    0 (FVC_NONE)
                1506    LOAD_CONST                      40: '-'
                1508    LOAD_FAST                       20: _var_var_38
                1510    LOAD_CONST                      39: 'second'
                1512    BINARY_SUBSCR                   
                1516    FORMAT_VALUE                    0 (FVC_NONE)
                1518    BUILD_STRING                    11
                1520    LOAD_FAST                       20: _var_var_38
                1522    LOAD_CONST                      41: 'str'
                1524    STORE_SUBSCR                    
                1528    LOAD_FAST                       3: data
                1530    LOAD_CONST                      10: 'Settings'
                1532    BINARY_SUBSCR                   
                1536    LOAD_ATTR                       9: get
                1556    LOAD_CONST                      42: 'silent'
                1558    CALL                            1
                1566    STORE_FAST                      21: _var_var_39
                1568    LOAD_FAST                       3: data
                1570    LOAD_CONST                      10: 'Settings'
                1572    BINARY_SUBSCR                   
                1576    LOAD_ATTR                       9: get
                1596    LOAD_CONST                      43: 'message'
                1598    CALL                            1
                1606    STORE_FAST                      22: _var_var_40
                1608    LOAD_FAST                       3: data
                1610    LOAD_CONST                      10: 'Settings'
                1612    BINARY_SUBSCR                   
                1616    LOAD_ATTR                       9: get
                1636    PUSH_NULL                       
                1638    LOAD_CONST                      1: '__pyarmor_assert_14559__'
                1640    LOAD_CONST                      44: 'video_note'   # b'\x81\xf4\x11\x176\xf5\x81\xdc\x14\xee\x08'
                1642    CALL                            1
                1650    CALL                            1
                1658    STORE_FAST                      23: _var_var_41
                1660    LOAD_GLOBAL                     15: NULL + random
                1670    LOAD_ATTR                       16: randint
                1690    LOAD_FAST                       9: _var_var_27
                1692    LOAD_FAST                       10: _var_var_28
                1694    CALL                            2
                1702    STORE_FAST                      24: _var_var_42
                1704    BUILD_LIST                      0
                1706    STORE_FAST                      25: _var_var_43
                1708    LOAD_CONST                      16: 0
                1710    STORE_FAST                      26: _var_var_44
                1712    LOAD_CONST                      16: 0
                1714    STORE_FAST                      27: _var_var_45
                1716    LOAD_FAST                       1: config
                1718    PUSH_NULL                       
                1720    LOAD_CONST                      1: '__pyarmor_assert_14559__'
                1722    LOAD_CONST                      45: 'peer_flood'   # b'\x81\xf2\x1d\x16!\xc5\xb8\xde\x14\xf5\t'
                1724    CALL                            1
                1732    BINARY_SUBSCR                   
                1736    STORE_FAST                      28: _var_var_46
                1738    LOAD_FAST                       20: _var_var_38
                1740    LOAD_CONST                      27: 'active'
                1742    BINARY_SUBSCR                   
                1746    LOAD_CONST                      46: True
                1748    COMPARE_OP                      40 (==)
                1752    POP_JUMP_IF_FALSE               41 (to 1836)
                1754    LOAD_GLOBAL                     19: NULL + Logs
                1764    LOAD_ATTR                       20: PrintLog
                1784    LOAD_FAST                       1: config
                1786    LOAD_FAST                       0: account
                1788    LOAD_GLOBAL                     4: Lang
                1798    PUSH_NULL                       
                1800    LOAD_CONST                      1: '__pyarmor_assert_14559__'
                1802    LOAD_CONST                      47: 'time_sending_activated'   # b'\x81\xf6\x11\x1e6\xc5\xad\xd7\x15\xfe\x04\xcek\xd3\xf9\x86\x1bT\xad\xa6\xbe\xceJ'
                1804    CALL                            1
                1812    BINARY_SUBSCR                   
                1816    LOAD_FAST                       20: _var_var_38
                1818    LOAD_CONST                      41: 'str'
                1820    BINARY_SUBSCR                   
                1824    KW_NAMES                        48: ('config', 'account', 'message', 'param')
                1826    CALL                            4
                1834    POP_TOP                         
                1836    LOAD_FAST                       27: _var_var_45
                1838    LOAD_FAST                       24: _var_var_42
                1840    COMPARE_OP                      2 (<)
                1844    POP_JUMP_IF_FALSE               567 (to 2982)
                1848    LOAD_FAST                       5: stop_thread
                1850    LOAD_ATTR                       23: is_set
                1870    CALL                            0
                1878    POP_JUMP_IF_FALSE               10 (to 1900)
                1880    LOAD_GLOBAL                     25: NULL + StopProgram
                1890    CALL                            0
                1898    RAISE_VARARGS                   1
                1900    LOAD_GLOBAL                     27: NULL + db_parsing
                1910    LOAD_FAST                       8: _var_var_26
                1912    CALL                            1
                1920    LOAD_ATTR                       29: get_group
                1940    LOAD_CONST                      49: 'username'
                1942    KW_NAMES                        50: ('mode',)
                1944    CALL                            1
                1952    STORE_FAST                      29: _var_var_47
                1954    LOAD_FAST                       29: _var_var_47
                1956    LOAD_CONST                      6: False
                1958    COMPARE_OP                      40 (==)
                1962    POP_JUMP_IF_FALSE               39 (to 2042)
                1964    LOAD_GLOBAL                     19: NULL + Logs
                1974    LOAD_ATTR                       20: PrintLog
                1994    LOAD_FAST                       1: config
                1996    LOAD_FAST                       0: account
                1998    LOAD_GLOBAL                     4: Lang
                2008    PUSH_NULL                       
                2010    LOAD_CONST                      1: '__pyarmor_assert_14559__'
                2012    LOAD_CONST                      51: 'database_none_groups'   # b'\x81\xe6\x19\x072\xf8\xbf\xc1\x1e\xc5\x03\xcfb\xe9\xc7\x82\x1dR\xae\xb7\xb9'
                2014    CALL                            1
                2022    BINARY_SUBSCR                   
                2026    KW_NAMES                        52: ('config', 'account', 'message')
                2028    CALL                            3
                2036    POP_TOP                         
                2038    JUMP_FORWARD                    470 (to 2982)
                2042    LOAD_GLOBAL                     31: NULL + tg_links
                2052    CALL                            0
                2060    LOAD_ATTR                       33: standart
                2080    LOAD_FAST                       29: _var_var_47
                2082    LOAD_CONST                      13: 1
                2084    BINARY_SUBSCR                   
                2088    CALL                            1
                2096    STORE_FAST                      30: _var_var_48
                2098    LOAD_GLOBAL                     35: NULL + tg_group
                2108    LOAD_FAST                       1: config
                2110    LOAD_FAST                       7: _var_var_25
                2112    LOAD_FAST                       0: account
                2114    LOAD_FAST                       30: _var_var_48
                2116    LOAD_FAST                       15: _var_var_33
                2118    LOAD_GLOBAL                     4: Lang
                2128    LOAD_FAST                       5: stop_thread
                2130    KW_NAMES                        53: ('config', 'client', 'account', 'group_link', 'max_flood_wait', 'lang', 'stop_thread')
                2132    CALL                            7
                2140    LOAD_ATTR                       37: go_to
                2160    CALL                            0
                2168    STORE_FAST                      31: _var_var_49
                2170    LOAD_FAST                       31: _var_var_49
                2172    PUSH_NULL                       
                2174    LOAD_CONST                      1: '__pyarmor_assert_14559__'
                2176    LOAD_CONST                      20: 'max_flood_wait'   # b'\x81\xef\x19\x0b\x0c\xfc\xb2\xdd\x14\xfe2\xd7m\xe5\xec'
                2178    CALL                            1
                2186    COMPARE_OP                      40 (==)
                2190    POP_JUMP_IF_FALSE               40 (to 2272)
                2192    LOAD_GLOBAL                     27: NULL + db_parsing
                2202    LOAD_FAST                       8: _var_var_26
                2204    CALL                            1
                2212    LOAD_ATTR                       39: update_group
                2232    LOAD_FAST                       29: _var_var_47
                2234    LOAD_CONST                      13: 1
                2236    BINARY_SUBSCR                   
                2240    PUSH_NULL                       
                2242    LOAD_CONST                      1: '__pyarmor_assert_14559__'
                2244    LOAD_CONST                      54: 'MaxFloodWait'   # b'\x81\xcf\x19\x0b\x15\xf6\xb1\xdd\x1f\xcd\x0c\xc9x'
                2246    CALL                            1
                2254    LOAD_CONST                      49: 'username'
                2256    KW_NAMES                        55: ('username', 'status', 'mode')
                2258    CALL                            3
                2266    POP_TOP                         
                2268    JUMP_FORWARD                    355 (to 2982)
                2272    LOAD_GLOBAL                     41: NULL + entity
                2282    CALL                            0
                2290    LOAD_ATTR                       43: check
                2310    LOAD_FAST                       31: _var_var_49
                2312    CALL                            1
                2320    STORE_FAST                      32: _var_var_50
                2322    LOAD_GLOBAL                     45: NULL + type
                2332    LOAD_FAST                       32: _var_var_50
                2334    CALL                            1
                2342    LOAD_GLOBAL                     46: dict
                2352    COMPARE_OP                      40 (==)
                2356    POP_JUMP_IF_FALSE               212 (to 2782)
                2358    LOAD_FAST                       32: _var_var_50
                2360    LOAD_CONST                      56: 'type'
                2362    BINARY_SUBSCR                   
                2366    LOAD_CONST                      57: 'group'
                2368    COMPARE_OP                      40 (==)
                2372    POP_JUMP_IF_FALSE               204 (to 2782)
                2374    LOAD_GLOBAL                     27: NULL + db_parsing
                2384    LOAD_FAST                       8: _var_var_26
                2386    CALL                            1
                2394    LOAD_ATTR                       39: update_group
                2414    LOAD_FAST                       32: _var_var_50
                2416    LOAD_CONST                      58: 'info'
                2418    BINARY_SUBSCR                   
                2422    LOAD_CONST                      59: 'id'
                2424    BINARY_SUBSCR                   
                2428    LOAD_FAST                       30: _var_var_48
                2430    LOAD_FAST                       32: _var_var_50
                2432    LOAD_CONST                      58: 'info'
                2434    BINARY_SUBSCR                   
                2438    LOAD_CONST                      60: 'title'
                2440    BINARY_SUBSCR                   
                2444    LOAD_FAST                       32: _var_var_50
                2446    LOAD_CONST                      58: 'info'
                2448    BINARY_SUBSCR                   
                2452    LOAD_CONST                      61: 'count'
                2454    BINARY_SUBSCR                   
                2458    LOAD_FAST                       32: _var_var_50
                2460    LOAD_CONST                      58: 'info'
                2462    BINARY_SUBSCR                   
                2466    LOAD_CONST                      62: 'photo'
                2468    BINARY_SUBSCR                   
                2472    LOAD_FAST                       32: _var_var_50
                2474    LOAD_CONST                      58: 'info'
                2476    BINARY_SUBSCR                   
                2480    LOAD_CONST                      63: 'invite'
                2482    BINARY_SUBSCR                   
                2486    LOAD_FAST                       32: _var_var_50
                2488    LOAD_CONST                      58: 'info'
                2490    BINARY_SUBSCR                   
                2494    PUSH_NULL                       
                2496    LOAD_CONST                      1: '__pyarmor_assert_14559__'
                2498    LOAD_CONST                      64: 'send_messages'   # b'\x81\xf1\x1d\x1d7\xc5\xb3\xd7\x08\xe9\x0c\xc7i\xff'
                2500    CALL                            1
                2508    BINARY_SUBSCR                   
                2512    LOAD_FAST                       32: _var_var_50
                2514    LOAD_CONST                      58: 'info'
                2516    BINARY_SUBSCR                   
                2520    PUSH_NULL                       
                2522    LOAD_CONST                      1: '__pyarmor_assert_14559__'
                2524    LOAD_CONST                      65: 'send_media'   # b'\x81\xf1\x1d\x1d7\xc5\xb3\xd7\x1f\xf3\x0c'
                2526    CALL                            1
                2534    BINARY_SUBSCR                   
                2538    LOAD_FAST                       32: _var_var_50
                2540    LOAD_CONST                      58: 'info'
                2542    BINARY_SUBSCR                   
                2546    PUSH_NULL                       
                2548    LOAD_CONST                      1: '__pyarmor_assert_14559__'
                2550    LOAD_CONST                      66: 'send_stickers'   # b'\x81\xf1\x1d\x1d7\xc5\xad\xc6\x12\xf9\x06\xc5~\xff'
                2552    CALL                            1
                2560    BINARY_SUBSCR                   
                2564    LOAD_FAST                       32: _var_var_50
                2566    LOAD_CONST                      58: 'info'
                2568    BINARY_SUBSCR                   
                2572    PUSH_NULL                       
                2574    LOAD_CONST                      1: '__pyarmor_assert_14559__'
                2576    LOAD_CONST                      67: 'send_polls'   # b'\x81\xf1\x1d\x1d7\xc5\xae\xdd\x17\xf6\x1e'
                2578    CALL                            1
                2586    BINARY_SUBSCR                   
                2590    LOAD_FAST                       32: _var_var_50
                2592    LOAD_CONST                      58: 'info'
                2594    BINARY_SUBSCR                   
                2598    PUSH_NULL                       
                2600    LOAD_CONST                      1: '__pyarmor_assert_14559__'
                2602    LOAD_CONST                      68: 'slow_mode'   # b'\x81\xf1\x14\x1c$\xc5\xb3\xdd\x1f\xff'
                2604    CALL                            1
                2612    BINARY_SUBSCR                   
                2616    LOAD_FAST                       32: _var_var_50
                2618    LOAD_CONST                      58: 'info'
                2620    BINARY_SUBSCR                   
                2624    LOAD_CONST                      69: 'scam'
                2626    BINARY_SUBSCR                   
                2630    LOAD_FAST                       32: _var_var_50
                2632    LOAD_CONST                      58: 'info'
                2634    BINARY_SUBSCR                   
                2638    LOAD_CONST                      70: 'types'
                2640    BINARY_SUBSCR                   
                2644    LOAD_CONST                      71: 'Done'
                2646    LOAD_CONST                      49: 'username'
                2648    KW_NAMES                        72: ('group_id', 'username', 'title', 'count', 'photo', 'invite', 'send_messages', 'send_media', 'send_stickers', 'send_pools', 'slow_mode', 'scam', 'types', 'status', 'mode')
                2650    CALL                            15
                2658    POP_TOP                         
                2660    LOAD_FAST                       27: _var_var_45
                2662    LOAD_CONST                      13: 1
                2664    BINARY_OP                       13 (+=)
                2668    STORE_FAST                      27: _var_var_45
                2670    LOAD_FAST                       25: _var_var_43
                2672    LOAD_ATTR                       49: append
                2692    LOAD_FAST                       32: _var_var_50
                2694    CALL                            1
                2702    POP_TOP                         
                2704    LOAD_GLOBAL                     19: NULL + Logs
                2714    LOAD_ATTR                       20: PrintLog
                2734    LOAD_FAST                       1: config
                2736    LOAD_FAST                       0: account
                2738    LOAD_GLOBAL                     4: Lang
                2748    PUSH_NULL                       
                2750    LOAD_CONST                      1: '__pyarmor_assert_14559__'
                2752    LOAD_CONST                      73: 'success_joined_channel'   # b'\x81\xf1\r\x100\xff\xad\xc1$\xf0\x02\xc9b\xe9\xfc\xba\x0cU\xba\xa9\xa4\xceB'
                2754    CALL                            1
                2762    BINARY_SUBSCR                   
                2766    LOAD_FAST                       30: _var_var_48
                2768    KW_NAMES                        48: ('config', 'account', 'message', 'param')
                2770    CALL                            4
                2778    POP_TOP                         
                2780    JUMP_FORWARD                    73 (to 2928)
                2782    LOAD_GLOBAL                     19: NULL + Logs
                2792    LOAD_ATTR                       20: PrintLog
                2812    LOAD_FAST                       1: config
                2814    LOAD_FAST                       0: account
                2816    LOAD_GLOBAL                     4: Lang
                2826    PUSH_NULL                       
                2828    LOAD_CONST                      1: '__pyarmor_assert_14559__'
                2830    LOAD_CONST                      74: 'group_not_found'   # b'\x81\xe5\n\x1c&\xea\x81\xdc\x14\xee2\xc6c\xf9\xf6\x81'
                2832    CALL                            1
                2840    BINARY_SUBSCR                   
                2844    LOAD_FAST                       29: _var_var_47
                2846    LOAD_CONST                      13: 1
                2848    BINARY_SUBSCR                   
                2852    KW_NAMES                        48: ('config', 'account', 'message', 'param')
                2854    CALL                            4
                2862    POP_TOP                         
                2864    LOAD_GLOBAL                     27: NULL + db_parsing
                2874    LOAD_FAST                       8: _var_var_26
                2876    CALL                            1
                2884    LOAD_ATTR                       39: update_group
                2904    LOAD_FAST                       29: _var_var_47
                2906    LOAD_CONST                      13: 1
                2908    BINARY_SUBSCR                   
                2912    LOAD_CONST                      75: 'NotFound'
                2914    LOAD_CONST                      49: 'username'
                2916    KW_NAMES                        55: ('username', 'status', 'mode')
                2918    CALL                            3
                2926    POP_TOP                         
                2928    LOAD_FAST                       24: _var_var_42
                2930    LOAD_FAST                       27: _var_var_45
                2932    COMPARE_OP                      55 (!=)
                2936    POP_JUMP_IF_FALSE               15 (to 2968)
                2938    LOAD_GLOBAL                     51: NULL + DelayOnline
                2948    LOAD_FAST                       0: account
                2950    LOAD_FAST                       7: _var_var_25
                2952    LOAD_FAST                       13: _var_var_31
                2954    LOAD_FAST                       14: _var_var_32
                2956    LOAD_FAST                       5: stop_thread
                2958    CALL                            5
                2966    POP_TOP                         
                2968    LOAD_FAST                       27: _var_var_45
                2970    LOAD_FAST                       24: _var_var_42
                2972    COMPARE_OP                      2 (<)
                2976    POP_JUMP_IF_FALSE               2 (to 2982)
                2978    JUMP_BACKWARD                   567 (to 1848)
                2982    LOAD_GLOBAL                     53: NULL + len
                2992    LOAD_FAST                       25: _var_var_43
                2994    CALL                            1
                3002    LOAD_CONST                      13: 1
                3004    COMPARE_OP                      2 (<)
                3008    POP_JUMP_IF_FALSE               55 (to 3120)
                3010    LOAD_GLOBAL                     19: NULL + Logs
                3020    LOAD_ATTR                       20: PrintLog
                3040    LOAD_FAST                       1: config
                3042    LOAD_FAST                       0: account
                3044    PUSH_NULL                       
                3046    LOAD_CONST                      1: '__pyarmor_assert_14559__'
                3048    LOAD_CONST                      76: 'Error: Groups is empty'   # b'\x81\xc7\n\x01<\xe8\xe4\x92<\xe8\x02\xd5|\xff\xb8\x8c\x1c\x1d\xbe\xaa\xba\xdfW'
                3050    CALL                            1
                3058    KW_NAMES                        52: ('config', 'account', 'message')
                3060    CALL                            3
                3068    POP_TOP                         
                3070    LOAD_FAST                       0: account
                3072    LOAD_CONST                      77: 'Error'
                3074    LOAD_CONST                      8: ('account', 'status')
                3076    BUILD_CONST_KEY_MAP             2
                3078    LOAD_GLOBAL                     7: NULL + Disconnect
                3088    LOAD_FAST                       7: _var_var_25
                3090    CALL                            1
                3098    POP_TOP                         
                3100    NOP                             
                3102    NOP                             
                3104    JUMP_FORWARD                    959 (to 5026)
                3108    CALL                            1
                3116    POP_TOP                         
                3118    RETURN_VALUE                    
                3120    LOAD_FAST                       16: _var_var_34
                3122    POP_JUMP_IF_FALSE               232 (to 3588)
                3124    LOAD_GLOBAL                     55: NULL + temp_group
                3134    LOAD_FAST                       7: _var_var_25
                3136    CALL                            1
                3144    LOAD_ATTR                       57: create
                3164    CALL                            0
                3172    STORE_FAST                      33: _var_var_51
                3174    LOAD_FAST                       33: _var_var_51
                3176    LOAD_CONST                      6: False
                3178    COMPARE_OP                      40 (==)
                3182    POP_JUMP_IF_FALSE               55 (to 3294)
                3184    LOAD_GLOBAL                     19: NULL + Logs
                3194    LOAD_ATTR                       20: PrintLog
                3214    LOAD_FAST                       1: config
                3216    LOAD_FAST                       0: account
                3218    PUSH_NULL                       
                3220    LOAD_CONST                      1: '__pyarmor_assert_14559__'
                3222    LOAD_CONST                      78: 'Error: Temp group is not created. Stop account'   # b'\x81\xc7\n\x01<\xe8\xe4\x92/\xff\x00\xd0,\xeb\xea\x8a\x1aM\xfb\xae\xb9\x8b@\xc3\x11/\xa0N\x05\xb0\n\xe0>\x1c`>\x8c\xc5\xa4n\x19\xea\xfbR\xc8\xd6\x1b'
                3224    CALL                            1
                3232    KW_NAMES                        52: ('config', 'account', 'message')
                3234    CALL                            3
                3242    POP_TOP                         
                3244    LOAD_FAST                       0: account
                3246    LOAD_CONST                      77: 'Error'
                3248    LOAD_CONST                      8: ('account', 'status')
                3250    BUILD_CONST_KEY_MAP             2
                3252    LOAD_GLOBAL                     7: NULL + Disconnect
                3262    LOAD_FAST                       7: _var_var_25
                3264    CALL                            1
                3272    POP_TOP                         
                3274    NOP                             
                3276    NOP                             
                3278    JUMP_FORWARD                    872 (to 5026)
                3282    CALL                            1
                3290    POP_TOP                         
                3292    RETURN_VALUE                    
                3294    LOAD_GLOBAL                     19: NULL + Logs
                3304    LOAD_ATTR                       20: PrintLog
                3324    LOAD_FAST                       1: config
                3326    LOAD_FAST                       0: account
                3328    LOAD_GLOBAL                     4: Lang
                3338    PUSH_NULL                       
                3340    LOAD_CONST                      1: '__pyarmor_assert_14559__'
                3342    LOAD_CONST                      79: 'chat_created'   # b"\x81\xe1\x10\x12'\xc5\xbd\xc0\x1e\xfb\x19\xc5h"
                3344    CALL                            1
                3352    BINARY_SUBSCR                   
                3356    KW_NAMES                        52: ('config', 'account', 'message')
                3358    CALL                            3
                3366    POP_TOP                         
                3368    LOAD_GLOBAL                     59: NULL + sender
                3378    LOAD_FAST                       1: config
                3380    LOAD_GLOBAL                     4: Lang
                3390    LOAD_FAST                       7: _var_var_25
                3392    LOAD_FAST                       0: account
                3394    LOAD_FAST                       33: _var_var_51
                3396    LOAD_FAST                       22: _var_var_40
                3398    LOAD_FAST                       21: _var_var_39
                3400    LOAD_FAST                       20: _var_var_38
                3402    LOAD_FAST                       18: _var_var_36
                3404    LOAD_FAST                       15: _var_var_33
                3406    LOAD_CONST                      6: False
                3408    LOAD_FAST                       23: _var_var_41
                3410    LOAD_FAST                       5: stop_thread
                3412    KW_NAMES                        80: ('config', 'lang', 'client', 'account', 'entity', 'message', 'silent', 'sending_time', 'link_preview', 'max_flood', 'delete_dialog', 'video_note', 'stop_thread')
                3414    CALL                            13
                3422    LOAD_ATTR                       61: direct
                3442    CALL                            0
                3450    STORE_FAST                      34: _var_var_52
                3452    LOAD_FAST                       34: _var_var_52
                3454    LOAD_CONST                      16: 0
                3456    BINARY_SUBSCR                   
                3460    LOAD_CONST                      71: 'Done'
                3462    COMPARE_OP                      55 (!=)
                3466    POP_JUMP_IF_FALSE               55 (to 3578)
                3468    LOAD_GLOBAL                     19: NULL + Logs
                3478    LOAD_ATTR                       20: PrintLog
                3498    LOAD_FAST                       1: config
                3500    LOAD_FAST                       0: account
                3502    PUSH_NULL                       
                3504    LOAD_CONST                      1: '__pyarmor_assert_14559__'
                3506    LOAD_CONST                      78: 'Error: Temp group is not created. Stop account'   # b'\x81\xc7\n\x01<\xe8\xe4\x92/\xff\x00\xd0,\xeb\xea\x8a\x1aM\xfb\xae\xb9\x8b@\xc3\x11/\xa0N\x05\xb0\n\xe0>\x1c`>\x8c\xc5\xa4n\x19\xea\xfbR\xc8\xd6\x1b'
                3508    CALL                            1
                3516    KW_NAMES                        52: ('config', 'account', 'message')
                3518    CALL                            3
                3526    POP_TOP                         
                3528    LOAD_FAST                       0: account
                3530    LOAD_CONST                      77: 'Error'
                3532    LOAD_CONST                      8: ('account', 'status')
                3534    BUILD_CONST_KEY_MAP             2
                3536    LOAD_GLOBAL                     7: NULL + Disconnect
                3546    LOAD_FAST                       7: _var_var_25
                3548    CALL                            1
                3556    POP_TOP                         
                3558    NOP                             
                3560    NOP                             
                3562    JUMP_FORWARD                    730 (to 5026)
                3566    CALL                            1
                3574    POP_TOP                         
                3576    RETURN_VALUE                    
                3578    LOAD_FAST                       34: _var_var_52
                3580    LOAD_CONST                      13: 1
                3582    BINARY_SUBSCR                   
                3586    STORE_FAST                      34: _var_var_52
                3588    LOAD_FAST                       25: _var_var_43
                3590    GET_ITER                        
                3592    FOR_ITER                        377 (to 4350)
                3598    STORE_FAST                      29: _var_var_47
                3600    LOAD_FAST                       5: stop_thread
                3602    LOAD_ATTR                       23: is_set
                3622    CALL                            0
                3630    POP_JUMP_IF_FALSE               10 (to 3652)
                3632    LOAD_GLOBAL                     25: NULL + StopProgram
                3642    CALL                            0
                3650    RAISE_VARARGS                   1
                3652    LOAD_GLOBAL                     51: NULL + DelayOnline
                3662    LOAD_FAST                       0: account
                3664    LOAD_FAST                       7: _var_var_25
                3666    LOAD_FAST                       11: _var_var_29
                3668    LOAD_FAST                       12: _var_var_30
                3670    LOAD_FAST                       5: stop_thread
                3672    CALL                            5
                3680    POP_TOP                         
                3682    LOAD_GLOBAL                     59: NULL + sender
                3692    LOAD_FAST                       1: config
                3694    LOAD_GLOBAL                     4: Lang
                3704    LOAD_FAST                       7: _var_var_25
                3706    LOAD_FAST                       0: account
                3708    LOAD_FAST                       29: _var_var_47
                3710    LOAD_CONST                      81: 'entity'
                3712    BINARY_SUBSCR                   
                3716    LOAD_FAST                       16: _var_var_34
                3718    POP_JUMP_IF_FALSE               2 (to 3724)
                3720    LOAD_FAST_CHECK                 34: _var_var_52
                3722    JUMP_FORWARD                    1 (to 3726)
                3724    LOAD_FAST                       22: _var_var_40
                3726    LOAD_FAST                       21: _var_var_39
                3728    LOAD_FAST                       20: _var_var_38
                3730    LOAD_FAST                       18: _var_var_36
                3732    LOAD_FAST                       15: _var_var_33
                3734    LOAD_CONST                      6: False
                3736    LOAD_FAST                       23: _var_var_41
                3738    LOAD_FAST                       3: data
                3740    LOAD_CONST                      10: 'Settings'
                3742    BINARY_SUBSCR                   
                3746    LOAD_ATTR                       9: get
                3766    PUSH_NULL                       
                3768    LOAD_CONST                      1: '__pyarmor_assert_14559__'
                3770    LOAD_CONST                      82: 'forward_drop_author'   # b'\x81\xe4\x17\x01$\xfb\xac\xd6$\xfe\x1f\xcf|\xd3\xf9\x90\x1bU\xb4\xb5'
                3772    CALL                            1
                3780    CALL                            1
                3788    LOAD_FAST                       5: stop_thread
                3790    KW_NAMES                        83: ('config', 'lang', 'client', 'account', 'entity', 'message', 'silent', 'sending_time', 'link_preview', 'max_flood', 'delete_dialog', 'video_note', 'forward_drop_author', 'stop_thread')
                3792    CALL                            14
                3800    STORE_FAST                      35: _var_var_53
                3802    LOAD_FAST                       16: _var_var_34
                3804    POP_JUMP_IF_FALSE               18 (to 3842)
                3806    LOAD_FAST                       35: _var_var_53
                3808    LOAD_ATTR                       63: repost
                3828    LOAD_FAST_CHECK                 33: _var_var_51
                3830    CALL                            1
                3838    STORE_FAST                      36: _var_var_54
                3840    JUMP_FORWARD                    16 (to 3874)
                3842    LOAD_FAST                       35: _var_var_53
                3844    LOAD_ATTR                       61: direct
                3864    CALL                            0
                3872    STORE_FAST                      36: _var_var_54
                3874    LOAD_FAST                       36: _var_var_54
                3876    LOAD_CONST                      16: 0
                3878    BINARY_SUBSCR                   
                3882    STORE_FAST                      37: _var_var_55
                3884    LOAD_FAST                       36: _var_var_54
                3886    LOAD_CONST                      84: 2
                3888    BINARY_SUBSCR                   
                3892    STORE_FAST                      38: _var_var_56
                3894    LOAD_FAST                       36: _var_var_54
                3896    LOAD_CONST                      85: 3
                3898    BINARY_SUBSCR                   
                3902    STORE_FAST                      39: _var_var_57
                3904    LOAD_FAST                       37: _var_var_55
                3906    PUSH_NULL                       
                3908    LOAD_CONST                      1: '__pyarmor_assert_14559__'
                3910    LOAD_CONST                      86: 'UserBannedInChannelError'   # b'\x81\xd7\x0b\x16!\xd8\xbf\xdc\x15\xff\t\xe9b\xcf\xf0\x84\x01S\xbe\xab\x8f\xd9\\\xc3\x17'
                3912    CALL                            1
                3920    COMPARE_OP                      40 (==)
                3924    POP_JUMP_IF_FALSE               4 (to 3934)
                3926    LOAD_FAST                       19: _var_var_37
                3928    POP_JUMP_IF_FALSE               2 (to 3934)
                3930    LOAD_CONST                      6: False
                3932    STORE_FAST                      39: _var_var_57
                3934    LOAD_FAST                       37: _var_var_55
                3936    PUSH_NULL                       
                3938    LOAD_CONST                      1: '__pyarmor_assert_14559__'
                3940    LOAD_CONST                      87: 'PeerFloodError'   # b'\x81\xd2\x1d\x16!\xdc\xb2\xdd\x14\xfe(\xd2~\xe3\xea'
                3942    CALL                            1
                3950    COMPARE_OP                      40 (==)
                3954    POP_JUMP_IF_FALSE               12 (to 3980)
                3956    LOAD_FAST                       28: _var_var_46
                3958    LOAD_CONST                      16: 0
                3960    COMPARE_OP                      68 (>)
                3964    POP_JUMP_IF_FALSE               7 (to 3980)
                3966    LOAD_FAST                       28: _var_var_46
                3968    LOAD_CONST                      13: 1
                3970    BINARY_OP                       23 (-=)
                3974    STORE_FAST                      28: _var_var_46
                3976    LOAD_CONST                      6: False
                3978    STORE_FAST                      39: _var_var_57
                3980    LOAD_GLOBAL                     65: NULL + db_statistic
                3990    LOAD_FAST                       4: statistic
                3992    CALL                            1
                4000    LOAD_ATTR                       67: insert
                4020    LOAD_FAST                       0: account
                4022    LOAD_FAST                       29: _var_var_47
                4024    LOAD_CONST                      58: 'info'
                4026    BINARY_SUBSCR                   
                4030    LOAD_CONST                      59: 'id'
                4032    BINARY_SUBSCR                   
                4036    LOAD_FAST                       29: _var_var_47
                4038    LOAD_CONST                      58: 'info'
                4040    BINARY_SUBSCR                   
                4044    LOAD_CONST                      49: 'username'
                4046    BINARY_SUBSCR                   
                4050    LOAD_FAST                       37: _var_var_55
                4052    LOAD_FAST                       38: _var_var_56
                4054    KW_NAMES                        88: ('account', 'group_id', 'group_link', 'send_status', 'message')
                4056    CALL                            5
                4064    POP_TOP                         
                4066    LOAD_GLOBAL                     19: NULL + Logs
                4076    LOAD_ATTR                       20: PrintLog
                4096    LOAD_FAST                       1: config
                4098    LOAD_FAST                       0: account
                4100    LOAD_CONST                      89: 'Send - '
                4102    LOAD_FAST                       29: _var_var_47
                4104    LOAD_CONST                      58: 'info'
                4106    BINARY_SUBSCR                   
                4110    LOAD_CONST                      59: 'id'
                4112    BINARY_SUBSCR                   
                4116    FORMAT_VALUE                    0 (FVC_NONE)
                4118    LOAD_CONST                      90: ':'
                4120    LOAD_FAST                       29: _var_var_47
                4122    LOAD_CONST                      58: 'info'
                4124    BINARY_SUBSCR                   
                4128    LOAD_CONST                      60: 'title'
                4130    BINARY_SUBSCR                   
                4134    FORMAT_VALUE                    0 (FVC_NONE)
                4136    BUILD_STRING                    4
                4138    LOAD_CONST                      91: 'Status: '
                4140    LOAD_FAST                       37: _var_var_55
                4142    FORMAT_VALUE                    0 (FVC_NONE)
                4144    BUILD_STRING                    2
                4146    KW_NAMES                        92: ('config', 'account', 'message', 'end')
                4148    CALL                            4
                4156    POP_TOP                         
                4158    LOAD_FAST                       17: _var_var_35
                4160    POP_JUMP_IF_FALSE               77 (to 4316)
                4162    LOAD_GLOBAL                     35: NULL + tg_group
                4172    LOAD_FAST                       1: config
                4174    LOAD_FAST                       7: _var_var_25
                4176    LOAD_FAST                       0: account
                4178    LOAD_FAST                       15: _var_var_33
                4180    LOAD_GLOBAL                     4: Lang
                4190    LOAD_FAST                       5: stop_thread
                4192    KW_NAMES                        93: ('config', 'client', 'account', 'max_flood_wait', 'lang', 'stop_thread')
                4194    CALL                            6
                4202    LOAD_ATTR                       69: go_out
                4222    LOAD_FAST                       29: _var_var_47
                4224    LOAD_CONST                      81: 'entity'
                4226    BINARY_SUBSCR                   
                4230    KW_NAMES                        94: ('entity',)
                4232    CALL                            1
                4240    POP_TOP                         
                4242    LOAD_GLOBAL                     19: NULL + Logs
                4252    LOAD_ATTR                       20: PrintLog
                4272    LOAD_FAST                       1: config
                4274    LOAD_FAST                       0: account
                4276    PUSH_NULL                       
                4278    LOAD_CONST                      1: '__pyarmor_assert_14559__'
                4280    LOAD_CONST                      95: 'Left group:'   # b"\x81\xce\x1d\x15'\xba\xb9\xc0\x14\xef\x1d\x9a"
                4282    CALL                            1
                4290    LOAD_FAST                       29: _var_var_47
                4292    LOAD_CONST                      58: 'info'
                4294    BINARY_SUBSCR                   
                4298    LOAD_CONST                      60: 'title'
                4300    BINARY_SUBSCR                   
                4304    KW_NAMES                        48: ('config', 'account', 'message', 'param')
                4306    CALL                            4
                4314    POP_TOP                         
                4316    LOAD_FAST                       39: _var_var_57
                4318    POP_JUMP_IF_FALSE               2 (to 4324)
                4320    POP_TOP                         
                4322    JUMP_FORWARD                    15 (to 4354)
                4324    LOAD_FAST                       26: _var_var_44
                4326    LOAD_CONST                      13: 1
                4328    BINARY_OP                       13 (+=)
                4332    STORE_FAST                      26: _var_var_44
                4334    LOAD_FAST                       26: _var_var_44
                4336    LOAD_FAST                       24: _var_var_42
                4338    COMPARE_OP                      92 (>=)
                4342    POP_JUMP_IF_TRUE                2 (to 4348)
                4344    JUMP_BACKWARD                   378 (to 3592)
                4348    POP_TOP                         
                4350    JUMP_FORWARD                    1 (to 4354)
                4352    END_FOR                         
                4354    LOAD_FAST                       16: _var_var_34
                4356    POP_JUMP_IF_FALSE               26 (to 4410)
                4358    LOAD_GLOBAL                     55: NULL + temp_group
                4368    LOAD_FAST                       7: _var_var_25
                4370    CALL                            1
                4378    LOAD_ATTR                       71: delete
                4398    LOAD_FAST_CHECK                 33: _var_var_51
                4400    CALL                            1
                4408    POP_TOP                         
                4410    LOAD_GLOBAL                     7: NULL + Disconnect
                4420    LOAD_FAST_CHECK                 7: _var_var_25
                4422    CALL                            1
                4430    POP_TOP                         
                4432    LOAD_GLOBAL                     19: NULL + Logs
                4442    LOAD_ATTR                       20: PrintLog
                4462    LOAD_FAST                       1: config
                4464    LOAD_FAST                       0: account
                4466    LOAD_GLOBAL                     4: Lang
                4476    PUSH_NULL                       
                4478    LOAD_CONST                      1: '__pyarmor_assert_14559__'
                4480    LOAD_CONST                      96: 'work_account_completed'   # b'\x81\xf5\x17\x018\xc5\xbf\xd1\x18\xf5\x18\xcex\xd3\xfb\x8a\x02M\xb7\xa2\xbe\xceJ'
                4482    CALL                            1
                4490    BINARY_SUBSCR                   
                4494    KW_NAMES                        52: ('config', 'account', 'message')
                4496    CALL                            3
                4504    POP_TOP                         
                4506    LOAD_FAST                       0: account
                4508    LOAD_CONST                      97: 'done'
                4510    LOAD_CONST                      8: ('account', 'status')
                4512    BUILD_CONST_KEY_MAP             2
                4514    NOP                             
                4516    NOP                             
                4518    NOP                             
                4520    JUMP_FORWARD                    252 (to 5026)
                4522    CALL                            1
                4530    POP_TOP                         
                4532    RETURN_VALUE                    
                4534    PUSH_EXC_INFO                   
                4536    POP_TOP                         
                4538    POP_EXCEPT                      
                4540    JUMP_BACKWARD                   2197 (to 150)
                4544    COPY                            3
                4546    POP_EXCEPT                      
                4548    RERAISE                         1
                4550    PUSH_EXC_INFO                   
                4552    POP_TOP                         
                4554    POP_EXCEPT                      
                4556    JUMP_BACKWARD                   730 (to 3100)
                4560    COPY                            3
                4562    POP_EXCEPT                      
                4564    RERAISE                         1
                4566    PUSH_EXC_INFO                   
                4568    POP_TOP                         
                4570    POP_EXCEPT                      
                4572    JUMP_BACKWARD                   651 (to 3274)
                4576    COPY                            3
                4578    POP_EXCEPT                      
                4580    RERAISE                         1
                4582    PUSH_EXC_INFO                   
                4584    POP_TOP                         
                4586    POP_EXCEPT                      
                4588    JUMP_BACKWARD                   517 (to 3558)
                4592    COPY                            3
                4594    POP_EXCEPT                      
                4596    RERAISE                         1
                4598    PUSH_EXC_INFO                   
                4600    LOAD_GLOBAL                     24: StopProgram
                4610    CHECK_EXC_MATCH                 
                4612    POP_JUMP_IF_FALSE               3 (to 4620)
                4614    POP_TOP                         
                4616    POP_EXCEPT                      
                4618    JUMP_BACKWARD                   105 (to 4410)
                4620    LOAD_GLOBAL                     72: StopAccount
                4630    LOAD_GLOBAL                     74: PeerFlood
                4640    LOAD_GLOBAL                     76: MaxFlood
                4650    LOAD_GLOBAL                     78: BanAccount
                4660    BUILD_TUPLE                     4
                4662    CHECK_EXC_MATCH                 
                4664    POP_JUMP_IF_FALSE               98 (to 4862)
                4666    STORE_FAST                      40: _var_var_3
                4668    LOAD_GLOBAL                     19: NULL + Logs
                4678    LOAD_ATTR                       20: PrintLog
                4698    LOAD_FAST                       1: config
                4700    LOAD_FAST                       0: account
                4702    LOAD_GLOBAL                     4: Lang
                4712    PUSH_NULL                       
                4714    LOAD_CONST                      1: '__pyarmor_assert_14559__'
                4716    LOAD_CONST                      96: 'work_account_completed'   # b'\x81\xf5\x17\x018\xc5\xbf\xd1\x18\xf5\x18\xcex\xd3\xfb\x8a\x02M\xb7\xa2\xbe\xceJ'
                4718    CALL                            1
                4726    BINARY_SUBSCR                   
                4730    LOAD_FAST                       40: _var_var_3
                4732    LOAD_ATTR                       80: status
                4752    KW_NAMES                        92: ('config', 'account', 'message', 'end')
                4754    CALL                            4
                4762    POP_TOP                         
                4764    LOAD_FAST                       40: _var_var_3
                4766    LOAD_ATTR                       82: result
                4786    SWAP                            2
                4788    POP_EXCEPT                      
                4790    LOAD_CONST                      0: None
                4792    STORE_FAST                      40: _var_var_3
                4794    DELETE_FAST                     40: _var_var_3
                4796    LOAD_GLOBAL                     7: NULL + Disconnect
                4806    LOAD_FAST_CHECK                 7: _var_var_25
                4808    CALL                            1
                4816    POP_TOP                         
                4818    JUMP_FORWARD                    7 (to 4834)
                4820    PUSH_EXC_INFO                   
                4822    POP_TOP                         
                4824    POP_EXCEPT                      
                4826    JUMP_FORWARD                    3 (to 4834)
                4828    COPY                            3
                4830    POP_EXCEPT                      
                4832    RERAISE                         1
                4834    NOP                             
                4836    NOP                             
                4838    NOP                             
                4840    JUMP_FORWARD                    92 (to 5026)
                4842    CALL                            1
                4850    POP_TOP                         
                4852    RETURN_VALUE                    
                4854    LOAD_CONST                      0: None
                4856    STORE_FAST                      40: _var_var_3
                4858    DELETE_FAST                     40: _var_var_3
                4860    RERAISE                         1
                4862    LOAD_GLOBAL                     84: Exception
                4872    CHECK_EXC_MATCH                 
                4874    POP_JUMP_IF_FALSE               26 (to 4928)
                4876    STORE_FAST                      40: _var_var_3
                4878    PUSH_NULL                       
                4880    LOAD_GLOBAL                     87: NULL + logging
                4890    LOAD_FAST                       40: _var_var_3
                4892    CALL                            1
                4900    CALL                            0
                4908    POP_TOP                         
                4910    POP_EXCEPT                      
                4912    LOAD_CONST                      0: None
                4914    STORE_FAST                      40: _var_var_3
                4916    DELETE_FAST                     40: _var_var_3
                4918    JUMP_BACKWARD                   255 (to 4410)
                4920    LOAD_CONST                      0: None
                4922    STORE_FAST                      40: _var_var_3
                4924    DELETE_FAST                     40: _var_var_3
                4926    RERAISE                         1
                4928    RERAISE                         0
                4930    COPY                            3
                4932    POP_EXCEPT                      
                4934    RERAISE                         1
                4936    PUSH_EXC_INFO                   
                4938    POP_TOP                         
                4940    POP_EXCEPT                      
                4942    JUMP_BACKWARD                   257 (to 4432)
                4946    COPY                            3
                4948    POP_EXCEPT                      
                4950    RERAISE                         1
                4952    PUSH_EXC_INFO                   
                4954    LOAD_GLOBAL                     7: NULL + Disconnect
                4964    LOAD_FAST_CHECK                 7: _var_var_25
                4966    CALL                            1
                4974    POP_TOP                         
                4976    RERAISE                         0
                4978    PUSH_EXC_INFO                   
                4980    POP_TOP                         
                4982    POP_EXCEPT                      
                4984    RERAISE                         0
                4986    COPY                            3
                4988    POP_EXCEPT                      
                4990    RERAISE                         1
                4992    COPY                            3
                4994    POP_EXCEPT                      
                4996    RERAISE                         1
                4998    PUSH_EXC_INFO                   
                5000    PUSH_NULL                       
                5002    LOAD_CONST                      9: '__pyarmor_exit_14561__'
                5004    NOP                             
                5006    LOAD_CONST                      3: b'<COAddr>\x07\x00\x00\x1al\x13\x00\x00\x00\x00\x00\x00\x00\x00\x00\x00\x00\x00\x00\x00'
                5008    CALL                            1
                5016    POP_TOP                         
                5018    RERAISE                         0
                5020    COPY                            3
                5022    POP_EXCEPT                      
                5024    RERAISE                         1
                5026    PUSH_NULL                       
                5028    LOAD_CONST                      9: '__pyarmor_exit_14561__'
                5030    LOAD_CONST                      3: b'<COAddr>\x07\x00\x00\x1al\x13\x00\x00\x00\x00\x00\x00\x00\x00\x00\x00\x00\x00\x00\x00'
                5032    BUILD_TUPLE                     1
                5034    CALL_FUNCTION_EX                0
                5036    POP_TOP                         
                5038    RETURN_VALUE                    
            [Exception Table]
                30 to 128 -> 4598 [0] 
                128 to 150 -> 4534 [1] 
                170 to 2978 -> 4598 [0] 
                2982 to 3078 -> 4598 [0] 
                3078 to 3100 -> 4550 [1] 
                3120 to 3252 -> 4598 [0] 
                3252 to 3274 -> 4566 [1] 
                3294 to 3536 -> 4598 [0] 
                3536 to 3558 -> 4582 [1] 
                3578 to 4344 -> 4598 [0] 
                4348 to 4410 -> 4598 [0] 
                4410 to 4432 -> 4936 [0] 
                4432 to 4514 -> 4998 [0] 
                4534 to 4538 -> 4544 [2] lasti
                4538 to 4550 -> 4998 [0] 
                4550 to 4554 -> 4560 [2] lasti
                4554 to 4566 -> 4998 [0] 
                4566 to 4570 -> 4576 [2] lasti
                4570 to 4582 -> 4998 [0] 
                4582 to 4586 -> 4592 [2] lasti
                4586 to 4598 -> 4998 [0] 
                4598 to 4616 -> 4930 [1] lasti
                4616 to 4620 -> 4952 [0] 
                4620 to 4668 -> 4930 [1] lasti
                4668 to 4786 -> 4854 [1] lasti
                4786 to 4788 -> 4930 [1] lasti
                4788 to 4796 -> 4952 [0] 
                4796 to 4818 -> 4820 [1] 
                4818 to 4820 -> 4998 [0] 
                4820 to 4824 -> 4828 [2] lasti
                4824 to 4834 -> 4998 [0] 
                4854 to 4878 -> 4930 [1] lasti
                4878 to 4910 -> 4920 [1] lasti
                4910 to 4920 -> 4952 [0] 
                4920 to 4930 -> 4930 [1] lasti
                4930 to 4936 -> 4952 [0] 
                4936 to 4940 -> 4946 [1] lasti
                4940 to 4952 -> 4998 [0] 
                4952 to 4954 -> 4992 [1] lasti
                4954 to 4976 -> 4978 [2] 
                4976 to 4978 -> 4992 [1] lasti
                4978 to 4982 -> 4986 [3] lasti
                4982 to 4992 -> 4992 [1] lasti
                4992 to 4998 -> 4998 [0] 
                4998 to 5020 -> 5020 [1] lasti
        '__pyarmor_exit_14552__'
    [Disassembly]
        0       NOP                             
        2       NOP                             
        4       PUSH_NULL                       
        6       LOAD_CONST                      1: '__pyarmor_enter_14551__'
        8       LOAD_CONST                      2: b'<COAddr>\x05\x00\x00\x1a\xd2\x01\x00\x00\x00\x00\x00\x00\x00\x00\x00\x00\x00\x00\x00\x00'
        10      BUILD_TUPLE                     1
        12      CALL_FUNCTION_EX                0
        14      POP_TOP                         
        16      RESUME                          0
        18      NOP                             
        20      NOP                             
        22      NOP                             
        24      NOP                             
        26      LOAD_CONST                      3: 0
        28      LOAD_CONST                      4: None
        30      IMPORT_NAME                     1: os
        32      STORE_NAME                      1: os
        34      LOAD_CONST                      3: 0
        36      LOAD_CONST                      4: None
        38      IMPORT_NAME                     2: eel
        40      STORE_NAME                      2: eel
        42      LOAD_CONST                      3: 0
        44      LOAD_CONST                      4: None
        46      IMPORT_NAME                     3: json
        48      STORE_NAME                      3: json
        50      LOAD_CONST                      3: 0
        52      LOAD_CONST                      4: None
        54      IMPORT_NAME                     4: random
        56      STORE_NAME                      4: random
        58      LOAD_CONST                      3: 0
        60      LOAD_CONST                      4: None
        62      IMPORT_NAME                     5: datetime
        64      STORE_NAME                      5: datetime
        66      LOAD_CONST                      3: 0
        68      LOAD_CONST                      4: None
        70      IMPORT_NAME                     6: concurrent.futures
        72      STORE_NAME                      7: concurrent
        74      LOAD_CONST                      3: 0
        76      LOAD_CONST                      5: ('Thread', 'Event')
        78      IMPORT_NAME                     8: threading
        80      IMPORT_FROM                     9: Thread
        82      STORE_NAME                      9: Thread
        84      IMPORT_FROM                     10: Event
        86      STORE_NAME                      10: Event
        88      POP_TOP                         
        90      LOAD_CONST                      3: 0
        92      LOAD_CONST                      6: ('StopProgram',)
        94      IMPORT_NAME                     11: multithon.errors
        96      IMPORT_FROM                     12: StopProgram
        98      STORE_NAME                      12: StopProgram
        100     POP_TOP                         
        102     LOAD_CONST                      3: 0
        104     LOAD_CONST                      7: ('AutoStop',)
        106     IMPORT_NAME                     13: program.static_classes
        108     IMPORT_FROM                     14: AutoStop
        110     STORE_NAME                      14: AutoStop
        112     POP_TOP                         
        114     LOAD_CONST                      3: 0
        116     LOAD_CONST                      8: ('BanAccount',)
        118     IMPORT_NAME                     13: program.static_classes
        120     IMPORT_FROM                     15: BanAccount
        122     STORE_NAME                      15: BanAccount
        124     POP_TOP                         
        126     LOAD_CONST                      3: 0
        128     LOAD_CONST                      9: ('GetLang',)
        130     IMPORT_NAME                     13: program.static_classes
        132     IMPORT_FROM                     16: GetLang
        134     STORE_NAME                      16: GetLang
        136     POP_TOP                         
        138     LOAD_CONST                      3: 0
        140     LOAD_CONST                      10: ('Logs',)
        142     IMPORT_NAME                     13: program.static_classes
        144     IMPORT_FROM                     17: Logs
        146     STORE_NAME                      17: Logs
        148     POP_TOP                         
        150     LOAD_CONST                      3: 0
        152     LOAD_CONST                      11: ('MaxFlood',)
        154     IMPORT_NAME                     13: program.static_classes
        156     IMPORT_FROM                     18: MaxFlood
        158     STORE_NAME                      18: MaxFlood
        160     POP_TOP                         
        162     LOAD_CONST                      3: 0
        164     LOAD_CONST                      12: ('PeerFlood',)
        166     IMPORT_NAME                     13: program.static_classes
        168     IMPORT_FROM                     19: PeerFlood
        170     STORE_NAME                      19: PeerFlood
        172     POP_TOP                         
        174     LOAD_CONST                      3: 0
        176     LOAD_CONST                      13: ('StopAccount',)
        178     IMPORT_NAME                     13: program.static_classes
        180     IMPORT_FROM                     20: StopAccount
        182     STORE_NAME                      20: StopAccount
        184     POP_TOP                         
        186     LOAD_CONST                      3: 0
        188     LOAD_CONST                      14: ('check_module',)
        190     IMPORT_NAME                     13: program.static_classes
        192     IMPORT_FROM                     21: check_module
        194     STORE_NAME                      21: check_module
        196     POP_TOP                         
        198     LOAD_CONST                      3: 0
        200     LOAD_CONST                      15: ('logging',)
        202     IMPORT_NAME                     13: program.static_classes
        204     IMPORT_FROM                     22: logging
        206     STORE_NAME                      22: logging
        208     POP_TOP                         
        210     LOAD_CONST                      3: 0
        212     LOAD_CONST                      16: ('memory_check_switcher',)
        214     IMPORT_NAME                     13: program.static_classes
        216     IMPORT_FROM                     23: memory_check_switcher
        218     STORE_NAME                      23: memory_check_switcher
        220     POP_TOP                         
        222     LOAD_CONST                      3: 0
        224     LOAD_CONST                      17: ('memory_set_pid',)
        226     IMPORT_NAME                     13: program.static_classes
        228     IMPORT_FROM                     24: memory_set_pid
        230     STORE_NAME                      24: memory_set_pid
        232     POP_TOP                         
        234     LOAD_CONST                      3: 0
        236     LOAD_CONST                      18: ('DelayOnline',)
        238     IMPORT_NAME                     25: program.telegram
        240     IMPORT_FROM                     26: DelayOnline
        242     STORE_NAME                      26: DelayOnline
        244     POP_TOP                         
        246     LOAD_CONST                      3: 0
        248     LOAD_CONST                      19: ('Disconnect',)
        250     IMPORT_NAME                     25: program.telegram
        252     IMPORT_FROM                     27: Disconnect
        254     STORE_NAME                      27: Disconnect
        256     POP_TOP                         
        258     LOAD_CONST                      3: 0
        260     LOAD_CONST                      20: ('Restart_wait',)
        262     IMPORT_NAME                     25: program.telegram
        264     IMPORT_FROM                     28: Restart_wait
        266     STORE_NAME                      28: Restart_wait
        268     POP_TOP                         
        270     LOAD_CONST                      3: 0
        272     LOAD_CONST                      21: ('Thread_wait',)
        274     IMPORT_NAME                     25: program.telegram
        276     IMPORT_FROM                     29: Thread_wait
        278     STORE_NAME                      29: Thread_wait
        280     POP_TOP                         
        282     LOAD_CONST                      3: 0
        284     LOAD_CONST                      22: ('account_works',)
        286     IMPORT_NAME                     25: program.telegram
        288     IMPORT_FROM                     30: account_works
        290     STORE_NAME                      30: account_works
        292     POP_TOP                         
        294     LOAD_CONST                      3: 0
        296     LOAD_CONST                      23: ('entity',)
        298     IMPORT_NAME                     25: program.telegram
        300     IMPORT_FROM                     31: entity
        302     STORE_NAME                      31: entity
        304     POP_TOP                         
        306     LOAD_CONST                      3: 0
        308     LOAD_CONST                      24: ('tg_group',)
        310     IMPORT_NAME                     25: program.telegram
        312     IMPORT_FROM                     32: tg_group
        314     STORE_NAME                      32: tg_group
        316     POP_TOP                         
        318     LOAD_CONST                      3: 0
        320     LOAD_CONST                      25: ('tg_links',)
        322     IMPORT_NAME                     25: program.telegram
        324     IMPORT_FROM                     33: tg_links
        326     STORE_NAME                      33: tg_links
        328     POP_TOP                         
        330     LOAD_CONST                      3: 0
        332     LOAD_CONST                      26: ('GetConfig',)
        334     IMPORT_NAME                     34: program.general
        336     IMPORT_FROM                     35: GetConfig
        338     STORE_NAME                      35: GetConfig
        340     POP_TOP                         
        342     LOAD_CONST                      3: 0
        344     LOAD_CONST                      27: ('GetProxy',)
        346     IMPORT_NAME                     34: program.general
        348     IMPORT_FROM                     36: GetProxy
        350     STORE_NAME                      36: GetProxy
        352     POP_TOP                         
        354     LOAD_CONST                      3: 0
        356     LOAD_CONST                      28: ('StopDetect',)
        358     IMPORT_NAME                     34: program.general
        360     IMPORT_FROM                     37: StopDetect
        362     STORE_NAME                      37: StopDetect
        364     POP_TOP                         
        366     LOAD_CONST                      3: 0
        368     LOAD_CONST                      29: ('check_get_settings',)
        370     IMPORT_NAME                     34: program.general
        372     IMPORT_FROM                     38: check_get_settings
        374     STORE_NAME                      38: check_get_settings
        376     POP_TOP                         
        378     LOAD_CONST                      3: 0
        380     LOAD_CONST                      30: ('del_task_manager',)
        382     IMPORT_NAME                     34: program.general
        384     IMPORT_FROM                     39: del_task_manager
        386     STORE_NAME                      39: del_task_manager
        388     POP_TOP                         
        390     LOAD_CONST                      3: 0
        392     LOAD_CONST                      31: ('getFile',)
        394     IMPORT_NAME                     34: program.general
        396     IMPORT_FROM                     40: getFile
        398     STORE_NAME                      40: getFile
        400     POP_TOP                         
        402     LOAD_CONST                      3: 0
        404     LOAD_CONST                      32: ('set_task_manager',)
        406     IMPORT_NAME                     34: program.general
        408     IMPORT_FROM                     41: set_task_manager
        410     STORE_NAME                      41: set_task_manager
        412     POP_TOP                         
        414     LOAD_CONST                      3: 0
        416     LOAD_CONST                      33: ('db_parsing',)
        418     IMPORT_NAME                     42: program.database
        420     IMPORT_FROM                     43: db_parsing
        422     STORE_NAME                      43: db_parsing
        424     POP_TOP                         
        426     LOAD_CONST                      3: 0
        428     LOAD_CONST                      34: ('db_statistic',)
        430     IMPORT_NAME                     42: program.database
        432     IMPORT_FROM                     44: db_statistic
        434     STORE_NAME                      44: db_statistic
        436     POP_TOP                         
        438     LOAD_CONST                      35: 1
        440     LOAD_CONST                      36: ('sender', 'temp_group')
        442     IMPORT_NAME                     45: func.sender
        444     IMPORT_FROM                     46: sender
        446     STORE_NAME                      46: sender
        448     IMPORT_FROM                     47: temp_group
        450     STORE_NAME                      47: temp_group
        452     POP_TOP                         
        454     LOAD_CONST                      37: <CODE> Send_groups
        456     MAKE_FUNCTION                   0
        458     STORE_NAME                      48: Send_groups
        460     LOAD_CONST                      38: <CODE> START
        462     MAKE_FUNCTION                   0
        464     STORE_NAME                      49: START
        466     LOAD_CONST                      39: <CODE> worker
        468     MAKE_FUNCTION                   0
        470     STORE_NAME                      50: worker
        472     LOAD_CONST                      4: None
        474     NOP                             
        476     NOP                             
        478     NOP                             
        480     JUMP_FORWARD                    19 (to 520)
        488     POP_TOP                         
        490     RETURN_CONST                    4: None
        492     PUSH_EXC_INFO                   
        494     PUSH_NULL                       
        496     LOAD_CONST                      40: '__pyarmor_exit_14552__'
        498     NOP                             
        500     LOAD_CONST                      2: b'<COAddr>\x05\x00\x00\x1a\xd2\x01\x00\x00\x00\x00\x00\x00\x00\x00\x00\x00\x00\x00\x00\x00'
        502     CALL                            1
        510     POP_TOP                         
        512     RERAISE                         0
        514     COPY                            3
        516     POP_EXCEPT                      
        518     RERAISE                         1
        520     PUSH_NULL                       
        522     LOAD_CONST                      40: '__pyarmor_exit_14552__'
        524     LOAD_CONST                      2: b'<COAddr>\x05\x00\x00\x1a\xd2\x01\x00\x00\x00\x00\x00\x00\x00\x00\x00\x00\x00\x00\x00\x00'
        526     BUILD_TUPLE                     1
        528     CALL_FUNCTION_EX                0
        530     POP_TOP                         
        532     RETURN_VALUE                    
    [Exception Table]
        26 to 472 -> 492 [0] 
        492 to 514 -> 514 [1] lasti
