#decoded by lolz.live/mrpenny / t.me/zeus_jackpot
# ================================
# Примечания по Pyarmor:
# - Байт-код и объекты кода Pyarmor соответствуют стандартному Python, но присутствуют специальные вызовы функций среды выполнения (runtime) Pyarmor.
# - Вызовы строк — это не ошибки, а маркеры, которые обрабатываются Pyarmor во время выполнения.
#
# Руководство по декомпиляции (без среды выполнения):
# 1. Игнорируйте зашифрованные байты после `#`; используйте только строку до `#`.
# 2. Удалите "__pyarmor_enter_xxx__"(b"<COAddr>...") и "__pyarmor_leave_xxx__"(b"<COAddr>...") (пролог/эпилог).
# 3. "__pyarmor_assert_xxx__"(A) не является настоящим оператором assert.
#    - Если A — это имя или читаемая строка: замените на A.
#    - Если A — это (X, "Y"): замените на X.Y.
#    - Если A — это (X, "Y", Z): замените на X.Y = Z.
#    - В противном случае: выберите наиболее подходящую/логичную замену.
# 4. "__pyarmor_bcc_xxx__"(...) указывает на машинный (нативный) код; тело функции недоступно. Добавьте комментарий.
# ================================

[Code]
    File Name: <frozen program.modules.Stat_generator>
    Object Name: <module>
    Qualified Name: <module>
    Arg Count: 0
    Pos Only Arg Count: 0
    KW Only Arg Count: 0
    Stack Size: 5
    Flags: 0x20000000 (CO_PYARMOR_OBFUSCATED)
    [Names]
        '__assert_armored__'
        'eel'
        'sqlite3'
        'datetime'
        'threading'
        'Thread'
        'Event'
        'multithon.errors'
        'StopProgram'
        'program.static_classes'
        'GetLang'
        'Logs'
        'memory_set_pid'
        'program.general'
        'GetConfig'
        'StopDetect'
        'getFile'
        'Stat_generator'
        'START_Stat_generator'
    [Locals+Names]
    [Constants]
        '__pyarmor_assert_14658__'
        '__pyarmor_enter_14659__'
        b'<COAddr>\x07\x00\x00\x1a\xb4\x00\x00\x00\x00\x00\x00\x00\x00\x00\x00\x00\x00\x00\x00\x00'
        0
        None
        (
            'Thread'
            'Event'
        )
        (
            'StopProgram'
        )
        (
            'GetLang'
        )
        (
            'Logs'
        )
        (
            'memory_set_pid'
        )
        (
            'GetConfig'
        )
        (
            'StopDetect'
        )
        (
            'getFile'
        )
        [Code]
            File Name: <frozen program.modules.Stat_generator>
            Object Name: Stat_generator
            Qualified Name: Stat_generator
            Arg Count: 1
            Pos Only Arg Count: 0
            KW Only Arg Count: 0
            Stack Size: 7
            Flags: 0x20000003 (CO_OPTIMIZED | CO_NEWLOCALS | CO_PYARMOR_OBFUSCATED)
            [Names]
                'get'
                'getFile'
                'GetConfig'
                'config'
                'GetLang'
                'Lang'
                'Event'
                'memory_set_pid'
                'Thread'
                'START_Stat_generator'
                'start'
                'Logs'
                'WaitStopAnsfer'
                'UpdateLogInWindow'
                'Exception'
                'print'
                'str'
            [Locals+Names]
                'data'
                '__assert_armored__'
                '_var_var_0'
                '_var_var_1'
                '_var_var_2'
            [Constants]
                None
                '__pyarmor_assert_14661__'
                '__pyarmor_enter_14662__'
                b'<COAddr>\x05\x00\x00\x1aL\x02\x00\x00\x00\x00\x00\x00\x00\x00\x00\x00\x00\x00\x00\x00'
                'action'
                'getFile'
                '__pyarmor_exit_14663__'
                (
                    'target'
                    'args'
                )
                True
                (
                    'target'
                    'args'
                    'daemon'
                )
                'Stat_union: '   # b"\x81\xd1\x0c\x12'\xc5\xab\xdc\x12\xf5\x03\x9a,"
                False
            [Disassembly]
                0       NOP                             
                2       NOP                             
                4       PUSH_NULL                       
                6       LOAD_CONST                      2: '__pyarmor_enter_14662__'
                8       LOAD_CONST                      3: b'<COAddr>\x05\x00\x00\x1aL\x02\x00\x00\x00\x00\x00\x00\x00\x00\x00\x00\x00\x00\x00\x00'
                10      BUILD_TUPLE                     1
                12      CALL_FUNCTION_EX                0
                14      POP_TOP                         
                16      RESUME                          0
                18      NOP                             
                20      NOP                             
                22      NOP                             
                24      NOP                             
                26      NOP                             
                28      NOP                             
                30      LOAD_FAST                       0: data
                32      LOAD_ATTR                       1: get
                52      LOAD_CONST                      4: 'action'
                54      CALL                            1
                62      POP_JUMP_IF_NONE                28 (to 120)
                64      LOAD_FAST                       0: data
                66      LOAD_CONST                      4: 'action'
                68      BINARY_SUBSCR                   
                72      LOAD_CONST                      5: 'getFile'
                74      COMPARE_OP                      40 (==)
                78      POP_JUMP_IF_FALSE               20 (to 120)
                80      LOAD_GLOBAL                     3: NULL + getFile
                90      LOAD_FAST                       0: data
                92      CALL                            1
                100     NOP                             
                102     NOP                             
                104     JUMP_FORWARD                    267 (to 642)
                108     CALL                            1
                116     POP_TOP                         
                118     RETURN_VALUE                    
                120     LOAD_GLOBAL                     5: NULL + GetConfig
                130     CALL                            0
                138     STORE_GLOBAL                    3: config
                140     LOAD_GLOBAL                     9: NULL + GetLang
                150     LOAD_GLOBAL                     6: config
                160     CALL                            1
                168     STORE_GLOBAL                    5: Lang
                170     LOAD_GLOBAL                     13: NULL + Event
                180     CALL                            0
                188     STORE_FAST                      2: _var_var_0
                190     LOAD_GLOBAL                     15: NULL + memory_set_pid
                200     CALL                            0
                208     STORE_FAST                      3: _var_var_1
                210     LOAD_GLOBAL                     17: NULL + Thread
                220     LOAD_GLOBAL                     18: START_Stat_generator
                230     LOAD_FAST                       0: data
                232     LOAD_FAST                       2: _var_var_0
                234     BUILD_TUPLE                     2
                236     KW_NAMES                        7: ('target', 'args')
                238     CALL                            2
                246     LOAD_ATTR                       21: start
                266     CALL                            0
                274     POP_TOP                         
                276     LOAD_GLOBAL                     17: NULL + Thread
                286     LOAD_GLOBAL                     22: Logs
                296     LOAD_ATTR                       24: WaitStopAnsfer
                316     LOAD_GLOBAL                     6: config
                326     LOAD_FAST                       3: _var_var_1
                328     LOAD_FAST                       2: _var_var_0
                330     BUILD_TUPLE                     3
                332     LOAD_CONST                      8: True
                334     KW_NAMES                        9: ('target', 'args', 'daemon')
                336     CALL                            3
                344     LOAD_ATTR                       21: start
                364     CALL                            0
                372     POP_TOP                         
                374     LOAD_GLOBAL                     17: NULL + Thread
                384     LOAD_GLOBAL                     22: Logs
                394     LOAD_ATTR                       26: UpdateLogInWindow
                414     LOAD_GLOBAL                     6: config
                424     LOAD_FAST                       3: _var_var_1
                426     LOAD_FAST                       2: _var_var_0
                428     BUILD_TUPLE                     3
                430     LOAD_CONST                      8: True
                432     KW_NAMES                        9: ('target', 'args', 'daemon')
                434     CALL                            3
                442     LOAD_ATTR                       21: start
                462     CALL                            0
                470     POP_TOP                         
                472     NOP                             
                474     LOAD_CONST                      8: True
                476     NOP                             
                478     NOP                             
                480     NOP                             
                482     JUMP_FORWARD                    79 (to 642)
                490     POP_TOP                         
                492     RETURN_CONST                    8: True
                494     PUSH_EXC_INFO                   
                496     LOAD_GLOBAL                     28: Exception
                506     CHECK_EXC_MATCH                 
                508     POP_JUMP_IF_FALSE               48 (to 606)
                510     STORE_FAST                      4: _var_var_2
                512     LOAD_GLOBAL                     31: NULL + print
                522     PUSH_NULL                       
                524     LOAD_CONST                      1: '__pyarmor_assert_14661__'
                526     LOAD_CONST                      10: 'Stat_union: '   # b"\x81\xd1\x0c\x12'\xc5\xab\xdc\x12\xf5\x03\x9a,"
                528     CALL                            1
                536     LOAD_GLOBAL                     33: NULL + str
                546     LOAD_FAST                       4: _var_var_2
                548     CALL                            1
                556     BINARY_OP                       0 (+)
                560     CALL                            1
                568     POP_TOP                         
                570     POP_EXCEPT                      
                572     LOAD_CONST                      0: None
                574     STORE_FAST                      4: _var_var_2
                576     DELETE_FAST                     4: _var_var_2
                578     LOAD_CONST                      11: False
                580     NOP                             
                582     NOP                             
                584     NOP                             
                586     JUMP_FORWARD                    27 (to 642)
                594     POP_TOP                         
                596     RETURN_CONST                    11: False
                598     LOAD_CONST                      0: None
                600     STORE_FAST                      4: _var_var_2
                602     DELETE_FAST                     4: _var_var_2
                604     RERAISE                         1
                606     RERAISE                         0
                608     COPY                            3
                610     POP_EXCEPT                      
                612     RERAISE                         1
                614     PUSH_EXC_INFO                   
                616     PUSH_NULL                       
                618     LOAD_CONST                      6: '__pyarmor_exit_14663__'
                620     NOP                             
                622     LOAD_CONST                      3: b'<COAddr>\x05\x00\x00\x1aL\x02\x00\x00\x00\x00\x00\x00\x00\x00\x00\x00\x00\x00\x00\x00'
                624     CALL                            1
                632     POP_TOP                         
                634     RERAISE                         0
                636     COPY                            3
                638     POP_EXCEPT                      
                640     RERAISE                         1
                642     PUSH_NULL                       
                644     LOAD_CONST                      6: '__pyarmor_exit_14663__'
                646     LOAD_CONST                      3: b'<COAddr>\x05\x00\x00\x1aL\x02\x00\x00\x00\x00\x00\x00\x00\x00\x00\x00\x00\x00\x00\x00'
                648     BUILD_TUPLE                     1
                650     CALL_FUNCTION_EX                0
                652     POP_TOP                         
                654     RETURN_VALUE                    
            [Exception Table]
                30 to 100 -> 494 [0] 
                120 to 472 -> 494 [0] 
                494 to 512 -> 608 [1] lasti
                512 to 570 -> 598 [1] lasti
                570 to 578 -> 614 [0] 
                598 to 608 -> 608 [1] lasti
                608 to 614 -> 614 [0] 
                614 to 636 -> 636 [1] lasti
        [Code]
            File Name: <frozen program.modules.Stat_generator>
            Object Name: START_Stat_generator
            Qualified Name: START_Stat_generator
            Arg Count: 2
            Pos Only Arg Count: 0
            KW Only Arg Count: 0
            Stack Size: 9
            Flags: 0x20000003 (CO_OPTIMIZED | CO_NEWLOCALS | CO_PYARMOR_OBFUSCATED)
            [Names]
                'get'
                'Logs'
                'LangCheck'
                'PrintLog'
                'Lang'
                'datetime'
                'now'
                'strftime'
                'sqlite3'
                'connect'
                'PARSE_DECLTYPES'
                'cursor'
                'execute'
                'fetchall'
                'open'
                'write'
                'str'
                'commit'
                'close'
                'eel'
                'WriteResult'
                'Exception'
                'StopDetect'
                'StopProgram'
                'print'
            [Locals+Names]
                'data'
                'stop_thread'
                '__assert_armored__'
                '_var_var_3'
                '_var_var_4'
                '_var_var_5'
                '_var_var_6'
                '_var_var_7'
                '_var_var_8'
                '_var_var_9'
                '_var_var_10'
                '_var_var_11'
                '_var_var_12'
                '_var_var_13'
                '_var_var_14'
                '_var_var_15'
                '_var_var_2'
            [Constants]
                None
                '__pyarmor_assert_14664__'
                '__pyarmor_enter_14665__'
                b'<COAddr>\x07\x00\x00\x1a\x08\t\x00\x00\x00\x00\x00\x00\x00\x00\x00\x00\x00\x00\x00\x00'
                'Settings'
                'file_db'
                'only_invite_done'   # b'\x81\xed\x16\x1f*\xc5\xb7\xdc\r\xf3\x19\xc5S\xe8\xf7\x8b\n'
                'only_send_done'   # b'\x81\xed\x16\x1f*\xc5\xad\xd7\x15\xfe2\xc4c\xe2\xfd'
                'program_running'   # b'\x81\xf2\n\x1c4\xe8\xbf\xdf$\xe8\x18\xceb\xe5\xf6\x82'
                (
                    'message'
                )
                '%Y-%m-%d_%H-%M-%S'   # b'\x81\xa7!^v\xf7\xf3\x97\x1f\xc5H\xe8!\xa9\xd5\xc8Jn'
                'additives/stat_generator/'   # b'\x81\xe3\x1c\x17:\xee\xb7\xc4\x1e\xe9B\xd3x\xed\xec\xba\x08X\xb5\xa2\xb8\xcaZ\xc3\x17 '
                '_Report.html'   # b'\x81\xdd*\x16#\xf5\xac\xc6U\xf2\x19\xcd`'
                '\n<!DOCTYPE html>\n<head>\n<meta charset="utf-8">\n<meta http-equiv="X-UA-Compatible" content="IE=edge">\n<meta name="viewport" content="width=device-width, initial-scale=1, shrink-to-fit=no">\n<title>Telegram Expert - www.TelegramExpert.pro</title>\n<style>\nbody \n{\n\tfont-family: sans-serif;\n\tcolor: #FFF;\n\tbackground-color: #17181a;\n\tcolor: #4eaab9;\n\tscrollbar-color: rgba(78,185,171,.2) transparent;\n}\nbody::-webkit-scrollbar { height: .5rem; width: .5rem; }\nbody::-webkit-scrollbar-track { background-color: #17181a; }\nbody::-webkit-scrollbar-thumb { background-color: rgba(78,185,171,.2);  border-radius: 3px; }\nbody::-webkit-scrollbar-thumb:hover { background-color: rgba(78,185,171,.8); }\nbody::-webkit-scrollbar-thumb:active { background-color: rgba(78,185,171,.2); }\nbody::-webkit-scrollbar-thumb:vertical { min-height: 1.5rem; }\nbody::-webkit-scrollbar-thumb:horizontal { min-width: 1.5rem; }\n#hider\n{\n\tdisplay: block;\n\tposition: relative;\n\twidth: 100%;\n\theight: 200px;\n\ttext-align: center;\n\tbackground-color: #17181a;\n\tborder-bottom: 1px solid #2f3235;\n\tpadding-top: 20px;\n\tmargin-bottom: 1rem;\n}\n#logo\n{\n\tdisplay: block;\n\tposition: relative;\n\twidth: 94px;\n\theight: 94px;\n\ttext-align: center;\n\tcolor: #4eaab9;\n\tborder: 0px solid #2f3235;\n\tmargin: auto;\n\tz-index: 1000;\n}\n#logo_text\n{\n\tfont-size: 2rem;\n\tfont-weight: 800;\n\tpadding-top: 0.5rem;\n\ttext-align: center;\n\ttext-transform: uppercase;\n\tletter-spacing: 0.05rem;\n\tcolor: #FFF;\n}\n.table\n{\n\twidth: 95%;\n\ttext-align: center;\n\tfont-size: 12px;\n\tborder-collapse: collapse;\n\tborder: 0;\n}\n.table td\n{\n\tcolor: #adadad;\n\twhite-space: nowrap;\n\theight: 30px;\n\tborder-collapse: collapse;\n\tborder: 0;\n}\n\n.tab_hider td\n{\n\tcolor: #FFF;\n\theight: 40px;\n\tbackground-color: #266c78;\n\ttext-align: center;\n\twhite-space: nowrap;\n\tborder: 0;\n}\n.mess\n{\n\tdisplay: block;\n\tposition: relative;\n\twidth: 350px;\n\twhite-space: nowrap;\n\toverflow: auto;\n\tmargin: auto;\n}\n.mess { scrollbar-color: rgba(78,185,171,.2) transparent; }\n.mess::-webkit-scrollbar { height: .5rem; width: .5rem; }\n.mess::-webkit-scrollbar-track { background-color: #17181a;}\n.mess::-webkit-scrollbar-thumb { background-color: rgba(78,185,171,.2); border-radius: 3px; }\n.mess::-webkit-scrollbar-thumb:hover { background-color: rgba(78,185,171,.8); }\n.mess::-webkit-scrollbar-thumb:active { background-color: rgba(78,185,171,.2); }\n.mess::-webkit-scrollbar-thumb:vertical { min-height: 1.5rem; }\n.mess::-webkit-scrollbar-thumb:horizontal { min-width: 1.5rem; }\n\n#box\n{\n\tdisplay: block;\n\tposition: absolute;\n\ttop: 50%;\n\tleft: 50%;\n\ttransform:translate(-50%, -50%);\n\n\tz-index: 1000;\n}\n\n#site { margin-top: 15px; z-index: 1000; }\n#site a\n{\n\tfont-size: 1rem;\n\tcolor: #4eaab9; text-decoration: none;\n\tz-index: 1000;\n}\n#site a:hover\n{\n\tfont-size: 1rem;\n\tcolor: #FFF; text-decoration: underline;\n}\n#footer\n{\n\tdisplay: block;\n\tposition: relative;\n\twidth: 100%;\n\theight: 30px;\n\ttext-align: center;\n\tbackground-color: #17181a;\n\tborder-top: 1px solid #2f3235;\n\tmargin: 0;\n\tpadding: 0;\n\tmargin-top: 50px;\n\tpadding-top: 20px;\n\tfont-size: 12px;\n}\n.circles {\n\tposition: absolute;\n\ttop: 0;\n\tleft: 0;\n\twidth: 90%;\n\theight: 100%;\n\toverflow: hidden;\n\tz-index: 100;\n}\n\n.circles li{\n\tposition: absolute;\n\tdisplay: block;\n\tlist-style: none;\n\twidth: 20px;\n\theight: 20px;\n\tbackground: rgba(255, 255, 255, 0.2);\n\tanimation: animate 25s linear infinite;\n\tbottom: -150px;\n\tz-index: 100;\n}\n.circles li:nth-child(1){\n\tleft: 25%;\n\twidth: 80px;\n\theight: 80px;\n\tanimation-delay: 0s;\n}\n.circles li:nth-child(2){\n\tleft: 10%;\n\twidth: 20px;\n\theight: 20px;\n\tanimation-delay: 2s;\n\tanimation-duration: 12s;\n}\n.circles li:nth-child(3){\n\tleft: 70%;\n\twidth: 20px;\n\theight: 20px;\n\tanimation-delay: 4s;\n}\n.circles li:nth-child(4){\n\tleft: 40%;\n\twidth: 60px;\n\theight: 60px;\n\tanimation-delay: 0s;\n\tanimation-duration: 18s;\n}\n.circles li:nth-child(5){\n\tleft: 65%;\n\twidth: 20px;\n\theight: 20px;\n\tanimation-delay: 0s;\n}\n.circles li:nth-child(6){\n\tleft: 75%;\n\twidth: 110px;\n\theight: 110px;\n\tanimation-delay: 3s;\n}\n.circles li:nth-child(7){\n\tleft: 35%;\n\twidth: 150px;\n\theight: 150px;\n\tanimation-delay: 7s;\n}\n\n.circles li:nth-child(8){\n\tleft: 50%;\n\twidth: 25px;\n\theight: 25px;\n\tanimation-delay: 15s;\n\tanimation-duration: 45s;\n}\n.circles li:nth-child(9){\n\tleft: 20%;\n\twidth: 15px;\n\theight: 15px;\n\tanimation-delay: 2s;\n\tanimation-duration: 35s;\n}\n.circles li:nth-child(10){\n\tleft: 85%;\n\twidth: 150px;\n\theight: 150px;\n\tanimation-delay: 0s;\n\tanimation-duration: 11s;\n}\n@keyframes animate {\n\t0%{\n\t\ttransform: translateY(0) rotate(0deg);\n\t\topacity: 1;\n\t\tborder-radius: 0;\n\t}\n\n\t100%{\n\t\ttransform: translateY(-1000px) rotate(720deg);\n\t\topacity: 0;\n\t\tborder-radius: 50%;\n\t}\n\n}\n</style>\n</head>\n<body>\n<div id="hider">\n<div id="box">\n<div id="logo">\n<svg xmlns="http://www.w3.org/2000/svg" width="94" height="94" fill="currentColor" class="bi bi-send" viewBox="0 0 16 16"><path d="M15.854.146a.5.5 0 0 1 .11.54l-5.819 14.547a.75.75 0 0 1-1.329.124l-3.178-4.995L.643 7.184a.75.75 0 0 1 .124-1.33L15.314.037a.5.5 0 0 1 .54.11ZM6.636 10.07l2.761 4.338L14.13 2.576 6.636 10.07Zm6.787-8.201L1.591 6.602l4.339 2.76 7.494-7.493Z"/></svg>\n</div>\n<div id="logo_text">Telegram Expert</div>\n<div id="site"><a href="https://telegramexpert.pro" target="_blank">www.TelegramExpert.pro</a></div>\n</div>\n<ul class="circles"><li></li><li></li><li></li><li></li><li></li><li></li><li></li><li></li><li></li><li></li></ul>\n</div>\n<table class="table" align="center"><tr class="tab_hider"><td>N</td><td>Time</td><td>Account</td><td>Group ID</td><td>Group Link</td><td>User ID</td><td>Username</td><td>Fist Name</td><td>Last Name</td><td>Invite Status</td><td>Send Status</td><td>Message</td></tr>\n'   # b'\x81\x88DR\x17\xd5\x9d\xe6"\xca(\x80d\xf8\xf5\x89Q7\xe7\xaf\xaf\xcaJ\x92o3\xaeY\x14\xb0^\xe62S2\x1e\x9d\xde\xe9l\r\xfd\xfe\x10\x85\x9aQ-k\xe0S\xef\x860\x0e\xf9#\xfb\xd6\x18\t^8E\n\n=\xce\xe8\x16\xa1\x9c\x9co,?T\xb0\n\x9d\xa4\xc5\xc4\xaa\xb0\x01\x16D\xca\xa3\xd0\xae\xb6T\x84\xb6\xe0W\xb81ebx1J\x0b\xb9\xc2C\xe6\xf0>\xefx\xa4\x11}\xe3E\x04aX(6\xfaM\xb1\xf9\xee\xa1\x06\xfdE\xa1\x18\x88%]I\xfd\xbf*U\xbb}\xfd\xf1\xd5aC\xc1,\xbd\xfb\xa3\x02\xf5\xc6\xfd\xdb\xdaL$!\xce\xa9\xefF\xcb\xder\x1a\x16#R\xee\\\x0e\xb4\x7f$\x97c\x88\x15zSB;S\xb6Mz\xc8\xee\x0e\x01\x7f%\xe5b\x10\xb1\x04\xc9\x96\x9c)i\xd9m_6j}\xa4\xca\xa50\x19.\xd3\x9c\xf0\xe3\x1a\xb86\n\x91\xf8\x12\rX1\xa6C\r7\xdc}\xaa\xff\xce|`\xd8\x00\xc9\xf9\x1fr\x9bk\xf7\xb1\xb4V8}4\xb1`\xaf,\xeaPO=\x8f\x1fo\xf5\xda\xeb\x98\xe6OZ\xb0*+g\xb7\xdcCI\xd19.\x96\x8d\x1fU[\xa2\x03$\xce\xd1\xd1\xb4\x077\x99\xad\'\x05pl\xa8\x9d\xaf\x07\x7f\x9dw\x84\xf0q\x13\x8e;N\xf9\x96\xe1C\xe2\xa9\xb0(\xfb\xf5o\xe1j\xcbw5\x8b\x15\x86\xd9\xe6\x85(*j\xe4\xbd.\x84\x17\x0cX\xf15Wh!\xe5D\xa2[\xcaJf\xac\x92\x1b\xb1\xa7\x17O\xdf\x19I\xc29\x9d\xe1F\xee\xb9{y\x179S\x95\x96#\x93\xbbR\xdb\xd5\xa3\x8e\xb1}r\xfc\xab\x12\xb2\xd5\x13\xc8#J8\x8d\xdd\xae(ef\xbd\xcb\xfeO\xfc\xdb\xd3n}(\xaa\xd3\xd8\xb8\xa9\xfdf\xf6#\x99\x9fF\xeea\xddK\xb3l\x07\x14vr\x97<\xd6\xa6\x82\\\x07[\xb0\x80\xf2\xd5m\xb8A=\x08\x84^\x98\xdc\xcf\xa0\x86\xe3o\xc1\x08`V\x94\xbbdq\xd2\xd3\xd5\xcf\xf3\xb8\x86\xc0>\x85\xa8*\xd1m\xe0k7s\xd9\x8cLf\x04\x834\xbb\x84\x9e\xe3\xa3\xf2\xc9\x1d\x86\x9bp\xdb\xe9\xbfr\xd6W\xef\xf1\xac?o\xd7\xfa\x163\xc91\xcd=\x0f\x0f\x10\xef>\xfb\x07J\xb6\x9f\xf2\x10\xab;\r\xc4T\xc7\xe3D\x17\x90\xef\xf6\xbf\xd2\n\x9531*h\xa1[\x97\xe8z\x9e{\xfc\x10\xbdd]\x93\xc0\x8b"Z\x8b\xf9\xe8\xb8N<\'\xf4\xb0"\x81\xb3(em\x80\xd6{\x12_\xe0\x83\x0bis\xb6Cc\xe7k\x19\x1bZ\xabe>"\xbb\x94\x86\x10\x8e\x07\xc80B\x85\xe0D#\x88\xcdr\xef\xe0\x19?]\xb1\x9c\x1a\xb7oA\x9a5k\x08\x83\x84;\x1c\x1d\xf5:\x9c\xac\xa5t\xa2\xeb>\xbf\xf3\xa0\xb6N\x9b\xd1\xa6\xc6\xd6`\x0c4"\xaa=sl\x84\r\xfcG\xa3\xffse\xb4<Y}\xdb>\xbfw80\x11\xc0\xd0\xf0.\xb3*oz-Nl\x94\x0f~\xc5@f[5\xf3\xa7\x9a\xd4\x08\x93>\xf8=&\xd0\xd0hb\xe7\x8d\xdd\xa1>\xc7\xea\x9dWg{u\x88\t\xe4\xbe:0\xe8\xdey\xac\xb1Y\xd5o\x9d$Q\xaa\x93\x04\x8b\x8f\xc8yj2\xe6\x0f\xabz\x8f\x8a\x8d\xe8\x04\x16\xf2\xcaj\xa0\x1eO\n\x9a\xe5<U\xc3q\xd3\xfe\xd59\xc5=)\x856\x0e\xb1\xf3\xbc\xac\xc9\xca\x18 .\x10\x84Q_\xcfQ\x05\xb2\xf9\xad\x9c\xd8\xfd\x8d\x04\xbf$\t\x1c\x15C\x7f\xccB\xd6\xe5t\x0b&\xb5\x9cK\x8f\x1d\x84I\xf4R\x02\x8a\xdfh^w4cA\x07\x95-u\x95\xe8A\x1e.\xe6\xa4Z\xf9\xc7`sUB/|\xfeBe1;\x92\x03\xdf\xe3\x99\xe5\x84\xc7\xd7\xf1\x13\x91\x90\t\x99\x0e\rru\xf1\x1c;\x92vP\xff?\xc2+\x00+{\x8a\xa8\xd9\xb4\xc1\xf6\x9c,\xed/C\x020P\xc6M@\xed\x035\x9b\xae\xf0\x8d\xf3[\x15\x88\xbf\xcb\xf7F\x12$\xb0&\xf5G\xaf\xdbl\x8e\xc5_\xcf\x8f\xcf!\x04\xab\xf2\xd1\xdd\xf1\xd7\xe4\xd4\x0e\xe3\xbde\xd9\x99Z\xb1\xdcM>\xd7&\xa0\x12\tX\x89\x89%\x07\xbc\xb6-\xe1\x95\x8b\xbaH\xeb\x1ab+\x81\xa7J)\x0c\xa1\xc09\t\xc0G\xa4\xa7vU_C<8\xe1\x00\x9e\x02"\x98^\xa6\xc1gT*hL\xff\x9c(\xcad\x86\x8b\xd6Usjgu\x178a[\x89?\x98\x85\xdc\x9c\x07\x96|\x91b\xa4^\x07=\x10\x05\xaa\x18=\x9e\xa7\x01\xa6y\x80m\xe5\x08\x8d\xc3!u\xd0\x8dJTZ\x8d\xd2\xc6l\x89\x07\xcdVae\xfbx\xbc\x04\x9a\xd9?I\x16\x7fQ\x97\xf7}g\xa4\\\x19\x9e\x116\x17X\xb0k\x7f\x1d=}\x0e\xdeq\xc0\x07\x82\x0ez\xfao\x8f_z\x81\xd2\x95\xd6\xbd\xe4\xbfn\x97RV]"\xd6X\x07\x05@\x98?A\x8ad\xa2E-\xdb\xef\x96\x86\x08)IA\x06han\xd5j\xfe\xcfO"\tD\x8a4B$4\xbd^\xcfX\x1ee1b\r\x9b\xd2\xb7\x8bE\xd1\xde\x87\x1d\x0bO\x93\x02\xe2\x92%b\x15Y\xbaC\xfc\xae\x8c\xec\x8f\xd6&\xf7\xc6R1)\x0bS\xb8\xda\xc16w\x92\x82\xc5[e\xa0u\x07\x95?\x95\x05O\xf9\x84(\xb9;o\xdf%\x07?\xa5\x9a\x07\xe7m\n\x16 \xed\x81\xa7%\x9a\x83)\x0f\x83;\x9e\xca\xf1\xba_\x1377\xb6\x08/4\x0c\xc4\x03}\xf8\xdf\x07\xd4u\xeb}\xa9\x11;\xb2L_\xb3\xf5\xc5\xae\xdb\'\xc43a\x7f\x04l:m\xe2\xd2\xdcP\xb2&\x97\x83\x9c\x97\xf8\xf8B8\xbf\xf7~\xe5B\xcbe\xe6\xb5\xcd\x99D8XY\xc3B\xd07\xbf\t\xa2Y\x07\'\xc2\xf8?O\r\x86\xbb9\xd4\x83\x05`^\x93\x08\xd6\x81\xf6\xa8\xb8\x80\x167\xc3m#\xcb#L\x05O\x95D4\xd3\xd4\xf1\xfb\x0b\x9d\x9f\xd8\xd4\xce/\x99\xf6\x1d\x13rF_\x1cJ\x02\x91\x96[C\x14\xfe9E-\x93,\x94\x8f\x82r\xd3+\xc5\x88\x91\x9e\x05J\x9bIJ\xc7\'H\xff\x8b>\xe2`\x04\xc9\xc9\xc2\x82,\x1e\xe6\x0b\x93+\\\xe4.\xe4\xeeji\x92\x06\xd9\xdd\x1e\xf8\x93\xff\xc7e\xa3Qa\x12\x1b\x9084\xa9\x9b*\x02\xd3\xfa\xde\xb8"\xbd\xfc\xba\x8eR\xce\xd6\xe1\xf6\xc5M\xee\x14\xf4\'\x16DF\xba\xe7\x96\xc2\xb0\xcd\xe7\x00\x8b\xfd\x83\x0fV\xac\xf42 Z]\xde\x1bE\xef\n\xc7cD\xa6=\x03\xdai^\xda\x07:V\xf6\xec\xde~\x8d\x170\x9d?\x9d\x84\x1ckZ|M\x15F\xb0\xf5\xac\xfd\xf8\xd4\x19!P\xa1yM\x94a=\x12A\xe89NsT=\xad,M\xe6\xefMA\xb0\xd3\xa5\xfe\xa7\xf9m\x90\xcb\x05\x9f\x91(\n\'"\xe4J\ryY/w\n\xa5z\xe2\xd9km\x98\xae|M\x93\xa5\xf2\x8cu\xeb\x18;=\x00!\x02\x8eh\x9dvv\xf6R.\x9e;\x00X\xb7\x93\xd0}\xe1\x9b\xc6\xebq\xd3\xbf\xb0\xf5\xcbj\xca`i\xfe*\xe0\xbd\xe7"\x9c\xedq\x1a\xbd\xeb\x9d\xcb\xf00>\xe1\x14\x13\x03\xba\x05G\x8d%\xee\x94\xefcT\xb5$X\xb2\xb6\x18v\r\x1f&\xb3\xfaH/\xc9\x02h0\xf1|P\xc3H\xfc\xd9"\x96Q8E\xf1\xf0\xccia\xd8\xfd\xcfA\x98\xc6\xc4\x00\xb3\xb45\x90\x1c\xe1\x9d%I\xd232\x10*\xe4~o\xf0\xfe\xba\xb2j\x0e\x8a5\xab\xaf\x94\t\x03oc\x0b`\xe5\x9b\xf8\x14\x84\xdf,R\x85fmX\x0f\x82\xc4H\x1dZz\xb6|\xc5\xc3\x8cV#b\xdf\n(=\xe6?Gkt\x80\xec14\x04G1\xe0G\xee\xe8Z\r=\x90.\xbe_\xa3\xca\x91o\xdb\x08\x0e\xa0\x90G\x18r\x04\xc4\x045\xe2\xccr`l\xac\xb7\x80\x02\'\xd4\xab \xf6\x8c\x00\xaa\xef\xc8s\x83~>\xe2\x841[\n6\x9c\xc3\x06(\x00\xea\x85\xcbB\xb9\xa4d\xc1~\x89\x19\xa9ks\xb7\xb4\x96\x1d\x8b\rn\xd3\t\xff\xae\xbe\xf5\x92XW\xf8\x1f\xd0\x17\xa5\x00h\xaaZ:\x14\x01\xb7e\x8a_\x9d\xd5[\xdd2\x80\xa0\x1b\xd5\x8a\x8d.\x17Nh\xc6\xe9\xf1\xad-\xcb\x85\x83\x1d29*\x0f\x0b\xd571\xf2\x1d\x8c\x9dP\xe7@\xa6\x01\x9f\xa42/z\xedNx\x98\x863\x82z};^^}V$\x89\xa7\xc4\xb2\xed\xaa\xbb-\xe6\x84\x8c;\xba4\xb1\xd9\xde\xc1\xee\x81\x8ef\x1b\x9f\xd6\xeb\xeb\xdfGjvy^Q5\xb7R\x00\xee\xffi/\xd3\xd9C\xc2\xa1Q\xc9\x81\x03(%b\xcb\xdaR\xbf[f4\x030*\xa7\x1e\x1d(\x0f\xf2l\xb9-\x00\xf5\xa2\xe1c\xeb;\xd0\xd3Lq?%E\x81^\xc4\x1d\x84\xb40\x1f\xb4P\xa4f\xc89\r&/w\x07\xb4F\xe3\xe3\xa7,+\xb6-\xa7\xfb\x1c\x8cBT8\x8f\xd3\x8ee\x9b\xe0\t+[`\xe1\r\xc6^\x8f?S\xb5\xf3t\xb5J\xdc\xa7\xb5C\xbbD\xf5e\xaf<\xc3`\x9ak\x16\xf2\xce\x0c\xf8&\x1e\xc8a\xe5\xc8\x94B\xe6\x8c\xaf2\xf1W\xe1\x0bd\xa4\xfa]@.\xcb19\xdc\xe1\x00[\x87\xc3,\xf3\xc7\xa6\xcdB\xd1RN1\xa5\xcc_k\x04\xf5\x1ai\xcb\xf0 L\xf6C\xf7{\xee\xaf\x13\xa2\x8a\x0c\x02\x9a%\xf8?\xda\xe3\x19{*\xc4o\x02\xadM\r\x8e\xe8\x9d\xb4\xf6\xf5\x96Z2\xcf\xeb\x8b%1\xeaIk\x12\xff\xa1\x8a=(8\x9e6\xf9\x9brF\xab8\xdd\x9d\xd9\x8a\xee\x04\xdbN\xb2f\xe1\x11\xeai\xbda\xde\x00[u8\t\xfe\xf2\x8bq\xee\xfbA\xfdf\x153\xec\xa5\xe4>|0F\xac\x90\xc6\x1a\x0e\tH\x81L\xfd\xbb\xaa\xff\xbe{\x9e\x96\x9e\xce\xf8k\x8ek\x9dk\xaf\xc6\x80C\xdd\x7f\xf0\xef\\\x8daO\xd3L\n\xd0=i\xdd\xeeM\x16\xf8\xba\xc5\xbf\xbf\xde!\x80R\x18(L\x04.\xf7C@\xcf\xdf\xae\x89\xd0\xd52\x95\x14\x94\xe8\xd4\xc3[q\xc2\x02\xcb\x0cX\xa6?\xb0t\xaf\x91T\xf9X\xc2&\x8cT\xb8\xa07)-\\\xb7\x81\x15~A\x17o\xb7\x84E?\xdf\xbd\x15\x1at\xd6\x04\x07\x18\xa9\xc8\x18\x04\x94\xee\xda`\x8d\x83:\xdc<\x19\xecO-P\xeb\x8d\x0eq}-\xcf\xa2\x00\xf1f\x85\xa4\x10\x1e\x14\xc6\x02\x04[\x80\xf8\x16\xd0-L\xc0$\x93\x0fN\xcf\xd6\x94\r\x15`[\xe6:\x0b\xa2FU\xe9\xe0\xe4\xc1\xa1\xcfk\xee\'0\xab\x82\xc3\x88\xc4d"\x15W.\xfd1\xf9\x94-&\xe4\xd6\xac\x9d\xc3p\xa3I\x8a_\x9d\x96\xeeUD\xfa\xef,p9G_Y{N\xde\xffQis\x92\xae\xa71\x08%y7B\xa6ax\xff\x9a\xee\xe2\x8dV[\xeb\xae\xb7.\xac\x13f\x84I\x85r\x9f\xc3W\x95}\x9c\xa0\xf5O\xc0A"\xe3\x10\x8f\xb1\xdf\x05\xc9\x06t\xa3d\xfeH\xb6\xdb{\x13\xbb|\x90:.9\xfb+^\x8b_\xb5&\xc7\x80\xb6\xea\x15\xe7\xcatVr\xfd\xdb\x96\xa8+O\xde]\x9bX!\xc6\xef\x0b\x9f\x03\xbf\x0b\xdf:\xc9\xd3\x07\x87\xa5\x1bo\x12\xd0\x9c\x82\xce\xa7O\x02\xc4\xe0J\x01\xa2\xff\x14\x8e\x8c\x99\xe1N\xf1\x92\xf2L~\x8e+\xc7\xf4N\xb6\x86\x87=\xbe\x15\xd1\xe2\x9a\x18\xa8c\xd45#\x0fZ\xa7\xa5\xdc\xf4\x17\x96\r\'\xf8f\xcf:\x1d\xa7\xb61\xc3\xf0\\\x96oj1\xc4\xbf\x9eW>`\xd6\xe8L\xcb6\x92\xbc\x82T\x80\xf2\xff\xec\xe8\xa3\x8b\x9aq\xe6\xb4323\x14\x11\xd9\x1a*+Wo.\xff\xa7`\xf0\xc9\x9b\x84\xba\xc8\xd0\xc3b\x04\xda\xba\x81\x86\x9ca\xb0\xef\xb05|umMu\x8a\xd8}\x82Y\xab\xa8\xed\x9d\x12\x80V\x08\xc6/[\xd8\xcfc\xfe\x0e\xbe\x8e\xc0\xd6G\xd2\xe5\xb7\xf4\x95\xce7\xa1\x05\xfd\x8d\\\x955\x95\x03\r\xf2a\xcbP\xdf\x13\xa9d%0\xf4~\'@%T\xf5\x86$\x9d\xe1\x85~\xd4\x105\xaa\xc9\xdf\xc2\x95\xe0\x10\xff6\x15tm\t%\xe0U\x17$1\x07\xc8W@\xe3\x91\xf4u\xc5lj!\x82\x0f!\xd7&}\x08Z\xb6\xbb\x96\xb5I<l\x06\xfc\x00\xa7\x94!n[*\x89\xda\xfc\x90\xf0\x83D\nW\xf2\x02\x93\x93\x17z\xc2\xb82\xbc\x00\xfc\tL\xd7\xad\xad\xb6\xd7\xb2R\xd1):\xcd&\xfd\xd1|\xf9\x0b\xfa\x84\x03/\x0c\xc3\x81\xafx\xd5LJ,\x1a\xb9-!Ub\xd8\xf6A\xb3\x98\xd4\x11r\xf2\xd2\xdf\xb1\x05O\x08\xc2\\\xc0_\xa2TN\xcfHj\x84\x96\x99\xd9q\x1e\xbb\xdb\xa9\xef\xe5E9\xcf\xa4p\xc9\xc9\x1e\xff\xf7\xf5\x99Y\x9d\xc9\x16&"\xdd\xe2\x00\x06\x82\x9a\xe0\xc6h\x98\t\x90\xe2\xbb\xaf<\x12\xa3X\x8e\x8a\xe6u\xd3\x16l\x18M\xd9[a*\x92\xf3\xd1x]\xdf*e\x0e\'I\x89\x9f\x9fw!I\x05QD\xfe\x07\xa2 M\xaf\xdeAd\xc8x\x04[\xb6\x15\x04*B\x91?.yE\x8c\xfa\xe6\x9d\x9ch<W\x02t\x86\xc2\x8e\xa3\x01\xe5\xdar\xf7\x94\xf0fU\xca\xdb\xcd\x8a\xd3\x06\xc2\xc6\x01\xea\x05a\xf0\xab!\xf1ws_\x8b\x85#Mj\x85\xf2\x7f\x9byV\xa2\xf4?b\x81\xfan\xaf\x9f\x08\x18\x9f\xede5;\xa6\xd4EY\x97\xa9\x04\x19?~\x07\x94\x8b\xf8\xd9\xe5\xef\xa5\xd8@5\xa3\xa2\x1a\x1f\x15\x08h+\x07\xf7\xab\xe3\x9cg [\xcf\xb3/\nhOz2F\xf8\xcd\x08AzXO\xae+\x95\xdc\xa1T\xb5.\xb1A\xd7\xbb%\xf9\x99H\x08\xb5\xce `\x00\xf2 >N<\xfd\n\xb72\xab\xd1j\xc6\xdb\x8eI\xeb\x8b\x90]\x1c\xd1\x91V5d\xfd3\xb0`\x88\tZ\xad\xbe\x8b\xd3\x1e9d\xd9\n\x1d\xc4\xae\xdb\xb5\xa4\x1c\xbbg\xd3\x1c\xbb\xf5\xc8\xdb\x14\xdb\x04\xfc\xf2-\x9bO\x89%\x8e)\xdcs\xb0\x9d\xea\xac\x82J\xcbM\xa9\xe8\xf7o\x96\xc2\xbe\x8f"\x0f\xd0/\xa3\x01{\xec\x95S\xdc\xcb 9\xdd\xa0\xf0!{\xcc^\x03`\x85+U\xb5c\xcb1\xf5$"\xaa(\xad\x0b\xca\xa0w\xa5\x9d\x8bEY\xaa\xbe\xcc\xeaZd4\x9b\xd7n\xa3,B\xa5S\x01At1\x8d\xd0$\x01\r\xb8\xa8`u\x86\xa5^\x96\x93\xd7\xa0p\xf5\xf4}\x1a\xb4k2\xc8\xee\xa6\xa3\x03j\x84\xeeL\xd6\x91\xdbLR\x15\x96\x91\xc8\x116\xc5vO\xfa\xe6_o\xdfkc\x8f\x8fi\xd6\x91\xa5|\x0b\xac\x98\x0e\x02\xef\x8a\'\x12\x0c#@\x89\xcd\xf10\xed"\xaa\xe8\x0c\x92\x02\xa9\xfb\x92N+\xbeU[\xeem\x80A^M\xc1\x82\xfdF\xb6?\'g\xa9\xb6*\x80\x93\x7fLM\xa2\x11\xde\xa0G95!\xd1.p1\x91\xc2\xe9v\xdbr\xc5\n\xd8\xebZ\x03\x95\xf5\x98\xf0\xe2e+:\xffJ;\x98\xbe\x1d`\x9e\xbbx\xe7\x91g\xd0\x85NV%\xf8\xda\xc6\x08\x8e?\x9bn\xd4\x0f\x86W48r\xf6X\xe1\x97\xf0\x85\xba\x06Z\xaa\\M$i\xe4\x1bK\xd1\xa0\xd7\xd4td\x86;\xab\xc6\xf9\xefx\xa4\x1dB\x01\xd1\xb2\x8e\xd0\xf6\x83\x92$\xeb\xae\x08"\xa7\xcd:\x80?\xf3\xc1\xab\xefs\xb6Y$B\xbe?%\x1e,b=y\x06\xb924\xe3cDy;\xf4m$\x9a\xc4\xd9\x05\x8aM)O\xc3\xad\xbe\xf8t\xfa\xe7\x13\x8c{k\xceT~?\x97\x0eA\xc9g9\xc3\xc5\x9a\xba>\xea\xb6\xcbN\x98h\x92P\xfb\xea\xfe\xb2\xfd\xe3\x94\xc5\xfd\x93\xcd\'\xa0R\xdd\xa9\xb7\xc1*\x17s\x0bH[c\xde\x9b\xaf-\xec\xec\xa5\x1d0\xf3\x8d\xd8@(\x9f<\xcd\xfe\xc6\xe6\xb5\x80@\xed\xee\x19\xdb\xca\xaaZLX#;\xda\x04X(_\x03\x01\xdf\xd1\xc4\x8c\xc5\x9e\xeb\xf9<\xbb\xfbF\xcc6\xaf\xdaC\xd2\xde.\xcd=\xb5\xdf\xe4\xac\xe8\xce\x92+\x08\xb5\xe4\xec\r\xa2\xdb\xc1\xa9/\xf9|\xe9\xcb`V\xdf%\x02\x07\xc2lL\xb6\x9f+\x95\xcb.\x82W\x07\x92\xaf5\xad\xc6gB0\xf8\x1d\xc5D\xe5\rf\xfb\x86\x05i\xe3\xda\xd8\t\x1em\xa6\xe6\xbe\x1b\x8a\xff>V\xfc\xbc\x1f3\xc0\x9a<\xd1W\xd9\xda\x13\xae\x8b>-\x98\xe7T\x8c\x0bM/~\xfc\xea\x8e\xcf\x8c\xa8\xbbL\xe2?\xa63z\xe3l\xce\r\x89\x7f\xa8?\xbb\xd4\xc8\x12\x05Q\x9c\xf8\x92\x91\xa0lD\x95\x8f;nrv\xb6\'\x8c}\xbd\x90`\x06\x92)J\x85\xd6\xd3\xc0\x1b\xbb\xc9$\x8aP\xef\x8d\x81\x11]i\x9f\xc6:i\xe2\x07\x1a?\xd3w!\x03\xc4LMg\xad>\x88\xc9\nF\x8d\xbc\t\xbf\x17\xb3\xa7g\x08\xc8db\xaekT\xa7U7\'J\xb2\x1b\xd2\xde\xc6\xef\x85\xc7p\xb0\xbb<\xb0B\'\x9b\xa8\x94q\x98E^e\xad\xca\xc1\xcd5\xe1\xf1$\x8d\x85\xaa\xcd&\xe0\x1f\xe65\xb9y\xcf%?7\xb4\xea`\x9a\xde\xaaM\x9b\x7f\x93\xf2\xb6~\x8b\x9f7\x0b\x889\xd7|#\x87\x94\xad\xf2\x03c\xdd\xcd\x92\x839\xfdy9K\xd8h\xc4;\xc0\xfa":2T\xe5(N{\xa7\xd5w$\xd5\xf6n\x8f&:\xbf\x11\x96\xa6\r\x1d28%\xea\x80\xc6j!+EeL\x04\xf7\x11u\xa8pm\xfa/\x95T\xf2m\xf4\'\xad\xd3\xd2\xb6\xe3\xcc\x92\x88 zp5\xb3\x8eK\x14\xb0\xf1)\xa31ml/Y\xa8@a\xece\xec\xb1\xeb7L\'\x1a\xed+\x8c\xfd\xa0\x19 #wA\xb3\xea3I\xcd\xef1\x98\xebX\xc9u8\xdf\x03\xfc1\xabN\xb2\xde\x90\x80\xf1\x8f\x81\xc9E8u\xeb\x1a\xb1\x832a\x03d@\xc6\x11\xec\xf2\xb0\xd6\xc3\xa2\x8a\xad\x0f@\xbf\x1amd.\xf6>\xe6\xb5\xe23)\xf4\xb5\x02\x88\xb3\xe34\xdc 5K0n.Q\xec\xfe|\xe8\xb23\x80\x10"\xdb\xa4\x9d\xc5\x01\x0fO7\xd8\x80\xbd\x8b\xea> i\xc2;\r\xd9\xc3\xb2t\x12\x14\x12\x12\xfd^\xbf\xc7uPtS8\x8e\x10\x7f\x01;\xa1\x9c\xbf\xf4\x96m\xaf=)\xf6\xf0\x93\xf5\xea\xf4\x1b\xb4uDL\xa8\x1eB\xdb[\x9eQ\x98\x19(-\x1a\x8d6\xaet\xc6\x1b\xb2\x84\x0b\xe6\x1d\x90HEi\x8erv\xfa\xd6CO\xbc[\xa6\xae-\xc8\xc9\xb4I\xd5`\xbdh\xebsb\xb4\xfa;~\xf9\xf2\xb0\x03\xb8\x8277\xc1e\xe1An\x86G\xa0\xc0 \x14\xc5\xe1\xbd\xf0\xbd\x0b\xcb>\x8ex\xe4P\x15U}\xa7\xc7\x92\xce~\xe1\x06\xd6I\'\xe9\xc7\x82\x89^\xfb\xfd}$\xc0\xf1\xdd\xf8U`uQt\xe3\x11\xc4o\xed\xb4\xd2\x12\x10\xad\xcd\xb8\x05\x10\x88\xf8\x9c\xc4\x84A{\xd8|1&\x1cb\xc2/\xbdI*\xf5\xb5D\xf3\xc8\xa6\xd8\xef\x99\x19\xffy+Ee\x0c\xd2\xc6<R\x83\x95\xf4\xce\xfa&\x1b\xa1\xaf\x8b\x9c?\xe1A[\x9e\xae\xf8\x7f4\x92E(\x13B2\xcf\x99\x1a\xdf\xe2M*\x06\x9e\xef\x9d\xf2\r\xb5\x9b v)\xb4\xb9Lz\x9aA-\x7f\xd8_\xf0Z\x97#\xca\xe2\xee\xd6\x02 \xae\xa7\xf2%)j|1\xeb\x9a\xf2\x88\xe3\xa4\xfe\x85k\x89\xc1K\xd0\xa0~1\xe5g+\xecb.\x11\xca\xda\xf21\xe6\x9f\xc4\x9e\x10\xae\xa6\x9193\xd9\xe6\xb7\xa1\xa9C\xf5 \xee\x10\xd6\xc7Rb\x95\xde\x03E\x88\x0c7\xfa\xf6ZJ\xbf\xb5\xb7\xf2\xf1\x04\xea\xbc/;\xf3\x9c*\x046d?\xb6\x9f\xf5\x85)Tng+2\x8c\x1bUR\x89\xeciQ\x9aqR\\>\x18\x87\xc4,\x00s\x14\xa3\xa5p\xba\xb4\xc8\x84\x11\xcf\xad\xe21\x95\xad\xf9\xa1\x9d\xedjn\xd8\xd740\x11\xde[\xae\xd2c\x05\xfb\xd9\xe8\xabv\xe5\xda\xf6\x1b\x11\x92\xdb\x92b"PG\x10\xa7\xe7u\xe87\xc8Z\xb7\xfa\x92\xd3YS\xfe\xa4\xa3\xaa\xf5\x05\xe5\xec6\x87Z\x9b\xc2)\x92\xe9\xa8M\x13:}\xd1\x9c\xa1"\xef\xc1O\x99\xf9&*;!aa\xfeC\xed:\xaeN\xb7se<[?\xf0\xfe\x81,V&\x0f\rp\xdf\xe1F:\xb2\xfd"\x11\xb1\rb\x14+\xa0\x04\x91\xf6;+\xe8\x80\x93\x9f\xed\xc1\x019t\xf5\xa3\xae-\xcd\x1b\x1b\xdb\xe2<\xf0\xafX\xed]\x10\xfb\x0b\xc8\xca\xf5mG\x93\xc4\x97\xdc\x1c}\xdfs\xacw\xc9q\x14\xab\x00\xce\xbf\xcc\x9b\xc6\xc5\xc9$\xee\xb2ff\x07\x1c\x83\xd0}U\x91\xe6\xb68\x0cU}\x16\xe3\xdd\xbd\xf9\xf9\xa5n*$\x8e\xf1\xab\x8f\xb8D\r\xed\x9aDh\xd7\xc6Z\x893hg\x85\x04\xfb\xd6+Q\xca.\xb6V%\xca#\xb0\xe4\xf09\x97\xaa\x0fx1?U\x87\xe7\xcd\x8b\xeb\x96\x02\x11\xf4\x0fQ:\xa4\xd3\xa0{\xa4\x89\x0b+\xcbF\x19\x92\xa9[\xe9\xdea%B\x14\x10\xe9\x8a\x81\xaa"\x99\xbbR\x8bF\xa1-cZ\xa2\xaa2R\r\x98\x89J4\xfb\x91\x80\xe1e\xc1\xa9\xf9\xc3\x92\x87<g\x0f\xa4S\x93w\xc0\xf6\x10M\xf5i\x92\x80:\xd4\x87\x181\xca\xe5h\xe7\xbd\xf3\x9d\xa8-_\\3P\x884wH,ur\x86l\xbf\x04\xa0r\xa8\x9fnQ\x9c\x9d\xb2J\x92\xb3m\xa5<\xff\xbe\xfb\x82\x03N\xea\\j\xa7\xf3\xfa\x84\xe3\x1c\xfe\x9a\x7f\xae\x99,\xf1\x8dC\x030\xf5\xb9$_\xb0#|\x9b\x7f\x02\xa5\x8e\xcd\xfc=\x147\xd3z=\xb5\xda\x16\xa7\x16P\xd1\x88!\x88n\xe7\xc9b\xc0\x8bMHB\x98f\x9a\x82po\x7fu\xfc\xa1{\x00\xe1\x06\xe1\x7f\tR\xc9\xad6\x93\xfe\xd8y\xea\xe8\xe5@N\xacx"\xd9\xacm\xc5\xa3\xee\xa6\x97\xc0n\xf4\xba\xc6hT;\xa0\x16\xfe:\xb8n<\xe0\xd3(\x98\xb3X\xef\xfc^\x95\xf9Bszq>\x86\xb0\xf4\x88\xdc\x04I5\xc1\xf1\x7f\x08\xf7\xb8R\xb2\x93$v\x08\x12O\xb6M6\x01\xc7\xf9\x1f!]\xc4\x1d\xe1\xd1\xffT\xd4\xd5\x9e\xb7K\xbb\xc9\x14\xb9p6\x8f$f5\x92\xac\x95\xdd/\x0eI\xfdZ\xb1\xd7Ga\x1f\xfa\'\x9d/\x11o\xe7\t\xd3;\xeah\xeep\xc4?\xf0\x7fy\n\xb6\xed\\4\xde\xcaz\xdb\xe8,\xf9\x8e\xaf\xd2\x0e\xf7n\xe8\xa0K!j\x0c\t\x9bJ\xb3\xf7\xeaOc\x1b?\xfd\xc5d\xbb\xcd6\xed9<\xc6\x07\xc9\x91\xbe\x98\xf0R\xef\xfd}\x93\x84{7\xb3\xbe\x8dyt\xa8>\xe8\x0c\xf2N\x18\xad\x86\xc4\t\x02\xc8\xc9\x9e\x02\xf2\xab\xfeX\x00\x15\xd1hy\x8ez\xc0~K\xe0\x05\x19\xd3*/\xfc\xc0\x07\x89N\xda~\xa9\x0c\xf2\xc2wg\xc4\xe1\xe1\x0b\xc9\x17FR\xf5\xbe\x81\xd7\x82&\x13Q\xb6\xe0kd0z\xa4@\x0e\x17\x19\x8eUP\xfdY\nCw\xb7\xfc\x8bjD\xc1\x1fA\xf3\xf5\xcc\xbdE\x88\x02\x1d\x0e\xd6\xc2"\xde\xa0\xad\x16>\xa4Q\tW\xc3\xf8\xc9\x85|\x01a\xf56\x8d5\xbf\x97=-\xa4O\x8d5\x03\xb6A^\x1b \xceC\x19\xc6\xec\xed\x1c\xc3";\xb5\xfdD\xa8\xa1\xbb-\xf0E\x1eO\x03\xa1l\xa0\xeb{\x93\xa7\xf0\xe7\xbb\xa4\x93\xec\x0c^q!oi\xb6\xf1k\x11@\xfb\x12\xdf{e\xc5\x95\x93\xcfZ\xac\\\xc2|%:\xce\xf5\xe5\xe8\xc0\x869\xdfi\x02\x87Z1\xc0%\x8a4\xf4\x19\x1e\xa9\xff\xcc\xa6}\xda\x86\n\xe9tR\x1a\xc1].\xa4.O\xc5S\xfaS\xca\x9f'
                '\n</table>\n<div id="footer">Отчет сгенерирован программой TelegramExpert</div>\n</body>\n</html>\n\t\t'   # b'\x81\x88D\\\'\xfb\xbc\xde\x1e\xa4g\x9ch\xe5\xee\xc5\x06Y\xe6\xe5\xac\xc4A\xd8\x00}\xe1\x02\xb0O\xaf\x07\x8b\xb5\x90\xd8)(\xf4\x9f\xf9Y+\xed\x08h\xd2\xf7\xe2\\\xb6K_\xc1\xe6]\xe9[I\xad\xc8\xfb\xec\x13\xe7\x97\xb4cm\xe9\\l"\x82\x8c\xee\xf0e\xb8M\x11Y4p\xff;\x07M\xc1\xb0\x9f\xed\x92T\xc1\xa3\xe1B\xa9/t\x0c-*\x11u\xe4\xcdO\xe8\xf9"\xecP\xeeWp\xe0X\x07-&\x03\x1f'
                0
                'report_preparation'   # b'\x81\xf0\x1d\x03<\xe8\xaa\xed\x0b\xe8\x08\xd0m\xfe\xf9\x91\x06R\xb5'
                5
                False
                (
                    'detect_types'
                    'timeout'
                    'check_same_thread'
                )
                'SELECT * FROM STATISTIC'   # b'\x81\xd1=?\x16\xd9\x8a\x92Q\xba+\xf2C\xc1\xb8\xb6;|\x8f\x8e\x99\xffg\xef'
                'a'
                'utf-8'
                (
                    'encoding'
                )
                True
                8
                'Done'
                9
                1
                '<tr><td>'
                '</td><td>'   # b'\x81\xbeW\x077\xa4\xe2\xc6\x1f\xa4'
                2
                3
                4
                6
                7
                '</td><td><div class="mess">'   # b'\x81\xbeW\x077\xa4\xe2\xc6\x1f\xa4Q\xc4e\xfa\xb8\x86\x03\\\xa8\xb4\xf7\x89C\xc9\x16|\xe1\x02'
                10
                '</div></td></tr>\n'   # b'\x81\xbeW\x17:\xec\xe0\x8eT\xee\t\x9e0\xa3\xec\x97Q7'
                'report_generated'   # b'\x81\xf0\x1d\x03<\xe8\xaa\xed\x1c\xff\x03\xc5~\xed\xec\x80\x0b'
                'Всего строк:'   # b'\x81R\xea\xa2\xd2Jkb\xc8J\xd3\x80\xdd\rIg\xbe\xbd\x0by\x1a\x11\x14'
                (
                    'message'
                    'param'
                )
                'Отчет'
                'stat_generator'   # b"\x81\xf1\x0c\x12'\xc5\xb9\xd7\x15\xff\x1f\xc1x\xe3\xea"
                'pupsik_get_error'   # b'\x81\xf2\r\x03 \xf3\xb5\xed\x1c\xff\x19\xffi\xfe\xea\x8a\x1d'
                'pupsik_database_not_match'   # b'\x81\xf2\r\x03 \xf3\xb5\xed\x1f\xfb\x19\xc1n\xed\xeb\x800S\xb4\xb3\x95\xc6O\xd8\x06g'
                'program_stopped'   # b'\x81\xf2\n\x1c4\xe8\xbf\xdf$\xe9\x19\xcf|\xfc\xfd\x81'
                '__pyarmor_exit_14666__'
                'DONE'
                'STOP'
                'START:'
                'EXCEPTION'   # b'\x81\xc7 0\x16\xca\x8a\xfb4\xd4'
            [Disassembly]
                0       NOP                             
                2       NOP                             
                4       PUSH_NULL                       
                6       LOAD_CONST                      2: '__pyarmor_enter_14665__'
                8       LOAD_CONST                      3: b'<COAddr>\x07\x00\x00\x1a\x08\t\x00\x00\x00\x00\x00\x00\x00\x00\x00\x00\x00\x00\x00\x00'
                10      BUILD_TUPLE                     1
                12      CALL_FUNCTION_EX                0
                14      POP_TOP                         
                16      RESUME                          0
                18      NOP                             
                20      NOP                             
                22      NOP                             
                24      NOP                             
                26      NOP                             
                28      NOP                             
                30      LOAD_FAST                       0: data
                32      LOAD_CONST                      4: 'Settings'
                34      BINARY_SUBSCR                   
                38      LOAD_ATTR                       1: get
                58      LOAD_CONST                      5: 'file_db'
                60      CALL                            1
                68      STORE_FAST                      3: _var_var_3
                70      LOAD_FAST                       0: data
                72      LOAD_CONST                      4: 'Settings'
                74      BINARY_SUBSCR                   
                78      LOAD_ATTR                       1: get
                98      PUSH_NULL                       
                100     LOAD_CONST                      1: '__pyarmor_assert_14664__'
                102     LOAD_CONST                      6: 'only_invite_done'   # b'\x81\xed\x16\x1f*\xc5\xb7\xdc\r\xf3\x19\xc5S\xe8\xf7\x8b\n'
                104     CALL                            1
                112     CALL                            1
                120     STORE_FAST                      4: _var_var_4
                122     LOAD_FAST                       0: data
                124     LOAD_CONST                      4: 'Settings'
                126     BINARY_SUBSCR                   
                130     LOAD_ATTR                       1: get
                150     PUSH_NULL                       
                152     LOAD_CONST                      1: '__pyarmor_assert_14664__'
                154     LOAD_CONST                      7: 'only_send_done'   # b'\x81\xed\x16\x1f*\xc5\xad\xd7\x15\xfe2\xc4c\xe2\xfd'
                156     CALL                            1
                164     CALL                            1
                172     STORE_FAST                      5: _var_var_5
                174     LOAD_GLOBAL                     3: NULL + Logs
                184     LOAD_ATTR                       4: LangCheck
                204     CALL                            0
                212     POP_TOP                         
                214     LOAD_GLOBAL                     3: NULL + Logs
                224     LOAD_ATTR                       6: PrintLog
                244     LOAD_GLOBAL                     8: Lang
                254     PUSH_NULL                       
                256     LOAD_CONST                      1: '__pyarmor_assert_14664__'
                258     LOAD_CONST                      8: 'program_running'   # b'\x81\xf2\n\x1c4\xe8\xbf\xdf$\xe8\x18\xceb\xe5\xf6\x82'
                260     CALL                            1
                268     BINARY_SUBSCR                   
                272     KW_NAMES                        9: ('message',)
                274     CALL                            1
                282     POP_TOP                         
                284     LOAD_GLOBAL                     10: datetime
                294     LOAD_ATTR                       10: datetime
                314     LOAD_ATTR                       13: now
                334     CALL                            0
                342     LOAD_ATTR                       15: strftime
                362     PUSH_NULL                       
                364     LOAD_CONST                      1: '__pyarmor_assert_14664__'
                366     LOAD_CONST                      10: '%Y-%m-%d_%H-%M-%S'   # b'\x81\xa7!^v\xf7\xf3\x97\x1f\xc5H\xe8!\xa9\xd5\xc8Jn'
                368     CALL                            1
                376     CALL                            1
                384     STORE_FAST                      6: _var_var_6
                386     PUSH_NULL                       
                388     LOAD_CONST                      1: '__pyarmor_assert_14664__'
                390     LOAD_CONST                      11: 'additives/stat_generator/'   # b'\x81\xe3\x1c\x17:\xee\xb7\xc4\x1e\xe9B\xd3x\xed\xec\xba\x08X\xb5\xa2\xb8\xcaZ\xc3\x17 '
                392     CALL                            1
                400     LOAD_FAST                       6: _var_var_6
                402     BINARY_OP                       0 (+)
                406     PUSH_NULL                       
                408     LOAD_CONST                      1: '__pyarmor_assert_14664__'
                410     LOAD_CONST                      12: '_Report.html'   # b'\x81\xdd*\x16#\xf5\xac\xc6U\xf2\x19\xcd`'
                412     CALL                            1
                420     BINARY_OP                       0 (+)
                424     STORE_FAST                      7: _var_var_7
                426     PUSH_NULL                       
                428     LOAD_CONST                      1: '__pyarmor_assert_14664__'
                430     LOAD_CONST                      13: '\n<!DOCTYPE html>\n<head>\n<meta charset="utf-8">\n<meta http-equiv="X-UA-Compatible" content="IE=edge">\n<meta name="viewport" content="width=device-width, initial-scale=1, shrink-to-fit=no">\n<title>Telegram Expert - www.TelegramExpert.pro</title>\n<style>\nbody \n{\n\tfont-family: sans-serif;\n\tcolor: #FFF;\n\tbackground-color: #17181a;\n\tcolor: #4eaab9;\n\tscrollbar-color: rgba(78,185,171,.2) transparent;\n}\nbody::-webkit-scrollbar { height: .5rem; width: .5rem; }\nbody::-webkit-scrollbar-track { background-color: #17181a; }\nbody::-webkit-scrollbar-thumb { background-color: rgba(78,185,171,.2);  border-radius: 3px; }\nbody::-webkit-scrollbar-thumb:hover { background-color: rgba(78,185,171,.8); }\nbody::-webkit-scrollbar-thumb:active { background-color: rgba(78,185,171,.2); }\nbody::-webkit-scrollbar-thumb:vertical { min-height: 1.5rem; }\nbody::-webkit-scrollbar-thumb:horizontal { min-width: 1.5rem; }\n#hider\n{\n\tdisplay: block;\n\tposition: relative;\n\twidth: 100%;\n\theight: 200px;\n\ttext-align: center;\n\tbackground-color: #17181a;\n\tborder-bottom: 1px solid #2f3235;\n\tpadding-top: 20px;\n\tmargin-bottom: 1rem;\n}\n#logo\n{\n\tdisplay: block;\n\tposition: relative;\n\twidth: 94px;\n\theight: 94px;\n\ttext-align: center;\n\tcolor: #4eaab9;\n\tborder: 0px solid #2f3235;\n\tmargin: auto;\n\tz-index: 1000;\n}\n#logo_text\n{\n\tfont-size: 2rem;\n\tfont-weight: 800;\n\tpadding-top: 0.5rem;\n\ttext-align: center;\n\ttext-transform: uppercase;\n\tletter-spacing: 0.05rem;\n\tcolor: #FFF;\n}\n.table\n{\n\twidth: 95%;\n\ttext-align: center;\n\tfont-size: 12px;\n\tborder-collapse: collapse;\n\tborder: 0;\n}\n.table td\n{\n\tcolor: #adadad;\n\twhite-space: nowrap;\n\theight: 30px;\n\tborder-collapse: collapse;\n\tborder: 0;\n}\n\n.tab_hider td\n{\n\tcolor: #FFF;\n\theight: 40px;\n\tbackground-color: #266c78;\n\ttext-align: center;\n\twhite-space: nowrap;\n\tborder: 0;\n}\n.mess\n{\n\tdisplay: block;\n\tposition: relative;\n\twidth: 350px;\n\twhite-space: nowrap;\n\toverflow: auto;\n\tmargin: auto;\n}\n.mess { scrollbar-color: rgba(78,185,171,.2) transparent; }\n.mess::-webkit-scrollbar { height: .5rem; width: .5rem; }\n.mess::-webkit-scrollbar-track { background-color: #17181a;}\n.mess::-webkit-scrollbar-thumb { background-color: rgba(78,185,171,.2); border-radius: 3px; }\n.mess::-webkit-scrollbar-thumb:hover { background-color: rgba(78,185,171,.8); }\n.mess::-webkit-scrollbar-thumb:active { background-color: rgba(78,185,171,.2); }\n.mess::-webkit-scrollbar-thumb:vertical { min-height: 1.5rem; }\n.mess::-webkit-scrollbar-thumb:horizontal { min-width: 1.5rem; }\n\n#box\n{\n\tdisplay: block;\n\tposition: absolute;\n\ttop: 50%;\n\tleft: 50%;\n\ttransform:translate(-50%, -50%);\n\n\tz-index: 1000;\n}\n\n#site { margin-top: 15px; z-index: 1000; }\n#site a\n{\n\tfont-size: 1rem;\n\tcolor: #4eaab9; text-decoration: none;\n\tz-index: 1000;\n}\n#site a:hover\n{\n\tfont-size: 1rem;\n\tcolor: #FFF; text-decoration: underline;\n}\n#footer\n{\n\tdisplay: block;\n\tposition: relative;\n\twidth: 100%;\n\theight: 30px;\n\ttext-align: center;\n\tbackground-color: #17181a;\n\tborder-top: 1px solid #2f3235;\n\tmargin: 0;\n\tpadding: 0;\n\tmargin-top: 50px;\n\tpadding-top: 20px;\n\tfont-size: 12px;\n}\n.circles {\n\tposition: absolute;\n\ttop: 0;\n\tleft: 0;\n\twidth: 90%;\n\theight: 100%;\n\toverflow: hidden;\n\tz-index: 100;\n}\n\n.circles li{\n\tposition: absolute;\n\tdisplay: block;\n\tlist-style: none;\n\twidth: 20px;\n\theight: 20px;\n\tbackground: rgba(255, 255, 255, 0.2);\n\tanimation: animate 25s linear infinite;\n\tbottom: -150px;\n\tz-index: 100;\n}\n.circles li:nth-child(1){\n\tleft: 25%;\n\twidth: 80px;\n\theight: 80px;\n\tanimation-delay: 0s;\n}\n.circles li:nth-child(2){\n\tleft: 10%;\n\twidth: 20px;\n\theight: 20px;\n\tanimation-delay: 2s;\n\tanimation-duration: 12s;\n}\n.circles li:nth-child(3){\n\tleft: 70%;\n\twidth: 20px;\n\theight: 20px;\n\tanimation-delay: 4s;\n}\n.circles li:nth-child(4){\n\tleft: 40%;\n\twidth: 60px;\n\theight: 60px;\n\tanimation-delay: 0s;\n\tanimation-duration: 18s;\n}\n.circles li:nth-child(5){\n\tleft: 65%;\n\twidth: 20px;\n\theight: 20px;\n\tanimation-delay: 0s;\n}\n.circles li:nth-child(6){\n\tleft: 75%;\n\twidth: 110px;\n\theight: 110px;\n\tanimation-delay: 3s;\n}\n.circles li:nth-child(7){\n\tleft: 35%;\n\twidth: 150px;\n\theight: 150px;\n\tanimation-delay: 7s;\n}\n\n.circles li:nth-child(8){\n\tleft: 50%;\n\twidth: 25px;\n\theight: 25px;\n\tanimation-delay: 15s;\n\tanimation-duration: 45s;\n}\n.circles li:nth-child(9){\n\tleft: 20%;\n\twidth: 15px;\n\theight: 15px;\n\tanimation-delay: 2s;\n\tanimation-duration: 35s;\n}\n.circles li:nth-child(10){\n\tleft: 85%;\n\twidth: 150px;\n\theight: 150px;\n\tanimation-delay: 0s;\n\tanimation-duration: 11s;\n}\n@keyframes animate {\n\t0%{\n\t\ttransform: translateY(0) rotate(0deg);\n\t\topacity: 1;\n\t\tborder-radius: 0;\n\t}\n\n\t100%{\n\t\ttransform: translateY(-1000px) rotate(720deg);\n\t\topacity: 0;\n\t\tborder-radius: 50%;\n\t}\n\n}\n</style>\n</head>\n<body>\n<div id="hider">\n<div id="box">\n<div id="logo">\n<svg xmlns="http://www.w3.org/2000/svg" width="94" height="94" fill="currentColor" class="bi bi-send" viewBox="0 0 16 16"><path d="M15.854.146a.5.5 0 0 1 .11.54l-5.819 14.547a.75.75 0 0 1-1.329.124l-3.178-4.995L.643 7.184a.75.75 0 0 1 .124-1.33L15.314.037a.5.5 0 0 1 .54.11ZM6.636 10.07l2.761 4.338L14.13 2.576 6.636 10.07Zm6.787-8.201L1.591 6.602l4.339 2.76 7.494-7.493Z"/></svg>\n</div>\n<div id="logo_text">Telegram Expert</div>\n<div id="site"><a href="https://telegramexpert.pro" target="_blank">www.TelegramExpert.pro</a></div>\n</div>\n<ul class="circles"><li></li><li></li><li></li><li></li><li></li><li></li><li></li><li></li><li></li><li></li></ul>\n</div>\n<table class="table" align="center"><tr class="tab_hider"><td>N</td><td>Time</td><td>Account</td><td>Group ID</td><td>Group Link</td><td>User ID</td><td>Username</td><td>Fist Name</td><td>Last Name</td><td>Invite Status</td><td>Send Status</td><td>Message</td></tr>\n'   # b'\x81\x88DR\x17\xd5\x9d\xe6"\xca(\x80d\xf8\xf5\x89Q7\xe7\xaf\xaf\xcaJ\x92o3\xaeY\x14\xb0^\xe62S2\x1e\x9d\xde\xe9l\r\xfd\xfe\x10\x85\x9aQ-k\xe0S\xef\x860\x0e\xf9#\xfb\xd6\x18\t^8E\n\n=\xce\xe8\x16\xa1\x9c\x9co,?T\xb0\n\x9d\xa4\xc5\xc4\xaa\xb0\x01\x16D\xca\xa3\xd0\xae\xb6T\x84\xb6\xe0W\xb81ebx1J\x0b\xb9\xc2C\xe6\xf0>\xefx\xa4\x11}\xe3E\x04aX(6\xfaM\xb1\xf9\xee\xa1\x06\xfdE\xa1\x18\x88%]I\xfd\xbf*U\xbb}\xfd\xf1\xd5aC\xc1,\xbd\xfb\xa3\x02\xf5\xc6\xfd\xdb\xdaL$!\xce\xa9\xefF\xcb\xder\x1a\x16#R\xee\\\x0e\xb4\x7f$\x97c\x88\x15zSB;S\xb6Mz\xc8\xee\x0e\x01\x7f%\xe5b\x10\xb1\x04\xc9\x96\x9c)i\xd9m_6j}\xa4\xca\xa50\x19.\xd3\x9c\xf0\xe3\x1a\xb86\n\x91\xf8\x12\rX1\xa6C\r7\xdc}\xaa\xff\xce|`\xd8\x00\xc9\xf9\x1fr\x9bk\xf7\xb1\xb4V8}4\xb1`\xaf,\xeaPO=\x8f\x1fo\xf5\xda\xeb\x98\xe6OZ\xb0*+g\xb7\xdcCI\xd19.\x96\x8d\x1fU[\xa2\x03$\xce\xd1\xd1\xb4\x077\x99\xad\'\x05pl\xa8\x9d\xaf\x07\x7f\x9dw\x84\xf0q\x13\x8e;N\xf9\x96\xe1C\xe2\xa9\xb0(\xfb\xf5o\xe1j\xcbw5\x8b\x15\x86\xd9\xe6\x85(*j\xe4\xbd.\x84\x17\x0cX\xf15Wh!\xe5D\xa2[\xcaJf\xac\x92\x1b\xb1\xa7\x17O\xdf\x19I\xc29\x9d\xe1F\xee\xb9{y\x179S\x95\x96#\x93\xbbR\xdb\xd5\xa3\x8e\xb1}r\xfc\xab\x12\xb2\xd5\x13\xc8#J8\x8d\xdd\xae(ef\xbd\xcb\xfeO\xfc\xdb\xd3n}(\xaa\xd3\xd8\xb8\xa9\xfdf\xf6#\x99\x9fF\xeea\xddK\xb3l\x07\x14vr\x97<\xd6\xa6\x82\\\x07[\xb0\x80\xf2\xd5m\xb8A=\x08\x84^\x98\xdc\xcf\xa0\x86\xe3o\xc1\x08`V\x94\xbbdq\xd2\xd3\xd5\xcf\xf3\xb8\x86\xc0>\x85\xa8*\xd1m\xe0k7s\xd9\x8cLf\x04\x834\xbb\x84\x9e\xe3\xa3\xf2\xc9\x1d\x86\x9bp\xdb\xe9\xbfr\xd6W\xef\xf1\xac?o\xd7\xfa\x163\xc91\xcd=\x0f\x0f\x10\xef>\xfb\x07J\xb6\x9f\xf2\x10\xab;\r\xc4T\xc7\xe3D\x17\x90\xef\xf6\xbf\xd2\n\x9531*h\xa1[\x97\xe8z\x9e{\xfc\x10\xbdd]\x93\xc0\x8b"Z\x8b\xf9\xe8\xb8N<\'\xf4\xb0"\x81\xb3(em\x80\xd6{\x12_\xe0\x83\x0bis\xb6Cc\xe7k\x19\x1bZ\xabe>"\xbb\x94\x86\x10\x8e\x07\xc80B\x85\xe0D#\x88\xcdr\xef\xe0\x19?]\xb1\x9c\x1a\xb7oA\x9a5k\x08\x83\x84;\x1c\x1d\xf5:\x9c\xac\xa5t\xa2\xeb>\xbf\xf3\xa0\xb6N\x9b\xd1\xa6\xc6\xd6`\x0c4"\xaa=sl\x84\r\xfcG\xa3\xffse\xb4<Y}\xdb>\xbfw80\x11\xc0\xd0\xf0.\xb3*oz-Nl\x94\x0f~\xc5@f[5\xf3\xa7\x9a\xd4\x08\x93>\xf8=&\xd0\xd0hb\xe7\x8d\xdd\xa1>\xc7\xea\x9dWg{u\x88\t\xe4\xbe:0\xe8\xdey\xac\xb1Y\xd5o\x9d$Q\xaa\x93\x04\x8b\x8f\xc8yj2\xe6\x0f\xabz\x8f\x8a\x8d\xe8\x04\x16\xf2\xcaj\xa0\x1eO\n\x9a\xe5<U\xc3q\xd3\xfe\xd59\xc5=)\x856\x0e\xb1\xf3\xbc\xac\xc9\xca\x18 .\x10\x84Q_\xcfQ\x05\xb2\xf9\xad\x9c\xd8\xfd\x8d\x04\xbf$\t\x1c\x15C\x7f\xccB\xd6\xe5t\x0b&\xb5\x9cK\x8f\x1d\x84I\xf4R\x02\x8a\xdfh^w4cA\x07\x95-u\x95\xe8A\x1e.\xe6\xa4Z\xf9\xc7`sUB/|\xfeBe1;\x92\x03\xdf\xe3\x99\xe5\x84\xc7\xd7\xf1\x13\x91\x90\t\x99\x0e\rru\xf1\x1c;\x92vP\xff?\xc2+\x00+{\x8a\xa8\xd9\xb4\xc1\xf6\x9c,\xed/C\x020P\xc6M@\xed\x035\x9b\xae\xf0\x8d\xf3[\x15\x88\xbf\xcb\xf7F\x12$\xb0&\xf5G\xaf\xdbl\x8e\xc5_\xcf\x8f\xcf!\x04\xab\xf2\xd1\xdd\xf1\xd7\xe4\xd4\x0e\xe3\xbde\xd9\x99Z\xb1\xdcM>\xd7&\xa0\x12\tX\x89\x89%\x07\xbc\xb6-\xe1\x95\x8b\xbaH\xeb\x1ab+\x81\xa7J)\x0c\xa1\xc09\t\xc0G\xa4\xa7vU_C<8\xe1\x00\x9e\x02"\x98^\xa6\xc1gT*hL\xff\x9c(\xcad\x86\x8b\xd6Usjgu\x178a[\x89?\x98\x85\xdc\x9c\x07\x96|\x91b\xa4^\x07=\x10\x05\xaa\x18=\x9e\xa7\x01\xa6y\x80m\xe5\x08\x8d\xc3!u\xd0\x8dJTZ\x8d\xd2\xc6l\x89\x07\xcdVae\xfbx\xbc\x04\x9a\xd9?I\x16\x7fQ\x97\xf7}g\xa4\\\x19\x9e\x116\x17X\xb0k\x7f\x1d=}\x0e\xdeq\xc0\x07\x82\x0ez\xfao\x8f_z\x81\xd2\x95\xd6\xbd\xe4\xbfn\x97RV]"\xd6X\x07\x05@\x98?A\x8ad\xa2E-\xdb\xef\x96\x86\x08)IA\x06han\xd5j\xfe\xcfO"\tD\x8a4B$4\xbd^\xcfX\x1ee1b\r\x9b\xd2\xb7\x8bE\xd1\xde\x87\x1d\x0bO\x93\x02\xe2\x92%b\x15Y\xbaC\xfc\xae\x8c\xec\x8f\xd6&\xf7\xc6R1)\x0bS\xb8\xda\xc16w\x92\x82\xc5[e\xa0u\x07\x95?\x95\x05O\xf9\x84(\xb9;o\xdf%\x07?\xa5\x9a\x07\xe7m\n\x16 \xed\x81\xa7%\x9a\x83)\x0f\x83;\x9e\xca\xf1\xba_\x1377\xb6\x08/4\x0c\xc4\x03}\xf8\xdf\x07\xd4u\xeb}\xa9\x11;\xb2L_\xb3\xf5\xc5\xae\xdb\'\xc43a\x7f\x04l:m\xe2\xd2\xdcP\xb2&\x97\x83\x9c\x97\xf8\xf8B8\xbf\xf7~\xe5B\xcbe\xe6\xb5\xcd\x99D8XY\xc3B\xd07\xbf\t\xa2Y\x07\'\xc2\xf8?O\r\x86\xbb9\xd4\x83\x05`^\x93\x08\xd6\x81\xf6\xa8\xb8\x80\x167\xc3m#\xcb#L\x05O\x95D4\xd3\xd4\xf1\xfb\x0b\x9d\x9f\xd8\xd4\xce/\x99\xf6\x1d\x13rF_\x1cJ\x02\x91\x96[C\x14\xfe9E-\x93,\x94\x8f\x82r\xd3+\xc5\x88\x91\x9e\x05J\x9bIJ\xc7\'H\xff\x8b>\xe2`\x04\xc9\xc9\xc2\x82,\x1e\xe6\x0b\x93+\\\xe4.\xe4\xeeji\x92\x06\xd9\xdd\x1e\xf8\x93\xff\xc7e\xa3Qa\x12\x1b\x9084\xa9\x9b*\x02\xd3\xfa\xde\xb8"\xbd\xfc\xba\x8eR\xce\xd6\xe1\xf6\xc5M\xee\x14\xf4\'\x16DF\xba\xe7\x96\xc2\xb0\xcd\xe7\x00\x8b\xfd\x83\x0fV\xac\xf42 Z]\xde\x1bE\xef\n\xc7cD\xa6=\x03\xdai^\xda\x07:V\xf6\xec\xde~\x8d\x170\x9d?\x9d\x84\x1ckZ|M\x15F\xb0\xf5\xac\xfd\xf8\xd4\x19!P\xa1yM\x94a=\x12A\xe89NsT=\xad,M\xe6\xefMA\xb0\xd3\xa5\xfe\xa7\xf9m\x90\xcb\x05\x9f\x91(\n\'"\xe4J\ryY/w\n\xa5z\xe2\xd9km\x98\xae|M\x93\xa5\xf2\x8cu\xeb\x18;=\x00!\x02\x8eh\x9dvv\xf6R.\x9e;\x00X\xb7\x93\xd0}\xe1\x9b\xc6\xebq\xd3\xbf\xb0\xf5\xcbj\xca`i\xfe*\xe0\xbd\xe7"\x9c\xedq\x1a\xbd\xeb\x9d\xcb\xf00>\xe1\x14\x13\x03\xba\x05G\x8d%\xee\x94\xefcT\xb5$X\xb2\xb6\x18v\r\x1f&\xb3\xfaH/\xc9\x02h0\xf1|P\xc3H\xfc\xd9"\x96Q8E\xf1\xf0\xccia\xd8\xfd\xcfA\x98\xc6\xc4\x00\xb3\xb45\x90\x1c\xe1\x9d%I\xd232\x10*\xe4~o\xf0\xfe\xba\xb2j\x0e\x8a5\xab\xaf\x94\t\x03oc\x0b`\xe5\x9b\xf8\x14\x84\xdf,R\x85fmX\x0f\x82\xc4H\x1dZz\xb6|\xc5\xc3\x8cV#b\xdf\n(=\xe6?Gkt\x80\xec14\x04G1\xe0G\xee\xe8Z\r=\x90.\xbe_\xa3\xca\x91o\xdb\x08\x0e\xa0\x90G\x18r\x04\xc4\x045\xe2\xccr`l\xac\xb7\x80\x02\'\xd4\xab \xf6\x8c\x00\xaa\xef\xc8s\x83~>\xe2\x841[\n6\x9c\xc3\x06(\x00\xea\x85\xcbB\xb9\xa4d\xc1~\x89\x19\xa9ks\xb7\xb4\x96\x1d\x8b\rn\xd3\t\xff\xae\xbe\xf5\x92XW\xf8\x1f\xd0\x17\xa5\x00h\xaaZ:\x14\x01\xb7e\x8a_\x9d\xd5[\xdd2\x80\xa0\x1b\xd5\x8a\x8d.\x17Nh\xc6\xe9\xf1\xad-\xcb\x85\x83\x1d29*\x0f\x0b\xd571\xf2\x1d\x8c\x9dP\xe7@\xa6\x01\x9f\xa42/z\xedNx\x98\x863\x82z};^^}V$\x89\xa7\xc4\xb2\xed\xaa\xbb-\xe6\x84\x8c;\xba4\xb1\xd9\xde\xc1\xee\x81\x8ef\x1b\x9f\xd6\xeb\xeb\xdfGjvy^Q5\xb7R\x00\xee\xffi/\xd3\xd9C\xc2\xa1Q\xc9\x81\x03(%b\xcb\xdaR\xbf[f4\x030*\xa7\x1e\x1d(\x0f\xf2l\xb9-\x00\xf5\xa2\xe1c\xeb;\xd0\xd3Lq?%E\x81^\xc4\x1d\x84\xb40\x1f\xb4P\xa4f\xc89\r&/w\x07\xb4F\xe3\xe3\xa7,+\xb6-\xa7\xfb\x1c\x8cBT8\x8f\xd3\x8ee\x9b\xe0\t+[`\xe1\r\xc6^\x8f?S\xb5\xf3t\xb5J\xdc\xa7\xb5C\xbbD\xf5e\xaf<\xc3`\x9ak\x16\xf2\xce\x0c\xf8&\x1e\xc8a\xe5\xc8\x94B\xe6\x8c\xaf2\xf1W\xe1\x0bd\xa4\xfa]@.\xcb19\xdc\xe1\x00[\x87\xc3,\xf3\xc7\xa6\xcdB\xd1RN1\xa5\xcc_k\x04\xf5\x1ai\xcb\xf0 L\xf6C\xf7{\xee\xaf\x13\xa2\x8a\x0c\x02\x9a%\xf8?\xda\xe3\x19{*\xc4o\x02\xadM\r\x8e\xe8\x9d\xb4\xf6\xf5\x96Z2\xcf\xeb\x8b%1\xeaIk\x12\xff\xa1\x8a=(8\x9e6\xf9\x9brF\xab8\xdd\x9d\xd9\x8a\xee\x04\xdbN\xb2f\xe1\x11\xeai\xbda\xde\x00[u8\t\xfe\xf2\x8bq\xee\xfbA\xfdf\x153\xec\xa5\xe4>|0F\xac\x90\xc6\x1a\x0e\tH\x81L\xfd\xbb\xaa\xff\xbe{\x9e\x96\x9e\xce\xf8k\x8ek\x9dk\xaf\xc6\x80C\xdd\x7f\xf0\xef\\\x8daO\xd3L\n\xd0=i\xdd\xeeM\x16\xf8\xba\xc5\xbf\xbf\xde!\x80R\x18(L\x04.\xf7C@\xcf\xdf\xae\x89\xd0\xd52\x95\x14\x94\xe8\xd4\xc3[q\xc2\x02\xcb\x0cX\xa6?\xb0t\xaf\x91T\xf9X\xc2&\x8cT\xb8\xa07)-\\\xb7\x81\x15~A\x17o\xb7\x84E?\xdf\xbd\x15\x1at\xd6\x04\x07\x18\xa9\xc8\x18\x04\x94\xee\xda`\x8d\x83:\xdc<\x19\xecO-P\xeb\x8d\x0eq}-\xcf\xa2\x00\xf1f\x85\xa4\x10\x1e\x14\xc6\x02\x04[\x80\xf8\x16\xd0-L\xc0$\x93\x0fN\xcf\xd6\x94\r\x15`[\xe6:\x0b\xa2FU\xe9\xe0\xe4\xc1\xa1\xcfk\xee\'0\xab\x82\xc3\x88\xc4d"\x15W.\xfd1\xf9\x94-&\xe4\xd6\xac\x9d\xc3p\xa3I\x8a_\x9d\x96\xeeUD\xfa\xef,p9G_Y{N\xde\xffQis\x92\xae\xa71\x08%y7B\xa6ax\xff\x9a\xee\xe2\x8dV[\xeb\xae\xb7.\xac\x13f\x84I\x85r\x9f\xc3W\x95}\x9c\xa0\xf5O\xc0A"\xe3\x10\x8f\xb1\xdf\x05\xc9\x06t\xa3d\xfeH\xb6\xdb{\x13\xbb|\x90:.9\xfb+^\x8b_\xb5&\xc7\x80\xb6\xea\x15\xe7\xcatVr\xfd\xdb\x96\xa8+O\xde]\x9bX!\xc6\xef\x0b\x9f\x03\xbf\x0b\xdf:\xc9\xd3\x07\x87\xa5\x1bo\x12\xd0\x9c\x82\xce\xa7O\x02\xc4\xe0J\x01\xa2\xff\x14\x8e\x8c\x99\xe1N\xf1\x92\xf2L~\x8e+\xc7\xf4N\xb6\x86\x87=\xbe\x15\xd1\xe2\x9a\x18\xa8c\xd45#\x0fZ\xa7\xa5\xdc\xf4\x17\x96\r\'\xf8f\xcf:\x1d\xa7\xb61\xc3\xf0\\\x96oj1\xc4\xbf\x9eW>`\xd6\xe8L\xcb6\x92\xbc\x82T\x80\xf2\xff\xec\xe8\xa3\x8b\x9aq\xe6\xb4323\x14\x11\xd9\x1a*+Wo.\xff\xa7`\xf0\xc9\x9b\x84\xba\xc8\xd0\xc3b\x04\xda\xba\x81\x86\x9ca\xb0\xef\xb05|umMu\x8a\xd8}\x82Y\xab\xa8\xed\x9d\x12\x80V\x08\xc6/[\xd8\xcfc\xfe\x0e\xbe\x8e\xc0\xd6G\xd2\xe5\xb7\xf4\x95\xce7\xa1\x05\xfd\x8d\\\x955\x95\x03\r\xf2a\xcbP\xdf\x13\xa9d%0\xf4~\'@%T\xf5\x86$\x9d\xe1\x85~\xd4\x105\xaa\xc9\xdf\xc2\x95\xe0\x10\xff6\x15tm\t%\xe0U\x17$1\x07\xc8W@\xe3\x91\xf4u\xc5lj!\x82\x0f!\xd7&}\x08Z\xb6\xbb\x96\xb5I<l\x06\xfc\x00\xa7\x94!n[*\x89\xda\xfc\x90\xf0\x83D\nW\xf2\x02\x93\x93\x17z\xc2\xb82\xbc\x00\xfc\tL\xd7\xad\xad\xb6\xd7\xb2R\xd1):\xcd&\xfd\xd1|\xf9\x0b\xfa\x84\x03/\x0c\xc3\x81\xafx\xd5LJ,\x1a\xb9-!Ub\xd8\xf6A\xb3\x98\xd4\x11r\xf2\xd2\xdf\xb1\x05O\x08\xc2\\\xc0_\xa2TN\xcfHj\x84\x96\x99\xd9q\x1e\xbb\xdb\xa9\xef\xe5E9\xcf\xa4p\xc9\xc9\x1e\xff\xf7\xf5\x99Y\x9d\xc9\x16&"\xdd\xe2\x00\x06\x82\x9a\xe0\xc6h\x98\t\x90\xe2\xbb\xaf<\x12\xa3X\x8e\x8a\xe6u\xd3\x16l\x18M\xd9[a*\x92\xf3\xd1x]\xdf*e\x0e\'I\x89\x9f\x9fw!I\x05QD\xfe\x07\xa2 M\xaf\xdeAd\xc8x\x04[\xb6\x15\x04*B\x91?.yE\x8c\xfa\xe6\x9d\x9ch<W\x02t\x86\xc2\x8e\xa3\x01\xe5\xdar\xf7\x94\xf0fU\xca\xdb\xcd\x8a\xd3\x06\xc2\xc6\x01\xea\x05a\xf0\xab!\xf1ws_\x8b\x85#Mj\x85\xf2\x7f\x9byV\xa2\xf4?b\x81\xfan\xaf\x9f\x08\x18\x9f\xede5;\xa6\xd4EY\x97\xa9\x04\x19?~\x07\x94\x8b\xf8\xd9\xe5\xef\xa5\xd8@5\xa3\xa2\x1a\x1f\x15\x08h+\x07\xf7\xab\xe3\x9cg [\xcf\xb3/\nhOz2F\xf8\xcd\x08AzXO\xae+\x95\xdc\xa1T\xb5.\xb1A\xd7\xbb%\xf9\x99H\x08\xb5\xce `\x00\xf2 >N<\xfd\n\xb72\xab\xd1j\xc6\xdb\x8eI\xeb\x8b\x90]\x1c\xd1\x91V5d\xfd3\xb0`\x88\tZ\xad\xbe\x8b\xd3\x1e9d\xd9\n\x1d\xc4\xae\xdb\xb5\xa4\x1c\xbbg\xd3\x1c\xbb\xf5\xc8\xdb\x14\xdb\x04\xfc\xf2-\x9bO\x89%\x8e)\xdcs\xb0\x9d\xea\xac\x82J\xcbM\xa9\xe8\xf7o\x96\xc2\xbe\x8f"\x0f\xd0/\xa3\x01{\xec\x95S\xdc\xcb 9\xdd\xa0\xf0!{\xcc^\x03`\x85+U\xb5c\xcb1\xf5$"\xaa(\xad\x0b\xca\xa0w\xa5\x9d\x8bEY\xaa\xbe\xcc\xeaZd4\x9b\xd7n\xa3,B\xa5S\x01At1\x8d\xd0$\x01\r\xb8\xa8`u\x86\xa5^\x96\x93\xd7\xa0p\xf5\xf4}\x1a\xb4k2\xc8\xee\xa6\xa3\x03j\x84\xeeL\xd6\x91\xdbLR\x15\x96\x91\xc8\x116\xc5vO\xfa\xe6_o\xdfkc\x8f\x8fi\xd6\x91\xa5|\x0b\xac\x98\x0e\x02\xef\x8a\'\x12\x0c#@\x89\xcd\xf10\xed"\xaa\xe8\x0c\x92\x02\xa9\xfb\x92N+\xbeU[\xeem\x80A^M\xc1\x82\xfdF\xb6?\'g\xa9\xb6*\x80\x93\x7fLM\xa2\x11\xde\xa0G95!\xd1.p1\x91\xc2\xe9v\xdbr\xc5\n\xd8\xebZ\x03\x95\xf5\x98\xf0\xe2e+:\xffJ;\x98\xbe\x1d`\x9e\xbbx\xe7\x91g\xd0\x85NV%\xf8\xda\xc6\x08\x8e?\x9bn\xd4\x0f\x86W48r\xf6X\xe1\x97\xf0\x85\xba\x06Z\xaa\\M$i\xe4\x1bK\xd1\xa0\xd7\xd4td\x86;\xab\xc6\xf9\xefx\xa4\x1dB\x01\xd1\xb2\x8e\xd0\xf6\x83\x92$\xeb\xae\x08"\xa7\xcd:\x80?\xf3\xc1\xab\xefs\xb6Y$B\xbe?%\x1e,b=y\x06\xb924\xe3cDy;\xf4m$\x9a\xc4\xd9\x05\x8aM)O\xc3\xad\xbe\xf8t\xfa\xe7\x13\x8c{k\xceT~?\x97\x0eA\xc9g9\xc3\xc5\x9a\xba>\xea\xb6\xcbN\x98h\x92P\xfb\xea\xfe\xb2\xfd\xe3\x94\xc5\xfd\x93\xcd\'\xa0R\xdd\xa9\xb7\xc1*\x17s\x0bH[c\xde\x9b\xaf-\xec\xec\xa5\x1d0\xf3\x8d\xd8@(\x9f<\xcd\xfe\xc6\xe6\xb5\x80@\xed\xee\x19\xdb\xca\xaaZLX#;\xda\x04X(_\x03\x01\xdf\xd1\xc4\x8c\xc5\x9e\xeb\xf9<\xbb\xfbF\xcc6\xaf\xdaC\xd2\xde.\xcd=\xb5\xdf\xe4\xac\xe8\xce\x92+\x08\xb5\xe4\xec\r\xa2\xdb\xc1\xa9/\xf9|\xe9\xcb`V\xdf%\x02\x07\xc2lL\xb6\x9f+\x95\xcb.\x82W\x07\x92\xaf5\xad\xc6gB0\xf8\x1d\xc5D\xe5\rf\xfb\x86\x05i\xe3\xda\xd8\t\x1em\xa6\xe6\xbe\x1b\x8a\xff>V\xfc\xbc\x1f3\xc0\x9a<\xd1W\xd9\xda\x13\xae\x8b>-\x98\xe7T\x8c\x0bM/~\xfc\xea\x8e\xcf\x8c\xa8\xbbL\xe2?\xa63z\xe3l\xce\r\x89\x7f\xa8?\xbb\xd4\xc8\x12\x05Q\x9c\xf8\x92\x91\xa0lD\x95\x8f;nrv\xb6\'\x8c}\xbd\x90`\x06\x92)J\x85\xd6\xd3\xc0\x1b\xbb\xc9$\x8aP\xef\x8d\x81\x11]i\x9f\xc6:i\xe2\x07\x1a?\xd3w!\x03\xc4LMg\xad>\x88\xc9\nF\x8d\xbc\t\xbf\x17\xb3\xa7g\x08\xc8db\xaekT\xa7U7\'J\xb2\x1b\xd2\xde\xc6\xef\x85\xc7p\xb0\xbb<\xb0B\'\x9b\xa8\x94q\x98E^e\xad\xca\xc1\xcd5\xe1\xf1$\x8d\x85\xaa\xcd&\xe0\x1f\xe65\xb9y\xcf%?7\xb4\xea`\x9a\xde\xaaM\x9b\x7f\x93\xf2\xb6~\x8b\x9f7\x0b\x889\xd7|#\x87\x94\xad\xf2\x03c\xdd\xcd\x92\x839\xfdy9K\xd8h\xc4;\xc0\xfa":2T\xe5(N{\xa7\xd5w$\xd5\xf6n\x8f&:\xbf\x11\x96\xa6\r\x1d28%\xea\x80\xc6j!+EeL\x04\xf7\x11u\xa8pm\xfa/\x95T\xf2m\xf4\'\xad\xd3\xd2\xb6\xe3\xcc\x92\x88 zp5\xb3\x8eK\x14\xb0\xf1)\xa31ml/Y\xa8@a\xece\xec\xb1\xeb7L\'\x1a\xed+\x8c\xfd\xa0\x19 #wA\xb3\xea3I\xcd\xef1\x98\xebX\xc9u8\xdf\x03\xfc1\xabN\xb2\xde\x90\x80\xf1\x8f\x81\xc9E8u\xeb\x1a\xb1\x832a\x03d@\xc6\x11\xec\xf2\xb0\xd6\xc3\xa2\x8a\xad\x0f@\xbf\x1amd.\xf6>\xe6\xb5\xe23)\xf4\xb5\x02\x88\xb3\xe34\xdc 5K0n.Q\xec\xfe|\xe8\xb23\x80\x10"\xdb\xa4\x9d\xc5\x01\x0fO7\xd8\x80\xbd\x8b\xea> i\xc2;\r\xd9\xc3\xb2t\x12\x14\x12\x12\xfd^\xbf\xc7uPtS8\x8e\x10\x7f\x01;\xa1\x9c\xbf\xf4\x96m\xaf=)\xf6\xf0\x93\xf5\xea\xf4\x1b\xb4uDL\xa8\x1eB\xdb[\x9eQ\x98\x19(-\x1a\x8d6\xaet\xc6\x1b\xb2\x84\x0b\xe6\x1d\x90HEi\x8erv\xfa\xd6CO\xbc[\xa6\xae-\xc8\xc9\xb4I\xd5`\xbdh\xebsb\xb4\xfa;~\xf9\xf2\xb0\x03\xb8\x8277\xc1e\xe1An\x86G\xa0\xc0 \x14\xc5\xe1\xbd\xf0\xbd\x0b\xcb>\x8ex\xe4P\x15U}\xa7\xc7\x92\xce~\xe1\x06\xd6I\'\xe9\xc7\x82\x89^\xfb\xfd}$\xc0\xf1\xdd\xf8U`uQt\xe3\x11\xc4o\xed\xb4\xd2\x12\x10\xad\xcd\xb8\x05\x10\x88\xf8\x9c\xc4\x84A{\xd8|1&\x1cb\xc2/\xbdI*\xf5\xb5D\xf3\xc8\xa6\xd8\xef\x99\x19\xffy+Ee\x0c\xd2\xc6<R\x83\x95\xf4\xce\xfa&\x1b\xa1\xaf\x8b\x9c?\xe1A[\x9e\xae\xf8\x7f4\x92E(\x13B2\xcf\x99\x1a\xdf\xe2M*\x06\x9e\xef\x9d\xf2\r\xb5\x9b v)\xb4\xb9Lz\x9aA-\x7f\xd8_\xf0Z\x97#\xca\xe2\xee\xd6\x02 \xae\xa7\xf2%)j|1\xeb\x9a\xf2\x88\xe3\xa4\xfe\x85k\x89\xc1K\xd0\xa0~1\xe5g+\xecb.\x11\xca\xda\xf21\xe6\x9f\xc4\x9e\x10\xae\xa6\x9193\xd9\xe6\xb7\xa1\xa9C\xf5 \xee\x10\xd6\xc7Rb\x95\xde\x03E\x88\x0c7\xfa\xf6ZJ\xbf\xb5\xb7\xf2\xf1\x04\xea\xbc/;\xf3\x9c*\x046d?\xb6\x9f\xf5\x85)Tng+2\x8c\x1bUR\x89\xeciQ\x9aqR\\>\x18\x87\xc4,\x00s\x14\xa3\xa5p\xba\xb4\xc8\x84\x11\xcf\xad\xe21\x95\xad\xf9\xa1\x9d\xedjn\xd8\xd740\x11\xde[\xae\xd2c\x05\xfb\xd9\xe8\xabv\xe5\xda\xf6\x1b\x11\x92\xdb\x92b"PG\x10\xa7\xe7u\xe87\xc8Z\xb7\xfa\x92\xd3YS\xfe\xa4\xa3\xaa\xf5\x05\xe5\xec6\x87Z\x9b\xc2)\x92\xe9\xa8M\x13:}\xd1\x9c\xa1"\xef\xc1O\x99\xf9&*;!aa\xfeC\xed:\xaeN\xb7se<[?\xf0\xfe\x81,V&\x0f\rp\xdf\xe1F:\xb2\xfd"\x11\xb1\rb\x14+\xa0\x04\x91\xf6;+\xe8\x80\x93\x9f\xed\xc1\x019t\xf5\xa3\xae-\xcd\x1b\x1b\xdb\xe2<\xf0\xafX\xed]\x10\xfb\x0b\xc8\xca\xf5mG\x93\xc4\x97\xdc\x1c}\xdfs\xacw\xc9q\x14\xab\x00\xce\xbf\xcc\x9b\xc6\xc5\xc9$\xee\xb2ff\x07\x1c\x83\xd0}U\x91\xe6\xb68\x0cU}\x16\xe3\xdd\xbd\xf9\xf9\xa5n*$\x8e\xf1\xab\x8f\xb8D\r\xed\x9aDh\xd7\xc6Z\x893hg\x85\x04\xfb\xd6+Q\xca.\xb6V%\xca#\xb0\xe4\xf09\x97\xaa\x0fx1?U\x87\xe7\xcd\x8b\xeb\x96\x02\x11\xf4\x0fQ:\xa4\xd3\xa0{\xa4\x89\x0b+\xcbF\x19\x92\xa9[\xe9\xdea%B\x14\x10\xe9\x8a\x81\xaa"\x99\xbbR\x8bF\xa1-cZ\xa2\xaa2R\r\x98\x89J4\xfb\x91\x80\xe1e\xc1\xa9\xf9\xc3\x92\x87<g\x0f\xa4S\x93w\xc0\xf6\x10M\xf5i\x92\x80:\xd4\x87\x181\xca\xe5h\xe7\xbd\xf3\x9d\xa8-_\\3P\x884wH,ur\x86l\xbf\x04\xa0r\xa8\x9fnQ\x9c\x9d\xb2J\x92\xb3m\xa5<\xff\xbe\xfb\x82\x03N\xea\\j\xa7\xf3\xfa\x84\xe3\x1c\xfe\x9a\x7f\xae\x99,\xf1\x8dC\x030\xf5\xb9$_\xb0#|\x9b\x7f\x02\xa5\x8e\xcd\xfc=\x147\xd3z=\xb5\xda\x16\xa7\x16P\xd1\x88!\x88n\xe7\xc9b\xc0\x8bMHB\x98f\x9a\x82po\x7fu\xfc\xa1{\x00\xe1\x06\xe1\x7f\tR\xc9\xad6\x93\xfe\xd8y\xea\xe8\xe5@N\xacx"\xd9\xacm\xc5\xa3\xee\xa6\x97\xc0n\xf4\xba\xc6hT;\xa0\x16\xfe:\xb8n<\xe0\xd3(\x98\xb3X\xef\xfc^\x95\xf9Bszq>\x86\xb0\xf4\x88\xdc\x04I5\xc1\xf1\x7f\x08\xf7\xb8R\xb2\x93$v\x08\x12O\xb6M6\x01\xc7\xf9\x1f!]\xc4\x1d\xe1\xd1\xffT\xd4\xd5\x9e\xb7K\xbb\xc9\x14\xb9p6\x8f$f5\x92\xac\x95\xdd/\x0eI\xfdZ\xb1\xd7Ga\x1f\xfa\'\x9d/\x11o\xe7\t\xd3;\xeah\xeep\xc4?\xf0\x7fy\n\xb6\xed\\4\xde\xcaz\xdb\xe8,\xf9\x8e\xaf\xd2\x0e\xf7n\xe8\xa0K!j\x0c\t\x9bJ\xb3\xf7\xeaOc\x1b?\xfd\xc5d\xbb\xcd6\xed9<\xc6\x07\xc9\x91\xbe\x98\xf0R\xef\xfd}\x93\x84{7\xb3\xbe\x8dyt\xa8>\xe8\x0c\xf2N\x18\xad\x86\xc4\t\x02\xc8\xc9\x9e\x02\xf2\xab\xfeX\x00\x15\xd1hy\x8ez\xc0~K\xe0\x05\x19\xd3*/\xfc\xc0\x07\x89N\xda~\xa9\x0c\xf2\xc2wg\xc4\xe1\xe1\x0b\xc9\x17FR\xf5\xbe\x81\xd7\x82&\x13Q\xb6\xe0kd0z\xa4@\x0e\x17\x19\x8eUP\xfdY\nCw\xb7\xfc\x8bjD\xc1\x1fA\xf3\xf5\xcc\xbdE\x88\x02\x1d\x0e\xd6\xc2"\xde\xa0\xad\x16>\xa4Q\tW\xc3\xf8\xc9\x85|\x01a\xf56\x8d5\xbf\x97=-\xa4O\x8d5\x03\xb6A^\x1b \xceC\x19\xc6\xec\xed\x1c\xc3";\xb5\xfdD\xa8\xa1\xbb-\xf0E\x1eO\x03\xa1l\xa0\xeb{\x93\xa7\xf0\xe7\xbb\xa4\x93\xec\x0c^q!oi\xb6\xf1k\x11@\xfb\x12\xdf{e\xc5\x95\x93\xcfZ\xac\\\xc2|%:\xce\xf5\xe5\xe8\xc0\x869\xdfi\x02\x87Z1\xc0%\x8a4\xf4\x19\x1e\xa9\xff\xcc\xa6}\xda\x86\n\xe9tR\x1a\xc1].\xa4.O\xc5S\xfaS\xca\x9f'
                432     CALL                            1
                440     STORE_FAST                      8: _var_var_8
                442     PUSH_NULL                       
                444     LOAD_CONST                      1: '__pyarmor_assert_14664__'
                446     LOAD_CONST                      14: '\n</table>\n<div id="footer">Отчет сгенерирован программой TelegramExpert</div>\n</body>\n</html>\n\t\t'   # b'\x81\x88D\\\'\xfb\xbc\xde\x1e\xa4g\x9ch\xe5\xee\xc5\x06Y\xe6\xe5\xac\xc4A\xd8\x00}\xe1\x02\xb0O\xaf\x07\x8b\xb5\x90\xd8)(\xf4\x9f\xf9Y+\xed\x08h\xd2\xf7\xe2\\\xb6K_\xc1\xe6]\xe9[I\xad\xc8\xfb\xec\x13\xe7\x97\xb4cm\xe9\\l"\x82\x8c\xee\xf0e\xb8M\x11Y4p\xff;\x07M\xc1\xb0\x9f\xed\x92T\xc1\xa3\xe1B\xa9/t\x0c-*\x11u\xe4\xcdO\xe8\xf9"\xecP\xeeWp\xe0X\x07-&\x03\x1f'
                448     CALL                            1
                456     STORE_FAST                      9: _var_var_9
                458     LOAD_CONST                      15: 0
                460     STORE_FAST                      10: _var_var_10
                462     LOAD_GLOBAL                     3: NULL + Logs
                472     LOAD_ATTR                       6: PrintLog
                492     LOAD_GLOBAL                     8: Lang
                502     PUSH_NULL                       
                504     LOAD_CONST                      1: '__pyarmor_assert_14664__'
                506     LOAD_CONST                      16: 'report_preparation'   # b'\x81\xf0\x1d\x03<\xe8\xaa\xed\x0b\xe8\x08\xd0m\xfe\xf9\x91\x06R\xb5'
                508     CALL                            1
                516     BINARY_SUBSCR                   
                520     KW_NAMES                        9: ('message',)
                522     CALL                            1
                530     POP_TOP                         
                532     NOP                             
                534     LOAD_GLOBAL                     17: NULL + sqlite3
                544     LOAD_ATTR                       18: connect
                564     LOAD_FAST                       3: _var_var_3
                566     LOAD_GLOBAL                     16: sqlite3
                576     LOAD_ATTR                       20: PARSE_DECLTYPES
                596     LOAD_CONST                      17: 5
                598     LOAD_CONST                      18: False
                600     KW_NAMES                        19: ('detect_types', 'timeout', 'check_same_thread')
                602     CALL                            4
                610     STORE_FAST                      11: _var_var_11
                612     LOAD_FAST                       11: _var_var_11
                614     LOAD_ATTR                       23: cursor
                634     CALL                            0
                642     STORE_FAST                      12: _var_var_12
                644     LOAD_FAST                       12: _var_var_12
                646     LOAD_ATTR                       25: execute
                666     PUSH_NULL                       
                668     LOAD_CONST                      1: '__pyarmor_assert_14664__'
                670     LOAD_CONST                      20: 'SELECT * FROM STATISTIC'   # b'\x81\xd1=?\x16\xd9\x8a\x92Q\xba+\xf2C\xc1\xb8\xb6;|\x8f\x8e\x99\xffg\xef'
                672     CALL                            1
                680     CALL                            1
                688     POP_TOP                         
                690     LOAD_FAST                       12: _var_var_12
                692     LOAD_ATTR                       27: fetchall
                712     CALL                            0
                720     STORE_FAST                      0: data
                722     LOAD_GLOBAL                     29: NULL + open
                732     LOAD_FAST                       7: _var_var_7
                734     LOAD_CONST                      21: 'a'
                736     LOAD_CONST                      22: 'utf-8'
                738     KW_NAMES                        23: ('encoding',)
                740     CALL                            3
                748     BEFORE_WITH                     
                750     STORE_FAST                      13: _var_var_13
                752     LOAD_FAST                       13: _var_var_13
                754     LOAD_ATTR                       31: write
                774     LOAD_FAST                       8: _var_var_8
                776     CALL                            1
                784     POP_TOP                         
                786     LOAD_FAST                       0: data
                788     GET_ITER                        
                790     FOR_ITER                        358 (to 1510)
                796     STORE_FAST                      14: _var_var_14
                798     LOAD_CONST                      18: False
                800     STORE_FAST                      15: _var_var_15
                802     LOAD_FAST                       4: _var_var_4
                804     LOAD_CONST                      24: True
                806     COMPARE_OP                      40 (==)
                810     POP_JUMP_IF_TRUE                5 (to 822)
                812     LOAD_FAST                       5: _var_var_5
                814     LOAD_CONST                      24: True
                816     COMPARE_OP                      40 (==)
                820     POP_JUMP_IF_FALSE               31 (to 884)
                822     LOAD_FAST                       4: _var_var_4
                824     LOAD_CONST                      24: True
                826     COMPARE_OP                      40 (==)
                830     POP_JUMP_IF_FALSE               10 (to 852)
                832     LOAD_FAST                       14: _var_var_14
                834     LOAD_CONST                      25: 8
                836     BINARY_SUBSCR                   
                840     LOAD_CONST                      26: 'Done'
                842     COMPARE_OP                      40 (==)
                846     POP_JUMP_IF_FALSE               2 (to 852)
                848     LOAD_CONST                      24: True
                850     STORE_FAST                      15: _var_var_15
                852     LOAD_FAST                       5: _var_var_5
                854     LOAD_CONST                      24: True
                856     COMPARE_OP                      40 (==)
                860     POP_JUMP_IF_FALSE               13 (to 888)
                862     LOAD_FAST                       14: _var_var_14
                864     LOAD_CONST                      27: 9
                866     BINARY_SUBSCR                   
                870     LOAD_CONST                      26: 'Done'
                872     COMPARE_OP                      40 (==)
                876     POP_JUMP_IF_FALSE               5 (to 888)
                878     LOAD_CONST                      24: True
                880     STORE_FAST                      15: _var_var_15
                882     JUMP_FORWARD                    2 (to 888)
                884     LOAD_CONST                      24: True
                886     STORE_FAST                      15: _var_var_15
                888     LOAD_FAST                       15: _var_var_15
                890     POP_JUMP_IF_TRUE                1 (to 894)
                892     JUMP_BACKWARD                   52 (to 790)
                894     LOAD_FAST                       10: _var_var_10
                896     LOAD_CONST                      28: 1
                898     BINARY_OP                       13 (+=)
                902     STORE_FAST                      10: _var_var_10
                904     LOAD_FAST                       13: _var_var_13
                906     LOAD_ATTR                       31: write
                926     LOAD_CONST                      29: '<tr><td>'
                928     LOAD_GLOBAL                     33: NULL + str
                938     LOAD_FAST                       10: _var_var_10
                940     CALL                            1
                948     BINARY_OP                       0 (+)
                952     PUSH_NULL                       
                954     LOAD_CONST                      1: '__pyarmor_assert_14664__'
                956     LOAD_CONST                      30: '</td><td>'   # b'\x81\xbeW\x077\xa4\xe2\xc6\x1f\xa4'
                958     CALL                            1
                966     BINARY_OP                       0 (+)
                970     LOAD_GLOBAL                     33: NULL + str
                980     LOAD_FAST                       14: _var_var_14
                982     LOAD_CONST                      15: 0
                984     BINARY_SUBSCR                   
                988     CALL                            1
                996     BINARY_OP                       0 (+)
                1000    PUSH_NULL                       
                1002    LOAD_CONST                      1: '__pyarmor_assert_14664__'
                1004    LOAD_CONST                      30: '</td><td>'   # b'\x81\xbeW\x077\xa4\xe2\xc6\x1f\xa4'
                1006    CALL                            1
                1014    BINARY_OP                       0 (+)
                1018    LOAD_GLOBAL                     33: NULL + str
                1028    LOAD_FAST                       14: _var_var_14
                1030    LOAD_CONST                      28: 1
                1032    BINARY_SUBSCR                   
                1036    CALL                            1
                1044    BINARY_OP                       0 (+)
                1048    PUSH_NULL                       
                1050    LOAD_CONST                      1: '__pyarmor_assert_14664__'
                1052    LOAD_CONST                      30: '</td><td>'   # b'\x81\xbeW\x077\xa4\xe2\xc6\x1f\xa4'
                1054    CALL                            1
                1062    BINARY_OP                       0 (+)
                1066    LOAD_GLOBAL                     33: NULL + str
                1076    LOAD_FAST                       14: _var_var_14
                1078    LOAD_CONST                      31: 2
                1080    BINARY_SUBSCR                   
                1084    CALL                            1
                1092    BINARY_OP                       0 (+)
                1096    PUSH_NULL                       
                1098    LOAD_CONST                      1: '__pyarmor_assert_14664__'
                1100    LOAD_CONST                      30: '</td><td>'   # b'\x81\xbeW\x077\xa4\xe2\xc6\x1f\xa4'
                1102    CALL                            1
                1110    BINARY_OP                       0 (+)
                1114    LOAD_GLOBAL                     33: NULL + str
                1124    LOAD_FAST                       14: _var_var_14
                1126    LOAD_CONST                      32: 3
                1128    BINARY_SUBSCR                   
                1132    CALL                            1
                1140    BINARY_OP                       0 (+)
                1144    PUSH_NULL                       
                1146    LOAD_CONST                      1: '__pyarmor_assert_14664__'
                1148    LOAD_CONST                      30: '</td><td>'   # b'\x81\xbeW\x077\xa4\xe2\xc6\x1f\xa4'
                1150    CALL                            1
                1158    BINARY_OP                       0 (+)
                1162    LOAD_GLOBAL                     33: NULL + str
                1172    LOAD_FAST                       14: _var_var_14
                1174    LOAD_CONST                      33: 4
                1176    BINARY_SUBSCR                   
                1180    CALL                            1
                1188    BINARY_OP                       0 (+)
                1192    PUSH_NULL                       
                1194    LOAD_CONST                      1: '__pyarmor_assert_14664__'
                1196    LOAD_CONST                      30: '</td><td>'   # b'\x81\xbeW\x077\xa4\xe2\xc6\x1f\xa4'
                1198    CALL                            1
                1206    BINARY_OP                       0 (+)
                1210    LOAD_GLOBAL                     33: NULL + str
                1220    LOAD_FAST                       14: _var_var_14
                1222    LOAD_CONST                      17: 5
                1224    BINARY_SUBSCR                   
                1228    CALL                            1
                1236    BINARY_OP                       0 (+)
                1240    PUSH_NULL                       
                1242    LOAD_CONST                      1: '__pyarmor_assert_14664__'
                1244    LOAD_CONST                      30: '</td><td>'   # b'\x81\xbeW\x077\xa4\xe2\xc6\x1f\xa4'
                1246    CALL                            1
                1254    BINARY_OP                       0 (+)
                1258    LOAD_GLOBAL                     33: NULL + str
                1268    LOAD_FAST                       14: _var_var_14
                1270    LOAD_CONST                      34: 6
                1272    BINARY_SUBSCR                   
                1276    CALL                            1
                1284    BINARY_OP                       0 (+)
                1288    PUSH_NULL                       
                1290    LOAD_CONST                      1: '__pyarmor_assert_14664__'
                1292    LOAD_CONST                      30: '</td><td>'   # b'\x81\xbeW\x077\xa4\xe2\xc6\x1f\xa4'
                1294    CALL                            1
                1302    BINARY_OP                       0 (+)
                1306    LOAD_GLOBAL                     33: NULL + str
                1316    LOAD_FAST                       14: _var_var_14
                1318    LOAD_CONST                      35: 7
                1320    BINARY_SUBSCR                   
                1324    CALL                            1
                1332    BINARY_OP                       0 (+)
                1336    PUSH_NULL                       
                1338    LOAD_CONST                      1: '__pyarmor_assert_14664__'
                1340    LOAD_CONST                      30: '</td><td>'   # b'\x81\xbeW\x077\xa4\xe2\xc6\x1f\xa4'
                1342    CALL                            1
                1350    BINARY_OP                       0 (+)
                1354    LOAD_GLOBAL                     33: NULL + str
                1364    LOAD_FAST                       14: _var_var_14
                1366    LOAD_CONST                      25: 8
                1368    BINARY_SUBSCR                   
                1372    CALL                            1
                1380    BINARY_OP                       0 (+)
                1384    PUSH_NULL                       
                1386    LOAD_CONST                      1: '__pyarmor_assert_14664__'
                1388    LOAD_CONST                      30: '</td><td>'   # b'\x81\xbeW\x077\xa4\xe2\xc6\x1f\xa4'
                1390    CALL                            1
                1398    BINARY_OP                       0 (+)
                1402    LOAD_GLOBAL                     33: NULL + str
                1412    LOAD_FAST                       14: _var_var_14
                1414    LOAD_CONST                      27: 9
                1416    BINARY_SUBSCR                   
                1420    CALL                            1
                1428    BINARY_OP                       0 (+)
                1432    PUSH_NULL                       
                1434    LOAD_CONST                      1: '__pyarmor_assert_14664__'
                1436    LOAD_CONST                      36: '</td><td><div class="mess">'   # b'\x81\xbeW\x077\xa4\xe2\xc6\x1f\xa4Q\xc4e\xfa\xb8\x86\x03\\\xa8\xb4\xf7\x89C\xc9\x16|\xe1\x02'
                1438    CALL                            1
                1446    BINARY_OP                       0 (+)
                1450    LOAD_GLOBAL                     33: NULL + str
                1460    LOAD_FAST                       14: _var_var_14
                1462    LOAD_CONST                      37: 10
                1464    BINARY_SUBSCR                   
                1468    CALL                            1
                1476    BINARY_OP                       0 (+)
                1480    PUSH_NULL                       
                1482    LOAD_CONST                      1: '__pyarmor_assert_14664__'
                1484    LOAD_CONST                      38: '</div></td></tr>\n'   # b'\x81\xbeW\x17:\xec\xe0\x8eT\xee\t\x9e0\xa3\xec\x97Q7'
                1486    CALL                            1
                1494    BINARY_OP                       0 (+)
                1498    CALL                            1
                1506    POP_TOP                         
                1508    JUMP_BACKWARD                   361 (to 790)
                1512    END_FOR                         
                1514    LOAD_FAST                       13: _var_var_13
                1516    LOAD_ATTR                       31: write
                1536    LOAD_FAST                       9: _var_var_9
                1538    CALL                            1
                1546    POP_TOP                         
                1548    LOAD_CONST                      0: None
                1550    LOAD_CONST                      0: None
                1552    LOAD_CONST                      0: None
                1554    CALL                            2
                1562    POP_TOP                         
                1564    LOAD_FAST                       11: _var_var_11
                1566    LOAD_ATTR                       35: commit
                1586    CALL                            0
                1594    POP_TOP                         
                1596    LOAD_FAST                       11: _var_var_11
                1598    LOAD_ATTR                       37: close
                1618    CALL                            0
                1626    POP_TOP                         
                1628    LOAD_GLOBAL                     3: NULL + Logs
                1638    LOAD_ATTR                       6: PrintLog
                1658    LOAD_GLOBAL                     8: Lang
                1668    PUSH_NULL                       
                1670    LOAD_CONST                      1: '__pyarmor_assert_14664__'
                1672    LOAD_CONST                      39: 'report_generated'   # b'\x81\xf0\x1d\x03<\xe8\xaa\xed\x1c\xff\x03\xc5~\xed\xec\x80\x0b'
                1674    CALL                            1
                1682    BINARY_SUBSCR                   
                1686    KW_NAMES                        9: ('message',)
                1688    CALL                            1
                1696    POP_TOP                         
                1698    LOAD_GLOBAL                     3: NULL + Logs
                1708    LOAD_ATTR                       6: PrintLog
                1728    PUSH_NULL                       
                1730    LOAD_CONST                      1: '__pyarmor_assert_14664__'
                1732    LOAD_CONST                      40: 'Всего строк:'   # b'\x81R\xea\xa2\xd2Jkb\xc8J\xd3\x80\xdd\rIg\xbe\xbd\x0by\x1a\x11\x14'
                1734    CALL                            1
                1742    LOAD_FAST                       10: _var_var_10
                1744    KW_NAMES                        41: ('message', 'param')
                1746    CALL                            2
                1754    POP_TOP                         
                1756    LOAD_GLOBAL                     39: NULL + eel
                1766    LOAD_ATTR                       40: WriteResult
                1786    LOAD_CONST                      42: 'Отчет'
                1788    PUSH_NULL                       
                1790    LOAD_CONST                      1: '__pyarmor_assert_14664__'
                1792    LOAD_CONST                      43: 'stat_generator'   # b"\x81\xf1\x0c\x12'\xc5\xb9\xd7\x15\xff\x1f\xc1x\xe3\xea"
                1794    CALL                            1
                1802    LOAD_FAST                       6: _var_var_6
                1804    PUSH_NULL                       
                1806    LOAD_CONST                      1: '__pyarmor_assert_14664__'
                1808    LOAD_CONST                      12: '_Report.html'   # b'\x81\xdd*\x16#\xf5\xac\xc6U\xf2\x19\xcd`'
                1810    CALL                            1
                1818    BINARY_OP                       0 (+)
                1822    CALL                            3
                1830    POP_TOP                         
                1832    LOAD_GLOBAL                     45: NULL + StopDetect
                1842    LOAD_FAST                       1: stop_thread
                1844    CALL                            1
                1852    POP_TOP                         
                1854    NOP                             
                1856    LOAD_CONST                      48: 'DONE'
                1858    NOP                             
                1860    NOP                             
                1862    NOP                             
                1864    JUMP_FORWARD                    250 (to 2366)
                1872    POP_TOP                         
                1874    RETURN_CONST                    48: 'DONE'
                1876    PUSH_EXC_INFO                   
                1878    WITH_EXCEPT_START               
                1880    POP_JUMP_IF_TRUE                1 (to 1884)
                1882    RERAISE                         2
                1884    POP_TOP                         
                1886    POP_EXCEPT                      
                1888    POP_TOP                         
                1890    POP_TOP                         
                1892    JUMP_BACKWARD                   165 (to 1564)
                1894    COPY                            3
                1896    POP_EXCEPT                      
                1898    RERAISE                         1
                1900    PUSH_EXC_INFO                   
                1902    LOAD_GLOBAL                     42: Exception
                1912    CHECK_EXC_MATCH                 
                1914    POP_JUMP_IF_FALSE               115 (to 2146)
                1916    STORE_FAST                      16: _var_var_2
                1918    LOAD_GLOBAL                     3: NULL + Logs
                1928    LOAD_ATTR                       6: PrintLog
                1948    LOAD_GLOBAL                     8: Lang
                1958    PUSH_NULL                       
                1960    LOAD_CONST                      1: '__pyarmor_assert_14664__'
                1962    LOAD_CONST                      44: 'pupsik_get_error'   # b'\x81\xf2\r\x03 \xf3\xb5\xed\x1c\xff\x19\xffi\xfe\xea\x8a\x1d'
                1964    CALL                            1
                1972    BINARY_SUBSCR                   
                1976    KW_NAMES                        9: ('message',)
                1978    CALL                            1
                1986    POP_TOP                         
                1988    LOAD_GLOBAL                     3: NULL + Logs
                1998    LOAD_ATTR                       6: PrintLog
                2018    LOAD_GLOBAL                     8: Lang
                2028    PUSH_NULL                       
                2030    LOAD_CONST                      1: '__pyarmor_assert_14664__'
                2032    LOAD_CONST                      45: 'pupsik_database_not_match'   # b'\x81\xf2\r\x03 \xf3\xb5\xed\x1f\xfb\x19\xc1n\xed\xeb\x800S\xb4\xb3\x95\xc6O\xd8\x06g'
                2034    CALL                            1
                2042    BINARY_SUBSCR                   
                2046    KW_NAMES                        9: ('message',)
                2048    CALL                            1
                2056    POP_TOP                         
                2058    LOAD_GLOBAL                     3: NULL + Logs
                2068    LOAD_ATTR                       6: PrintLog
                2088    LOAD_GLOBAL                     8: Lang
                2098    PUSH_NULL                       
                2100    LOAD_CONST                      1: '__pyarmor_assert_14664__'
                2102    LOAD_CONST                      46: 'program_stopped'   # b'\x81\xf2\n\x1c4\xe8\xbf\xdf$\xe9\x19\xcf|\xfc\xfd\x81'
                2104    CALL                            1
                2112    BINARY_SUBSCR                   
                2116    KW_NAMES                        9: ('message',)
                2118    CALL                            1
                2126    POP_TOP                         
                2128    POP_EXCEPT                      
                2130    LOAD_CONST                      0: None
                2132    STORE_FAST                      16: _var_var_2
                2134    DELETE_FAST                     16: _var_var_2
                2136    JUMP_BACKWARD                   153 (to 1832)
                2138    LOAD_CONST                      0: None
                2140    STORE_FAST                      16: _var_var_2
                2142    DELETE_FAST                     16: _var_var_2
                2144    RERAISE                         1
                2146    RERAISE                         0
                2148    COPY                            3
                2150    POP_EXCEPT                      
                2152    RERAISE                         1
                2154    PUSH_EXC_INFO                   
                2156    LOAD_GLOBAL                     46: StopProgram
                2166    CHECK_EXC_MATCH                 
                2168    POP_JUMP_IF_FALSE               23 (to 2216)
                2170    POP_TOP                         
                2172    LOAD_GLOBAL                     45: NULL + StopDetect
                2182    LOAD_FAST                       1: stop_thread
                2184    CALL                            1
                2192    POP_TOP                         
                2194    POP_EXCEPT                      
                2196    LOAD_CONST                      49: 'STOP'
                2198    NOP                             
                2200    NOP                             
                2202    NOP                             
                2204    JUMP_FORWARD                    80 (to 2366)
                2212    POP_TOP                         
                2214    RETURN_CONST                    49: 'STOP'
                2216    LOAD_GLOBAL                     42: Exception
                2226    CHECK_EXC_MATCH                 
                2228    POP_JUMP_IF_FALSE               50 (to 2330)
                2230    STORE_FAST                      16: _var_var_2
                2232    LOAD_GLOBAL                     49: NULL + print
                2242    LOAD_CONST                      50: 'START:'
                2244    LOAD_GLOBAL                     33: NULL + str
                2254    LOAD_FAST                       16: _var_var_2
                2256    CALL                            1
                2264    BINARY_OP                       0 (+)
                2268    CALL                            1
                2276    POP_TOP                         
                2278    PUSH_NULL                       
                2280    LOAD_CONST                      1: '__pyarmor_assert_14664__'
                2282    LOAD_CONST                      51: 'EXCEPTION'   # b'\x81\xc7 0\x16\xca\x8a\xfb4\xd4'
                2284    CALL                            1
                2292    SWAP                            2
                2294    POP_EXCEPT                      
                2296    LOAD_CONST                      0: None
                2298    STORE_FAST                      16: _var_var_2
                2300    DELETE_FAST                     16: _var_var_2
                2302    NOP                             
                2304    NOP                             
                2306    NOP                             
                2308    JUMP_FORWARD                    28 (to 2366)
                2310    CALL                            1
                2318    POP_TOP                         
                2320    RETURN_VALUE                    
                2322    LOAD_CONST                      0: None
                2324    STORE_FAST                      16: _var_var_2
                2326    DELETE_FAST                     16: _var_var_2
                2328    RERAISE                         1
                2330    RERAISE                         0
                2332    COPY                            3
                2334    POP_EXCEPT                      
                2336    RERAISE                         1
                2338    PUSH_EXC_INFO                   
                2340    PUSH_NULL                       
                2342    LOAD_CONST                      47: '__pyarmor_exit_14666__'
                2344    NOP                             
                2346    LOAD_CONST                      3: b'<COAddr>\x07\x00\x00\x1a\x08\t\x00\x00\x00\x00\x00\x00\x00\x00\x00\x00\x00\x00\x00\x00'
                2348    CALL                            1
                2356    POP_TOP                         
                2358    RERAISE                         0
                2360    COPY                            3
                2362    POP_EXCEPT                      
                2364    RERAISE                         1
                2366    PUSH_NULL                       
                2368    LOAD_CONST                      47: '__pyarmor_exit_14666__'
                2370    LOAD_CONST                      3: b'<COAddr>\x07\x00\x00\x1a\x08\t\x00\x00\x00\x00\x00\x00\x00\x00\x00\x00\x00\x00\x00\x00'
                2372    BUILD_TUPLE                     1
                2374    CALL_FUNCTION_EX                0
                2376    POP_TOP                         
                2378    RETURN_VALUE                    
            [Exception Table]
                30 to 532 -> 2154 [0] 
                534 to 750 -> 1900 [0] 
                750 to 892 -> 1876 [1] lasti
                894 to 1548 -> 1876 [1] lasti
                1548 to 1832 -> 1900 [0] 
                1832 to 1854 -> 2154 [0] 
                1876 to 1886 -> 1894 [3] lasti
                1886 to 1900 -> 1900 [0] 
                1900 to 1918 -> 2148 [1] lasti
                1918 to 2128 -> 2138 [1] lasti
                2128 to 2138 -> 2154 [0] 
                2138 to 2148 -> 2148 [1] lasti
                2148 to 2154 -> 2154 [0] 
                2154 to 2194 -> 2332 [1] lasti
                2194 to 2196 -> 2338 [0] 
                2216 to 2232 -> 2332 [1] lasti
                2232 to 2292 -> 2322 [1] lasti
                2292 to 2294 -> 2332 [1] lasti
                2294 to 2302 -> 2338 [0] 
                2322 to 2332 -> 2332 [1] lasti
                2332 to 2338 -> 2338 [0] 
                2338 to 2360 -> 2360 [1] lasti
        '__pyarmor_exit_14660__'
    [Disassembly]
        0       NOP                             
        2       NOP                             
        4       PUSH_NULL                       
        6       LOAD_CONST                      1: '__pyarmor_enter_14659__'
        8       LOAD_CONST                      2: b'<COAddr>\x07\x00\x00\x1a\xb4\x00\x00\x00\x00\x00\x00\x00\x00\x00\x00\x00\x00\x00\x00\x00'
        10      BUILD_TUPLE                     1
        12      CALL_FUNCTION_EX                0
        14      POP_TOP                         
        16      RESUME                          0
        18      NOP                             
        20      NOP                             
        22      NOP                             
        24      NOP                             
        26      LOAD_CONST                      3: 0
        28      LOAD_CONST                      4: None
        30      IMPORT_NAME                     1: eel
        32      STORE_NAME                      1: eel
        34      LOAD_CONST                      3: 0
        36      LOAD_CONST                      4: None
        38      IMPORT_NAME                     2: sqlite3
        40      STORE_NAME                      2: sqlite3
        42      LOAD_CONST                      3: 0
        44      LOAD_CONST                      4: None
        46      IMPORT_NAME                     3: datetime
        48      STORE_NAME                      3: datetime
        50      LOAD_CONST                      3: 0
        52      LOAD_CONST                      5: ('Thread', 'Event')
        54      IMPORT_NAME                     4: threading
        56      IMPORT_FROM                     5: Thread
        58      STORE_NAME                      5: Thread
        60      IMPORT_FROM                     6: Event
        62      STORE_NAME                      6: Event
        64      POP_TOP                         
        66      LOAD_CONST                      3: 0
        68      LOAD_CONST                      6: ('StopProgram',)
        70      IMPORT_NAME                     7: multithon.errors
        72      IMPORT_FROM                     8: StopProgram
        74      STORE_NAME                      8: StopProgram
        76      POP_TOP                         
        78      LOAD_CONST                      3: 0
        80      LOAD_CONST                      7: ('GetLang',)
        82      IMPORT_NAME                     9: program.static_classes
        84      IMPORT_FROM                     10: GetLang
        86      STORE_NAME                      10: GetLang
        88      POP_TOP                         
        90      LOAD_CONST                      3: 0
        92      LOAD_CONST                      8: ('Logs',)
        94      IMPORT_NAME                     9: program.static_classes
        96      IMPORT_FROM                     11: Logs
        98      STORE_NAME                      11: Logs
        100     POP_TOP                         
        102     LOAD_CONST                      3: 0
        104     LOAD_CONST                      9: ('memory_set_pid',)
        106     IMPORT_NAME                     9: program.static_classes
        108     IMPORT_FROM                     12: memory_set_pid
        110     STORE_NAME                      12: memory_set_pid
        112     POP_TOP                         
        114     LOAD_CONST                      3: 0
        116     LOAD_CONST                      10: ('GetConfig',)
        118     IMPORT_NAME                     13: program.general
        120     IMPORT_FROM                     14: GetConfig
        122     STORE_NAME                      14: GetConfig
        124     POP_TOP                         
        126     LOAD_CONST                      3: 0
        128     LOAD_CONST                      11: ('StopDetect',)
        130     IMPORT_NAME                     13: program.general
        132     IMPORT_FROM                     15: StopDetect
        134     STORE_NAME                      15: StopDetect
        136     POP_TOP                         
        138     LOAD_CONST                      3: 0
        140     LOAD_CONST                      12: ('getFile',)
        142     IMPORT_NAME                     13: program.general
        144     IMPORT_FROM                     16: getFile
        146     STORE_NAME                      16: getFile
        148     POP_TOP                         
        150     LOAD_CONST                      3: 0
        152     LOAD_CONST                      8: ('Logs',)
        154     IMPORT_NAME                     9: program.static_classes
        156     IMPORT_FROM                     11: Logs
        158     STORE_NAME                      11: Logs
        160     POP_TOP                         
        162     LOAD_CONST                      3: 0
        164     LOAD_CONST                      7: ('GetLang',)
        166     IMPORT_NAME                     9: program.static_classes
        168     IMPORT_FROM                     10: GetLang
        170     STORE_NAME                      10: GetLang
        172     POP_TOP                         
        174     LOAD_CONST                      13: <CODE> Stat_generator
        176     MAKE_FUNCTION                   0
        178     STORE_NAME                      17: Stat_generator
        180     LOAD_CONST                      14: <CODE> START_Stat_generator
        182     MAKE_FUNCTION                   0
        184     STORE_NAME                      18: START_Stat_generator
        186     LOAD_CONST                      4: None
        188     NOP                             
        190     NOP                             
        192     NOP                             
        194     JUMP_FORWARD                    19 (to 234)
        202     POP_TOP                         
        204     RETURN_CONST                    4: None
        206     PUSH_EXC_INFO                   
        208     PUSH_NULL                       
        210     LOAD_CONST                      15: '__pyarmor_exit_14660__'
        212     NOP                             
        214     LOAD_CONST                      2: b'<COAddr>\x07\x00\x00\x1a\xb4\x00\x00\x00\x00\x00\x00\x00\x00\x00\x00\x00\x00\x00\x00\x00'
        216     CALL                            1
        224     POP_TOP                         
        226     RERAISE                         0
        228     COPY                            3
        230     POP_EXCEPT                      
        232     RERAISE                         1
        234     PUSH_NULL                       
        236     LOAD_CONST                      15: '__pyarmor_exit_14660__'
        238     LOAD_CONST                      2: b'<COAddr>\x07\x00\x00\x1a\xb4\x00\x00\x00\x00\x00\x00\x00\x00\x00\x00\x00\x00\x00\x00\x00'
        240     BUILD_TUPLE                     1
        242     CALL_FUNCTION_EX                0
        244     POP_TOP                         
        246     RETURN_VALUE                    
    [Exception Table]
        26 to 186 -> 206 [0] 
        206 to 228 -> 228 [1] lasti
