#decoded by lolz.live/mrpenny / t.me/zeus_jackpot
# ================================
# Примечания по Pyarmor:
# - Байт-код и объекты кода Pyarmor соответствуют стандартному Python, но присутствуют специальные вызовы функций среды выполнения (runtime) Pyarmor.
# - Вызовы строк — это не ошибки, а маркеры, которые обрабатываются Pyarmor во время выполнения.
#
# Руководство по декомпиляции (без среды выполнения):
# 1. Игнорируйте зашифрованные байты после `#`; используйте только строку до `#`.
# 2. Удалите "__pyarmor_enter_xxx__"(b"<COAddr>...") и "__pyarmor_leave_xxx__"(b"<COAddr>...") (пролог/эпилог).
# 3. "__pyarmor_assert_xxx__"(A) не является настоящим оператором assert.
#    - Если A — это имя или читаемая строка: замените на A.
#    - Если A — это (X, "Y"): замените на X.Y.
#    - Если A — это (X, "Y", Z): замените на X.Y = Z.
#    - В противном случае: выберите наиболее подходящую/логичную замену.
# 4. "__pyarmor_bcc_xxx__"(...) указывает на машинный (нативный) код; тело функции недоступно. Добавьте комментарий.
# ================================

[Code]
    File Name: <frozen program.modules.Stat_union>
    Object Name: <module>
    Qualified Name: <module>
    Arg Count: 0
    Pos Only Arg Count: 0
    KW Only Arg Count: 0
    Stack Size: 5
    Flags: 0x20000000 (CO_PYARMOR_OBFUSCATED)
    [Names]
        '__assert_armored__'
        'eel'
        'sqlite3'
        'datetime'
        'threading'
        'Thread'
        'Event'
        'multithon.errors'
        'StopProgram'
        'program.static_classes'
        'GetLang'
        'Logs'
        'memory_set_pid'
        'program.general'
        'GetConfig'
        'StopDetect'
        'getFile'
        'Stat_union'
        'START_Stat_union'
        'db_union_base'
        'DB_CREATE_RESULT'
        'DB_GET_COUNT'
        'DB_GET_PARSE_DATA'
        'DB_UNION_BASE'
    [Locals+Names]
    [Constants]
        '__pyarmor_assert_14667__'
        '__pyarmor_enter_14668__'
        b'<COAddr>\x07\x00\x00\x1a\xd4\x00\x00\x00\x00\x00\x00\x00\x00\x00\x00\x00\x00\x00\x00\x00'
        0
        None
        (
            'Thread'
            'Event'
        )
        (
            'StopProgram'
        )
        (
            'GetLang'
        )
        (
            'Logs'
        )
        (
            'memory_set_pid'
        )
        (
            'GetConfig'
        )
        (
            'StopDetect'
        )
        (
            'getFile'
        )
        [Code]
            File Name: <frozen program.modules.Stat_union>
            Object Name: Stat_union
            Qualified Name: Stat_union
            Arg Count: 1
            Pos Only Arg Count: 0
            KW Only Arg Count: 0
            Stack Size: 7
            Flags: 0x20000003 (CO_OPTIMIZED | CO_NEWLOCALS | CO_PYARMOR_OBFUSCATED)
            [Names]
                'get'
                'getFile'
                'GetConfig'
                'config'
                'GetLang'
                'Lang'
                'Event'
                'memory_set_pid'
                'Thread'
                'START_Stat_union'
                'start'
                'Logs'
                'WaitStopAnsfer'
                'UpdateLogInWindow'
                'Exception'
                'print'
                'str'
            [Locals+Names]
                'data'
                '__assert_armored__'
                '_var_var_0'
                '_var_var_1'
                '_var_var_2'
            [Constants]
                None
                '__pyarmor_assert_14670__'
                '__pyarmor_enter_14671__'
                b'<COAddr>\x05\x00\x00\x1aL\x02\x00\x00\x00\x00\x00\x00\x00\x00\x00\x00\x00\x00\x00\x00'
                'action'
                'getFile'
                '__pyarmor_exit_14672__'
                (
                    'target'
                    'args'
                )
                True
                (
                    'target'
                    'args'
                    'daemon'
                )
                'Stat_union: '   # b"\x81\xd1\x0c\x12'\xc5\xab\xdc\x12\xf5\x03\x9a,"
                False
            [Disassembly]
                0       NOP                             
                2       NOP                             
                4       PUSH_NULL                       
                6       LOAD_CONST                      2: '__pyarmor_enter_14671__'
                8       LOAD_CONST                      3: b'<COAddr>\x05\x00\x00\x1aL\x02\x00\x00\x00\x00\x00\x00\x00\x00\x00\x00\x00\x00\x00\x00'
                10      BUILD_TUPLE                     1
                12      CALL_FUNCTION_EX                0
                14      POP_TOP                         
                16      RESUME                          0
                18      NOP                             
                20      NOP                             
                22      NOP                             
                24      NOP                             
                26      NOP                             
                28      NOP                             
                30      LOAD_FAST                       0: data
                32      LOAD_ATTR                       1: get
                52      LOAD_CONST                      4: 'action'
                54      CALL                            1
                62      POP_JUMP_IF_NONE                28 (to 120)
                64      LOAD_FAST                       0: data
                66      LOAD_CONST                      4: 'action'
                68      BINARY_SUBSCR                   
                72      LOAD_CONST                      5: 'getFile'
                74      COMPARE_OP                      40 (==)
                78      POP_JUMP_IF_FALSE               20 (to 120)
                80      LOAD_GLOBAL                     3: NULL + getFile
                90      LOAD_FAST                       0: data
                92      CALL                            1
                100     NOP                             
                102     NOP                             
                104     JUMP_FORWARD                    267 (to 642)
                108     CALL                            1
                116     POP_TOP                         
                118     RETURN_VALUE                    
                120     LOAD_GLOBAL                     5: NULL + GetConfig
                130     CALL                            0
                138     STORE_GLOBAL                    3: config
                140     LOAD_GLOBAL                     9: NULL + GetLang
                150     LOAD_GLOBAL                     6: config
                160     CALL                            1
                168     STORE_GLOBAL                    5: Lang
                170     LOAD_GLOBAL                     13: NULL + Event
                180     CALL                            0
                188     STORE_FAST                      2: _var_var_0
                190     LOAD_GLOBAL                     15: NULL + memory_set_pid
                200     CALL                            0
                208     STORE_FAST                      3: _var_var_1
                210     LOAD_GLOBAL                     17: NULL + Thread
                220     LOAD_GLOBAL                     18: START_Stat_union
                230     LOAD_FAST                       0: data
                232     LOAD_FAST                       2: _var_var_0
                234     BUILD_TUPLE                     2
                236     KW_NAMES                        7: ('target', 'args')
                238     CALL                            2
                246     LOAD_ATTR                       21: start
                266     CALL                            0
                274     POP_TOP                         
                276     LOAD_GLOBAL                     17: NULL + Thread
                286     LOAD_GLOBAL                     22: Logs
                296     LOAD_ATTR                       24: WaitStopAnsfer
                316     LOAD_GLOBAL                     6: config
                326     LOAD_FAST                       3: _var_var_1
                328     LOAD_FAST                       2: _var_var_0
                330     BUILD_TUPLE                     3
                332     LOAD_CONST                      8: True
                334     KW_NAMES                        9: ('target', 'args', 'daemon')
                336     CALL                            3
                344     LOAD_ATTR                       21: start
                364     CALL                            0
                372     POP_TOP                         
                374     LOAD_GLOBAL                     17: NULL + Thread
                384     LOAD_GLOBAL                     22: Logs
                394     LOAD_ATTR                       26: UpdateLogInWindow
                414     LOAD_GLOBAL                     6: config
                424     LOAD_FAST                       3: _var_var_1
                426     LOAD_FAST                       2: _var_var_0
                428     BUILD_TUPLE                     3
                430     LOAD_CONST                      8: True
                432     KW_NAMES                        9: ('target', 'args', 'daemon')
                434     CALL                            3
                442     LOAD_ATTR                       21: start
                462     CALL                            0
                470     POP_TOP                         
                472     NOP                             
                474     LOAD_CONST                      8: True
                476     NOP                             
                478     NOP                             
                480     NOP                             
                482     JUMP_FORWARD                    79 (to 642)
                490     POP_TOP                         
                492     RETURN_CONST                    8: True
                494     PUSH_EXC_INFO                   
                496     LOAD_GLOBAL                     28: Exception
                506     CHECK_EXC_MATCH                 
                508     POP_JUMP_IF_FALSE               48 (to 606)
                510     STORE_FAST                      4: _var_var_2
                512     LOAD_GLOBAL                     31: NULL + print
                522     PUSH_NULL                       
                524     LOAD_CONST                      1: '__pyarmor_assert_14670__'
                526     LOAD_CONST                      10: 'Stat_union: '   # b"\x81\xd1\x0c\x12'\xc5\xab\xdc\x12\xf5\x03\x9a,"
                528     CALL                            1
                536     LOAD_GLOBAL                     33: NULL + str
                546     LOAD_FAST                       4: _var_var_2
                548     CALL                            1
                556     BINARY_OP                       0 (+)
                560     CALL                            1
                568     POP_TOP                         
                570     POP_EXCEPT                      
                572     LOAD_CONST                      0: None
                574     STORE_FAST                      4: _var_var_2
                576     DELETE_FAST                     4: _var_var_2
                578     LOAD_CONST                      11: False
                580     NOP                             
                582     NOP                             
                584     NOP                             
                586     JUMP_FORWARD                    27 (to 642)
                594     POP_TOP                         
                596     RETURN_CONST                    11: False
                598     LOAD_CONST                      0: None
                600     STORE_FAST                      4: _var_var_2
                602     DELETE_FAST                     4: _var_var_2
                604     RERAISE                         1
                606     RERAISE                         0
                608     COPY                            3
                610     POP_EXCEPT                      
                612     RERAISE                         1
                614     PUSH_EXC_INFO                   
                616     PUSH_NULL                       
                618     LOAD_CONST                      6: '__pyarmor_exit_14672__'
                620     NOP                             
                622     LOAD_CONST                      3: b'<COAddr>\x05\x00\x00\x1aL\x02\x00\x00\x00\x00\x00\x00\x00\x00\x00\x00\x00\x00\x00\x00'
                624     CALL                            1
                632     POP_TOP                         
                634     RERAISE                         0
                636     COPY                            3
                638     POP_EXCEPT                      
                640     RERAISE                         1
                642     PUSH_NULL                       
                644     LOAD_CONST                      6: '__pyarmor_exit_14672__'
                646     LOAD_CONST                      3: b'<COAddr>\x05\x00\x00\x1aL\x02\x00\x00\x00\x00\x00\x00\x00\x00\x00\x00\x00\x00\x00\x00'
                648     BUILD_TUPLE                     1
                650     CALL_FUNCTION_EX                0
                652     POP_TOP                         
                654     RETURN_VALUE                    
            [Exception Table]
                30 to 100 -> 494 [0] 
                120 to 472 -> 494 [0] 
                494 to 512 -> 608 [1] lasti
                512 to 570 -> 598 [1] lasti
                570 to 578 -> 614 [0] 
                598 to 608 -> 608 [1] lasti
                608 to 614 -> 614 [0] 
                614 to 636 -> 636 [1] lasti
        [Code]
            File Name: <frozen program.modules.Stat_union>
            Object Name: START_Stat_union
            Qualified Name: START_Stat_union
            Arg Count: 2
            Pos Only Arg Count: 0
            KW Only Arg Count: 0
            Stack Size: 8
            Flags: 0x20000003 (CO_OPTIMIZED | CO_NEWLOCALS | CO_PYARMOR_OBFUSCATED)
            [Names]
                'get'
                'Logs'
                'LangCheck'
                'PrintLog'
                'Lang'
                'datetime'
                'now'
                'strftime'
                'DB_CREATE_RESULT'
                'eel'
                'sendErrorBox'
                'WriteResult'
                'is_set'
                'StopProgram'
                'db_union_base'
                'DB_GET_COUNT'
                'StopDetect'
                'Exception'
                'print'
                'str'
            [Locals+Names]
                'data'
                'stop_thread'
                '__assert_armored__'
                '_var_var_3'
                '_var_var_4'
                '_var_var_5'
                '_var_var_6'
                '_var_var_7'
                '_var_var_8'
                '_var_var_9'
                '_var_var_10'
                '_var_var_11'
                '_var_var_12'
                '_var_var_13'
                '_var_var_14'
                '_var_var_2'
            [Constants]
                None
                '__pyarmor_assert_14673__'
                '__pyarmor_enter_14674__'
                b'<COAddr>\x07\x00\x00\x1a\x0e\x06\x00\x00\x00\x00\x00\x00\x00\x00\x00\x00\x00\x00\x00\x00'
                'logId'
                'Settings'
                'file_db_1'   # b'\x81\xe4\x11\x1f6\xc5\xba\xd0$\xab'
                'file_db_2'   # b'\x81\xe4\x11\x1f6\xc5\xba\xd0$\xa8'
                'file_db_3'   # b'\x81\xe4\x11\x1f6\xc5\xba\xd0$\xa9'
                'file_db_4'   # b'\x81\xe4\x11\x1f6\xc5\xba\xd0$\xae'
                'file_db_5'   # b'\x81\xe4\x11\x1f6\xc5\xba\xd0$\xaf'
                'program_running'   # b'\x81\xf2\n\x1c4\xe8\xbf\xdf$\xe8\x18\xceb\xe5\xf6\x82'
                (
                    'message'
                )
                '%Y-%m-%d_%H-%M-%S'   # b'\x81\xa7!^v\xf7\xf3\x97\x1f\xc5H\xe8!\xa9\xd5\xc8Jn'
                'stat_union'   # b"\x81\xf1\x0c\x12'\xc5\xab\xdc\x12\xf5\x03"
                '_Result'
                False
                "I can't create a database of results"   # b'\x81\xcbX\x102\xf4\xf9\xc6[\xf9\x1f\xc5m\xf8\xfd\xc5\x0e\x1d\xbf\xa6\xbe\xcaL\xcd\x16j\xe3S\x06\xf1\x0c\xe0)G,\x19\x8b'
                '__pyarmor_exit_14675__'
                'Result'
                '_Result.db'   # b'\x81\xdd*\x16 \xef\xb2\xc6U\xfe\x0f'
                'created_database_import'   # b'\x81\xe1\n\x162\xee\xbb\xd6$\xfe\x0c\xd4m\xee\xf9\x96\nb\xb2\xaa\xba\xc4\\\xd8'
                0
                ''
                1
                (
                    'NUM'
                )
                2
                3
                4
                5
                'Добавлено в базу данных:'   # b'\x81R\xec\xa3\xedJob\xcbJ\xdfp\xb7\\-5\xd2\xede\xe7\x1a\x19\x0e|\xd4\xdfs\xec\xd7\x00\xfd\xa5\x8a\x86\x90\xdd(\x17\x04\xf3\xa9\x02I\xb8\x87'
                'строк'
                (
                    'message'
                    'param'
                    'end'
                )
                'DONE'
                'STOP'
                'START:'
                'EXCEPTION'   # b'\x81\xc7 0\x16\xca\x8a\xfb4\xd4'
            [Disassembly]
                0       NOP                             
                2       NOP                             
                4       PUSH_NULL                       
                6       LOAD_CONST                      2: '__pyarmor_enter_14674__'
                8       LOAD_CONST                      3: b'<COAddr>\x07\x00\x00\x1a\x0e\x06\x00\x00\x00\x00\x00\x00\x00\x00\x00\x00\x00\x00\x00\x00'
                10      BUILD_TUPLE                     1
                12      CALL_FUNCTION_EX                0
                14      POP_TOP                         
                16      RESUME                          0
                18      NOP                             
                20      NOP                             
                22      NOP                             
                24      NOP                             
                26      NOP                             
                28      NOP                             
                30      LOAD_FAST                       0: data
                32      LOAD_ATTR                       1: get
                52      LOAD_CONST                      4: 'logId'
                54      CALL                            1
                62      STORE_FAST                      3: _var_var_3
                64      LOAD_FAST                       0: data
                66      LOAD_CONST                      5: 'Settings'
                68      BINARY_SUBSCR                   
                72      LOAD_ATTR                       1: get
                92      PUSH_NULL                       
                94      LOAD_CONST                      1: '__pyarmor_assert_14673__'
                96      LOAD_CONST                      6: 'file_db_1'   # b'\x81\xe4\x11\x1f6\xc5\xba\xd0$\xab'
                98      CALL                            1
                106     CALL                            1
                114     STORE_FAST                      4: _var_var_4
                116     LOAD_FAST                       0: data
                118     LOAD_CONST                      5: 'Settings'
                120     BINARY_SUBSCR                   
                124     LOAD_ATTR                       1: get
                144     PUSH_NULL                       
                146     LOAD_CONST                      1: '__pyarmor_assert_14673__'
                148     LOAD_CONST                      7: 'file_db_2'   # b'\x81\xe4\x11\x1f6\xc5\xba\xd0$\xa8'
                150     CALL                            1
                158     CALL                            1
                166     STORE_FAST                      5: _var_var_5
                168     LOAD_FAST                       0: data
                170     LOAD_CONST                      5: 'Settings'
                172     BINARY_SUBSCR                   
                176     LOAD_ATTR                       1: get
                196     PUSH_NULL                       
                198     LOAD_CONST                      1: '__pyarmor_assert_14673__'
                200     LOAD_CONST                      8: 'file_db_3'   # b'\x81\xe4\x11\x1f6\xc5\xba\xd0$\xa9'
                202     CALL                            1
                210     CALL                            1
                218     STORE_FAST                      6: _var_var_6
                220     LOAD_FAST                       0: data
                222     LOAD_CONST                      5: 'Settings'
                224     BINARY_SUBSCR                   
                228     LOAD_ATTR                       1: get
                248     PUSH_NULL                       
                250     LOAD_CONST                      1: '__pyarmor_assert_14673__'
                252     LOAD_CONST                      9: 'file_db_4'   # b'\x81\xe4\x11\x1f6\xc5\xba\xd0$\xae'
                254     CALL                            1
                262     CALL                            1
                270     STORE_FAST                      7: _var_var_7
                272     LOAD_FAST                       0: data
                274     LOAD_CONST                      5: 'Settings'
                276     BINARY_SUBSCR                   
                280     LOAD_ATTR                       1: get
                300     PUSH_NULL                       
                302     LOAD_CONST                      1: '__pyarmor_assert_14673__'
                304     LOAD_CONST                      10: 'file_db_5'   # b'\x81\xe4\x11\x1f6\xc5\xba\xd0$\xaf'
                306     CALL                            1
                314     CALL                            1
                322     STORE_FAST                      8: _var_var_8
                324     LOAD_GLOBAL                     3: NULL + Logs
                334     LOAD_ATTR                       4: LangCheck
                354     CALL                            0
                362     POP_TOP                         
                364     LOAD_GLOBAL                     3: NULL + Logs
                374     LOAD_ATTR                       6: PrintLog
                394     LOAD_GLOBAL                     8: Lang
                404     PUSH_NULL                       
                406     LOAD_CONST                      1: '__pyarmor_assert_14673__'
                408     LOAD_CONST                      11: 'program_running'   # b'\x81\xf2\n\x1c4\xe8\xbf\xdf$\xe8\x18\xceb\xe5\xf6\x82'
                410     CALL                            1
                418     BINARY_SUBSCR                   
                422     KW_NAMES                        12: ('message',)
                424     CALL                            1
                432     POP_TOP                         
                434     LOAD_GLOBAL                     10: datetime
                444     LOAD_ATTR                       10: datetime
                464     LOAD_ATTR                       13: now
                484     CALL                            0
                492     LOAD_ATTR                       15: strftime
                512     PUSH_NULL                       
                514     LOAD_CONST                      1: '__pyarmor_assert_14673__'
                516     LOAD_CONST                      13: '%Y-%m-%d_%H-%M-%S'   # b'\x81\xa7!^v\xf7\xf3\x97\x1f\xc5H\xe8!\xa9\xd5\xc8Jn'
                518     CALL                            1
                526     CALL                            1
                534     STORE_FAST                      9: _var_var_9
                536     LOAD_GLOBAL                     17: NULL + DB_CREATE_RESULT
                546     LOAD_FAST                       9: _var_var_9
                548     PUSH_NULL                       
                550     LOAD_CONST                      1: '__pyarmor_assert_14673__'
                552     LOAD_CONST                      14: 'stat_union'   # b"\x81\xf1\x0c\x12'\xc5\xab\xdc\x12\xf5\x03"
                554     CALL                            1
                562     LOAD_CONST                      15: '_Result'
                564     CALL                            3
                572     STORE_FAST                      10: _var_var_10
                574     LOAD_FAST                       10: _var_var_10
                576     LOAD_CONST                      16: False
                578     COMPARE_OP                      40 (==)
                582     POP_JUMP_IF_FALSE               37 (to 658)
                584     LOAD_GLOBAL                     19: NULL + eel
                594     LOAD_ATTR                       20: sendErrorBox
                614     PUSH_NULL                       
                616     LOAD_CONST                      1: '__pyarmor_assert_14673__'
                618     LOAD_CONST                      17: "I can't create a database of results"   # b'\x81\xcbX\x102\xf4\xf9\xc6[\xf9\x1f\xc5m\xf8\xfd\xc5\x0e\x1d\xbf\xa6\xbe\xcaL\xcd\x16j\xe3S\x06\xf1\x0c\xe0)G,\x19\x8b'
                620     CALL                            1
                628     CALL                            1
                636     POP_TOP                         
                638     LOAD_CONST                      0: None
                640     NOP                             
                642     NOP                             
                644     JUMP_FORWARD                    478 (to 1604)
                654     POP_TOP                         
                656     RETURN_CONST                    0: None
                658     LOAD_GLOBAL                     19: NULL + eel
                668     LOAD_ATTR                       22: WriteResult
                688     LOAD_CONST                      19: 'Result'
                690     PUSH_NULL                       
                692     LOAD_CONST                      1: '__pyarmor_assert_14673__'
                694     LOAD_CONST                      14: 'stat_union'   # b"\x81\xf1\x0c\x12'\xc5\xab\xdc\x12\xf5\x03"
                696     CALL                            1
                704     LOAD_FAST                       9: _var_var_9
                706     PUSH_NULL                       
                708     LOAD_CONST                      1: '__pyarmor_assert_14673__'
                710     LOAD_CONST                      20: '_Result.db'   # b'\x81\xdd*\x16 \xef\xb2\xc6U\xfe\x0f'
                712     CALL                            1
                720     BINARY_OP                       0 (+)
                724     CALL                            3
                732     POP_TOP                         
                734     LOAD_GLOBAL                     3: NULL + Logs
                744     LOAD_ATTR                       6: PrintLog
                764     LOAD_GLOBAL                     8: Lang
                774     PUSH_NULL                       
                776     LOAD_CONST                      1: '__pyarmor_assert_14673__'
                778     LOAD_CONST                      21: 'created_database_import'   # b'\x81\xe1\n\x162\xee\xbb\xd6$\xfe\x0c\xd4m\xee\xf9\x96\nb\xb2\xaa\xba\xc4\\\xd8'
                780     CALL                            1
                788     BINARY_SUBSCR                   
                792     KW_NAMES                        12: ('message',)
                794     CALL                            1
                802     POP_TOP                         
                804     LOAD_CONST                      22: 0
                806     STORE_FAST                      11: _var_var_11
                808     LOAD_CONST                      22: 0
                810     STORE_FAST                      12: _var_var_12
                812     LOAD_CONST                      22: 0
                814     STORE_FAST                      13: _var_var_13
                816     LOAD_FAST                       4: _var_var_4
                818     LOAD_CONST                      23: ''
                820     COMPARE_OP                      55 (!=)
                824     POP_JUMP_IF_FALSE               40 (to 906)
                826     LOAD_FAST                       1: stop_thread
                828     LOAD_ATTR                       25: is_set
                848     CALL                            0
                856     POP_JUMP_IF_FALSE               10 (to 878)
                858     LOAD_GLOBAL                     27: NULL + StopProgram
                868     CALL                            0
                876     RAISE_VARARGS                   1
                878     LOAD_GLOBAL                     29: NULL + db_union_base
                888     LOAD_FAST                       4: _var_var_4
                890     LOAD_FAST                       10: _var_var_10
                892     LOAD_CONST                      24: 1
                894     KW_NAMES                        25: ('NUM',)
                896     CALL                            3
                904     POP_TOP                         
                906     LOAD_FAST                       5: _var_var_5
                908     LOAD_CONST                      23: ''
                910     COMPARE_OP                      55 (!=)
                914     POP_JUMP_IF_FALSE               40 (to 996)
                916     LOAD_FAST                       1: stop_thread
                918     LOAD_ATTR                       25: is_set
                938     CALL                            0
                946     POP_JUMP_IF_FALSE               10 (to 968)
                948     LOAD_GLOBAL                     27: NULL + StopProgram
                958     CALL                            0
                966     RAISE_VARARGS                   1
                968     LOAD_GLOBAL                     29: NULL + db_union_base
                978     LOAD_FAST                       5: _var_var_5
                980     LOAD_FAST                       10: _var_var_10
                982     LOAD_CONST                      26: 2
                984     KW_NAMES                        25: ('NUM',)
                986     CALL                            3
                994     POP_TOP                         
                996     LOAD_FAST                       6: _var_var_6
                998     LOAD_CONST                      23: ''
                1000    COMPARE_OP                      55 (!=)
                1004    POP_JUMP_IF_FALSE               40 (to 1086)
                1006    LOAD_FAST                       1: stop_thread
                1008    LOAD_ATTR                       25: is_set
                1028    CALL                            0
                1036    POP_JUMP_IF_FALSE               10 (to 1058)
                1038    LOAD_GLOBAL                     27: NULL + StopProgram
                1048    CALL                            0
                1056    RAISE_VARARGS                   1
                1058    LOAD_GLOBAL                     29: NULL + db_union_base
                1068    LOAD_FAST                       6: _var_var_6
                1070    LOAD_FAST                       10: _var_var_10
                1072    LOAD_CONST                      27: 3
                1074    KW_NAMES                        25: ('NUM',)
                1076    CALL                            3
                1084    POP_TOP                         
                1086    LOAD_FAST                       7: _var_var_7
                1088    LOAD_CONST                      23: ''
                1090    COMPARE_OP                      55 (!=)
                1094    POP_JUMP_IF_FALSE               40 (to 1176)
                1096    LOAD_FAST                       1: stop_thread
                1098    LOAD_ATTR                       25: is_set
                1118    CALL                            0
                1126    POP_JUMP_IF_FALSE               10 (to 1148)
                1128    LOAD_GLOBAL                     27: NULL + StopProgram
                1138    CALL                            0
                1146    RAISE_VARARGS                   1
                1148    LOAD_GLOBAL                     29: NULL + db_union_base
                1158    LOAD_FAST                       7: _var_var_7
                1160    LOAD_FAST                       10: _var_var_10
                1162    LOAD_CONST                      28: 4
                1164    KW_NAMES                        25: ('NUM',)
                1166    CALL                            3
                1174    POP_TOP                         
                1176    LOAD_FAST                       8: _var_var_8
                1178    LOAD_CONST                      23: ''
                1180    COMPARE_OP                      55 (!=)
                1184    POP_JUMP_IF_FALSE               40 (to 1266)
                1186    LOAD_FAST                       1: stop_thread
                1188    LOAD_ATTR                       25: is_set
                1208    CALL                            0
                1216    POP_JUMP_IF_FALSE               10 (to 1238)
                1218    LOAD_GLOBAL                     27: NULL + StopProgram
                1228    CALL                            0
                1236    RAISE_VARARGS                   1
                1238    LOAD_GLOBAL                     29: NULL + db_union_base
                1248    LOAD_FAST                       8: _var_var_8
                1250    LOAD_FAST                       10: _var_var_10
                1252    LOAD_CONST                      29: 5
                1254    KW_NAMES                        25: ('NUM',)
                1256    CALL                            3
                1264    POP_TOP                         
                1266    LOAD_GLOBAL                     31: NULL + DB_GET_COUNT
                1276    LOAD_FAST                       10: _var_var_10
                1278    CALL                            1
                1286    STORE_FAST                      14: _var_var_14
                1288    LOAD_GLOBAL                     3: NULL + Logs
                1298    LOAD_ATTR                       6: PrintLog
                1318    PUSH_NULL                       
                1320    LOAD_CONST                      1: '__pyarmor_assert_14673__'
                1322    LOAD_CONST                      30: 'Добавлено в базу данных:'   # b'\x81R\xec\xa3\xedJob\xcbJ\xdfp\xb7\\-5\xd2\xede\xe7\x1a\x19\x0e|\xd4\xdfs\xec\xd7\x00\xfd\xa5\x8a\x86\x90\xdd(\x17\x04\xf3\xa9\x02I\xb8\x87'
                1324    CALL                            1
                1332    LOAD_FAST                       14: _var_var_14
                1334    LOAD_CONST                      31: 'строк'
                1336    KW_NAMES                        32: ('message', 'param', 'end')
                1338    CALL                            3
                1346    POP_TOP                         
                1348    LOAD_GLOBAL                     33: NULL + StopDetect
                1358    LOAD_FAST                       1: stop_thread
                1360    CALL                            1
                1368    POP_TOP                         
                1370    NOP                             
                1372    LOAD_CONST                      33: 'DONE'
                1374    NOP                             
                1376    NOP                             
                1378    NOP                             
                1380    JUMP_FORWARD                    111 (to 1604)
                1388    POP_TOP                         
                1390    RETURN_CONST                    33: 'DONE'
                1392    PUSH_EXC_INFO                   
                1394    LOAD_GLOBAL                     26: StopProgram
                1404    CHECK_EXC_MATCH                 
                1406    POP_JUMP_IF_FALSE               23 (to 1454)
                1408    POP_TOP                         
                1410    LOAD_GLOBAL                     33: NULL + StopDetect
                1420    LOAD_FAST                       1: stop_thread
                1422    CALL                            1
                1430    POP_TOP                         
                1432    POP_EXCEPT                      
                1434    LOAD_CONST                      34: 'STOP'
                1436    NOP                             
                1438    NOP                             
                1440    NOP                             
                1442    JUMP_FORWARD                    80 (to 1604)
                1450    POP_TOP                         
                1452    RETURN_CONST                    34: 'STOP'
                1454    LOAD_GLOBAL                     34: Exception
                1464    CHECK_EXC_MATCH                 
                1466    POP_JUMP_IF_FALSE               50 (to 1568)
                1468    STORE_FAST                      15: _var_var_2
                1470    LOAD_GLOBAL                     37: NULL + print
                1480    LOAD_CONST                      35: 'START:'
                1482    LOAD_GLOBAL                     39: NULL + str
                1492    LOAD_FAST                       15: _var_var_2
                1494    CALL                            1
                1502    BINARY_OP                       0 (+)
                1506    CALL                            1
                1514    POP_TOP                         
                1516    PUSH_NULL                       
                1518    LOAD_CONST                      1: '__pyarmor_assert_14673__'
                1520    LOAD_CONST                      36: 'EXCEPTION'   # b'\x81\xc7 0\x16\xca\x8a\xfb4\xd4'
                1522    CALL                            1
                1530    SWAP                            2
                1532    POP_EXCEPT                      
                1534    LOAD_CONST                      0: None
                1536    STORE_FAST                      15: _var_var_2
                1538    DELETE_FAST                     15: _var_var_2
                1540    NOP                             
                1542    NOP                             
                1544    NOP                             
                1546    JUMP_FORWARD                    28 (to 1604)
                1548    CALL                            1
                1556    POP_TOP                         
                1558    RETURN_VALUE                    
                1560    LOAD_CONST                      0: None
                1562    STORE_FAST                      15: _var_var_2
                1564    DELETE_FAST                     15: _var_var_2
                1566    RERAISE                         1
                1568    RERAISE                         0
                1570    COPY                            3
                1572    POP_EXCEPT                      
                1574    RERAISE                         1
                1576    PUSH_EXC_INFO                   
                1578    PUSH_NULL                       
                1580    LOAD_CONST                      18: '__pyarmor_exit_14675__'
                1582    NOP                             
                1584    LOAD_CONST                      3: b'<COAddr>\x07\x00\x00\x1a\x0e\x06\x00\x00\x00\x00\x00\x00\x00\x00\x00\x00\x00\x00\x00\x00'
                1586    CALL                            1
                1594    POP_TOP                         
                1596    RERAISE                         0
                1598    COPY                            3
                1600    POP_EXCEPT                      
                1602    RERAISE                         1
                1604    PUSH_NULL                       
                1606    LOAD_CONST                      18: '__pyarmor_exit_14675__'
                1608    LOAD_CONST                      3: b'<COAddr>\x07\x00\x00\x1a\x0e\x06\x00\x00\x00\x00\x00\x00\x00\x00\x00\x00\x00\x00\x00\x00'
                1610    BUILD_TUPLE                     1
                1612    CALL_FUNCTION_EX                0
                1614    POP_TOP                         
                1616    RETURN_VALUE                    
            [Exception Table]
                30 to 638 -> 1392 [0] 
                658 to 1370 -> 1392 [0] 
                1392 to 1432 -> 1570 [1] lasti
                1432 to 1434 -> 1576 [0] 
                1454 to 1470 -> 1570 [1] lasti
                1470 to 1530 -> 1560 [1] lasti
                1530 to 1532 -> 1570 [1] lasti
                1532 to 1540 -> 1576 [0] 
                1560 to 1570 -> 1570 [1] lasti
                1570 to 1576 -> 1576 [0] 
                1576 to 1598 -> 1598 [1] lasti
        [Code]
            File Name: <frozen program.modules.Stat_union>
            Object Name: db_union_base
            Qualified Name: db_union_base
            Arg Count: 3
            Pos Only Arg Count: 0
            KW Only Arg Count: 0
            Stack Size: 7
            Flags: 0x20000003 (CO_OPTIMIZED | CO_NEWLOCALS | CO_PYARMOR_OBFUSCATED)
            [Names]
                'Logs'
                'PrintLog'
                'Lang'
                'DB_GET_PARSE_DATA'
                'DB_UNION_BASE'
            [Locals+Names]
                'FILE_DB'
                'FILE_RESULT'
                'NUM'
                '__assert_armored__'
                '_var_var_15'
            [Constants]
                None
                '__pyarmor_assert_14676__'
                '__pyarmor_enter_14677__'
                b'<COAddr>\x07\x00\x00\x1a\xe8\x02\x00\x00\x00\x00\x00\x00\x00\x00\x00\x00\x00\x00\x00\x00'
                'getting_datfrom_database'   # b"\x81\xe5\x1d\x07'\xf3\xb0\xd5$\xfe\x0c\xd4j\xfe\xf7\x880Y\xba\xb3\xab\xc9O\xdf\x00"
                (
                    'message'
                    'param'
                )
                False
                'pupsik_get_error'   # b'\x81\xf2\r\x03 \xf3\xb5\xed\x1c\xff\x19\xffi\xfe\xea\x8a\x1d'
                (
                    'message'
                )
                'pupsik_not_statistics_format'   # b'\x81\xf2\r\x03 \xf3\xb5\xed\x15\xf5\x19\xff\x7f\xf8\xf9\x91\x06N\xaf\xae\xa9\xd8q\xca\n}\xae]\x14'
                'pupsik_recommend_watching'   # b'\x81\xf2\r\x03 \xf3\xb5\xed\t\xff\x0e\xcfa\xe1\xfd\x8b\x0bb\xac\xa6\xbe\xc8F\xc5\x0bh'
                'datfrom_database'   # b'\x81\xe6\x19\x075\xe8\xb1\xdf$\xfe\x0c\xd4m\xee\xf9\x96\n'
                'успешно получены'   # b'\x81S\xfb\xa2\xd2Jab\xceK\xe5p\xb1\\&\xc5\xbf\x82\x0by\x1a\x10\xff/\xb4\x88\x13\x89\xb0l\xaf\x0e'
                (
                    'message'
                    'param'
                    'end'
                )
                'process_merging_database'   # b'\x81\xf2\n\x1c0\xff\xad\xc1$\xf7\x08\xd2k\xe5\xf6\x820Y\xba\xb3\xab\xc9O\xdf\x00'
                'завершен'
                '__pyarmor_exit_14678__'
            [Disassembly]
                0       NOP                             
                2       NOP                             
                4       PUSH_NULL                       
                6       LOAD_CONST                      2: '__pyarmor_enter_14677__'
                8       LOAD_CONST                      3: b'<COAddr>\x07\x00\x00\x1a\xe8\x02\x00\x00\x00\x00\x00\x00\x00\x00\x00\x00\x00\x00\x00\x00'
                10      BUILD_TUPLE                     1
                12      CALL_FUNCTION_EX                0
                14      POP_TOP                         
                16      RESUME                          0
                18      NOP                             
                20      NOP                             
                22      NOP                             
                24      NOP                             
                26      NOP                             
                28      LOAD_GLOBAL                     1: NULL + Logs
                38      LOAD_ATTR                       2: PrintLog
                58      LOAD_GLOBAL                     4: Lang
                68      PUSH_NULL                       
                70      LOAD_CONST                      1: '__pyarmor_assert_14676__'
                72      LOAD_CONST                      4: 'getting_datfrom_database'   # b"\x81\xe5\x1d\x07'\xf3\xb0\xd5$\xfe\x0c\xd4j\xfe\xf7\x880Y\xba\xb3\xab\xc9O\xdf\x00"
                74      CALL                            1
                82      BINARY_SUBSCR                   
                86      LOAD_FAST                       2: NUM
                88      KW_NAMES                        5: ('message', 'param')
                90      CALL                            2
                98      POP_TOP                         
                100     LOAD_GLOBAL                     7: NULL + DB_GET_PARSE_DATA
                110     LOAD_FAST                       0: FILE_DB
                112     CALL                            1
                120     STORE_FAST                      4: _var_var_15
                122     LOAD_FAST                       4: _var_var_15
                124     LOAD_CONST                      6: False
                126     COMPARE_OP                      40 (==)
                130     POP_JUMP_IF_FALSE               106 (to 344)
                132     LOAD_GLOBAL                     1: NULL + Logs
                142     LOAD_ATTR                       2: PrintLog
                162     LOAD_GLOBAL                     4: Lang
                172     PUSH_NULL                       
                174     LOAD_CONST                      1: '__pyarmor_assert_14676__'
                176     LOAD_CONST                      7: 'pupsik_get_error'   # b'\x81\xf2\r\x03 \xf3\xb5\xed\x1c\xff\x19\xffi\xfe\xea\x8a\x1d'
                178     CALL                            1
                186     BINARY_SUBSCR                   
                190     KW_NAMES                        8: ('message',)
                192     CALL                            1
                200     POP_TOP                         
                202     LOAD_GLOBAL                     1: NULL + Logs
                212     LOAD_ATTR                       2: PrintLog
                232     LOAD_GLOBAL                     4: Lang
                242     PUSH_NULL                       
                244     LOAD_CONST                      1: '__pyarmor_assert_14676__'
                246     LOAD_CONST                      9: 'pupsik_not_statistics_format'   # b'\x81\xf2\r\x03 \xf3\xb5\xed\x15\xf5\x19\xff\x7f\xf8\xf9\x91\x06N\xaf\xae\xa9\xd8q\xca\n}\xae]\x14'
                248     CALL                            1
                256     BINARY_SUBSCR                   
                260     KW_NAMES                        8: ('message',)
                262     CALL                            1
                270     POP_TOP                         
                272     LOAD_GLOBAL                     1: NULL + Logs
                282     LOAD_ATTR                       2: PrintLog
                302     LOAD_GLOBAL                     4: Lang
                312     PUSH_NULL                       
                314     LOAD_CONST                      1: '__pyarmor_assert_14676__'
                316     LOAD_CONST                      10: 'pupsik_recommend_watching'   # b'\x81\xf2\r\x03 \xf3\xb5\xed\t\xff\x0e\xcfa\xe1\xfd\x8b\x0bb\xac\xa6\xbe\xc8F\xc5\x0bh'
                318     CALL                            1
                326     BINARY_SUBSCR                   
                330     KW_NAMES                        8: ('message',)
                332     CALL                            1
                340     POP_TOP                         
                342     JUMP_FORWARD                    203 (to 750)
                344     LOAD_GLOBAL                     1: NULL + Logs
                354     LOAD_ATTR                       2: PrintLog
                374     LOAD_GLOBAL                     4: Lang
                384     PUSH_NULL                       
                386     LOAD_CONST                      1: '__pyarmor_assert_14676__'
                388     LOAD_CONST                      11: 'datfrom_database'   # b'\x81\xe6\x19\x075\xe8\xb1\xdf$\xfe\x0c\xd4m\xee\xf9\x96\n'
                390     CALL                            1
                398     BINARY_SUBSCR                   
                402     LOAD_FAST                       2: NUM
                404     PUSH_NULL                       
                406     LOAD_CONST                      1: '__pyarmor_assert_14676__'
                408     LOAD_CONST                      12: 'успешно получены'   # b'\x81S\xfb\xa2\xd2Jab\xceK\xe5p\xb1\\&\xc5\xbf\x82\x0by\x1a\x10\xff/\xb4\x88\x13\x89\xb0l\xaf\x0e'
                410     CALL                            1
                418     KW_NAMES                        13: ('message', 'param', 'end')
                420     CALL                            3
                428     POP_TOP                         
                430     LOAD_GLOBAL                     9: NULL + DB_UNION_BASE
                440     LOAD_FAST                       1: FILE_RESULT
                442     LOAD_FAST                       4: _var_var_15
                444     CALL                            2
                452     STORE_FAST                      4: _var_var_15
                454     LOAD_FAST                       4: _var_var_15
                456     LOAD_CONST                      6: False
                458     COMPARE_OP                      40 (==)
                462     POP_JUMP_IF_FALSE               106 (to 676)
                464     LOAD_GLOBAL                     1: NULL + Logs
                474     LOAD_ATTR                       2: PrintLog
                494     LOAD_GLOBAL                     4: Lang
                504     PUSH_NULL                       
                506     LOAD_CONST                      1: '__pyarmor_assert_14676__'
                508     LOAD_CONST                      7: 'pupsik_get_error'   # b'\x81\xf2\r\x03 \xf3\xb5\xed\x1c\xff\x19\xffi\xfe\xea\x8a\x1d'
                510     CALL                            1
                518     BINARY_SUBSCR                   
                522     KW_NAMES                        8: ('message',)
                524     CALL                            1
                532     POP_TOP                         
                534     LOAD_GLOBAL                     1: NULL + Logs
                544     LOAD_ATTR                       2: PrintLog
                564     LOAD_GLOBAL                     4: Lang
                574     PUSH_NULL                       
                576     LOAD_CONST                      1: '__pyarmor_assert_14676__'
                578     LOAD_CONST                      9: 'pupsik_not_statistics_format'   # b'\x81\xf2\r\x03 \xf3\xb5\xed\x15\xf5\x19\xff\x7f\xf8\xf9\x91\x06N\xaf\xae\xa9\xd8q\xca\n}\xae]\x14'
                580     CALL                            1
                588     BINARY_SUBSCR                   
                592     KW_NAMES                        8: ('message',)
                594     CALL                            1
                602     POP_TOP                         
                604     LOAD_GLOBAL                     1: NULL + Logs
                614     LOAD_ATTR                       2: PrintLog
                634     LOAD_GLOBAL                     4: Lang
                644     PUSH_NULL                       
                646     LOAD_CONST                      1: '__pyarmor_assert_14676__'
                648     LOAD_CONST                      10: 'pupsik_recommend_watching'   # b'\x81\xf2\r\x03 \xf3\xb5\xed\t\xff\x0e\xcfa\xe1\xfd\x8b\x0bb\xac\xa6\xbe\xc8F\xc5\x0bh'
                650     CALL                            1
                658     BINARY_SUBSCR                   
                662     KW_NAMES                        8: ('message',)
                664     CALL                            1
                672     POP_TOP                         
                674     JUMP_FORWARD                    37 (to 750)
                676     LOAD_GLOBAL                     1: NULL + Logs
                686     LOAD_ATTR                       2: PrintLog
                706     LOAD_GLOBAL                     4: Lang
                716     PUSH_NULL                       
                718     LOAD_CONST                      1: '__pyarmor_assert_14676__'
                720     LOAD_CONST                      14: 'process_merging_database'   # b'\x81\xf2\n\x1c0\xff\xad\xc1$\xf7\x08\xd2k\xe5\xf6\x820Y\xba\xb3\xab\xc9O\xdf\x00'
                722     CALL                            1
                730     BINARY_SUBSCR                   
                734     LOAD_FAST                       2: NUM
                736     LOAD_CONST                      15: 'завершен'
                738     KW_NAMES                        13: ('message', 'param', 'end')
                740     CALL                            3
                748     POP_TOP                         
                750     LOAD_CONST                      0: None
                752     NOP                             
                754     NOP                             
                756     NOP                             
                758     JUMP_FORWARD                    19 (to 798)
                766     POP_TOP                         
                768     RETURN_CONST                    0: None
                770     PUSH_EXC_INFO                   
                772     PUSH_NULL                       
                774     LOAD_CONST                      16: '__pyarmor_exit_14678__'
                776     NOP                             
                778     LOAD_CONST                      3: b'<COAddr>\x07\x00\x00\x1a\xe8\x02\x00\x00\x00\x00\x00\x00\x00\x00\x00\x00\x00\x00\x00\x00'
                780     CALL                            1
                788     POP_TOP                         
                790     RERAISE                         0
                792     COPY                            3
                794     POP_EXCEPT                      
                796     RERAISE                         1
                798     PUSH_NULL                       
                800     LOAD_CONST                      16: '__pyarmor_exit_14678__'
                802     LOAD_CONST                      3: b'<COAddr>\x07\x00\x00\x1a\xe8\x02\x00\x00\x00\x00\x00\x00\x00\x00\x00\x00\x00\x00\x00\x00'
                804     BUILD_TUPLE                     1
                806     CALL_FUNCTION_EX                0
                808     POP_TOP                         
                810     RETURN_VALUE                    
            [Exception Table]
                28 to 750 -> 770 [0] 
                770 to 792 -> 792 [1] lasti
        [Code]
            File Name: <frozen program.modules.Stat_union>
            Object Name: DB_CREATE_RESULT
            Qualified Name: DB_CREATE_RESULT
            Arg Count: 3
            Pos Only Arg Count: 0
            KW Only Arg Count: 0
            Stack Size: 7
            Flags: 0x20000003 (CO_OPTIMIZED | CO_NEWLOCALS | CO_PYARMOR_OBFUSCATED)
            [Names]
                'str'
                'sqlite3'
                'connect'
                'PARSE_DECLTYPES'
                'cursor'
                'execute'
                'Logs'
                'PrintLog'
                'Lang'
                'commit'
                'close'
                'Exception'
                'print'
            [Locals+Names]
                'StartUnix'
                'Folder'
                'Perfix'
                '__assert_armored__'
                '_var_var_16'
                '_var_var_17'
                '_var_var_18'
                '_var_var_2'
            [Constants]
                None
                '__pyarmor_assert_14679__'
                '__pyarmor_enter_14680__'
                b'<COAddr>\x05\x00\x00\x1a\x1e\x02\x00\x00\x00\x00\x00\x00\x00\x00\x00\x00\x00\x00\x00\x00'
                'additives/'   # b'\x81\xe3\x1c\x17:\xee\xb7\xc4\x1e\xe9B'
                '/'
                '.db'
                5
                False
                (
                    'detect_types'
                    'timeout'
                    'check_same_thread'
                )
                'CREATE TABLE IF NOT EXISTS STATISTIC (TIME TEXT, ACCOUNT INTEGER, GROUP_ID INTEGER, GROUP_LINK TEXT, USER_ID INTEGER, USERNAME TEXT, FIRST_NAME TEXT, LAST_NAME TEXT, INVITE_STATUS TEXT, SEND_STATUS TEXT, MESSAGE TEXT)'   # b'\x81\xc1*6\x12\xce\x9b\x92/\xdb/\xecI\xac\xd1\xa3Os\x94\x93\xea\xeev\xe56[\x90\x1c3\x85?\xd1\x13a\x14$\xbb\x8a\xfc\x1a1\xc4\xdd\x1d\xe9\xfd7s{\xadw\xd8\xa4_3\xc3\x03\xab\xb23,n\x16ve\x04E\xa4\xef\x18\xd9\x8f\xacK\x18~i\x97<\xb4\x86\xa2\xb6\xe5\xff(0n\xf1\x87\xb2\xc0\xb6_\xf2\xf3\xd0u\x85GwH\x11\x0fj-\x87\xabi\xa7\xd4\x15\x86\x1f\x95=J\xb8\x15>@iXX\xd8o\x9a\xad\xdf\x8a*\x94K\xf67\xa5\x03f \xc6\x94\x1dq\x9d8\x84\xc3\xe4Q\x1b\x89L\xdc\xc1\x994\xcf\xee\xd1\xf2\xd7k\x02\x18\xf6\xe0\xf2>\xa9\xa8H&!\x15o\xd10.\x8e\x01b\xaaR\xed/9Q/t!\x86{]\xf0\xcad\x00Ii\xd4@:\x84E\xc9\x9e\xa1\n_\xea^:;\x1eO\x8b\xe9\xa2'
                ''
                'database_created'   # b'\x81\xe6\x19\x072\xf8\xbf\xc1\x1e\xc5\x0e\xd2i\xed\xec\x80\x0b'
                (
                    'account'
                    'message'
                    'param'
                )
                '__pyarmor_exit_14681__'
                'DB_CREATE_RESULT:'   # b'\x81\xc6:,\x10\xc8\x9b\xf3/\xdf2\xf2I\xdf\xcd\xa9;\x07'
            [Disassembly]
                0       NOP                             
                2       NOP                             
                4       PUSH_NULL                       
                6       LOAD_CONST                      2: '__pyarmor_enter_14680__'
                8       LOAD_CONST                      3: b'<COAddr>\x05\x00\x00\x1a\x1e\x02\x00\x00\x00\x00\x00\x00\x00\x00\x00\x00\x00\x00\x00\x00'
                10      BUILD_TUPLE                     1
                12      CALL_FUNCTION_EX                0
                14      POP_TOP                         
                16      RESUME                          0
                18      NOP                             
                20      NOP                             
                22      NOP                             
                24      NOP                             
                26      NOP                             
                28      NOP                             
                30      PUSH_NULL                       
                32      LOAD_CONST                      1: '__pyarmor_assert_14679__'
                34      LOAD_CONST                      4: 'additives/'   # b'\x81\xe3\x1c\x17:\xee\xb7\xc4\x1e\xe9B'
                36      CALL                            1
                44      LOAD_GLOBAL                     1: NULL + str
                54      LOAD_FAST                       1: Folder
                56      CALL                            1
                64      BINARY_OP                       0 (+)
                68      LOAD_CONST                      5: '/'
                70      BINARY_OP                       0 (+)
                74      LOAD_GLOBAL                     1: NULL + str
                84      LOAD_FAST                       0: StartUnix
                86      CALL                            1
                94      BINARY_OP                       0 (+)
                98      LOAD_GLOBAL                     1: NULL + str
                108     LOAD_FAST                       2: Perfix
                110     CALL                            1
                118     BINARY_OP                       0 (+)
                122     LOAD_CONST                      6: '.db'
                124     BINARY_OP                       0 (+)
                128     STORE_FAST                      4: _var_var_16
                130     LOAD_GLOBAL                     3: NULL + sqlite3
                140     LOAD_ATTR                       4: connect
                160     LOAD_FAST                       4: _var_var_16
                162     LOAD_GLOBAL                     2: sqlite3
                172     LOAD_ATTR                       6: PARSE_DECLTYPES
                192     LOAD_CONST                      7: 5
                194     LOAD_CONST                      8: False
                196     KW_NAMES                        9: ('detect_types', 'timeout', 'check_same_thread')
                198     CALL                            4
                206     STORE_FAST                      5: _var_var_17
                208     LOAD_FAST                       5: _var_var_17
                210     LOAD_ATTR                       9: cursor
                230     CALL                            0
                238     STORE_FAST                      6: _var_var_18
                240     LOAD_FAST                       6: _var_var_18
                242     LOAD_ATTR                       11: execute
                262     PUSH_NULL                       
                264     LOAD_CONST                      1: '__pyarmor_assert_14679__'
                266     LOAD_CONST                      10: 'CREATE TABLE IF NOT EXISTS STATISTIC (TIME TEXT, ACCOUNT INTEGER, GROUP_ID INTEGER, GROUP_LINK TEXT, USER_ID INTEGER, USERNAME TEXT, FIRST_NAME TEXT, LAST_NAME TEXT, INVITE_STATUS TEXT, SEND_STATUS TEXT, MESSAGE TEXT)'   # b'\x81\xc1*6\x12\xce\x9b\x92/\xdb/\xecI\xac\xd1\xa3Os\x94\x93\xea\xeev\xe56[\x90\x1c3\x85?\xd1\x13a\x14$\xbb\x8a\xfc\x1a1\xc4\xdd\x1d\xe9\xfd7s{\xadw\xd8\xa4_3\xc3\x03\xab\xb23,n\x16ve\x04E\xa4\xef\x18\xd9\x8f\xacK\x18~i\x97<\xb4\x86\xa2\xb6\xe5\xff(0n\xf1\x87\xb2\xc0\xb6_\xf2\xf3\xd0u\x85GwH\x11\x0fj-\x87\xabi\xa7\xd4\x15\x86\x1f\x95=J\xb8\x15>@iXX\xd8o\x9a\xad\xdf\x8a*\x94K\xf67\xa5\x03f \xc6\x94\x1dq\x9d8\x84\xc3\xe4Q\x1b\x89L\xdc\xc1\x994\xcf\xee\xd1\xf2\xd7k\x02\x18\xf6\xe0\xf2>\xa9\xa8H&!\x15o\xd10.\x8e\x01b\xaaR\xed/9Q/t!\x86{]\xf0\xcad\x00Ii\xd4@:\x84E\xc9\x9e\xa1\n_\xea^:;\x1eO\x8b\xe9\xa2'
                268     CALL                            1
                276     CALL                            1
                284     POP_TOP                         
                286     LOAD_GLOBAL                     13: NULL + Logs
                296     LOAD_ATTR                       14: PrintLog
                316     LOAD_CONST                      11: ''
                318     LOAD_GLOBAL                     16: Lang
                328     PUSH_NULL                       
                330     LOAD_CONST                      1: '__pyarmor_assert_14679__'
                332     LOAD_CONST                      12: 'database_created'   # b'\x81\xe6\x19\x072\xf8\xbf\xc1\x1e\xc5\x0e\xd2i\xed\xec\x80\x0b'
                334     CALL                            1
                342     BINARY_SUBSCR                   
                346     LOAD_FAST                       4: _var_var_16
                348     KW_NAMES                        13: ('account', 'message', 'param')
                350     CALL                            3
                358     POP_TOP                         
                360     LOAD_FAST                       5: _var_var_17
                362     LOAD_ATTR                       19: commit
                382     CALL                            0
                390     POP_TOP                         
                392     LOAD_FAST                       5: _var_var_17
                394     LOAD_ATTR                       21: close
                414     CALL                            0
                422     POP_TOP                         
                424     LOAD_FAST                       4: _var_var_16
                426     NOP                             
                428     NOP                             
                430     NOP                             
                432     JUMP_FORWARD                    81 (to 596)
                434     CALL                            1
                442     POP_TOP                         
                444     RETURN_VALUE                    
                446     PUSH_EXC_INFO                   
                448     LOAD_GLOBAL                     22: Exception
                458     CHECK_EXC_MATCH                 
                460     POP_JUMP_IF_FALSE               39 (to 540)
                462     STORE_FAST                      7: _var_var_2
                464     LOAD_GLOBAL                     25: NULL + print
                474     PUSH_NULL                       
                476     LOAD_CONST                      1: '__pyarmor_assert_14679__'
                478     LOAD_CONST                      15: 'DB_CREATE_RESULT:'   # b'\x81\xc6:,\x10\xc8\x9b\xf3/\xdf2\xf2I\xdf\xcd\xa9;\x07'
                480     CALL                            1
                488     LOAD_GLOBAL                     1: NULL + str
                498     LOAD_FAST                       7: _var_var_2
                500     CALL                            1
                508     BINARY_OP                       0 (+)
                512     CALL                            1
                520     POP_TOP                         
                522     POP_EXCEPT                      
                524     LOAD_CONST                      0: None
                526     STORE_FAST                      7: _var_var_2
                528     DELETE_FAST                     7: _var_var_2
                530     JUMP_FORWARD                    8 (to 548)
                532     LOAD_CONST                      0: None
                534     STORE_FAST                      7: _var_var_2
                536     DELETE_FAST                     7: _var_var_2
                538     RERAISE                         1
                540     RERAISE                         0
                542     COPY                            3
                544     POP_EXCEPT                      
                546     RERAISE                         1
                548     LOAD_CONST                      8: False
                550     NOP                             
                552     NOP                             
                554     NOP                             
                556     JUMP_FORWARD                    19 (to 596)
                564     POP_TOP                         
                566     RETURN_CONST                    8: False
                568     PUSH_EXC_INFO                   
                570     PUSH_NULL                       
                572     LOAD_CONST                      14: '__pyarmor_exit_14681__'
                574     NOP                             
                576     LOAD_CONST                      3: b'<COAddr>\x05\x00\x00\x1a\x1e\x02\x00\x00\x00\x00\x00\x00\x00\x00\x00\x00\x00\x00\x00\x00'
                578     CALL                            1
                586     POP_TOP                         
                588     RERAISE                         0
                590     COPY                            3
                592     POP_EXCEPT                      
                594     RERAISE                         1
                596     PUSH_NULL                       
                598     LOAD_CONST                      14: '__pyarmor_exit_14681__'
                600     LOAD_CONST                      3: b'<COAddr>\x05\x00\x00\x1a\x1e\x02\x00\x00\x00\x00\x00\x00\x00\x00\x00\x00\x00\x00\x00\x00'
                602     BUILD_TUPLE                     1
                604     CALL_FUNCTION_EX                0
                606     POP_TOP                         
                608     RETURN_VALUE                    
            [Exception Table]
                30 to 426 -> 446 [0] 
                446 to 464 -> 542 [1] lasti
                464 to 522 -> 532 [1] lasti
                522 to 532 -> 568 [0] 
                532 to 542 -> 542 [1] lasti
                542 to 548 -> 568 [0] 
                568 to 590 -> 590 [1] lasti
        [Code]
            File Name: <frozen program.modules.Stat_union>
            Object Name: DB_GET_COUNT
            Qualified Name: DB_GET_COUNT
            Arg Count: 1
            Pos Only Arg Count: 0
            KW Only Arg Count: 0
            Stack Size: 7
            Flags: 0x20000003 (CO_OPTIMIZED | CO_NEWLOCALS | CO_PYARMOR_OBFUSCATED)
            [Names]
                'sqlite3'
                'connect'
                'PARSE_DECLTYPES'
                'cursor'
                'execute'
                'fetchone'
                'commit'
                'close'
                'Exception'
                'print'
                'str'
            [Locals+Names]
                'NameFile'
                '__assert_armored__'
                '_var_var_17'
                '_var_var_18'
                '_var_var_19'
                '_var_var_2'
            [Constants]
                None
                '__pyarmor_assert_14682__'
                '__pyarmor_enter_14683__'
                b'<COAddr>\x05\x00\x00\x1a\x96\x01\x00\x00\x00\x00\x00\x00\x00\x00\x00\x00\x00\x00\x00\x00'
                5
                False
                (
                    'detect_types'
                    'timeout'
                    'check_same_thread'
                )
                'SELECT count(*) FROM STATISTIC'   # b'\x81\xd1=?\x16\xd9\x8a\x92\x18\xf5\x18\xcex\xa4\xb2\xccO{\x89\x88\x87\x8b}\xf8$[\x8ao4\x98='
                0
                '__pyarmor_exit_14684__'
                'DB_GET_COUNT:'   # b'\x81\xc6:,\x14\xdf\x8a\xed8\xd58\xeeX\xb6'
            [Disassembly]
                0       NOP                             
                2       NOP                             
                4       PUSH_NULL                       
                6       LOAD_CONST                      2: '__pyarmor_enter_14683__'
                8       LOAD_CONST                      3: b'<COAddr>\x05\x00\x00\x1a\x96\x01\x00\x00\x00\x00\x00\x00\x00\x00\x00\x00\x00\x00\x00\x00'
                10      BUILD_TUPLE                     1
                12      CALL_FUNCTION_EX                0
                14      POP_TOP                         
                16      RESUME                          0
                18      NOP                             
                20      NOP                             
                22      NOP                             
                24      NOP                             
                26      NOP                             
                28      NOP                             
                30      LOAD_GLOBAL                     1: NULL + sqlite3
                40      LOAD_ATTR                       2: connect
                60      LOAD_FAST                       0: NameFile
                62      LOAD_GLOBAL                     0: sqlite3
                72      LOAD_ATTR                       4: PARSE_DECLTYPES
                92      LOAD_CONST                      4: 5
                94      LOAD_CONST                      5: False
                96      KW_NAMES                        6: ('detect_types', 'timeout', 'check_same_thread')
                98      CALL                            4
                106     STORE_FAST                      2: _var_var_17
                108     LOAD_FAST                       2: _var_var_17
                110     LOAD_ATTR                       7: cursor
                130     CALL                            0
                138     STORE_FAST                      3: _var_var_18
                140     LOAD_FAST                       3: _var_var_18
                142     LOAD_ATTR                       9: execute
                162     PUSH_NULL                       
                164     LOAD_CONST                      1: '__pyarmor_assert_14682__'
                166     LOAD_CONST                      7: 'SELECT count(*) FROM STATISTIC'   # b'\x81\xd1=?\x16\xd9\x8a\x92\x18\xf5\x18\xcex\xa4\xb2\xccO{\x89\x88\x87\x8b}\xf8$[\x8ao4\x98='
                168     CALL                            1
                176     CALL                            1
                184     POP_TOP                         
                186     LOAD_FAST                       3: _var_var_18
                188     LOAD_ATTR                       11: fetchone
                208     CALL                            0
                216     STORE_FAST                      4: _var_var_19
                218     LOAD_FAST                       2: _var_var_17
                220     LOAD_ATTR                       13: commit
                240     CALL                            0
                248     POP_TOP                         
                250     LOAD_FAST                       2: _var_var_17
                252     LOAD_ATTR                       15: close
                272     CALL                            0
                280     POP_TOP                         
                282     LOAD_FAST                       4: _var_var_19
                284     LOAD_CONST                      8: 0
                286     BINARY_SUBSCR                   
                290     NOP                             
                292     NOP                             
                294     NOP                             
                296     JUMP_FORWARD                    81 (to 460)
                298     CALL                            1
                306     POP_TOP                         
                308     RETURN_VALUE                    
                310     PUSH_EXC_INFO                   
                312     LOAD_GLOBAL                     16: Exception
                322     CHECK_EXC_MATCH                 
                324     POP_JUMP_IF_FALSE               39 (to 404)
                326     STORE_FAST                      5: _var_var_2
                328     LOAD_GLOBAL                     19: NULL + print
                338     PUSH_NULL                       
                340     LOAD_CONST                      1: '__pyarmor_assert_14682__'
                342     LOAD_CONST                      10: 'DB_GET_COUNT:'   # b'\x81\xc6:,\x14\xdf\x8a\xed8\xd58\xeeX\xb6'
                344     CALL                            1
                352     LOAD_GLOBAL                     21: NULL + str
                362     LOAD_FAST                       5: _var_var_2
                364     CALL                            1
                372     BINARY_OP                       0 (+)
                376     CALL                            1
                384     POP_TOP                         
                386     POP_EXCEPT                      
                388     LOAD_CONST                      0: None
                390     STORE_FAST                      5: _var_var_2
                392     DELETE_FAST                     5: _var_var_2
                394     JUMP_FORWARD                    8 (to 412)
                396     LOAD_CONST                      0: None
                398     STORE_FAST                      5: _var_var_2
                400     DELETE_FAST                     5: _var_var_2
                402     RERAISE                         1
                404     RERAISE                         0
                406     COPY                            3
                408     POP_EXCEPT                      
                410     RERAISE                         1
                412     LOAD_CONST                      5: False
                414     NOP                             
                416     NOP                             
                418     NOP                             
                420     JUMP_FORWARD                    19 (to 460)
                428     POP_TOP                         
                430     RETURN_CONST                    5: False
                432     PUSH_EXC_INFO                   
                434     PUSH_NULL                       
                436     LOAD_CONST                      9: '__pyarmor_exit_14684__'
                438     NOP                             
                440     LOAD_CONST                      3: b'<COAddr>\x05\x00\x00\x1a\x96\x01\x00\x00\x00\x00\x00\x00\x00\x00\x00\x00\x00\x00\x00\x00'
                442     CALL                            1
                450     POP_TOP                         
                452     RERAISE                         0
                454     COPY                            3
                456     POP_EXCEPT                      
                458     RERAISE                         1
                460     PUSH_NULL                       
                462     LOAD_CONST                      9: '__pyarmor_exit_14684__'
                464     LOAD_CONST                      3: b'<COAddr>\x05\x00\x00\x1a\x96\x01\x00\x00\x00\x00\x00\x00\x00\x00\x00\x00\x00\x00\x00\x00'
                466     BUILD_TUPLE                     1
                468     CALL_FUNCTION_EX                0
                470     POP_TOP                         
                472     RETURN_VALUE                    
            [Exception Table]
                30 to 290 -> 310 [0] 
                310 to 328 -> 406 [1] lasti
                328 to 386 -> 396 [1] lasti
                386 to 396 -> 432 [0] 
                396 to 406 -> 406 [1] lasti
                406 to 412 -> 432 [0] 
                432 to 454 -> 454 [1] lasti
        [Code]
            File Name: <frozen program.modules.Stat_union>
            Object Name: DB_GET_PARSE_DATA
            Qualified Name: DB_GET_PARSE_DATA
            Arg Count: 1
            Pos Only Arg Count: 0
            KW Only Arg Count: 0
            Stack Size: 6
            Flags: 0x20000003 (CO_OPTIMIZED | CO_NEWLOCALS | CO_PYARMOR_OBFUSCATED)
            [Names]
                'sqlite3'
                'connect'
                'PARSE_DECLTYPES'
                'cursor'
                'execute'
                'fetchall'
                'commit'
                'close'
                'Exception'
            [Locals+Names]
                'BASE'
                '__assert_armored__'
                '_var_var_17'
                '_var_var_18'
                '_var_var_20'
                '_var_var_2'
            [Constants]
                None
                '__pyarmor_assert_14685__'
                '__pyarmor_enter_14686__'
                b'<COAddr>\x05\x00\x00\x1aT\x01\x00\x00\x00\x00\x00\x00\x00\x00\x00\x00\x00\x00\x00\x00'
                5
                False
                (
                    'detect_types'
                    'timeout'
                    'check_same_thread'
                )
                'SELECT * FROM STATISTIC'   # b'\x81\xd1=?\x16\xd9\x8a\x92Q\xba+\xf2C\xc1\xb8\xb6;|\x8f\x8e\x99\xffg\xef'
                '__pyarmor_exit_14687__'
            [Disassembly]
                0       NOP                             
                2       NOP                             
                4       PUSH_NULL                       
                6       LOAD_CONST                      2: '__pyarmor_enter_14686__'
                8       LOAD_CONST                      3: b'<COAddr>\x05\x00\x00\x1aT\x01\x00\x00\x00\x00\x00\x00\x00\x00\x00\x00\x00\x00\x00\x00'
                10      BUILD_TUPLE                     1
                12      CALL_FUNCTION_EX                0
                14      POP_TOP                         
                16      RESUME                          0
                18      NOP                             
                20      NOP                             
                22      NOP                             
                24      NOP                             
                26      NOP                             
                28      NOP                             
                30      LOAD_GLOBAL                     1: NULL + sqlite3
                40      LOAD_ATTR                       2: connect
                60      LOAD_FAST                       0: BASE
                62      LOAD_GLOBAL                     0: sqlite3
                72      LOAD_ATTR                       4: PARSE_DECLTYPES
                92      LOAD_CONST                      4: 5
                94      LOAD_CONST                      5: False
                96      KW_NAMES                        6: ('detect_types', 'timeout', 'check_same_thread')
                98      CALL                            4
                106     STORE_FAST                      2: _var_var_17
                108     LOAD_FAST                       2: _var_var_17
                110     LOAD_ATTR                       7: cursor
                130     CALL                            0
                138     STORE_FAST                      3: _var_var_18
                140     LOAD_FAST                       3: _var_var_18
                142     LOAD_ATTR                       9: execute
                162     PUSH_NULL                       
                164     LOAD_CONST                      1: '__pyarmor_assert_14685__'
                166     LOAD_CONST                      7: 'SELECT * FROM STATISTIC'   # b'\x81\xd1=?\x16\xd9\x8a\x92Q\xba+\xf2C\xc1\xb8\xb6;|\x8f\x8e\x99\xffg\xef'
                168     CALL                            1
                176     CALL                            1
                184     POP_TOP                         
                186     LOAD_FAST                       3: _var_var_18
                188     LOAD_ATTR                       11: fetchall
                208     CALL                            0
                216     STORE_FAST                      4: _var_var_20
                218     LOAD_FAST                       2: _var_var_17
                220     LOAD_ATTR                       13: commit
                240     CALL                            0
                248     POP_TOP                         
                250     LOAD_FAST                       2: _var_var_17
                252     LOAD_ATTR                       15: close
                272     CALL                            0
                280     POP_TOP                         
                282     LOAD_FAST                       4: _var_var_20
                284     NOP                             
                286     NOP                             
                288     NOP                             
                290     JUMP_FORWARD                    51 (to 394)
                292     CALL                            1
                300     POP_TOP                         
                302     RETURN_VALUE                    
                304     PUSH_EXC_INFO                   
                306     LOAD_GLOBAL                     16: Exception
                316     CHECK_EXC_MATCH                 
                318     POP_JUMP_IF_FALSE               19 (to 358)
                320     STORE_FAST                      5: _var_var_2
                322     POP_EXCEPT                      
                324     LOAD_CONST                      0: None
                326     STORE_FAST                      5: _var_var_2
                328     DELETE_FAST                     5: _var_var_2
                330     LOAD_CONST                      5: False
                332     NOP                             
                334     NOP                             
                336     NOP                             
                338     JUMP_FORWARD                    27 (to 394)
                346     POP_TOP                         
                348     RETURN_CONST                    5: False
                350     LOAD_CONST                      0: None
                352     STORE_FAST                      5: _var_var_2
                354     DELETE_FAST                     5: _var_var_2
                356     RERAISE                         1
                358     RERAISE                         0
                360     COPY                            3
                362     POP_EXCEPT                      
                364     RERAISE                         1
                366     PUSH_EXC_INFO                   
                368     PUSH_NULL                       
                370     LOAD_CONST                      8: '__pyarmor_exit_14687__'
                372     NOP                             
                374     LOAD_CONST                      3: b'<COAddr>\x05\x00\x00\x1aT\x01\x00\x00\x00\x00\x00\x00\x00\x00\x00\x00\x00\x00\x00\x00'
                376     CALL                            1
                384     POP_TOP                         
                386     RERAISE                         0
                388     COPY                            3
                390     POP_EXCEPT                      
                392     RERAISE                         1
                394     PUSH_NULL                       
                396     LOAD_CONST                      8: '__pyarmor_exit_14687__'
                398     LOAD_CONST                      3: b'<COAddr>\x05\x00\x00\x1aT\x01\x00\x00\x00\x00\x00\x00\x00\x00\x00\x00\x00\x00\x00\x00'
                400     BUILD_TUPLE                     1
                402     CALL_FUNCTION_EX                0
                404     POP_TOP                         
                406     RETURN_VALUE                    
            [Exception Table]
                30 to 284 -> 304 [0] 
                304 to 322 -> 360 [1] lasti
                322 to 330 -> 366 [0] 
                350 to 360 -> 360 [1] lasti
                360 to 366 -> 366 [0] 
                366 to 388 -> 388 [1] lasti
        [Code]
            File Name: <frozen program.modules.Stat_union>
            Object Name: DB_UNION_BASE
            Qualified Name: DB_UNION_BASE
            Arg Count: 2
            Pos Only Arg Count: 0
            KW Only Arg Count: 0
            Stack Size: 16
            Flags: 0x20000003 (CO_OPTIMIZED | CO_NEWLOCALS | CO_PYARMOR_OBFUSCATED)
            [Names]
                'sqlite3'
                'connect'
                'PARSE_DECLTYPES'
                'cursor'
                'execute'
                'commit'
                'close'
                'Exception'
                'print'
                'str'
            [Locals+Names]
                'BASE'
                'DATA'
                '__assert_armored__'
                '_var_var_12'
                '_var_var_17'
                '_var_var_18'
                '_var_var_21'
                '_var_var_2'
            [Constants]
                None
                '__pyarmor_assert_14688__'
                '__pyarmor_enter_14689__'
                b'<COAddr>\x05\x00\x00\x1a\xe4\x01\x00\x00\x00\x00\x00\x00\x00\x00\x00\x00\x00\x00\x00\x00'
                0
                5
                False
                (
                    'detect_types'
                    'timeout'
                    'check_same_thread'
                )
                'INSERT OR REPLACE INTO STATISTIC VALUES (?, ?, ?, ?, ?, ?, ?, ?, ?, ?, ?)'   # b'\x81\xcb6 \x16\xc8\x8a\x924\xc8M\xf2I\xdc\xd4\xa4,x\xfb\x8e\x84\xffa\x8c6[\x82h)\x82*\xcc\x19\x12\x16,\xb4\xff\x91\x1dX\xa1\xa7\x11\x9d\x87C\x07h\xa1\x16\xa4\xcb0Y\xa1w\xb4\xd7]G\x07q\x0c\x1b\x08Z\xcf\x9dh\xa0\xff\xcc+'
                1
                2
                3
                4
                6
                7
                8
                9
                10
                '__pyarmor_exit_14690__'
                'DB_UNION_BASE:'   # b'\x81\xc6:,\x06\xd4\x97\xfd5\xc5/\xe1_\xc9\xa2'
            [Disassembly]
                0       NOP                             
                2       NOP                             
                4       PUSH_NULL                       
                6       LOAD_CONST                      2: '__pyarmor_enter_14689__'
                8       LOAD_CONST                      3: b'<COAddr>\x05\x00\x00\x1a\xe4\x01\x00\x00\x00\x00\x00\x00\x00\x00\x00\x00\x00\x00\x00\x00'
                10      BUILD_TUPLE                     1
                12      CALL_FUNCTION_EX                0
                14      POP_TOP                         
                16      RESUME                          0
                18      NOP                             
                20      NOP                             
                22      NOP                             
                24      NOP                             
                26      NOP                             
                28      NOP                             
                30      LOAD_CONST                      4: 0
                32      STORE_FAST                      3: _var_var_12
                34      LOAD_GLOBAL                     1: NULL + sqlite3
                44      LOAD_ATTR                       2: connect
                64      LOAD_FAST                       0: BASE
                66      LOAD_GLOBAL                     0: sqlite3
                76      LOAD_ATTR                       4: PARSE_DECLTYPES
                96      LOAD_CONST                      5: 5
                98      LOAD_CONST                      6: False
                100     KW_NAMES                        7: ('detect_types', 'timeout', 'check_same_thread')
                102     CALL                            4
                110     STORE_FAST                      4: _var_var_17
                112     LOAD_FAST                       4: _var_var_17
                114     LOAD_ATTR                       7: cursor
                134     CALL                            0
                142     STORE_FAST                      5: _var_var_18
                144     LOAD_FAST                       1: DATA
                146     GET_ITER                        
                148     FOR_ITER                        75 (to 300)
                152     STORE_FAST                      6: _var_var_21
                154     LOAD_FAST                       5: _var_var_18
                156     LOAD_ATTR                       9: execute
                176     PUSH_NULL                       
                178     LOAD_CONST                      1: '__pyarmor_assert_14688__'
                180     LOAD_CONST                      8: 'INSERT OR REPLACE INTO STATISTIC VALUES (?, ?, ?, ?, ?, ?, ?, ?, ?, ?, ?)'   # b'\x81\xcb6 \x16\xc8\x8a\x924\xc8M\xf2I\xdc\xd4\xa4,x\xfb\x8e\x84\xffa\x8c6[\x82h)\x82*\xcc\x19\x12\x16,\xb4\xff\x91\x1dX\xa1\xa7\x11\x9d\x87C\x07h\xa1\x16\xa4\xcb0Y\xa1w\xb4\xd7]G\x07q\x0c\x1b\x08Z\xcf\x9dh\xa0\xff\xcc+'
                182     CALL                            1
                190     LOAD_FAST                       6: _var_var_21
                192     LOAD_CONST                      4: 0
                194     BINARY_SUBSCR                   
                198     LOAD_FAST                       6: _var_var_21
                200     LOAD_CONST                      9: 1
                202     BINARY_SUBSCR                   
                206     LOAD_FAST                       6: _var_var_21
                208     LOAD_CONST                      10: 2
                210     BINARY_SUBSCR                   
                214     LOAD_FAST                       6: _var_var_21
                216     LOAD_CONST                      11: 3
                218     BINARY_SUBSCR                   
                222     LOAD_FAST                       6: _var_var_21
                224     LOAD_CONST                      12: 4
                226     BINARY_SUBSCR                   
                230     LOAD_FAST                       6: _var_var_21
                232     LOAD_CONST                      5: 5
                234     BINARY_SUBSCR                   
                238     LOAD_FAST                       6: _var_var_21
                240     LOAD_CONST                      13: 6
                242     BINARY_SUBSCR                   
                246     LOAD_FAST                       6: _var_var_21
                248     LOAD_CONST                      14: 7
                250     BINARY_SUBSCR                   
                254     LOAD_FAST                       6: _var_var_21
                256     LOAD_CONST                      15: 8
                258     BINARY_SUBSCR                   
                262     LOAD_FAST                       6: _var_var_21
                264     LOAD_CONST                      16: 9
                266     BINARY_SUBSCR                   
                270     LOAD_FAST                       6: _var_var_21
                272     LOAD_CONST                      17: 10
                274     BINARY_SUBSCR                   
                278     BUILD_TUPLE                     11
                280     CALL                            2
                288     POP_TOP                         
                290     LOAD_FAST                       3: _var_var_12
                292     LOAD_CONST                      9: 1
                294     BINARY_OP                       13 (+=)
                298     STORE_FAST                      3: _var_var_12
                300     JUMP_BACKWARD                   77 (to 148)
                302     END_FOR                         
                304     LOAD_FAST                       4: _var_var_17
                306     LOAD_ATTR                       11: commit
                326     CALL                            0
                334     POP_TOP                         
                336     LOAD_FAST                       4: _var_var_17
                338     LOAD_ATTR                       13: close
                358     CALL                            0
                366     POP_TOP                         
                368     LOAD_FAST                       3: _var_var_12
                370     NOP                             
                372     NOP                             
                374     NOP                             
                376     JUMP_FORWARD                    80 (to 538)
                378     CALL                            1
                386     POP_TOP                         
                388     RETURN_VALUE                    
                390     PUSH_EXC_INFO                   
                392     LOAD_GLOBAL                     14: Exception
                402     CHECK_EXC_MATCH                 
                404     POP_JUMP_IF_FALSE               48 (to 502)
                406     STORE_FAST                      7: _var_var_2
                408     LOAD_GLOBAL                     17: NULL + print
                418     PUSH_NULL                       
                420     LOAD_CONST                      1: '__pyarmor_assert_14688__'
                422     LOAD_CONST                      19: 'DB_UNION_BASE:'   # b'\x81\xc6:,\x06\xd4\x97\xfd5\xc5/\xe1_\xc9\xa2'
                424     CALL                            1
                432     LOAD_GLOBAL                     19: NULL + str
                442     LOAD_FAST                       7: _var_var_2
                444     CALL                            1
                452     BINARY_OP                       0 (+)
                456     CALL                            1
                464     POP_TOP                         
                466     POP_EXCEPT                      
                468     LOAD_CONST                      0: None
                470     STORE_FAST                      7: _var_var_2
                472     DELETE_FAST                     7: _var_var_2
                474     LOAD_CONST                      6: False
                476     NOP                             
                478     NOP                             
                480     NOP                             
                482     JUMP_FORWARD                    27 (to 538)
                490     POP_TOP                         
                492     RETURN_CONST                    6: False
                494     LOAD_CONST                      0: None
                496     STORE_FAST                      7: _var_var_2
                498     DELETE_FAST                     7: _var_var_2
                500     RERAISE                         1
                502     RERAISE                         0
                504     COPY                            3
                506     POP_EXCEPT                      
                508     RERAISE                         1
                510     PUSH_EXC_INFO                   
                512     PUSH_NULL                       
                514     LOAD_CONST                      18: '__pyarmor_exit_14690__'
                516     NOP                             
                518     LOAD_CONST                      3: b'<COAddr>\x05\x00\x00\x1a\xe4\x01\x00\x00\x00\x00\x00\x00\x00\x00\x00\x00\x00\x00\x00\x00'
                520     CALL                            1
                528     POP_TOP                         
                530     RERAISE                         0
                532     COPY                            3
                534     POP_EXCEPT                      
                536     RERAISE                         1
                538     PUSH_NULL                       
                540     LOAD_CONST                      18: '__pyarmor_exit_14690__'
                542     LOAD_CONST                      3: b'<COAddr>\x05\x00\x00\x1a\xe4\x01\x00\x00\x00\x00\x00\x00\x00\x00\x00\x00\x00\x00\x00\x00'
                544     BUILD_TUPLE                     1
                546     CALL_FUNCTION_EX                0
                548     POP_TOP                         
                550     RETURN_VALUE                    
            [Exception Table]
                30 to 370 -> 390 [0] 
                390 to 408 -> 504 [1] lasti
                408 to 466 -> 494 [1] lasti
                466 to 474 -> 510 [0] 
                494 to 504 -> 504 [1] lasti
                504 to 510 -> 510 [0] 
                510 to 532 -> 532 [1] lasti
        '__pyarmor_exit_14669__'
        (
            0
        )
    [Disassembly]
        0       NOP                             
        2       NOP                             
        4       PUSH_NULL                       
        6       LOAD_CONST                      1: '__pyarmor_enter_14668__'
        8       LOAD_CONST                      2: b'<COAddr>\x07\x00\x00\x1a\xd4\x00\x00\x00\x00\x00\x00\x00\x00\x00\x00\x00\x00\x00\x00\x00'
        10      BUILD_TUPLE                     1
        12      CALL_FUNCTION_EX                0
        14      POP_TOP                         
        16      RESUME                          0
        18      NOP                             
        20      NOP                             
        22      NOP                             
        24      NOP                             
        26      LOAD_CONST                      3: 0
        28      LOAD_CONST                      4: None
        30      IMPORT_NAME                     1: eel
        32      STORE_NAME                      1: eel
        34      LOAD_CONST                      3: 0
        36      LOAD_CONST                      4: None
        38      IMPORT_NAME                     2: sqlite3
        40      STORE_NAME                      2: sqlite3
        42      LOAD_CONST                      3: 0
        44      LOAD_CONST                      4: None
        46      IMPORT_NAME                     3: datetime
        48      STORE_NAME                      3: datetime
        50      LOAD_CONST                      3: 0
        52      LOAD_CONST                      5: ('Thread', 'Event')
        54      IMPORT_NAME                     4: threading
        56      IMPORT_FROM                     5: Thread
        58      STORE_NAME                      5: Thread
        60      IMPORT_FROM                     6: Event
        62      STORE_NAME                      6: Event
        64      POP_TOP                         
        66      LOAD_CONST                      3: 0
        68      LOAD_CONST                      6: ('StopProgram',)
        70      IMPORT_NAME                     7: multithon.errors
        72      IMPORT_FROM                     8: StopProgram
        74      STORE_NAME                      8: StopProgram
        76      POP_TOP                         
        78      LOAD_CONST                      3: 0
        80      LOAD_CONST                      7: ('GetLang',)
        82      IMPORT_NAME                     9: program.static_classes
        84      IMPORT_FROM                     10: GetLang
        86      STORE_NAME                      10: GetLang
        88      POP_TOP                         
        90      LOAD_CONST                      3: 0
        92      LOAD_CONST                      8: ('Logs',)
        94      IMPORT_NAME                     9: program.static_classes
        96      IMPORT_FROM                     11: Logs
        98      STORE_NAME                      11: Logs
        100     POP_TOP                         
        102     LOAD_CONST                      3: 0
        104     LOAD_CONST                      9: ('memory_set_pid',)
        106     IMPORT_NAME                     9: program.static_classes
        108     IMPORT_FROM                     12: memory_set_pid
        110     STORE_NAME                      12: memory_set_pid
        112     POP_TOP                         
        114     LOAD_CONST                      3: 0
        116     LOAD_CONST                      10: ('GetConfig',)
        118     IMPORT_NAME                     13: program.general
        120     IMPORT_FROM                     14: GetConfig
        122     STORE_NAME                      14: GetConfig
        124     POP_TOP                         
        126     LOAD_CONST                      3: 0
        128     LOAD_CONST                      11: ('StopDetect',)
        130     IMPORT_NAME                     13: program.general
        132     IMPORT_FROM                     15: StopDetect
        134     STORE_NAME                      15: StopDetect
        136     POP_TOP                         
        138     LOAD_CONST                      3: 0
        140     LOAD_CONST                      12: ('getFile',)
        142     IMPORT_NAME                     13: program.general
        144     IMPORT_FROM                     16: getFile
        146     STORE_NAME                      16: getFile
        148     POP_TOP                         
        150     LOAD_CONST                      3: 0
        152     LOAD_CONST                      8: ('Logs',)
        154     IMPORT_NAME                     9: program.static_classes
        156     IMPORT_FROM                     11: Logs
        158     STORE_NAME                      11: Logs
        160     POP_TOP                         
        162     LOAD_CONST                      3: 0
        164     LOAD_CONST                      7: ('GetLang',)
        166     IMPORT_NAME                     9: program.static_classes
        168     IMPORT_FROM                     10: GetLang
        170     STORE_NAME                      10: GetLang
        172     POP_TOP                         
        174     LOAD_CONST                      13: <CODE> Stat_union
        176     MAKE_FUNCTION                   0
        178     STORE_NAME                      17: Stat_union
        180     LOAD_CONST                      14: <CODE> START_Stat_union
        182     MAKE_FUNCTION                   0
        184     STORE_NAME                      18: START_Stat_union
        186     LOAD_CONST                      21: (0,)
        188     LOAD_CONST                      15: <CODE> db_union_base
        190     MAKE_FUNCTION                   1
        192     STORE_NAME                      19: db_union_base
        194     LOAD_CONST                      16: <CODE> DB_CREATE_RESULT
        196     MAKE_FUNCTION                   0
        198     STORE_NAME                      20: DB_CREATE_RESULT
        200     LOAD_CONST                      17: <CODE> DB_GET_COUNT
        202     MAKE_FUNCTION                   0
        204     STORE_NAME                      21: DB_GET_COUNT
        206     LOAD_CONST                      18: <CODE> DB_GET_PARSE_DATA
        208     MAKE_FUNCTION                   0
        210     STORE_NAME                      22: DB_GET_PARSE_DATA
        212     LOAD_CONST                      19: <CODE> DB_UNION_BASE
        214     MAKE_FUNCTION                   0
        216     STORE_NAME                      23: DB_UNION_BASE
        218     LOAD_CONST                      4: None
        220     NOP                             
        222     NOP                             
        224     NOP                             
        226     JUMP_FORWARD                    19 (to 266)
        234     POP_TOP                         
        236     RETURN_CONST                    4: None
        238     PUSH_EXC_INFO                   
        240     PUSH_NULL                       
        242     LOAD_CONST                      20: '__pyarmor_exit_14669__'
        244     NOP                             
        246     LOAD_CONST                      2: b'<COAddr>\x07\x00\x00\x1a\xd4\x00\x00\x00\x00\x00\x00\x00\x00\x00\x00\x00\x00\x00\x00\x00'
        248     CALL                            1
        256     POP_TOP                         
        258     RERAISE                         0
        260     COPY                            3
        262     POP_EXCEPT                      
        264     RERAISE                         1
        266     PUSH_NULL                       
        268     LOAD_CONST                      20: '__pyarmor_exit_14669__'
        270     LOAD_CONST                      2: b'<COAddr>\x07\x00\x00\x1a\xd4\x00\x00\x00\x00\x00\x00\x00\x00\x00\x00\x00\x00\x00\x00\x00'
        272     BUILD_TUPLE                     1
        274     CALL_FUNCTION_EX                0
        276     POP_TOP                         
        278     RETURN_VALUE                    
    [Exception Table]
        26 to 218 -> 238 [0] 
        238 to 260 -> 260 [1] lasti
