#decoded by lolz.live/mrpenny / t.me/zeus_jackpot
# ================================
# Примечания по Pyarmor:
# - Байт-код и объекты кода Pyarmor соответствуют стандартному Python, но присутствуют специальные вызовы функций среды выполнения (runtime) Pyarmor.
# - Вызовы строк — это не ошибки, а маркеры, которые обрабатываются Pyarmor во время выполнения.
#
# Руководство по декомпиляции (без среды выполнения):
# 1. Игнорируйте зашифрованные байты после `#`; используйте только строку до `#`.
# 2. Удалите "__pyarmor_enter_xxx__"(b"<COAddr>...") и "__pyarmor_leave_xxx__"(b"<COAddr>...") (пролог/эпилог).
# 3. "__pyarmor_assert_xxx__"(A) не является настоящим оператором assert.
#    - Если A — это имя или читаемая строка: замените на A.
#    - Если A — это (X, "Y"): замените на X.Y.
#    - Если A — это (X, "Y", Z): замените на X.Y = Z.
#    - В противном случае: выберите наиболее подходящую/логичную замену.
# 4. "__pyarmor_bcc_xxx__"(...) указывает на машинный (нативный) код; тело функции недоступно. Добавьте комментарий.
# ================================

[Code]
    File Name: <frozen program.modules.Stories_public>
    Object Name: <module>
    Qualified Name: <module>
    Arg Count: 0
    Pos Only Arg Count: 0
    KW Only Arg Count: 0
    Stack Size: 5
    Flags: 0x20000000 (CO_PYARMOR_OBFUSCATED)
    [Names]
        '__assert_armored__'
        'eel'
        'json'
        'random'
        'spintax'
        'datetime'
        'concurrent.futures'
        'concurrent'
        'threading'
        'Thread'
        'Event'
        'multithon.sync'
        'functions'
        'types'
        'utils'
        'errors'
        'multithon.errors'
        'StopProgram'
        'program.static_classes'
        'GetLang'
        'Logs'
        'logging'
        'memory_check_switcher'
        'memory_set_pid'
        'program.telegram'
        'DelayOnline'
        'Disconnect'
        'Thread_wait'
        'account_works'
        'program.general'
        'GetConfig'
        'GetProxy'
        'StopDetect'
        'del_task_manager'
        'set_task_manager'
        'program.database'
        'db_stories_public'
        'db_stories_public_statistic'
        'db_stories_public_users'
        'func.sender'
        'TelegramMessageHelloSticker'
        'Stories_public'
        'START'
        'worker'
        'StoriesFileStat'
        'get_story_id'
        'correct_usernames_for_tag'
    [Locals+Names]
    [Constants]
        '__pyarmor_assert_14724__'
        '__pyarmor_enter_14725__'
        b'<COAddr>\x05\x00\x00\x1a\x82\x01\x00\x00\x00\x00\x00\x00\x00\x00\x00\x00\x00\x00\x00\x00'
        0
        None
        (
            'Thread'
            'Event'
        )
        (
            'functions'
            'types'
            'utils'
            'errors'
        )
        (
            'StopProgram'
        )
        (
            'GetLang'
        )
        (
            'Logs'
        )
        (
            'logging'
        )
        (
            'memory_check_switcher'
        )
        (
            'memory_set_pid'
        )
        (
            'DelayOnline'
        )
        (
            'Disconnect'
        )
        (
            'Thread_wait'
        )
        (
            'account_works'
        )
        (
            'GetConfig'
        )
        (
            'GetProxy'
        )
        (
            'StopDetect'
        )
        (
            'del_task_manager'
        )
        (
            'set_task_manager'
        )
        (
            'db_stories_public'
        )
        (
            'db_stories_public_statistic'
        )
        (
            'db_stories_public_users'
        )
        1
        (
            'TelegramMessageHelloSticker'
        )
        [Code]
            File Name: <frozen program.modules.Stories_public>
            Object Name: Stories_public
            Qualified Name: Stories_public
            Arg Count: 1
            Pos Only Arg Count: 0
            KW Only Arg Count: 0
            Stack Size: 8
            Flags: 0x20000003 (CO_OPTIMIZED | CO_NEWLOCALS | CO_PYARMOR_OBFUSCATED)
            [Names]
                'GetConfig'
                'config'
                'GetLang'
                'Lang'
                'GetProxy'
                'eel'
                'sendSuccessBox'
                'memory_check_switcher'
                'Event'
                'memory_set_pid'
                'Thread'
                'START'
                'start'
                'Logs'
                'WaitStopAnsfer'
                'UpdateLogInWindow'
                'BaseException'
                'logging'
            [Locals+Names]
                'data'
                '__assert_armored__'
                '_var_var_0'
                '_var_var_1'
                '_var_var_2'
                '_var_var_3'
            [Constants]
                None
                '__pyarmor_assert_14727__'
                '__pyarmor_enter_14728__'
                b'<COAddr>\x07\x00\x00\x1aT\x02\x00\x00\x00\x00\x00\x00\x00\x00\x00\x00\x00\x00\x00\x00'
                'program_running'   # b'\x81\xf2\n\x1c4\xe8\xbf\xdf$\xe8\x18\xceb\xe5\xf6\x82'
                '__pyarmor_exit_14729__'
                False
                (
                    'target'
                    'args'
                )
                True
                (
                    'target'
                    'args'
                    'daemon'
                )
            [Disassembly]
                0       NOP                             
                2       NOP                             
                4       PUSH_NULL                       
                6       LOAD_CONST                      2: '__pyarmor_enter_14728__'
                8       LOAD_CONST                      3: b'<COAddr>\x07\x00\x00\x1aT\x02\x00\x00\x00\x00\x00\x00\x00\x00\x00\x00\x00\x00\x00\x00'
                10      BUILD_TUPLE                     1
                12      CALL_FUNCTION_EX                0
                14      POP_TOP                         
                16      RESUME                          0
                18      NOP                             
                20      NOP                             
                22      NOP                             
                24      NOP                             
                26      NOP                             
                28      NOP                             
                30      LOAD_GLOBAL                     1: NULL + GetConfig
                40      CALL                            0
                48      STORE_GLOBAL                    1: config
                50      LOAD_GLOBAL                     5: NULL + GetLang
                60      LOAD_GLOBAL                     2: config
                70      CALL                            1
                78      STORE_GLOBAL                    3: Lang
                80      LOAD_GLOBAL                     9: NULL + GetProxy
                90      CALL                            0
                98      STORE_FAST                      2: _var_var_0
                100     LOAD_GLOBAL                     11: NULL + eel
                110     LOAD_ATTR                       12: sendSuccessBox
                130     LOAD_GLOBAL                     6: Lang
                140     PUSH_NULL                       
                142     LOAD_CONST                      1: '__pyarmor_assert_14727__'
                144     LOAD_CONST                      4: 'program_running'   # b'\x81\xf2\n\x1c4\xe8\xbf\xdf$\xe8\x18\xceb\xe5\xf6\x82'
                146     CALL                            1
                154     BINARY_SUBSCR                   
                158     CALL                            1
                166     POP_TOP                         
                168     LOAD_GLOBAL                     15: NULL + memory_check_switcher
                178     CALL                            0
                186     POP_JUMP_IF_TRUE                11 (to 210)
                188     NOP                             
                190     LOAD_CONST                      6: False
                192     NOP                             
                194     NOP                             
                196     NOP                             
                198     JUMP_FORWARD                    225 (to 650)
                206     POP_TOP                         
                208     RETURN_CONST                    6: False
                210     LOAD_GLOBAL                     17: NULL + Event
                220     CALL                            0
                228     STORE_FAST                      3: _var_var_1
                230     LOAD_GLOBAL                     19: NULL + memory_set_pid
                240     CALL                            0
                248     STORE_FAST                      4: _var_var_2
                250     LOAD_GLOBAL                     21: NULL + Thread
                260     LOAD_GLOBAL                     22: START
                270     LOAD_FAST                       0: data
                272     LOAD_GLOBAL                     2: config
                282     LOAD_FAST                       4: _var_var_2
                284     LOAD_FAST                       2: _var_var_0
                286     LOAD_FAST                       3: _var_var_1
                288     BUILD_TUPLE                     5
                290     KW_NAMES                        7: ('target', 'args')
                292     CALL                            2
                300     LOAD_ATTR                       25: start
                320     CALL                            0
                328     POP_TOP                         
                330     LOAD_GLOBAL                     21: NULL + Thread
                340     LOAD_GLOBAL                     26: Logs
                350     LOAD_ATTR                       28: WaitStopAnsfer
                370     LOAD_GLOBAL                     2: config
                380     LOAD_FAST                       4: _var_var_2
                382     LOAD_FAST                       3: _var_var_1
                384     BUILD_TUPLE                     3
                386     LOAD_CONST                      8: True
                388     KW_NAMES                        9: ('target', 'args', 'daemon')
                390     CALL                            3
                398     LOAD_ATTR                       25: start
                418     CALL                            0
                426     POP_TOP                         
                428     LOAD_GLOBAL                     21: NULL + Thread
                438     LOAD_GLOBAL                     26: Logs
                448     LOAD_ATTR                       30: UpdateLogInWindow
                468     LOAD_GLOBAL                     2: config
                478     LOAD_FAST                       4: _var_var_2
                480     LOAD_FAST                       3: _var_var_1
                482     BUILD_TUPLE                     3
                484     LOAD_CONST                      8: True
                486     KW_NAMES                        9: ('target', 'args', 'daemon')
                488     CALL                            3
                496     LOAD_ATTR                       25: start
                516     CALL                            0
                524     POP_TOP                         
                526     LOAD_CONST                      0: None
                528     NOP                             
                530     NOP                             
                532     NOP                             
                534     JUMP_FORWARD                    57 (to 650)
                542     POP_TOP                         
                544     RETURN_CONST                    0: None
                546     PUSH_EXC_INFO                   
                548     LOAD_GLOBAL                     32: BaseException
                558     CHECK_EXC_MATCH                 
                560     POP_JUMP_IF_FALSE               26 (to 614)
                562     STORE_FAST                      5: _var_var_3
                564     PUSH_NULL                       
                566     LOAD_GLOBAL                     35: NULL + logging
                576     LOAD_FAST                       5: _var_var_3
                578     CALL                            1
                586     CALL                            0
                594     POP_TOP                         
                596     POP_EXCEPT                      
                598     LOAD_CONST                      0: None
                600     STORE_FAST                      5: _var_var_3
                602     DELETE_FAST                     5: _var_var_3
                604     JUMP_BACKWARD                   40 (to 526)
                606     LOAD_CONST                      0: None
                608     STORE_FAST                      5: _var_var_3
                610     DELETE_FAST                     5: _var_var_3
                612     RERAISE                         1
                614     RERAISE                         0
                616     COPY                            3
                618     POP_EXCEPT                      
                620     RERAISE                         1
                622     PUSH_EXC_INFO                   
                624     PUSH_NULL                       
                626     LOAD_CONST                      5: '__pyarmor_exit_14729__'
                628     NOP                             
                630     LOAD_CONST                      3: b'<COAddr>\x07\x00\x00\x1aT\x02\x00\x00\x00\x00\x00\x00\x00\x00\x00\x00\x00\x00\x00\x00'
                632     CALL                            1
                640     POP_TOP                         
                642     RERAISE                         0
                644     COPY                            3
                646     POP_EXCEPT                      
                648     RERAISE                         1
                650     PUSH_NULL                       
                652     LOAD_CONST                      5: '__pyarmor_exit_14729__'
                654     LOAD_CONST                      3: b'<COAddr>\x07\x00\x00\x1aT\x02\x00\x00\x00\x00\x00\x00\x00\x00\x00\x00\x00\x00\x00\x00'
                656     BUILD_TUPLE                     1
                658     CALL_FUNCTION_EX                0
                660     POP_TOP                         
                662     RETURN_VALUE                    
            [Exception Table]
                30 to 188 -> 546 [0] 
                210 to 526 -> 546 [0] 
                546 to 564 -> 616 [1] lasti
                564 to 596 -> 606 [1] lasti
                596 to 606 -> 622 [0] 
                606 to 616 -> 616 [1] lasti
                616 to 622 -> 622 [0] 
                622 to 644 -> 644 [1] lasti
        [Code]
            File Name: <frozen program.modules.Stories_public>
            Object Name: START
            Qualified Name: START
            Arg Count: 5
            Pos Only Arg Count: 0
            KW Only Arg Count: 0
            Stack Size: 16
            Flags: 0x20000003 (CO_OPTIMIZED | CO_NEWLOCALS | CO_PYARMOR_OBFUSCATED)
            [Names]
                'is_set'
                'StopProgram'
                'isinstance'
                'list'
                'len'
                'eel'
                'sendErrorBox'
                'Lang'
                'get'
                'int'
                'datetime'
                'now'
                'strftime'
                'db_stories_public'
                'put'
                'db_stories_public_statistic'
                'create'
                'WriteResult'
                'StoriesFileStat'
                'write'
                'db_stories_public_users'
                'set_task_manager'
                'concurrent'
                'futures'
                'ThreadPoolExecutor'
                'StreamStat'
                'json'
                'dumps'
                'append'
                'submit'
                'worker'
                'as_completed'
                'BaseException'
                'logging'
                'del_task_manager'
                'StopDetect'
            [Locals+Names]
                'data'
                'config'
                'pid'
                'proxy'
                'stop_thread'
                '__assert_armored__'
                '_var_var_4'
                '_var_var_5'
                '_var_var_6'
                '_var_var_7'
                '_var_var_8'
                '_var_var_9'
                '_var_var_10'
                '_var_var_11'
                '_var_var_12'
                '_var_var_13'
                '_var_var_14'
                '_var_var_15'
                '_var_var_16'
                '_var_var_17'
                '_var_var_18'
                '_var_var_19'
                '_var_var_20'
                '_var_var_3'
            [Constants]
                None
                '__pyarmor_assert_14730__'
                '__pyarmor_enter_14731__'
                b'<COAddr>\x07\x00\x00\x1a\x96\x08\x00\x00\x00\x00\x00\x00\x00\x00\x00\x00\x00\x00\x00\x00'
                'Accounts'
                1
                'select_accounts_works'   # b'\x81\xf1\x1d\x1f6\xf9\xaa\xed\x1a\xf9\x0e\xcfy\xe2\xec\x960J\xb4\xb5\xa1\xd8'
                'Settings'
                'thread_rules'   # b'\x81\xf6\x10\x016\xfb\xba\xed\t\xef\x01\xc5\x7f'
                True
                'thread_count'   # b'\x81\xf6\x10\x016\xfb\xba\xed\x18\xf5\x18\xcex'
                'files_list'   # b'\x81\xe4\x11\x1f6\xe9\x81\xde\x12\xe9\x19'
                'select_files_works'   # b'\x81\xf1\x1d\x1f6\xf9\xaa\xed\x1d\xf3\x01\xc5\x7f\xd3\xef\x8a\x1dV\xa8'
                '%Y-%m-%d_%H-%M-%S'   # b'\x81\xa7!^v\xf7\xf3\x97\x1f\xc5H\xe8!\xa9\xd5\xc8Jn'
                'additives/stories_public/'   # b'\x81\xe3\x1c\x17:\xee\xb7\xc4\x1e\xe9B\xd3x\xe3\xea\x8c\nN\x84\xb7\xbf\xc9B\xc5\x06 '
                '_base.db'
                (
                    'files'
                )
                '_statistic.db'   # b'\x81\xdd\x0b\x072\xee\xb7\xc1\x0f\xf3\x0e\x8eh\xee'
                'Statistic'   # b"\x81\xd1\x0c\x12'\xf3\xad\xc6\x12\xf9"
                'stories_public'   # b'\x81\xf1\x0c\x1c!\xf3\xbb\xc1$\xea\x18\xc2`\xe5\xfb'
                '_stories.txt'   # b'\x81\xdd\x0b\x07<\xe8\xb7\xd7\x08\xb4\x19\xd8x'
                'Stories'
                'tag_users'   # b'\x81\xf6\x19\x14\x0c\xef\xad\xd7\t\xe9'
                '_users.db'   # b'\x81\xdd\r\x006\xe8\xad\x9c\x1f\xf8'
                'usernames'   # b'\x81\xf7\x0b\x16!\xf4\xbf\xdf\x1e\xe9'
                (
                    'users'
                )
                'Users'
                'stuff'
                (
                    'accounts'
                    'name'
                )
                (
                    'max_workers'
                )
                0
                'st_task'
                'st_stream'   # b'\x81\xf1\x0c, \xee\xac\xd7\x1a\xf7'
                'st_wait'
                'st_done'
                '__pyarmor_exit_14732__'
                'Done'
            [Disassembly]
                0       NOP                             
                2       NOP                             
                4       PUSH_NULL                       
                6       LOAD_CONST                      2: '__pyarmor_enter_14731__'
                8       LOAD_CONST                      3: b'<COAddr>\x07\x00\x00\x1a\x96\x08\x00\x00\x00\x00\x00\x00\x00\x00\x00\x00\x00\x00\x00\x00'
                10      BUILD_TUPLE                     1
                12      CALL_FUNCTION_EX                0
                14      POP_TOP                         
                16      RESUME                          0
                18      NOP                             
                20      NOP                             
                22      NOP                             
                24      NOP                             
                26      NOP                             
                28      NOP                             
                30      LOAD_FAST                       4: stop_thread
                32      LOAD_ATTR                       1: is_set
                52      CALL                            0
                60      POP_JUMP_IF_FALSE               10 (to 82)
                62      LOAD_GLOBAL                     3: NULL + StopProgram
                72      CALL                            0
                80      RAISE_VARARGS                   1
                82      LOAD_FAST                       0: data
                84      LOAD_CONST                      4: 'Accounts'
                86      BINARY_SUBSCR                   
                90      STORE_FAST                      6: _var_var_4
                92      LOAD_GLOBAL                     5: NULL + isinstance
                102     LOAD_FAST                       6: _var_var_4
                104     LOAD_GLOBAL                     6: list
                114     CALL                            2
                122     POP_JUMP_IF_TRUE                3 (to 130)
                124     LOAD_FAST                       6: _var_var_4
                126     BUILD_LIST                      1
                128     STORE_FAST                      6: _var_var_4
                130     LOAD_GLOBAL                     9: NULL + len
                140     LOAD_FAST                       6: _var_var_4
                142     CALL                            1
                150     LOAD_CONST                      5: 1
                152     COMPARE_OP                      2 (<)
                156     POP_JUMP_IF_FALSE               44 (to 246)
                158     LOAD_GLOBAL                     11: NULL + eel
                168     LOAD_ATTR                       12: sendErrorBox
                188     LOAD_GLOBAL                     14: Lang
                198     PUSH_NULL                       
                200     LOAD_CONST                      1: '__pyarmor_assert_14730__'
                202     LOAD_CONST                      6: 'select_accounts_works'   # b'\x81\xf1\x1d\x1f6\xf9\xaa\xed\x1a\xf9\x0e\xcfy\xe2\xec\x960J\xb4\xb5\xa1\xd8'
                204     CALL                            1
                212     BINARY_SUBSCR                   
                216     CALL                            1
                224     POP_TOP                         
                226     LOAD_GLOBAL                     3: NULL + StopProgram
                236     CALL                            0
                244     RAISE_VARARGS                   1
                246     LOAD_FAST                       0: data
                248     LOAD_CONST                      7: 'Settings'
                250     BINARY_SUBSCR                   
                254     LOAD_ATTR                       17: get
                274     PUSH_NULL                       
                276     LOAD_CONST                      1: '__pyarmor_assert_14730__'
                278     LOAD_CONST                      8: 'thread_rules'   # b'\x81\xf6\x10\x016\xfb\xba\xed\t\xef\x01\xc5\x7f'
                280     CALL                            1
                288     CALL                            1
                296     LOAD_CONST                      9: True
                298     COMPARE_OP                      40 (==)
                302     POP_JUMP_IF_FALSE               36 (to 376)
                304     LOAD_GLOBAL                     19: NULL + int
                314     LOAD_FAST                       0: data
                316     LOAD_CONST                      7: 'Settings'
                318     BINARY_SUBSCR                   
                322     LOAD_ATTR                       17: get
                342     PUSH_NULL                       
                344     LOAD_CONST                      1: '__pyarmor_assert_14730__'
                346     LOAD_CONST                      10: 'thread_count'   # b'\x81\xf6\x10\x016\xfb\xba\xed\x18\xf5\x18\xcex'
                348     CALL                            1
                356     CALL                            1
                364     CALL                            1
                372     STORE_FAST                      7: _var_var_5
                374     JUMP_FORWARD                    11 (to 398)
                376     LOAD_FAST                       1: config
                378     PUSH_NULL                       
                380     LOAD_CONST                      1: '__pyarmor_assert_14730__'
                382     LOAD_CONST                      10: 'thread_count'   # b'\x81\xf6\x10\x016\xfb\xba\xed\x18\xf5\x18\xcex'
                384     CALL                            1
                392     BINARY_SUBSCR                   
                396     STORE_FAST                      7: _var_var_5
                398     LOAD_FAST                       0: data
                400     LOAD_CONST                      7: 'Settings'
                402     BINARY_SUBSCR                   
                406     LOAD_ATTR                       17: get
                426     PUSH_NULL                       
                428     LOAD_CONST                      1: '__pyarmor_assert_14730__'
                430     LOAD_CONST                      11: 'files_list'   # b'\x81\xe4\x11\x1f6\xe9\x81\xde\x12\xe9\x19'
                432     CALL                            1
                440     CALL                            1
                448     STORE_FAST                      8: _var_var_6
                450     LOAD_GLOBAL                     5: NULL + isinstance
                460     LOAD_FAST                       8: _var_var_6
                462     LOAD_GLOBAL                     6: list
                472     CALL                            2
                480     POP_JUMP_IF_TRUE                3 (to 488)
                482     LOAD_FAST                       8: _var_var_6
                484     BUILD_LIST                      1
                486     STORE_FAST                      8: _var_var_6
                488     LOAD_GLOBAL                     9: NULL + len
                498     LOAD_FAST                       8: _var_var_6
                500     CALL                            1
                508     LOAD_CONST                      5: 1
                510     COMPARE_OP                      2 (<)
                514     POP_JUMP_IF_FALSE               44 (to 604)
                516     LOAD_GLOBAL                     11: NULL + eel
                526     LOAD_ATTR                       12: sendErrorBox
                546     LOAD_GLOBAL                     14: Lang
                556     PUSH_NULL                       
                558     LOAD_CONST                      1: '__pyarmor_assert_14730__'
                560     LOAD_CONST                      12: 'select_files_works'   # b'\x81\xf1\x1d\x1f6\xf9\xaa\xed\x1d\xf3\x01\xc5\x7f\xd3\xef\x8a\x1dV\xa8'
                562     CALL                            1
                570     BINARY_SUBSCR                   
                574     CALL                            1
                582     POP_TOP                         
                584     LOAD_GLOBAL                     3: NULL + StopProgram
                594     CALL                            0
                602     RAISE_VARARGS                   1
                604     LOAD_GLOBAL                     20: datetime
                614     LOAD_ATTR                       20: datetime
                634     LOAD_ATTR                       23: now
                654     CALL                            0
                662     LOAD_ATTR                       25: strftime
                682     PUSH_NULL                       
                684     LOAD_CONST                      1: '__pyarmor_assert_14730__'
                686     LOAD_CONST                      13: '%Y-%m-%d_%H-%M-%S'   # b'\x81\xa7!^v\xf7\xf3\x97\x1f\xc5H\xe8!\xa9\xd5\xc8Jn'
                688     CALL                            1
                696     CALL                            1
                704     STORE_FAST                      9: _var_var_7
                706     LOAD_GLOBAL                     27: NULL + db_stories_public
                716     PUSH_NULL                       
                718     LOAD_CONST                      1: '__pyarmor_assert_14730__'
                720     LOAD_CONST                      14: 'additives/stories_public/'   # b'\x81\xe3\x1c\x17:\xee\xb7\xc4\x1e\xe9B\xd3x\xe3\xea\x8c\nN\x84\xb7\xbf\xc9B\xc5\x06 '
                722     CALL                            1
                730     LOAD_FAST                       9: _var_var_7
                732     FORMAT_VALUE                    0 (FVC_NONE)
                734     LOAD_CONST                      15: '_base.db'
                736     BUILD_STRING                    3
                738     CALL                            1
                746     STORE_FAST                      10: _var_var_8
                748     LOAD_FAST                       10: _var_var_8
                750     LOAD_ATTR                       29: put
                770     LOAD_FAST                       8: _var_var_6
                772     KW_NAMES                        16: ('files',)
                774     CALL                            1
                782     POP_TOP                         
                784     LOAD_GLOBAL                     31: NULL + db_stories_public_statistic
                794     PUSH_NULL                       
                796     LOAD_CONST                      1: '__pyarmor_assert_14730__'
                798     LOAD_CONST                      14: 'additives/stories_public/'   # b'\x81\xe3\x1c\x17:\xee\xb7\xc4\x1e\xe9B\xd3x\xe3\xea\x8c\nN\x84\xb7\xbf\xc9B\xc5\x06 '
                800     CALL                            1
                808     LOAD_FAST                       9: _var_var_7
                810     FORMAT_VALUE                    0 (FVC_NONE)
                812     PUSH_NULL                       
                814     LOAD_CONST                      1: '__pyarmor_assert_14730__'
                816     LOAD_CONST                      17: '_statistic.db'   # b'\x81\xdd\x0b\x072\xee\xb7\xc1\x0f\xf3\x0e\x8eh\xee'
                818     CALL                            1
                826     BUILD_STRING                    3
                828     CALL                            1
                836     STORE_FAST                      11: _var_var_9
                838     LOAD_FAST                       11: _var_var_9
                840     LOAD_ATTR                       33: create
                860     CALL                            0
                868     POP_TOP                         
                870     LOAD_GLOBAL                     11: NULL + eel
                880     LOAD_ATTR                       34: WriteResult
                900     PUSH_NULL                       
                902     LOAD_CONST                      1: '__pyarmor_assert_14730__'
                904     LOAD_CONST                      18: 'Statistic'   # b"\x81\xd1\x0c\x12'\xf3\xad\xc6\x12\xf9"
                906     CALL                            1
                914     PUSH_NULL                       
                916     LOAD_CONST                      1: '__pyarmor_assert_14730__'
                918     LOAD_CONST                      19: 'stories_public'   # b'\x81\xf1\x0c\x1c!\xf3\xbb\xc1$\xea\x18\xc2`\xe5\xfb'
                920     CALL                            1
                928     LOAD_FAST                       9: _var_var_7
                930     FORMAT_VALUE                    0 (FVC_NONE)
                932     PUSH_NULL                       
                934     LOAD_CONST                      1: '__pyarmor_assert_14730__'
                936     LOAD_CONST                      17: '_statistic.db'   # b'\x81\xdd\x0b\x072\xee\xb7\xc1\x0f\xf3\x0e\x8eh\xee'
                938     CALL                            1
                946     BUILD_STRING                    2
                948     CALL                            3
                956     POP_TOP                         
                958     LOAD_GLOBAL                     37: NULL + StoriesFileStat
                968     PUSH_NULL                       
                970     LOAD_CONST                      1: '__pyarmor_assert_14730__'
                972     LOAD_CONST                      14: 'additives/stories_public/'   # b'\x81\xe3\x1c\x17:\xee\xb7\xc4\x1e\xe9B\xd3x\xe3\xea\x8c\nN\x84\xb7\xbf\xc9B\xc5\x06 '
                974     CALL                            1
                982     LOAD_FAST                       9: _var_var_7
                984     FORMAT_VALUE                    0 (FVC_NONE)
                986     PUSH_NULL                       
                988     LOAD_CONST                      1: '__pyarmor_assert_14730__'
                990     LOAD_CONST                      20: '_stories.txt'   # b'\x81\xdd\x0b\x07<\xe8\xb7\xd7\x08\xb4\x19\xd8x'
                992     CALL                            1
                1000    BUILD_STRING                    3
                1002    CALL                            1
                1010    STORE_FAST                      12: _var_var_10
                1012    LOAD_FAST                       12: _var_var_10
                1014    LOAD_ATTR                       39: write
                1034    CALL                            0
                1042    POP_TOP                         
                1044    LOAD_GLOBAL                     11: NULL + eel
                1054    LOAD_ATTR                       34: WriteResult
                1074    LOAD_CONST                      21: 'Stories'
                1076    PUSH_NULL                       
                1078    LOAD_CONST                      1: '__pyarmor_assert_14730__'
                1080    LOAD_CONST                      19: 'stories_public'   # b'\x81\xf1\x0c\x1c!\xf3\xbb\xc1$\xea\x18\xc2`\xe5\xfb'
                1082    CALL                            1
                1090    LOAD_FAST                       9: _var_var_7
                1092    FORMAT_VALUE                    0 (FVC_NONE)
                1094    PUSH_NULL                       
                1096    LOAD_CONST                      1: '__pyarmor_assert_14730__'
                1098    LOAD_CONST                      20: '_stories.txt'   # b'\x81\xdd\x0b\x07<\xe8\xb7\xd7\x08\xb4\x19\xd8x'
                1100    CALL                            1
                1108    BUILD_STRING                    2
                1110    CALL                            3
                1118    POP_TOP                         
                1120    LOAD_FAST                       0: data
                1122    LOAD_CONST                      7: 'Settings'
                1124    BINARY_SUBSCR                   
                1128    LOAD_ATTR                       17: get
                1148    PUSH_NULL                       
                1150    LOAD_CONST                      1: '__pyarmor_assert_14730__'
                1152    LOAD_CONST                      22: 'tag_users'   # b'\x81\xf6\x19\x14\x0c\xef\xad\xd7\t\xe9'
                1154    CALL                            1
                1162    CALL                            1
                1170    STORE_FAST                      13: _var_var_11
                1172    LOAD_CONST                      0: None
                1174    STORE_FAST                      14: _var_var_12
                1176    LOAD_FAST                       13: _var_var_11
                1178    POP_JUMP_IF_FALSE               107 (to 1394)
                1180    LOAD_GLOBAL                     41: NULL + db_stories_public_users
                1190    PUSH_NULL                       
                1192    LOAD_CONST                      1: '__pyarmor_assert_14730__'
                1194    LOAD_CONST                      14: 'additives/stories_public/'   # b'\x81\xe3\x1c\x17:\xee\xb7\xc4\x1e\xe9B\xd3x\xe3\xea\x8c\nN\x84\xb7\xbf\xc9B\xc5\x06 '
                1196    CALL                            1
                1204    LOAD_FAST                       9: _var_var_7
                1206    FORMAT_VALUE                    0 (FVC_NONE)
                1208    PUSH_NULL                       
                1210    LOAD_CONST                      1: '__pyarmor_assert_14730__'
                1212    LOAD_CONST                      23: '_users.db'   # b'\x81\xdd\r\x006\xe8\xad\x9c\x1f\xf8'
                1214    CALL                            1
                1222    BUILD_STRING                    3
                1224    CALL                            1
                1232    STORE_FAST                      14: _var_var_12
                1234    LOAD_FAST                       14: _var_var_12
                1236    LOAD_ATTR                       29: put
                1256    LOAD_FAST                       0: data
                1258    LOAD_CONST                      7: 'Settings'
                1260    BINARY_SUBSCR                   
                1264    LOAD_ATTR                       17: get
                1284    PUSH_NULL                       
                1286    LOAD_CONST                      1: '__pyarmor_assert_14730__'
                1288    LOAD_CONST                      24: 'usernames'   # b'\x81\xf7\x0b\x16!\xf4\xbf\xdf\x1e\xe9'
                1290    CALL                            1
                1298    CALL                            1
                1306    KW_NAMES                        25: ('users',)
                1308    CALL                            1
                1316    POP_TOP                         
                1318    LOAD_GLOBAL                     11: NULL + eel
                1328    LOAD_ATTR                       34: WriteResult
                1348    LOAD_CONST                      26: 'Users'
                1350    PUSH_NULL                       
                1352    LOAD_CONST                      1: '__pyarmor_assert_14730__'
                1354    LOAD_CONST                      19: 'stories_public'   # b'\x81\xf1\x0c\x1c!\xf3\xbb\xc1$\xea\x18\xc2`\xe5\xfb'
                1356    CALL                            1
                1364    LOAD_FAST                       9: _var_var_7
                1366    FORMAT_VALUE                    0 (FVC_NONE)
                1368    PUSH_NULL                       
                1370    LOAD_CONST                      1: '__pyarmor_assert_14730__'
                1372    LOAD_CONST                      23: '_users.db'   # b'\x81\xdd\r\x006\xe8\xad\x9c\x1f\xf8'
                1374    CALL                            1
                1382    BUILD_STRING                    2
                1384    CALL                            3
                1392    POP_TOP                         
                1394    LOAD_GLOBAL                     43: NULL + set_task_manager
                1404    LOAD_FAST                       2: pid
                1406    LOAD_FAST                       6: _var_var_4
                1408    LOAD_FAST                       0: data
                1410    LOAD_CONST                      27: 'stuff'
                1412    BINARY_SUBSCR                   
                1416    KW_NAMES                        28: ('accounts', 'name')
                1418    CALL                            3
                1426    POP_TOP                         
                1428    LOAD_GLOBAL                     44: concurrent
                1438    LOAD_ATTR                       46: futures
                1458    LOAD_ATTR                       49: ThreadPoolExecutor
                1478    LOAD_FAST                       7: _var_var_5
                1480    KW_NAMES                        29: ('max_workers',)
                1482    CALL                            1
                1490    BEFORE_WITH                     
                1492    STORE_FAST                      15: _var_var_13
                1494    BUILD_LIST                      0
                1496    STORE_FAST                      16: _var_var_14
                1498    LOAD_GLOBAL                     9: NULL + len
                1508    LOAD_FAST                       6: _var_var_4
                1510    CALL                            1
                1518    STORE_FAST                      17: _var_var_15
                1520    LOAD_FAST                       7: _var_var_5
                1522    STORE_FAST                      18: _var_var_16
                1524    LOAD_FAST                       17: _var_var_15
                1526    STORE_FAST                      19: _var_var_17
                1528    LOAD_CONST                      30: 0
                1530    STORE_FAST                      20: _var_var_18
                1532    LOAD_GLOBAL                     11: NULL + eel
                1542    LOAD_ATTR                       50: StreamStat
                1562    LOAD_GLOBAL                     53: NULL + json
                1572    LOAD_ATTR                       54: dumps
                1592    LOAD_CONST                      31: 'st_task'
                1594    LOAD_FAST                       17: _var_var_15
                1596    PUSH_NULL                       
                1598    LOAD_CONST                      1: '__pyarmor_assert_14730__'
                1600    LOAD_CONST                      32: 'st_stream'   # b'\x81\xf1\x0c, \xee\xac\xd7\x1a\xf7'
                1602    CALL                            1
                1610    LOAD_FAST                       18: _var_var_16
                1612    LOAD_CONST                      33: 'st_wait'
                1614    LOAD_FAST                       19: _var_var_17
                1616    LOAD_CONST                      34: 'st_done'
                1618    LOAD_FAST                       20: _var_var_18
                1620    BUILD_MAP                       4
                1622    CALL                            1
                1630    CALL                            1
                1638    POP_TOP                         
                1640    LOAD_FAST                       6: _var_var_4
                1642    GET_ITER                        
                1644    FOR_ITER                        47 (to 1740)
                1648    STORE_FAST                      21: _var_var_19
                1650    LOAD_FAST                       16: _var_var_14
                1652    LOAD_ATTR                       57: append
                1672    LOAD_FAST                       15: _var_var_13
                1674    LOAD_ATTR                       59: submit
                1694    LOAD_GLOBAL                     60: worker
                1704    LOAD_FAST                       21: _var_var_19
                1706    LOAD_FAST                       1: config
                1708    LOAD_FAST                       3: proxy
                1710    LOAD_FAST                       0: data
                1712    LOAD_FAST                       10: _var_var_8
                1714    LOAD_FAST                       11: _var_var_9
                1716    LOAD_FAST                       14: _var_var_12
                1718    LOAD_FAST                       12: _var_var_10
                1720    LOAD_FAST                       4: stop_thread
                1722    CALL                            10
                1730    CALL                            1
                1738    POP_TOP                         
                1740    JUMP_BACKWARD                   49 (to 1644)
                1742    END_FOR                         
                1744    LOAD_GLOBAL                     44: concurrent
                1754    LOAD_ATTR                       46: futures
                1774    LOAD_ATTR                       63: as_completed
                1794    LOAD_FAST                       16: _var_var_14
                1796    CALL                            1
                1804    GET_ITER                        
                1806    FOR_ITER                        66 (to 1940)
                1810    STORE_FAST                      22: _var_var_20
                1812    LOAD_FAST                       20: _var_var_18
                1814    LOAD_CONST                      5: 1
                1816    BINARY_OP                       13 (+=)
                1820    STORE_FAST                      20: _var_var_18
                1822    LOAD_FAST                       19: _var_var_17
                1824    LOAD_CONST                      5: 1
                1826    BINARY_OP                       23 (-=)
                1830    STORE_FAST                      19: _var_var_17
                1832    LOAD_GLOBAL                     11: NULL + eel
                1842    LOAD_ATTR                       50: StreamStat
                1862    LOAD_GLOBAL                     53: NULL + json
                1872    LOAD_ATTR                       54: dumps
                1892    LOAD_CONST                      31: 'st_task'
                1894    LOAD_FAST                       17: _var_var_15
                1896    PUSH_NULL                       
                1898    LOAD_CONST                      1: '__pyarmor_assert_14730__'
                1900    LOAD_CONST                      32: 'st_stream'   # b'\x81\xf1\x0c, \xee\xac\xd7\x1a\xf7'
                1902    CALL                            1
                1910    LOAD_FAST                       18: _var_var_16
                1912    LOAD_CONST                      33: 'st_wait'
                1914    LOAD_FAST                       19: _var_var_17
                1916    LOAD_CONST                      34: 'st_done'
                1918    LOAD_FAST                       20: _var_var_18
                1920    BUILD_MAP                       4
                1922    CALL                            1
                1930    CALL                            1
                1938    POP_TOP                         
                1940    JUMP_BACKWARD                   68 (to 1806)
                1942    END_FOR                         
                1944    NOP                             
                1946    LOAD_CONST                      0: None
                1948    LOAD_CONST                      0: None
                1950    LOAD_CONST                      0: None
                1952    CALL                            2
                1960    POP_TOP                         
                1962    LOAD_GLOBAL                     69: NULL + del_task_manager
                1972    LOAD_FAST                       2: pid
                1974    CALL                            1
                1982    POP_TOP                         
                1984    LOAD_GLOBAL                     71: NULL + StopDetect
                1994    LOAD_FAST                       4: stop_thread
                1996    CALL                            1
                2004    POP_TOP                         
                2006    NOP                             
                2008    LOAD_CONST                      36: 'Done'
                2010    NOP                             
                2012    NOP                             
                2014    NOP                             
                2016    JUMP_FORWARD                    117 (to 2252)
                2024    POP_TOP                         
                2026    RETURN_CONST                    36: 'Done'
                2028    PUSH_EXC_INFO                   
                2030    WITH_EXCEPT_START               
                2032    POP_JUMP_IF_TRUE                1 (to 2036)
                2034    RERAISE                         2
                2036    POP_TOP                         
                2038    POP_EXCEPT                      
                2040    POP_TOP                         
                2042    POP_TOP                         
                2044    JUMP_BACKWARD                   42 (to 1962)
                2046    COPY                            3
                2048    POP_EXCEPT                      
                2050    RERAISE                         1
                2052    PUSH_EXC_INFO                   
                2054    LOAD_GLOBAL                     2: StopProgram
                2064    CHECK_EXC_MATCH                 
                2066    POP_JUMP_IF_FALSE               3 (to 2074)
                2068    POP_TOP                         
                2070    POP_EXCEPT                      
                2072    JUMP_BACKWARD                   56 (to 1962)
                2074    LOAD_GLOBAL                     64: BaseException
                2084    CHECK_EXC_MATCH                 
                2086    POP_JUMP_IF_FALSE               26 (to 2140)
                2088    STORE_FAST                      23: _var_var_3
                2090    PUSH_NULL                       
                2092    LOAD_GLOBAL                     67: NULL + logging
                2102    LOAD_FAST                       23: _var_var_3
                2104    CALL                            1
                2112    CALL                            0
                2120    POP_TOP                         
                2122    POP_EXCEPT                      
                2124    LOAD_CONST                      0: None
                2126    STORE_FAST                      23: _var_var_3
                2128    DELETE_FAST                     23: _var_var_3
                2130    JUMP_BACKWARD                   85 (to 1962)
                2132    LOAD_CONST                      0: None
                2134    STORE_FAST                      23: _var_var_3
                2136    DELETE_FAST                     23: _var_var_3
                2138    RERAISE                         1
                2140    RERAISE                         0
                2142    COPY                            3
                2144    POP_EXCEPT                      
                2146    RERAISE                         1
                2148    PUSH_EXC_INFO                   
                2150    LOAD_GLOBAL                     69: NULL + del_task_manager
                2160    LOAD_FAST                       2: pid
                2162    CALL                            1
                2170    POP_TOP                         
                2172    LOAD_GLOBAL                     71: NULL + StopDetect
                2182    LOAD_FAST                       4: stop_thread
                2184    CALL                            1
                2192    POP_TOP                         
                2194    POP_TOP                         
                2196    POP_EXCEPT                      
                2198    LOAD_CONST                      36: 'Done'
                2200    NOP                             
                2202    NOP                             
                2204    NOP                             
                2206    JUMP_FORWARD                    22 (to 2252)
                2214    POP_TOP                         
                2216    RETURN_CONST                    36: 'Done'
                2218    COPY                            3
                2220    POP_EXCEPT                      
                2222    RERAISE                         1
                2224    PUSH_EXC_INFO                   
                2226    PUSH_NULL                       
                2228    LOAD_CONST                      35: '__pyarmor_exit_14732__'
                2230    NOP                             
                2232    LOAD_CONST                      3: b'<COAddr>\x07\x00\x00\x1a\x96\x08\x00\x00\x00\x00\x00\x00\x00\x00\x00\x00\x00\x00\x00\x00'
                2234    CALL                            1
                2242    POP_TOP                         
                2244    RERAISE                         0
                2246    COPY                            3
                2248    POP_EXCEPT                      
                2250    RERAISE                         1
                2252    PUSH_NULL                       
                2254    LOAD_CONST                      35: '__pyarmor_exit_14732__'
                2256    LOAD_CONST                      3: b'<COAddr>\x07\x00\x00\x1a\x96\x08\x00\x00\x00\x00\x00\x00\x00\x00\x00\x00\x00\x00\x00\x00'
                2258    BUILD_TUPLE                     1
                2260    CALL_FUNCTION_EX                0
                2262    POP_TOP                         
                2264    RETURN_VALUE                    
            [Exception Table]
                30 to 1492 -> 2052 [0] 
                1492 to 1944 -> 2028 [1] lasti
                1946 to 1962 -> 2052 [0] 
                1962 to 2006 -> 2224 [0] 
                2028 to 2038 -> 2046 [3] lasti
                2038 to 2052 -> 2052 [0] 
                2052 to 2070 -> 2142 [1] lasti
                2070 to 2074 -> 2148 [0] 
                2074 to 2090 -> 2142 [1] lasti
                2090 to 2122 -> 2132 [1] lasti
                2122 to 2132 -> 2148 [0] 
                2132 to 2142 -> 2142 [1] lasti
                2142 to 2148 -> 2148 [0] 
                2148 to 2196 -> 2218 [1] lasti
                2196 to 2198 -> 2224 [0] 
                2218 to 2224 -> 2224 [0] 
                2224 to 2246 -> 2246 [1] lasti
        [Code]
            File Name: <frozen program.modules.Stories_public>
            Object Name: worker
            Qualified Name: worker
            Arg Count: 9
            Pos Only Arg Count: 0
            KW Only Arg Count: 0
            Stack Size: 15
            Flags: 0x20000003 (CO_OPTIMIZED | CO_NEWLOCALS | CO_PYARMOR_OBFUSCATED)
            [Names]
                'Thread_wait'
                'account_works'
                'Lang'
                'Disconnect'
                'Logs'
                'PrintLog'
                'int'
                'get'
                'random'
                'randint'
                'types'
                'InputPrivacyValueAllowAll'
                'InputPrivacyValueAllowContacts'
                'get_me'
                'username'
                'ValueError'
                'TelegramMessageHelloSticker'
                'spintax'
                'spin'
                'range'
                'append'
                'len'
                'send'
                'update'
                'DelayOnline'
                'correct_usernames_for_tag'
                'endswith'
                'upload_file'
                'utils'
                'get_attributes'
                'InputMediaUploadedDocument'
                'InputMediaUploadedPhoto'
                'layer'
                'functions'
                'stories'
                'SendStoryRequest'
                'SendStoryRequest_L210'
                'get_story_id'
                'errors'
                'BadRequestError'
                'Exception'
                'insert'
                'write'
                'StopProgram'
                'BaseException'
                'logging'
            [Locals+Names]
                'account'
                'config'
                'proxy'
                'data'
                'base_files'
                'base_stat'
                'base_users'
                'text_file'
                'stop_thread'
                '__assert_armored__'
                '_var_var_21'
                '_var_var_22'
                '_var_var_23'
                '_var_var_24'
                '_var_var_25'
                '_var_var_26'
                '_var_var_27'
                '_var_var_28'
                '_var_var_11'
                '_var_var_29'
                '_var_var_30'
                '_var_var_31'
                '_var_var_32'
                '_var_var_33'
                '_var_var_34'
                '_var_var_35'
                '_var_var_36'
                '_var_var_37'
                '_var_var_38'
                '_var_var_39'
                '_var_var_40'
                '_var_var_41'
                '_var_var_42'
                '_var_var_43'
                '_var_var_44'
                '_var_var_45'
                '_var_var_46'
                '_var_var_20'
                '_var_var_47'
                '_var_var_48'
                '_var_var_49'
                '_var_var_50'
                '_var_var_51'
                '_var_var_52'
                '_var_var_53'
                '_var_var_54'
                '_var_var_55'
                '_var_var_56'
                '_var_var_3'
            [Constants]
                None
                '__pyarmor_assert_14733__'
                '__pyarmor_enter_14734__'
                b'<COAddr>\x05\x00\x00\x1a\x94\x0e\x00\x00\x00\x00\x00\x00\x00\x00\x00\x00\x00\x00\x00\x00'
                'Stories_public'   # b'\x81\xd1\x0c\x1c!\xf3\xbb\xc1$\xea\x18\xc2`\xe5\xfb'
                (
                    'module'
                )
                False
                'false'
                (
                    'account'
                    'status'
                )
                'work_account_completed'   # b'\x81\xf5\x17\x018\xc5\xbf\xd1\x18\xf5\x18\xcex\xd3\xfb\x8a\x02M\xb7\xa2\xbe\xceJ'
                (
                    'config'
                    'account'
                    'message'
                )
                'done'
                '__pyarmor_exit_14735__'
                'Settings'
                'kol_min'
                'kol_max'
                'wait_min'
                'wait_max'
                'share'
                'message'
                ''
                'option'
                'tag_users'   # b'\x81\xf6\x19\x14\x0c\xef\xad\xd7\t\xe9'
                'tag_min'
                'tag_max'
                'tag_wait_min'   # b'\x81\xf6\x19\x14\x0c\xed\xbf\xdb\x0f\xc5\x00\xc9b'
                'tag_wait_max'   # b'\x81\xf6\x19\x14\x0c\xed\xbf\xdb\x0f\xc5\x00\xc1t'
                'unic'
                True
                'all'
                'stories_set_username'   # b'\x81\xf1\x0c\x1c!\xf3\xbb\xc1$\xe9\x08\xd4S\xf9\xeb\x80\x1dS\xba\xaa\xaf'
                'stories_account_off'   # b'\x81\xf1\x0c\x1c!\xf3\xbb\xc1$\xfb\x0e\xc3c\xf9\xf6\x910R\xbd\xa1'
                'Username not set'   # b'\x81\xd7\x0b\x16!\xf4\xbf\xdf\x1e\xba\x03\xcfx\xac\xeb\x80\x1b'
                500
                (
                    'config'
                    'lang'
                    'account'
                    'client'
                    'max_flood'
                    'stop'
                )
                'Done'
                (
                    'unic'
                )
                'stories_files_empty'   # b'\x81\xf1\x0c\x1c!\xf3\xbb\xc1$\xfc\x04\xcci\xff\xc7\x80\x02M\xaf\xbe'
                'Error'
                'stories_database_empty'   # b'\x81\xf1\x0c\x1c!\xf3\xbb\xc1$\xfe\x0c\xd4m\xee\xf9\x96\nb\xbe\xaa\xba\xdfW'
                0
                'stories_no_users_for_tag'   # b'\x81\xf1\x0c\x1c!\xf3\xbb\xc1$\xf4\x02\xffy\xff\xfd\x97\x1cb\xbd\xa8\xb8\xf4Z\xcd\x02'
                'stories_prepare_users'   # b'\x81\xf1\x0c\x1c!\xf3\xbb\xc1$\xea\x1f\xc5|\xed\xea\x800H\xa8\xa2\xb8\xd8'
                (
                    'entity'
                    'delete'
                )
                'status'
                (
                    'username'
                    'status'
                )
                (
                    'config'
                    'account'
                    'message'
                    'end'
                )
                'stories_no_prepared_users'   # b'\x81\xf1\x0c\x1c!\xf3\xbb\xc1$\xf4\x02\xff|\xfe\xfd\x95\x0eO\xbe\xa3\x95\xde]\xc9\x17|'
                ' '
                'stories_public'   # b'\x81\xf1\x0c\x1c!\xf3\xbb\xc1$\xea\x18\xc2`\xe5\xfb'
                '.mp4'
                (
                    'file'
                    'mime_type'
                    'attributes'
                    'nosound_video'
                    'force_file'
                    'spoiler'
                    'stickers'
                    'ttl_seconds'
                )
                (
                    'file'
                    'spoiler'
                    'stickers'
                    'ttl_seconds'
                )
                211
                'me'
                86400
                (
                    'peer'
                    'media'
                    'privacy_rules'
                    'pinned'
                    'noforwards'
                    'fwd_modified'
                    'media_areas'
                    'caption'
                    'period'
                    'fwd_from_id'
                    'fwd_from_story'
                )
                'https://t.me/'   # b'\x81\xea\x0c\x07#\xe9\xe4\x9dT\xeeC\xcdi\xa3'
                '/s/'
                'stories_done_link'   # b'\x81\xf1\x0c\x1c!\xf3\xbb\xc1$\xfe\x02\xcei\xd3\xf4\x8c\x01V'
                'stories_error_file'   # b'\x81\xf1\x0c\x1c!\xf3\xbb\xc1$\xff\x1f\xd2c\xfe\xc7\x83\x06Q\xbe'
                (
                    'account'
                    'link'
                    'file'
                    'description'
                    'status'
                )
                1
            [Disassembly]
                0       NOP                             
                2       NOP                             
                4       PUSH_NULL                       
                6       LOAD_CONST                      2: '__pyarmor_enter_14734__'
                8       LOAD_CONST                      3: b'<COAddr>\x05\x00\x00\x1a\x94\x0e\x00\x00\x00\x00\x00\x00\x00\x00\x00\x00\x00\x00\x00\x00'
                10      BUILD_TUPLE                     1
                12      CALL_FUNCTION_EX                0
                14      POP_TOP                         
                16      RESUME                          0
                18      NOP                             
                20      NOP                             
                22      NOP                             
                24      NOP                             
                26      NOP                             
                28      NOP                             
                30      LOAD_GLOBAL                     1: NULL + Thread_wait
                40      LOAD_FAST                       3: data
                42      LOAD_FAST                       1: config
                44      LOAD_FAST                       8: stop_thread
                46      CALL                            3
                54      POP_TOP                         
                56      LOAD_GLOBAL                     3: NULL + account_works
                66      LOAD_FAST                       1: config
                68      LOAD_GLOBAL                     4: Lang
                78      LOAD_FAST                       2: proxy
                80      LOAD_FAST                       0: account
                82      LOAD_FAST                       8: stop_thread
                84      PUSH_NULL                       
                86      LOAD_CONST                      1: '__pyarmor_assert_14733__'
                88      LOAD_CONST                      4: 'Stories_public'   # b'\x81\xd1\x0c\x1c!\xf3\xbb\xc1$\xea\x18\xc2`\xe5\xfb'
                90      CALL                            1
                98      KW_NAMES                        5: ('module',)
                100     CALL                            6
                108     STORE_FAST                      10: _var_var_21
                110     LOAD_FAST                       10: _var_var_21
                112     LOAD_CONST                      6: False
                114     COMPARE_OP                      40 (==)
                118     POP_JUMP_IF_FALSE               68 (to 256)
                120     LOAD_FAST                       0: account
                122     LOAD_CONST                      7: 'false'
                124     LOAD_CONST                      8: ('account', 'status')
                126     BUILD_CONST_KEY_MAP             2
                128     LOAD_GLOBAL                     7: NULL + Disconnect
                138     LOAD_FAST                       10: _var_var_21
                140     CALL                            1
                148     POP_TOP                         
                150     LOAD_GLOBAL                     9: NULL + Logs
                160     LOAD_ATTR                       10: PrintLog
                180     LOAD_FAST                       1: config
                182     LOAD_FAST                       0: account
                184     LOAD_GLOBAL                     4: Lang
                194     PUSH_NULL                       
                196     LOAD_CONST                      1: '__pyarmor_assert_14733__'
                198     LOAD_CONST                      9: 'work_account_completed'   # b'\x81\xf5\x17\x018\xc5\xbf\xd1\x18\xf5\x18\xcex\xd3\xfb\x8a\x02M\xb7\xa2\xbe\xceJ'
                200     CALL                            1
                208     BINARY_SUBSCR                   
                212     KW_NAMES                        10: ('config', 'account', 'message')
                214     CALL                            3
                222     POP_TOP                         
                224     LOAD_FAST                       0: account
                226     LOAD_CONST                      11: 'done'
                228     LOAD_CONST                      8: ('account', 'status')
                230     BUILD_CONST_KEY_MAP             2
                232     SWAP                            2
                234     POP_TOP                         
                236     NOP                             
                238     NOP                             
                240     JUMP_FORWARD                    1771 (to 3786)
                244     CALL                            1
                252     POP_TOP                         
                254     RETURN_VALUE                    
                256     LOAD_GLOBAL                     13: NULL + int
                266     LOAD_FAST                       3: data
                268     LOAD_CONST                      13: 'Settings'
                270     BINARY_SUBSCR                   
                274     LOAD_ATTR                       15: get
                294     LOAD_CONST                      14: 'kol_min'
                296     CALL                            1
                304     CALL                            1
                312     STORE_FAST                      11: _var_var_22
                314     LOAD_GLOBAL                     13: NULL + int
                324     LOAD_FAST                       3: data
                326     LOAD_CONST                      13: 'Settings'
                328     BINARY_SUBSCR                   
                332     LOAD_ATTR                       15: get
                352     LOAD_CONST                      15: 'kol_max'
                354     CALL                            1
                362     CALL                            1
                370     STORE_FAST                      12: _var_var_23
                372     LOAD_GLOBAL                     13: NULL + int
                382     LOAD_FAST                       3: data
                384     LOAD_CONST                      13: 'Settings'
                386     BINARY_SUBSCR                   
                390     LOAD_ATTR                       15: get
                410     LOAD_CONST                      16: 'wait_min'
                412     CALL                            1
                420     CALL                            1
                428     STORE_FAST                      13: _var_var_24
                430     LOAD_GLOBAL                     13: NULL + int
                440     LOAD_FAST                       3: data
                442     LOAD_CONST                      13: 'Settings'
                444     BINARY_SUBSCR                   
                448     LOAD_ATTR                       15: get
                468     LOAD_CONST                      17: 'wait_max'
                470     CALL                            1
                478     CALL                            1
                486     STORE_FAST                      14: _var_var_25
                488     LOAD_FAST                       3: data
                490     LOAD_CONST                      13: 'Settings'
                492     BINARY_SUBSCR                   
                496     LOAD_ATTR                       15: get
                516     LOAD_CONST                      18: 'share'
                518     CALL                            1
                526     STORE_FAST                      15: _var_var_26
                528     LOAD_FAST                       3: data
                530     LOAD_CONST                      13: 'Settings'
                532     BINARY_SUBSCR                   
                536     LOAD_ATTR                       15: get
                556     LOAD_CONST                      19: 'message'
                558     LOAD_CONST                      20: ''
                560     CALL                            2
                568     STORE_FAST                      16: _var_var_27
                570     LOAD_FAST                       3: data
                572     LOAD_CONST                      13: 'Settings'
                574     BINARY_SUBSCR                   
                578     LOAD_ATTR                       15: get
                598     LOAD_CONST                      21: 'option'
                600     CALL                            1
                608     STORE_FAST                      17: _var_var_28
                610     LOAD_FAST                       3: data
                612     LOAD_CONST                      13: 'Settings'
                614     BINARY_SUBSCR                   
                618     LOAD_ATTR                       15: get
                638     PUSH_NULL                       
                640     LOAD_CONST                      1: '__pyarmor_assert_14733__'
                642     LOAD_CONST                      22: 'tag_users'   # b'\x81\xf6\x19\x14\x0c\xef\xad\xd7\t\xe9'
                644     CALL                            1
                652     CALL                            1
                660     STORE_FAST                      18: _var_var_11
                662     LOAD_GLOBAL                     13: NULL + int
                672     LOAD_FAST                       3: data
                674     LOAD_CONST                      13: 'Settings'
                676     BINARY_SUBSCR                   
                680     LOAD_ATTR                       15: get
                700     LOAD_CONST                      23: 'tag_min'
                702     CALL                            1
                710     CALL                            1
                718     STORE_FAST                      19: _var_var_29
                720     LOAD_GLOBAL                     13: NULL + int
                730     LOAD_FAST                       3: data
                732     LOAD_CONST                      13: 'Settings'
                734     BINARY_SUBSCR                   
                738     LOAD_ATTR                       15: get
                758     LOAD_CONST                      24: 'tag_max'
                760     CALL                            1
                768     CALL                            1
                776     STORE_FAST                      20: _var_var_30
                778     LOAD_GLOBAL                     13: NULL + int
                788     LOAD_FAST                       3: data
                790     LOAD_CONST                      13: 'Settings'
                792     BINARY_SUBSCR                   
                796     LOAD_ATTR                       15: get
                816     PUSH_NULL                       
                818     LOAD_CONST                      1: '__pyarmor_assert_14733__'
                820     LOAD_CONST                      25: 'tag_wait_min'   # b'\x81\xf6\x19\x14\x0c\xed\xbf\xdb\x0f\xc5\x00\xc9b'
                822     CALL                            1
                830     CALL                            1
                838     CALL                            1
                846     STORE_FAST                      21: _var_var_31
                848     LOAD_GLOBAL                     13: NULL + int
                858     LOAD_FAST                       3: data
                860     LOAD_CONST                      13: 'Settings'
                862     BINARY_SUBSCR                   
                866     LOAD_ATTR                       15: get
                886     PUSH_NULL                       
                888     LOAD_CONST                      1: '__pyarmor_assert_14733__'
                890     LOAD_CONST                      26: 'tag_wait_max'   # b'\x81\xf6\x19\x14\x0c\xed\xbf\xdb\x0f\xc5\x00\xc1t'
                892     CALL                            1
                900     CALL                            1
                908     CALL                            1
                916     STORE_FAST                      22: _var_var_32
                918     LOAD_GLOBAL                     17: NULL + random
                928     LOAD_ATTR                       18: randint
                948     LOAD_FAST                       11: _var_var_22
                950     LOAD_FAST                       12: _var_var_23
                952     CALL                            2
                960     STORE_FAST                      23: _var_var_33
                962     LOAD_CONST                      0: None
                964     STORE_FAST                      24: _var_var_34
                966     LOAD_CONST                      0: None
                968     STORE_FAST                      25: _var_var_35
                970     LOAD_FAST                       17: _var_var_28
                972     LOAD_CONST                      27: 'unic'
                974     COMPARE_OP                      40 (==)
                978     POP_JUMP_IF_FALSE               2 (to 984)
                980     LOAD_CONST                      28: True
                982     JUMP_FORWARD                    1 (to 986)
                984     LOAD_CONST                      6: False
                986     STORE_FAST                      26: _var_var_36
                988     LOAD_FAST                       15: _var_var_26
                990     LOAD_CONST                      29: 'all'
                992     COMPARE_OP                      40 (==)
                996     POP_JUMP_IF_FALSE               21 (to 1040)
                998     LOAD_GLOBAL                     21: NULL + types
                1008    LOAD_ATTR                       22: InputPrivacyValueAllowAll
                1028    CALL                            0
                1036    STORE_FAST                      27: _var_var_37
                1038    JUMP_FORWARD                    20 (to 1080)
                1040    LOAD_GLOBAL                     21: NULL + types
                1050    LOAD_ATTR                       24: InputPrivacyValueAllowContacts
                1070    CALL                            0
                1078    STORE_FAST                      27: _var_var_37
                1080    LOAD_FAST                       10: _var_var_21
                1082    LOAD_ATTR                       27: get_me
                1102    CALL                            0
                1110    STORE_FAST                      28: _var_var_38
                1112    LOAD_FAST                       28: _var_var_38
                1114    LOAD_ATTR                       28: username
                1134    POP_JUMP_IF_TRUE                91 (to 1318)
                1136    LOAD_GLOBAL                     9: NULL + Logs
                1146    LOAD_ATTR                       10: PrintLog
                1166    LOAD_FAST                       1: config
                1168    LOAD_FAST                       0: account
                1170    LOAD_GLOBAL                     4: Lang
                1180    PUSH_NULL                       
                1182    LOAD_CONST                      1: '__pyarmor_assert_14733__'
                1184    LOAD_CONST                      30: 'stories_set_username'   # b'\x81\xf1\x0c\x1c!\xf3\xbb\xc1$\xe9\x08\xd4S\xf9\xeb\x80\x1dS\xba\xaa\xaf'
                1186    CALL                            1
                1194    BINARY_SUBSCR                   
                1198    KW_NAMES                        10: ('config', 'account', 'message')
                1200    CALL                            3
                1208    POP_TOP                         
                1210    LOAD_GLOBAL                     9: NULL + Logs
                1220    LOAD_ATTR                       10: PrintLog
                1240    LOAD_FAST                       1: config
                1242    LOAD_FAST                       0: account
                1244    LOAD_GLOBAL                     4: Lang
                1254    PUSH_NULL                       
                1256    LOAD_CONST                      1: '__pyarmor_assert_14733__'
                1258    LOAD_CONST                      31: 'stories_account_off'   # b'\x81\xf1\x0c\x1c!\xf3\xbb\xc1$\xfb\x0e\xc3c\xf9\xf6\x910R\xbd\xa1'
                1260    CALL                            1
                1268    BINARY_SUBSCR                   
                1272    KW_NAMES                        10: ('config', 'account', 'message')
                1274    CALL                            3
                1282    POP_TOP                         
                1284    LOAD_GLOBAL                     31: NULL + ValueError
                1294    PUSH_NULL                       
                1296    LOAD_CONST                      1: '__pyarmor_assert_14733__'
                1298    LOAD_CONST                      32: 'Username not set'   # b'\x81\xd7\x0b\x16!\xf4\xbf\xdf\x1e\xba\x03\xcfx\xac\xeb\x80\x1b'
                1300    CALL                            1
                1308    CALL                            1
                1316    RAISE_VARARGS                   1
                1318    LOAD_FAST                       28: _var_var_38
                1320    LOAD_ATTR                       28: username
                1340    STORE_FAST                      29: _var_var_39
                1342    LOAD_GLOBAL                     33: NULL + TelegramMessageHelloSticker
                1352    LOAD_FAST                       1: config
                1354    LOAD_GLOBAL                     4: Lang
                1364    LOAD_FAST                       0: account
                1366    LOAD_FAST                       10: _var_var_21
                1368    LOAD_CONST                      33: 500
                1370    LOAD_FAST                       8: stop_thread
                1372    KW_NAMES                        34: ('config', 'lang', 'account', 'client', 'max_flood', 'stop')
                1374    CALL                            6
                1382    STORE_FAST                      30: _var_var_40
                1384    NOP                             
                1386    NOP                             
                1388    BUILD_LIST                      0
                1390    STORE_FAST                      31: _var_var_41
                1392    LOAD_GLOBAL                     35: NULL + spintax
                1402    LOAD_ATTR                       36: spin
                1422    LOAD_FAST                       16: _var_var_27
                1424    CALL                            1
                1432    STORE_FAST                      32: _var_var_42
                1434    LOAD_CONST                      0: None
                1436    STORE_FAST                      33: _var_var_43
                1438    LOAD_CONST                      35: 'Done'
                1440    STORE_FAST                      25: _var_var_35
                1442    LOAD_FAST                       4: base_files
                1444    LOAD_ATTR                       15: get
                1464    LOAD_FAST                       26: _var_var_36
                1466    KW_NAMES                        36: ('unic',)
                1468    CALL                            1
                1476    STORE_FAST                      24: _var_var_34
                1478    LOAD_FAST                       24: _var_var_34
                1480    POP_JUMP_IF_TRUE                41 (to 1564)
                1482    LOAD_GLOBAL                     9: NULL + Logs
                1492    LOAD_ATTR                       10: PrintLog
                1512    LOAD_FAST                       1: config
                1514    LOAD_FAST                       0: account
                1516    LOAD_GLOBAL                     4: Lang
                1526    PUSH_NULL                       
                1528    LOAD_CONST                      1: '__pyarmor_assert_14733__'
                1530    LOAD_CONST                      37: 'stories_files_empty'   # b'\x81\xf1\x0c\x1c!\xf3\xbb\xc1$\xfc\x04\xcci\xff\xc7\x80\x02M\xaf\xbe'
                1532    CALL                            1
                1540    BINARY_SUBSCR                   
                1544    KW_NAMES                        10: ('config', 'account', 'message')
                1546    CALL                            3
                1554    POP_TOP                         
                1556    LOAD_CONST                      38: 'Error'
                1558    STORE_FAST                      25: _var_var_35
                1560    JUMP_FORWARD                    787 (to 3138)
                1564    LOAD_FAST                       18: _var_var_11
                1566    POP_JUMP_IF_FALSE               386 (to 2342)
                1570    LOAD_GLOBAL                     17: NULL + random
                1580    LOAD_ATTR                       18: randint
                1600    LOAD_FAST                       19: _var_var_29
                1602    LOAD_FAST                       20: _var_var_30
                1604    CALL                            2
                1612    STORE_FAST                      34: _var_var_44
                1614    BUILD_LIST                      0
                1616    STORE_FAST                      35: _var_var_45
                1618    BUILD_LIST                      0
                1620    STORE_FAST                      36: _var_var_46
                1622    LOAD_GLOBAL                     39: NULL + range
                1632    LOAD_FAST                       34: _var_var_44
                1634    CALL                            1
                1642    GET_ITER                        
                1644    FOR_ITER                        76 (to 1798)
                1648    STORE_FAST                      37: _var_var_20
                1650    LOAD_FAST                       6: base_users
                1652    LOAD_ATTR                       15: get
                1672    CALL                            0
                1680    STORE_FAST                      38: _var_var_47
                1682    LOAD_FAST                       38: _var_var_47
                1684    POP_JUMP_IF_TRUE                39 (to 1764)
                1686    LOAD_GLOBAL                     9: NULL + Logs
                1696    LOAD_ATTR                       10: PrintLog
                1716    LOAD_FAST                       1: config
                1718    LOAD_FAST                       0: account
                1720    LOAD_GLOBAL                     4: Lang
                1730    PUSH_NULL                       
                1732    LOAD_CONST                      1: '__pyarmor_assert_14733__'
                1734    LOAD_CONST                      39: 'stories_database_empty'   # b'\x81\xf1\x0c\x1c!\xf3\xbb\xc1$\xfe\x0c\xd4m\xee\xf9\x96\nb\xbe\xaa\xba\xdfW'
                1736    CALL                            1
                1744    BINARY_SUBSCR                   
                1748    KW_NAMES                        10: ('config', 'account', 'message')
                1750    CALL                            3
                1758    POP_TOP                         
                1760    POP_TOP                         
                1762    JUMP_FORWARD                    19 (to 1802)
                1764    LOAD_FAST                       35: _var_var_45
                1766    LOAD_ATTR                       41: append
                1786    LOAD_FAST                       38: _var_var_47
                1788    CALL                            1
                1796    POP_TOP                         
                1798    JUMP_BACKWARD                   78 (to 1644)
                1800    END_FOR                         
                1802    LOAD_GLOBAL                     43: NULL + len
                1812    LOAD_FAST                       35: _var_var_45
                1814    CALL                            1
                1822    LOAD_CONST                      40: 0
                1824    COMPARE_OP                      40 (==)
                1828    POP_JUMP_IF_FALSE               39 (to 1908)
                1830    LOAD_GLOBAL                     9: NULL + Logs
                1840    LOAD_ATTR                       10: PrintLog
                1860    LOAD_FAST                       1: config
                1862    LOAD_FAST                       0: account
                1864    LOAD_GLOBAL                     4: Lang
                1874    PUSH_NULL                       
                1876    LOAD_CONST                      1: '__pyarmor_assert_14733__'
                1878    LOAD_CONST                      41: 'stories_no_users_for_tag'   # b'\x81\xf1\x0c\x1c!\xf3\xbb\xc1$\xf4\x02\xffy\xff\xfd\x97\x1cb\xbd\xa8\xb8\xf4Z\xcd\x02'
                1880    CALL                            1
                1888    BINARY_SUBSCR                   
                1892    KW_NAMES                        10: ('config', 'account', 'message')
                1894    CALL                            3
                1902    POP_TOP                         
                1904    JUMP_FORWARD                    615 (to 3138)
                1908    LOAD_GLOBAL                     9: NULL + Logs
                1918    LOAD_ATTR                       10: PrintLog
                1938    LOAD_FAST                       1: config
                1940    LOAD_FAST                       0: account
                1942    LOAD_GLOBAL                     4: Lang
                1952    PUSH_NULL                       
                1954    LOAD_CONST                      1: '__pyarmor_assert_14733__'
                1956    LOAD_CONST                      42: 'stories_prepare_users'   # b'\x81\xf1\x0c\x1c!\xf3\xbb\xc1$\xea\x1f\xc5|\xed\xea\x800H\xa8\xa2\xb8\xd8'
                1958    CALL                            1
                1966    BINARY_SUBSCR                   
                1970    KW_NAMES                        10: ('config', 'account', 'message')
                1972    CALL                            3
                1980    POP_TOP                         
                1982    LOAD_FAST                       35: _var_var_45
                1984    GET_ITER                        
                1986    FOR_ITER                        111 (to 2210)
                1990    STORE_FAST                      39: _var_var_48
                1992    LOAD_FAST                       30: _var_var_40
                1994    LOAD_ATTR                       45: send
                2014    LOAD_FAST                       39: _var_var_48
                2016    LOAD_CONST                      28: True
                2018    KW_NAMES                        43: ('entity', 'delete')
                2020    CALL                            2
                2028    STORE_FAST                      40: _var_var_49
                2030    LOAD_FAST                       6: base_users
                2032    LOAD_ATTR                       47: update
                2052    LOAD_FAST                       39: _var_var_48
                2054    LOAD_FAST                       40: _var_var_49
                2056    LOAD_CONST                      44: 'status'
                2058    BINARY_SUBSCR                   
                2062    KW_NAMES                        45: ('username', 'status')
                2064    CALL                            2
                2072    POP_TOP                         
                2074    LOAD_GLOBAL                     9: NULL + Logs
                2084    LOAD_ATTR                       10: PrintLog
                2104    LOAD_FAST                       1: config
                2106    LOAD_FAST                       0: account
                2108    LOAD_FAST                       39: _var_var_48
                2110    LOAD_FAST                       40: _var_var_49
                2112    LOAD_CONST                      44: 'status'
                2114    BINARY_SUBSCR                   
                2118    KW_NAMES                        46: ('config', 'account', 'message', 'end')
                2120    CALL                            4
                2128    POP_TOP                         
                2130    LOAD_FAST                       40: _var_var_49
                2132    LOAD_CONST                      44: 'status'
                2134    BINARY_SUBSCR                   
                2138    LOAD_CONST                      35: 'Done'
                2140    COMPARE_OP                      40 (==)
                2144    POP_JUMP_IF_FALSE               17 (to 2180)
                2146    LOAD_FAST                       36: _var_var_46
                2148    LOAD_ATTR                       41: append
                2168    LOAD_FAST                       39: _var_var_48
                2170    CALL                            1
                2178    POP_TOP                         
                2180    LOAD_GLOBAL                     49: NULL + DelayOnline
                2190    LOAD_FAST                       0: account
                2192    LOAD_FAST                       10: _var_var_21
                2194    LOAD_FAST                       21: _var_var_31
                2196    LOAD_FAST                       22: _var_var_32
                2198    LOAD_FAST                       8: stop_thread
                2200    CALL                            5
                2208    POP_TOP                         
                2210    JUMP_BACKWARD                   113 (to 1986)
                2212    END_FOR                         
                2214    LOAD_GLOBAL                     43: NULL + len
                2224    LOAD_FAST                       36: _var_var_46
                2226    CALL                            1
                2234    LOAD_CONST                      40: 0
                2236    COMPARE_OP                      40 (==)
                2240    POP_JUMP_IF_FALSE               39 (to 2320)
                2242    LOAD_GLOBAL                     9: NULL + Logs
                2252    LOAD_ATTR                       10: PrintLog
                2272    LOAD_FAST                       1: config
                2274    LOAD_FAST                       0: account
                2276    LOAD_GLOBAL                     4: Lang
                2286    PUSH_NULL                       
                2288    LOAD_CONST                      1: '__pyarmor_assert_14733__'
                2290    LOAD_CONST                      47: 'stories_no_prepared_users'   # b'\x81\xf1\x0c\x1c!\xf3\xbb\xc1$\xf4\x02\xff|\xfe\xfd\x95\x0eO\xbe\xa3\x95\xde]\xc9\x17|'
                2292    CALL                            1
                2300    BINARY_SUBSCR                   
                2304    KW_NAMES                        10: ('config', 'account', 'message')
                2306    CALL                            3
                2314    POP_TOP                         
                2316    JUMP_FORWARD                    409 (to 3138)
                2320    LOAD_GLOBAL                     51: NULL + correct_usernames_for_tag
                2330    LOAD_FAST                       36: _var_var_46
                2332    CALL                            1
                2340    STORE_FAST                      31: _var_var_41
                2342    LOAD_FAST                       31: _var_var_41
                2344    POP_JUMP_IF_FALSE               7 (to 2360)
                2346    LOAD_FAST                       32: _var_var_42
                2348    FORMAT_VALUE                    0 (FVC_NONE)
                2350    LOAD_CONST                      48: ' '
                2352    LOAD_FAST                       31: _var_var_41
                2354    FORMAT_VALUE                    0 (FVC_NONE)
                2356    BUILD_STRING                    3
                2358    STORE_FAST                      32: _var_var_42
                2360    LOAD_GLOBAL                     9: NULL + Logs
                2370    LOAD_ATTR                       10: PrintLog
                2390    LOAD_FAST                       1: config
                2392    LOAD_FAST                       0: account
                2394    LOAD_GLOBAL                     4: Lang
                2404    PUSH_NULL                       
                2406    LOAD_CONST                      1: '__pyarmor_assert_14733__'
                2408    LOAD_CONST                      49: 'stories_public'   # b'\x81\xf1\x0c\x1c!\xf3\xbb\xc1$\xea\x18\xc2`\xe5\xfb'
                2410    CALL                            1
                2418    BINARY_SUBSCR                   
                2422    KW_NAMES                        10: ('config', 'account', 'message')
                2424    CALL                            3
                2432    POP_TOP                         
                2434    LOAD_FAST                       24: _var_var_34
                2436    LOAD_ATTR                       53: endswith
                2456    LOAD_CONST                      50: '.mp4'
                2458    CALL                            1
                2466    POP_JUMP_IF_FALSE               71 (to 2610)
                2468    LOAD_FAST                       10: _var_var_21
                2470    LOAD_ATTR                       55: upload_file
                2490    LOAD_FAST                       24: _var_var_34
                2492    CALL                            1
                2500    STORE_FAST                      41: _var_var_50
                2502    LOAD_GLOBAL                     57: NULL + utils
                2512    LOAD_ATTR                       58: get_attributes
                2532    LOAD_FAST                       24: _var_var_34
                2534    CALL                            1
                2542    UNPACK_SEQUENCE                 2
                2546    STORE_FAST                      42: _var_var_51
                2548    STORE_FAST                      43: _var_var_52
                2550    LOAD_GLOBAL                     21: NULL + types
                2560    LOAD_ATTR                       60: InputMediaUploadedDocument
                2580    LOAD_FAST                       41: _var_var_50
                2582    LOAD_FAST                       43: _var_var_52
                2584    LOAD_FAST                       42: _var_var_51
                2586    LOAD_CONST                      6: False
                2588    LOAD_CONST                      6: False
                2590    LOAD_CONST                      6: False
                2592    BUILD_LIST                      0
                2594    LOAD_CONST                      40: 0
                2596    KW_NAMES                        51: ('file', 'mime_type', 'attributes', 'nosound_video', 'force_file', 'spoiler', 'stickers', 'ttl_seconds')
                2598    CALL                            8
                2606    STORE_FAST                      44: _var_var_53
                2608    JUMP_FORWARD                    40 (to 2690)
                2610    LOAD_GLOBAL                     21: NULL + types
                2620    LOAD_ATTR                       62: InputMediaUploadedPhoto
                2640    LOAD_FAST                       10: _var_var_21
                2642    LOAD_ATTR                       55: upload_file
                2662    LOAD_FAST                       24: _var_var_34
                2664    CALL                            1
                2672    LOAD_CONST                      6: False
                2674    BUILD_LIST                      0
                2676    LOAD_CONST                      40: 0
                2678    KW_NAMES                        52: ('file', 'spoiler', 'stickers', 'ttl_seconds')
                2680    CALL                            4
                2688    STORE_FAST                      44: _var_var_53
                2690    LOAD_FAST                       10: _var_var_21
                2692    LOAD_ATTR                       64: layer
                2712    LOAD_CONST                      53: 211
                2714    COMPARE_OP                      92 (>=)
                2718    POP_JUMP_IF_FALSE               27 (to 2774)
                2720    LOAD_GLOBAL                     66: functions
                2730    LOAD_ATTR                       68: stories
                2750    LOAD_ATTR                       70: SendStoryRequest
                2770    STORE_FAST                      45: _var_var_54
                2772    JUMP_FORWARD                    26 (to 2826)
                2774    LOAD_GLOBAL                     66: functions
                2784    LOAD_ATTR                       68: stories
                2804    LOAD_ATTR                       72: SendStoryRequest_L210
                2824    STORE_FAST                      45: _var_var_54
                2826    PUSH_NULL                       
                2828    LOAD_FAST                       10: _var_var_21
                2830    PUSH_NULL                       
                2832    LOAD_FAST                       45: _var_var_54
                2834    LOAD_CONST                      54: 'me'
                2836    LOAD_FAST                       44: _var_var_53
                2838    LOAD_FAST                       27: _var_var_37
                2840    BUILD_LIST                      1
                2842    LOAD_CONST                      28: True
                2844    LOAD_CONST                      6: False
                2846    LOAD_CONST                      6: False
                2848    BUILD_LIST                      0
                2850    LOAD_FAST                       32: _var_var_42
                2852    LOAD_CONST                      55: 86400
                2854    LOAD_CONST                      0: None
                2856    LOAD_CONST                      0: None
                2858    KW_NAMES                        56: ('peer', 'media', 'privacy_rules', 'pinned', 'noforwards', 'fwd_modified', 'media_areas', 'caption', 'period', 'fwd_from_id', 'fwd_from_story')
                2860    CALL                            11
                2868    CALL                            1
                2876    STORE_FAST                      46: _var_var_55
                2878    LOAD_GLOBAL                     75: NULL + get_story_id
                2888    LOAD_FAST                       46: _var_var_55
                2890    CALL                            1
                2898    STORE_FAST                      47: _var_var_56
                2900    PUSH_NULL                       
                2902    LOAD_CONST                      1: '__pyarmor_assert_14733__'
                2904    LOAD_CONST                      57: 'https://t.me/'   # b'\x81\xea\x0c\x07#\xe9\xe4\x9dT\xeeC\xcdi\xa3'
                2906    CALL                            1
                2914    LOAD_FAST                       29: _var_var_39
                2916    FORMAT_VALUE                    0 (FVC_NONE)
                2918    LOAD_CONST                      58: '/s/'
                2920    LOAD_FAST                       47: _var_var_56
                2922    FORMAT_VALUE                    0 (FVC_NONE)
                2924    BUILD_STRING                    4
                2926    STORE_FAST                      33: _var_var_43
                2928    LOAD_GLOBAL                     9: NULL + Logs
                2938    LOAD_ATTR                       10: PrintLog
                2958    LOAD_FAST                       1: config
                2960    LOAD_FAST                       0: account
                2962    LOAD_GLOBAL                     4: Lang
                2972    PUSH_NULL                       
                2974    LOAD_CONST                      1: '__pyarmor_assert_14733__'
                2976    LOAD_CONST                      59: 'stories_done_link'   # b'\x81\xf1\x0c\x1c!\xf3\xbb\xc1$\xfe\x02\xcei\xd3\xf4\x8c\x01V'
                2978    CALL                            1
                2986    BINARY_SUBSCR                   
                2990    LOAD_FAST                       33: _var_var_43
                2992    KW_NAMES                        46: ('config', 'account', 'message', 'end')
                2994    CALL                            4
                3002    POP_TOP                         
                3004    LOAD_FAST                       5: base_stat
                3006    LOAD_ATTR                       83: insert
                3026    LOAD_FAST                       0: account
                3028    LOAD_FAST_CHECK                 33: _var_var_43
                3030    LOAD_FAST                       24: _var_var_34
                3032    LOAD_FAST_CHECK                 32: _var_var_42
                3034    LOAD_FAST                       25: _var_var_35
                3036    KW_NAMES                        61: ('account', 'link', 'file', 'description', 'status')
                3038    CALL                            5
                3046    POP_TOP                         
                3048    LOAD_FAST                       7: text_file
                3050    LOAD_ATTR                       85: write
                3070    LOAD_FAST                       33: _var_var_43
                3072    CALL                            1
                3080    POP_TOP                         
                3082    LOAD_FAST                       23: _var_var_33
                3084    LOAD_CONST                      62: 1
                3086    BINARY_OP                       23 (-=)
                3090    STORE_FAST                      23: _var_var_33
                3092    LOAD_FAST                       23: _var_var_33
                3094    LOAD_CONST                      40: 0
                3096    COMPARE_OP                      26 (<=)
                3100    POP_JUMP_IF_FALSE               1 (to 3104)
                3102    JUMP_FORWARD                    17 (to 3138)
                3104    LOAD_GLOBAL                     49: NULL + DelayOnline
                3114    LOAD_FAST                       0: account
                3116    LOAD_FAST                       10: _var_var_21
                3118    LOAD_FAST                       13: _var_var_24
                3120    LOAD_FAST                       14: _var_var_25
                3122    LOAD_FAST                       8: stop_thread
                3124    CALL                            5
                3132    POP_TOP                         
                3134    JUMP_BACKWARD                   876 (to 1386)
                3138    LOAD_GLOBAL                     7: NULL + Disconnect
                3148    LOAD_FAST_CHECK                 10: _var_var_21
                3150    CALL                            1
                3158    POP_TOP                         
                3160    LOAD_GLOBAL                     9: NULL + Logs
                3170    LOAD_ATTR                       10: PrintLog
                3190    LOAD_FAST                       1: config
                3192    LOAD_FAST                       0: account
                3194    LOAD_GLOBAL                     4: Lang
                3204    PUSH_NULL                       
                3206    LOAD_CONST                      1: '__pyarmor_assert_14733__'
                3208    LOAD_CONST                      9: 'work_account_completed'   # b'\x81\xf5\x17\x018\xc5\xbf\xd1\x18\xf5\x18\xcex\xd3\xfb\x8a\x02M\xb7\xa2\xbe\xceJ'
                3210    CALL                            1
                3218    BINARY_SUBSCR                   
                3222    KW_NAMES                        10: ('config', 'account', 'message')
                3224    CALL                            3
                3232    POP_TOP                         
                3234    LOAD_FAST                       0: account
                3236    LOAD_CONST                      11: 'done'
                3238    LOAD_CONST                      8: ('account', 'status')
                3240    BUILD_CONST_KEY_MAP             2
                3242    NOP                             
                3244    NOP                             
                3246    JUMP_FORWARD                    268 (to 3786)
                3250    CALL                            1
                3258    POP_TOP                         
                3260    RETURN_VALUE                    
                3262    PUSH_EXC_INFO                   
                3264    POP_TOP                         
                3266    POP_EXCEPT                      
                3268    JUMP_BACKWARD                   1561 (to 150)
                3272    COPY                            3
                3274    POP_EXCEPT                      
                3276    RERAISE                         1
                3278    PUSH_EXC_INFO                   
                3280    LOAD_GLOBAL                     76: errors
                3290    LOAD_ATTR                       78: BadRequestError
                3310    CHECK_EXC_MATCH                 
                3312    POP_JUMP_IF_FALSE               42 (to 3398)
                3314    POP_TOP                         
                3316    LOAD_GLOBAL                     9: NULL + Logs
                3326    LOAD_ATTR                       10: PrintLog
                3346    LOAD_FAST                       1: config
                3348    LOAD_FAST                       0: account
                3350    LOAD_GLOBAL                     4: Lang
                3360    PUSH_NULL                       
                3362    LOAD_CONST                      1: '__pyarmor_assert_14733__'
                3364    LOAD_CONST                      60: 'stories_error_file'   # b'\x81\xf1\x0c\x1c!\xf3\xbb\xc1$\xff\x1f\xd2c\xfe\xc7\x83\x06Q\xbe'
                3366    CALL                            1
                3374    BINARY_SUBSCR                   
                3378    KW_NAMES                        10: ('config', 'account', 'message')
                3380    CALL                            3
                3388    POP_TOP                         
                3390    LOAD_FAST_CHECK                 48: _var_var_3
                3392    STORE_FAST                      25: _var_var_35
                3394    POP_EXCEPT                      
                3396    JUMP_BACKWARD                   197 (to 3004)
                3398    LOAD_GLOBAL                     80: Exception
                3408    CHECK_EXC_MATCH                 
                3410    POP_JUMP_IF_FALSE               36 (to 3484)
                3412    STORE_FAST                      48: _var_var_3
                3414    LOAD_GLOBAL                     9: NULL + Logs
                3424    LOAD_ATTR                       10: PrintLog
                3444    LOAD_FAST                       1: config
                3446    LOAD_FAST                       0: account
                3448    LOAD_FAST                       48: _var_var_3
                3450    KW_NAMES                        10: ('config', 'account', 'message')
                3452    CALL                            3
                3460    POP_TOP                         
                3462    LOAD_FAST                       48: _var_var_3
                3464    STORE_FAST                      25: _var_var_35
                3466    POP_EXCEPT                      
                3468    LOAD_CONST                      0: None
                3470    STORE_FAST                      48: _var_var_3
                3472    DELETE_FAST                     48: _var_var_3
                3474    JUMP_BACKWARD                   236 (to 3004)
                3476    LOAD_CONST                      0: None
                3478    STORE_FAST                      48: _var_var_3
                3480    DELETE_FAST                     48: _var_var_3
                3482    RERAISE                         1
                3484    RERAISE                         0
                3486    COPY                            3
                3488    POP_EXCEPT                      
                3490    RERAISE                         1
                3492    PUSH_EXC_INFO                   
                3494    LOAD_GLOBAL                     86: StopProgram
                3504    CHECK_EXC_MATCH                 
                3506    POP_JUMP_IF_FALSE               3 (to 3514)
                3508    POP_TOP                         
                3510    POP_EXCEPT                      
                3512    JUMP_BACKWARD                   188 (to 3138)
                3514    LOAD_GLOBAL                     88: BaseException
                3524    CHECK_EXC_MATCH                 
                3526    POP_JUMP_IF_FALSE               26 (to 3580)
                3528    STORE_FAST                      48: _var_var_3
                3530    PUSH_NULL                       
                3532    LOAD_GLOBAL                     91: NULL + logging
                3542    LOAD_FAST                       48: _var_var_3
                3544    CALL                            1
                3552    CALL                            0
                3560    POP_TOP                         
                3562    POP_EXCEPT                      
                3564    LOAD_CONST                      0: None
                3566    STORE_FAST                      48: _var_var_3
                3568    DELETE_FAST                     48: _var_var_3
                3570    JUMP_BACKWARD                   217 (to 3138)
                3572    LOAD_CONST                      0: None
                3574    STORE_FAST                      48: _var_var_3
                3576    DELETE_FAST                     48: _var_var_3
                3578    RERAISE                         1
                3580    RERAISE                         0
                3582    COPY                            3
                3584    POP_EXCEPT                      
                3586    RERAISE                         1
                3588    PUSH_EXC_INFO                   
                3590    POP_TOP                         
                3592    POP_EXCEPT                      
                3594    JUMP_BACKWARD                   218 (to 3160)
                3596    COPY                            3
                3598    POP_EXCEPT                      
                3600    RERAISE                         1
                3602    PUSH_EXC_INFO                   
                3604    LOAD_GLOBAL                     7: NULL + Disconnect
                3614    LOAD_FAST_CHECK                 10: _var_var_21
                3616    CALL                            1
                3624    POP_TOP                         
                3626    JUMP_FORWARD                    7 (to 3642)
                3628    PUSH_EXC_INFO                   
                3630    POP_TOP                         
                3632    POP_EXCEPT                      
                3634    JUMP_FORWARD                    3 (to 3642)
                3636    COPY                            3
                3638    POP_EXCEPT                      
                3640    RERAISE                         1
                3642    LOAD_GLOBAL                     9: NULL + Logs
                3652    LOAD_ATTR                       10: PrintLog
                3672    LOAD_FAST                       1: config
                3674    LOAD_FAST                       0: account
                3676    LOAD_GLOBAL                     4: Lang
                3686    PUSH_NULL                       
                3688    LOAD_CONST                      1: '__pyarmor_assert_14733__'
                3690    LOAD_CONST                      9: 'work_account_completed'   # b'\x81\xf5\x17\x018\xc5\xbf\xd1\x18\xf5\x18\xcex\xd3\xfb\x8a\x02M\xb7\xa2\xbe\xceJ'
                3692    CALL                            1
                3700    BINARY_SUBSCR                   
                3704    KW_NAMES                        10: ('config', 'account', 'message')
                3706    CALL                            3
                3714    POP_TOP                         
                3716    LOAD_FAST                       0: account
                3718    LOAD_CONST                      11: 'done'
                3720    LOAD_CONST                      8: ('account', 'status')
                3722    BUILD_CONST_KEY_MAP             2
                3724    SWAP                            2
                3726    POP_TOP                         
                3728    SWAP                            2
                3730    POP_EXCEPT                      
                3732    NOP                             
                3734    NOP                             
                3736    NOP                             
                3738    JUMP_FORWARD                    23 (to 3786)
                3740    CALL                            1
                3748    POP_TOP                         
                3750    RETURN_VALUE                    
                3752    COPY                            3
                3754    POP_EXCEPT                      
                3756    RERAISE                         1
                3758    PUSH_EXC_INFO                   
                3760    PUSH_NULL                       
                3762    LOAD_CONST                      12: '__pyarmor_exit_14735__'
                3764    NOP                             
                3766    LOAD_CONST                      3: b'<COAddr>\x05\x00\x00\x1a\x94\x0e\x00\x00\x00\x00\x00\x00\x00\x00\x00\x00\x00\x00\x00\x00'
                3768    CALL                            1
                3776    POP_TOP                         
                3778    RERAISE                         0
                3780    COPY                            3
                3782    POP_EXCEPT                      
                3784    RERAISE                         1
                3786    PUSH_NULL                       
                3788    LOAD_CONST                      12: '__pyarmor_exit_14735__'
                3790    LOAD_CONST                      3: b'<COAddr>\x05\x00\x00\x1a\x94\x0e\x00\x00\x00\x00\x00\x00\x00\x00\x00\x00\x00\x00\x00\x00'
                3792    BUILD_TUPLE                     1
                3794    CALL_FUNCTION_EX                0
                3796    POP_TOP                         
                3798    RETURN_VALUE                    
            [Exception Table]
                30 to 128 -> 3492 [0] 
                128 to 150 -> 3262 [1] 
                150 to 236 -> 3758 [0] 
                256 to 1386 -> 3492 [0] 
                1388 to 1560 -> 3278 [0] 
                1560 to 1564 -> 3492 [0] 
                1564 to 1904 -> 3278 [0] 
                1904 to 1908 -> 3492 [0] 
                1908 to 2316 -> 3278 [0] 
                2316 to 2320 -> 3492 [0] 
                2320 to 3004 -> 3278 [0] 
                3004 to 3138 -> 3492 [0] 
                3138 to 3160 -> 3588 [0] 
                3160 to 3242 -> 3758 [0] 
                3262 to 3266 -> 3272 [2] lasti
                3266 to 3278 -> 3758 [0] 
                3278 to 3394 -> 3486 [1] lasti
                3394 to 3398 -> 3492 [0] 
                3398 to 3414 -> 3486 [1] lasti
                3414 to 3466 -> 3476 [1] lasti
                3466 to 3476 -> 3492 [0] 
                3476 to 3486 -> 3486 [1] lasti
                3486 to 3492 -> 3492 [0] 
                3492 to 3510 -> 3582 [1] lasti
                3510 to 3514 -> 3602 [0] 
                3514 to 3530 -> 3582 [1] lasti
                3530 to 3562 -> 3572 [1] lasti
                3562 to 3572 -> 3602 [0] 
                3572 to 3582 -> 3582 [1] lasti
                3582 to 3588 -> 3602 [0] 
                3588 to 3592 -> 3596 [1] lasti
                3592 to 3602 -> 3758 [0] 
                3602 to 3604 -> 3752 [1] lasti
                3604 to 3626 -> 3628 [2] 
                3626 to 3628 -> 3752 [1] lasti
                3628 to 3632 -> 3636 [3] lasti
                3632 to 3730 -> 3752 [1] lasti
                3730 to 3732 -> 3758 [0] 
                3752 to 3758 -> 3758 [0] 
                3758 to 3780 -> 3780 [1] lasti
        [Code]
            File Name: <frozen program.modules.Stories_public>
            Object Name: StoriesFileStat
            Qualified Name: StoriesFileStat
            Arg Count: 0
            Pos Only Arg Count: 0
            KW Only Arg Count: 0
            Stack Size: 5
            Flags: 0x20000000 (CO_PYARMOR_OBFUSCATED)
            [Names]
                '__name__'
                '__module__'
                '__qualname__'
                '__assert_armored__'
                'str'
                '__init__'
                'write'
            [Locals+Names]
            [Constants]
                'StoriesFileStat'
                '__pyarmor_assert_14736__'
                '__pyarmor_enter_14737__'
                b'<COAddr>\x07\x00\x00".\x00\x00\x00\x00\x00\x00\x00\x00\x00\x00\x00\x00\x00\x00\x00'
                'path'
                'return'
                None
                [Code]
                    File Name: <frozen program.modules.Stories_public>
                    Object Name: __init__
                    Qualified Name: StoriesFileStat.__init__
                    Arg Count: 2
                    Pos Only Arg Count: 0
                    KW Only Arg Count: 0
                    Stack Size: 5
                    Flags: 0x20000003 (CO_OPTIMIZED | CO_NEWLOCALS | CO_PYARMOR_OBFUSCATED)
                    [Names]
                        'path'
                    [Locals+Names]
                        'self'
                        'path'
                        '__assert_armored__'
                    [Constants]
                        None
                        '__pyarmor_assert_14739__'
                        '__pyarmor_enter_14740__'
                        b'<COAddr>\x07\x00\x00\x1a$\x00\x00\x00\x00\x00\x00\x00\x00\x00\x00\x00\x00\x00\x00\x00'
                        '__pyarmor_exit_14741__'
                    [Disassembly]
                        0       NOP                             
                        2       NOP                             
                        4       PUSH_NULL                       
                        6       LOAD_CONST                      2: '__pyarmor_enter_14740__'
                        8       LOAD_CONST                      3: b'<COAddr>\x07\x00\x00\x1a$\x00\x00\x00\x00\x00\x00\x00\x00\x00\x00\x00\x00\x00\x00\x00'
                        10      BUILD_TUPLE                     1
                        12      CALL_FUNCTION_EX                0
                        14      POP_TOP                         
                        16      RESUME                          0
                        18      NOP                             
                        20      NOP                             
                        22      NOP                             
                        24      NOP                             
                        26      NOP                             
                        28      LOAD_FAST                       1: path
                        30      LOAD_FAST                       0: self
                        32      STORE_ATTR                      0: path
                        42      LOAD_CONST                      0: None
                        44      NOP                             
                        46      NOP                             
                        48      NOP                             
                        50      JUMP_FORWARD                    19 (to 90)
                        58      POP_TOP                         
                        60      RETURN_CONST                    0: None
                        62      PUSH_EXC_INFO                   
                        64      PUSH_NULL                       
                        66      LOAD_CONST                      4: '__pyarmor_exit_14741__'
                        68      NOP                             
                        70      LOAD_CONST                      3: b'<COAddr>\x07\x00\x00\x1a$\x00\x00\x00\x00\x00\x00\x00\x00\x00\x00\x00\x00\x00\x00\x00'
                        72      CALL                            1
                        80      POP_TOP                         
                        82      RERAISE                         0
                        84      COPY                            3
                        86      POP_EXCEPT                      
                        88      RERAISE                         1
                        90      PUSH_NULL                       
                        92      LOAD_CONST                      4: '__pyarmor_exit_14741__'
                        94      LOAD_CONST                      3: b'<COAddr>\x07\x00\x00\x1a$\x00\x00\x00\x00\x00\x00\x00\x00\x00\x00\x00\x00\x00\x00\x00'
                        96      BUILD_TUPLE                     1
                        98      CALL_FUNCTION_EX                0
                        100     POP_TOP                         
                        102     RETURN_VALUE                    
                    [Exception Table]
                        28 to 42 -> 62 [0] 
                        62 to 84 -> 84 [1] lasti
                [Code]
                    File Name: <frozen program.modules.Stories_public>
                    Object Name: write
                    Qualified Name: StoriesFileStat.write
                    Arg Count: 2
                    Pos Only Arg Count: 0
                    KW Only Arg Count: 0
                    Stack Size: 6
                    Flags: 0x20000003 (CO_OPTIMIZED | CO_NEWLOCALS | CO_PYARMOR_OBFUSCATED)
                    [Names]
                        'open'
                        'path'
                        'write'
                    [Locals+Names]
                        'self'
                        'text'
                        '__assert_armored__'
                        '_var_var_57'
                    [Constants]
                        None
                        '__pyarmor_assert_14742__'
                        '__pyarmor_enter_14743__'
                        b'<COAddr>\x05\x00\x00\x1a\xbc\x00\x00\x00\x00\x00\x00\x00\x00\x00\x00\x00\x00\x00\x00\x00'
                        'a'
                        '\n'
                        ''
                        '__pyarmor_exit_14744__'
                    [Disassembly]
                        0       NOP                             
                        2       NOP                             
                        4       PUSH_NULL                       
                        6       LOAD_CONST                      2: '__pyarmor_enter_14743__'
                        8       LOAD_CONST                      3: b'<COAddr>\x05\x00\x00\x1a\xbc\x00\x00\x00\x00\x00\x00\x00\x00\x00\x00\x00\x00\x00\x00\x00'
                        10      BUILD_TUPLE                     1
                        12      CALL_FUNCTION_EX                0
                        14      POP_TOP                         
                        16      RESUME                          0
                        18      NOP                             
                        20      NOP                             
                        22      NOP                             
                        24      NOP                             
                        26      NOP                             
                        28      LOAD_GLOBAL                     1: NULL + open
                        38      LOAD_FAST                       0: self
                        40      LOAD_ATTR                       2: path
                        60      LOAD_CONST                      4: 'a'
                        62      CALL                            2
                        70      BEFORE_WITH                     
                        72      STORE_FAST                      3: _var_var_57
                        74      LOAD_FAST                       1: text
                        76      POP_JUMP_IF_FALSE               21 (to 120)
                        78      LOAD_FAST                       3: _var_var_57
                        80      LOAD_ATTR                       5: write
                        100     LOAD_FAST                       1: text
                        102     FORMAT_VALUE                    0 (FVC_NONE)
                        104     LOAD_CONST                      5: '\n'
                        106     BUILD_STRING                    2
                        108     CALL                            1
                        116     POP_TOP                         
                        118     JUMP_FORWARD                    17 (to 154)
                        120     LOAD_FAST                       3: _var_var_57
                        122     LOAD_ATTR                       5: write
                        142     LOAD_CONST                      6: ''
                        144     CALL                            1
                        152     POP_TOP                         
                        154     LOAD_CONST                      0: None
                        156     LOAD_CONST                      0: None
                        158     LOAD_CONST                      0: None
                        160     CALL                            2
                        168     POP_TOP                         
                        170     LOAD_CONST                      0: None
                        172     NOP                             
                        174     NOP                             
                        176     NOP                             
                        178     JUMP_FORWARD                    31 (to 242)
                        186     POP_TOP                         
                        188     RETURN_CONST                    0: None
                        190     PUSH_EXC_INFO                   
                        192     WITH_EXCEPT_START               
                        194     POP_JUMP_IF_TRUE                1 (to 198)
                        196     RERAISE                         2
                        198     POP_TOP                         
                        200     POP_EXCEPT                      
                        202     POP_TOP                         
                        204     POP_TOP                         
                        206     JUMP_BACKWARD                   19 (to 170)
                        208     COPY                            3
                        210     POP_EXCEPT                      
                        212     RERAISE                         1
                        214     PUSH_EXC_INFO                   
                        216     PUSH_NULL                       
                        218     LOAD_CONST                      7: '__pyarmor_exit_14744__'
                        220     NOP                             
                        222     LOAD_CONST                      3: b'<COAddr>\x05\x00\x00\x1a\xbc\x00\x00\x00\x00\x00\x00\x00\x00\x00\x00\x00\x00\x00\x00\x00'
                        224     CALL                            1
                        232     POP_TOP                         
                        234     RERAISE                         0
                        236     COPY                            3
                        238     POP_EXCEPT                      
                        240     RERAISE                         1
                        242     PUSH_NULL                       
                        244     LOAD_CONST                      7: '__pyarmor_exit_14744__'
                        246     LOAD_CONST                      3: b'<COAddr>\x05\x00\x00\x1a\xbc\x00\x00\x00\x00\x00\x00\x00\x00\x00\x00\x00\x00\x00\x00\x00'
                        248     BUILD_TUPLE                     1
                        250     CALL_FUNCTION_EX                0
                        252     POP_TOP                         
                        254     RETURN_VALUE                    
                    [Exception Table]
                        28 to 72 -> 214 [0] 
                        72 to 154 -> 190 [1] lasti
                        154 to 170 -> 214 [0] 
                        190 to 200 -> 208 [3] lasti
                        200 to 214 -> 214 [0] 
                        214 to 236 -> 236 [1] lasti
                '__pyarmor_exit_14738__'
                (
                    None
                )
            [Disassembly]
                0       NOP                             
                2       LOAD_NAME                       0: __name__
                4       STORE_NAME                      1: __module__
                6       LOAD_CONST                      0: 'StoriesFileStat'
                8       STORE_NAME                      2: __qualname__
                10      NOP                             
                12      PUSH_NULL                       
                14      LOAD_CONST                      2: '__pyarmor_enter_14737__'
                16      LOAD_CONST                      3: b'<COAddr>\x07\x00\x00".\x00\x00\x00\x00\x00\x00\x00\x00\x00\x00\x00\x00\x00\x00\x00'
                18      BUILD_TUPLE                     1
                20      CALL_FUNCTION_EX                0
                22      POP_TOP                         
                24      RESUME                          0
                26      NOP                             
                28      NOP                             
                30      NOP                             
                32      NOP                             
                34      NOP                             
                36      LOAD_CONST                      4: 'path'
                38      LOAD_NAME                       4: str
                40      LOAD_CONST                      5: 'return'
                42      LOAD_CONST                      6: None
                44      BUILD_TUPLE                     4
                46      LOAD_CONST                      7: <CODE> __init__
                48      MAKE_FUNCTION                   4
                50      STORE_NAME                      5: __init__
                52      LOAD_CONST                      10: (None,)
                54      LOAD_CONST                      8: <CODE> write
                56      MAKE_FUNCTION                   1
                58      STORE_NAME                      6: write
                60      LOAD_CONST                      6: None
                62      NOP                             
                64      NOP                             
                66      NOP                             
                68      JUMP_FORWARD                    19 (to 108)
                76      POP_TOP                         
                78      RETURN_CONST                    6: None
                80      PUSH_EXC_INFO                   
                82      PUSH_NULL                       
                84      LOAD_CONST                      9: '__pyarmor_exit_14738__'
                86      NOP                             
                88      LOAD_CONST                      3: b'<COAddr>\x07\x00\x00".\x00\x00\x00\x00\x00\x00\x00\x00\x00\x00\x00\x00\x00\x00\x00'
                90      CALL                            1
                98      POP_TOP                         
                100     RERAISE                         0
                102     COPY                            3
                104     POP_EXCEPT                      
                106     RERAISE                         1
                108     PUSH_NULL                       
                110     LOAD_CONST                      9: '__pyarmor_exit_14738__'
                112     LOAD_CONST                      3: b'<COAddr>\x07\x00\x00".\x00\x00\x00\x00\x00\x00\x00\x00\x00\x00\x00\x00\x00\x00\x00'
                114     BUILD_TUPLE                     1
                116     CALL_FUNCTION_EX                0
                118     POP_TOP                         
                120     RETURN_VALUE                    
            [Exception Table]
                36 to 60 -> 80 [0] 
                80 to 102 -> 102 [1] lasti
        'StoriesFileStat'
        [Code]
            File Name: <frozen program.modules.Stories_public>
            Object Name: get_story_id
            Qualified Name: get_story_id
            Arg Count: 1
            Pos Only Arg Count: 0
            KW Only Arg Count: 0
            Stack Size: 5
            Flags: 0x20000003 (CO_OPTIMIZED | CO_NEWLOCALS | CO_PYARMOR_OBFUSCATED)
            [Names]
                'hasattr'
                'updates'
                'isinstance'
                'types'
                'UpdateStory'
                'story'
                'id'
                'UpdateStoryID'
            [Locals+Names]
                'response'
                '__assert_armored__'
                '_var_var_56'
                '_var_var_58'
            [Constants]
                None
                '__pyarmor_assert_14745__'
                '__pyarmor_enter_14746__'
                b'<COAddr>\x07\x00\x00\x1a\n\x01\x00\x00\x00\x00\x00\x00\x00\x00\x00\x00\x00\x00\x00\x00'
                'updates'
                '__pyarmor_exit_14747__'
            [Disassembly]
                0       NOP                             
                2       NOP                             
                4       PUSH_NULL                       
                6       LOAD_CONST                      2: '__pyarmor_enter_14746__'
                8       LOAD_CONST                      3: b'<COAddr>\x07\x00\x00\x1a\n\x01\x00\x00\x00\x00\x00\x00\x00\x00\x00\x00\x00\x00\x00\x00'
                10      BUILD_TUPLE                     1
                12      CALL_FUNCTION_EX                0
                14      POP_TOP                         
                16      RESUME                          0
                18      NOP                             
                20      NOP                             
                22      NOP                             
                24      NOP                             
                26      NOP                             
                28      LOAD_CONST                      0: None
                30      STORE_FAST                      2: _var_var_56
                32      LOAD_GLOBAL                     1: NULL + hasattr
                42      LOAD_FAST                       0: response
                44      LOAD_CONST                      4: 'updates'
                46      CALL                            2
                54      POP_JUMP_IF_FALSE               107 (to 270)
                56      LOAD_FAST                       0: response
                58      LOAD_ATTR                       2: updates
                78      GET_ITER                        
                80      FOR_ITER                        92 (to 266)
                84      STORE_FAST                      3: _var_var_58
                86      LOAD_GLOBAL                     5: NULL + isinstance
                96      LOAD_FAST                       3: _var_var_58
                98      LOAD_GLOBAL                     6: types
                108     LOAD_ATTR                       8: UpdateStory
                128     CALL                            2
                136     POP_JUMP_IF_FALSE               24 (to 186)
                138     LOAD_FAST                       3: _var_var_58
                140     LOAD_ATTR                       10: story
                160     LOAD_ATTR                       12: id
                180     STORE_FAST                      2: _var_var_56
                182     POP_TOP                         
                184     JUMP_FORWARD                    42 (to 270)
                186     LOAD_GLOBAL                     5: NULL + isinstance
                196     LOAD_FAST                       3: _var_var_58
                198     LOAD_GLOBAL                     6: types
                208     LOAD_ATTR                       14: UpdateStoryID
                228     CALL                            2
                236     POP_JUMP_IF_TRUE                1 (to 240)
                238     JUMP_BACKWARD                   80 (to 80)
                240     LOAD_FAST                       3: _var_var_58
                242     LOAD_ATTR                       12: id
                262     STORE_FAST                      2: _var_var_56
                264     POP_TOP                         
                266     JUMP_FORWARD                    1 (to 270)
                268     END_FOR                         
                270     LOAD_FAST                       2: _var_var_56
                272     NOP                             
                274     NOP                             
                276     NOP                             
                278     JUMP_FORWARD                    20 (to 320)
                280     CALL                            1
                288     POP_TOP                         
                290     RETURN_VALUE                    
                292     PUSH_EXC_INFO                   
                294     PUSH_NULL                       
                296     LOAD_CONST                      5: '__pyarmor_exit_14747__'
                298     NOP                             
                300     LOAD_CONST                      3: b'<COAddr>\x07\x00\x00\x1a\n\x01\x00\x00\x00\x00\x00\x00\x00\x00\x00\x00\x00\x00\x00\x00'
                302     CALL                            1
                310     POP_TOP                         
                312     RERAISE                         0
                314     COPY                            3
                316     POP_EXCEPT                      
                318     RERAISE                         1
                320     PUSH_NULL                       
                322     LOAD_CONST                      5: '__pyarmor_exit_14747__'
                324     LOAD_CONST                      3: b'<COAddr>\x07\x00\x00\x1a\n\x01\x00\x00\x00\x00\x00\x00\x00\x00\x00\x00\x00\x00\x00\x00'
                326     BUILD_TUPLE                     1
                328     CALL_FUNCTION_EX                0
                330     POP_TOP                         
                332     RETURN_VALUE                    
            [Exception Table]
                28 to 238 -> 292 [0] 
                240 to 272 -> 292 [0] 
                292 to 314 -> 314 [1] lasti
        [Code]
            File Name: <frozen program.modules.Stories_public>
            Object Name: correct_usernames_for_tag
            Qualified Name: correct_usernames_for_tag
            Arg Count: 1
            Pos Only Arg Count: 0
            KW Only Arg Count: 0
            Stack Size: 5
            Flags: 0x20000003 (CO_OPTIMIZED | CO_NEWLOCALS | CO_PYARMOR_OBFUSCATED)
            [Names]
            [Locals+Names]
                'users'
                '__assert_armored__'
                '_var_var_49'
                '_var_var_47'
            [Constants]
                None
                '__pyarmor_assert_14748__'
                '__pyarmor_enter_14749__'
                b'<COAddr>\x05\x00\x00\x1a<\x00\x00\x00\x00\x00\x00\x00\x00\x00\x00\x00\x00\x00\x00\x00'
                ''
                '@'
                ' '
                '__pyarmor_exit_14750__'
            [Disassembly]
                0       NOP                             
                2       NOP                             
                4       PUSH_NULL                       
                6       LOAD_CONST                      2: '__pyarmor_enter_14749__'
                8       LOAD_CONST                      3: b'<COAddr>\x05\x00\x00\x1a<\x00\x00\x00\x00\x00\x00\x00\x00\x00\x00\x00\x00\x00\x00\x00'
                10      BUILD_TUPLE                     1
                12      CALL_FUNCTION_EX                0
                14      POP_TOP                         
                16      RESUME                          0
                18      NOP                             
                20      NOP                             
                22      NOP                             
                24      NOP                             
                26      NOP                             
                28      LOAD_CONST                      4: ''
                30      STORE_FAST                      2: _var_var_49
                32      LOAD_FAST                       0: users
                34      GET_ITER                        
                36      FOR_ITER                        11 (to 60)
                40      STORE_FAST                      3: _var_var_47
                42      LOAD_FAST                       2: _var_var_49
                44      LOAD_CONST                      5: '@'
                46      LOAD_FAST                       3: _var_var_47
                48      FORMAT_VALUE                    0 (FVC_NONE)
                50      LOAD_CONST                      6: ' '
                52      BUILD_STRING                    3
                54      BINARY_OP                       13 (+=)
                58      STORE_FAST                      2: _var_var_49
                60      JUMP_BACKWARD                   13 (to 36)
                62      END_FOR                         
                64      LOAD_FAST                       2: _var_var_49
                66      NOP                             
                68      NOP                             
                70      NOP                             
                72      JUMP_FORWARD                    20 (to 114)
                74      CALL                            1
                82      POP_TOP                         
                84      RETURN_VALUE                    
                86      PUSH_EXC_INFO                   
                88      PUSH_NULL                       
                90      LOAD_CONST                      7: '__pyarmor_exit_14750__'
                92      NOP                             
                94      LOAD_CONST                      3: b'<COAddr>\x05\x00\x00\x1a<\x00\x00\x00\x00\x00\x00\x00\x00\x00\x00\x00\x00\x00\x00\x00'
                96      CALL                            1
                104     POP_TOP                         
                106     RERAISE                         0
                108     COPY                            3
                110     POP_EXCEPT                      
                112     RERAISE                         1
                114     PUSH_NULL                       
                116     LOAD_CONST                      7: '__pyarmor_exit_14750__'
                118     LOAD_CONST                      3: b'<COAddr>\x05\x00\x00\x1a<\x00\x00\x00\x00\x00\x00\x00\x00\x00\x00\x00\x00\x00\x00\x00'
                120     BUILD_TUPLE                     1
                122     CALL_FUNCTION_EX                0
                124     POP_TOP                         
                126     RETURN_VALUE                    
            [Exception Table]
                28 to 66 -> 86 [0] 
                86 to 108 -> 108 [1] lasti
        '__pyarmor_exit_14726__'
    [Disassembly]
        0       NOP                             
        2       NOP                             
        4       PUSH_NULL                       
        6       LOAD_CONST                      1: '__pyarmor_enter_14725__'
        8       LOAD_CONST                      2: b'<COAddr>\x05\x00\x00\x1a\x82\x01\x00\x00\x00\x00\x00\x00\x00\x00\x00\x00\x00\x00\x00\x00'
        10      BUILD_TUPLE                     1
        12      CALL_FUNCTION_EX                0
        14      POP_TOP                         
        16      RESUME                          0
        18      NOP                             
        20      NOP                             
        22      NOP                             
        24      NOP                             
        26      LOAD_CONST                      3: 0
        28      LOAD_CONST                      4: None
        30      IMPORT_NAME                     1: eel
        32      STORE_NAME                      1: eel
        34      LOAD_CONST                      3: 0
        36      LOAD_CONST                      4: None
        38      IMPORT_NAME                     2: json
        40      STORE_NAME                      2: json
        42      LOAD_CONST                      3: 0
        44      LOAD_CONST                      4: None
        46      IMPORT_NAME                     3: random
        48      STORE_NAME                      3: random
        50      LOAD_CONST                      3: 0
        52      LOAD_CONST                      4: None
        54      IMPORT_NAME                     4: spintax
        56      STORE_NAME                      4: spintax
        58      LOAD_CONST                      3: 0
        60      LOAD_CONST                      4: None
        62      IMPORT_NAME                     5: datetime
        64      STORE_NAME                      5: datetime
        66      LOAD_CONST                      3: 0
        68      LOAD_CONST                      4: None
        70      IMPORT_NAME                     6: concurrent.futures
        72      STORE_NAME                      7: concurrent
        74      LOAD_CONST                      3: 0
        76      LOAD_CONST                      5: ('Thread', 'Event')
        78      IMPORT_NAME                     8: threading
        80      IMPORT_FROM                     9: Thread
        82      STORE_NAME                      9: Thread
        84      IMPORT_FROM                     10: Event
        86      STORE_NAME                      10: Event
        88      POP_TOP                         
        90      LOAD_CONST                      3: 0
        92      LOAD_CONST                      6: ('functions', 'types', 'utils', 'errors')
        94      IMPORT_NAME                     11: multithon.sync
        96      IMPORT_FROM                     12: functions
        98      STORE_NAME                      12: functions
        100     IMPORT_FROM                     13: types
        102     STORE_NAME                      13: types
        104     IMPORT_FROM                     14: utils
        106     STORE_NAME                      14: utils
        108     IMPORT_FROM                     15: errors
        110     STORE_NAME                      15: errors
        112     POP_TOP                         
        114     LOAD_CONST                      3: 0
        116     LOAD_CONST                      7: ('StopProgram',)
        118     IMPORT_NAME                     16: multithon.errors
        120     IMPORT_FROM                     17: StopProgram
        122     STORE_NAME                      17: StopProgram
        124     POP_TOP                         
        126     LOAD_CONST                      3: 0
        128     LOAD_CONST                      8: ('GetLang',)
        130     IMPORT_NAME                     18: program.static_classes
        132     IMPORT_FROM                     19: GetLang
        134     STORE_NAME                      19: GetLang
        136     POP_TOP                         
        138     LOAD_CONST                      3: 0
        140     LOAD_CONST                      9: ('Logs',)
        142     IMPORT_NAME                     18: program.static_classes
        144     IMPORT_FROM                     20: Logs
        146     STORE_NAME                      20: Logs
        148     POP_TOP                         
        150     LOAD_CONST                      3: 0
        152     LOAD_CONST                      10: ('logging',)
        154     IMPORT_NAME                     18: program.static_classes
        156     IMPORT_FROM                     21: logging
        158     STORE_NAME                      21: logging
        160     POP_TOP                         
        162     LOAD_CONST                      3: 0
        164     LOAD_CONST                      11: ('memory_check_switcher',)
        166     IMPORT_NAME                     18: program.static_classes
        168     IMPORT_FROM                     22: memory_check_switcher
        170     STORE_NAME                      22: memory_check_switcher
        172     POP_TOP                         
        174     LOAD_CONST                      3: 0
        176     LOAD_CONST                      12: ('memory_set_pid',)
        178     IMPORT_NAME                     18: program.static_classes
        180     IMPORT_FROM                     23: memory_set_pid
        182     STORE_NAME                      23: memory_set_pid
        184     POP_TOP                         
        186     LOAD_CONST                      3: 0
        188     LOAD_CONST                      13: ('DelayOnline',)
        190     IMPORT_NAME                     24: program.telegram
        192     IMPORT_FROM                     25: DelayOnline
        194     STORE_NAME                      25: DelayOnline
        196     POP_TOP                         
        198     LOAD_CONST                      3: 0
        200     LOAD_CONST                      14: ('Disconnect',)
        202     IMPORT_NAME                     24: program.telegram
        204     IMPORT_FROM                     26: Disconnect
        206     STORE_NAME                      26: Disconnect
        208     POP_TOP                         
        210     LOAD_CONST                      3: 0
        212     LOAD_CONST                      15: ('Thread_wait',)
        214     IMPORT_NAME                     24: program.telegram
        216     IMPORT_FROM                     27: Thread_wait
        218     STORE_NAME                      27: Thread_wait
        220     POP_TOP                         
        222     LOAD_CONST                      3: 0
        224     LOAD_CONST                      16: ('account_works',)
        226     IMPORT_NAME                     24: program.telegram
        228     IMPORT_FROM                     28: account_works
        230     STORE_NAME                      28: account_works
        232     POP_TOP                         
        234     LOAD_CONST                      3: 0
        236     LOAD_CONST                      17: ('GetConfig',)
        238     IMPORT_NAME                     29: program.general
        240     IMPORT_FROM                     30: GetConfig
        242     STORE_NAME                      30: GetConfig
        244     POP_TOP                         
        246     LOAD_CONST                      3: 0
        248     LOAD_CONST                      18: ('GetProxy',)
        250     IMPORT_NAME                     29: program.general
        252     IMPORT_FROM                     31: GetProxy
        254     STORE_NAME                      31: GetProxy
        256     POP_TOP                         
        258     LOAD_CONST                      3: 0
        260     LOAD_CONST                      19: ('StopDetect',)
        262     IMPORT_NAME                     29: program.general
        264     IMPORT_FROM                     32: StopDetect
        266     STORE_NAME                      32: StopDetect
        268     POP_TOP                         
        270     LOAD_CONST                      3: 0
        272     LOAD_CONST                      20: ('del_task_manager',)
        274     IMPORT_NAME                     29: program.general
        276     IMPORT_FROM                     33: del_task_manager
        278     STORE_NAME                      33: del_task_manager
        280     POP_TOP                         
        282     LOAD_CONST                      3: 0
        284     LOAD_CONST                      21: ('set_task_manager',)
        286     IMPORT_NAME                     29: program.general
        288     IMPORT_FROM                     34: set_task_manager
        290     STORE_NAME                      34: set_task_manager
        292     POP_TOP                         
        294     LOAD_CONST                      3: 0
        296     LOAD_CONST                      22: ('db_stories_public',)
        298     IMPORT_NAME                     35: program.database
        300     IMPORT_FROM                     36: db_stories_public
        302     STORE_NAME                      36: db_stories_public
        304     POP_TOP                         
        306     LOAD_CONST                      3: 0
        308     LOAD_CONST                      23: ('db_stories_public_statistic',)
        310     IMPORT_NAME                     35: program.database
        312     IMPORT_FROM                     37: db_stories_public_statistic
        314     STORE_NAME                      37: db_stories_public_statistic
        316     POP_TOP                         
        318     LOAD_CONST                      3: 0
        320     LOAD_CONST                      24: ('db_stories_public_users',)
        322     IMPORT_NAME                     35: program.database
        324     IMPORT_FROM                     38: db_stories_public_users
        326     STORE_NAME                      38: db_stories_public_users
        328     POP_TOP                         
        330     LOAD_CONST                      25: 1
        332     LOAD_CONST                      26: ('TelegramMessageHelloSticker',)
        334     IMPORT_NAME                     39: func.sender
        336     IMPORT_FROM                     40: TelegramMessageHelloSticker
        338     STORE_NAME                      40: TelegramMessageHelloSticker
        340     POP_TOP                         
        342     LOAD_CONST                      27: <CODE> Stories_public
        344     MAKE_FUNCTION                   0
        346     STORE_NAME                      41: Stories_public
        348     LOAD_CONST                      28: <CODE> START
        350     MAKE_FUNCTION                   0
        352     STORE_NAME                      42: START
        354     LOAD_CONST                      29: <CODE> worker
        356     MAKE_FUNCTION                   0
        358     STORE_NAME                      43: worker
        360     PUSH_NULL                       
        362     LOAD_BUILD_CLASS                
        364     LOAD_CONST                      30: <CODE> StoriesFileStat
        366     MAKE_FUNCTION                   0
        368     LOAD_CONST                      31: 'StoriesFileStat'
        370     CALL                            2
        378     STORE_NAME                      44: StoriesFileStat
        380     LOAD_CONST                      32: <CODE> get_story_id
        382     MAKE_FUNCTION                   0
        384     STORE_NAME                      45: get_story_id
        386     LOAD_CONST                      33: <CODE> correct_usernames_for_tag
        388     MAKE_FUNCTION                   0
        390     STORE_NAME                      46: correct_usernames_for_tag
        392     LOAD_CONST                      4: None
        394     NOP                             
        396     NOP                             
        398     NOP                             
        400     JUMP_FORWARD                    19 (to 440)
        408     POP_TOP                         
        410     RETURN_CONST                    4: None
        412     PUSH_EXC_INFO                   
        414     PUSH_NULL                       
        416     LOAD_CONST                      34: '__pyarmor_exit_14726__'
        418     NOP                             
        420     LOAD_CONST                      2: b'<COAddr>\x05\x00\x00\x1a\x82\x01\x00\x00\x00\x00\x00\x00\x00\x00\x00\x00\x00\x00\x00\x00'
        422     CALL                            1
        430     POP_TOP                         
        432     RERAISE                         0
        434     COPY                            3
        436     POP_EXCEPT                      
        438     RERAISE                         1
        440     PUSH_NULL                       
        442     LOAD_CONST                      34: '__pyarmor_exit_14726__'
        444     LOAD_CONST                      2: b'<COAddr>\x05\x00\x00\x1a\x82\x01\x00\x00\x00\x00\x00\x00\x00\x00\x00\x00\x00\x00\x00\x00'
        446     BUILD_TUPLE                     1
        448     CALL_FUNCTION_EX                0
        450     POP_TOP                         
        452     RETURN_VALUE                    
    [Exception Table]
        26 to 392 -> 412 [0] 
        412 to 434 -> 434 [1] lasti
