#decoded by lolz.live/mrpenny / t.me/zeus_jackpot
# ================================
# Примечания по Pyarmor:
# - Байт-код и объекты кода Pyarmor соответствуют стандартному Python, но присутствуют специальные вызовы функций среды выполнения (runtime) Pyarmor.
# - Вызовы строк — это не ошибки, а маркеры, которые обрабатываются Pyarmor во время выполнения.
#
# Руководство по декомпиляции (без среды выполнения):
# 1. Игнорируйте зашифрованные байты после `#`; используйте только строку до `#`.
# 2. Удалите "__pyarmor_enter_xxx__"(b"<COAddr>...") и "__pyarmor_leave_xxx__"(b"<COAddr>...") (пролог/эпилог).
# 3. "__pyarmor_assert_xxx__"(A) не является настоящим оператором assert.
#    - Если A — это имя или читаемая строка: замените на A.
#    - Если A — это (X, "Y"): замените на X.Y.
#    - Если A — это (X, "Y", Z): замените на X.Y = Z.
#    - В противном случае: выберите наиболее подходящую/логичную замену.
# 4. "__pyarmor_bcc_xxx__"(...) указывает на машинный (нативный) код; тело функции недоступно. Добавьте комментарий.
# ================================

[Code]
    File Name: <frozen program.modules.Unsubscribe>
    Object Name: <module>
    Qualified Name: <module>
    Arg Count: 0
    Pos Only Arg Count: 0
    KW Only Arg Count: 0
    Stack Size: 5
    Flags: 0x20000000 (CO_PYARMOR_OBFUSCATED)
    [Names]
        '__assert_armored__'
        'eel'
        'json'
        'random'
        'sqlite3'
        'datetime'
        'concurrent.futures'
        'concurrent'
        'threading'
        'Thread'
        'Event'
        'multithon.sync'
        'functions'
        'types'
        'errors'
        'multithon.errors'
        'StopProgram'
        'program.static_classes'
        'GetLang'
        'Logs'
        'logging'
        'memory_check_switcher'
        'memory_set_pid'
        'program.telegram'
        'DelayOnline'
        'Disconnect'
        'Thread_wait'
        'account_works'
        'program.general'
        'GetConfig'
        'GetProxy'
        'StopDetect'
        'check_get_settings'
        'del_task_manager'
        'set_task_manager'
        'Unsubscribe'
        'START'
        'DB_CREATE_RESULT'
        'DB_SET_STATISTIC'
        'EntityCorrectGroup'
        'Unsubscribes'
    [Locals+Names]
    [Constants]
        '__pyarmor_assert_14790__'
        '__pyarmor_enter_14791__'
        b'<COAddr>\x07\x00\x00\x1aP\x01\x00\x00\x00\x00\x00\x00\x00\x00\x00\x00\x00\x00\x00\x00'
        0
        None
        (
            'Thread'
            'Event'
        )
        (
            'functions'
            'types'
            'errors'
        )
        (
            'StopProgram'
        )
        (
            'GetLang'
        )
        (
            'Logs'
        )
        (
            'logging'
        )
        (
            'memory_check_switcher'
        )
        (
            'memory_set_pid'
        )
        (
            'DelayOnline'
        )
        (
            'Disconnect'
        )
        (
            'Thread_wait'
        )
        (
            'account_works'
        )
        (
            'GetConfig'
        )
        (
            'GetProxy'
        )
        (
            'StopDetect'
        )
        (
            'check_get_settings'
        )
        (
            'del_task_manager'
        )
        (
            'set_task_manager'
        )
        [Code]
            File Name: <frozen program.modules.Unsubscribe>
            Object Name: Unsubscribe
            Qualified Name: Unsubscribe
            Arg Count: 1
            Pos Only Arg Count: 0
            KW Only Arg Count: 0
            Stack Size: 8
            Flags: 0x20000003 (CO_OPTIMIZED | CO_NEWLOCALS | CO_PYARMOR_OBFUSCATED)
            [Names]
                'GetConfig'
                'config'
                'GetLang'
                'Lang'
                'GetProxy'
                'eel'
                'sendSuccessBox'
                'memory_check_switcher'
                'Event'
                'memory_set_pid'
                'Thread'
                'START'
                'start'
                'Logs'
                'WaitStopAnsfer'
                'UpdateLogInWindow'
                'BaseException'
                'logging'
            [Locals+Names]
                'data'
                '__assert_armored__'
                '_var_var_0'
                '_var_var_1'
                '_var_var_2'
                '_var_var_3'
            [Constants]
                None
                '__pyarmor_assert_14793__'
                '__pyarmor_enter_14794__'
                b'<COAddr>\x05\x00\x00\x1aT\x02\x00\x00\x00\x00\x00\x00\x00\x00\x00\x00\x00\x00\x00\x00'
                'program_running'   # b'\x81\xf2\n\x1c4\xe8\xbf\xdf$\xe8\x18\xceb\xe5\xf6\x82'
                '__pyarmor_exit_14795__'
                False
                (
                    'target'
                    'args'
                )
                True
                (
                    'target'
                    'args'
                    'daemon'
                )
            [Disassembly]
                0       NOP                             
                2       NOP                             
                4       PUSH_NULL                       
                6       LOAD_CONST                      2: '__pyarmor_enter_14794__'
                8       LOAD_CONST                      3: b'<COAddr>\x05\x00\x00\x1aT\x02\x00\x00\x00\x00\x00\x00\x00\x00\x00\x00\x00\x00\x00\x00'
                10      BUILD_TUPLE                     1
                12      CALL_FUNCTION_EX                0
                14      POP_TOP                         
                16      RESUME                          0
                18      NOP                             
                20      NOP                             
                22      NOP                             
                24      NOP                             
                26      NOP                             
                28      NOP                             
                30      LOAD_GLOBAL                     1: NULL + GetConfig
                40      CALL                            0
                48      STORE_GLOBAL                    1: config
                50      LOAD_GLOBAL                     5: NULL + GetLang
                60      LOAD_GLOBAL                     2: config
                70      CALL                            1
                78      STORE_GLOBAL                    3: Lang
                80      LOAD_GLOBAL                     9: NULL + GetProxy
                90      CALL                            0
                98      STORE_FAST                      2: _var_var_0
                100     LOAD_GLOBAL                     11: NULL + eel
                110     LOAD_ATTR                       12: sendSuccessBox
                130     LOAD_GLOBAL                     6: Lang
                140     PUSH_NULL                       
                142     LOAD_CONST                      1: '__pyarmor_assert_14793__'
                144     LOAD_CONST                      4: 'program_running'   # b'\x81\xf2\n\x1c4\xe8\xbf\xdf$\xe8\x18\xceb\xe5\xf6\x82'
                146     CALL                            1
                154     BINARY_SUBSCR                   
                158     CALL                            1
                166     POP_TOP                         
                168     LOAD_GLOBAL                     15: NULL + memory_check_switcher
                178     CALL                            0
                186     POP_JUMP_IF_TRUE                11 (to 210)
                188     NOP                             
                190     LOAD_CONST                      6: False
                192     NOP                             
                194     NOP                             
                196     NOP                             
                198     JUMP_FORWARD                    225 (to 650)
                206     POP_TOP                         
                208     RETURN_CONST                    6: False
                210     LOAD_GLOBAL                     17: NULL + Event
                220     CALL                            0
                228     STORE_FAST                      3: _var_var_1
                230     LOAD_GLOBAL                     19: NULL + memory_set_pid
                240     CALL                            0
                248     STORE_FAST                      4: _var_var_2
                250     LOAD_GLOBAL                     21: NULL + Thread
                260     LOAD_GLOBAL                     22: START
                270     LOAD_FAST                       0: data
                272     LOAD_GLOBAL                     2: config
                282     LOAD_FAST                       4: _var_var_2
                284     LOAD_FAST                       2: _var_var_0
                286     LOAD_FAST                       3: _var_var_1
                288     BUILD_TUPLE                     5
                290     KW_NAMES                        7: ('target', 'args')
                292     CALL                            2
                300     LOAD_ATTR                       25: start
                320     CALL                            0
                328     POP_TOP                         
                330     LOAD_GLOBAL                     21: NULL + Thread
                340     LOAD_GLOBAL                     26: Logs
                350     LOAD_ATTR                       28: WaitStopAnsfer
                370     LOAD_GLOBAL                     2: config
                380     LOAD_FAST                       4: _var_var_2
                382     LOAD_FAST                       3: _var_var_1
                384     BUILD_TUPLE                     3
                386     LOAD_CONST                      8: True
                388     KW_NAMES                        9: ('target', 'args', 'daemon')
                390     CALL                            3
                398     LOAD_ATTR                       25: start
                418     CALL                            0
                426     POP_TOP                         
                428     LOAD_GLOBAL                     21: NULL + Thread
                438     LOAD_GLOBAL                     26: Logs
                448     LOAD_ATTR                       30: UpdateLogInWindow
                468     LOAD_GLOBAL                     2: config
                478     LOAD_FAST                       4: _var_var_2
                480     LOAD_FAST                       3: _var_var_1
                482     BUILD_TUPLE                     3
                484     LOAD_CONST                      8: True
                486     KW_NAMES                        9: ('target', 'args', 'daemon')
                488     CALL                            3
                496     LOAD_ATTR                       25: start
                516     CALL                            0
                524     POP_TOP                         
                526     LOAD_CONST                      0: None
                528     NOP                             
                530     NOP                             
                532     NOP                             
                534     JUMP_FORWARD                    57 (to 650)
                542     POP_TOP                         
                544     RETURN_CONST                    0: None
                546     PUSH_EXC_INFO                   
                548     LOAD_GLOBAL                     32: BaseException
                558     CHECK_EXC_MATCH                 
                560     POP_JUMP_IF_FALSE               26 (to 614)
                562     STORE_FAST                      5: _var_var_3
                564     PUSH_NULL                       
                566     LOAD_GLOBAL                     35: NULL + logging
                576     LOAD_FAST                       5: _var_var_3
                578     CALL                            1
                586     CALL                            0
                594     POP_TOP                         
                596     POP_EXCEPT                      
                598     LOAD_CONST                      0: None
                600     STORE_FAST                      5: _var_var_3
                602     DELETE_FAST                     5: _var_var_3
                604     JUMP_BACKWARD                   40 (to 526)
                606     LOAD_CONST                      0: None
                608     STORE_FAST                      5: _var_var_3
                610     DELETE_FAST                     5: _var_var_3
                612     RERAISE                         1
                614     RERAISE                         0
                616     COPY                            3
                618     POP_EXCEPT                      
                620     RERAISE                         1
                622     PUSH_EXC_INFO                   
                624     PUSH_NULL                       
                626     LOAD_CONST                      5: '__pyarmor_exit_14795__'
                628     NOP                             
                630     LOAD_CONST                      3: b'<COAddr>\x05\x00\x00\x1aT\x02\x00\x00\x00\x00\x00\x00\x00\x00\x00\x00\x00\x00\x00\x00'
                632     CALL                            1
                640     POP_TOP                         
                642     RERAISE                         0
                644     COPY                            3
                646     POP_EXCEPT                      
                648     RERAISE                         1
                650     PUSH_NULL                       
                652     LOAD_CONST                      5: '__pyarmor_exit_14795__'
                654     LOAD_CONST                      3: b'<COAddr>\x05\x00\x00\x1aT\x02\x00\x00\x00\x00\x00\x00\x00\x00\x00\x00\x00\x00\x00\x00'
                656     BUILD_TUPLE                     1
                658     CALL_FUNCTION_EX                0
                660     POP_TOP                         
                662     RETURN_VALUE                    
            [Exception Table]
                30 to 188 -> 546 [0] 
                210 to 526 -> 546 [0] 
                546 to 564 -> 616 [1] lasti
                564 to 596 -> 606 [1] lasti
                596 to 606 -> 622 [0] 
                606 to 616 -> 616 [1] lasti
                616 to 622 -> 622 [0] 
                622 to 644 -> 644 [1] lasti
        [Code]
            File Name: <frozen program.modules.Unsubscribe>
            Object Name: START
            Qualified Name: START
            Arg Count: 5
            Pos Only Arg Count: 0
            KW Only Arg Count: 0
            Stack Size: 14
            Flags: 0x20000003 (CO_OPTIMIZED | CO_NEWLOCALS | CO_PYARMOR_OBFUSCATED)
            [Names]
                'is_set'
                'StopProgram'
                'check_get_settings'
                'get'
                'isinstance'
                'list'
                'int'
                'len'
                'eel'
                'sendErrorBox'
                'Lang'
                'Logs'
                'PrintLog'
                'LangCheck'
                'datetime'
                'now'
                'strftime'
                'DB_CREATE_RESULT'
                'WriteResult'
                'set_task_manager'
                'concurrent'
                'futures'
                'ThreadPoolExecutor'
                'StreamStat'
                'json'
                'dumps'
                'append'
                'submit'
                'Unsubscribes'
                'as_completed'
                'BaseException'
                'logging'
                'del_task_manager'
                'StopDetect'
            [Locals+Names]
                'data'
                'config'
                'pid'
                'proxy'
                'stop_thread'
                '__assert_armored__'
                '_var_var_4'
                '_var_var_5'
                '_var_var_6'
                '_var_var_7'
                '_var_var_8'
                '_var_var_9'
                '_var_var_10'
                '_var_var_11'
                '_var_var_12'
                '_var_var_13'
                '_var_var_14'
                '_var_var_15'
                '_var_var_16'
                '_var_var_3'
            [Constants]
                None
                '__pyarmor_assert_14796__'
                '__pyarmor_enter_14797__'
                b'<COAddr>\x05\x00\x00\x1a\x8c\x07\x00\x00\x00\x00\x00\x00\x00\x00\x00\x00\x00\x00\x00\x00'
                'Settings'
                'Accounts'
                1
                'select_accounts_works'   # b'\x81\xf1\x1d\x1f6\xf9\xaa\xed\x1a\xf9\x0e\xcfy\xe2\xec\x960J\xb4\xb5\xa1\xd8'
                'unsubscribe_channel'   # b'\x81\xf7\x16\x00&\xf8\xad\xd1\t\xf3\x0f\xc5S\xef\xf0\x84\x01S\xbe\xab'
                False
                'unsubscribe_group'   # b'\x81\xf7\x16\x00&\xf8\xad\xd1\t\xf3\x0f\xc5S\xeb\xea\x8a\x1aM'
                'pupsik_settings_error'   # b'\x81\xf2\r\x03 \xf3\xb5\xed\x08\xff\x19\xd4e\xe2\xff\x960X\xa9\xb5\xa5\xd9'
                (
                    'message'
                )
                'pupsik_mass_unsubscribes'   # b'\x81\xf2\r\x03 \xf3\xb5\xed\x16\xfb\x1e\xd3S\xf9\xf6\x96\x1a_\xa8\xa4\xb8\xc2L\xc9\x16'
                'thread_rules'   # b'\x81\xf6\x10\x016\xfb\xba\xed\t\xef\x01\xc5\x7f'
                True
                'thread_count'   # b'\x81\xf6\x10\x016\xfb\xba\xed\x18\xf5\x18\xcex'
                'use_stat'
                '%Y-%m-%d_%H-%M-%S'   # b'\x81\xa7!^v\xf7\xf3\x97\x1f\xc5H\xe8!\xa9\xd5\xc8Jn'
                'unsubscribe'   # b'\x81\xf7\x16\x00&\xf8\xad\xd1\t\xf3\x0f\xc5'
                "I can't create a statistics file"   # b'\x81\xcbX\x102\xf4\xf9\xc6[\xf9\x1f\xc5m\xf8\xfd\xc5\x0e\x1d\xa8\xb3\xab\xdfG\xdf\x11f\xa0O@\xb7\x17\xe9?'
                'Statistics'   # b"\x81\xd1\x0c\x12'\xf3\xad\xc6\x12\xf9\x1e"
                '.db'
                'stuff'
                (
                    'accounts'
                    'name'
                )
                (
                    'max_workers'
                )
                0
                'st_task'
                'st_stream'   # b'\x81\xf1\x0c, \xee\xac\xd7\x1a\xf7'
                'st_wait'
                'st_done'
                '__pyarmor_exit_14798__'
                'Done'
            [Disassembly]
                0       NOP                             
                2       NOP                             
                4       PUSH_NULL                       
                6       LOAD_CONST                      2: '__pyarmor_enter_14797__'
                8       LOAD_CONST                      3: b'<COAddr>\x05\x00\x00\x1a\x8c\x07\x00\x00\x00\x00\x00\x00\x00\x00\x00\x00\x00\x00\x00\x00'
                10      BUILD_TUPLE                     1
                12      CALL_FUNCTION_EX                0
                14      POP_TOP                         
                16      RESUME                          0
                18      NOP                             
                20      NOP                             
                22      NOP                             
                24      NOP                             
                26      NOP                             
                28      NOP                             
                30      LOAD_FAST                       4: stop_thread
                32      LOAD_ATTR                       1: is_set
                52      CALL                            0
                60      POP_JUMP_IF_FALSE               10 (to 82)
                62      LOAD_GLOBAL                     3: NULL + StopProgram
                72      CALL                            0
                80      RAISE_VARARGS                   1
                82      LOAD_GLOBAL                     5: NULL + check_get_settings
                92      LOAD_FAST                       0: data
                94      LOAD_ATTR                       7: get
                114     LOAD_CONST                      4: 'Settings'
                116     CALL                            1
                124     CALL                            1
                132     POP_TOP                         
                134     LOAD_FAST                       0: data
                136     LOAD_CONST                      5: 'Accounts'
                138     BINARY_SUBSCR                   
                142     STORE_FAST                      6: _var_var_4
                144     LOAD_GLOBAL                     9: NULL + isinstance
                154     LOAD_FAST                       6: _var_var_4
                156     LOAD_GLOBAL                     10: list
                166     CALL                            2
                174     POP_JUMP_IF_TRUE                3 (to 182)
                176     LOAD_FAST                       6: _var_var_4
                178     BUILD_LIST                      1
                180     STORE_FAST                      6: _var_var_4
                182     LOAD_GLOBAL                     13: NULL + int
                192     LOAD_GLOBAL                     15: NULL + len
                202     LOAD_FAST                       6: _var_var_4
                204     CALL                            1
                212     CALL                            1
                220     LOAD_CONST                      6: 1
                222     COMPARE_OP                      2 (<)
                226     POP_JUMP_IF_FALSE               44 (to 316)
                228     LOAD_GLOBAL                     17: NULL + eel
                238     LOAD_ATTR                       18: sendErrorBox
                258     LOAD_GLOBAL                     20: Lang
                268     PUSH_NULL                       
                270     LOAD_CONST                      1: '__pyarmor_assert_14796__'
                272     LOAD_CONST                      7: 'select_accounts_works'   # b'\x81\xf1\x1d\x1f6\xf9\xaa\xed\x1a\xf9\x0e\xcfy\xe2\xec\x960J\xb4\xb5\xa1\xd8'
                274     CALL                            1
                282     BINARY_SUBSCR                   
                286     CALL                            1
                294     POP_TOP                         
                296     LOAD_GLOBAL                     3: NULL + StopProgram
                306     CALL                            0
                314     RAISE_VARARGS                   1
                316     LOAD_FAST                       0: data
                318     LOAD_CONST                      4: 'Settings'
                320     BINARY_SUBSCR                   
                324     LOAD_ATTR                       7: get
                344     PUSH_NULL                       
                346     LOAD_CONST                      1: '__pyarmor_assert_14796__'
                348     LOAD_CONST                      8: 'unsubscribe_channel'   # b'\x81\xf7\x16\x00&\xf8\xad\xd1\t\xf3\x0f\xc5S\xef\xf0\x84\x01S\xbe\xab'
                350     CALL                            1
                358     CALL                            1
                366     LOAD_CONST                      9: False
                368     COMPARE_OP                      40 (==)
                372     POP_JUMP_IF_FALSE               109 (to 592)
                374     LOAD_FAST                       0: data
                376     LOAD_CONST                      4: 'Settings'
                378     BINARY_SUBSCR                   
                382     LOAD_ATTR                       7: get
                402     PUSH_NULL                       
                404     LOAD_CONST                      1: '__pyarmor_assert_14796__'
                406     LOAD_CONST                      10: 'unsubscribe_group'   # b'\x81\xf7\x16\x00&\xf8\xad\xd1\t\xf3\x0f\xc5S\xeb\xea\x8a\x1aM'
                408     CALL                            1
                416     CALL                            1
                424     LOAD_CONST                      9: False
                426     COMPARE_OP                      40 (==)
                430     POP_JUMP_IF_FALSE               80 (to 592)
                432     LOAD_GLOBAL                     23: NULL + Logs
                442     LOAD_ATTR                       24: PrintLog
                462     LOAD_GLOBAL                     20: Lang
                472     PUSH_NULL                       
                474     LOAD_CONST                      1: '__pyarmor_assert_14796__'
                476     LOAD_CONST                      11: 'pupsik_settings_error'   # b'\x81\xf2\r\x03 \xf3\xb5\xed\x08\xff\x19\xd4e\xe2\xff\x960X\xa9\xb5\xa5\xd9'
                478     CALL                            1
                486     BINARY_SUBSCR                   
                490     KW_NAMES                        12: ('message',)
                492     CALL                            1
                500     POP_TOP                         
                502     LOAD_GLOBAL                     23: NULL + Logs
                512     LOAD_ATTR                       24: PrintLog
                532     LOAD_GLOBAL                     20: Lang
                542     PUSH_NULL                       
                544     LOAD_CONST                      1: '__pyarmor_assert_14796__'
                546     LOAD_CONST                      13: 'pupsik_mass_unsubscribes'   # b'\x81\xf2\r\x03 \xf3\xb5\xed\x16\xfb\x1e\xd3S\xf9\xf6\x96\x1a_\xa8\xa4\xb8\xc2L\xc9\x16'
                548     CALL                            1
                556     BINARY_SUBSCR                   
                560     KW_NAMES                        12: ('message',)
                562     CALL                            1
                570     POP_TOP                         
                572     LOAD_GLOBAL                     3: NULL + StopProgram
                582     CALL                            0
                590     RAISE_VARARGS                   1
                592     LOAD_FAST                       0: data
                594     LOAD_CONST                      4: 'Settings'
                596     BINARY_SUBSCR                   
                600     LOAD_ATTR                       7: get
                620     PUSH_NULL                       
                622     LOAD_CONST                      1: '__pyarmor_assert_14796__'
                624     LOAD_CONST                      14: 'thread_rules'   # b'\x81\xf6\x10\x016\xfb\xba\xed\t\xef\x01\xc5\x7f'
                626     CALL                            1
                634     CALL                            1
                642     LOAD_CONST                      15: True
                644     COMPARE_OP                      40 (==)
                648     POP_JUMP_IF_FALSE               36 (to 722)
                650     LOAD_GLOBAL                     13: NULL + int
                660     LOAD_FAST                       0: data
                662     LOAD_CONST                      4: 'Settings'
                664     BINARY_SUBSCR                   
                668     LOAD_ATTR                       7: get
                688     PUSH_NULL                       
                690     LOAD_CONST                      1: '__pyarmor_assert_14796__'
                692     LOAD_CONST                      16: 'thread_count'   # b'\x81\xf6\x10\x016\xfb\xba\xed\x18\xf5\x18\xcex'
                694     CALL                            1
                702     CALL                            1
                710     CALL                            1
                718     STORE_FAST                      7: _var_var_5
                720     JUMP_FORWARD                    11 (to 744)
                722     LOAD_FAST                       1: config
                724     PUSH_NULL                       
                726     LOAD_CONST                      1: '__pyarmor_assert_14796__'
                728     LOAD_CONST                      16: 'thread_count'   # b'\x81\xf6\x10\x016\xfb\xba\xed\x18\xf5\x18\xcex'
                730     CALL                            1
                738     BINARY_SUBSCR                   
                742     STORE_FAST                      7: _var_var_5
                744     LOAD_FAST                       0: data
                746     LOAD_CONST                      4: 'Settings'
                748     BINARY_SUBSCR                   
                752     LOAD_ATTR                       7: get
                772     LOAD_CONST                      17: 'use_stat'
                774     CALL                            1
                782     STORE_FAST                      8: _var_var_6
                784     LOAD_GLOBAL                     23: NULL + Logs
                794     LOAD_ATTR                       26: LangCheck
                814     CALL                            0
                822     POP_TOP                         
                824     LOAD_FAST                       8: _var_var_6
                826     POP_JUMP_IF_FALSE               150 (to 1128)
                828     LOAD_GLOBAL                     28: datetime
                838     LOAD_ATTR                       28: datetime
                858     LOAD_ATTR                       31: now
                878     CALL                            0
                886     LOAD_ATTR                       33: strftime
                906     PUSH_NULL                       
                908     LOAD_CONST                      1: '__pyarmor_assert_14796__'
                910     LOAD_CONST                      18: '%Y-%m-%d_%H-%M-%S'   # b'\x81\xa7!^v\xf7\xf3\x97\x1f\xc5H\xe8!\xa9\xd5\xc8Jn'
                912     CALL                            1
                920     CALL                            1
                928     STORE_FAST                      9: _var_var_7
                930     LOAD_GLOBAL                     35: NULL + DB_CREATE_RESULT
                940     LOAD_FAST                       9: _var_var_7
                942     PUSH_NULL                       
                944     LOAD_CONST                      1: '__pyarmor_assert_14796__'
                946     LOAD_CONST                      19: 'unsubscribe'   # b'\x81\xf7\x16\x00&\xf8\xad\xd1\t\xf3\x0f\xc5'
                948     CALL                            1
                956     CALL                            2
                964     STORE_FAST                      10: _var_var_8
                966     LOAD_FAST                       10: _var_var_8
                968     LOAD_CONST                      9: False
                970     COMPARE_OP                      40 (==)
                974     POP_JUMP_IF_FALSE               37 (to 1050)
                976     LOAD_GLOBAL                     17: NULL + eel
                986     LOAD_ATTR                       18: sendErrorBox
                1006    PUSH_NULL                       
                1008    LOAD_CONST                      1: '__pyarmor_assert_14796__'
                1010    LOAD_CONST                      20: "I can't create a statistics file"   # b'\x81\xcbX\x102\xf4\xf9\xc6[\xf9\x1f\xc5m\xf8\xfd\xc5\x0e\x1d\xa8\xb3\xab\xdfG\xdf\x11f\xa0O@\xb7\x17\xe9?'
                1012    CALL                            1
                1020    CALL                            1
                1028    POP_TOP                         
                1030    LOAD_GLOBAL                     3: NULL + StopProgram
                1040    CALL                            0
                1048    RAISE_VARARGS                   1
                1050    LOAD_GLOBAL                     17: NULL + eel
                1060    LOAD_ATTR                       36: WriteResult
                1080    PUSH_NULL                       
                1082    LOAD_CONST                      1: '__pyarmor_assert_14796__'
                1084    LOAD_CONST                      21: 'Statistics'   # b"\x81\xd1\x0c\x12'\xf3\xad\xc6\x12\xf9\x1e"
                1086    CALL                            1
                1094    PUSH_NULL                       
                1096    LOAD_CONST                      1: '__pyarmor_assert_14796__'
                1098    LOAD_CONST                      19: 'unsubscribe'   # b'\x81\xf7\x16\x00&\xf8\xad\xd1\t\xf3\x0f\xc5'
                1100    CALL                            1
                1108    LOAD_FAST                       9: _var_var_7
                1110    LOAD_CONST                      22: '.db'
                1112    BINARY_OP                       0 (+)
                1116    CALL                            3
                1124    POP_TOP                         
                1126    JUMP_FORWARD                    2 (to 1132)
                1128    LOAD_CONST                      0: None
                1130    STORE_FAST                      10: _var_var_8
                1132    LOAD_GLOBAL                     39: NULL + set_task_manager
                1142    LOAD_FAST                       2: pid
                1144    LOAD_FAST                       6: _var_var_4
                1146    LOAD_FAST                       0: data
                1148    LOAD_CONST                      23: 'stuff'
                1150    BINARY_SUBSCR                   
                1154    KW_NAMES                        24: ('accounts', 'name')
                1156    CALL                            3
                1164    POP_TOP                         
                1166    LOAD_GLOBAL                     40: concurrent
                1176    LOAD_ATTR                       42: futures
                1196    LOAD_ATTR                       45: ThreadPoolExecutor
                1216    LOAD_FAST                       7: _var_var_5
                1218    KW_NAMES                        25: ('max_workers',)
                1220    CALL                            1
                1228    BEFORE_WITH                     
                1230    STORE_FAST                      11: _var_var_9
                1232    BUILD_LIST                      0
                1234    STORE_FAST                      12: _var_var_10
                1236    LOAD_GLOBAL                     15: NULL + len
                1246    LOAD_FAST                       6: _var_var_4
                1248    CALL                            1
                1256    STORE_FAST                      13: _var_var_11
                1258    LOAD_FAST                       7: _var_var_5
                1260    STORE_FAST                      14: _var_var_12
                1262    LOAD_FAST                       13: _var_var_11
                1264    STORE_FAST                      15: _var_var_13
                1266    LOAD_CONST                      26: 0
                1268    STORE_FAST                      16: _var_var_14
                1270    LOAD_GLOBAL                     17: NULL + eel
                1280    LOAD_ATTR                       46: StreamStat
                1300    LOAD_GLOBAL                     49: NULL + json
                1310    LOAD_ATTR                       50: dumps
                1330    LOAD_CONST                      27: 'st_task'
                1332    LOAD_FAST                       13: _var_var_11
                1334    PUSH_NULL                       
                1336    LOAD_CONST                      1: '__pyarmor_assert_14796__'
                1338    LOAD_CONST                      28: 'st_stream'   # b'\x81\xf1\x0c, \xee\xac\xd7\x1a\xf7'
                1340    CALL                            1
                1348    LOAD_FAST                       14: _var_var_12
                1350    LOAD_CONST                      29: 'st_wait'
                1352    LOAD_FAST                       15: _var_var_13
                1354    LOAD_CONST                      30: 'st_done'
                1356    LOAD_FAST                       16: _var_var_14
                1358    BUILD_MAP                       4
                1360    CALL                            1
                1368    CALL                            1
                1376    POP_TOP                         
                1378    LOAD_FAST                       6: _var_var_4
                1380    GET_ITER                        
                1382    FOR_ITER                        45 (to 1474)
                1386    STORE_FAST                      17: _var_var_15
                1388    LOAD_FAST                       12: _var_var_10
                1390    LOAD_ATTR                       53: append
                1410    LOAD_FAST                       11: _var_var_9
                1412    LOAD_ATTR                       55: submit
                1432    LOAD_GLOBAL                     56: Unsubscribes
                1442    LOAD_FAST                       17: _var_var_15
                1444    LOAD_FAST                       1: config
                1446    LOAD_FAST                       3: proxy
                1448    LOAD_FAST                       0: data
                1450    LOAD_FAST                       10: _var_var_8
                1452    LOAD_FAST                       4: stop_thread
                1454    LOAD_CONST                      26: 0
                1456    CALL                            8
                1464    CALL                            1
                1472    POP_TOP                         
                1474    JUMP_BACKWARD                   47 (to 1382)
                1476    END_FOR                         
                1478    LOAD_GLOBAL                     40: concurrent
                1488    LOAD_ATTR                       42: futures
                1508    LOAD_ATTR                       59: as_completed
                1528    LOAD_FAST                       12: _var_var_10
                1530    CALL                            1
                1538    GET_ITER                        
                1540    FOR_ITER                        66 (to 1674)
                1544    STORE_FAST                      18: _var_var_16
                1546    LOAD_FAST                       16: _var_var_14
                1548    LOAD_CONST                      6: 1
                1550    BINARY_OP                       13 (+=)
                1554    STORE_FAST                      16: _var_var_14
                1556    LOAD_FAST                       15: _var_var_13
                1558    LOAD_CONST                      6: 1
                1560    BINARY_OP                       23 (-=)
                1564    STORE_FAST                      15: _var_var_13
                1566    LOAD_GLOBAL                     17: NULL + eel
                1576    LOAD_ATTR                       46: StreamStat
                1596    LOAD_GLOBAL                     49: NULL + json
                1606    LOAD_ATTR                       50: dumps
                1626    LOAD_CONST                      27: 'st_task'
                1628    LOAD_FAST                       13: _var_var_11
                1630    PUSH_NULL                       
                1632    LOAD_CONST                      1: '__pyarmor_assert_14796__'
                1634    LOAD_CONST                      28: 'st_stream'   # b'\x81\xf1\x0c, \xee\xac\xd7\x1a\xf7'
                1636    CALL                            1
                1644    LOAD_FAST                       14: _var_var_12
                1646    LOAD_CONST                      29: 'st_wait'
                1648    LOAD_FAST                       15: _var_var_13
                1650    LOAD_CONST                      30: 'st_done'
                1652    LOAD_FAST                       16: _var_var_14
                1654    BUILD_MAP                       4
                1656    CALL                            1
                1664    CALL                            1
                1672    POP_TOP                         
                1674    JUMP_BACKWARD                   68 (to 1540)
                1676    END_FOR                         
                1678    NOP                             
                1680    LOAD_CONST                      0: None
                1682    LOAD_CONST                      0: None
                1684    LOAD_CONST                      0: None
                1686    CALL                            2
                1694    POP_TOP                         
                1696    LOAD_GLOBAL                     65: NULL + del_task_manager
                1706    LOAD_FAST                       2: pid
                1708    CALL                            1
                1716    POP_TOP                         
                1718    LOAD_GLOBAL                     67: NULL + StopDetect
                1728    LOAD_FAST                       4: stop_thread
                1730    CALL                            1
                1738    POP_TOP                         
                1740    NOP                             
                1742    LOAD_CONST                      32: 'Done'
                1744    NOP                             
                1746    NOP                             
                1748    NOP                             
                1750    JUMP_FORWARD                    117 (to 1986)
                1758    POP_TOP                         
                1760    RETURN_CONST                    32: 'Done'
                1762    PUSH_EXC_INFO                   
                1764    WITH_EXCEPT_START               
                1766    POP_JUMP_IF_TRUE                1 (to 1770)
                1768    RERAISE                         2
                1770    POP_TOP                         
                1772    POP_EXCEPT                      
                1774    POP_TOP                         
                1776    POP_TOP                         
                1778    JUMP_BACKWARD                   42 (to 1696)
                1780    COPY                            3
                1782    POP_EXCEPT                      
                1784    RERAISE                         1
                1786    PUSH_EXC_INFO                   
                1788    LOAD_GLOBAL                     2: StopProgram
                1798    CHECK_EXC_MATCH                 
                1800    POP_JUMP_IF_FALSE               3 (to 1808)
                1802    POP_TOP                         
                1804    POP_EXCEPT                      
                1806    JUMP_BACKWARD                   56 (to 1696)
                1808    LOAD_GLOBAL                     60: BaseException
                1818    CHECK_EXC_MATCH                 
                1820    POP_JUMP_IF_FALSE               26 (to 1874)
                1822    STORE_FAST                      19: _var_var_3
                1824    PUSH_NULL                       
                1826    LOAD_GLOBAL                     63: NULL + logging
                1836    LOAD_FAST                       19: _var_var_3
                1838    CALL                            1
                1846    CALL                            0
                1854    POP_TOP                         
                1856    POP_EXCEPT                      
                1858    LOAD_CONST                      0: None
                1860    STORE_FAST                      19: _var_var_3
                1862    DELETE_FAST                     19: _var_var_3
                1864    JUMP_BACKWARD                   85 (to 1696)
                1866    LOAD_CONST                      0: None
                1868    STORE_FAST                      19: _var_var_3
                1870    DELETE_FAST                     19: _var_var_3
                1872    RERAISE                         1
                1874    RERAISE                         0
                1876    COPY                            3
                1878    POP_EXCEPT                      
                1880    RERAISE                         1
                1882    PUSH_EXC_INFO                   
                1884    LOAD_GLOBAL                     65: NULL + del_task_manager
                1894    LOAD_FAST                       2: pid
                1896    CALL                            1
                1904    POP_TOP                         
                1906    LOAD_GLOBAL                     67: NULL + StopDetect
                1916    LOAD_FAST                       4: stop_thread
                1918    CALL                            1
                1926    POP_TOP                         
                1928    POP_TOP                         
                1930    POP_EXCEPT                      
                1932    LOAD_CONST                      32: 'Done'
                1934    NOP                             
                1936    NOP                             
                1938    NOP                             
                1940    JUMP_FORWARD                    22 (to 1986)
                1948    POP_TOP                         
                1950    RETURN_CONST                    32: 'Done'
                1952    COPY                            3
                1954    POP_EXCEPT                      
                1956    RERAISE                         1
                1958    PUSH_EXC_INFO                   
                1960    PUSH_NULL                       
                1962    LOAD_CONST                      31: '__pyarmor_exit_14798__'
                1964    NOP                             
                1966    LOAD_CONST                      3: b'<COAddr>\x05\x00\x00\x1a\x8c\x07\x00\x00\x00\x00\x00\x00\x00\x00\x00\x00\x00\x00\x00\x00'
                1968    CALL                            1
                1976    POP_TOP                         
                1978    RERAISE                         0
                1980    COPY                            3
                1982    POP_EXCEPT                      
                1984    RERAISE                         1
                1986    PUSH_NULL                       
                1988    LOAD_CONST                      31: '__pyarmor_exit_14798__'
                1990    LOAD_CONST                      3: b'<COAddr>\x05\x00\x00\x1a\x8c\x07\x00\x00\x00\x00\x00\x00\x00\x00\x00\x00\x00\x00\x00\x00'
                1992    BUILD_TUPLE                     1
                1994    CALL_FUNCTION_EX                0
                1996    POP_TOP                         
                1998    RETURN_VALUE                    
            [Exception Table]
                30 to 1230 -> 1786 [0] 
                1230 to 1678 -> 1762 [1] lasti
                1680 to 1696 -> 1786 [0] 
                1696 to 1740 -> 1958 [0] 
                1762 to 1772 -> 1780 [3] lasti
                1772 to 1786 -> 1786 [0] 
                1786 to 1804 -> 1876 [1] lasti
                1804 to 1808 -> 1882 [0] 
                1808 to 1824 -> 1876 [1] lasti
                1824 to 1856 -> 1866 [1] lasti
                1856 to 1866 -> 1882 [0] 
                1866 to 1876 -> 1876 [1] lasti
                1876 to 1882 -> 1882 [0] 
                1882 to 1930 -> 1952 [1] lasti
                1930 to 1932 -> 1958 [0] 
                1952 to 1958 -> 1958 [0] 
                1958 to 1980 -> 1980 [1] lasti
        [Code]
            File Name: <frozen program.modules.Unsubscribe>
            Object Name: DB_CREATE_RESULT
            Qualified Name: DB_CREATE_RESULT
            Arg Count: 2
            Pos Only Arg Count: 0
            KW Only Arg Count: 0
            Stack Size: 7
            Flags: 0x20000003 (CO_OPTIMIZED | CO_NEWLOCALS | CO_PYARMOR_OBFUSCATED)
            [Names]
                'str'
                'sqlite3'
                'connect'
                'PARSE_DECLTYPES'
                'cursor'
                'execute'
                'Logs'
                'PrintLog'
                'Lang'
                'commit'
                'close'
                'Exception'
                'print'
            [Locals+Names]
                'StartUnix'
                'Folder'
                '__assert_armored__'
                '_var_var_17'
                '_var_var_18'
                '_var_var_19'
                '_var_var_20'
            [Constants]
                None
                '__pyarmor_assert_14799__'
                '__pyarmor_enter_14800__'
                b'<COAddr>\x05\x00\x00\x1a4\x02\x00\x00\x00\x00\x00\x00\x00\x00\x00\x00\x00\x00\x00\x00'
                'additives/'   # b'\x81\xe3\x1c\x17:\xee\xb7\xc4\x1e\xe9B'
                '/'
                '.db'
                5
                False
                (
                    'detect_types'
                    'timeout'
                    'check_same_thread'
                )
                'CREATE TABLE IF NOT EXISTS GROUPS (ID INTEGER, USERNAME TEXT, TITLE TEXT, COUNT INTEGER, PHOTO INTEGER, INVITE INTEGER, SEND_MESSAGES INTEGER, SEND_MEDIA INTEGER, SEND_STICKERS INTEGER, SEND_POLLS INTEGER, SLOWMODE INTEGER, SCAM INTEGER, TYPE TEXT, STATUS TEXT)'   # b'\x81\xc1*6\x12\xce\x9b\x92/\xdb/\xecI\xac\xd1\xa3Os\x94\x93\xea\xeev\xe56[\x90\x1c\'\x831\xd0\na`E\xb1\xee\xf4\x076\xdd\xddz\xf8\xeaC\x07\x02\xdes\xc9\xa9Q+\xc8w\xdf\xbe%,\x07qg~|)\xa6\x9d\x03\xc9\x87\xa7.|\x1do\x8c&\xa5\xe1\xae\xaa\x9d\x9a(\'s\x88\xf7\xbd\xc4\xb0E\xf6\xf3\xcd~\x89V\x1c-\x16p\x0f6\x96\xb4d\xd3\xd8{\x9b\x14\x86=_\xd1gG3\x7fOX\xdd}\x92\xc8\xd8\x9c3\x87"\x85Q\xa5\x1fa1\xde\x9f\x0e\x10\xf8K\x95\xc8\xf8Zz\xecD\xd4\xd3\xed"\xcf\xfb\xd9\xf0\xb2mk`\xf1\x89\x9c3\xb8\xadU;\'\x01y\xd7"Z\x92\x1c\x16\xbbP\xf0)9Q/t!\x86{^\xeb\xc7|\x06:\x00\xceQ\'\x97,\xbb\xff\xc4\n@\xe4N2T\x0eO\xf3\xf4\xc509\x05\xf3\xa9\xae\xa2$\xbe\x0f7\xd4\xc3(wm\x04\x8c-\x0ec\xe1P\x96\xdf\xd0"\x19\xf3 \x9c\xb5)\x18\xd0]\xcd\x86\xed"w^j\x91'
                'CREATE TABLE IF NOT EXISTS USERS (USER_ID INTEGER, GROUP_ID INTEGER, PHONE TEXT, USERNAME TEXT, FIRST_NAME TEXT, LAST_NAME TEXT, BIO TEXT, GENDER TEXT, PHOTO INTEGER, PREMIUM INTEGER, STATUS TEXT, TIME TEXT, INVITE_STATUS TEXT, SEND_STATUS TEXT)'   # b'\x81\xc1*6\x12\xce\x9b\x92/\xdb/\xecI\xac\xd1\xa3Os\x94\x93\xea\xeev\xe56[\x90\x1c5\x82;\xd7\t\x12h8\xab\xef\x86\x111\xcd\xb8t\xf3\xec*`\x12\xdf\x1a\xbb\xa0B)\xd8\x07\xd4\xb29Xb\x1fgro \xb1\x91w\xdc\x97\xbcL\x19~t\x9c0\xa5\xed\xc7\xb1\x9a\x9a=,`\xe9\x92\xcd\xd8\xbaI\xed\xff\xa4v\x94A\x08<\x1b\x12n2\x9d\xc2y\xc2\xc5\x0f\xfez\x9e9K\xc0j%RaO6\xcdg\x87\xd9\xa7\xef0\x89(\xf6%\xa9\taX\xb9\x9d\x19r\x9c]\x82\xa6\xe8@o\xfd,\xbd\xc2\x85$\xd5\xe0\xbc\xfe\xb9k\x02\x07\xe7\x9e\xfeW\xb7\xacD?-\x1fq\xa584\x8f\x17\x05\xbbE\x99[F%=e:\x91\x04Z\xe1\xd3dy:\x1d\xc9H\'\xf0=\xac\x8b\xb0u,\xe2W)R\x1eO\x8c\xee\xdf%(\x17\xe5\xdb\xd6\xc7/\xa9bZ\xa7\xcf(gw\x10\x9d>v\x16\xe6)\x92\xdf\xa8"u'
                ''
                'database_created'   # b'\x81\xe6\x19\x072\xf8\xbf\xc1\x1e\xc5\x0e\xd2i\xed\xec\x80\x0b'
                (
                    'account'
                    'message'
                    'param'
                )
                '__pyarmor_exit_14801__'
                'DB_CREATE_RESULT:'   # b'\x81\xc6:,\x10\xc8\x9b\xf3/\xdf2\xf2I\xdf\xcd\xa9;\x07'
            [Disassembly]
                0       NOP                             
                2       NOP                             
                4       PUSH_NULL                       
                6       LOAD_CONST                      2: '__pyarmor_enter_14800__'
                8       LOAD_CONST                      3: b'<COAddr>\x05\x00\x00\x1a4\x02\x00\x00\x00\x00\x00\x00\x00\x00\x00\x00\x00\x00\x00\x00'
                10      BUILD_TUPLE                     1
                12      CALL_FUNCTION_EX                0
                14      POP_TOP                         
                16      RESUME                          0
                18      NOP                             
                20      NOP                             
                22      NOP                             
                24      NOP                             
                26      NOP                             
                28      NOP                             
                30      PUSH_NULL                       
                32      LOAD_CONST                      1: '__pyarmor_assert_14799__'
                34      LOAD_CONST                      4: 'additives/'   # b'\x81\xe3\x1c\x17:\xee\xb7\xc4\x1e\xe9B'
                36      CALL                            1
                44      LOAD_GLOBAL                     1: NULL + str
                54      LOAD_FAST                       1: Folder
                56      CALL                            1
                64      BINARY_OP                       0 (+)
                68      LOAD_CONST                      5: '/'
                70      BINARY_OP                       0 (+)
                74      LOAD_GLOBAL                     1: NULL + str
                84      LOAD_FAST                       0: StartUnix
                86      CALL                            1
                94      BINARY_OP                       0 (+)
                98      LOAD_CONST                      6: '.db'
                100     BINARY_OP                       0 (+)
                104     STORE_FAST                      3: _var_var_17
                106     LOAD_GLOBAL                     3: NULL + sqlite3
                116     LOAD_ATTR                       4: connect
                136     LOAD_FAST                       3: _var_var_17
                138     LOAD_GLOBAL                     2: sqlite3
                148     LOAD_ATTR                       6: PARSE_DECLTYPES
                168     LOAD_CONST                      7: 5
                170     LOAD_CONST                      8: False
                172     KW_NAMES                        9: ('detect_types', 'timeout', 'check_same_thread')
                174     CALL                            4
                182     STORE_FAST                      4: _var_var_18
                184     LOAD_FAST                       4: _var_var_18
                186     LOAD_ATTR                       9: cursor
                206     CALL                            0
                214     STORE_FAST                      5: _var_var_19
                216     LOAD_FAST                       5: _var_var_19
                218     LOAD_ATTR                       11: execute
                238     PUSH_NULL                       
                240     LOAD_CONST                      1: '__pyarmor_assert_14799__'
                242     LOAD_CONST                      10: 'CREATE TABLE IF NOT EXISTS GROUPS (ID INTEGER, USERNAME TEXT, TITLE TEXT, COUNT INTEGER, PHOTO INTEGER, INVITE INTEGER, SEND_MESSAGES INTEGER, SEND_MEDIA INTEGER, SEND_STICKERS INTEGER, SEND_POLLS INTEGER, SLOWMODE INTEGER, SCAM INTEGER, TYPE TEXT, STATUS TEXT)'   # b'\x81\xc1*6\x12\xce\x9b\x92/\xdb/\xecI\xac\xd1\xa3Os\x94\x93\xea\xeev\xe56[\x90\x1c\'\x831\xd0\na`E\xb1\xee\xf4\x076\xdd\xddz\xf8\xeaC\x07\x02\xdes\xc9\xa9Q+\xc8w\xdf\xbe%,\x07qg~|)\xa6\x9d\x03\xc9\x87\xa7.|\x1do\x8c&\xa5\xe1\xae\xaa\x9d\x9a(\'s\x88\xf7\xbd\xc4\xb0E\xf6\xf3\xcd~\x89V\x1c-\x16p\x0f6\x96\xb4d\xd3\xd8{\x9b\x14\x86=_\xd1gG3\x7fOX\xdd}\x92\xc8\xd8\x9c3\x87"\x85Q\xa5\x1fa1\xde\x9f\x0e\x10\xf8K\x95\xc8\xf8Zz\xecD\xd4\xd3\xed"\xcf\xfb\xd9\xf0\xb2mk`\xf1\x89\x9c3\xb8\xadU;\'\x01y\xd7"Z\x92\x1c\x16\xbbP\xf0)9Q/t!\x86{^\xeb\xc7|\x06:\x00\xceQ\'\x97,\xbb\xff\xc4\n@\xe4N2T\x0eO\xf3\xf4\xc509\x05\xf3\xa9\xae\xa2$\xbe\x0f7\xd4\xc3(wm\x04\x8c-\x0ec\xe1P\x96\xdf\xd0"\x19\xf3 \x9c\xb5)\x18\xd0]\xcd\x86\xed"w^j\x91'
                244     CALL                            1
                252     CALL                            1
                260     POP_TOP                         
                262     LOAD_FAST                       5: _var_var_19
                264     LOAD_ATTR                       11: execute
                284     PUSH_NULL                       
                286     LOAD_CONST                      1: '__pyarmor_assert_14799__'
                288     LOAD_CONST                      11: 'CREATE TABLE IF NOT EXISTS USERS (USER_ID INTEGER, GROUP_ID INTEGER, PHONE TEXT, USERNAME TEXT, FIRST_NAME TEXT, LAST_NAME TEXT, BIO TEXT, GENDER TEXT, PHOTO INTEGER, PREMIUM INTEGER, STATUS TEXT, TIME TEXT, INVITE_STATUS TEXT, SEND_STATUS TEXT)'   # b'\x81\xc1*6\x12\xce\x9b\x92/\xdb/\xecI\xac\xd1\xa3Os\x94\x93\xea\xeev\xe56[\x90\x1c5\x82;\xd7\t\x12h8\xab\xef\x86\x111\xcd\xb8t\xf3\xec*`\x12\xdf\x1a\xbb\xa0B)\xd8\x07\xd4\xb29Xb\x1fgro \xb1\x91w\xdc\x97\xbcL\x19~t\x9c0\xa5\xed\xc7\xb1\x9a\x9a=,`\xe9\x92\xcd\xd8\xbaI\xed\xff\xa4v\x94A\x08<\x1b\x12n2\x9d\xc2y\xc2\xc5\x0f\xfez\x9e9K\xc0j%RaO6\xcdg\x87\xd9\xa7\xef0\x89(\xf6%\xa9\taX\xb9\x9d\x19r\x9c]\x82\xa6\xe8@o\xfd,\xbd\xc2\x85$\xd5\xe0\xbc\xfe\xb9k\x02\x07\xe7\x9e\xfeW\xb7\xacD?-\x1fq\xa584\x8f\x17\x05\xbbE\x99[F%=e:\x91\x04Z\xe1\xd3dy:\x1d\xc9H\'\xf0=\xac\x8b\xb0u,\xe2W)R\x1eO\x8c\xee\xdf%(\x17\xe5\xdb\xd6\xc7/\xa9bZ\xa7\xcf(gw\x10\x9d>v\x16\xe6)\x92\xdf\xa8"u'
                290     CALL                            1
                298     CALL                            1
                306     POP_TOP                         
                308     LOAD_GLOBAL                     13: NULL + Logs
                318     LOAD_ATTR                       14: PrintLog
                338     LOAD_CONST                      12: ''
                340     LOAD_GLOBAL                     16: Lang
                350     PUSH_NULL                       
                352     LOAD_CONST                      1: '__pyarmor_assert_14799__'
                354     LOAD_CONST                      13: 'database_created'   # b'\x81\xe6\x19\x072\xf8\xbf\xc1\x1e\xc5\x0e\xd2i\xed\xec\x80\x0b'
                356     CALL                            1
                364     BINARY_SUBSCR                   
                368     LOAD_FAST                       3: _var_var_17
                370     KW_NAMES                        14: ('account', 'message', 'param')
                372     CALL                            3
                380     POP_TOP                         
                382     LOAD_FAST                       4: _var_var_18
                384     LOAD_ATTR                       19: commit
                404     CALL                            0
                412     POP_TOP                         
                414     LOAD_FAST                       4: _var_var_18
                416     LOAD_ATTR                       21: close
                436     CALL                            0
                444     POP_TOP                         
                446     LOAD_FAST                       3: _var_var_17
                448     NOP                             
                450     NOP                             
                452     NOP                             
                454     JUMP_FORWARD                    81 (to 618)
                456     CALL                            1
                464     POP_TOP                         
                466     RETURN_VALUE                    
                468     PUSH_EXC_INFO                   
                470     LOAD_GLOBAL                     22: Exception
                480     CHECK_EXC_MATCH                 
                482     POP_JUMP_IF_FALSE               39 (to 562)
                484     STORE_FAST                      6: _var_var_20
                486     LOAD_GLOBAL                     25: NULL + print
                496     PUSH_NULL                       
                498     LOAD_CONST                      1: '__pyarmor_assert_14799__'
                500     LOAD_CONST                      16: 'DB_CREATE_RESULT:'   # b'\x81\xc6:,\x10\xc8\x9b\xf3/\xdf2\xf2I\xdf\xcd\xa9;\x07'
                502     CALL                            1
                510     LOAD_GLOBAL                     1: NULL + str
                520     LOAD_FAST                       6: _var_var_20
                522     CALL                            1
                530     BINARY_OP                       0 (+)
                534     CALL                            1
                542     POP_TOP                         
                544     POP_EXCEPT                      
                546     LOAD_CONST                      0: None
                548     STORE_FAST                      6: _var_var_20
                550     DELETE_FAST                     6: _var_var_20
                552     JUMP_FORWARD                    8 (to 570)
                554     LOAD_CONST                      0: None
                556     STORE_FAST                      6: _var_var_20
                558     DELETE_FAST                     6: _var_var_20
                560     RERAISE                         1
                562     RERAISE                         0
                564     COPY                            3
                566     POP_EXCEPT                      
                568     RERAISE                         1
                570     LOAD_CONST                      8: False
                572     NOP                             
                574     NOP                             
                576     NOP                             
                578     JUMP_FORWARD                    19 (to 618)
                586     POP_TOP                         
                588     RETURN_CONST                    8: False
                590     PUSH_EXC_INFO                   
                592     PUSH_NULL                       
                594     LOAD_CONST                      15: '__pyarmor_exit_14801__'
                596     NOP                             
                598     LOAD_CONST                      3: b'<COAddr>\x05\x00\x00\x1a4\x02\x00\x00\x00\x00\x00\x00\x00\x00\x00\x00\x00\x00\x00\x00'
                600     CALL                            1
                608     POP_TOP                         
                610     RERAISE                         0
                612     COPY                            3
                614     POP_EXCEPT                      
                616     RERAISE                         1
                618     PUSH_NULL                       
                620     LOAD_CONST                      15: '__pyarmor_exit_14801__'
                622     LOAD_CONST                      3: b'<COAddr>\x05\x00\x00\x1a4\x02\x00\x00\x00\x00\x00\x00\x00\x00\x00\x00\x00\x00\x00\x00'
                624     BUILD_TUPLE                     1
                626     CALL_FUNCTION_EX                0
                628     POP_TOP                         
                630     RETURN_VALUE                    
            [Exception Table]
                30 to 448 -> 468 [0] 
                468 to 486 -> 564 [1] lasti
                486 to 544 -> 554 [1] lasti
                544 to 554 -> 590 [0] 
                554 to 564 -> 564 [1] lasti
                564 to 570 -> 590 [0] 
                590 to 612 -> 612 [1] lasti
        [Code]
            File Name: <frozen program.modules.Unsubscribe>
            Object Name: DB_SET_STATISTIC
            Qualified Name: DB_SET_STATISTIC
            Arg Count: 3
            Pos Only Arg Count: 0
            KW Only Arg Count: 0
            Stack Size: 18
            Flags: 0x20000003 (CO_OPTIMIZED | CO_NEWLOCALS | CO_PYARMOR_OBFUSCATED)
            [Names]
                'sqlite3'
                'connect'
                'PARSE_DECLTYPES'
                'cursor'
                'execute'
                'commit'
                'close'
                'Exception'
                'print'
                'str'
                'DB_SET_STATISTIC'
            [Locals+Names]
                'FILE_DB'
                'INFO'
                'ERROR'
                '__assert_armored__'
                '_var_var_18'
                '_var_var_19'
                '_var_var_21'
                '_var_var_20'
            [Constants]
                None
                '__pyarmor_assert_14802__'
                '__pyarmor_enter_14803__'
                b'<COAddr>\x07\x00\x00\x1a`\x02\x00\x00\x00\x00\x00\x00\x00\x00\x00\x00\x00\x00\x00\x00'
                10
                '__pyarmor_exit_14804__'
                False
                5
                (
                    'detect_types'
                    'timeout'
                    'check_same_thread'
                )
                'INSERT OR REPLACE INTO GROUPS VALUES (?, ?, ?, ?, ?, ?, ?, ?, ?, ?, ?, ?, ?, ?)'   # b'\x81\xcb6 \x16\xc8\x8a\x924\xc8M\xf2I\xdc\xd4\xa4,x\xfb\x8e\x84\xffa\x8c"]\x8ci0\x82^\xd3\x1b~\x15(\xab\x8a\xfcqT\xa9\xa7\x11\x9d\x87C\x07h\xa1\x16\xa4\xcb0Y\xa1w\xb4\xd7]G\x07q\x0c\x1b\x08Z\xcf\x9dh\xa0\xff\xcc.|a\x0c\xf9W\xd8'
                'id'
                'username'
                'title'
                'count'
                'photo'
                'invite'
                'send_messages'   # b'\x81\xf1\x1d\x1d7\xc5\xb3\xd7\x08\xe9\x0c\xc7i\xff'
                'send_media'   # b'\x81\xf1\x1d\x1d7\xc5\xb3\xd7\x1f\xf3\x0c'
                'send_stickers'   # b'\x81\xf1\x1d\x1d7\xc5\xad\xc6\x12\xf9\x06\xc5~\xff'
                'send_polls'   # b'\x81\xf1\x1d\x1d7\xc5\xae\xdd\x17\xf6\x1e'
                'slowmode'
                'scam'
                'type'
                'status'
                'DB_SET_RESULT_GROUPS:'   # b'\x81\xc6:,\x00\xdf\x8a\xed)\xdf>\xf5@\xd8\xc7\xa2=r\x8e\x97\x99\x91'
                1
                True
            [Disassembly]
                0       NOP                             
                2       NOP                             
                4       PUSH_NULL                       
                6       LOAD_CONST                      2: '__pyarmor_enter_14803__'
                8       LOAD_CONST                      3: b'<COAddr>\x07\x00\x00\x1a`\x02\x00\x00\x00\x00\x00\x00\x00\x00\x00\x00\x00\x00\x00\x00'
                10      BUILD_TUPLE                     1
                12      CALL_FUNCTION_EX                0
                14      POP_TOP                         
                16      RESUME                          0
                18      NOP                             
                20      NOP                             
                22      NOP                             
                24      NOP                             
                26      NOP                             
                28      LOAD_FAST                       2: ERROR
                30      LOAD_CONST                      4: 10
                32      COMPARE_OP                      68 (>)
                36      POP_JUMP_IF_FALSE               11 (to 60)
                38      NOP                             
                40      LOAD_CONST                      6: False
                42      NOP                             
                44      NOP                             
                46      JUMP_FORWARD                    306 (to 662)
                56      POP_TOP                         
                58      RETURN_CONST                    6: False
                60      NOP                             
                62      LOAD_GLOBAL                     1: NULL + sqlite3
                72      LOAD_ATTR                       2: connect
                92      LOAD_FAST                       0: FILE_DB
                94      LOAD_GLOBAL                     0: sqlite3
                104     LOAD_ATTR                       4: PARSE_DECLTYPES
                124     LOAD_CONST                      7: 5
                126     LOAD_CONST                      6: False
                128     KW_NAMES                        8: ('detect_types', 'timeout', 'check_same_thread')
                130     CALL                            4
                138     STORE_FAST                      4: _var_var_18
                140     LOAD_FAST                       4: _var_var_18
                142     LOAD_ATTR                       7: cursor
                162     CALL                            0
                170     STORE_FAST                      5: _var_var_19
                172     LOAD_FAST                       1: INFO
                174     STORE_FAST                      6: _var_var_21
                176     LOAD_FAST                       6: _var_var_21
                178     LOAD_CONST                      6: False
                180     COMPARE_OP                      55 (!=)
                184     POP_JUMP_IF_FALSE               104 (to 394)
                186     LOAD_FAST                       5: _var_var_19
                188     LOAD_ATTR                       9: execute
                208     PUSH_NULL                       
                210     LOAD_CONST                      1: '__pyarmor_assert_14802__'
                212     LOAD_CONST                      9: 'INSERT OR REPLACE INTO GROUPS VALUES (?, ?, ?, ?, ?, ?, ?, ?, ?, ?, ?, ?, ?, ?)'   # b'\x81\xcb6 \x16\xc8\x8a\x924\xc8M\xf2I\xdc\xd4\xa4,x\xfb\x8e\x84\xffa\x8c"]\x8ci0\x82^\xd3\x1b~\x15(\xab\x8a\xfcqT\xa9\xa7\x11\x9d\x87C\x07h\xa1\x16\xa4\xcb0Y\xa1w\xb4\xd7]G\x07q\x0c\x1b\x08Z\xcf\x9dh\xa0\xff\xcc.|a\x0c\xf9W\xd8'
                214     CALL                            1
                222     LOAD_FAST                       6: _var_var_21
                224     LOAD_CONST                      10: 'id'
                226     BINARY_SUBSCR                   
                230     LOAD_FAST                       6: _var_var_21
                232     LOAD_CONST                      11: 'username'
                234     BINARY_SUBSCR                   
                238     LOAD_FAST                       6: _var_var_21
                240     LOAD_CONST                      12: 'title'
                242     BINARY_SUBSCR                   
                246     LOAD_FAST                       6: _var_var_21
                248     LOAD_CONST                      13: 'count'
                250     BINARY_SUBSCR                   
                254     LOAD_FAST                       6: _var_var_21
                256     LOAD_CONST                      14: 'photo'
                258     BINARY_SUBSCR                   
                262     LOAD_FAST                       6: _var_var_21
                264     LOAD_CONST                      15: 'invite'
                266     BINARY_SUBSCR                   
                270     LOAD_FAST                       6: _var_var_21
                272     PUSH_NULL                       
                274     LOAD_CONST                      1: '__pyarmor_assert_14802__'
                276     LOAD_CONST                      16: 'send_messages'   # b'\x81\xf1\x1d\x1d7\xc5\xb3\xd7\x08\xe9\x0c\xc7i\xff'
                278     CALL                            1
                286     BINARY_SUBSCR                   
                290     LOAD_FAST                       6: _var_var_21
                292     PUSH_NULL                       
                294     LOAD_CONST                      1: '__pyarmor_assert_14802__'
                296     LOAD_CONST                      17: 'send_media'   # b'\x81\xf1\x1d\x1d7\xc5\xb3\xd7\x1f\xf3\x0c'
                298     CALL                            1
                306     BINARY_SUBSCR                   
                310     LOAD_FAST                       6: _var_var_21
                312     PUSH_NULL                       
                314     LOAD_CONST                      1: '__pyarmor_assert_14802__'
                316     LOAD_CONST                      18: 'send_stickers'   # b'\x81\xf1\x1d\x1d7\xc5\xad\xc6\x12\xf9\x06\xc5~\xff'
                318     CALL                            1
                326     BINARY_SUBSCR                   
                330     LOAD_FAST                       6: _var_var_21
                332     PUSH_NULL                       
                334     LOAD_CONST                      1: '__pyarmor_assert_14802__'
                336     LOAD_CONST                      19: 'send_polls'   # b'\x81\xf1\x1d\x1d7\xc5\xae\xdd\x17\xf6\x1e'
                338     CALL                            1
                346     BINARY_SUBSCR                   
                350     LOAD_FAST                       6: _var_var_21
                352     LOAD_CONST                      20: 'slowmode'
                354     BINARY_SUBSCR                   
                358     LOAD_FAST                       6: _var_var_21
                360     LOAD_CONST                      21: 'scam'
                362     BINARY_SUBSCR                   
                366     LOAD_FAST                       6: _var_var_21
                368     LOAD_CONST                      22: 'type'
                370     BINARY_SUBSCR                   
                374     LOAD_FAST                       6: _var_var_21
                376     LOAD_CONST                      23: 'status'
                378     BINARY_SUBSCR                   
                382     BUILD_TUPLE                     14
                384     CALL                            2
                392     POP_TOP                         
                394     LOAD_FAST                       4: _var_var_18
                396     LOAD_ATTR                       11: commit
                416     CALL                            0
                424     POP_TOP                         
                426     LOAD_FAST                       4: _var_var_18
                428     LOAD_ATTR                       13: close
                448     CALL                            0
                456     POP_TOP                         
                458     LOAD_CONST                      26: True
                460     NOP                             
                462     NOP                             
                464     NOP                             
                466     JUMP_FORWARD                    97 (to 662)
                474     POP_TOP                         
                476     RETURN_CONST                    26: True
                478     PUSH_EXC_INFO                   
                480     LOAD_GLOBAL                     14: Exception
                490     CHECK_EXC_MATCH                 
                492     POP_JUMP_IF_FALSE               66 (to 626)
                494     STORE_FAST                      7: _var_var_20
                496     LOAD_GLOBAL                     17: NULL + print
                506     PUSH_NULL                       
                508     LOAD_CONST                      1: '__pyarmor_assert_14802__'
                510     LOAD_CONST                      24: 'DB_SET_RESULT_GROUPS:'   # b'\x81\xc6:,\x00\xdf\x8a\xed)\xdf>\xf5@\xd8\xc7\xa2=r\x8e\x97\x99\x91'
                512     CALL                            1
                520     LOAD_GLOBAL                     19: NULL + str
                530     LOAD_FAST                       7: _var_var_20
                532     CALL                            1
                540     BINARY_OP                       0 (+)
                544     CALL                            1
                552     POP_TOP                         
                554     LOAD_FAST                       2: ERROR
                556     LOAD_CONST                      25: 1
                558     BINARY_OP                       13 (+=)
                562     STORE_FAST                      2: ERROR
                564     LOAD_GLOBAL                     21: NULL + DB_SET_STATISTIC
                574     LOAD_FAST                       0: FILE_DB
                576     LOAD_FAST                       1: INFO
                578     LOAD_FAST                       2: ERROR
                580     CALL                            3
                588     SWAP                            2
                590     POP_EXCEPT                      
                592     LOAD_CONST                      0: None
                594     STORE_FAST                      7: _var_var_20
                596     DELETE_FAST                     7: _var_var_20
                598     NOP                             
                600     NOP                             
                602     NOP                             
                604     JUMP_FORWARD                    28 (to 662)
                606     CALL                            1
                614     POP_TOP                         
                616     RETURN_VALUE                    
                618     LOAD_CONST                      0: None
                620     STORE_FAST                      7: _var_var_20
                622     DELETE_FAST                     7: _var_var_20
                624     RERAISE                         1
                626     RERAISE                         0
                628     COPY                            3
                630     POP_EXCEPT                      
                632     RERAISE                         1
                634     PUSH_EXC_INFO                   
                636     PUSH_NULL                       
                638     LOAD_CONST                      5: '__pyarmor_exit_14804__'
                640     NOP                             
                642     LOAD_CONST                      3: b'<COAddr>\x07\x00\x00\x1a`\x02\x00\x00\x00\x00\x00\x00\x00\x00\x00\x00\x00\x00\x00\x00'
                644     CALL                            1
                652     POP_TOP                         
                654     RERAISE                         0
                656     COPY                            3
                658     POP_EXCEPT                      
                660     RERAISE                         1
                662     PUSH_NULL                       
                664     LOAD_CONST                      5: '__pyarmor_exit_14804__'
                666     LOAD_CONST                      3: b'<COAddr>\x07\x00\x00\x1a`\x02\x00\x00\x00\x00\x00\x00\x00\x00\x00\x00\x00\x00\x00\x00'
                668     BUILD_TUPLE                     1
                670     CALL_FUNCTION_EX                0
                672     POP_TOP                         
                674     RETURN_VALUE                    
            [Exception Table]
                28 to 38 -> 634 [0] 
                62 to 458 -> 478 [0] 
                478 to 496 -> 628 [1] lasti
                496 to 588 -> 618 [1] lasti
                588 to 590 -> 628 [1] lasti
                590 to 598 -> 634 [0] 
                618 to 628 -> 628 [1] lasti
                628 to 634 -> 634 [0] 
                634 to 656 -> 656 [1] lasti
        [Code]
            File Name: <frozen program.modules.Unsubscribe>
            Object Name: EntityCorrectGroup
            Qualified Name: EntityCorrectGroup
            Arg Count: 1
            Pos Only Arg Count: 0
            KW Only Arg Count: 0
            Stack Size: 12
            Flags: 0x20000003 (CO_OPTIMIZED | CO_NEWLOCALS | CO_PYARMOR_OBFUSCATED)
            [Names]
                'isinstance'
                'types'
                'User'
                'User_L199'
                'User_L195'
                'User_L185'
                'User_L184'
                'User_L166'
                'User_L165'
                'User_L159'
                'id'
                'hasattr'
                'username'
                'title'
                'participants_count'
                'photo'
                'ChatPhoto'
                'default_banned_rights'
                'invite_users'
                'send_messages'
                'send_media'
                'send_stickers'
                'send_polls'
                'slowmode_enabled'
                'scam'
                'Chat'
                'Channel'
                'Channel_L203'
                'Channel_L199'
                'Channel_L195'
                'Channel_L185'
                'Channel_L167'
                'Channel_L166'
                'Channel_L165'
                'Channel_L161'
                'megagroup'
                'gigagroup'
            [Locals+Names]
                'entity'
                '__assert_armored__'
                '_var_var_21'
            [Constants]
                None
                '__pyarmor_assert_14805__'
                '__pyarmor_enter_14806__'
                b'<COAddr>\x07\x00\x00\x1a\x98\x08\x00\x00\x00\x00\x00\x00\x00\x00\x00\x00\x00\x00\x00\x00'
                '__pyarmor_exit_14807__'
                False
                'id'
                'username'
                'title'
                'participants_count'   # b"\x81\xf2\x19\x01'\xf3\xbd\xdb\x0b\xfb\x03\xd4\x7f\xd3\xfb\x8a\x1aS\xaf"
                'count'
                'photo'
                1
                0
                'default_banned_rights'   # b'\x81\xe6\x1d\x152\xef\xb2\xc6$\xf8\x0c\xceb\xe9\xfc\xba\x1dT\xbc\xaf\xbe\xd8'
                'invite'
                'send_messages'   # b'\x81\xf1\x1d\x1d7\xc5\xb3\xd7\x08\xe9\x0c\xc7i\xff'
                'send_media'   # b'\x81\xf1\x1d\x1d7\xc5\xb3\xd7\x1f\xf3\x0c'
                'send_stickers'   # b'\x81\xf1\x1d\x1d7\xc5\xad\xc6\x12\xf9\x06\xc5~\xff'
                'send_polls'   # b'\x81\xf1\x1d\x1d7\xc5\xae\xdd\x17\xf6\x1e'
                'slowmode_enabled'   # b'\x81\xf1\x14\x1c$\xf7\xb1\xd6\x1e\xc5\x08\xcem\xee\xf4\x80\x0b'
                'slowmode'
                'scam'
                'CHAT'
                'type'
                'megagroup'   # b'\x81\xef\x1d\x142\xfd\xac\xdd\x0e\xea'
                'gigagroup'   # b'\x81\xe5\x11\x142\xfd\xac\xdd\x0e\xea'
                'MEGA_GROUP'   # b'\x81\xcf=4\x12\xc5\x99\xe04\xcf='
                'GIGA_GROUP'   # b'\x81\xc514\x12\xc5\x99\xe04\xcf='
                'CHANNEL'
                'NotDefined'   # b'\x81\xcc\x17\x07\x17\xff\xb8\xdb\x15\xff\t'
                'Ready'
                'status'
            [Disassembly]
                0       NOP                             
                2       NOP                             
                4       PUSH_NULL                       
                6       LOAD_CONST                      2: '__pyarmor_enter_14806__'
                8       LOAD_CONST                      3: b'<COAddr>\x07\x00\x00\x1a\x98\x08\x00\x00\x00\x00\x00\x00\x00\x00\x00\x00\x00\x00\x00\x00'
                10      BUILD_TUPLE                     1
                12      CALL_FUNCTION_EX                0
                14      POP_TOP                         
                16      RESUME                          0
                18      NOP                             
                20      NOP                             
                22      NOP                             
                24      NOP                             
                26      NOP                             
                28      LOAD_FAST                       0: entity
                30      LOAD_CONST                      0: None
                32      COMPARE_OP                      40 (==)
                36      POP_JUMP_IF_FALSE               11 (to 60)
                38      NOP                             
                40      LOAD_CONST                      5: False
                42      NOP                             
                44      NOP                             
                46      JUMP_FORWARD                    1102 (to 2254)
                56      POP_TOP                         
                58      RETURN_CONST                    5: False
                60      LOAD_FAST                       0: entity
                62      LOAD_CONST                      5: False
                64      COMPARE_OP                      40 (==)
                68      POP_JUMP_IF_FALSE               11 (to 92)
                70      NOP                             
                72      LOAD_CONST                      5: False
                74      NOP                             
                76      NOP                             
                78      JUMP_FORWARD                    1086 (to 2254)
                88      POP_TOP                         
                90      RETURN_CONST                    5: False
                92      LOAD_GLOBAL                     1: NULL + isinstance
                102     LOAD_FAST                       0: entity
                104     LOAD_GLOBAL                     2: types
                114     LOAD_ATTR                       4: User
                134     LOAD_GLOBAL                     2: types
                144     LOAD_ATTR                       6: User_L199
                164     LOAD_GLOBAL                     2: types
                174     LOAD_ATTR                       8: User_L195
                194     LOAD_GLOBAL                     2: types
                204     LOAD_ATTR                       10: User_L185
                224     LOAD_GLOBAL                     2: types
                234     LOAD_ATTR                       12: User_L184
                254     LOAD_GLOBAL                     2: types
                264     LOAD_ATTR                       14: User_L166
                284     LOAD_GLOBAL                     2: types
                294     LOAD_ATTR                       16: User_L165
                314     LOAD_GLOBAL                     2: types
                324     LOAD_ATTR                       18: User_L159
                344     BUILD_TUPLE                     8
                346     CALL                            2
                354     POP_JUMP_IF_FALSE               11 (to 378)
                356     NOP                             
                358     LOAD_CONST                      5: False
                360     NOP                             
                362     NOP                             
                364     JUMP_FORWARD                    943 (to 2254)
                374     POP_TOP                         
                376     RETURN_CONST                    5: False
                378     BUILD_MAP                       0
                380     STORE_FAST                      2: _var_var_21
                382     LOAD_FAST                       0: entity
                384     LOAD_ATTR                       20: id
                404     LOAD_FAST                       2: _var_var_21
                406     LOAD_CONST                      6: 'id'
                408     STORE_SUBSCR                    
                412     LOAD_GLOBAL                     23: NULL + hasattr
                422     LOAD_FAST                       0: entity
                424     LOAD_CONST                      7: 'username'
                426     CALL                            2
                434     POP_JUMP_IF_FALSE               16 (to 468)
                436     LOAD_FAST                       0: entity
                438     LOAD_ATTR                       24: username
                458     LOAD_FAST                       2: _var_var_21
                460     LOAD_CONST                      7: 'username'
                462     STORE_SUBSCR                    
                466     JUMP_FORWARD                    5 (to 478)
                468     LOAD_CONST                      0: None
                470     LOAD_FAST                       2: _var_var_21
                472     LOAD_CONST                      7: 'username'
                474     STORE_SUBSCR                    
                478     LOAD_GLOBAL                     23: NULL + hasattr
                488     LOAD_FAST                       0: entity
                490     LOAD_CONST                      8: 'title'
                492     CALL                            2
                500     POP_JUMP_IF_FALSE               16 (to 534)
                502     LOAD_FAST                       0: entity
                504     LOAD_ATTR                       26: title
                524     LOAD_FAST                       2: _var_var_21
                526     LOAD_CONST                      8: 'title'
                528     STORE_SUBSCR                    
                532     JUMP_FORWARD                    5 (to 544)
                534     LOAD_CONST                      0: None
                536     LOAD_FAST                       2: _var_var_21
                538     LOAD_CONST                      8: 'title'
                540     STORE_SUBSCR                    
                544     LOAD_GLOBAL                     23: NULL + hasattr
                554     LOAD_FAST                       0: entity
                556     PUSH_NULL                       
                558     LOAD_CONST                      1: '__pyarmor_assert_14805__'
                560     LOAD_CONST                      9: 'participants_count'   # b"\x81\xf2\x19\x01'\xf3\xbd\xdb\x0b\xfb\x03\xd4\x7f\xd3\xfb\x8a\x1aS\xaf"
                562     CALL                            1
                570     CALL                            2
                578     POP_JUMP_IF_FALSE               16 (to 612)
                580     LOAD_FAST                       0: entity
                582     LOAD_ATTR                       28: participants_count
                602     LOAD_FAST                       2: _var_var_21
                604     LOAD_CONST                      10: 'count'
                606     STORE_SUBSCR                    
                610     JUMP_FORWARD                    5 (to 622)
                612     LOAD_CONST                      0: None
                614     LOAD_FAST                       2: _var_var_21
                616     LOAD_CONST                      10: 'count'
                618     STORE_SUBSCR                    
                622     LOAD_GLOBAL                     23: NULL + hasattr
                632     LOAD_FAST                       0: entity
                634     LOAD_CONST                      11: 'photo'
                636     CALL                            2
                644     POP_JUMP_IF_FALSE               48 (to 742)
                646     LOAD_GLOBAL                     1: NULL + isinstance
                656     LOAD_FAST                       0: entity
                658     LOAD_ATTR                       30: photo
                678     LOAD_GLOBAL                     2: types
                688     LOAD_ATTR                       32: ChatPhoto
                708     CALL                            2
                716     POP_JUMP_IF_FALSE               6 (to 730)
                718     LOAD_CONST                      12: 1
                720     LOAD_FAST                       2: _var_var_21
                722     LOAD_CONST                      11: 'photo'
                724     STORE_SUBSCR                    
                728     JUMP_FORWARD                    11 (to 752)
                730     LOAD_CONST                      13: 0
                732     LOAD_FAST                       2: _var_var_21
                734     LOAD_CONST                      11: 'photo'
                736     STORE_SUBSCR                    
                740     JUMP_FORWARD                    5 (to 752)
                742     LOAD_CONST                      13: 0
                744     LOAD_FAST                       2: _var_var_21
                746     LOAD_CONST                      11: 'photo'
                748     STORE_SUBSCR                    
                752     LOAD_GLOBAL                     23: NULL + hasattr
                762     LOAD_FAST                       0: entity
                764     PUSH_NULL                       
                766     LOAD_CONST                      1: '__pyarmor_assert_14805__'
                768     LOAD_CONST                      14: 'default_banned_rights'   # b'\x81\xe6\x1d\x152\xef\xb2\xc6$\xf8\x0c\xceb\xe9\xfc\xba\x1dT\xbc\xaf\xbe\xd8'
                770     CALL                            1
                778     CALL                            2
                786     POP_JUMP_IF_FALSE               279 (to 1348)
                790     LOAD_FAST                       0: entity
                792     LOAD_ATTR                       34: default_banned_rights
                812     LOAD_CONST                      0: None
                814     COMPARE_OP                      55 (!=)
                818     POP_JUMP_IF_FALSE               214 (to 1248)
                820     LOAD_FAST                       0: entity
                822     LOAD_ATTR                       34: default_banned_rights
                842     LOAD_ATTR                       36: invite_users
                862     POP_JUMP_IF_FALSE               6 (to 876)
                864     LOAD_CONST                      12: 1
                866     LOAD_FAST                       2: _var_var_21
                868     LOAD_CONST                      15: 'invite'
                870     STORE_SUBSCR                    
                874     JUMP_FORWARD                    5 (to 886)
                876     LOAD_CONST                      13: 0
                878     LOAD_FAST                       2: _var_var_21
                880     LOAD_CONST                      15: 'invite'
                882     STORE_SUBSCR                    
                886     LOAD_FAST                       0: entity
                888     LOAD_ATTR                       34: default_banned_rights
                908     LOAD_ATTR                       38: send_messages
                928     POP_JUMP_IF_FALSE               12 (to 954)
                930     LOAD_CONST                      12: 1
                932     LOAD_FAST                       2: _var_var_21
                934     PUSH_NULL                       
                936     LOAD_CONST                      1: '__pyarmor_assert_14805__'
                938     LOAD_CONST                      16: 'send_messages'   # b'\x81\xf1\x1d\x1d7\xc5\xb3\xd7\x08\xe9\x0c\xc7i\xff'
                940     CALL                            1
                948     STORE_SUBSCR                    
                952     JUMP_FORWARD                    11 (to 976)
                954     LOAD_CONST                      13: 0
                956     LOAD_FAST                       2: _var_var_21
                958     PUSH_NULL                       
                960     LOAD_CONST                      1: '__pyarmor_assert_14805__'
                962     LOAD_CONST                      16: 'send_messages'   # b'\x81\xf1\x1d\x1d7\xc5\xb3\xd7\x08\xe9\x0c\xc7i\xff'
                964     CALL                            1
                972     STORE_SUBSCR                    
                976     LOAD_FAST                       0: entity
                978     LOAD_ATTR                       34: default_banned_rights
                998     LOAD_ATTR                       40: send_media
                1018    POP_JUMP_IF_FALSE               12 (to 1044)
                1020    LOAD_CONST                      12: 1
                1022    LOAD_FAST                       2: _var_var_21
                1024    PUSH_NULL                       
                1026    LOAD_CONST                      1: '__pyarmor_assert_14805__'
                1028    LOAD_CONST                      17: 'send_media'   # b'\x81\xf1\x1d\x1d7\xc5\xb3\xd7\x1f\xf3\x0c'
                1030    CALL                            1
                1038    STORE_SUBSCR                    
                1042    JUMP_FORWARD                    11 (to 1066)
                1044    LOAD_CONST                      13: 0
                1046    LOAD_FAST                       2: _var_var_21
                1048    PUSH_NULL                       
                1050    LOAD_CONST                      1: '__pyarmor_assert_14805__'
                1052    LOAD_CONST                      17: 'send_media'   # b'\x81\xf1\x1d\x1d7\xc5\xb3\xd7\x1f\xf3\x0c'
                1054    CALL                            1
                1062    STORE_SUBSCR                    
                1066    LOAD_FAST                       0: entity
                1068    LOAD_ATTR                       34: default_banned_rights
                1088    LOAD_ATTR                       42: send_stickers
                1108    POP_JUMP_IF_FALSE               12 (to 1134)
                1110    LOAD_CONST                      12: 1
                1112    LOAD_FAST                       2: _var_var_21
                1114    PUSH_NULL                       
                1116    LOAD_CONST                      1: '__pyarmor_assert_14805__'
                1118    LOAD_CONST                      18: 'send_stickers'   # b'\x81\xf1\x1d\x1d7\xc5\xad\xc6\x12\xf9\x06\xc5~\xff'
                1120    CALL                            1
                1128    STORE_SUBSCR                    
                1132    JUMP_FORWARD                    11 (to 1156)
                1134    LOAD_CONST                      13: 0
                1136    LOAD_FAST                       2: _var_var_21
                1138    PUSH_NULL                       
                1140    LOAD_CONST                      1: '__pyarmor_assert_14805__'
                1142    LOAD_CONST                      18: 'send_stickers'   # b'\x81\xf1\x1d\x1d7\xc5\xad\xc6\x12\xf9\x06\xc5~\xff'
                1144    CALL                            1
                1152    STORE_SUBSCR                    
                1156    LOAD_FAST                       0: entity
                1158    LOAD_ATTR                       34: default_banned_rights
                1178    LOAD_ATTR                       44: send_polls
                1198    POP_JUMP_IF_FALSE               12 (to 1224)
                1200    LOAD_CONST                      12: 1
                1202    LOAD_FAST                       2: _var_var_21
                1204    PUSH_NULL                       
                1206    LOAD_CONST                      1: '__pyarmor_assert_14805__'
                1208    LOAD_CONST                      19: 'send_polls'   # b'\x81\xf1\x1d\x1d7\xc5\xae\xdd\x17\xf6\x1e'
                1210    CALL                            1
                1218    STORE_SUBSCR                    
                1222    JUMP_FORWARD                    111 (to 1446)
                1224    LOAD_CONST                      13: 0
                1226    LOAD_FAST                       2: _var_var_21
                1228    PUSH_NULL                       
                1230    LOAD_CONST                      1: '__pyarmor_assert_14805__'
                1232    LOAD_CONST                      19: 'send_polls'   # b'\x81\xf1\x1d\x1d7\xc5\xae\xdd\x17\xf6\x1e'
                1234    CALL                            1
                1242    STORE_SUBSCR                    
                1246    JUMP_FORWARD                    99 (to 1446)
                1248    LOAD_CONST                      12: 1
                1250    LOAD_FAST                       2: _var_var_21
                1252    LOAD_CONST                      15: 'invite'
                1254    STORE_SUBSCR                    
                1258    LOAD_CONST                      12: 1
                1260    LOAD_FAST                       2: _var_var_21
                1262    PUSH_NULL                       
                1264    LOAD_CONST                      1: '__pyarmor_assert_14805__'
                1266    LOAD_CONST                      16: 'send_messages'   # b'\x81\xf1\x1d\x1d7\xc5\xb3\xd7\x08\xe9\x0c\xc7i\xff'
                1268    CALL                            1
                1276    STORE_SUBSCR                    
                1280    LOAD_CONST                      12: 1
                1282    LOAD_FAST                       2: _var_var_21
                1284    PUSH_NULL                       
                1286    LOAD_CONST                      1: '__pyarmor_assert_14805__'
                1288    LOAD_CONST                      17: 'send_media'   # b'\x81\xf1\x1d\x1d7\xc5\xb3\xd7\x1f\xf3\x0c'
                1290    CALL                            1
                1298    STORE_SUBSCR                    
                1302    LOAD_CONST                      12: 1
                1304    LOAD_FAST                       2: _var_var_21
                1306    PUSH_NULL                       
                1308    LOAD_CONST                      1: '__pyarmor_assert_14805__'
                1310    LOAD_CONST                      18: 'send_stickers'   # b'\x81\xf1\x1d\x1d7\xc5\xad\xc6\x12\xf9\x06\xc5~\xff'
                1312    CALL                            1
                1320    STORE_SUBSCR                    
                1324    LOAD_CONST                      12: 1
                1326    LOAD_FAST                       2: _var_var_21
                1328    PUSH_NULL                       
                1330    LOAD_CONST                      1: '__pyarmor_assert_14805__'
                1332    LOAD_CONST                      19: 'send_polls'   # b'\x81\xf1\x1d\x1d7\xc5\xae\xdd\x17\xf6\x1e'
                1334    CALL                            1
                1342    STORE_SUBSCR                    
                1346    JUMP_FORWARD                    49 (to 1446)
                1348    LOAD_CONST                      13: 0
                1350    LOAD_FAST                       2: _var_var_21
                1352    LOAD_CONST                      15: 'invite'
                1354    STORE_SUBSCR                    
                1358    LOAD_CONST                      13: 0
                1360    LOAD_FAST                       2: _var_var_21
                1362    PUSH_NULL                       
                1364    LOAD_CONST                      1: '__pyarmor_assert_14805__'
                1366    LOAD_CONST                      16: 'send_messages'   # b'\x81\xf1\x1d\x1d7\xc5\xb3\xd7\x08\xe9\x0c\xc7i\xff'
                1368    CALL                            1
                1376    STORE_SUBSCR                    
                1380    LOAD_CONST                      13: 0
                1382    LOAD_FAST                       2: _var_var_21
                1384    PUSH_NULL                       
                1386    LOAD_CONST                      1: '__pyarmor_assert_14805__'
                1388    LOAD_CONST                      17: 'send_media'   # b'\x81\xf1\x1d\x1d7\xc5\xb3\xd7\x1f\xf3\x0c'
                1390    CALL                            1
                1398    STORE_SUBSCR                    
                1402    LOAD_CONST                      13: 0
                1404    LOAD_FAST                       2: _var_var_21
                1406    PUSH_NULL                       
                1408    LOAD_CONST                      1: '__pyarmor_assert_14805__'
                1410    LOAD_CONST                      18: 'send_stickers'   # b'\x81\xf1\x1d\x1d7\xc5\xad\xc6\x12\xf9\x06\xc5~\xff'
                1412    CALL                            1
                1420    STORE_SUBSCR                    
                1424    LOAD_CONST                      13: 0
                1426    LOAD_FAST                       2: _var_var_21
                1428    PUSH_NULL                       
                1430    LOAD_CONST                      1: '__pyarmor_assert_14805__'
                1432    LOAD_CONST                      19: 'send_polls'   # b'\x81\xf1\x1d\x1d7\xc5\xae\xdd\x17\xf6\x1e'
                1434    CALL                            1
                1442    STORE_SUBSCR                    
                1446    LOAD_GLOBAL                     23: NULL + hasattr
                1456    LOAD_FAST                       0: entity
                1458    PUSH_NULL                       
                1460    LOAD_CONST                      1: '__pyarmor_assert_14805__'
                1462    LOAD_CONST                      20: 'slowmode_enabled'   # b'\x81\xf1\x14\x1c$\xf7\xb1\xd6\x1e\xc5\x08\xcem\xee\xf4\x80\x0b'
                1464    CALL                            1
                1472    CALL                            2
                1480    POP_JUMP_IF_FALSE               24 (to 1530)
                1482    LOAD_FAST                       0: entity
                1484    LOAD_ATTR                       46: slowmode_enabled
                1504    POP_JUMP_IF_FALSE               6 (to 1518)
                1506    LOAD_CONST                      12: 1
                1508    LOAD_FAST                       2: _var_var_21
                1510    LOAD_CONST                      21: 'slowmode'
                1512    STORE_SUBSCR                    
                1516    JUMP_FORWARD                    11 (to 1540)
                1518    LOAD_CONST                      13: 0
                1520    LOAD_FAST                       2: _var_var_21
                1522    LOAD_CONST                      21: 'slowmode'
                1524    STORE_SUBSCR                    
                1528    JUMP_FORWARD                    5 (to 1540)
                1530    LOAD_CONST                      13: 0
                1532    LOAD_FAST                       2: _var_var_21
                1534    LOAD_CONST                      21: 'slowmode'
                1536    STORE_SUBSCR                    
                1540    LOAD_GLOBAL                     23: NULL + hasattr
                1550    LOAD_FAST                       0: entity
                1552    LOAD_CONST                      22: 'scam'
                1554    CALL                            2
                1562    POP_JUMP_IF_FALSE               24 (to 1612)
                1564    LOAD_FAST                       0: entity
                1566    LOAD_ATTR                       48: scam
                1586    POP_JUMP_IF_FALSE               6 (to 1600)
                1588    LOAD_CONST                      12: 1
                1590    LOAD_FAST                       2: _var_var_21
                1592    LOAD_CONST                      22: 'scam'
                1594    STORE_SUBSCR                    
                1598    JUMP_FORWARD                    11 (to 1622)
                1600    LOAD_CONST                      13: 0
                1602    LOAD_FAST                       2: _var_var_21
                1604    LOAD_CONST                      22: 'scam'
                1606    STORE_SUBSCR                    
                1610    JUMP_FORWARD                    5 (to 1622)
                1612    LOAD_CONST                      13: 0
                1614    LOAD_FAST                       2: _var_var_21
                1616    LOAD_CONST                      22: 'scam'
                1618    STORE_SUBSCR                    
                1622    LOAD_GLOBAL                     1: NULL + isinstance
                1632    LOAD_FAST                       0: entity
                1634    LOAD_GLOBAL                     2: types
                1644    LOAD_ATTR                       50: Chat
                1664    CALL                            2
                1672    POP_JUMP_IF_FALSE               6 (to 1686)
                1674    LOAD_CONST                      23: 'CHAT'
                1676    LOAD_FAST                       2: _var_var_21
                1678    LOAD_CONST                      24: 'type'
                1680    STORE_SUBSCR                    
                1684    JUMP_FORWARD                    254 (to 2194)
                1686    LOAD_GLOBAL                     1: NULL + isinstance
                1696    LOAD_FAST                       0: entity
                1698    LOAD_GLOBAL                     2: types
                1708    LOAD_ATTR                       52: Channel
                1728    LOAD_GLOBAL                     2: types
                1738    LOAD_ATTR                       54: Channel_L203
                1758    LOAD_GLOBAL                     2: types
                1768    LOAD_ATTR                       56: Channel_L199
                1788    LOAD_GLOBAL                     2: types
                1798    LOAD_ATTR                       58: Channel_L195
                1818    LOAD_GLOBAL                     2: types
                1828    LOAD_ATTR                       60: Channel_L185
                1848    LOAD_GLOBAL                     2: types
                1858    LOAD_ATTR                       62: Channel_L167
                1878    LOAD_GLOBAL                     2: types
                1888    LOAD_ATTR                       64: Channel_L166
                1908    LOAD_GLOBAL                     2: types
                1918    LOAD_ATTR                       66: Channel_L165
                1938    LOAD_GLOBAL                     2: types
                1948    LOAD_ATTR                       68: Channel_L161
                1968    BUILD_TUPLE                     9
                1970    CALL                            2
                1978    POP_JUMP_IF_FALSE               96 (to 2172)
                1980    LOAD_GLOBAL                     23: NULL + hasattr
                1990    LOAD_FAST                       0: entity
                1992    PUSH_NULL                       
                1994    LOAD_CONST                      1: '__pyarmor_assert_14805__'
                1996    LOAD_CONST                      25: 'megagroup'   # b'\x81\xef\x1d\x142\xfd\xac\xdd\x0e\xea'
                1998    CALL                            1
                2006    CALL                            2
                2014    POP_JUMP_IF_FALSE               72 (to 2160)
                2016    LOAD_GLOBAL                     23: NULL + hasattr
                2026    LOAD_FAST                       0: entity
                2028    PUSH_NULL                       
                2030    LOAD_CONST                      1: '__pyarmor_assert_14805__'
                2032    LOAD_CONST                      26: 'gigagroup'   # b'\x81\xe5\x11\x142\xfd\xac\xdd\x0e\xea'
                2034    CALL                            1
                2042    CALL                            2
                2050    POP_JUMP_IF_FALSE               54 (to 2160)
                2052    LOAD_FAST                       0: entity
                2054    LOAD_ATTR                       70: megagroup
                2074    POP_JUMP_IF_FALSE               12 (to 2100)
                2076    PUSH_NULL                       
                2078    LOAD_CONST                      1: '__pyarmor_assert_14805__'
                2080    LOAD_CONST                      27: 'MEGA_GROUP'   # b'\x81\xcf=4\x12\xc5\x99\xe04\xcf='
                2082    CALL                            1
                2090    LOAD_FAST                       2: _var_var_21
                2092    LOAD_CONST                      24: 'type'
                2094    STORE_SUBSCR                    
                2098    JUMP_FORWARD                    47 (to 2194)
                2100    LOAD_FAST                       0: entity
                2102    LOAD_ATTR                       72: gigagroup
                2122    POP_JUMP_IF_FALSE               12 (to 2148)
                2124    PUSH_NULL                       
                2126    LOAD_CONST                      1: '__pyarmor_assert_14805__'
                2128    LOAD_CONST                      28: 'GIGA_GROUP'   # b'\x81\xc514\x12\xc5\x99\xe04\xcf='
                2130    CALL                            1
                2138    LOAD_FAST                       2: _var_var_21
                2140    LOAD_CONST                      24: 'type'
                2142    STORE_SUBSCR                    
                2146    JUMP_FORWARD                    23 (to 2194)
                2148    LOAD_CONST                      29: 'CHANNEL'
                2150    LOAD_FAST                       2: _var_var_21
                2152    LOAD_CONST                      24: 'type'
                2154    STORE_SUBSCR                    
                2158    JUMP_FORWARD                    17 (to 2194)
                2160    LOAD_CONST                      29: 'CHANNEL'
                2162    LOAD_FAST                       2: _var_var_21
                2164    LOAD_CONST                      24: 'type'
                2166    STORE_SUBSCR                    
                2170    JUMP_FORWARD                    11 (to 2194)
                2172    PUSH_NULL                       
                2174    LOAD_CONST                      1: '__pyarmor_assert_14805__'
                2176    LOAD_CONST                      30: 'NotDefined'   # b'\x81\xcc\x17\x07\x17\xff\xb8\xdb\x15\xff\t'
                2178    CALL                            1
                2186    LOAD_FAST                       2: _var_var_21
                2188    LOAD_CONST                      24: 'type'
                2190    STORE_SUBSCR                    
                2194    LOAD_CONST                      31: 'Ready'
                2196    LOAD_FAST                       2: _var_var_21
                2198    LOAD_CONST                      32: 'status'
                2200    STORE_SUBSCR                    
                2204    LOAD_FAST                       2: _var_var_21
                2206    NOP                             
                2208    NOP                             
                2210    NOP                             
                2212    JUMP_FORWARD                    20 (to 2254)
                2214    CALL                            1
                2222    POP_TOP                         
                2224    RETURN_VALUE                    
                2226    PUSH_EXC_INFO                   
                2228    PUSH_NULL                       
                2230    LOAD_CONST                      4: '__pyarmor_exit_14807__'
                2232    NOP                             
                2234    LOAD_CONST                      3: b'<COAddr>\x07\x00\x00\x1a\x98\x08\x00\x00\x00\x00\x00\x00\x00\x00\x00\x00\x00\x00\x00\x00'
                2236    CALL                            1
                2244    POP_TOP                         
                2246    RERAISE                         0
                2248    COPY                            3
                2250    POP_EXCEPT                      
                2252    RERAISE                         1
                2254    PUSH_NULL                       
                2256    LOAD_CONST                      4: '__pyarmor_exit_14807__'
                2258    LOAD_CONST                      3: b'<COAddr>\x07\x00\x00\x1a\x98\x08\x00\x00\x00\x00\x00\x00\x00\x00\x00\x00\x00\x00\x00\x00'
                2260    BUILD_TUPLE                     1
                2262    CALL_FUNCTION_EX                0
                2264    POP_TOP                         
                2266    RETURN_VALUE                    
            [Exception Table]
                28 to 38 -> 2226 [0] 
                60 to 70 -> 2226 [0] 
                92 to 356 -> 2226 [0] 
                378 to 2206 -> 2226 [0] 
                2226 to 2248 -> 2248 [1] lasti
        [Code]
            File Name: <frozen program.modules.Unsubscribe>
            Object Name: Unsubscribes
            Qualified Name: Unsubscribes
            Arg Count: 7
            Pos Only Arg Count: 0
            KW Only Arg Count: 0
            Stack Size: 11
            Flags: 0x20000003 (CO_OPTIMIZED | CO_NEWLOCALS | CO_PYARMOR_OBFUSCATED)
            [Names]
                'Thread_wait'
                'account_works'
                'Lang'
                'Disconnect'
                'Logs'
                'PrintLog'
                'functions'
                'account'
                'UpdateStatusRequest'
                'get'
                'int'
                'is_set'
                'StopProgram'
                'iter_dialogs'
                'hasattr'
                'EntityCorrectGroup'
                'entity'
                'delete'
                'DB_SET_STATISTIC'
                'errors'
                'FloodWaitError'
                'PeerFloodError'
                'ChatIdInvalidError'
                'PeerIdInvalidError'
                'UserNotParticipantError'
                'Exception'
                'seconds'
                'random'
                'randint'
                'DelayOnline'
                'BaseException'
                'logging'
            [Locals+Names]
                'account'
                'config'
                'proxy'
                'data'
                'statistic'
                'stop_thread'
                'err'
                '__assert_armored__'
                '_var_var_22'
                '_var_var_23'
                '_var_var_24'
                '_var_var_25'
                '_var_var_26'
                '_var_var_6'
                '_var_var_27'
                '_var_var_28'
                '_var_var_29'
                '_var_var_30'
                '_var_var_31'
                '_var_var_21'
                '_var_var_20'
                '_var_var_32'
                '_var_var_33'
                '_var_var_3'
            [Constants]
                None
                '__pyarmor_assert_14808__'
                '__pyarmor_enter_14809__'
                b'<COAddr>\x05\x00\x00\x1a\xac\x0b\x00\x00\x00\x00\x00\x00\x00\x00\x00\x00\x00\x00\x00\x00'
                'Unsubscribes'   # b'\x81\xd7\x16\x00&\xf8\xad\xd1\t\xf3\x0f\xc5\x7f'
                (
                    'module'
                )
                False
                'false'
                (
                    'account'
                    'status'
                )
                'work_account_completed'   # b'\x81\xf5\x17\x018\xc5\xbf\xd1\x18\xf5\x18\xcex\xd3\xfb\x8a\x02M\xb7\xa2\xbe\xceJ'
                (
                    'config'
                    'account'
                    'message'
                )
                'done'
                '__pyarmor_exit_14810__'
                (
                    'offline'
                )
                'Settings'
                'unsubscribe_channel'   # b'\x81\xf7\x16\x00&\xf8\xad\xd1\t\xf3\x0f\xc5S\xef\xf0\x84\x01S\xbe\xab'
                'unsubscribe_group'   # b'\x81\xf7\x16\x00&\xf8\xad\xd1\t\xf3\x0f\xc5S\xeb\xea\x8a\x1aM'
                'wait_from'   # b"\x81\xf5\x19\x1a'\xc5\xb8\xc0\x14\xf7"
                'wait_to'
                'use_stat'
                0
                'Done'
                500
                (
                    'limit'
                )
                'entity'
                True
                'type'
                'MEGA_GROUP'   # b'\x81\xcf=4\x12\xc5\x99\xe04\xcf='
                'GIGA_GROUP'   # b'\x81\xc514\x12\xc5\x99\xe04\xcf='
                'CHAT'
                'left_group'   # b"\x81\xee\x1d\x15'\xc5\xb9\xc0\x14\xef\x1d"
                'title'
                (
                    'config'
                    'account'
                    'message'
                    'param'
                )
                1
                'CHANNEL'
                'left_channel'   # b"\x81\xee\x1d\x15'\xc5\xbd\xda\x1a\xf4\x03\xc5`"
                'FloodWaitError'   # b'\x81\xc4\x14\x1c<\xfe\x89\xd3\x12\xee(\xd2~\xe3\xea'
                'PeerFloodError'   # b'\x81\xd2\x1d\x16!\xdc\xb2\xdd\x14\xfe(\xd2~\xe3\xea'
                'ChatIdInvalidError'   # b"\x81\xc1\x10\x12'\xd3\xba\xfb\x15\xec\x0c\xcce\xe8\xdd\x97\x1dR\xa9"
                'PeerIdInvalidError'   # b'\x81\xd2\x1d\x16!\xd3\xba\xfb\x15\xec\x0c\xcce\xe8\xdd\x97\x1dR\xa9'
                'UserNotParticipantError'   # b'\x81\xd7\x0b\x16!\xd4\xb1\xc6+\xfb\x1f\xd4e\xef\xf1\x95\x0eS\xaf\x82\xb8\xd9A\xde'
                'Exception'   # b'\x81\xc7\x00\x106\xea\xaa\xdb\x14\xf4'
                'an_unhandled_error_was_detected'   # b'\x81\xe3\x16,&\xf4\xb6\xd3\x15\xfe\x01\xc5h\xd3\xfd\x97\x1dR\xa9\x98\xbd\xca]\xf3\x01j\xb7Y\x03\xa5\x1b\xe1'
                30
                'restriction_detected'   # b"\x81\xf0\x1d\x00'\xe8\xb7\xd1\x0f\xf3\x02\xceS\xe8\xfd\x91\n^\xaf\xa2\xae"
                10
                20
                'algorithm_running_wait'   # b'\x81\xe3\x14\x14<\xe8\xb7\xc6\x13\xf72\xd2y\xe2\xf6\x8c\x01Z\x84\xb0\xab\xc2Z'
                'back_in_ranks'   # b'\x81\xe0\x19\x108\xc5\xb7\xdc$\xe8\x0c\xceg\xff'
            [Disassembly]
                0       NOP                             
                2       NOP                             
                4       PUSH_NULL                       
                6       LOAD_CONST                      2: '__pyarmor_enter_14809__'
                8       LOAD_CONST                      3: b'<COAddr>\x05\x00\x00\x1a\xac\x0b\x00\x00\x00\x00\x00\x00\x00\x00\x00\x00\x00\x00\x00\x00'
                10      BUILD_TUPLE                     1
                12      CALL_FUNCTION_EX                0
                14      POP_TOP                         
                16      RESUME                          0
                18      NOP                             
                20      NOP                             
                22      NOP                             
                24      NOP                             
                26      NOP                             
                28      NOP                             
                30      LOAD_GLOBAL                     1: NULL + Thread_wait
                40      LOAD_FAST                       3: data
                42      LOAD_FAST                       1: config
                44      LOAD_FAST                       5: stop_thread
                46      CALL                            3
                54      POP_TOP                         
                56      LOAD_GLOBAL                     3: NULL + account_works
                66      LOAD_FAST                       1: config
                68      LOAD_GLOBAL                     4: Lang
                78      LOAD_FAST                       2: proxy
                80      LOAD_FAST                       0: account
                82      LOAD_FAST                       5: stop_thread
                84      PUSH_NULL                       
                86      LOAD_CONST                      1: '__pyarmor_assert_14808__'
                88      LOAD_CONST                      4: 'Unsubscribes'   # b'\x81\xd7\x16\x00&\xf8\xad\xd1\t\xf3\x0f\xc5\x7f'
                90      CALL                            1
                98      KW_NAMES                        5: ('module',)
                100     CALL                            6
                108     STORE_FAST                      8: _var_var_22
                110     LOAD_FAST                       8: _var_var_22
                112     LOAD_CONST                      6: False
                114     COMPARE_OP                      40 (==)
                118     POP_JUMP_IF_FALSE               68 (to 256)
                120     LOAD_FAST                       0: account
                122     LOAD_CONST                      7: 'false'
                124     LOAD_CONST                      8: ('account', 'status')
                126     BUILD_CONST_KEY_MAP             2
                128     LOAD_GLOBAL                     7: NULL + Disconnect
                138     LOAD_FAST                       8: _var_var_22
                140     CALL                            1
                148     POP_TOP                         
                150     LOAD_GLOBAL                     9: NULL + Logs
                160     LOAD_ATTR                       10: PrintLog
                180     LOAD_FAST                       1: config
                182     LOAD_FAST                       0: account
                184     LOAD_GLOBAL                     4: Lang
                194     PUSH_NULL                       
                196     LOAD_CONST                      1: '__pyarmor_assert_14808__'
                198     LOAD_CONST                      9: 'work_account_completed'   # b'\x81\xf5\x17\x018\xc5\xbf\xd1\x18\xf5\x18\xcex\xd3\xfb\x8a\x02M\xb7\xa2\xbe\xceJ'
                200     CALL                            1
                208     BINARY_SUBSCR                   
                212     KW_NAMES                        10: ('config', 'account', 'message')
                214     CALL                            3
                222     POP_TOP                         
                224     LOAD_FAST                       0: account
                226     LOAD_CONST                      11: 'done'
                228     LOAD_CONST                      8: ('account', 'status')
                230     BUILD_CONST_KEY_MAP             2
                232     SWAP                            2
                234     POP_TOP                         
                236     NOP                             
                238     NOP                             
                240     JUMP_FORWARD                    1399 (to 3042)
                244     CALL                            1
                252     POP_TOP                         
                254     RETURN_VALUE                    
                256     PUSH_NULL                       
                258     LOAD_FAST                       8: _var_var_22
                260     LOAD_GLOBAL                     12: functions
                270     LOAD_ATTR                       14: account
                290     LOAD_ATTR                       17: UpdateStatusRequest
                310     LOAD_CONST                      6: False
                312     KW_NAMES                        13: ('offline',)
                314     CALL                            1
                322     CALL                            1
                330     POP_TOP                         
                332     LOAD_FAST                       3: data
                334     LOAD_CONST                      14: 'Settings'
                336     BINARY_SUBSCR                   
                340     LOAD_ATTR                       19: get
                360     PUSH_NULL                       
                362     LOAD_CONST                      1: '__pyarmor_assert_14808__'
                364     LOAD_CONST                      15: 'unsubscribe_channel'   # b'\x81\xf7\x16\x00&\xf8\xad\xd1\t\xf3\x0f\xc5S\xef\xf0\x84\x01S\xbe\xab'
                366     CALL                            1
                374     CALL                            1
                382     STORE_FAST                      9: _var_var_23
                384     LOAD_FAST                       3: data
                386     LOAD_CONST                      14: 'Settings'
                388     BINARY_SUBSCR                   
                392     LOAD_ATTR                       19: get
                412     PUSH_NULL                       
                414     LOAD_CONST                      1: '__pyarmor_assert_14808__'
                416     LOAD_CONST                      16: 'unsubscribe_group'   # b'\x81\xf7\x16\x00&\xf8\xad\xd1\t\xf3\x0f\xc5S\xeb\xea\x8a\x1aM'
                418     CALL                            1
                426     CALL                            1
                434     STORE_FAST                      10: _var_var_24
                436     LOAD_GLOBAL                     21: NULL + int
                446     LOAD_FAST                       3: data
                448     LOAD_CONST                      14: 'Settings'
                450     BINARY_SUBSCR                   
                454     LOAD_ATTR                       19: get
                474     PUSH_NULL                       
                476     LOAD_CONST                      1: '__pyarmor_assert_14808__'
                478     LOAD_CONST                      17: 'wait_from'   # b"\x81\xf5\x19\x1a'\xc5\xb8\xc0\x14\xf7"
                480     CALL                            1
                488     CALL                            1
                496     CALL                            1
                504     STORE_FAST                      11: _var_var_25
                506     LOAD_GLOBAL                     21: NULL + int
                516     LOAD_FAST                       3: data
                518     LOAD_CONST                      14: 'Settings'
                520     BINARY_SUBSCR                   
                524     LOAD_ATTR                       19: get
                544     LOAD_CONST                      18: 'wait_to'
                546     CALL                            1
                554     CALL                            1
                562     STORE_FAST                      12: _var_var_26
                564     LOAD_FAST                       3: data
                566     LOAD_CONST                      14: 'Settings'
                568     BINARY_SUBSCR                   
                572     LOAD_ATTR                       19: get
                592     LOAD_CONST                      19: 'use_stat'
                594     CALL                            1
                602     STORE_FAST                      13: _var_var_6
                604     LOAD_CONST                      20: 0
                606     STORE_FAST                      14: _var_var_27
                608     LOAD_CONST                      21: 'Done'
                610     STORE_FAST                      15: _var_var_28
                612     LOAD_FAST                       5: stop_thread
                614     LOAD_ATTR                       23: is_set
                634     CALL                            0
                642     POP_JUMP_IF_FALSE               10 (to 664)
                644     LOAD_GLOBAL                     25: NULL + StopProgram
                654     CALL                            0
                662     RAISE_VARARGS                   1
                664     LOAD_FAST                       8: _var_var_22
                666     LOAD_ATTR                       27: iter_dialogs
                686     LOAD_CONST                      22: 500
                688     KW_NAMES                        23: ('limit',)
                690     CALL                            1
                698     STORE_FAST                      16: _var_var_29
                700     LOAD_FAST                       16: _var_var_29
                702     GET_ITER                        
                704     FOR_ITER                        480 (to 1668)
                710     STORE_FAST                      17: _var_var_30
                712     LOAD_CONST                      6: False
                714     STORE_FAST                      18: _var_var_31
                716     LOAD_FAST                       5: stop_thread
                718     LOAD_ATTR                       23: is_set
                738     CALL                            0
                746     POP_JUMP_IF_FALSE               10 (to 768)
                748     LOAD_GLOBAL                     25: NULL + StopProgram
                758     CALL                            0
                766     RAISE_VARARGS                   1
                768     LOAD_GLOBAL                     29: NULL + hasattr
                778     LOAD_FAST                       17: _var_var_30
                780     LOAD_CONST                      24: 'entity'
                782     CALL                            2
                790     POP_JUMP_IF_TRUE                1 (to 794)
                792     JUMP_BACKWARD                   45 (to 704)
                794     NOP                             
                796     LOAD_GLOBAL                     31: NULL + EntityCorrectGroup
                806     LOAD_FAST                       17: _var_var_30
                808     LOAD_ATTR                       32: entity
                828     CALL                            1
                836     STORE_FAST                      19: _var_var_21
                838     LOAD_FAST                       19: _var_var_21
                840     LOAD_CONST                      6: False
                842     COMPARE_OP                      55 (!=)
                846     POP_JUMP_IF_FALSE               206 (to 1260)
                848     LOAD_FAST                       10: _var_var_24
                850     LOAD_CONST                      25: True
                852     COMPARE_OP                      40 (==)
                856     POP_JUMP_IF_FALSE               100 (to 1058)
                858     LOAD_FAST                       19: _var_var_21
                860     LOAD_CONST                      26: 'type'
                862     BINARY_SUBSCR                   
                866     PUSH_NULL                       
                868     LOAD_CONST                      1: '__pyarmor_assert_14808__'
                870     LOAD_CONST                      27: 'MEGA_GROUP'   # b'\x81\xcf=4\x12\xc5\x99\xe04\xcf='
                872     CALL                            1
                880     COMPARE_OP                      40 (==)
                884     POP_JUMP_IF_TRUE                22 (to 930)
                886     LOAD_FAST                       19: _var_var_21
                888     LOAD_CONST                      26: 'type'
                890     BINARY_SUBSCR                   
                894     PUSH_NULL                       
                896     LOAD_CONST                      1: '__pyarmor_assert_14808__'
                898     LOAD_CONST                      28: 'GIGA_GROUP'   # b'\x81\xc514\x12\xc5\x99\xe04\xcf='
                900     CALL                            1
                908     COMPARE_OP                      40 (==)
                912     POP_JUMP_IF_TRUE                8 (to 930)
                914     LOAD_FAST                       19: _var_var_21
                916     LOAD_CONST                      26: 'type'
                918     BINARY_SUBSCR                   
                922     LOAD_CONST                      29: 'CHAT'
                924     COMPARE_OP                      40 (==)
                928     POP_JUMP_IF_FALSE               64 (to 1058)
                930     LOAD_FAST                       17: _var_var_30
                932     LOAD_ATTR                       35: delete
                952     CALL                            0
                960     POP_TOP                         
                962     LOAD_GLOBAL                     9: NULL + Logs
                972     LOAD_ATTR                       10: PrintLog
                992     LOAD_FAST                       1: config
                994     LOAD_FAST                       0: account
                996     LOAD_GLOBAL                     4: Lang
                1006    PUSH_NULL                       
                1008    LOAD_CONST                      1: '__pyarmor_assert_14808__'
                1010    LOAD_CONST                      30: 'left_group'   # b"\x81\xee\x1d\x15'\xc5\xb9\xc0\x14\xef\x1d"
                1012    CALL                            1
                1020    BINARY_SUBSCR                   
                1024    LOAD_FAST                       19: _var_var_21
                1026    LOAD_CONST                      31: 'title'
                1028    BINARY_SUBSCR                   
                1032    KW_NAMES                        32: ('config', 'account', 'message', 'param')
                1034    CALL                            4
                1042    POP_TOP                         
                1044    LOAD_FAST                       14: _var_var_27
                1046    LOAD_CONST                      33: 1
                1048    BINARY_OP                       13 (+=)
                1052    STORE_FAST                      14: _var_var_27
                1054    LOAD_CONST                      25: True
                1056    STORE_FAST                      18: _var_var_31
                1058    LOAD_FAST                       9: _var_var_23
                1060    LOAD_CONST                      25: True
                1062    COMPARE_OP                      40 (==)
                1066    POP_JUMP_IF_FALSE               72 (to 1212)
                1068    LOAD_FAST                       19: _var_var_21
                1070    LOAD_CONST                      26: 'type'
                1072    BINARY_SUBSCR                   
                1076    LOAD_CONST                      34: 'CHANNEL'
                1078    COMPARE_OP                      40 (==)
                1082    POP_JUMP_IF_FALSE               64 (to 1212)
                1084    LOAD_FAST                       17: _var_var_30
                1086    LOAD_ATTR                       35: delete
                1106    CALL                            0
                1114    POP_TOP                         
                1116    LOAD_GLOBAL                     9: NULL + Logs
                1126    LOAD_ATTR                       10: PrintLog
                1146    LOAD_FAST                       1: config
                1148    LOAD_FAST                       0: account
                1150    LOAD_GLOBAL                     4: Lang
                1160    PUSH_NULL                       
                1162    LOAD_CONST                      1: '__pyarmor_assert_14808__'
                1164    LOAD_CONST                      35: 'left_channel'   # b"\x81\xee\x1d\x15'\xc5\xbd\xda\x1a\xf4\x03\xc5`"
                1166    CALL                            1
                1174    BINARY_SUBSCR                   
                1178    LOAD_FAST                       19: _var_var_21
                1180    LOAD_CONST                      31: 'title'
                1182    BINARY_SUBSCR                   
                1186    KW_NAMES                        32: ('config', 'account', 'message', 'param')
                1188    CALL                            4
                1196    POP_TOP                         
                1198    LOAD_FAST                       14: _var_var_27
                1200    LOAD_CONST                      33: 1
                1202    BINARY_OP                       13 (+=)
                1206    STORE_FAST                      14: _var_var_27
                1208    LOAD_CONST                      25: True
                1210    STORE_FAST                      18: _var_var_31
                1212    LOAD_FAST                       18: _var_var_31
                1214    LOAD_CONST                      25: True
                1216    COMPARE_OP                      40 (==)
                1220    POP_JUMP_IF_FALSE               19 (to 1260)
                1222    LOAD_FAST                       13: _var_var_6
                1224    LOAD_CONST                      25: True
                1226    COMPARE_OP                      40 (==)
                1230    POP_JUMP_IF_FALSE               14 (to 1260)
                1232    LOAD_CONST                      6: False
                1234    STORE_FAST                      18: _var_var_31
                1236    LOAD_GLOBAL                     37: NULL + DB_SET_STATISTIC
                1246    LOAD_FAST                       4: statistic
                1248    LOAD_FAST                       19: _var_var_21
                1250    CALL                            2
                1258    POP_TOP                         
                1260    LOAD_FAST                       15: _var_var_28
                1262    PUSH_NULL                       
                1264    LOAD_CONST                      1: '__pyarmor_assert_14808__'
                1266    LOAD_CONST                      36: 'FloodWaitError'   # b'\x81\xc4\x14\x1c<\xfe\x89\xd3\x12\xee(\xd2~\xe3\xea'
                1268    CALL                            1
                1276    COMPARE_OP                      40 (==)
                1280    POP_JUMP_IF_FALSE               173 (to 1628)
                1282    LOAD_GLOBAL                     21: NULL + int
                1292    LOAD_FAST_CHECK                 20: _var_var_20
                1294    LOAD_ATTR                       52: seconds
                1314    CALL                            1
                1322    STORE_FAST                      21: _var_var_32
                1324    LOAD_GLOBAL                     9: NULL + Logs
                1334    LOAD_ATTR                       10: PrintLog
                1354    LOAD_FAST                       1: config
                1356    LOAD_FAST                       0: account
                1358    LOAD_GLOBAL                     4: Lang
                1368    PUSH_NULL                       
                1370    LOAD_CONST                      1: '__pyarmor_assert_14808__'
                1372    LOAD_CONST                      44: 'restriction_detected'   # b"\x81\xf0\x1d\x00'\xe8\xb7\xd1\x0f\xf3\x02\xceS\xe8\xfd\x91\n^\xaf\xa2\xae"
                1374    CALL                            1
                1382    BINARY_SUBSCR                   
                1386    KW_NAMES                        10: ('config', 'account', 'message')
                1388    CALL                            3
                1396    POP_TOP                         
                1398    LOAD_FAST                       21: _var_var_32
                1400    LOAD_GLOBAL                     55: NULL + random
                1410    LOAD_ATTR                       56: randint
                1430    LOAD_CONST                      45: 10
                1432    LOAD_CONST                      46: 20
                1434    CALL                            2
                1442    BINARY_OP                       0 (+)
                1446    STORE_FAST                      22: _var_var_33
                1448    LOAD_GLOBAL                     9: NULL + Logs
                1458    LOAD_ATTR                       10: PrintLog
                1478    LOAD_FAST                       1: config
                1480    LOAD_FAST                       0: account
                1482    LOAD_GLOBAL                     4: Lang
                1492    PUSH_NULL                       
                1494    LOAD_CONST                      1: '__pyarmor_assert_14808__'
                1496    LOAD_CONST                      47: 'algorithm_running_wait'   # b'\x81\xe3\x14\x14<\xe8\xb7\xc6\x13\xf72\xd2y\xe2\xf6\x8c\x01Z\x84\xb0\xab\xc2Z'
                1498    CALL                            1
                1506    BINARY_SUBSCR                   
                1510    LOAD_FAST                       22: _var_var_33
                1512    KW_NAMES                        32: ('config', 'account', 'message', 'param')
                1514    CALL                            4
                1522    POP_TOP                         
                1524    LOAD_GLOBAL                     59: NULL + DelayOnline
                1534    LOAD_FAST                       0: account
                1536    LOAD_FAST                       8: _var_var_22
                1538    LOAD_FAST                       22: _var_var_33
                1540    LOAD_FAST                       22: _var_var_33
                1542    LOAD_FAST                       5: stop_thread
                1544    CALL                            5
                1552    POP_TOP                         
                1554    LOAD_GLOBAL                     9: NULL + Logs
                1564    LOAD_ATTR                       10: PrintLog
                1584    LOAD_FAST                       1: config
                1586    LOAD_FAST                       0: account
                1588    LOAD_GLOBAL                     4: Lang
                1598    PUSH_NULL                       
                1600    LOAD_CONST                      1: '__pyarmor_assert_14808__'
                1602    LOAD_CONST                      48: 'back_in_ranks'   # b'\x81\xe0\x19\x108\xc5\xb7\xdc$\xe8\x0c\xceg\xff'
                1604    CALL                            1
                1612    BINARY_SUBSCR                   
                1616    KW_NAMES                        10: ('config', 'account', 'message')
                1618    CALL                            3
                1626    POP_TOP                         
                1628    LOAD_FAST                       18: _var_var_31
                1630    POP_JUMP_IF_TRUE                2 (to 1636)
                1632    JUMP_BACKWARD                   466 (to 704)
                1636    LOAD_GLOBAL                     59: NULL + DelayOnline
                1646    LOAD_FAST                       0: account
                1648    LOAD_FAST                       8: _var_var_22
                1650    LOAD_FAST                       11: _var_var_25
                1652    LOAD_FAST                       12: _var_var_26
                1654    LOAD_FAST                       5: stop_thread
                1656    CALL                            5
                1664    POP_TOP                         
                1666    JUMP_BACKWARD                   483 (to 704)
                1670    END_FOR                         
                1672    NOP                             
                1674    LOAD_GLOBAL                     7: NULL + Disconnect
                1684    LOAD_FAST_CHECK                 8: _var_var_22
                1686    CALL                            1
                1694    POP_TOP                         
                1696    LOAD_GLOBAL                     9: NULL + Logs
                1706    LOAD_ATTR                       10: PrintLog
                1726    LOAD_FAST                       1: config
                1728    LOAD_FAST                       0: account
                1730    LOAD_GLOBAL                     4: Lang
                1740    PUSH_NULL                       
                1742    LOAD_CONST                      1: '__pyarmor_assert_14808__'
                1744    LOAD_CONST                      9: 'work_account_completed'   # b'\x81\xf5\x17\x018\xc5\xbf\xd1\x18\xf5\x18\xcex\xd3\xfb\x8a\x02M\xb7\xa2\xbe\xceJ'
                1746    CALL                            1
                1754    BINARY_SUBSCR                   
                1758    KW_NAMES                        10: ('config', 'account', 'message')
                1760    CALL                            3
                1768    POP_TOP                         
                1770    LOAD_FAST                       0: account
                1772    LOAD_CONST                      11: 'done'
                1774    LOAD_CONST                      8: ('account', 'status')
                1776    BUILD_CONST_KEY_MAP             2
                1778    NOP                             
                1780    NOP                             
                1782    JUMP_FORWARD                    628 (to 3042)
                1786    CALL                            1
                1794    POP_TOP                         
                1796    RETURN_VALUE                    
                1798    PUSH_EXC_INFO                   
                1800    POP_TOP                         
                1802    POP_EXCEPT                      
                1804    JUMP_BACKWARD                   829 (to 150)
                1808    COPY                            3
                1810    POP_EXCEPT                      
                1812    RERAISE                         1
                1814    PUSH_EXC_INFO                   
                1816    POP_TOP                         
                1818    POP_EXCEPT                      
                1820    JUMP_BACKWARD                   385 (to 1054)
                1824    COPY                            3
                1826    POP_EXCEPT                      
                1828    RERAISE                         1
                1830    PUSH_EXC_INFO                   
                1832    POP_TOP                         
                1834    POP_EXCEPT                      
                1836    JUMP_BACKWARD                   316 (to 1208)
                1840    COPY                            3
                1842    POP_EXCEPT                      
                1844    RERAISE                         1
                1846    PUSH_EXC_INFO                   
                1848    LOAD_GLOBAL                     38: errors
                1858    LOAD_ATTR                       40: FloodWaitError
                1878    CHECK_EXC_MATCH                 
                1880    POP_JUMP_IF_FALSE               19 (to 1920)
                1882    STORE_FAST                      20: _var_var_20
                1884    PUSH_NULL                       
                1886    LOAD_CONST                      1: '__pyarmor_assert_14808__'
                1888    LOAD_CONST                      36: 'FloodWaitError'   # b'\x81\xc4\x14\x1c<\xfe\x89\xd3\x12\xee(\xd2~\xe3\xea'
                1890    CALL                            1
                1898    STORE_FAST                      15: _var_var_28
                1900    POP_EXCEPT                      
                1902    LOAD_CONST                      0: None
                1904    STORE_FAST                      20: _var_var_20
                1906    DELETE_FAST                     20: _var_var_20
                1908    JUMP_BACKWARD                   326 (to 1260)
                1912    LOAD_CONST                      0: None
                1914    STORE_FAST                      20: _var_var_20
                1916    DELETE_FAST                     20: _var_var_20
                1918    RERAISE                         1
                1920    LOAD_GLOBAL                     38: errors
                1930    LOAD_ATTR                       42: PeerFloodError
                1950    CHECK_EXC_MATCH                 
                1952    POP_JUMP_IF_FALSE               12 (to 1978)
                1954    POP_TOP                         
                1956    PUSH_NULL                       
                1958    LOAD_CONST                      1: '__pyarmor_assert_14808__'
                1960    LOAD_CONST                      37: 'PeerFloodError'   # b'\x81\xd2\x1d\x16!\xdc\xb2\xdd\x14\xfe(\xd2~\xe3\xea'
                1962    CALL                            1
                1970    STORE_FAST                      15: _var_var_28
                1972    POP_EXCEPT                      
                1974    JUMP_BACKWARD                   359 (to 1260)
                1978    LOAD_GLOBAL                     38: errors
                1988    LOAD_ATTR                       44: ChatIdInvalidError
                2008    CHECK_EXC_MATCH                 
                2010    POP_JUMP_IF_FALSE               12 (to 2036)
                2012    POP_TOP                         
                2014    PUSH_NULL                       
                2016    LOAD_CONST                      1: '__pyarmor_assert_14808__'
                2018    LOAD_CONST                      38: 'ChatIdInvalidError'   # b"\x81\xc1\x10\x12'\xd3\xba\xfb\x15\xec\x0c\xcce\xe8\xdd\x97\x1dR\xa9"
                2020    CALL                            1
                2028    STORE_FAST                      15: _var_var_28
                2030    POP_EXCEPT                      
                2032    JUMP_BACKWARD                   388 (to 1260)
                2036    LOAD_GLOBAL                     38: errors
                2046    LOAD_ATTR                       46: PeerIdInvalidError
                2066    CHECK_EXC_MATCH                 
                2068    POP_JUMP_IF_FALSE               12 (to 2094)
                2070    POP_TOP                         
                2072    PUSH_NULL                       
                2074    LOAD_CONST                      1: '__pyarmor_assert_14808__'
                2076    LOAD_CONST                      39: 'PeerIdInvalidError'   # b'\x81\xd2\x1d\x16!\xd3\xba\xfb\x15\xec\x0c\xcce\xe8\xdd\x97\x1dR\xa9'
                2078    CALL                            1
                2086    STORE_FAST                      15: _var_var_28
                2088    POP_EXCEPT                      
                2090    JUMP_BACKWARD                   417 (to 1260)
                2094    LOAD_GLOBAL                     38: errors
                2104    LOAD_ATTR                       48: UserNotParticipantError
                2124    CHECK_EXC_MATCH                 
                2126    POP_JUMP_IF_FALSE               12 (to 2152)
                2128    POP_TOP                         
                2130    PUSH_NULL                       
                2132    LOAD_CONST                      1: '__pyarmor_assert_14808__'
                2134    LOAD_CONST                      40: 'UserNotParticipantError'   # b'\x81\xd7\x0b\x16!\xd4\xb1\xc6+\xfb\x1f\xd4e\xef\xf1\x95\x0eS\xaf\x82\xb8\xd9A\xde'
                2136    CALL                            1
                2144    STORE_FAST                      15: _var_var_28
                2146    POP_EXCEPT                      
                2148    JUMP_BACKWARD                   446 (to 1260)
                2152    LOAD_GLOBAL                     50: Exception
                2162    CHECK_EXC_MATCH                 
                2164    POP_JUMP_IF_FALSE               57 (to 2280)
                2166    STORE_FAST                      20: _var_var_20
                2168    PUSH_NULL                       
                2170    LOAD_CONST                      1: '__pyarmor_assert_14808__'
                2172    LOAD_CONST                      41: 'Exception'   # b'\x81\xc7\x00\x106\xea\xaa\xdb\x14\xf4'
                2174    CALL                            1
                2182    STORE_FAST                      15: _var_var_28
                2184    LOAD_GLOBAL                     9: NULL + Logs
                2194    LOAD_ATTR                       10: PrintLog
                2214    LOAD_FAST                       1: config
                2216    LOAD_FAST                       0: account
                2218    LOAD_GLOBAL                     4: Lang
                2228    PUSH_NULL                       
                2230    LOAD_CONST                      1: '__pyarmor_assert_14808__'
                2232    LOAD_CONST                      42: 'an_unhandled_error_was_detected'   # b'\x81\xe3\x16,&\xf4\xb6\xd3\x15\xfe\x01\xc5h\xd3\xfd\x97\x1dR\xa9\x98\xbd\xca]\xf3\x01j\xb7Y\x03\xa5\x1b\xe1'
                2234    CALL                            1
                2242    BINARY_SUBSCR                   
                2246    LOAD_FAST                       20: _var_var_20
                2248    KW_NAMES                        32: ('config', 'account', 'message', 'param')
                2250    CALL                            4
                2258    POP_TOP                         
                2260    POP_EXCEPT                      
                2262    LOAD_CONST                      0: None
                2264    STORE_FAST                      20: _var_var_20
                2266    DELETE_FAST                     20: _var_var_20
                2268    JUMP_BACKWARD                   506 (to 1260)
                2272    LOAD_CONST                      0: None
                2274    STORE_FAST                      20: _var_var_20
                2276    DELETE_FAST                     20: _var_var_20
                2278    RERAISE                         1
                2280    RERAISE                         0
                2282    COPY                            3
                2284    POP_EXCEPT                      
                2286    RERAISE                         1
                2288    PUSH_EXC_INFO                   
                2290    POP_TOP                         
                2292    LOAD_CONST                      43: 30
                2294    STORE_FAST                      21: _var_var_32
                2296    POP_EXCEPT                      
                2298    JUMP_BACKWARD                   489 (to 1324)
                2302    COPY                            3
                2304    POP_EXCEPT                      
                2306    RERAISE                         1
                2308    PUSH_EXC_INFO                   
                2310    LOAD_FAST                       15: _var_var_28
                2312    PUSH_NULL                       
                2314    LOAD_CONST                      1: '__pyarmor_assert_14808__'
                2316    LOAD_CONST                      36: 'FloodWaitError'   # b'\x81\xc4\x14\x1c<\xfe\x89\xd3\x12\xee(\xd2~\xe3\xea'
                2318    CALL                            1
                2326    COMPARE_OP                      40 (==)
                2330    POP_JUMP_IF_FALSE               183 (to 2698)
                2332    LOAD_GLOBAL                     21: NULL + int
                2342    LOAD_FAST_CHECK                 20: _var_var_20
                2344    LOAD_ATTR                       52: seconds
                2364    CALL                            1
                2372    STORE_FAST                      21: _var_var_32
                2374    JUMP_FORWARD                    9 (to 2394)
                2376    PUSH_EXC_INFO                   
                2378    POP_TOP                         
                2380    LOAD_CONST                      43: 30
                2382    STORE_FAST                      21: _var_var_32
                2384    POP_EXCEPT                      
                2386    JUMP_FORWARD                    3 (to 2394)
                2388    COPY                            3
                2390    POP_EXCEPT                      
                2392    RERAISE                         1
                2394    LOAD_GLOBAL                     9: NULL + Logs
                2404    LOAD_ATTR                       10: PrintLog
                2424    LOAD_FAST                       1: config
                2426    LOAD_FAST                       0: account
                2428    LOAD_GLOBAL                     4: Lang
                2438    PUSH_NULL                       
                2440    LOAD_CONST                      1: '__pyarmor_assert_14808__'
                2442    LOAD_CONST                      44: 'restriction_detected'   # b"\x81\xf0\x1d\x00'\xe8\xb7\xd1\x0f\xf3\x02\xceS\xe8\xfd\x91\n^\xaf\xa2\xae"
                2444    CALL                            1
                2452    BINARY_SUBSCR                   
                2456    KW_NAMES                        10: ('config', 'account', 'message')
                2458    CALL                            3
                2466    POP_TOP                         
                2468    LOAD_FAST                       21: _var_var_32
                2470    LOAD_GLOBAL                     55: NULL + random
                2480    LOAD_ATTR                       56: randint
                2500    LOAD_CONST                      45: 10
                2502    LOAD_CONST                      46: 20
                2504    CALL                            2
                2512    BINARY_OP                       0 (+)
                2516    STORE_FAST                      22: _var_var_33
                2518    LOAD_GLOBAL                     9: NULL + Logs
                2528    LOAD_ATTR                       10: PrintLog
                2548    LOAD_FAST                       1: config
                2550    LOAD_FAST                       0: account
                2552    LOAD_GLOBAL                     4: Lang
                2562    PUSH_NULL                       
                2564    LOAD_CONST                      1: '__pyarmor_assert_14808__'
                2566    LOAD_CONST                      47: 'algorithm_running_wait'   # b'\x81\xe3\x14\x14<\xe8\xb7\xc6\x13\xf72\xd2y\xe2\xf6\x8c\x01Z\x84\xb0\xab\xc2Z'
                2568    CALL                            1
                2576    BINARY_SUBSCR                   
                2580    LOAD_FAST                       22: _var_var_33
                2582    KW_NAMES                        32: ('config', 'account', 'message', 'param')
                2584    CALL                            4
                2592    POP_TOP                         
                2594    LOAD_GLOBAL                     59: NULL + DelayOnline
                2604    LOAD_FAST                       0: account
                2606    LOAD_FAST                       8: _var_var_22
                2608    LOAD_FAST                       22: _var_var_33
                2610    LOAD_FAST                       22: _var_var_33
                2612    LOAD_FAST                       5: stop_thread
                2614    CALL                            5
                2622    POP_TOP                         
                2624    LOAD_GLOBAL                     9: NULL + Logs
                2634    LOAD_ATTR                       10: PrintLog
                2654    LOAD_FAST                       1: config
                2656    LOAD_FAST                       0: account
                2658    LOAD_GLOBAL                     4: Lang
                2668    PUSH_NULL                       
                2670    LOAD_CONST                      1: '__pyarmor_assert_14808__'
                2672    LOAD_CONST                      48: 'back_in_ranks'   # b'\x81\xe0\x19\x108\xc5\xb7\xdc$\xe8\x0c\xceg\xff'
                2674    CALL                            1
                2682    BINARY_SUBSCR                   
                2686    KW_NAMES                        10: ('config', 'account', 'message')
                2688    CALL                            3
                2696    POP_TOP                         
                2698    LOAD_FAST                       18: _var_var_31
                2700    POP_JUMP_IF_FALSE               16 (to 2734)
                2702    LOAD_GLOBAL                     59: NULL + DelayOnline
                2712    LOAD_FAST                       0: account
                2714    LOAD_FAST                       8: _var_var_22
                2716    LOAD_FAST                       11: _var_var_25
                2718    LOAD_FAST                       12: _var_var_26
                2720    LOAD_FAST                       5: stop_thread
                2722    CALL                            5
                2730    POP_TOP                         
                2732    RERAISE                         0
                2734    RERAISE                         0
                2736    COPY                            3
                2738    POP_EXCEPT                      
                2740    RERAISE                         1
                2742    PUSH_EXC_INFO                   
                2744    LOAD_GLOBAL                     24: StopProgram
                2754    CHECK_EXC_MATCH                 
                2756    POP_JUMP_IF_FALSE               4 (to 2766)
                2758    POP_TOP                         
                2760    POP_EXCEPT                      
                2762    JUMP_BACKWARD                   546 (to 1674)
                2766    LOAD_GLOBAL                     60: BaseException
                2776    CHECK_EXC_MATCH                 
                2778    POP_JUMP_IF_FALSE               27 (to 2834)
                2780    STORE_FAST                      23: _var_var_3
                2782    PUSH_NULL                       
                2784    LOAD_GLOBAL                     63: NULL + logging
                2794    LOAD_FAST                       23: _var_var_3
                2796    CALL                            1
                2804    CALL                            0
                2812    POP_TOP                         
                2814    POP_EXCEPT                      
                2816    LOAD_CONST                      0: None
                2818    STORE_FAST                      23: _var_var_3
                2820    DELETE_FAST                     23: _var_var_3
                2822    JUMP_BACKWARD                   576 (to 1674)
                2826    LOAD_CONST                      0: None
                2828    STORE_FAST                      23: _var_var_3
                2830    DELETE_FAST                     23: _var_var_3
                2832    RERAISE                         1
                2834    RERAISE                         0
                2836    COPY                            3
                2838    POP_EXCEPT                      
                2840    RERAISE                         1
                2842    PUSH_EXC_INFO                   
                2844    POP_TOP                         
                2846    POP_EXCEPT                      
                2848    JUMP_BACKWARD                   578 (to 1696)
                2852    COPY                            3
                2854    POP_EXCEPT                      
                2856    RERAISE                         1
                2858    PUSH_EXC_INFO                   
                2860    LOAD_GLOBAL                     7: NULL + Disconnect
                2870    LOAD_FAST_CHECK                 8: _var_var_22
                2872    CALL                            1
                2880    POP_TOP                         
                2882    JUMP_FORWARD                    7 (to 2898)
                2884    PUSH_EXC_INFO                   
                2886    POP_TOP                         
                2888    POP_EXCEPT                      
                2890    JUMP_FORWARD                    3 (to 2898)
                2892    COPY                            3
                2894    POP_EXCEPT                      
                2896    RERAISE                         1
                2898    LOAD_GLOBAL                     9: NULL + Logs
                2908    LOAD_ATTR                       10: PrintLog
                2928    LOAD_FAST                       1: config
                2930    LOAD_FAST                       0: account
                2932    LOAD_GLOBAL                     4: Lang
                2942    PUSH_NULL                       
                2944    LOAD_CONST                      1: '__pyarmor_assert_14808__'
                2946    LOAD_CONST                      9: 'work_account_completed'   # b'\x81\xf5\x17\x018\xc5\xbf\xd1\x18\xf5\x18\xcex\xd3\xfb\x8a\x02M\xb7\xa2\xbe\xceJ'
                2948    CALL                            1
                2956    BINARY_SUBSCR                   
                2960    KW_NAMES                        10: ('config', 'account', 'message')
                2962    CALL                            3
                2970    POP_TOP                         
                2972    LOAD_FAST                       0: account
                2974    LOAD_CONST                      11: 'done'
                2976    LOAD_CONST                      8: ('account', 'status')
                2978    BUILD_CONST_KEY_MAP             2
                2980    SWAP                            2
                2982    POP_TOP                         
                2984    SWAP                            2
                2986    POP_EXCEPT                      
                2988    NOP                             
                2990    NOP                             
                2992    NOP                             
                2994    JUMP_FORWARD                    23 (to 3042)
                2996    CALL                            1
                3004    POP_TOP                         
                3006    RETURN_VALUE                    
                3008    COPY                            3
                3010    POP_EXCEPT                      
                3012    RERAISE                         1
                3014    PUSH_EXC_INFO                   
                3016    PUSH_NULL                       
                3018    LOAD_CONST                      12: '__pyarmor_exit_14810__'
                3020    NOP                             
                3022    LOAD_CONST                      3: b'<COAddr>\x05\x00\x00\x1a\xac\x0b\x00\x00\x00\x00\x00\x00\x00\x00\x00\x00\x00\x00\x00\x00'
                3024    CALL                            1
                3032    POP_TOP                         
                3034    RERAISE                         0
                3036    COPY                            3
                3038    POP_EXCEPT                      
                3040    RERAISE                         1
                3042    PUSH_NULL                       
                3044    LOAD_CONST                      12: '__pyarmor_exit_14810__'
                3046    LOAD_CONST                      3: b'<COAddr>\x05\x00\x00\x1a\xac\x0b\x00\x00\x00\x00\x00\x00\x00\x00\x00\x00\x00\x00\x00\x00'
                3048    BUILD_TUPLE                     1
                3050    CALL_FUNCTION_EX                0
                3052    POP_TOP                         
                3054    RETURN_VALUE                    
            [Exception Table]
                30 to 128 -> 2742 [0] 
                128 to 150 -> 1798 [1] 
                150 to 236 -> 3014 [0] 
                256 to 792 -> 2742 [0] 
                796 to 930 -> 1846 [1] 
                930 to 1054 -> 1814 [1] 
                1054 to 1084 -> 1846 [1] 
                1084 to 1208 -> 1830 [1] 
                1208 to 1260 -> 1846 [1] 
                1260 to 1282 -> 2742 [0] 
                1282 to 1324 -> 2288 [1] 
                1324 to 1632 -> 2742 [0] 
                1636 to 1672 -> 2742 [0] 
                1672 to 1674 -> 2858 [0] 
                1674 to 1696 -> 2842 [0] 
                1696 to 1778 -> 3014 [0] 
                1798 to 1802 -> 1808 [2] lasti
                1802 to 1814 -> 3014 [0] 
                1814 to 1818 -> 1824 [2] lasti
                1818 to 1830 -> 1846 [1] 
                1830 to 1834 -> 1840 [2] lasti
                1834 to 1846 -> 1846 [1] 
                1846 to 1884 -> 2282 [2] lasti
                1884 to 1900 -> 1912 [2] lasti
                1900 to 1912 -> 2308 [1] 
                1912 to 1972 -> 2282 [2] lasti
                1972 to 1978 -> 2308 [1] 
                1978 to 2030 -> 2282 [2] lasti
                2030 to 2036 -> 2308 [1] 
                2036 to 2088 -> 2282 [2] lasti
                2088 to 2094 -> 2308 [1] 
                2094 to 2146 -> 2282 [2] lasti
                2146 to 2152 -> 2308 [1] 
                2152 to 2168 -> 2282 [2] lasti
                2168 to 2260 -> 2272 [2] lasti
                2260 to 2272 -> 2308 [1] 
                2272 to 2282 -> 2282 [2] lasti
                2282 to 2288 -> 2308 [1] 
                2288 to 2296 -> 2302 [2] lasti
                2296 to 2308 -> 2742 [0] 
                2308 to 2332 -> 2736 [2] lasti
                2332 to 2374 -> 2376 [3] 
                2374 to 2376 -> 2736 [2] lasti
                2376 to 2384 -> 2388 [4] lasti
                2384 to 2736 -> 2736 [2] lasti
                2736 to 2742 -> 2742 [0] 
                2742 to 2760 -> 2836 [1] lasti
                2760 to 2766 -> 2858 [0] 
                2766 to 2782 -> 2836 [1] lasti
                2782 to 2814 -> 2826 [1] lasti
                2814 to 2826 -> 2858 [0] 
                2826 to 2836 -> 2836 [1] lasti
                2836 to 2842 -> 2858 [0] 
                2842 to 2846 -> 2852 [1] lasti
                2846 to 2858 -> 3014 [0] 
                2858 to 2860 -> 3008 [1] lasti
                2860 to 2882 -> 2884 [2] 
                2882 to 2884 -> 3008 [1] lasti
                2884 to 2888 -> 2892 [3] lasti
                2888 to 2986 -> 3008 [1] lasti
                2986 to 2988 -> 3014 [0] 
                3008 to 3014 -> 3014 [0] 
                3014 to 3036 -> 3036 [1] lasti
        '__pyarmor_exit_14792__'
        (
            0
        )
    [Disassembly]
        0       NOP                             
        2       NOP                             
        4       PUSH_NULL                       
        6       LOAD_CONST                      1: '__pyarmor_enter_14791__'
        8       LOAD_CONST                      2: b'<COAddr>\x07\x00\x00\x1aP\x01\x00\x00\x00\x00\x00\x00\x00\x00\x00\x00\x00\x00\x00\x00'
        10      BUILD_TUPLE                     1
        12      CALL_FUNCTION_EX                0
        14      POP_TOP                         
        16      RESUME                          0
        18      NOP                             
        20      NOP                             
        22      NOP                             
        24      NOP                             
        26      LOAD_CONST                      3: 0
        28      LOAD_CONST                      4: None
        30      IMPORT_NAME                     1: eel
        32      STORE_NAME                      1: eel
        34      LOAD_CONST                      3: 0
        36      LOAD_CONST                      4: None
        38      IMPORT_NAME                     2: json
        40      STORE_NAME                      2: json
        42      LOAD_CONST                      3: 0
        44      LOAD_CONST                      4: None
        46      IMPORT_NAME                     3: random
        48      STORE_NAME                      3: random
        50      LOAD_CONST                      3: 0
        52      LOAD_CONST                      4: None
        54      IMPORT_NAME                     4: sqlite3
        56      STORE_NAME                      4: sqlite3
        58      LOAD_CONST                      3: 0
        60      LOAD_CONST                      4: None
        62      IMPORT_NAME                     5: datetime
        64      STORE_NAME                      5: datetime
        66      LOAD_CONST                      3: 0
        68      LOAD_CONST                      4: None
        70      IMPORT_NAME                     6: concurrent.futures
        72      STORE_NAME                      7: concurrent
        74      LOAD_CONST                      3: 0
        76      LOAD_CONST                      5: ('Thread', 'Event')
        78      IMPORT_NAME                     8: threading
        80      IMPORT_FROM                     9: Thread
        82      STORE_NAME                      9: Thread
        84      IMPORT_FROM                     10: Event
        86      STORE_NAME                      10: Event
        88      POP_TOP                         
        90      LOAD_CONST                      3: 0
        92      LOAD_CONST                      6: ('functions', 'types', 'errors')
        94      IMPORT_NAME                     11: multithon.sync
        96      IMPORT_FROM                     12: functions
        98      STORE_NAME                      12: functions
        100     IMPORT_FROM                     13: types
        102     STORE_NAME                      13: types
        104     IMPORT_FROM                     14: errors
        106     STORE_NAME                      14: errors
        108     POP_TOP                         
        110     LOAD_CONST                      3: 0
        112     LOAD_CONST                      7: ('StopProgram',)
        114     IMPORT_NAME                     15: multithon.errors
        116     IMPORT_FROM                     16: StopProgram
        118     STORE_NAME                      16: StopProgram
        120     POP_TOP                         
        122     LOAD_CONST                      3: 0
        124     LOAD_CONST                      8: ('GetLang',)
        126     IMPORT_NAME                     17: program.static_classes
        128     IMPORT_FROM                     18: GetLang
        130     STORE_NAME                      18: GetLang
        132     POP_TOP                         
        134     LOAD_CONST                      3: 0
        136     LOAD_CONST                      9: ('Logs',)
        138     IMPORT_NAME                     17: program.static_classes
        140     IMPORT_FROM                     19: Logs
        142     STORE_NAME                      19: Logs
        144     POP_TOP                         
        146     LOAD_CONST                      3: 0
        148     LOAD_CONST                      10: ('logging',)
        150     IMPORT_NAME                     17: program.static_classes
        152     IMPORT_FROM                     20: logging
        154     STORE_NAME                      20: logging
        156     POP_TOP                         
        158     LOAD_CONST                      3: 0
        160     LOAD_CONST                      11: ('memory_check_switcher',)
        162     IMPORT_NAME                     17: program.static_classes
        164     IMPORT_FROM                     21: memory_check_switcher
        166     STORE_NAME                      21: memory_check_switcher
        168     POP_TOP                         
        170     LOAD_CONST                      3: 0
        172     LOAD_CONST                      12: ('memory_set_pid',)
        174     IMPORT_NAME                     17: program.static_classes
        176     IMPORT_FROM                     22: memory_set_pid
        178     STORE_NAME                      22: memory_set_pid
        180     POP_TOP                         
        182     LOAD_CONST                      3: 0
        184     LOAD_CONST                      13: ('DelayOnline',)
        186     IMPORT_NAME                     23: program.telegram
        188     IMPORT_FROM                     24: DelayOnline
        190     STORE_NAME                      24: DelayOnline
        192     POP_TOP                         
        194     LOAD_CONST                      3: 0
        196     LOAD_CONST                      14: ('Disconnect',)
        198     IMPORT_NAME                     23: program.telegram
        200     IMPORT_FROM                     25: Disconnect
        202     STORE_NAME                      25: Disconnect
        204     POP_TOP                         
        206     LOAD_CONST                      3: 0
        208     LOAD_CONST                      15: ('Thread_wait',)
        210     IMPORT_NAME                     23: program.telegram
        212     IMPORT_FROM                     26: Thread_wait
        214     STORE_NAME                      26: Thread_wait
        216     POP_TOP                         
        218     LOAD_CONST                      3: 0
        220     LOAD_CONST                      16: ('account_works',)
        222     IMPORT_NAME                     23: program.telegram
        224     IMPORT_FROM                     27: account_works
        226     STORE_NAME                      27: account_works
        228     POP_TOP                         
        230     LOAD_CONST                      3: 0
        232     LOAD_CONST                      17: ('GetConfig',)
        234     IMPORT_NAME                     28: program.general
        236     IMPORT_FROM                     29: GetConfig
        238     STORE_NAME                      29: GetConfig
        240     POP_TOP                         
        242     LOAD_CONST                      3: 0
        244     LOAD_CONST                      18: ('GetProxy',)
        246     IMPORT_NAME                     28: program.general
        248     IMPORT_FROM                     30: GetProxy
        250     STORE_NAME                      30: GetProxy
        252     POP_TOP                         
        254     LOAD_CONST                      3: 0
        256     LOAD_CONST                      19: ('StopDetect',)
        258     IMPORT_NAME                     28: program.general
        260     IMPORT_FROM                     31: StopDetect
        262     STORE_NAME                      31: StopDetect
        264     POP_TOP                         
        266     LOAD_CONST                      3: 0
        268     LOAD_CONST                      20: ('check_get_settings',)
        270     IMPORT_NAME                     28: program.general
        272     IMPORT_FROM                     32: check_get_settings
        274     STORE_NAME                      32: check_get_settings
        276     POP_TOP                         
        278     LOAD_CONST                      3: 0
        280     LOAD_CONST                      21: ('del_task_manager',)
        282     IMPORT_NAME                     28: program.general
        284     IMPORT_FROM                     33: del_task_manager
        286     STORE_NAME                      33: del_task_manager
        288     POP_TOP                         
        290     LOAD_CONST                      3: 0
        292     LOAD_CONST                      22: ('set_task_manager',)
        294     IMPORT_NAME                     28: program.general
        296     IMPORT_FROM                     34: set_task_manager
        298     STORE_NAME                      34: set_task_manager
        300     POP_TOP                         
        302     LOAD_CONST                      23: <CODE> Unsubscribe
        304     MAKE_FUNCTION                   0
        306     STORE_NAME                      35: Unsubscribe
        308     LOAD_CONST                      24: <CODE> START
        310     MAKE_FUNCTION                   0
        312     STORE_NAME                      36: START
        314     LOAD_CONST                      25: <CODE> DB_CREATE_RESULT
        316     MAKE_FUNCTION                   0
        318     STORE_NAME                      37: DB_CREATE_RESULT
        320     LOAD_CONST                      30: (0,)
        322     LOAD_CONST                      26: <CODE> DB_SET_STATISTIC
        324     MAKE_FUNCTION                   1
        326     STORE_NAME                      38: DB_SET_STATISTIC
        328     LOAD_CONST                      27: <CODE> EntityCorrectGroup
        330     MAKE_FUNCTION                   0
        332     STORE_NAME                      39: EntityCorrectGroup
        334     LOAD_CONST                      30: (0,)
        336     LOAD_CONST                      28: <CODE> Unsubscribes
        338     MAKE_FUNCTION                   1
        340     STORE_NAME                      40: Unsubscribes
        342     LOAD_CONST                      4: None
        344     NOP                             
        346     NOP                             
        348     NOP                             
        350     JUMP_FORWARD                    19 (to 390)
        358     POP_TOP                         
        360     RETURN_CONST                    4: None
        362     PUSH_EXC_INFO                   
        364     PUSH_NULL                       
        366     LOAD_CONST                      29: '__pyarmor_exit_14792__'
        368     NOP                             
        370     LOAD_CONST                      2: b'<COAddr>\x07\x00\x00\x1aP\x01\x00\x00\x00\x00\x00\x00\x00\x00\x00\x00\x00\x00\x00\x00'
        372     CALL                            1
        380     POP_TOP                         
        382     RERAISE                         0
        384     COPY                            3
        386     POP_EXCEPT                      
        388     RERAISE                         1
        390     PUSH_NULL                       
        392     LOAD_CONST                      29: '__pyarmor_exit_14792__'
        394     LOAD_CONST                      2: b'<COAddr>\x07\x00\x00\x1aP\x01\x00\x00\x00\x00\x00\x00\x00\x00\x00\x00\x00\x00\x00\x00'
        396     BUILD_TUPLE                     1
        398     CALL_FUNCTION_EX                0
        400     POP_TOP                         
        402     RETURN_VALUE                    
    [Exception Table]
        26 to 342 -> 362 [0] 
        362 to 384 -> 384 [1] lasti
