#decoded by lolz.live/mrpenny / t.me/zeus_jackpot
# ================================
# Примечания по Pyarmor:
# - Байт-код и объекты кода Pyarmor соответствуют стандартному Python, но присутствуют специальные вызовы функций среды выполнения (runtime) Pyarmor.
# - Вызовы строк — это не ошибки, а маркеры, которые обрабатываются Pyarmor во время выполнения.
#
# Руководство по декомпиляции (без среды выполнения):
# 1. Игнорируйте зашифрованные байты после `#`; используйте только строку до `#`.
# 2. Удалите "__pyarmor_enter_xxx__"(b"<COAddr>...") и "__pyarmor_leave_xxx__"(b"<COAddr>...") (пролог/эпилог).
# 3. "__pyarmor_assert_xxx__"(A) не является настоящим оператором assert.
#    - Если A — это имя или читаемая строка: замените на A.
#    - Если A — это (X, "Y"): замените на X.Y.
#    - Если A — это (X, "Y", Z): замените на X.Y = Z.
#    - В противном случае: выберите наиболее подходящую/логичную замену.
# 4. "__pyarmor_bcc_xxx__"(...) указывает на машинный (нативный) код; тело функции недоступно. Добавьте комментарий.
# ================================

[Code]
    File Name: <frozen program.modules.Views_proxy>
    Object Name: <module>
    Qualified Name: <module>
    Arg Count: 0
    Pos Only Arg Count: 0
    KW Only Arg Count: 0
    Stack Size: 5
    Flags: 0x20000000 (CO_PYARMOR_OBFUSCATED)
    [Names]
        '__assert_armored__'
        're'
        'eel'
        'time'
        'json'
        'random'
        'requests'
        'concurrent.futures'
        'concurrent'
        'bs4'
        'BeautifulSoup'
        'threading'
        'Thread'
        'Event'
        'multithon.errors'
        'StopProgram'
        'requests.adapters'
        'HTTPAdapter'
        'Retry'
        'program.static_classes'
        'GetLang'
        'Logs'
        'logging'
        'memory_check_switcher'
        'memory_set_pid'
        'program.telegram'
        'Thread_wait'
        'program.general'
        'GetConfig'
        'GetProxy'
        'StopDetect'
        'del_task_manager'
        'getFile'
        'set_task_manager'
        'getPath'
        'program.database'
        'db_proxy'
        'Views_proxy'
        'START'
        'worker'
        'ViewsWeb'
        'proxy_get'
    [Locals+Names]
    [Constants]
        '__pyarmor_assert_14826__'
        '__pyarmor_enter_14827__'
        b'<COAddr>\x07\x00\x00\x1aX\x01\x00\x00\x00\x00\x00\x00\x00\x00\x00\x00\x00\x00\x00\x00'
        0
        None
        (
            'BeautifulSoup'
        )
        (
            'Thread'
            'Event'
        )
        (
            'StopProgram'
        )
        (
            'HTTPAdapter'
            'Retry'
        )
        (
            'GetLang'
        )
        (
            'Logs'
        )
        (
            'logging'
        )
        (
            'memory_check_switcher'
        )
        (
            'memory_set_pid'
        )
        (
            'Thread_wait'
        )
        (
            'GetConfig'
        )
        (
            'GetProxy'
        )
        (
            'StopDetect'
        )
        (
            'del_task_manager'
        )
        (
            'getFile'
        )
        (
            'set_task_manager'
        )
        (
            'getPath'
        )
        (
            'db_proxy'
        )
        [Code]
            File Name: <frozen program.modules.Views_proxy>
            Object Name: Views_proxy
            Qualified Name: Views_proxy
            Arg Count: 1
            Pos Only Arg Count: 0
            KW Only Arg Count: 0
            Stack Size: 8
            Flags: 0x20000003 (CO_OPTIMIZED | CO_NEWLOCALS | CO_PYARMOR_OBFUSCATED)
            [Names]
                'get'
                'getFile'
                'getPath'
                'GetConfig'
                'config'
                'GetLang'
                'Lang'
                'GetProxy'
                'eel'
                'sendSuccessBox'
                'memory_check_switcher'
                'Event'
                'memory_set_pid'
                'Thread'
                'START'
                'start'
                'Logs'
                'WaitStopAnsfer'
                'UpdateLogInWindow'
                'BaseException'
                'logging'
            [Locals+Names]
                'data'
                '__assert_armored__'
                '_var_var_0'
                '_var_var_1'
                '_var_var_2'
                '_var_var_3'
            [Constants]
                None
                '__pyarmor_assert_14829__'
                '__pyarmor_enter_14830__'
                b'<COAddr>\x05\x00\x00\x1a\x08\x03\x00\x00\x00\x00\x00\x00\x00\x00\x00\x00\x00\x00\x00\x00'
                'action'
                'getFile'
                '__pyarmor_exit_14831__'
                'getPath'
                'program_running'   # b'\x81\xf2\n\x1c4\xe8\xbf\xdf$\xe8\x18\xceb\xe5\xf6\x82'
                False
                (
                    'target'
                    'args'
                )
                True
                (
                    'target'
                    'args'
                    'daemon'
                )
            [Disassembly]
                0       NOP                             
                2       NOP                             
                4       PUSH_NULL                       
                6       LOAD_CONST                      2: '__pyarmor_enter_14830__'
                8       LOAD_CONST                      3: b'<COAddr>\x05\x00\x00\x1a\x08\x03\x00\x00\x00\x00\x00\x00\x00\x00\x00\x00\x00\x00\x00\x00'
                10      BUILD_TUPLE                     1
                12      CALL_FUNCTION_EX                0
                14      POP_TOP                         
                16      RESUME                          0
                18      NOP                             
                20      NOP                             
                22      NOP                             
                24      NOP                             
                26      NOP                             
                28      NOP                             
                30      LOAD_FAST                       0: data
                32      LOAD_ATTR                       1: get
                52      LOAD_CONST                      4: 'action'
                54      CALL                            1
                62      POP_JUMP_IF_NONE                28 (to 120)
                64      LOAD_FAST                       0: data
                66      LOAD_CONST                      4: 'action'
                68      BINARY_SUBSCR                   
                72      LOAD_CONST                      5: 'getFile'
                74      COMPARE_OP                      40 (==)
                78      POP_JUMP_IF_FALSE               20 (to 120)
                80      LOAD_GLOBAL                     3: NULL + getFile
                90      LOAD_FAST                       0: data
                92      CALL                            1
                100     NOP                             
                102     NOP                             
                104     JUMP_FORWARD                    361 (to 830)
                108     CALL                            1
                116     POP_TOP                         
                118     RETURN_VALUE                    
                120     LOAD_FAST                       0: data
                122     LOAD_ATTR                       1: get
                142     LOAD_CONST                      4: 'action'
                144     CALL                            1
                152     POP_JUMP_IF_NONE                28 (to 210)
                154     LOAD_FAST                       0: data
                156     LOAD_CONST                      4: 'action'
                158     BINARY_SUBSCR                   
                162     LOAD_CONST                      7: 'getPath'
                164     COMPARE_OP                      40 (==)
                168     POP_JUMP_IF_FALSE               20 (to 210)
                170     LOAD_GLOBAL                     5: NULL + getPath
                180     LOAD_FAST                       0: data
                182     CALL                            1
                190     NOP                             
                192     NOP                             
                194     JUMP_FORWARD                    316 (to 830)
                198     CALL                            1
                206     POP_TOP                         
                208     RETURN_VALUE                    
                210     LOAD_GLOBAL                     7: NULL + GetConfig
                220     CALL                            0
                228     STORE_GLOBAL                    4: config
                230     LOAD_GLOBAL                     11: NULL + GetLang
                240     LOAD_GLOBAL                     8: config
                250     CALL                            1
                258     STORE_GLOBAL                    6: Lang
                260     LOAD_GLOBAL                     15: NULL + GetProxy
                270     CALL                            0
                278     STORE_FAST                      2: _var_var_0
                280     LOAD_GLOBAL                     17: NULL + eel
                290     LOAD_ATTR                       18: sendSuccessBox
                310     LOAD_GLOBAL                     12: Lang
                320     PUSH_NULL                       
                322     LOAD_CONST                      1: '__pyarmor_assert_14829__'
                324     LOAD_CONST                      8: 'program_running'   # b'\x81\xf2\n\x1c4\xe8\xbf\xdf$\xe8\x18\xceb\xe5\xf6\x82'
                326     CALL                            1
                334     BINARY_SUBSCR                   
                338     CALL                            1
                346     POP_TOP                         
                348     LOAD_GLOBAL                     21: NULL + memory_check_switcher
                358     CALL                            0
                366     POP_JUMP_IF_TRUE                11 (to 390)
                368     NOP                             
                370     LOAD_CONST                      9: False
                372     NOP                             
                374     NOP                             
                376     NOP                             
                378     JUMP_FORWARD                    225 (to 830)
                386     POP_TOP                         
                388     RETURN_CONST                    9: False
                390     LOAD_GLOBAL                     23: NULL + Event
                400     CALL                            0
                408     STORE_FAST                      3: _var_var_1
                410     LOAD_GLOBAL                     25: NULL + memory_set_pid
                420     CALL                            0
                428     STORE_FAST                      4: _var_var_2
                430     LOAD_GLOBAL                     27: NULL + Thread
                440     LOAD_GLOBAL                     28: START
                450     LOAD_FAST                       0: data
                452     LOAD_GLOBAL                     8: config
                462     LOAD_FAST                       4: _var_var_2
                464     LOAD_FAST                       2: _var_var_0
                466     LOAD_FAST                       3: _var_var_1
                468     BUILD_TUPLE                     5
                470     KW_NAMES                        10: ('target', 'args')
                472     CALL                            2
                480     LOAD_ATTR                       31: start
                500     CALL                            0
                508     POP_TOP                         
                510     LOAD_GLOBAL                     27: NULL + Thread
                520     LOAD_GLOBAL                     32: Logs
                530     LOAD_ATTR                       34: WaitStopAnsfer
                550     LOAD_GLOBAL                     8: config
                560     LOAD_FAST                       4: _var_var_2
                562     LOAD_FAST                       3: _var_var_1
                564     BUILD_TUPLE                     3
                566     LOAD_CONST                      11: True
                568     KW_NAMES                        12: ('target', 'args', 'daemon')
                570     CALL                            3
                578     LOAD_ATTR                       31: start
                598     CALL                            0
                606     POP_TOP                         
                608     LOAD_GLOBAL                     27: NULL + Thread
                618     LOAD_GLOBAL                     32: Logs
                628     LOAD_ATTR                       36: UpdateLogInWindow
                648     LOAD_GLOBAL                     8: config
                658     LOAD_FAST                       4: _var_var_2
                660     LOAD_FAST                       3: _var_var_1
                662     BUILD_TUPLE                     3
                664     LOAD_CONST                      11: True
                666     KW_NAMES                        12: ('target', 'args', 'daemon')
                668     CALL                            3
                676     LOAD_ATTR                       31: start
                696     CALL                            0
                704     POP_TOP                         
                706     LOAD_CONST                      0: None
                708     NOP                             
                710     NOP                             
                712     NOP                             
                714     JUMP_FORWARD                    57 (to 830)
                722     POP_TOP                         
                724     RETURN_CONST                    0: None
                726     PUSH_EXC_INFO                   
                728     LOAD_GLOBAL                     38: BaseException
                738     CHECK_EXC_MATCH                 
                740     POP_JUMP_IF_FALSE               26 (to 794)
                742     STORE_FAST                      5: _var_var_3
                744     PUSH_NULL                       
                746     LOAD_GLOBAL                     41: NULL + logging
                756     LOAD_FAST                       5: _var_var_3
                758     CALL                            1
                766     CALL                            0
                774     POP_TOP                         
                776     POP_EXCEPT                      
                778     LOAD_CONST                      0: None
                780     STORE_FAST                      5: _var_var_3
                782     DELETE_FAST                     5: _var_var_3
                784     JUMP_BACKWARD                   40 (to 706)
                786     LOAD_CONST                      0: None
                788     STORE_FAST                      5: _var_var_3
                790     DELETE_FAST                     5: _var_var_3
                792     RERAISE                         1
                794     RERAISE                         0
                796     COPY                            3
                798     POP_EXCEPT                      
                800     RERAISE                         1
                802     PUSH_EXC_INFO                   
                804     PUSH_NULL                       
                806     LOAD_CONST                      6: '__pyarmor_exit_14831__'
                808     NOP                             
                810     LOAD_CONST                      3: b'<COAddr>\x05\x00\x00\x1a\x08\x03\x00\x00\x00\x00\x00\x00\x00\x00\x00\x00\x00\x00\x00\x00'
                812     CALL                            1
                820     POP_TOP                         
                822     RERAISE                         0
                824     COPY                            3
                826     POP_EXCEPT                      
                828     RERAISE                         1
                830     PUSH_NULL                       
                832     LOAD_CONST                      6: '__pyarmor_exit_14831__'
                834     LOAD_CONST                      3: b'<COAddr>\x05\x00\x00\x1a\x08\x03\x00\x00\x00\x00\x00\x00\x00\x00\x00\x00\x00\x00\x00\x00'
                836     BUILD_TUPLE                     1
                838     CALL_FUNCTION_EX                0
                840     POP_TOP                         
                842     RETURN_VALUE                    
            [Exception Table]
                30 to 100 -> 726 [0] 
                120 to 190 -> 726 [0] 
                210 to 368 -> 726 [0] 
                390 to 706 -> 726 [0] 
                726 to 744 -> 796 [1] lasti
                744 to 776 -> 786 [1] lasti
                776 to 786 -> 802 [0] 
                786 to 796 -> 796 [1] lasti
                796 to 802 -> 802 [0] 
                802 to 824 -> 824 [1] lasti
        [Code]
            File Name: <frozen program.modules.Views_proxy>
            Object Name: START
            Qualified Name: START
            Arg Count: 5
            Pos Only Arg Count: 0
            KW Only Arg Count: 0
            Stack Size: 14
            Flags: 0x20000003 (CO_OPTIMIZED | CO_NEWLOCALS | CO_PYARMOR_OBFUSCATED)
            [Names]
                'is_set'
                'StopProgram'
                'get'
                'int'
                'proxy_get'
                'set_task_manager'
                'concurrent'
                'futures'
                'ThreadPoolExecutor'
                'len'
                'eel'
                'StreamStat'
                'json'
                'dumps'
                'append'
                'submit'
                'worker'
                'as_completed'
                'BaseException'
                'logging'
                'del_task_manager'
                'StopDetect'
            [Locals+Names]
                'data'
                'config'
                'pid'
                'proxy'
                'stop_thread'
                '__assert_armored__'
                '_var_var_4'
                '_var_var_5'
                '_var_var_6'
                '_var_var_7'
                '_var_var_8'
                '_var_var_9'
                '_var_var_10'
                '_var_var_11'
                '_var_var_12'
                '_var_var_13'
                '_var_var_3'
            [Constants]
                None
                '__pyarmor_assert_14832__'
                '__pyarmor_enter_14833__'
                b'<COAddr>\x07\x00\x00\x1aR\x04\x00\x00\x00\x00\x00\x00\x00\x00\x00\x00\x00\x00\x00\x00'
                'Settings'
                'thread_rules'   # b'\x81\xf6\x10\x016\xfb\xba\xed\t\xef\x01\xc5\x7f'
                True
                'thread_count'   # b'\x81\xf6\x10\x016\xfb\xba\xed\x18\xf5\x18\xcex'
                'usernames'   # b'\x81\xf7\x0b\x16!\xf4\xbf\xdf\x1e\xe9'
                'stuff'
                (
                    'accounts'
                    'name'
                )
                (
                    'max_workers'
                )
                0
                'st_task'
                'st_stream'   # b'\x81\xf1\x0c, \xee\xac\xd7\x1a\xf7'
                'st_wait'
                'st_done'
                1
                '__pyarmor_exit_14834__'
                'Done'
            [Disassembly]
                0       NOP                             
                2       NOP                             
                4       PUSH_NULL                       
                6       LOAD_CONST                      2: '__pyarmor_enter_14833__'
                8       LOAD_CONST                      3: b'<COAddr>\x07\x00\x00\x1aR\x04\x00\x00\x00\x00\x00\x00\x00\x00\x00\x00\x00\x00\x00\x00'
                10      BUILD_TUPLE                     1
                12      CALL_FUNCTION_EX                0
                14      POP_TOP                         
                16      RESUME                          0
                18      NOP                             
                20      NOP                             
                22      NOP                             
                24      NOP                             
                26      NOP                             
                28      NOP                             
                30      LOAD_FAST                       4: stop_thread
                32      LOAD_ATTR                       1: is_set
                52      CALL                            0
                60      POP_JUMP_IF_FALSE               10 (to 82)
                62      LOAD_GLOBAL                     3: NULL + StopProgram
                72      CALL                            0
                80      RAISE_VARARGS                   1
                82      LOAD_FAST                       0: data
                84      LOAD_CONST                      4: 'Settings'
                86      BINARY_SUBSCR                   
                90      LOAD_ATTR                       5: get
                110     PUSH_NULL                       
                112     LOAD_CONST                      1: '__pyarmor_assert_14832__'
                114     LOAD_CONST                      5: 'thread_rules'   # b'\x81\xf6\x10\x016\xfb\xba\xed\t\xef\x01\xc5\x7f'
                116     CALL                            1
                124     CALL                            1
                132     LOAD_CONST                      6: True
                134     COMPARE_OP                      40 (==)
                138     POP_JUMP_IF_FALSE               36 (to 212)
                140     LOAD_GLOBAL                     7: NULL + int
                150     LOAD_FAST                       0: data
                152     LOAD_CONST                      4: 'Settings'
                154     BINARY_SUBSCR                   
                158     LOAD_ATTR                       5: get
                178     PUSH_NULL                       
                180     LOAD_CONST                      1: '__pyarmor_assert_14832__'
                182     LOAD_CONST                      7: 'thread_count'   # b'\x81\xf6\x10\x016\xfb\xba\xed\x18\xf5\x18\xcex'
                184     CALL                            1
                192     CALL                            1
                200     CALL                            1
                208     STORE_FAST                      6: _var_var_4
                210     JUMP_FORWARD                    11 (to 234)
                212     LOAD_FAST                       1: config
                214     PUSH_NULL                       
                216     LOAD_CONST                      1: '__pyarmor_assert_14832__'
                218     LOAD_CONST                      7: 'thread_count'   # b'\x81\xf6\x10\x016\xfb\xba\xed\x18\xf5\x18\xcex'
                220     CALL                            1
                228     BINARY_SUBSCR                   
                232     STORE_FAST                      6: _var_var_4
                234     LOAD_FAST                       0: data
                236     LOAD_CONST                      4: 'Settings'
                238     BINARY_SUBSCR                   
                242     LOAD_ATTR                       5: get
                262     PUSH_NULL                       
                264     LOAD_CONST                      1: '__pyarmor_assert_14832__'
                266     LOAD_CONST                      8: 'usernames'   # b'\x81\xf7\x0b\x16!\xf4\xbf\xdf\x1e\xe9'
                268     CALL                            1
                276     BUILD_LIST                      0
                278     CALL                            2
                286     STORE_FAST                      7: _var_var_5
                288     LOAD_GLOBAL                     9: NULL + proxy_get
                298     CALL                            0
                306     STORE_FAST                      3: proxy
                308     LOAD_GLOBAL                     11: NULL + set_task_manager
                318     LOAD_FAST                       2: pid
                320     BUILD_LIST                      0
                322     LOAD_FAST                       0: data
                324     LOAD_CONST                      9: 'stuff'
                326     BINARY_SUBSCR                   
                330     KW_NAMES                        10: ('accounts', 'name')
                332     CALL                            3
                340     POP_TOP                         
                342     LOAD_GLOBAL                     12: concurrent
                352     LOAD_ATTR                       14: futures
                372     LOAD_ATTR                       17: ThreadPoolExecutor
                392     LOAD_FAST                       6: _var_var_4
                394     KW_NAMES                        11: ('max_workers',)
                396     CALL                            1
                404     BEFORE_WITH                     
                406     STORE_FAST                      8: _var_var_6
                408     BUILD_LIST                      0
                410     STORE_FAST                      9: _var_var_7
                412     LOAD_GLOBAL                     19: NULL + len
                422     LOAD_FAST                       7: _var_var_5
                424     CALL                            1
                432     STORE_FAST                      10: _var_var_8
                434     LOAD_FAST                       6: _var_var_4
                436     STORE_FAST                      11: _var_var_9
                438     LOAD_FAST                       10: _var_var_8
                440     STORE_FAST                      12: _var_var_10
                442     LOAD_CONST                      12: 0
                444     STORE_FAST                      13: _var_var_11
                446     LOAD_GLOBAL                     21: NULL + eel
                456     LOAD_ATTR                       22: StreamStat
                476     LOAD_GLOBAL                     25: NULL + json
                486     LOAD_ATTR                       26: dumps
                506     LOAD_CONST                      13: 'st_task'
                508     LOAD_FAST                       10: _var_var_8
                510     PUSH_NULL                       
                512     LOAD_CONST                      1: '__pyarmor_assert_14832__'
                514     LOAD_CONST                      14: 'st_stream'   # b'\x81\xf1\x0c, \xee\xac\xd7\x1a\xf7'
                516     CALL                            1
                524     LOAD_FAST                       11: _var_var_9
                526     LOAD_CONST                      15: 'st_wait'
                528     LOAD_FAST                       12: _var_var_10
                530     LOAD_CONST                      16: 'st_done'
                532     LOAD_FAST                       13: _var_var_11
                534     BUILD_MAP                       4
                536     CALL                            1
                544     CALL                            1
                552     POP_TOP                         
                554     LOAD_FAST                       7: _var_var_5
                556     GET_ITER                        
                558     FOR_ITER                        43 (to 646)
                562     STORE_FAST                      14: _var_var_12
                564     LOAD_FAST                       9: _var_var_7
                566     LOAD_ATTR                       29: append
                586     LOAD_FAST                       8: _var_var_6
                588     LOAD_ATTR                       31: submit
                608     LOAD_GLOBAL                     32: worker
                618     LOAD_FAST                       14: _var_var_12
                620     LOAD_FAST                       1: config
                622     LOAD_FAST                       3: proxy
                624     LOAD_FAST                       0: data
                626     LOAD_FAST                       4: stop_thread
                628     CALL                            6
                636     CALL                            1
                644     POP_TOP                         
                646     JUMP_BACKWARD                   45 (to 558)
                648     END_FOR                         
                650     LOAD_GLOBAL                     12: concurrent
                660     LOAD_ATTR                       14: futures
                680     LOAD_ATTR                       35: as_completed
                700     LOAD_FAST                       9: _var_var_7
                702     CALL                            1
                710     GET_ITER                        
                712     FOR_ITER                        66 (to 846)
                716     STORE_FAST                      15: _var_var_13
                718     LOAD_FAST                       13: _var_var_11
                720     LOAD_CONST                      17: 1
                722     BINARY_OP                       13 (+=)
                726     STORE_FAST                      13: _var_var_11
                728     LOAD_FAST                       12: _var_var_10
                730     LOAD_CONST                      17: 1
                732     BINARY_OP                       23 (-=)
                736     STORE_FAST                      12: _var_var_10
                738     LOAD_GLOBAL                     21: NULL + eel
                748     LOAD_ATTR                       22: StreamStat
                768     LOAD_GLOBAL                     25: NULL + json
                778     LOAD_ATTR                       26: dumps
                798     LOAD_CONST                      13: 'st_task'
                800     LOAD_FAST                       10: _var_var_8
                802     PUSH_NULL                       
                804     LOAD_CONST                      1: '__pyarmor_assert_14832__'
                806     LOAD_CONST                      14: 'st_stream'   # b'\x81\xf1\x0c, \xee\xac\xd7\x1a\xf7'
                808     CALL                            1
                816     LOAD_FAST                       11: _var_var_9
                818     LOAD_CONST                      15: 'st_wait'
                820     LOAD_FAST                       12: _var_var_10
                822     LOAD_CONST                      16: 'st_done'
                824     LOAD_FAST                       13: _var_var_11
                826     BUILD_MAP                       4
                828     CALL                            1
                836     CALL                            1
                844     POP_TOP                         
                846     JUMP_BACKWARD                   68 (to 712)
                848     END_FOR                         
                850     DELETE_FAST                     9: _var_var_7
                852     DELETE_FAST                     0: data
                854     LOAD_CONST                      0: None
                856     LOAD_CONST                      0: None
                858     LOAD_CONST                      0: None
                860     CALL                            2
                868     POP_TOP                         
                870     LOAD_GLOBAL                     41: NULL + del_task_manager
                880     LOAD_FAST                       2: pid
                882     CALL                            1
                890     POP_TOP                         
                892     LOAD_GLOBAL                     43: NULL + StopDetect
                902     LOAD_FAST                       4: stop_thread
                904     CALL                            1
                912     POP_TOP                         
                914     NOP                             
                916     LOAD_CONST                      19: 'Done'
                918     NOP                             
                920     NOP                             
                922     NOP                             
                924     JUMP_FORWARD                    117 (to 1160)
                932     POP_TOP                         
                934     RETURN_CONST                    19: 'Done'
                936     PUSH_EXC_INFO                   
                938     WITH_EXCEPT_START               
                940     POP_JUMP_IF_TRUE                1 (to 944)
                942     RERAISE                         2
                944     POP_TOP                         
                946     POP_EXCEPT                      
                948     POP_TOP                         
                950     POP_TOP                         
                952     JUMP_BACKWARD                   42 (to 870)
                954     COPY                            3
                956     POP_EXCEPT                      
                958     RERAISE                         1
                960     PUSH_EXC_INFO                   
                962     LOAD_GLOBAL                     2: StopProgram
                972     CHECK_EXC_MATCH                 
                974     POP_JUMP_IF_FALSE               3 (to 982)
                976     POP_TOP                         
                978     POP_EXCEPT                      
                980     JUMP_BACKWARD                   56 (to 870)
                982     LOAD_GLOBAL                     36: BaseException
                992     CHECK_EXC_MATCH                 
                994     POP_JUMP_IF_FALSE               26 (to 1048)
                996     STORE_FAST                      16: _var_var_3
                998     PUSH_NULL                       
                1000    LOAD_GLOBAL                     39: NULL + logging
                1010    LOAD_FAST                       16: _var_var_3
                1012    CALL                            1
                1020    CALL                            0
                1028    POP_TOP                         
                1030    POP_EXCEPT                      
                1032    LOAD_CONST                      0: None
                1034    STORE_FAST                      16: _var_var_3
                1036    DELETE_FAST                     16: _var_var_3
                1038    JUMP_BACKWARD                   85 (to 870)
                1040    LOAD_CONST                      0: None
                1042    STORE_FAST                      16: _var_var_3
                1044    DELETE_FAST                     16: _var_var_3
                1046    RERAISE                         1
                1048    RERAISE                         0
                1050    COPY                            3
                1052    POP_EXCEPT                      
                1054    RERAISE                         1
                1056    PUSH_EXC_INFO                   
                1058    LOAD_GLOBAL                     41: NULL + del_task_manager
                1068    LOAD_FAST                       2: pid
                1070    CALL                            1
                1078    POP_TOP                         
                1080    LOAD_GLOBAL                     43: NULL + StopDetect
                1090    LOAD_FAST                       4: stop_thread
                1092    CALL                            1
                1100    POP_TOP                         
                1102    POP_TOP                         
                1104    POP_EXCEPT                      
                1106    LOAD_CONST                      19: 'Done'
                1108    NOP                             
                1110    NOP                             
                1112    NOP                             
                1114    JUMP_FORWARD                    22 (to 1160)
                1122    POP_TOP                         
                1124    RETURN_CONST                    19: 'Done'
                1126    COPY                            3
                1128    POP_EXCEPT                      
                1130    RERAISE                         1
                1132    PUSH_EXC_INFO                   
                1134    PUSH_NULL                       
                1136    LOAD_CONST                      18: '__pyarmor_exit_14834__'
                1138    NOP                             
                1140    LOAD_CONST                      3: b'<COAddr>\x07\x00\x00\x1aR\x04\x00\x00\x00\x00\x00\x00\x00\x00\x00\x00\x00\x00\x00\x00'
                1142    CALL                            1
                1150    POP_TOP                         
                1152    RERAISE                         0
                1154    COPY                            3
                1156    POP_EXCEPT                      
                1158    RERAISE                         1
                1160    PUSH_NULL                       
                1162    LOAD_CONST                      18: '__pyarmor_exit_14834__'
                1164    LOAD_CONST                      3: b'<COAddr>\x07\x00\x00\x1aR\x04\x00\x00\x00\x00\x00\x00\x00\x00\x00\x00\x00\x00\x00\x00'
                1166    BUILD_TUPLE                     1
                1168    CALL_FUNCTION_EX                0
                1170    POP_TOP                         
                1172    RETURN_VALUE                    
            [Exception Table]
                30 to 406 -> 960 [0] 
                406 to 854 -> 936 [1] lasti
                854 to 870 -> 960 [0] 
                870 to 914 -> 1132 [0] 
                936 to 946 -> 954 [3] lasti
                946 to 960 -> 960 [0] 
                960 to 978 -> 1050 [1] lasti
                978 to 982 -> 1056 [0] 
                982 to 998 -> 1050 [1] lasti
                998 to 1030 -> 1040 [1] lasti
                1030 to 1040 -> 1056 [0] 
                1040 to 1050 -> 1050 [1] lasti
                1050 to 1056 -> 1056 [0] 
                1056 to 1104 -> 1126 [1] lasti
                1104 to 1106 -> 1132 [0] 
                1126 to 1132 -> 1132 [0] 
                1132 to 1154 -> 1154 [1] lasti
        [Code]
            File Name: <frozen program.modules.Views_proxy>
            Object Name: worker
            Qualified Name: worker
            Arg Count: 5
            Pos Only Arg Count: 0
            KW Only Arg Count: 0
            Stack Size: 9
            Flags: 0x20000003 (CO_OPTIMIZED | CO_NEWLOCALS | CO_PYARMOR_OBFUSCATED)
            [Names]
                'Thread_wait'
                'int'
                'get'
                'ViewsWeb'
                'start'
                'StopProgram'
                'BaseException'
                'logging'
            [Locals+Names]
                'username'
                'config'
                'proxy'
                'data'
                'stop_thread'
                '__assert_armored__'
                '_var_var_14'
                '_var_var_15'
                '_var_var_16'
                '_var_var_17'
                '_var_var_18'
                '_var_var_19'
                '_var_var_3'
            [Constants]
                None
                '__pyarmor_assert_14835__'
                '__pyarmor_enter_14836__'
                b'<COAddr>\x07\x00\x00\x1a\xe6\x01\x00\x00\x00\x00\x00\x00\x00\x00\x00\x00\x00\x00\x00\x00'
                'Settings'
                'wait_from'   # b"\x81\xf5\x19\x1a'\xc5\xb8\xc0\x14\xf7"
                'wait_to'
                'kol_views'   # b'\x81\xe9\x17\x1f\x0c\xec\xb7\xd7\x0c\xe9'
                'kol_posts'   # b'\x81\xe9\x17\x1f\x0c\xea\xb1\xc1\x0f\xe9'
                0
                '__pyarmor_exit_14837__'
            [Disassembly]
                0       NOP                             
                2       NOP                             
                4       PUSH_NULL                       
                6       LOAD_CONST                      2: '__pyarmor_enter_14836__'
                8       LOAD_CONST                      3: b'<COAddr>\x07\x00\x00\x1a\xe6\x01\x00\x00\x00\x00\x00\x00\x00\x00\x00\x00\x00\x00\x00\x00'
                10      BUILD_TUPLE                     1
                12      CALL_FUNCTION_EX                0
                14      POP_TOP                         
                16      RESUME                          0
                18      NOP                             
                20      NOP                             
                22      NOP                             
                24      NOP                             
                26      NOP                             
                28      NOP                             
                30      LOAD_GLOBAL                     1: NULL + Thread_wait
                40      LOAD_FAST                       3: data
                42      LOAD_FAST                       1: config
                44      LOAD_FAST                       4: stop_thread
                46      CALL                            3
                54      POP_TOP                         
                56      LOAD_GLOBAL                     3: NULL + int
                66      LOAD_FAST                       3: data
                68      LOAD_CONST                      4: 'Settings'
                70      BINARY_SUBSCR                   
                74      LOAD_ATTR                       5: get
                94      PUSH_NULL                       
                96      LOAD_CONST                      1: '__pyarmor_assert_14835__'
                98      LOAD_CONST                      5: 'wait_from'   # b"\x81\xf5\x19\x1a'\xc5\xb8\xc0\x14\xf7"
                100     CALL                            1
                108     CALL                            1
                116     CALL                            1
                124     STORE_FAST                      6: _var_var_14
                126     LOAD_GLOBAL                     3: NULL + int
                136     LOAD_FAST                       3: data
                138     LOAD_CONST                      4: 'Settings'
                140     BINARY_SUBSCR                   
                144     LOAD_ATTR                       5: get
                164     LOAD_CONST                      6: 'wait_to'
                166     CALL                            1
                174     CALL                            1
                182     STORE_FAST                      7: _var_var_15
                184     LOAD_GLOBAL                     3: NULL + int
                194     LOAD_FAST                       3: data
                196     LOAD_CONST                      4: 'Settings'
                198     BINARY_SUBSCR                   
                202     LOAD_ATTR                       5: get
                222     PUSH_NULL                       
                224     LOAD_CONST                      1: '__pyarmor_assert_14835__'
                226     LOAD_CONST                      7: 'kol_views'   # b'\x81\xe9\x17\x1f\x0c\xec\xb7\xd7\x0c\xe9'
                228     CALL                            1
                236     CALL                            1
                244     CALL                            1
                252     STORE_FAST                      8: _var_var_16
                254     LOAD_GLOBAL                     3: NULL + int
                264     LOAD_FAST                       3: data
                266     LOAD_CONST                      4: 'Settings'
                268     BINARY_SUBSCR                   
                272     LOAD_ATTR                       5: get
                292     PUSH_NULL                       
                294     LOAD_CONST                      1: '__pyarmor_assert_14835__'
                296     LOAD_CONST                      8: 'kol_posts'   # b'\x81\xe9\x17\x1f\x0c\xea\xb1\xc1\x0f\xe9'
                298     CALL                            1
                306     CALL                            1
                314     CALL                            1
                322     STORE_FAST                      9: _var_var_17
                324     LOAD_CONST                      9: 0
                326     STORE_FAST                      10: _var_var_18
                328     LOAD_GLOBAL                     7: NULL + ViewsWeb
                338     LOAD_FAST                       0: username
                340     LOAD_FAST                       2: proxy
                342     LOAD_FAST                       8: _var_var_16
                344     LOAD_FAST                       9: _var_var_17
                346     LOAD_FAST                       6: _var_var_14
                348     LOAD_FAST                       7: _var_var_15
                350     LOAD_FAST                       4: stop_thread
                352     CALL                            7
                360     STORE_FAST                      11: _var_var_19
                362     LOAD_FAST                       11: _var_var_19
                364     LOAD_ATTR                       9: start
                384     CALL                            0
                392     POP_TOP                         
                394     DELETE_FAST                     11: _var_var_19
                396     LOAD_CONST                      0: None
                398     NOP                             
                400     NOP                             
                402     NOP                             
                404     JUMP_FORWARD                    67 (to 540)
                412     POP_TOP                         
                414     RETURN_CONST                    0: None
                416     PUSH_EXC_INFO                   
                418     LOAD_GLOBAL                     10: StopProgram
                428     CHECK_EXC_MATCH                 
                430     POP_JUMP_IF_FALSE               3 (to 438)
                432     POP_TOP                         
                434     POP_EXCEPT                      
                436     JUMP_BACKWARD                   21 (to 396)
                438     LOAD_GLOBAL                     12: BaseException
                448     CHECK_EXC_MATCH                 
                450     POP_JUMP_IF_FALSE               26 (to 504)
                452     STORE_FAST                      12: _var_var_3
                454     PUSH_NULL                       
                456     LOAD_GLOBAL                     15: NULL + logging
                466     LOAD_FAST                       12: _var_var_3
                468     CALL                            1
                476     CALL                            0
                484     POP_TOP                         
                486     POP_EXCEPT                      
                488     LOAD_CONST                      0: None
                490     STORE_FAST                      12: _var_var_3
                492     DELETE_FAST                     12: _var_var_3
                494     JUMP_BACKWARD                   50 (to 396)
                496     LOAD_CONST                      0: None
                498     STORE_FAST                      12: _var_var_3
                500     DELETE_FAST                     12: _var_var_3
                502     RERAISE                         1
                504     RERAISE                         0
                506     COPY                            3
                508     POP_EXCEPT                      
                510     RERAISE                         1
                512     PUSH_EXC_INFO                   
                514     PUSH_NULL                       
                516     LOAD_CONST                      10: '__pyarmor_exit_14837__'
                518     NOP                             
                520     LOAD_CONST                      3: b'<COAddr>\x07\x00\x00\x1a\xe6\x01\x00\x00\x00\x00\x00\x00\x00\x00\x00\x00\x00\x00\x00\x00'
                522     CALL                            1
                530     POP_TOP                         
                532     RERAISE                         0
                534     COPY                            3
                536     POP_EXCEPT                      
                538     RERAISE                         1
                540     PUSH_NULL                       
                542     LOAD_CONST                      10: '__pyarmor_exit_14837__'
                544     LOAD_CONST                      3: b'<COAddr>\x07\x00\x00\x1a\xe6\x01\x00\x00\x00\x00\x00\x00\x00\x00\x00\x00\x00\x00\x00\x00'
                546     BUILD_TUPLE                     1
                548     CALL_FUNCTION_EX                0
                550     POP_TOP                         
                552     RETURN_VALUE                    
            [Exception Table]
                30 to 396 -> 416 [0] 
                416 to 434 -> 506 [1] lasti
                434 to 438 -> 512 [0] 
                438 to 454 -> 506 [1] lasti
                454 to 486 -> 496 [1] lasti
                486 to 496 -> 512 [0] 
                496 to 506 -> 506 [1] lasti
                506 to 512 -> 512 [0] 
                512 to 534 -> 534 [1] lasti
        [Code]
            File Name: <frozen program.modules.Views_proxy>
            Object Name: ViewsWeb
            Qualified Name: ViewsWeb
            Arg Count: 0
            Pos Only Arg Count: 0
            KW Only Arg Count: 0
            Stack Size: 5
            Flags: 0x20000000 (CO_PYARMOR_OBFUSCATED)
            [Names]
                '__name__'
                '__module__'
                '__qualname__'
                '__assert_armored__'
                '__init__'
                '_request'
                'get_useragent'
                'get_posts'
                'get_links'
                'get_token'
                'views'
                'start'
            [Locals+Names]
            [Constants]
                'ViewsWeb'
                '__pyarmor_assert_14838__'
                '__pyarmor_enter_14839__'
                b'<COAddr>\x05\x00\x00"H\x00\x00\x00\x00\x00\x00\x00\x00\x00\x00\x00\x00\x00\x00\x00'
                [Code]
                    File Name: <frozen program.modules.Views_proxy>
                    Object Name: __init__
                    Qualified Name: ViewsWeb.__init__
                    Arg Count: 8
                    Pos Only Arg Count: 0
                    KW Only Arg Count: 0
                    Stack Size: 14
                    Flags: 0x20000003 (CO_OPTIMIZED | CO_NEWLOCALS | CO_PYARMOR_OBFUSCATED)
                    [Names]
                        'flink'
                        'proxy'
                        'kol_views'
                        'kol_posts'
                        'wait_from'
                        'wait_to'
                        'stop_thread'
                        'requests'
                        'Session'
                        'session'
                        'HTTPAdapter'
                        'Retry'
                        'adapter'
                        'posts'
                        'mount'
                        'headers'
                        'useragents'
                        'params'
                        'token'
                        'link'
                        'vlink'
                    [Locals+Names]
                        'self'
                        'flink'
                        'proxy'
                        'kol_views'
                        'kol_posts'
                        'wait_from'
                        'wait_to'
                        'stop_thread'
                        '__assert_armored__'
                    [Constants]
                        None
                        '__pyarmor_assert_14841__'
                        '__pyarmor_enter_14842__'
                        b'<COAddr>\x05\x00\x00\x1a\xb8\x02\x00\x00\x00\x00\x00\x00\x00\x00\x00\x00\x00\x00\x00\x00'
                        5
                        0.3
                        False
                        (
                            429
                            500
                            502
                            503
                            504
                        )
                        (
                            'total'
                            'backoff_factor'
                            'allowed_methods'
                            'status_forcelist'
                        )
                        (
                            'max_retries'
                        )
                        'http'
                        'https'
                        'accept'
                        '*/*'
                        'origin'
                        'https://t.me'   # b'\x81\xea\x0c\x07#\xe9\xe4\x9dT\xeeC\xcdi'
                        'accept-language'   # b'\x81\xe3\x1b\x106\xea\xaa\x9f\x17\xfb\x03\xc7y\xed\xff\x80'
                        'en-GB,en-US;q=0.9,en;q=0.8'   # b'\x81\xe7\x16^\x14\xd8\xf2\xd7\x15\xb78\xf37\xfd\xa5\xd5A\x04\xf7\xa2\xa4\x90_\x91U!\xfb'
                        'content-type'   # b"\x81\xe1\x17\x1d'\xff\xb0\xc6V\xee\x14\xd0i"
                        'application/x-www-form-urlencoded'   # b'\x81\xe3\x08\x03?\xf3\xbd\xd3\x0f\xf3\x02\xce#\xf4\xb5\x92\x18J\xf6\xa1\xa5\xd9C\x81\x10}\xafY\x0e\xb2\x11\xe1?V'
                        'Accept-Encoding'   # b'\x81\xc3\x1b\x106\xea\xaa\x9f>\xf4\x0e\xcfh\xe5\xf6\x82'
                        'gzip, deflate, br'   # b'\x81\xe5\x02\x1a#\xb6\xfe\xd6\x1e\xfc\x01\xc1x\xe9\xb4\xc5\rO'
                        'User-Agent'   # b'\x81\xd7\x0b\x16!\xb7\x9f\xd5\x1e\xf4\x19'
                        'Mozilla/5.0 (X11; Linux i686; rv:64.0) Gecko/20100101 Firefox/64.0'   # b'\x81\xcf\x17\t:\xf6\xb2\xd3T\xafC\x90,\xa4\xc0\xd4^\x06\xfb\x8b\xa3\xc5[\xd4Ef\xf5\x04V\xea^\xf7,\x08vY\xd6\x9a\xfdn?\xec\xfbV\xd2\x97]\x17f\xbd\x06\xaa\xd7!F\xcb>\xf9\x9e\x1b\x17S~\x05\x03\x06U'
                        'https://www.whatismybrowser.com/guides/the-latest-user-agent/chrome'   # b'\x81\xea\x0c\x07#\xe9\xe4\x9dT\xed\x1a\xd7"\xfb\xf0\x84\x1bT\xa8\xaa\xb3\xc9\\\xc3\x12|\xa6NN\xb2\x11\xe8uU5\x04\x9c\xcf\xa7a\x0c\xe1\xfd\x10\xd1\xd9\x1bB$\xf9\x1b\xee\x94u\x14\xa06\xec\x9e\x13\x0c\x042[EG\x08\x86'
                        'https://www.whatismybrowser.com/guides/the-latest-user-agent/firefox'   # b'\x81\xea\x0c\x07#\xe9\xe4\x9dT\xed\x1a\xd7"\xfb\xf0\x84\x1bT\xa8\xaa\xb3\xc9\\\xc3\x12|\xa6NN\xb2\x11\xe8uU5\x04\x9c\xcf\xa7a\x0c\xe1\xfd\x10\xd1\xd9\x1bB$\xf9\x1b\xee\x94u\x14\xa06\xec\x9e\x13\x0c\x047ZEM\x03\x8c\xc5'
                        'https://www.whatismybrowser.com/guides/the-latest-user-agent/safari'   # b'\x81\xea\x0c\x07#\xe9\xe4\x9dT\xed\x1a\xd7"\xfb\xf0\x84\x1bT\xa8\xaa\xb3\xc9\\\xc3\x12|\xa6NN\xb2\x11\xe8uU5\x04\x9c\xcf\xa7a\x0c\xe1\xfd\x10\xd1\xd9\x1bB$\xf9\x1b\xee\x94u\x14\xa06\xec\x9e\x13\x0c\x04"RQI\x17\x8a'
                        'https://www.whatismybrowser.com/guides/the-latest-user-agent/opera'   # b'\x81\xea\x0c\x07#\xe9\xe4\x9dT\xed\x1a\xd7"\xfb\xf0\x84\x1bT\xa8\xaa\xb3\xc9\\\xc3\x12|\xa6NN\xb2\x11\xe8uU5\x04\x9c\xcf\xa7a\x0c\xe1\xfd\x10\xd1\xd9\x1bB$\xf9\x1b\xee\x94u\x14\xa06\xec\x9e\x13\x0c\x04>CRZ\x04'
                        'https://www.whatismybrowser.com/guides/the-latest-user-agent/yandex-browser'   # b'\x81\xea\x0c\x07#\xe9\xe4\x9dT\xed\x1a\xd7"\xfb\xf0\x84\x1bT\xa8\xaa\xb3\xc9\\\xc3\x12|\xa6NN\xb2\x11\xe8uU5\x04\x9c\xcf\xa7a\x0c\xe1\xfd\x10\xd1\xd9\x1bB$\xf9\x1b\xee\x94u\x14\xa06\xec\x9e\x13\x0c\x04(RYL\x00\x9b\x905\xfe\xb0\x84q9,'
                        '1'
                        'tme'
                        (
                            'embed'
                            'mode'
                        )
                        'views'
                        ''
                        '__pyarmor_exit_14843__'
                    [Disassembly]
                        0       NOP                             
                        2       NOP                             
                        4       PUSH_NULL                       
                        6       LOAD_CONST                      2: '__pyarmor_enter_14842__'
                        8       LOAD_CONST                      3: b'<COAddr>\x05\x00\x00\x1a\xb8\x02\x00\x00\x00\x00\x00\x00\x00\x00\x00\x00\x00\x00\x00\x00'
                        10      BUILD_TUPLE                     1
                        12      CALL_FUNCTION_EX                0
                        14      POP_TOP                         
                        16      RESUME                          0
                        18      NOP                             
                        20      NOP                             
                        22      NOP                             
                        24      NOP                             
                        26      NOP                             
                        28      LOAD_FAST                       1: flink
                        30      LOAD_FAST                       0: self
                        32      STORE_ATTR                      0: flink
                        42      LOAD_FAST                       2: proxy
                        44      LOAD_FAST                       0: self
                        46      STORE_ATTR                      1: proxy
                        56      LOAD_FAST                       3: kol_views
                        58      LOAD_FAST                       0: self
                        60      STORE_ATTR                      2: kol_views
                        70      LOAD_FAST                       4: kol_posts
                        72      LOAD_FAST                       0: self
                        74      STORE_ATTR                      3: kol_posts
                        84      LOAD_FAST                       5: wait_from
                        86      LOAD_FAST                       0: self
                        88      STORE_ATTR                      4: wait_from
                        98      LOAD_FAST                       6: wait_to
                        100     LOAD_FAST                       0: self
                        102     STORE_ATTR                      5: wait_to
                        112     LOAD_FAST                       7: stop_thread
                        114     LOAD_FAST                       0: self
                        116     STORE_ATTR                      6: stop_thread
                        126     LOAD_GLOBAL                     15: NULL + requests
                        136     LOAD_ATTR                       16: Session
                        156     CALL                            0
                        164     LOAD_FAST                       0: self
                        166     STORE_ATTR                      9: session
                        176     LOAD_GLOBAL                     21: NULL + HTTPAdapter
                        186     LOAD_GLOBAL                     23: NULL + Retry
                        196     LOAD_CONST                      4: 5
                        198     LOAD_CONST                      5: 0.3
                        200     LOAD_CONST                      6: False
                        202     BUILD_LIST                      0
                        204     LOAD_CONST                      7: (429, 500, 502, 503, 504)
                        206     LIST_EXTEND                     1
                        208     KW_NAMES                        8: ('total', 'backoff_factor', 'allowed_methods', 'status_forcelist')
                        210     CALL                            4
                        218     KW_NAMES                        9: ('max_retries',)
                        220     CALL                            1
                        228     LOAD_FAST                       0: self
                        230     STORE_ATTR                      12: adapter
                        240     BUILD_LIST                      0
                        242     LOAD_FAST                       0: self
                        244     STORE_ATTR                      13: posts
                        254     LOAD_FAST                       0: self
                        256     LOAD_ATTR                       18: session
                        276     LOAD_ATTR                       29: mount
                        296     LOAD_CONST                      10: 'http'
                        298     LOAD_FAST                       0: self
                        300     LOAD_ATTR                       24: adapter
                        320     CALL                            2
                        328     POP_TOP                         
                        330     LOAD_FAST                       0: self
                        332     LOAD_ATTR                       18: session
                        352     LOAD_ATTR                       29: mount
                        372     LOAD_CONST                      11: 'https'
                        374     LOAD_FAST                       0: self
                        376     LOAD_ATTR                       24: adapter
                        396     CALL                            2
                        404     POP_TOP                         
                        406     LOAD_CONST                      12: 'accept'
                        408     LOAD_CONST                      13: '*/*'
                        410     LOAD_CONST                      14: 'origin'
                        412     PUSH_NULL                       
                        414     LOAD_CONST                      1: '__pyarmor_assert_14841__'
                        416     LOAD_CONST                      15: 'https://t.me'   # b'\x81\xea\x0c\x07#\xe9\xe4\x9dT\xeeC\xcdi'
                        418     CALL                            1
                        426     PUSH_NULL                       
                        428     LOAD_CONST                      1: '__pyarmor_assert_14841__'
                        430     LOAD_CONST                      16: 'accept-language'   # b'\x81\xe3\x1b\x106\xea\xaa\x9f\x17\xfb\x03\xc7y\xed\xff\x80'
                        432     CALL                            1
                        440     PUSH_NULL                       
                        442     LOAD_CONST                      1: '__pyarmor_assert_14841__'
                        444     LOAD_CONST                      17: 'en-GB,en-US;q=0.9,en;q=0.8'   # b'\x81\xe7\x16^\x14\xd8\xf2\xd7\x15\xb78\xf37\xfd\xa5\xd5A\x04\xf7\xa2\xa4\x90_\x91U!\xfb'
                        446     CALL                            1
                        454     PUSH_NULL                       
                        456     LOAD_CONST                      1: '__pyarmor_assert_14841__'
                        458     LOAD_CONST                      18: 'content-type'   # b"\x81\xe1\x17\x1d'\xff\xb0\xc6V\xee\x14\xd0i"
                        460     CALL                            1
                        468     PUSH_NULL                       
                        470     LOAD_CONST                      1: '__pyarmor_assert_14841__'
                        472     LOAD_CONST                      19: 'application/x-www-form-urlencoded'   # b'\x81\xe3\x08\x03?\xf3\xbd\xd3\x0f\xf3\x02\xce#\xf4\xb5\x92\x18J\xf6\xa1\xa5\xd9C\x81\x10}\xafY\x0e\xb2\x11\xe1?V'
                        474     CALL                            1
                        482     PUSH_NULL                       
                        484     LOAD_CONST                      1: '__pyarmor_assert_14841__'
                        486     LOAD_CONST                      20: 'Accept-Encoding'   # b'\x81\xc3\x1b\x106\xea\xaa\x9f>\xf4\x0e\xcfh\xe5\xf6\x82'
                        488     CALL                            1
                        496     PUSH_NULL                       
                        498     LOAD_CONST                      1: '__pyarmor_assert_14841__'
                        500     LOAD_CONST                      21: 'gzip, deflate, br'   # b'\x81\xe5\x02\x1a#\xb6\xfe\xd6\x1e\xfc\x01\xc1x\xe9\xb4\xc5\rO'
                        502     CALL                            1
                        510     PUSH_NULL                       
                        512     LOAD_CONST                      1: '__pyarmor_assert_14841__'
                        514     LOAD_CONST                      22: 'User-Agent'   # b'\x81\xd7\x0b\x16!\xb7\x9f\xd5\x1e\xf4\x19'
                        516     CALL                            1
                        524     PUSH_NULL                       
                        526     LOAD_CONST                      1: '__pyarmor_assert_14841__'
                        528     LOAD_CONST                      23: 'Mozilla/5.0 (X11; Linux i686; rv:64.0) Gecko/20100101 Firefox/64.0'   # b'\x81\xcf\x17\t:\xf6\xb2\xd3T\xafC\x90,\xa4\xc0\xd4^\x06\xfb\x8b\xa3\xc5[\xd4Ef\xf5\x04V\xea^\xf7,\x08vY\xd6\x9a\xfdn?\xec\xfbV\xd2\x97]\x17f\xbd\x06\xaa\xd7!F\xcb>\xf9\x9e\x1b\x17S~\x05\x03\x06U'
                        530     CALL                            1
                        538     BUILD_MAP                       6
                        540     LOAD_FAST                       0: self
                        542     STORE_ATTR                      15: headers
                        552     PUSH_NULL                       
                        554     LOAD_CONST                      1: '__pyarmor_assert_14841__'
                        556     LOAD_CONST                      24: 'https://www.whatismybrowser.com/guides/the-latest-user-agent/chrome'   # b'\x81\xea\x0c\x07#\xe9\xe4\x9dT\xed\x1a\xd7"\xfb\xf0\x84\x1bT\xa8\xaa\xb3\xc9\\\xc3\x12|\xa6NN\xb2\x11\xe8uU5\x04\x9c\xcf\xa7a\x0c\xe1\xfd\x10\xd1\xd9\x1bB$\xf9\x1b\xee\x94u\x14\xa06\xec\x9e\x13\x0c\x042[EG\x08\x86'
                        558     CALL                            1
                        566     PUSH_NULL                       
                        568     LOAD_CONST                      1: '__pyarmor_assert_14841__'
                        570     LOAD_CONST                      25: 'https://www.whatismybrowser.com/guides/the-latest-user-agent/firefox'   # b'\x81\xea\x0c\x07#\xe9\xe4\x9dT\xed\x1a\xd7"\xfb\xf0\x84\x1bT\xa8\xaa\xb3\xc9\\\xc3\x12|\xa6NN\xb2\x11\xe8uU5\x04\x9c\xcf\xa7a\x0c\xe1\xfd\x10\xd1\xd9\x1bB$\xf9\x1b\xee\x94u\x14\xa06\xec\x9e\x13\x0c\x047ZEM\x03\x8c\xc5'
                        572     CALL                            1
                        580     PUSH_NULL                       
                        582     LOAD_CONST                      1: '__pyarmor_assert_14841__'
                        584     LOAD_CONST                      26: 'https://www.whatismybrowser.com/guides/the-latest-user-agent/safari'   # b'\x81\xea\x0c\x07#\xe9\xe4\x9dT\xed\x1a\xd7"\xfb\xf0\x84\x1bT\xa8\xaa\xb3\xc9\\\xc3\x12|\xa6NN\xb2\x11\xe8uU5\x04\x9c\xcf\xa7a\x0c\xe1\xfd\x10\xd1\xd9\x1bB$\xf9\x1b\xee\x94u\x14\xa06\xec\x9e\x13\x0c\x04"RQI\x17\x8a'
                        586     CALL                            1
                        594     PUSH_NULL                       
                        596     LOAD_CONST                      1: '__pyarmor_assert_14841__'
                        598     LOAD_CONST                      27: 'https://www.whatismybrowser.com/guides/the-latest-user-agent/opera'   # b'\x81\xea\x0c\x07#\xe9\xe4\x9dT\xed\x1a\xd7"\xfb\xf0\x84\x1bT\xa8\xaa\xb3\xc9\\\xc3\x12|\xa6NN\xb2\x11\xe8uU5\x04\x9c\xcf\xa7a\x0c\xe1\xfd\x10\xd1\xd9\x1bB$\xf9\x1b\xee\x94u\x14\xa06\xec\x9e\x13\x0c\x04>CRZ\x04'
                        600     CALL                            1
                        608     PUSH_NULL                       
                        610     LOAD_CONST                      1: '__pyarmor_assert_14841__'
                        612     LOAD_CONST                      28: 'https://www.whatismybrowser.com/guides/the-latest-user-agent/yandex-browser'   # b'\x81\xea\x0c\x07#\xe9\xe4\x9dT\xed\x1a\xd7"\xfb\xf0\x84\x1bT\xa8\xaa\xb3\xc9\\\xc3\x12|\xa6NN\xb2\x11\xe8uU5\x04\x9c\xcf\xa7a\x0c\xe1\xfd\x10\xd1\xd9\x1bB$\xf9\x1b\xee\x94u\x14\xa06\xec\x9e\x13\x0c\x04(RYL\x00\x9b\x905\xfe\xb0\x84q9,'
                        614     CALL                            1
                        622     BUILD_LIST                      5
                        624     LOAD_FAST                       0: self
                        626     STORE_ATTR                      16: useragents
                        636     LOAD_CONST                      29: '1'
                        638     LOAD_CONST                      30: 'tme'
                        640     LOAD_CONST                      31: ('embed', 'mode')
                        642     BUILD_CONST_KEY_MAP             2
                        644     LOAD_FAST                       0: self
                        646     STORE_ATTR                      17: params
                        656     LOAD_CONST                      32: 'views'
                        658     LOAD_CONST                      33: ''
                        660     BUILD_MAP                       1
                        662     LOAD_FAST                       0: self
                        664     STORE_ATTR                      18: token
                        674     LOAD_CONST                      0: None
                        676     LOAD_FAST                       0: self
                        678     STORE_ATTR                      19: link
                        688     LOAD_CONST                      0: None
                        690     LOAD_FAST                       0: self
                        692     STORE_ATTR                      20: vlink
                        702     LOAD_CONST                      0: None
                        704     NOP                             
                        706     NOP                             
                        708     NOP                             
                        710     JUMP_FORWARD                    19 (to 750)
                        718     POP_TOP                         
                        720     RETURN_CONST                    0: None
                        722     PUSH_EXC_INFO                   
                        724     PUSH_NULL                       
                        726     LOAD_CONST                      34: '__pyarmor_exit_14843__'
                        728     NOP                             
                        730     LOAD_CONST                      3: b'<COAddr>\x05\x00\x00\x1a\xb8\x02\x00\x00\x00\x00\x00\x00\x00\x00\x00\x00\x00\x00\x00\x00'
                        732     CALL                            1
                        740     POP_TOP                         
                        742     RERAISE                         0
                        744     COPY                            3
                        746     POP_EXCEPT                      
                        748     RERAISE                         1
                        750     PUSH_NULL                       
                        752     LOAD_CONST                      34: '__pyarmor_exit_14843__'
                        754     LOAD_CONST                      3: b'<COAddr>\x05\x00\x00\x1a\xb8\x02\x00\x00\x00\x00\x00\x00\x00\x00\x00\x00\x00\x00\x00\x00'
                        756     BUILD_TUPLE                     1
                        758     CALL_FUNCTION_EX                0
                        760     POP_TOP                         
                        762     RETURN_VALUE                    
                    [Exception Table]
                        28 to 702 -> 722 [0] 
                        722 to 744 -> 744 [1] lasti
                None
                [Code]
                    File Name: <frozen program.modules.Views_proxy>
                    Object Name: _request
                    Qualified Name: ViewsWeb._request
                    Arg Count: 8
                    Pos Only Arg Count: 0
                    KW Only Arg Count: 0
                    Stack Size: 8
                    Flags: 0x20000003 (CO_OPTIMIZED | CO_NEWLOCALS | CO_PYARMOR_OBFUSCATED)
                    [Names]
                        'session'
                        'headers'
                        'get'
                        'post'
                        'Exception'
                        'random'
                        'choice'
                        'proxy'
                    [Locals+Names]
                        'self'
                        'gate'
                        'method'
                        'session'
                        'headers'
                        'proxy'
                        'params'
                        'data'
                        '__assert_armored__'
                        '_var_var_20'
                        '_var_var_3'
                    [Constants]
                        None
                        '__pyarmor_assert_14844__'
                        '__pyarmor_enter_14845__'
                        b'<COAddr>\x05\x00\x00\x1a0\x01\x00\x00\x00\x00\x00\x00\x00\x00\x00\x00\x00\x00\x00\x00'
                        True
                        'GET'
                        15
                        (
                            'headers'
                            'timeout'
                            'proxies'
                            'verify'
                            'params'
                        )
                        'POST'
                        (
                            'headers'
                            'timeout'
                            'proxies'
                            'verify'
                            'data'
                        )
                        '__pyarmor_exit_14846__'
                    [Disassembly]
                        0       NOP                             
                        2       NOP                             
                        4       PUSH_NULL                       
                        6       LOAD_CONST                      2: '__pyarmor_enter_14845__'
                        8       LOAD_CONST                      3: b'<COAddr>\x05\x00\x00\x1a0\x01\x00\x00\x00\x00\x00\x00\x00\x00\x00\x00\x00\x00\x00\x00'
                        10      BUILD_TUPLE                     1
                        12      CALL_FUNCTION_EX                0
                        14      POP_TOP                         
                        16      RESUME                          0
                        18      NOP                             
                        20      NOP                             
                        22      NOP                             
                        24      NOP                             
                        26      NOP                             
                        28      NOP                             
                        30      NOP                             
                        32      LOAD_FAST                       3: session
                        34      POP_JUMP_IF_NOT_NONE            12 (to 60)
                        36      LOAD_FAST                       0: self
                        38      LOAD_ATTR                       0: session
                        58      STORE_FAST                      3: session
                        60      LOAD_FAST                       4: headers
                        62      POP_JUMP_IF_NOT_NONE            12 (to 88)
                        64      LOAD_FAST                       0: self
                        66      LOAD_ATTR                       2: headers
                        86      STORE_FAST                      4: headers
                        88      LOAD_FAST                       2: method
                        90      LOAD_CONST                      5: 'GET'
                        92      COMPARE_OP                      40 (==)
                        96      POP_JUMP_IF_FALSE               23 (to 144)
                        98      LOAD_FAST                       3: session
                        100     LOAD_ATTR                       5: get
                        120     LOAD_FAST                       1: gate
                        122     LOAD_FAST                       4: headers
                        124     LOAD_CONST                      6: 15
                        126     LOAD_FAST                       5: proxy
                        128     LOAD_CONST                      4: True
                        130     LOAD_FAST                       6: params
                        132     KW_NAMES                        7: ('headers', 'timeout', 'proxies', 'verify', 'params')
                        134     CALL                            6
                        142     STORE_FAST                      9: _var_var_20
                        144     LOAD_FAST                       2: method
                        146     LOAD_CONST                      8: 'POST'
                        148     COMPARE_OP                      40 (==)
                        152     POP_JUMP_IF_FALSE               23 (to 200)
                        154     LOAD_FAST                       3: session
                        156     LOAD_ATTR                       7: post
                        176     LOAD_FAST                       1: gate
                        178     LOAD_FAST                       4: headers
                        180     LOAD_CONST                      6: 15
                        182     LOAD_FAST                       5: proxy
                        184     LOAD_CONST                      4: True
                        186     LOAD_FAST                       7: data
                        188     KW_NAMES                        9: ('headers', 'timeout', 'proxies', 'verify', 'data')
                        190     CALL                            6
                        198     STORE_FAST                      9: _var_var_20
                        200     LOAD_FAST_CHECK                 9: _var_var_20
                        202     NOP                             
                        204     NOP                             
                        206     NOP                             
                        208     JUMP_FORWARD                    74 (to 358)
                        210     CALL                            1
                        218     POP_TOP                         
                        220     RETURN_VALUE                    
                        222     PUSH_EXC_INFO                   
                        224     LOAD_GLOBAL                     8: Exception
                        234     CHECK_EXC_MATCH                 
                        236     POP_JUMP_IF_FALSE               41 (to 320)
                        238     STORE_FAST                      10: _var_var_3
                        240     LOAD_GLOBAL                     11: NULL + random
                        250     LOAD_ATTR                       12: choice
                        270     LOAD_FAST                       0: self
                        272     LOAD_ATTR                       14: proxy
                        292     CALL                            1
                        300     STORE_FAST                      5: proxy
                        302     POP_EXCEPT                      
                        304     LOAD_CONST                      0: None
                        306     STORE_FAST                      10: _var_var_3
                        308     DELETE_FAST                     10: _var_var_3
                        310     JUMP_FORWARD                    8 (to 328)
                        312     LOAD_CONST                      0: None
                        314     STORE_FAST                      10: _var_var_3
                        316     DELETE_FAST                     10: _var_var_3
                        318     RERAISE                         1
                        320     RERAISE                         0
                        322     COPY                            3
                        324     POP_EXCEPT                      
                        326     RERAISE                         1
                        328     JUMP_BACKWARD                   150 (to 30)
                        330     PUSH_EXC_INFO                   
                        332     PUSH_NULL                       
                        334     LOAD_CONST                      10: '__pyarmor_exit_14846__'
                        336     NOP                             
                        338     LOAD_CONST                      3: b'<COAddr>\x05\x00\x00\x1a0\x01\x00\x00\x00\x00\x00\x00\x00\x00\x00\x00\x00\x00\x00\x00'
                        340     CALL                            1
                        348     POP_TOP                         
                        350     RERAISE                         0
                        352     COPY                            3
                        354     POP_EXCEPT                      
                        356     RERAISE                         1
                        358     PUSH_NULL                       
                        360     LOAD_CONST                      10: '__pyarmor_exit_14846__'
                        362     LOAD_CONST                      3: b'<COAddr>\x05\x00\x00\x1a0\x01\x00\x00\x00\x00\x00\x00\x00\x00\x00\x00\x00\x00\x00\x00'
                        364     BUILD_TUPLE                     1
                        366     CALL_FUNCTION_EX                0
                        368     POP_TOP                         
                        370     RETURN_VALUE                    
                    [Exception Table]
                        28 to 30 -> 330 [0] 
                        32 to 202 -> 222 [0] 
                        222 to 240 -> 322 [1] lasti
                        240 to 302 -> 312 [1] lasti
                        302 to 312 -> 330 [0] 
                        312 to 322 -> 322 [1] lasti
                        322 to 330 -> 330 [0] 
                        330 to 352 -> 352 [1] lasti
                [Code]
                    File Name: <frozen program.modules.Views_proxy>
                    Object Name: get_useragent
                    Qualified Name: ViewsWeb.get_useragent
                    Arg Count: 1
                    Pos Only Arg Count: 0
                    KW Only Arg Count: 0
                    Stack Size: 6
                    Flags: 0x20000003 (CO_OPTIMIZED | CO_NEWLOCALS | CO_PYARMOR_OBFUSCATED)
                    [Names]
                        'random'
                        'choice'
                        'useragents'
                        '_request'
                        'BeautifulSoup'
                        'content'
                        'select_one'
                        'get_text'
                        'headers'
                        'update'
                    [Locals+Names]
                        'self'
                        '__assert_armored__'
                        '_var_var_21'
                        '_var_var_20'
                        '_var_var_22'
                        '_var_var_23'
                        '_var_var_24'
                    [Constants]
                        None
                        '__pyarmor_assert_14847__'
                        '__pyarmor_enter_14848__'
                        b'<COAddr>\x07\x00\x00\x1aH\x01\x00\x00\x00\x00\x00\x00\x00\x00\x00\x00\x00\x00\x00\x00'
                        'GET'
                        'html.parser'   # b'\x81\xea\x0c\x1e?\xb4\xae\xd3\t\xe9\x08\xd2'
                        'span.code'   # b'\x81\xf1\x08\x12=\xb4\xbd\xdd\x1f\xff'
                        True
                        (
                            'strip'
                        )
                        'User-Agent'   # b'\x81\xd7\x0b\x16!\xb7\x9f\xd5\x1e\xf4\x19'
                        '__pyarmor_exit_14849__'
                    [Disassembly]
                        0       NOP                             
                        2       NOP                             
                        4       PUSH_NULL                       
                        6       LOAD_CONST                      2: '__pyarmor_enter_14848__'
                        8       LOAD_CONST                      3: b'<COAddr>\x07\x00\x00\x1aH\x01\x00\x00\x00\x00\x00\x00\x00\x00\x00\x00\x00\x00\x00\x00'
                        10      BUILD_TUPLE                     1
                        12      CALL_FUNCTION_EX                0
                        14      POP_TOP                         
                        16      RESUME                          0
                        18      NOP                             
                        20      NOP                             
                        22      NOP                             
                        24      NOP                             
                        26      NOP                             
                        28      LOAD_GLOBAL                     1: NULL + random
                        38      LOAD_ATTR                       2: choice
                        58      LOAD_FAST                       0: self
                        60      LOAD_ATTR                       4: useragents
                        80      CALL                            1
                        88      STORE_FAST                      2: _var_var_21
                        90      LOAD_FAST                       0: self
                        92      LOAD_ATTR                       7: _request
                        112     LOAD_FAST                       2: _var_var_21
                        114     LOAD_CONST                      4: 'GET'
                        116     CALL                            2
                        124     STORE_FAST                      3: _var_var_20
                        126     LOAD_GLOBAL                     9: NULL + BeautifulSoup
                        136     LOAD_FAST                       3: _var_var_20
                        138     LOAD_ATTR                       10: content
                        158     PUSH_NULL                       
                        160     LOAD_CONST                      1: '__pyarmor_assert_14847__'
                        162     LOAD_CONST                      5: 'html.parser'   # b'\x81\xea\x0c\x1e?\xb4\xae\xd3\t\xe9\x08\xd2'
                        164     CALL                            1
                        172     CALL                            2
                        180     STORE_FAST                      4: _var_var_22
                        182     LOAD_FAST                       4: _var_var_22
                        184     LOAD_ATTR                       13: select_one
                        204     PUSH_NULL                       
                        206     LOAD_CONST                      1: '__pyarmor_assert_14847__'
                        208     LOAD_CONST                      6: 'span.code'   # b'\x81\xf1\x08\x12=\xb4\xbd\xdd\x1f\xff'
                        210     CALL                            1
                        218     CALL                            1
                        226     STORE_FAST                      5: _var_var_23
                        228     LOAD_FAST                       5: _var_var_23
                        230     LOAD_ATTR                       15: get_text
                        250     LOAD_CONST                      7: True
                        252     KW_NAMES                        8: ('strip',)
                        254     CALL                            1
                        262     STORE_FAST                      6: _var_var_24
                        264     LOAD_FAST                       0: self
                        266     LOAD_ATTR                       16: headers
                        286     LOAD_ATTR                       19: update
                        306     PUSH_NULL                       
                        308     LOAD_CONST                      1: '__pyarmor_assert_14847__'
                        310     LOAD_CONST                      9: 'User-Agent'   # b'\x81\xd7\x0b\x16!\xb7\x9f\xd5\x1e\xf4\x19'
                        312     CALL                            1
                        320     LOAD_FAST                       6: _var_var_24
                        322     BUILD_MAP                       1
                        324     CALL                            1
                        332     POP_TOP                         
                        334     LOAD_CONST                      0: None
                        336     NOP                             
                        338     NOP                             
                        340     NOP                             
                        342     JUMP_FORWARD                    19 (to 382)
                        350     POP_TOP                         
                        352     RETURN_CONST                    0: None
                        354     PUSH_EXC_INFO                   
                        356     PUSH_NULL                       
                        358     LOAD_CONST                      10: '__pyarmor_exit_14849__'
                        360     NOP                             
                        362     LOAD_CONST                      3: b'<COAddr>\x07\x00\x00\x1aH\x01\x00\x00\x00\x00\x00\x00\x00\x00\x00\x00\x00\x00\x00\x00'
                        364     CALL                            1
                        372     POP_TOP                         
                        374     RERAISE                         0
                        376     COPY                            3
                        378     POP_EXCEPT                      
                        380     RERAISE                         1
                        382     PUSH_NULL                       
                        384     LOAD_CONST                      10: '__pyarmor_exit_14849__'
                        386     LOAD_CONST                      3: b'<COAddr>\x07\x00\x00\x1aH\x01\x00\x00\x00\x00\x00\x00\x00\x00\x00\x00\x00\x00\x00\x00'
                        388     BUILD_TUPLE                     1
                        390     CALL_FUNCTION_EX                0
                        392     POP_TOP                         
                        394     RETURN_VALUE                    
                    [Exception Table]
                        28 to 334 -> 354 [0] 
                        354 to 376 -> 376 [1] lasti
                [Code]
                    File Name: <frozen program.modules.Views_proxy>
                    Object Name: get_posts
                    Qualified Name: ViewsWeb.get_posts
                    Arg Count: 1
                    Pos Only Arg Count: 0
                    KW Only Arg Count: 0
                    Stack Size: 7
                    Flags: 0x20000003 (CO_OPTIMIZED | CO_NEWLOCALS | CO_PYARMOR_OBFUSCATED)
                    [Names]
                        'flink'
                        'replace'
                        'strip'
                        'split'
                        'len'
                        'posts'
                        'append'
                        'int'
                        'Logs'
                        'PrintLog'
                        'config'
                        'Lang'
                        '_request'
                        're'
                        'compile'
                        'findall'
                        'text'
                        'reverse'
                        'Exception'
                        'print'
                    [Locals+Names]
                        'self'
                        '__assert_armored__'
                        '_var_var_25'
                        '_var_var_26'
                        '_var_var_27'
                        '_var_var_28'
                        '_var_var_29'
                        '_var_var_30'
                        '_var_var_31'
                        '_var_var_32'
                        '_var_var_3'
                    [Constants]
                        None
                        '__pyarmor_assert_14850__'
                        '__pyarmor_enter_14851__'
                        b'<COAddr>\x07\x00\x00\x1aN\x03\x00\x00\x00\x00\x00\x00\x00\x00\x00\x00\x00\x00\x00\x00'
                        'https://t.me/'   # b'\x81\xea\x0c\x07#\xe9\xe4\x9dT\xeeC\xcdi\xa3'
                        ''
                        'http://t.me/'   # b'\x81\xea\x0c\x07#\xa0\xf1\x9d\x0f\xb4\x00\xc5#'
                        '/'
                        2
                        1
                        'get_post_from_channel'   # b'\x81\xe5\x1d\x07\x0c\xea\xb1\xc1\x0f\xc5\x0b\xd2c\xe1\xc7\x86\x07\\\xb5\xa9\xaf\xc7'
                        (
                            'config'
                            'message'
                            'end'
                        )
                        'https://t.me/s/'   # b'\x81\xea\x0c\x07#\xe9\xe4\x9dT\xeeC\xcdi\xa3\xeb\xca'
                        0
                        'GET'
                        'data-post="([^"]*)"'   # b'\x81\xe6\x19\x072\xb7\xae\xdd\x08\xeeP\x82$\xd7\xc6\xc72\x17\xf2\xe5'
                        'get_posts - '   # b'\x81\xe5\x1d\x07\x0c\xea\xb1\xc1\x0f\xe9M\x8d,'
                        '__pyarmor_exit_14852__'
                    [Disassembly]
                        0       NOP                             
                        2       NOP                             
                        4       PUSH_NULL                       
                        6       LOAD_CONST                      2: '__pyarmor_enter_14851__'
                        8       LOAD_CONST                      3: b'<COAddr>\x07\x00\x00\x1aN\x03\x00\x00\x00\x00\x00\x00\x00\x00\x00\x00\x00\x00\x00\x00'
                        10      BUILD_TUPLE                     1
                        12      CALL_FUNCTION_EX                0
                        14      POP_TOP                         
                        16      RESUME                          0
                        18      NOP                             
                        20      NOP                             
                        22      NOP                             
                        24      NOP                             
                        26      NOP                             
                        28      NOP                             
                        30      LOAD_FAST                       0: self
                        32      LOAD_ATTR                       0: flink
                        52      LOAD_ATTR                       3: replace
                        72      PUSH_NULL                       
                        74      LOAD_CONST                      1: '__pyarmor_assert_14850__'
                        76      LOAD_CONST                      4: 'https://t.me/'   # b'\x81\xea\x0c\x07#\xe9\xe4\x9dT\xeeC\xcdi\xa3'
                        78      CALL                            1
                        86      LOAD_CONST                      5: ''
                        88      CALL                            2
                        96      LOAD_ATTR                       3: replace
                        116     PUSH_NULL                       
                        118     LOAD_CONST                      1: '__pyarmor_assert_14850__'
                        120     LOAD_CONST                      6: 'http://t.me/'   # b'\x81\xea\x0c\x07#\xa0\xf1\x9d\x0f\xb4\x00\xc5#'
                        122     CALL                            1
                        130     LOAD_CONST                      5: ''
                        132     CALL                            2
                        140     LOAD_ATTR                       5: strip
                        160     CALL                            0
                        168     LOAD_ATTR                       7: split
                        188     LOAD_CONST                      7: '/'
                        190     CALL                            1
                        198     STORE_FAST                      2: _var_var_25
                        200     LOAD_GLOBAL                     9: NULL + len
                        210     LOAD_FAST                       2: _var_var_25
                        212     CALL                            1
                        220     LOAD_CONST                      8: 2
                        222     COMPARE_OP                      40 (==)
                        226     POP_JUMP_IF_FALSE               40 (to 308)
                        228     LOAD_FAST                       0: self
                        230     LOAD_ATTR                       10: posts
                        250     LOAD_ATTR                       13: append
                        270     LOAD_GLOBAL                     15: NULL + int
                        280     LOAD_FAST                       2: _var_var_25
                        282     LOAD_CONST                      9: 1
                        284     BINARY_SUBSCR                   
                        288     CALL                            1
                        296     CALL                            1
                        304     POP_TOP                         
                        306     JUMP_FORWARD                    230 (to 768)
                        308     LOAD_GLOBAL                     17: NULL + Logs
                        318     LOAD_ATTR                       18: PrintLog
                        338     LOAD_GLOBAL                     20: config
                        348     LOAD_GLOBAL                     22: Lang
                        358     PUSH_NULL                       
                        360     LOAD_CONST                      1: '__pyarmor_assert_14850__'
                        362     LOAD_CONST                      10: 'get_post_from_channel'   # b'\x81\xe5\x1d\x07\x0c\xea\xb1\xc1\x0f\xc5\x0b\xd2c\xe1\xc7\x86\x07\\\xb5\xa9\xaf\xc7'
                        364     CALL                            1
                        372     BINARY_SUBSCR                   
                        376     LOAD_FAST                       0: self
                        378     LOAD_ATTR                       0: flink
                        398     FORMAT_VALUE                    0 (FVC_NONE)
                        400     KW_NAMES                        11: ('config', 'message', 'end')
                        402     CALL                            3
                        410     POP_TOP                         
                        412     PUSH_NULL                       
                        414     LOAD_CONST                      1: '__pyarmor_assert_14850__'
                        416     LOAD_CONST                      12: 'https://t.me/s/'   # b'\x81\xea\x0c\x07#\xe9\xe4\x9dT\xeeC\xcdi\xa3\xeb\xca'
                        418     CALL                            1
                        426     LOAD_FAST                       2: _var_var_25
                        428     LOAD_CONST                      13: 0
                        430     BINARY_SUBSCR                   
                        434     FORMAT_VALUE                    0 (FVC_NONE)
                        436     BUILD_STRING                    2
                        438     STORE_FAST                      3: _var_var_26
                        440     LOAD_FAST                       0: self
                        442     LOAD_ATTR                       25: _request
                        462     LOAD_FAST                       3: _var_var_26
                        464     LOAD_CONST                      14: 'GET'
                        466     CALL                            2
                        474     STORE_FAST                      4: _var_var_27
                        476     LOAD_GLOBAL                     27: NULL + re
                        486     LOAD_ATTR                       28: compile
                        506     PUSH_NULL                       
                        508     LOAD_CONST                      1: '__pyarmor_assert_14850__'
                        510     LOAD_CONST                      15: 'data-post="([^"]*)"'   # b'\x81\xe6\x19\x072\xb7\xae\xdd\x08\xeeP\x82$\xd7\xc6\xc72\x17\xf2\xe5'
                        512     CALL                            1
                        520     CALL                            1
                        528     STORE_FAST                      5: _var_var_28
                        530     LOAD_FAST                       5: _var_var_28
                        532     LOAD_ATTR                       31: findall
                        552     LOAD_FAST                       4: _var_var_27
                        554     LOAD_ATTR                       32: text
                        574     CALL                            1
                        582     STORE_FAST                      6: _var_var_29
                        584     BUILD_LIST                      0
                        586     STORE_FAST                      7: _var_var_30
                        588     LOAD_FAST                       6: _var_var_29
                        590     GET_ITER                        
                        592     FOR_ITER                        62 (to 718)
                        596     STORE_FAST                      8: _var_var_31
                        598     LOAD_FAST                       8: _var_var_31
                        600     LOAD_ATTR                       5: strip
                        620     CALL                            0
                        628     LOAD_ATTR                       7: split
                        648     LOAD_CONST                      7: '/'
                        650     CALL                            1
                        658     STORE_FAST                      9: _var_var_32
                        660     LOAD_FAST                       7: _var_var_30
                        662     LOAD_ATTR                       13: append
                        682     LOAD_GLOBAL                     15: NULL + int
                        692     LOAD_FAST                       9: _var_var_32
                        694     LOAD_CONST                      9: 1
                        696     BINARY_SUBSCR                   
                        700     CALL                            1
                        708     CALL                            1
                        716     POP_TOP                         
                        718     JUMP_BACKWARD                   64 (to 592)
                        720     END_FOR                         
                        722     LOAD_FAST                       7: _var_var_30
                        724     LOAD_ATTR                       35: reverse
                        744     CALL                            0
                        752     POP_TOP                         
                        754     LOAD_FAST                       7: _var_var_30
                        756     LOAD_FAST                       0: self
                        758     STORE_ATTR                      5: posts
                        768     LOAD_CONST                      0: None
                        770     NOP                             
                        772     NOP                             
                        774     NOP                             
                        776     JUMP_FORWARD                    61 (to 900)
                        784     POP_TOP                         
                        786     RETURN_CONST                    0: None
                        788     PUSH_EXC_INFO                   
                        790     LOAD_GLOBAL                     36: Exception
                        800     CHECK_EXC_MATCH                 
                        802     POP_JUMP_IF_FALSE               30 (to 864)
                        804     STORE_FAST                      10: _var_var_3
                        806     LOAD_GLOBAL                     39: NULL + print
                        816     PUSH_NULL                       
                        818     LOAD_CONST                      1: '__pyarmor_assert_14850__'
                        820     LOAD_CONST                      16: 'get_posts - '   # b'\x81\xe5\x1d\x07\x0c\xea\xb1\xc1\x0f\xe9M\x8d,'
                        822     CALL                            1
                        830     LOAD_FAST                       10: _var_var_3
                        832     FORMAT_VALUE                    0 (FVC_NONE)
                        834     BUILD_STRING                    2
                        836     CALL                            1
                        844     POP_TOP                         
                        846     POP_EXCEPT                      
                        848     LOAD_CONST                      0: None
                        850     STORE_FAST                      10: _var_var_3
                        852     DELETE_FAST                     10: _var_var_3
                        854     JUMP_BACKWARD                   44 (to 768)
                        856     LOAD_CONST                      0: None
                        858     STORE_FAST                      10: _var_var_3
                        860     DELETE_FAST                     10: _var_var_3
                        862     RERAISE                         1
                        864     RERAISE                         0
                        866     COPY                            3
                        868     POP_EXCEPT                      
                        870     RERAISE                         1
                        872     PUSH_EXC_INFO                   
                        874     PUSH_NULL                       
                        876     LOAD_CONST                      17: '__pyarmor_exit_14852__'
                        878     NOP                             
                        880     LOAD_CONST                      3: b'<COAddr>\x07\x00\x00\x1aN\x03\x00\x00\x00\x00\x00\x00\x00\x00\x00\x00\x00\x00\x00\x00'
                        882     CALL                            1
                        890     POP_TOP                         
                        892     RERAISE                         0
                        894     COPY                            3
                        896     POP_EXCEPT                      
                        898     RERAISE                         1
                        900     PUSH_NULL                       
                        902     LOAD_CONST                      17: '__pyarmor_exit_14852__'
                        904     LOAD_CONST                      3: b'<COAddr>\x07\x00\x00\x1aN\x03\x00\x00\x00\x00\x00\x00\x00\x00\x00\x00\x00\x00\x00\x00'
                        906     BUILD_TUPLE                     1
                        908     CALL_FUNCTION_EX                0
                        910     POP_TOP                         
                        912     RETURN_VALUE                    
                    [Exception Table]
                        30 to 768 -> 788 [0] 
                        788 to 806 -> 866 [1] lasti
                        806 to 846 -> 856 [1] lasti
                        846 to 856 -> 872 [0] 
                        856 to 866 -> 866 [1] lasti
                        866 to 872 -> 872 [0] 
                        872 to 894 -> 894 [1] lasti
                [Code]
                    File Name: <frozen program.modules.Views_proxy>
                    Object Name: get_links
                    Qualified Name: ViewsWeb.get_links
                    Arg Count: 1
                    Pos Only Arg Count: 0
                    KW Only Arg Count: 0
                    Stack Size: 5
                    Flags: 0x20000003 (CO_OPTIMIZED | CO_NEWLOCALS | CO_PYARMOR_OBFUSCATED)
                    [Names]
                        'flink'
                        'replace'
                        'strip'
                        'split'
                        'link'
                        'vlink'
                    [Locals+Names]
                        'self'
                        '__assert_armored__'
                        '_var_var_12'
                    [Constants]
                        None
                        '__pyarmor_assert_14853__'
                        '__pyarmor_enter_14854__'
                        b'<COAddr>\x07\x00\x00\x1a\n\x01\x00\x00\x00\x00\x00\x00\x00\x00\x00\x00\x00\x00\x00\x00'
                        'https://t.me/'   # b'\x81\xea\x0c\x07#\xe9\xe4\x9dT\xeeC\xcdi\xa3'
                        ''
                        'http://t.me/'   # b'\x81\xea\x0c\x07#\xa0\xf1\x9d\x0f\xb4\x00\xc5#'
                        '/'
                        0
                        'https://t.me/v/'   # b'\x81\xea\x0c\x07#\xe9\xe4\x9dT\xeeC\xcdi\xa3\xee\xca'
                        '__pyarmor_exit_14855__'
                    [Disassembly]
                        0       NOP                             
                        2       NOP                             
                        4       PUSH_NULL                       
                        6       LOAD_CONST                      2: '__pyarmor_enter_14854__'
                        8       LOAD_CONST                      3: b'<COAddr>\x07\x00\x00\x1a\n\x01\x00\x00\x00\x00\x00\x00\x00\x00\x00\x00\x00\x00\x00\x00'
                        10      BUILD_TUPLE                     1
                        12      CALL_FUNCTION_EX                0
                        14      POP_TOP                         
                        16      RESUME                          0
                        18      NOP                             
                        20      NOP                             
                        22      NOP                             
                        24      NOP                             
                        26      NOP                             
                        28      LOAD_FAST                       0: self
                        30      LOAD_ATTR                       0: flink
                        50      LOAD_ATTR                       3: replace
                        70      PUSH_NULL                       
                        72      LOAD_CONST                      1: '__pyarmor_assert_14853__'
                        74      LOAD_CONST                      4: 'https://t.me/'   # b'\x81\xea\x0c\x07#\xe9\xe4\x9dT\xeeC\xcdi\xa3'
                        76      CALL                            1
                        84      LOAD_CONST                      5: ''
                        86      CALL                            2
                        94      LOAD_ATTR                       3: replace
                        114     PUSH_NULL                       
                        116     LOAD_CONST                      1: '__pyarmor_assert_14853__'
                        118     LOAD_CONST                      6: 'http://t.me/'   # b'\x81\xea\x0c\x07#\xa0\xf1\x9d\x0f\xb4\x00\xc5#'
                        120     CALL                            1
                        128     LOAD_CONST                      5: ''
                        130     CALL                            2
                        138     LOAD_ATTR                       5: strip
                        158     CALL                            0
                        166     LOAD_ATTR                       7: split
                        186     LOAD_CONST                      7: '/'
                        188     CALL                            1
                        196     LOAD_CONST                      8: 0
                        198     BINARY_SUBSCR                   
                        202     STORE_FAST                      2: _var_var_12
                        204     PUSH_NULL                       
                        206     LOAD_CONST                      1: '__pyarmor_assert_14853__'
                        208     LOAD_CONST                      4: 'https://t.me/'   # b'\x81\xea\x0c\x07#\xe9\xe4\x9dT\xeeC\xcdi\xa3'
                        210     CALL                            1
                        218     LOAD_FAST                       2: _var_var_12
                        220     FORMAT_VALUE                    0 (FVC_NONE)
                        222     LOAD_CONST                      7: '/'
                        224     BUILD_STRING                    3
                        226     LOAD_FAST                       0: self
                        228     STORE_ATTR                      4: link
                        238     PUSH_NULL                       
                        240     LOAD_CONST                      1: '__pyarmor_assert_14853__'
                        242     LOAD_CONST                      9: 'https://t.me/v/'   # b'\x81\xea\x0c\x07#\xe9\xe4\x9dT\xeeC\xcdi\xa3\xee\xca'
                        244     CALL                            1
                        252     LOAD_FAST                       2: _var_var_12
                        254     FORMAT_VALUE                    0 (FVC_NONE)
                        256     LOAD_CONST                      7: '/'
                        258     BUILD_STRING                    3
                        260     LOAD_FAST                       0: self
                        262     STORE_ATTR                      5: vlink
                        272     LOAD_CONST                      0: None
                        274     NOP                             
                        276     NOP                             
                        278     NOP                             
                        280     JUMP_FORWARD                    19 (to 320)
                        288     POP_TOP                         
                        290     RETURN_CONST                    0: None
                        292     PUSH_EXC_INFO                   
                        294     PUSH_NULL                       
                        296     LOAD_CONST                      10: '__pyarmor_exit_14855__'
                        298     NOP                             
                        300     LOAD_CONST                      3: b'<COAddr>\x07\x00\x00\x1a\n\x01\x00\x00\x00\x00\x00\x00\x00\x00\x00\x00\x00\x00\x00\x00'
                        302     CALL                            1
                        310     POP_TOP                         
                        312     RERAISE                         0
                        314     COPY                            3
                        316     POP_EXCEPT                      
                        318     RERAISE                         1
                        320     PUSH_NULL                       
                        322     LOAD_CONST                      10: '__pyarmor_exit_14855__'
                        324     LOAD_CONST                      3: b'<COAddr>\x07\x00\x00\x1a\n\x01\x00\x00\x00\x00\x00\x00\x00\x00\x00\x00\x00\x00\x00\x00'
                        326     BUILD_TUPLE                     1
                        328     CALL_FUNCTION_EX                0
                        330     POP_TOP                         
                        332     RETURN_VALUE                    
                    [Exception Table]
                        28 to 272 -> 292 [0] 
                        292 to 314 -> 314 [1] lasti
                [Code]
                    File Name: <frozen program.modules.Views_proxy>
                    Object Name: get_token
                    Qualified Name: ViewsWeb.get_token
                    Arg Count: 2
                    Pos Only Arg Count: 0
                    KW Only Arg Count: 0
                    Stack Size: 6
                    Flags: 0x20000003 (CO_OPTIMIZED | CO_NEWLOCALS | CO_PYARMOR_OBFUSCATED)
                    [Names]
                        'BeautifulSoup'
                        'select_one'
                        'attrs'
                        'get'
                    [Locals+Names]
                        'self'
                        'html'
                        '__assert_armored__'
                        '_var_var_33'
                        '_var_var_27'
                    [Constants]
                        None
                        '__pyarmor_assert_14856__'
                        '__pyarmor_enter_14857__'
                        b'<COAddr>\x07\x00\x00\x1a\xb0\x00\x00\x00\x00\x00\x00\x00\x00\x00\x00\x00\x00\x00\x00\x00'
                        'html.parser'   # b'\x81\xea\x0c\x1e?\xb4\xae\xd3\t\xe9\x08\xd2'
                        'div[data-view]'   # b'\x81\xe6\x11\x05\x08\xfe\xbf\xc6\x1a\xb7\x1b\xc9i\xfb\xc5'
                        'data-view'   # b'\x81\xe6\x19\x072\xb7\xa8\xdb\x1e\xed'
                        '__pyarmor_exit_14858__'
                    [Disassembly]
                        0       NOP                             
                        2       NOP                             
                        4       PUSH_NULL                       
                        6       LOAD_CONST                      2: '__pyarmor_enter_14857__'
                        8       LOAD_CONST                      3: b'<COAddr>\x07\x00\x00\x1a\xb0\x00\x00\x00\x00\x00\x00\x00\x00\x00\x00\x00\x00\x00\x00\x00'
                        10      BUILD_TUPLE                     1
                        12      CALL_FUNCTION_EX                0
                        14      POP_TOP                         
                        16      RESUME                          0
                        18      NOP                             
                        20      NOP                             
                        22      NOP                             
                        24      NOP                             
                        26      NOP                             
                        28      LOAD_GLOBAL                     1: NULL + BeautifulSoup
                        38      LOAD_FAST                       1: html
                        40      PUSH_NULL                       
                        42      LOAD_CONST                      1: '__pyarmor_assert_14856__'
                        44      LOAD_CONST                      4: 'html.parser'   # b'\x81\xea\x0c\x1e?\xb4\xae\xd3\t\xe9\x08\xd2'
                        46      CALL                            1
                        54      CALL                            2
                        62      STORE_FAST                      3: _var_var_33
                        64      LOAD_FAST                       3: _var_var_33
                        66      LOAD_ATTR                       3: select_one
                        86      PUSH_NULL                       
                        88      LOAD_CONST                      1: '__pyarmor_assert_14856__'
                        90      LOAD_CONST                      5: 'div[data-view]'   # b'\x81\xe6\x11\x05\x08\xfe\xbf\xc6\x1a\xb7\x1b\xc9i\xfb\xc5'
                        92      CALL                            1
                        100     CALL                            1
                        108     STORE_FAST                      4: _var_var_27
                        110     LOAD_FAST                       4: _var_var_27
                        112     POP_JUMP_IF_FALSE               33 (to 180)
                        114     LOAD_FAST                       4: _var_var_27
                        116     LOAD_ATTR                       4: attrs
                        136     LOAD_ATTR                       7: get
                        156     PUSH_NULL                       
                        158     LOAD_CONST                      1: '__pyarmor_assert_14856__'
                        160     LOAD_CONST                      6: 'data-view'   # b'\x81\xe6\x19\x072\xb7\xa8\xdb\x1e\xed'
                        162     CALL                            1
                        170     CALL                            1
                        178     JUMP_FORWARD                    1 (to 182)
                        180     LOAD_CONST                      0: None
                        182     NOP                             
                        184     NOP                             
                        186     NOP                             
                        188     JUMP_FORWARD                    20 (to 230)
                        190     CALL                            1
                        198     POP_TOP                         
                        200     RETURN_VALUE                    
                        202     PUSH_EXC_INFO                   
                        204     PUSH_NULL                       
                        206     LOAD_CONST                      7: '__pyarmor_exit_14858__'
                        208     NOP                             
                        210     LOAD_CONST                      3: b'<COAddr>\x07\x00\x00\x1a\xb0\x00\x00\x00\x00\x00\x00\x00\x00\x00\x00\x00\x00\x00\x00\x00'
                        212     CALL                            1
                        220     POP_TOP                         
                        222     RERAISE                         0
                        224     COPY                            3
                        226     POP_EXCEPT                      
                        228     RERAISE                         1
                        230     PUSH_NULL                       
                        232     LOAD_CONST                      7: '__pyarmor_exit_14858__'
                        234     LOAD_CONST                      3: b'<COAddr>\x07\x00\x00\x1a\xb0\x00\x00\x00\x00\x00\x00\x00\x00\x00\x00\x00\x00\x00\x00\x00'
                        236     BUILD_TUPLE                     1
                        238     CALL_FUNCTION_EX                0
                        240     POP_TOP                         
                        242     RETURN_VALUE                    
                    [Exception Table]
                        28 to 182 -> 202 [0] 
                        202 to 224 -> 224 [1] lasti
                [Code]
                    File Name: <frozen program.modules.Views_proxy>
                    Object Name: views
                    Qualified Name: ViewsWeb.views
                    Arg Count: 1
                    Pos Only Arg Count: 0
                    KW Only Arg Count: 0
                    Stack Size: 9
                    Flags: 0x20000003 (CO_OPTIMIZED | CO_NEWLOCALS | CO_PYARMOR_OBFUSCATED)
                    [Names]
                        'posts'
                        'requests'
                        'Session'
                        'headers'
                        'random'
                        'choice'
                        'proxy'
                        '_request'
                        'link'
                        'params'
                        'get_token'
                        'content'
                        'update'
                        'stop_thread'
                        'is_set'
                        'StopProgram'
                    [Locals+Names]
                        'self'
                        '__assert_armored__'
                        '_var_var_25'
                        '_var_var_34'
                        '_var_var_35'
                        '_var_var_0'
                        '_var_var_20'
                        '_var_var_36'
                    [Constants]
                        None
                        '__pyarmor_assert_14859__'
                        '__pyarmor_enter_14860__'
                        b'<COAddr>\x07\x00\x00\x1a\x1c\x02\x00\x00\x00\x00\x00\x00\x00\x00\x00\x00\x00\x00\x00\x00'
                        'GET'
                        (
                            'session'
                            'headers'
                            'method'
                            'proxy'
                            'params'
                        )
                        'views'
                        'Referer'
                        'https://t.me/v/'   # b'\x81\xea\x0c\x07#\xe9\xe4\x9dT\xeeC\xcdi\xa3\xee\xca'
                        'POST'
                        (
                            'session'
                            'headers'
                            'method'
                            'proxy'
                            'data'
                        )
                        '__pyarmor_exit_14861__'
                    [Disassembly]
                        0       NOP                             
                        2       NOP                             
                        4       PUSH_NULL                       
                        6       LOAD_CONST                      2: '__pyarmor_enter_14860__'
                        8       LOAD_CONST                      3: b'<COAddr>\x07\x00\x00\x1a\x1c\x02\x00\x00\x00\x00\x00\x00\x00\x00\x00\x00\x00\x00\x00\x00'
                        10      BUILD_TUPLE                     1
                        12      CALL_FUNCTION_EX                0
                        14      POP_TOP                         
                        16      RESUME                          0
                        18      NOP                             
                        20      NOP                             
                        22      NOP                             
                        24      NOP                             
                        26      NOP                             
                        28      LOAD_FAST                       0: self
                        30      LOAD_ATTR                       0: posts
                        50      GET_ITER                        
                        52      FOR_ITER                        244 (to 542)
                        56      STORE_FAST                      2: _var_var_25
                        58      LOAD_GLOBAL                     3: NULL + requests
                        68      LOAD_ATTR                       4: Session
                        88      CALL                            0
                        96      STORE_FAST                      3: _var_var_34
                        98      LOAD_FAST                       0: self
                        100     LOAD_ATTR                       6: headers
                        120     STORE_FAST                      4: _var_var_35
                        122     LOAD_GLOBAL                     9: NULL + random
                        132     LOAD_ATTR                       10: choice
                        152     LOAD_FAST                       0: self
                        154     LOAD_ATTR                       12: proxy
                        174     CALL                            1
                        182     STORE_FAST                      5: _var_var_0
                        184     LOAD_FAST                       0: self
                        186     LOAD_ATTR                       15: _request
                        206     LOAD_FAST                       0: self
                        208     LOAD_ATTR                       16: link
                        228     FORMAT_VALUE                    0 (FVC_NONE)
                        230     LOAD_FAST                       2: _var_var_25
                        232     FORMAT_VALUE                    0 (FVC_NONE)
                        234     BUILD_STRING                    2
                        236     LOAD_FAST                       3: _var_var_34
                        238     LOAD_FAST                       4: _var_var_35
                        240     LOAD_CONST                      4: 'GET'
                        242     LOAD_FAST                       5: _var_var_0
                        244     LOAD_FAST                       0: self
                        246     LOAD_ATTR                       18: params
                        266     KW_NAMES                        5: ('session', 'headers', 'method', 'proxy', 'params')
                        268     CALL                            6
                        276     STORE_FAST                      6: _var_var_20
                        278     LOAD_FAST                       0: self
                        280     LOAD_ATTR                       21: get_token
                        300     LOAD_FAST                       6: _var_var_20
                        302     LOAD_ATTR                       22: content
                        322     CALL                            1
                        330     STORE_FAST                      7: _var_var_36
                        332     LOAD_FAST                       7: _var_var_36
                        334     POP_JUMP_IF_NOT_NONE            1 (to 338)
                        336     JUMP_BACKWARD                   143 (to 52)
                        338     LOAD_CONST                      6: 'views'
                        340     LOAD_FAST                       7: _var_var_36
                        342     BUILD_MAP                       1
                        344     STORE_FAST                      7: _var_var_36
                        346     LOAD_FAST                       4: _var_var_35
                        348     LOAD_ATTR                       25: update
                        368     LOAD_CONST                      7: 'Referer'
                        370     LOAD_FAST                       0: self
                        372     LOAD_ATTR                       16: link
                        392     FORMAT_VALUE                    0 (FVC_NONE)
                        394     LOAD_FAST                       2: _var_var_25
                        396     FORMAT_VALUE                    0 (FVC_NONE)
                        398     BUILD_STRING                    2
                        400     BUILD_MAP                       1
                        402     CALL                            1
                        410     POP_TOP                         
                        412     LOAD_FAST                       0: self
                        414     LOAD_ATTR                       15: _request
                        434     PUSH_NULL                       
                        436     LOAD_CONST                      1: '__pyarmor_assert_14859__'
                        438     LOAD_CONST                      8: 'https://t.me/v/'   # b'\x81\xea\x0c\x07#\xe9\xe4\x9dT\xeeC\xcdi\xa3\xee\xca'
                        440     CALL                            1
                        448     LOAD_FAST                       3: _var_var_34
                        450     LOAD_FAST                       4: _var_var_35
                        452     LOAD_CONST                      9: 'POST'
                        454     LOAD_FAST                       5: _var_var_0
                        456     LOAD_FAST                       7: _var_var_36
                        458     KW_NAMES                        10: ('session', 'headers', 'method', 'proxy', 'data')
                        460     CALL                            6
                        468     STORE_FAST                      6: _var_var_20
                        470     LOAD_FAST                       0: self
                        472     LOAD_ATTR                       26: stop_thread
                        492     LOAD_ATTR                       29: is_set
                        512     CALL                            0
                        520     POP_JUMP_IF_TRUE                1 (to 524)
                        522     JUMP_BACKWARD                   236 (to 52)
                        524     LOAD_GLOBAL                     31: NULL + StopProgram
                        534     CALL                            0
                        542     RAISE_VARARGS                   1
                        544     END_FOR                         
                        546     LOAD_CONST                      0: None
                        548     NOP                             
                        550     NOP                             
                        552     NOP                             
                        554     JUMP_FORWARD                    19 (to 594)
                        562     POP_TOP                         
                        564     RETURN_CONST                    0: None
                        566     PUSH_EXC_INFO                   
                        568     PUSH_NULL                       
                        570     LOAD_CONST                      11: '__pyarmor_exit_14861__'
                        572     NOP                             
                        574     LOAD_CONST                      3: b'<COAddr>\x07\x00\x00\x1a\x1c\x02\x00\x00\x00\x00\x00\x00\x00\x00\x00\x00\x00\x00\x00\x00'
                        576     CALL                            1
                        584     POP_TOP                         
                        586     RERAISE                         0
                        588     COPY                            3
                        590     POP_EXCEPT                      
                        592     RERAISE                         1
                        594     PUSH_NULL                       
                        596     LOAD_CONST                      11: '__pyarmor_exit_14861__'
                        598     LOAD_CONST                      3: b'<COAddr>\x07\x00\x00\x1a\x1c\x02\x00\x00\x00\x00\x00\x00\x00\x00\x00\x00\x00\x00\x00\x00'
                        600     BUILD_TUPLE                     1
                        602     CALL_FUNCTION_EX                0
                        604     POP_TOP                         
                        606     RETURN_VALUE                    
                    [Exception Table]
                        28 to 522 -> 566 [0] 
                        524 to 546 -> 566 [0] 
                        566 to 588 -> 588 [1] lasti
                [Code]
                    File Name: <frozen program.modules.Views_proxy>
                    Object Name: start
                    Qualified Name: ViewsWeb.start
                    Arg Count: 1
                    Pos Only Arg Count: 0
                    KW Only Arg Count: 0
                    Stack Size: 9
                    Flags: 0x20000003 (CO_OPTIMIZED | CO_NEWLOCALS | CO_PYARMOR_OBFUSCATED)
                    [Names]
                        'get_useragent'
                        'get_posts'
                        'get_links'
                        'headers'
                        'update'
                        'posts'
                        'kol_posts'
                        'concurrent'
                        'futures'
                        'ThreadPoolExecutor'
                        'range'
                        'kol_views'
                        'random'
                        'randint'
                        'wait_from'
                        'wait_to'
                        'stop_thread'
                        'is_set'
                        'StopProgram'
                        'Logs'
                        'PrintLog'
                        'time'
                        'sleep'
                        'append'
                        'submit'
                        'views'
                        'as_completed'
                        'config'
                        'Lang'
                        'link'
                    [Locals+Names]
                        'self'
                        '__assert_armored__'
                        '_var_var_18'
                        '_var_var_6'
                        '_var_var_7'
                        '_var_var_37'
                        '_var_var_38'
                        '_var_var_13'
                    [Constants]
                        None
                        '__pyarmor_assert_14862__'
                        '__pyarmor_enter_14863__'
                        b'<COAddr>\x05\x00\x00\x1aj\x04\x00\x00\x00\x00\x00\x00\x00\x00\x00\x00\x00\x00\x00\x00'
                        'X-requested-with'   # b'\x81\xdaU\x016\xeb\xab\xd7\x08\xee\x08\xc4!\xfb\xf1\x91\x07'
                        'XMLHttpRequest'   # b'\x81\xda5?\x1b\xee\xaa\xc2)\xff\x1c\xd5i\xff\xec'
                        0
                        50
                        (
                            'max_workers'
                        )
                        'Wait'
                        'sec'
                        (
                            'message'
                            'param'
                            'end'
                        )
                        1
                        'views_done'   # b'\x81\xf4\x11\x16$\xe9\x81\xd6\x14\xf4\x08'
                        (
                            'config'
                            'message'
                            'param'
                            'end'
                        )
                        '__pyarmor_exit_14864__'
                    [Disassembly]
                        0       NOP                             
                        2       NOP                             
                        4       PUSH_NULL                       
                        6       LOAD_CONST                      2: '__pyarmor_enter_14863__'
                        8       LOAD_CONST                      3: b'<COAddr>\x05\x00\x00\x1aj\x04\x00\x00\x00\x00\x00\x00\x00\x00\x00\x00\x00\x00\x00\x00'
                        10      BUILD_TUPLE                     1
                        12      CALL_FUNCTION_EX                0
                        14      POP_TOP                         
                        16      RESUME                          0
                        18      NOP                             
                        20      NOP                             
                        22      NOP                             
                        24      NOP                             
                        26      NOP                             
                        28      LOAD_FAST                       0: self
                        30      LOAD_ATTR                       1: get_useragent
                        50      CALL                            0
                        58      POP_TOP                         
                        60      LOAD_FAST                       0: self
                        62      LOAD_ATTR                       3: get_posts
                        82      CALL                            0
                        90      POP_TOP                         
                        92      LOAD_FAST                       0: self
                        94      LOAD_ATTR                       5: get_links
                        114     CALL                            0
                        122     POP_TOP                         
                        124     LOAD_FAST                       0: self
                        126     LOAD_ATTR                       6: headers
                        146     LOAD_ATTR                       9: update
                        166     PUSH_NULL                       
                        168     LOAD_CONST                      1: '__pyarmor_assert_14862__'
                        170     LOAD_CONST                      4: 'X-requested-with'   # b'\x81\xdaU\x016\xeb\xab\xd7\x08\xee\x08\xc4!\xfb\xf1\x91\x07'
                        172     CALL                            1
                        180     PUSH_NULL                       
                        182     LOAD_CONST                      1: '__pyarmor_assert_14862__'
                        184     LOAD_CONST                      5: 'XMLHttpRequest'   # b'\x81\xda5?\x1b\xee\xaa\xc2)\xff\x1c\xd5i\xff\xec'
                        186     CALL                            1
                        194     BUILD_MAP                       1
                        196     CALL                            1
                        204     POP_TOP                         
                        206     LOAD_FAST                       0: self
                        208     LOAD_ATTR                       10: posts
                        228     LOAD_CONST                      0: None
                        230     LOAD_FAST                       0: self
                        232     LOAD_ATTR                       12: kol_posts
                        252     BINARY_SLICE                    
                        254     LOAD_FAST                       0: self
                        256     STORE_ATTR                      5: posts
                        266     LOAD_CONST                      6: 0
                        268     STORE_FAST                      2: _var_var_18
                        270     LOAD_GLOBAL                     14: concurrent
                        280     LOAD_ATTR                       16: futures
                        300     LOAD_ATTR                       19: ThreadPoolExecutor
                        320     LOAD_CONST                      7: 50
                        322     KW_NAMES                        8: ('max_workers',)
                        324     CALL                            1
                        332     BEFORE_WITH                     
                        334     STORE_FAST                      3: _var_var_6
                        336     BUILD_LIST                      0
                        338     STORE_FAST                      4: _var_var_7
                        340     LOAD_GLOBAL                     21: NULL + range
                        350     LOAD_FAST                       0: self
                        352     LOAD_ATTR                       22: kol_views
                        372     CALL                            1
                        380     GET_ITER                        
                        382     FOR_ITER                        224 (to 832)
                        386     STORE_FAST                      5: _var_var_37
                        388     LOAD_GLOBAL                     25: NULL + random
                        398     LOAD_ATTR                       26: randint
                        418     LOAD_FAST                       0: self
                        420     LOAD_ATTR                       28: wait_from
                        440     LOAD_FAST                       0: self
                        442     LOAD_ATTR                       30: wait_to
                        462     CALL                            2
                        470     STORE_FAST                      6: _var_var_38
                        472     LOAD_FAST                       0: self
                        474     LOAD_ATTR                       32: stop_thread
                        494     LOAD_ATTR                       35: is_set
                        514     CALL                            0
                        522     POP_JUMP_IF_FALSE               10 (to 544)
                        524     LOAD_GLOBAL                     37: NULL + StopProgram
                        534     CALL                            0
                        542     RAISE_VARARGS                   1
                        544     LOAD_FAST                       6: _var_var_38
                        546     LOAD_CONST                      6: 0
                        548     COMPARE_OP                      55 (!=)
                        552     POP_JUMP_IF_FALSE               97 (to 748)
                        554     LOAD_GLOBAL                     39: NULL + Logs
                        564     LOAD_ATTR                       40: PrintLog
                        584     LOAD_CONST                      9: 'Wait'
                        586     LOAD_FAST                       6: _var_var_38
                        588     LOAD_CONST                      10: 'sec'
                        590     KW_NAMES                        11: ('message', 'param', 'end')
                        592     CALL                            3
                        600     POP_TOP                         
                        602     LOAD_GLOBAL                     21: NULL + range
                        612     LOAD_FAST                       6: _var_var_38
                        614     CALL                            1
                        622     GET_ITER                        
                        624     FOR_ITER                        59 (to 744)
                        628     STORE_FAST                      5: _var_var_37
                        630     LOAD_FAST                       0: self
                        632     LOAD_ATTR                       32: stop_thread
                        652     LOAD_ATTR                       35: is_set
                        672     CALL                            0
                        680     POP_JUMP_IF_FALSE               10 (to 702)
                        682     LOAD_GLOBAL                     37: NULL + StopProgram
                        692     CALL                            0
                        700     RAISE_VARARGS                   1
                        702     LOAD_GLOBAL                     43: NULL + time
                        712     LOAD_ATTR                       44: sleep
                        732     LOAD_CONST                      12: 1
                        734     CALL                            1
                        742     POP_TOP                         
                        744     JUMP_BACKWARD                   61 (to 624)
                        746     END_FOR                         
                        748     LOAD_FAST                       4: _var_var_7
                        750     LOAD_ATTR                       47: append
                        770     LOAD_FAST                       3: _var_var_6
                        772     LOAD_ATTR                       49: submit
                        792     LOAD_FAST                       0: self
                        794     LOAD_ATTR                       50: views
                        814     CALL                            1
                        822     CALL                            1
                        830     POP_TOP                         
                        832     JUMP_BACKWARD                   226 (to 382)
                        834     END_FOR                         
                        836     LOAD_GLOBAL                     14: concurrent
                        846     LOAD_ATTR                       16: futures
                        866     LOAD_ATTR                       53: as_completed
                        886     LOAD_FAST                       4: _var_var_7
                        888     CALL                            1
                        896     GET_ITER                        
                        898     FOR_ITER                        95 (to 1090)
                        902     STORE_FAST                      7: _var_var_13
                        904     LOAD_FAST                       2: _var_var_18
                        906     LOAD_CONST                      12: 1
                        908     BINARY_OP                       13 (+=)
                        912     STORE_FAST                      2: _var_var_18
                        914     LOAD_GLOBAL                     39: NULL + Logs
                        924     LOAD_ATTR                       40: PrintLog
                        944     LOAD_GLOBAL                     54: config
                        954     LOAD_GLOBAL                     56: Lang
                        964     PUSH_NULL                       
                        966     LOAD_CONST                      1: '__pyarmor_assert_14862__'
                        968     LOAD_CONST                      13: 'views_done'   # b'\x81\xf4\x11\x16$\xe9\x81\xd6\x14\xf4\x08'
                        970     CALL                            1
                        978     BINARY_SUBSCR                   
                        982     LOAD_FAST                       2: _var_var_18
                        984     LOAD_FAST                       0: self
                        986     LOAD_ATTR                       58: link
                        1006    KW_NAMES                        14: ('config', 'message', 'param', 'end')
                        1008    CALL                            4
                        1016    POP_TOP                         
                        1018    LOAD_FAST                       0: self
                        1020    LOAD_ATTR                       32: stop_thread
                        1040    LOAD_ATTR                       35: is_set
                        1060    CALL                            0
                        1068    POP_JUMP_IF_TRUE                1 (to 1072)
                        1070    JUMP_BACKWARD                   87 (to 898)
                        1072    LOAD_GLOBAL                     37: NULL + StopProgram
                        1082    CALL                            0
                        1090    RAISE_VARARGS                   1
                        1092    END_FOR                         
                        1094    NOP                             
                        1096    LOAD_CONST                      0: None
                        1098    LOAD_CONST                      0: None
                        1100    LOAD_CONST                      0: None
                        1102    CALL                            2
                        1110    POP_TOP                         
                        1112    LOAD_CONST                      0: None
                        1114    NOP                             
                        1116    NOP                             
                        1118    NOP                             
                        1120    JUMP_FORWARD                    31 (to 1184)
                        1128    POP_TOP                         
                        1130    RETURN_CONST                    0: None
                        1132    PUSH_EXC_INFO                   
                        1134    WITH_EXCEPT_START               
                        1136    POP_JUMP_IF_TRUE                1 (to 1140)
                        1138    RERAISE                         2
                        1140    POP_TOP                         
                        1142    POP_EXCEPT                      
                        1144    POP_TOP                         
                        1146    POP_TOP                         
                        1148    JUMP_BACKWARD                   19 (to 1112)
                        1150    COPY                            3
                        1152    POP_EXCEPT                      
                        1154    RERAISE                         1
                        1156    PUSH_EXC_INFO                   
                        1158    PUSH_NULL                       
                        1160    LOAD_CONST                      15: '__pyarmor_exit_14864__'
                        1162    NOP                             
                        1164    LOAD_CONST                      3: b'<COAddr>\x05\x00\x00\x1aj\x04\x00\x00\x00\x00\x00\x00\x00\x00\x00\x00\x00\x00\x00\x00'
                        1166    CALL                            1
                        1174    POP_TOP                         
                        1176    RERAISE                         0
                        1178    COPY                            3
                        1180    POP_EXCEPT                      
                        1182    RERAISE                         1
                        1184    PUSH_NULL                       
                        1186    LOAD_CONST                      15: '__pyarmor_exit_14864__'
                        1188    LOAD_CONST                      3: b'<COAddr>\x05\x00\x00\x1aj\x04\x00\x00\x00\x00\x00\x00\x00\x00\x00\x00\x00\x00\x00\x00'
                        1190    BUILD_TUPLE                     1
                        1192    CALL_FUNCTION_EX                0
                        1194    POP_TOP                         
                        1196    RETURN_VALUE                    
                    [Exception Table]
                        28 to 334 -> 1156 [0] 
                        334 to 1070 -> 1132 [1] lasti
                        1072 to 1094 -> 1132 [1] lasti
                        1096 to 1112 -> 1156 [0] 
                        1132 to 1142 -> 1150 [3] lasti
                        1142 to 1156 -> 1156 [0] 
                        1156 to 1178 -> 1178 [1] lasti
                '__pyarmor_exit_14840__'
                (
                    'GET'
                    None
                    None
                    None
                    None
                    None
                )
            [Disassembly]
                0       NOP                             
                2       LOAD_NAME                       0: __name__
                4       STORE_NAME                      1: __module__
                6       LOAD_CONST                      0: 'ViewsWeb'
                8       STORE_NAME                      2: __qualname__
                10      NOP                             
                12      PUSH_NULL                       
                14      LOAD_CONST                      2: '__pyarmor_enter_14839__'
                16      LOAD_CONST                      3: b'<COAddr>\x05\x00\x00"H\x00\x00\x00\x00\x00\x00\x00\x00\x00\x00\x00\x00\x00\x00\x00'
                18      BUILD_TUPLE                     1
                20      CALL_FUNCTION_EX                0
                22      POP_TOP                         
                24      RESUME                          0
                26      NOP                             
                28      NOP                             
                30      NOP                             
                32      NOP                             
                34      NOP                             
                36      LOAD_CONST                      4: <CODE> __init__
                38      MAKE_FUNCTION                   0
                40      STORE_NAME                      4: __init__
                42      LOAD_CONST                      14: ('GET', None, None, None, None, None)
                44      LOAD_CONST                      6: <CODE> _request
                46      MAKE_FUNCTION                   1
                48      STORE_NAME                      5: _request
                50      LOAD_CONST                      7: <CODE> get_useragent
                52      MAKE_FUNCTION                   0
                54      STORE_NAME                      6: get_useragent
                56      LOAD_CONST                      8: <CODE> get_posts
                58      MAKE_FUNCTION                   0
                60      STORE_NAME                      7: get_posts
                62      LOAD_CONST                      9: <CODE> get_links
                64      MAKE_FUNCTION                   0
                66      STORE_NAME                      8: get_links
                68      LOAD_CONST                      10: <CODE> get_token
                70      MAKE_FUNCTION                   0
                72      STORE_NAME                      9: get_token
                74      LOAD_CONST                      11: <CODE> views
                76      MAKE_FUNCTION                   0
                78      STORE_NAME                      10: views
                80      LOAD_CONST                      12: <CODE> start
                82      MAKE_FUNCTION                   0
                84      STORE_NAME                      11: start
                86      LOAD_CONST                      5: None
                88      NOP                             
                90      NOP                             
                92      NOP                             
                94      JUMP_FORWARD                    19 (to 134)
                102     POP_TOP                         
                104     RETURN_CONST                    5: None
                106     PUSH_EXC_INFO                   
                108     PUSH_NULL                       
                110     LOAD_CONST                      13: '__pyarmor_exit_14840__'
                112     NOP                             
                114     LOAD_CONST                      3: b'<COAddr>\x05\x00\x00"H\x00\x00\x00\x00\x00\x00\x00\x00\x00\x00\x00\x00\x00\x00\x00'
                116     CALL                            1
                124     POP_TOP                         
                126     RERAISE                         0
                128     COPY                            3
                130     POP_EXCEPT                      
                132     RERAISE                         1
                134     PUSH_NULL                       
                136     LOAD_CONST                      13: '__pyarmor_exit_14840__'
                138     LOAD_CONST                      3: b'<COAddr>\x05\x00\x00"H\x00\x00\x00\x00\x00\x00\x00\x00\x00\x00\x00\x00\x00\x00\x00'
                140     BUILD_TUPLE                     1
                142     CALL_FUNCTION_EX                0
                144     POP_TOP                         
                146     RETURN_VALUE                    
            [Exception Table]
                36 to 86 -> 106 [0] 
                106 to 128 -> 128 [1] lasti
        'ViewsWeb'
        [Code]
            File Name: <frozen program.modules.Views_proxy>
            Object Name: proxy_get
            Qualified Name: proxy_get
            Arg Count: 0
            Pos Only Arg Count: 0
            KW Only Arg Count: 0
            Stack Size: 9
            Flags: 0x20000003 (CO_OPTIMIZED | CO_NEWLOCALS | CO_PYARMOR_OBFUSCATED)
            [Names]
                'db_proxy'
                'get'
                'lower'
                'append'
            [Locals+Names]
                '__assert_armored__'
                '_var_var_39'
                '_var_var_40'
                '_var_var_0'
                '_var_var_41'
                '_var_var_42'
                '_var_var_43'
                '_var_var_44'
                '_var_var_45'
                '_var_var_46'
            [Constants]
                None
                '__pyarmor_assert_14865__'
                '__pyarmor_enter_14866__'
                b'<COAddr>\x07\x00\x00\x1a\xf2\x01\x00\x00\x00\x00\x00\x00\x00\x00\x00\x00\x00\x00\x00\x00'
                1
                2
                3
                4
                5
                ''
                '__pyarmor_exit_14867__'
                False
                'http'
                'http://'
                ':'
                '@'
                'socks4'
                'socks4h://'   # b'\x81\xf1\x17\x108\xe9\xea\xdaA\xb5B'
                'socks5'
                'socks5h://'   # b'\x81\xf1\x17\x108\xe9\xeb\xdaA\xb5B'
                (
                    'http'
                    'https'
                )
            [Disassembly]
                0       NOP                             
                2       NOP                             
                4       PUSH_NULL                       
                6       LOAD_CONST                      2: '__pyarmor_enter_14866__'
                8       LOAD_CONST                      3: b'<COAddr>\x07\x00\x00\x1a\xf2\x01\x00\x00\x00\x00\x00\x00\x00\x00\x00\x00\x00\x00\x00\x00'
                10      BUILD_TUPLE                     1
                12      CALL_FUNCTION_EX                0
                14      POP_TOP                         
                16      RESUME                          0
                18      NOP                             
                20      NOP                             
                22      NOP                             
                24      NOP                             
                26      NOP                             
                28      LOAD_GLOBAL                     1: NULL + db_proxy
                38      CALL                            0
                46      LOAD_ATTR                       3: get
                66      CALL                            0
                74      STORE_FAST                      1: _var_var_39
                76      BUILD_LIST                      0
                78      STORE_FAST                      2: _var_var_40
                80      LOAD_FAST                       1: _var_var_39
                82      GET_ITER                        
                84      FOR_ITER                        206 (to 498)
                88      STORE_FAST                      3: _var_var_0
                90      LOAD_FAST                       3: _var_var_0
                92      LOAD_CONST                      4: 1
                94      BINARY_SUBSCR                   
                98      STORE_FAST                      4: _var_var_41
                100     LOAD_FAST                       3: _var_var_0
                102     LOAD_CONST                      5: 2
                104     BINARY_SUBSCR                   
                108     STORE_FAST                      5: _var_var_42
                110     LOAD_FAST                       3: _var_var_0
                112     LOAD_CONST                      6: 3
                114     BINARY_SUBSCR                   
                118     STORE_FAST                      6: _var_var_43
                120     LOAD_FAST                       3: _var_var_0
                122     LOAD_CONST                      7: 4
                124     BINARY_SUBSCR                   
                128     STORE_FAST                      7: _var_var_44
                130     LOAD_FAST                       3: _var_var_0
                132     LOAD_CONST                      8: 5
                134     BINARY_SUBSCR                   
                138     STORE_FAST                      8: _var_var_45
                140     LOAD_FAST                       8: _var_var_45
                142     LOAD_CONST                      9: ''
                144     COMPARE_OP                      40 (==)
                148     POP_JUMP_IF_TRUE                2 (to 154)
                150     LOAD_FAST                       8: _var_var_45
                152     POP_JUMP_IF_NOT_NONE            11 (to 176)
                154     POP_TOP                         
                156     LOAD_CONST                      11: False
                158     NOP                             
                160     NOP                             
                162     NOP                             
                164     JUMP_FORWARD                    193 (to 552)
                172     POP_TOP                         
                174     RETURN_CONST                    11: False
                176     LOAD_FAST                       8: _var_var_45
                178     LOAD_ATTR                       5: lower
                198     CALL                            0
                206     STORE_FAST                      8: _var_var_45
                208     LOAD_FAST                       8: _var_var_45
                210     LOAD_CONST                      12: 'http'
                212     COMPARE_OP                      40 (==)
                216     POP_JUMP_IF_FALSE               25 (to 268)
                218     LOAD_FAST                       6: _var_var_43
                220     POP_JUMP_IF_NOT_NONE            8 (to 238)
                222     LOAD_CONST                      13: 'http://'
                224     LOAD_FAST                       4: _var_var_41
                226     FORMAT_VALUE                    0 (FVC_NONE)
                228     LOAD_CONST                      14: ':'
                230     LOAD_FAST                       5: _var_var_42
                232     FORMAT_VALUE                    0 (FVC_NONE)
                234     BUILD_STRING                    4
                236     JUMP_FORWARD                    13 (to 264)
                238     LOAD_CONST                      13: 'http://'
                240     LOAD_FAST                       6: _var_var_43
                242     FORMAT_VALUE                    0 (FVC_NONE)
                244     LOAD_CONST                      14: ':'
                246     LOAD_FAST                       7: _var_var_44
                248     FORMAT_VALUE                    0 (FVC_NONE)
                250     LOAD_CONST                      15: '@'
                252     LOAD_FAST                       4: _var_var_41
                254     FORMAT_VALUE                    0 (FVC_NONE)
                256     LOAD_CONST                      14: ':'
                258     LOAD_FAST                       5: _var_var_42
                260     FORMAT_VALUE                    0 (FVC_NONE)
                262     BUILD_STRING                    8
                264     STORE_FAST                      9: _var_var_46
                266     JUMP_FORWARD                    95 (to 458)
                268     LOAD_FAST                       8: _var_var_45
                270     LOAD_CONST                      16: 'socks4'
                272     COMPARE_OP                      40 (==)
                276     POP_JUMP_IF_FALSE               37 (to 352)
                278     LOAD_FAST                       6: _var_var_43
                280     POP_JUMP_IF_NOT_NONE            14 (to 310)
                282     PUSH_NULL                       
                284     LOAD_CONST                      1: '__pyarmor_assert_14865__'
                286     LOAD_CONST                      17: 'socks4h://'   # b'\x81\xf1\x17\x108\xe9\xea\xdaA\xb5B'
                288     CALL                            1
                296     LOAD_FAST                       4: _var_var_41
                298     FORMAT_VALUE                    0 (FVC_NONE)
                300     LOAD_CONST                      14: ':'
                302     LOAD_FAST                       5: _var_var_42
                304     FORMAT_VALUE                    0 (FVC_NONE)
                306     BUILD_STRING                    4
                308     JUMP_FORWARD                    19 (to 348)
                310     PUSH_NULL                       
                312     LOAD_CONST                      1: '__pyarmor_assert_14865__'
                314     LOAD_CONST                      17: 'socks4h://'   # b'\x81\xf1\x17\x108\xe9\xea\xdaA\xb5B'
                316     CALL                            1
                324     LOAD_FAST                       6: _var_var_43
                326     FORMAT_VALUE                    0 (FVC_NONE)
                328     LOAD_CONST                      14: ':'
                330     LOAD_FAST                       7: _var_var_44
                332     FORMAT_VALUE                    0 (FVC_NONE)
                334     LOAD_CONST                      15: '@'
                336     LOAD_FAST                       4: _var_var_41
                338     FORMAT_VALUE                    0 (FVC_NONE)
                340     LOAD_CONST                      14: ':'
                342     LOAD_FAST                       5: _var_var_42
                344     FORMAT_VALUE                    0 (FVC_NONE)
                346     BUILD_STRING                    8
                348     STORE_FAST                      9: _var_var_46
                350     JUMP_FORWARD                    53 (to 458)
                352     LOAD_FAST                       8: _var_var_45
                354     LOAD_CONST                      18: 'socks5'
                356     COMPARE_OP                      40 (==)
                360     POP_JUMP_IF_FALSE               37 (to 436)
                362     LOAD_FAST                       6: _var_var_43
                364     POP_JUMP_IF_NOT_NONE            14 (to 394)
                366     PUSH_NULL                       
                368     LOAD_CONST                      1: '__pyarmor_assert_14865__'
                370     LOAD_CONST                      19: 'socks5h://'   # b'\x81\xf1\x17\x108\xe9\xeb\xdaA\xb5B'
                372     CALL                            1
                380     LOAD_FAST                       4: _var_var_41
                382     FORMAT_VALUE                    0 (FVC_NONE)
                384     LOAD_CONST                      14: ':'
                386     LOAD_FAST                       5: _var_var_42
                388     FORMAT_VALUE                    0 (FVC_NONE)
                390     BUILD_STRING                    4
                392     JUMP_FORWARD                    19 (to 432)
                394     PUSH_NULL                       
                396     LOAD_CONST                      1: '__pyarmor_assert_14865__'
                398     LOAD_CONST                      19: 'socks5h://'   # b'\x81\xf1\x17\x108\xe9\xeb\xdaA\xb5B'
                400     CALL                            1
                408     LOAD_FAST                       6: _var_var_43
                410     FORMAT_VALUE                    0 (FVC_NONE)
                412     LOAD_CONST                      14: ':'
                414     LOAD_FAST                       7: _var_var_44
                416     FORMAT_VALUE                    0 (FVC_NONE)
                418     LOAD_CONST                      15: '@'
                420     LOAD_FAST                       4: _var_var_41
                422     FORMAT_VALUE                    0 (FVC_NONE)
                424     LOAD_CONST                      14: ':'
                426     LOAD_FAST                       5: _var_var_42
                428     FORMAT_VALUE                    0 (FVC_NONE)
                430     BUILD_STRING                    8
                432     STORE_FAST                      9: _var_var_46
                434     JUMP_FORWARD                    11 (to 458)
                436     POP_TOP                         
                438     LOAD_CONST                      11: False
                440     NOP                             
                442     NOP                             
                444     NOP                             
                446     JUMP_FORWARD                    52 (to 552)
                454     POP_TOP                         
                456     RETURN_CONST                    11: False
                458     LOAD_FAST                       2: _var_var_40
                460     LOAD_ATTR                       7: append
                480     LOAD_FAST                       9: _var_var_46
                482     LOAD_FAST                       9: _var_var_46
                484     LOAD_CONST                      20: ('http', 'https')
                486     BUILD_CONST_KEY_MAP             2
                488     CALL                            1
                496     POP_TOP                         
                498     JUMP_BACKWARD                   208 (to 84)
                500     END_FOR                         
                502     LOAD_FAST                       2: _var_var_40
                504     NOP                             
                506     NOP                             
                508     NOP                             
                510     JUMP_FORWARD                    20 (to 552)
                512     CALL                            1
                520     POP_TOP                         
                522     RETURN_VALUE                    
                524     PUSH_EXC_INFO                   
                526     PUSH_NULL                       
                528     LOAD_CONST                      10: '__pyarmor_exit_14867__'
                530     NOP                             
                532     LOAD_CONST                      3: b'<COAddr>\x07\x00\x00\x1a\xf2\x01\x00\x00\x00\x00\x00\x00\x00\x00\x00\x00\x00\x00\x00\x00'
                534     CALL                            1
                542     POP_TOP                         
                544     RERAISE                         0
                546     COPY                            3
                548     POP_EXCEPT                      
                550     RERAISE                         1
                552     PUSH_NULL                       
                554     LOAD_CONST                      10: '__pyarmor_exit_14867__'
                556     LOAD_CONST                      3: b'<COAddr>\x07\x00\x00\x1a\xf2\x01\x00\x00\x00\x00\x00\x00\x00\x00\x00\x00\x00\x00\x00\x00'
                558     BUILD_TUPLE                     1
                560     CALL_FUNCTION_EX                0
                562     POP_TOP                         
                564     RETURN_VALUE                    
            [Exception Table]
                28 to 156 -> 524 [0] 
                176 to 438 -> 524 [0] 
                458 to 504 -> 524 [0] 
                524 to 546 -> 546 [1] lasti
        '__pyarmor_exit_14828__'
    [Disassembly]
        0       NOP                             
        2       NOP                             
        4       PUSH_NULL                       
        6       LOAD_CONST                      1: '__pyarmor_enter_14827__'
        8       LOAD_CONST                      2: b'<COAddr>\x07\x00\x00\x1aX\x01\x00\x00\x00\x00\x00\x00\x00\x00\x00\x00\x00\x00\x00\x00'
        10      BUILD_TUPLE                     1
        12      CALL_FUNCTION_EX                0
        14      POP_TOP                         
        16      RESUME                          0
        18      NOP                             
        20      NOP                             
        22      NOP                             
        24      NOP                             
        26      LOAD_CONST                      3: 0
        28      LOAD_CONST                      4: None
        30      IMPORT_NAME                     1: re
        32      STORE_NAME                      1: re
        34      LOAD_CONST                      3: 0
        36      LOAD_CONST                      4: None
        38      IMPORT_NAME                     2: eel
        40      STORE_NAME                      2: eel
        42      LOAD_CONST                      3: 0
        44      LOAD_CONST                      4: None
        46      IMPORT_NAME                     3: time
        48      STORE_NAME                      3: time
        50      LOAD_CONST                      3: 0
        52      LOAD_CONST                      4: None
        54      IMPORT_NAME                     4: json
        56      STORE_NAME                      4: json
        58      LOAD_CONST                      3: 0
        60      LOAD_CONST                      4: None
        62      IMPORT_NAME                     5: random
        64      STORE_NAME                      5: random
        66      LOAD_CONST                      3: 0
        68      LOAD_CONST                      4: None
        70      IMPORT_NAME                     6: requests
        72      STORE_NAME                      6: requests
        74      LOAD_CONST                      3: 0
        76      LOAD_CONST                      4: None
        78      IMPORT_NAME                     7: concurrent.futures
        80      STORE_NAME                      8: concurrent
        82      LOAD_CONST                      3: 0
        84      LOAD_CONST                      5: ('BeautifulSoup',)
        86      IMPORT_NAME                     9: bs4
        88      IMPORT_FROM                     10: BeautifulSoup
        90      STORE_NAME                      10: BeautifulSoup
        92      POP_TOP                         
        94      LOAD_CONST                      3: 0
        96      LOAD_CONST                      6: ('Thread', 'Event')
        98      IMPORT_NAME                     11: threading
        100     IMPORT_FROM                     12: Thread
        102     STORE_NAME                      12: Thread
        104     IMPORT_FROM                     13: Event
        106     STORE_NAME                      13: Event
        108     POP_TOP                         
        110     LOAD_CONST                      3: 0
        112     LOAD_CONST                      7: ('StopProgram',)
        114     IMPORT_NAME                     14: multithon.errors
        116     IMPORT_FROM                     15: StopProgram
        118     STORE_NAME                      15: StopProgram
        120     POP_TOP                         
        122     LOAD_CONST                      3: 0
        124     LOAD_CONST                      8: ('HTTPAdapter', 'Retry')
        126     IMPORT_NAME                     16: requests.adapters
        128     IMPORT_FROM                     17: HTTPAdapter
        130     STORE_NAME                      17: HTTPAdapter
        132     IMPORT_FROM                     18: Retry
        134     STORE_NAME                      18: Retry
        136     POP_TOP                         
        138     LOAD_CONST                      3: 0
        140     LOAD_CONST                      9: ('GetLang',)
        142     IMPORT_NAME                     19: program.static_classes
        144     IMPORT_FROM                     20: GetLang
        146     STORE_NAME                      20: GetLang
        148     POP_TOP                         
        150     LOAD_CONST                      3: 0
        152     LOAD_CONST                      10: ('Logs',)
        154     IMPORT_NAME                     19: program.static_classes
        156     IMPORT_FROM                     21: Logs
        158     STORE_NAME                      21: Logs
        160     POP_TOP                         
        162     LOAD_CONST                      3: 0
        164     LOAD_CONST                      11: ('logging',)
        166     IMPORT_NAME                     19: program.static_classes
        168     IMPORT_FROM                     22: logging
        170     STORE_NAME                      22: logging
        172     POP_TOP                         
        174     LOAD_CONST                      3: 0
        176     LOAD_CONST                      12: ('memory_check_switcher',)
        178     IMPORT_NAME                     19: program.static_classes
        180     IMPORT_FROM                     23: memory_check_switcher
        182     STORE_NAME                      23: memory_check_switcher
        184     POP_TOP                         
        186     LOAD_CONST                      3: 0
        188     LOAD_CONST                      13: ('memory_set_pid',)
        190     IMPORT_NAME                     19: program.static_classes
        192     IMPORT_FROM                     24: memory_set_pid
        194     STORE_NAME                      24: memory_set_pid
        196     POP_TOP                         
        198     LOAD_CONST                      3: 0
        200     LOAD_CONST                      14: ('Thread_wait',)
        202     IMPORT_NAME                     25: program.telegram
        204     IMPORT_FROM                     26: Thread_wait
        206     STORE_NAME                      26: Thread_wait
        208     POP_TOP                         
        210     LOAD_CONST                      3: 0
        212     LOAD_CONST                      15: ('GetConfig',)
        214     IMPORT_NAME                     27: program.general
        216     IMPORT_FROM                     28: GetConfig
        218     STORE_NAME                      28: GetConfig
        220     POP_TOP                         
        222     LOAD_CONST                      3: 0
        224     LOAD_CONST                      16: ('GetProxy',)
        226     IMPORT_NAME                     27: program.general
        228     IMPORT_FROM                     29: GetProxy
        230     STORE_NAME                      29: GetProxy
        232     POP_TOP                         
        234     LOAD_CONST                      3: 0
        236     LOAD_CONST                      17: ('StopDetect',)
        238     IMPORT_NAME                     27: program.general
        240     IMPORT_FROM                     30: StopDetect
        242     STORE_NAME                      30: StopDetect
        244     POP_TOP                         
        246     LOAD_CONST                      3: 0
        248     LOAD_CONST                      18: ('del_task_manager',)
        250     IMPORT_NAME                     27: program.general
        252     IMPORT_FROM                     31: del_task_manager
        254     STORE_NAME                      31: del_task_manager
        256     POP_TOP                         
        258     LOAD_CONST                      3: 0
        260     LOAD_CONST                      19: ('getFile',)
        262     IMPORT_NAME                     27: program.general
        264     IMPORT_FROM                     32: getFile
        266     STORE_NAME                      32: getFile
        268     POP_TOP                         
        270     LOAD_CONST                      3: 0
        272     LOAD_CONST                      20: ('set_task_manager',)
        274     IMPORT_NAME                     27: program.general
        276     IMPORT_FROM                     33: set_task_manager
        278     STORE_NAME                      33: set_task_manager
        280     POP_TOP                         
        282     LOAD_CONST                      3: 0
        284     LOAD_CONST                      21: ('getPath',)
        286     IMPORT_NAME                     27: program.general
        288     IMPORT_FROM                     34: getPath
        290     STORE_NAME                      34: getPath
        292     POP_TOP                         
        294     LOAD_CONST                      3: 0
        296     LOAD_CONST                      22: ('db_proxy',)
        298     IMPORT_NAME                     35: program.database
        300     IMPORT_FROM                     36: db_proxy
        302     STORE_NAME                      36: db_proxy
        304     POP_TOP                         
        306     LOAD_CONST                      23: <CODE> Views_proxy
        308     MAKE_FUNCTION                   0
        310     STORE_NAME                      37: Views_proxy
        312     LOAD_CONST                      24: <CODE> START
        314     MAKE_FUNCTION                   0
        316     STORE_NAME                      38: START
        318     LOAD_CONST                      25: <CODE> worker
        320     MAKE_FUNCTION                   0
        322     STORE_NAME                      39: worker
        324     PUSH_NULL                       
        326     LOAD_BUILD_CLASS                
        328     LOAD_CONST                      26: <CODE> ViewsWeb
        330     MAKE_FUNCTION                   0
        332     LOAD_CONST                      27: 'ViewsWeb'
        334     CALL                            2
        342     STORE_NAME                      40: ViewsWeb
        344     LOAD_CONST                      28: <CODE> proxy_get
        346     MAKE_FUNCTION                   0
        348     STORE_NAME                      41: proxy_get
        350     LOAD_CONST                      4: None
        352     NOP                             
        354     NOP                             
        356     NOP                             
        358     JUMP_FORWARD                    19 (to 398)
        366     POP_TOP                         
        368     RETURN_CONST                    4: None
        370     PUSH_EXC_INFO                   
        372     PUSH_NULL                       
        374     LOAD_CONST                      29: '__pyarmor_exit_14828__'
        376     NOP                             
        378     LOAD_CONST                      2: b'<COAddr>\x07\x00\x00\x1aX\x01\x00\x00\x00\x00\x00\x00\x00\x00\x00\x00\x00\x00\x00\x00'
        380     CALL                            1
        388     POP_TOP                         
        390     RERAISE                         0
        392     COPY                            3
        394     POP_EXCEPT                      
        396     RERAISE                         1
        398     PUSH_NULL                       
        400     LOAD_CONST                      29: '__pyarmor_exit_14828__'
        402     LOAD_CONST                      2: b'<COAddr>\x07\x00\x00\x1aX\x01\x00\x00\x00\x00\x00\x00\x00\x00\x00\x00\x00\x00\x00\x00'
        404     BUILD_TUPLE                     1
        406     CALL_FUNCTION_EX                0
        408     POP_TOP                         
        410     RETURN_VALUE                    
    [Exception Table]
        26 to 350 -> 370 [0] 
        370 to 392 -> 392 [1] lasti
