#decoded by lolz.live/mrpenny / t.me/zeus_jackpot
# ================================
# Примечания по Pyarmor:
# - Байт-код и объекты кода Pyarmor соответствуют стандартному Python, но присутствуют специальные вызовы функций среды выполнения (runtime) Pyarmor.
# - Вызовы строк — это не ошибки, а маркеры, которые обрабатываются Pyarmor во время выполнения.
#
# Руководство по декомпиляции (без среды выполнения):
# 1. Игнорируйте зашифрованные байты после `#`; используйте только строку до `#`.
# 2. Удалите "__pyarmor_enter_xxx__"(b"<COAddr>...") и "__pyarmor_leave_xxx__"(b"<COAddr>...") (пролог/эпилог).
# 3. "__pyarmor_assert_xxx__"(A) не является настоящим оператором assert.
#    - Если A — это имя или читаемая строка: замените на A.
#    - Если A — это (X, "Y"): замените на X.Y.
#    - Если A — это (X, "Y", Z): замените на X.Y = Z.
#    - В противном случае: выберите наиболее подходящую/логичную замену.
# 4. "__pyarmor_bcc_xxx__"(...) указывает на машинный (нативный) код; тело функции недоступно. Добавьте комментарий.
# ================================

[Code]
    File Name: <frozen multithon.tl.types.bots>
    Object Name: <module>
    Qualified Name: <module>
    Arg Count: 0
    Pos Only Arg Count: 0
    KW Only Arg Count: 0
    Stack Size: 5
    Flags: 0x20000000 (CO_PYARMOR_OBFUSCATED)
    [Names]
        '__assert_armored__'
        'tl.tlobject'
        'TLObject'
        'typing'
        'Optional'
        'List'
        'Union'
        'TYPE_CHECKING'
        'os'
        'struct'
        'datetime'
        'tl.types'
        'TypeBotPreviewMedia'
        'TypeUser'
        'BotInfo'
        'PopularAppBots'
        'PreviewInfo'
    [Locals+Names]
    [Constants]
        '__pyarmor_assert_38166__'
        '__pyarmor_enter_38167__'
        b'<COAddr>\x07\x00\x00\x1a\xba\x00\x00\x00\x00\x00\x00\x00\x00\x00\x00\x00\x00\x00\x00\x00'
        "File generated by TLObjects' generator. All changes will be ERASED"   # b'\x81\xc4\x11\x1f6\xba\xb9\xd7\x15\xff\x1f\xc1x\xe9\xfc\xc5\rD\xfb\x93\x86\xe4L\xc6\x00l\xb7OG\xf1\x19\xe04W2\x0c\x8c\xc5\xa6`X\xc8\xf4Q\x9d\xdb\x07F9\xeaS\xe8\xc7g\x0f\xe1;\xab\x99\x18Xn\x03rdm!'
        3
        (
            'TLObject'
        )
        0
        (
            'Optional'
            'List'
            'Union'
            'TYPE_CHECKING'
        )
        None
        (
            'datetime'
        )
        (
            'TypeBotPreviewMedia'
            'TypeUser'
        )
        [Code]
            File Name: <frozen multithon.tl.types.bots>
            Object Name: BotInfo
            Qualified Name: BotInfo
            Arg Count: 0
            Pos Only Arg Count: 0
            KW Only Arg Count: 0
            Stack Size: 6
            Flags: 0x20000000 (CO_PYARMOR_OBFUSCATED)
            [Names]
                '__name__'
                '__module__'
                '__qualname__'
                '__assert_armored__'
                'CONSTRUCTOR_ID'
                'SUBCLASS_OF_ID'
                'str'
                '__init__'
                'to_dict'
                '_bytes'
                'classmethod'
                'from_reader'
            [Locals+Names]
            [Constants]
                'BotInfo'
                '__pyarmor_assert_38169__'
                '__pyarmor_enter_38170__'
                b'<COAddr>\x07\x00\x00"N\x00\x00\x00\x00\x00\x00\x00\x00\x00\x00\x00\x00\x00\x00\x00'
                0xE8A775B0
                0xCA7B2235
                'name'
                'about'
                'description'
                [Code]
                    File Name: <frozen multithon.tl.types.bots>
                    Object Name: __init__
                    Qualified Name: BotInfo.__init__
                    Arg Count: 4
                    Pos Only Arg Count: 0
                    KW Only Arg Count: 0
                    Stack Size: 5
                    Flags: 0x20000003 (CO_OPTIMIZED | CO_NEWLOCALS | CO_PYARMOR_OBFUSCATED)
                    [Names]
                        'name'
                        'about'
                        'description'
                    [Locals+Names]
                        'self'
                        'name'
                        'about'
                        'description'
                        '__assert_armored__'
                    [Constants]
                        '\n        Constructor for bots.BotInfo: Instance of BotInfo.\n        '
                        '__pyarmor_assert_38172__'
                        '__pyarmor_enter_38173__'
                        b'<COAddr>\x07\x00\x00\x1a@\x00\x00\x00\x00\x00\x00\x00\x00\x00\x00\x00\x00\x00\x00\x00'
                        '__pyarmor_exit_38174__'
                        None
                    [Disassembly]
                        0       NOP                             
                        2       NOP                             
                        4       PUSH_NULL                       
                        6       LOAD_CONST                      2: '__pyarmor_enter_38173__'
                        8       LOAD_CONST                      3: b'<COAddr>\x07\x00\x00\x1a@\x00\x00\x00\x00\x00\x00\x00\x00\x00\x00\x00\x00\x00\x00\x00'
                        10      BUILD_TUPLE                     1
                        12      CALL_FUNCTION_EX                0
                        14      POP_TOP                         
                        16      RESUME                          0
                        18      NOP                             
                        20      NOP                             
                        22      NOP                             
                        24      NOP                             
                        26      NOP                             
                        28      LOAD_FAST                       1: name
                        30      LOAD_FAST                       0: self
                        32      STORE_ATTR                      0: name
                        42      LOAD_FAST                       2: about
                        44      LOAD_FAST                       0: self
                        46      STORE_ATTR                      1: about
                        56      LOAD_FAST                       3: description
                        58      LOAD_FAST                       0: self
                        60      STORE_ATTR                      2: description
                        70      LOAD_CONST                      5: None
                        72      NOP                             
                        74      NOP                             
                        76      NOP                             
                        78      JUMP_FORWARD                    19 (to 118)
                        86      POP_TOP                         
                        88      RETURN_CONST                    5: None
                        90      PUSH_EXC_INFO                   
                        92      PUSH_NULL                       
                        94      LOAD_CONST                      4: '__pyarmor_exit_38174__'
                        96      NOP                             
                        98      LOAD_CONST                      3: b'<COAddr>\x07\x00\x00\x1a@\x00\x00\x00\x00\x00\x00\x00\x00\x00\x00\x00\x00\x00\x00\x00'
                        100     CALL                            1
                        108     POP_TOP                         
                        110     RERAISE                         0
                        112     COPY                            3
                        114     POP_EXCEPT                      
                        116     RERAISE                         1
                        118     PUSH_NULL                       
                        120     LOAD_CONST                      4: '__pyarmor_exit_38174__'
                        122     LOAD_CONST                      3: b'<COAddr>\x07\x00\x00\x1a@\x00\x00\x00\x00\x00\x00\x00\x00\x00\x00\x00\x00\x00\x00\x00'
                        124     BUILD_TUPLE                     1
                        126     CALL_FUNCTION_EX                0
                        128     POP_TOP                         
                        130     RETURN_VALUE                    
                    [Exception Table]
                        28 to 70 -> 90 [0] 
                        90 to 112 -> 112 [1] lasti
                [Code]
                    File Name: <frozen multithon.tl.types.bots>
                    Object Name: to_dict
                    Qualified Name: BotInfo.to_dict
                    Arg Count: 1
                    Pos Only Arg Count: 0
                    KW Only Arg Count: 0
                    Stack Size: 9
                    Flags: 0x20000003 (CO_OPTIMIZED | CO_NEWLOCALS | CO_PYARMOR_OBFUSCATED)
                    [Names]
                        'name'
                        'about'
                        'description'
                    [Locals+Names]
                        'self'
                        '__assert_armored__'
                    [Constants]
                        None
                        '__pyarmor_assert_38175__'
                        '__pyarmor_enter_38176__'
                        b'<COAddr>\x05\x00\x00\x1ap\x00\x00\x00\x00\x00\x00\x00\x00\x00\x00\x00\x00\x00\x00\x00'
                        '_'
                        'BotInfo'
                        'name'
                        'about'
                        'description'   # b'\x81\xe6\x1d\x000\xe8\xb7\xc2\x0f\xf3\x02\xce'
                        '__pyarmor_exit_38177__'
                    [Disassembly]
                        0       NOP                             
                        2       NOP                             
                        4       PUSH_NULL                       
                        6       LOAD_CONST                      2: '__pyarmor_enter_38176__'
                        8       LOAD_CONST                      3: b'<COAddr>\x05\x00\x00\x1ap\x00\x00\x00\x00\x00\x00\x00\x00\x00\x00\x00\x00\x00\x00\x00'
                        10      BUILD_TUPLE                     1
                        12      CALL_FUNCTION_EX                0
                        14      POP_TOP                         
                        16      RESUME                          0
                        18      NOP                             
                        20      NOP                             
                        22      NOP                             
                        24      NOP                             
                        26      NOP                             
                        28      LOAD_CONST                      4: '_'
                        30      LOAD_CONST                      5: 'BotInfo'
                        32      LOAD_CONST                      6: 'name'
                        34      LOAD_FAST                       0: self
                        36      LOAD_ATTR                       0: name
                        56      LOAD_CONST                      7: 'about'
                        58      LOAD_FAST                       0: self
                        60      LOAD_ATTR                       2: about
                        80      PUSH_NULL                       
                        82      LOAD_CONST                      1: '__pyarmor_assert_38175__'
                        84      LOAD_CONST                      8: 'description'   # b'\x81\xe6\x1d\x000\xe8\xb7\xc2\x0f\xf3\x02\xce'
                        86      CALL                            1
                        94      LOAD_FAST                       0: self
                        96      LOAD_ATTR                       4: description
                        116     BUILD_MAP                       4
                        118     NOP                             
                        120     NOP                             
                        122     NOP                             
                        124     JUMP_FORWARD                    20 (to 166)
                        126     CALL                            1
                        134     POP_TOP                         
                        136     RETURN_VALUE                    
                        138     PUSH_EXC_INFO                   
                        140     PUSH_NULL                       
                        142     LOAD_CONST                      9: '__pyarmor_exit_38177__'
                        144     NOP                             
                        146     LOAD_CONST                      3: b'<COAddr>\x05\x00\x00\x1ap\x00\x00\x00\x00\x00\x00\x00\x00\x00\x00\x00\x00\x00\x00\x00'
                        148     CALL                            1
                        156     POP_TOP                         
                        158     RERAISE                         0
                        160     COPY                            3
                        162     POP_EXCEPT                      
                        164     RERAISE                         1
                        166     PUSH_NULL                       
                        168     LOAD_CONST                      9: '__pyarmor_exit_38177__'
                        170     LOAD_CONST                      3: b'<COAddr>\x05\x00\x00\x1ap\x00\x00\x00\x00\x00\x00\x00\x00\x00\x00\x00\x00\x00\x00\x00'
                        172     BUILD_TUPLE                     1
                        174     CALL_FUNCTION_EX                0
                        176     POP_TOP                         
                        178     RETURN_VALUE                    
                    [Exception Table]
                        28 to 118 -> 138 [0] 
                        138 to 160 -> 160 [1] lasti
                [Code]
                    File Name: <frozen multithon.tl.types.bots>
                    Object Name: _bytes
                    Qualified Name: BotInfo._bytes
                    Arg Count: 1
                    Pos Only Arg Count: 0
                    KW Only Arg Count: 0
                    Stack Size: 8
                    Flags: 0x20000003 (CO_OPTIMIZED | CO_NEWLOCALS | CO_PYARMOR_OBFUSCATED)
                    [Names]
                        'join'
                        'serialize_bytes'
                        'name'
                        'about'
                        'description'
                    [Locals+Names]
                        'self'
                        '__assert_armored__'
                    [Constants]
                        None
                        '__pyarmor_assert_38178__'
                        '__pyarmor_enter_38179__'
                        b'<COAddr>\x07\x00\x00\x1a\xd4\x00\x00\x00\x00\x00\x00\x00\x00\x00\x00\x00\x00\x00\x00\x00'
                        b''
                        b'\xb0u\xa7\xe8'
                        '__pyarmor_exit_38180__'
                    [Disassembly]
                        0       NOP                             
                        2       NOP                             
                        4       PUSH_NULL                       
                        6       LOAD_CONST                      2: '__pyarmor_enter_38179__'
                        8       LOAD_CONST                      3: b'<COAddr>\x07\x00\x00\x1a\xd4\x00\x00\x00\x00\x00\x00\x00\x00\x00\x00\x00\x00\x00\x00\x00'
                        10      BUILD_TUPLE                     1
                        12      CALL_FUNCTION_EX                0
                        14      POP_TOP                         
                        16      RESUME                          0
                        18      NOP                             
                        20      NOP                             
                        22      NOP                             
                        24      NOP                             
                        26      NOP                             
                        28      LOAD_CONST                      4: b''
                        30      LOAD_ATTR                       1: join
                        50      LOAD_CONST                      5: b'\xb0u\xa7\xe8'
                        52      LOAD_FAST                       0: self
                        54      LOAD_ATTR                       3: serialize_bytes
                        74      LOAD_FAST                       0: self
                        76      LOAD_ATTR                       4: name
                        96      CALL                            1
                        104     LOAD_FAST                       0: self
                        106     LOAD_ATTR                       3: serialize_bytes
                        126     LOAD_FAST                       0: self
                        128     LOAD_ATTR                       6: about
                        148     CALL                            1
                        156     LOAD_FAST                       0: self
                        158     LOAD_ATTR                       3: serialize_bytes
                        178     LOAD_FAST                       0: self
                        180     LOAD_ATTR                       8: description
                        200     CALL                            1
                        208     BUILD_TUPLE                     4
                        210     CALL                            1
                        218     NOP                             
                        220     NOP                             
                        222     NOP                             
                        224     JUMP_FORWARD                    20 (to 266)
                        226     CALL                            1
                        234     POP_TOP                         
                        236     RETURN_VALUE                    
                        238     PUSH_EXC_INFO                   
                        240     PUSH_NULL                       
                        242     LOAD_CONST                      6: '__pyarmor_exit_38180__'
                        244     NOP                             
                        246     LOAD_CONST                      3: b'<COAddr>\x07\x00\x00\x1a\xd4\x00\x00\x00\x00\x00\x00\x00\x00\x00\x00\x00\x00\x00\x00\x00'
                        248     CALL                            1
                        256     POP_TOP                         
                        258     RERAISE                         0
                        260     COPY                            3
                        262     POP_EXCEPT                      
                        264     RERAISE                         1
                        266     PUSH_NULL                       
                        268     LOAD_CONST                      6: '__pyarmor_exit_38180__'
                        270     LOAD_CONST                      3: b'<COAddr>\x07\x00\x00\x1a\xd4\x00\x00\x00\x00\x00\x00\x00\x00\x00\x00\x00\x00\x00\x00\x00'
                        272     BUILD_TUPLE                     1
                        274     CALL_FUNCTION_EX                0
                        276     POP_TOP                         
                        278     RETURN_VALUE                    
                    [Exception Table]
                        28 to 218 -> 238 [0] 
                        238 to 260 -> 260 [1] lasti
                [Code]
                    File Name: <frozen multithon.tl.types.bots>
                    Object Name: from_reader
                    Qualified Name: BotInfo.from_reader
                    Arg Count: 2
                    Pos Only Arg Count: 0
                    KW Only Arg Count: 0
                    Stack Size: 5
                    Flags: 0x20000003 (CO_OPTIMIZED | CO_NEWLOCALS | CO_PYARMOR_OBFUSCATED)
                    [Names]
                        'tgread_string'
                    [Locals+Names]
                        'cls'
                        'reader'
                        '__assert_armored__'
                        '_var_var_0'
                        '_var_var_1'
                        '_var_var_2'
                    [Constants]
                        None
                        '__pyarmor_assert_38181__'
                        '__pyarmor_enter_38182__'
                        b'<COAddr>\x05\x00\x00\x1a\x8a\x00\x00\x00\x00\x00\x00\x00\x00\x00\x00\x00\x00\x00\x00\x00'
                        (
                            'name'
                            'about'
                            'description'
                        )
                        '__pyarmor_exit_38183__'
                    [Disassembly]
                        0       NOP                             
                        2       NOP                             
                        4       PUSH_NULL                       
                        6       LOAD_CONST                      2: '__pyarmor_enter_38182__'
                        8       LOAD_CONST                      3: b'<COAddr>\x05\x00\x00\x1a\x8a\x00\x00\x00\x00\x00\x00\x00\x00\x00\x00\x00\x00\x00\x00\x00'
                        10      BUILD_TUPLE                     1
                        12      CALL_FUNCTION_EX                0
                        14      POP_TOP                         
                        16      RESUME                          0
                        18      NOP                             
                        20      NOP                             
                        22      NOP                             
                        24      NOP                             
                        26      NOP                             
                        28      LOAD_FAST                       1: reader
                        30      LOAD_ATTR                       1: tgread_string
                        50      CALL                            0
                        58      STORE_FAST                      3: _var_var_0
                        60      LOAD_FAST                       1: reader
                        62      LOAD_ATTR                       1: tgread_string
                        82      CALL                            0
                        90      STORE_FAST                      4: _var_var_1
                        92      LOAD_FAST                       1: reader
                        94      LOAD_ATTR                       1: tgread_string
                        114     CALL                            0
                        122     STORE_FAST                      5: _var_var_2
                        124     PUSH_NULL                       
                        126     LOAD_FAST                       0: cls
                        128     LOAD_FAST                       3: _var_var_0
                        130     LOAD_FAST                       4: _var_var_1
                        132     LOAD_FAST                       5: _var_var_2
                        134     KW_NAMES                        4: ('name', 'about', 'description')
                        136     CALL                            3
                        144     NOP                             
                        146     NOP                             
                        148     NOP                             
                        150     JUMP_FORWARD                    20 (to 192)
                        152     CALL                            1
                        160     POP_TOP                         
                        162     RETURN_VALUE                    
                        164     PUSH_EXC_INFO                   
                        166     PUSH_NULL                       
                        168     LOAD_CONST                      5: '__pyarmor_exit_38183__'
                        170     NOP                             
                        172     LOAD_CONST                      3: b'<COAddr>\x05\x00\x00\x1a\x8a\x00\x00\x00\x00\x00\x00\x00\x00\x00\x00\x00\x00\x00\x00\x00'
                        174     CALL                            1
                        182     POP_TOP                         
                        184     RERAISE                         0
                        186     COPY                            3
                        188     POP_EXCEPT                      
                        190     RERAISE                         1
                        192     PUSH_NULL                       
                        194     LOAD_CONST                      5: '__pyarmor_exit_38183__'
                        196     LOAD_CONST                      3: b'<COAddr>\x05\x00\x00\x1a\x8a\x00\x00\x00\x00\x00\x00\x00\x00\x00\x00\x00\x00\x00\x00\x00'
                        198     BUILD_TUPLE                     1
                        200     CALL_FUNCTION_EX                0
                        202     POP_TOP                         
                        204     RETURN_VALUE                    
                    [Exception Table]
                        28 to 144 -> 164 [0] 
                        164 to 186 -> 186 [1] lasti
                '__pyarmor_exit_38171__'
                None
            [Disassembly]
                0       NOP                             
                2       LOAD_NAME                       0: __name__
                4       STORE_NAME                      1: __module__
                6       LOAD_CONST                      0: 'BotInfo'
                8       STORE_NAME                      2: __qualname__
                10      NOP                             
                12      PUSH_NULL                       
                14      LOAD_CONST                      2: '__pyarmor_enter_38170__'
                16      LOAD_CONST                      3: b'<COAddr>\x07\x00\x00"N\x00\x00\x00\x00\x00\x00\x00\x00\x00\x00\x00\x00\x00\x00\x00'
                18      BUILD_TUPLE                     1
                20      CALL_FUNCTION_EX                0
                22      POP_TOP                         
                24      RESUME                          0
                26      NOP                             
                28      NOP                             
                30      NOP                             
                32      NOP                             
                34      NOP                             
                36      LOAD_CONST                      4: 0xE8A775B0
                38      STORE_NAME                      4: CONSTRUCTOR_ID
                40      LOAD_CONST                      5: 0xCA7B2235
                42      STORE_NAME                      5: SUBCLASS_OF_ID
                44      LOAD_CONST                      6: 'name'
                46      LOAD_NAME                       6: str
                48      LOAD_CONST                      7: 'about'
                50      LOAD_NAME                       6: str
                52      LOAD_CONST                      8: 'description'
                54      LOAD_NAME                       6: str
                56      BUILD_TUPLE                     6
                58      LOAD_CONST                      9: <CODE> __init__
                60      MAKE_FUNCTION                   4
                62      STORE_NAME                      7: __init__
                64      LOAD_CONST                      10: <CODE> to_dict
                66      MAKE_FUNCTION                   0
                68      STORE_NAME                      8: to_dict
                70      LOAD_CONST                      11: <CODE> _bytes
                72      MAKE_FUNCTION                   0
                74      STORE_NAME                      9: _bytes
                76      LOAD_NAME                       10: classmethod
                78      LOAD_CONST                      12: <CODE> from_reader
                80      MAKE_FUNCTION                   0
                82      CALL                            0
                90      STORE_NAME                      11: from_reader
                92      LOAD_CONST                      14: None
                94      NOP                             
                96      NOP                             
                98      NOP                             
                100     JUMP_FORWARD                    19 (to 140)
                108     POP_TOP                         
                110     RETURN_CONST                    14: None
                112     PUSH_EXC_INFO                   
                114     PUSH_NULL                       
                116     LOAD_CONST                      13: '__pyarmor_exit_38171__'
                118     NOP                             
                120     LOAD_CONST                      3: b'<COAddr>\x07\x00\x00"N\x00\x00\x00\x00\x00\x00\x00\x00\x00\x00\x00\x00\x00\x00\x00'
                122     CALL                            1
                130     POP_TOP                         
                132     RERAISE                         0
                134     COPY                            3
                136     POP_EXCEPT                      
                138     RERAISE                         1
                140     PUSH_NULL                       
                142     LOAD_CONST                      13: '__pyarmor_exit_38171__'
                144     LOAD_CONST                      3: b'<COAddr>\x07\x00\x00"N\x00\x00\x00\x00\x00\x00\x00\x00\x00\x00\x00\x00\x00\x00\x00'
                146     BUILD_TUPLE                     1
                148     CALL_FUNCTION_EX                0
                150     POP_TOP                         
                152     RETURN_VALUE                    
            [Exception Table]
                36 to 92 -> 112 [0] 
                112 to 134 -> 134 [1] lasti
        'BotInfo'
        [Code]
            File Name: <frozen multithon.tl.types.bots>
            Object Name: PopularAppBots
            Qualified Name: PopularAppBots
            Arg Count: 0
            Pos Only Arg Count: 0
            KW Only Arg Count: 0
            Stack Size: 6
            Flags: 0x20000000 (CO_PYARMOR_OBFUSCATED)
            [Names]
                '__name__'
                '__module__'
                '__qualname__'
                '__assert_armored__'
                'CONSTRUCTOR_ID'
                'SUBCLASS_OF_ID'
                'List'
                'Optional'
                'str'
                '__init__'
                'to_dict'
                '_bytes'
                'classmethod'
                'from_reader'
            [Locals+Names]
            [Constants]
                'PopularAppBots'
                '__pyarmor_assert_38184__'
                '__pyarmor_enter_38185__'
                b'<COAddr>\x05\x00\x00"X\x00\x00\x00\x00\x00\x00\x00\x00\x00\x00\x00\x00\x00\x00\x00'
                428978491
                2070199933
                None
                'users'
                'TypeUser'
                'next_offset'
                [Code]
                    File Name: <frozen multithon.tl.types.bots>
                    Object Name: __init__
                    Qualified Name: PopularAppBots.__init__
                    Arg Count: 3
                    Pos Only Arg Count: 0
                    KW Only Arg Count: 0
                    Stack Size: 5
                    Flags: 0x20000003 (CO_OPTIMIZED | CO_NEWLOCALS | CO_PYARMOR_OBFUSCATED)
                    [Names]
                        'users'
                        'next_offset'
                    [Locals+Names]
                        'self'
                        'users'
                        'next_offset'
                        '__assert_armored__'
                    [Constants]
                        '\n        Constructor for bots.PopularAppBots: Instance of PopularAppBots.\n        '
                        '__pyarmor_assert_38187__'
                        '__pyarmor_enter_38188__'
                        b'<COAddr>\x07\x00\x00\x1a2\x00\x00\x00\x00\x00\x00\x00\x00\x00\x00\x00\x00\x00\x00\x00'
                        '__pyarmor_exit_38189__'
                        None
                    [Disassembly]
                        0       NOP                             
                        2       NOP                             
                        4       PUSH_NULL                       
                        6       LOAD_CONST                      2: '__pyarmor_enter_38188__'
                        8       LOAD_CONST                      3: b'<COAddr>\x07\x00\x00\x1a2\x00\x00\x00\x00\x00\x00\x00\x00\x00\x00\x00\x00\x00\x00\x00'
                        10      BUILD_TUPLE                     1
                        12      CALL_FUNCTION_EX                0
                        14      POP_TOP                         
                        16      RESUME                          0
                        18      NOP                             
                        20      NOP                             
                        22      NOP                             
                        24      NOP                             
                        26      NOP                             
                        28      LOAD_FAST                       1: users
                        30      LOAD_FAST                       0: self
                        32      STORE_ATTR                      0: users
                        42      LOAD_FAST                       2: next_offset
                        44      LOAD_FAST                       0: self
                        46      STORE_ATTR                      1: next_offset
                        56      LOAD_CONST                      5: None
                        58      NOP                             
                        60      NOP                             
                        62      NOP                             
                        64      JUMP_FORWARD                    19 (to 104)
                        72      POP_TOP                         
                        74      RETURN_CONST                    5: None
                        76      PUSH_EXC_INFO                   
                        78      PUSH_NULL                       
                        80      LOAD_CONST                      4: '__pyarmor_exit_38189__'
                        82      NOP                             
                        84      LOAD_CONST                      3: b'<COAddr>\x07\x00\x00\x1a2\x00\x00\x00\x00\x00\x00\x00\x00\x00\x00\x00\x00\x00\x00\x00'
                        86      CALL                            1
                        94      POP_TOP                         
                        96      RERAISE                         0
                        98      COPY                            3
                        100     POP_EXCEPT                      
                        102     RERAISE                         1
                        104     PUSH_NULL                       
                        106     LOAD_CONST                      4: '__pyarmor_exit_38189__'
                        108     LOAD_CONST                      3: b'<COAddr>\x07\x00\x00\x1a2\x00\x00\x00\x00\x00\x00\x00\x00\x00\x00\x00\x00\x00\x00\x00'
                        110     BUILD_TUPLE                     1
                        112     CALL_FUNCTION_EX                0
                        114     POP_TOP                         
                        116     RETURN_VALUE                    
                    [Exception Table]
                        28 to 56 -> 76 [0] 
                        76 to 98 -> 98 [1] lasti
                [Code]
                    File Name: <frozen multithon.tl.types.bots>
                    Object Name: to_dict
                    Qualified Name: PopularAppBots.to_dict
                    Arg Count: 1
                    Pos Only Arg Count: 0
                    KW Only Arg Count: 0
                    Stack Size: 10
                    Flags: 0x20000003 (CO_OPTIMIZED | CO_NEWLOCALS | CO_PYARMOR_OBFUSCATED)
                    [Names]
                        'users'
                        'isinstance'
                        'TLObject'
                        'to_dict'
                        'next_offset'
                    [Locals+Names]
                        'self'
                        '__assert_armored__'
                        '_var_var_3'
                    [Constants]
                        None
                        '__pyarmor_assert_38190__'
                        '__pyarmor_enter_38191__'
                        b'<COAddr>\x07\x00\x00\x1a\xe6\x00\x00\x00\x00\x00\x00\x00\x00\x00\x00\x00\x00\x00\x00\x00'
                        '_'
                        'PopularAppBots'   # b'\x81\xd2\x17\x03&\xf6\xbf\xc0:\xea\x1d\xe2c\xf8\xeb'
                        'users'
                        'next_offset'   # b"\x81\xec\x1d\x0b'\xc5\xb1\xd4\x1d\xe9\x08\xd4"
                        '__pyarmor_exit_38192__'
                    [Disassembly]
                        0       NOP                             
                        2       NOP                             
                        4       PUSH_NULL                       
                        6       LOAD_CONST                      2: '__pyarmor_enter_38191__'
                        8       LOAD_CONST                      3: b'<COAddr>\x07\x00\x00\x1a\xe6\x00\x00\x00\x00\x00\x00\x00\x00\x00\x00\x00\x00\x00\x00\x00'
                        10      BUILD_TUPLE                     1
                        12      CALL_FUNCTION_EX                0
                        14      POP_TOP                         
                        16      RESUME                          0
                        18      NOP                             
                        20      NOP                             
                        22      NOP                             
                        24      NOP                             
                        26      NOP                             
                        28      LOAD_CONST                      4: '_'
                        30      PUSH_NULL                       
                        32      LOAD_CONST                      1: '__pyarmor_assert_38190__'
                        34      LOAD_CONST                      5: 'PopularAppBots'   # b'\x81\xd2\x17\x03&\xf6\xbf\xc0:\xea\x1d\xe2c\xf8\xeb'
                        36      CALL                            1
                        44      LOAD_CONST                      6: 'users'
                        46      LOAD_FAST                       0: self
                        48      LOAD_ATTR                       0: users
                        68      POP_JUMP_IF_NOT_NONE            2 (to 74)
                        70      BUILD_LIST                      0
                        72      JUMP_FORWARD                    57 (to 188)
                        74      LOAD_FAST                       0: self
                        76      LOAD_ATTR                       0: users
                        96      GET_ITER                        
                        98      LOAD_FAST_AND_CLEAR             2: _var_var_3
                        100     SWAP                            2
                        102     BUILD_LIST                      0
                        104     SWAP                            2
                        106     FOR_ITER                        36 (to 180)
                        110     STORE_FAST                      2: _var_var_3
                        112     LOAD_GLOBAL                     3: NULL + isinstance
                        122     LOAD_FAST                       2: _var_var_3
                        124     LOAD_GLOBAL                     4: TLObject
                        134     CALL                            2
                        142     POP_JUMP_IF_FALSE               16 (to 176)
                        144     LOAD_FAST                       2: _var_var_3
                        146     LOAD_ATTR                       7: to_dict
                        166     CALL                            0
                        174     JUMP_FORWARD                    1 (to 178)
                        176     LOAD_FAST                       2: _var_var_3
                        178     LIST_APPEND                     2
                        180     JUMP_BACKWARD                   38 (to 106)
                        182     END_FOR                         
                        184     SWAP                            2
                        186     STORE_FAST                      2: _var_var_3
                        188     PUSH_NULL                       
                        190     LOAD_CONST                      1: '__pyarmor_assert_38190__'
                        192     LOAD_CONST                      7: 'next_offset'   # b"\x81\xec\x1d\x0b'\xc5\xb1\xd4\x1d\xe9\x08\xd4"
                        194     CALL                            1
                        202     LOAD_FAST                       0: self
                        204     LOAD_ATTR                       8: next_offset
                        224     BUILD_MAP                       3
                        226     NOP                             
                        228     NOP                             
                        230     NOP                             
                        232     JUMP_FORWARD                    25 (to 284)
                        234     CALL                            1
                        242     POP_TOP                         
                        244     RETURN_VALUE                    
                        246     SWAP                            2
                        248     POP_TOP                         
                        250     SWAP                            2
                        252     STORE_FAST                      2: _var_var_3
                        254     RERAISE                         0
                        256     PUSH_EXC_INFO                   
                        258     PUSH_NULL                       
                        260     LOAD_CONST                      8: '__pyarmor_exit_38192__'
                        262     NOP                             
                        264     LOAD_CONST                      3: b'<COAddr>\x07\x00\x00\x1a\xe6\x00\x00\x00\x00\x00\x00\x00\x00\x00\x00\x00\x00\x00\x00\x00'
                        266     CALL                            1
                        274     POP_TOP                         
                        276     RERAISE                         0
                        278     COPY                            3
                        280     POP_EXCEPT                      
                        282     RERAISE                         1
                        284     PUSH_NULL                       
                        286     LOAD_CONST                      8: '__pyarmor_exit_38192__'
                        288     LOAD_CONST                      3: b'<COAddr>\x07\x00\x00\x1a\xe6\x00\x00\x00\x00\x00\x00\x00\x00\x00\x00\x00\x00\x00\x00\x00'
                        290     BUILD_TUPLE                     1
                        292     CALL_FUNCTION_EX                0
                        294     POP_TOP                         
                        296     RETURN_VALUE                    
                    [Exception Table]
                        28 to 102 -> 256 [0] 
                        102 to 184 -> 246 [5] 
                        184 to 226 -> 256 [0] 
                        246 to 256 -> 256 [0] 
                        256 to 278 -> 278 [1] lasti
                [Code]
                    File Name: <frozen multithon.tl.types.bots>
                    Object Name: _bytes
                    Qualified Name: PopularAppBots._bytes
                    Arg Count: 1
                    Pos Only Arg Count: 0
                    KW Only Arg Count: 0
                    Stack Size: 12
                    Flags: 0x20000003 (CO_OPTIMIZED | CO_NEWLOCALS | CO_PYARMOR_OBFUSCATED)
                    [Names]
                        'join'
                        'struct'
                        'pack'
                        'next_offset'
                        'serialize_bytes'
                        'len'
                        'users'
                    [Locals+Names]
                        'self'
                        '__assert_armored__'
                    [Constants]
                        None
                        '__pyarmor_assert_38193__'
                        '__pyarmor_enter_38194__'
                        b'<COAddr>\x07\x00\x00\x1a\x9a\x01\x00\x00\x00\x00\x00\x00\x00\x00\x00\x00\x00\x00\x00\x00'
                        b''
                        b';\xb1\x91\x19'
                        '<I'
                        False
                        0
                        1
                        b'\x15\xc4\xb5\x1c'
                        '<i'
                        [Code]
                            File Name: <frozen multithon.tl.types.bots>
                            Object Name: <genexpr>
                            Qualified Name: PopularAppBots._bytes.<locals>.<genexpr>
                            Arg Count: 1
                            Pos Only Arg Count: 0
                            KW Only Arg Count: 0
                            Stack Size: 3
                            Flags: 0x00000033 (CO_OPTIMIZED | CO_NEWLOCALS | CO_NESTED | CO_GENERATOR)
                            [Names]
                                '_bytes'
                            [Locals+Names]
                                '.0'
                                '_var_var_3'
                            [Constants]
                                None
                            [Disassembly]
                                0       RETURN_GENERATOR                
                                2       POP_TOP                         
                                4       RESUME                          0
                                6       LOAD_FAST                       0: .0
                                8       FOR_ITER                        20 (to 50)
                                12      STORE_FAST                      1: _var_var_3
                                14      LOAD_FAST                       1: _var_var_3
                                16      LOAD_ATTR                       1: _bytes
                                36      CALL                            0
                                44      YIELD_VALUE                     1
                                46      RESUME                          1
                                48      POP_TOP                         
                                50      JUMP_BACKWARD                   22 (to 8)
                                52      END_FOR                         
                                54      RETURN_CONST                    0: None
                                56      CALL_INTRINSIC_1                3 (INTRINSIC_STOPITERATION_ERROR)
                                58      RERAISE                         1
                            [Exception Table]
                                4 to 56 -> 56 [0] lasti
                        '__pyarmor_exit_38195__'
                    [Disassembly]
                        0       NOP                             
                        2       NOP                             
                        4       PUSH_NULL                       
                        6       LOAD_CONST                      2: '__pyarmor_enter_38194__'
                        8       LOAD_CONST                      3: b'<COAddr>\x07\x00\x00\x1a\x9a\x01\x00\x00\x00\x00\x00\x00\x00\x00\x00\x00\x00\x00\x00\x00'
                        10      BUILD_TUPLE                     1
                        12      CALL_FUNCTION_EX                0
                        14      POP_TOP                         
                        16      RESUME                          0
                        18      NOP                             
                        20      NOP                             
                        22      NOP                             
                        24      NOP                             
                        26      NOP                             
                        28      LOAD_CONST                      4: b''
                        30      LOAD_ATTR                       1: join
                        50      LOAD_CONST                      5: b';\xb1\x91\x19'
                        52      LOAD_GLOBAL                     3: NULL + struct
                        62      LOAD_ATTR                       4: pack
                        82      LOAD_CONST                      6: '<I'
                        84      LOAD_FAST                       0: self
                        86      LOAD_ATTR                       6: next_offset
                        106     POP_JUMP_IF_NONE                14 (to 136)
                        108     LOAD_FAST                       0: self
                        110     LOAD_ATTR                       6: next_offset
                        130     LOAD_CONST                      7: False
                        132     IS_OP                           0 (is)
                        134     POP_JUMP_IF_FALSE               2 (to 140)
                        136     LOAD_CONST                      8: 0
                        138     JUMP_FORWARD                    1 (to 142)
                        140     LOAD_CONST                      9: 1
                        142     CALL                            2
                        150     LOAD_FAST                       0: self
                        152     LOAD_ATTR                       6: next_offset
                        172     POP_JUMP_IF_NONE                14 (to 202)
                        174     LOAD_FAST                       0: self
                        176     LOAD_ATTR                       6: next_offset
                        196     LOAD_CONST                      7: False
                        198     IS_OP                           0 (is)
                        200     POP_JUMP_IF_FALSE               2 (to 206)
                        202     LOAD_CONST                      4: b''
                        204     JUMP_FORWARD                    26 (to 258)
                        206     LOAD_FAST                       0: self
                        208     LOAD_ATTR                       9: serialize_bytes
                        228     LOAD_FAST                       0: self
                        230     LOAD_ATTR                       6: next_offset
                        250     CALL                            1
                        258     LOAD_CONST                      10: b'\x15\xc4\xb5\x1c'
                        260     LOAD_GLOBAL                     3: NULL + struct
                        270     LOAD_ATTR                       4: pack
                        290     LOAD_CONST                      11: '<i'
                        292     LOAD_GLOBAL                     11: NULL + len
                        302     LOAD_FAST                       0: self
                        304     LOAD_ATTR                       12: users
                        324     CALL                            1
                        332     CALL                            2
                        340     LOAD_CONST                      4: b''
                        342     LOAD_ATTR                       1: join
                        362     LOAD_CONST                      12: <CODE> <genexpr>
                        364     MAKE_FUNCTION                   0
                        366     LOAD_FAST                       0: self
                        368     LOAD_ATTR                       12: users
                        388     GET_ITER                        
                        390     CALL                            0
                        398     CALL                            1
                        406     BUILD_TUPLE                     6
                        408     CALL                            1
                        416     NOP                             
                        418     NOP                             
                        420     NOP                             
                        422     JUMP_FORWARD                    20 (to 464)
                        424     CALL                            1
                        432     POP_TOP                         
                        434     RETURN_VALUE                    
                        436     PUSH_EXC_INFO                   
                        438     PUSH_NULL                       
                        440     LOAD_CONST                      13: '__pyarmor_exit_38195__'
                        442     NOP                             
                        444     LOAD_CONST                      3: b'<COAddr>\x07\x00\x00\x1a\x9a\x01\x00\x00\x00\x00\x00\x00\x00\x00\x00\x00\x00\x00\x00\x00'
                        446     CALL                            1
                        454     POP_TOP                         
                        456     RERAISE                         0
                        458     COPY                            3
                        460     POP_EXCEPT                      
                        462     RERAISE                         1
                        464     PUSH_NULL                       
                        466     LOAD_CONST                      13: '__pyarmor_exit_38195__'
                        468     LOAD_CONST                      3: b'<COAddr>\x07\x00\x00\x1a\x9a\x01\x00\x00\x00\x00\x00\x00\x00\x00\x00\x00\x00\x00\x00\x00'
                        470     BUILD_TUPLE                     1
                        472     CALL_FUNCTION_EX                0
                        474     POP_TOP                         
                        476     RETURN_VALUE                    
                    [Exception Table]
                        28 to 416 -> 436 [0] 
                        436 to 458 -> 458 [1] lasti
                [Code]
                    File Name: <frozen multithon.tl.types.bots>
                    Object Name: from_reader
                    Qualified Name: PopularAppBots.from_reader
                    Arg Count: 2
                    Pos Only Arg Count: 0
                    KW Only Arg Count: 0
                    Stack Size: 5
                    Flags: 0x20000003 (CO_OPTIMIZED | CO_NEWLOCALS | CO_PYARMOR_OBFUSCATED)
                    [Names]
                        'read_int'
                        'tgread_string'
                        'range'
                        'tgread_object'
                        'append'
                    [Locals+Names]
                        'cls'
                        'reader'
                        '__assert_armored__'
                        '_var_var_4'
                        '_var_var_5'
                        '_var_var_6'
                        '_var_var_7'
                        '_var_var_8'
                    [Constants]
                        None
                        '__pyarmor_assert_38196__'
                        '__pyarmor_enter_38197__'
                        b'<COAddr>\x07\x00\x00\x1a\x1a\x01\x00\x00\x00\x00\x00\x00\x00\x00\x00\x00\x00\x00\x00\x00'
                        1
                        (
                            'users'
                            'next_offset'
                        )
                        '__pyarmor_exit_38198__'
                    [Disassembly]
                        0       NOP                             
                        2       NOP                             
                        4       PUSH_NULL                       
                        6       LOAD_CONST                      2: '__pyarmor_enter_38197__'
                        8       LOAD_CONST                      3: b'<COAddr>\x07\x00\x00\x1a\x1a\x01\x00\x00\x00\x00\x00\x00\x00\x00\x00\x00\x00\x00\x00\x00'
                        10      BUILD_TUPLE                     1
                        12      CALL_FUNCTION_EX                0
                        14      POP_TOP                         
                        16      RESUME                          0
                        18      NOP                             
                        20      NOP                             
                        22      NOP                             
                        24      NOP                             
                        26      NOP                             
                        28      LOAD_FAST                       1: reader
                        30      LOAD_ATTR                       1: read_int
                        50      CALL                            0
                        58      STORE_FAST                      3: _var_var_4
                        60      LOAD_FAST                       3: _var_var_4
                        62      LOAD_CONST                      4: 1
                        64      BINARY_OP                       1 (&)
                        68      POP_JUMP_IF_FALSE               17 (to 104)
                        70      LOAD_FAST                       1: reader
                        72      LOAD_ATTR                       3: tgread_string
                        92      CALL                            0
                        100     STORE_FAST                      4: _var_var_5
                        102     JUMP_FORWARD                    2 (to 108)
                        104     LOAD_CONST                      0: None
                        106     STORE_FAST                      4: _var_var_5
                        108     LOAD_FAST                       1: reader
                        110     LOAD_ATTR                       1: read_int
                        130     CALL                            0
                        138     POP_TOP                         
                        140     BUILD_LIST                      0
                        142     STORE_FAST                      5: _var_var_6
                        144     LOAD_GLOBAL                     5: NULL + range
                        154     LOAD_FAST                       1: reader
                        156     LOAD_ATTR                       1: read_int
                        176     CALL                            0
                        184     CALL                            1
                        192     GET_ITER                        
                        194     FOR_ITER                        35 (to 266)
                        198     STORE_FAST                      6: _var_var_7
                        200     LOAD_FAST                       1: reader
                        202     LOAD_ATTR                       7: tgread_object
                        222     CALL                            0
                        230     STORE_FAST                      7: _var_var_8
                        232     LOAD_FAST                       5: _var_var_6
                        234     LOAD_ATTR                       9: append
                        254     LOAD_FAST                       7: _var_var_8
                        256     CALL                            1
                        264     POP_TOP                         
                        266     JUMP_BACKWARD                   37 (to 194)
                        268     END_FOR                         
                        270     PUSH_NULL                       
                        272     LOAD_FAST                       0: cls
                        274     LOAD_FAST                       5: _var_var_6
                        276     LOAD_FAST                       4: _var_var_5
                        278     KW_NAMES                        5: ('users', 'next_offset')
                        280     CALL                            2
                        288     NOP                             
                        290     NOP                             
                        292     NOP                             
                        294     JUMP_FORWARD                    20 (to 336)
                        296     CALL                            1
                        304     POP_TOP                         
                        306     RETURN_VALUE                    
                        308     PUSH_EXC_INFO                   
                        310     PUSH_NULL                       
                        312     LOAD_CONST                      6: '__pyarmor_exit_38198__'
                        314     NOP                             
                        316     LOAD_CONST                      3: b'<COAddr>\x07\x00\x00\x1a\x1a\x01\x00\x00\x00\x00\x00\x00\x00\x00\x00\x00\x00\x00\x00\x00'
                        318     CALL                            1
                        326     POP_TOP                         
                        328     RERAISE                         0
                        330     COPY                            3
                        332     POP_EXCEPT                      
                        334     RERAISE                         1
                        336     PUSH_NULL                       
                        338     LOAD_CONST                      6: '__pyarmor_exit_38198__'
                        340     LOAD_CONST                      3: b'<COAddr>\x07\x00\x00\x1a\x1a\x01\x00\x00\x00\x00\x00\x00\x00\x00\x00\x00\x00\x00\x00\x00'
                        342     BUILD_TUPLE                     1
                        344     CALL_FUNCTION_EX                0
                        346     POP_TOP                         
                        348     RETURN_VALUE                    
                    [Exception Table]
                        28 to 288 -> 308 [0] 
                        308 to 330 -> 330 [1] lasti
                '__pyarmor_exit_38186__'
                (
                    None
                )
            [Disassembly]
                0       NOP                             
                2       LOAD_NAME                       0: __name__
                4       STORE_NAME                      1: __module__
                6       LOAD_CONST                      0: 'PopularAppBots'
                8       STORE_NAME                      2: __qualname__
                10      NOP                             
                12      PUSH_NULL                       
                14      LOAD_CONST                      2: '__pyarmor_enter_38185__'
                16      LOAD_CONST                      3: b'<COAddr>\x05\x00\x00"X\x00\x00\x00\x00\x00\x00\x00\x00\x00\x00\x00\x00\x00\x00\x00'
                18      BUILD_TUPLE                     1
                20      CALL_FUNCTION_EX                0
                22      POP_TOP                         
                24      RESUME                          0
                26      NOP                             
                28      NOP                             
                30      NOP                             
                32      NOP                             
                34      NOP                             
                36      LOAD_CONST                      4: 428978491
                38      STORE_NAME                      4: CONSTRUCTOR_ID
                40      LOAD_CONST                      5: 2070199933
                42      STORE_NAME                      5: SUBCLASS_OF_ID
                44      LOAD_CONST                      15: (None,)
                46      LOAD_CONST                      7: 'users'
                48      LOAD_NAME                       6: List
                50      LOAD_CONST                      8: 'TypeUser'
                52      BINARY_SUBSCR                   
                56      LOAD_CONST                      9: 'next_offset'
                58      LOAD_NAME                       7: Optional
                60      LOAD_NAME                       8: str
                62      BINARY_SUBSCR                   
                66      BUILD_TUPLE                     4
                68      LOAD_CONST                      10: <CODE> __init__
                70      MAKE_FUNCTION                   5
                72      STORE_NAME                      9: __init__
                74      LOAD_CONST                      11: <CODE> to_dict
                76      MAKE_FUNCTION                   0
                78      STORE_NAME                      10: to_dict
                80      LOAD_CONST                      12: <CODE> _bytes
                82      MAKE_FUNCTION                   0
                84      STORE_NAME                      11: _bytes
                86      LOAD_NAME                       12: classmethod
                88      LOAD_CONST                      13: <CODE> from_reader
                90      MAKE_FUNCTION                   0
                92      CALL                            0
                100     STORE_NAME                      13: from_reader
                102     LOAD_CONST                      6: None
                104     NOP                             
                106     NOP                             
                108     NOP                             
                110     JUMP_FORWARD                    19 (to 150)
                118     POP_TOP                         
                120     RETURN_CONST                    6: None
                122     PUSH_EXC_INFO                   
                124     PUSH_NULL                       
                126     LOAD_CONST                      14: '__pyarmor_exit_38186__'
                128     NOP                             
                130     LOAD_CONST                      3: b'<COAddr>\x05\x00\x00"X\x00\x00\x00\x00\x00\x00\x00\x00\x00\x00\x00\x00\x00\x00\x00'
                132     CALL                            1
                140     POP_TOP                         
                142     RERAISE                         0
                144     COPY                            3
                146     POP_EXCEPT                      
                148     RERAISE                         1
                150     PUSH_NULL                       
                152     LOAD_CONST                      14: '__pyarmor_exit_38186__'
                154     LOAD_CONST                      3: b'<COAddr>\x05\x00\x00"X\x00\x00\x00\x00\x00\x00\x00\x00\x00\x00\x00\x00\x00\x00\x00'
                156     BUILD_TUPLE                     1
                158     CALL_FUNCTION_EX                0
                160     POP_TOP                         
                162     RETURN_VALUE                    
            [Exception Table]
                36 to 102 -> 122 [0] 
                122 to 144 -> 144 [1] lasti
        'PopularAppBots'
        [Code]
            File Name: <frozen multithon.tl.types.bots>
            Object Name: PreviewInfo
            Qualified Name: PreviewInfo
            Arg Count: 0
            Pos Only Arg Count: 0
            KW Only Arg Count: 0
            Stack Size: 5
            Flags: 0x20000000 (CO_PYARMOR_OBFUSCATED)
            [Names]
                '__name__'
                '__module__'
                '__qualname__'
                '__assert_armored__'
                'CONSTRUCTOR_ID'
                'SUBCLASS_OF_ID'
                'List'
                'str'
                '__init__'
                'to_dict'
                '_bytes'
                'classmethod'
                'from_reader'
            [Locals+Names]
            [Constants]
                'PreviewInfo'
                '__pyarmor_assert_38199__'
                '__pyarmor_enter_38200__'
                b'<COAddr>\x07\x00\x00"b\x00\x00\x00\x00\x00\x00\x00\x00\x00\x00\x00\x00\x00\x00\x00'
                212278628
                0xF0C27F35
                'media'
                'TypeBotPreviewMedia'   # b'\x81\xd6\x01\x036\xd8\xb1\xc6+\xe8\x08\xd6e\xe9\xef\xa8\nY\xb2\xa6'
                'lang_codes'
                [Code]
                    File Name: <frozen multithon.tl.types.bots>
                    Object Name: __init__
                    Qualified Name: PreviewInfo.__init__
                    Arg Count: 3
                    Pos Only Arg Count: 0
                    KW Only Arg Count: 0
                    Stack Size: 5
                    Flags: 0x20000003 (CO_OPTIMIZED | CO_NEWLOCALS | CO_PYARMOR_OBFUSCATED)
                    [Names]
                        'media'
                        'lang_codes'
                    [Locals+Names]
                        'self'
                        'media'
                        'lang_codes'
                        '__assert_armored__'
                    [Constants]
                        '\n        Constructor for bots.PreviewInfo: Instance of PreviewInfo.\n        '
                        '__pyarmor_assert_38202__'
                        '__pyarmor_enter_38203__'
                        b'<COAddr>\x07\x00\x00\x1a2\x00\x00\x00\x00\x00\x00\x00\x00\x00\x00\x00\x00\x00\x00\x00'
                        '__pyarmor_exit_38204__'
                        None
                    [Disassembly]
                        0       NOP                             
                        2       NOP                             
                        4       PUSH_NULL                       
                        6       LOAD_CONST                      2: '__pyarmor_enter_38203__'
                        8       LOAD_CONST                      3: b'<COAddr>\x07\x00\x00\x1a2\x00\x00\x00\x00\x00\x00\x00\x00\x00\x00\x00\x00\x00\x00\x00'
                        10      BUILD_TUPLE                     1
                        12      CALL_FUNCTION_EX                0
                        14      POP_TOP                         
                        16      RESUME                          0
                        18      NOP                             
                        20      NOP                             
                        22      NOP                             
                        24      NOP                             
                        26      NOP                             
                        28      LOAD_FAST                       1: media
                        30      LOAD_FAST                       0: self
                        32      STORE_ATTR                      0: media
                        42      LOAD_FAST                       2: lang_codes
                        44      LOAD_FAST                       0: self
                        46      STORE_ATTR                      1: lang_codes
                        56      LOAD_CONST                      5: None
                        58      NOP                             
                        60      NOP                             
                        62      NOP                             
                        64      JUMP_FORWARD                    19 (to 104)
                        72      POP_TOP                         
                        74      RETURN_CONST                    5: None
                        76      PUSH_EXC_INFO                   
                        78      PUSH_NULL                       
                        80      LOAD_CONST                      4: '__pyarmor_exit_38204__'
                        82      NOP                             
                        84      LOAD_CONST                      3: b'<COAddr>\x07\x00\x00\x1a2\x00\x00\x00\x00\x00\x00\x00\x00\x00\x00\x00\x00\x00\x00\x00'
                        86      CALL                            1
                        94      POP_TOP                         
                        96      RERAISE                         0
                        98      COPY                            3
                        100     POP_EXCEPT                      
                        102     RERAISE                         1
                        104     PUSH_NULL                       
                        106     LOAD_CONST                      4: '__pyarmor_exit_38204__'
                        108     LOAD_CONST                      3: b'<COAddr>\x07\x00\x00\x1a2\x00\x00\x00\x00\x00\x00\x00\x00\x00\x00\x00\x00\x00\x00\x00'
                        110     BUILD_TUPLE                     1
                        112     CALL_FUNCTION_EX                0
                        114     POP_TOP                         
                        116     RETURN_VALUE                    
                    [Exception Table]
                        28 to 56 -> 76 [0] 
                        76 to 98 -> 98 [1] lasti
                [Code]
                    File Name: <frozen multithon.tl.types.bots>
                    Object Name: to_dict
                    Qualified Name: PreviewInfo.to_dict
                    Arg Count: 1
                    Pos Only Arg Count: 0
                    KW Only Arg Count: 0
                    Stack Size: 10
                    Flags: 0x20000003 (CO_OPTIMIZED | CO_NEWLOCALS | CO_PYARMOR_OBFUSCATED)
                    [Names]
                        'media'
                        'isinstance'
                        'TLObject'
                        'to_dict'
                        'lang_codes'
                    [Locals+Names]
                        'self'
                        '__assert_armored__'
                        '_var_var_3'
                    [Constants]
                        None
                        '__pyarmor_assert_38205__'
                        '__pyarmor_enter_38206__'
                        b'<COAddr>\x07\x00\x00\x1a\x08\x01\x00\x00\x00\x00\x00\x00\x00\x00\x00\x00\x00\x00\x00\x00'
                        '_'
                        'PreviewInfo'   # b'\x81\xd2\n\x16%\xf3\xbb\xc52\xf4\x0b\xcf'
                        'media'
                        'lang_codes'   # b'\x81\xee\x19\x1d4\xc5\xbd\xdd\x1f\xff\x1e'
                        '__pyarmor_exit_38207__'
                    [Disassembly]
                        0       NOP                             
                        2       NOP                             
                        4       PUSH_NULL                       
                        6       LOAD_CONST                      2: '__pyarmor_enter_38206__'
                        8       LOAD_CONST                      3: b'<COAddr>\x07\x00\x00\x1a\x08\x01\x00\x00\x00\x00\x00\x00\x00\x00\x00\x00\x00\x00\x00\x00'
                        10      BUILD_TUPLE                     1
                        12      CALL_FUNCTION_EX                0
                        14      POP_TOP                         
                        16      RESUME                          0
                        18      NOP                             
                        20      NOP                             
                        22      NOP                             
                        24      NOP                             
                        26      NOP                             
                        28      LOAD_CONST                      4: '_'
                        30      PUSH_NULL                       
                        32      LOAD_CONST                      1: '__pyarmor_assert_38205__'
                        34      LOAD_CONST                      5: 'PreviewInfo'   # b'\x81\xd2\n\x16%\xf3\xbb\xc52\xf4\x0b\xcf'
                        36      CALL                            1
                        44      LOAD_CONST                      6: 'media'
                        46      LOAD_FAST                       0: self
                        48      LOAD_ATTR                       0: media
                        68      POP_JUMP_IF_NOT_NONE            2 (to 74)
                        70      BUILD_LIST                      0
                        72      JUMP_FORWARD                    57 (to 188)
                        74      LOAD_FAST                       0: self
                        76      LOAD_ATTR                       0: media
                        96      GET_ITER                        
                        98      LOAD_FAST_AND_CLEAR             2: _var_var_3
                        100     SWAP                            2
                        102     BUILD_LIST                      0
                        104     SWAP                            2
                        106     FOR_ITER                        36 (to 180)
                        110     STORE_FAST                      2: _var_var_3
                        112     LOAD_GLOBAL                     3: NULL + isinstance
                        122     LOAD_FAST                       2: _var_var_3
                        124     LOAD_GLOBAL                     4: TLObject
                        134     CALL                            2
                        142     POP_JUMP_IF_FALSE               16 (to 176)
                        144     LOAD_FAST                       2: _var_var_3
                        146     LOAD_ATTR                       7: to_dict
                        166     CALL                            0
                        174     JUMP_FORWARD                    1 (to 178)
                        176     LOAD_FAST                       2: _var_var_3
                        178     LIST_APPEND                     2
                        180     JUMP_BACKWARD                   38 (to 106)
                        182     END_FOR                         
                        184     SWAP                            2
                        186     STORE_FAST                      2: _var_var_3
                        188     PUSH_NULL                       
                        190     LOAD_CONST                      1: '__pyarmor_assert_38205__'
                        192     LOAD_CONST                      7: 'lang_codes'   # b'\x81\xee\x19\x1d4\xc5\xbd\xdd\x1f\xff\x1e'
                        194     CALL                            1
                        202     LOAD_FAST                       0: self
                        204     LOAD_ATTR                       8: lang_codes
                        224     POP_JUMP_IF_NOT_NONE            2 (to 230)
                        226     BUILD_LIST                      0
                        228     JUMP_FORWARD                    14 (to 258)
                        230     LOAD_FAST                       0: self
                        232     LOAD_ATTR                       8: lang_codes
                        252     LOAD_CONST                      0: None
                        254     LOAD_CONST                      0: None
                        256     BINARY_SLICE                    
                        258     BUILD_MAP                       3
                        260     NOP                             
                        262     NOP                             
                        264     NOP                             
                        266     JUMP_FORWARD                    25 (to 318)
                        268     CALL                            1
                        276     POP_TOP                         
                        278     RETURN_VALUE                    
                        280     SWAP                            2
                        282     POP_TOP                         
                        284     SWAP                            2
                        286     STORE_FAST                      2: _var_var_3
                        288     RERAISE                         0
                        290     PUSH_EXC_INFO                   
                        292     PUSH_NULL                       
                        294     LOAD_CONST                      8: '__pyarmor_exit_38207__'
                        296     NOP                             
                        298     LOAD_CONST                      3: b'<COAddr>\x07\x00\x00\x1a\x08\x01\x00\x00\x00\x00\x00\x00\x00\x00\x00\x00\x00\x00\x00\x00'
                        300     CALL                            1
                        308     POP_TOP                         
                        310     RERAISE                         0
                        312     COPY                            3
                        314     POP_EXCEPT                      
                        316     RERAISE                         1
                        318     PUSH_NULL                       
                        320     LOAD_CONST                      8: '__pyarmor_exit_38207__'
                        322     LOAD_CONST                      3: b'<COAddr>\x07\x00\x00\x1a\x08\x01\x00\x00\x00\x00\x00\x00\x00\x00\x00\x00\x00\x00\x00\x00'
                        324     BUILD_TUPLE                     1
                        326     CALL_FUNCTION_EX                0
                        328     POP_TOP                         
                        330     RETURN_VALUE                    
                    [Exception Table]
                        28 to 102 -> 290 [0] 
                        102 to 184 -> 280 [5] 
                        184 to 260 -> 290 [0] 
                        280 to 290 -> 290 [0] 
                        290 to 312 -> 312 [1] lasti
                [Code]
                    File Name: <frozen multithon.tl.types.bots>
                    Object Name: _bytes
                    Qualified Name: PreviewInfo._bytes
                    Arg Count: 1
                    Pos Only Arg Count: 0
                    KW Only Arg Count: 0
                    Stack Size: 13
                    Flags: 0x20000003 (CO_OPTIMIZED | CO_NEWLOCALS | CO_PYARMOR_OBFUSCATED)
                    [Names]
                        'join'
                        'struct'
                        'pack'
                        'len'
                        'media'
                        'lang_codes'
                    [Locals+Names]
                        'self'
                        '__assert_armored__'
                    [Constants]
                        None
                        '__pyarmor_assert_38208__'
                        '__pyarmor_enter_38209__'
                        b'<COAddr>\x05\x00\x00\x1cd\x01\x00\x00\x00\x00\x00\x00\x00\x00\x00\x00\x00\x00\x00\x00'
                        b''
                        b'd\x1d\xa7\x0c'
                        b'\x15\xc4\xb5\x1c'
                        '<i'
                        [Code]
                            File Name: <frozen multithon.tl.types.bots>
                            Object Name: <genexpr>
                            Qualified Name: PreviewInfo._bytes.<locals>.<genexpr>
                            Arg Count: 1
                            Pos Only Arg Count: 0
                            KW Only Arg Count: 0
                            Stack Size: 3
                            Flags: 0x00000033 (CO_OPTIMIZED | CO_NEWLOCALS | CO_NESTED | CO_GENERATOR)
                            [Names]
                                '_bytes'
                            [Locals+Names]
                                '.0'
                                '_var_var_3'
                            [Constants]
                                None
                            [Disassembly]
                                0       RETURN_GENERATOR                
                                2       POP_TOP                         
                                4       RESUME                          0
                                6       LOAD_FAST                       0: .0
                                8       FOR_ITER                        20 (to 50)
                                12      STORE_FAST                      1: _var_var_3
                                14      LOAD_FAST                       1: _var_var_3
                                16      LOAD_ATTR                       1: _bytes
                                36      CALL                            0
                                44      YIELD_VALUE                     1
                                46      RESUME                          1
                                48      POP_TOP                         
                                50      JUMP_BACKWARD                   22 (to 8)
                                52      END_FOR                         
                                54      RETURN_CONST                    0: None
                                56      CALL_INTRINSIC_1                3 (INTRINSIC_STOPITERATION_ERROR)
                                58      RERAISE                         1
                            [Exception Table]
                                4 to 56 -> 56 [0] lasti
                        [Code]
                            File Name: <frozen multithon.tl.types.bots>
                            Object Name: <genexpr>
                            Qualified Name: PreviewInfo._bytes.<locals>.<genexpr>
                            Arg Count: 1
                            Pos Only Arg Count: 0
                            KW Only Arg Count: 0
                            Stack Size: 4
                            Flags: 0x00000033 (CO_OPTIMIZED | CO_NEWLOCALS | CO_NESTED | CO_GENERATOR)
                            [Names]
                                'serialize_bytes'
                            [Locals+Names]
                                '.0'
                                '_var_var_3'
                                'self'
                            [Constants]
                                None
                            [Disassembly]
                                0       COPY_FREE_VARS                  1
                                2       RETURN_GENERATOR                
                                4       POP_TOP                         
                                6       RESUME                          0
                                8       LOAD_FAST                       0: .0
                                10      FOR_ITER                        21 (to 54)
                                14      STORE_FAST                      1: _var_var_3
                                16      LOAD_DEREF                      2: self
                                18      LOAD_ATTR                       1: serialize_bytes
                                38      LOAD_FAST                       1: _var_var_3
                                40      CALL                            1
                                48      YIELD_VALUE                     1
                                50      RESUME                          1
                                52      POP_TOP                         
                                54      JUMP_BACKWARD                   23 (to 10)
                                56      END_FOR                         
                                58      RETURN_CONST                    0: None
                                60      CALL_INTRINSIC_1                3 (INTRINSIC_STOPITERATION_ERROR)
                                62      RERAISE                         1
                            [Exception Table]
                                6 to 60 -> 60 [0] lasti
                        '__pyarmor_exit_38210__'
                    [Disassembly]
                        0       MAKE_CELL                       0: self
                        2       NOP                             
                        4       NOP                             
                        6       PUSH_NULL                       
                        8       LOAD_CONST                      2: '__pyarmor_enter_38209__'
                        10      LOAD_CONST                      3: b'<COAddr>\x05\x00\x00\x1cd\x01\x00\x00\x00\x00\x00\x00\x00\x00\x00\x00\x00\x00\x00\x00'
                        12      BUILD_TUPLE                     1
                        14      CALL_FUNCTION_EX                0
                        16      POP_TOP                         
                        18      RESUME                          0
                        20      NOP                             
                        22      NOP                             
                        24      NOP                             
                        26      NOP                             
                        28      NOP                             
                        30      LOAD_CONST                      4: b''
                        32      LOAD_ATTR                       1: join
                        52      LOAD_CONST                      5: b'd\x1d\xa7\x0c'
                        54      LOAD_CONST                      6: b'\x15\xc4\xb5\x1c'
                        56      LOAD_GLOBAL                     3: NULL + struct
                        66      LOAD_ATTR                       4: pack
                        86      LOAD_CONST                      7: '<i'
                        88      LOAD_GLOBAL                     7: NULL + len
                        98      LOAD_DEREF                      0: self
                        100     LOAD_ATTR                       8: media
                        120     CALL                            1
                        128     CALL                            2
                        136     LOAD_CONST                      4: b''
                        138     LOAD_ATTR                       1: join
                        158     LOAD_CONST                      8: <CODE> <genexpr>
                        160     MAKE_FUNCTION                   0
                        162     LOAD_DEREF                      0: self
                        164     LOAD_ATTR                       8: media
                        184     GET_ITER                        
                        186     CALL                            0
                        194     CALL                            1
                        202     LOAD_CONST                      6: b'\x15\xc4\xb5\x1c'
                        204     LOAD_GLOBAL                     3: NULL + struct
                        214     LOAD_ATTR                       4: pack
                        234     LOAD_CONST                      7: '<i'
                        236     LOAD_GLOBAL                     7: NULL + len
                        246     LOAD_DEREF                      0: self
                        248     LOAD_ATTR                       10: lang_codes
                        268     CALL                            1
                        276     CALL                            2
                        284     LOAD_CONST                      4: b''
                        286     LOAD_ATTR                       1: join
                        306     LOAD_CLOSURE                    0: self
                        308     BUILD_TUPLE                     1
                        310     LOAD_CONST                      9: <CODE> <genexpr>
                        312     MAKE_FUNCTION                   8
                        314     LOAD_DEREF                      0: self
                        316     LOAD_ATTR                       10: lang_codes
                        336     GET_ITER                        
                        338     CALL                            0
                        346     CALL                            1
                        354     BUILD_TUPLE                     7
                        356     CALL                            1
                        364     NOP                             
                        366     NOP                             
                        368     NOP                             
                        370     JUMP_FORWARD                    20 (to 412)
                        372     CALL                            1
                        380     POP_TOP                         
                        382     RETURN_VALUE                    
                        384     PUSH_EXC_INFO                   
                        386     PUSH_NULL                       
                        388     LOAD_CONST                      10: '__pyarmor_exit_38210__'
                        390     NOP                             
                        392     LOAD_CONST                      3: b'<COAddr>\x05\x00\x00\x1cd\x01\x00\x00\x00\x00\x00\x00\x00\x00\x00\x00\x00\x00\x00\x00'
                        394     CALL                            1
                        402     POP_TOP                         
                        404     RERAISE                         0
                        406     COPY                            3
                        408     POP_EXCEPT                      
                        410     RERAISE                         1
                        412     PUSH_NULL                       
                        414     LOAD_CONST                      10: '__pyarmor_exit_38210__'
                        416     LOAD_CONST                      3: b'<COAddr>\x05\x00\x00\x1cd\x01\x00\x00\x00\x00\x00\x00\x00\x00\x00\x00\x00\x00\x00\x00'
                        418     BUILD_TUPLE                     1
                        420     CALL_FUNCTION_EX                0
                        422     POP_TOP                         
                        424     RETURN_VALUE                    
                    [Exception Table]
                        30 to 364 -> 384 [0] 
                        384 to 406 -> 406 [1] lasti
                [Code]
                    File Name: <frozen multithon.tl.types.bots>
                    Object Name: from_reader
                    Qualified Name: PreviewInfo.from_reader
                    Arg Count: 2
                    Pos Only Arg Count: 0
                    KW Only Arg Count: 0
                    Stack Size: 5
                    Flags: 0x20000003 (CO_OPTIMIZED | CO_NEWLOCALS | CO_PYARMOR_OBFUSCATED)
                    [Names]
                        'read_int'
                        'range'
                        'tgread_object'
                        'append'
                        'tgread_string'
                    [Locals+Names]
                        'cls'
                        'reader'
                        '__assert_armored__'
                        '_var_var_9'
                        '_var_var_7'
                        '_var_var_8'
                        '_var_var_10'
                    [Constants]
                        None
                        '__pyarmor_assert_38211__'
                        '__pyarmor_enter_38212__'
                        b'<COAddr>\x07\x00\x00\x1al\x01\x00\x00\x00\x00\x00\x00\x00\x00\x00\x00\x00\x00\x00\x00'
                        (
                            'media'
                            'lang_codes'
                        )
                        '__pyarmor_exit_38213__'
                    [Disassembly]
                        0       NOP                             
                        2       NOP                             
                        4       PUSH_NULL                       
                        6       LOAD_CONST                      2: '__pyarmor_enter_38212__'
                        8       LOAD_CONST                      3: b'<COAddr>\x07\x00\x00\x1al\x01\x00\x00\x00\x00\x00\x00\x00\x00\x00\x00\x00\x00\x00\x00'
                        10      BUILD_TUPLE                     1
                        12      CALL_FUNCTION_EX                0
                        14      POP_TOP                         
                        16      RESUME                          0
                        18      NOP                             
                        20      NOP                             
                        22      NOP                             
                        24      NOP                             
                        26      NOP                             
                        28      LOAD_FAST                       1: reader
                        30      LOAD_ATTR                       1: read_int
                        50      CALL                            0
                        58      POP_TOP                         
                        60      BUILD_LIST                      0
                        62      STORE_FAST                      3: _var_var_9
                        64      LOAD_GLOBAL                     3: NULL + range
                        74      LOAD_FAST                       1: reader
                        76      LOAD_ATTR                       1: read_int
                        96      CALL                            0
                        104     CALL                            1
                        112     GET_ITER                        
                        114     FOR_ITER                        35 (to 186)
                        118     STORE_FAST                      4: _var_var_7
                        120     LOAD_FAST                       1: reader
                        122     LOAD_ATTR                       5: tgread_object
                        142     CALL                            0
                        150     STORE_FAST                      5: _var_var_8
                        152     LOAD_FAST                       3: _var_var_9
                        154     LOAD_ATTR                       7: append
                        174     LOAD_FAST                       5: _var_var_8
                        176     CALL                            1
                        184     POP_TOP                         
                        186     JUMP_BACKWARD                   37 (to 114)
                        188     END_FOR                         
                        190     LOAD_FAST                       1: reader
                        192     LOAD_ATTR                       1: read_int
                        212     CALL                            0
                        220     POP_TOP                         
                        222     BUILD_LIST                      0
                        224     STORE_FAST                      6: _var_var_10
                        226     LOAD_GLOBAL                     3: NULL + range
                        236     LOAD_FAST                       1: reader
                        238     LOAD_ATTR                       1: read_int
                        258     CALL                            0
                        266     CALL                            1
                        274     GET_ITER                        
                        276     FOR_ITER                        35 (to 348)
                        280     STORE_FAST                      4: _var_var_7
                        282     LOAD_FAST                       1: reader
                        284     LOAD_ATTR                       9: tgread_string
                        304     CALL                            0
                        312     STORE_FAST                      5: _var_var_8
                        314     LOAD_FAST                       6: _var_var_10
                        316     LOAD_ATTR                       7: append
                        336     LOAD_FAST                       5: _var_var_8
                        338     CALL                            1
                        346     POP_TOP                         
                        348     JUMP_BACKWARD                   37 (to 276)
                        350     END_FOR                         
                        352     PUSH_NULL                       
                        354     LOAD_FAST                       0: cls
                        356     LOAD_FAST                       3: _var_var_9
                        358     LOAD_FAST                       6: _var_var_10
                        360     KW_NAMES                        4: ('media', 'lang_codes')
                        362     CALL                            2
                        370     NOP                             
                        372     NOP                             
                        374     NOP                             
                        376     JUMP_FORWARD                    20 (to 418)
                        378     CALL                            1
                        386     POP_TOP                         
                        388     RETURN_VALUE                    
                        390     PUSH_EXC_INFO                   
                        392     PUSH_NULL                       
                        394     LOAD_CONST                      5: '__pyarmor_exit_38213__'
                        396     NOP                             
                        398     LOAD_CONST                      3: b'<COAddr>\x07\x00\x00\x1al\x01\x00\x00\x00\x00\x00\x00\x00\x00\x00\x00\x00\x00\x00\x00'
                        400     CALL                            1
                        408     POP_TOP                         
                        410     RERAISE                         0
                        412     COPY                            3
                        414     POP_EXCEPT                      
                        416     RERAISE                         1
                        418     PUSH_NULL                       
                        420     LOAD_CONST                      5: '__pyarmor_exit_38213__'
                        422     LOAD_CONST                      3: b'<COAddr>\x07\x00\x00\x1al\x01\x00\x00\x00\x00\x00\x00\x00\x00\x00\x00\x00\x00\x00\x00'
                        424     BUILD_TUPLE                     1
                        426     CALL_FUNCTION_EX                0
                        428     POP_TOP                         
                        430     RETURN_VALUE                    
                    [Exception Table]
                        28 to 370 -> 390 [0] 
                        390 to 412 -> 412 [1] lasti
                '__pyarmor_exit_38201__'
                None
            [Disassembly]
                0       NOP                             
                2       LOAD_NAME                       0: __name__
                4       STORE_NAME                      1: __module__
                6       LOAD_CONST                      0: 'PreviewInfo'
                8       STORE_NAME                      2: __qualname__
                10      NOP                             
                12      PUSH_NULL                       
                14      LOAD_CONST                      2: '__pyarmor_enter_38200__'
                16      LOAD_CONST                      3: b'<COAddr>\x07\x00\x00"b\x00\x00\x00\x00\x00\x00\x00\x00\x00\x00\x00\x00\x00\x00\x00'
                18      BUILD_TUPLE                     1
                20      CALL_FUNCTION_EX                0
                22      POP_TOP                         
                24      RESUME                          0
                26      NOP                             
                28      NOP                             
                30      NOP                             
                32      NOP                             
                34      NOP                             
                36      LOAD_CONST                      4: 212278628
                38      STORE_NAME                      4: CONSTRUCTOR_ID
                40      LOAD_CONST                      5: 0xF0C27F35
                42      STORE_NAME                      5: SUBCLASS_OF_ID
                44      LOAD_CONST                      6: 'media'
                46      LOAD_NAME                       6: List
                48      PUSH_NULL                       
                50      LOAD_CONST                      1: '__pyarmor_assert_38199__'
                52      LOAD_CONST                      7: 'TypeBotPreviewMedia'   # b'\x81\xd6\x01\x036\xd8\xb1\xc6+\xe8\x08\xd6e\xe9\xef\xa8\nY\xb2\xa6'
                54      CALL                            1
                62      BINARY_SUBSCR                   
                66      LOAD_CONST                      8: 'lang_codes'
                68      LOAD_NAME                       6: List
                70      LOAD_NAME                       7: str
                72      BINARY_SUBSCR                   
                76      BUILD_TUPLE                     4
                78      LOAD_CONST                      9: <CODE> __init__
                80      MAKE_FUNCTION                   4
                82      STORE_NAME                      8: __init__
                84      LOAD_CONST                      10: <CODE> to_dict
                86      MAKE_FUNCTION                   0
                88      STORE_NAME                      9: to_dict
                90      LOAD_CONST                      11: <CODE> _bytes
                92      MAKE_FUNCTION                   0
                94      STORE_NAME                      10: _bytes
                96      LOAD_NAME                       11: classmethod
                98      LOAD_CONST                      12: <CODE> from_reader
                100     MAKE_FUNCTION                   0
                102     CALL                            0
                110     STORE_NAME                      12: from_reader
                112     LOAD_CONST                      14: None
                114     NOP                             
                116     NOP                             
                118     NOP                             
                120     JUMP_FORWARD                    19 (to 160)
                128     POP_TOP                         
                130     RETURN_CONST                    14: None
                132     PUSH_EXC_INFO                   
                134     PUSH_NULL                       
                136     LOAD_CONST                      13: '__pyarmor_exit_38201__'
                138     NOP                             
                140     LOAD_CONST                      3: b'<COAddr>\x07\x00\x00"b\x00\x00\x00\x00\x00\x00\x00\x00\x00\x00\x00\x00\x00\x00\x00'
                142     CALL                            1
                150     POP_TOP                         
                152     RERAISE                         0
                154     COPY                            3
                156     POP_EXCEPT                      
                158     RERAISE                         1
                160     PUSH_NULL                       
                162     LOAD_CONST                      13: '__pyarmor_exit_38201__'
                164     LOAD_CONST                      3: b'<COAddr>\x07\x00\x00"b\x00\x00\x00\x00\x00\x00\x00\x00\x00\x00\x00\x00\x00\x00\x00'
                166     BUILD_TUPLE                     1
                168     CALL_FUNCTION_EX                0
                170     POP_TOP                         
                172     RETURN_VALUE                    
            [Exception Table]
                36 to 112 -> 132 [0] 
                132 to 154 -> 154 [1] lasti
        'PreviewInfo'
        '__pyarmor_exit_38168__'
    [Disassembly]
        0       NOP                             
        2       NOP                             
        4       PUSH_NULL                       
        6       LOAD_CONST                      1: '__pyarmor_enter_38167__'
        8       LOAD_CONST                      2: b'<COAddr>\x07\x00\x00\x1a\xba\x00\x00\x00\x00\x00\x00\x00\x00\x00\x00\x00\x00\x00\x00\x00'
        10      BUILD_TUPLE                     1
        12      CALL_FUNCTION_EX                0
        14      POP_TOP                         
        16      RESUME                          0
        18      NOP                             
        20      NOP                             
        22      NOP                             
        24      NOP                             
        26      PUSH_NULL                       
        28      LOAD_CONST                      0: '__pyarmor_assert_38166__'
        30      LOAD_CONST                      3: "File generated by TLObjects' generator. All changes will be ERASED"   # b'\x81\xc4\x11\x1f6\xba\xb9\xd7\x15\xff\x1f\xc1x\xe9\xfc\xc5\rD\xfb\x93\x86\xe4L\xc6\x00l\xb7OG\xf1\x19\xe04W2\x0c\x8c\xc5\xa6`X\xc8\xf4Q\x9d\xdb\x07F9\xeaS\xe8\xc7g\x0f\xe1;\xab\x99\x18Xn\x03rdm!'
        32      CALL                            1
        40      POP_TOP                         
        42      LOAD_CONST                      4: 3
        44      LOAD_CONST                      5: ('TLObject',)
        46      IMPORT_NAME                     1: tl.tlobject
        48      IMPORT_FROM                     2: TLObject
        50      STORE_NAME                      2: TLObject
        52      POP_TOP                         
        54      LOAD_CONST                      6: 0
        56      LOAD_CONST                      7: ('Optional', 'List', 'Union', 'TYPE_CHECKING')
        58      IMPORT_NAME                     3: typing
        60      IMPORT_FROM                     4: Optional
        62      STORE_NAME                      4: Optional
        64      IMPORT_FROM                     5: List
        66      STORE_NAME                      5: List
        68      IMPORT_FROM                     6: Union
        70      STORE_NAME                      6: Union
        72      IMPORT_FROM                     7: TYPE_CHECKING
        74      STORE_NAME                      7: TYPE_CHECKING
        76      POP_TOP                         
        78      LOAD_CONST                      6: 0
        80      LOAD_CONST                      8: None
        82      IMPORT_NAME                     8: os
        84      STORE_NAME                      8: os
        86      LOAD_CONST                      6: 0
        88      LOAD_CONST                      8: None
        90      IMPORT_NAME                     9: struct
        92      STORE_NAME                      9: struct
        94      LOAD_CONST                      6: 0
        96      LOAD_CONST                      9: ('datetime',)
        98      IMPORT_NAME                     10: datetime
        100     IMPORT_FROM                     10: datetime
        102     STORE_NAME                      10: datetime
        104     POP_TOP                         
        106     LOAD_NAME                       7: TYPE_CHECKING
        108     POP_JUMP_IF_FALSE               8 (to 126)
        110     LOAD_CONST                      4: 3
        112     LOAD_CONST                      10: ('TypeBotPreviewMedia', 'TypeUser')
        114     IMPORT_NAME                     11: tl.types
        116     IMPORT_FROM                     12: TypeBotPreviewMedia
        118     STORE_NAME                      12: TypeBotPreviewMedia
        120     IMPORT_FROM                     13: TypeUser
        122     STORE_NAME                      13: TypeUser
        124     POP_TOP                         
        126     PUSH_NULL                       
        128     LOAD_BUILD_CLASS                
        130     LOAD_CONST                      11: <CODE> BotInfo
        132     MAKE_FUNCTION                   0
        134     LOAD_CONST                      12: 'BotInfo'
        136     LOAD_NAME                       2: TLObject
        138     CALL                            3
        146     STORE_NAME                      14: BotInfo
        148     PUSH_NULL                       
        150     LOAD_BUILD_CLASS                
        152     LOAD_CONST                      13: <CODE> PopularAppBots
        154     MAKE_FUNCTION                   0
        156     LOAD_CONST                      14: 'PopularAppBots'
        158     LOAD_NAME                       2: TLObject
        160     CALL                            3
        168     STORE_NAME                      15: PopularAppBots
        170     PUSH_NULL                       
        172     LOAD_BUILD_CLASS                
        174     LOAD_CONST                      15: <CODE> PreviewInfo
        176     MAKE_FUNCTION                   0
        178     LOAD_CONST                      16: 'PreviewInfo'
        180     LOAD_NAME                       2: TLObject
        182     CALL                            3
        190     STORE_NAME                      16: PreviewInfo
        192     LOAD_CONST                      8: None
        194     NOP                             
        196     NOP                             
        198     NOP                             
        200     JUMP_FORWARD                    19 (to 240)
        208     POP_TOP                         
        210     RETURN_CONST                    8: None
        212     PUSH_EXC_INFO                   
        214     PUSH_NULL                       
        216     LOAD_CONST                      17: '__pyarmor_exit_38168__'
        218     NOP                             
        220     LOAD_CONST                      2: b'<COAddr>\x07\x00\x00\x1a\xba\x00\x00\x00\x00\x00\x00\x00\x00\x00\x00\x00\x00\x00\x00\x00'
        222     CALL                            1
        230     POP_TOP                         
        232     RERAISE                         0
        234     COPY                            3
        236     POP_EXCEPT                      
        238     RERAISE                         1
        240     PUSH_NULL                       
        242     LOAD_CONST                      17: '__pyarmor_exit_38168__'
        244     LOAD_CONST                      2: b'<COAddr>\x07\x00\x00\x1a\xba\x00\x00\x00\x00\x00\x00\x00\x00\x00\x00\x00\x00\x00\x00\x00'
        246     BUILD_TUPLE                     1
        248     CALL_FUNCTION_EX                0
        250     POP_TOP                         
        252     RETURN_VALUE                    
    [Exception Table]
        26 to 192 -> 212 [0] 
        212 to 234 -> 234 [1] lasti
