#decoded by lolz.live/mrpenny / t.me/zeus_jackpot
# ================================
# Примечания по Pyarmor:
# - Байт-код и объекты кода Pyarmor соответствуют стандартному Python, но присутствуют специальные вызовы функций среды выполнения (runtime) Pyarmor.
# - Вызовы строк — это не ошибки, а маркеры, которые обрабатываются Pyarmor во время выполнения.
#
# Руководство по декомпиляции (без среды выполнения):
# 1. Игнорируйте зашифрованные байты после `#`; используйте только строку до `#`.
# 2. Удалите "__pyarmor_enter_xxx__"(b"<COAddr>...") и "__pyarmor_leave_xxx__"(b"<COAddr>...") (пролог/эпилог).
# 3. "__pyarmor_assert_xxx__"(A) не является настоящим оператором assert.
#    - Если A — это имя или читаемая строка: замените на A.
#    - Если A — это (X, "Y"): замените на X.Y.
#    - Если A — это (X, "Y", Z): замените на X.Y = Z.
#    - В противном случае: выберите наиболее подходящую/логичную замену.
# 4. "__pyarmor_bcc_xxx__"(...) указывает на машинный (нативный) код; тело функции недоступно. Добавьте комментарий.
# ================================

[Code]
    File Name: <frozen multithon.tl.types.photos>
    Object Name: <module>
    Qualified Name: <module>
    Arg Count: 0
    Pos Only Arg Count: 0
    KW Only Arg Count: 0
    Stack Size: 5
    Flags: 0x20000000 (CO_PYARMOR_OBFUSCATED)
    [Names]
        '__assert_armored__'
        'tl.tlobject'
        'TLObject'
        'typing'
        'Optional'
        'List'
        'Union'
        'TYPE_CHECKING'
        'os'
        'struct'
        'datetime'
        'tl.types'
        'TypePhoto'
        'TypeUser'
        'Photo'
        'Photos'
        'PhotosSlice'
    [Locals+Names]
    [Constants]
        '__pyarmor_assert_40992__'
        '__pyarmor_enter_40993__'
        b'<COAddr>\x05\x00\x00\x1a\xba\x00\x00\x00\x00\x00\x00\x00\x00\x00\x00\x00\x00\x00\x00\x00'
        "File generated by TLObjects' generator. All changes will be ERASED"   # b'\x81\xc4\x11\x1f6\xba\xb9\xd7\x15\xff\x1f\xc1x\xe9\xfc\xc5\rD\xfb\x93\x86\xe4L\xc6\x00l\xb7OG\xf1\x19\xe04W2\x0c\x8c\xc5\xa6`X\xc8\xf4Q\x9d\xdb\x07F9\xeaS\xe8\xc7g\x0f\xe1;\xab\x99\x18Xn\x03rdm!'
        3
        (
            'TLObject'
        )
        0
        (
            'Optional'
            'List'
            'Union'
            'TYPE_CHECKING'
        )
        None
        (
            'datetime'
        )
        (
            'TypePhoto'
            'TypeUser'
        )
        [Code]
            File Name: <frozen multithon.tl.types.photos>
            Object Name: Photo
            Qualified Name: Photo
            Arg Count: 0
            Pos Only Arg Count: 0
            KW Only Arg Count: 0
            Stack Size: 5
            Flags: 0x20000000 (CO_PYARMOR_OBFUSCATED)
            [Names]
                '__name__'
                '__module__'
                '__qualname__'
                '__assert_armored__'
                'CONSTRUCTOR_ID'
                'SUBCLASS_OF_ID'
                'List'
                '__init__'
                'to_dict'
                '_bytes'
                'classmethod'
                'from_reader'
            [Locals+Names]
            [Constants]
                'Photo'
                '__pyarmor_assert_40995__'
                '__pyarmor_enter_40996__'
                b'<COAddr>\x05\x00\x00"\\\x00\x00\x00\x00\x00\x00\x00\x00\x00\x00\x00\x00\x00\x00\x00'
                539045032
                0xC292BD24
                'photo'
                'TypePhoto'   # b'\x81\xd6\x01\x036\xca\xb6\xdd\x0f\xf5'
                'users'
                'TypeUser'
                [Code]
                    File Name: <frozen multithon.tl.types.photos>
                    Object Name: __init__
                    Qualified Name: Photo.__init__
                    Arg Count: 3
                    Pos Only Arg Count: 0
                    KW Only Arg Count: 0
                    Stack Size: 5
                    Flags: 0x20000003 (CO_OPTIMIZED | CO_NEWLOCALS | CO_PYARMOR_OBFUSCATED)
                    [Names]
                        'photo'
                        'users'
                    [Locals+Names]
                        'self'
                        'photo'
                        'users'
                        '__assert_armored__'
                    [Constants]
                        '\n        Constructor for photos.Photo: Instance of Photo.\n        '
                        '__pyarmor_assert_40998__'
                        '__pyarmor_enter_40999__'
                        b'<COAddr>\x05\x00\x00\x1a2\x00\x00\x00\x00\x00\x00\x00\x00\x00\x00\x00\x00\x00\x00\x00'
                        '__pyarmor_exit_41000__'
                        None
                    [Disassembly]
                        0       NOP                             
                        2       NOP                             
                        4       PUSH_NULL                       
                        6       LOAD_CONST                      2: '__pyarmor_enter_40999__'
                        8       LOAD_CONST                      3: b'<COAddr>\x05\x00\x00\x1a2\x00\x00\x00\x00\x00\x00\x00\x00\x00\x00\x00\x00\x00\x00\x00'
                        10      BUILD_TUPLE                     1
                        12      CALL_FUNCTION_EX                0
                        14      POP_TOP                         
                        16      RESUME                          0
                        18      NOP                             
                        20      NOP                             
                        22      NOP                             
                        24      NOP                             
                        26      NOP                             
                        28      LOAD_FAST                       1: photo
                        30      LOAD_FAST                       0: self
                        32      STORE_ATTR                      0: photo
                        42      LOAD_FAST                       2: users
                        44      LOAD_FAST                       0: self
                        46      STORE_ATTR                      1: users
                        56      LOAD_CONST                      5: None
                        58      NOP                             
                        60      NOP                             
                        62      NOP                             
                        64      JUMP_FORWARD                    19 (to 104)
                        72      POP_TOP                         
                        74      RETURN_CONST                    5: None
                        76      PUSH_EXC_INFO                   
                        78      PUSH_NULL                       
                        80      LOAD_CONST                      4: '__pyarmor_exit_41000__'
                        82      NOP                             
                        84      LOAD_CONST                      3: b'<COAddr>\x05\x00\x00\x1a2\x00\x00\x00\x00\x00\x00\x00\x00\x00\x00\x00\x00\x00\x00\x00'
                        86      CALL                            1
                        94      POP_TOP                         
                        96      RERAISE                         0
                        98      COPY                            3
                        100     POP_EXCEPT                      
                        102     RERAISE                         1
                        104     PUSH_NULL                       
                        106     LOAD_CONST                      4: '__pyarmor_exit_41000__'
                        108     LOAD_CONST                      3: b'<COAddr>\x05\x00\x00\x1a2\x00\x00\x00\x00\x00\x00\x00\x00\x00\x00\x00\x00\x00\x00\x00'
                        110     BUILD_TUPLE                     1
                        112     CALL_FUNCTION_EX                0
                        114     POP_TOP                         
                        116     RETURN_VALUE                    
                    [Exception Table]
                        28 to 56 -> 76 [0] 
                        76 to 98 -> 98 [1] lasti
                [Code]
                    File Name: <frozen multithon.tl.types.photos>
                    Object Name: to_dict
                    Qualified Name: Photo.to_dict
                    Arg Count: 1
                    Pos Only Arg Count: 0
                    KW Only Arg Count: 0
                    Stack Size: 9
                    Flags: 0x20000003 (CO_OPTIMIZED | CO_NEWLOCALS | CO_PYARMOR_OBFUSCATED)
                    [Names]
                        'isinstance'
                        'photo'
                        'TLObject'
                        'to_dict'
                        'users'
                    [Locals+Names]
                        'self'
                        '__assert_armored__'
                        '_var_var_0'
                    [Constants]
                        None
                        '__pyarmor_assert_41001__'
                        '__pyarmor_enter_41002__'
                        b'<COAddr>\x07\x00\x00\x1a2\x01\x00\x00\x00\x00\x00\x00\x00\x00\x00\x00\x00\x00\x00\x00'
                        'Photo'
                        (
                            '_'
                            'photo'
                            'users'
                        )
                        '__pyarmor_exit_41003__'
                    [Disassembly]
                        0       NOP                             
                        2       NOP                             
                        4       PUSH_NULL                       
                        6       LOAD_CONST                      2: '__pyarmor_enter_41002__'
                        8       LOAD_CONST                      3: b'<COAddr>\x07\x00\x00\x1a2\x01\x00\x00\x00\x00\x00\x00\x00\x00\x00\x00\x00\x00\x00\x00'
                        10      BUILD_TUPLE                     1
                        12      CALL_FUNCTION_EX                0
                        14      POP_TOP                         
                        16      RESUME                          0
                        18      NOP                             
                        20      NOP                             
                        22      NOP                             
                        24      NOP                             
                        26      NOP                             
                        28      LOAD_CONST                      4: 'Photo'
                        30      LOAD_GLOBAL                     1: NULL + isinstance
                        40      LOAD_FAST                       0: self
                        42      LOAD_ATTR                       2: photo
                        62      LOAD_GLOBAL                     4: TLObject
                        72      CALL                            2
                        80      POP_JUMP_IF_FALSE               26 (to 134)
                        82      LOAD_FAST                       0: self
                        84      LOAD_ATTR                       2: photo
                        104     LOAD_ATTR                       7: to_dict
                        124     CALL                            0
                        132     JUMP_FORWARD                    11 (to 156)
                        134     LOAD_FAST                       0: self
                        136     LOAD_ATTR                       2: photo
                        156     LOAD_FAST                       0: self
                        158     LOAD_ATTR                       8: users
                        178     POP_JUMP_IF_NOT_NONE            2 (to 184)
                        180     BUILD_LIST                      0
                        182     JUMP_FORWARD                    57 (to 298)
                        184     LOAD_FAST                       0: self
                        186     LOAD_ATTR                       8: users
                        206     GET_ITER                        
                        208     LOAD_FAST_AND_CLEAR             2: _var_var_0
                        210     SWAP                            2
                        212     BUILD_LIST                      0
                        214     SWAP                            2
                        216     FOR_ITER                        36 (to 290)
                        220     STORE_FAST                      2: _var_var_0
                        222     LOAD_GLOBAL                     1: NULL + isinstance
                        232     LOAD_FAST                       2: _var_var_0
                        234     LOAD_GLOBAL                     4: TLObject
                        244     CALL                            2
                        252     POP_JUMP_IF_FALSE               16 (to 286)
                        254     LOAD_FAST                       2: _var_var_0
                        256     LOAD_ATTR                       7: to_dict
                        276     CALL                            0
                        284     JUMP_FORWARD                    1 (to 288)
                        286     LOAD_FAST                       2: _var_var_0
                        288     LIST_APPEND                     2
                        290     JUMP_BACKWARD                   38 (to 216)
                        292     END_FOR                         
                        294     SWAP                            2
                        296     STORE_FAST                      2: _var_var_0
                        298     LOAD_CONST                      5: ('_', 'photo', 'users')
                        300     BUILD_CONST_KEY_MAP             3
                        302     NOP                             
                        304     NOP                             
                        306     NOP                             
                        308     JUMP_FORWARD                    25 (to 360)
                        310     CALL                            1
                        318     POP_TOP                         
                        320     RETURN_VALUE                    
                        322     SWAP                            2
                        324     POP_TOP                         
                        326     SWAP                            2
                        328     STORE_FAST                      2: _var_var_0
                        330     RERAISE                         0
                        332     PUSH_EXC_INFO                   
                        334     PUSH_NULL                       
                        336     LOAD_CONST                      6: '__pyarmor_exit_41003__'
                        338     NOP                             
                        340     LOAD_CONST                      3: b'<COAddr>\x07\x00\x00\x1a2\x01\x00\x00\x00\x00\x00\x00\x00\x00\x00\x00\x00\x00\x00\x00'
                        342     CALL                            1
                        350     POP_TOP                         
                        352     RERAISE                         0
                        354     COPY                            3
                        356     POP_EXCEPT                      
                        358     RERAISE                         1
                        360     PUSH_NULL                       
                        362     LOAD_CONST                      6: '__pyarmor_exit_41003__'
                        364     LOAD_CONST                      3: b'<COAddr>\x07\x00\x00\x1a2\x01\x00\x00\x00\x00\x00\x00\x00\x00\x00\x00\x00\x00\x00\x00'
                        366     BUILD_TUPLE                     1
                        368     CALL_FUNCTION_EX                0
                        370     POP_TOP                         
                        372     RETURN_VALUE                    
                    [Exception Table]
                        28 to 212 -> 332 [0] 
                        212 to 294 -> 322 [4] 
                        294 to 302 -> 332 [0] 
                        322 to 332 -> 332 [0] 
                        332 to 354 -> 354 [1] lasti
                [Code]
                    File Name: <frozen multithon.tl.types.photos>
                    Object Name: _bytes
                    Qualified Name: Photo._bytes
                    Arg Count: 1
                    Pos Only Arg Count: 0
                    KW Only Arg Count: 0
                    Stack Size: 11
                    Flags: 0x20000003 (CO_OPTIMIZED | CO_NEWLOCALS | CO_PYARMOR_OBFUSCATED)
                    [Names]
                        'join'
                        'photo'
                        '_bytes'
                        'struct'
                        'pack'
                        'len'
                        'users'
                    [Locals+Names]
                        'self'
                        '__assert_armored__'
                    [Constants]
                        None
                        '__pyarmor_assert_41004__'
                        '__pyarmor_enter_41005__'
                        b'<COAddr>\x07\x00\x00\x1a\xfe\x00\x00\x00\x00\x00\x00\x00\x00\x00\x00\x00\x00\x00\x00\x00'
                        b''
                        b'\xa8,! '
                        b'\x15\xc4\xb5\x1c'
                        '<i'
                        [Code]
                            File Name: <frozen multithon.tl.types.photos>
                            Object Name: <genexpr>
                            Qualified Name: Photo._bytes.<locals>.<genexpr>
                            Arg Count: 1
                            Pos Only Arg Count: 0
                            KW Only Arg Count: 0
                            Stack Size: 3
                            Flags: 0x00000033 (CO_OPTIMIZED | CO_NEWLOCALS | CO_NESTED | CO_GENERATOR)
                            [Names]
                                '_bytes'
                            [Locals+Names]
                                '.0'
                                '_var_var_0'
                            [Constants]
                                None
                            [Disassembly]
                                0       RETURN_GENERATOR                
                                2       POP_TOP                         
                                4       RESUME                          0
                                6       LOAD_FAST                       0: .0
                                8       FOR_ITER                        20 (to 50)
                                12      STORE_FAST                      1: _var_var_0
                                14      LOAD_FAST                       1: _var_var_0
                                16      LOAD_ATTR                       1: _bytes
                                36      CALL                            0
                                44      YIELD_VALUE                     1
                                46      RESUME                          1
                                48      POP_TOP                         
                                50      JUMP_BACKWARD                   22 (to 8)
                                52      END_FOR                         
                                54      RETURN_CONST                    0: None
                                56      CALL_INTRINSIC_1                3 (INTRINSIC_STOPITERATION_ERROR)
                                58      RERAISE                         1
                            [Exception Table]
                                4 to 56 -> 56 [0] lasti
                        '__pyarmor_exit_41006__'
                    [Disassembly]
                        0       NOP                             
                        2       NOP                             
                        4       PUSH_NULL                       
                        6       LOAD_CONST                      2: '__pyarmor_enter_41005__'
                        8       LOAD_CONST                      3: b'<COAddr>\x07\x00\x00\x1a\xfe\x00\x00\x00\x00\x00\x00\x00\x00\x00\x00\x00\x00\x00\x00\x00'
                        10      BUILD_TUPLE                     1
                        12      CALL_FUNCTION_EX                0
                        14      POP_TOP                         
                        16      RESUME                          0
                        18      NOP                             
                        20      NOP                             
                        22      NOP                             
                        24      NOP                             
                        26      NOP                             
                        28      LOAD_CONST                      4: b''
                        30      LOAD_ATTR                       1: join
                        50      LOAD_CONST                      5: b'\xa8,! '
                        52      LOAD_FAST                       0: self
                        54      LOAD_ATTR                       2: photo
                        74      LOAD_ATTR                       5: _bytes
                        94      CALL                            0
                        102     LOAD_CONST                      6: b'\x15\xc4\xb5\x1c'
                        104     LOAD_GLOBAL                     7: NULL + struct
                        114     LOAD_ATTR                       8: pack
                        134     LOAD_CONST                      7: '<i'
                        136     LOAD_GLOBAL                     11: NULL + len
                        146     LOAD_FAST                       0: self
                        148     LOAD_ATTR                       12: users
                        168     CALL                            1
                        176     CALL                            2
                        184     LOAD_CONST                      4: b''
                        186     LOAD_ATTR                       1: join
                        206     LOAD_CONST                      8: <CODE> <genexpr>
                        208     MAKE_FUNCTION                   0
                        210     LOAD_FAST                       0: self
                        212     LOAD_ATTR                       12: users
                        232     GET_ITER                        
                        234     CALL                            0
                        242     CALL                            1
                        250     BUILD_TUPLE                     5
                        252     CALL                            1
                        260     NOP                             
                        262     NOP                             
                        264     NOP                             
                        266     JUMP_FORWARD                    20 (to 308)
                        268     CALL                            1
                        276     POP_TOP                         
                        278     RETURN_VALUE                    
                        280     PUSH_EXC_INFO                   
                        282     PUSH_NULL                       
                        284     LOAD_CONST                      9: '__pyarmor_exit_41006__'
                        286     NOP                             
                        288     LOAD_CONST                      3: b'<COAddr>\x07\x00\x00\x1a\xfe\x00\x00\x00\x00\x00\x00\x00\x00\x00\x00\x00\x00\x00\x00\x00'
                        290     CALL                            1
                        298     POP_TOP                         
                        300     RERAISE                         0
                        302     COPY                            3
                        304     POP_EXCEPT                      
                        306     RERAISE                         1
                        308     PUSH_NULL                       
                        310     LOAD_CONST                      9: '__pyarmor_exit_41006__'
                        312     LOAD_CONST                      3: b'<COAddr>\x07\x00\x00\x1a\xfe\x00\x00\x00\x00\x00\x00\x00\x00\x00\x00\x00\x00\x00\x00\x00'
                        314     BUILD_TUPLE                     1
                        316     CALL_FUNCTION_EX                0
                        318     POP_TOP                         
                        320     RETURN_VALUE                    
                    [Exception Table]
                        28 to 260 -> 280 [0] 
                        280 to 302 -> 302 [1] lasti
                [Code]
                    File Name: <frozen multithon.tl.types.photos>
                    Object Name: from_reader
                    Qualified Name: Photo.from_reader
                    Arg Count: 2
                    Pos Only Arg Count: 0
                    KW Only Arg Count: 0
                    Stack Size: 5
                    Flags: 0x20000003 (CO_OPTIMIZED | CO_NEWLOCALS | CO_PYARMOR_OBFUSCATED)
                    [Names]
                        'tgread_object'
                        'read_int'
                        'range'
                        'append'
                    [Locals+Names]
                        'cls'
                        'reader'
                        '__assert_armored__'
                        '_var_var_1'
                        '_var_var_2'
                        '_var_var_3'
                        '_var_var_4'
                    [Constants]
                        None
                        '__pyarmor_assert_41007__'
                        '__pyarmor_enter_41008__'
                        b'<COAddr>\x07\x00\x00\x1a\xea\x00\x00\x00\x00\x00\x00\x00\x00\x00\x00\x00\x00\x00\x00\x00'
                        (
                            'photo'
                            'users'
                        )
                        '__pyarmor_exit_41009__'
                    [Disassembly]
                        0       NOP                             
                        2       NOP                             
                        4       PUSH_NULL                       
                        6       LOAD_CONST                      2: '__pyarmor_enter_41008__'
                        8       LOAD_CONST                      3: b'<COAddr>\x07\x00\x00\x1a\xea\x00\x00\x00\x00\x00\x00\x00\x00\x00\x00\x00\x00\x00\x00\x00'
                        10      BUILD_TUPLE                     1
                        12      CALL_FUNCTION_EX                0
                        14      POP_TOP                         
                        16      RESUME                          0
                        18      NOP                             
                        20      NOP                             
                        22      NOP                             
                        24      NOP                             
                        26      NOP                             
                        28      LOAD_FAST                       1: reader
                        30      LOAD_ATTR                       1: tgread_object
                        50      CALL                            0
                        58      STORE_FAST                      3: _var_var_1
                        60      LOAD_FAST                       1: reader
                        62      LOAD_ATTR                       3: read_int
                        82      CALL                            0
                        90      POP_TOP                         
                        92      BUILD_LIST                      0
                        94      STORE_FAST                      4: _var_var_2
                        96      LOAD_GLOBAL                     5: NULL + range
                        106     LOAD_FAST                       1: reader
                        108     LOAD_ATTR                       3: read_int
                        128     CALL                            0
                        136     CALL                            1
                        144     GET_ITER                        
                        146     FOR_ITER                        35 (to 218)
                        150     STORE_FAST                      5: _var_var_3
                        152     LOAD_FAST                       1: reader
                        154     LOAD_ATTR                       1: tgread_object
                        174     CALL                            0
                        182     STORE_FAST                      6: _var_var_4
                        184     LOAD_FAST                       4: _var_var_2
                        186     LOAD_ATTR                       7: append
                        206     LOAD_FAST                       6: _var_var_4
                        208     CALL                            1
                        216     POP_TOP                         
                        218     JUMP_BACKWARD                   37 (to 146)
                        220     END_FOR                         
                        222     PUSH_NULL                       
                        224     LOAD_FAST                       0: cls
                        226     LOAD_FAST                       3: _var_var_1
                        228     LOAD_FAST                       4: _var_var_2
                        230     KW_NAMES                        4: ('photo', 'users')
                        232     CALL                            2
                        240     NOP                             
                        242     NOP                             
                        244     NOP                             
                        246     JUMP_FORWARD                    20 (to 288)
                        248     CALL                            1
                        256     POP_TOP                         
                        258     RETURN_VALUE                    
                        260     PUSH_EXC_INFO                   
                        262     PUSH_NULL                       
                        264     LOAD_CONST                      5: '__pyarmor_exit_41009__'
                        266     NOP                             
                        268     LOAD_CONST                      3: b'<COAddr>\x07\x00\x00\x1a\xea\x00\x00\x00\x00\x00\x00\x00\x00\x00\x00\x00\x00\x00\x00\x00'
                        270     CALL                            1
                        278     POP_TOP                         
                        280     RERAISE                         0
                        282     COPY                            3
                        284     POP_EXCEPT                      
                        286     RERAISE                         1
                        288     PUSH_NULL                       
                        290     LOAD_CONST                      5: '__pyarmor_exit_41009__'
                        292     LOAD_CONST                      3: b'<COAddr>\x07\x00\x00\x1a\xea\x00\x00\x00\x00\x00\x00\x00\x00\x00\x00\x00\x00\x00\x00\x00'
                        294     BUILD_TUPLE                     1
                        296     CALL_FUNCTION_EX                0
                        298     POP_TOP                         
                        300     RETURN_VALUE                    
                    [Exception Table]
                        28 to 240 -> 260 [0] 
                        260 to 282 -> 282 [1] lasti
                '__pyarmor_exit_40997__'
                None
            [Disassembly]
                0       NOP                             
                2       LOAD_NAME                       0: __name__
                4       STORE_NAME                      1: __module__
                6       LOAD_CONST                      0: 'Photo'
                8       STORE_NAME                      2: __qualname__
                10      NOP                             
                12      PUSH_NULL                       
                14      LOAD_CONST                      2: '__pyarmor_enter_40996__'
                16      LOAD_CONST                      3: b'<COAddr>\x05\x00\x00"\\\x00\x00\x00\x00\x00\x00\x00\x00\x00\x00\x00\x00\x00\x00\x00'
                18      BUILD_TUPLE                     1
                20      CALL_FUNCTION_EX                0
                22      POP_TOP                         
                24      RESUME                          0
                26      NOP                             
                28      NOP                             
                30      NOP                             
                32      NOP                             
                34      NOP                             
                36      LOAD_CONST                      4: 539045032
                38      STORE_NAME                      4: CONSTRUCTOR_ID
                40      LOAD_CONST                      5: 0xC292BD24
                42      STORE_NAME                      5: SUBCLASS_OF_ID
                44      LOAD_CONST                      6: 'photo'
                46      PUSH_NULL                       
                48      LOAD_CONST                      1: '__pyarmor_assert_40995__'
                50      LOAD_CONST                      7: 'TypePhoto'   # b'\x81\xd6\x01\x036\xca\xb6\xdd\x0f\xf5'
                52      CALL                            1
                60      LOAD_CONST                      8: 'users'
                62      LOAD_NAME                       6: List
                64      LOAD_CONST                      9: 'TypeUser'
                66      BINARY_SUBSCR                   
                70      BUILD_TUPLE                     4
                72      LOAD_CONST                      10: <CODE> __init__
                74      MAKE_FUNCTION                   4
                76      STORE_NAME                      7: __init__
                78      LOAD_CONST                      11: <CODE> to_dict
                80      MAKE_FUNCTION                   0
                82      STORE_NAME                      8: to_dict
                84      LOAD_CONST                      12: <CODE> _bytes
                86      MAKE_FUNCTION                   0
                88      STORE_NAME                      9: _bytes
                90      LOAD_NAME                       10: classmethod
                92      LOAD_CONST                      13: <CODE> from_reader
                94      MAKE_FUNCTION                   0
                96      CALL                            0
                104     STORE_NAME                      11: from_reader
                106     LOAD_CONST                      15: None
                108     NOP                             
                110     NOP                             
                112     NOP                             
                114     JUMP_FORWARD                    19 (to 154)
                122     POP_TOP                         
                124     RETURN_CONST                    15: None
                126     PUSH_EXC_INFO                   
                128     PUSH_NULL                       
                130     LOAD_CONST                      14: '__pyarmor_exit_40997__'
                132     NOP                             
                134     LOAD_CONST                      3: b'<COAddr>\x05\x00\x00"\\\x00\x00\x00\x00\x00\x00\x00\x00\x00\x00\x00\x00\x00\x00\x00'
                136     CALL                            1
                144     POP_TOP                         
                146     RERAISE                         0
                148     COPY                            3
                150     POP_EXCEPT                      
                152     RERAISE                         1
                154     PUSH_NULL                       
                156     LOAD_CONST                      14: '__pyarmor_exit_40997__'
                158     LOAD_CONST                      3: b'<COAddr>\x05\x00\x00"\\\x00\x00\x00\x00\x00\x00\x00\x00\x00\x00\x00\x00\x00\x00\x00'
                160     BUILD_TUPLE                     1
                162     CALL_FUNCTION_EX                0
                164     POP_TOP                         
                166     RETURN_VALUE                    
            [Exception Table]
                36 to 106 -> 126 [0] 
                126 to 148 -> 148 [1] lasti
        'Photo'
        [Code]
            File Name: <frozen multithon.tl.types.photos>
            Object Name: Photos
            Qualified Name: Photos
            Arg Count: 0
            Pos Only Arg Count: 0
            KW Only Arg Count: 0
            Stack Size: 5
            Flags: 0x20000000 (CO_PYARMOR_OBFUSCATED)
            [Names]
                '__name__'
                '__module__'
                '__qualname__'
                '__assert_armored__'
                'CONSTRUCTOR_ID'
                'SUBCLASS_OF_ID'
                'List'
                '__init__'
                'to_dict'
                '_bytes'
                'classmethod'
                'from_reader'
            [Locals+Names]
            [Constants]
                'Photos'
                '__pyarmor_assert_41010__'
                '__pyarmor_enter_41011__'
                b'<COAddr>\x07\x00\x00"b\x00\x00\x00\x00\x00\x00\x00\x00\x00\x00\x00\x00\x00\x00\x00'
                0x8DCA6AA5
                667924839
                'photos'
                'TypePhoto'   # b'\x81\xd6\x01\x036\xca\xb6\xdd\x0f\xf5'
                'users'
                'TypeUser'
                [Code]
                    File Name: <frozen multithon.tl.types.photos>
                    Object Name: __init__
                    Qualified Name: Photos.__init__
                    Arg Count: 3
                    Pos Only Arg Count: 0
                    KW Only Arg Count: 0
                    Stack Size: 5
                    Flags: 0x20000003 (CO_OPTIMIZED | CO_NEWLOCALS | CO_PYARMOR_OBFUSCATED)
                    [Names]
                        'photos'
                        'users'
                    [Locals+Names]
                        'self'
                        'photos'
                        'users'
                        '__assert_armored__'
                    [Constants]
                        '\n        Constructor for photos.Photos: Instance of either Photos, PhotosSlice.\n        '
                        '__pyarmor_assert_41013__'
                        '__pyarmor_enter_41014__'
                        b'<COAddr>\x05\x00\x00\x1a2\x00\x00\x00\x00\x00\x00\x00\x00\x00\x00\x00\x00\x00\x00\x00'
                        '__pyarmor_exit_41015__'
                        None
                    [Disassembly]
                        0       NOP                             
                        2       NOP                             
                        4       PUSH_NULL                       
                        6       LOAD_CONST                      2: '__pyarmor_enter_41014__'
                        8       LOAD_CONST                      3: b'<COAddr>\x05\x00\x00\x1a2\x00\x00\x00\x00\x00\x00\x00\x00\x00\x00\x00\x00\x00\x00\x00'
                        10      BUILD_TUPLE                     1
                        12      CALL_FUNCTION_EX                0
                        14      POP_TOP                         
                        16      RESUME                          0
                        18      NOP                             
                        20      NOP                             
                        22      NOP                             
                        24      NOP                             
                        26      NOP                             
                        28      LOAD_FAST                       1: photos
                        30      LOAD_FAST                       0: self
                        32      STORE_ATTR                      0: photos
                        42      LOAD_FAST                       2: users
                        44      LOAD_FAST                       0: self
                        46      STORE_ATTR                      1: users
                        56      LOAD_CONST                      5: None
                        58      NOP                             
                        60      NOP                             
                        62      NOP                             
                        64      JUMP_FORWARD                    19 (to 104)
                        72      POP_TOP                         
                        74      RETURN_CONST                    5: None
                        76      PUSH_EXC_INFO                   
                        78      PUSH_NULL                       
                        80      LOAD_CONST                      4: '__pyarmor_exit_41015__'
                        82      NOP                             
                        84      LOAD_CONST                      3: b'<COAddr>\x05\x00\x00\x1a2\x00\x00\x00\x00\x00\x00\x00\x00\x00\x00\x00\x00\x00\x00\x00'
                        86      CALL                            1
                        94      POP_TOP                         
                        96      RERAISE                         0
                        98      COPY                            3
                        100     POP_EXCEPT                      
                        102     RERAISE                         1
                        104     PUSH_NULL                       
                        106     LOAD_CONST                      4: '__pyarmor_exit_41015__'
                        108     LOAD_CONST                      3: b'<COAddr>\x05\x00\x00\x1a2\x00\x00\x00\x00\x00\x00\x00\x00\x00\x00\x00\x00\x00\x00\x00'
                        110     BUILD_TUPLE                     1
                        112     CALL_FUNCTION_EX                0
                        114     POP_TOP                         
                        116     RETURN_VALUE                    
                    [Exception Table]
                        28 to 56 -> 76 [0] 
                        76 to 98 -> 98 [1] lasti
                [Code]
                    File Name: <frozen multithon.tl.types.photos>
                    Object Name: to_dict
                    Qualified Name: Photos.to_dict
                    Arg Count: 1
                    Pos Only Arg Count: 0
                    KW Only Arg Count: 0
                    Stack Size: 9
                    Flags: 0x20000003 (CO_OPTIMIZED | CO_NEWLOCALS | CO_PYARMOR_OBFUSCATED)
                    [Names]
                        'photos'
                        'isinstance'
                        'TLObject'
                        'to_dict'
                        'users'
                    [Locals+Names]
                        'self'
                        '__assert_armored__'
                        '_var_var_0'
                    [Constants]
                        None
                        '__pyarmor_assert_41016__'
                        '__pyarmor_enter_41017__'
                        b'<COAddr>\x07\x00\x00\x1aL\x01\x00\x00\x00\x00\x00\x00\x00\x00\x00\x00\x00\x00\x00\x00'
                        'Photos'
                        (
                            '_'
                            'photos'
                            'users'
                        )
                        '__pyarmor_exit_41018__'
                    [Disassembly]
                        0       NOP                             
                        2       NOP                             
                        4       PUSH_NULL                       
                        6       LOAD_CONST                      2: '__pyarmor_enter_41017__'
                        8       LOAD_CONST                      3: b'<COAddr>\x07\x00\x00\x1aL\x01\x00\x00\x00\x00\x00\x00\x00\x00\x00\x00\x00\x00\x00\x00'
                        10      BUILD_TUPLE                     1
                        12      CALL_FUNCTION_EX                0
                        14      POP_TOP                         
                        16      RESUME                          0
                        18      NOP                             
                        20      NOP                             
                        22      NOP                             
                        24      NOP                             
                        26      NOP                             
                        28      LOAD_CONST                      4: 'Photos'
                        30      LOAD_FAST                       0: self
                        32      LOAD_ATTR                       0: photos
                        52      POP_JUMP_IF_NOT_NONE            2 (to 58)
                        54      BUILD_LIST                      0
                        56      JUMP_FORWARD                    57 (to 172)
                        58      LOAD_FAST                       0: self
                        60      LOAD_ATTR                       0: photos
                        80      GET_ITER                        
                        82      LOAD_FAST_AND_CLEAR             2: _var_var_0
                        84      SWAP                            2
                        86      BUILD_LIST                      0
                        88      SWAP                            2
                        90      FOR_ITER                        36 (to 164)
                        94      STORE_FAST                      2: _var_var_0
                        96      LOAD_GLOBAL                     3: NULL + isinstance
                        106     LOAD_FAST                       2: _var_var_0
                        108     LOAD_GLOBAL                     4: TLObject
                        118     CALL                            2
                        126     POP_JUMP_IF_FALSE               16 (to 160)
                        128     LOAD_FAST                       2: _var_var_0
                        130     LOAD_ATTR                       7: to_dict
                        150     CALL                            0
                        158     JUMP_FORWARD                    1 (to 162)
                        160     LOAD_FAST                       2: _var_var_0
                        162     LIST_APPEND                     2
                        164     JUMP_BACKWARD                   38 (to 90)
                        166     END_FOR                         
                        168     SWAP                            2
                        170     STORE_FAST                      2: _var_var_0
                        172     LOAD_FAST                       0: self
                        174     LOAD_ATTR                       8: users
                        194     POP_JUMP_IF_NOT_NONE            2 (to 200)
                        196     BUILD_LIST                      0
                        198     JUMP_FORWARD                    57 (to 314)
                        200     LOAD_FAST                       0: self
                        202     LOAD_ATTR                       8: users
                        222     GET_ITER                        
                        224     LOAD_FAST_AND_CLEAR             2: _var_var_0
                        226     SWAP                            2
                        228     BUILD_LIST                      0
                        230     SWAP                            2
                        232     FOR_ITER                        36 (to 306)
                        236     STORE_FAST                      2: _var_var_0
                        238     LOAD_GLOBAL                     3: NULL + isinstance
                        248     LOAD_FAST                       2: _var_var_0
                        250     LOAD_GLOBAL                     4: TLObject
                        260     CALL                            2
                        268     POP_JUMP_IF_FALSE               16 (to 302)
                        270     LOAD_FAST                       2: _var_var_0
                        272     LOAD_ATTR                       7: to_dict
                        292     CALL                            0
                        300     JUMP_FORWARD                    1 (to 304)
                        302     LOAD_FAST                       2: _var_var_0
                        304     LIST_APPEND                     2
                        306     JUMP_BACKWARD                   38 (to 232)
                        308     END_FOR                         
                        310     SWAP                            2
                        312     STORE_FAST                      2: _var_var_0
                        314     LOAD_CONST                      5: ('_', 'photos', 'users')
                        316     BUILD_CONST_KEY_MAP             3
                        318     NOP                             
                        320     NOP                             
                        322     NOP                             
                        324     JUMP_FORWARD                    30 (to 386)
                        326     CALL                            1
                        334     POP_TOP                         
                        336     RETURN_VALUE                    
                        338     SWAP                            2
                        340     POP_TOP                         
                        342     SWAP                            2
                        344     STORE_FAST                      2: _var_var_0
                        346     RERAISE                         0
                        348     SWAP                            2
                        350     POP_TOP                         
                        352     SWAP                            2
                        354     STORE_FAST                      2: _var_var_0
                        356     RERAISE                         0
                        358     PUSH_EXC_INFO                   
                        360     PUSH_NULL                       
                        362     LOAD_CONST                      6: '__pyarmor_exit_41018__'
                        364     NOP                             
                        366     LOAD_CONST                      3: b'<COAddr>\x07\x00\x00\x1aL\x01\x00\x00\x00\x00\x00\x00\x00\x00\x00\x00\x00\x00\x00\x00'
                        368     CALL                            1
                        376     POP_TOP                         
                        378     RERAISE                         0
                        380     COPY                            3
                        382     POP_EXCEPT                      
                        384     RERAISE                         1
                        386     PUSH_NULL                       
                        388     LOAD_CONST                      6: '__pyarmor_exit_41018__'
                        390     LOAD_CONST                      3: b'<COAddr>\x07\x00\x00\x1aL\x01\x00\x00\x00\x00\x00\x00\x00\x00\x00\x00\x00\x00\x00\x00'
                        392     BUILD_TUPLE                     1
                        394     CALL_FUNCTION_EX                0
                        396     POP_TOP                         
                        398     RETURN_VALUE                    
                    [Exception Table]
                        28 to 86 -> 358 [0] 
                        86 to 168 -> 338 [3] 
                        168 to 228 -> 358 [0] 
                        228 to 310 -> 348 [4] 
                        310 to 318 -> 358 [0] 
                        338 to 358 -> 358 [0] 
                        358 to 380 -> 380 [1] lasti
                [Code]
                    File Name: <frozen multithon.tl.types.photos>
                    Object Name: _bytes
                    Qualified Name: Photos._bytes
                    Arg Count: 1
                    Pos Only Arg Count: 0
                    KW Only Arg Count: 0
                    Stack Size: 13
                    Flags: 0x20000003 (CO_OPTIMIZED | CO_NEWLOCALS | CO_PYARMOR_OBFUSCATED)
                    [Names]
                        'join'
                        'struct'
                        'pack'
                        'len'
                        'photos'
                        'users'
                    [Locals+Names]
                        'self'
                        '__assert_armored__'
                    [Constants]
                        None
                        '__pyarmor_assert_41019__'
                        '__pyarmor_enter_41020__'
                        b'<COAddr>\x05\x00\x00\x1a`\x01\x00\x00\x00\x00\x00\x00\x00\x00\x00\x00\x00\x00\x00\x00'
                        b''
                        b'\xa5j\xca\x8d'
                        b'\x15\xc4\xb5\x1c'
                        '<i'
                        [Code]
                            File Name: <frozen multithon.tl.types.photos>
                            Object Name: <genexpr>
                            Qualified Name: Photos._bytes.<locals>.<genexpr>
                            Arg Count: 1
                            Pos Only Arg Count: 0
                            KW Only Arg Count: 0
                            Stack Size: 3
                            Flags: 0x00000033 (CO_OPTIMIZED | CO_NEWLOCALS | CO_NESTED | CO_GENERATOR)
                            [Names]
                                '_bytes'
                            [Locals+Names]
                                '.0'
                                '_var_var_0'
                            [Constants]
                                None
                            [Disassembly]
                                0       RETURN_GENERATOR                
                                2       POP_TOP                         
                                4       RESUME                          0
                                6       LOAD_FAST                       0: .0
                                8       FOR_ITER                        20 (to 50)
                                12      STORE_FAST                      1: _var_var_0
                                14      LOAD_FAST                       1: _var_var_0
                                16      LOAD_ATTR                       1: _bytes
                                36      CALL                            0
                                44      YIELD_VALUE                     1
                                46      RESUME                          1
                                48      POP_TOP                         
                                50      JUMP_BACKWARD                   22 (to 8)
                                52      END_FOR                         
                                54      RETURN_CONST                    0: None
                                56      CALL_INTRINSIC_1                3 (INTRINSIC_STOPITERATION_ERROR)
                                58      RERAISE                         1
                            [Exception Table]
                                4 to 56 -> 56 [0] lasti
                        [Code]
                            File Name: <frozen multithon.tl.types.photos>
                            Object Name: <genexpr>
                            Qualified Name: Photos._bytes.<locals>.<genexpr>
                            Arg Count: 1
                            Pos Only Arg Count: 0
                            KW Only Arg Count: 0
                            Stack Size: 3
                            Flags: 0x00000033 (CO_OPTIMIZED | CO_NEWLOCALS | CO_NESTED | CO_GENERATOR)
                            [Names]
                                '_bytes'
                            [Locals+Names]
                                '.0'
                                '_var_var_0'
                            [Constants]
                                None
                            [Disassembly]
                                0       RETURN_GENERATOR                
                                2       POP_TOP                         
                                4       RESUME                          0
                                6       LOAD_FAST                       0: .0
                                8       FOR_ITER                        20 (to 50)
                                12      STORE_FAST                      1: _var_var_0
                                14      LOAD_FAST                       1: _var_var_0
                                16      LOAD_ATTR                       1: _bytes
                                36      CALL                            0
                                44      YIELD_VALUE                     1
                                46      RESUME                          1
                                48      POP_TOP                         
                                50      JUMP_BACKWARD                   22 (to 8)
                                52      END_FOR                         
                                54      RETURN_CONST                    0: None
                                56      CALL_INTRINSIC_1                3 (INTRINSIC_STOPITERATION_ERROR)
                                58      RERAISE                         1
                            [Exception Table]
                                4 to 56 -> 56 [0] lasti
                        '__pyarmor_exit_41021__'
                    [Disassembly]
                        0       NOP                             
                        2       NOP                             
                        4       PUSH_NULL                       
                        6       LOAD_CONST                      2: '__pyarmor_enter_41020__'
                        8       LOAD_CONST                      3: b'<COAddr>\x05\x00\x00\x1a`\x01\x00\x00\x00\x00\x00\x00\x00\x00\x00\x00\x00\x00\x00\x00'
                        10      BUILD_TUPLE                     1
                        12      CALL_FUNCTION_EX                0
                        14      POP_TOP                         
                        16      RESUME                          0
                        18      NOP                             
                        20      NOP                             
                        22      NOP                             
                        24      NOP                             
                        26      NOP                             
                        28      LOAD_CONST                      4: b''
                        30      LOAD_ATTR                       1: join
                        50      LOAD_CONST                      5: b'\xa5j\xca\x8d'
                        52      LOAD_CONST                      6: b'\x15\xc4\xb5\x1c'
                        54      LOAD_GLOBAL                     3: NULL + struct
                        64      LOAD_ATTR                       4: pack
                        84      LOAD_CONST                      7: '<i'
                        86      LOAD_GLOBAL                     7: NULL + len
                        96      LOAD_FAST                       0: self
                        98      LOAD_ATTR                       8: photos
                        118     CALL                            1
                        126     CALL                            2
                        134     LOAD_CONST                      4: b''
                        136     LOAD_ATTR                       1: join
                        156     LOAD_CONST                      8: <CODE> <genexpr>
                        158     MAKE_FUNCTION                   0
                        160     LOAD_FAST                       0: self
                        162     LOAD_ATTR                       8: photos
                        182     GET_ITER                        
                        184     CALL                            0
                        192     CALL                            1
                        200     LOAD_CONST                      6: b'\x15\xc4\xb5\x1c'
                        202     LOAD_GLOBAL                     3: NULL + struct
                        212     LOAD_ATTR                       4: pack
                        232     LOAD_CONST                      7: '<i'
                        234     LOAD_GLOBAL                     7: NULL + len
                        244     LOAD_FAST                       0: self
                        246     LOAD_ATTR                       10: users
                        266     CALL                            1
                        274     CALL                            2
                        282     LOAD_CONST                      4: b''
                        284     LOAD_ATTR                       1: join
                        304     LOAD_CONST                      9: <CODE> <genexpr>
                        306     MAKE_FUNCTION                   0
                        308     LOAD_FAST                       0: self
                        310     LOAD_ATTR                       10: users
                        330     GET_ITER                        
                        332     CALL                            0
                        340     CALL                            1
                        348     BUILD_TUPLE                     7
                        350     CALL                            1
                        358     NOP                             
                        360     NOP                             
                        362     NOP                             
                        364     JUMP_FORWARD                    20 (to 406)
                        366     CALL                            1
                        374     POP_TOP                         
                        376     RETURN_VALUE                    
                        378     PUSH_EXC_INFO                   
                        380     PUSH_NULL                       
                        382     LOAD_CONST                      10: '__pyarmor_exit_41021__'
                        384     NOP                             
                        386     LOAD_CONST                      3: b'<COAddr>\x05\x00\x00\x1a`\x01\x00\x00\x00\x00\x00\x00\x00\x00\x00\x00\x00\x00\x00\x00'
                        388     CALL                            1
                        396     POP_TOP                         
                        398     RERAISE                         0
                        400     COPY                            3
                        402     POP_EXCEPT                      
                        404     RERAISE                         1
                        406     PUSH_NULL                       
                        408     LOAD_CONST                      10: '__pyarmor_exit_41021__'
                        410     LOAD_CONST                      3: b'<COAddr>\x05\x00\x00\x1a`\x01\x00\x00\x00\x00\x00\x00\x00\x00\x00\x00\x00\x00\x00\x00'
                        412     BUILD_TUPLE                     1
                        414     CALL_FUNCTION_EX                0
                        416     POP_TOP                         
                        418     RETURN_VALUE                    
                    [Exception Table]
                        28 to 358 -> 378 [0] 
                        378 to 400 -> 400 [1] lasti
                [Code]
                    File Name: <frozen multithon.tl.types.photos>
                    Object Name: from_reader
                    Qualified Name: Photos.from_reader
                    Arg Count: 2
                    Pos Only Arg Count: 0
                    KW Only Arg Count: 0
                    Stack Size: 5
                    Flags: 0x20000003 (CO_OPTIMIZED | CO_NEWLOCALS | CO_PYARMOR_OBFUSCATED)
                    [Names]
                        'read_int'
                        'range'
                        'tgread_object'
                        'append'
                    [Locals+Names]
                        'cls'
                        'reader'
                        '__assert_armored__'
                        '_var_var_5'
                        '_var_var_3'
                        '_var_var_4'
                        '_var_var_2'
                    [Constants]
                        None
                        '__pyarmor_assert_41022__'
                        '__pyarmor_enter_41023__'
                        b'<COAddr>\x07\x00\x00\x1al\x01\x00\x00\x00\x00\x00\x00\x00\x00\x00\x00\x00\x00\x00\x00'
                        (
                            'photos'
                            'users'
                        )
                        '__pyarmor_exit_41024__'
                    [Disassembly]
                        0       NOP                             
                        2       NOP                             
                        4       PUSH_NULL                       
                        6       LOAD_CONST                      2: '__pyarmor_enter_41023__'
                        8       LOAD_CONST                      3: b'<COAddr>\x07\x00\x00\x1al\x01\x00\x00\x00\x00\x00\x00\x00\x00\x00\x00\x00\x00\x00\x00'
                        10      BUILD_TUPLE                     1
                        12      CALL_FUNCTION_EX                0
                        14      POP_TOP                         
                        16      RESUME                          0
                        18      NOP                             
                        20      NOP                             
                        22      NOP                             
                        24      NOP                             
                        26      NOP                             
                        28      LOAD_FAST                       1: reader
                        30      LOAD_ATTR                       1: read_int
                        50      CALL                            0
                        58      POP_TOP                         
                        60      BUILD_LIST                      0
                        62      STORE_FAST                      3: _var_var_5
                        64      LOAD_GLOBAL                     3: NULL + range
                        74      LOAD_FAST                       1: reader
                        76      LOAD_ATTR                       1: read_int
                        96      CALL                            0
                        104     CALL                            1
                        112     GET_ITER                        
                        114     FOR_ITER                        35 (to 186)
                        118     STORE_FAST                      4: _var_var_3
                        120     LOAD_FAST                       1: reader
                        122     LOAD_ATTR                       5: tgread_object
                        142     CALL                            0
                        150     STORE_FAST                      5: _var_var_4
                        152     LOAD_FAST                       3: _var_var_5
                        154     LOAD_ATTR                       7: append
                        174     LOAD_FAST                       5: _var_var_4
                        176     CALL                            1
                        184     POP_TOP                         
                        186     JUMP_BACKWARD                   37 (to 114)
                        188     END_FOR                         
                        190     LOAD_FAST                       1: reader
                        192     LOAD_ATTR                       1: read_int
                        212     CALL                            0
                        220     POP_TOP                         
                        222     BUILD_LIST                      0
                        224     STORE_FAST                      6: _var_var_2
                        226     LOAD_GLOBAL                     3: NULL + range
                        236     LOAD_FAST                       1: reader
                        238     LOAD_ATTR                       1: read_int
                        258     CALL                            0
                        266     CALL                            1
                        274     GET_ITER                        
                        276     FOR_ITER                        35 (to 348)
                        280     STORE_FAST                      4: _var_var_3
                        282     LOAD_FAST                       1: reader
                        284     LOAD_ATTR                       5: tgread_object
                        304     CALL                            0
                        312     STORE_FAST                      5: _var_var_4
                        314     LOAD_FAST                       6: _var_var_2
                        316     LOAD_ATTR                       7: append
                        336     LOAD_FAST                       5: _var_var_4
                        338     CALL                            1
                        346     POP_TOP                         
                        348     JUMP_BACKWARD                   37 (to 276)
                        350     END_FOR                         
                        352     PUSH_NULL                       
                        354     LOAD_FAST                       0: cls
                        356     LOAD_FAST                       3: _var_var_5
                        358     LOAD_FAST                       6: _var_var_2
                        360     KW_NAMES                        4: ('photos', 'users')
                        362     CALL                            2
                        370     NOP                             
                        372     NOP                             
                        374     NOP                             
                        376     JUMP_FORWARD                    20 (to 418)
                        378     CALL                            1
                        386     POP_TOP                         
                        388     RETURN_VALUE                    
                        390     PUSH_EXC_INFO                   
                        392     PUSH_NULL                       
                        394     LOAD_CONST                      5: '__pyarmor_exit_41024__'
                        396     NOP                             
                        398     LOAD_CONST                      3: b'<COAddr>\x07\x00\x00\x1al\x01\x00\x00\x00\x00\x00\x00\x00\x00\x00\x00\x00\x00\x00\x00'
                        400     CALL                            1
                        408     POP_TOP                         
                        410     RERAISE                         0
                        412     COPY                            3
                        414     POP_EXCEPT                      
                        416     RERAISE                         1
                        418     PUSH_NULL                       
                        420     LOAD_CONST                      5: '__pyarmor_exit_41024__'
                        422     LOAD_CONST                      3: b'<COAddr>\x07\x00\x00\x1al\x01\x00\x00\x00\x00\x00\x00\x00\x00\x00\x00\x00\x00\x00\x00'
                        424     BUILD_TUPLE                     1
                        426     CALL_FUNCTION_EX                0
                        428     POP_TOP                         
                        430     RETURN_VALUE                    
                    [Exception Table]
                        28 to 370 -> 390 [0] 
                        390 to 412 -> 412 [1] lasti
                '__pyarmor_exit_41012__'
                None
            [Disassembly]
                0       NOP                             
                2       LOAD_NAME                       0: __name__
                4       STORE_NAME                      1: __module__
                6       LOAD_CONST                      0: 'Photos'
                8       STORE_NAME                      2: __qualname__
                10      NOP                             
                12      PUSH_NULL                       
                14      LOAD_CONST                      2: '__pyarmor_enter_41011__'
                16      LOAD_CONST                      3: b'<COAddr>\x07\x00\x00"b\x00\x00\x00\x00\x00\x00\x00\x00\x00\x00\x00\x00\x00\x00\x00'
                18      BUILD_TUPLE                     1
                20      CALL_FUNCTION_EX                0
                22      POP_TOP                         
                24      RESUME                          0
                26      NOP                             
                28      NOP                             
                30      NOP                             
                32      NOP                             
                34      NOP                             
                36      LOAD_CONST                      4: 0x8DCA6AA5
                38      STORE_NAME                      4: CONSTRUCTOR_ID
                40      LOAD_CONST                      5: 667924839
                42      STORE_NAME                      5: SUBCLASS_OF_ID
                44      LOAD_CONST                      6: 'photos'
                46      LOAD_NAME                       6: List
                48      PUSH_NULL                       
                50      LOAD_CONST                      1: '__pyarmor_assert_41010__'
                52      LOAD_CONST                      7: 'TypePhoto'   # b'\x81\xd6\x01\x036\xca\xb6\xdd\x0f\xf5'
                54      CALL                            1
                62      BINARY_SUBSCR                   
                66      LOAD_CONST                      8: 'users'
                68      LOAD_NAME                       6: List
                70      LOAD_CONST                      9: 'TypeUser'
                72      BINARY_SUBSCR                   
                76      BUILD_TUPLE                     4
                78      LOAD_CONST                      10: <CODE> __init__
                80      MAKE_FUNCTION                   4
                82      STORE_NAME                      7: __init__
                84      LOAD_CONST                      11: <CODE> to_dict
                86      MAKE_FUNCTION                   0
                88      STORE_NAME                      8: to_dict
                90      LOAD_CONST                      12: <CODE> _bytes
                92      MAKE_FUNCTION                   0
                94      STORE_NAME                      9: _bytes
                96      LOAD_NAME                       10: classmethod
                98      LOAD_CONST                      13: <CODE> from_reader
                100     MAKE_FUNCTION                   0
                102     CALL                            0
                110     STORE_NAME                      11: from_reader
                112     LOAD_CONST                      15: None
                114     NOP                             
                116     NOP                             
                118     NOP                             
                120     JUMP_FORWARD                    19 (to 160)
                128     POP_TOP                         
                130     RETURN_CONST                    15: None
                132     PUSH_EXC_INFO                   
                134     PUSH_NULL                       
                136     LOAD_CONST                      14: '__pyarmor_exit_41012__'
                138     NOP                             
                140     LOAD_CONST                      3: b'<COAddr>\x07\x00\x00"b\x00\x00\x00\x00\x00\x00\x00\x00\x00\x00\x00\x00\x00\x00\x00'
                142     CALL                            1
                150     POP_TOP                         
                152     RERAISE                         0
                154     COPY                            3
                156     POP_EXCEPT                      
                158     RERAISE                         1
                160     PUSH_NULL                       
                162     LOAD_CONST                      14: '__pyarmor_exit_41012__'
                164     LOAD_CONST                      3: b'<COAddr>\x07\x00\x00"b\x00\x00\x00\x00\x00\x00\x00\x00\x00\x00\x00\x00\x00\x00\x00'
                166     BUILD_TUPLE                     1
                168     CALL_FUNCTION_EX                0
                170     POP_TOP                         
                172     RETURN_VALUE                    
            [Exception Table]
                36 to 112 -> 132 [0] 
                132 to 154 -> 154 [1] lasti
        'Photos'
        [Code]
            File Name: <frozen multithon.tl.types.photos>
            Object Name: PhotosSlice
            Qualified Name: PhotosSlice
            Arg Count: 0
            Pos Only Arg Count: 0
            KW Only Arg Count: 0
            Stack Size: 7
            Flags: 0x20000000 (CO_PYARMOR_OBFUSCATED)
            [Names]
                '__name__'
                '__module__'
                '__qualname__'
                '__assert_armored__'
                'CONSTRUCTOR_ID'
                'SUBCLASS_OF_ID'
                'int'
                'List'
                '__init__'
                'to_dict'
                '_bytes'
                'classmethod'
                'from_reader'
            [Locals+Names]
            [Constants]
                'PhotosSlice'
                '__pyarmor_assert_41025__'
                '__pyarmor_enter_41026__'
                b'<COAddr>\x05\x00\x00"f\x00\x00\x00\x00\x00\x00\x00\x00\x00\x00\x00\x00\x00\x00\x00'
                352657236
                667924839
                'count'
                'photos'
                'TypePhoto'   # b'\x81\xd6\x01\x036\xca\xb6\xdd\x0f\xf5'
                'users'
                'TypeUser'
                [Code]
                    File Name: <frozen multithon.tl.types.photos>
                    Object Name: __init__
                    Qualified Name: PhotosSlice.__init__
                    Arg Count: 4
                    Pos Only Arg Count: 0
                    KW Only Arg Count: 0
                    Stack Size: 5
                    Flags: 0x20000003 (CO_OPTIMIZED | CO_NEWLOCALS | CO_PYARMOR_OBFUSCATED)
                    [Names]
                        'count'
                        'photos'
                        'users'
                    [Locals+Names]
                        'self'
                        'count'
                        'photos'
                        'users'
                        '__assert_armored__'
                    [Constants]
                        '\n        Constructor for photos.Photos: Instance of either Photos, PhotosSlice.\n        '
                        '__pyarmor_assert_41028__'
                        '__pyarmor_enter_41029__'
                        b'<COAddr>\x07\x00\x00\x1a@\x00\x00\x00\x00\x00\x00\x00\x00\x00\x00\x00\x00\x00\x00\x00'
                        '__pyarmor_exit_41030__'
                        None
                    [Disassembly]
                        0       NOP                             
                        2       NOP                             
                        4       PUSH_NULL                       
                        6       LOAD_CONST                      2: '__pyarmor_enter_41029__'
                        8       LOAD_CONST                      3: b'<COAddr>\x07\x00\x00\x1a@\x00\x00\x00\x00\x00\x00\x00\x00\x00\x00\x00\x00\x00\x00\x00'
                        10      BUILD_TUPLE                     1
                        12      CALL_FUNCTION_EX                0
                        14      POP_TOP                         
                        16      RESUME                          0
                        18      NOP                             
                        20      NOP                             
                        22      NOP                             
                        24      NOP                             
                        26      NOP                             
                        28      LOAD_FAST                       1: count
                        30      LOAD_FAST                       0: self
                        32      STORE_ATTR                      0: count
                        42      LOAD_FAST                       2: photos
                        44      LOAD_FAST                       0: self
                        46      STORE_ATTR                      1: photos
                        56      LOAD_FAST                       3: users
                        58      LOAD_FAST                       0: self
                        60      STORE_ATTR                      2: users
                        70      LOAD_CONST                      5: None
                        72      NOP                             
                        74      NOP                             
                        76      NOP                             
                        78      JUMP_FORWARD                    19 (to 118)
                        86      POP_TOP                         
                        88      RETURN_CONST                    5: None
                        90      PUSH_EXC_INFO                   
                        92      PUSH_NULL                       
                        94      LOAD_CONST                      4: '__pyarmor_exit_41030__'
                        96      NOP                             
                        98      LOAD_CONST                      3: b'<COAddr>\x07\x00\x00\x1a@\x00\x00\x00\x00\x00\x00\x00\x00\x00\x00\x00\x00\x00\x00\x00'
                        100     CALL                            1
                        108     POP_TOP                         
                        110     RERAISE                         0
                        112     COPY                            3
                        114     POP_EXCEPT                      
                        116     RERAISE                         1
                        118     PUSH_NULL                       
                        120     LOAD_CONST                      4: '__pyarmor_exit_41030__'
                        122     LOAD_CONST                      3: b'<COAddr>\x07\x00\x00\x1a@\x00\x00\x00\x00\x00\x00\x00\x00\x00\x00\x00\x00\x00\x00\x00'
                        124     BUILD_TUPLE                     1
                        126     CALL_FUNCTION_EX                0
                        128     POP_TOP                         
                        130     RETURN_VALUE                    
                    [Exception Table]
                        28 to 70 -> 90 [0] 
                        90 to 112 -> 112 [1] lasti
                [Code]
                    File Name: <frozen multithon.tl.types.photos>
                    Object Name: to_dict
                    Qualified Name: PhotosSlice.to_dict
                    Arg Count: 1
                    Pos Only Arg Count: 0
                    KW Only Arg Count: 0
                    Stack Size: 10
                    Flags: 0x20000003 (CO_OPTIMIZED | CO_NEWLOCALS | CO_PYARMOR_OBFUSCATED)
                    [Names]
                        'count'
                        'photos'
                        'isinstance'
                        'TLObject'
                        'to_dict'
                        'users'
                    [Locals+Names]
                        'self'
                        '__assert_armored__'
                        '_var_var_0'
                    [Constants]
                        None
                        '__pyarmor_assert_41031__'
                        '__pyarmor_enter_41032__'
                        b'<COAddr>\x07\x00\x00\x1an\x01\x00\x00\x00\x00\x00\x00\x00\x00\x00\x00\x00\x00\x00\x00'
                        'PhotosSlice'   # b"\x81\xd2\x10\x1c'\xf5\xad\xe1\x17\xf3\x0e\xc5"
                        (
                            '_'
                            'count'
                            'photos'
                            'users'
                        )
                        '__pyarmor_exit_41033__'
                    [Disassembly]
                        0       NOP                             
                        2       NOP                             
                        4       PUSH_NULL                       
                        6       LOAD_CONST                      2: '__pyarmor_enter_41032__'
                        8       LOAD_CONST                      3: b'<COAddr>\x07\x00\x00\x1an\x01\x00\x00\x00\x00\x00\x00\x00\x00\x00\x00\x00\x00\x00\x00'
                        10      BUILD_TUPLE                     1
                        12      CALL_FUNCTION_EX                0
                        14      POP_TOP                         
                        16      RESUME                          0
                        18      NOP                             
                        20      NOP                             
                        22      NOP                             
                        24      NOP                             
                        26      NOP                             
                        28      PUSH_NULL                       
                        30      LOAD_CONST                      1: '__pyarmor_assert_41031__'
                        32      LOAD_CONST                      4: 'PhotosSlice'   # b"\x81\xd2\x10\x1c'\xf5\xad\xe1\x17\xf3\x0e\xc5"
                        34      CALL                            1
                        42      LOAD_FAST                       0: self
                        44      LOAD_ATTR                       0: count
                        64      LOAD_FAST                       0: self
                        66      LOAD_ATTR                       2: photos
                        86      POP_JUMP_IF_NOT_NONE            2 (to 92)
                        88      BUILD_LIST                      0
                        90      JUMP_FORWARD                    57 (to 206)
                        92      LOAD_FAST                       0: self
                        94      LOAD_ATTR                       2: photos
                        114     GET_ITER                        
                        116     LOAD_FAST_AND_CLEAR             2: _var_var_0
                        118     SWAP                            2
                        120     BUILD_LIST                      0
                        122     SWAP                            2
                        124     FOR_ITER                        36 (to 198)
                        128     STORE_FAST                      2: _var_var_0
                        130     LOAD_GLOBAL                     5: NULL + isinstance
                        140     LOAD_FAST                       2: _var_var_0
                        142     LOAD_GLOBAL                     6: TLObject
                        152     CALL                            2
                        160     POP_JUMP_IF_FALSE               16 (to 194)
                        162     LOAD_FAST                       2: _var_var_0
                        164     LOAD_ATTR                       9: to_dict
                        184     CALL                            0
                        192     JUMP_FORWARD                    1 (to 196)
                        194     LOAD_FAST                       2: _var_var_0
                        196     LIST_APPEND                     2
                        198     JUMP_BACKWARD                   38 (to 124)
                        200     END_FOR                         
                        202     SWAP                            2
                        204     STORE_FAST                      2: _var_var_0
                        206     LOAD_FAST                       0: self
                        208     LOAD_ATTR                       10: users
                        228     POP_JUMP_IF_NOT_NONE            2 (to 234)
                        230     BUILD_LIST                      0
                        232     JUMP_FORWARD                    57 (to 348)
                        234     LOAD_FAST                       0: self
                        236     LOAD_ATTR                       10: users
                        256     GET_ITER                        
                        258     LOAD_FAST_AND_CLEAR             2: _var_var_0
                        260     SWAP                            2
                        262     BUILD_LIST                      0
                        264     SWAP                            2
                        266     FOR_ITER                        36 (to 340)
                        270     STORE_FAST                      2: _var_var_0
                        272     LOAD_GLOBAL                     5: NULL + isinstance
                        282     LOAD_FAST                       2: _var_var_0
                        284     LOAD_GLOBAL                     6: TLObject
                        294     CALL                            2
                        302     POP_JUMP_IF_FALSE               16 (to 336)
                        304     LOAD_FAST                       2: _var_var_0
                        306     LOAD_ATTR                       9: to_dict
                        326     CALL                            0
                        334     JUMP_FORWARD                    1 (to 338)
                        336     LOAD_FAST                       2: _var_var_0
                        338     LIST_APPEND                     2
                        340     JUMP_BACKWARD                   38 (to 266)
                        342     END_FOR                         
                        344     SWAP                            2
                        346     STORE_FAST                      2: _var_var_0
                        348     LOAD_CONST                      5: ('_', 'count', 'photos', 'users')
                        350     BUILD_CONST_KEY_MAP             4
                        352     NOP                             
                        354     NOP                             
                        356     NOP                             
                        358     JUMP_FORWARD                    30 (to 420)
                        360     CALL                            1
                        368     POP_TOP                         
                        370     RETURN_VALUE                    
                        372     SWAP                            2
                        374     POP_TOP                         
                        376     SWAP                            2
                        378     STORE_FAST                      2: _var_var_0
                        380     RERAISE                         0
                        382     SWAP                            2
                        384     POP_TOP                         
                        386     SWAP                            2
                        388     STORE_FAST                      2: _var_var_0
                        390     RERAISE                         0
                        392     PUSH_EXC_INFO                   
                        394     PUSH_NULL                       
                        396     LOAD_CONST                      6: '__pyarmor_exit_41033__'
                        398     NOP                             
                        400     LOAD_CONST                      3: b'<COAddr>\x07\x00\x00\x1an\x01\x00\x00\x00\x00\x00\x00\x00\x00\x00\x00\x00\x00\x00\x00'
                        402     CALL                            1
                        410     POP_TOP                         
                        412     RERAISE                         0
                        414     COPY                            3
                        416     POP_EXCEPT                      
                        418     RERAISE                         1
                        420     PUSH_NULL                       
                        422     LOAD_CONST                      6: '__pyarmor_exit_41033__'
                        424     LOAD_CONST                      3: b'<COAddr>\x07\x00\x00\x1an\x01\x00\x00\x00\x00\x00\x00\x00\x00\x00\x00\x00\x00\x00\x00'
                        426     BUILD_TUPLE                     1
                        428     CALL_FUNCTION_EX                0
                        430     POP_TOP                         
                        432     RETURN_VALUE                    
                    [Exception Table]
                        28 to 120 -> 392 [0] 
                        120 to 202 -> 372 [4] 
                        202 to 262 -> 392 [0] 
                        262 to 344 -> 382 [5] 
                        344 to 352 -> 392 [0] 
                        372 to 392 -> 392 [0] 
                        392 to 414 -> 414 [1] lasti
                [Code]
                    File Name: <frozen multithon.tl.types.photos>
                    Object Name: _bytes
                    Qualified Name: PhotosSlice._bytes
                    Arg Count: 1
                    Pos Only Arg Count: 0
                    KW Only Arg Count: 0
                    Stack Size: 14
                    Flags: 0x20000003 (CO_OPTIMIZED | CO_NEWLOCALS | CO_PYARMOR_OBFUSCATED)
                    [Names]
                        'join'
                        'struct'
                        'pack'
                        'count'
                        'len'
                        'photos'
                        'users'
                    [Locals+Names]
                        'self'
                        '__assert_armored__'
                    [Constants]
                        None
                        '__pyarmor_assert_41034__'
                        '__pyarmor_enter_41035__'
                        b'<COAddr>\x07\x00\x00\x1a\x9e\x01\x00\x00\x00\x00\x00\x00\x00\x00\x00\x00\x00\x00\x00\x00'
                        b''
                        b'T\x1f\x05\x15'
                        '<i'
                        b'\x15\xc4\xb5\x1c'
                        [Code]
                            File Name: <frozen multithon.tl.types.photos>
                            Object Name: <genexpr>
                            Qualified Name: PhotosSlice._bytes.<locals>.<genexpr>
                            Arg Count: 1
                            Pos Only Arg Count: 0
                            KW Only Arg Count: 0
                            Stack Size: 3
                            Flags: 0x00000033 (CO_OPTIMIZED | CO_NEWLOCALS | CO_NESTED | CO_GENERATOR)
                            [Names]
                                '_bytes'
                            [Locals+Names]
                                '.0'
                                '_var_var_0'
                            [Constants]
                                None
                            [Disassembly]
                                0       RETURN_GENERATOR                
                                2       POP_TOP                         
                                4       RESUME                          0
                                6       LOAD_FAST                       0: .0
                                8       FOR_ITER                        20 (to 50)
                                12      STORE_FAST                      1: _var_var_0
                                14      LOAD_FAST                       1: _var_var_0
                                16      LOAD_ATTR                       1: _bytes
                                36      CALL                            0
                                44      YIELD_VALUE                     1
                                46      RESUME                          1
                                48      POP_TOP                         
                                50      JUMP_BACKWARD                   22 (to 8)
                                52      END_FOR                         
                                54      RETURN_CONST                    0: None
                                56      CALL_INTRINSIC_1                3 (INTRINSIC_STOPITERATION_ERROR)
                                58      RERAISE                         1
                            [Exception Table]
                                4 to 56 -> 56 [0] lasti
                        [Code]
                            File Name: <frozen multithon.tl.types.photos>
                            Object Name: <genexpr>
                            Qualified Name: PhotosSlice._bytes.<locals>.<genexpr>
                            Arg Count: 1
                            Pos Only Arg Count: 0
                            KW Only Arg Count: 0
                            Stack Size: 3
                            Flags: 0x00000033 (CO_OPTIMIZED | CO_NEWLOCALS | CO_NESTED | CO_GENERATOR)
                            [Names]
                                '_bytes'
                            [Locals+Names]
                                '.0'
                                '_var_var_0'
                            [Constants]
                                None
                            [Disassembly]
                                0       RETURN_GENERATOR                
                                2       POP_TOP                         
                                4       RESUME                          0
                                6       LOAD_FAST                       0: .0
                                8       FOR_ITER                        20 (to 50)
                                12      STORE_FAST                      1: _var_var_0
                                14      LOAD_FAST                       1: _var_var_0
                                16      LOAD_ATTR                       1: _bytes
                                36      CALL                            0
                                44      YIELD_VALUE                     1
                                46      RESUME                          1
                                48      POP_TOP                         
                                50      JUMP_BACKWARD                   22 (to 8)
                                52      END_FOR                         
                                54      RETURN_CONST                    0: None
                                56      CALL_INTRINSIC_1                3 (INTRINSIC_STOPITERATION_ERROR)
                                58      RERAISE                         1
                            [Exception Table]
                                4 to 56 -> 56 [0] lasti
                        '__pyarmor_exit_41036__'
                    [Disassembly]
                        0       NOP                             
                        2       NOP                             
                        4       PUSH_NULL                       
                        6       LOAD_CONST                      2: '__pyarmor_enter_41035__'
                        8       LOAD_CONST                      3: b'<COAddr>\x07\x00\x00\x1a\x9e\x01\x00\x00\x00\x00\x00\x00\x00\x00\x00\x00\x00\x00\x00\x00'
                        10      BUILD_TUPLE                     1
                        12      CALL_FUNCTION_EX                0
                        14      POP_TOP                         
                        16      RESUME                          0
                        18      NOP                             
                        20      NOP                             
                        22      NOP                             
                        24      NOP                             
                        26      NOP                             
                        28      LOAD_CONST                      4: b''
                        30      LOAD_ATTR                       1: join
                        50      LOAD_CONST                      5: b'T\x1f\x05\x15'
                        52      LOAD_GLOBAL                     3: NULL + struct
                        62      LOAD_ATTR                       4: pack
                        82      LOAD_CONST                      6: '<i'
                        84      LOAD_FAST                       0: self
                        86      LOAD_ATTR                       6: count
                        106     CALL                            2
                        114     LOAD_CONST                      7: b'\x15\xc4\xb5\x1c'
                        116     LOAD_GLOBAL                     3: NULL + struct
                        126     LOAD_ATTR                       4: pack
                        146     LOAD_CONST                      6: '<i'
                        148     LOAD_GLOBAL                     9: NULL + len
                        158     LOAD_FAST                       0: self
                        160     LOAD_ATTR                       10: photos
                        180     CALL                            1
                        188     CALL                            2
                        196     LOAD_CONST                      4: b''
                        198     LOAD_ATTR                       1: join
                        218     LOAD_CONST                      8: <CODE> <genexpr>
                        220     MAKE_FUNCTION                   0
                        222     LOAD_FAST                       0: self
                        224     LOAD_ATTR                       10: photos
                        244     GET_ITER                        
                        246     CALL                            0
                        254     CALL                            1
                        262     LOAD_CONST                      7: b'\x15\xc4\xb5\x1c'
                        264     LOAD_GLOBAL                     3: NULL + struct
                        274     LOAD_ATTR                       4: pack
                        294     LOAD_CONST                      6: '<i'
                        296     LOAD_GLOBAL                     9: NULL + len
                        306     LOAD_FAST                       0: self
                        308     LOAD_ATTR                       12: users
                        328     CALL                            1
                        336     CALL                            2
                        344     LOAD_CONST                      4: b''
                        346     LOAD_ATTR                       1: join
                        366     LOAD_CONST                      9: <CODE> <genexpr>
                        368     MAKE_FUNCTION                   0
                        370     LOAD_FAST                       0: self
                        372     LOAD_ATTR                       12: users
                        392     GET_ITER                        
                        394     CALL                            0
                        402     CALL                            1
                        410     BUILD_TUPLE                     8
                        412     CALL                            1
                        420     NOP                             
                        422     NOP                             
                        424     NOP                             
                        426     JUMP_FORWARD                    20 (to 468)
                        428     CALL                            1
                        436     POP_TOP                         
                        438     RETURN_VALUE                    
                        440     PUSH_EXC_INFO                   
                        442     PUSH_NULL                       
                        444     LOAD_CONST                      10: '__pyarmor_exit_41036__'
                        446     NOP                             
                        448     LOAD_CONST                      3: b'<COAddr>\x07\x00\x00\x1a\x9e\x01\x00\x00\x00\x00\x00\x00\x00\x00\x00\x00\x00\x00\x00\x00'
                        450     CALL                            1
                        458     POP_TOP                         
                        460     RERAISE                         0
                        462     COPY                            3
                        464     POP_EXCEPT                      
                        466     RERAISE                         1
                        468     PUSH_NULL                       
                        470     LOAD_CONST                      10: '__pyarmor_exit_41036__'
                        472     LOAD_CONST                      3: b'<COAddr>\x07\x00\x00\x1a\x9e\x01\x00\x00\x00\x00\x00\x00\x00\x00\x00\x00\x00\x00\x00\x00'
                        474     BUILD_TUPLE                     1
                        476     CALL_FUNCTION_EX                0
                        478     POP_TOP                         
                        480     RETURN_VALUE                    
                    [Exception Table]
                        28 to 420 -> 440 [0] 
                        440 to 462 -> 462 [1] lasti
                [Code]
                    File Name: <frozen multithon.tl.types.photos>
                    Object Name: from_reader
                    Qualified Name: PhotosSlice.from_reader
                    Arg Count: 2
                    Pos Only Arg Count: 0
                    KW Only Arg Count: 0
                    Stack Size: 5
                    Flags: 0x20000003 (CO_OPTIMIZED | CO_NEWLOCALS | CO_PYARMOR_OBFUSCATED)
                    [Names]
                        'read_int'
                        'range'
                        'tgread_object'
                        'append'
                    [Locals+Names]
                        'cls'
                        'reader'
                        '__assert_armored__'
                        '_var_var_6'
                        '_var_var_5'
                        '_var_var_3'
                        '_var_var_4'
                        '_var_var_2'
                    [Constants]
                        None
                        '__pyarmor_assert_41037__'
                        '__pyarmor_enter_41038__'
                        b'<COAddr>\x07\x00\x00\x1a\x8e\x01\x00\x00\x00\x00\x00\x00\x00\x00\x00\x00\x00\x00\x00\x00'
                        (
                            'count'
                            'photos'
                            'users'
                        )
                        '__pyarmor_exit_41039__'
                    [Disassembly]
                        0       NOP                             
                        2       NOP                             
                        4       PUSH_NULL                       
                        6       LOAD_CONST                      2: '__pyarmor_enter_41038__'
                        8       LOAD_CONST                      3: b'<COAddr>\x07\x00\x00\x1a\x8e\x01\x00\x00\x00\x00\x00\x00\x00\x00\x00\x00\x00\x00\x00\x00'
                        10      BUILD_TUPLE                     1
                        12      CALL_FUNCTION_EX                0
                        14      POP_TOP                         
                        16      RESUME                          0
                        18      NOP                             
                        20      NOP                             
                        22      NOP                             
                        24      NOP                             
                        26      NOP                             
                        28      LOAD_FAST                       1: reader
                        30      LOAD_ATTR                       1: read_int
                        50      CALL                            0
                        58      STORE_FAST                      3: _var_var_6
                        60      LOAD_FAST                       1: reader
                        62      LOAD_ATTR                       1: read_int
                        82      CALL                            0
                        90      POP_TOP                         
                        92      BUILD_LIST                      0
                        94      STORE_FAST                      4: _var_var_5
                        96      LOAD_GLOBAL                     3: NULL + range
                        106     LOAD_FAST                       1: reader
                        108     LOAD_ATTR                       1: read_int
                        128     CALL                            0
                        136     CALL                            1
                        144     GET_ITER                        
                        146     FOR_ITER                        35 (to 218)
                        150     STORE_FAST                      5: _var_var_3
                        152     LOAD_FAST                       1: reader
                        154     LOAD_ATTR                       5: tgread_object
                        174     CALL                            0
                        182     STORE_FAST                      6: _var_var_4
                        184     LOAD_FAST                       4: _var_var_5
                        186     LOAD_ATTR                       7: append
                        206     LOAD_FAST                       6: _var_var_4
                        208     CALL                            1
                        216     POP_TOP                         
                        218     JUMP_BACKWARD                   37 (to 146)
                        220     END_FOR                         
                        222     LOAD_FAST                       1: reader
                        224     LOAD_ATTR                       1: read_int
                        244     CALL                            0
                        252     POP_TOP                         
                        254     BUILD_LIST                      0
                        256     STORE_FAST                      7: _var_var_2
                        258     LOAD_GLOBAL                     3: NULL + range
                        268     LOAD_FAST                       1: reader
                        270     LOAD_ATTR                       1: read_int
                        290     CALL                            0
                        298     CALL                            1
                        306     GET_ITER                        
                        308     FOR_ITER                        35 (to 380)
                        312     STORE_FAST                      5: _var_var_3
                        314     LOAD_FAST                       1: reader
                        316     LOAD_ATTR                       5: tgread_object
                        336     CALL                            0
                        344     STORE_FAST                      6: _var_var_4
                        346     LOAD_FAST                       7: _var_var_2
                        348     LOAD_ATTR                       7: append
                        368     LOAD_FAST                       6: _var_var_4
                        370     CALL                            1
                        378     POP_TOP                         
                        380     JUMP_BACKWARD                   37 (to 308)
                        382     END_FOR                         
                        384     PUSH_NULL                       
                        386     LOAD_FAST                       0: cls
                        388     LOAD_FAST                       3: _var_var_6
                        390     LOAD_FAST                       4: _var_var_5
                        392     LOAD_FAST                       7: _var_var_2
                        394     KW_NAMES                        4: ('count', 'photos', 'users')
                        396     CALL                            3
                        404     NOP                             
                        406     NOP                             
                        408     NOP                             
                        410     JUMP_FORWARD                    20 (to 452)
                        412     CALL                            1
                        420     POP_TOP                         
                        422     RETURN_VALUE                    
                        424     PUSH_EXC_INFO                   
                        426     PUSH_NULL                       
                        428     LOAD_CONST                      5: '__pyarmor_exit_41039__'
                        430     NOP                             
                        432     LOAD_CONST                      3: b'<COAddr>\x07\x00\x00\x1a\x8e\x01\x00\x00\x00\x00\x00\x00\x00\x00\x00\x00\x00\x00\x00\x00'
                        434     CALL                            1
                        442     POP_TOP                         
                        444     RERAISE                         0
                        446     COPY                            3
                        448     POP_EXCEPT                      
                        450     RERAISE                         1
                        452     PUSH_NULL                       
                        454     LOAD_CONST                      5: '__pyarmor_exit_41039__'
                        456     LOAD_CONST                      3: b'<COAddr>\x07\x00\x00\x1a\x8e\x01\x00\x00\x00\x00\x00\x00\x00\x00\x00\x00\x00\x00\x00\x00'
                        458     BUILD_TUPLE                     1
                        460     CALL_FUNCTION_EX                0
                        462     POP_TOP                         
                        464     RETURN_VALUE                    
                    [Exception Table]
                        28 to 404 -> 424 [0] 
                        424 to 446 -> 446 [1] lasti
                '__pyarmor_exit_41027__'
                None
            [Disassembly]
                0       NOP                             
                2       LOAD_NAME                       0: __name__
                4       STORE_NAME                      1: __module__
                6       LOAD_CONST                      0: 'PhotosSlice'
                8       STORE_NAME                      2: __qualname__
                10      NOP                             
                12      PUSH_NULL                       
                14      LOAD_CONST                      2: '__pyarmor_enter_41026__'
                16      LOAD_CONST                      3: b'<COAddr>\x05\x00\x00"f\x00\x00\x00\x00\x00\x00\x00\x00\x00\x00\x00\x00\x00\x00\x00'
                18      BUILD_TUPLE                     1
                20      CALL_FUNCTION_EX                0
                22      POP_TOP                         
                24      RESUME                          0
                26      NOP                             
                28      NOP                             
                30      NOP                             
                32      NOP                             
                34      NOP                             
                36      LOAD_CONST                      4: 352657236
                38      STORE_NAME                      4: CONSTRUCTOR_ID
                40      LOAD_CONST                      5: 667924839
                42      STORE_NAME                      5: SUBCLASS_OF_ID
                44      LOAD_CONST                      6: 'count'
                46      LOAD_NAME                       6: int
                48      LOAD_CONST                      7: 'photos'
                50      LOAD_NAME                       7: List
                52      PUSH_NULL                       
                54      LOAD_CONST                      1: '__pyarmor_assert_41025__'
                56      LOAD_CONST                      8: 'TypePhoto'   # b'\x81\xd6\x01\x036\xca\xb6\xdd\x0f\xf5'
                58      CALL                            1
                66      BINARY_SUBSCR                   
                70      LOAD_CONST                      9: 'users'
                72      LOAD_NAME                       7: List
                74      LOAD_CONST                      10: 'TypeUser'
                76      BINARY_SUBSCR                   
                80      BUILD_TUPLE                     6
                82      LOAD_CONST                      11: <CODE> __init__
                84      MAKE_FUNCTION                   4
                86      STORE_NAME                      8: __init__
                88      LOAD_CONST                      12: <CODE> to_dict
                90      MAKE_FUNCTION                   0
                92      STORE_NAME                      9: to_dict
                94      LOAD_CONST                      13: <CODE> _bytes
                96      MAKE_FUNCTION                   0
                98      STORE_NAME                      10: _bytes
                100     LOAD_NAME                       11: classmethod
                102     LOAD_CONST                      14: <CODE> from_reader
                104     MAKE_FUNCTION                   0
                106     CALL                            0
                114     STORE_NAME                      12: from_reader
                116     LOAD_CONST                      16: None
                118     NOP                             
                120     NOP                             
                122     NOP                             
                124     JUMP_FORWARD                    19 (to 164)
                132     POP_TOP                         
                134     RETURN_CONST                    16: None
                136     PUSH_EXC_INFO                   
                138     PUSH_NULL                       
                140     LOAD_CONST                      15: '__pyarmor_exit_41027__'
                142     NOP                             
                144     LOAD_CONST                      3: b'<COAddr>\x05\x00\x00"f\x00\x00\x00\x00\x00\x00\x00\x00\x00\x00\x00\x00\x00\x00\x00'
                146     CALL                            1
                154     POP_TOP                         
                156     RERAISE                         0
                158     COPY                            3
                160     POP_EXCEPT                      
                162     RERAISE                         1
                164     PUSH_NULL                       
                166     LOAD_CONST                      15: '__pyarmor_exit_41027__'
                168     LOAD_CONST                      3: b'<COAddr>\x05\x00\x00"f\x00\x00\x00\x00\x00\x00\x00\x00\x00\x00\x00\x00\x00\x00\x00'
                170     BUILD_TUPLE                     1
                172     CALL_FUNCTION_EX                0
                174     POP_TOP                         
                176     RETURN_VALUE                    
            [Exception Table]
                36 to 116 -> 136 [0] 
                136 to 158 -> 158 [1] lasti
        'PhotosSlice'
        '__pyarmor_exit_40994__'
    [Disassembly]
        0       NOP                             
        2       NOP                             
        4       PUSH_NULL                       
        6       LOAD_CONST                      1: '__pyarmor_enter_40993__'
        8       LOAD_CONST                      2: b'<COAddr>\x05\x00\x00\x1a\xba\x00\x00\x00\x00\x00\x00\x00\x00\x00\x00\x00\x00\x00\x00\x00'
        10      BUILD_TUPLE                     1
        12      CALL_FUNCTION_EX                0
        14      POP_TOP                         
        16      RESUME                          0
        18      NOP                             
        20      NOP                             
        22      NOP                             
        24      NOP                             
        26      PUSH_NULL                       
        28      LOAD_CONST                      0: '__pyarmor_assert_40992__'
        30      LOAD_CONST                      3: "File generated by TLObjects' generator. All changes will be ERASED"   # b'\x81\xc4\x11\x1f6\xba\xb9\xd7\x15\xff\x1f\xc1x\xe9\xfc\xc5\rD\xfb\x93\x86\xe4L\xc6\x00l\xb7OG\xf1\x19\xe04W2\x0c\x8c\xc5\xa6`X\xc8\xf4Q\x9d\xdb\x07F9\xeaS\xe8\xc7g\x0f\xe1;\xab\x99\x18Xn\x03rdm!'
        32      CALL                            1
        40      POP_TOP                         
        42      LOAD_CONST                      4: 3
        44      LOAD_CONST                      5: ('TLObject',)
        46      IMPORT_NAME                     1: tl.tlobject
        48      IMPORT_FROM                     2: TLObject
        50      STORE_NAME                      2: TLObject
        52      POP_TOP                         
        54      LOAD_CONST                      6: 0
        56      LOAD_CONST                      7: ('Optional', 'List', 'Union', 'TYPE_CHECKING')
        58      IMPORT_NAME                     3: typing
        60      IMPORT_FROM                     4: Optional
        62      STORE_NAME                      4: Optional
        64      IMPORT_FROM                     5: List
        66      STORE_NAME                      5: List
        68      IMPORT_FROM                     6: Union
        70      STORE_NAME                      6: Union
        72      IMPORT_FROM                     7: TYPE_CHECKING
        74      STORE_NAME                      7: TYPE_CHECKING
        76      POP_TOP                         
        78      LOAD_CONST                      6: 0
        80      LOAD_CONST                      8: None
        82      IMPORT_NAME                     8: os
        84      STORE_NAME                      8: os
        86      LOAD_CONST                      6: 0
        88      LOAD_CONST                      8: None
        90      IMPORT_NAME                     9: struct
        92      STORE_NAME                      9: struct
        94      LOAD_CONST                      6: 0
        96      LOAD_CONST                      9: ('datetime',)
        98      IMPORT_NAME                     10: datetime
        100     IMPORT_FROM                     10: datetime
        102     STORE_NAME                      10: datetime
        104     POP_TOP                         
        106     LOAD_NAME                       7: TYPE_CHECKING
        108     POP_JUMP_IF_FALSE               8 (to 126)
        110     LOAD_CONST                      4: 3
        112     LOAD_CONST                      10: ('TypePhoto', 'TypeUser')
        114     IMPORT_NAME                     11: tl.types
        116     IMPORT_FROM                     12: TypePhoto
        118     STORE_NAME                      12: TypePhoto
        120     IMPORT_FROM                     13: TypeUser
        122     STORE_NAME                      13: TypeUser
        124     POP_TOP                         
        126     PUSH_NULL                       
        128     LOAD_BUILD_CLASS                
        130     LOAD_CONST                      11: <CODE> Photo
        132     MAKE_FUNCTION                   0
        134     LOAD_CONST                      12: 'Photo'
        136     LOAD_NAME                       2: TLObject
        138     CALL                            3
        146     STORE_NAME                      14: Photo
        148     PUSH_NULL                       
        150     LOAD_BUILD_CLASS                
        152     LOAD_CONST                      13: <CODE> Photos
        154     MAKE_FUNCTION                   0
        156     LOAD_CONST                      14: 'Photos'
        158     LOAD_NAME                       2: TLObject
        160     CALL                            3
        168     STORE_NAME                      15: Photos
        170     PUSH_NULL                       
        172     LOAD_BUILD_CLASS                
        174     LOAD_CONST                      15: <CODE> PhotosSlice
        176     MAKE_FUNCTION                   0
        178     LOAD_CONST                      16: 'PhotosSlice'
        180     LOAD_NAME                       2: TLObject
        182     CALL                            3
        190     STORE_NAME                      16: PhotosSlice
        192     LOAD_CONST                      8: None
        194     NOP                             
        196     NOP                             
        198     NOP                             
        200     JUMP_FORWARD                    19 (to 240)
        208     POP_TOP                         
        210     RETURN_CONST                    8: None
        212     PUSH_EXC_INFO                   
        214     PUSH_NULL                       
        216     LOAD_CONST                      17: '__pyarmor_exit_40994__'
        218     NOP                             
        220     LOAD_CONST                      2: b'<COAddr>\x05\x00\x00\x1a\xba\x00\x00\x00\x00\x00\x00\x00\x00\x00\x00\x00\x00\x00\x00\x00'
        222     CALL                            1
        230     POP_TOP                         
        232     RERAISE                         0
        234     COPY                            3
        236     POP_EXCEPT                      
        238     RERAISE                         1
        240     PUSH_NULL                       
        242     LOAD_CONST                      17: '__pyarmor_exit_40994__'
        244     LOAD_CONST                      2: b'<COAddr>\x05\x00\x00\x1a\xba\x00\x00\x00\x00\x00\x00\x00\x00\x00\x00\x00\x00\x00\x00\x00'
        246     BUILD_TUPLE                     1
        248     CALL_FUNCTION_EX                0
        250     POP_TOP                         
        252     RETURN_VALUE                    
    [Exception Table]
        26 to 192 -> 212 [0] 
        212 to 234 -> 234 [1] lasti
