#decoded by lolz.live/mrpenny / t.me/zeus_jackpot
# ================================
# Примечания по Pyarmor:
# - Байт-код и объекты кода Pyarmor соответствуют стандартному Python, но присутствуют специальные вызовы функций среды выполнения (runtime) Pyarmor.
# - Вызовы строк — это не ошибки, а маркеры, которые обрабатываются Pyarmor во время выполнения.
#
# Руководство по декомпиляции (без среды выполнения):
# 1. Игнорируйте зашифрованные байты после `#`; используйте только строку до `#`.
# 2. Удалите "__pyarmor_enter_xxx__"(b"<COAddr>...") и "__pyarmor_leave_xxx__"(b"<COAddr>...") (пролог/эпилог).
# 3. "__pyarmor_assert_xxx__"(A) не является настоящим оператором assert.
#    - Если A — это имя или читаемая строка: замените на A.
#    - Если A — это (X, "Y"): замените на X.Y.
#    - Если A — это (X, "Y", Z): замените на X.Y = Z.
#    - В противном случае: выберите наиболее подходящую/логичную замену.
# 4. "__pyarmor_bcc_xxx__"(...) указывает на машинный (нативный) код; тело функции недоступно. Добавьте комментарий.
# ================================

[Code]
    File Name: <frozen multithon.tl.types.premium>
    Object Name: <module>
    Qualified Name: <module>
    Arg Count: 0
    Pos Only Arg Count: 0
    KW Only Arg Count: 0
    Stack Size: 5
    Flags: 0x20000000 (CO_PYARMOR_OBFUSCATED)
    [Names]
        '__assert_armored__'
        'tl.tlobject'
        'TLObject'
        'typing'
        'Optional'
        'List'
        'Union'
        'TYPE_CHECKING'
        'os'
        'struct'
        'datetime'
        'tl.types'
        'TypeBoost'
        'TypeChat'
        'TypeMyBoost'
        'TypePrepaidGiveaway'
        'TypeStatsPercentValue'
        'TypeUser'
        'BoostsList'
        'BoostsStatus'
        'MyBoosts'
    [Locals+Names]
    [Constants]
        '__pyarmor_assert_41040__'
        '__pyarmor_enter_41041__'
        b'<COAddr>\x05\x00\x00\x1a\xca\x00\x00\x00\x00\x00\x00\x00\x00\x00\x00\x00\x00\x00\x00\x00'
        "File generated by TLObjects' generator. All changes will be ERASED"   # b'\x81\xc4\x11\x1f6\xba\xb9\xd7\x15\xff\x1f\xc1x\xe9\xfc\xc5\rD\xfb\x93\x86\xe4L\xc6\x00l\xb7OG\xf1\x19\xe04W2\x0c\x8c\xc5\xa6`X\xc8\xf4Q\x9d\xdb\x07F9\xeaS\xe8\xc7g\x0f\xe1;\xab\x99\x18Xn\x03rdm!'
        3
        (
            'TLObject'
        )
        0
        (
            'Optional'
            'List'
            'Union'
            'TYPE_CHECKING'
        )
        None
        (
            'datetime'
        )
        (
            'TypeBoost'
            'TypeChat'
            'TypeMyBoost'
            'TypePrepaidGiveaway'
            'TypeStatsPercentValue'
            'TypeUser'
        )
        [Code]
            File Name: <frozen multithon.tl.types.premium>
            Object Name: BoostsList
            Qualified Name: BoostsList
            Arg Count: 0
            Pos Only Arg Count: 0
            KW Only Arg Count: 0
            Stack Size: 10
            Flags: 0x20000000 (CO_PYARMOR_OBFUSCATED)
            [Names]
                '__name__'
                '__module__'
                '__qualname__'
                '__assert_armored__'
                'CONSTRUCTOR_ID'
                'SUBCLASS_OF_ID'
                'int'
                'List'
                'Optional'
                'str'
                '__init__'
                'to_dict'
                '_bytes'
                'classmethod'
                'from_reader'
            [Locals+Names]
            [Constants]
                'BoostsList'
                '__pyarmor_assert_41043__'
                '__pyarmor_enter_41044__'
                b'<COAddr>\x05\x00\x00"r\x00\x00\x00\x00\x00\x00\x00\x00\x00\x00\x00\x00\x00\x00\x00'
                0x86F8613C
                573941949
                None
                'count'
                'boosts'
                'TypeBoost'   # b'\x81\xd6\x01\x036\xd8\xb1\xdd\x08\xee'
                'users'
                'TypeUser'
                'next_offset'
                [Code]
                    File Name: <frozen multithon.tl.types.premium>
                    Object Name: __init__
                    Qualified Name: BoostsList.__init__
                    Arg Count: 5
                    Pos Only Arg Count: 0
                    KW Only Arg Count: 0
                    Stack Size: 5
                    Flags: 0x20000003 (CO_OPTIMIZED | CO_NEWLOCALS | CO_PYARMOR_OBFUSCATED)
                    [Names]
                        'count'
                        'boosts'
                        'users'
                        'next_offset'
                    [Locals+Names]
                        'self'
                        'count'
                        'boosts'
                        'users'
                        'next_offset'
                        '__assert_armored__'
                    [Constants]
                        '\n        Constructor for premium.BoostsList: Instance of BoostsList.\n        '
                        '__pyarmor_assert_41046__'
                        '__pyarmor_enter_41047__'
                        b'<COAddr>\x07\x00\x00\x1aN\x00\x00\x00\x00\x00\x00\x00\x00\x00\x00\x00\x00\x00\x00\x00'
                        '__pyarmor_exit_41048__'
                        None
                    [Disassembly]
                        0       NOP                             
                        2       NOP                             
                        4       PUSH_NULL                       
                        6       LOAD_CONST                      2: '__pyarmor_enter_41047__'
                        8       LOAD_CONST                      3: b'<COAddr>\x07\x00\x00\x1aN\x00\x00\x00\x00\x00\x00\x00\x00\x00\x00\x00\x00\x00\x00\x00'
                        10      BUILD_TUPLE                     1
                        12      CALL_FUNCTION_EX                0
                        14      POP_TOP                         
                        16      RESUME                          0
                        18      NOP                             
                        20      NOP                             
                        22      NOP                             
                        24      NOP                             
                        26      NOP                             
                        28      LOAD_FAST                       1: count
                        30      LOAD_FAST                       0: self
                        32      STORE_ATTR                      0: count
                        42      LOAD_FAST                       2: boosts
                        44      LOAD_FAST                       0: self
                        46      STORE_ATTR                      1: boosts
                        56      LOAD_FAST                       3: users
                        58      LOAD_FAST                       0: self
                        60      STORE_ATTR                      2: users
                        70      LOAD_FAST                       4: next_offset
                        72      LOAD_FAST                       0: self
                        74      STORE_ATTR                      3: next_offset
                        84      LOAD_CONST                      5: None
                        86      NOP                             
                        88      NOP                             
                        90      NOP                             
                        92      JUMP_FORWARD                    19 (to 132)
                        100     POP_TOP                         
                        102     RETURN_CONST                    5: None
                        104     PUSH_EXC_INFO                   
                        106     PUSH_NULL                       
                        108     LOAD_CONST                      4: '__pyarmor_exit_41048__'
                        110     NOP                             
                        112     LOAD_CONST                      3: b'<COAddr>\x07\x00\x00\x1aN\x00\x00\x00\x00\x00\x00\x00\x00\x00\x00\x00\x00\x00\x00\x00'
                        114     CALL                            1
                        122     POP_TOP                         
                        124     RERAISE                         0
                        126     COPY                            3
                        128     POP_EXCEPT                      
                        130     RERAISE                         1
                        132     PUSH_NULL                       
                        134     LOAD_CONST                      4: '__pyarmor_exit_41048__'
                        136     LOAD_CONST                      3: b'<COAddr>\x07\x00\x00\x1aN\x00\x00\x00\x00\x00\x00\x00\x00\x00\x00\x00\x00\x00\x00\x00'
                        138     BUILD_TUPLE                     1
                        140     CALL_FUNCTION_EX                0
                        142     POP_TOP                         
                        144     RETURN_VALUE                    
                    [Exception Table]
                        28 to 84 -> 104 [0] 
                        104 to 126 -> 126 [1] lasti
                [Code]
                    File Name: <frozen multithon.tl.types.premium>
                    Object Name: to_dict
                    Qualified Name: BoostsList.to_dict
                    Arg Count: 1
                    Pos Only Arg Count: 0
                    KW Only Arg Count: 0
                    Stack Size: 14
                    Flags: 0x20000003 (CO_OPTIMIZED | CO_NEWLOCALS | CO_PYARMOR_OBFUSCATED)
                    [Names]
                        'count'
                        'boosts'
                        'isinstance'
                        'TLObject'
                        'to_dict'
                        'users'
                        'next_offset'
                    [Locals+Names]
                        'self'
                        '__assert_armored__'
                        '_var_var_0'
                    [Constants]
                        None
                        '__pyarmor_assert_41049__'
                        '__pyarmor_enter_41050__'
                        b'<COAddr>\x05\x00\x00\x1a\x98\x01\x00\x00\x00\x00\x00\x00\x00\x00\x00\x00\x00\x00\x00\x00'
                        '_'
                        'BoostsList'   # b'\x81\xc0\x17\x1c \xee\xad\xfe\x12\xe9\x19'
                        'count'
                        'boosts'
                        'users'
                        'next_offset'   # b"\x81\xec\x1d\x0b'\xc5\xb1\xd4\x1d\xe9\x08\xd4"
                        '__pyarmor_exit_41051__'
                    [Disassembly]
                        0       NOP                             
                        2       NOP                             
                        4       PUSH_NULL                       
                        6       LOAD_CONST                      2: '__pyarmor_enter_41050__'
                        8       LOAD_CONST                      3: b'<COAddr>\x05\x00\x00\x1a\x98\x01\x00\x00\x00\x00\x00\x00\x00\x00\x00\x00\x00\x00\x00\x00'
                        10      BUILD_TUPLE                     1
                        12      CALL_FUNCTION_EX                0
                        14      POP_TOP                         
                        16      RESUME                          0
                        18      NOP                             
                        20      NOP                             
                        22      NOP                             
                        24      NOP                             
                        26      NOP                             
                        28      LOAD_CONST                      4: '_'
                        30      PUSH_NULL                       
                        32      LOAD_CONST                      1: '__pyarmor_assert_41049__'
                        34      LOAD_CONST                      5: 'BoostsList'   # b'\x81\xc0\x17\x1c \xee\xad\xfe\x12\xe9\x19'
                        36      CALL                            1
                        44      LOAD_CONST                      6: 'count'
                        46      LOAD_FAST                       0: self
                        48      LOAD_ATTR                       0: count
                        68      LOAD_CONST                      7: 'boosts'
                        70      LOAD_FAST                       0: self
                        72      LOAD_ATTR                       2: boosts
                        92      POP_JUMP_IF_NOT_NONE            2 (to 98)
                        94      BUILD_LIST                      0
                        96      JUMP_FORWARD                    57 (to 212)
                        98      LOAD_FAST                       0: self
                        100     LOAD_ATTR                       2: boosts
                        120     GET_ITER                        
                        122     LOAD_FAST_AND_CLEAR             2: _var_var_0
                        124     SWAP                            2
                        126     BUILD_LIST                      0
                        128     SWAP                            2
                        130     FOR_ITER                        36 (to 204)
                        134     STORE_FAST                      2: _var_var_0
                        136     LOAD_GLOBAL                     5: NULL + isinstance
                        146     LOAD_FAST                       2: _var_var_0
                        148     LOAD_GLOBAL                     6: TLObject
                        158     CALL                            2
                        166     POP_JUMP_IF_FALSE               16 (to 200)
                        168     LOAD_FAST                       2: _var_var_0
                        170     LOAD_ATTR                       9: to_dict
                        190     CALL                            0
                        198     JUMP_FORWARD                    1 (to 202)
                        200     LOAD_FAST                       2: _var_var_0
                        202     LIST_APPEND                     2
                        204     JUMP_BACKWARD                   38 (to 130)
                        206     END_FOR                         
                        208     SWAP                            2
                        210     STORE_FAST                      2: _var_var_0
                        212     LOAD_CONST                      8: 'users'
                        214     LOAD_FAST                       0: self
                        216     LOAD_ATTR                       10: users
                        236     POP_JUMP_IF_NOT_NONE            2 (to 242)
                        238     BUILD_LIST                      0
                        240     JUMP_FORWARD                    57 (to 356)
                        242     LOAD_FAST                       0: self
                        244     LOAD_ATTR                       10: users
                        264     GET_ITER                        
                        266     LOAD_FAST_AND_CLEAR             2: _var_var_0
                        268     SWAP                            2
                        270     BUILD_LIST                      0
                        272     SWAP                            2
                        274     FOR_ITER                        36 (to 348)
                        278     STORE_FAST                      2: _var_var_0
                        280     LOAD_GLOBAL                     5: NULL + isinstance
                        290     LOAD_FAST                       2: _var_var_0
                        292     LOAD_GLOBAL                     6: TLObject
                        302     CALL                            2
                        310     POP_JUMP_IF_FALSE               16 (to 344)
                        312     LOAD_FAST                       2: _var_var_0
                        314     LOAD_ATTR                       9: to_dict
                        334     CALL                            0
                        342     JUMP_FORWARD                    1 (to 346)
                        344     LOAD_FAST                       2: _var_var_0
                        346     LIST_APPEND                     2
                        348     JUMP_BACKWARD                   38 (to 274)
                        350     END_FOR                         
                        352     SWAP                            2
                        354     STORE_FAST                      2: _var_var_0
                        356     PUSH_NULL                       
                        358     LOAD_CONST                      1: '__pyarmor_assert_41049__'
                        360     LOAD_CONST                      9: 'next_offset'   # b"\x81\xec\x1d\x0b'\xc5\xb1\xd4\x1d\xe9\x08\xd4"
                        362     CALL                            1
                        370     LOAD_FAST                       0: self
                        372     LOAD_ATTR                       12: next_offset
                        392     BUILD_MAP                       5
                        394     NOP                             
                        396     NOP                             
                        398     NOP                             
                        400     JUMP_FORWARD                    30 (to 462)
                        402     CALL                            1
                        410     POP_TOP                         
                        412     RETURN_VALUE                    
                        414     SWAP                            2
                        416     POP_TOP                         
                        418     SWAP                            2
                        420     STORE_FAST                      2: _var_var_0
                        422     RERAISE                         0
                        424     SWAP                            2
                        426     POP_TOP                         
                        428     SWAP                            2
                        430     STORE_FAST                      2: _var_var_0
                        432     RERAISE                         0
                        434     PUSH_EXC_INFO                   
                        436     PUSH_NULL                       
                        438     LOAD_CONST                      10: '__pyarmor_exit_41051__'
                        440     NOP                             
                        442     LOAD_CONST                      3: b'<COAddr>\x05\x00\x00\x1a\x98\x01\x00\x00\x00\x00\x00\x00\x00\x00\x00\x00\x00\x00\x00\x00'
                        444     CALL                            1
                        452     POP_TOP                         
                        454     RERAISE                         0
                        456     COPY                            3
                        458     POP_EXCEPT                      
                        460     RERAISE                         1
                        462     PUSH_NULL                       
                        464     LOAD_CONST                      10: '__pyarmor_exit_41051__'
                        466     LOAD_CONST                      3: b'<COAddr>\x05\x00\x00\x1a\x98\x01\x00\x00\x00\x00\x00\x00\x00\x00\x00\x00\x00\x00\x00\x00'
                        468     BUILD_TUPLE                     1
                        470     CALL_FUNCTION_EX                0
                        472     POP_TOP                         
                        474     RETURN_VALUE                    
                    [Exception Table]
                        28 to 126 -> 434 [0] 
                        126 to 208 -> 414 [7] 
                        208 to 270 -> 434 [0] 
                        270 to 352 -> 424 [9] 
                        352 to 394 -> 434 [0] 
                        414 to 434 -> 434 [0] 
                        434 to 456 -> 456 [1] lasti
                [Code]
                    File Name: <frozen multithon.tl.types.premium>
                    Object Name: _bytes
                    Qualified Name: BoostsList._bytes
                    Arg Count: 1
                    Pos Only Arg Count: 0
                    KW Only Arg Count: 0
                    Stack Size: 16
                    Flags: 0x20000003 (CO_OPTIMIZED | CO_NEWLOCALS | CO_PYARMOR_OBFUSCATED)
                    [Names]
                        'join'
                        'struct'
                        'pack'
                        'next_offset'
                        'count'
                        'len'
                        'boosts'
                        'serialize_bytes'
                        'users'
                    [Locals+Names]
                        'self'
                        '__assert_armored__'
                    [Constants]
                        None
                        '__pyarmor_assert_41052__'
                        '__pyarmor_enter_41053__'
                        b'<COAddr>\x05\x00\x00\x1al\x02\x00\x00\x00\x00\x00\x00\x00\x00\x00\x00\x00\x00\x00\x00'
                        b''
                        b'<a\xf8\x86'
                        '<I'
                        False
                        0
                        1
                        '<i'
                        b'\x15\xc4\xb5\x1c'
                        [Code]
                            File Name: <frozen multithon.tl.types.premium>
                            Object Name: <genexpr>
                            Qualified Name: BoostsList._bytes.<locals>.<genexpr>
                            Arg Count: 1
                            Pos Only Arg Count: 0
                            KW Only Arg Count: 0
                            Stack Size: 3
                            Flags: 0x00000033 (CO_OPTIMIZED | CO_NEWLOCALS | CO_NESTED | CO_GENERATOR)
                            [Names]
                                '_bytes'
                            [Locals+Names]
                                '.0'
                                '_var_var_0'
                            [Constants]
                                None
                            [Disassembly]
                                0       RETURN_GENERATOR                
                                2       POP_TOP                         
                                4       RESUME                          0
                                6       LOAD_FAST                       0: .0
                                8       FOR_ITER                        20 (to 50)
                                12      STORE_FAST                      1: _var_var_0
                                14      LOAD_FAST                       1: _var_var_0
                                16      LOAD_ATTR                       1: _bytes
                                36      CALL                            0
                                44      YIELD_VALUE                     1
                                46      RESUME                          1
                                48      POP_TOP                         
                                50      JUMP_BACKWARD                   22 (to 8)
                                52      END_FOR                         
                                54      RETURN_CONST                    0: None
                                56      CALL_INTRINSIC_1                3 (INTRINSIC_STOPITERATION_ERROR)
                                58      RERAISE                         1
                            [Exception Table]
                                4 to 56 -> 56 [0] lasti
                        [Code]
                            File Name: <frozen multithon.tl.types.premium>
                            Object Name: <genexpr>
                            Qualified Name: BoostsList._bytes.<locals>.<genexpr>
                            Arg Count: 1
                            Pos Only Arg Count: 0
                            KW Only Arg Count: 0
                            Stack Size: 3
                            Flags: 0x00000033 (CO_OPTIMIZED | CO_NEWLOCALS | CO_NESTED | CO_GENERATOR)
                            [Names]
                                '_bytes'
                            [Locals+Names]
                                '.0'
                                '_var_var_0'
                            [Constants]
                                None
                            [Disassembly]
                                0       RETURN_GENERATOR                
                                2       POP_TOP                         
                                4       RESUME                          0
                                6       LOAD_FAST                       0: .0
                                8       FOR_ITER                        20 (to 50)
                                12      STORE_FAST                      1: _var_var_0
                                14      LOAD_FAST                       1: _var_var_0
                                16      LOAD_ATTR                       1: _bytes
                                36      CALL                            0
                                44      YIELD_VALUE                     1
                                46      RESUME                          1
                                48      POP_TOP                         
                                50      JUMP_BACKWARD                   22 (to 8)
                                52      END_FOR                         
                                54      RETURN_CONST                    0: None
                                56      CALL_INTRINSIC_1                3 (INTRINSIC_STOPITERATION_ERROR)
                                58      RERAISE                         1
                            [Exception Table]
                                4 to 56 -> 56 [0] lasti
                        '__pyarmor_exit_41054__'
                    [Disassembly]
                        0       NOP                             
                        2       NOP                             
                        4       PUSH_NULL                       
                        6       LOAD_CONST                      2: '__pyarmor_enter_41053__'
                        8       LOAD_CONST                      3: b'<COAddr>\x05\x00\x00\x1al\x02\x00\x00\x00\x00\x00\x00\x00\x00\x00\x00\x00\x00\x00\x00'
                        10      BUILD_TUPLE                     1
                        12      CALL_FUNCTION_EX                0
                        14      POP_TOP                         
                        16      RESUME                          0
                        18      NOP                             
                        20      NOP                             
                        22      NOP                             
                        24      NOP                             
                        26      NOP                             
                        28      LOAD_CONST                      4: b''
                        30      LOAD_ATTR                       1: join
                        50      LOAD_CONST                      5: b'<a\xf8\x86'
                        52      LOAD_GLOBAL                     3: NULL + struct
                        62      LOAD_ATTR                       4: pack
                        82      LOAD_CONST                      6: '<I'
                        84      LOAD_FAST                       0: self
                        86      LOAD_ATTR                       6: next_offset
                        106     POP_JUMP_IF_NONE                14 (to 136)
                        108     LOAD_FAST                       0: self
                        110     LOAD_ATTR                       6: next_offset
                        130     LOAD_CONST                      7: False
                        132     IS_OP                           0 (is)
                        134     POP_JUMP_IF_FALSE               2 (to 140)
                        136     LOAD_CONST                      8: 0
                        138     JUMP_FORWARD                    1 (to 142)
                        140     LOAD_CONST                      9: 1
                        142     CALL                            2
                        150     LOAD_GLOBAL                     3: NULL + struct
                        160     LOAD_ATTR                       4: pack
                        180     LOAD_CONST                      10: '<i'
                        182     LOAD_FAST                       0: self
                        184     LOAD_ATTR                       8: count
                        204     CALL                            2
                        212     LOAD_CONST                      11: b'\x15\xc4\xb5\x1c'
                        214     LOAD_GLOBAL                     3: NULL + struct
                        224     LOAD_ATTR                       4: pack
                        244     LOAD_CONST                      10: '<i'
                        246     LOAD_GLOBAL                     11: NULL + len
                        256     LOAD_FAST                       0: self
                        258     LOAD_ATTR                       12: boosts
                        278     CALL                            1
                        286     CALL                            2
                        294     LOAD_CONST                      4: b''
                        296     LOAD_ATTR                       1: join
                        316     LOAD_CONST                      12: <CODE> <genexpr>
                        318     MAKE_FUNCTION                   0
                        320     LOAD_FAST                       0: self
                        322     LOAD_ATTR                       12: boosts
                        342     GET_ITER                        
                        344     CALL                            0
                        352     CALL                            1
                        360     LOAD_FAST                       0: self
                        362     LOAD_ATTR                       6: next_offset
                        382     POP_JUMP_IF_NONE                14 (to 412)
                        384     LOAD_FAST                       0: self
                        386     LOAD_ATTR                       6: next_offset
                        406     LOAD_CONST                      7: False
                        408     IS_OP                           0 (is)
                        410     POP_JUMP_IF_FALSE               2 (to 416)
                        412     LOAD_CONST                      4: b''
                        414     JUMP_FORWARD                    26 (to 468)
                        416     LOAD_FAST                       0: self
                        418     LOAD_ATTR                       15: serialize_bytes
                        438     LOAD_FAST                       0: self
                        440     LOAD_ATTR                       6: next_offset
                        460     CALL                            1
                        468     LOAD_CONST                      11: b'\x15\xc4\xb5\x1c'
                        470     LOAD_GLOBAL                     3: NULL + struct
                        480     LOAD_ATTR                       4: pack
                        500     LOAD_CONST                      10: '<i'
                        502     LOAD_GLOBAL                     11: NULL + len
                        512     LOAD_FAST                       0: self
                        514     LOAD_ATTR                       16: users
                        534     CALL                            1
                        542     CALL                            2
                        550     LOAD_CONST                      4: b''
                        552     LOAD_ATTR                       1: join
                        572     LOAD_CONST                      13: <CODE> <genexpr>
                        574     MAKE_FUNCTION                   0
                        576     LOAD_FAST                       0: self
                        578     LOAD_ATTR                       16: users
                        598     GET_ITER                        
                        600     CALL                            0
                        608     CALL                            1
                        616     BUILD_TUPLE                     10
                        618     CALL                            1
                        626     NOP                             
                        628     NOP                             
                        630     NOP                             
                        632     JUMP_FORWARD                    20 (to 674)
                        634     CALL                            1
                        642     POP_TOP                         
                        644     RETURN_VALUE                    
                        646     PUSH_EXC_INFO                   
                        648     PUSH_NULL                       
                        650     LOAD_CONST                      14: '__pyarmor_exit_41054__'
                        652     NOP                             
                        654     LOAD_CONST                      3: b'<COAddr>\x05\x00\x00\x1al\x02\x00\x00\x00\x00\x00\x00\x00\x00\x00\x00\x00\x00\x00\x00'
                        656     CALL                            1
                        664     POP_TOP                         
                        666     RERAISE                         0
                        668     COPY                            3
                        670     POP_EXCEPT                      
                        672     RERAISE                         1
                        674     PUSH_NULL                       
                        676     LOAD_CONST                      14: '__pyarmor_exit_41054__'
                        678     LOAD_CONST                      3: b'<COAddr>\x05\x00\x00\x1al\x02\x00\x00\x00\x00\x00\x00\x00\x00\x00\x00\x00\x00\x00\x00'
                        680     BUILD_TUPLE                     1
                        682     CALL_FUNCTION_EX                0
                        684     POP_TOP                         
                        686     RETURN_VALUE                    
                    [Exception Table]
                        28 to 626 -> 646 [0] 
                        646 to 668 -> 668 [1] lasti
                [Code]
                    File Name: <frozen multithon.tl.types.premium>
                    Object Name: from_reader
                    Qualified Name: BoostsList.from_reader
                    Arg Count: 2
                    Pos Only Arg Count: 0
                    KW Only Arg Count: 0
                    Stack Size: 6
                    Flags: 0x20000003 (CO_OPTIMIZED | CO_NEWLOCALS | CO_PYARMOR_OBFUSCATED)
                    [Names]
                        'read_int'
                        'range'
                        'tgread_object'
                        'append'
                        'tgread_string'
                    [Locals+Names]
                        'cls'
                        'reader'
                        '__assert_armored__'
                        '_var_var_1'
                        '_var_var_2'
                        '_var_var_3'
                        '_var_var_4'
                        '_var_var_5'
                        '_var_var_6'
                        '_var_var_7'
                    [Constants]
                        None
                        '__pyarmor_assert_41055__'
                        '__pyarmor_enter_41056__'
                        b'<COAddr>\x07\x00\x00\x1a\xe0\x01\x00\x00\x00\x00\x00\x00\x00\x00\x00\x00\x00\x00\x00\x00'
                        1
                        (
                            'count'
                            'boosts'
                            'users'
                            'next_offset'
                        )
                        '__pyarmor_exit_41057__'
                    [Disassembly]
                        0       NOP                             
                        2       NOP                             
                        4       PUSH_NULL                       
                        6       LOAD_CONST                      2: '__pyarmor_enter_41056__'
                        8       LOAD_CONST                      3: b'<COAddr>\x07\x00\x00\x1a\xe0\x01\x00\x00\x00\x00\x00\x00\x00\x00\x00\x00\x00\x00\x00\x00'
                        10      BUILD_TUPLE                     1
                        12      CALL_FUNCTION_EX                0
                        14      POP_TOP                         
                        16      RESUME                          0
                        18      NOP                             
                        20      NOP                             
                        22      NOP                             
                        24      NOP                             
                        26      NOP                             
                        28      LOAD_FAST                       1: reader
                        30      LOAD_ATTR                       1: read_int
                        50      CALL                            0
                        58      STORE_FAST                      3: _var_var_1
                        60      LOAD_FAST                       1: reader
                        62      LOAD_ATTR                       1: read_int
                        82      CALL                            0
                        90      STORE_FAST                      4: _var_var_2
                        92      LOAD_FAST                       1: reader
                        94      LOAD_ATTR                       1: read_int
                        114     CALL                            0
                        122     POP_TOP                         
                        124     BUILD_LIST                      0
                        126     STORE_FAST                      5: _var_var_3
                        128     LOAD_GLOBAL                     3: NULL + range
                        138     LOAD_FAST                       1: reader
                        140     LOAD_ATTR                       1: read_int
                        160     CALL                            0
                        168     CALL                            1
                        176     GET_ITER                        
                        178     FOR_ITER                        35 (to 250)
                        182     STORE_FAST                      6: _var_var_4
                        184     LOAD_FAST                       1: reader
                        186     LOAD_ATTR                       5: tgread_object
                        206     CALL                            0
                        214     STORE_FAST                      7: _var_var_5
                        216     LOAD_FAST                       5: _var_var_3
                        218     LOAD_ATTR                       7: append
                        238     LOAD_FAST                       7: _var_var_5
                        240     CALL                            1
                        248     POP_TOP                         
                        250     JUMP_BACKWARD                   37 (to 178)
                        252     END_FOR                         
                        254     LOAD_FAST                       3: _var_var_1
                        256     LOAD_CONST                      4: 1
                        258     BINARY_OP                       1 (&)
                        262     POP_JUMP_IF_FALSE               17 (to 298)
                        264     LOAD_FAST                       1: reader
                        266     LOAD_ATTR                       9: tgread_string
                        286     CALL                            0
                        294     STORE_FAST                      8: _var_var_6
                        296     JUMP_FORWARD                    2 (to 302)
                        298     LOAD_CONST                      0: None
                        300     STORE_FAST                      8: _var_var_6
                        302     LOAD_FAST                       1: reader
                        304     LOAD_ATTR                       1: read_int
                        324     CALL                            0
                        332     POP_TOP                         
                        334     BUILD_LIST                      0
                        336     STORE_FAST                      9: _var_var_7
                        338     LOAD_GLOBAL                     3: NULL + range
                        348     LOAD_FAST                       1: reader
                        350     LOAD_ATTR                       1: read_int
                        370     CALL                            0
                        378     CALL                            1
                        386     GET_ITER                        
                        388     FOR_ITER                        35 (to 460)
                        392     STORE_FAST                      6: _var_var_4
                        394     LOAD_FAST                       1: reader
                        396     LOAD_ATTR                       5: tgread_object
                        416     CALL                            0
                        424     STORE_FAST                      7: _var_var_5
                        426     LOAD_FAST                       9: _var_var_7
                        428     LOAD_ATTR                       7: append
                        448     LOAD_FAST                       7: _var_var_5
                        450     CALL                            1
                        458     POP_TOP                         
                        460     JUMP_BACKWARD                   37 (to 388)
                        462     END_FOR                         
                        464     PUSH_NULL                       
                        466     LOAD_FAST                       0: cls
                        468     LOAD_FAST                       4: _var_var_2
                        470     LOAD_FAST                       5: _var_var_3
                        472     LOAD_FAST                       9: _var_var_7
                        474     LOAD_FAST                       8: _var_var_6
                        476     KW_NAMES                        5: ('count', 'boosts', 'users', 'next_offset')
                        478     CALL                            4
                        486     NOP                             
                        488     NOP                             
                        490     NOP                             
                        492     JUMP_FORWARD                    20 (to 534)
                        494     CALL                            1
                        502     POP_TOP                         
                        504     RETURN_VALUE                    
                        506     PUSH_EXC_INFO                   
                        508     PUSH_NULL                       
                        510     LOAD_CONST                      6: '__pyarmor_exit_41057__'
                        512     NOP                             
                        514     LOAD_CONST                      3: b'<COAddr>\x07\x00\x00\x1a\xe0\x01\x00\x00\x00\x00\x00\x00\x00\x00\x00\x00\x00\x00\x00\x00'
                        516     CALL                            1
                        524     POP_TOP                         
                        526     RERAISE                         0
                        528     COPY                            3
                        530     POP_EXCEPT                      
                        532     RERAISE                         1
                        534     PUSH_NULL                       
                        536     LOAD_CONST                      6: '__pyarmor_exit_41057__'
                        538     LOAD_CONST                      3: b'<COAddr>\x07\x00\x00\x1a\xe0\x01\x00\x00\x00\x00\x00\x00\x00\x00\x00\x00\x00\x00\x00\x00'
                        540     BUILD_TUPLE                     1
                        542     CALL_FUNCTION_EX                0
                        544     POP_TOP                         
                        546     RETURN_VALUE                    
                    [Exception Table]
                        28 to 486 -> 506 [0] 
                        506 to 528 -> 528 [1] lasti
                '__pyarmor_exit_41045__'
                (
                    None
                )
            [Disassembly]
                0       NOP                             
                2       LOAD_NAME                       0: __name__
                4       STORE_NAME                      1: __module__
                6       LOAD_CONST                      0: 'BoostsList'
                8       STORE_NAME                      2: __qualname__
                10      NOP                             
                12      PUSH_NULL                       
                14      LOAD_CONST                      2: '__pyarmor_enter_41044__'
                16      LOAD_CONST                      3: b'<COAddr>\x05\x00\x00"r\x00\x00\x00\x00\x00\x00\x00\x00\x00\x00\x00\x00\x00\x00\x00'
                18      BUILD_TUPLE                     1
                20      CALL_FUNCTION_EX                0
                22      POP_TOP                         
                24      RESUME                          0
                26      NOP                             
                28      NOP                             
                30      NOP                             
                32      NOP                             
                34      NOP                             
                36      LOAD_CONST                      4: 0x86F8613C
                38      STORE_NAME                      4: CONSTRUCTOR_ID
                40      LOAD_CONST                      5: 573941949
                42      STORE_NAME                      5: SUBCLASS_OF_ID
                44      LOAD_CONST                      18: (None,)
                46      LOAD_CONST                      7: 'count'
                48      LOAD_NAME                       6: int
                50      LOAD_CONST                      8: 'boosts'
                52      LOAD_NAME                       7: List
                54      PUSH_NULL                       
                56      LOAD_CONST                      1: '__pyarmor_assert_41043__'
                58      LOAD_CONST                      9: 'TypeBoost'   # b'\x81\xd6\x01\x036\xd8\xb1\xdd\x08\xee'
                60      CALL                            1
                68      BINARY_SUBSCR                   
                72      LOAD_CONST                      10: 'users'
                74      LOAD_NAME                       7: List
                76      LOAD_CONST                      11: 'TypeUser'
                78      BINARY_SUBSCR                   
                82      LOAD_CONST                      12: 'next_offset'
                84      LOAD_NAME                       8: Optional
                86      LOAD_NAME                       9: str
                88      BINARY_SUBSCR                   
                92      BUILD_TUPLE                     8
                94      LOAD_CONST                      13: <CODE> __init__
                96      MAKE_FUNCTION                   5
                98      STORE_NAME                      10: __init__
                100     LOAD_CONST                      14: <CODE> to_dict
                102     MAKE_FUNCTION                   0
                104     STORE_NAME                      11: to_dict
                106     LOAD_CONST                      15: <CODE> _bytes
                108     MAKE_FUNCTION                   0
                110     STORE_NAME                      12: _bytes
                112     LOAD_NAME                       13: classmethod
                114     LOAD_CONST                      16: <CODE> from_reader
                116     MAKE_FUNCTION                   0
                118     CALL                            0
                126     STORE_NAME                      14: from_reader
                128     LOAD_CONST                      6: None
                130     NOP                             
                132     NOP                             
                134     NOP                             
                136     JUMP_FORWARD                    19 (to 176)
                144     POP_TOP                         
                146     RETURN_CONST                    6: None
                148     PUSH_EXC_INFO                   
                150     PUSH_NULL                       
                152     LOAD_CONST                      17: '__pyarmor_exit_41045__'
                154     NOP                             
                156     LOAD_CONST                      3: b'<COAddr>\x05\x00\x00"r\x00\x00\x00\x00\x00\x00\x00\x00\x00\x00\x00\x00\x00\x00\x00'
                158     CALL                            1
                166     POP_TOP                         
                168     RERAISE                         0
                170     COPY                            3
                172     POP_EXCEPT                      
                174     RERAISE                         1
                176     PUSH_NULL                       
                178     LOAD_CONST                      17: '__pyarmor_exit_41045__'
                180     LOAD_CONST                      3: b'<COAddr>\x05\x00\x00"r\x00\x00\x00\x00\x00\x00\x00\x00\x00\x00\x00\x00\x00\x00\x00'
                182     BUILD_TUPLE                     1
                184     CALL_FUNCTION_EX                0
                186     POP_TOP                         
                188     RETURN_VALUE                    
            [Exception Table]
                36 to 128 -> 148 [0] 
                148 to 170 -> 170 [1] lasti
        'BoostsList'
        [Code]
            File Name: <frozen multithon.tl.types.premium>
            Object Name: BoostsStatus
            Qualified Name: BoostsStatus
            Arg Count: 0
            Pos Only Arg Count: 0
            KW Only Arg Count: 0
            Stack Size: 23
            Flags: 0x20000000 (CO_PYARMOR_OBFUSCATED)
            [Names]
                '__name__'
                '__module__'
                '__qualname__'
                '__assert_armored__'
                'CONSTRUCTOR_ID'
                'SUBCLASS_OF_ID'
                'int'
                'str'
                'Optional'
                'bool'
                'List'
                '__init__'
                'to_dict'
                '_bytes'
                'classmethod'
                'from_reader'
            [Locals+Names]
            [Constants]
                'BoostsStatus'
                '__pyarmor_assert_41058__'
                '__pyarmor_enter_41059__'
                b'<COAddr>\x07\x00\x00"\xb4\x00\x00\x00\x00\x00\x00\x00\x00\x00\x00\x00\x00\x00\x00\x00'
                1230586490
                0xC31B1AB9
                None
                'level'
                'current_level_boosts'
                'boosts'
                'boost_url'
                'my_boost'
                'gift_boosts'
                'next_level_boosts'
                'premium_audience'
                'TypeStatsPercentValue'   # b'\x81\xd6\x01\x036\xc9\xaa\xd3\x0f\xe9=\xc5~\xef\xfd\x8b\x1bk\xba\xab\xbf\xce'
                'prepaid_giveaways'
                'TypePrepaidGiveaway'   # b'\x81\xd6\x01\x036\xca\xac\xd7\x0b\xfb\x04\xc4K\xe5\xee\x80\x0eJ\xba\xbe'
                'my_boost_slots'
                [Code]
                    File Name: <frozen multithon.tl.types.premium>
                    Object Name: __init__
                    Qualified Name: BoostsStatus.__init__
                    Arg Count: 11
                    Pos Only Arg Count: 0
                    KW Only Arg Count: 0
                    Stack Size: 5
                    Flags: 0x20000003 (CO_OPTIMIZED | CO_NEWLOCALS | CO_PYARMOR_OBFUSCATED)
                    [Names]
                        'level'
                        'current_level_boosts'
                        'boosts'
                        'boost_url'
                        'my_boost'
                        'gift_boosts'
                        'next_level_boosts'
                        'premium_audience'
                        'prepaid_giveaways'
                        'my_boost_slots'
                    [Locals+Names]
                        'self'
                        'level'
                        'current_level_boosts'
                        'boosts'
                        'boost_url'
                        'my_boost'
                        'gift_boosts'
                        'next_level_boosts'
                        'premium_audience'
                        'prepaid_giveaways'
                        'my_boost_slots'
                        '__assert_armored__'
                    [Constants]
                        '\n        Constructor for premium.BoostsStatus: Instance of BoostsStatus.\n        '
                        '__pyarmor_assert_41061__'
                        '__pyarmor_enter_41062__'
                        b'<COAddr>\x07\x00\x00\x1a\xa2\x00\x00\x00\x00\x00\x00\x00\x00\x00\x00\x00\x00\x00\x00\x00'
                        '__pyarmor_exit_41063__'
                        None
                    [Disassembly]
                        0       NOP                             
                        2       NOP                             
                        4       PUSH_NULL                       
                        6       LOAD_CONST                      2: '__pyarmor_enter_41062__'
                        8       LOAD_CONST                      3: b'<COAddr>\x07\x00\x00\x1a\xa2\x00\x00\x00\x00\x00\x00\x00\x00\x00\x00\x00\x00\x00\x00\x00'
                        10      BUILD_TUPLE                     1
                        12      CALL_FUNCTION_EX                0
                        14      POP_TOP                         
                        16      RESUME                          0
                        18      NOP                             
                        20      NOP                             
                        22      NOP                             
                        24      NOP                             
                        26      NOP                             
                        28      LOAD_FAST                       1: level
                        30      LOAD_FAST                       0: self
                        32      STORE_ATTR                      0: level
                        42      LOAD_FAST                       2: current_level_boosts
                        44      LOAD_FAST                       0: self
                        46      STORE_ATTR                      1: current_level_boosts
                        56      LOAD_FAST                       3: boosts
                        58      LOAD_FAST                       0: self
                        60      STORE_ATTR                      2: boosts
                        70      LOAD_FAST                       4: boost_url
                        72      LOAD_FAST                       0: self
                        74      STORE_ATTR                      3: boost_url
                        84      LOAD_FAST                       5: my_boost
                        86      LOAD_FAST                       0: self
                        88      STORE_ATTR                      4: my_boost
                        98      LOAD_FAST                       6: gift_boosts
                        100     LOAD_FAST                       0: self
                        102     STORE_ATTR                      5: gift_boosts
                        112     LOAD_FAST                       7: next_level_boosts
                        114     LOAD_FAST                       0: self
                        116     STORE_ATTR                      6: next_level_boosts
                        126     LOAD_FAST                       8: premium_audience
                        128     LOAD_FAST                       0: self
                        130     STORE_ATTR                      7: premium_audience
                        140     LOAD_FAST                       9: prepaid_giveaways
                        142     LOAD_FAST                       0: self
                        144     STORE_ATTR                      8: prepaid_giveaways
                        154     LOAD_FAST                       10: my_boost_slots
                        156     LOAD_FAST                       0: self
                        158     STORE_ATTR                      9: my_boost_slots
                        168     LOAD_CONST                      5: None
                        170     NOP                             
                        172     NOP                             
                        174     NOP                             
                        176     JUMP_FORWARD                    19 (to 216)
                        184     POP_TOP                         
                        186     RETURN_CONST                    5: None
                        188     PUSH_EXC_INFO                   
                        190     PUSH_NULL                       
                        192     LOAD_CONST                      4: '__pyarmor_exit_41063__'
                        194     NOP                             
                        196     LOAD_CONST                      3: b'<COAddr>\x07\x00\x00\x1a\xa2\x00\x00\x00\x00\x00\x00\x00\x00\x00\x00\x00\x00\x00\x00\x00'
                        198     CALL                            1
                        206     POP_TOP                         
                        208     RERAISE                         0
                        210     COPY                            3
                        212     POP_EXCEPT                      
                        214     RERAISE                         1
                        216     PUSH_NULL                       
                        218     LOAD_CONST                      4: '__pyarmor_exit_41063__'
                        220     LOAD_CONST                      3: b'<COAddr>\x07\x00\x00\x1a\xa2\x00\x00\x00\x00\x00\x00\x00\x00\x00\x00\x00\x00\x00\x00\x00'
                        222     BUILD_TUPLE                     1
                        224     CALL_FUNCTION_EX                0
                        226     POP_TOP                         
                        228     RETURN_VALUE                    
                    [Exception Table]
                        28 to 168 -> 188 [0] 
                        188 to 210 -> 210 [1] lasti
                [Code]
                    File Name: <frozen multithon.tl.types.premium>
                    Object Name: to_dict
                    Qualified Name: BoostsStatus.to_dict
                    Arg Count: 1
                    Pos Only Arg Count: 0
                    KW Only Arg Count: 0
                    Stack Size: 26
                    Flags: 0x20000003 (CO_OPTIMIZED | CO_NEWLOCALS | CO_PYARMOR_OBFUSCATED)
                    [Names]
                        'level'
                        'current_level_boosts'
                        'boosts'
                        'boost_url'
                        'my_boost'
                        'gift_boosts'
                        'next_level_boosts'
                        'isinstance'
                        'premium_audience'
                        'TLObject'
                        'to_dict'
                        'prepaid_giveaways'
                        'my_boost_slots'
                    [Locals+Names]
                        'self'
                        '__assert_armored__'
                        '_var_var_0'
                    [Constants]
                        None
                        '__pyarmor_assert_41064__'
                        '__pyarmor_enter_41065__'
                        b'<COAddr>\x05\x00\x00\x1ax\x02\x00\x00\x00\x00\x00\x00\x00\x00\x00\x00\x00\x00\x00\x00'
                        '_'
                        'BoostsStatus'   # b'\x81\xc0\x17\x1c \xee\xad\xe1\x0f\xfb\x19\xd5\x7f'
                        'level'
                        'current_level_boosts'   # b'\x81\xe1\r\x01!\xff\xb0\xc6$\xf6\x08\xd6i\xe0\xc7\x87\x00R\xa8\xb3\xb9'
                        'boosts'
                        'boost_url'   # b'\x81\xe0\x17\x1c \xee\x81\xc7\t\xf6'
                        'my_boost'
                        'gift_boosts'   # b"\x81\xe5\x11\x15'\xc5\xbc\xdd\x14\xe9\x19\xd3"
                        'next_level_boosts'   # b"\x81\xec\x1d\x0b'\xc5\xb2\xd7\r\xff\x01\xffn\xe3\xf7\x96\x1bN"
                        'premium_audience'   # b'\x81\xf2\n\x16>\xf3\xab\xdf$\xfb\x18\xc4e\xe9\xf6\x86\n'
                        'prepaid_giveaways'   # b'\x81\xf2\n\x16#\xfb\xb7\xd6$\xfd\x04\xd6i\xed\xef\x84\x16N'
                        'my_boost_slots'   # b'\x81\xef\x01,1\xf5\xb1\xc1\x0f\xc5\x1e\xccc\xf8\xeb'
                        '__pyarmor_exit_41066__'
                    [Disassembly]
                        0       NOP                             
                        2       NOP                             
                        4       PUSH_NULL                       
                        6       LOAD_CONST                      2: '__pyarmor_enter_41065__'
                        8       LOAD_CONST                      3: b'<COAddr>\x05\x00\x00\x1ax\x02\x00\x00\x00\x00\x00\x00\x00\x00\x00\x00\x00\x00\x00\x00'
                        10      BUILD_TUPLE                     1
                        12      CALL_FUNCTION_EX                0
                        14      POP_TOP                         
                        16      RESUME                          0
                        18      NOP                             
                        20      NOP                             
                        22      NOP                             
                        24      NOP                             
                        26      NOP                             
                        28      LOAD_CONST                      4: '_'
                        30      PUSH_NULL                       
                        32      LOAD_CONST                      1: '__pyarmor_assert_41064__'
                        34      LOAD_CONST                      5: 'BoostsStatus'   # b'\x81\xc0\x17\x1c \xee\xad\xe1\x0f\xfb\x19\xd5\x7f'
                        36      CALL                            1
                        44      LOAD_CONST                      6: 'level'
                        46      LOAD_FAST                       0: self
                        48      LOAD_ATTR                       0: level
                        68      PUSH_NULL                       
                        70      LOAD_CONST                      1: '__pyarmor_assert_41064__'
                        72      LOAD_CONST                      7: 'current_level_boosts'   # b'\x81\xe1\r\x01!\xff\xb0\xc6$\xf6\x08\xd6i\xe0\xc7\x87\x00R\xa8\xb3\xb9'
                        74      CALL                            1
                        82      LOAD_FAST                       0: self
                        84      LOAD_ATTR                       2: current_level_boosts
                        104     LOAD_CONST                      8: 'boosts'
                        106     LOAD_FAST                       0: self
                        108     LOAD_ATTR                       4: boosts
                        128     PUSH_NULL                       
                        130     LOAD_CONST                      1: '__pyarmor_assert_41064__'
                        132     LOAD_CONST                      9: 'boost_url'   # b'\x81\xe0\x17\x1c \xee\x81\xc7\t\xf6'
                        134     CALL                            1
                        142     LOAD_FAST                       0: self
                        144     LOAD_ATTR                       6: boost_url
                        164     LOAD_CONST                      10: 'my_boost'
                        166     LOAD_FAST                       0: self
                        168     LOAD_ATTR                       8: my_boost
                        188     PUSH_NULL                       
                        190     LOAD_CONST                      1: '__pyarmor_assert_41064__'
                        192     LOAD_CONST                      11: 'gift_boosts'   # b"\x81\xe5\x11\x15'\xc5\xbc\xdd\x14\xe9\x19\xd3"
                        194     CALL                            1
                        202     LOAD_FAST                       0: self
                        204     LOAD_ATTR                       10: gift_boosts
                        224     PUSH_NULL                       
                        226     LOAD_CONST                      1: '__pyarmor_assert_41064__'
                        228     LOAD_CONST                      12: 'next_level_boosts'   # b"\x81\xec\x1d\x0b'\xc5\xb2\xd7\r\xff\x01\xffn\xe3\xf7\x96\x1bN"
                        230     CALL                            1
                        238     LOAD_FAST                       0: self
                        240     LOAD_ATTR                       12: next_level_boosts
                        260     PUSH_NULL                       
                        262     LOAD_CONST                      1: '__pyarmor_assert_41064__'
                        264     LOAD_CONST                      13: 'premium_audience'   # b'\x81\xf2\n\x16>\xf3\xab\xdf$\xfb\x18\xc4e\xe9\xf6\x86\n'
                        266     CALL                            1
                        274     LOAD_GLOBAL                     15: NULL + isinstance
                        284     LOAD_FAST                       0: self
                        286     LOAD_ATTR                       16: premium_audience
                        306     LOAD_GLOBAL                     18: TLObject
                        316     CALL                            2
                        324     POP_JUMP_IF_FALSE               26 (to 378)
                        326     LOAD_FAST                       0: self
                        328     LOAD_ATTR                       16: premium_audience
                        348     LOAD_ATTR                       21: to_dict
                        368     CALL                            0
                        376     JUMP_FORWARD                    11 (to 400)
                        378     LOAD_FAST                       0: self
                        380     LOAD_ATTR                       16: premium_audience
                        400     PUSH_NULL                       
                        402     LOAD_CONST                      1: '__pyarmor_assert_41064__'
                        404     LOAD_CONST                      14: 'prepaid_giveaways'   # b'\x81\xf2\n\x16#\xfb\xb7\xd6$\xfd\x04\xd6i\xed\xef\x84\x16N'
                        406     CALL                            1
                        414     LOAD_FAST                       0: self
                        416     LOAD_ATTR                       22: prepaid_giveaways
                        436     POP_JUMP_IF_NOT_NONE            2 (to 442)
                        438     BUILD_LIST                      0
                        440     JUMP_FORWARD                    57 (to 556)
                        442     LOAD_FAST                       0: self
                        444     LOAD_ATTR                       22: prepaid_giveaways
                        464     GET_ITER                        
                        466     LOAD_FAST_AND_CLEAR             2: _var_var_0
                        468     SWAP                            2
                        470     BUILD_LIST                      0
                        472     SWAP                            2
                        474     FOR_ITER                        36 (to 548)
                        478     STORE_FAST                      2: _var_var_0
                        480     LOAD_GLOBAL                     15: NULL + isinstance
                        490     LOAD_FAST                       2: _var_var_0
                        492     LOAD_GLOBAL                     18: TLObject
                        502     CALL                            2
                        510     POP_JUMP_IF_FALSE               16 (to 544)
                        512     LOAD_FAST                       2: _var_var_0
                        514     LOAD_ATTR                       21: to_dict
                        534     CALL                            0
                        542     JUMP_FORWARD                    1 (to 546)
                        544     LOAD_FAST                       2: _var_var_0
                        546     LIST_APPEND                     2
                        548     JUMP_BACKWARD                   38 (to 474)
                        550     END_FOR                         
                        552     SWAP                            2
                        554     STORE_FAST                      2: _var_var_0
                        556     PUSH_NULL                       
                        558     LOAD_CONST                      1: '__pyarmor_assert_41064__'
                        560     LOAD_CONST                      15: 'my_boost_slots'   # b'\x81\xef\x01,1\xf5\xb1\xc1\x0f\xc5\x1e\xccc\xf8\xeb'
                        562     CALL                            1
                        570     LOAD_FAST                       0: self
                        572     LOAD_ATTR                       24: my_boost_slots
                        592     POP_JUMP_IF_NOT_NONE            2 (to 598)
                        594     BUILD_LIST                      0
                        596     JUMP_FORWARD                    14 (to 626)
                        598     LOAD_FAST                       0: self
                        600     LOAD_ATTR                       24: my_boost_slots
                        620     LOAD_CONST                      0: None
                        622     LOAD_CONST                      0: None
                        624     BINARY_SLICE                    
                        626     BUILD_MAP                       11
                        628     NOP                             
                        630     NOP                             
                        632     NOP                             
                        634     JUMP_FORWARD                    25 (to 686)
                        636     CALL                            1
                        644     POP_TOP                         
                        646     RETURN_VALUE                    
                        648     SWAP                            2
                        650     POP_TOP                         
                        652     SWAP                            2
                        654     STORE_FAST                      2: _var_var_0
                        656     RERAISE                         0
                        658     PUSH_EXC_INFO                   
                        660     PUSH_NULL                       
                        662     LOAD_CONST                      16: '__pyarmor_exit_41066__'
                        664     NOP                             
                        666     LOAD_CONST                      3: b'<COAddr>\x05\x00\x00\x1ax\x02\x00\x00\x00\x00\x00\x00\x00\x00\x00\x00\x00\x00\x00\x00'
                        668     CALL                            1
                        676     POP_TOP                         
                        678     RERAISE                         0
                        680     COPY                            3
                        682     POP_EXCEPT                      
                        684     RERAISE                         1
                        686     PUSH_NULL                       
                        688     LOAD_CONST                      16: '__pyarmor_exit_41066__'
                        690     LOAD_CONST                      3: b'<COAddr>\x05\x00\x00\x1ax\x02\x00\x00\x00\x00\x00\x00\x00\x00\x00\x00\x00\x00\x00\x00'
                        692     BUILD_TUPLE                     1
                        694     CALL_FUNCTION_EX                0
                        696     POP_TOP                         
                        698     RETURN_VALUE                    
                    [Exception Table]
                        28 to 470 -> 658 [0] 
                        470 to 552 -> 648 [21] 
                        552 to 628 -> 658 [0] 
                        648 to 658 -> 658 [0] 
                        658 to 680 -> 680 [1] lasti
                [Code]
                    File Name: <frozen multithon.tl.types.premium>
                    Object Name: _bytes
                    Qualified Name: BoostsStatus._bytes
                    Arg Count: 1
                    Pos Only Arg Count: 0
                    KW Only Arg Count: 0
                    Stack Size: 21
                    Flags: 0x20000003 (CO_OPTIMIZED | CO_NEWLOCALS | CO_PYARMOR_OBFUSCATED)
                    [Names]
                        'my_boost'
                        'my_boost_slots'
                        'join'
                        'struct'
                        'pack'
                        'gift_boosts'
                        'next_level_boosts'
                        'premium_audience'
                        'prepaid_giveaways'
                        'level'
                        'current_level_boosts'
                        'boosts'
                        '_bytes'
                        'serialize_bytes'
                        'boost_url'
                        'len'
                    [Locals+Names]
                        'self'
                        '__assert_armored__'
                    [Constants]
                        None
                        '__pyarmor_assert_41067__'
                        '__pyarmor_enter_41068__'
                        b'<COAddr>\x07\x00\x00\x1a\xce\x06\x00\x00\x00\x00\x00\x00\x00\x00\x00\x00\x00\x00\x00\x00'
                        False
                        'my_boost, my_boost_slots parameters must all be False-y (like None) or all me True-y'   # b'\x81\xef\x01,1\xf5\xb1\xc1\x0f\xb6M\xcdu\xd3\xfa\x8a\x00N\xaf\x98\xb9\xc7A\xd8\x16/\xb3]\x12\xb0\x13\xe0.W2\x1e\xd8\xc7\xa1=\x0c\xa9\xf9Q\xd1\x98\rBw\xcbW\xf7\x94uK\xf4w\xa3\x97\x14\x13Nq}XF\x00\xca\x9d8\xfe\xff\x92n0~M\xbcH\xa5\xb3\x92\x81\xe4\xa6'
                        b''
                        b'zBYI'
                        '<I'
                        0
                        4
                        16
                        1
                        2
                        8
                        '<i'
                        b'\x15\xc4\xb5\x1c'
                        [Code]
                            File Name: <frozen multithon.tl.types.premium>
                            Object Name: <genexpr>
                            Qualified Name: BoostsStatus._bytes.<locals>.<genexpr>
                            Arg Count: 1
                            Pos Only Arg Count: 0
                            KW Only Arg Count: 0
                            Stack Size: 3
                            Flags: 0x00000033 (CO_OPTIMIZED | CO_NEWLOCALS | CO_NESTED | CO_GENERATOR)
                            [Names]
                                '_bytes'
                            [Locals+Names]
                                '.0'
                                '_var_var_0'
                            [Constants]
                                None
                            [Disassembly]
                                0       RETURN_GENERATOR                
                                2       POP_TOP                         
                                4       RESUME                          0
                                6       LOAD_FAST                       0: .0
                                8       FOR_ITER                        20 (to 50)
                                12      STORE_FAST                      1: _var_var_0
                                14      LOAD_FAST                       1: _var_var_0
                                16      LOAD_ATTR                       1: _bytes
                                36      CALL                            0
                                44      YIELD_VALUE                     1
                                46      RESUME                          1
                                48      POP_TOP                         
                                50      JUMP_BACKWARD                   22 (to 8)
                                52      END_FOR                         
                                54      RETURN_CONST                    0: None
                                56      CALL_INTRINSIC_1                3 (INTRINSIC_STOPITERATION_ERROR)
                                58      RERAISE                         1
                            [Exception Table]
                                4 to 56 -> 56 [0] lasti
                        [Code]
                            File Name: <frozen multithon.tl.types.premium>
                            Object Name: <genexpr>
                            Qualified Name: BoostsStatus._bytes.<locals>.<genexpr>
                            Arg Count: 1
                            Pos Only Arg Count: 0
                            KW Only Arg Count: 0
                            Stack Size: 5
                            Flags: 0x00000033 (CO_OPTIMIZED | CO_NEWLOCALS | CO_NESTED | CO_GENERATOR)
                            [Names]
                                'struct'
                                'pack'
                            [Locals+Names]
                                '.0'
                                '_var_var_0'
                            [Constants]
                                '<i'
                                None
                            [Disassembly]
                                0       RETURN_GENERATOR                
                                2       POP_TOP                         
                                4       RESUME                          0
                                6       LOAD_FAST                       0: .0
                                8       FOR_ITER                        26 (to 62)
                                12      STORE_FAST                      1: _var_var_0
                                14      LOAD_GLOBAL                     1: NULL + struct
                                24      LOAD_ATTR                       2: pack
                                44      LOAD_CONST                      0: '<i'
                                46      LOAD_FAST                       1: _var_var_0
                                48      CALL                            2
                                56      YIELD_VALUE                     1
                                58      RESUME                          1
                                60      POP_TOP                         
                                62      JUMP_BACKWARD                   28 (to 8)
                                64      END_FOR                         
                                66      RETURN_CONST                    1: None
                                68      CALL_INTRINSIC_1                3 (INTRINSIC_STOPITERATION_ERROR)
                                70      RERAISE                         1
                            [Exception Table]
                                4 to 68 -> 68 [0] lasti
                        '__pyarmor_exit_41069__'
                    [Disassembly]
                        0       NOP                             
                        2       NOP                             
                        4       PUSH_NULL                       
                        6       LOAD_CONST                      2: '__pyarmor_enter_41068__'
                        8       LOAD_CONST                      3: b'<COAddr>\x07\x00\x00\x1a\xce\x06\x00\x00\x00\x00\x00\x00\x00\x00\x00\x00\x00\x00\x00\x00'
                        10      BUILD_TUPLE                     1
                        12      CALL_FUNCTION_EX                0
                        14      POP_TOP                         
                        16      RESUME                          0
                        18      NOP                             
                        20      NOP                             
                        22      NOP                             
                        24      NOP                             
                        26      NOP                             
                        28      LOAD_FAST                       0: self
                        30      LOAD_ATTR                       0: my_boost
                        50      POP_JUMP_IF_TRUE                12 (to 76)
                        52      LOAD_FAST                       0: self
                        54      LOAD_ATTR                       0: my_boost
                        74      POP_JUMP_IF_NONE                24 (to 124)
                        76      LOAD_FAST                       0: self
                        78      LOAD_ATTR                       2: my_boost_slots
                        98      POP_JUMP_IF_TRUE                77 (to 254)
                        100     LOAD_FAST                       0: self
                        102     LOAD_ATTR                       2: my_boost_slots
                        122     POP_JUMP_IF_NOT_NONE            65 (to 254)
                        124     LOAD_FAST                       0: self
                        126     LOAD_ATTR                       0: my_boost
                        146     POP_JUMP_IF_NONE                14 (to 176)
                        148     LOAD_FAST                       0: self
                        150     LOAD_ATTR                       0: my_boost
                        170     LOAD_CONST                      4: False
                        172     IS_OP                           0 (is)
                        174     POP_JUMP_IF_FALSE               26 (to 228)
                        176     LOAD_FAST                       0: self
                        178     LOAD_ATTR                       2: my_boost_slots
                        198     POP_JUMP_IF_NONE                27 (to 254)
                        200     LOAD_FAST                       0: self
                        202     LOAD_ATTR                       2: my_boost_slots
                        222     LOAD_CONST                      4: False
                        224     IS_OP                           0 (is)
                        226     POP_JUMP_IF_TRUE                13 (to 254)
                        228     LOAD_ASSERTION_ERROR            
                        230     PUSH_NULL                       
                        232     LOAD_CONST                      1: '__pyarmor_assert_41067__'
                        234     LOAD_CONST                      5: 'my_boost, my_boost_slots parameters must all be False-y (like None) or all me True-y'   # b'\x81\xef\x01,1\xf5\xb1\xc1\x0f\xb6M\xcdu\xd3\xfa\x8a\x00N\xaf\x98\xb9\xc7A\xd8\x16/\xb3]\x12\xb0\x13\xe0.W2\x1e\xd8\xc7\xa1=\x0c\xa9\xf9Q\xd1\x98\rBw\xcbW\xf7\x94uK\xf4w\xa3\x97\x14\x13Nq}XF\x00\xca\x9d8\xfe\xff\x92n0~M\xbcH\xa5\xb3\x92\x81\xe4\xa6'
                        236     CALL                            1
                        244     CALL                            0
                        252     RAISE_VARARGS                   1
                        254     LOAD_CONST                      6: b''
                        256     LOAD_ATTR                       5: join
                        276     LOAD_CONST                      7: b'zBYI'
                        278     LOAD_GLOBAL                     7: NULL + struct
                        288     LOAD_ATTR                       8: pack
                        308     LOAD_CONST                      8: '<I'
                        310     LOAD_FAST                       0: self
                        312     LOAD_ATTR                       0: my_boost
                        332     POP_JUMP_IF_NONE                14 (to 362)
                        334     LOAD_FAST                       0: self
                        336     LOAD_ATTR                       0: my_boost
                        356     LOAD_CONST                      4: False
                        358     IS_OP                           0 (is)
                        360     POP_JUMP_IF_FALSE               2 (to 366)
                        362     LOAD_CONST                      9: 0
                        364     JUMP_FORWARD                    1 (to 368)
                        366     LOAD_CONST                      10: 4
                        368     LOAD_FAST                       0: self
                        370     LOAD_ATTR                       10: gift_boosts
                        390     POP_JUMP_IF_NONE                14 (to 420)
                        392     LOAD_FAST                       0: self
                        394     LOAD_ATTR                       10: gift_boosts
                        414     LOAD_CONST                      4: False
                        416     IS_OP                           0 (is)
                        418     POP_JUMP_IF_FALSE               2 (to 424)
                        420     LOAD_CONST                      9: 0
                        422     JUMP_FORWARD                    1 (to 426)
                        424     LOAD_CONST                      11: 16
                        426     BINARY_OP                       7 (|)
                        430     LOAD_FAST                       0: self
                        432     LOAD_ATTR                       12: next_level_boosts
                        452     POP_JUMP_IF_NONE                14 (to 482)
                        454     LOAD_FAST                       0: self
                        456     LOAD_ATTR                       12: next_level_boosts
                        476     LOAD_CONST                      4: False
                        478     IS_OP                           0 (is)
                        480     POP_JUMP_IF_FALSE               2 (to 486)
                        482     LOAD_CONST                      9: 0
                        484     JUMP_FORWARD                    1 (to 488)
                        486     LOAD_CONST                      12: 1
                        488     BINARY_OP                       7 (|)
                        492     LOAD_FAST                       0: self
                        494     LOAD_ATTR                       14: premium_audience
                        514     POP_JUMP_IF_NONE                14 (to 544)
                        516     LOAD_FAST                       0: self
                        518     LOAD_ATTR                       14: premium_audience
                        538     LOAD_CONST                      4: False
                        540     IS_OP                           0 (is)
                        542     POP_JUMP_IF_FALSE               2 (to 548)
                        544     LOAD_CONST                      9: 0
                        546     JUMP_FORWARD                    1 (to 550)
                        548     LOAD_CONST                      13: 2
                        550     BINARY_OP                       7 (|)
                        554     LOAD_FAST                       0: self
                        556     LOAD_ATTR                       16: prepaid_giveaways
                        576     POP_JUMP_IF_NONE                14 (to 606)
                        578     LOAD_FAST                       0: self
                        580     LOAD_ATTR                       16: prepaid_giveaways
                        600     LOAD_CONST                      4: False
                        602     IS_OP                           0 (is)
                        604     POP_JUMP_IF_FALSE               2 (to 610)
                        606     LOAD_CONST                      9: 0
                        608     JUMP_FORWARD                    1 (to 612)
                        610     LOAD_CONST                      14: 8
                        612     BINARY_OP                       7 (|)
                        616     LOAD_FAST                       0: self
                        618     LOAD_ATTR                       2: my_boost_slots
                        638     POP_JUMP_IF_NONE                14 (to 668)
                        640     LOAD_FAST                       0: self
                        642     LOAD_ATTR                       2: my_boost_slots
                        662     LOAD_CONST                      4: False
                        664     IS_OP                           0 (is)
                        666     POP_JUMP_IF_FALSE               2 (to 672)
                        668     LOAD_CONST                      9: 0
                        670     JUMP_FORWARD                    1 (to 674)
                        672     LOAD_CONST                      10: 4
                        674     BINARY_OP                       7 (|)
                        678     CALL                            2
                        686     LOAD_GLOBAL                     7: NULL + struct
                        696     LOAD_ATTR                       8: pack
                        716     LOAD_CONST                      15: '<i'
                        718     LOAD_FAST                       0: self
                        720     LOAD_ATTR                       18: level
                        740     CALL                            2
                        748     LOAD_GLOBAL                     7: NULL + struct
                        758     LOAD_ATTR                       8: pack
                        778     LOAD_CONST                      15: '<i'
                        780     LOAD_FAST                       0: self
                        782     LOAD_ATTR                       20: current_level_boosts
                        802     CALL                            2
                        810     LOAD_GLOBAL                     7: NULL + struct
                        820     LOAD_ATTR                       8: pack
                        840     LOAD_CONST                      15: '<i'
                        842     LOAD_FAST                       0: self
                        844     LOAD_ATTR                       22: boosts
                        864     CALL                            2
                        872     LOAD_FAST                       0: self
                        874     LOAD_ATTR                       10: gift_boosts
                        894     POP_JUMP_IF_NONE                14 (to 924)
                        896     LOAD_FAST                       0: self
                        898     LOAD_ATTR                       10: gift_boosts
                        918     LOAD_CONST                      4: False
                        920     IS_OP                           0 (is)
                        922     POP_JUMP_IF_FALSE               2 (to 928)
                        924     LOAD_CONST                      6: b''
                        926     JUMP_FORWARD                    31 (to 990)
                        928     LOAD_GLOBAL                     7: NULL + struct
                        938     LOAD_ATTR                       8: pack
                        958     LOAD_CONST                      15: '<i'
                        960     LOAD_FAST                       0: self
                        962     LOAD_ATTR                       10: gift_boosts
                        982     CALL                            2
                        990     LOAD_FAST                       0: self
                        992     LOAD_ATTR                       12: next_level_boosts
                        1012    POP_JUMP_IF_NONE                14 (to 1042)
                        1014    LOAD_FAST                       0: self
                        1016    LOAD_ATTR                       12: next_level_boosts
                        1036    LOAD_CONST                      4: False
                        1038    IS_OP                           0 (is)
                        1040    POP_JUMP_IF_FALSE               2 (to 1046)
                        1042    LOAD_CONST                      6: b''
                        1044    JUMP_FORWARD                    31 (to 1108)
                        1046    LOAD_GLOBAL                     7: NULL + struct
                        1056    LOAD_ATTR                       8: pack
                        1076    LOAD_CONST                      15: '<i'
                        1078    LOAD_FAST                       0: self
                        1080    LOAD_ATTR                       12: next_level_boosts
                        1100    CALL                            2
                        1108    LOAD_FAST                       0: self
                        1110    LOAD_ATTR                       14: premium_audience
                        1130    POP_JUMP_IF_NONE                14 (to 1160)
                        1132    LOAD_FAST                       0: self
                        1134    LOAD_ATTR                       14: premium_audience
                        1154    LOAD_CONST                      4: False
                        1156    IS_OP                           0 (is)
                        1158    POP_JUMP_IF_FALSE               2 (to 1164)
                        1160    LOAD_CONST                      6: b''
                        1162    JUMP_FORWARD                    25 (to 1214)
                        1164    LOAD_FAST                       0: self
                        1166    LOAD_ATTR                       14: premium_audience
                        1186    LOAD_ATTR                       25: _bytes
                        1206    CALL                            0
                        1214    LOAD_FAST                       0: self
                        1216    LOAD_ATTR                       27: serialize_bytes
                        1236    LOAD_FAST                       0: self
                        1238    LOAD_ATTR                       28: boost_url
                        1258    CALL                            1
                        1266    LOAD_FAST                       0: self
                        1268    LOAD_ATTR                       16: prepaid_giveaways
                        1288    POP_JUMP_IF_NONE                14 (to 1318)
                        1290    LOAD_FAST                       0: self
                        1292    LOAD_ATTR                       16: prepaid_giveaways
                        1312    LOAD_CONST                      4: False
                        1314    IS_OP                           0 (is)
                        1316    POP_JUMP_IF_FALSE               2 (to 1322)
                        1318    LOAD_CONST                      6: b''
                        1320    JUMP_FORWARD                    90 (to 1502)
                        1322    LOAD_CONST                      6: b''
                        1324    LOAD_ATTR                       5: join
                        1344    LOAD_CONST                      16: b'\x15\xc4\xb5\x1c'
                        1346    LOAD_GLOBAL                     7: NULL + struct
                        1356    LOAD_ATTR                       8: pack
                        1376    LOAD_CONST                      15: '<i'
                        1378    LOAD_GLOBAL                     31: NULL + len
                        1388    LOAD_FAST                       0: self
                        1390    LOAD_ATTR                       16: prepaid_giveaways
                        1410    CALL                            1
                        1418    CALL                            2
                        1426    LOAD_CONST                      6: b''
                        1428    LOAD_ATTR                       5: join
                        1448    LOAD_CONST                      17: <CODE> <genexpr>
                        1450    MAKE_FUNCTION                   0
                        1452    LOAD_FAST                       0: self
                        1454    LOAD_ATTR                       16: prepaid_giveaways
                        1474    GET_ITER                        
                        1476    CALL                            0
                        1484    CALL                            1
                        1492    BUILD_TUPLE                     3
                        1494    CALL                            1
                        1502    LOAD_FAST                       0: self
                        1504    LOAD_ATTR                       2: my_boost_slots
                        1524    POP_JUMP_IF_NONE                14 (to 1554)
                        1526    LOAD_FAST                       0: self
                        1528    LOAD_ATTR                       2: my_boost_slots
                        1548    LOAD_CONST                      4: False
                        1550    IS_OP                           0 (is)
                        1552    POP_JUMP_IF_FALSE               2 (to 1558)
                        1554    LOAD_CONST                      6: b''
                        1556    JUMP_FORWARD                    90 (to 1738)
                        1558    LOAD_CONST                      6: b''
                        1560    LOAD_ATTR                       5: join
                        1580    LOAD_CONST                      16: b'\x15\xc4\xb5\x1c'
                        1582    LOAD_GLOBAL                     7: NULL + struct
                        1592    LOAD_ATTR                       8: pack
                        1612    LOAD_CONST                      15: '<i'
                        1614    LOAD_GLOBAL                     31: NULL + len
                        1624    LOAD_FAST                       0: self
                        1626    LOAD_ATTR                       2: my_boost_slots
                        1646    CALL                            1
                        1654    CALL                            2
                        1662    LOAD_CONST                      6: b''
                        1664    LOAD_ATTR                       5: join
                        1684    LOAD_CONST                      18: <CODE> <genexpr>
                        1686    MAKE_FUNCTION                   0
                        1688    LOAD_FAST                       0: self
                        1690    LOAD_ATTR                       2: my_boost_slots
                        1710    GET_ITER                        
                        1712    CALL                            0
                        1720    CALL                            1
                        1728    BUILD_TUPLE                     3
                        1730    CALL                            1
                        1738    BUILD_TUPLE                     11
                        1740    CALL                            1
                        1748    NOP                             
                        1750    NOP                             
                        1752    NOP                             
                        1754    JUMP_FORWARD                    20 (to 1796)
                        1756    CALL                            1
                        1764    POP_TOP                         
                        1766    RETURN_VALUE                    
                        1768    PUSH_EXC_INFO                   
                        1770    PUSH_NULL                       
                        1772    LOAD_CONST                      19: '__pyarmor_exit_41069__'
                        1774    NOP                             
                        1776    LOAD_CONST                      3: b'<COAddr>\x07\x00\x00\x1a\xce\x06\x00\x00\x00\x00\x00\x00\x00\x00\x00\x00\x00\x00\x00\x00'
                        1778    CALL                            1
                        1786    POP_TOP                         
                        1788    RERAISE                         0
                        1790    COPY                            3
                        1792    POP_EXCEPT                      
                        1794    RERAISE                         1
                        1796    PUSH_NULL                       
                        1798    LOAD_CONST                      19: '__pyarmor_exit_41069__'
                        1800    LOAD_CONST                      3: b'<COAddr>\x07\x00\x00\x1a\xce\x06\x00\x00\x00\x00\x00\x00\x00\x00\x00\x00\x00\x00\x00\x00'
                        1802    BUILD_TUPLE                     1
                        1804    CALL_FUNCTION_EX                0
                        1806    POP_TOP                         
                        1808    RETURN_VALUE                    
                    [Exception Table]
                        28 to 1748 -> 1768 [0] 
                        1768 to 1790 -> 1790 [1] lasti
                [Code]
                    File Name: <frozen multithon.tl.types.premium>
                    Object Name: from_reader
                    Qualified Name: BoostsStatus.from_reader
                    Arg Count: 2
                    Pos Only Arg Count: 0
                    KW Only Arg Count: 0
                    Stack Size: 12
                    Flags: 0x20000003 (CO_OPTIMIZED | CO_NEWLOCALS | CO_PYARMOR_OBFUSCATED)
                    [Names]
                        'read_int'
                        'bool'
                        'tgread_object'
                        'tgread_string'
                        'range'
                        'append'
                    [Locals+Names]
                        'cls'
                        'reader'
                        '__assert_armored__'
                        '_var_var_1'
                        '_var_var_8'
                        '_var_var_9'
                        '_var_var_10'
                        '_var_var_3'
                        '_var_var_11'
                        '_var_var_12'
                        '_var_var_13'
                        '_var_var_14'
                        '_var_var_15'
                        '_var_var_4'
                        '_var_var_5'
                        '_var_var_16'
                    [Constants]
                        None
                        '__pyarmor_assert_41070__'
                        '__pyarmor_enter_41071__'
                        b'<COAddr>\x07\x00\x00\x1a\xe8\x02\x00\x00\x00\x00\x00\x00\x00\x00\x00\x00\x00\x00\x00\x00'
                        4
                        16
                        1
                        2
                        8
                        (
                            'level'
                            'current_level_boosts'
                            'boosts'
                            'boost_url'
                            'my_boost'
                            'gift_boosts'
                            'next_level_boosts'
                            'premium_audience'
                            'prepaid_giveaways'
                            'my_boost_slots'
                        )
                        '__pyarmor_exit_41072__'
                    [Disassembly]
                        0       NOP                             
                        2       NOP                             
                        4       PUSH_NULL                       
                        6       LOAD_CONST                      2: '__pyarmor_enter_41071__'
                        8       LOAD_CONST                      3: b'<COAddr>\x07\x00\x00\x1a\xe8\x02\x00\x00\x00\x00\x00\x00\x00\x00\x00\x00\x00\x00\x00\x00'
                        10      BUILD_TUPLE                     1
                        12      CALL_FUNCTION_EX                0
                        14      POP_TOP                         
                        16      RESUME                          0
                        18      NOP                             
                        20      NOP                             
                        22      NOP                             
                        24      NOP                             
                        26      NOP                             
                        28      LOAD_FAST                       1: reader
                        30      LOAD_ATTR                       1: read_int
                        50      CALL                            0
                        58      STORE_FAST                      3: _var_var_1
                        60      LOAD_GLOBAL                     3: NULL + bool
                        70      LOAD_FAST                       3: _var_var_1
                        72      LOAD_CONST                      4: 4
                        74      BINARY_OP                       1 (&)
                        78      CALL                            1
                        86      STORE_FAST                      4: _var_var_8
                        88      LOAD_FAST                       1: reader
                        90      LOAD_ATTR                       1: read_int
                        110     CALL                            0
                        118     STORE_FAST                      5: _var_var_9
                        120     LOAD_FAST                       1: reader
                        122     LOAD_ATTR                       1: read_int
                        142     CALL                            0
                        150     STORE_FAST                      6: _var_var_10
                        152     LOAD_FAST                       1: reader
                        154     LOAD_ATTR                       1: read_int
                        174     CALL                            0
                        182     STORE_FAST                      7: _var_var_3
                        184     LOAD_FAST                       3: _var_var_1
                        186     LOAD_CONST                      5: 16
                        188     BINARY_OP                       1 (&)
                        192     POP_JUMP_IF_FALSE               17 (to 228)
                        194     LOAD_FAST                       1: reader
                        196     LOAD_ATTR                       1: read_int
                        216     CALL                            0
                        224     STORE_FAST                      8: _var_var_11
                        226     JUMP_FORWARD                    2 (to 232)
                        228     LOAD_CONST                      0: None
                        230     STORE_FAST                      8: _var_var_11
                        232     LOAD_FAST                       3: _var_var_1
                        234     LOAD_CONST                      6: 1
                        236     BINARY_OP                       1 (&)
                        240     POP_JUMP_IF_FALSE               17 (to 276)
                        242     LOAD_FAST                       1: reader
                        244     LOAD_ATTR                       1: read_int
                        264     CALL                            0
                        272     STORE_FAST                      9: _var_var_12
                        274     JUMP_FORWARD                    2 (to 280)
                        276     LOAD_CONST                      0: None
                        278     STORE_FAST                      9: _var_var_12
                        280     LOAD_FAST                       3: _var_var_1
                        282     LOAD_CONST                      7: 2
                        284     BINARY_OP                       1 (&)
                        288     POP_JUMP_IF_FALSE               17 (to 324)
                        290     LOAD_FAST                       1: reader
                        292     LOAD_ATTR                       5: tgread_object
                        312     CALL                            0
                        320     STORE_FAST                      10: _var_var_13
                        322     JUMP_FORWARD                    2 (to 328)
                        324     LOAD_CONST                      0: None
                        326     STORE_FAST                      10: _var_var_13
                        328     LOAD_FAST                       1: reader
                        330     LOAD_ATTR                       7: tgread_string
                        350     CALL                            0
                        358     STORE_FAST                      11: _var_var_14
                        360     LOAD_FAST                       3: _var_var_1
                        362     LOAD_CONST                      8: 8
                        364     BINARY_OP                       1 (&)
                        368     POP_JUMP_IF_FALSE               82 (to 534)
                        370     LOAD_FAST                       1: reader
                        372     LOAD_ATTR                       1: read_int
                        392     CALL                            0
                        400     POP_TOP                         
                        402     BUILD_LIST                      0
                        404     STORE_FAST                      12: _var_var_15
                        406     LOAD_GLOBAL                     9: NULL + range
                        416     LOAD_FAST                       1: reader
                        418     LOAD_ATTR                       1: read_int
                        438     CALL                            0
                        446     CALL                            1
                        454     GET_ITER                        
                        456     FOR_ITER                        35 (to 528)
                        460     STORE_FAST                      13: _var_var_4
                        462     LOAD_FAST                       1: reader
                        464     LOAD_ATTR                       5: tgread_object
                        484     CALL                            0
                        492     STORE_FAST                      14: _var_var_5
                        494     LOAD_FAST                       12: _var_var_15
                        496     LOAD_ATTR                       11: append
                        516     LOAD_FAST                       14: _var_var_5
                        518     CALL                            1
                        526     POP_TOP                         
                        528     JUMP_BACKWARD                   37 (to 456)
                        530     END_FOR                         
                        532     JUMP_FORWARD                    2 (to 538)
                        534     LOAD_CONST                      0: None
                        536     STORE_FAST                      12: _var_var_15
                        538     LOAD_FAST                       3: _var_var_1
                        540     LOAD_CONST                      4: 4
                        542     BINARY_OP                       1 (&)
                        546     POP_JUMP_IF_FALSE               82 (to 712)
                        548     LOAD_FAST                       1: reader
                        550     LOAD_ATTR                       1: read_int
                        570     CALL                            0
                        578     POP_TOP                         
                        580     BUILD_LIST                      0
                        582     STORE_FAST                      15: _var_var_16
                        584     LOAD_GLOBAL                     9: NULL + range
                        594     LOAD_FAST                       1: reader
                        596     LOAD_ATTR                       1: read_int
                        616     CALL                            0
                        624     CALL                            1
                        632     GET_ITER                        
                        634     FOR_ITER                        35 (to 706)
                        638     STORE_FAST                      13: _var_var_4
                        640     LOAD_FAST                       1: reader
                        642     LOAD_ATTR                       1: read_int
                        662     CALL                            0
                        670     STORE_FAST                      14: _var_var_5
                        672     LOAD_FAST                       15: _var_var_16
                        674     LOAD_ATTR                       11: append
                        694     LOAD_FAST                       14: _var_var_5
                        696     CALL                            1
                        704     POP_TOP                         
                        706     JUMP_BACKWARD                   37 (to 634)
                        708     END_FOR                         
                        710     JUMP_FORWARD                    2 (to 716)
                        712     LOAD_CONST                      0: None
                        714     STORE_FAST                      15: _var_var_16
                        716     PUSH_NULL                       
                        718     LOAD_FAST                       0: cls
                        720     LOAD_FAST                       5: _var_var_9
                        722     LOAD_FAST                       6: _var_var_10
                        724     LOAD_FAST                       7: _var_var_3
                        726     LOAD_FAST                       11: _var_var_14
                        728     LOAD_FAST                       4: _var_var_8
                        730     LOAD_FAST                       8: _var_var_11
                        732     LOAD_FAST                       9: _var_var_12
                        734     LOAD_FAST                       10: _var_var_13
                        736     LOAD_FAST                       12: _var_var_15
                        738     LOAD_FAST                       15: _var_var_16
                        740     KW_NAMES                        9: ('level', 'current_level_boosts', 'boosts', 'boost_url', 'my_boost', 'gift_boosts', 'next_level_boosts', 'premium_audience', 'prepaid_giveaways', 'my_boost_slots')
                        742     CALL                            10
                        750     NOP                             
                        752     NOP                             
                        754     NOP                             
                        756     JUMP_FORWARD                    20 (to 798)
                        758     CALL                            1
                        766     POP_TOP                         
                        768     RETURN_VALUE                    
                        770     PUSH_EXC_INFO                   
                        772     PUSH_NULL                       
                        774     LOAD_CONST                      10: '__pyarmor_exit_41072__'
                        776     NOP                             
                        778     LOAD_CONST                      3: b'<COAddr>\x07\x00\x00\x1a\xe8\x02\x00\x00\x00\x00\x00\x00\x00\x00\x00\x00\x00\x00\x00\x00'
                        780     CALL                            1
                        788     POP_TOP                         
                        790     RERAISE                         0
                        792     COPY                            3
                        794     POP_EXCEPT                      
                        796     RERAISE                         1
                        798     PUSH_NULL                       
                        800     LOAD_CONST                      10: '__pyarmor_exit_41072__'
                        802     LOAD_CONST                      3: b'<COAddr>\x07\x00\x00\x1a\xe8\x02\x00\x00\x00\x00\x00\x00\x00\x00\x00\x00\x00\x00\x00\x00'
                        804     BUILD_TUPLE                     1
                        806     CALL_FUNCTION_EX                0
                        808     POP_TOP                         
                        810     RETURN_VALUE                    
                    [Exception Table]
                        28 to 750 -> 770 [0] 
                        770 to 792 -> 792 [1] lasti
                '__pyarmor_exit_41060__'
                (
                    None
                    None
                    None
                    None
                    None
                    None
                )
            [Disassembly]
                0       NOP                             
                2       LOAD_NAME                       0: __name__
                4       STORE_NAME                      1: __module__
                6       LOAD_CONST                      0: 'BoostsStatus'
                8       STORE_NAME                      2: __qualname__
                10      NOP                             
                12      PUSH_NULL                       
                14      LOAD_CONST                      2: '__pyarmor_enter_41059__'
                16      LOAD_CONST                      3: b'<COAddr>\x07\x00\x00"\xb4\x00\x00\x00\x00\x00\x00\x00\x00\x00\x00\x00\x00\x00\x00\x00'
                18      BUILD_TUPLE                     1
                20      CALL_FUNCTION_EX                0
                22      POP_TOP                         
                24      RESUME                          0
                26      NOP                             
                28      NOP                             
                30      NOP                             
                32      NOP                             
                34      NOP                             
                36      LOAD_CONST                      4: 1230586490
                38      STORE_NAME                      4: CONSTRUCTOR_ID
                40      LOAD_CONST                      5: 0xC31B1AB9
                42      STORE_NAME                      5: SUBCLASS_OF_ID
                44      LOAD_CONST                      24: (None, None, None, None, None, None)
                46      LOAD_CONST                      7: 'level'
                48      LOAD_NAME                       6: int
                50      LOAD_CONST                      8: 'current_level_boosts'
                52      LOAD_NAME                       6: int
                54      LOAD_CONST                      9: 'boosts'
                56      LOAD_NAME                       6: int
                58      LOAD_CONST                      10: 'boost_url'
                60      LOAD_NAME                       7: str
                62      LOAD_CONST                      11: 'my_boost'
                64      LOAD_NAME                       8: Optional
                66      LOAD_NAME                       9: bool
                68      BINARY_SUBSCR                   
                72      LOAD_CONST                      12: 'gift_boosts'
                74      LOAD_NAME                       8: Optional
                76      LOAD_NAME                       6: int
                78      BINARY_SUBSCR                   
                82      LOAD_CONST                      13: 'next_level_boosts'
                84      LOAD_NAME                       8: Optional
                86      LOAD_NAME                       6: int
                88      BINARY_SUBSCR                   
                92      LOAD_CONST                      14: 'premium_audience'
                94      LOAD_NAME                       8: Optional
                96      PUSH_NULL                       
                98      LOAD_CONST                      1: '__pyarmor_assert_41058__'
                100     LOAD_CONST                      15: 'TypeStatsPercentValue'   # b'\x81\xd6\x01\x036\xc9\xaa\xd3\x0f\xe9=\xc5~\xef\xfd\x8b\x1bk\xba\xab\xbf\xce'
                102     CALL                            1
                110     BINARY_SUBSCR                   
                114     LOAD_CONST                      16: 'prepaid_giveaways'
                116     LOAD_NAME                       8: Optional
                118     LOAD_NAME                       10: List
                120     PUSH_NULL                       
                122     LOAD_CONST                      1: '__pyarmor_assert_41058__'
                124     LOAD_CONST                      17: 'TypePrepaidGiveaway'   # b'\x81\xd6\x01\x036\xca\xac\xd7\x0b\xfb\x04\xc4K\xe5\xee\x80\x0eJ\xba\xbe'
                126     CALL                            1
                134     BINARY_SUBSCR                   
                138     BINARY_SUBSCR                   
                142     LOAD_CONST                      18: 'my_boost_slots'
                144     LOAD_NAME                       8: Optional
                146     LOAD_NAME                       10: List
                148     LOAD_NAME                       6: int
                150     BINARY_SUBSCR                   
                154     BINARY_SUBSCR                   
                158     BUILD_TUPLE                     20
                160     LOAD_CONST                      19: <CODE> __init__
                162     MAKE_FUNCTION                   5
                164     STORE_NAME                      11: __init__
                166     LOAD_CONST                      20: <CODE> to_dict
                168     MAKE_FUNCTION                   0
                170     STORE_NAME                      12: to_dict
                172     LOAD_CONST                      21: <CODE> _bytes
                174     MAKE_FUNCTION                   0
                176     STORE_NAME                      13: _bytes
                178     LOAD_NAME                       14: classmethod
                180     LOAD_CONST                      22: <CODE> from_reader
                182     MAKE_FUNCTION                   0
                184     CALL                            0
                192     STORE_NAME                      15: from_reader
                194     LOAD_CONST                      6: None
                196     NOP                             
                198     NOP                             
                200     NOP                             
                202     JUMP_FORWARD                    19 (to 242)
                210     POP_TOP                         
                212     RETURN_CONST                    6: None
                214     PUSH_EXC_INFO                   
                216     PUSH_NULL                       
                218     LOAD_CONST                      23: '__pyarmor_exit_41060__'
                220     NOP                             
                222     LOAD_CONST                      3: b'<COAddr>\x07\x00\x00"\xb4\x00\x00\x00\x00\x00\x00\x00\x00\x00\x00\x00\x00\x00\x00\x00'
                224     CALL                            1
                232     POP_TOP                         
                234     RERAISE                         0
                236     COPY                            3
                238     POP_EXCEPT                      
                240     RERAISE                         1
                242     PUSH_NULL                       
                244     LOAD_CONST                      23: '__pyarmor_exit_41060__'
                246     LOAD_CONST                      3: b'<COAddr>\x07\x00\x00"\xb4\x00\x00\x00\x00\x00\x00\x00\x00\x00\x00\x00\x00\x00\x00\x00'
                248     BUILD_TUPLE                     1
                250     CALL_FUNCTION_EX                0
                252     POP_TOP                         
                254     RETURN_VALUE                    
            [Exception Table]
                36 to 194 -> 214 [0] 
                214 to 236 -> 236 [1] lasti
        'BoostsStatus'
        [Code]
            File Name: <frozen multithon.tl.types.premium>
            Object Name: MyBoosts
            Qualified Name: MyBoosts
            Arg Count: 0
            Pos Only Arg Count: 0
            KW Only Arg Count: 0
            Stack Size: 7
            Flags: 0x20000000 (CO_PYARMOR_OBFUSCATED)
            [Names]
                '__name__'
                '__module__'
                '__qualname__'
                '__assert_armored__'
                'CONSTRUCTOR_ID'
                'SUBCLASS_OF_ID'
                'List'
                '__init__'
                'to_dict'
                '_bytes'
                'classmethod'
                'from_reader'
            [Locals+Names]
            [Constants]
                'MyBoosts'
                '__pyarmor_assert_41073__'
                '__pyarmor_enter_41074__'
                b'<COAddr>\x05\x00\x00"l\x00\x00\x00\x00\x00\x00\x00\x00\x00\x00\x00\x00\x00\x00\x00'
                0x9AE228E2
                0xAD3512DB
                'my_boosts'
                'TypeMyBoost'   # b'\x81\xd6\x01\x036\xd7\xa7\xf0\x14\xf5\x1e\xd4'
                'chats'
                'TypeChat'
                'users'
                'TypeUser'
                [Code]
                    File Name: <frozen multithon.tl.types.premium>
                    Object Name: __init__
                    Qualified Name: MyBoosts.__init__
                    Arg Count: 4
                    Pos Only Arg Count: 0
                    KW Only Arg Count: 0
                    Stack Size: 5
                    Flags: 0x20000003 (CO_OPTIMIZED | CO_NEWLOCALS | CO_PYARMOR_OBFUSCATED)
                    [Names]
                        'my_boosts'
                        'chats'
                        'users'
                    [Locals+Names]
                        'self'
                        'my_boosts'
                        'chats'
                        'users'
                        '__assert_armored__'
                    [Constants]
                        '\n        Constructor for premium.MyBoosts: Instance of MyBoosts.\n        '
                        '__pyarmor_assert_41076__'
                        '__pyarmor_enter_41077__'
                        b'<COAddr>\x05\x00\x00\x1a@\x00\x00\x00\x00\x00\x00\x00\x00\x00\x00\x00\x00\x00\x00\x00'
                        '__pyarmor_exit_41078__'
                        None
                    [Disassembly]
                        0       NOP                             
                        2       NOP                             
                        4       PUSH_NULL                       
                        6       LOAD_CONST                      2: '__pyarmor_enter_41077__'
                        8       LOAD_CONST                      3: b'<COAddr>\x05\x00\x00\x1a@\x00\x00\x00\x00\x00\x00\x00\x00\x00\x00\x00\x00\x00\x00\x00'
                        10      BUILD_TUPLE                     1
                        12      CALL_FUNCTION_EX                0
                        14      POP_TOP                         
                        16      RESUME                          0
                        18      NOP                             
                        20      NOP                             
                        22      NOP                             
                        24      NOP                             
                        26      NOP                             
                        28      LOAD_FAST                       1: my_boosts
                        30      LOAD_FAST                       0: self
                        32      STORE_ATTR                      0: my_boosts
                        42      LOAD_FAST                       2: chats
                        44      LOAD_FAST                       0: self
                        46      STORE_ATTR                      1: chats
                        56      LOAD_FAST                       3: users
                        58      LOAD_FAST                       0: self
                        60      STORE_ATTR                      2: users
                        70      LOAD_CONST                      5: None
                        72      NOP                             
                        74      NOP                             
                        76      NOP                             
                        78      JUMP_FORWARD                    19 (to 118)
                        86      POP_TOP                         
                        88      RETURN_CONST                    5: None
                        90      PUSH_EXC_INFO                   
                        92      PUSH_NULL                       
                        94      LOAD_CONST                      4: '__pyarmor_exit_41078__'
                        96      NOP                             
                        98      LOAD_CONST                      3: b'<COAddr>\x05\x00\x00\x1a@\x00\x00\x00\x00\x00\x00\x00\x00\x00\x00\x00\x00\x00\x00\x00'
                        100     CALL                            1
                        108     POP_TOP                         
                        110     RERAISE                         0
                        112     COPY                            3
                        114     POP_EXCEPT                      
                        116     RERAISE                         1
                        118     PUSH_NULL                       
                        120     LOAD_CONST                      4: '__pyarmor_exit_41078__'
                        122     LOAD_CONST                      3: b'<COAddr>\x05\x00\x00\x1a@\x00\x00\x00\x00\x00\x00\x00\x00\x00\x00\x00\x00\x00\x00\x00'
                        124     BUILD_TUPLE                     1
                        126     CALL_FUNCTION_EX                0
                        128     POP_TOP                         
                        130     RETURN_VALUE                    
                    [Exception Table]
                        28 to 70 -> 90 [0] 
                        90 to 112 -> 112 [1] lasti
                [Code]
                    File Name: <frozen multithon.tl.types.premium>
                    Object Name: to_dict
                    Qualified Name: MyBoosts.to_dict
                    Arg Count: 1
                    Pos Only Arg Count: 0
                    KW Only Arg Count: 0
                    Stack Size: 14
                    Flags: 0x20000003 (CO_OPTIMIZED | CO_NEWLOCALS | CO_PYARMOR_OBFUSCATED)
                    [Names]
                        'my_boosts'
                        'isinstance'
                        'TLObject'
                        'to_dict'
                        'chats'
                        'users'
                    [Locals+Names]
                        'self'
                        '__assert_armored__'
                        '_var_var_0'
                    [Constants]
                        None
                        '__pyarmor_assert_41079__'
                        '__pyarmor_enter_41080__'
                        b'<COAddr>\x07\x00\x00\x1a\xf6\x01\x00\x00\x00\x00\x00\x00\x00\x00\x00\x00\x00\x00\x00\x00'
                        '_'
                        'MyBoosts'
                        'my_boosts'   # b'\x81\xef\x01,1\xf5\xb1\xc1\x0f\xe9'
                        'chats'
                        'users'
                        '__pyarmor_exit_41081__'
                    [Disassembly]
                        0       NOP                             
                        2       NOP                             
                        4       PUSH_NULL                       
                        6       LOAD_CONST                      2: '__pyarmor_enter_41080__'
                        8       LOAD_CONST                      3: b'<COAddr>\x07\x00\x00\x1a\xf6\x01\x00\x00\x00\x00\x00\x00\x00\x00\x00\x00\x00\x00\x00\x00'
                        10      BUILD_TUPLE                     1
                        12      CALL_FUNCTION_EX                0
                        14      POP_TOP                         
                        16      RESUME                          0
                        18      NOP                             
                        20      NOP                             
                        22      NOP                             
                        24      NOP                             
                        26      NOP                             
                        28      LOAD_CONST                      4: '_'
                        30      LOAD_CONST                      5: 'MyBoosts'
                        32      PUSH_NULL                       
                        34      LOAD_CONST                      1: '__pyarmor_assert_41079__'
                        36      LOAD_CONST                      6: 'my_boosts'   # b'\x81\xef\x01,1\xf5\xb1\xc1\x0f\xe9'
                        38      CALL                            1
                        46      LOAD_FAST                       0: self
                        48      LOAD_ATTR                       0: my_boosts
                        68      POP_JUMP_IF_NOT_NONE            2 (to 74)
                        70      BUILD_LIST                      0
                        72      JUMP_FORWARD                    57 (to 188)
                        74      LOAD_FAST                       0: self
                        76      LOAD_ATTR                       0: my_boosts
                        96      GET_ITER                        
                        98      LOAD_FAST_AND_CLEAR             2: _var_var_0
                        100     SWAP                            2
                        102     BUILD_LIST                      0
                        104     SWAP                            2
                        106     FOR_ITER                        36 (to 180)
                        110     STORE_FAST                      2: _var_var_0
                        112     LOAD_GLOBAL                     3: NULL + isinstance
                        122     LOAD_FAST                       2: _var_var_0
                        124     LOAD_GLOBAL                     4: TLObject
                        134     CALL                            2
                        142     POP_JUMP_IF_FALSE               16 (to 176)
                        144     LOAD_FAST                       2: _var_var_0
                        146     LOAD_ATTR                       7: to_dict
                        166     CALL                            0
                        174     JUMP_FORWARD                    1 (to 178)
                        176     LOAD_FAST                       2: _var_var_0
                        178     LIST_APPEND                     2
                        180     JUMP_BACKWARD                   38 (to 106)
                        182     END_FOR                         
                        184     SWAP                            2
                        186     STORE_FAST                      2: _var_var_0
                        188     LOAD_CONST                      7: 'chats'
                        190     LOAD_FAST                       0: self
                        192     LOAD_ATTR                       8: chats
                        212     POP_JUMP_IF_NOT_NONE            2 (to 218)
                        214     BUILD_LIST                      0
                        216     JUMP_FORWARD                    57 (to 332)
                        218     LOAD_FAST                       0: self
                        220     LOAD_ATTR                       8: chats
                        240     GET_ITER                        
                        242     LOAD_FAST_AND_CLEAR             2: _var_var_0
                        244     SWAP                            2
                        246     BUILD_LIST                      0
                        248     SWAP                            2
                        250     FOR_ITER                        36 (to 324)
                        254     STORE_FAST                      2: _var_var_0
                        256     LOAD_GLOBAL                     3: NULL + isinstance
                        266     LOAD_FAST                       2: _var_var_0
                        268     LOAD_GLOBAL                     4: TLObject
                        278     CALL                            2
                        286     POP_JUMP_IF_FALSE               16 (to 320)
                        288     LOAD_FAST                       2: _var_var_0
                        290     LOAD_ATTR                       7: to_dict
                        310     CALL                            0
                        318     JUMP_FORWARD                    1 (to 322)
                        320     LOAD_FAST                       2: _var_var_0
                        322     LIST_APPEND                     2
                        324     JUMP_BACKWARD                   38 (to 250)
                        326     END_FOR                         
                        328     SWAP                            2
                        330     STORE_FAST                      2: _var_var_0
                        332     LOAD_CONST                      8: 'users'
                        334     LOAD_FAST                       0: self
                        336     LOAD_ATTR                       10: users
                        356     POP_JUMP_IF_NOT_NONE            2 (to 362)
                        358     BUILD_LIST                      0
                        360     JUMP_FORWARD                    57 (to 476)
                        362     LOAD_FAST                       0: self
                        364     LOAD_ATTR                       10: users
                        384     GET_ITER                        
                        386     LOAD_FAST_AND_CLEAR             2: _var_var_0
                        388     SWAP                            2
                        390     BUILD_LIST                      0
                        392     SWAP                            2
                        394     FOR_ITER                        36 (to 468)
                        398     STORE_FAST                      2: _var_var_0
                        400     LOAD_GLOBAL                     3: NULL + isinstance
                        410     LOAD_FAST                       2: _var_var_0
                        412     LOAD_GLOBAL                     4: TLObject
                        422     CALL                            2
                        430     POP_JUMP_IF_FALSE               16 (to 464)
                        432     LOAD_FAST                       2: _var_var_0
                        434     LOAD_ATTR                       7: to_dict
                        454     CALL                            0
                        462     JUMP_FORWARD                    1 (to 466)
                        464     LOAD_FAST                       2: _var_var_0
                        466     LIST_APPEND                     2
                        468     JUMP_BACKWARD                   38 (to 394)
                        470     END_FOR                         
                        472     SWAP                            2
                        474     STORE_FAST                      2: _var_var_0
                        476     BUILD_MAP                       4
                        478     NOP                             
                        480     NOP                             
                        482     NOP                             
                        484     JUMP_FORWARD                    35 (to 556)
                        486     CALL                            1
                        494     POP_TOP                         
                        496     RETURN_VALUE                    
                        498     SWAP                            2
                        500     POP_TOP                         
                        502     SWAP                            2
                        504     STORE_FAST                      2: _var_var_0
                        506     RERAISE                         0
                        508     SWAP                            2
                        510     POP_TOP                         
                        512     SWAP                            2
                        514     STORE_FAST                      2: _var_var_0
                        516     RERAISE                         0
                        518     SWAP                            2
                        520     POP_TOP                         
                        522     SWAP                            2
                        524     STORE_FAST                      2: _var_var_0
                        526     RERAISE                         0
                        528     PUSH_EXC_INFO                   
                        530     PUSH_NULL                       
                        532     LOAD_CONST                      9: '__pyarmor_exit_41081__'
                        534     NOP                             
                        536     LOAD_CONST                      3: b'<COAddr>\x07\x00\x00\x1a\xf6\x01\x00\x00\x00\x00\x00\x00\x00\x00\x00\x00\x00\x00\x00\x00'
                        538     CALL                            1
                        546     POP_TOP                         
                        548     RERAISE                         0
                        550     COPY                            3
                        552     POP_EXCEPT                      
                        554     RERAISE                         1
                        556     PUSH_NULL                       
                        558     LOAD_CONST                      9: '__pyarmor_exit_41081__'
                        560     LOAD_CONST                      3: b'<COAddr>\x07\x00\x00\x1a\xf6\x01\x00\x00\x00\x00\x00\x00\x00\x00\x00\x00\x00\x00\x00\x00'
                        562     BUILD_TUPLE                     1
                        564     CALL_FUNCTION_EX                0
                        566     POP_TOP                         
                        568     RETURN_VALUE                    
                    [Exception Table]
                        28 to 102 -> 528 [0] 
                        102 to 184 -> 498 [5] 
                        184 to 246 -> 528 [0] 
                        246 to 328 -> 508 [7] 
                        328 to 390 -> 528 [0] 
                        390 to 472 -> 518 [9] 
                        472 to 478 -> 528 [0] 
                        498 to 528 -> 528 [0] 
                        528 to 550 -> 550 [1] lasti
                [Code]
                    File Name: <frozen multithon.tl.types.premium>
                    Object Name: _bytes
                    Qualified Name: MyBoosts._bytes
                    Arg Count: 1
                    Pos Only Arg Count: 0
                    KW Only Arg Count: 0
                    Stack Size: 16
                    Flags: 0x20000003 (CO_OPTIMIZED | CO_NEWLOCALS | CO_PYARMOR_OBFUSCATED)
                    [Names]
                        'join'
                        'struct'
                        'pack'
                        'len'
                        'my_boosts'
                        'chats'
                        'users'
                    [Locals+Names]
                        'self'
                        '__assert_armored__'
                    [Constants]
                        None
                        '__pyarmor_assert_41082__'
                        '__pyarmor_enter_41083__'
                        b'<COAddr>\x05\x00\x00\x1a\xf4\x01\x00\x00\x00\x00\x00\x00\x00\x00\x00\x00\x00\x00\x00\x00'
                        b''
                        b'\xe2(\xe2\x9a'
                        b'\x15\xc4\xb5\x1c'
                        '<i'
                        [Code]
                            File Name: <frozen multithon.tl.types.premium>
                            Object Name: <genexpr>
                            Qualified Name: MyBoosts._bytes.<locals>.<genexpr>
                            Arg Count: 1
                            Pos Only Arg Count: 0
                            KW Only Arg Count: 0
                            Stack Size: 3
                            Flags: 0x00000033 (CO_OPTIMIZED | CO_NEWLOCALS | CO_NESTED | CO_GENERATOR)
                            [Names]
                                '_bytes'
                            [Locals+Names]
                                '.0'
                                '_var_var_0'
                            [Constants]
                                None
                            [Disassembly]
                                0       RETURN_GENERATOR                
                                2       POP_TOP                         
                                4       RESUME                          0
                                6       LOAD_FAST                       0: .0
                                8       FOR_ITER                        20 (to 50)
                                12      STORE_FAST                      1: _var_var_0
                                14      LOAD_FAST                       1: _var_var_0
                                16      LOAD_ATTR                       1: _bytes
                                36      CALL                            0
                                44      YIELD_VALUE                     1
                                46      RESUME                          1
                                48      POP_TOP                         
                                50      JUMP_BACKWARD                   22 (to 8)
                                52      END_FOR                         
                                54      RETURN_CONST                    0: None
                                56      CALL_INTRINSIC_1                3 (INTRINSIC_STOPITERATION_ERROR)
                                58      RERAISE                         1
                            [Exception Table]
                                4 to 56 -> 56 [0] lasti
                        [Code]
                            File Name: <frozen multithon.tl.types.premium>
                            Object Name: <genexpr>
                            Qualified Name: MyBoosts._bytes.<locals>.<genexpr>
                            Arg Count: 1
                            Pos Only Arg Count: 0
                            KW Only Arg Count: 0
                            Stack Size: 3
                            Flags: 0x00000033 (CO_OPTIMIZED | CO_NEWLOCALS | CO_NESTED | CO_GENERATOR)
                            [Names]
                                '_bytes'
                            [Locals+Names]
                                '.0'
                                '_var_var_0'
                            [Constants]
                                None
                            [Disassembly]
                                0       RETURN_GENERATOR                
                                2       POP_TOP                         
                                4       RESUME                          0
                                6       LOAD_FAST                       0: .0
                                8       FOR_ITER                        20 (to 50)
                                12      STORE_FAST                      1: _var_var_0
                                14      LOAD_FAST                       1: _var_var_0
                                16      LOAD_ATTR                       1: _bytes
                                36      CALL                            0
                                44      YIELD_VALUE                     1
                                46      RESUME                          1
                                48      POP_TOP                         
                                50      JUMP_BACKWARD                   22 (to 8)
                                52      END_FOR                         
                                54      RETURN_CONST                    0: None
                                56      CALL_INTRINSIC_1                3 (INTRINSIC_STOPITERATION_ERROR)
                                58      RERAISE                         1
                            [Exception Table]
                                4 to 56 -> 56 [0] lasti
                        [Code]
                            File Name: <frozen multithon.tl.types.premium>
                            Object Name: <genexpr>
                            Qualified Name: MyBoosts._bytes.<locals>.<genexpr>
                            Arg Count: 1
                            Pos Only Arg Count: 0
                            KW Only Arg Count: 0
                            Stack Size: 3
                            Flags: 0x00000033 (CO_OPTIMIZED | CO_NEWLOCALS | CO_NESTED | CO_GENERATOR)
                            [Names]
                                '_bytes'
                            [Locals+Names]
                                '.0'
                                '_var_var_0'
                            [Constants]
                                None
                            [Disassembly]
                                0       RETURN_GENERATOR                
                                2       POP_TOP                         
                                4       RESUME                          0
                                6       LOAD_FAST                       0: .0
                                8       FOR_ITER                        20 (to 50)
                                12      STORE_FAST                      1: _var_var_0
                                14      LOAD_FAST                       1: _var_var_0
                                16      LOAD_ATTR                       1: _bytes
                                36      CALL                            0
                                44      YIELD_VALUE                     1
                                46      RESUME                          1
                                48      POP_TOP                         
                                50      JUMP_BACKWARD                   22 (to 8)
                                52      END_FOR                         
                                54      RETURN_CONST                    0: None
                                56      CALL_INTRINSIC_1                3 (INTRINSIC_STOPITERATION_ERROR)
                                58      RERAISE                         1
                            [Exception Table]
                                4 to 56 -> 56 [0] lasti
                        '__pyarmor_exit_41084__'
                    [Disassembly]
                        0       NOP                             
                        2       NOP                             
                        4       PUSH_NULL                       
                        6       LOAD_CONST                      2: '__pyarmor_enter_41083__'
                        8       LOAD_CONST                      3: b'<COAddr>\x05\x00\x00\x1a\xf4\x01\x00\x00\x00\x00\x00\x00\x00\x00\x00\x00\x00\x00\x00\x00'
                        10      BUILD_TUPLE                     1
                        12      CALL_FUNCTION_EX                0
                        14      POP_TOP                         
                        16      RESUME                          0
                        18      NOP                             
                        20      NOP                             
                        22      NOP                             
                        24      NOP                             
                        26      NOP                             
                        28      LOAD_CONST                      4: b''
                        30      LOAD_ATTR                       1: join
                        50      LOAD_CONST                      5: b'\xe2(\xe2\x9a'
                        52      LOAD_CONST                      6: b'\x15\xc4\xb5\x1c'
                        54      LOAD_GLOBAL                     3: NULL + struct
                        64      LOAD_ATTR                       4: pack
                        84      LOAD_CONST                      7: '<i'
                        86      LOAD_GLOBAL                     7: NULL + len
                        96      LOAD_FAST                       0: self
                        98      LOAD_ATTR                       8: my_boosts
                        118     CALL                            1
                        126     CALL                            2
                        134     LOAD_CONST                      4: b''
                        136     LOAD_ATTR                       1: join
                        156     LOAD_CONST                      8: <CODE> <genexpr>
                        158     MAKE_FUNCTION                   0
                        160     LOAD_FAST                       0: self
                        162     LOAD_ATTR                       8: my_boosts
                        182     GET_ITER                        
                        184     CALL                            0
                        192     CALL                            1
                        200     LOAD_CONST                      6: b'\x15\xc4\xb5\x1c'
                        202     LOAD_GLOBAL                     3: NULL + struct
                        212     LOAD_ATTR                       4: pack
                        232     LOAD_CONST                      7: '<i'
                        234     LOAD_GLOBAL                     7: NULL + len
                        244     LOAD_FAST                       0: self
                        246     LOAD_ATTR                       10: chats
                        266     CALL                            1
                        274     CALL                            2
                        282     LOAD_CONST                      4: b''
                        284     LOAD_ATTR                       1: join
                        304     LOAD_CONST                      9: <CODE> <genexpr>
                        306     MAKE_FUNCTION                   0
                        308     LOAD_FAST                       0: self
                        310     LOAD_ATTR                       10: chats
                        330     GET_ITER                        
                        332     CALL                            0
                        340     CALL                            1
                        348     LOAD_CONST                      6: b'\x15\xc4\xb5\x1c'
                        350     LOAD_GLOBAL                     3: NULL + struct
                        360     LOAD_ATTR                       4: pack
                        380     LOAD_CONST                      7: '<i'
                        382     LOAD_GLOBAL                     7: NULL + len
                        392     LOAD_FAST                       0: self
                        394     LOAD_ATTR                       12: users
                        414     CALL                            1
                        422     CALL                            2
                        430     LOAD_CONST                      4: b''
                        432     LOAD_ATTR                       1: join
                        452     LOAD_CONST                      10: <CODE> <genexpr>
                        454     MAKE_FUNCTION                   0
                        456     LOAD_FAST                       0: self
                        458     LOAD_ATTR                       12: users
                        478     GET_ITER                        
                        480     CALL                            0
                        488     CALL                            1
                        496     BUILD_TUPLE                     10
                        498     CALL                            1
                        506     NOP                             
                        508     NOP                             
                        510     NOP                             
                        512     JUMP_FORWARD                    20 (to 554)
                        514     CALL                            1
                        522     POP_TOP                         
                        524     RETURN_VALUE                    
                        526     PUSH_EXC_INFO                   
                        528     PUSH_NULL                       
                        530     LOAD_CONST                      11: '__pyarmor_exit_41084__'
                        532     NOP                             
                        534     LOAD_CONST                      3: b'<COAddr>\x05\x00\x00\x1a\xf4\x01\x00\x00\x00\x00\x00\x00\x00\x00\x00\x00\x00\x00\x00\x00'
                        536     CALL                            1
                        544     POP_TOP                         
                        546     RERAISE                         0
                        548     COPY                            3
                        550     POP_EXCEPT                      
                        552     RERAISE                         1
                        554     PUSH_NULL                       
                        556     LOAD_CONST                      11: '__pyarmor_exit_41084__'
                        558     LOAD_CONST                      3: b'<COAddr>\x05\x00\x00\x1a\xf4\x01\x00\x00\x00\x00\x00\x00\x00\x00\x00\x00\x00\x00\x00\x00'
                        560     BUILD_TUPLE                     1
                        562     CALL_FUNCTION_EX                0
                        564     POP_TOP                         
                        566     RETURN_VALUE                    
                    [Exception Table]
                        28 to 506 -> 526 [0] 
                        526 to 548 -> 548 [1] lasti
                [Code]
                    File Name: <frozen multithon.tl.types.premium>
                    Object Name: from_reader
                    Qualified Name: MyBoosts.from_reader
                    Arg Count: 2
                    Pos Only Arg Count: 0
                    KW Only Arg Count: 0
                    Stack Size: 5
                    Flags: 0x20000003 (CO_OPTIMIZED | CO_NEWLOCALS | CO_PYARMOR_OBFUSCATED)
                    [Names]
                        'read_int'
                        'range'
                        'tgread_object'
                        'append'
                    [Locals+Names]
                        'cls'
                        'reader'
                        '__assert_armored__'
                        '_var_var_17'
                        '_var_var_4'
                        '_var_var_5'
                        '_var_var_18'
                        '_var_var_7'
                    [Constants]
                        None
                        '__pyarmor_assert_41085__'
                        '__pyarmor_enter_41086__'
                        b'<COAddr>\x05\x00\x00\x1a\x10\x02\x00\x00\x00\x00\x00\x00\x00\x00\x00\x00\x00\x00\x00\x00'
                        (
                            'my_boosts'
                            'chats'
                            'users'
                        )
                        '__pyarmor_exit_41087__'
                    [Disassembly]
                        0       NOP                             
                        2       NOP                             
                        4       PUSH_NULL                       
                        6       LOAD_CONST                      2: '__pyarmor_enter_41086__'
                        8       LOAD_CONST                      3: b'<COAddr>\x05\x00\x00\x1a\x10\x02\x00\x00\x00\x00\x00\x00\x00\x00\x00\x00\x00\x00\x00\x00'
                        10      BUILD_TUPLE                     1
                        12      CALL_FUNCTION_EX                0
                        14      POP_TOP                         
                        16      RESUME                          0
                        18      NOP                             
                        20      NOP                             
                        22      NOP                             
                        24      NOP                             
                        26      NOP                             
                        28      LOAD_FAST                       1: reader
                        30      LOAD_ATTR                       1: read_int
                        50      CALL                            0
                        58      POP_TOP                         
                        60      BUILD_LIST                      0
                        62      STORE_FAST                      3: _var_var_17
                        64      LOAD_GLOBAL                     3: NULL + range
                        74      LOAD_FAST                       1: reader
                        76      LOAD_ATTR                       1: read_int
                        96      CALL                            0
                        104     CALL                            1
                        112     GET_ITER                        
                        114     FOR_ITER                        35 (to 186)
                        118     STORE_FAST                      4: _var_var_4
                        120     LOAD_FAST                       1: reader
                        122     LOAD_ATTR                       5: tgread_object
                        142     CALL                            0
                        150     STORE_FAST                      5: _var_var_5
                        152     LOAD_FAST                       3: _var_var_17
                        154     LOAD_ATTR                       7: append
                        174     LOAD_FAST                       5: _var_var_5
                        176     CALL                            1
                        184     POP_TOP                         
                        186     JUMP_BACKWARD                   37 (to 114)
                        188     END_FOR                         
                        190     LOAD_FAST                       1: reader
                        192     LOAD_ATTR                       1: read_int
                        212     CALL                            0
                        220     POP_TOP                         
                        222     BUILD_LIST                      0
                        224     STORE_FAST                      6: _var_var_18
                        226     LOAD_GLOBAL                     3: NULL + range
                        236     LOAD_FAST                       1: reader
                        238     LOAD_ATTR                       1: read_int
                        258     CALL                            0
                        266     CALL                            1
                        274     GET_ITER                        
                        276     FOR_ITER                        35 (to 348)
                        280     STORE_FAST                      4: _var_var_4
                        282     LOAD_FAST                       1: reader
                        284     LOAD_ATTR                       5: tgread_object
                        304     CALL                            0
                        312     STORE_FAST                      5: _var_var_5
                        314     LOAD_FAST                       6: _var_var_18
                        316     LOAD_ATTR                       7: append
                        336     LOAD_FAST                       5: _var_var_5
                        338     CALL                            1
                        346     POP_TOP                         
                        348     JUMP_BACKWARD                   37 (to 276)
                        350     END_FOR                         
                        352     LOAD_FAST                       1: reader
                        354     LOAD_ATTR                       1: read_int
                        374     CALL                            0
                        382     POP_TOP                         
                        384     BUILD_LIST                      0
                        386     STORE_FAST                      7: _var_var_7
                        388     LOAD_GLOBAL                     3: NULL + range
                        398     LOAD_FAST                       1: reader
                        400     LOAD_ATTR                       1: read_int
                        420     CALL                            0
                        428     CALL                            1
                        436     GET_ITER                        
                        438     FOR_ITER                        35 (to 510)
                        442     STORE_FAST                      4: _var_var_4
                        444     LOAD_FAST                       1: reader
                        446     LOAD_ATTR                       5: tgread_object
                        466     CALL                            0
                        474     STORE_FAST                      5: _var_var_5
                        476     LOAD_FAST                       7: _var_var_7
                        478     LOAD_ATTR                       7: append
                        498     LOAD_FAST                       5: _var_var_5
                        500     CALL                            1
                        508     POP_TOP                         
                        510     JUMP_BACKWARD                   37 (to 438)
                        512     END_FOR                         
                        514     PUSH_NULL                       
                        516     LOAD_FAST                       0: cls
                        518     LOAD_FAST                       3: _var_var_17
                        520     LOAD_FAST                       6: _var_var_18
                        522     LOAD_FAST                       7: _var_var_7
                        524     KW_NAMES                        4: ('my_boosts', 'chats', 'users')
                        526     CALL                            3
                        534     NOP                             
                        536     NOP                             
                        538     NOP                             
                        540     JUMP_FORWARD                    20 (to 582)
                        542     CALL                            1
                        550     POP_TOP                         
                        552     RETURN_VALUE                    
                        554     PUSH_EXC_INFO                   
                        556     PUSH_NULL                       
                        558     LOAD_CONST                      5: '__pyarmor_exit_41087__'
                        560     NOP                             
                        562     LOAD_CONST                      3: b'<COAddr>\x05\x00\x00\x1a\x10\x02\x00\x00\x00\x00\x00\x00\x00\x00\x00\x00\x00\x00\x00\x00'
                        564     CALL                            1
                        572     POP_TOP                         
                        574     RERAISE                         0
                        576     COPY                            3
                        578     POP_EXCEPT                      
                        580     RERAISE                         1
                        582     PUSH_NULL                       
                        584     LOAD_CONST                      5: '__pyarmor_exit_41087__'
                        586     LOAD_CONST                      3: b'<COAddr>\x05\x00\x00\x1a\x10\x02\x00\x00\x00\x00\x00\x00\x00\x00\x00\x00\x00\x00\x00\x00'
                        588     BUILD_TUPLE                     1
                        590     CALL_FUNCTION_EX                0
                        592     POP_TOP                         
                        594     RETURN_VALUE                    
                    [Exception Table]
                        28 to 534 -> 554 [0] 
                        554 to 576 -> 576 [1] lasti
                '__pyarmor_exit_41075__'
                None
            [Disassembly]
                0       NOP                             
                2       LOAD_NAME                       0: __name__
                4       STORE_NAME                      1: __module__
                6       LOAD_CONST                      0: 'MyBoosts'
                8       STORE_NAME                      2: __qualname__
                10      NOP                             
                12      PUSH_NULL                       
                14      LOAD_CONST                      2: '__pyarmor_enter_41074__'
                16      LOAD_CONST                      3: b'<COAddr>\x05\x00\x00"l\x00\x00\x00\x00\x00\x00\x00\x00\x00\x00\x00\x00\x00\x00\x00'
                18      BUILD_TUPLE                     1
                20      CALL_FUNCTION_EX                0
                22      POP_TOP                         
                24      RESUME                          0
                26      NOP                             
                28      NOP                             
                30      NOP                             
                32      NOP                             
                34      NOP                             
                36      LOAD_CONST                      4: 0x9AE228E2
                38      STORE_NAME                      4: CONSTRUCTOR_ID
                40      LOAD_CONST                      5: 0xAD3512DB
                42      STORE_NAME                      5: SUBCLASS_OF_ID
                44      LOAD_CONST                      6: 'my_boosts'
                46      LOAD_NAME                       6: List
                48      PUSH_NULL                       
                50      LOAD_CONST                      1: '__pyarmor_assert_41073__'
                52      LOAD_CONST                      7: 'TypeMyBoost'   # b'\x81\xd6\x01\x036\xd7\xa7\xf0\x14\xf5\x1e\xd4'
                54      CALL                            1
                62      BINARY_SUBSCR                   
                66      LOAD_CONST                      8: 'chats'
                68      LOAD_NAME                       6: List
                70      LOAD_CONST                      9: 'TypeChat'
                72      BINARY_SUBSCR                   
                76      LOAD_CONST                      10: 'users'
                78      LOAD_NAME                       6: List
                80      LOAD_CONST                      11: 'TypeUser'
                82      BINARY_SUBSCR                   
                86      BUILD_TUPLE                     6
                88      LOAD_CONST                      12: <CODE> __init__
                90      MAKE_FUNCTION                   4
                92      STORE_NAME                      7: __init__
                94      LOAD_CONST                      13: <CODE> to_dict
                96      MAKE_FUNCTION                   0
                98      STORE_NAME                      8: to_dict
                100     LOAD_CONST                      14: <CODE> _bytes
                102     MAKE_FUNCTION                   0
                104     STORE_NAME                      9: _bytes
                106     LOAD_NAME                       10: classmethod
                108     LOAD_CONST                      15: <CODE> from_reader
                110     MAKE_FUNCTION                   0
                112     CALL                            0
                120     STORE_NAME                      11: from_reader
                122     LOAD_CONST                      17: None
                124     NOP                             
                126     NOP                             
                128     NOP                             
                130     JUMP_FORWARD                    19 (to 170)
                138     POP_TOP                         
                140     RETURN_CONST                    17: None
                142     PUSH_EXC_INFO                   
                144     PUSH_NULL                       
                146     LOAD_CONST                      16: '__pyarmor_exit_41075__'
                148     NOP                             
                150     LOAD_CONST                      3: b'<COAddr>\x05\x00\x00"l\x00\x00\x00\x00\x00\x00\x00\x00\x00\x00\x00\x00\x00\x00\x00'
                152     CALL                            1
                160     POP_TOP                         
                162     RERAISE                         0
                164     COPY                            3
                166     POP_EXCEPT                      
                168     RERAISE                         1
                170     PUSH_NULL                       
                172     LOAD_CONST                      16: '__pyarmor_exit_41075__'
                174     LOAD_CONST                      3: b'<COAddr>\x05\x00\x00"l\x00\x00\x00\x00\x00\x00\x00\x00\x00\x00\x00\x00\x00\x00\x00'
                176     BUILD_TUPLE                     1
                178     CALL_FUNCTION_EX                0
                180     POP_TOP                         
                182     RETURN_VALUE                    
            [Exception Table]
                36 to 122 -> 142 [0] 
                142 to 164 -> 164 [1] lasti
        'MyBoosts'
        '__pyarmor_exit_41042__'
    [Disassembly]
        0       NOP                             
        2       NOP                             
        4       PUSH_NULL                       
        6       LOAD_CONST                      1: '__pyarmor_enter_41041__'
        8       LOAD_CONST                      2: b'<COAddr>\x05\x00\x00\x1a\xca\x00\x00\x00\x00\x00\x00\x00\x00\x00\x00\x00\x00\x00\x00\x00'
        10      BUILD_TUPLE                     1
        12      CALL_FUNCTION_EX                0
        14      POP_TOP                         
        16      RESUME                          0
        18      NOP                             
        20      NOP                             
        22      NOP                             
        24      NOP                             
        26      PUSH_NULL                       
        28      LOAD_CONST                      0: '__pyarmor_assert_41040__'
        30      LOAD_CONST                      3: "File generated by TLObjects' generator. All changes will be ERASED"   # b'\x81\xc4\x11\x1f6\xba\xb9\xd7\x15\xff\x1f\xc1x\xe9\xfc\xc5\rD\xfb\x93\x86\xe4L\xc6\x00l\xb7OG\xf1\x19\xe04W2\x0c\x8c\xc5\xa6`X\xc8\xf4Q\x9d\xdb\x07F9\xeaS\xe8\xc7g\x0f\xe1;\xab\x99\x18Xn\x03rdm!'
        32      CALL                            1
        40      POP_TOP                         
        42      LOAD_CONST                      4: 3
        44      LOAD_CONST                      5: ('TLObject',)
        46      IMPORT_NAME                     1: tl.tlobject
        48      IMPORT_FROM                     2: TLObject
        50      STORE_NAME                      2: TLObject
        52      POP_TOP                         
        54      LOAD_CONST                      6: 0
        56      LOAD_CONST                      7: ('Optional', 'List', 'Union', 'TYPE_CHECKING')
        58      IMPORT_NAME                     3: typing
        60      IMPORT_FROM                     4: Optional
        62      STORE_NAME                      4: Optional
        64      IMPORT_FROM                     5: List
        66      STORE_NAME                      5: List
        68      IMPORT_FROM                     6: Union
        70      STORE_NAME                      6: Union
        72      IMPORT_FROM                     7: TYPE_CHECKING
        74      STORE_NAME                      7: TYPE_CHECKING
        76      POP_TOP                         
        78      LOAD_CONST                      6: 0
        80      LOAD_CONST                      8: None
        82      IMPORT_NAME                     8: os
        84      STORE_NAME                      8: os
        86      LOAD_CONST                      6: 0
        88      LOAD_CONST                      8: None
        90      IMPORT_NAME                     9: struct
        92      STORE_NAME                      9: struct
        94      LOAD_CONST                      6: 0
        96      LOAD_CONST                      9: ('datetime',)
        98      IMPORT_NAME                     10: datetime
        100     IMPORT_FROM                     10: datetime
        102     STORE_NAME                      10: datetime
        104     POP_TOP                         
        106     LOAD_NAME                       7: TYPE_CHECKING
        108     POP_JUMP_IF_FALSE               16 (to 142)
        110     LOAD_CONST                      4: 3
        112     LOAD_CONST                      10: ('TypeBoost', 'TypeChat', 'TypeMyBoost', 'TypePrepaidGiveaway', 'TypeStatsPercentValue', 'TypeUser')
        114     IMPORT_NAME                     11: tl.types
        116     IMPORT_FROM                     12: TypeBoost
        118     STORE_NAME                      12: TypeBoost
        120     IMPORT_FROM                     13: TypeChat
        122     STORE_NAME                      13: TypeChat
        124     IMPORT_FROM                     14: TypeMyBoost
        126     STORE_NAME                      14: TypeMyBoost
        128     IMPORT_FROM                     15: TypePrepaidGiveaway
        130     STORE_NAME                      15: TypePrepaidGiveaway
        132     IMPORT_FROM                     16: TypeStatsPercentValue
        134     STORE_NAME                      16: TypeStatsPercentValue
        136     IMPORT_FROM                     17: TypeUser
        138     STORE_NAME                      17: TypeUser
        140     POP_TOP                         
        142     PUSH_NULL                       
        144     LOAD_BUILD_CLASS                
        146     LOAD_CONST                      11: <CODE> BoostsList
        148     MAKE_FUNCTION                   0
        150     LOAD_CONST                      12: 'BoostsList'
        152     LOAD_NAME                       2: TLObject
        154     CALL                            3
        162     STORE_NAME                      18: BoostsList
        164     PUSH_NULL                       
        166     LOAD_BUILD_CLASS                
        168     LOAD_CONST                      13: <CODE> BoostsStatus
        170     MAKE_FUNCTION                   0
        172     LOAD_CONST                      14: 'BoostsStatus'
        174     LOAD_NAME                       2: TLObject
        176     CALL                            3
        184     STORE_NAME                      19: BoostsStatus
        186     PUSH_NULL                       
        188     LOAD_BUILD_CLASS                
        190     LOAD_CONST                      15: <CODE> MyBoosts
        192     MAKE_FUNCTION                   0
        194     LOAD_CONST                      16: 'MyBoosts'
        196     LOAD_NAME                       2: TLObject
        198     CALL                            3
        206     STORE_NAME                      20: MyBoosts
        208     LOAD_CONST                      8: None
        210     NOP                             
        212     NOP                             
        214     NOP                             
        216     JUMP_FORWARD                    19 (to 256)
        224     POP_TOP                         
        226     RETURN_CONST                    8: None
        228     PUSH_EXC_INFO                   
        230     PUSH_NULL                       
        232     LOAD_CONST                      17: '__pyarmor_exit_41042__'
        234     NOP                             
        236     LOAD_CONST                      2: b'<COAddr>\x05\x00\x00\x1a\xca\x00\x00\x00\x00\x00\x00\x00\x00\x00\x00\x00\x00\x00\x00\x00'
        238     CALL                            1
        246     POP_TOP                         
        248     RERAISE                         0
        250     COPY                            3
        252     POP_EXCEPT                      
        254     RERAISE                         1
        256     PUSH_NULL                       
        258     LOAD_CONST                      17: '__pyarmor_exit_41042__'
        260     LOAD_CONST                      2: b'<COAddr>\x05\x00\x00\x1a\xca\x00\x00\x00\x00\x00\x00\x00\x00\x00\x00\x00\x00\x00\x00\x00'
        262     BUILD_TUPLE                     1
        264     CALL_FUNCTION_EX                0
        266     POP_TOP                         
        268     RETURN_VALUE                    
    [Exception Table]
        26 to 208 -> 228 [0] 
        228 to 250 -> 250 [1] lasti
