#decoded by lolz.live/mrpenny / t.me/zeus_jackpot
# ================================
# Примечания по Pyarmor:
# - Байт-код и объекты кода Pyarmor соответствуют стандартному Python, но присутствуют специальные вызовы функций среды выполнения (runtime) Pyarmor.
# - Вызовы строк — это не ошибки, а маркеры, которые обрабатываются Pyarmor во время выполнения.
#
# Руководство по декомпиляции (без среды выполнения):
# 1. Игнорируйте зашифрованные байты после `#`; используйте только строку до `#`.
# 2. Удалите "__pyarmor_enter_xxx__"(b"<COAddr>...") и "__pyarmor_leave_xxx__"(b"<COAddr>...") (пролог/эпилог).
# 3. "__pyarmor_assert_xxx__"(A) не является настоящим оператором assert.
#    - Если A — это имя или читаемая строка: замените на A.
#    - Если A — это (X, "Y"): замените на X.Y.
#    - Если A — это (X, "Y", Z): замените на X.Y = Z.
#    - В противном случае: выберите наиболее подходящую/логичную замену.
# 4. "__pyarmor_bcc_xxx__"(...) указывает на машинный (нативный) код; тело функции недоступно. Добавьте комментарий.
# ================================

[Code]
    File Name: <frozen multithon.tl.types.storage>
    Object Name: <module>
    Qualified Name: <module>
    Arg Count: 0
    Pos Only Arg Count: 0
    KW Only Arg Count: 0
    Stack Size: 5
    Flags: 0x20000000 (CO_PYARMOR_OBFUSCATED)
    [Names]
        '__assert_armored__'
        'tl.tlobject'
        'TLObject'
        'typing'
        'Optional'
        'List'
        'Union'
        'TYPE_CHECKING'
        'os'
        'struct'
        'datetime'
        'FileGif'
        'FileJpeg'
        'FileMov'
        'FileMp3'
        'FileMp4'
        'FilePartial'
        'FilePdf'
        'FilePng'
        'FileUnknown'
        'FileWebp'
    [Locals+Names]
    [Constants]
        '__pyarmor_assert_41262__'
        '__pyarmor_enter_41263__'
        b'<COAddr>\x07\x00\x00\x1a@\x01\x00\x00\x00\x00\x00\x00\x00\x00\x00\x00\x00\x00\x00\x00'
        "File generated by TLObjects' generator. All changes will be ERASED"   # b'\x81\xc4\x11\x1f6\xba\xb9\xd7\x15\xff\x1f\xc1x\xe9\xfc\xc5\rD\xfb\x93\x86\xe4L\xc6\x00l\xb7OG\xf1\x19\xe04W2\x0c\x8c\xc5\xa6`X\xc8\xf4Q\x9d\xdb\x07F9\xeaS\xe8\xc7g\x0f\xe1;\xab\x99\x18Xn\x03rdm!'
        3
        (
            'TLObject'
        )
        0
        (
            'Optional'
            'List'
            'Union'
            'TYPE_CHECKING'
        )
        None
        (
            'datetime'
        )
        [Code]
            File Name: <frozen multithon.tl.types.storage>
            Object Name: FileGif
            Qualified Name: FileGif
            Arg Count: 0
            Pos Only Arg Count: 0
            KW Only Arg Count: 0
            Stack Size: 5
            Flags: 0x20000000 (CO_PYARMOR_OBFUSCATED)
            [Names]
                '__name__'
                '__module__'
                '__qualname__'
                '__assert_armored__'
                'CONSTRUCTOR_ID'
                'SUBCLASS_OF_ID'
                'to_dict'
                '_bytes'
                'classmethod'
                'from_reader'
            [Locals+Names]
            [Constants]
                'FileGif'
                '__pyarmor_assert_41265__'
                '__pyarmor_enter_41266__'
                b'<COAddr>\x05\x00\x00":\x00\x00\x00\x00\x00\x00\x00\x00\x00\x00\x00\x00\x00\x00\x00'
                0xCAE1AADF
                0xF3A1E6F3
                [Code]
                    File Name: <frozen multithon.tl.types.storage>
                    Object Name: to_dict
                    Qualified Name: FileGif.to_dict
                    Arg Count: 1
                    Pos Only Arg Count: 0
                    KW Only Arg Count: 0
                    Stack Size: 5
                    Flags: 0x20000003 (CO_OPTIMIZED | CO_NEWLOCALS | CO_PYARMOR_OBFUSCATED)
                    [Names]
                    [Locals+Names]
                        'self'
                        '__assert_armored__'
                    [Constants]
                        None
                        '__pyarmor_assert_41268__'
                        '__pyarmor_enter_41269__'
                        b'<COAddr>\x07\x00\x00\x1a\x1c\x00\x00\x00\x00\x00\x00\x00\x00\x00\x00\x00\x00\x00\x00\x00'
                        '_'
                        'FileGif'
                        '__pyarmor_exit_41270__'
                    [Disassembly]
                        0       NOP                             
                        2       NOP                             
                        4       PUSH_NULL                       
                        6       LOAD_CONST                      2: '__pyarmor_enter_41269__'
                        8       LOAD_CONST                      3: b'<COAddr>\x07\x00\x00\x1a\x1c\x00\x00\x00\x00\x00\x00\x00\x00\x00\x00\x00\x00\x00\x00\x00'
                        10      BUILD_TUPLE                     1
                        12      CALL_FUNCTION_EX                0
                        14      POP_TOP                         
                        16      RESUME                          0
                        18      NOP                             
                        20      NOP                             
                        22      NOP                             
                        24      NOP                             
                        26      NOP                             
                        28      LOAD_CONST                      4: '_'
                        30      LOAD_CONST                      5: 'FileGif'
                        32      BUILD_MAP                       1
                        34      NOP                             
                        36      NOP                             
                        38      NOP                             
                        40      JUMP_FORWARD                    20 (to 82)
                        42      CALL                            1
                        50      POP_TOP                         
                        52      RETURN_VALUE                    
                        54      PUSH_EXC_INFO                   
                        56      PUSH_NULL                       
                        58      LOAD_CONST                      6: '__pyarmor_exit_41270__'
                        60      NOP                             
                        62      LOAD_CONST                      3: b'<COAddr>\x07\x00\x00\x1a\x1c\x00\x00\x00\x00\x00\x00\x00\x00\x00\x00\x00\x00\x00\x00\x00'
                        64      CALL                            1
                        72      POP_TOP                         
                        74      RERAISE                         0
                        76      COPY                            3
                        78      POP_EXCEPT                      
                        80      RERAISE                         1
                        82      PUSH_NULL                       
                        84      LOAD_CONST                      6: '__pyarmor_exit_41270__'
                        86      LOAD_CONST                      3: b'<COAddr>\x07\x00\x00\x1a\x1c\x00\x00\x00\x00\x00\x00\x00\x00\x00\x00\x00\x00\x00\x00\x00'
                        88      BUILD_TUPLE                     1
                        90      CALL_FUNCTION_EX                0
                        92      POP_TOP                         
                        94      RETURN_VALUE                    
                    [Exception Table]
                        28 to 34 -> 54 [0] 
                        54 to 76 -> 76 [1] lasti
                [Code]
                    File Name: <frozen multithon.tl.types.storage>
                    Object Name: _bytes
                    Qualified Name: FileGif._bytes
                    Arg Count: 1
                    Pos Only Arg Count: 0
                    KW Only Arg Count: 0
                    Stack Size: 5
                    Flags: 0x20000003 (CO_OPTIMIZED | CO_NEWLOCALS | CO_PYARMOR_OBFUSCATED)
                    [Names]
                        'join'
                    [Locals+Names]
                        'self'
                        '__assert_armored__'
                    [Constants]
                        None
                        '__pyarmor_assert_41271__'
                        '__pyarmor_enter_41272__'
                        b'<COAddr>\x07\x00\x00\x1a6\x00\x00\x00\x00\x00\x00\x00\x00\x00\x00\x00\x00\x00\x00\x00'
                        b''
                        (
                            b'\xdf\xaa\xe1\xca'
                        )
                        '__pyarmor_exit_41273__'
                    [Disassembly]
                        0       NOP                             
                        2       NOP                             
                        4       PUSH_NULL                       
                        6       LOAD_CONST                      2: '__pyarmor_enter_41272__'
                        8       LOAD_CONST                      3: b'<COAddr>\x07\x00\x00\x1a6\x00\x00\x00\x00\x00\x00\x00\x00\x00\x00\x00\x00\x00\x00\x00'
                        10      BUILD_TUPLE                     1
                        12      CALL_FUNCTION_EX                0
                        14      POP_TOP                         
                        16      RESUME                          0
                        18      NOP                             
                        20      NOP                             
                        22      NOP                             
                        24      NOP                             
                        26      NOP                             
                        28      LOAD_CONST                      4: b''
                        30      LOAD_ATTR                       1: join
                        50      LOAD_CONST                      5: (b'\xdf\xaa\xe1\xca',)
                        52      CALL                            1
                        60      NOP                             
                        62      NOP                             
                        64      NOP                             
                        66      JUMP_FORWARD                    20 (to 108)
                        68      CALL                            1
                        76      POP_TOP                         
                        78      RETURN_VALUE                    
                        80      PUSH_EXC_INFO                   
                        82      PUSH_NULL                       
                        84      LOAD_CONST                      6: '__pyarmor_exit_41273__'
                        86      NOP                             
                        88      LOAD_CONST                      3: b'<COAddr>\x07\x00\x00\x1a6\x00\x00\x00\x00\x00\x00\x00\x00\x00\x00\x00\x00\x00\x00\x00'
                        90      CALL                            1
                        98      POP_TOP                         
                        100     RERAISE                         0
                        102     COPY                            3
                        104     POP_EXCEPT                      
                        106     RERAISE                         1
                        108     PUSH_NULL                       
                        110     LOAD_CONST                      6: '__pyarmor_exit_41273__'
                        112     LOAD_CONST                      3: b'<COAddr>\x07\x00\x00\x1a6\x00\x00\x00\x00\x00\x00\x00\x00\x00\x00\x00\x00\x00\x00\x00'
                        114     BUILD_TUPLE                     1
                        116     CALL_FUNCTION_EX                0
                        118     POP_TOP                         
                        120     RETURN_VALUE                    
                    [Exception Table]
                        28 to 60 -> 80 [0] 
                        80 to 102 -> 102 [1] lasti
                [Code]
                    File Name: <frozen multithon.tl.types.storage>
                    Object Name: from_reader
                    Qualified Name: FileGif.from_reader
                    Arg Count: 2
                    Pos Only Arg Count: 0
                    KW Only Arg Count: 0
                    Stack Size: 5
                    Flags: 0x20000003 (CO_OPTIMIZED | CO_NEWLOCALS | CO_PYARMOR_OBFUSCATED)
                    [Names]
                    [Locals+Names]
                        'cls'
                        'reader'
                        '__assert_armored__'
                    [Constants]
                        None
                        '__pyarmor_assert_41274__'
                        '__pyarmor_enter_41275__'
                        b'<COAddr>\x07\x00\x00\x1a"\x00\x00\x00\x00\x00\x00\x00\x00\x00\x00\x00\x00\x00\x00\x00'
                        '__pyarmor_exit_41276__'
                    [Disassembly]
                        0       NOP                             
                        2       NOP                             
                        4       PUSH_NULL                       
                        6       LOAD_CONST                      2: '__pyarmor_enter_41275__'
                        8       LOAD_CONST                      3: b'<COAddr>\x07\x00\x00\x1a"\x00\x00\x00\x00\x00\x00\x00\x00\x00\x00\x00\x00\x00\x00\x00'
                        10      BUILD_TUPLE                     1
                        12      CALL_FUNCTION_EX                0
                        14      POP_TOP                         
                        16      RESUME                          0
                        18      NOP                             
                        20      NOP                             
                        22      NOP                             
                        24      NOP                             
                        26      NOP                             
                        28      PUSH_NULL                       
                        30      LOAD_FAST                       0: cls
                        32      CALL                            0
                        40      NOP                             
                        42      NOP                             
                        44      NOP                             
                        46      JUMP_FORWARD                    20 (to 88)
                        48      CALL                            1
                        56      POP_TOP                         
                        58      RETURN_VALUE                    
                        60      PUSH_EXC_INFO                   
                        62      PUSH_NULL                       
                        64      LOAD_CONST                      4: '__pyarmor_exit_41276__'
                        66      NOP                             
                        68      LOAD_CONST                      3: b'<COAddr>\x07\x00\x00\x1a"\x00\x00\x00\x00\x00\x00\x00\x00\x00\x00\x00\x00\x00\x00\x00'
                        70      CALL                            1
                        78      POP_TOP                         
                        80      RERAISE                         0
                        82      COPY                            3
                        84      POP_EXCEPT                      
                        86      RERAISE                         1
                        88      PUSH_NULL                       
                        90      LOAD_CONST                      4: '__pyarmor_exit_41276__'
                        92      LOAD_CONST                      3: b'<COAddr>\x07\x00\x00\x1a"\x00\x00\x00\x00\x00\x00\x00\x00\x00\x00\x00\x00\x00\x00\x00'
                        94      BUILD_TUPLE                     1
                        96      CALL_FUNCTION_EX                0
                        98      POP_TOP                         
                        100     RETURN_VALUE                    
                    [Exception Table]
                        28 to 40 -> 60 [0] 
                        60 to 82 -> 82 [1] lasti
                '__pyarmor_exit_41267__'
                None
            [Disassembly]
                0       NOP                             
                2       LOAD_NAME                       0: __name__
                4       STORE_NAME                      1: __module__
                6       LOAD_CONST                      0: 'FileGif'
                8       STORE_NAME                      2: __qualname__
                10      NOP                             
                12      PUSH_NULL                       
                14      LOAD_CONST                      2: '__pyarmor_enter_41266__'
                16      LOAD_CONST                      3: b'<COAddr>\x05\x00\x00":\x00\x00\x00\x00\x00\x00\x00\x00\x00\x00\x00\x00\x00\x00\x00'
                18      BUILD_TUPLE                     1
                20      CALL_FUNCTION_EX                0
                22      POP_TOP                         
                24      RESUME                          0
                26      NOP                             
                28      NOP                             
                30      NOP                             
                32      NOP                             
                34      NOP                             
                36      LOAD_CONST                      4: 0xCAE1AADF
                38      STORE_NAME                      4: CONSTRUCTOR_ID
                40      LOAD_CONST                      5: 0xF3A1E6F3
                42      STORE_NAME                      5: SUBCLASS_OF_ID
                44      LOAD_CONST                      6: <CODE> to_dict
                46      MAKE_FUNCTION                   0
                48      STORE_NAME                      6: to_dict
                50      LOAD_CONST                      7: <CODE> _bytes
                52      MAKE_FUNCTION                   0
                54      STORE_NAME                      7: _bytes
                56      LOAD_NAME                       8: classmethod
                58      LOAD_CONST                      8: <CODE> from_reader
                60      MAKE_FUNCTION                   0
                62      CALL                            0
                70      STORE_NAME                      9: from_reader
                72      LOAD_CONST                      10: None
                74      NOP                             
                76      NOP                             
                78      NOP                             
                80      JUMP_FORWARD                    19 (to 120)
                88      POP_TOP                         
                90      RETURN_CONST                    10: None
                92      PUSH_EXC_INFO                   
                94      PUSH_NULL                       
                96      LOAD_CONST                      9: '__pyarmor_exit_41267__'
                98      NOP                             
                100     LOAD_CONST                      3: b'<COAddr>\x05\x00\x00":\x00\x00\x00\x00\x00\x00\x00\x00\x00\x00\x00\x00\x00\x00\x00'
                102     CALL                            1
                110     POP_TOP                         
                112     RERAISE                         0
                114     COPY                            3
                116     POP_EXCEPT                      
                118     RERAISE                         1
                120     PUSH_NULL                       
                122     LOAD_CONST                      9: '__pyarmor_exit_41267__'
                124     LOAD_CONST                      3: b'<COAddr>\x05\x00\x00":\x00\x00\x00\x00\x00\x00\x00\x00\x00\x00\x00\x00\x00\x00\x00'
                126     BUILD_TUPLE                     1
                128     CALL_FUNCTION_EX                0
                130     POP_TOP                         
                132     RETURN_VALUE                    
            [Exception Table]
                36 to 72 -> 92 [0] 
                92 to 114 -> 114 [1] lasti
        'FileGif'
        [Code]
            File Name: <frozen multithon.tl.types.storage>
            Object Name: FileJpeg
            Qualified Name: FileJpeg
            Arg Count: 0
            Pos Only Arg Count: 0
            KW Only Arg Count: 0
            Stack Size: 5
            Flags: 0x20000000 (CO_PYARMOR_OBFUSCATED)
            [Names]
                '__name__'
                '__module__'
                '__qualname__'
                '__assert_armored__'
                'CONSTRUCTOR_ID'
                'SUBCLASS_OF_ID'
                'to_dict'
                '_bytes'
                'classmethod'
                'from_reader'
            [Locals+Names]
            [Constants]
                'FileJpeg'
                '__pyarmor_assert_41277__'
                '__pyarmor_enter_41278__'
                b'<COAddr>\x05\x00\x00":\x00\x00\x00\x00\x00\x00\x00\x00\x00\x00\x00\x00\x00\x00\x00'
                8322574
                0xF3A1E6F3
                [Code]
                    File Name: <frozen multithon.tl.types.storage>
                    Object Name: to_dict
                    Qualified Name: FileJpeg.to_dict
                    Arg Count: 1
                    Pos Only Arg Count: 0
                    KW Only Arg Count: 0
                    Stack Size: 5
                    Flags: 0x20000003 (CO_OPTIMIZED | CO_NEWLOCALS | CO_PYARMOR_OBFUSCATED)
                    [Names]
                    [Locals+Names]
                        'self'
                        '__assert_armored__'
                    [Constants]
                        None
                        '__pyarmor_assert_41280__'
                        '__pyarmor_enter_41281__'
                        b'<COAddr>\x05\x00\x00\x1a\x1c\x00\x00\x00\x00\x00\x00\x00\x00\x00\x00\x00\x00\x00\x00\x00'
                        '_'
                        'FileJpeg'
                        '__pyarmor_exit_41282__'
                    [Disassembly]
                        0       NOP                             
                        2       NOP                             
                        4       PUSH_NULL                       
                        6       LOAD_CONST                      2: '__pyarmor_enter_41281__'
                        8       LOAD_CONST                      3: b'<COAddr>\x05\x00\x00\x1a\x1c\x00\x00\x00\x00\x00\x00\x00\x00\x00\x00\x00\x00\x00\x00\x00'
                        10      BUILD_TUPLE                     1
                        12      CALL_FUNCTION_EX                0
                        14      POP_TOP                         
                        16      RESUME                          0
                        18      NOP                             
                        20      NOP                             
                        22      NOP                             
                        24      NOP                             
                        26      NOP                             
                        28      LOAD_CONST                      4: '_'
                        30      LOAD_CONST                      5: 'FileJpeg'
                        32      BUILD_MAP                       1
                        34      NOP                             
                        36      NOP                             
                        38      NOP                             
                        40      JUMP_FORWARD                    20 (to 82)
                        42      CALL                            1
                        50      POP_TOP                         
                        52      RETURN_VALUE                    
                        54      PUSH_EXC_INFO                   
                        56      PUSH_NULL                       
                        58      LOAD_CONST                      6: '__pyarmor_exit_41282__'
                        60      NOP                             
                        62      LOAD_CONST                      3: b'<COAddr>\x05\x00\x00\x1a\x1c\x00\x00\x00\x00\x00\x00\x00\x00\x00\x00\x00\x00\x00\x00\x00'
                        64      CALL                            1
                        72      POP_TOP                         
                        74      RERAISE                         0
                        76      COPY                            3
                        78      POP_EXCEPT                      
                        80      RERAISE                         1
                        82      PUSH_NULL                       
                        84      LOAD_CONST                      6: '__pyarmor_exit_41282__'
                        86      LOAD_CONST                      3: b'<COAddr>\x05\x00\x00\x1a\x1c\x00\x00\x00\x00\x00\x00\x00\x00\x00\x00\x00\x00\x00\x00\x00'
                        88      BUILD_TUPLE                     1
                        90      CALL_FUNCTION_EX                0
                        92      POP_TOP                         
                        94      RETURN_VALUE                    
                    [Exception Table]
                        28 to 34 -> 54 [0] 
                        54 to 76 -> 76 [1] lasti
                [Code]
                    File Name: <frozen multithon.tl.types.storage>
                    Object Name: _bytes
                    Qualified Name: FileJpeg._bytes
                    Arg Count: 1
                    Pos Only Arg Count: 0
                    KW Only Arg Count: 0
                    Stack Size: 5
                    Flags: 0x20000003 (CO_OPTIMIZED | CO_NEWLOCALS | CO_PYARMOR_OBFUSCATED)
                    [Names]
                        'join'
                    [Locals+Names]
                        'self'
                        '__assert_armored__'
                    [Constants]
                        None
                        '__pyarmor_assert_41283__'
                        '__pyarmor_enter_41284__'
                        b'<COAddr>\x07\x00\x00\x1a6\x00\x00\x00\x00\x00\x00\x00\x00\x00\x00\x00\x00\x00\x00\x00'
                        b''
                        (
                            b'\x0e\xfe~\x00'
                        )
                        '__pyarmor_exit_41285__'
                    [Disassembly]
                        0       NOP                             
                        2       NOP                             
                        4       PUSH_NULL                       
                        6       LOAD_CONST                      2: '__pyarmor_enter_41284__'
                        8       LOAD_CONST                      3: b'<COAddr>\x07\x00\x00\x1a6\x00\x00\x00\x00\x00\x00\x00\x00\x00\x00\x00\x00\x00\x00\x00'
                        10      BUILD_TUPLE                     1
                        12      CALL_FUNCTION_EX                0
                        14      POP_TOP                         
                        16      RESUME                          0
                        18      NOP                             
                        20      NOP                             
                        22      NOP                             
                        24      NOP                             
                        26      NOP                             
                        28      LOAD_CONST                      4: b''
                        30      LOAD_ATTR                       1: join
                        50      LOAD_CONST                      5: (b'\x0e\xfe~\x00',)
                        52      CALL                            1
                        60      NOP                             
                        62      NOP                             
                        64      NOP                             
                        66      JUMP_FORWARD                    20 (to 108)
                        68      CALL                            1
                        76      POP_TOP                         
                        78      RETURN_VALUE                    
                        80      PUSH_EXC_INFO                   
                        82      PUSH_NULL                       
                        84      LOAD_CONST                      6: '__pyarmor_exit_41285__'
                        86      NOP                             
                        88      LOAD_CONST                      3: b'<COAddr>\x07\x00\x00\x1a6\x00\x00\x00\x00\x00\x00\x00\x00\x00\x00\x00\x00\x00\x00\x00'
                        90      CALL                            1
                        98      POP_TOP                         
                        100     RERAISE                         0
                        102     COPY                            3
                        104     POP_EXCEPT                      
                        106     RERAISE                         1
                        108     PUSH_NULL                       
                        110     LOAD_CONST                      6: '__pyarmor_exit_41285__'
                        112     LOAD_CONST                      3: b'<COAddr>\x07\x00\x00\x1a6\x00\x00\x00\x00\x00\x00\x00\x00\x00\x00\x00\x00\x00\x00\x00'
                        114     BUILD_TUPLE                     1
                        116     CALL_FUNCTION_EX                0
                        118     POP_TOP                         
                        120     RETURN_VALUE                    
                    [Exception Table]
                        28 to 60 -> 80 [0] 
                        80 to 102 -> 102 [1] lasti
                [Code]
                    File Name: <frozen multithon.tl.types.storage>
                    Object Name: from_reader
                    Qualified Name: FileJpeg.from_reader
                    Arg Count: 2
                    Pos Only Arg Count: 0
                    KW Only Arg Count: 0
                    Stack Size: 5
                    Flags: 0x20000003 (CO_OPTIMIZED | CO_NEWLOCALS | CO_PYARMOR_OBFUSCATED)
                    [Names]
                    [Locals+Names]
                        'cls'
                        'reader'
                        '__assert_armored__'
                    [Constants]
                        None
                        '__pyarmor_assert_41286__'
                        '__pyarmor_enter_41287__'
                        b'<COAddr>\x05\x00\x00\x1a"\x00\x00\x00\x00\x00\x00\x00\x00\x00\x00\x00\x00\x00\x00\x00'
                        '__pyarmor_exit_41288__'
                    [Disassembly]
                        0       NOP                             
                        2       NOP                             
                        4       PUSH_NULL                       
                        6       LOAD_CONST                      2: '__pyarmor_enter_41287__'
                        8       LOAD_CONST                      3: b'<COAddr>\x05\x00\x00\x1a"\x00\x00\x00\x00\x00\x00\x00\x00\x00\x00\x00\x00\x00\x00\x00'
                        10      BUILD_TUPLE                     1
                        12      CALL_FUNCTION_EX                0
                        14      POP_TOP                         
                        16      RESUME                          0
                        18      NOP                             
                        20      NOP                             
                        22      NOP                             
                        24      NOP                             
                        26      NOP                             
                        28      PUSH_NULL                       
                        30      LOAD_FAST                       0: cls
                        32      CALL                            0
                        40      NOP                             
                        42      NOP                             
                        44      NOP                             
                        46      JUMP_FORWARD                    20 (to 88)
                        48      CALL                            1
                        56      POP_TOP                         
                        58      RETURN_VALUE                    
                        60      PUSH_EXC_INFO                   
                        62      PUSH_NULL                       
                        64      LOAD_CONST                      4: '__pyarmor_exit_41288__'
                        66      NOP                             
                        68      LOAD_CONST                      3: b'<COAddr>\x05\x00\x00\x1a"\x00\x00\x00\x00\x00\x00\x00\x00\x00\x00\x00\x00\x00\x00\x00'
                        70      CALL                            1
                        78      POP_TOP                         
                        80      RERAISE                         0
                        82      COPY                            3
                        84      POP_EXCEPT                      
                        86      RERAISE                         1
                        88      PUSH_NULL                       
                        90      LOAD_CONST                      4: '__pyarmor_exit_41288__'
                        92      LOAD_CONST                      3: b'<COAddr>\x05\x00\x00\x1a"\x00\x00\x00\x00\x00\x00\x00\x00\x00\x00\x00\x00\x00\x00\x00'
                        94      BUILD_TUPLE                     1
                        96      CALL_FUNCTION_EX                0
                        98      POP_TOP                         
                        100     RETURN_VALUE                    
                    [Exception Table]
                        28 to 40 -> 60 [0] 
                        60 to 82 -> 82 [1] lasti
                '__pyarmor_exit_41279__'
                None
            [Disassembly]
                0       NOP                             
                2       LOAD_NAME                       0: __name__
                4       STORE_NAME                      1: __module__
                6       LOAD_CONST                      0: 'FileJpeg'
                8       STORE_NAME                      2: __qualname__
                10      NOP                             
                12      PUSH_NULL                       
                14      LOAD_CONST                      2: '__pyarmor_enter_41278__'
                16      LOAD_CONST                      3: b'<COAddr>\x05\x00\x00":\x00\x00\x00\x00\x00\x00\x00\x00\x00\x00\x00\x00\x00\x00\x00'
                18      BUILD_TUPLE                     1
                20      CALL_FUNCTION_EX                0
                22      POP_TOP                         
                24      RESUME                          0
                26      NOP                             
                28      NOP                             
                30      NOP                             
                32      NOP                             
                34      NOP                             
                36      LOAD_CONST                      4: 8322574
                38      STORE_NAME                      4: CONSTRUCTOR_ID
                40      LOAD_CONST                      5: 0xF3A1E6F3
                42      STORE_NAME                      5: SUBCLASS_OF_ID
                44      LOAD_CONST                      6: <CODE> to_dict
                46      MAKE_FUNCTION                   0
                48      STORE_NAME                      6: to_dict
                50      LOAD_CONST                      7: <CODE> _bytes
                52      MAKE_FUNCTION                   0
                54      STORE_NAME                      7: _bytes
                56      LOAD_NAME                       8: classmethod
                58      LOAD_CONST                      8: <CODE> from_reader
                60      MAKE_FUNCTION                   0
                62      CALL                            0
                70      STORE_NAME                      9: from_reader
                72      LOAD_CONST                      10: None
                74      NOP                             
                76      NOP                             
                78      NOP                             
                80      JUMP_FORWARD                    19 (to 120)
                88      POP_TOP                         
                90      RETURN_CONST                    10: None
                92      PUSH_EXC_INFO                   
                94      PUSH_NULL                       
                96      LOAD_CONST                      9: '__pyarmor_exit_41279__'
                98      NOP                             
                100     LOAD_CONST                      3: b'<COAddr>\x05\x00\x00":\x00\x00\x00\x00\x00\x00\x00\x00\x00\x00\x00\x00\x00\x00\x00'
                102     CALL                            1
                110     POP_TOP                         
                112     RERAISE                         0
                114     COPY                            3
                116     POP_EXCEPT                      
                118     RERAISE                         1
                120     PUSH_NULL                       
                122     LOAD_CONST                      9: '__pyarmor_exit_41279__'
                124     LOAD_CONST                      3: b'<COAddr>\x05\x00\x00":\x00\x00\x00\x00\x00\x00\x00\x00\x00\x00\x00\x00\x00\x00\x00'
                126     BUILD_TUPLE                     1
                128     CALL_FUNCTION_EX                0
                130     POP_TOP                         
                132     RETURN_VALUE                    
            [Exception Table]
                36 to 72 -> 92 [0] 
                92 to 114 -> 114 [1] lasti
        'FileJpeg'
        [Code]
            File Name: <frozen multithon.tl.types.storage>
            Object Name: FileMov
            Qualified Name: FileMov
            Arg Count: 0
            Pos Only Arg Count: 0
            KW Only Arg Count: 0
            Stack Size: 5
            Flags: 0x20000000 (CO_PYARMOR_OBFUSCATED)
            [Names]
                '__name__'
                '__module__'
                '__qualname__'
                '__assert_armored__'
                'CONSTRUCTOR_ID'
                'SUBCLASS_OF_ID'
                'to_dict'
                '_bytes'
                'classmethod'
                'from_reader'
            [Locals+Names]
            [Constants]
                'FileMov'
                '__pyarmor_assert_41289__'
                '__pyarmor_enter_41290__'
                b'<COAddr>\x07\x00\x00":\x00\x00\x00\x00\x00\x00\x00\x00\x00\x00\x00\x00\x00\x00\x00'
                1258941372
                0xF3A1E6F3
                [Code]
                    File Name: <frozen multithon.tl.types.storage>
                    Object Name: to_dict
                    Qualified Name: FileMov.to_dict
                    Arg Count: 1
                    Pos Only Arg Count: 0
                    KW Only Arg Count: 0
                    Stack Size: 5
                    Flags: 0x20000003 (CO_OPTIMIZED | CO_NEWLOCALS | CO_PYARMOR_OBFUSCATED)
                    [Names]
                    [Locals+Names]
                        'self'
                        '__assert_armored__'
                    [Constants]
                        None
                        '__pyarmor_assert_41292__'
                        '__pyarmor_enter_41293__'
                        b'<COAddr>\x05\x00\x00\x1a\x1c\x00\x00\x00\x00\x00\x00\x00\x00\x00\x00\x00\x00\x00\x00\x00'
                        '_'
                        'FileMov'
                        '__pyarmor_exit_41294__'
                    [Disassembly]
                        0       NOP                             
                        2       NOP                             
                        4       PUSH_NULL                       
                        6       LOAD_CONST                      2: '__pyarmor_enter_41293__'
                        8       LOAD_CONST                      3: b'<COAddr>\x05\x00\x00\x1a\x1c\x00\x00\x00\x00\x00\x00\x00\x00\x00\x00\x00\x00\x00\x00\x00'
                        10      BUILD_TUPLE                     1
                        12      CALL_FUNCTION_EX                0
                        14      POP_TOP                         
                        16      RESUME                          0
                        18      NOP                             
                        20      NOP                             
                        22      NOP                             
                        24      NOP                             
                        26      NOP                             
                        28      LOAD_CONST                      4: '_'
                        30      LOAD_CONST                      5: 'FileMov'
                        32      BUILD_MAP                       1
                        34      NOP                             
                        36      NOP                             
                        38      NOP                             
                        40      JUMP_FORWARD                    20 (to 82)
                        42      CALL                            1
                        50      POP_TOP                         
                        52      RETURN_VALUE                    
                        54      PUSH_EXC_INFO                   
                        56      PUSH_NULL                       
                        58      LOAD_CONST                      6: '__pyarmor_exit_41294__'
                        60      NOP                             
                        62      LOAD_CONST                      3: b'<COAddr>\x05\x00\x00\x1a\x1c\x00\x00\x00\x00\x00\x00\x00\x00\x00\x00\x00\x00\x00\x00\x00'
                        64      CALL                            1
                        72      POP_TOP                         
                        74      RERAISE                         0
                        76      COPY                            3
                        78      POP_EXCEPT                      
                        80      RERAISE                         1
                        82      PUSH_NULL                       
                        84      LOAD_CONST                      6: '__pyarmor_exit_41294__'
                        86      LOAD_CONST                      3: b'<COAddr>\x05\x00\x00\x1a\x1c\x00\x00\x00\x00\x00\x00\x00\x00\x00\x00\x00\x00\x00\x00\x00'
                        88      BUILD_TUPLE                     1
                        90      CALL_FUNCTION_EX                0
                        92      POP_TOP                         
                        94      RETURN_VALUE                    
                    [Exception Table]
                        28 to 34 -> 54 [0] 
                        54 to 76 -> 76 [1] lasti
                [Code]
                    File Name: <frozen multithon.tl.types.storage>
                    Object Name: _bytes
                    Qualified Name: FileMov._bytes
                    Arg Count: 1
                    Pos Only Arg Count: 0
                    KW Only Arg Count: 0
                    Stack Size: 5
                    Flags: 0x20000003 (CO_OPTIMIZED | CO_NEWLOCALS | CO_PYARMOR_OBFUSCATED)
                    [Names]
                        'join'
                    [Locals+Names]
                        'self'
                        '__assert_armored__'
                    [Constants]
                        None
                        '__pyarmor_assert_41295__'
                        '__pyarmor_enter_41296__'
                        b'<COAddr>\x07\x00\x00\x1a6\x00\x00\x00\x00\x00\x00\x00\x00\x00\x00\x00\x00\x00\x00\x00'
                        b''
                        (
                            b'\xbc\xeb\tK'
                        )
                        '__pyarmor_exit_41297__'
                    [Disassembly]
                        0       NOP                             
                        2       NOP                             
                        4       PUSH_NULL                       
                        6       LOAD_CONST                      2: '__pyarmor_enter_41296__'
                        8       LOAD_CONST                      3: b'<COAddr>\x07\x00\x00\x1a6\x00\x00\x00\x00\x00\x00\x00\x00\x00\x00\x00\x00\x00\x00\x00'
                        10      BUILD_TUPLE                     1
                        12      CALL_FUNCTION_EX                0
                        14      POP_TOP                         
                        16      RESUME                          0
                        18      NOP                             
                        20      NOP                             
                        22      NOP                             
                        24      NOP                             
                        26      NOP                             
                        28      LOAD_CONST                      4: b''
                        30      LOAD_ATTR                       1: join
                        50      LOAD_CONST                      5: (b'\xbc\xeb\tK',)
                        52      CALL                            1
                        60      NOP                             
                        62      NOP                             
                        64      NOP                             
                        66      JUMP_FORWARD                    20 (to 108)
                        68      CALL                            1
                        76      POP_TOP                         
                        78      RETURN_VALUE                    
                        80      PUSH_EXC_INFO                   
                        82      PUSH_NULL                       
                        84      LOAD_CONST                      6: '__pyarmor_exit_41297__'
                        86      NOP                             
                        88      LOAD_CONST                      3: b'<COAddr>\x07\x00\x00\x1a6\x00\x00\x00\x00\x00\x00\x00\x00\x00\x00\x00\x00\x00\x00\x00'
                        90      CALL                            1
                        98      POP_TOP                         
                        100     RERAISE                         0
                        102     COPY                            3
                        104     POP_EXCEPT                      
                        106     RERAISE                         1
                        108     PUSH_NULL                       
                        110     LOAD_CONST                      6: '__pyarmor_exit_41297__'
                        112     LOAD_CONST                      3: b'<COAddr>\x07\x00\x00\x1a6\x00\x00\x00\x00\x00\x00\x00\x00\x00\x00\x00\x00\x00\x00\x00'
                        114     BUILD_TUPLE                     1
                        116     CALL_FUNCTION_EX                0
                        118     POP_TOP                         
                        120     RETURN_VALUE                    
                    [Exception Table]
                        28 to 60 -> 80 [0] 
                        80 to 102 -> 102 [1] lasti
                [Code]
                    File Name: <frozen multithon.tl.types.storage>
                    Object Name: from_reader
                    Qualified Name: FileMov.from_reader
                    Arg Count: 2
                    Pos Only Arg Count: 0
                    KW Only Arg Count: 0
                    Stack Size: 5
                    Flags: 0x20000003 (CO_OPTIMIZED | CO_NEWLOCALS | CO_PYARMOR_OBFUSCATED)
                    [Names]
                    [Locals+Names]
                        'cls'
                        'reader'
                        '__assert_armored__'
                    [Constants]
                        None
                        '__pyarmor_assert_41298__'
                        '__pyarmor_enter_41299__'
                        b'<COAddr>\x05\x00\x00\x1a"\x00\x00\x00\x00\x00\x00\x00\x00\x00\x00\x00\x00\x00\x00\x00'
                        '__pyarmor_exit_41300__'
                    [Disassembly]
                        0       NOP                             
                        2       NOP                             
                        4       PUSH_NULL                       
                        6       LOAD_CONST                      2: '__pyarmor_enter_41299__'
                        8       LOAD_CONST                      3: b'<COAddr>\x05\x00\x00\x1a"\x00\x00\x00\x00\x00\x00\x00\x00\x00\x00\x00\x00\x00\x00\x00'
                        10      BUILD_TUPLE                     1
                        12      CALL_FUNCTION_EX                0
                        14      POP_TOP                         
                        16      RESUME                          0
                        18      NOP                             
                        20      NOP                             
                        22      NOP                             
                        24      NOP                             
                        26      NOP                             
                        28      PUSH_NULL                       
                        30      LOAD_FAST                       0: cls
                        32      CALL                            0
                        40      NOP                             
                        42      NOP                             
                        44      NOP                             
                        46      JUMP_FORWARD                    20 (to 88)
                        48      CALL                            1
                        56      POP_TOP                         
                        58      RETURN_VALUE                    
                        60      PUSH_EXC_INFO                   
                        62      PUSH_NULL                       
                        64      LOAD_CONST                      4: '__pyarmor_exit_41300__'
                        66      NOP                             
                        68      LOAD_CONST                      3: b'<COAddr>\x05\x00\x00\x1a"\x00\x00\x00\x00\x00\x00\x00\x00\x00\x00\x00\x00\x00\x00\x00'
                        70      CALL                            1
                        78      POP_TOP                         
                        80      RERAISE                         0
                        82      COPY                            3
                        84      POP_EXCEPT                      
                        86      RERAISE                         1
                        88      PUSH_NULL                       
                        90      LOAD_CONST                      4: '__pyarmor_exit_41300__'
                        92      LOAD_CONST                      3: b'<COAddr>\x05\x00\x00\x1a"\x00\x00\x00\x00\x00\x00\x00\x00\x00\x00\x00\x00\x00\x00\x00'
                        94      BUILD_TUPLE                     1
                        96      CALL_FUNCTION_EX                0
                        98      POP_TOP                         
                        100     RETURN_VALUE                    
                    [Exception Table]
                        28 to 40 -> 60 [0] 
                        60 to 82 -> 82 [1] lasti
                '__pyarmor_exit_41291__'
                None
            [Disassembly]
                0       NOP                             
                2       LOAD_NAME                       0: __name__
                4       STORE_NAME                      1: __module__
                6       LOAD_CONST                      0: 'FileMov'
                8       STORE_NAME                      2: __qualname__
                10      NOP                             
                12      PUSH_NULL                       
                14      LOAD_CONST                      2: '__pyarmor_enter_41290__'
                16      LOAD_CONST                      3: b'<COAddr>\x07\x00\x00":\x00\x00\x00\x00\x00\x00\x00\x00\x00\x00\x00\x00\x00\x00\x00'
                18      BUILD_TUPLE                     1
                20      CALL_FUNCTION_EX                0
                22      POP_TOP                         
                24      RESUME                          0
                26      NOP                             
                28      NOP                             
                30      NOP                             
                32      NOP                             
                34      NOP                             
                36      LOAD_CONST                      4: 1258941372
                38      STORE_NAME                      4: CONSTRUCTOR_ID
                40      LOAD_CONST                      5: 0xF3A1E6F3
                42      STORE_NAME                      5: SUBCLASS_OF_ID
                44      LOAD_CONST                      6: <CODE> to_dict
                46      MAKE_FUNCTION                   0
                48      STORE_NAME                      6: to_dict
                50      LOAD_CONST                      7: <CODE> _bytes
                52      MAKE_FUNCTION                   0
                54      STORE_NAME                      7: _bytes
                56      LOAD_NAME                       8: classmethod
                58      LOAD_CONST                      8: <CODE> from_reader
                60      MAKE_FUNCTION                   0
                62      CALL                            0
                70      STORE_NAME                      9: from_reader
                72      LOAD_CONST                      10: None
                74      NOP                             
                76      NOP                             
                78      NOP                             
                80      JUMP_FORWARD                    19 (to 120)
                88      POP_TOP                         
                90      RETURN_CONST                    10: None
                92      PUSH_EXC_INFO                   
                94      PUSH_NULL                       
                96      LOAD_CONST                      9: '__pyarmor_exit_41291__'
                98      NOP                             
                100     LOAD_CONST                      3: b'<COAddr>\x07\x00\x00":\x00\x00\x00\x00\x00\x00\x00\x00\x00\x00\x00\x00\x00\x00\x00'
                102     CALL                            1
                110     POP_TOP                         
                112     RERAISE                         0
                114     COPY                            3
                116     POP_EXCEPT                      
                118     RERAISE                         1
                120     PUSH_NULL                       
                122     LOAD_CONST                      9: '__pyarmor_exit_41291__'
                124     LOAD_CONST                      3: b'<COAddr>\x07\x00\x00":\x00\x00\x00\x00\x00\x00\x00\x00\x00\x00\x00\x00\x00\x00\x00'
                126     BUILD_TUPLE                     1
                128     CALL_FUNCTION_EX                0
                130     POP_TOP                         
                132     RETURN_VALUE                    
            [Exception Table]
                36 to 72 -> 92 [0] 
                92 to 114 -> 114 [1] lasti
        'FileMov'
        [Code]
            File Name: <frozen multithon.tl.types.storage>
            Object Name: FileMp3
            Qualified Name: FileMp3
            Arg Count: 0
            Pos Only Arg Count: 0
            KW Only Arg Count: 0
            Stack Size: 5
            Flags: 0x20000000 (CO_PYARMOR_OBFUSCATED)
            [Names]
                '__name__'
                '__module__'
                '__qualname__'
                '__assert_armored__'
                'CONSTRUCTOR_ID'
                'SUBCLASS_OF_ID'
                'to_dict'
                '_bytes'
                'classmethod'
                'from_reader'
            [Locals+Names]
            [Constants]
                'FileMp3'
                '__pyarmor_assert_41301__'
                '__pyarmor_enter_41302__'
                b'<COAddr>\x07\x00\x00":\x00\x00\x00\x00\x00\x00\x00\x00\x00\x00\x00\x00\x00\x00\x00'
                1384777335
                0xF3A1E6F3
                [Code]
                    File Name: <frozen multithon.tl.types.storage>
                    Object Name: to_dict
                    Qualified Name: FileMp3.to_dict
                    Arg Count: 1
                    Pos Only Arg Count: 0
                    KW Only Arg Count: 0
                    Stack Size: 5
                    Flags: 0x20000003 (CO_OPTIMIZED | CO_NEWLOCALS | CO_PYARMOR_OBFUSCATED)
                    [Names]
                    [Locals+Names]
                        'self'
                        '__assert_armored__'
                    [Constants]
                        None
                        '__pyarmor_assert_41304__'
                        '__pyarmor_enter_41305__'
                        b'<COAddr>\x05\x00\x00\x1a\x1c\x00\x00\x00\x00\x00\x00\x00\x00\x00\x00\x00\x00\x00\x00\x00'
                        '_'
                        'FileMp3'
                        '__pyarmor_exit_41306__'
                    [Disassembly]
                        0       NOP                             
                        2       NOP                             
                        4       PUSH_NULL                       
                        6       LOAD_CONST                      2: '__pyarmor_enter_41305__'
                        8       LOAD_CONST                      3: b'<COAddr>\x05\x00\x00\x1a\x1c\x00\x00\x00\x00\x00\x00\x00\x00\x00\x00\x00\x00\x00\x00\x00'
                        10      BUILD_TUPLE                     1
                        12      CALL_FUNCTION_EX                0
                        14      POP_TOP                         
                        16      RESUME                          0
                        18      NOP                             
                        20      NOP                             
                        22      NOP                             
                        24      NOP                             
                        26      NOP                             
                        28      LOAD_CONST                      4: '_'
                        30      LOAD_CONST                      5: 'FileMp3'
                        32      BUILD_MAP                       1
                        34      NOP                             
                        36      NOP                             
                        38      NOP                             
                        40      JUMP_FORWARD                    20 (to 82)
                        42      CALL                            1
                        50      POP_TOP                         
                        52      RETURN_VALUE                    
                        54      PUSH_EXC_INFO                   
                        56      PUSH_NULL                       
                        58      LOAD_CONST                      6: '__pyarmor_exit_41306__'
                        60      NOP                             
                        62      LOAD_CONST                      3: b'<COAddr>\x05\x00\x00\x1a\x1c\x00\x00\x00\x00\x00\x00\x00\x00\x00\x00\x00\x00\x00\x00\x00'
                        64      CALL                            1
                        72      POP_TOP                         
                        74      RERAISE                         0
                        76      COPY                            3
                        78      POP_EXCEPT                      
                        80      RERAISE                         1
                        82      PUSH_NULL                       
                        84      LOAD_CONST                      6: '__pyarmor_exit_41306__'
                        86      LOAD_CONST                      3: b'<COAddr>\x05\x00\x00\x1a\x1c\x00\x00\x00\x00\x00\x00\x00\x00\x00\x00\x00\x00\x00\x00\x00'
                        88      BUILD_TUPLE                     1
                        90      CALL_FUNCTION_EX                0
                        92      POP_TOP                         
                        94      RETURN_VALUE                    
                    [Exception Table]
                        28 to 34 -> 54 [0] 
                        54 to 76 -> 76 [1] lasti
                [Code]
                    File Name: <frozen multithon.tl.types.storage>
                    Object Name: _bytes
                    Qualified Name: FileMp3._bytes
                    Arg Count: 1
                    Pos Only Arg Count: 0
                    KW Only Arg Count: 0
                    Stack Size: 5
                    Flags: 0x20000003 (CO_OPTIMIZED | CO_NEWLOCALS | CO_PYARMOR_OBFUSCATED)
                    [Names]
                        'join'
                    [Locals+Names]
                        'self'
                        '__assert_armored__'
                    [Constants]
                        None
                        '__pyarmor_assert_41307__'
                        '__pyarmor_enter_41308__'
                        b'<COAddr>\x05\x00\x00\x1a6\x00\x00\x00\x00\x00\x00\x00\x00\x00\x00\x00\x00\x00\x00\x00'
                        b''
                        (
                            b'w\x06\x8aR'
                        )
                        '__pyarmor_exit_41309__'
                    [Disassembly]
                        0       NOP                             
                        2       NOP                             
                        4       PUSH_NULL                       
                        6       LOAD_CONST                      2: '__pyarmor_enter_41308__'
                        8       LOAD_CONST                      3: b'<COAddr>\x05\x00\x00\x1a6\x00\x00\x00\x00\x00\x00\x00\x00\x00\x00\x00\x00\x00\x00\x00'
                        10      BUILD_TUPLE                     1
                        12      CALL_FUNCTION_EX                0
                        14      POP_TOP                         
                        16      RESUME                          0
                        18      NOP                             
                        20      NOP                             
                        22      NOP                             
                        24      NOP                             
                        26      NOP                             
                        28      LOAD_CONST                      4: b''
                        30      LOAD_ATTR                       1: join
                        50      LOAD_CONST                      5: (b'w\x06\x8aR',)
                        52      CALL                            1
                        60      NOP                             
                        62      NOP                             
                        64      NOP                             
                        66      JUMP_FORWARD                    20 (to 108)
                        68      CALL                            1
                        76      POP_TOP                         
                        78      RETURN_VALUE                    
                        80      PUSH_EXC_INFO                   
                        82      PUSH_NULL                       
                        84      LOAD_CONST                      6: '__pyarmor_exit_41309__'
                        86      NOP                             
                        88      LOAD_CONST                      3: b'<COAddr>\x05\x00\x00\x1a6\x00\x00\x00\x00\x00\x00\x00\x00\x00\x00\x00\x00\x00\x00\x00'
                        90      CALL                            1
                        98      POP_TOP                         
                        100     RERAISE                         0
                        102     COPY                            3
                        104     POP_EXCEPT                      
                        106     RERAISE                         1
                        108     PUSH_NULL                       
                        110     LOAD_CONST                      6: '__pyarmor_exit_41309__'
                        112     LOAD_CONST                      3: b'<COAddr>\x05\x00\x00\x1a6\x00\x00\x00\x00\x00\x00\x00\x00\x00\x00\x00\x00\x00\x00\x00'
                        114     BUILD_TUPLE                     1
                        116     CALL_FUNCTION_EX                0
                        118     POP_TOP                         
                        120     RETURN_VALUE                    
                    [Exception Table]
                        28 to 60 -> 80 [0] 
                        80 to 102 -> 102 [1] lasti
                [Code]
                    File Name: <frozen multithon.tl.types.storage>
                    Object Name: from_reader
                    Qualified Name: FileMp3.from_reader
                    Arg Count: 2
                    Pos Only Arg Count: 0
                    KW Only Arg Count: 0
                    Stack Size: 5
                    Flags: 0x20000003 (CO_OPTIMIZED | CO_NEWLOCALS | CO_PYARMOR_OBFUSCATED)
                    [Names]
                    [Locals+Names]
                        'cls'
                        'reader'
                        '__assert_armored__'
                    [Constants]
                        None
                        '__pyarmor_assert_41310__'
                        '__pyarmor_enter_41311__'
                        b'<COAddr>\x07\x00\x00\x1a"\x00\x00\x00\x00\x00\x00\x00\x00\x00\x00\x00\x00\x00\x00\x00'
                        '__pyarmor_exit_41312__'
                    [Disassembly]
                        0       NOP                             
                        2       NOP                             
                        4       PUSH_NULL                       
                        6       LOAD_CONST                      2: '__pyarmor_enter_41311__'
                        8       LOAD_CONST                      3: b'<COAddr>\x07\x00\x00\x1a"\x00\x00\x00\x00\x00\x00\x00\x00\x00\x00\x00\x00\x00\x00\x00'
                        10      BUILD_TUPLE                     1
                        12      CALL_FUNCTION_EX                0
                        14      POP_TOP                         
                        16      RESUME                          0
                        18      NOP                             
                        20      NOP                             
                        22      NOP                             
                        24      NOP                             
                        26      NOP                             
                        28      PUSH_NULL                       
                        30      LOAD_FAST                       0: cls
                        32      CALL                            0
                        40      NOP                             
                        42      NOP                             
                        44      NOP                             
                        46      JUMP_FORWARD                    20 (to 88)
                        48      CALL                            1
                        56      POP_TOP                         
                        58      RETURN_VALUE                    
                        60      PUSH_EXC_INFO                   
                        62      PUSH_NULL                       
                        64      LOAD_CONST                      4: '__pyarmor_exit_41312__'
                        66      NOP                             
                        68      LOAD_CONST                      3: b'<COAddr>\x07\x00\x00\x1a"\x00\x00\x00\x00\x00\x00\x00\x00\x00\x00\x00\x00\x00\x00\x00'
                        70      CALL                            1
                        78      POP_TOP                         
                        80      RERAISE                         0
                        82      COPY                            3
                        84      POP_EXCEPT                      
                        86      RERAISE                         1
                        88      PUSH_NULL                       
                        90      LOAD_CONST                      4: '__pyarmor_exit_41312__'
                        92      LOAD_CONST                      3: b'<COAddr>\x07\x00\x00\x1a"\x00\x00\x00\x00\x00\x00\x00\x00\x00\x00\x00\x00\x00\x00\x00'
                        94      BUILD_TUPLE                     1
                        96      CALL_FUNCTION_EX                0
                        98      POP_TOP                         
                        100     RETURN_VALUE                    
                    [Exception Table]
                        28 to 40 -> 60 [0] 
                        60 to 82 -> 82 [1] lasti
                '__pyarmor_exit_41303__'
                None
            [Disassembly]
                0       NOP                             
                2       LOAD_NAME                       0: __name__
                4       STORE_NAME                      1: __module__
                6       LOAD_CONST                      0: 'FileMp3'
                8       STORE_NAME                      2: __qualname__
                10      NOP                             
                12      PUSH_NULL                       
                14      LOAD_CONST                      2: '__pyarmor_enter_41302__'
                16      LOAD_CONST                      3: b'<COAddr>\x07\x00\x00":\x00\x00\x00\x00\x00\x00\x00\x00\x00\x00\x00\x00\x00\x00\x00'
                18      BUILD_TUPLE                     1
                20      CALL_FUNCTION_EX                0
                22      POP_TOP                         
                24      RESUME                          0
                26      NOP                             
                28      NOP                             
                30      NOP                             
                32      NOP                             
                34      NOP                             
                36      LOAD_CONST                      4: 1384777335
                38      STORE_NAME                      4: CONSTRUCTOR_ID
                40      LOAD_CONST                      5: 0xF3A1E6F3
                42      STORE_NAME                      5: SUBCLASS_OF_ID
                44      LOAD_CONST                      6: <CODE> to_dict
                46      MAKE_FUNCTION                   0
                48      STORE_NAME                      6: to_dict
                50      LOAD_CONST                      7: <CODE> _bytes
                52      MAKE_FUNCTION                   0
                54      STORE_NAME                      7: _bytes
                56      LOAD_NAME                       8: classmethod
                58      LOAD_CONST                      8: <CODE> from_reader
                60      MAKE_FUNCTION                   0
                62      CALL                            0
                70      STORE_NAME                      9: from_reader
                72      LOAD_CONST                      10: None
                74      NOP                             
                76      NOP                             
                78      NOP                             
                80      JUMP_FORWARD                    19 (to 120)
                88      POP_TOP                         
                90      RETURN_CONST                    10: None
                92      PUSH_EXC_INFO                   
                94      PUSH_NULL                       
                96      LOAD_CONST                      9: '__pyarmor_exit_41303__'
                98      NOP                             
                100     LOAD_CONST                      3: b'<COAddr>\x07\x00\x00":\x00\x00\x00\x00\x00\x00\x00\x00\x00\x00\x00\x00\x00\x00\x00'
                102     CALL                            1
                110     POP_TOP                         
                112     RERAISE                         0
                114     COPY                            3
                116     POP_EXCEPT                      
                118     RERAISE                         1
                120     PUSH_NULL                       
                122     LOAD_CONST                      9: '__pyarmor_exit_41303__'
                124     LOAD_CONST                      3: b'<COAddr>\x07\x00\x00":\x00\x00\x00\x00\x00\x00\x00\x00\x00\x00\x00\x00\x00\x00\x00'
                126     BUILD_TUPLE                     1
                128     CALL_FUNCTION_EX                0
                130     POP_TOP                         
                132     RETURN_VALUE                    
            [Exception Table]
                36 to 72 -> 92 [0] 
                92 to 114 -> 114 [1] lasti
        'FileMp3'
        [Code]
            File Name: <frozen multithon.tl.types.storage>
            Object Name: FileMp4
            Qualified Name: FileMp4
            Arg Count: 0
            Pos Only Arg Count: 0
            KW Only Arg Count: 0
            Stack Size: 5
            Flags: 0x20000000 (CO_PYARMOR_OBFUSCATED)
            [Names]
                '__name__'
                '__module__'
                '__qualname__'
                '__assert_armored__'
                'CONSTRUCTOR_ID'
                'SUBCLASS_OF_ID'
                'to_dict'
                '_bytes'
                'classmethod'
                'from_reader'
            [Locals+Names]
            [Constants]
                'FileMp4'
                '__pyarmor_assert_41313__'
                '__pyarmor_enter_41314__'
                b'<COAddr>\x05\x00\x00":\x00\x00\x00\x00\x00\x00\x00\x00\x00\x00\x00\x00\x00\x00\x00'
                0xB3CEA0E4
                0xF3A1E6F3
                [Code]
                    File Name: <frozen multithon.tl.types.storage>
                    Object Name: to_dict
                    Qualified Name: FileMp4.to_dict
                    Arg Count: 1
                    Pos Only Arg Count: 0
                    KW Only Arg Count: 0
                    Stack Size: 5
                    Flags: 0x20000003 (CO_OPTIMIZED | CO_NEWLOCALS | CO_PYARMOR_OBFUSCATED)
                    [Names]
                    [Locals+Names]
                        'self'
                        '__assert_armored__'
                    [Constants]
                        None
                        '__pyarmor_assert_41316__'
                        '__pyarmor_enter_41317__'
                        b'<COAddr>\x05\x00\x00\x1a\x1c\x00\x00\x00\x00\x00\x00\x00\x00\x00\x00\x00\x00\x00\x00\x00'
                        '_'
                        'FileMp4'
                        '__pyarmor_exit_41318__'
                    [Disassembly]
                        0       NOP                             
                        2       NOP                             
                        4       PUSH_NULL                       
                        6       LOAD_CONST                      2: '__pyarmor_enter_41317__'
                        8       LOAD_CONST                      3: b'<COAddr>\x05\x00\x00\x1a\x1c\x00\x00\x00\x00\x00\x00\x00\x00\x00\x00\x00\x00\x00\x00\x00'
                        10      BUILD_TUPLE                     1
                        12      CALL_FUNCTION_EX                0
                        14      POP_TOP                         
                        16      RESUME                          0
                        18      NOP                             
                        20      NOP                             
                        22      NOP                             
                        24      NOP                             
                        26      NOP                             
                        28      LOAD_CONST                      4: '_'
                        30      LOAD_CONST                      5: 'FileMp4'
                        32      BUILD_MAP                       1
                        34      NOP                             
                        36      NOP                             
                        38      NOP                             
                        40      JUMP_FORWARD                    20 (to 82)
                        42      CALL                            1
                        50      POP_TOP                         
                        52      RETURN_VALUE                    
                        54      PUSH_EXC_INFO                   
                        56      PUSH_NULL                       
                        58      LOAD_CONST                      6: '__pyarmor_exit_41318__'
                        60      NOP                             
                        62      LOAD_CONST                      3: b'<COAddr>\x05\x00\x00\x1a\x1c\x00\x00\x00\x00\x00\x00\x00\x00\x00\x00\x00\x00\x00\x00\x00'
                        64      CALL                            1
                        72      POP_TOP                         
                        74      RERAISE                         0
                        76      COPY                            3
                        78      POP_EXCEPT                      
                        80      RERAISE                         1
                        82      PUSH_NULL                       
                        84      LOAD_CONST                      6: '__pyarmor_exit_41318__'
                        86      LOAD_CONST                      3: b'<COAddr>\x05\x00\x00\x1a\x1c\x00\x00\x00\x00\x00\x00\x00\x00\x00\x00\x00\x00\x00\x00\x00'
                        88      BUILD_TUPLE                     1
                        90      CALL_FUNCTION_EX                0
                        92      POP_TOP                         
                        94      RETURN_VALUE                    
                    [Exception Table]
                        28 to 34 -> 54 [0] 
                        54 to 76 -> 76 [1] lasti
                [Code]
                    File Name: <frozen multithon.tl.types.storage>
                    Object Name: _bytes
                    Qualified Name: FileMp4._bytes
                    Arg Count: 1
                    Pos Only Arg Count: 0
                    KW Only Arg Count: 0
                    Stack Size: 5
                    Flags: 0x20000003 (CO_OPTIMIZED | CO_NEWLOCALS | CO_PYARMOR_OBFUSCATED)
                    [Names]
                        'join'
                    [Locals+Names]
                        'self'
                        '__assert_armored__'
                    [Constants]
                        None
                        '__pyarmor_assert_41319__'
                        '__pyarmor_enter_41320__'
                        b'<COAddr>\x07\x00\x00\x1a6\x00\x00\x00\x00\x00\x00\x00\x00\x00\x00\x00\x00\x00\x00\x00'
                        b''
                        (
                            b'\xe4\xa0\xce\xb3'
                        )
                        '__pyarmor_exit_41321__'
                    [Disassembly]
                        0       NOP                             
                        2       NOP                             
                        4       PUSH_NULL                       
                        6       LOAD_CONST                      2: '__pyarmor_enter_41320__'
                        8       LOAD_CONST                      3: b'<COAddr>\x07\x00\x00\x1a6\x00\x00\x00\x00\x00\x00\x00\x00\x00\x00\x00\x00\x00\x00\x00'
                        10      BUILD_TUPLE                     1
                        12      CALL_FUNCTION_EX                0
                        14      POP_TOP                         
                        16      RESUME                          0
                        18      NOP                             
                        20      NOP                             
                        22      NOP                             
                        24      NOP                             
                        26      NOP                             
                        28      LOAD_CONST                      4: b''
                        30      LOAD_ATTR                       1: join
                        50      LOAD_CONST                      5: (b'\xe4\xa0\xce\xb3',)
                        52      CALL                            1
                        60      NOP                             
                        62      NOP                             
                        64      NOP                             
                        66      JUMP_FORWARD                    20 (to 108)
                        68      CALL                            1
                        76      POP_TOP                         
                        78      RETURN_VALUE                    
                        80      PUSH_EXC_INFO                   
                        82      PUSH_NULL                       
                        84      LOAD_CONST                      6: '__pyarmor_exit_41321__'
                        86      NOP                             
                        88      LOAD_CONST                      3: b'<COAddr>\x07\x00\x00\x1a6\x00\x00\x00\x00\x00\x00\x00\x00\x00\x00\x00\x00\x00\x00\x00'
                        90      CALL                            1
                        98      POP_TOP                         
                        100     RERAISE                         0
                        102     COPY                            3
                        104     POP_EXCEPT                      
                        106     RERAISE                         1
                        108     PUSH_NULL                       
                        110     LOAD_CONST                      6: '__pyarmor_exit_41321__'
                        112     LOAD_CONST                      3: b'<COAddr>\x07\x00\x00\x1a6\x00\x00\x00\x00\x00\x00\x00\x00\x00\x00\x00\x00\x00\x00\x00'
                        114     BUILD_TUPLE                     1
                        116     CALL_FUNCTION_EX                0
                        118     POP_TOP                         
                        120     RETURN_VALUE                    
                    [Exception Table]
                        28 to 60 -> 80 [0] 
                        80 to 102 -> 102 [1] lasti
                [Code]
                    File Name: <frozen multithon.tl.types.storage>
                    Object Name: from_reader
                    Qualified Name: FileMp4.from_reader
                    Arg Count: 2
                    Pos Only Arg Count: 0
                    KW Only Arg Count: 0
                    Stack Size: 5
                    Flags: 0x20000003 (CO_OPTIMIZED | CO_NEWLOCALS | CO_PYARMOR_OBFUSCATED)
                    [Names]
                    [Locals+Names]
                        'cls'
                        'reader'
                        '__assert_armored__'
                    [Constants]
                        None
                        '__pyarmor_assert_41322__'
                        '__pyarmor_enter_41323__'
                        b'<COAddr>\x07\x00\x00\x1a"\x00\x00\x00\x00\x00\x00\x00\x00\x00\x00\x00\x00\x00\x00\x00'
                        '__pyarmor_exit_41324__'
                    [Disassembly]
                        0       NOP                             
                        2       NOP                             
                        4       PUSH_NULL                       
                        6       LOAD_CONST                      2: '__pyarmor_enter_41323__'
                        8       LOAD_CONST                      3: b'<COAddr>\x07\x00\x00\x1a"\x00\x00\x00\x00\x00\x00\x00\x00\x00\x00\x00\x00\x00\x00\x00'
                        10      BUILD_TUPLE                     1
                        12      CALL_FUNCTION_EX                0
                        14      POP_TOP                         
                        16      RESUME                          0
                        18      NOP                             
                        20      NOP                             
                        22      NOP                             
                        24      NOP                             
                        26      NOP                             
                        28      PUSH_NULL                       
                        30      LOAD_FAST                       0: cls
                        32      CALL                            0
                        40      NOP                             
                        42      NOP                             
                        44      NOP                             
                        46      JUMP_FORWARD                    20 (to 88)
                        48      CALL                            1
                        56      POP_TOP                         
                        58      RETURN_VALUE                    
                        60      PUSH_EXC_INFO                   
                        62      PUSH_NULL                       
                        64      LOAD_CONST                      4: '__pyarmor_exit_41324__'
                        66      NOP                             
                        68      LOAD_CONST                      3: b'<COAddr>\x07\x00\x00\x1a"\x00\x00\x00\x00\x00\x00\x00\x00\x00\x00\x00\x00\x00\x00\x00'
                        70      CALL                            1
                        78      POP_TOP                         
                        80      RERAISE                         0
                        82      COPY                            3
                        84      POP_EXCEPT                      
                        86      RERAISE                         1
                        88      PUSH_NULL                       
                        90      LOAD_CONST                      4: '__pyarmor_exit_41324__'
                        92      LOAD_CONST                      3: b'<COAddr>\x07\x00\x00\x1a"\x00\x00\x00\x00\x00\x00\x00\x00\x00\x00\x00\x00\x00\x00\x00'
                        94      BUILD_TUPLE                     1
                        96      CALL_FUNCTION_EX                0
                        98      POP_TOP                         
                        100     RETURN_VALUE                    
                    [Exception Table]
                        28 to 40 -> 60 [0] 
                        60 to 82 -> 82 [1] lasti
                '__pyarmor_exit_41315__'
                None
            [Disassembly]
                0       NOP                             
                2       LOAD_NAME                       0: __name__
                4       STORE_NAME                      1: __module__
                6       LOAD_CONST                      0: 'FileMp4'
                8       STORE_NAME                      2: __qualname__
                10      NOP                             
                12      PUSH_NULL                       
                14      LOAD_CONST                      2: '__pyarmor_enter_41314__'
                16      LOAD_CONST                      3: b'<COAddr>\x05\x00\x00":\x00\x00\x00\x00\x00\x00\x00\x00\x00\x00\x00\x00\x00\x00\x00'
                18      BUILD_TUPLE                     1
                20      CALL_FUNCTION_EX                0
                22      POP_TOP                         
                24      RESUME                          0
                26      NOP                             
                28      NOP                             
                30      NOP                             
                32      NOP                             
                34      NOP                             
                36      LOAD_CONST                      4: 0xB3CEA0E4
                38      STORE_NAME                      4: CONSTRUCTOR_ID
                40      LOAD_CONST                      5: 0xF3A1E6F3
                42      STORE_NAME                      5: SUBCLASS_OF_ID
                44      LOAD_CONST                      6: <CODE> to_dict
                46      MAKE_FUNCTION                   0
                48      STORE_NAME                      6: to_dict
                50      LOAD_CONST                      7: <CODE> _bytes
                52      MAKE_FUNCTION                   0
                54      STORE_NAME                      7: _bytes
                56      LOAD_NAME                       8: classmethod
                58      LOAD_CONST                      8: <CODE> from_reader
                60      MAKE_FUNCTION                   0
                62      CALL                            0
                70      STORE_NAME                      9: from_reader
                72      LOAD_CONST                      10: None
                74      NOP                             
                76      NOP                             
                78      NOP                             
                80      JUMP_FORWARD                    19 (to 120)
                88      POP_TOP                         
                90      RETURN_CONST                    10: None
                92      PUSH_EXC_INFO                   
                94      PUSH_NULL                       
                96      LOAD_CONST                      9: '__pyarmor_exit_41315__'
                98      NOP                             
                100     LOAD_CONST                      3: b'<COAddr>\x05\x00\x00":\x00\x00\x00\x00\x00\x00\x00\x00\x00\x00\x00\x00\x00\x00\x00'
                102     CALL                            1
                110     POP_TOP                         
                112     RERAISE                         0
                114     COPY                            3
                116     POP_EXCEPT                      
                118     RERAISE                         1
                120     PUSH_NULL                       
                122     LOAD_CONST                      9: '__pyarmor_exit_41315__'
                124     LOAD_CONST                      3: b'<COAddr>\x05\x00\x00":\x00\x00\x00\x00\x00\x00\x00\x00\x00\x00\x00\x00\x00\x00\x00'
                126     BUILD_TUPLE                     1
                128     CALL_FUNCTION_EX                0
                130     POP_TOP                         
                132     RETURN_VALUE                    
            [Exception Table]
                36 to 72 -> 92 [0] 
                92 to 114 -> 114 [1] lasti
        'FileMp4'
        [Code]
            File Name: <frozen multithon.tl.types.storage>
            Object Name: FilePartial
            Qualified Name: FilePartial
            Arg Count: 0
            Pos Only Arg Count: 0
            KW Only Arg Count: 0
            Stack Size: 5
            Flags: 0x20000000 (CO_PYARMOR_OBFUSCATED)
            [Names]
                '__name__'
                '__module__'
                '__qualname__'
                '__assert_armored__'
                'CONSTRUCTOR_ID'
                'SUBCLASS_OF_ID'
                'to_dict'
                '_bytes'
                'classmethod'
                'from_reader'
            [Locals+Names]
            [Constants]
                'FilePartial'
                '__pyarmor_assert_41325__'
                '__pyarmor_enter_41326__'
                b'<COAddr>\x07\x00\x00":\x00\x00\x00\x00\x00\x00\x00\x00\x00\x00\x00\x00\x00\x00\x00'
                1086091090
                0xF3A1E6F3
                [Code]
                    File Name: <frozen multithon.tl.types.storage>
                    Object Name: to_dict
                    Qualified Name: FilePartial.to_dict
                    Arg Count: 1
                    Pos Only Arg Count: 0
                    KW Only Arg Count: 0
                    Stack Size: 5
                    Flags: 0x20000003 (CO_OPTIMIZED | CO_NEWLOCALS | CO_PYARMOR_OBFUSCATED)
                    [Names]
                    [Locals+Names]
                        'self'
                        '__assert_armored__'
                    [Constants]
                        None
                        '__pyarmor_assert_41328__'
                        '__pyarmor_enter_41329__'
                        b'<COAddr>\x05\x00\x00\x1a(\x00\x00\x00\x00\x00\x00\x00\x00\x00\x00\x00\x00\x00\x00\x00'
                        '_'
                        'FilePartial'   # b'\x81\xc4\x11\x1f6\xca\xbf\xc0\x0f\xf3\x0c\xcc'
                        '__pyarmor_exit_41330__'
                    [Disassembly]
                        0       NOP                             
                        2       NOP                             
                        4       PUSH_NULL                       
                        6       LOAD_CONST                      2: '__pyarmor_enter_41329__'
                        8       LOAD_CONST                      3: b'<COAddr>\x05\x00\x00\x1a(\x00\x00\x00\x00\x00\x00\x00\x00\x00\x00\x00\x00\x00\x00\x00'
                        10      BUILD_TUPLE                     1
                        12      CALL_FUNCTION_EX                0
                        14      POP_TOP                         
                        16      RESUME                          0
                        18      NOP                             
                        20      NOP                             
                        22      NOP                             
                        24      NOP                             
                        26      NOP                             
                        28      LOAD_CONST                      4: '_'
                        30      PUSH_NULL                       
                        32      LOAD_CONST                      1: '__pyarmor_assert_41328__'
                        34      LOAD_CONST                      5: 'FilePartial'   # b'\x81\xc4\x11\x1f6\xca\xbf\xc0\x0f\xf3\x0c\xcc'
                        36      CALL                            1
                        44      BUILD_MAP                       1
                        46      NOP                             
                        48      NOP                             
                        50      NOP                             
                        52      JUMP_FORWARD                    20 (to 94)
                        54      CALL                            1
                        62      POP_TOP                         
                        64      RETURN_VALUE                    
                        66      PUSH_EXC_INFO                   
                        68      PUSH_NULL                       
                        70      LOAD_CONST                      6: '__pyarmor_exit_41330__'
                        72      NOP                             
                        74      LOAD_CONST                      3: b'<COAddr>\x05\x00\x00\x1a(\x00\x00\x00\x00\x00\x00\x00\x00\x00\x00\x00\x00\x00\x00\x00'
                        76      CALL                            1
                        84      POP_TOP                         
                        86      RERAISE                         0
                        88      COPY                            3
                        90      POP_EXCEPT                      
                        92      RERAISE                         1
                        94      PUSH_NULL                       
                        96      LOAD_CONST                      6: '__pyarmor_exit_41330__'
                        98      LOAD_CONST                      3: b'<COAddr>\x05\x00\x00\x1a(\x00\x00\x00\x00\x00\x00\x00\x00\x00\x00\x00\x00\x00\x00\x00'
                        100     BUILD_TUPLE                     1
                        102     CALL_FUNCTION_EX                0
                        104     POP_TOP                         
                        106     RETURN_VALUE                    
                    [Exception Table]
                        28 to 46 -> 66 [0] 
                        66 to 88 -> 88 [1] lasti
                [Code]
                    File Name: <frozen multithon.tl.types.storage>
                    Object Name: _bytes
                    Qualified Name: FilePartial._bytes
                    Arg Count: 1
                    Pos Only Arg Count: 0
                    KW Only Arg Count: 0
                    Stack Size: 5
                    Flags: 0x20000003 (CO_OPTIMIZED | CO_NEWLOCALS | CO_PYARMOR_OBFUSCATED)
                    [Names]
                        'join'
                    [Locals+Names]
                        'self'
                        '__assert_armored__'
                    [Constants]
                        None
                        '__pyarmor_assert_41331__'
                        '__pyarmor_enter_41332__'
                        b'<COAddr>\x07\x00\x00\x1a6\x00\x00\x00\x00\x00\x00\x00\x00\x00\x00\x00\x00\x00\x00\x00'
                        b''
                        (
                            b'Ro\xbc@'
                        )
                        '__pyarmor_exit_41333__'
                    [Disassembly]
                        0       NOP                             
                        2       NOP                             
                        4       PUSH_NULL                       
                        6       LOAD_CONST                      2: '__pyarmor_enter_41332__'
                        8       LOAD_CONST                      3: b'<COAddr>\x07\x00\x00\x1a6\x00\x00\x00\x00\x00\x00\x00\x00\x00\x00\x00\x00\x00\x00\x00'
                        10      BUILD_TUPLE                     1
                        12      CALL_FUNCTION_EX                0
                        14      POP_TOP                         
                        16      RESUME                          0
                        18      NOP                             
                        20      NOP                             
                        22      NOP                             
                        24      NOP                             
                        26      NOP                             
                        28      LOAD_CONST                      4: b''
                        30      LOAD_ATTR                       1: join
                        50      LOAD_CONST                      5: (b'Ro\xbc@',)
                        52      CALL                            1
                        60      NOP                             
                        62      NOP                             
                        64      NOP                             
                        66      JUMP_FORWARD                    20 (to 108)
                        68      CALL                            1
                        76      POP_TOP                         
                        78      RETURN_VALUE                    
                        80      PUSH_EXC_INFO                   
                        82      PUSH_NULL                       
                        84      LOAD_CONST                      6: '__pyarmor_exit_41333__'
                        86      NOP                             
                        88      LOAD_CONST                      3: b'<COAddr>\x07\x00\x00\x1a6\x00\x00\x00\x00\x00\x00\x00\x00\x00\x00\x00\x00\x00\x00\x00'
                        90      CALL                            1
                        98      POP_TOP                         
                        100     RERAISE                         0
                        102     COPY                            3
                        104     POP_EXCEPT                      
                        106     RERAISE                         1
                        108     PUSH_NULL                       
                        110     LOAD_CONST                      6: '__pyarmor_exit_41333__'
                        112     LOAD_CONST                      3: b'<COAddr>\x07\x00\x00\x1a6\x00\x00\x00\x00\x00\x00\x00\x00\x00\x00\x00\x00\x00\x00\x00'
                        114     BUILD_TUPLE                     1
                        116     CALL_FUNCTION_EX                0
                        118     POP_TOP                         
                        120     RETURN_VALUE                    
                    [Exception Table]
                        28 to 60 -> 80 [0] 
                        80 to 102 -> 102 [1] lasti
                [Code]
                    File Name: <frozen multithon.tl.types.storage>
                    Object Name: from_reader
                    Qualified Name: FilePartial.from_reader
                    Arg Count: 2
                    Pos Only Arg Count: 0
                    KW Only Arg Count: 0
                    Stack Size: 5
                    Flags: 0x20000003 (CO_OPTIMIZED | CO_NEWLOCALS | CO_PYARMOR_OBFUSCATED)
                    [Names]
                    [Locals+Names]
                        'cls'
                        'reader'
                        '__assert_armored__'
                    [Constants]
                        None
                        '__pyarmor_assert_41334__'
                        '__pyarmor_enter_41335__'
                        b'<COAddr>\x07\x00\x00\x1a"\x00\x00\x00\x00\x00\x00\x00\x00\x00\x00\x00\x00\x00\x00\x00'
                        '__pyarmor_exit_41336__'
                    [Disassembly]
                        0       NOP                             
                        2       NOP                             
                        4       PUSH_NULL                       
                        6       LOAD_CONST                      2: '__pyarmor_enter_41335__'
                        8       LOAD_CONST                      3: b'<COAddr>\x07\x00\x00\x1a"\x00\x00\x00\x00\x00\x00\x00\x00\x00\x00\x00\x00\x00\x00\x00'
                        10      BUILD_TUPLE                     1
                        12      CALL_FUNCTION_EX                0
                        14      POP_TOP                         
                        16      RESUME                          0
                        18      NOP                             
                        20      NOP                             
                        22      NOP                             
                        24      NOP                             
                        26      NOP                             
                        28      PUSH_NULL                       
                        30      LOAD_FAST                       0: cls
                        32      CALL                            0
                        40      NOP                             
                        42      NOP                             
                        44      NOP                             
                        46      JUMP_FORWARD                    20 (to 88)
                        48      CALL                            1
                        56      POP_TOP                         
                        58      RETURN_VALUE                    
                        60      PUSH_EXC_INFO                   
                        62      PUSH_NULL                       
                        64      LOAD_CONST                      4: '__pyarmor_exit_41336__'
                        66      NOP                             
                        68      LOAD_CONST                      3: b'<COAddr>\x07\x00\x00\x1a"\x00\x00\x00\x00\x00\x00\x00\x00\x00\x00\x00\x00\x00\x00\x00'
                        70      CALL                            1
                        78      POP_TOP                         
                        80      RERAISE                         0
                        82      COPY                            3
                        84      POP_EXCEPT                      
                        86      RERAISE                         1
                        88      PUSH_NULL                       
                        90      LOAD_CONST                      4: '__pyarmor_exit_41336__'
                        92      LOAD_CONST                      3: b'<COAddr>\x07\x00\x00\x1a"\x00\x00\x00\x00\x00\x00\x00\x00\x00\x00\x00\x00\x00\x00\x00'
                        94      BUILD_TUPLE                     1
                        96      CALL_FUNCTION_EX                0
                        98      POP_TOP                         
                        100     RETURN_VALUE                    
                    [Exception Table]
                        28 to 40 -> 60 [0] 
                        60 to 82 -> 82 [1] lasti
                '__pyarmor_exit_41327__'
                None
            [Disassembly]
                0       NOP                             
                2       LOAD_NAME                       0: __name__
                4       STORE_NAME                      1: __module__
                6       LOAD_CONST                      0: 'FilePartial'
                8       STORE_NAME                      2: __qualname__
                10      NOP                             
                12      PUSH_NULL                       
                14      LOAD_CONST                      2: '__pyarmor_enter_41326__'
                16      LOAD_CONST                      3: b'<COAddr>\x07\x00\x00":\x00\x00\x00\x00\x00\x00\x00\x00\x00\x00\x00\x00\x00\x00\x00'
                18      BUILD_TUPLE                     1
                20      CALL_FUNCTION_EX                0
                22      POP_TOP                         
                24      RESUME                          0
                26      NOP                             
                28      NOP                             
                30      NOP                             
                32      NOP                             
                34      NOP                             
                36      LOAD_CONST                      4: 1086091090
                38      STORE_NAME                      4: CONSTRUCTOR_ID
                40      LOAD_CONST                      5: 0xF3A1E6F3
                42      STORE_NAME                      5: SUBCLASS_OF_ID
                44      LOAD_CONST                      6: <CODE> to_dict
                46      MAKE_FUNCTION                   0
                48      STORE_NAME                      6: to_dict
                50      LOAD_CONST                      7: <CODE> _bytes
                52      MAKE_FUNCTION                   0
                54      STORE_NAME                      7: _bytes
                56      LOAD_NAME                       8: classmethod
                58      LOAD_CONST                      8: <CODE> from_reader
                60      MAKE_FUNCTION                   0
                62      CALL                            0
                70      STORE_NAME                      9: from_reader
                72      LOAD_CONST                      10: None
                74      NOP                             
                76      NOP                             
                78      NOP                             
                80      JUMP_FORWARD                    19 (to 120)
                88      POP_TOP                         
                90      RETURN_CONST                    10: None
                92      PUSH_EXC_INFO                   
                94      PUSH_NULL                       
                96      LOAD_CONST                      9: '__pyarmor_exit_41327__'
                98      NOP                             
                100     LOAD_CONST                      3: b'<COAddr>\x07\x00\x00":\x00\x00\x00\x00\x00\x00\x00\x00\x00\x00\x00\x00\x00\x00\x00'
                102     CALL                            1
                110     POP_TOP                         
                112     RERAISE                         0
                114     COPY                            3
                116     POP_EXCEPT                      
                118     RERAISE                         1
                120     PUSH_NULL                       
                122     LOAD_CONST                      9: '__pyarmor_exit_41327__'
                124     LOAD_CONST                      3: b'<COAddr>\x07\x00\x00":\x00\x00\x00\x00\x00\x00\x00\x00\x00\x00\x00\x00\x00\x00\x00'
                126     BUILD_TUPLE                     1
                128     CALL_FUNCTION_EX                0
                130     POP_TOP                         
                132     RETURN_VALUE                    
            [Exception Table]
                36 to 72 -> 92 [0] 
                92 to 114 -> 114 [1] lasti
        'FilePartial'
        [Code]
            File Name: <frozen multithon.tl.types.storage>
            Object Name: FilePdf
            Qualified Name: FilePdf
            Arg Count: 0
            Pos Only Arg Count: 0
            KW Only Arg Count: 0
            Stack Size: 5
            Flags: 0x20000000 (CO_PYARMOR_OBFUSCATED)
            [Names]
                '__name__'
                '__module__'
                '__qualname__'
                '__assert_armored__'
                'CONSTRUCTOR_ID'
                'SUBCLASS_OF_ID'
                'to_dict'
                '_bytes'
                'classmethod'
                'from_reader'
            [Locals+Names]
            [Constants]
                'FilePdf'
                '__pyarmor_assert_41337__'
                '__pyarmor_enter_41338__'
                b'<COAddr>\x05\x00\x00":\x00\x00\x00\x00\x00\x00\x00\x00\x00\x00\x00\x00\x00\x00\x00'
                0xAE1E508D
                0xF3A1E6F3
                [Code]
                    File Name: <frozen multithon.tl.types.storage>
                    Object Name: to_dict
                    Qualified Name: FilePdf.to_dict
                    Arg Count: 1
                    Pos Only Arg Count: 0
                    KW Only Arg Count: 0
                    Stack Size: 5
                    Flags: 0x20000003 (CO_OPTIMIZED | CO_NEWLOCALS | CO_PYARMOR_OBFUSCATED)
                    [Names]
                    [Locals+Names]
                        'self'
                        '__assert_armored__'
                    [Constants]
                        None
                        '__pyarmor_assert_41340__'
                        '__pyarmor_enter_41341__'
                        b'<COAddr>\x07\x00\x00\x1a\x1c\x00\x00\x00\x00\x00\x00\x00\x00\x00\x00\x00\x00\x00\x00\x00'
                        '_'
                        'FilePdf'
                        '__pyarmor_exit_41342__'
                    [Disassembly]
                        0       NOP                             
                        2       NOP                             
                        4       PUSH_NULL                       
                        6       LOAD_CONST                      2: '__pyarmor_enter_41341__'
                        8       LOAD_CONST                      3: b'<COAddr>\x07\x00\x00\x1a\x1c\x00\x00\x00\x00\x00\x00\x00\x00\x00\x00\x00\x00\x00\x00\x00'
                        10      BUILD_TUPLE                     1
                        12      CALL_FUNCTION_EX                0
                        14      POP_TOP                         
                        16      RESUME                          0
                        18      NOP                             
                        20      NOP                             
                        22      NOP                             
                        24      NOP                             
                        26      NOP                             
                        28      LOAD_CONST                      4: '_'
                        30      LOAD_CONST                      5: 'FilePdf'
                        32      BUILD_MAP                       1
                        34      NOP                             
                        36      NOP                             
                        38      NOP                             
                        40      JUMP_FORWARD                    20 (to 82)
                        42      CALL                            1
                        50      POP_TOP                         
                        52      RETURN_VALUE                    
                        54      PUSH_EXC_INFO                   
                        56      PUSH_NULL                       
                        58      LOAD_CONST                      6: '__pyarmor_exit_41342__'
                        60      NOP                             
                        62      LOAD_CONST                      3: b'<COAddr>\x07\x00\x00\x1a\x1c\x00\x00\x00\x00\x00\x00\x00\x00\x00\x00\x00\x00\x00\x00\x00'
                        64      CALL                            1
                        72      POP_TOP                         
                        74      RERAISE                         0
                        76      COPY                            3
                        78      POP_EXCEPT                      
                        80      RERAISE                         1
                        82      PUSH_NULL                       
                        84      LOAD_CONST                      6: '__pyarmor_exit_41342__'
                        86      LOAD_CONST                      3: b'<COAddr>\x07\x00\x00\x1a\x1c\x00\x00\x00\x00\x00\x00\x00\x00\x00\x00\x00\x00\x00\x00\x00'
                        88      BUILD_TUPLE                     1
                        90      CALL_FUNCTION_EX                0
                        92      POP_TOP                         
                        94      RETURN_VALUE                    
                    [Exception Table]
                        28 to 34 -> 54 [0] 
                        54 to 76 -> 76 [1] lasti
                [Code]
                    File Name: <frozen multithon.tl.types.storage>
                    Object Name: _bytes
                    Qualified Name: FilePdf._bytes
                    Arg Count: 1
                    Pos Only Arg Count: 0
                    KW Only Arg Count: 0
                    Stack Size: 5
                    Flags: 0x20000003 (CO_OPTIMIZED | CO_NEWLOCALS | CO_PYARMOR_OBFUSCATED)
                    [Names]
                        'join'
                    [Locals+Names]
                        'self'
                        '__assert_armored__'
                    [Constants]
                        None
                        '__pyarmor_assert_41343__'
                        '__pyarmor_enter_41344__'
                        b'<COAddr>\x05\x00\x00\x1a6\x00\x00\x00\x00\x00\x00\x00\x00\x00\x00\x00\x00\x00\x00\x00'
                        b''
                        (
                            b'\x8dP\x1e\xae'
                        )
                        '__pyarmor_exit_41345__'
                    [Disassembly]
                        0       NOP                             
                        2       NOP                             
                        4       PUSH_NULL                       
                        6       LOAD_CONST                      2: '__pyarmor_enter_41344__'
                        8       LOAD_CONST                      3: b'<COAddr>\x05\x00\x00\x1a6\x00\x00\x00\x00\x00\x00\x00\x00\x00\x00\x00\x00\x00\x00\x00'
                        10      BUILD_TUPLE                     1
                        12      CALL_FUNCTION_EX                0
                        14      POP_TOP                         
                        16      RESUME                          0
                        18      NOP                             
                        20      NOP                             
                        22      NOP                             
                        24      NOP                             
                        26      NOP                             
                        28      LOAD_CONST                      4: b''
                        30      LOAD_ATTR                       1: join
                        50      LOAD_CONST                      5: (b'\x8dP\x1e\xae',)
                        52      CALL                            1
                        60      NOP                             
                        62      NOP                             
                        64      NOP                             
                        66      JUMP_FORWARD                    20 (to 108)
                        68      CALL                            1
                        76      POP_TOP                         
                        78      RETURN_VALUE                    
                        80      PUSH_EXC_INFO                   
                        82      PUSH_NULL                       
                        84      LOAD_CONST                      6: '__pyarmor_exit_41345__'
                        86      NOP                             
                        88      LOAD_CONST                      3: b'<COAddr>\x05\x00\x00\x1a6\x00\x00\x00\x00\x00\x00\x00\x00\x00\x00\x00\x00\x00\x00\x00'
                        90      CALL                            1
                        98      POP_TOP                         
                        100     RERAISE                         0
                        102     COPY                            3
                        104     POP_EXCEPT                      
                        106     RERAISE                         1
                        108     PUSH_NULL                       
                        110     LOAD_CONST                      6: '__pyarmor_exit_41345__'
                        112     LOAD_CONST                      3: b'<COAddr>\x05\x00\x00\x1a6\x00\x00\x00\x00\x00\x00\x00\x00\x00\x00\x00\x00\x00\x00\x00'
                        114     BUILD_TUPLE                     1
                        116     CALL_FUNCTION_EX                0
                        118     POP_TOP                         
                        120     RETURN_VALUE                    
                    [Exception Table]
                        28 to 60 -> 80 [0] 
                        80 to 102 -> 102 [1] lasti
                [Code]
                    File Name: <frozen multithon.tl.types.storage>
                    Object Name: from_reader
                    Qualified Name: FilePdf.from_reader
                    Arg Count: 2
                    Pos Only Arg Count: 0
                    KW Only Arg Count: 0
                    Stack Size: 5
                    Flags: 0x20000003 (CO_OPTIMIZED | CO_NEWLOCALS | CO_PYARMOR_OBFUSCATED)
                    [Names]
                    [Locals+Names]
                        'cls'
                        'reader'
                        '__assert_armored__'
                    [Constants]
                        None
                        '__pyarmor_assert_41346__'
                        '__pyarmor_enter_41347__'
                        b'<COAddr>\x07\x00\x00\x1a"\x00\x00\x00\x00\x00\x00\x00\x00\x00\x00\x00\x00\x00\x00\x00'
                        '__pyarmor_exit_41348__'
                    [Disassembly]
                        0       NOP                             
                        2       NOP                             
                        4       PUSH_NULL                       
                        6       LOAD_CONST                      2: '__pyarmor_enter_41347__'
                        8       LOAD_CONST                      3: b'<COAddr>\x07\x00\x00\x1a"\x00\x00\x00\x00\x00\x00\x00\x00\x00\x00\x00\x00\x00\x00\x00'
                        10      BUILD_TUPLE                     1
                        12      CALL_FUNCTION_EX                0
                        14      POP_TOP                         
                        16      RESUME                          0
                        18      NOP                             
                        20      NOP                             
                        22      NOP                             
                        24      NOP                             
                        26      NOP                             
                        28      PUSH_NULL                       
                        30      LOAD_FAST                       0: cls
                        32      CALL                            0
                        40      NOP                             
                        42      NOP                             
                        44      NOP                             
                        46      JUMP_FORWARD                    20 (to 88)
                        48      CALL                            1
                        56      POP_TOP                         
                        58      RETURN_VALUE                    
                        60      PUSH_EXC_INFO                   
                        62      PUSH_NULL                       
                        64      LOAD_CONST                      4: '__pyarmor_exit_41348__'
                        66      NOP                             
                        68      LOAD_CONST                      3: b'<COAddr>\x07\x00\x00\x1a"\x00\x00\x00\x00\x00\x00\x00\x00\x00\x00\x00\x00\x00\x00\x00'
                        70      CALL                            1
                        78      POP_TOP                         
                        80      RERAISE                         0
                        82      COPY                            3
                        84      POP_EXCEPT                      
                        86      RERAISE                         1
                        88      PUSH_NULL                       
                        90      LOAD_CONST                      4: '__pyarmor_exit_41348__'
                        92      LOAD_CONST                      3: b'<COAddr>\x07\x00\x00\x1a"\x00\x00\x00\x00\x00\x00\x00\x00\x00\x00\x00\x00\x00\x00\x00'
                        94      BUILD_TUPLE                     1
                        96      CALL_FUNCTION_EX                0
                        98      POP_TOP                         
                        100     RETURN_VALUE                    
                    [Exception Table]
                        28 to 40 -> 60 [0] 
                        60 to 82 -> 82 [1] lasti
                '__pyarmor_exit_41339__'
                None
            [Disassembly]
                0       NOP                             
                2       LOAD_NAME                       0: __name__
                4       STORE_NAME                      1: __module__
                6       LOAD_CONST                      0: 'FilePdf'
                8       STORE_NAME                      2: __qualname__
                10      NOP                             
                12      PUSH_NULL                       
                14      LOAD_CONST                      2: '__pyarmor_enter_41338__'
                16      LOAD_CONST                      3: b'<COAddr>\x05\x00\x00":\x00\x00\x00\x00\x00\x00\x00\x00\x00\x00\x00\x00\x00\x00\x00'
                18      BUILD_TUPLE                     1
                20      CALL_FUNCTION_EX                0
                22      POP_TOP                         
                24      RESUME                          0
                26      NOP                             
                28      NOP                             
                30      NOP                             
                32      NOP                             
                34      NOP                             
                36      LOAD_CONST                      4: 0xAE1E508D
                38      STORE_NAME                      4: CONSTRUCTOR_ID
                40      LOAD_CONST                      5: 0xF3A1E6F3
                42      STORE_NAME                      5: SUBCLASS_OF_ID
                44      LOAD_CONST                      6: <CODE> to_dict
                46      MAKE_FUNCTION                   0
                48      STORE_NAME                      6: to_dict
                50      LOAD_CONST                      7: <CODE> _bytes
                52      MAKE_FUNCTION                   0
                54      STORE_NAME                      7: _bytes
                56      LOAD_NAME                       8: classmethod
                58      LOAD_CONST                      8: <CODE> from_reader
                60      MAKE_FUNCTION                   0
                62      CALL                            0
                70      STORE_NAME                      9: from_reader
                72      LOAD_CONST                      10: None
                74      NOP                             
                76      NOP                             
                78      NOP                             
                80      JUMP_FORWARD                    19 (to 120)
                88      POP_TOP                         
                90      RETURN_CONST                    10: None
                92      PUSH_EXC_INFO                   
                94      PUSH_NULL                       
                96      LOAD_CONST                      9: '__pyarmor_exit_41339__'
                98      NOP                             
                100     LOAD_CONST                      3: b'<COAddr>\x05\x00\x00":\x00\x00\x00\x00\x00\x00\x00\x00\x00\x00\x00\x00\x00\x00\x00'
                102     CALL                            1
                110     POP_TOP                         
                112     RERAISE                         0
                114     COPY                            3
                116     POP_EXCEPT                      
                118     RERAISE                         1
                120     PUSH_NULL                       
                122     LOAD_CONST                      9: '__pyarmor_exit_41339__'
                124     LOAD_CONST                      3: b'<COAddr>\x05\x00\x00":\x00\x00\x00\x00\x00\x00\x00\x00\x00\x00\x00\x00\x00\x00\x00'
                126     BUILD_TUPLE                     1
                128     CALL_FUNCTION_EX                0
                130     POP_TOP                         
                132     RETURN_VALUE                    
            [Exception Table]
                36 to 72 -> 92 [0] 
                92 to 114 -> 114 [1] lasti
        'FilePdf'
        [Code]
            File Name: <frozen multithon.tl.types.storage>
            Object Name: FilePng
            Qualified Name: FilePng
            Arg Count: 0
            Pos Only Arg Count: 0
            KW Only Arg Count: 0
            Stack Size: 5
            Flags: 0x20000000 (CO_PYARMOR_OBFUSCATED)
            [Names]
                '__name__'
                '__module__'
                '__qualname__'
                '__assert_armored__'
                'CONSTRUCTOR_ID'
                'SUBCLASS_OF_ID'
                'to_dict'
                '_bytes'
                'classmethod'
                'from_reader'
            [Locals+Names]
            [Constants]
                'FilePng'
                '__pyarmor_assert_41349__'
                '__pyarmor_enter_41350__'
                b'<COAddr>\x05\x00\x00":\x00\x00\x00\x00\x00\x00\x00\x00\x00\x00\x00\x00\x00\x00\x00'
                172975040
                0xF3A1E6F3
                [Code]
                    File Name: <frozen multithon.tl.types.storage>
                    Object Name: to_dict
                    Qualified Name: FilePng.to_dict
                    Arg Count: 1
                    Pos Only Arg Count: 0
                    KW Only Arg Count: 0
                    Stack Size: 5
                    Flags: 0x20000003 (CO_OPTIMIZED | CO_NEWLOCALS | CO_PYARMOR_OBFUSCATED)
                    [Names]
                    [Locals+Names]
                        'self'
                        '__assert_armored__'
                    [Constants]
                        None
                        '__pyarmor_assert_41352__'
                        '__pyarmor_enter_41353__'
                        b'<COAddr>\x07\x00\x00\x1a\x1c\x00\x00\x00\x00\x00\x00\x00\x00\x00\x00\x00\x00\x00\x00\x00'
                        '_'
                        'FilePng'
                        '__pyarmor_exit_41354__'
                    [Disassembly]
                        0       NOP                             
                        2       NOP                             
                        4       PUSH_NULL                       
                        6       LOAD_CONST                      2: '__pyarmor_enter_41353__'
                        8       LOAD_CONST                      3: b'<COAddr>\x07\x00\x00\x1a\x1c\x00\x00\x00\x00\x00\x00\x00\x00\x00\x00\x00\x00\x00\x00\x00'
                        10      BUILD_TUPLE                     1
                        12      CALL_FUNCTION_EX                0
                        14      POP_TOP                         
                        16      RESUME                          0
                        18      NOP                             
                        20      NOP                             
                        22      NOP                             
                        24      NOP                             
                        26      NOP                             
                        28      LOAD_CONST                      4: '_'
                        30      LOAD_CONST                      5: 'FilePng'
                        32      BUILD_MAP                       1
                        34      NOP                             
                        36      NOP                             
                        38      NOP                             
                        40      JUMP_FORWARD                    20 (to 82)
                        42      CALL                            1
                        50      POP_TOP                         
                        52      RETURN_VALUE                    
                        54      PUSH_EXC_INFO                   
                        56      PUSH_NULL                       
                        58      LOAD_CONST                      6: '__pyarmor_exit_41354__'
                        60      NOP                             
                        62      LOAD_CONST                      3: b'<COAddr>\x07\x00\x00\x1a\x1c\x00\x00\x00\x00\x00\x00\x00\x00\x00\x00\x00\x00\x00\x00\x00'
                        64      CALL                            1
                        72      POP_TOP                         
                        74      RERAISE                         0
                        76      COPY                            3
                        78      POP_EXCEPT                      
                        80      RERAISE                         1
                        82      PUSH_NULL                       
                        84      LOAD_CONST                      6: '__pyarmor_exit_41354__'
                        86      LOAD_CONST                      3: b'<COAddr>\x07\x00\x00\x1a\x1c\x00\x00\x00\x00\x00\x00\x00\x00\x00\x00\x00\x00\x00\x00\x00'
                        88      BUILD_TUPLE                     1
                        90      CALL_FUNCTION_EX                0
                        92      POP_TOP                         
                        94      RETURN_VALUE                    
                    [Exception Table]
                        28 to 34 -> 54 [0] 
                        54 to 76 -> 76 [1] lasti
                [Code]
                    File Name: <frozen multithon.tl.types.storage>
                    Object Name: _bytes
                    Qualified Name: FilePng._bytes
                    Arg Count: 1
                    Pos Only Arg Count: 0
                    KW Only Arg Count: 0
                    Stack Size: 5
                    Flags: 0x20000003 (CO_OPTIMIZED | CO_NEWLOCALS | CO_PYARMOR_OBFUSCATED)
                    [Names]
                        'join'
                    [Locals+Names]
                        'self'
                        '__assert_armored__'
                    [Constants]
                        None
                        '__pyarmor_assert_41355__'
                        '__pyarmor_enter_41356__'
                        b'<COAddr>\x05\x00\x00\x1a6\x00\x00\x00\x00\x00\x00\x00\x00\x00\x00\x00\x00\x00\x00\x00'
                        b''
                        (
                            b'\xc0cO\n'
                        )
                        '__pyarmor_exit_41357__'
                    [Disassembly]
                        0       NOP                             
                        2       NOP                             
                        4       PUSH_NULL                       
                        6       LOAD_CONST                      2: '__pyarmor_enter_41356__'
                        8       LOAD_CONST                      3: b'<COAddr>\x05\x00\x00\x1a6\x00\x00\x00\x00\x00\x00\x00\x00\x00\x00\x00\x00\x00\x00\x00'
                        10      BUILD_TUPLE                     1
                        12      CALL_FUNCTION_EX                0
                        14      POP_TOP                         
                        16      RESUME                          0
                        18      NOP                             
                        20      NOP                             
                        22      NOP                             
                        24      NOP                             
                        26      NOP                             
                        28      LOAD_CONST                      4: b''
                        30      LOAD_ATTR                       1: join
                        50      LOAD_CONST                      5: (b'\xc0cO\n',)
                        52      CALL                            1
                        60      NOP                             
                        62      NOP                             
                        64      NOP                             
                        66      JUMP_FORWARD                    20 (to 108)
                        68      CALL                            1
                        76      POP_TOP                         
                        78      RETURN_VALUE                    
                        80      PUSH_EXC_INFO                   
                        82      PUSH_NULL                       
                        84      LOAD_CONST                      6: '__pyarmor_exit_41357__'
                        86      NOP                             
                        88      LOAD_CONST                      3: b'<COAddr>\x05\x00\x00\x1a6\x00\x00\x00\x00\x00\x00\x00\x00\x00\x00\x00\x00\x00\x00\x00'
                        90      CALL                            1
                        98      POP_TOP                         
                        100     RERAISE                         0
                        102     COPY                            3
                        104     POP_EXCEPT                      
                        106     RERAISE                         1
                        108     PUSH_NULL                       
                        110     LOAD_CONST                      6: '__pyarmor_exit_41357__'
                        112     LOAD_CONST                      3: b'<COAddr>\x05\x00\x00\x1a6\x00\x00\x00\x00\x00\x00\x00\x00\x00\x00\x00\x00\x00\x00\x00'
                        114     BUILD_TUPLE                     1
                        116     CALL_FUNCTION_EX                0
                        118     POP_TOP                         
                        120     RETURN_VALUE                    
                    [Exception Table]
                        28 to 60 -> 80 [0] 
                        80 to 102 -> 102 [1] lasti
                [Code]
                    File Name: <frozen multithon.tl.types.storage>
                    Object Name: from_reader
                    Qualified Name: FilePng.from_reader
                    Arg Count: 2
                    Pos Only Arg Count: 0
                    KW Only Arg Count: 0
                    Stack Size: 5
                    Flags: 0x20000003 (CO_OPTIMIZED | CO_NEWLOCALS | CO_PYARMOR_OBFUSCATED)
                    [Names]
                    [Locals+Names]
                        'cls'
                        'reader'
                        '__assert_armored__'
                    [Constants]
                        None
                        '__pyarmor_assert_41358__'
                        '__pyarmor_enter_41359__'
                        b'<COAddr>\x05\x00\x00\x1a"\x00\x00\x00\x00\x00\x00\x00\x00\x00\x00\x00\x00\x00\x00\x00'
                        '__pyarmor_exit_41360__'
                    [Disassembly]
                        0       NOP                             
                        2       NOP                             
                        4       PUSH_NULL                       
                        6       LOAD_CONST                      2: '__pyarmor_enter_41359__'
                        8       LOAD_CONST                      3: b'<COAddr>\x05\x00\x00\x1a"\x00\x00\x00\x00\x00\x00\x00\x00\x00\x00\x00\x00\x00\x00\x00'
                        10      BUILD_TUPLE                     1
                        12      CALL_FUNCTION_EX                0
                        14      POP_TOP                         
                        16      RESUME                          0
                        18      NOP                             
                        20      NOP                             
                        22      NOP                             
                        24      NOP                             
                        26      NOP                             
                        28      PUSH_NULL                       
                        30      LOAD_FAST                       0: cls
                        32      CALL                            0
                        40      NOP                             
                        42      NOP                             
                        44      NOP                             
                        46      JUMP_FORWARD                    20 (to 88)
                        48      CALL                            1
                        56      POP_TOP                         
                        58      RETURN_VALUE                    
                        60      PUSH_EXC_INFO                   
                        62      PUSH_NULL                       
                        64      LOAD_CONST                      4: '__pyarmor_exit_41360__'
                        66      NOP                             
                        68      LOAD_CONST                      3: b'<COAddr>\x05\x00\x00\x1a"\x00\x00\x00\x00\x00\x00\x00\x00\x00\x00\x00\x00\x00\x00\x00'
                        70      CALL                            1
                        78      POP_TOP                         
                        80      RERAISE                         0
                        82      COPY                            3
                        84      POP_EXCEPT                      
                        86      RERAISE                         1
                        88      PUSH_NULL                       
                        90      LOAD_CONST                      4: '__pyarmor_exit_41360__'
                        92      LOAD_CONST                      3: b'<COAddr>\x05\x00\x00\x1a"\x00\x00\x00\x00\x00\x00\x00\x00\x00\x00\x00\x00\x00\x00\x00'
                        94      BUILD_TUPLE                     1
                        96      CALL_FUNCTION_EX                0
                        98      POP_TOP                         
                        100     RETURN_VALUE                    
                    [Exception Table]
                        28 to 40 -> 60 [0] 
                        60 to 82 -> 82 [1] lasti
                '__pyarmor_exit_41351__'
                None
            [Disassembly]
                0       NOP                             
                2       LOAD_NAME                       0: __name__
                4       STORE_NAME                      1: __module__
                6       LOAD_CONST                      0: 'FilePng'
                8       STORE_NAME                      2: __qualname__
                10      NOP                             
                12      PUSH_NULL                       
                14      LOAD_CONST                      2: '__pyarmor_enter_41350__'
                16      LOAD_CONST                      3: b'<COAddr>\x05\x00\x00":\x00\x00\x00\x00\x00\x00\x00\x00\x00\x00\x00\x00\x00\x00\x00'
                18      BUILD_TUPLE                     1
                20      CALL_FUNCTION_EX                0
                22      POP_TOP                         
                24      RESUME                          0
                26      NOP                             
                28      NOP                             
                30      NOP                             
                32      NOP                             
                34      NOP                             
                36      LOAD_CONST                      4: 172975040
                38      STORE_NAME                      4: CONSTRUCTOR_ID
                40      LOAD_CONST                      5: 0xF3A1E6F3
                42      STORE_NAME                      5: SUBCLASS_OF_ID
                44      LOAD_CONST                      6: <CODE> to_dict
                46      MAKE_FUNCTION                   0
                48      STORE_NAME                      6: to_dict
                50      LOAD_CONST                      7: <CODE> _bytes
                52      MAKE_FUNCTION                   0
                54      STORE_NAME                      7: _bytes
                56      LOAD_NAME                       8: classmethod
                58      LOAD_CONST                      8: <CODE> from_reader
                60      MAKE_FUNCTION                   0
                62      CALL                            0
                70      STORE_NAME                      9: from_reader
                72      LOAD_CONST                      10: None
                74      NOP                             
                76      NOP                             
                78      NOP                             
                80      JUMP_FORWARD                    19 (to 120)
                88      POP_TOP                         
                90      RETURN_CONST                    10: None
                92      PUSH_EXC_INFO                   
                94      PUSH_NULL                       
                96      LOAD_CONST                      9: '__pyarmor_exit_41351__'
                98      NOP                             
                100     LOAD_CONST                      3: b'<COAddr>\x05\x00\x00":\x00\x00\x00\x00\x00\x00\x00\x00\x00\x00\x00\x00\x00\x00\x00'
                102     CALL                            1
                110     POP_TOP                         
                112     RERAISE                         0
                114     COPY                            3
                116     POP_EXCEPT                      
                118     RERAISE                         1
                120     PUSH_NULL                       
                122     LOAD_CONST                      9: '__pyarmor_exit_41351__'
                124     LOAD_CONST                      3: b'<COAddr>\x05\x00\x00":\x00\x00\x00\x00\x00\x00\x00\x00\x00\x00\x00\x00\x00\x00\x00'
                126     BUILD_TUPLE                     1
                128     CALL_FUNCTION_EX                0
                130     POP_TOP                         
                132     RETURN_VALUE                    
            [Exception Table]
                36 to 72 -> 92 [0] 
                92 to 114 -> 114 [1] lasti
        'FilePng'
        [Code]
            File Name: <frozen multithon.tl.types.storage>
            Object Name: FileUnknown
            Qualified Name: FileUnknown
            Arg Count: 0
            Pos Only Arg Count: 0
            KW Only Arg Count: 0
            Stack Size: 5
            Flags: 0x20000000 (CO_PYARMOR_OBFUSCATED)
            [Names]
                '__name__'
                '__module__'
                '__qualname__'
                '__assert_armored__'
                'CONSTRUCTOR_ID'
                'SUBCLASS_OF_ID'
                'to_dict'
                '_bytes'
                'classmethod'
                'from_reader'
            [Locals+Names]
            [Constants]
                'FileUnknown'
                '__pyarmor_assert_41361__'
                '__pyarmor_enter_41362__'
                b'<COAddr>\x07\x00\x00":\x00\x00\x00\x00\x00\x00\x00\x00\x00\x00\x00\x00\x00\x00\x00'
                0xAA963B05
                0xF3A1E6F3
                [Code]
                    File Name: <frozen multithon.tl.types.storage>
                    Object Name: to_dict
                    Qualified Name: FileUnknown.to_dict
                    Arg Count: 1
                    Pos Only Arg Count: 0
                    KW Only Arg Count: 0
                    Stack Size: 5
                    Flags: 0x20000003 (CO_OPTIMIZED | CO_NEWLOCALS | CO_PYARMOR_OBFUSCATED)
                    [Names]
                    [Locals+Names]
                        'self'
                        '__assert_armored__'
                    [Constants]
                        None
                        '__pyarmor_assert_41364__'
                        '__pyarmor_enter_41365__'
                        b'<COAddr>\x05\x00\x00\x1a(\x00\x00\x00\x00\x00\x00\x00\x00\x00\x00\x00\x00\x00\x00\x00'
                        '_'
                        'FileUnknown'   # b'\x81\xc4\x11\x1f6\xcf\xb0\xd9\x15\xf5\x1a\xce'
                        '__pyarmor_exit_41366__'
                    [Disassembly]
                        0       NOP                             
                        2       NOP                             
                        4       PUSH_NULL                       
                        6       LOAD_CONST                      2: '__pyarmor_enter_41365__'
                        8       LOAD_CONST                      3: b'<COAddr>\x05\x00\x00\x1a(\x00\x00\x00\x00\x00\x00\x00\x00\x00\x00\x00\x00\x00\x00\x00'
                        10      BUILD_TUPLE                     1
                        12      CALL_FUNCTION_EX                0
                        14      POP_TOP                         
                        16      RESUME                          0
                        18      NOP                             
                        20      NOP                             
                        22      NOP                             
                        24      NOP                             
                        26      NOP                             
                        28      LOAD_CONST                      4: '_'
                        30      PUSH_NULL                       
                        32      LOAD_CONST                      1: '__pyarmor_assert_41364__'
                        34      LOAD_CONST                      5: 'FileUnknown'   # b'\x81\xc4\x11\x1f6\xcf\xb0\xd9\x15\xf5\x1a\xce'
                        36      CALL                            1
                        44      BUILD_MAP                       1
                        46      NOP                             
                        48      NOP                             
                        50      NOP                             
                        52      JUMP_FORWARD                    20 (to 94)
                        54      CALL                            1
                        62      POP_TOP                         
                        64      RETURN_VALUE                    
                        66      PUSH_EXC_INFO                   
                        68      PUSH_NULL                       
                        70      LOAD_CONST                      6: '__pyarmor_exit_41366__'
                        72      NOP                             
                        74      LOAD_CONST                      3: b'<COAddr>\x05\x00\x00\x1a(\x00\x00\x00\x00\x00\x00\x00\x00\x00\x00\x00\x00\x00\x00\x00'
                        76      CALL                            1
                        84      POP_TOP                         
                        86      RERAISE                         0
                        88      COPY                            3
                        90      POP_EXCEPT                      
                        92      RERAISE                         1
                        94      PUSH_NULL                       
                        96      LOAD_CONST                      6: '__pyarmor_exit_41366__'
                        98      LOAD_CONST                      3: b'<COAddr>\x05\x00\x00\x1a(\x00\x00\x00\x00\x00\x00\x00\x00\x00\x00\x00\x00\x00\x00\x00'
                        100     BUILD_TUPLE                     1
                        102     CALL_FUNCTION_EX                0
                        104     POP_TOP                         
                        106     RETURN_VALUE                    
                    [Exception Table]
                        28 to 46 -> 66 [0] 
                        66 to 88 -> 88 [1] lasti
                [Code]
                    File Name: <frozen multithon.tl.types.storage>
                    Object Name: _bytes
                    Qualified Name: FileUnknown._bytes
                    Arg Count: 1
                    Pos Only Arg Count: 0
                    KW Only Arg Count: 0
                    Stack Size: 5
                    Flags: 0x20000003 (CO_OPTIMIZED | CO_NEWLOCALS | CO_PYARMOR_OBFUSCATED)
                    [Names]
                        'join'
                    [Locals+Names]
                        'self'
                        '__assert_armored__'
                    [Constants]
                        None
                        '__pyarmor_assert_41367__'
                        '__pyarmor_enter_41368__'
                        b'<COAddr>\x05\x00\x00\x1a6\x00\x00\x00\x00\x00\x00\x00\x00\x00\x00\x00\x00\x00\x00\x00'
                        b''
                        (
                            b'\x05;\x96\xaa'
                        )
                        '__pyarmor_exit_41369__'
                    [Disassembly]
                        0       NOP                             
                        2       NOP                             
                        4       PUSH_NULL                       
                        6       LOAD_CONST                      2: '__pyarmor_enter_41368__'
                        8       LOAD_CONST                      3: b'<COAddr>\x05\x00\x00\x1a6\x00\x00\x00\x00\x00\x00\x00\x00\x00\x00\x00\x00\x00\x00\x00'
                        10      BUILD_TUPLE                     1
                        12      CALL_FUNCTION_EX                0
                        14      POP_TOP                         
                        16      RESUME                          0
                        18      NOP                             
                        20      NOP                             
                        22      NOP                             
                        24      NOP                             
                        26      NOP                             
                        28      LOAD_CONST                      4: b''
                        30      LOAD_ATTR                       1: join
                        50      LOAD_CONST                      5: (b'\x05;\x96\xaa',)
                        52      CALL                            1
                        60      NOP                             
                        62      NOP                             
                        64      NOP                             
                        66      JUMP_FORWARD                    20 (to 108)
                        68      CALL                            1
                        76      POP_TOP                         
                        78      RETURN_VALUE                    
                        80      PUSH_EXC_INFO                   
                        82      PUSH_NULL                       
                        84      LOAD_CONST                      6: '__pyarmor_exit_41369__'
                        86      NOP                             
                        88      LOAD_CONST                      3: b'<COAddr>\x05\x00\x00\x1a6\x00\x00\x00\x00\x00\x00\x00\x00\x00\x00\x00\x00\x00\x00\x00'
                        90      CALL                            1
                        98      POP_TOP                         
                        100     RERAISE                         0
                        102     COPY                            3
                        104     POP_EXCEPT                      
                        106     RERAISE                         1
                        108     PUSH_NULL                       
                        110     LOAD_CONST                      6: '__pyarmor_exit_41369__'
                        112     LOAD_CONST                      3: b'<COAddr>\x05\x00\x00\x1a6\x00\x00\x00\x00\x00\x00\x00\x00\x00\x00\x00\x00\x00\x00\x00'
                        114     BUILD_TUPLE                     1
                        116     CALL_FUNCTION_EX                0
                        118     POP_TOP                         
                        120     RETURN_VALUE                    
                    [Exception Table]
                        28 to 60 -> 80 [0] 
                        80 to 102 -> 102 [1] lasti
                [Code]
                    File Name: <frozen multithon.tl.types.storage>
                    Object Name: from_reader
                    Qualified Name: FileUnknown.from_reader
                    Arg Count: 2
                    Pos Only Arg Count: 0
                    KW Only Arg Count: 0
                    Stack Size: 5
                    Flags: 0x20000003 (CO_OPTIMIZED | CO_NEWLOCALS | CO_PYARMOR_OBFUSCATED)
                    [Names]
                    [Locals+Names]
                        'cls'
                        'reader'
                        '__assert_armored__'
                    [Constants]
                        None
                        '__pyarmor_assert_41370__'
                        '__pyarmor_enter_41371__'
                        b'<COAddr>\x05\x00\x00\x1a"\x00\x00\x00\x00\x00\x00\x00\x00\x00\x00\x00\x00\x00\x00\x00'
                        '__pyarmor_exit_41372__'
                    [Disassembly]
                        0       NOP                             
                        2       NOP                             
                        4       PUSH_NULL                       
                        6       LOAD_CONST                      2: '__pyarmor_enter_41371__'
                        8       LOAD_CONST                      3: b'<COAddr>\x05\x00\x00\x1a"\x00\x00\x00\x00\x00\x00\x00\x00\x00\x00\x00\x00\x00\x00\x00'
                        10      BUILD_TUPLE                     1
                        12      CALL_FUNCTION_EX                0
                        14      POP_TOP                         
                        16      RESUME                          0
                        18      NOP                             
                        20      NOP                             
                        22      NOP                             
                        24      NOP                             
                        26      NOP                             
                        28      PUSH_NULL                       
                        30      LOAD_FAST                       0: cls
                        32      CALL                            0
                        40      NOP                             
                        42      NOP                             
                        44      NOP                             
                        46      JUMP_FORWARD                    20 (to 88)
                        48      CALL                            1
                        56      POP_TOP                         
                        58      RETURN_VALUE                    
                        60      PUSH_EXC_INFO                   
                        62      PUSH_NULL                       
                        64      LOAD_CONST                      4: '__pyarmor_exit_41372__'
                        66      NOP                             
                        68      LOAD_CONST                      3: b'<COAddr>\x05\x00\x00\x1a"\x00\x00\x00\x00\x00\x00\x00\x00\x00\x00\x00\x00\x00\x00\x00'
                        70      CALL                            1
                        78      POP_TOP                         
                        80      RERAISE                         0
                        82      COPY                            3
                        84      POP_EXCEPT                      
                        86      RERAISE                         1
                        88      PUSH_NULL                       
                        90      LOAD_CONST                      4: '__pyarmor_exit_41372__'
                        92      LOAD_CONST                      3: b'<COAddr>\x05\x00\x00\x1a"\x00\x00\x00\x00\x00\x00\x00\x00\x00\x00\x00\x00\x00\x00\x00'
                        94      BUILD_TUPLE                     1
                        96      CALL_FUNCTION_EX                0
                        98      POP_TOP                         
                        100     RETURN_VALUE                    
                    [Exception Table]
                        28 to 40 -> 60 [0] 
                        60 to 82 -> 82 [1] lasti
                '__pyarmor_exit_41363__'
                None
            [Disassembly]
                0       NOP                             
                2       LOAD_NAME                       0: __name__
                4       STORE_NAME                      1: __module__
                6       LOAD_CONST                      0: 'FileUnknown'
                8       STORE_NAME                      2: __qualname__
                10      NOP                             
                12      PUSH_NULL                       
                14      LOAD_CONST                      2: '__pyarmor_enter_41362__'
                16      LOAD_CONST                      3: b'<COAddr>\x07\x00\x00":\x00\x00\x00\x00\x00\x00\x00\x00\x00\x00\x00\x00\x00\x00\x00'
                18      BUILD_TUPLE                     1
                20      CALL_FUNCTION_EX                0
                22      POP_TOP                         
                24      RESUME                          0
                26      NOP                             
                28      NOP                             
                30      NOP                             
                32      NOP                             
                34      NOP                             
                36      LOAD_CONST                      4: 0xAA963B05
                38      STORE_NAME                      4: CONSTRUCTOR_ID
                40      LOAD_CONST                      5: 0xF3A1E6F3
                42      STORE_NAME                      5: SUBCLASS_OF_ID
                44      LOAD_CONST                      6: <CODE> to_dict
                46      MAKE_FUNCTION                   0
                48      STORE_NAME                      6: to_dict
                50      LOAD_CONST                      7: <CODE> _bytes
                52      MAKE_FUNCTION                   0
                54      STORE_NAME                      7: _bytes
                56      LOAD_NAME                       8: classmethod
                58      LOAD_CONST                      8: <CODE> from_reader
                60      MAKE_FUNCTION                   0
                62      CALL                            0
                70      STORE_NAME                      9: from_reader
                72      LOAD_CONST                      10: None
                74      NOP                             
                76      NOP                             
                78      NOP                             
                80      JUMP_FORWARD                    19 (to 120)
                88      POP_TOP                         
                90      RETURN_CONST                    10: None
                92      PUSH_EXC_INFO                   
                94      PUSH_NULL                       
                96      LOAD_CONST                      9: '__pyarmor_exit_41363__'
                98      NOP                             
                100     LOAD_CONST                      3: b'<COAddr>\x07\x00\x00":\x00\x00\x00\x00\x00\x00\x00\x00\x00\x00\x00\x00\x00\x00\x00'
                102     CALL                            1
                110     POP_TOP                         
                112     RERAISE                         0
                114     COPY                            3
                116     POP_EXCEPT                      
                118     RERAISE                         1
                120     PUSH_NULL                       
                122     LOAD_CONST                      9: '__pyarmor_exit_41363__'
                124     LOAD_CONST                      3: b'<COAddr>\x07\x00\x00":\x00\x00\x00\x00\x00\x00\x00\x00\x00\x00\x00\x00\x00\x00\x00'
                126     BUILD_TUPLE                     1
                128     CALL_FUNCTION_EX                0
                130     POP_TOP                         
                132     RETURN_VALUE                    
            [Exception Table]
                36 to 72 -> 92 [0] 
                92 to 114 -> 114 [1] lasti
        'FileUnknown'
        [Code]
            File Name: <frozen multithon.tl.types.storage>
            Object Name: FileWebp
            Qualified Name: FileWebp
            Arg Count: 0
            Pos Only Arg Count: 0
            KW Only Arg Count: 0
            Stack Size: 5
            Flags: 0x20000000 (CO_PYARMOR_OBFUSCATED)
            [Names]
                '__name__'
                '__module__'
                '__qualname__'
                '__assert_armored__'
                'CONSTRUCTOR_ID'
                'SUBCLASS_OF_ID'
                'to_dict'
                '_bytes'
                'classmethod'
                'from_reader'
            [Locals+Names]
            [Constants]
                'FileWebp'
                '__pyarmor_assert_41373__'
                '__pyarmor_enter_41374__'
                b'<COAddr>\x07\x00\x00":\x00\x00\x00\x00\x00\x00\x00\x00\x00\x00\x00\x00\x00\x00\x00'
                276907596
                0xF3A1E6F3
                [Code]
                    File Name: <frozen multithon.tl.types.storage>
                    Object Name: to_dict
                    Qualified Name: FileWebp.to_dict
                    Arg Count: 1
                    Pos Only Arg Count: 0
                    KW Only Arg Count: 0
                    Stack Size: 5
                    Flags: 0x20000003 (CO_OPTIMIZED | CO_NEWLOCALS | CO_PYARMOR_OBFUSCATED)
                    [Names]
                    [Locals+Names]
                        'self'
                        '__assert_armored__'
                    [Constants]
                        None
                        '__pyarmor_assert_41376__'
                        '__pyarmor_enter_41377__'
                        b'<COAddr>\x05\x00\x00\x1a\x1c\x00\x00\x00\x00\x00\x00\x00\x00\x00\x00\x00\x00\x00\x00\x00'
                        '_'
                        'FileWebp'
                        '__pyarmor_exit_41378__'
                    [Disassembly]
                        0       NOP                             
                        2       NOP                             
                        4       PUSH_NULL                       
                        6       LOAD_CONST                      2: '__pyarmor_enter_41377__'
                        8       LOAD_CONST                      3: b'<COAddr>\x05\x00\x00\x1a\x1c\x00\x00\x00\x00\x00\x00\x00\x00\x00\x00\x00\x00\x00\x00\x00'
                        10      BUILD_TUPLE                     1
                        12      CALL_FUNCTION_EX                0
                        14      POP_TOP                         
                        16      RESUME                          0
                        18      NOP                             
                        20      NOP                             
                        22      NOP                             
                        24      NOP                             
                        26      NOP                             
                        28      LOAD_CONST                      4: '_'
                        30      LOAD_CONST                      5: 'FileWebp'
                        32      BUILD_MAP                       1
                        34      NOP                             
                        36      NOP                             
                        38      NOP                             
                        40      JUMP_FORWARD                    20 (to 82)
                        42      CALL                            1
                        50      POP_TOP                         
                        52      RETURN_VALUE                    
                        54      PUSH_EXC_INFO                   
                        56      PUSH_NULL                       
                        58      LOAD_CONST                      6: '__pyarmor_exit_41378__'
                        60      NOP                             
                        62      LOAD_CONST                      3: b'<COAddr>\x05\x00\x00\x1a\x1c\x00\x00\x00\x00\x00\x00\x00\x00\x00\x00\x00\x00\x00\x00\x00'
                        64      CALL                            1
                        72      POP_TOP                         
                        74      RERAISE                         0
                        76      COPY                            3
                        78      POP_EXCEPT                      
                        80      RERAISE                         1
                        82      PUSH_NULL                       
                        84      LOAD_CONST                      6: '__pyarmor_exit_41378__'
                        86      LOAD_CONST                      3: b'<COAddr>\x05\x00\x00\x1a\x1c\x00\x00\x00\x00\x00\x00\x00\x00\x00\x00\x00\x00\x00\x00\x00'
                        88      BUILD_TUPLE                     1
                        90      CALL_FUNCTION_EX                0
                        92      POP_TOP                         
                        94      RETURN_VALUE                    
                    [Exception Table]
                        28 to 34 -> 54 [0] 
                        54 to 76 -> 76 [1] lasti
                [Code]
                    File Name: <frozen multithon.tl.types.storage>
                    Object Name: _bytes
                    Qualified Name: FileWebp._bytes
                    Arg Count: 1
                    Pos Only Arg Count: 0
                    KW Only Arg Count: 0
                    Stack Size: 5
                    Flags: 0x20000003 (CO_OPTIMIZED | CO_NEWLOCALS | CO_PYARMOR_OBFUSCATED)
                    [Names]
                        'join'
                    [Locals+Names]
                        'self'
                        '__assert_armored__'
                    [Constants]
                        None
                        '__pyarmor_assert_41379__'
                        '__pyarmor_enter_41380__'
                        b'<COAddr>\x07\x00\x00\x1a6\x00\x00\x00\x00\x00\x00\x00\x00\x00\x00\x00\x00\x00\x00\x00'
                        b''
                        (
                            b'LF\x81\x10'
                        )
                        '__pyarmor_exit_41381__'
                    [Disassembly]
                        0       NOP                             
                        2       NOP                             
                        4       PUSH_NULL                       
                        6       LOAD_CONST                      2: '__pyarmor_enter_41380__'
                        8       LOAD_CONST                      3: b'<COAddr>\x07\x00\x00\x1a6\x00\x00\x00\x00\x00\x00\x00\x00\x00\x00\x00\x00\x00\x00\x00'
                        10      BUILD_TUPLE                     1
                        12      CALL_FUNCTION_EX                0
                        14      POP_TOP                         
                        16      RESUME                          0
                        18      NOP                             
                        20      NOP                             
                        22      NOP                             
                        24      NOP                             
                        26      NOP                             
                        28      LOAD_CONST                      4: b''
                        30      LOAD_ATTR                       1: join
                        50      LOAD_CONST                      5: (b'LF\x81\x10',)
                        52      CALL                            1
                        60      NOP                             
                        62      NOP                             
                        64      NOP                             
                        66      JUMP_FORWARD                    20 (to 108)
                        68      CALL                            1
                        76      POP_TOP                         
                        78      RETURN_VALUE                    
                        80      PUSH_EXC_INFO                   
                        82      PUSH_NULL                       
                        84      LOAD_CONST                      6: '__pyarmor_exit_41381__'
                        86      NOP                             
                        88      LOAD_CONST                      3: b'<COAddr>\x07\x00\x00\x1a6\x00\x00\x00\x00\x00\x00\x00\x00\x00\x00\x00\x00\x00\x00\x00'
                        90      CALL                            1
                        98      POP_TOP                         
                        100     RERAISE                         0
                        102     COPY                            3
                        104     POP_EXCEPT                      
                        106     RERAISE                         1
                        108     PUSH_NULL                       
                        110     LOAD_CONST                      6: '__pyarmor_exit_41381__'
                        112     LOAD_CONST                      3: b'<COAddr>\x07\x00\x00\x1a6\x00\x00\x00\x00\x00\x00\x00\x00\x00\x00\x00\x00\x00\x00\x00'
                        114     BUILD_TUPLE                     1
                        116     CALL_FUNCTION_EX                0
                        118     POP_TOP                         
                        120     RETURN_VALUE                    
                    [Exception Table]
                        28 to 60 -> 80 [0] 
                        80 to 102 -> 102 [1] lasti
                [Code]
                    File Name: <frozen multithon.tl.types.storage>
                    Object Name: from_reader
                    Qualified Name: FileWebp.from_reader
                    Arg Count: 2
                    Pos Only Arg Count: 0
                    KW Only Arg Count: 0
                    Stack Size: 5
                    Flags: 0x20000003 (CO_OPTIMIZED | CO_NEWLOCALS | CO_PYARMOR_OBFUSCATED)
                    [Names]
                    [Locals+Names]
                        'cls'
                        'reader'
                        '__assert_armored__'
                    [Constants]
                        None
                        '__pyarmor_assert_41382__'
                        '__pyarmor_enter_41383__'
                        b'<COAddr>\x05\x00\x00\x1a"\x00\x00\x00\x00\x00\x00\x00\x00\x00\x00\x00\x00\x00\x00\x00'
                        '__pyarmor_exit_41384__'
                    [Disassembly]
                        0       NOP                             
                        2       NOP                             
                        4       PUSH_NULL                       
                        6       LOAD_CONST                      2: '__pyarmor_enter_41383__'
                        8       LOAD_CONST                      3: b'<COAddr>\x05\x00\x00\x1a"\x00\x00\x00\x00\x00\x00\x00\x00\x00\x00\x00\x00\x00\x00\x00'
                        10      BUILD_TUPLE                     1
                        12      CALL_FUNCTION_EX                0
                        14      POP_TOP                         
                        16      RESUME                          0
                        18      NOP                             
                        20      NOP                             
                        22      NOP                             
                        24      NOP                             
                        26      NOP                             
                        28      PUSH_NULL                       
                        30      LOAD_FAST                       0: cls
                        32      CALL                            0
                        40      NOP                             
                        42      NOP                             
                        44      NOP                             
                        46      JUMP_FORWARD                    20 (to 88)
                        48      CALL                            1
                        56      POP_TOP                         
                        58      RETURN_VALUE                    
                        60      PUSH_EXC_INFO                   
                        62      PUSH_NULL                       
                        64      LOAD_CONST                      4: '__pyarmor_exit_41384__'
                        66      NOP                             
                        68      LOAD_CONST                      3: b'<COAddr>\x05\x00\x00\x1a"\x00\x00\x00\x00\x00\x00\x00\x00\x00\x00\x00\x00\x00\x00\x00'
                        70      CALL                            1
                        78      POP_TOP                         
                        80      RERAISE                         0
                        82      COPY                            3
                        84      POP_EXCEPT                      
                        86      RERAISE                         1
                        88      PUSH_NULL                       
                        90      LOAD_CONST                      4: '__pyarmor_exit_41384__'
                        92      LOAD_CONST                      3: b'<COAddr>\x05\x00\x00\x1a"\x00\x00\x00\x00\x00\x00\x00\x00\x00\x00\x00\x00\x00\x00\x00'
                        94      BUILD_TUPLE                     1
                        96      CALL_FUNCTION_EX                0
                        98      POP_TOP                         
                        100     RETURN_VALUE                    
                    [Exception Table]
                        28 to 40 -> 60 [0] 
                        60 to 82 -> 82 [1] lasti
                '__pyarmor_exit_41375__'
                None
            [Disassembly]
                0       NOP                             
                2       LOAD_NAME                       0: __name__
                4       STORE_NAME                      1: __module__
                6       LOAD_CONST                      0: 'FileWebp'
                8       STORE_NAME                      2: __qualname__
                10      NOP                             
                12      PUSH_NULL                       
                14      LOAD_CONST                      2: '__pyarmor_enter_41374__'
                16      LOAD_CONST                      3: b'<COAddr>\x07\x00\x00":\x00\x00\x00\x00\x00\x00\x00\x00\x00\x00\x00\x00\x00\x00\x00'
                18      BUILD_TUPLE                     1
                20      CALL_FUNCTION_EX                0
                22      POP_TOP                         
                24      RESUME                          0
                26      NOP                             
                28      NOP                             
                30      NOP                             
                32      NOP                             
                34      NOP                             
                36      LOAD_CONST                      4: 276907596
                38      STORE_NAME                      4: CONSTRUCTOR_ID
                40      LOAD_CONST                      5: 0xF3A1E6F3
                42      STORE_NAME                      5: SUBCLASS_OF_ID
                44      LOAD_CONST                      6: <CODE> to_dict
                46      MAKE_FUNCTION                   0
                48      STORE_NAME                      6: to_dict
                50      LOAD_CONST                      7: <CODE> _bytes
                52      MAKE_FUNCTION                   0
                54      STORE_NAME                      7: _bytes
                56      LOAD_NAME                       8: classmethod
                58      LOAD_CONST                      8: <CODE> from_reader
                60      MAKE_FUNCTION                   0
                62      CALL                            0
                70      STORE_NAME                      9: from_reader
                72      LOAD_CONST                      10: None
                74      NOP                             
                76      NOP                             
                78      NOP                             
                80      JUMP_FORWARD                    19 (to 120)
                88      POP_TOP                         
                90      RETURN_CONST                    10: None
                92      PUSH_EXC_INFO                   
                94      PUSH_NULL                       
                96      LOAD_CONST                      9: '__pyarmor_exit_41375__'
                98      NOP                             
                100     LOAD_CONST                      3: b'<COAddr>\x07\x00\x00":\x00\x00\x00\x00\x00\x00\x00\x00\x00\x00\x00\x00\x00\x00\x00'
                102     CALL                            1
                110     POP_TOP                         
                112     RERAISE                         0
                114     COPY                            3
                116     POP_EXCEPT                      
                118     RERAISE                         1
                120     PUSH_NULL                       
                122     LOAD_CONST                      9: '__pyarmor_exit_41375__'
                124     LOAD_CONST                      3: b'<COAddr>\x07\x00\x00":\x00\x00\x00\x00\x00\x00\x00\x00\x00\x00\x00\x00\x00\x00\x00'
                126     BUILD_TUPLE                     1
                128     CALL_FUNCTION_EX                0
                130     POP_TOP                         
                132     RETURN_VALUE                    
            [Exception Table]
                36 to 72 -> 92 [0] 
                92 to 114 -> 114 [1] lasti
        'FileWebp'
        '__pyarmor_exit_41264__'
    [Disassembly]
        0       NOP                             
        2       NOP                             
        4       PUSH_NULL                       
        6       LOAD_CONST                      1: '__pyarmor_enter_41263__'
        8       LOAD_CONST                      2: b'<COAddr>\x07\x00\x00\x1a@\x01\x00\x00\x00\x00\x00\x00\x00\x00\x00\x00\x00\x00\x00\x00'
        10      BUILD_TUPLE                     1
        12      CALL_FUNCTION_EX                0
        14      POP_TOP                         
        16      RESUME                          0
        18      NOP                             
        20      NOP                             
        22      NOP                             
        24      NOP                             
        26      PUSH_NULL                       
        28      LOAD_CONST                      0: '__pyarmor_assert_41262__'
        30      LOAD_CONST                      3: "File generated by TLObjects' generator. All changes will be ERASED"   # b'\x81\xc4\x11\x1f6\xba\xb9\xd7\x15\xff\x1f\xc1x\xe9\xfc\xc5\rD\xfb\x93\x86\xe4L\xc6\x00l\xb7OG\xf1\x19\xe04W2\x0c\x8c\xc5\xa6`X\xc8\xf4Q\x9d\xdb\x07F9\xeaS\xe8\xc7g\x0f\xe1;\xab\x99\x18Xn\x03rdm!'
        32      CALL                            1
        40      POP_TOP                         
        42      LOAD_CONST                      4: 3
        44      LOAD_CONST                      5: ('TLObject',)
        46      IMPORT_NAME                     1: tl.tlobject
        48      IMPORT_FROM                     2: TLObject
        50      STORE_NAME                      2: TLObject
        52      POP_TOP                         
        54      LOAD_CONST                      6: 0
        56      LOAD_CONST                      7: ('Optional', 'List', 'Union', 'TYPE_CHECKING')
        58      IMPORT_NAME                     3: typing
        60      IMPORT_FROM                     4: Optional
        62      STORE_NAME                      4: Optional
        64      IMPORT_FROM                     5: List
        66      STORE_NAME                      5: List
        68      IMPORT_FROM                     6: Union
        70      STORE_NAME                      6: Union
        72      IMPORT_FROM                     7: TYPE_CHECKING
        74      STORE_NAME                      7: TYPE_CHECKING
        76      POP_TOP                         
        78      LOAD_CONST                      6: 0
        80      LOAD_CONST                      8: None
        82      IMPORT_NAME                     8: os
        84      STORE_NAME                      8: os
        86      LOAD_CONST                      6: 0
        88      LOAD_CONST                      8: None
        90      IMPORT_NAME                     9: struct
        92      STORE_NAME                      9: struct
        94      LOAD_CONST                      6: 0
        96      LOAD_CONST                      9: ('datetime',)
        98      IMPORT_NAME                     10: datetime
        100     IMPORT_FROM                     10: datetime
        102     STORE_NAME                      10: datetime
        104     POP_TOP                         
        106     PUSH_NULL                       
        108     LOAD_BUILD_CLASS                
        110     LOAD_CONST                      10: <CODE> FileGif
        112     MAKE_FUNCTION                   0
        114     LOAD_CONST                      11: 'FileGif'
        116     LOAD_NAME                       2: TLObject
        118     CALL                            3
        126     STORE_NAME                      11: FileGif
        128     PUSH_NULL                       
        130     LOAD_BUILD_CLASS                
        132     LOAD_CONST                      12: <CODE> FileJpeg
        134     MAKE_FUNCTION                   0
        136     LOAD_CONST                      13: 'FileJpeg'
        138     LOAD_NAME                       2: TLObject
        140     CALL                            3
        148     STORE_NAME                      12: FileJpeg
        150     PUSH_NULL                       
        152     LOAD_BUILD_CLASS                
        154     LOAD_CONST                      14: <CODE> FileMov
        156     MAKE_FUNCTION                   0
        158     LOAD_CONST                      15: 'FileMov'
        160     LOAD_NAME                       2: TLObject
        162     CALL                            3
        170     STORE_NAME                      13: FileMov
        172     PUSH_NULL                       
        174     LOAD_BUILD_CLASS                
        176     LOAD_CONST                      16: <CODE> FileMp3
        178     MAKE_FUNCTION                   0
        180     LOAD_CONST                      17: 'FileMp3'
        182     LOAD_NAME                       2: TLObject
        184     CALL                            3
        192     STORE_NAME                      14: FileMp3
        194     PUSH_NULL                       
        196     LOAD_BUILD_CLASS                
        198     LOAD_CONST                      18: <CODE> FileMp4
        200     MAKE_FUNCTION                   0
        202     LOAD_CONST                      19: 'FileMp4'
        204     LOAD_NAME                       2: TLObject
        206     CALL                            3
        214     STORE_NAME                      15: FileMp4
        216     PUSH_NULL                       
        218     LOAD_BUILD_CLASS                
        220     LOAD_CONST                      20: <CODE> FilePartial
        222     MAKE_FUNCTION                   0
        224     LOAD_CONST                      21: 'FilePartial'
        226     LOAD_NAME                       2: TLObject
        228     CALL                            3
        236     STORE_NAME                      16: FilePartial
        238     PUSH_NULL                       
        240     LOAD_BUILD_CLASS                
        242     LOAD_CONST                      22: <CODE> FilePdf
        244     MAKE_FUNCTION                   0
        246     LOAD_CONST                      23: 'FilePdf'
        248     LOAD_NAME                       2: TLObject
        250     CALL                            3
        258     STORE_NAME                      17: FilePdf
        260     PUSH_NULL                       
        262     LOAD_BUILD_CLASS                
        264     LOAD_CONST                      24: <CODE> FilePng
        266     MAKE_FUNCTION                   0
        268     LOAD_CONST                      25: 'FilePng'
        270     LOAD_NAME                       2: TLObject
        272     CALL                            3
        280     STORE_NAME                      18: FilePng
        282     PUSH_NULL                       
        284     LOAD_BUILD_CLASS                
        286     LOAD_CONST                      26: <CODE> FileUnknown
        288     MAKE_FUNCTION                   0
        290     LOAD_CONST                      27: 'FileUnknown'
        292     LOAD_NAME                       2: TLObject
        294     CALL                            3
        302     STORE_NAME                      19: FileUnknown
        304     PUSH_NULL                       
        306     LOAD_BUILD_CLASS                
        308     LOAD_CONST                      28: <CODE> FileWebp
        310     MAKE_FUNCTION                   0
        312     LOAD_CONST                      29: 'FileWebp'
        314     LOAD_NAME                       2: TLObject
        316     CALL                            3
        324     STORE_NAME                      20: FileWebp
        326     LOAD_CONST                      8: None
        328     NOP                             
        330     NOP                             
        332     NOP                             
        334     JUMP_FORWARD                    19 (to 374)
        342     POP_TOP                         
        344     RETURN_CONST                    8: None
        346     PUSH_EXC_INFO                   
        348     PUSH_NULL                       
        350     LOAD_CONST                      30: '__pyarmor_exit_41264__'
        352     NOP                             
        354     LOAD_CONST                      2: b'<COAddr>\x07\x00\x00\x1a@\x01\x00\x00\x00\x00\x00\x00\x00\x00\x00\x00\x00\x00\x00\x00'
        356     CALL                            1
        364     POP_TOP                         
        366     RERAISE                         0
        368     COPY                            3
        370     POP_EXCEPT                      
        372     RERAISE                         1
        374     PUSH_NULL                       
        376     LOAD_CONST                      30: '__pyarmor_exit_41264__'
        378     LOAD_CONST                      2: b'<COAddr>\x07\x00\x00\x1a@\x01\x00\x00\x00\x00\x00\x00\x00\x00\x00\x00\x00\x00\x00\x00'
        380     BUILD_TUPLE                     1
        382     CALL_FUNCTION_EX                0
        384     POP_TOP                         
        386     RETURN_VALUE                    
    [Exception Table]
        26 to 326 -> 346 [0] 
        346 to 368 -> 368 [1] lasti
