#decoded by lolz.live/mrpenny / t.me/zeus_jackpot
# ================================
# Примечания по Pyarmor:
# - Байт-код и объекты кода Pyarmor соответствуют стандартному Python, но присутствуют специальные вызовы функций среды выполнения (runtime) Pyarmor.
# - Вызовы строк — это не ошибки, а маркеры, которые обрабатываются Pyarmor во время выполнения.
#
# Руководство по декомпиляции (без среды выполнения):
# 1. Игнорируйте зашифрованные байты после `#`; используйте только строку до `#`.
# 2. Удалите "__pyarmor_enter_xxx__"(b"<COAddr>...") и "__pyarmor_leave_xxx__"(b"<COAddr>...") (пролог/эпилог).
# 3. "__pyarmor_assert_xxx__"(A) не является настоящим оператором assert.
#    - Если A — это имя или читаемая строка: замените на A.
#    - Если A — это (X, "Y"): замените на X.Y.
#    - Если A — это (X, "Y", Z): замените на X.Y = Z.
#    - В противном случае: выберите наиболее подходящую/логичную замену.
# 4. "__pyarmor_bcc_xxx__"(...) указывает на машинный (нативный) код; тело функции недоступно. Добавьте комментарий.
# ================================

[Code]
    File Name: <frozen multithon.tl.types.upload>
    Object Name: <module>
    Qualified Name: <module>
    Arg Count: 0
    Pos Only Arg Count: 0
    KW Only Arg Count: 0
    Stack Size: 5
    Flags: 0x20000000 (CO_PYARMOR_OBFUSCATED)
    [Names]
        '__assert_armored__'
        'tl.tlobject'
        'TLObject'
        'typing'
        'Optional'
        'List'
        'Union'
        'TYPE_CHECKING'
        'os'
        'struct'
        'datetime'
        'tl.types.storage'
        'TypeFileType'
        'tl.types'
        'TypeFileHash'
        'CdnFile'
        'CdnFileReuploadNeeded'
        'File'
        'FileCdnRedirect'
        'WebFile'
    [Locals+Names]
    [Constants]
        '__pyarmor_assert_41673__'
        '__pyarmor_enter_41674__'
        b'<COAddr>\x05\x00\x00\x1a\xee\x00\x00\x00\x00\x00\x00\x00\x00\x00\x00\x00\x00\x00\x00\x00'
        "File generated by TLObjects' generator. All changes will be ERASED"   # b'\x81\xc4\x11\x1f6\xba\xb9\xd7\x15\xff\x1f\xc1x\xe9\xfc\xc5\rD\xfb\x93\x86\xe4L\xc6\x00l\xb7OG\xf1\x19\xe04W2\x0c\x8c\xc5\xa6`X\xc8\xf4Q\x9d\xdb\x07F9\xeaS\xe8\xc7g\x0f\xe1;\xab\x99\x18Xn\x03rdm!'
        3
        (
            'TLObject'
        )
        0
        (
            'Optional'
            'List'
            'Union'
            'TYPE_CHECKING'
        )
        None
        (
            'datetime'
        )
        (
            'TypeFileType'
        )
        (
            'TypeFileHash'
        )
        [Code]
            File Name: <frozen multithon.tl.types.upload>
            Object Name: CdnFile
            Qualified Name: CdnFile
            Arg Count: 0
            Pos Only Arg Count: 0
            KW Only Arg Count: 0
            Stack Size: 5
            Flags: 0x20000000 (CO_PYARMOR_OBFUSCATED)
            [Names]
                '__name__'
                '__module__'
                '__qualname__'
                '__assert_armored__'
                'CONSTRUCTOR_ID'
                'SUBCLASS_OF_ID'
                'bytes'
                '__init__'
                'to_dict'
                '_bytes'
                'classmethod'
                'from_reader'
            [Locals+Names]
            [Constants]
                'CdnFile'
                '__pyarmor_assert_41676__'
                '__pyarmor_enter_41677__'
                b'<COAddr>\x05\x00\x00"F\x00\x00\x00\x00\x00\x00\x00\x00\x00\x00\x00\x00\x00\x00\x00'
                0xA99FCA4F
                0xF5CCF928
                'bytes'
                [Code]
                    File Name: <frozen multithon.tl.types.upload>
                    Object Name: __init__
                    Qualified Name: CdnFile.__init__
                    Arg Count: 2
                    Pos Only Arg Count: 0
                    KW Only Arg Count: 0
                    Stack Size: 5
                    Flags: 0x20000003 (CO_OPTIMIZED | CO_NEWLOCALS | CO_PYARMOR_OBFUSCATED)
                    [Names]
                        'bytes'
                    [Locals+Names]
                        'self'
                        'bytes'
                        '__assert_armored__'
                    [Constants]
                        '\n        Constructor for upload.CdnFile: Instance of either CdnFileReuploadNeeded, CdnFile.\n        '
                        '__pyarmor_assert_41679__'
                        '__pyarmor_enter_41680__'
                        b'<COAddr>\x07\x00\x00\x1a$\x00\x00\x00\x00\x00\x00\x00\x00\x00\x00\x00\x00\x00\x00\x00'
                        '__pyarmor_exit_41681__'
                        None
                    [Disassembly]
                        0       NOP                             
                        2       NOP                             
                        4       PUSH_NULL                       
                        6       LOAD_CONST                      2: '__pyarmor_enter_41680__'
                        8       LOAD_CONST                      3: b'<COAddr>\x07\x00\x00\x1a$\x00\x00\x00\x00\x00\x00\x00\x00\x00\x00\x00\x00\x00\x00\x00'
                        10      BUILD_TUPLE                     1
                        12      CALL_FUNCTION_EX                0
                        14      POP_TOP                         
                        16      RESUME                          0
                        18      NOP                             
                        20      NOP                             
                        22      NOP                             
                        24      NOP                             
                        26      NOP                             
                        28      LOAD_FAST                       1: bytes
                        30      LOAD_FAST                       0: self
                        32      STORE_ATTR                      0: bytes
                        42      LOAD_CONST                      5: None
                        44      NOP                             
                        46      NOP                             
                        48      NOP                             
                        50      JUMP_FORWARD                    19 (to 90)
                        58      POP_TOP                         
                        60      RETURN_CONST                    5: None
                        62      PUSH_EXC_INFO                   
                        64      PUSH_NULL                       
                        66      LOAD_CONST                      4: '__pyarmor_exit_41681__'
                        68      NOP                             
                        70      LOAD_CONST                      3: b'<COAddr>\x07\x00\x00\x1a$\x00\x00\x00\x00\x00\x00\x00\x00\x00\x00\x00\x00\x00\x00\x00'
                        72      CALL                            1
                        80      POP_TOP                         
                        82      RERAISE                         0
                        84      COPY                            3
                        86      POP_EXCEPT                      
                        88      RERAISE                         1
                        90      PUSH_NULL                       
                        92      LOAD_CONST                      4: '__pyarmor_exit_41681__'
                        94      LOAD_CONST                      3: b'<COAddr>\x07\x00\x00\x1a$\x00\x00\x00\x00\x00\x00\x00\x00\x00\x00\x00\x00\x00\x00\x00'
                        96      BUILD_TUPLE                     1
                        98      CALL_FUNCTION_EX                0
                        100     POP_TOP                         
                        102     RETURN_VALUE                    
                    [Exception Table]
                        28 to 42 -> 62 [0] 
                        62 to 84 -> 84 [1] lasti
                [Code]
                    File Name: <frozen multithon.tl.types.upload>
                    Object Name: to_dict
                    Qualified Name: CdnFile.to_dict
                    Arg Count: 1
                    Pos Only Arg Count: 0
                    KW Only Arg Count: 0
                    Stack Size: 5
                    Flags: 0x20000003 (CO_OPTIMIZED | CO_NEWLOCALS | CO_PYARMOR_OBFUSCATED)
                    [Names]
                        'bytes'
                    [Locals+Names]
                        'self'
                        '__assert_armored__'
                    [Constants]
                        None
                        '__pyarmor_assert_41682__'
                        '__pyarmor_enter_41683__'
                        b'<COAddr>\x05\x00\x00\x1a2\x00\x00\x00\x00\x00\x00\x00\x00\x00\x00\x00\x00\x00\x00\x00'
                        'CdnFile'
                        (
                            '_'
                            'bytes'
                        )
                        '__pyarmor_exit_41684__'
                    [Disassembly]
                        0       NOP                             
                        2       NOP                             
                        4       PUSH_NULL                       
                        6       LOAD_CONST                      2: '__pyarmor_enter_41683__'
                        8       LOAD_CONST                      3: b'<COAddr>\x05\x00\x00\x1a2\x00\x00\x00\x00\x00\x00\x00\x00\x00\x00\x00\x00\x00\x00\x00'
                        10      BUILD_TUPLE                     1
                        12      CALL_FUNCTION_EX                0
                        14      POP_TOP                         
                        16      RESUME                          0
                        18      NOP                             
                        20      NOP                             
                        22      NOP                             
                        24      NOP                             
                        26      NOP                             
                        28      LOAD_CONST                      4: 'CdnFile'
                        30      LOAD_FAST                       0: self
                        32      LOAD_ATTR                       0: bytes
                        52      LOAD_CONST                      5: ('_', 'bytes')
                        54      BUILD_CONST_KEY_MAP             2
                        56      NOP                             
                        58      NOP                             
                        60      NOP                             
                        62      JUMP_FORWARD                    20 (to 104)
                        64      CALL                            1
                        72      POP_TOP                         
                        74      RETURN_VALUE                    
                        76      PUSH_EXC_INFO                   
                        78      PUSH_NULL                       
                        80      LOAD_CONST                      6: '__pyarmor_exit_41684__'
                        82      NOP                             
                        84      LOAD_CONST                      3: b'<COAddr>\x05\x00\x00\x1a2\x00\x00\x00\x00\x00\x00\x00\x00\x00\x00\x00\x00\x00\x00\x00'
                        86      CALL                            1
                        94      POP_TOP                         
                        96      RERAISE                         0
                        98      COPY                            3
                        100     POP_EXCEPT                      
                        102     RERAISE                         1
                        104     PUSH_NULL                       
                        106     LOAD_CONST                      6: '__pyarmor_exit_41684__'
                        108     LOAD_CONST                      3: b'<COAddr>\x05\x00\x00\x1a2\x00\x00\x00\x00\x00\x00\x00\x00\x00\x00\x00\x00\x00\x00\x00'
                        110     BUILD_TUPLE                     1
                        112     CALL_FUNCTION_EX                0
                        114     POP_TOP                         
                        116     RETURN_VALUE                    
                    [Exception Table]
                        28 to 56 -> 76 [0] 
                        76 to 98 -> 98 [1] lasti
                [Code]
                    File Name: <frozen multithon.tl.types.upload>
                    Object Name: _bytes
                    Qualified Name: CdnFile._bytes
                    Arg Count: 1
                    Pos Only Arg Count: 0
                    KW Only Arg Count: 0
                    Stack Size: 6
                    Flags: 0x20000003 (CO_OPTIMIZED | CO_NEWLOCALS | CO_PYARMOR_OBFUSCATED)
                    [Names]
                        'join'
                        'serialize_bytes'
                        'bytes'
                    [Locals+Names]
                        'self'
                        '__assert_armored__'
                    [Constants]
                        None
                        '__pyarmor_assert_41685__'
                        '__pyarmor_enter_41686__'
                        b'<COAddr>\x07\x00\x00\x1al\x00\x00\x00\x00\x00\x00\x00\x00\x00\x00\x00\x00\x00\x00\x00'
                        b''
                        b'O\xca\x9f\xa9'
                        '__pyarmor_exit_41687__'
                    [Disassembly]
                        0       NOP                             
                        2       NOP                             
                        4       PUSH_NULL                       
                        6       LOAD_CONST                      2: '__pyarmor_enter_41686__'
                        8       LOAD_CONST                      3: b'<COAddr>\x07\x00\x00\x1al\x00\x00\x00\x00\x00\x00\x00\x00\x00\x00\x00\x00\x00\x00\x00'
                        10      BUILD_TUPLE                     1
                        12      CALL_FUNCTION_EX                0
                        14      POP_TOP                         
                        16      RESUME                          0
                        18      NOP                             
                        20      NOP                             
                        22      NOP                             
                        24      NOP                             
                        26      NOP                             
                        28      LOAD_CONST                      4: b''
                        30      LOAD_ATTR                       1: join
                        50      LOAD_CONST                      5: b'O\xca\x9f\xa9'
                        52      LOAD_FAST                       0: self
                        54      LOAD_ATTR                       3: serialize_bytes
                        74      LOAD_FAST                       0: self
                        76      LOAD_ATTR                       4: bytes
                        96      CALL                            1
                        104     BUILD_TUPLE                     2
                        106     CALL                            1
                        114     NOP                             
                        116     NOP                             
                        118     NOP                             
                        120     JUMP_FORWARD                    20 (to 162)
                        122     CALL                            1
                        130     POP_TOP                         
                        132     RETURN_VALUE                    
                        134     PUSH_EXC_INFO                   
                        136     PUSH_NULL                       
                        138     LOAD_CONST                      6: '__pyarmor_exit_41687__'
                        140     NOP                             
                        142     LOAD_CONST                      3: b'<COAddr>\x07\x00\x00\x1al\x00\x00\x00\x00\x00\x00\x00\x00\x00\x00\x00\x00\x00\x00\x00'
                        144     CALL                            1
                        152     POP_TOP                         
                        154     RERAISE                         0
                        156     COPY                            3
                        158     POP_EXCEPT                      
                        160     RERAISE                         1
                        162     PUSH_NULL                       
                        164     LOAD_CONST                      6: '__pyarmor_exit_41687__'
                        166     LOAD_CONST                      3: b'<COAddr>\x07\x00\x00\x1al\x00\x00\x00\x00\x00\x00\x00\x00\x00\x00\x00\x00\x00\x00\x00'
                        168     BUILD_TUPLE                     1
                        170     CALL_FUNCTION_EX                0
                        172     POP_TOP                         
                        174     RETURN_VALUE                    
                    [Exception Table]
                        28 to 114 -> 134 [0] 
                        134 to 156 -> 156 [1] lasti
                [Code]
                    File Name: <frozen multithon.tl.types.upload>
                    Object Name: from_reader
                    Qualified Name: CdnFile.from_reader
                    Arg Count: 2
                    Pos Only Arg Count: 0
                    KW Only Arg Count: 0
                    Stack Size: 5
                    Flags: 0x20000003 (CO_OPTIMIZED | CO_NEWLOCALS | CO_PYARMOR_OBFUSCATED)
                    [Names]
                        'tgread_bytes'
                    [Locals+Names]
                        'cls'
                        'reader'
                        '__assert_armored__'
                        '_var_var_0'
                    [Constants]
                        None
                        '__pyarmor_assert_41688__'
                        '__pyarmor_enter_41689__'
                        b'<COAddr>\x07\x00\x00\x1aF\x00\x00\x00\x00\x00\x00\x00\x00\x00\x00\x00\x00\x00\x00\x00'
                        (
                            'bytes'
                        )
                        '__pyarmor_exit_41690__'
                    [Disassembly]
                        0       NOP                             
                        2       NOP                             
                        4       PUSH_NULL                       
                        6       LOAD_CONST                      2: '__pyarmor_enter_41689__'
                        8       LOAD_CONST                      3: b'<COAddr>\x07\x00\x00\x1aF\x00\x00\x00\x00\x00\x00\x00\x00\x00\x00\x00\x00\x00\x00\x00'
                        10      BUILD_TUPLE                     1
                        12      CALL_FUNCTION_EX                0
                        14      POP_TOP                         
                        16      RESUME                          0
                        18      NOP                             
                        20      NOP                             
                        22      NOP                             
                        24      NOP                             
                        26      NOP                             
                        28      LOAD_FAST                       1: reader
                        30      LOAD_ATTR                       1: tgread_bytes
                        50      CALL                            0
                        58      STORE_FAST                      3: _var_var_0
                        60      PUSH_NULL                       
                        62      LOAD_FAST                       0: cls
                        64      LOAD_FAST                       3: _var_var_0
                        66      KW_NAMES                        4: ('bytes',)
                        68      CALL                            1
                        76      NOP                             
                        78      NOP                             
                        80      NOP                             
                        82      JUMP_FORWARD                    20 (to 124)
                        84      CALL                            1
                        92      POP_TOP                         
                        94      RETURN_VALUE                    
                        96      PUSH_EXC_INFO                   
                        98      PUSH_NULL                       
                        100     LOAD_CONST                      5: '__pyarmor_exit_41690__'
                        102     NOP                             
                        104     LOAD_CONST                      3: b'<COAddr>\x07\x00\x00\x1aF\x00\x00\x00\x00\x00\x00\x00\x00\x00\x00\x00\x00\x00\x00\x00'
                        106     CALL                            1
                        114     POP_TOP                         
                        116     RERAISE                         0
                        118     COPY                            3
                        120     POP_EXCEPT                      
                        122     RERAISE                         1
                        124     PUSH_NULL                       
                        126     LOAD_CONST                      5: '__pyarmor_exit_41690__'
                        128     LOAD_CONST                      3: b'<COAddr>\x07\x00\x00\x1aF\x00\x00\x00\x00\x00\x00\x00\x00\x00\x00\x00\x00\x00\x00\x00'
                        130     BUILD_TUPLE                     1
                        132     CALL_FUNCTION_EX                0
                        134     POP_TOP                         
                        136     RETURN_VALUE                    
                    [Exception Table]
                        28 to 76 -> 96 [0] 
                        96 to 118 -> 118 [1] lasti
                '__pyarmor_exit_41678__'
                None
            [Disassembly]
                0       NOP                             
                2       LOAD_NAME                       0: __name__
                4       STORE_NAME                      1: __module__
                6       LOAD_CONST                      0: 'CdnFile'
                8       STORE_NAME                      2: __qualname__
                10      NOP                             
                12      PUSH_NULL                       
                14      LOAD_CONST                      2: '__pyarmor_enter_41677__'
                16      LOAD_CONST                      3: b'<COAddr>\x05\x00\x00"F\x00\x00\x00\x00\x00\x00\x00\x00\x00\x00\x00\x00\x00\x00\x00'
                18      BUILD_TUPLE                     1
                20      CALL_FUNCTION_EX                0
                22      POP_TOP                         
                24      RESUME                          0
                26      NOP                             
                28      NOP                             
                30      NOP                             
                32      NOP                             
                34      NOP                             
                36      LOAD_CONST                      4: 0xA99FCA4F
                38      STORE_NAME                      4: CONSTRUCTOR_ID
                40      LOAD_CONST                      5: 0xF5CCF928
                42      STORE_NAME                      5: SUBCLASS_OF_ID
                44      LOAD_CONST                      6: 'bytes'
                46      LOAD_NAME                       6: bytes
                48      BUILD_TUPLE                     2
                50      LOAD_CONST                      7: <CODE> __init__
                52      MAKE_FUNCTION                   4
                54      STORE_NAME                      7: __init__
                56      LOAD_CONST                      8: <CODE> to_dict
                58      MAKE_FUNCTION                   0
                60      STORE_NAME                      8: to_dict
                62      LOAD_CONST                      9: <CODE> _bytes
                64      MAKE_FUNCTION                   0
                66      STORE_NAME                      9: _bytes
                68      LOAD_NAME                       10: classmethod
                70      LOAD_CONST                      10: <CODE> from_reader
                72      MAKE_FUNCTION                   0
                74      CALL                            0
                82      STORE_NAME                      11: from_reader
                84      LOAD_CONST                      12: None
                86      NOP                             
                88      NOP                             
                90      NOP                             
                92      JUMP_FORWARD                    19 (to 132)
                100     POP_TOP                         
                102     RETURN_CONST                    12: None
                104     PUSH_EXC_INFO                   
                106     PUSH_NULL                       
                108     LOAD_CONST                      11: '__pyarmor_exit_41678__'
                110     NOP                             
                112     LOAD_CONST                      3: b'<COAddr>\x05\x00\x00"F\x00\x00\x00\x00\x00\x00\x00\x00\x00\x00\x00\x00\x00\x00\x00'
                114     CALL                            1
                122     POP_TOP                         
                124     RERAISE                         0
                126     COPY                            3
                128     POP_EXCEPT                      
                130     RERAISE                         1
                132     PUSH_NULL                       
                134     LOAD_CONST                      11: '__pyarmor_exit_41678__'
                136     LOAD_CONST                      3: b'<COAddr>\x05\x00\x00"F\x00\x00\x00\x00\x00\x00\x00\x00\x00\x00\x00\x00\x00\x00\x00'
                138     BUILD_TUPLE                     1
                140     CALL_FUNCTION_EX                0
                142     POP_TOP                         
                144     RETURN_VALUE                    
            [Exception Table]
                36 to 84 -> 104 [0] 
                104 to 126 -> 126 [1] lasti
        'CdnFile'
        [Code]
            File Name: <frozen multithon.tl.types.upload>
            Object Name: CdnFileReuploadNeeded
            Qualified Name: CdnFileReuploadNeeded
            Arg Count: 0
            Pos Only Arg Count: 0
            KW Only Arg Count: 0
            Stack Size: 5
            Flags: 0x20000000 (CO_PYARMOR_OBFUSCATED)
            [Names]
                '__name__'
                '__module__'
                '__qualname__'
                '__assert_armored__'
                'CONSTRUCTOR_ID'
                'SUBCLASS_OF_ID'
                'bytes'
                '__init__'
                'to_dict'
                '_bytes'
                'classmethod'
                'from_reader'
            [Locals+Names]
            [Constants]
                'CdnFileReuploadNeeded'
                '__pyarmor_assert_41691__'
                '__pyarmor_enter_41692__'
                b'<COAddr>\x07\x00\x00"F\x00\x00\x00\x00\x00\x00\x00\x00\x00\x00\x00\x00\x00\x00\x00'
                0xEEA8E46E
                0xF5CCF928
                'request_token'
                [Code]
                    File Name: <frozen multithon.tl.types.upload>
                    Object Name: __init__
                    Qualified Name: CdnFileReuploadNeeded.__init__
                    Arg Count: 2
                    Pos Only Arg Count: 0
                    KW Only Arg Count: 0
                    Stack Size: 5
                    Flags: 0x20000003 (CO_OPTIMIZED | CO_NEWLOCALS | CO_PYARMOR_OBFUSCATED)
                    [Names]
                        'request_token'
                    [Locals+Names]
                        'self'
                        'request_token'
                        '__assert_armored__'
                    [Constants]
                        '\n        Constructor for upload.CdnFile: Instance of either CdnFileReuploadNeeded, CdnFile.\n        '
                        '__pyarmor_assert_41694__'
                        '__pyarmor_enter_41695__'
                        b'<COAddr>\x05\x00\x00\x1a$\x00\x00\x00\x00\x00\x00\x00\x00\x00\x00\x00\x00\x00\x00\x00'
                        '__pyarmor_exit_41696__'
                        None
                    [Disassembly]
                        0       NOP                             
                        2       NOP                             
                        4       PUSH_NULL                       
                        6       LOAD_CONST                      2: '__pyarmor_enter_41695__'
                        8       LOAD_CONST                      3: b'<COAddr>\x05\x00\x00\x1a$\x00\x00\x00\x00\x00\x00\x00\x00\x00\x00\x00\x00\x00\x00\x00'
                        10      BUILD_TUPLE                     1
                        12      CALL_FUNCTION_EX                0
                        14      POP_TOP                         
                        16      RESUME                          0
                        18      NOP                             
                        20      NOP                             
                        22      NOP                             
                        24      NOP                             
                        26      NOP                             
                        28      LOAD_FAST                       1: request_token
                        30      LOAD_FAST                       0: self
                        32      STORE_ATTR                      0: request_token
                        42      LOAD_CONST                      5: None
                        44      NOP                             
                        46      NOP                             
                        48      NOP                             
                        50      JUMP_FORWARD                    19 (to 90)
                        58      POP_TOP                         
                        60      RETURN_CONST                    5: None
                        62      PUSH_EXC_INFO                   
                        64      PUSH_NULL                       
                        66      LOAD_CONST                      4: '__pyarmor_exit_41696__'
                        68      NOP                             
                        70      LOAD_CONST                      3: b'<COAddr>\x05\x00\x00\x1a$\x00\x00\x00\x00\x00\x00\x00\x00\x00\x00\x00\x00\x00\x00\x00'
                        72      CALL                            1
                        80      POP_TOP                         
                        82      RERAISE                         0
                        84      COPY                            3
                        86      POP_EXCEPT                      
                        88      RERAISE                         1
                        90      PUSH_NULL                       
                        92      LOAD_CONST                      4: '__pyarmor_exit_41696__'
                        94      LOAD_CONST                      3: b'<COAddr>\x05\x00\x00\x1a$\x00\x00\x00\x00\x00\x00\x00\x00\x00\x00\x00\x00\x00\x00\x00'
                        96      BUILD_TUPLE                     1
                        98      CALL_FUNCTION_EX                0
                        100     POP_TOP                         
                        102     RETURN_VALUE                    
                    [Exception Table]
                        28 to 42 -> 62 [0] 
                        62 to 84 -> 84 [1] lasti
                [Code]
                    File Name: <frozen multithon.tl.types.upload>
                    Object Name: to_dict
                    Qualified Name: CdnFileReuploadNeeded.to_dict
                    Arg Count: 1
                    Pos Only Arg Count: 0
                    KW Only Arg Count: 0
                    Stack Size: 5
                    Flags: 0x20000003 (CO_OPTIMIZED | CO_NEWLOCALS | CO_PYARMOR_OBFUSCATED)
                    [Names]
                        'request_token'
                    [Locals+Names]
                        'self'
                        '__assert_armored__'
                    [Constants]
                        None
                        '__pyarmor_assert_41697__'
                        '__pyarmor_enter_41698__'
                        b'<COAddr>\x05\x00\x00\x1aL\x00\x00\x00\x00\x00\x00\x00\x00\x00\x00\x00\x00\x00\x00\x00'
                        '_'
                        'CdnFileReuploadNeeded'   # b'\x81\xc1\x1c\x1d\x15\xf3\xb2\xd7)\xff\x18\xd0`\xe3\xf9\x81!X\xbe\xa3\xaf\xcf'
                        'request_token'   # b'\x81\xf0\x1d\x02&\xff\xad\xc6$\xee\x02\xcbi\xe2'
                        '__pyarmor_exit_41699__'
                    [Disassembly]
                        0       NOP                             
                        2       NOP                             
                        4       PUSH_NULL                       
                        6       LOAD_CONST                      2: '__pyarmor_enter_41698__'
                        8       LOAD_CONST                      3: b'<COAddr>\x05\x00\x00\x1aL\x00\x00\x00\x00\x00\x00\x00\x00\x00\x00\x00\x00\x00\x00\x00'
                        10      BUILD_TUPLE                     1
                        12      CALL_FUNCTION_EX                0
                        14      POP_TOP                         
                        16      RESUME                          0
                        18      NOP                             
                        20      NOP                             
                        22      NOP                             
                        24      NOP                             
                        26      NOP                             
                        28      LOAD_CONST                      4: '_'
                        30      PUSH_NULL                       
                        32      LOAD_CONST                      1: '__pyarmor_assert_41697__'
                        34      LOAD_CONST                      5: 'CdnFileReuploadNeeded'   # b'\x81\xc1\x1c\x1d\x15\xf3\xb2\xd7)\xff\x18\xd0`\xe3\xf9\x81!X\xbe\xa3\xaf\xcf'
                        36      CALL                            1
                        44      PUSH_NULL                       
                        46      LOAD_CONST                      1: '__pyarmor_assert_41697__'
                        48      LOAD_CONST                      6: 'request_token'   # b'\x81\xf0\x1d\x02&\xff\xad\xc6$\xee\x02\xcbi\xe2'
                        50      CALL                            1
                        58      LOAD_FAST                       0: self
                        60      LOAD_ATTR                       0: request_token
                        80      BUILD_MAP                       2
                        82      NOP                             
                        84      NOP                             
                        86      NOP                             
                        88      JUMP_FORWARD                    20 (to 130)
                        90      CALL                            1
                        98      POP_TOP                         
                        100     RETURN_VALUE                    
                        102     PUSH_EXC_INFO                   
                        104     PUSH_NULL                       
                        106     LOAD_CONST                      7: '__pyarmor_exit_41699__'
                        108     NOP                             
                        110     LOAD_CONST                      3: b'<COAddr>\x05\x00\x00\x1aL\x00\x00\x00\x00\x00\x00\x00\x00\x00\x00\x00\x00\x00\x00\x00'
                        112     CALL                            1
                        120     POP_TOP                         
                        122     RERAISE                         0
                        124     COPY                            3
                        126     POP_EXCEPT                      
                        128     RERAISE                         1
                        130     PUSH_NULL                       
                        132     LOAD_CONST                      7: '__pyarmor_exit_41699__'
                        134     LOAD_CONST                      3: b'<COAddr>\x05\x00\x00\x1aL\x00\x00\x00\x00\x00\x00\x00\x00\x00\x00\x00\x00\x00\x00\x00'
                        136     BUILD_TUPLE                     1
                        138     CALL_FUNCTION_EX                0
                        140     POP_TOP                         
                        142     RETURN_VALUE                    
                    [Exception Table]
                        28 to 82 -> 102 [0] 
                        102 to 124 -> 124 [1] lasti
                [Code]
                    File Name: <frozen multithon.tl.types.upload>
                    Object Name: _bytes
                    Qualified Name: CdnFileReuploadNeeded._bytes
                    Arg Count: 1
                    Pos Only Arg Count: 0
                    KW Only Arg Count: 0
                    Stack Size: 6
                    Flags: 0x20000003 (CO_OPTIMIZED | CO_NEWLOCALS | CO_PYARMOR_OBFUSCATED)
                    [Names]
                        'join'
                        'serialize_bytes'
                        'request_token'
                    [Locals+Names]
                        'self'
                        '__assert_armored__'
                    [Constants]
                        None
                        '__pyarmor_assert_41700__'
                        '__pyarmor_enter_41701__'
                        b'<COAddr>\x07\x00\x00\x1al\x00\x00\x00\x00\x00\x00\x00\x00\x00\x00\x00\x00\x00\x00\x00'
                        b''
                        b'n\xe4\xa8\xee'
                        '__pyarmor_exit_41702__'
                    [Disassembly]
                        0       NOP                             
                        2       NOP                             
                        4       PUSH_NULL                       
                        6       LOAD_CONST                      2: '__pyarmor_enter_41701__'
                        8       LOAD_CONST                      3: b'<COAddr>\x07\x00\x00\x1al\x00\x00\x00\x00\x00\x00\x00\x00\x00\x00\x00\x00\x00\x00\x00'
                        10      BUILD_TUPLE                     1
                        12      CALL_FUNCTION_EX                0
                        14      POP_TOP                         
                        16      RESUME                          0
                        18      NOP                             
                        20      NOP                             
                        22      NOP                             
                        24      NOP                             
                        26      NOP                             
                        28      LOAD_CONST                      4: b''
                        30      LOAD_ATTR                       1: join
                        50      LOAD_CONST                      5: b'n\xe4\xa8\xee'
                        52      LOAD_FAST                       0: self
                        54      LOAD_ATTR                       3: serialize_bytes
                        74      LOAD_FAST                       0: self
                        76      LOAD_ATTR                       4: request_token
                        96      CALL                            1
                        104     BUILD_TUPLE                     2
                        106     CALL                            1
                        114     NOP                             
                        116     NOP                             
                        118     NOP                             
                        120     JUMP_FORWARD                    20 (to 162)
                        122     CALL                            1
                        130     POP_TOP                         
                        132     RETURN_VALUE                    
                        134     PUSH_EXC_INFO                   
                        136     PUSH_NULL                       
                        138     LOAD_CONST                      6: '__pyarmor_exit_41702__'
                        140     NOP                             
                        142     LOAD_CONST                      3: b'<COAddr>\x07\x00\x00\x1al\x00\x00\x00\x00\x00\x00\x00\x00\x00\x00\x00\x00\x00\x00\x00'
                        144     CALL                            1
                        152     POP_TOP                         
                        154     RERAISE                         0
                        156     COPY                            3
                        158     POP_EXCEPT                      
                        160     RERAISE                         1
                        162     PUSH_NULL                       
                        164     LOAD_CONST                      6: '__pyarmor_exit_41702__'
                        166     LOAD_CONST                      3: b'<COAddr>\x07\x00\x00\x1al\x00\x00\x00\x00\x00\x00\x00\x00\x00\x00\x00\x00\x00\x00\x00'
                        168     BUILD_TUPLE                     1
                        170     CALL_FUNCTION_EX                0
                        172     POP_TOP                         
                        174     RETURN_VALUE                    
                    [Exception Table]
                        28 to 114 -> 134 [0] 
                        134 to 156 -> 156 [1] lasti
                [Code]
                    File Name: <frozen multithon.tl.types.upload>
                    Object Name: from_reader
                    Qualified Name: CdnFileReuploadNeeded.from_reader
                    Arg Count: 2
                    Pos Only Arg Count: 0
                    KW Only Arg Count: 0
                    Stack Size: 5
                    Flags: 0x20000003 (CO_OPTIMIZED | CO_NEWLOCALS | CO_PYARMOR_OBFUSCATED)
                    [Names]
                        'tgread_bytes'
                    [Locals+Names]
                        'cls'
                        'reader'
                        '__assert_armored__'
                        '_var_var_1'
                    [Constants]
                        None
                        '__pyarmor_assert_41703__'
                        '__pyarmor_enter_41704__'
                        b'<COAddr>\x07\x00\x00\x1aF\x00\x00\x00\x00\x00\x00\x00\x00\x00\x00\x00\x00\x00\x00\x00'
                        (
                            'request_token'
                        )
                        '__pyarmor_exit_41705__'
                    [Disassembly]
                        0       NOP                             
                        2       NOP                             
                        4       PUSH_NULL                       
                        6       LOAD_CONST                      2: '__pyarmor_enter_41704__'
                        8       LOAD_CONST                      3: b'<COAddr>\x07\x00\x00\x1aF\x00\x00\x00\x00\x00\x00\x00\x00\x00\x00\x00\x00\x00\x00\x00'
                        10      BUILD_TUPLE                     1
                        12      CALL_FUNCTION_EX                0
                        14      POP_TOP                         
                        16      RESUME                          0
                        18      NOP                             
                        20      NOP                             
                        22      NOP                             
                        24      NOP                             
                        26      NOP                             
                        28      LOAD_FAST                       1: reader
                        30      LOAD_ATTR                       1: tgread_bytes
                        50      CALL                            0
                        58      STORE_FAST                      3: _var_var_1
                        60      PUSH_NULL                       
                        62      LOAD_FAST                       0: cls
                        64      LOAD_FAST                       3: _var_var_1
                        66      KW_NAMES                        4: ('request_token',)
                        68      CALL                            1
                        76      NOP                             
                        78      NOP                             
                        80      NOP                             
                        82      JUMP_FORWARD                    20 (to 124)
                        84      CALL                            1
                        92      POP_TOP                         
                        94      RETURN_VALUE                    
                        96      PUSH_EXC_INFO                   
                        98      PUSH_NULL                       
                        100     LOAD_CONST                      5: '__pyarmor_exit_41705__'
                        102     NOP                             
                        104     LOAD_CONST                      3: b'<COAddr>\x07\x00\x00\x1aF\x00\x00\x00\x00\x00\x00\x00\x00\x00\x00\x00\x00\x00\x00\x00'
                        106     CALL                            1
                        114     POP_TOP                         
                        116     RERAISE                         0
                        118     COPY                            3
                        120     POP_EXCEPT                      
                        122     RERAISE                         1
                        124     PUSH_NULL                       
                        126     LOAD_CONST                      5: '__pyarmor_exit_41705__'
                        128     LOAD_CONST                      3: b'<COAddr>\x07\x00\x00\x1aF\x00\x00\x00\x00\x00\x00\x00\x00\x00\x00\x00\x00\x00\x00\x00'
                        130     BUILD_TUPLE                     1
                        132     CALL_FUNCTION_EX                0
                        134     POP_TOP                         
                        136     RETURN_VALUE                    
                    [Exception Table]
                        28 to 76 -> 96 [0] 
                        96 to 118 -> 118 [1] lasti
                '__pyarmor_exit_41693__'
                None
            [Disassembly]
                0       NOP                             
                2       LOAD_NAME                       0: __name__
                4       STORE_NAME                      1: __module__
                6       LOAD_CONST                      0: 'CdnFileReuploadNeeded'
                8       STORE_NAME                      2: __qualname__
                10      NOP                             
                12      PUSH_NULL                       
                14      LOAD_CONST                      2: '__pyarmor_enter_41692__'
                16      LOAD_CONST                      3: b'<COAddr>\x07\x00\x00"F\x00\x00\x00\x00\x00\x00\x00\x00\x00\x00\x00\x00\x00\x00\x00'
                18      BUILD_TUPLE                     1
                20      CALL_FUNCTION_EX                0
                22      POP_TOP                         
                24      RESUME                          0
                26      NOP                             
                28      NOP                             
                30      NOP                             
                32      NOP                             
                34      NOP                             
                36      LOAD_CONST                      4: 0xEEA8E46E
                38      STORE_NAME                      4: CONSTRUCTOR_ID
                40      LOAD_CONST                      5: 0xF5CCF928
                42      STORE_NAME                      5: SUBCLASS_OF_ID
                44      LOAD_CONST                      6: 'request_token'
                46      LOAD_NAME                       6: bytes
                48      BUILD_TUPLE                     2
                50      LOAD_CONST                      7: <CODE> __init__
                52      MAKE_FUNCTION                   4
                54      STORE_NAME                      7: __init__
                56      LOAD_CONST                      8: <CODE> to_dict
                58      MAKE_FUNCTION                   0
                60      STORE_NAME                      8: to_dict
                62      LOAD_CONST                      9: <CODE> _bytes
                64      MAKE_FUNCTION                   0
                66      STORE_NAME                      9: _bytes
                68      LOAD_NAME                       10: classmethod
                70      LOAD_CONST                      10: <CODE> from_reader
                72      MAKE_FUNCTION                   0
                74      CALL                            0
                82      STORE_NAME                      11: from_reader
                84      LOAD_CONST                      12: None
                86      NOP                             
                88      NOP                             
                90      NOP                             
                92      JUMP_FORWARD                    19 (to 132)
                100     POP_TOP                         
                102     RETURN_CONST                    12: None
                104     PUSH_EXC_INFO                   
                106     PUSH_NULL                       
                108     LOAD_CONST                      11: '__pyarmor_exit_41693__'
                110     NOP                             
                112     LOAD_CONST                      3: b'<COAddr>\x07\x00\x00"F\x00\x00\x00\x00\x00\x00\x00\x00\x00\x00\x00\x00\x00\x00\x00'
                114     CALL                            1
                122     POP_TOP                         
                124     RERAISE                         0
                126     COPY                            3
                128     POP_EXCEPT                      
                130     RERAISE                         1
                132     PUSH_NULL                       
                134     LOAD_CONST                      11: '__pyarmor_exit_41693__'
                136     LOAD_CONST                      3: b'<COAddr>\x07\x00\x00"F\x00\x00\x00\x00\x00\x00\x00\x00\x00\x00\x00\x00\x00\x00\x00'
                138     BUILD_TUPLE                     1
                140     CALL_FUNCTION_EX                0
                142     POP_TOP                         
                144     RETURN_VALUE                    
            [Exception Table]
                36 to 84 -> 104 [0] 
                104 to 126 -> 126 [1] lasti
        'CdnFileReuploadNeeded'
        [Code]
            File Name: <frozen multithon.tl.types.upload>
            Object Name: File
            Qualified Name: File
            Arg Count: 0
            Pos Only Arg Count: 0
            KW Only Arg Count: 0
            Stack Size: 6
            Flags: 0x20000000 (CO_PYARMOR_OBFUSCATED)
            [Names]
                '__name__'
                '__module__'
                '__qualname__'
                '__assert_armored__'
                'CONSTRUCTOR_ID'
                'SUBCLASS_OF_ID'
                'int'
                'bytes'
                '__init__'
                'to_dict'
                '_bytes'
                'classmethod'
                'from_reader'
            [Locals+Names]
            [Constants]
                'File'
                '__pyarmor_assert_41706__'
                '__pyarmor_enter_41707__'
                b'<COAddr>\x05\x00\x00"Z\x00\x00\x00\x00\x00\x00\x00\x00\x00\x00\x00\x00\x00\x00\x00'
                157948117
                1822152488
                'type'
                'TypeFileType'   # b'\x81\xd6\x01\x036\xdc\xb7\xde\x1e\xce\x14\xd0i'
                'mtime'
                'bytes'
                [Code]
                    File Name: <frozen multithon.tl.types.upload>
                    Object Name: __init__
                    Qualified Name: File.__init__
                    Arg Count: 4
                    Pos Only Arg Count: 0
                    KW Only Arg Count: 0
                    Stack Size: 5
                    Flags: 0x20000003 (CO_OPTIMIZED | CO_NEWLOCALS | CO_PYARMOR_OBFUSCATED)
                    [Names]
                        'type'
                        'mtime'
                        'bytes'
                    [Locals+Names]
                        'self'
                        'type'
                        'mtime'
                        'bytes'
                        '__assert_armored__'
                    [Constants]
                        '\n        Constructor for upload.File: Instance of either File, FileCdnRedirect.\n        '
                        '__pyarmor_assert_41709__'
                        '__pyarmor_enter_41710__'
                        b'<COAddr>\x07\x00\x00\x1a@\x00\x00\x00\x00\x00\x00\x00\x00\x00\x00\x00\x00\x00\x00\x00'
                        '__pyarmor_exit_41711__'
                        None
                    [Disassembly]
                        0       NOP                             
                        2       NOP                             
                        4       PUSH_NULL                       
                        6       LOAD_CONST                      2: '__pyarmor_enter_41710__'
                        8       LOAD_CONST                      3: b'<COAddr>\x07\x00\x00\x1a@\x00\x00\x00\x00\x00\x00\x00\x00\x00\x00\x00\x00\x00\x00\x00'
                        10      BUILD_TUPLE                     1
                        12      CALL_FUNCTION_EX                0
                        14      POP_TOP                         
                        16      RESUME                          0
                        18      NOP                             
                        20      NOP                             
                        22      NOP                             
                        24      NOP                             
                        26      NOP                             
                        28      LOAD_FAST                       1: type
                        30      LOAD_FAST                       0: self
                        32      STORE_ATTR                      0: type
                        42      LOAD_FAST                       2: mtime
                        44      LOAD_FAST                       0: self
                        46      STORE_ATTR                      1: mtime
                        56      LOAD_FAST                       3: bytes
                        58      LOAD_FAST                       0: self
                        60      STORE_ATTR                      2: bytes
                        70      LOAD_CONST                      5: None
                        72      NOP                             
                        74      NOP                             
                        76      NOP                             
                        78      JUMP_FORWARD                    19 (to 118)
                        86      POP_TOP                         
                        88      RETURN_CONST                    5: None
                        90      PUSH_EXC_INFO                   
                        92      PUSH_NULL                       
                        94      LOAD_CONST                      4: '__pyarmor_exit_41711__'
                        96      NOP                             
                        98      LOAD_CONST                      3: b'<COAddr>\x07\x00\x00\x1a@\x00\x00\x00\x00\x00\x00\x00\x00\x00\x00\x00\x00\x00\x00\x00'
                        100     CALL                            1
                        108     POP_TOP                         
                        110     RERAISE                         0
                        112     COPY                            3
                        114     POP_EXCEPT                      
                        116     RERAISE                         1
                        118     PUSH_NULL                       
                        120     LOAD_CONST                      4: '__pyarmor_exit_41711__'
                        122     LOAD_CONST                      3: b'<COAddr>\x07\x00\x00\x1a@\x00\x00\x00\x00\x00\x00\x00\x00\x00\x00\x00\x00\x00\x00\x00'
                        124     BUILD_TUPLE                     1
                        126     CALL_FUNCTION_EX                0
                        128     POP_TOP                         
                        130     RETURN_VALUE                    
                    [Exception Table]
                        28 to 70 -> 90 [0] 
                        90 to 112 -> 112 [1] lasti
                [Code]
                    File Name: <frozen multithon.tl.types.upload>
                    Object Name: to_dict
                    Qualified Name: File.to_dict
                    Arg Count: 1
                    Pos Only Arg Count: 0
                    KW Only Arg Count: 0
                    Stack Size: 5
                    Flags: 0x20000003 (CO_OPTIMIZED | CO_NEWLOCALS | CO_PYARMOR_OBFUSCATED)
                    [Names]
                        'isinstance'
                        'type'
                        'TLObject'
                        'to_dict'
                        'mtime'
                        'bytes'
                    [Locals+Names]
                        'self'
                        '__assert_armored__'
                    [Constants]
                        None
                        '__pyarmor_assert_41712__'
                        '__pyarmor_enter_41713__'
                        b'<COAddr>\x05\x00\x00\x1a\xc6\x00\x00\x00\x00\x00\x00\x00\x00\x00\x00\x00\x00\x00\x00\x00'
                        'File'
                        (
                            '_'
                            'type'
                            'mtime'
                            'bytes'
                        )
                        '__pyarmor_exit_41714__'
                    [Disassembly]
                        0       NOP                             
                        2       NOP                             
                        4       PUSH_NULL                       
                        6       LOAD_CONST                      2: '__pyarmor_enter_41713__'
                        8       LOAD_CONST                      3: b'<COAddr>\x05\x00\x00\x1a\xc6\x00\x00\x00\x00\x00\x00\x00\x00\x00\x00\x00\x00\x00\x00\x00'
                        10      BUILD_TUPLE                     1
                        12      CALL_FUNCTION_EX                0
                        14      POP_TOP                         
                        16      RESUME                          0
                        18      NOP                             
                        20      NOP                             
                        22      NOP                             
                        24      NOP                             
                        26      NOP                             
                        28      LOAD_CONST                      4: 'File'
                        30      LOAD_GLOBAL                     1: NULL + isinstance
                        40      LOAD_FAST                       0: self
                        42      LOAD_ATTR                       2: type
                        62      LOAD_GLOBAL                     4: TLObject
                        72      CALL                            2
                        80      POP_JUMP_IF_FALSE               26 (to 134)
                        82      LOAD_FAST                       0: self
                        84      LOAD_ATTR                       2: type
                        104     LOAD_ATTR                       7: to_dict
                        124     CALL                            0
                        132     JUMP_FORWARD                    11 (to 156)
                        134     LOAD_FAST                       0: self
                        136     LOAD_ATTR                       2: type
                        156     LOAD_FAST                       0: self
                        158     LOAD_ATTR                       8: mtime
                        178     LOAD_FAST                       0: self
                        180     LOAD_ATTR                       10: bytes
                        200     LOAD_CONST                      5: ('_', 'type', 'mtime', 'bytes')
                        202     BUILD_CONST_KEY_MAP             4
                        204     NOP                             
                        206     NOP                             
                        208     NOP                             
                        210     JUMP_FORWARD                    20 (to 252)
                        212     CALL                            1
                        220     POP_TOP                         
                        222     RETURN_VALUE                    
                        224     PUSH_EXC_INFO                   
                        226     PUSH_NULL                       
                        228     LOAD_CONST                      6: '__pyarmor_exit_41714__'
                        230     NOP                             
                        232     LOAD_CONST                      3: b'<COAddr>\x05\x00\x00\x1a\xc6\x00\x00\x00\x00\x00\x00\x00\x00\x00\x00\x00\x00\x00\x00\x00'
                        234     CALL                            1
                        242     POP_TOP                         
                        244     RERAISE                         0
                        246     COPY                            3
                        248     POP_EXCEPT                      
                        250     RERAISE                         1
                        252     PUSH_NULL                       
                        254     LOAD_CONST                      6: '__pyarmor_exit_41714__'
                        256     LOAD_CONST                      3: b'<COAddr>\x05\x00\x00\x1a\xc6\x00\x00\x00\x00\x00\x00\x00\x00\x00\x00\x00\x00\x00\x00\x00'
                        258     BUILD_TUPLE                     1
                        260     CALL_FUNCTION_EX                0
                        262     POP_TOP                         
                        264     RETURN_VALUE                    
                    [Exception Table]
                        28 to 204 -> 224 [0] 
                        224 to 246 -> 246 [1] lasti
                [Code]
                    File Name: <frozen multithon.tl.types.upload>
                    Object Name: _bytes
                    Qualified Name: File._bytes
                    Arg Count: 1
                    Pos Only Arg Count: 0
                    KW Only Arg Count: 0
                    Stack Size: 8
                    Flags: 0x20000003 (CO_OPTIMIZED | CO_NEWLOCALS | CO_PYARMOR_OBFUSCATED)
                    [Names]
                        'join'
                        'type'
                        '_bytes'
                        'struct'
                        'pack'
                        'mtime'
                        'serialize_bytes'
                        'bytes'
                    [Locals+Names]
                        'self'
                        '__assert_armored__'
                    [Constants]
                        None
                        '__pyarmor_assert_41715__'
                        '__pyarmor_enter_41716__'
                        b'<COAddr>\x07\x00\x00\x1a\xdc\x00\x00\x00\x00\x00\x00\x00\x00\x00\x00\x00\x00\x00\x00\x00'
                        b''
                        b'\xd5\x18j\t'
                        '<i'
                        '__pyarmor_exit_41717__'
                    [Disassembly]
                        0       NOP                             
                        2       NOP                             
                        4       PUSH_NULL                       
                        6       LOAD_CONST                      2: '__pyarmor_enter_41716__'
                        8       LOAD_CONST                      3: b'<COAddr>\x07\x00\x00\x1a\xdc\x00\x00\x00\x00\x00\x00\x00\x00\x00\x00\x00\x00\x00\x00\x00'
                        10      BUILD_TUPLE                     1
                        12      CALL_FUNCTION_EX                0
                        14      POP_TOP                         
                        16      RESUME                          0
                        18      NOP                             
                        20      NOP                             
                        22      NOP                             
                        24      NOP                             
                        26      NOP                             
                        28      LOAD_CONST                      4: b''
                        30      LOAD_ATTR                       1: join
                        50      LOAD_CONST                      5: b'\xd5\x18j\t'
                        52      LOAD_FAST                       0: self
                        54      LOAD_ATTR                       2: type
                        74      LOAD_ATTR                       5: _bytes
                        94      CALL                            0
                        102     LOAD_GLOBAL                     7: NULL + struct
                        112     LOAD_ATTR                       8: pack
                        132     LOAD_CONST                      6: '<i'
                        134     LOAD_FAST                       0: self
                        136     LOAD_ATTR                       10: mtime
                        156     CALL                            2
                        164     LOAD_FAST                       0: self
                        166     LOAD_ATTR                       13: serialize_bytes
                        186     LOAD_FAST                       0: self
                        188     LOAD_ATTR                       14: bytes
                        208     CALL                            1
                        216     BUILD_TUPLE                     4
                        218     CALL                            1
                        226     NOP                             
                        228     NOP                             
                        230     NOP                             
                        232     JUMP_FORWARD                    20 (to 274)
                        234     CALL                            1
                        242     POP_TOP                         
                        244     RETURN_VALUE                    
                        246     PUSH_EXC_INFO                   
                        248     PUSH_NULL                       
                        250     LOAD_CONST                      7: '__pyarmor_exit_41717__'
                        252     NOP                             
                        254     LOAD_CONST                      3: b'<COAddr>\x07\x00\x00\x1a\xdc\x00\x00\x00\x00\x00\x00\x00\x00\x00\x00\x00\x00\x00\x00\x00'
                        256     CALL                            1
                        264     POP_TOP                         
                        266     RERAISE                         0
                        268     COPY                            3
                        270     POP_EXCEPT                      
                        272     RERAISE                         1
                        274     PUSH_NULL                       
                        276     LOAD_CONST                      7: '__pyarmor_exit_41717__'
                        278     LOAD_CONST                      3: b'<COAddr>\x07\x00\x00\x1a\xdc\x00\x00\x00\x00\x00\x00\x00\x00\x00\x00\x00\x00\x00\x00\x00'
                        280     BUILD_TUPLE                     1
                        282     CALL_FUNCTION_EX                0
                        284     POP_TOP                         
                        286     RETURN_VALUE                    
                    [Exception Table]
                        28 to 226 -> 246 [0] 
                        246 to 268 -> 268 [1] lasti
                [Code]
                    File Name: <frozen multithon.tl.types.upload>
                    Object Name: from_reader
                    Qualified Name: File.from_reader
                    Arg Count: 2
                    Pos Only Arg Count: 0
                    KW Only Arg Count: 0
                    Stack Size: 5
                    Flags: 0x20000003 (CO_OPTIMIZED | CO_NEWLOCALS | CO_PYARMOR_OBFUSCATED)
                    [Names]
                        'tgread_object'
                        'read_int'
                        'tgread_bytes'
                    [Locals+Names]
                        'cls'
                        'reader'
                        '__assert_armored__'
                        '_var_var_2'
                        '_var_var_3'
                        '_var_var_0'
                    [Constants]
                        None
                        '__pyarmor_assert_41718__'
                        '__pyarmor_enter_41719__'
                        b'<COAddr>\x07\x00\x00\x1a\x8a\x00\x00\x00\x00\x00\x00\x00\x00\x00\x00\x00\x00\x00\x00\x00'
                        (
                            'type'
                            'mtime'
                            'bytes'
                        )
                        '__pyarmor_exit_41720__'
                    [Disassembly]
                        0       NOP                             
                        2       NOP                             
                        4       PUSH_NULL                       
                        6       LOAD_CONST                      2: '__pyarmor_enter_41719__'
                        8       LOAD_CONST                      3: b'<COAddr>\x07\x00\x00\x1a\x8a\x00\x00\x00\x00\x00\x00\x00\x00\x00\x00\x00\x00\x00\x00\x00'
                        10      BUILD_TUPLE                     1
                        12      CALL_FUNCTION_EX                0
                        14      POP_TOP                         
                        16      RESUME                          0
                        18      NOP                             
                        20      NOP                             
                        22      NOP                             
                        24      NOP                             
                        26      NOP                             
                        28      LOAD_FAST                       1: reader
                        30      LOAD_ATTR                       1: tgread_object
                        50      CALL                            0
                        58      STORE_FAST                      3: _var_var_2
                        60      LOAD_FAST                       1: reader
                        62      LOAD_ATTR                       3: read_int
                        82      CALL                            0
                        90      STORE_FAST                      4: _var_var_3
                        92      LOAD_FAST                       1: reader
                        94      LOAD_ATTR                       5: tgread_bytes
                        114     CALL                            0
                        122     STORE_FAST                      5: _var_var_0
                        124     PUSH_NULL                       
                        126     LOAD_FAST                       0: cls
                        128     LOAD_FAST                       3: _var_var_2
                        130     LOAD_FAST                       4: _var_var_3
                        132     LOAD_FAST                       5: _var_var_0
                        134     KW_NAMES                        4: ('type', 'mtime', 'bytes')
                        136     CALL                            3
                        144     NOP                             
                        146     NOP                             
                        148     NOP                             
                        150     JUMP_FORWARD                    20 (to 192)
                        152     CALL                            1
                        160     POP_TOP                         
                        162     RETURN_VALUE                    
                        164     PUSH_EXC_INFO                   
                        166     PUSH_NULL                       
                        168     LOAD_CONST                      5: '__pyarmor_exit_41720__'
                        170     NOP                             
                        172     LOAD_CONST                      3: b'<COAddr>\x07\x00\x00\x1a\x8a\x00\x00\x00\x00\x00\x00\x00\x00\x00\x00\x00\x00\x00\x00\x00'
                        174     CALL                            1
                        182     POP_TOP                         
                        184     RERAISE                         0
                        186     COPY                            3
                        188     POP_EXCEPT                      
                        190     RERAISE                         1
                        192     PUSH_NULL                       
                        194     LOAD_CONST                      5: '__pyarmor_exit_41720__'
                        196     LOAD_CONST                      3: b'<COAddr>\x07\x00\x00\x1a\x8a\x00\x00\x00\x00\x00\x00\x00\x00\x00\x00\x00\x00\x00\x00\x00'
                        198     BUILD_TUPLE                     1
                        200     CALL_FUNCTION_EX                0
                        202     POP_TOP                         
                        204     RETURN_VALUE                    
                    [Exception Table]
                        28 to 144 -> 164 [0] 
                        164 to 186 -> 186 [1] lasti
                '__pyarmor_exit_41708__'
                None
            [Disassembly]
                0       NOP                             
                2       LOAD_NAME                       0: __name__
                4       STORE_NAME                      1: __module__
                6       LOAD_CONST                      0: 'File'
                8       STORE_NAME                      2: __qualname__
                10      NOP                             
                12      PUSH_NULL                       
                14      LOAD_CONST                      2: '__pyarmor_enter_41707__'
                16      LOAD_CONST                      3: b'<COAddr>\x05\x00\x00"Z\x00\x00\x00\x00\x00\x00\x00\x00\x00\x00\x00\x00\x00\x00\x00'
                18      BUILD_TUPLE                     1
                20      CALL_FUNCTION_EX                0
                22      POP_TOP                         
                24      RESUME                          0
                26      NOP                             
                28      NOP                             
                30      NOP                             
                32      NOP                             
                34      NOP                             
                36      LOAD_CONST                      4: 157948117
                38      STORE_NAME                      4: CONSTRUCTOR_ID
                40      LOAD_CONST                      5: 1822152488
                42      STORE_NAME                      5: SUBCLASS_OF_ID
                44      LOAD_CONST                      6: 'type'
                46      PUSH_NULL                       
                48      LOAD_CONST                      1: '__pyarmor_assert_41706__'
                50      LOAD_CONST                      7: 'TypeFileType'   # b'\x81\xd6\x01\x036\xdc\xb7\xde\x1e\xce\x14\xd0i'
                52      CALL                            1
                60      LOAD_CONST                      8: 'mtime'
                62      LOAD_NAME                       6: int
                64      LOAD_CONST                      9: 'bytes'
                66      LOAD_NAME                       7: bytes
                68      BUILD_TUPLE                     6
                70      LOAD_CONST                      10: <CODE> __init__
                72      MAKE_FUNCTION                   4
                74      STORE_NAME                      8: __init__
                76      LOAD_CONST                      11: <CODE> to_dict
                78      MAKE_FUNCTION                   0
                80      STORE_NAME                      9: to_dict
                82      LOAD_CONST                      12: <CODE> _bytes
                84      MAKE_FUNCTION                   0
                86      STORE_NAME                      10: _bytes
                88      LOAD_NAME                       11: classmethod
                90      LOAD_CONST                      13: <CODE> from_reader
                92      MAKE_FUNCTION                   0
                94      CALL                            0
                102     STORE_NAME                      12: from_reader
                104     LOAD_CONST                      15: None
                106     NOP                             
                108     NOP                             
                110     NOP                             
                112     JUMP_FORWARD                    19 (to 152)
                120     POP_TOP                         
                122     RETURN_CONST                    15: None
                124     PUSH_EXC_INFO                   
                126     PUSH_NULL                       
                128     LOAD_CONST                      14: '__pyarmor_exit_41708__'
                130     NOP                             
                132     LOAD_CONST                      3: b'<COAddr>\x05\x00\x00"Z\x00\x00\x00\x00\x00\x00\x00\x00\x00\x00\x00\x00\x00\x00\x00'
                134     CALL                            1
                142     POP_TOP                         
                144     RERAISE                         0
                146     COPY                            3
                148     POP_EXCEPT                      
                150     RERAISE                         1
                152     PUSH_NULL                       
                154     LOAD_CONST                      14: '__pyarmor_exit_41708__'
                156     LOAD_CONST                      3: b'<COAddr>\x05\x00\x00"Z\x00\x00\x00\x00\x00\x00\x00\x00\x00\x00\x00\x00\x00\x00\x00'
                158     BUILD_TUPLE                     1
                160     CALL_FUNCTION_EX                0
                162     POP_TOP                         
                164     RETURN_VALUE                    
            [Exception Table]
                36 to 104 -> 124 [0] 
                124 to 146 -> 146 [1] lasti
        'File'
        [Code]
            File Name: <frozen multithon.tl.types.upload>
            Object Name: FileCdnRedirect
            Qualified Name: FileCdnRedirect
            Arg Count: 0
            Pos Only Arg Count: 0
            KW Only Arg Count: 0
            Stack Size: 13
            Flags: 0x20000000 (CO_PYARMOR_OBFUSCATED)
            [Names]
                '__name__'
                '__module__'
                '__qualname__'
                '__assert_armored__'
                'CONSTRUCTOR_ID'
                'SUBCLASS_OF_ID'
                'int'
                'bytes'
                'List'
                '__init__'
                'to_dict'
                '_bytes'
                'classmethod'
                'from_reader'
            [Locals+Names]
            [Constants]
                'FileCdnRedirect'
                '__pyarmor_assert_41721__'
                '__pyarmor_enter_41722__'
                b'<COAddr>\x05\x00\x00"h\x00\x00\x00\x00\x00\x00\x00\x00\x00\x00\x00\x00\x00\x00\x00'
                0xF18CDA44
                1822152488
                'dc_id'
                'file_token'
                'encryption_key'
                'encryption_iv'
                'file_hashes'
                'TypeFileHash'   # b'\x81\xd6\x01\x036\xdc\xb7\xde\x1e\xd2\x0c\xd3d'
                [Code]
                    File Name: <frozen multithon.tl.types.upload>
                    Object Name: __init__
                    Qualified Name: FileCdnRedirect.__init__
                    Arg Count: 6
                    Pos Only Arg Count: 0
                    KW Only Arg Count: 0
                    Stack Size: 5
                    Flags: 0x20000003 (CO_OPTIMIZED | CO_NEWLOCALS | CO_PYARMOR_OBFUSCATED)
                    [Names]
                        'dc_id'
                        'file_token'
                        'encryption_key'
                        'encryption_iv'
                        'file_hashes'
                    [Locals+Names]
                        'self'
                        'dc_id'
                        'file_token'
                        'encryption_key'
                        'encryption_iv'
                        'file_hashes'
                        '__assert_armored__'
                    [Constants]
                        '\n        Constructor for upload.File: Instance of either File, FileCdnRedirect.\n        '
                        '__pyarmor_assert_41724__'
                        '__pyarmor_enter_41725__'
                        b'<COAddr>\x05\x00\x00\x1a\\\x00\x00\x00\x00\x00\x00\x00\x00\x00\x00\x00\x00\x00\x00\x00'
                        '__pyarmor_exit_41726__'
                        None
                    [Disassembly]
                        0       NOP                             
                        2       NOP                             
                        4       PUSH_NULL                       
                        6       LOAD_CONST                      2: '__pyarmor_enter_41725__'
                        8       LOAD_CONST                      3: b'<COAddr>\x05\x00\x00\x1a\\\x00\x00\x00\x00\x00\x00\x00\x00\x00\x00\x00\x00\x00\x00\x00'
                        10      BUILD_TUPLE                     1
                        12      CALL_FUNCTION_EX                0
                        14      POP_TOP                         
                        16      RESUME                          0
                        18      NOP                             
                        20      NOP                             
                        22      NOP                             
                        24      NOP                             
                        26      NOP                             
                        28      LOAD_FAST                       1: dc_id
                        30      LOAD_FAST                       0: self
                        32      STORE_ATTR                      0: dc_id
                        42      LOAD_FAST                       2: file_token
                        44      LOAD_FAST                       0: self
                        46      STORE_ATTR                      1: file_token
                        56      LOAD_FAST                       3: encryption_key
                        58      LOAD_FAST                       0: self
                        60      STORE_ATTR                      2: encryption_key
                        70      LOAD_FAST                       4: encryption_iv
                        72      LOAD_FAST                       0: self
                        74      STORE_ATTR                      3: encryption_iv
                        84      LOAD_FAST                       5: file_hashes
                        86      LOAD_FAST                       0: self
                        88      STORE_ATTR                      4: file_hashes
                        98      LOAD_CONST                      5: None
                        100     NOP                             
                        102     NOP                             
                        104     NOP                             
                        106     JUMP_FORWARD                    19 (to 146)
                        114     POP_TOP                         
                        116     RETURN_CONST                    5: None
                        118     PUSH_EXC_INFO                   
                        120     PUSH_NULL                       
                        122     LOAD_CONST                      4: '__pyarmor_exit_41726__'
                        124     NOP                             
                        126     LOAD_CONST                      3: b'<COAddr>\x05\x00\x00\x1a\\\x00\x00\x00\x00\x00\x00\x00\x00\x00\x00\x00\x00\x00\x00\x00'
                        128     CALL                            1
                        136     POP_TOP                         
                        138     RERAISE                         0
                        140     COPY                            3
                        142     POP_EXCEPT                      
                        144     RERAISE                         1
                        146     PUSH_NULL                       
                        148     LOAD_CONST                      4: '__pyarmor_exit_41726__'
                        150     LOAD_CONST                      3: b'<COAddr>\x05\x00\x00\x1a\\\x00\x00\x00\x00\x00\x00\x00\x00\x00\x00\x00\x00\x00\x00\x00'
                        152     BUILD_TUPLE                     1
                        154     CALL_FUNCTION_EX                0
                        156     POP_TOP                         
                        158     RETURN_VALUE                    
                    [Exception Table]
                        28 to 98 -> 118 [0] 
                        118 to 140 -> 140 [1] lasti
                [Code]
                    File Name: <frozen multithon.tl.types.upload>
                    Object Name: to_dict
                    Qualified Name: FileCdnRedirect.to_dict
                    Arg Count: 1
                    Pos Only Arg Count: 0
                    KW Only Arg Count: 0
                    Stack Size: 18
                    Flags: 0x20000003 (CO_OPTIMIZED | CO_NEWLOCALS | CO_PYARMOR_OBFUSCATED)
                    [Names]
                        'dc_id'
                        'file_token'
                        'encryption_key'
                        'encryption_iv'
                        'file_hashes'
                        'isinstance'
                        'TLObject'
                        'to_dict'
                    [Locals+Names]
                        'self'
                        '__assert_armored__'
                        '_var_var_4'
                    [Constants]
                        None
                        '__pyarmor_assert_41727__'
                        '__pyarmor_enter_41728__'
                        b'<COAddr>\x07\x00\x00\x1aR\x01\x00\x00\x00\x00\x00\x00\x00\x00\x00\x00\x00\x00\x00\x00'
                        '_'
                        'FileCdnRedirect'   # b'\x81\xc4\x11\x1f6\xd9\xba\xdc)\xff\t\xc9~\xe9\xfb\x91'
                        'dc_id'
                        'file_token'   # b'\x81\xe4\x11\x1f6\xc5\xaa\xdd\x10\xff\x03'
                        'encryption_key'   # b'\x81\xe7\x16\x10!\xe3\xae\xc6\x12\xf5\x03\xffg\xe9\xe1'
                        'encryption_iv'   # b'\x81\xe7\x16\x10!\xe3\xae\xc6\x12\xf5\x03\xffe\xfa'
                        'file_hashes'   # b'\x81\xe4\x11\x1f6\xc5\xb6\xd3\x08\xf2\x08\xd3'
                        '__pyarmor_exit_41729__'
                    [Disassembly]
                        0       NOP                             
                        2       NOP                             
                        4       PUSH_NULL                       
                        6       LOAD_CONST                      2: '__pyarmor_enter_41728__'
                        8       LOAD_CONST                      3: b'<COAddr>\x07\x00\x00\x1aR\x01\x00\x00\x00\x00\x00\x00\x00\x00\x00\x00\x00\x00\x00\x00'
                        10      BUILD_TUPLE                     1
                        12      CALL_FUNCTION_EX                0
                        14      POP_TOP                         
                        16      RESUME                          0
                        18      NOP                             
                        20      NOP                             
                        22      NOP                             
                        24      NOP                             
                        26      NOP                             
                        28      LOAD_CONST                      4: '_'
                        30      PUSH_NULL                       
                        32      LOAD_CONST                      1: '__pyarmor_assert_41727__'
                        34      LOAD_CONST                      5: 'FileCdnRedirect'   # b'\x81\xc4\x11\x1f6\xd9\xba\xdc)\xff\t\xc9~\xe9\xfb\x91'
                        36      CALL                            1
                        44      LOAD_CONST                      6: 'dc_id'
                        46      LOAD_FAST                       0: self
                        48      LOAD_ATTR                       0: dc_id
                        68      PUSH_NULL                       
                        70      LOAD_CONST                      1: '__pyarmor_assert_41727__'
                        72      LOAD_CONST                      7: 'file_token'   # b'\x81\xe4\x11\x1f6\xc5\xaa\xdd\x10\xff\x03'
                        74      CALL                            1
                        82      LOAD_FAST                       0: self
                        84      LOAD_ATTR                       2: file_token
                        104     PUSH_NULL                       
                        106     LOAD_CONST                      1: '__pyarmor_assert_41727__'
                        108     LOAD_CONST                      8: 'encryption_key'   # b'\x81\xe7\x16\x10!\xe3\xae\xc6\x12\xf5\x03\xffg\xe9\xe1'
                        110     CALL                            1
                        118     LOAD_FAST                       0: self
                        120     LOAD_ATTR                       4: encryption_key
                        140     PUSH_NULL                       
                        142     LOAD_CONST                      1: '__pyarmor_assert_41727__'
                        144     LOAD_CONST                      9: 'encryption_iv'   # b'\x81\xe7\x16\x10!\xe3\xae\xc6\x12\xf5\x03\xffe\xfa'
                        146     CALL                            1
                        154     LOAD_FAST                       0: self
                        156     LOAD_ATTR                       6: encryption_iv
                        176     PUSH_NULL                       
                        178     LOAD_CONST                      1: '__pyarmor_assert_41727__'
                        180     LOAD_CONST                      10: 'file_hashes'   # b'\x81\xe4\x11\x1f6\xc5\xb6\xd3\x08\xf2\x08\xd3'
                        182     CALL                            1
                        190     LOAD_FAST                       0: self
                        192     LOAD_ATTR                       8: file_hashes
                        212     POP_JUMP_IF_NOT_NONE            2 (to 218)
                        214     BUILD_LIST                      0
                        216     JUMP_FORWARD                    57 (to 332)
                        218     LOAD_FAST                       0: self
                        220     LOAD_ATTR                       8: file_hashes
                        240     GET_ITER                        
                        242     LOAD_FAST_AND_CLEAR             2: _var_var_4
                        244     SWAP                            2
                        246     BUILD_LIST                      0
                        248     SWAP                            2
                        250     FOR_ITER                        36 (to 324)
                        254     STORE_FAST                      2: _var_var_4
                        256     LOAD_GLOBAL                     11: NULL + isinstance
                        266     LOAD_FAST                       2: _var_var_4
                        268     LOAD_GLOBAL                     12: TLObject
                        278     CALL                            2
                        286     POP_JUMP_IF_FALSE               16 (to 320)
                        288     LOAD_FAST                       2: _var_var_4
                        290     LOAD_ATTR                       15: to_dict
                        310     CALL                            0
                        318     JUMP_FORWARD                    1 (to 322)
                        320     LOAD_FAST                       2: _var_var_4
                        322     LIST_APPEND                     2
                        324     JUMP_BACKWARD                   38 (to 250)
                        326     END_FOR                         
                        328     SWAP                            2
                        330     STORE_FAST                      2: _var_var_4
                        332     BUILD_MAP                       6
                        334     NOP                             
                        336     NOP                             
                        338     NOP                             
                        340     JUMP_FORWARD                    25 (to 392)
                        342     CALL                            1
                        350     POP_TOP                         
                        352     RETURN_VALUE                    
                        354     SWAP                            2
                        356     POP_TOP                         
                        358     SWAP                            2
                        360     STORE_FAST                      2: _var_var_4
                        362     RERAISE                         0
                        364     PUSH_EXC_INFO                   
                        366     PUSH_NULL                       
                        368     LOAD_CONST                      11: '__pyarmor_exit_41729__'
                        370     NOP                             
                        372     LOAD_CONST                      3: b'<COAddr>\x07\x00\x00\x1aR\x01\x00\x00\x00\x00\x00\x00\x00\x00\x00\x00\x00\x00\x00\x00'
                        374     CALL                            1
                        382     POP_TOP                         
                        384     RERAISE                         0
                        386     COPY                            3
                        388     POP_EXCEPT                      
                        390     RERAISE                         1
                        392     PUSH_NULL                       
                        394     LOAD_CONST                      11: '__pyarmor_exit_41729__'
                        396     LOAD_CONST                      3: b'<COAddr>\x07\x00\x00\x1aR\x01\x00\x00\x00\x00\x00\x00\x00\x00\x00\x00\x00\x00\x00\x00'
                        398     BUILD_TUPLE                     1
                        400     CALL_FUNCTION_EX                0
                        402     POP_TOP                         
                        404     RETURN_VALUE                    
                    [Exception Table]
                        28 to 246 -> 364 [0] 
                        246 to 328 -> 354 [13] 
                        328 to 334 -> 364 [0] 
                        354 to 364 -> 364 [0] 
                        364 to 386 -> 386 [1] lasti
                [Code]
                    File Name: <frozen multithon.tl.types.upload>
                    Object Name: _bytes
                    Qualified Name: FileCdnRedirect._bytes
                    Arg Count: 1
                    Pos Only Arg Count: 0
                    KW Only Arg Count: 0
                    Stack Size: 14
                    Flags: 0x20000003 (CO_OPTIMIZED | CO_NEWLOCALS | CO_PYARMOR_OBFUSCATED)
                    [Names]
                        'join'
                        'struct'
                        'pack'
                        'dc_id'
                        'serialize_bytes'
                        'file_token'
                        'encryption_key'
                        'encryption_iv'
                        'len'
                        'file_hashes'
                    [Locals+Names]
                        'self'
                        '__assert_armored__'
                    [Constants]
                        None
                        '__pyarmor_assert_41730__'
                        '__pyarmor_enter_41731__'
                        b'<COAddr>\x05\x00\x00\x1a\xa6\x01\x00\x00\x00\x00\x00\x00\x00\x00\x00\x00\x00\x00\x00\x00'
                        b''
                        b'D\xda\x8c\xf1'
                        '<i'
                        b'\x15\xc4\xb5\x1c'
                        [Code]
                            File Name: <frozen multithon.tl.types.upload>
                            Object Name: <genexpr>
                            Qualified Name: FileCdnRedirect._bytes.<locals>.<genexpr>
                            Arg Count: 1
                            Pos Only Arg Count: 0
                            KW Only Arg Count: 0
                            Stack Size: 3
                            Flags: 0x00000033 (CO_OPTIMIZED | CO_NEWLOCALS | CO_NESTED | CO_GENERATOR)
                            [Names]
                                '_bytes'
                            [Locals+Names]
                                '.0'
                                '_var_var_4'
                            [Constants]
                                None
                            [Disassembly]
                                0       RETURN_GENERATOR                
                                2       POP_TOP                         
                                4       RESUME                          0
                                6       LOAD_FAST                       0: .0
                                8       FOR_ITER                        20 (to 50)
                                12      STORE_FAST                      1: _var_var_4
                                14      LOAD_FAST                       1: _var_var_4
                                16      LOAD_ATTR                       1: _bytes
                                36      CALL                            0
                                44      YIELD_VALUE                     1
                                46      RESUME                          1
                                48      POP_TOP                         
                                50      JUMP_BACKWARD                   22 (to 8)
                                52      END_FOR                         
                                54      RETURN_CONST                    0: None
                                56      CALL_INTRINSIC_1                3 (INTRINSIC_STOPITERATION_ERROR)
                                58      RERAISE                         1
                            [Exception Table]
                                4 to 56 -> 56 [0] lasti
                        '__pyarmor_exit_41732__'
                    [Disassembly]
                        0       NOP                             
                        2       NOP                             
                        4       PUSH_NULL                       
                        6       LOAD_CONST                      2: '__pyarmor_enter_41731__'
                        8       LOAD_CONST                      3: b'<COAddr>\x05\x00\x00\x1a\xa6\x01\x00\x00\x00\x00\x00\x00\x00\x00\x00\x00\x00\x00\x00\x00'
                        10      BUILD_TUPLE                     1
                        12      CALL_FUNCTION_EX                0
                        14      POP_TOP                         
                        16      RESUME                          0
                        18      NOP                             
                        20      NOP                             
                        22      NOP                             
                        24      NOP                             
                        26      NOP                             
                        28      LOAD_CONST                      4: b''
                        30      LOAD_ATTR                       1: join
                        50      LOAD_CONST                      5: b'D\xda\x8c\xf1'
                        52      LOAD_GLOBAL                     3: NULL + struct
                        62      LOAD_ATTR                       4: pack
                        82      LOAD_CONST                      6: '<i'
                        84      LOAD_FAST                       0: self
                        86      LOAD_ATTR                       6: dc_id
                        106     CALL                            2
                        114     LOAD_FAST                       0: self
                        116     LOAD_ATTR                       9: serialize_bytes
                        136     LOAD_FAST                       0: self
                        138     LOAD_ATTR                       10: file_token
                        158     CALL                            1
                        166     LOAD_FAST                       0: self
                        168     LOAD_ATTR                       9: serialize_bytes
                        188     LOAD_FAST                       0: self
                        190     LOAD_ATTR                       12: encryption_key
                        210     CALL                            1
                        218     LOAD_FAST                       0: self
                        220     LOAD_ATTR                       9: serialize_bytes
                        240     LOAD_FAST                       0: self
                        242     LOAD_ATTR                       14: encryption_iv
                        262     CALL                            1
                        270     LOAD_CONST                      7: b'\x15\xc4\xb5\x1c'
                        272     LOAD_GLOBAL                     3: NULL + struct
                        282     LOAD_ATTR                       4: pack
                        302     LOAD_CONST                      6: '<i'
                        304     LOAD_GLOBAL                     17: NULL + len
                        314     LOAD_FAST                       0: self
                        316     LOAD_ATTR                       18: file_hashes
                        336     CALL                            1
                        344     CALL                            2
                        352     LOAD_CONST                      4: b''
                        354     LOAD_ATTR                       1: join
                        374     LOAD_CONST                      8: <CODE> <genexpr>
                        376     MAKE_FUNCTION                   0
                        378     LOAD_FAST                       0: self
                        380     LOAD_ATTR                       18: file_hashes
                        400     GET_ITER                        
                        402     CALL                            0
                        410     CALL                            1
                        418     BUILD_TUPLE                     8
                        420     CALL                            1
                        428     NOP                             
                        430     NOP                             
                        432     NOP                             
                        434     JUMP_FORWARD                    20 (to 476)
                        436     CALL                            1
                        444     POP_TOP                         
                        446     RETURN_VALUE                    
                        448     PUSH_EXC_INFO                   
                        450     PUSH_NULL                       
                        452     LOAD_CONST                      9: '__pyarmor_exit_41732__'
                        454     NOP                             
                        456     LOAD_CONST                      3: b'<COAddr>\x05\x00\x00\x1a\xa6\x01\x00\x00\x00\x00\x00\x00\x00\x00\x00\x00\x00\x00\x00\x00'
                        458     CALL                            1
                        466     POP_TOP                         
                        468     RERAISE                         0
                        470     COPY                            3
                        472     POP_EXCEPT                      
                        474     RERAISE                         1
                        476     PUSH_NULL                       
                        478     LOAD_CONST                      9: '__pyarmor_exit_41732__'
                        480     LOAD_CONST                      3: b'<COAddr>\x05\x00\x00\x1a\xa6\x01\x00\x00\x00\x00\x00\x00\x00\x00\x00\x00\x00\x00\x00\x00'
                        482     BUILD_TUPLE                     1
                        484     CALL_FUNCTION_EX                0
                        486     POP_TOP                         
                        488     RETURN_VALUE                    
                    [Exception Table]
                        28 to 428 -> 448 [0] 
                        448 to 470 -> 470 [1] lasti
                [Code]
                    File Name: <frozen multithon.tl.types.upload>
                    Object Name: from_reader
                    Qualified Name: FileCdnRedirect.from_reader
                    Arg Count: 2
                    Pos Only Arg Count: 0
                    KW Only Arg Count: 0
                    Stack Size: 7
                    Flags: 0x20000003 (CO_OPTIMIZED | CO_NEWLOCALS | CO_PYARMOR_OBFUSCATED)
                    [Names]
                        'read_int'
                        'tgread_bytes'
                        'range'
                        'tgread_object'
                        'append'
                    [Locals+Names]
                        'cls'
                        'reader'
                        '__assert_armored__'
                        '_var_var_5'
                        '_var_var_6'
                        '_var_var_7'
                        '_var_var_8'
                        '_var_var_9'
                        '_var_var_10'
                        '_var_var_11'
                    [Constants]
                        None
                        '__pyarmor_assert_41733__'
                        '__pyarmor_enter_41734__'
                        b'<COAddr>\x05\x00\x00\x1aP\x01\x00\x00\x00\x00\x00\x00\x00\x00\x00\x00\x00\x00\x00\x00'
                        (
                            'dc_id'
                            'file_token'
                            'encryption_key'
                            'encryption_iv'
                            'file_hashes'
                        )
                        '__pyarmor_exit_41735__'
                    [Disassembly]
                        0       NOP                             
                        2       NOP                             
                        4       PUSH_NULL                       
                        6       LOAD_CONST                      2: '__pyarmor_enter_41734__'
                        8       LOAD_CONST                      3: b'<COAddr>\x05\x00\x00\x1aP\x01\x00\x00\x00\x00\x00\x00\x00\x00\x00\x00\x00\x00\x00\x00'
                        10      BUILD_TUPLE                     1
                        12      CALL_FUNCTION_EX                0
                        14      POP_TOP                         
                        16      RESUME                          0
                        18      NOP                             
                        20      NOP                             
                        22      NOP                             
                        24      NOP                             
                        26      NOP                             
                        28      LOAD_FAST                       1: reader
                        30      LOAD_ATTR                       1: read_int
                        50      CALL                            0
                        58      STORE_FAST                      3: _var_var_5
                        60      LOAD_FAST                       1: reader
                        62      LOAD_ATTR                       3: tgread_bytes
                        82      CALL                            0
                        90      STORE_FAST                      4: _var_var_6
                        92      LOAD_FAST                       1: reader
                        94      LOAD_ATTR                       3: tgread_bytes
                        114     CALL                            0
                        122     STORE_FAST                      5: _var_var_7
                        124     LOAD_FAST                       1: reader
                        126     LOAD_ATTR                       3: tgread_bytes
                        146     CALL                            0
                        154     STORE_FAST                      6: _var_var_8
                        156     LOAD_FAST                       1: reader
                        158     LOAD_ATTR                       1: read_int
                        178     CALL                            0
                        186     POP_TOP                         
                        188     BUILD_LIST                      0
                        190     STORE_FAST                      7: _var_var_9
                        192     LOAD_GLOBAL                     5: NULL + range
                        202     LOAD_FAST                       1: reader
                        204     LOAD_ATTR                       1: read_int
                        224     CALL                            0
                        232     CALL                            1
                        240     GET_ITER                        
                        242     FOR_ITER                        35 (to 314)
                        246     STORE_FAST                      8: _var_var_10
                        248     LOAD_FAST                       1: reader
                        250     LOAD_ATTR                       7: tgread_object
                        270     CALL                            0
                        278     STORE_FAST                      9: _var_var_11
                        280     LOAD_FAST                       7: _var_var_9
                        282     LOAD_ATTR                       9: append
                        302     LOAD_FAST                       9: _var_var_11
                        304     CALL                            1
                        312     POP_TOP                         
                        314     JUMP_BACKWARD                   37 (to 242)
                        316     END_FOR                         
                        318     PUSH_NULL                       
                        320     LOAD_FAST                       0: cls
                        322     LOAD_FAST                       3: _var_var_5
                        324     LOAD_FAST                       4: _var_var_6
                        326     LOAD_FAST                       5: _var_var_7
                        328     LOAD_FAST                       6: _var_var_8
                        330     LOAD_FAST                       7: _var_var_9
                        332     KW_NAMES                        4: ('dc_id', 'file_token', 'encryption_key', 'encryption_iv', 'file_hashes')
                        334     CALL                            5
                        342     NOP                             
                        344     NOP                             
                        346     NOP                             
                        348     JUMP_FORWARD                    20 (to 390)
                        350     CALL                            1
                        358     POP_TOP                         
                        360     RETURN_VALUE                    
                        362     PUSH_EXC_INFO                   
                        364     PUSH_NULL                       
                        366     LOAD_CONST                      5: '__pyarmor_exit_41735__'
                        368     NOP                             
                        370     LOAD_CONST                      3: b'<COAddr>\x05\x00\x00\x1aP\x01\x00\x00\x00\x00\x00\x00\x00\x00\x00\x00\x00\x00\x00\x00'
                        372     CALL                            1
                        380     POP_TOP                         
                        382     RERAISE                         0
                        384     COPY                            3
                        386     POP_EXCEPT                      
                        388     RERAISE                         1
                        390     PUSH_NULL                       
                        392     LOAD_CONST                      5: '__pyarmor_exit_41735__'
                        394     LOAD_CONST                      3: b'<COAddr>\x05\x00\x00\x1aP\x01\x00\x00\x00\x00\x00\x00\x00\x00\x00\x00\x00\x00\x00\x00'
                        396     BUILD_TUPLE                     1
                        398     CALL_FUNCTION_EX                0
                        400     POP_TOP                         
                        402     RETURN_VALUE                    
                    [Exception Table]
                        28 to 342 -> 362 [0] 
                        362 to 384 -> 384 [1] lasti
                '__pyarmor_exit_41723__'
                None
            [Disassembly]
                0       NOP                             
                2       LOAD_NAME                       0: __name__
                4       STORE_NAME                      1: __module__
                6       LOAD_CONST                      0: 'FileCdnRedirect'
                8       STORE_NAME                      2: __qualname__
                10      NOP                             
                12      PUSH_NULL                       
                14      LOAD_CONST                      2: '__pyarmor_enter_41722__'
                16      LOAD_CONST                      3: b'<COAddr>\x05\x00\x00"h\x00\x00\x00\x00\x00\x00\x00\x00\x00\x00\x00\x00\x00\x00\x00'
                18      BUILD_TUPLE                     1
                20      CALL_FUNCTION_EX                0
                22      POP_TOP                         
                24      RESUME                          0
                26      NOP                             
                28      NOP                             
                30      NOP                             
                32      NOP                             
                34      NOP                             
                36      LOAD_CONST                      4: 0xF18CDA44
                38      STORE_NAME                      4: CONSTRUCTOR_ID
                40      LOAD_CONST                      5: 1822152488
                42      STORE_NAME                      5: SUBCLASS_OF_ID
                44      LOAD_CONST                      6: 'dc_id'
                46      LOAD_NAME                       6: int
                48      LOAD_CONST                      7: 'file_token'
                50      LOAD_NAME                       7: bytes
                52      LOAD_CONST                      8: 'encryption_key'
                54      LOAD_NAME                       7: bytes
                56      LOAD_CONST                      9: 'encryption_iv'
                58      LOAD_NAME                       7: bytes
                60      LOAD_CONST                      10: 'file_hashes'
                62      LOAD_NAME                       8: List
                64      PUSH_NULL                       
                66      LOAD_CONST                      1: '__pyarmor_assert_41721__'
                68      LOAD_CONST                      11: 'TypeFileHash'   # b'\x81\xd6\x01\x036\xdc\xb7\xde\x1e\xd2\x0c\xd3d'
                70      CALL                            1
                78      BINARY_SUBSCR                   
                82      BUILD_TUPLE                     10
                84      LOAD_CONST                      12: <CODE> __init__
                86      MAKE_FUNCTION                   4
                88      STORE_NAME                      9: __init__
                90      LOAD_CONST                      13: <CODE> to_dict
                92      MAKE_FUNCTION                   0
                94      STORE_NAME                      10: to_dict
                96      LOAD_CONST                      14: <CODE> _bytes
                98      MAKE_FUNCTION                   0
                100     STORE_NAME                      11: _bytes
                102     LOAD_NAME                       12: classmethod
                104     LOAD_CONST                      15: <CODE> from_reader
                106     MAKE_FUNCTION                   0
                108     CALL                            0
                116     STORE_NAME                      13: from_reader
                118     LOAD_CONST                      17: None
                120     NOP                             
                122     NOP                             
                124     NOP                             
                126     JUMP_FORWARD                    19 (to 166)
                134     POP_TOP                         
                136     RETURN_CONST                    17: None
                138     PUSH_EXC_INFO                   
                140     PUSH_NULL                       
                142     LOAD_CONST                      16: '__pyarmor_exit_41723__'
                144     NOP                             
                146     LOAD_CONST                      3: b'<COAddr>\x05\x00\x00"h\x00\x00\x00\x00\x00\x00\x00\x00\x00\x00\x00\x00\x00\x00\x00'
                148     CALL                            1
                156     POP_TOP                         
                158     RERAISE                         0
                160     COPY                            3
                162     POP_EXCEPT                      
                164     RERAISE                         1
                166     PUSH_NULL                       
                168     LOAD_CONST                      16: '__pyarmor_exit_41723__'
                170     LOAD_CONST                      3: b'<COAddr>\x05\x00\x00"h\x00\x00\x00\x00\x00\x00\x00\x00\x00\x00\x00\x00\x00\x00\x00'
                172     BUILD_TUPLE                     1
                174     CALL_FUNCTION_EX                0
                176     POP_TOP                         
                178     RETURN_VALUE                    
            [Exception Table]
                36 to 118 -> 138 [0] 
                138 to 160 -> 160 [1] lasti
        'FileCdnRedirect'
        [Code]
            File Name: <frozen multithon.tl.types.upload>
            Object Name: WebFile
            Qualified Name: WebFile
            Arg Count: 0
            Pos Only Arg Count: 0
            KW Only Arg Count: 0
            Stack Size: 10
            Flags: 0x20000000 (CO_PYARMOR_OBFUSCATED)
            [Names]
                '__name__'
                '__module__'
                '__qualname__'
                '__assert_armored__'
                'CONSTRUCTOR_ID'
                'SUBCLASS_OF_ID'
                'int'
                'str'
                'bytes'
                '__init__'
                'to_dict'
                '_bytes'
                'classmethod'
                'from_reader'
            [Locals+Names]
            [Constants]
                'WebFile'
                '__pyarmor_assert_41736__'
                '__pyarmor_enter_41737__'
                b'<COAddr>\x05\x00\x00"b\x00\x00\x00\x00\x00\x00\x00\x00\x00\x00\x00\x00\x00\x00\x00'
                568808380
                1760657233
                'size'
                'mime_type'
                'file_type'
                'TypeFileType'   # b'\x81\xd6\x01\x036\xdc\xb7\xde\x1e\xce\x14\xd0i'
                'mtime'
                'bytes'
                [Code]
                    File Name: <frozen multithon.tl.types.upload>
                    Object Name: __init__
                    Qualified Name: WebFile.__init__
                    Arg Count: 6
                    Pos Only Arg Count: 0
                    KW Only Arg Count: 0
                    Stack Size: 5
                    Flags: 0x20000003 (CO_OPTIMIZED | CO_NEWLOCALS | CO_PYARMOR_OBFUSCATED)
                    [Names]
                        'size'
                        'mime_type'
                        'file_type'
                        'mtime'
                        'bytes'
                    [Locals+Names]
                        'self'
                        'size'
                        'mime_type'
                        'file_type'
                        'mtime'
                        'bytes'
                        '__assert_armored__'
                    [Constants]
                        '\n        Constructor for upload.WebFile: Instance of WebFile.\n        '
                        '__pyarmor_assert_41739__'
                        '__pyarmor_enter_41740__'
                        b'<COAddr>\x05\x00\x00\x1a\\\x00\x00\x00\x00\x00\x00\x00\x00\x00\x00\x00\x00\x00\x00\x00'
                        '__pyarmor_exit_41741__'
                        None
                    [Disassembly]
                        0       NOP                             
                        2       NOP                             
                        4       PUSH_NULL                       
                        6       LOAD_CONST                      2: '__pyarmor_enter_41740__'
                        8       LOAD_CONST                      3: b'<COAddr>\x05\x00\x00\x1a\\\x00\x00\x00\x00\x00\x00\x00\x00\x00\x00\x00\x00\x00\x00\x00'
                        10      BUILD_TUPLE                     1
                        12      CALL_FUNCTION_EX                0
                        14      POP_TOP                         
                        16      RESUME                          0
                        18      NOP                             
                        20      NOP                             
                        22      NOP                             
                        24      NOP                             
                        26      NOP                             
                        28      LOAD_FAST                       1: size
                        30      LOAD_FAST                       0: self
                        32      STORE_ATTR                      0: size
                        42      LOAD_FAST                       2: mime_type
                        44      LOAD_FAST                       0: self
                        46      STORE_ATTR                      1: mime_type
                        56      LOAD_FAST                       3: file_type
                        58      LOAD_FAST                       0: self
                        60      STORE_ATTR                      2: file_type
                        70      LOAD_FAST                       4: mtime
                        72      LOAD_FAST                       0: self
                        74      STORE_ATTR                      3: mtime
                        84      LOAD_FAST                       5: bytes
                        86      LOAD_FAST                       0: self
                        88      STORE_ATTR                      4: bytes
                        98      LOAD_CONST                      5: None
                        100     NOP                             
                        102     NOP                             
                        104     NOP                             
                        106     JUMP_FORWARD                    19 (to 146)
                        114     POP_TOP                         
                        116     RETURN_CONST                    5: None
                        118     PUSH_EXC_INFO                   
                        120     PUSH_NULL                       
                        122     LOAD_CONST                      4: '__pyarmor_exit_41741__'
                        124     NOP                             
                        126     LOAD_CONST                      3: b'<COAddr>\x05\x00\x00\x1a\\\x00\x00\x00\x00\x00\x00\x00\x00\x00\x00\x00\x00\x00\x00\x00'
                        128     CALL                            1
                        136     POP_TOP                         
                        138     RERAISE                         0
                        140     COPY                            3
                        142     POP_EXCEPT                      
                        144     RERAISE                         1
                        146     PUSH_NULL                       
                        148     LOAD_CONST                      4: '__pyarmor_exit_41741__'
                        150     LOAD_CONST                      3: b'<COAddr>\x05\x00\x00\x1a\\\x00\x00\x00\x00\x00\x00\x00\x00\x00\x00\x00\x00\x00\x00\x00'
                        152     BUILD_TUPLE                     1
                        154     CALL_FUNCTION_EX                0
                        156     POP_TOP                         
                        158     RETURN_VALUE                    
                    [Exception Table]
                        28 to 98 -> 118 [0] 
                        118 to 140 -> 140 [1] lasti
                [Code]
                    File Name: <frozen multithon.tl.types.upload>
                    Object Name: to_dict
                    Qualified Name: WebFile.to_dict
                    Arg Count: 1
                    Pos Only Arg Count: 0
                    KW Only Arg Count: 0
                    Stack Size: 12
                    Flags: 0x20000003 (CO_OPTIMIZED | CO_NEWLOCALS | CO_PYARMOR_OBFUSCATED)
                    [Names]
                        'size'
                        'mime_type'
                        'isinstance'
                        'file_type'
                        'TLObject'
                        'to_dict'
                        'mtime'
                        'bytes'
                    [Locals+Names]
                        'self'
                        '__assert_armored__'
                    [Constants]
                        None
                        '__pyarmor_assert_41742__'
                        '__pyarmor_enter_41743__'
                        b'<COAddr>\x05\x00\x00\x1a\x14\x01\x00\x00\x00\x00\x00\x00\x00\x00\x00\x00\x00\x00\x00\x00'
                        '_'
                        'WebFile'
                        'size'
                        'mime_type'   # b'\x81\xef\x11\x1e6\xc5\xaa\xcb\x0b\xff'
                        'file_type'   # b'\x81\xe4\x11\x1f6\xc5\xaa\xcb\x0b\xff'
                        'mtime'
                        'bytes'
                        '__pyarmor_exit_41744__'
                    [Disassembly]
                        0       NOP                             
                        2       NOP                             
                        4       PUSH_NULL                       
                        6       LOAD_CONST                      2: '__pyarmor_enter_41743__'
                        8       LOAD_CONST                      3: b'<COAddr>\x05\x00\x00\x1a\x14\x01\x00\x00\x00\x00\x00\x00\x00\x00\x00\x00\x00\x00\x00\x00'
                        10      BUILD_TUPLE                     1
                        12      CALL_FUNCTION_EX                0
                        14      POP_TOP                         
                        16      RESUME                          0
                        18      NOP                             
                        20      NOP                             
                        22      NOP                             
                        24      NOP                             
                        26      NOP                             
                        28      LOAD_CONST                      4: '_'
                        30      LOAD_CONST                      5: 'WebFile'
                        32      LOAD_CONST                      6: 'size'
                        34      LOAD_FAST                       0: self
                        36      LOAD_ATTR                       0: size
                        56      PUSH_NULL                       
                        58      LOAD_CONST                      1: '__pyarmor_assert_41742__'
                        60      LOAD_CONST                      7: 'mime_type'   # b'\x81\xef\x11\x1e6\xc5\xaa\xcb\x0b\xff'
                        62      CALL                            1
                        70      LOAD_FAST                       0: self
                        72      LOAD_ATTR                       2: mime_type
                        92      PUSH_NULL                       
                        94      LOAD_CONST                      1: '__pyarmor_assert_41742__'
                        96      LOAD_CONST                      8: 'file_type'   # b'\x81\xe4\x11\x1f6\xc5\xaa\xcb\x0b\xff'
                        98      CALL                            1
                        106     LOAD_GLOBAL                     5: NULL + isinstance
                        116     LOAD_FAST                       0: self
                        118     LOAD_ATTR                       6: file_type
                        138     LOAD_GLOBAL                     8: TLObject
                        148     CALL                            2
                        156     POP_JUMP_IF_FALSE               26 (to 210)
                        158     LOAD_FAST                       0: self
                        160     LOAD_ATTR                       6: file_type
                        180     LOAD_ATTR                       11: to_dict
                        200     CALL                            0
                        208     JUMP_FORWARD                    11 (to 232)
                        210     LOAD_FAST                       0: self
                        212     LOAD_ATTR                       6: file_type
                        232     LOAD_CONST                      9: 'mtime'
                        234     LOAD_FAST                       0: self
                        236     LOAD_ATTR                       12: mtime
                        256     LOAD_CONST                      10: 'bytes'
                        258     LOAD_FAST                       0: self
                        260     LOAD_ATTR                       14: bytes
                        280     BUILD_MAP                       6
                        282     NOP                             
                        284     NOP                             
                        286     NOP                             
                        288     JUMP_FORWARD                    20 (to 330)
                        290     CALL                            1
                        298     POP_TOP                         
                        300     RETURN_VALUE                    
                        302     PUSH_EXC_INFO                   
                        304     PUSH_NULL                       
                        306     LOAD_CONST                      11: '__pyarmor_exit_41744__'
                        308     NOP                             
                        310     LOAD_CONST                      3: b'<COAddr>\x05\x00\x00\x1a\x14\x01\x00\x00\x00\x00\x00\x00\x00\x00\x00\x00\x00\x00\x00\x00'
                        312     CALL                            1
                        320     POP_TOP                         
                        322     RERAISE                         0
                        324     COPY                            3
                        326     POP_EXCEPT                      
                        328     RERAISE                         1
                        330     PUSH_NULL                       
                        332     LOAD_CONST                      11: '__pyarmor_exit_41744__'
                        334     LOAD_CONST                      3: b'<COAddr>\x05\x00\x00\x1a\x14\x01\x00\x00\x00\x00\x00\x00\x00\x00\x00\x00\x00\x00\x00\x00'
                        336     BUILD_TUPLE                     1
                        338     CALL_FUNCTION_EX                0
                        340     POP_TOP                         
                        342     RETURN_VALUE                    
                    [Exception Table]
                        28 to 282 -> 302 [0] 
                        302 to 324 -> 324 [1] lasti
                [Code]
                    File Name: <frozen multithon.tl.types.upload>
                    Object Name: _bytes
                    Qualified Name: WebFile._bytes
                    Arg Count: 1
                    Pos Only Arg Count: 0
                    KW Only Arg Count: 0
                    Stack Size: 10
                    Flags: 0x20000003 (CO_OPTIMIZED | CO_NEWLOCALS | CO_PYARMOR_OBFUSCATED)
                    [Names]
                        'join'
                        'struct'
                        'pack'
                        'size'
                        'serialize_bytes'
                        'mime_type'
                        'file_type'
                        '_bytes'
                        'mtime'
                        'bytes'
                    [Locals+Names]
                        'self'
                        '__assert_armored__'
                    [Constants]
                        None
                        '__pyarmor_assert_41745__'
                        '__pyarmor_enter_41746__'
                        b'<COAddr>\x05\x00\x00\x1aN\x01\x00\x00\x00\x00\x00\x00\x00\x00\x00\x00\x00\x00\x00\x00'
                        b''
                        b'\xbcS\xe7!'
                        '<i'
                        '__pyarmor_exit_41747__'
                    [Disassembly]
                        0       NOP                             
                        2       NOP                             
                        4       PUSH_NULL                       
                        6       LOAD_CONST                      2: '__pyarmor_enter_41746__'
                        8       LOAD_CONST                      3: b'<COAddr>\x05\x00\x00\x1aN\x01\x00\x00\x00\x00\x00\x00\x00\x00\x00\x00\x00\x00\x00\x00'
                        10      BUILD_TUPLE                     1
                        12      CALL_FUNCTION_EX                0
                        14      POP_TOP                         
                        16      RESUME                          0
                        18      NOP                             
                        20      NOP                             
                        22      NOP                             
                        24      NOP                             
                        26      NOP                             
                        28      LOAD_CONST                      4: b''
                        30      LOAD_ATTR                       1: join
                        50      LOAD_CONST                      5: b'\xbcS\xe7!'
                        52      LOAD_GLOBAL                     3: NULL + struct
                        62      LOAD_ATTR                       4: pack
                        82      LOAD_CONST                      6: '<i'
                        84      LOAD_FAST                       0: self
                        86      LOAD_ATTR                       6: size
                        106     CALL                            2
                        114     LOAD_FAST                       0: self
                        116     LOAD_ATTR                       9: serialize_bytes
                        136     LOAD_FAST                       0: self
                        138     LOAD_ATTR                       10: mime_type
                        158     CALL                            1
                        166     LOAD_FAST                       0: self
                        168     LOAD_ATTR                       12: file_type
                        188     LOAD_ATTR                       15: _bytes
                        208     CALL                            0
                        216     LOAD_GLOBAL                     3: NULL + struct
                        226     LOAD_ATTR                       4: pack
                        246     LOAD_CONST                      6: '<i'
                        248     LOAD_FAST                       0: self
                        250     LOAD_ATTR                       16: mtime
                        270     CALL                            2
                        278     LOAD_FAST                       0: self
                        280     LOAD_ATTR                       9: serialize_bytes
                        300     LOAD_FAST                       0: self
                        302     LOAD_ATTR                       18: bytes
                        322     CALL                            1
                        330     BUILD_TUPLE                     6
                        332     CALL                            1
                        340     NOP                             
                        342     NOP                             
                        344     NOP                             
                        346     JUMP_FORWARD                    20 (to 388)
                        348     CALL                            1
                        356     POP_TOP                         
                        358     RETURN_VALUE                    
                        360     PUSH_EXC_INFO                   
                        362     PUSH_NULL                       
                        364     LOAD_CONST                      7: '__pyarmor_exit_41747__'
                        366     NOP                             
                        368     LOAD_CONST                      3: b'<COAddr>\x05\x00\x00\x1aN\x01\x00\x00\x00\x00\x00\x00\x00\x00\x00\x00\x00\x00\x00\x00'
                        370     CALL                            1
                        378     POP_TOP                         
                        380     RERAISE                         0
                        382     COPY                            3
                        384     POP_EXCEPT                      
                        386     RERAISE                         1
                        388     PUSH_NULL                       
                        390     LOAD_CONST                      7: '__pyarmor_exit_41747__'
                        392     LOAD_CONST                      3: b'<COAddr>\x05\x00\x00\x1aN\x01\x00\x00\x00\x00\x00\x00\x00\x00\x00\x00\x00\x00\x00\x00'
                        394     BUILD_TUPLE                     1
                        396     CALL_FUNCTION_EX                0
                        398     POP_TOP                         
                        400     RETURN_VALUE                    
                    [Exception Table]
                        28 to 340 -> 360 [0] 
                        360 to 382 -> 382 [1] lasti
                [Code]
                    File Name: <frozen multithon.tl.types.upload>
                    Object Name: from_reader
                    Qualified Name: WebFile.from_reader
                    Arg Count: 2
                    Pos Only Arg Count: 0
                    KW Only Arg Count: 0
                    Stack Size: 7
                    Flags: 0x20000003 (CO_OPTIMIZED | CO_NEWLOCALS | CO_PYARMOR_OBFUSCATED)
                    [Names]
                        'read_int'
                        'tgread_string'
                        'tgread_object'
                        'tgread_bytes'
                    [Locals+Names]
                        'cls'
                        'reader'
                        '__assert_armored__'
                        '_var_var_12'
                        '_var_var_13'
                        '_var_var_14'
                        '_var_var_3'
                        '_var_var_0'
                    [Constants]
                        None
                        '__pyarmor_assert_41748__'
                        '__pyarmor_enter_41749__'
                        b'<COAddr>\x07\x00\x00\x1a\xce\x00\x00\x00\x00\x00\x00\x00\x00\x00\x00\x00\x00\x00\x00\x00'
                        (
                            'size'
                            'mime_type'
                            'file_type'
                            'mtime'
                            'bytes'
                        )
                        '__pyarmor_exit_41750__'
                    [Disassembly]
                        0       NOP                             
                        2       NOP                             
                        4       PUSH_NULL                       
                        6       LOAD_CONST                      2: '__pyarmor_enter_41749__'
                        8       LOAD_CONST                      3: b'<COAddr>\x07\x00\x00\x1a\xce\x00\x00\x00\x00\x00\x00\x00\x00\x00\x00\x00\x00\x00\x00\x00'
                        10      BUILD_TUPLE                     1
                        12      CALL_FUNCTION_EX                0
                        14      POP_TOP                         
                        16      RESUME                          0
                        18      NOP                             
                        20      NOP                             
                        22      NOP                             
                        24      NOP                             
                        26      NOP                             
                        28      LOAD_FAST                       1: reader
                        30      LOAD_ATTR                       1: read_int
                        50      CALL                            0
                        58      STORE_FAST                      3: _var_var_12
                        60      LOAD_FAST                       1: reader
                        62      LOAD_ATTR                       3: tgread_string
                        82      CALL                            0
                        90      STORE_FAST                      4: _var_var_13
                        92      LOAD_FAST                       1: reader
                        94      LOAD_ATTR                       5: tgread_object
                        114     CALL                            0
                        122     STORE_FAST                      5: _var_var_14
                        124     LOAD_FAST                       1: reader
                        126     LOAD_ATTR                       1: read_int
                        146     CALL                            0
                        154     STORE_FAST                      6: _var_var_3
                        156     LOAD_FAST                       1: reader
                        158     LOAD_ATTR                       7: tgread_bytes
                        178     CALL                            0
                        186     STORE_FAST                      7: _var_var_0
                        188     PUSH_NULL                       
                        190     LOAD_FAST                       0: cls
                        192     LOAD_FAST                       3: _var_var_12
                        194     LOAD_FAST                       4: _var_var_13
                        196     LOAD_FAST                       5: _var_var_14
                        198     LOAD_FAST                       6: _var_var_3
                        200     LOAD_FAST                       7: _var_var_0
                        202     KW_NAMES                        4: ('size', 'mime_type', 'file_type', 'mtime', 'bytes')
                        204     CALL                            5
                        212     NOP                             
                        214     NOP                             
                        216     NOP                             
                        218     JUMP_FORWARD                    20 (to 260)
                        220     CALL                            1
                        228     POP_TOP                         
                        230     RETURN_VALUE                    
                        232     PUSH_EXC_INFO                   
                        234     PUSH_NULL                       
                        236     LOAD_CONST                      5: '__pyarmor_exit_41750__'
                        238     NOP                             
                        240     LOAD_CONST                      3: b'<COAddr>\x07\x00\x00\x1a\xce\x00\x00\x00\x00\x00\x00\x00\x00\x00\x00\x00\x00\x00\x00\x00'
                        242     CALL                            1
                        250     POP_TOP                         
                        252     RERAISE                         0
                        254     COPY                            3
                        256     POP_EXCEPT                      
                        258     RERAISE                         1
                        260     PUSH_NULL                       
                        262     LOAD_CONST                      5: '__pyarmor_exit_41750__'
                        264     LOAD_CONST                      3: b'<COAddr>\x07\x00\x00\x1a\xce\x00\x00\x00\x00\x00\x00\x00\x00\x00\x00\x00\x00\x00\x00\x00'
                        266     BUILD_TUPLE                     1
                        268     CALL_FUNCTION_EX                0
                        270     POP_TOP                         
                        272     RETURN_VALUE                    
                    [Exception Table]
                        28 to 212 -> 232 [0] 
                        232 to 254 -> 254 [1] lasti
                '__pyarmor_exit_41738__'
                None
            [Disassembly]
                0       NOP                             
                2       LOAD_NAME                       0: __name__
                4       STORE_NAME                      1: __module__
                6       LOAD_CONST                      0: 'WebFile'
                8       STORE_NAME                      2: __qualname__
                10      NOP                             
                12      PUSH_NULL                       
                14      LOAD_CONST                      2: '__pyarmor_enter_41737__'
                16      LOAD_CONST                      3: b'<COAddr>\x05\x00\x00"b\x00\x00\x00\x00\x00\x00\x00\x00\x00\x00\x00\x00\x00\x00\x00'
                18      BUILD_TUPLE                     1
                20      CALL_FUNCTION_EX                0
                22      POP_TOP                         
                24      RESUME                          0
                26      NOP                             
                28      NOP                             
                30      NOP                             
                32      NOP                             
                34      NOP                             
                36      LOAD_CONST                      4: 568808380
                38      STORE_NAME                      4: CONSTRUCTOR_ID
                40      LOAD_CONST                      5: 1760657233
                42      STORE_NAME                      5: SUBCLASS_OF_ID
                44      LOAD_CONST                      6: 'size'
                46      LOAD_NAME                       6: int
                48      LOAD_CONST                      7: 'mime_type'
                50      LOAD_NAME                       7: str
                52      LOAD_CONST                      8: 'file_type'
                54      PUSH_NULL                       
                56      LOAD_CONST                      1: '__pyarmor_assert_41736__'
                58      LOAD_CONST                      9: 'TypeFileType'   # b'\x81\xd6\x01\x036\xdc\xb7\xde\x1e\xce\x14\xd0i'
                60      CALL                            1
                68      LOAD_CONST                      10: 'mtime'
                70      LOAD_NAME                       6: int
                72      LOAD_CONST                      11: 'bytes'
                74      LOAD_NAME                       8: bytes
                76      BUILD_TUPLE                     10
                78      LOAD_CONST                      12: <CODE> __init__
                80      MAKE_FUNCTION                   4
                82      STORE_NAME                      9: __init__
                84      LOAD_CONST                      13: <CODE> to_dict
                86      MAKE_FUNCTION                   0
                88      STORE_NAME                      10: to_dict
                90      LOAD_CONST                      14: <CODE> _bytes
                92      MAKE_FUNCTION                   0
                94      STORE_NAME                      11: _bytes
                96      LOAD_NAME                       12: classmethod
                98      LOAD_CONST                      15: <CODE> from_reader
                100     MAKE_FUNCTION                   0
                102     CALL                            0
                110     STORE_NAME                      13: from_reader
                112     LOAD_CONST                      17: None
                114     NOP                             
                116     NOP                             
                118     NOP                             
                120     JUMP_FORWARD                    19 (to 160)
                128     POP_TOP                         
                130     RETURN_CONST                    17: None
                132     PUSH_EXC_INFO                   
                134     PUSH_NULL                       
                136     LOAD_CONST                      16: '__pyarmor_exit_41738__'
                138     NOP                             
                140     LOAD_CONST                      3: b'<COAddr>\x05\x00\x00"b\x00\x00\x00\x00\x00\x00\x00\x00\x00\x00\x00\x00\x00\x00\x00'
                142     CALL                            1
                150     POP_TOP                         
                152     RERAISE                         0
                154     COPY                            3
                156     POP_EXCEPT                      
                158     RERAISE                         1
                160     PUSH_NULL                       
                162     LOAD_CONST                      16: '__pyarmor_exit_41738__'
                164     LOAD_CONST                      3: b'<COAddr>\x05\x00\x00"b\x00\x00\x00\x00\x00\x00\x00\x00\x00\x00\x00\x00\x00\x00\x00'
                166     BUILD_TUPLE                     1
                168     CALL_FUNCTION_EX                0
                170     POP_TOP                         
                172     RETURN_VALUE                    
            [Exception Table]
                36 to 112 -> 132 [0] 
                132 to 154 -> 154 [1] lasti
        'WebFile'
        '__pyarmor_exit_41675__'
    [Disassembly]
        0       NOP                             
        2       NOP                             
        4       PUSH_NULL                       
        6       LOAD_CONST                      1: '__pyarmor_enter_41674__'
        8       LOAD_CONST                      2: b'<COAddr>\x05\x00\x00\x1a\xee\x00\x00\x00\x00\x00\x00\x00\x00\x00\x00\x00\x00\x00\x00\x00'
        10      BUILD_TUPLE                     1
        12      CALL_FUNCTION_EX                0
        14      POP_TOP                         
        16      RESUME                          0
        18      NOP                             
        20      NOP                             
        22      NOP                             
        24      NOP                             
        26      PUSH_NULL                       
        28      LOAD_CONST                      0: '__pyarmor_assert_41673__'
        30      LOAD_CONST                      3: "File generated by TLObjects' generator. All changes will be ERASED"   # b'\x81\xc4\x11\x1f6\xba\xb9\xd7\x15\xff\x1f\xc1x\xe9\xfc\xc5\rD\xfb\x93\x86\xe4L\xc6\x00l\xb7OG\xf1\x19\xe04W2\x0c\x8c\xc5\xa6`X\xc8\xf4Q\x9d\xdb\x07F9\xeaS\xe8\xc7g\x0f\xe1;\xab\x99\x18Xn\x03rdm!'
        32      CALL                            1
        40      POP_TOP                         
        42      LOAD_CONST                      4: 3
        44      LOAD_CONST                      5: ('TLObject',)
        46      IMPORT_NAME                     1: tl.tlobject
        48      IMPORT_FROM                     2: TLObject
        50      STORE_NAME                      2: TLObject
        52      POP_TOP                         
        54      LOAD_CONST                      6: 0
        56      LOAD_CONST                      7: ('Optional', 'List', 'Union', 'TYPE_CHECKING')
        58      IMPORT_NAME                     3: typing
        60      IMPORT_FROM                     4: Optional
        62      STORE_NAME                      4: Optional
        64      IMPORT_FROM                     5: List
        66      STORE_NAME                      5: List
        68      IMPORT_FROM                     6: Union
        70      STORE_NAME                      6: Union
        72      IMPORT_FROM                     7: TYPE_CHECKING
        74      STORE_NAME                      7: TYPE_CHECKING
        76      POP_TOP                         
        78      LOAD_CONST                      6: 0
        80      LOAD_CONST                      8: None
        82      IMPORT_NAME                     8: os
        84      STORE_NAME                      8: os
        86      LOAD_CONST                      6: 0
        88      LOAD_CONST                      8: None
        90      IMPORT_NAME                     9: struct
        92      STORE_NAME                      9: struct
        94      LOAD_CONST                      6: 0
        96      LOAD_CONST                      9: ('datetime',)
        98      IMPORT_NAME                     10: datetime
        100     IMPORT_FROM                     10: datetime
        102     STORE_NAME                      10: datetime
        104     POP_TOP                         
        106     LOAD_NAME                       7: TYPE_CHECKING
        108     POP_JUMP_IF_FALSE               12 (to 134)
        110     LOAD_CONST                      4: 3
        112     LOAD_CONST                      10: ('TypeFileType',)
        114     IMPORT_NAME                     11: tl.types.storage
        116     IMPORT_FROM                     12: TypeFileType
        118     STORE_NAME                      12: TypeFileType
        120     POP_TOP                         
        122     LOAD_CONST                      4: 3
        124     LOAD_CONST                      11: ('TypeFileHash',)
        126     IMPORT_NAME                     13: tl.types
        128     IMPORT_FROM                     14: TypeFileHash
        130     STORE_NAME                      14: TypeFileHash
        132     POP_TOP                         
        134     PUSH_NULL                       
        136     LOAD_BUILD_CLASS                
        138     LOAD_CONST                      12: <CODE> CdnFile
        140     MAKE_FUNCTION                   0
        142     LOAD_CONST                      13: 'CdnFile'
        144     LOAD_NAME                       2: TLObject
        146     CALL                            3
        154     STORE_NAME                      15: CdnFile
        156     PUSH_NULL                       
        158     LOAD_BUILD_CLASS                
        160     LOAD_CONST                      14: <CODE> CdnFileReuploadNeeded
        162     MAKE_FUNCTION                   0
        164     LOAD_CONST                      15: 'CdnFileReuploadNeeded'
        166     LOAD_NAME                       2: TLObject
        168     CALL                            3
        176     STORE_NAME                      16: CdnFileReuploadNeeded
        178     PUSH_NULL                       
        180     LOAD_BUILD_CLASS                
        182     LOAD_CONST                      16: <CODE> File
        184     MAKE_FUNCTION                   0
        186     LOAD_CONST                      17: 'File'
        188     LOAD_NAME                       2: TLObject
        190     CALL                            3
        198     STORE_NAME                      17: File
        200     PUSH_NULL                       
        202     LOAD_BUILD_CLASS                
        204     LOAD_CONST                      18: <CODE> FileCdnRedirect
        206     MAKE_FUNCTION                   0
        208     LOAD_CONST                      19: 'FileCdnRedirect'
        210     LOAD_NAME                       2: TLObject
        212     CALL                            3
        220     STORE_NAME                      18: FileCdnRedirect
        222     PUSH_NULL                       
        224     LOAD_BUILD_CLASS                
        226     LOAD_CONST                      20: <CODE> WebFile
        228     MAKE_FUNCTION                   0
        230     LOAD_CONST                      21: 'WebFile'
        232     LOAD_NAME                       2: TLObject
        234     CALL                            3
        242     STORE_NAME                      19: WebFile
        244     LOAD_CONST                      8: None
        246     NOP                             
        248     NOP                             
        250     NOP                             
        252     JUMP_FORWARD                    19 (to 292)
        260     POP_TOP                         
        262     RETURN_CONST                    8: None
        264     PUSH_EXC_INFO                   
        266     PUSH_NULL                       
        268     LOAD_CONST                      22: '__pyarmor_exit_41675__'
        270     NOP                             
        272     LOAD_CONST                      2: b'<COAddr>\x05\x00\x00\x1a\xee\x00\x00\x00\x00\x00\x00\x00\x00\x00\x00\x00\x00\x00\x00\x00'
        274     CALL                            1
        282     POP_TOP                         
        284     RERAISE                         0
        286     COPY                            3
        288     POP_EXCEPT                      
        290     RERAISE                         1
        292     PUSH_NULL                       
        294     LOAD_CONST                      22: '__pyarmor_exit_41675__'
        296     LOAD_CONST                      2: b'<COAddr>\x05\x00\x00\x1a\xee\x00\x00\x00\x00\x00\x00\x00\x00\x00\x00\x00\x00\x00\x00\x00'
        298     BUILD_TUPLE                     1
        300     CALL_FUNCTION_EX                0
        302     POP_TOP                         
        304     RETURN_VALUE                    
    [Exception Table]
        26 to 244 -> 264 [0] 
        264 to 286 -> 286 [1] lasti
