#decoded by lolz.live/mrpenny / t.me/zeus_jackpot
# ================================
# Примечания по Pyarmor:
# - Байт-код и объекты кода Pyarmor соответствуют стандартному Python, но присутствуют специальные вызовы функций среды выполнения (runtime) Pyarmor.
# - Вызовы строк — это не ошибки, а маркеры, которые обрабатываются Pyarmor во время выполнения.
#
# Руководство по декомпиляции (без среды выполнения):
# 1. Игнорируйте зашифрованные байты после `#`; используйте только строку до `#`.
# 2. Удалите "__pyarmor_enter_xxx__"(b"<COAddr>...") и "__pyarmor_leave_xxx__"(b"<COAddr>...") (пролог/эпилог).
# 3. "__pyarmor_assert_xxx__"(A) не является настоящим оператором assert.
#    - Если A — это имя или читаемая строка: замените на A.
#    - Если A — это (X, "Y"): замените на X.Y.
#    - Если A — это (X, "Y", Z): замените на X.Y = Z.
#    - В противном случае: выберите наиболее подходящую/логичную замену.
# 4. "__pyarmor_bcc_xxx__"(...) указывает на машинный (нативный) код; тело функции недоступно. Добавьте комментарий.
# ================================

[Code]
    File Name: <frozen multithon.tl.types.users>
    Object Name: <module>
    Qualified Name: <module>
    Arg Count: 0
    Pos Only Arg Count: 0
    KW Only Arg Count: 0
    Stack Size: 5
    Flags: 0x20000000 (CO_PYARMOR_OBFUSCATED)
    [Names]
        '__assert_armored__'
        'tl.tlobject'
        'TLObject'
        'typing'
        'Optional'
        'List'
        'Union'
        'TYPE_CHECKING'
        'os'
        'struct'
        'datetime'
        'tl.types'
        'TypeChat'
        'TypeUser'
        'TypeUserFull'
        'UserFull'
        'Users'
        'UsersSlice'
    [Locals+Names]
    [Constants]
        '__pyarmor_assert_41751__'
        '__pyarmor_enter_41752__'
        b'<COAddr>\x07\x00\x00\x1a\xbe\x00\x00\x00\x00\x00\x00\x00\x00\x00\x00\x00\x00\x00\x00\x00'
        "File generated by TLObjects' generator. All changes will be ERASED"   # b'\x81\xc4\x11\x1f6\xba\xb9\xd7\x15\xff\x1f\xc1x\xe9\xfc\xc5\rD\xfb\x93\x86\xe4L\xc6\x00l\xb7OG\xf1\x19\xe04W2\x0c\x8c\xc5\xa6`X\xc8\xf4Q\x9d\xdb\x07F9\xeaS\xe8\xc7g\x0f\xe1;\xab\x99\x18Xn\x03rdm!'
        3
        (
            'TLObject'
        )
        0
        (
            'Optional'
            'List'
            'Union'
            'TYPE_CHECKING'
        )
        None
        (
            'datetime'
        )
        (
            'TypeChat'
            'TypeUser'
            'TypeUserFull'
        )
        [Code]
            File Name: <frozen multithon.tl.types.users>
            Object Name: UserFull
            Qualified Name: UserFull
            Arg Count: 0
            Pos Only Arg Count: 0
            KW Only Arg Count: 0
            Stack Size: 7
            Flags: 0x20000000 (CO_PYARMOR_OBFUSCATED)
            [Names]
                '__name__'
                '__module__'
                '__qualname__'
                '__assert_armored__'
                'CONSTRUCTOR_ID'
                'SUBCLASS_OF_ID'
                'List'
                '__init__'
                'to_dict'
                '_bytes'
                'classmethod'
                'from_reader'
            [Locals+Names]
            [Constants]
                'UserFull'
                '__pyarmor_assert_41754__'
                '__pyarmor_enter_41755__'
                b'<COAddr>\x05\x00\x00"f\x00\x00\x00\x00\x00\x00\x00\x00\x00\x00\x00\x00\x00\x00\x00'
                997004590
                0x83DF9DF5
                'full_user'
                'TypeUserFull'   # b'\x81\xd6\x01\x036\xcf\xad\xd7\t\xdc\x18\xcc`'
                'chats'
                'TypeChat'
                'users'
                'TypeUser'
                [Code]
                    File Name: <frozen multithon.tl.types.users>
                    Object Name: __init__
                    Qualified Name: UserFull.__init__
                    Arg Count: 4
                    Pos Only Arg Count: 0
                    KW Only Arg Count: 0
                    Stack Size: 5
                    Flags: 0x20000003 (CO_OPTIMIZED | CO_NEWLOCALS | CO_PYARMOR_OBFUSCATED)
                    [Names]
                        'full_user'
                        'chats'
                        'users'
                    [Locals+Names]
                        'self'
                        'full_user'
                        'chats'
                        'users'
                        '__assert_armored__'
                    [Constants]
                        '\n        Constructor for users.UserFull: Instance of UserFull.\n        '
                        '__pyarmor_assert_41757__'
                        '__pyarmor_enter_41758__'
                        b'<COAddr>\x05\x00\x00\x1a@\x00\x00\x00\x00\x00\x00\x00\x00\x00\x00\x00\x00\x00\x00\x00'
                        '__pyarmor_exit_41759__'
                        None
                    [Disassembly]
                        0       NOP                             
                        2       NOP                             
                        4       PUSH_NULL                       
                        6       LOAD_CONST                      2: '__pyarmor_enter_41758__'
                        8       LOAD_CONST                      3: b'<COAddr>\x05\x00\x00\x1a@\x00\x00\x00\x00\x00\x00\x00\x00\x00\x00\x00\x00\x00\x00\x00'
                        10      BUILD_TUPLE                     1
                        12      CALL_FUNCTION_EX                0
                        14      POP_TOP                         
                        16      RESUME                          0
                        18      NOP                             
                        20      NOP                             
                        22      NOP                             
                        24      NOP                             
                        26      NOP                             
                        28      LOAD_FAST                       1: full_user
                        30      LOAD_FAST                       0: self
                        32      STORE_ATTR                      0: full_user
                        42      LOAD_FAST                       2: chats
                        44      LOAD_FAST                       0: self
                        46      STORE_ATTR                      1: chats
                        56      LOAD_FAST                       3: users
                        58      LOAD_FAST                       0: self
                        60      STORE_ATTR                      2: users
                        70      LOAD_CONST                      5: None
                        72      NOP                             
                        74      NOP                             
                        76      NOP                             
                        78      JUMP_FORWARD                    19 (to 118)
                        86      POP_TOP                         
                        88      RETURN_CONST                    5: None
                        90      PUSH_EXC_INFO                   
                        92      PUSH_NULL                       
                        94      LOAD_CONST                      4: '__pyarmor_exit_41759__'
                        96      NOP                             
                        98      LOAD_CONST                      3: b'<COAddr>\x05\x00\x00\x1a@\x00\x00\x00\x00\x00\x00\x00\x00\x00\x00\x00\x00\x00\x00\x00'
                        100     CALL                            1
                        108     POP_TOP                         
                        110     RERAISE                         0
                        112     COPY                            3
                        114     POP_EXCEPT                      
                        116     RERAISE                         1
                        118     PUSH_NULL                       
                        120     LOAD_CONST                      4: '__pyarmor_exit_41759__'
                        122     LOAD_CONST                      3: b'<COAddr>\x05\x00\x00\x1a@\x00\x00\x00\x00\x00\x00\x00\x00\x00\x00\x00\x00\x00\x00\x00'
                        124     BUILD_TUPLE                     1
                        126     CALL_FUNCTION_EX                0
                        128     POP_TOP                         
                        130     RETURN_VALUE                    
                    [Exception Table]
                        28 to 70 -> 90 [0] 
                        90 to 112 -> 112 [1] lasti
                [Code]
                    File Name: <frozen multithon.tl.types.users>
                    Object Name: to_dict
                    Qualified Name: UserFull.to_dict
                    Arg Count: 1
                    Pos Only Arg Count: 0
                    KW Only Arg Count: 0
                    Stack Size: 14
                    Flags: 0x20000003 (CO_OPTIMIZED | CO_NEWLOCALS | CO_PYARMOR_OBFUSCATED)
                    [Names]
                        'isinstance'
                        'full_user'
                        'TLObject'
                        'to_dict'
                        'chats'
                        'users'
                    [Locals+Names]
                        'self'
                        '__assert_armored__'
                        '_var_var_0'
                    [Constants]
                        None
                        '__pyarmor_assert_41760__'
                        '__pyarmor_enter_41761__'
                        b'<COAddr>\x07\x00\x00\x1a\xdc\x01\x00\x00\x00\x00\x00\x00\x00\x00\x00\x00\x00\x00\x00\x00'
                        '_'
                        'UserFull'
                        'full_user'   # b'\x81\xe4\r\x1f?\xc5\xab\xc1\x1e\xe8'
                        'chats'
                        'users'
                        '__pyarmor_exit_41762__'
                    [Disassembly]
                        0       NOP                             
                        2       NOP                             
                        4       PUSH_NULL                       
                        6       LOAD_CONST                      2: '__pyarmor_enter_41761__'
                        8       LOAD_CONST                      3: b'<COAddr>\x07\x00\x00\x1a\xdc\x01\x00\x00\x00\x00\x00\x00\x00\x00\x00\x00\x00\x00\x00\x00'
                        10      BUILD_TUPLE                     1
                        12      CALL_FUNCTION_EX                0
                        14      POP_TOP                         
                        16      RESUME                          0
                        18      NOP                             
                        20      NOP                             
                        22      NOP                             
                        24      NOP                             
                        26      NOP                             
                        28      LOAD_CONST                      4: '_'
                        30      LOAD_CONST                      5: 'UserFull'
                        32      PUSH_NULL                       
                        34      LOAD_CONST                      1: '__pyarmor_assert_41760__'
                        36      LOAD_CONST                      6: 'full_user'   # b'\x81\xe4\r\x1f?\xc5\xab\xc1\x1e\xe8'
                        38      CALL                            1
                        46      LOAD_GLOBAL                     1: NULL + isinstance
                        56      LOAD_FAST                       0: self
                        58      LOAD_ATTR                       2: full_user
                        78      LOAD_GLOBAL                     4: TLObject
                        88      CALL                            2
                        96      POP_JUMP_IF_FALSE               26 (to 150)
                        98      LOAD_FAST                       0: self
                        100     LOAD_ATTR                       2: full_user
                        120     LOAD_ATTR                       7: to_dict
                        140     CALL                            0
                        148     JUMP_FORWARD                    11 (to 172)
                        150     LOAD_FAST                       0: self
                        152     LOAD_ATTR                       2: full_user
                        172     LOAD_CONST                      7: 'chats'
                        174     LOAD_FAST                       0: self
                        176     LOAD_ATTR                       8: chats
                        196     POP_JUMP_IF_NOT_NONE            2 (to 202)
                        198     BUILD_LIST                      0
                        200     JUMP_FORWARD                    57 (to 316)
                        202     LOAD_FAST                       0: self
                        204     LOAD_ATTR                       8: chats
                        224     GET_ITER                        
                        226     LOAD_FAST_AND_CLEAR             2: _var_var_0
                        228     SWAP                            2
                        230     BUILD_LIST                      0
                        232     SWAP                            2
                        234     FOR_ITER                        36 (to 308)
                        238     STORE_FAST                      2: _var_var_0
                        240     LOAD_GLOBAL                     1: NULL + isinstance
                        250     LOAD_FAST                       2: _var_var_0
                        252     LOAD_GLOBAL                     4: TLObject
                        262     CALL                            2
                        270     POP_JUMP_IF_FALSE               16 (to 304)
                        272     LOAD_FAST                       2: _var_var_0
                        274     LOAD_ATTR                       7: to_dict
                        294     CALL                            0
                        302     JUMP_FORWARD                    1 (to 306)
                        304     LOAD_FAST                       2: _var_var_0
                        306     LIST_APPEND                     2
                        308     JUMP_BACKWARD                   38 (to 234)
                        310     END_FOR                         
                        312     SWAP                            2
                        314     STORE_FAST                      2: _var_var_0
                        316     LOAD_CONST                      8: 'users'
                        318     LOAD_FAST                       0: self
                        320     LOAD_ATTR                       10: users
                        340     POP_JUMP_IF_NOT_NONE            2 (to 346)
                        342     BUILD_LIST                      0
                        344     JUMP_FORWARD                    57 (to 460)
                        346     LOAD_FAST                       0: self
                        348     LOAD_ATTR                       10: users
                        368     GET_ITER                        
                        370     LOAD_FAST_AND_CLEAR             2: _var_var_0
                        372     SWAP                            2
                        374     BUILD_LIST                      0
                        376     SWAP                            2
                        378     FOR_ITER                        36 (to 452)
                        382     STORE_FAST                      2: _var_var_0
                        384     LOAD_GLOBAL                     1: NULL + isinstance
                        394     LOAD_FAST                       2: _var_var_0
                        396     LOAD_GLOBAL                     4: TLObject
                        406     CALL                            2
                        414     POP_JUMP_IF_FALSE               16 (to 448)
                        416     LOAD_FAST                       2: _var_var_0
                        418     LOAD_ATTR                       7: to_dict
                        438     CALL                            0
                        446     JUMP_FORWARD                    1 (to 450)
                        448     LOAD_FAST                       2: _var_var_0
                        450     LIST_APPEND                     2
                        452     JUMP_BACKWARD                   38 (to 378)
                        454     END_FOR                         
                        456     SWAP                            2
                        458     STORE_FAST                      2: _var_var_0
                        460     BUILD_MAP                       4
                        462     NOP                             
                        464     NOP                             
                        466     NOP                             
                        468     JUMP_FORWARD                    30 (to 530)
                        470     CALL                            1
                        478     POP_TOP                         
                        480     RETURN_VALUE                    
                        482     SWAP                            2
                        484     POP_TOP                         
                        486     SWAP                            2
                        488     STORE_FAST                      2: _var_var_0
                        490     RERAISE                         0
                        492     SWAP                            2
                        494     POP_TOP                         
                        496     SWAP                            2
                        498     STORE_FAST                      2: _var_var_0
                        500     RERAISE                         0
                        502     PUSH_EXC_INFO                   
                        504     PUSH_NULL                       
                        506     LOAD_CONST                      9: '__pyarmor_exit_41762__'
                        508     NOP                             
                        510     LOAD_CONST                      3: b'<COAddr>\x07\x00\x00\x1a\xdc\x01\x00\x00\x00\x00\x00\x00\x00\x00\x00\x00\x00\x00\x00\x00'
                        512     CALL                            1
                        520     POP_TOP                         
                        522     RERAISE                         0
                        524     COPY                            3
                        526     POP_EXCEPT                      
                        528     RERAISE                         1
                        530     PUSH_NULL                       
                        532     LOAD_CONST                      9: '__pyarmor_exit_41762__'
                        534     LOAD_CONST                      3: b'<COAddr>\x07\x00\x00\x1a\xdc\x01\x00\x00\x00\x00\x00\x00\x00\x00\x00\x00\x00\x00\x00\x00'
                        536     BUILD_TUPLE                     1
                        538     CALL_FUNCTION_EX                0
                        540     POP_TOP                         
                        542     RETURN_VALUE                    
                    [Exception Table]
                        28 to 230 -> 502 [0] 
                        230 to 312 -> 482 [7] 
                        312 to 374 -> 502 [0] 
                        374 to 456 -> 492 [9] 
                        456 to 462 -> 502 [0] 
                        482 to 502 -> 502 [0] 
                        502 to 524 -> 524 [1] lasti
                [Code]
                    File Name: <frozen multithon.tl.types.users>
                    Object Name: _bytes
                    Qualified Name: UserFull._bytes
                    Arg Count: 1
                    Pos Only Arg Count: 0
                    KW Only Arg Count: 0
                    Stack Size: 14
                    Flags: 0x20000003 (CO_OPTIMIZED | CO_NEWLOCALS | CO_PYARMOR_OBFUSCATED)
                    [Names]
                        'join'
                        'full_user'
                        '_bytes'
                        'struct'
                        'pack'
                        'len'
                        'chats'
                        'users'
                    [Locals+Names]
                        'self'
                        '__assert_armored__'
                    [Constants]
                        None
                        '__pyarmor_assert_41763__'
                        '__pyarmor_enter_41764__'
                        b'<COAddr>\x05\x00\x00\x1a\x92\x01\x00\x00\x00\x00\x00\x00\x00\x00\x00\x00\x00\x00\x00\x00'
                        b''
                        b'.\x15m;'
                        b'\x15\xc4\xb5\x1c'
                        '<i'
                        [Code]
                            File Name: <frozen multithon.tl.types.users>
                            Object Name: <genexpr>
                            Qualified Name: UserFull._bytes.<locals>.<genexpr>
                            Arg Count: 1
                            Pos Only Arg Count: 0
                            KW Only Arg Count: 0
                            Stack Size: 3
                            Flags: 0x00000033 (CO_OPTIMIZED | CO_NEWLOCALS | CO_NESTED | CO_GENERATOR)
                            [Names]
                                '_bytes'
                            [Locals+Names]
                                '.0'
                                '_var_var_0'
                            [Constants]
                                None
                            [Disassembly]
                                0       RETURN_GENERATOR                
                                2       POP_TOP                         
                                4       RESUME                          0
                                6       LOAD_FAST                       0: .0
                                8       FOR_ITER                        20 (to 50)
                                12      STORE_FAST                      1: _var_var_0
                                14      LOAD_FAST                       1: _var_var_0
                                16      LOAD_ATTR                       1: _bytes
                                36      CALL                            0
                                44      YIELD_VALUE                     1
                                46      RESUME                          1
                                48      POP_TOP                         
                                50      JUMP_BACKWARD                   22 (to 8)
                                52      END_FOR                         
                                54      RETURN_CONST                    0: None
                                56      CALL_INTRINSIC_1                3 (INTRINSIC_STOPITERATION_ERROR)
                                58      RERAISE                         1
                            [Exception Table]
                                4 to 56 -> 56 [0] lasti
                        [Code]
                            File Name: <frozen multithon.tl.types.users>
                            Object Name: <genexpr>
                            Qualified Name: UserFull._bytes.<locals>.<genexpr>
                            Arg Count: 1
                            Pos Only Arg Count: 0
                            KW Only Arg Count: 0
                            Stack Size: 3
                            Flags: 0x00000033 (CO_OPTIMIZED | CO_NEWLOCALS | CO_NESTED | CO_GENERATOR)
                            [Names]
                                '_bytes'
                            [Locals+Names]
                                '.0'
                                '_var_var_0'
                            [Constants]
                                None
                            [Disassembly]
                                0       RETURN_GENERATOR                
                                2       POP_TOP                         
                                4       RESUME                          0
                                6       LOAD_FAST                       0: .0
                                8       FOR_ITER                        20 (to 50)
                                12      STORE_FAST                      1: _var_var_0
                                14      LOAD_FAST                       1: _var_var_0
                                16      LOAD_ATTR                       1: _bytes
                                36      CALL                            0
                                44      YIELD_VALUE                     1
                                46      RESUME                          1
                                48      POP_TOP                         
                                50      JUMP_BACKWARD                   22 (to 8)
                                52      END_FOR                         
                                54      RETURN_CONST                    0: None
                                56      CALL_INTRINSIC_1                3 (INTRINSIC_STOPITERATION_ERROR)
                                58      RERAISE                         1
                            [Exception Table]
                                4 to 56 -> 56 [0] lasti
                        '__pyarmor_exit_41765__'
                    [Disassembly]
                        0       NOP                             
                        2       NOP                             
                        4       PUSH_NULL                       
                        6       LOAD_CONST                      2: '__pyarmor_enter_41764__'
                        8       LOAD_CONST                      3: b'<COAddr>\x05\x00\x00\x1a\x92\x01\x00\x00\x00\x00\x00\x00\x00\x00\x00\x00\x00\x00\x00\x00'
                        10      BUILD_TUPLE                     1
                        12      CALL_FUNCTION_EX                0
                        14      POP_TOP                         
                        16      RESUME                          0
                        18      NOP                             
                        20      NOP                             
                        22      NOP                             
                        24      NOP                             
                        26      NOP                             
                        28      LOAD_CONST                      4: b''
                        30      LOAD_ATTR                       1: join
                        50      LOAD_CONST                      5: b'.\x15m;'
                        52      LOAD_FAST                       0: self
                        54      LOAD_ATTR                       2: full_user
                        74      LOAD_ATTR                       5: _bytes
                        94      CALL                            0
                        102     LOAD_CONST                      6: b'\x15\xc4\xb5\x1c'
                        104     LOAD_GLOBAL                     7: NULL + struct
                        114     LOAD_ATTR                       8: pack
                        134     LOAD_CONST                      7: '<i'
                        136     LOAD_GLOBAL                     11: NULL + len
                        146     LOAD_FAST                       0: self
                        148     LOAD_ATTR                       12: chats
                        168     CALL                            1
                        176     CALL                            2
                        184     LOAD_CONST                      4: b''
                        186     LOAD_ATTR                       1: join
                        206     LOAD_CONST                      8: <CODE> <genexpr>
                        208     MAKE_FUNCTION                   0
                        210     LOAD_FAST                       0: self
                        212     LOAD_ATTR                       12: chats
                        232     GET_ITER                        
                        234     CALL                            0
                        242     CALL                            1
                        250     LOAD_CONST                      6: b'\x15\xc4\xb5\x1c'
                        252     LOAD_GLOBAL                     7: NULL + struct
                        262     LOAD_ATTR                       8: pack
                        282     LOAD_CONST                      7: '<i'
                        284     LOAD_GLOBAL                     11: NULL + len
                        294     LOAD_FAST                       0: self
                        296     LOAD_ATTR                       14: users
                        316     CALL                            1
                        324     CALL                            2
                        332     LOAD_CONST                      4: b''
                        334     LOAD_ATTR                       1: join
                        354     LOAD_CONST                      9: <CODE> <genexpr>
                        356     MAKE_FUNCTION                   0
                        358     LOAD_FAST                       0: self
                        360     LOAD_ATTR                       14: users
                        380     GET_ITER                        
                        382     CALL                            0
                        390     CALL                            1
                        398     BUILD_TUPLE                     8
                        400     CALL                            1
                        408     NOP                             
                        410     NOP                             
                        412     NOP                             
                        414     JUMP_FORWARD                    20 (to 456)
                        416     CALL                            1
                        424     POP_TOP                         
                        426     RETURN_VALUE                    
                        428     PUSH_EXC_INFO                   
                        430     PUSH_NULL                       
                        432     LOAD_CONST                      10: '__pyarmor_exit_41765__'
                        434     NOP                             
                        436     LOAD_CONST                      3: b'<COAddr>\x05\x00\x00\x1a\x92\x01\x00\x00\x00\x00\x00\x00\x00\x00\x00\x00\x00\x00\x00\x00'
                        438     CALL                            1
                        446     POP_TOP                         
                        448     RERAISE                         0
                        450     COPY                            3
                        452     POP_EXCEPT                      
                        454     RERAISE                         1
                        456     PUSH_NULL                       
                        458     LOAD_CONST                      10: '__pyarmor_exit_41765__'
                        460     LOAD_CONST                      3: b'<COAddr>\x05\x00\x00\x1a\x92\x01\x00\x00\x00\x00\x00\x00\x00\x00\x00\x00\x00\x00\x00\x00'
                        462     BUILD_TUPLE                     1
                        464     CALL_FUNCTION_EX                0
                        466     POP_TOP                         
                        468     RETURN_VALUE                    
                    [Exception Table]
                        28 to 408 -> 428 [0] 
                        428 to 450 -> 450 [1] lasti
                [Code]
                    File Name: <frozen multithon.tl.types.users>
                    Object Name: from_reader
                    Qualified Name: UserFull.from_reader
                    Arg Count: 2
                    Pos Only Arg Count: 0
                    KW Only Arg Count: 0
                    Stack Size: 5
                    Flags: 0x20000003 (CO_OPTIMIZED | CO_NEWLOCALS | CO_PYARMOR_OBFUSCATED)
                    [Names]
                        'tgread_object'
                        'read_int'
                        'range'
                        'append'
                    [Locals+Names]
                        'cls'
                        'reader'
                        '__assert_armored__'
                        '_var_var_1'
                        '_var_var_2'
                        '_var_var_3'
                        '_var_var_4'
                        '_var_var_5'
                    [Constants]
                        None
                        '__pyarmor_assert_41766__'
                        '__pyarmor_enter_41767__'
                        b'<COAddr>\x07\x00\x00\x1a\x8e\x01\x00\x00\x00\x00\x00\x00\x00\x00\x00\x00\x00\x00\x00\x00'
                        (
                            'full_user'
                            'chats'
                            'users'
                        )
                        '__pyarmor_exit_41768__'
                    [Disassembly]
                        0       NOP                             
                        2       NOP                             
                        4       PUSH_NULL                       
                        6       LOAD_CONST                      2: '__pyarmor_enter_41767__'
                        8       LOAD_CONST                      3: b'<COAddr>\x07\x00\x00\x1a\x8e\x01\x00\x00\x00\x00\x00\x00\x00\x00\x00\x00\x00\x00\x00\x00'
                        10      BUILD_TUPLE                     1
                        12      CALL_FUNCTION_EX                0
                        14      POP_TOP                         
                        16      RESUME                          0
                        18      NOP                             
                        20      NOP                             
                        22      NOP                             
                        24      NOP                             
                        26      NOP                             
                        28      LOAD_FAST                       1: reader
                        30      LOAD_ATTR                       1: tgread_object
                        50      CALL                            0
                        58      STORE_FAST                      3: _var_var_1
                        60      LOAD_FAST                       1: reader
                        62      LOAD_ATTR                       3: read_int
                        82      CALL                            0
                        90      POP_TOP                         
                        92      BUILD_LIST                      0
                        94      STORE_FAST                      4: _var_var_2
                        96      LOAD_GLOBAL                     5: NULL + range
                        106     LOAD_FAST                       1: reader
                        108     LOAD_ATTR                       3: read_int
                        128     CALL                            0
                        136     CALL                            1
                        144     GET_ITER                        
                        146     FOR_ITER                        35 (to 218)
                        150     STORE_FAST                      5: _var_var_3
                        152     LOAD_FAST                       1: reader
                        154     LOAD_ATTR                       1: tgread_object
                        174     CALL                            0
                        182     STORE_FAST                      6: _var_var_4
                        184     LOAD_FAST                       4: _var_var_2
                        186     LOAD_ATTR                       7: append
                        206     LOAD_FAST                       6: _var_var_4
                        208     CALL                            1
                        216     POP_TOP                         
                        218     JUMP_BACKWARD                   37 (to 146)
                        220     END_FOR                         
                        222     LOAD_FAST                       1: reader
                        224     LOAD_ATTR                       3: read_int
                        244     CALL                            0
                        252     POP_TOP                         
                        254     BUILD_LIST                      0
                        256     STORE_FAST                      7: _var_var_5
                        258     LOAD_GLOBAL                     5: NULL + range
                        268     LOAD_FAST                       1: reader
                        270     LOAD_ATTR                       3: read_int
                        290     CALL                            0
                        298     CALL                            1
                        306     GET_ITER                        
                        308     FOR_ITER                        35 (to 380)
                        312     STORE_FAST                      5: _var_var_3
                        314     LOAD_FAST                       1: reader
                        316     LOAD_ATTR                       1: tgread_object
                        336     CALL                            0
                        344     STORE_FAST                      6: _var_var_4
                        346     LOAD_FAST                       7: _var_var_5
                        348     LOAD_ATTR                       7: append
                        368     LOAD_FAST                       6: _var_var_4
                        370     CALL                            1
                        378     POP_TOP                         
                        380     JUMP_BACKWARD                   37 (to 308)
                        382     END_FOR                         
                        384     PUSH_NULL                       
                        386     LOAD_FAST                       0: cls
                        388     LOAD_FAST                       3: _var_var_1
                        390     LOAD_FAST                       4: _var_var_2
                        392     LOAD_FAST                       7: _var_var_5
                        394     KW_NAMES                        4: ('full_user', 'chats', 'users')
                        396     CALL                            3
                        404     NOP                             
                        406     NOP                             
                        408     NOP                             
                        410     JUMP_FORWARD                    20 (to 452)
                        412     CALL                            1
                        420     POP_TOP                         
                        422     RETURN_VALUE                    
                        424     PUSH_EXC_INFO                   
                        426     PUSH_NULL                       
                        428     LOAD_CONST                      5: '__pyarmor_exit_41768__'
                        430     NOP                             
                        432     LOAD_CONST                      3: b'<COAddr>\x07\x00\x00\x1a\x8e\x01\x00\x00\x00\x00\x00\x00\x00\x00\x00\x00\x00\x00\x00\x00'
                        434     CALL                            1
                        442     POP_TOP                         
                        444     RERAISE                         0
                        446     COPY                            3
                        448     POP_EXCEPT                      
                        450     RERAISE                         1
                        452     PUSH_NULL                       
                        454     LOAD_CONST                      5: '__pyarmor_exit_41768__'
                        456     LOAD_CONST                      3: b'<COAddr>\x07\x00\x00\x1a\x8e\x01\x00\x00\x00\x00\x00\x00\x00\x00\x00\x00\x00\x00\x00\x00'
                        458     BUILD_TUPLE                     1
                        460     CALL_FUNCTION_EX                0
                        462     POP_TOP                         
                        464     RETURN_VALUE                    
                    [Exception Table]
                        28 to 404 -> 424 [0] 
                        424 to 446 -> 446 [1] lasti
                '__pyarmor_exit_41756__'
                None
            [Disassembly]
                0       NOP                             
                2       LOAD_NAME                       0: __name__
                4       STORE_NAME                      1: __module__
                6       LOAD_CONST                      0: 'UserFull'
                8       STORE_NAME                      2: __qualname__
                10      NOP                             
                12      PUSH_NULL                       
                14      LOAD_CONST                      2: '__pyarmor_enter_41755__'
                16      LOAD_CONST                      3: b'<COAddr>\x05\x00\x00"f\x00\x00\x00\x00\x00\x00\x00\x00\x00\x00\x00\x00\x00\x00\x00'
                18      BUILD_TUPLE                     1
                20      CALL_FUNCTION_EX                0
                22      POP_TOP                         
                24      RESUME                          0
                26      NOP                             
                28      NOP                             
                30      NOP                             
                32      NOP                             
                34      NOP                             
                36      LOAD_CONST                      4: 997004590
                38      STORE_NAME                      4: CONSTRUCTOR_ID
                40      LOAD_CONST                      5: 0x83DF9DF5
                42      STORE_NAME                      5: SUBCLASS_OF_ID
                44      LOAD_CONST                      6: 'full_user'
                46      PUSH_NULL                       
                48      LOAD_CONST                      1: '__pyarmor_assert_41754__'
                50      LOAD_CONST                      7: 'TypeUserFull'   # b'\x81\xd6\x01\x036\xcf\xad\xd7\t\xdc\x18\xcc`'
                52      CALL                            1
                60      LOAD_CONST                      8: 'chats'
                62      LOAD_NAME                       6: List
                64      LOAD_CONST                      9: 'TypeChat'
                66      BINARY_SUBSCR                   
                70      LOAD_CONST                      10: 'users'
                72      LOAD_NAME                       6: List
                74      LOAD_CONST                      11: 'TypeUser'
                76      BINARY_SUBSCR                   
                80      BUILD_TUPLE                     6
                82      LOAD_CONST                      12: <CODE> __init__
                84      MAKE_FUNCTION                   4
                86      STORE_NAME                      7: __init__
                88      LOAD_CONST                      13: <CODE> to_dict
                90      MAKE_FUNCTION                   0
                92      STORE_NAME                      8: to_dict
                94      LOAD_CONST                      14: <CODE> _bytes
                96      MAKE_FUNCTION                   0
                98      STORE_NAME                      9: _bytes
                100     LOAD_NAME                       10: classmethod
                102     LOAD_CONST                      15: <CODE> from_reader
                104     MAKE_FUNCTION                   0
                106     CALL                            0
                114     STORE_NAME                      11: from_reader
                116     LOAD_CONST                      17: None
                118     NOP                             
                120     NOP                             
                122     NOP                             
                124     JUMP_FORWARD                    19 (to 164)
                132     POP_TOP                         
                134     RETURN_CONST                    17: None
                136     PUSH_EXC_INFO                   
                138     PUSH_NULL                       
                140     LOAD_CONST                      16: '__pyarmor_exit_41756__'
                142     NOP                             
                144     LOAD_CONST                      3: b'<COAddr>\x05\x00\x00"f\x00\x00\x00\x00\x00\x00\x00\x00\x00\x00\x00\x00\x00\x00\x00'
                146     CALL                            1
                154     POP_TOP                         
                156     RERAISE                         0
                158     COPY                            3
                160     POP_EXCEPT                      
                162     RERAISE                         1
                164     PUSH_NULL                       
                166     LOAD_CONST                      16: '__pyarmor_exit_41756__'
                168     LOAD_CONST                      3: b'<COAddr>\x05\x00\x00"f\x00\x00\x00\x00\x00\x00\x00\x00\x00\x00\x00\x00\x00\x00\x00'
                170     BUILD_TUPLE                     1
                172     CALL_FUNCTION_EX                0
                174     POP_TOP                         
                176     RETURN_VALUE                    
            [Exception Table]
                36 to 116 -> 136 [0] 
                136 to 158 -> 158 [1] lasti
        'UserFull'
        [Code]
            File Name: <frozen multithon.tl.types.users>
            Object Name: Users
            Qualified Name: Users
            Arg Count: 0
            Pos Only Arg Count: 0
            KW Only Arg Count: 0
            Stack Size: 5
            Flags: 0x20000000 (CO_PYARMOR_OBFUSCATED)
            [Names]
                '__name__'
                '__module__'
                '__qualname__'
                '__assert_armored__'
                'CONSTRUCTOR_ID'
                'SUBCLASS_OF_ID'
                'List'
                '__init__'
                'to_dict'
                '_bytes'
                'classmethod'
                'from_reader'
            [Locals+Names]
            [Constants]
                'Users'
                '__pyarmor_assert_41769__'
                '__pyarmor_enter_41770__'
                b'<COAddr>\x07\x00\x00"L\x00\x00\x00\x00\x00\x00\x00\x00\x00\x00\x00\x00\x00\x00\x00'
                1658259128
                0xF24BF0C0
                'users'
                'TypeUser'
                [Code]
                    File Name: <frozen multithon.tl.types.users>
                    Object Name: __init__
                    Qualified Name: Users.__init__
                    Arg Count: 2
                    Pos Only Arg Count: 0
                    KW Only Arg Count: 0
                    Stack Size: 5
                    Flags: 0x20000003 (CO_OPTIMIZED | CO_NEWLOCALS | CO_PYARMOR_OBFUSCATED)
                    [Names]
                        'users'
                    [Locals+Names]
                        'self'
                        'users'
                        '__assert_armored__'
                    [Constants]
                        '\n        Constructor for users.Users: Instance of either Users, UsersSlice.\n        '
                        '__pyarmor_assert_41772__'
                        '__pyarmor_enter_41773__'
                        b'<COAddr>\x07\x00\x00\x1a$\x00\x00\x00\x00\x00\x00\x00\x00\x00\x00\x00\x00\x00\x00\x00'
                        '__pyarmor_exit_41774__'
                        None
                    [Disassembly]
                        0       NOP                             
                        2       NOP                             
                        4       PUSH_NULL                       
                        6       LOAD_CONST                      2: '__pyarmor_enter_41773__'
                        8       LOAD_CONST                      3: b'<COAddr>\x07\x00\x00\x1a$\x00\x00\x00\x00\x00\x00\x00\x00\x00\x00\x00\x00\x00\x00\x00'
                        10      BUILD_TUPLE                     1
                        12      CALL_FUNCTION_EX                0
                        14      POP_TOP                         
                        16      RESUME                          0
                        18      NOP                             
                        20      NOP                             
                        22      NOP                             
                        24      NOP                             
                        26      NOP                             
                        28      LOAD_FAST                       1: users
                        30      LOAD_FAST                       0: self
                        32      STORE_ATTR                      0: users
                        42      LOAD_CONST                      5: None
                        44      NOP                             
                        46      NOP                             
                        48      NOP                             
                        50      JUMP_FORWARD                    19 (to 90)
                        58      POP_TOP                         
                        60      RETURN_CONST                    5: None
                        62      PUSH_EXC_INFO                   
                        64      PUSH_NULL                       
                        66      LOAD_CONST                      4: '__pyarmor_exit_41774__'
                        68      NOP                             
                        70      LOAD_CONST                      3: b'<COAddr>\x07\x00\x00\x1a$\x00\x00\x00\x00\x00\x00\x00\x00\x00\x00\x00\x00\x00\x00\x00'
                        72      CALL                            1
                        80      POP_TOP                         
                        82      RERAISE                         0
                        84      COPY                            3
                        86      POP_EXCEPT                      
                        88      RERAISE                         1
                        90      PUSH_NULL                       
                        92      LOAD_CONST                      4: '__pyarmor_exit_41774__'
                        94      LOAD_CONST                      3: b'<COAddr>\x07\x00\x00\x1a$\x00\x00\x00\x00\x00\x00\x00\x00\x00\x00\x00\x00\x00\x00\x00'
                        96      BUILD_TUPLE                     1
                        98      CALL_FUNCTION_EX                0
                        100     POP_TOP                         
                        102     RETURN_VALUE                    
                    [Exception Table]
                        28 to 42 -> 62 [0] 
                        62 to 84 -> 84 [1] lasti
                [Code]
                    File Name: <frozen multithon.tl.types.users>
                    Object Name: to_dict
                    Qualified Name: Users.to_dict
                    Arg Count: 1
                    Pos Only Arg Count: 0
                    KW Only Arg Count: 0
                    Stack Size: 8
                    Flags: 0x20000003 (CO_OPTIMIZED | CO_NEWLOCALS | CO_PYARMOR_OBFUSCATED)
                    [Names]
                        'users'
                        'isinstance'
                        'TLObject'
                        'to_dict'
                    [Locals+Names]
                        'self'
                        '__assert_armored__'
                        '_var_var_0'
                    [Constants]
                        None
                        '__pyarmor_assert_41775__'
                        '__pyarmor_enter_41776__'
                        b'<COAddr>\x05\x00\x00\x1a\xb4\x00\x00\x00\x00\x00\x00\x00\x00\x00\x00\x00\x00\x00\x00\x00'
                        'Users'
                        (
                            '_'
                            'users'
                        )
                        '__pyarmor_exit_41777__'
                    [Disassembly]
                        0       NOP                             
                        2       NOP                             
                        4       PUSH_NULL                       
                        6       LOAD_CONST                      2: '__pyarmor_enter_41776__'
                        8       LOAD_CONST                      3: b'<COAddr>\x05\x00\x00\x1a\xb4\x00\x00\x00\x00\x00\x00\x00\x00\x00\x00\x00\x00\x00\x00\x00'
                        10      BUILD_TUPLE                     1
                        12      CALL_FUNCTION_EX                0
                        14      POP_TOP                         
                        16      RESUME                          0
                        18      NOP                             
                        20      NOP                             
                        22      NOP                             
                        24      NOP                             
                        26      NOP                             
                        28      LOAD_CONST                      4: 'Users'
                        30      LOAD_FAST                       0: self
                        32      LOAD_ATTR                       0: users
                        52      POP_JUMP_IF_NOT_NONE            2 (to 58)
                        54      BUILD_LIST                      0
                        56      JUMP_FORWARD                    57 (to 172)
                        58      LOAD_FAST                       0: self
                        60      LOAD_ATTR                       0: users
                        80      GET_ITER                        
                        82      LOAD_FAST_AND_CLEAR             2: _var_var_0
                        84      SWAP                            2
                        86      BUILD_LIST                      0
                        88      SWAP                            2
                        90      FOR_ITER                        36 (to 164)
                        94      STORE_FAST                      2: _var_var_0
                        96      LOAD_GLOBAL                     3: NULL + isinstance
                        106     LOAD_FAST                       2: _var_var_0
                        108     LOAD_GLOBAL                     4: TLObject
                        118     CALL                            2
                        126     POP_JUMP_IF_FALSE               16 (to 160)
                        128     LOAD_FAST                       2: _var_var_0
                        130     LOAD_ATTR                       7: to_dict
                        150     CALL                            0
                        158     JUMP_FORWARD                    1 (to 162)
                        160     LOAD_FAST                       2: _var_var_0
                        162     LIST_APPEND                     2
                        164     JUMP_BACKWARD                   38 (to 90)
                        166     END_FOR                         
                        168     SWAP                            2
                        170     STORE_FAST                      2: _var_var_0
                        172     LOAD_CONST                      5: ('_', 'users')
                        174     BUILD_CONST_KEY_MAP             2
                        176     NOP                             
                        178     NOP                             
                        180     NOP                             
                        182     JUMP_FORWARD                    25 (to 234)
                        184     CALL                            1
                        192     POP_TOP                         
                        194     RETURN_VALUE                    
                        196     SWAP                            2
                        198     POP_TOP                         
                        200     SWAP                            2
                        202     STORE_FAST                      2: _var_var_0
                        204     RERAISE                         0
                        206     PUSH_EXC_INFO                   
                        208     PUSH_NULL                       
                        210     LOAD_CONST                      6: '__pyarmor_exit_41777__'
                        212     NOP                             
                        214     LOAD_CONST                      3: b'<COAddr>\x05\x00\x00\x1a\xb4\x00\x00\x00\x00\x00\x00\x00\x00\x00\x00\x00\x00\x00\x00\x00'
                        216     CALL                            1
                        224     POP_TOP                         
                        226     RERAISE                         0
                        228     COPY                            3
                        230     POP_EXCEPT                      
                        232     RERAISE                         1
                        234     PUSH_NULL                       
                        236     LOAD_CONST                      6: '__pyarmor_exit_41777__'
                        238     LOAD_CONST                      3: b'<COAddr>\x05\x00\x00\x1a\xb4\x00\x00\x00\x00\x00\x00\x00\x00\x00\x00\x00\x00\x00\x00\x00'
                        240     BUILD_TUPLE                     1
                        242     CALL_FUNCTION_EX                0
                        244     POP_TOP                         
                        246     RETURN_VALUE                    
                    [Exception Table]
                        28 to 86 -> 206 [0] 
                        86 to 168 -> 196 [3] 
                        168 to 176 -> 206 [0] 
                        196 to 206 -> 206 [0] 
                        206 to 228 -> 228 [1] lasti
                [Code]
                    File Name: <frozen multithon.tl.types.users>
                    Object Name: _bytes
                    Qualified Name: Users._bytes
                    Arg Count: 1
                    Pos Only Arg Count: 0
                    KW Only Arg Count: 0
                    Stack Size: 10
                    Flags: 0x20000003 (CO_OPTIMIZED | CO_NEWLOCALS | CO_PYARMOR_OBFUSCATED)
                    [Names]
                        'join'
                        'struct'
                        'pack'
                        'len'
                        'users'
                    [Locals+Names]
                        'self'
                        '__assert_armored__'
                    [Constants]
                        None
                        '__pyarmor_assert_41778__'
                        '__pyarmor_enter_41779__'
                        b'<COAddr>\x05\x00\x00\x1a\xcc\x00\x00\x00\x00\x00\x00\x00\x00\x00\x00\x00\x00\x00\x00\x00'
                        b''
                        b'\xb8\x06\xd7b'
                        b'\x15\xc4\xb5\x1c'
                        '<i'
                        [Code]
                            File Name: <frozen multithon.tl.types.users>
                            Object Name: <genexpr>
                            Qualified Name: Users._bytes.<locals>.<genexpr>
                            Arg Count: 1
                            Pos Only Arg Count: 0
                            KW Only Arg Count: 0
                            Stack Size: 3
                            Flags: 0x00000033 (CO_OPTIMIZED | CO_NEWLOCALS | CO_NESTED | CO_GENERATOR)
                            [Names]
                                '_bytes'
                            [Locals+Names]
                                '.0'
                                '_var_var_0'
                            [Constants]
                                None
                            [Disassembly]
                                0       RETURN_GENERATOR                
                                2       POP_TOP                         
                                4       RESUME                          0
                                6       LOAD_FAST                       0: .0
                                8       FOR_ITER                        20 (to 50)
                                12      STORE_FAST                      1: _var_var_0
                                14      LOAD_FAST                       1: _var_var_0
                                16      LOAD_ATTR                       1: _bytes
                                36      CALL                            0
                                44      YIELD_VALUE                     1
                                46      RESUME                          1
                                48      POP_TOP                         
                                50      JUMP_BACKWARD                   22 (to 8)
                                52      END_FOR                         
                                54      RETURN_CONST                    0: None
                                56      CALL_INTRINSIC_1                3 (INTRINSIC_STOPITERATION_ERROR)
                                58      RERAISE                         1
                            [Exception Table]
                                4 to 56 -> 56 [0] lasti
                        '__pyarmor_exit_41780__'
                    [Disassembly]
                        0       NOP                             
                        2       NOP                             
                        4       PUSH_NULL                       
                        6       LOAD_CONST                      2: '__pyarmor_enter_41779__'
                        8       LOAD_CONST                      3: b'<COAddr>\x05\x00\x00\x1a\xcc\x00\x00\x00\x00\x00\x00\x00\x00\x00\x00\x00\x00\x00\x00\x00'
                        10      BUILD_TUPLE                     1
                        12      CALL_FUNCTION_EX                0
                        14      POP_TOP                         
                        16      RESUME                          0
                        18      NOP                             
                        20      NOP                             
                        22      NOP                             
                        24      NOP                             
                        26      NOP                             
                        28      LOAD_CONST                      4: b''
                        30      LOAD_ATTR                       1: join
                        50      LOAD_CONST                      5: b'\xb8\x06\xd7b'
                        52      LOAD_CONST                      6: b'\x15\xc4\xb5\x1c'
                        54      LOAD_GLOBAL                     3: NULL + struct
                        64      LOAD_ATTR                       4: pack
                        84      LOAD_CONST                      7: '<i'
                        86      LOAD_GLOBAL                     7: NULL + len
                        96      LOAD_FAST                       0: self
                        98      LOAD_ATTR                       8: users
                        118     CALL                            1
                        126     CALL                            2
                        134     LOAD_CONST                      4: b''
                        136     LOAD_ATTR                       1: join
                        156     LOAD_CONST                      8: <CODE> <genexpr>
                        158     MAKE_FUNCTION                   0
                        160     LOAD_FAST                       0: self
                        162     LOAD_ATTR                       8: users
                        182     GET_ITER                        
                        184     CALL                            0
                        192     CALL                            1
                        200     BUILD_TUPLE                     4
                        202     CALL                            1
                        210     NOP                             
                        212     NOP                             
                        214     NOP                             
                        216     JUMP_FORWARD                    20 (to 258)
                        218     CALL                            1
                        226     POP_TOP                         
                        228     RETURN_VALUE                    
                        230     PUSH_EXC_INFO                   
                        232     PUSH_NULL                       
                        234     LOAD_CONST                      9: '__pyarmor_exit_41780__'
                        236     NOP                             
                        238     LOAD_CONST                      3: b'<COAddr>\x05\x00\x00\x1a\xcc\x00\x00\x00\x00\x00\x00\x00\x00\x00\x00\x00\x00\x00\x00\x00'
                        240     CALL                            1
                        248     POP_TOP                         
                        250     RERAISE                         0
                        252     COPY                            3
                        254     POP_EXCEPT                      
                        256     RERAISE                         1
                        258     PUSH_NULL                       
                        260     LOAD_CONST                      9: '__pyarmor_exit_41780__'
                        262     LOAD_CONST                      3: b'<COAddr>\x05\x00\x00\x1a\xcc\x00\x00\x00\x00\x00\x00\x00\x00\x00\x00\x00\x00\x00\x00\x00'
                        264     BUILD_TUPLE                     1
                        266     CALL_FUNCTION_EX                0
                        268     POP_TOP                         
                        270     RETURN_VALUE                    
                    [Exception Table]
                        28 to 210 -> 230 [0] 
                        230 to 252 -> 252 [1] lasti
                [Code]
                    File Name: <frozen multithon.tl.types.users>
                    Object Name: from_reader
                    Qualified Name: Users.from_reader
                    Arg Count: 2
                    Pos Only Arg Count: 0
                    KW Only Arg Count: 0
                    Stack Size: 5
                    Flags: 0x20000003 (CO_OPTIMIZED | CO_NEWLOCALS | CO_PYARMOR_OBFUSCATED)
                    [Names]
                        'read_int'
                        'range'
                        'tgread_object'
                        'append'
                    [Locals+Names]
                        'cls'
                        'reader'
                        '__assert_armored__'
                        '_var_var_5'
                        '_var_var_3'
                        '_var_var_4'
                    [Constants]
                        None
                        '__pyarmor_assert_41781__'
                        '__pyarmor_enter_41782__'
                        b'<COAddr>\x05\x00\x00\x1a\xc8\x00\x00\x00\x00\x00\x00\x00\x00\x00\x00\x00\x00\x00\x00\x00'
                        (
                            'users'
                        )
                        '__pyarmor_exit_41783__'
                    [Disassembly]
                        0       NOP                             
                        2       NOP                             
                        4       PUSH_NULL                       
                        6       LOAD_CONST                      2: '__pyarmor_enter_41782__'
                        8       LOAD_CONST                      3: b'<COAddr>\x05\x00\x00\x1a\xc8\x00\x00\x00\x00\x00\x00\x00\x00\x00\x00\x00\x00\x00\x00\x00'
                        10      BUILD_TUPLE                     1
                        12      CALL_FUNCTION_EX                0
                        14      POP_TOP                         
                        16      RESUME                          0
                        18      NOP                             
                        20      NOP                             
                        22      NOP                             
                        24      NOP                             
                        26      NOP                             
                        28      LOAD_FAST                       1: reader
                        30      LOAD_ATTR                       1: read_int
                        50      CALL                            0
                        58      POP_TOP                         
                        60      BUILD_LIST                      0
                        62      STORE_FAST                      3: _var_var_5
                        64      LOAD_GLOBAL                     3: NULL + range
                        74      LOAD_FAST                       1: reader
                        76      LOAD_ATTR                       1: read_int
                        96      CALL                            0
                        104     CALL                            1
                        112     GET_ITER                        
                        114     FOR_ITER                        35 (to 186)
                        118     STORE_FAST                      4: _var_var_3
                        120     LOAD_FAST                       1: reader
                        122     LOAD_ATTR                       5: tgread_object
                        142     CALL                            0
                        150     STORE_FAST                      5: _var_var_4
                        152     LOAD_FAST                       3: _var_var_5
                        154     LOAD_ATTR                       7: append
                        174     LOAD_FAST                       5: _var_var_4
                        176     CALL                            1
                        184     POP_TOP                         
                        186     JUMP_BACKWARD                   37 (to 114)
                        188     END_FOR                         
                        190     PUSH_NULL                       
                        192     LOAD_FAST                       0: cls
                        194     LOAD_FAST                       3: _var_var_5
                        196     KW_NAMES                        4: ('users',)
                        198     CALL                            1
                        206     NOP                             
                        208     NOP                             
                        210     NOP                             
                        212     JUMP_FORWARD                    20 (to 254)
                        214     CALL                            1
                        222     POP_TOP                         
                        224     RETURN_VALUE                    
                        226     PUSH_EXC_INFO                   
                        228     PUSH_NULL                       
                        230     LOAD_CONST                      5: '__pyarmor_exit_41783__'
                        232     NOP                             
                        234     LOAD_CONST                      3: b'<COAddr>\x05\x00\x00\x1a\xc8\x00\x00\x00\x00\x00\x00\x00\x00\x00\x00\x00\x00\x00\x00\x00'
                        236     CALL                            1
                        244     POP_TOP                         
                        246     RERAISE                         0
                        248     COPY                            3
                        250     POP_EXCEPT                      
                        252     RERAISE                         1
                        254     PUSH_NULL                       
                        256     LOAD_CONST                      5: '__pyarmor_exit_41783__'
                        258     LOAD_CONST                      3: b'<COAddr>\x05\x00\x00\x1a\xc8\x00\x00\x00\x00\x00\x00\x00\x00\x00\x00\x00\x00\x00\x00\x00'
                        260     BUILD_TUPLE                     1
                        262     CALL_FUNCTION_EX                0
                        264     POP_TOP                         
                        266     RETURN_VALUE                    
                    [Exception Table]
                        28 to 206 -> 226 [0] 
                        226 to 248 -> 248 [1] lasti
                '__pyarmor_exit_41771__'
                None
            [Disassembly]
                0       NOP                             
                2       LOAD_NAME                       0: __name__
                4       STORE_NAME                      1: __module__
                6       LOAD_CONST                      0: 'Users'
                8       STORE_NAME                      2: __qualname__
                10      NOP                             
                12      PUSH_NULL                       
                14      LOAD_CONST                      2: '__pyarmor_enter_41770__'
                16      LOAD_CONST                      3: b'<COAddr>\x07\x00\x00"L\x00\x00\x00\x00\x00\x00\x00\x00\x00\x00\x00\x00\x00\x00\x00'
                18      BUILD_TUPLE                     1
                20      CALL_FUNCTION_EX                0
                22      POP_TOP                         
                24      RESUME                          0
                26      NOP                             
                28      NOP                             
                30      NOP                             
                32      NOP                             
                34      NOP                             
                36      LOAD_CONST                      4: 1658259128
                38      STORE_NAME                      4: CONSTRUCTOR_ID
                40      LOAD_CONST                      5: 0xF24BF0C0
                42      STORE_NAME                      5: SUBCLASS_OF_ID
                44      LOAD_CONST                      6: 'users'
                46      LOAD_NAME                       6: List
                48      LOAD_CONST                      7: 'TypeUser'
                50      BINARY_SUBSCR                   
                54      BUILD_TUPLE                     2
                56      LOAD_CONST                      8: <CODE> __init__
                58      MAKE_FUNCTION                   4
                60      STORE_NAME                      7: __init__
                62      LOAD_CONST                      9: <CODE> to_dict
                64      MAKE_FUNCTION                   0
                66      STORE_NAME                      8: to_dict
                68      LOAD_CONST                      10: <CODE> _bytes
                70      MAKE_FUNCTION                   0
                72      STORE_NAME                      9: _bytes
                74      LOAD_NAME                       10: classmethod
                76      LOAD_CONST                      11: <CODE> from_reader
                78      MAKE_FUNCTION                   0
                80      CALL                            0
                88      STORE_NAME                      11: from_reader
                90      LOAD_CONST                      13: None
                92      NOP                             
                94      NOP                             
                96      NOP                             
                98      JUMP_FORWARD                    19 (to 138)
                106     POP_TOP                         
                108     RETURN_CONST                    13: None
                110     PUSH_EXC_INFO                   
                112     PUSH_NULL                       
                114     LOAD_CONST                      12: '__pyarmor_exit_41771__'
                116     NOP                             
                118     LOAD_CONST                      3: b'<COAddr>\x07\x00\x00"L\x00\x00\x00\x00\x00\x00\x00\x00\x00\x00\x00\x00\x00\x00\x00'
                120     CALL                            1
                128     POP_TOP                         
                130     RERAISE                         0
                132     COPY                            3
                134     POP_EXCEPT                      
                136     RERAISE                         1
                138     PUSH_NULL                       
                140     LOAD_CONST                      12: '__pyarmor_exit_41771__'
                142     LOAD_CONST                      3: b'<COAddr>\x07\x00\x00"L\x00\x00\x00\x00\x00\x00\x00\x00\x00\x00\x00\x00\x00\x00\x00'
                144     BUILD_TUPLE                     1
                146     CALL_FUNCTION_EX                0
                148     POP_TOP                         
                150     RETURN_VALUE                    
            [Exception Table]
                36 to 90 -> 110 [0] 
                110 to 132 -> 132 [1] lasti
        'Users'
        [Code]
            File Name: <frozen multithon.tl.types.users>
            Object Name: UsersSlice
            Qualified Name: UsersSlice
            Arg Count: 0
            Pos Only Arg Count: 0
            KW Only Arg Count: 0
            Stack Size: 5
            Flags: 0x20000000 (CO_PYARMOR_OBFUSCATED)
            [Names]
                '__name__'
                '__module__'
                '__qualname__'
                '__assert_armored__'
                'CONSTRUCTOR_ID'
                'SUBCLASS_OF_ID'
                'int'
                'List'
                '__init__'
                'to_dict'
                '_bytes'
                'classmethod'
                'from_reader'
            [Locals+Names]
            [Constants]
                'UsersSlice'
                '__pyarmor_assert_41784__'
                '__pyarmor_enter_41785__'
                b'<COAddr>\x05\x00\x00"P\x00\x00\x00\x00\x00\x00\x00\x00\x00\x00\x00\x00\x00\x00\x00'
                828000628
                0xF24BF0C0
                'count'
                'users'
                'TypeUser'
                [Code]
                    File Name: <frozen multithon.tl.types.users>
                    Object Name: __init__
                    Qualified Name: UsersSlice.__init__
                    Arg Count: 3
                    Pos Only Arg Count: 0
                    KW Only Arg Count: 0
                    Stack Size: 5
                    Flags: 0x20000003 (CO_OPTIMIZED | CO_NEWLOCALS | CO_PYARMOR_OBFUSCATED)
                    [Names]
                        'count'
                        'users'
                    [Locals+Names]
                        'self'
                        'count'
                        'users'
                        '__assert_armored__'
                    [Constants]
                        '\n        Constructor for users.Users: Instance of either Users, UsersSlice.\n        '
                        '__pyarmor_assert_41787__'
                        '__pyarmor_enter_41788__'
                        b'<COAddr>\x07\x00\x00\x1a2\x00\x00\x00\x00\x00\x00\x00\x00\x00\x00\x00\x00\x00\x00\x00'
                        '__pyarmor_exit_41789__'
                        None
                    [Disassembly]
                        0       NOP                             
                        2       NOP                             
                        4       PUSH_NULL                       
                        6       LOAD_CONST                      2: '__pyarmor_enter_41788__'
                        8       LOAD_CONST                      3: b'<COAddr>\x07\x00\x00\x1a2\x00\x00\x00\x00\x00\x00\x00\x00\x00\x00\x00\x00\x00\x00\x00'
                        10      BUILD_TUPLE                     1
                        12      CALL_FUNCTION_EX                0
                        14      POP_TOP                         
                        16      RESUME                          0
                        18      NOP                             
                        20      NOP                             
                        22      NOP                             
                        24      NOP                             
                        26      NOP                             
                        28      LOAD_FAST                       1: count
                        30      LOAD_FAST                       0: self
                        32      STORE_ATTR                      0: count
                        42      LOAD_FAST                       2: users
                        44      LOAD_FAST                       0: self
                        46      STORE_ATTR                      1: users
                        56      LOAD_CONST                      5: None
                        58      NOP                             
                        60      NOP                             
                        62      NOP                             
                        64      JUMP_FORWARD                    19 (to 104)
                        72      POP_TOP                         
                        74      RETURN_CONST                    5: None
                        76      PUSH_EXC_INFO                   
                        78      PUSH_NULL                       
                        80      LOAD_CONST                      4: '__pyarmor_exit_41789__'
                        82      NOP                             
                        84      LOAD_CONST                      3: b'<COAddr>\x07\x00\x00\x1a2\x00\x00\x00\x00\x00\x00\x00\x00\x00\x00\x00\x00\x00\x00\x00'
                        86      CALL                            1
                        94      POP_TOP                         
                        96      RERAISE                         0
                        98      COPY                            3
                        100     POP_EXCEPT                      
                        102     RERAISE                         1
                        104     PUSH_NULL                       
                        106     LOAD_CONST                      4: '__pyarmor_exit_41789__'
                        108     LOAD_CONST                      3: b'<COAddr>\x07\x00\x00\x1a2\x00\x00\x00\x00\x00\x00\x00\x00\x00\x00\x00\x00\x00\x00\x00'
                        110     BUILD_TUPLE                     1
                        112     CALL_FUNCTION_EX                0
                        114     POP_TOP                         
                        116     RETURN_VALUE                    
                    [Exception Table]
                        28 to 56 -> 76 [0] 
                        76 to 98 -> 98 [1] lasti
                [Code]
                    File Name: <frozen multithon.tl.types.users>
                    Object Name: to_dict
                    Qualified Name: UsersSlice.to_dict
                    Arg Count: 1
                    Pos Only Arg Count: 0
                    KW Only Arg Count: 0
                    Stack Size: 9
                    Flags: 0x20000003 (CO_OPTIMIZED | CO_NEWLOCALS | CO_PYARMOR_OBFUSCATED)
                    [Names]
                        'count'
                        'users'
                        'isinstance'
                        'TLObject'
                        'to_dict'
                    [Locals+Names]
                        'self'
                        '__assert_armored__'
                        '_var_var_0'
                    [Constants]
                        None
                        '__pyarmor_assert_41790__'
                        '__pyarmor_enter_41791__'
                        b'<COAddr>\x05\x00\x00\x1a\xd6\x00\x00\x00\x00\x00\x00\x00\x00\x00\x00\x00\x00\x00\x00\x00'
                        'UsersSlice'   # b'\x81\xd7\x0b\x16!\xe9\x8d\xde\x12\xf9\x08'
                        (
                            '_'
                            'count'
                            'users'
                        )
                        '__pyarmor_exit_41792__'
                    [Disassembly]
                        0       NOP                             
                        2       NOP                             
                        4       PUSH_NULL                       
                        6       LOAD_CONST                      2: '__pyarmor_enter_41791__'
                        8       LOAD_CONST                      3: b'<COAddr>\x05\x00\x00\x1a\xd6\x00\x00\x00\x00\x00\x00\x00\x00\x00\x00\x00\x00\x00\x00\x00'
                        10      BUILD_TUPLE                     1
                        12      CALL_FUNCTION_EX                0
                        14      POP_TOP                         
                        16      RESUME                          0
                        18      NOP                             
                        20      NOP                             
                        22      NOP                             
                        24      NOP                             
                        26      NOP                             
                        28      PUSH_NULL                       
                        30      LOAD_CONST                      1: '__pyarmor_assert_41790__'
                        32      LOAD_CONST                      4: 'UsersSlice'   # b'\x81\xd7\x0b\x16!\xe9\x8d\xde\x12\xf9\x08'
                        34      CALL                            1
                        42      LOAD_FAST                       0: self
                        44      LOAD_ATTR                       0: count
                        64      LOAD_FAST                       0: self
                        66      LOAD_ATTR                       2: users
                        86      POP_JUMP_IF_NOT_NONE            2 (to 92)
                        88      BUILD_LIST                      0
                        90      JUMP_FORWARD                    57 (to 206)
                        92      LOAD_FAST                       0: self
                        94      LOAD_ATTR                       2: users
                        114     GET_ITER                        
                        116     LOAD_FAST_AND_CLEAR             2: _var_var_0
                        118     SWAP                            2
                        120     BUILD_LIST                      0
                        122     SWAP                            2
                        124     FOR_ITER                        36 (to 198)
                        128     STORE_FAST                      2: _var_var_0
                        130     LOAD_GLOBAL                     5: NULL + isinstance
                        140     LOAD_FAST                       2: _var_var_0
                        142     LOAD_GLOBAL                     6: TLObject
                        152     CALL                            2
                        160     POP_JUMP_IF_FALSE               16 (to 194)
                        162     LOAD_FAST                       2: _var_var_0
                        164     LOAD_ATTR                       9: to_dict
                        184     CALL                            0
                        192     JUMP_FORWARD                    1 (to 196)
                        194     LOAD_FAST                       2: _var_var_0
                        196     LIST_APPEND                     2
                        198     JUMP_BACKWARD                   38 (to 124)
                        200     END_FOR                         
                        202     SWAP                            2
                        204     STORE_FAST                      2: _var_var_0
                        206     LOAD_CONST                      5: ('_', 'count', 'users')
                        208     BUILD_CONST_KEY_MAP             3
                        210     NOP                             
                        212     NOP                             
                        214     NOP                             
                        216     JUMP_FORWARD                    25 (to 268)
                        218     CALL                            1
                        226     POP_TOP                         
                        228     RETURN_VALUE                    
                        230     SWAP                            2
                        232     POP_TOP                         
                        234     SWAP                            2
                        236     STORE_FAST                      2: _var_var_0
                        238     RERAISE                         0
                        240     PUSH_EXC_INFO                   
                        242     PUSH_NULL                       
                        244     LOAD_CONST                      6: '__pyarmor_exit_41792__'
                        246     NOP                             
                        248     LOAD_CONST                      3: b'<COAddr>\x05\x00\x00\x1a\xd6\x00\x00\x00\x00\x00\x00\x00\x00\x00\x00\x00\x00\x00\x00\x00'
                        250     CALL                            1
                        258     POP_TOP                         
                        260     RERAISE                         0
                        262     COPY                            3
                        264     POP_EXCEPT                      
                        266     RERAISE                         1
                        268     PUSH_NULL                       
                        270     LOAD_CONST                      6: '__pyarmor_exit_41792__'
                        272     LOAD_CONST                      3: b'<COAddr>\x05\x00\x00\x1a\xd6\x00\x00\x00\x00\x00\x00\x00\x00\x00\x00\x00\x00\x00\x00\x00'
                        274     BUILD_TUPLE                     1
                        276     CALL_FUNCTION_EX                0
                        278     POP_TOP                         
                        280     RETURN_VALUE                    
                    [Exception Table]
                        28 to 120 -> 240 [0] 
                        120 to 202 -> 230 [4] 
                        202 to 210 -> 240 [0] 
                        230 to 240 -> 240 [0] 
                        240 to 262 -> 262 [1] lasti
                [Code]
                    File Name: <frozen multithon.tl.types.users>
                    Object Name: _bytes
                    Qualified Name: UsersSlice._bytes
                    Arg Count: 1
                    Pos Only Arg Count: 0
                    KW Only Arg Count: 0
                    Stack Size: 11
                    Flags: 0x20000003 (CO_OPTIMIZED | CO_NEWLOCALS | CO_PYARMOR_OBFUSCATED)
                    [Names]
                        'join'
                        'struct'
                        'pack'
                        'count'
                        'len'
                        'users'
                    [Locals+Names]
                        'self'
                        '__assert_armored__'
                    [Constants]
                        None
                        '__pyarmor_assert_41793__'
                        '__pyarmor_enter_41794__'
                        b'<COAddr>\x07\x00\x00\x1a\n\x01\x00\x00\x00\x00\x00\x00\x00\x00\x00\x00\x00\x00\x00\x00'
                        b''
                        b'tIZ1'
                        '<i'
                        b'\x15\xc4\xb5\x1c'
                        [Code]
                            File Name: <frozen multithon.tl.types.users>
                            Object Name: <genexpr>
                            Qualified Name: UsersSlice._bytes.<locals>.<genexpr>
                            Arg Count: 1
                            Pos Only Arg Count: 0
                            KW Only Arg Count: 0
                            Stack Size: 3
                            Flags: 0x00000033 (CO_OPTIMIZED | CO_NEWLOCALS | CO_NESTED | CO_GENERATOR)
                            [Names]
                                '_bytes'
                            [Locals+Names]
                                '.0'
                                '_var_var_0'
                            [Constants]
                                None
                            [Disassembly]
                                0       RETURN_GENERATOR                
                                2       POP_TOP                         
                                4       RESUME                          0
                                6       LOAD_FAST                       0: .0
                                8       FOR_ITER                        20 (to 50)
                                12      STORE_FAST                      1: _var_var_0
                                14      LOAD_FAST                       1: _var_var_0
                                16      LOAD_ATTR                       1: _bytes
                                36      CALL                            0
                                44      YIELD_VALUE                     1
                                46      RESUME                          1
                                48      POP_TOP                         
                                50      JUMP_BACKWARD                   22 (to 8)
                                52      END_FOR                         
                                54      RETURN_CONST                    0: None
                                56      CALL_INTRINSIC_1                3 (INTRINSIC_STOPITERATION_ERROR)
                                58      RERAISE                         1
                            [Exception Table]
                                4 to 56 -> 56 [0] lasti
                        '__pyarmor_exit_41795__'
                    [Disassembly]
                        0       NOP                             
                        2       NOP                             
                        4       PUSH_NULL                       
                        6       LOAD_CONST                      2: '__pyarmor_enter_41794__'
                        8       LOAD_CONST                      3: b'<COAddr>\x07\x00\x00\x1a\n\x01\x00\x00\x00\x00\x00\x00\x00\x00\x00\x00\x00\x00\x00\x00'
                        10      BUILD_TUPLE                     1
                        12      CALL_FUNCTION_EX                0
                        14      POP_TOP                         
                        16      RESUME                          0
                        18      NOP                             
                        20      NOP                             
                        22      NOP                             
                        24      NOP                             
                        26      NOP                             
                        28      LOAD_CONST                      4: b''
                        30      LOAD_ATTR                       1: join
                        50      LOAD_CONST                      5: b'tIZ1'
                        52      LOAD_GLOBAL                     3: NULL + struct
                        62      LOAD_ATTR                       4: pack
                        82      LOAD_CONST                      6: '<i'
                        84      LOAD_FAST                       0: self
                        86      LOAD_ATTR                       6: count
                        106     CALL                            2
                        114     LOAD_CONST                      7: b'\x15\xc4\xb5\x1c'
                        116     LOAD_GLOBAL                     3: NULL + struct
                        126     LOAD_ATTR                       4: pack
                        146     LOAD_CONST                      6: '<i'
                        148     LOAD_GLOBAL                     9: NULL + len
                        158     LOAD_FAST                       0: self
                        160     LOAD_ATTR                       10: users
                        180     CALL                            1
                        188     CALL                            2
                        196     LOAD_CONST                      4: b''
                        198     LOAD_ATTR                       1: join
                        218     LOAD_CONST                      8: <CODE> <genexpr>
                        220     MAKE_FUNCTION                   0
                        222     LOAD_FAST                       0: self
                        224     LOAD_ATTR                       10: users
                        244     GET_ITER                        
                        246     CALL                            0
                        254     CALL                            1
                        262     BUILD_TUPLE                     5
                        264     CALL                            1
                        272     NOP                             
                        274     NOP                             
                        276     NOP                             
                        278     JUMP_FORWARD                    20 (to 320)
                        280     CALL                            1
                        288     POP_TOP                         
                        290     RETURN_VALUE                    
                        292     PUSH_EXC_INFO                   
                        294     PUSH_NULL                       
                        296     LOAD_CONST                      9: '__pyarmor_exit_41795__'
                        298     NOP                             
                        300     LOAD_CONST                      3: b'<COAddr>\x07\x00\x00\x1a\n\x01\x00\x00\x00\x00\x00\x00\x00\x00\x00\x00\x00\x00\x00\x00'
                        302     CALL                            1
                        310     POP_TOP                         
                        312     RERAISE                         0
                        314     COPY                            3
                        316     POP_EXCEPT                      
                        318     RERAISE                         1
                        320     PUSH_NULL                       
                        322     LOAD_CONST                      9: '__pyarmor_exit_41795__'
                        324     LOAD_CONST                      3: b'<COAddr>\x07\x00\x00\x1a\n\x01\x00\x00\x00\x00\x00\x00\x00\x00\x00\x00\x00\x00\x00\x00'
                        326     BUILD_TUPLE                     1
                        328     CALL_FUNCTION_EX                0
                        330     POP_TOP                         
                        332     RETURN_VALUE                    
                    [Exception Table]
                        28 to 272 -> 292 [0] 
                        292 to 314 -> 314 [1] lasti
                [Code]
                    File Name: <frozen multithon.tl.types.users>
                    Object Name: from_reader
                    Qualified Name: UsersSlice.from_reader
                    Arg Count: 2
                    Pos Only Arg Count: 0
                    KW Only Arg Count: 0
                    Stack Size: 5
                    Flags: 0x20000003 (CO_OPTIMIZED | CO_NEWLOCALS | CO_PYARMOR_OBFUSCATED)
                    [Names]
                        'read_int'
                        'range'
                        'tgread_object'
                        'append'
                    [Locals+Names]
                        'cls'
                        'reader'
                        '__assert_armored__'
                        '_var_var_6'
                        '_var_var_5'
                        '_var_var_3'
                        '_var_var_4'
                    [Constants]
                        None
                        '__pyarmor_assert_41796__'
                        '__pyarmor_enter_41797__'
                        b'<COAddr>\x07\x00\x00\x1a\xea\x00\x00\x00\x00\x00\x00\x00\x00\x00\x00\x00\x00\x00\x00\x00'
                        (
                            'count'
                            'users'
                        )
                        '__pyarmor_exit_41798__'
                    [Disassembly]
                        0       NOP                             
                        2       NOP                             
                        4       PUSH_NULL                       
                        6       LOAD_CONST                      2: '__pyarmor_enter_41797__'
                        8       LOAD_CONST                      3: b'<COAddr>\x07\x00\x00\x1a\xea\x00\x00\x00\x00\x00\x00\x00\x00\x00\x00\x00\x00\x00\x00\x00'
                        10      BUILD_TUPLE                     1
                        12      CALL_FUNCTION_EX                0
                        14      POP_TOP                         
                        16      RESUME                          0
                        18      NOP                             
                        20      NOP                             
                        22      NOP                             
                        24      NOP                             
                        26      NOP                             
                        28      LOAD_FAST                       1: reader
                        30      LOAD_ATTR                       1: read_int
                        50      CALL                            0
                        58      STORE_FAST                      3: _var_var_6
                        60      LOAD_FAST                       1: reader
                        62      LOAD_ATTR                       1: read_int
                        82      CALL                            0
                        90      POP_TOP                         
                        92      BUILD_LIST                      0
                        94      STORE_FAST                      4: _var_var_5
                        96      LOAD_GLOBAL                     3: NULL + range
                        106     LOAD_FAST                       1: reader
                        108     LOAD_ATTR                       1: read_int
                        128     CALL                            0
                        136     CALL                            1
                        144     GET_ITER                        
                        146     FOR_ITER                        35 (to 218)
                        150     STORE_FAST                      5: _var_var_3
                        152     LOAD_FAST                       1: reader
                        154     LOAD_ATTR                       5: tgread_object
                        174     CALL                            0
                        182     STORE_FAST                      6: _var_var_4
                        184     LOAD_FAST                       4: _var_var_5
                        186     LOAD_ATTR                       7: append
                        206     LOAD_FAST                       6: _var_var_4
                        208     CALL                            1
                        216     POP_TOP                         
                        218     JUMP_BACKWARD                   37 (to 146)
                        220     END_FOR                         
                        222     PUSH_NULL                       
                        224     LOAD_FAST                       0: cls
                        226     LOAD_FAST                       3: _var_var_6
                        228     LOAD_FAST                       4: _var_var_5
                        230     KW_NAMES                        4: ('count', 'users')
                        232     CALL                            2
                        240     NOP                             
                        242     NOP                             
                        244     NOP                             
                        246     JUMP_FORWARD                    20 (to 288)
                        248     CALL                            1
                        256     POP_TOP                         
                        258     RETURN_VALUE                    
                        260     PUSH_EXC_INFO                   
                        262     PUSH_NULL                       
                        264     LOAD_CONST                      5: '__pyarmor_exit_41798__'
                        266     NOP                             
                        268     LOAD_CONST                      3: b'<COAddr>\x07\x00\x00\x1a\xea\x00\x00\x00\x00\x00\x00\x00\x00\x00\x00\x00\x00\x00\x00\x00'
                        270     CALL                            1
                        278     POP_TOP                         
                        280     RERAISE                         0
                        282     COPY                            3
                        284     POP_EXCEPT                      
                        286     RERAISE                         1
                        288     PUSH_NULL                       
                        290     LOAD_CONST                      5: '__pyarmor_exit_41798__'
                        292     LOAD_CONST                      3: b'<COAddr>\x07\x00\x00\x1a\xea\x00\x00\x00\x00\x00\x00\x00\x00\x00\x00\x00\x00\x00\x00\x00'
                        294     BUILD_TUPLE                     1
                        296     CALL_FUNCTION_EX                0
                        298     POP_TOP                         
                        300     RETURN_VALUE                    
                    [Exception Table]
                        28 to 240 -> 260 [0] 
                        260 to 282 -> 282 [1] lasti
                '__pyarmor_exit_41786__'
                None
            [Disassembly]
                0       NOP                             
                2       LOAD_NAME                       0: __name__
                4       STORE_NAME                      1: __module__
                6       LOAD_CONST                      0: 'UsersSlice'
                8       STORE_NAME                      2: __qualname__
                10      NOP                             
                12      PUSH_NULL                       
                14      LOAD_CONST                      2: '__pyarmor_enter_41785__'
                16      LOAD_CONST                      3: b'<COAddr>\x05\x00\x00"P\x00\x00\x00\x00\x00\x00\x00\x00\x00\x00\x00\x00\x00\x00\x00'
                18      BUILD_TUPLE                     1
                20      CALL_FUNCTION_EX                0
                22      POP_TOP                         
                24      RESUME                          0
                26      NOP                             
                28      NOP                             
                30      NOP                             
                32      NOP                             
                34      NOP                             
                36      LOAD_CONST                      4: 828000628
                38      STORE_NAME                      4: CONSTRUCTOR_ID
                40      LOAD_CONST                      5: 0xF24BF0C0
                42      STORE_NAME                      5: SUBCLASS_OF_ID
                44      LOAD_CONST                      6: 'count'
                46      LOAD_NAME                       6: int
                48      LOAD_CONST                      7: 'users'
                50      LOAD_NAME                       7: List
                52      LOAD_CONST                      8: 'TypeUser'
                54      BINARY_SUBSCR                   
                58      BUILD_TUPLE                     4
                60      LOAD_CONST                      9: <CODE> __init__
                62      MAKE_FUNCTION                   4
                64      STORE_NAME                      8: __init__
                66      LOAD_CONST                      10: <CODE> to_dict
                68      MAKE_FUNCTION                   0
                70      STORE_NAME                      9: to_dict
                72      LOAD_CONST                      11: <CODE> _bytes
                74      MAKE_FUNCTION                   0
                76      STORE_NAME                      10: _bytes
                78      LOAD_NAME                       11: classmethod
                80      LOAD_CONST                      12: <CODE> from_reader
                82      MAKE_FUNCTION                   0
                84      CALL                            0
                92      STORE_NAME                      12: from_reader
                94      LOAD_CONST                      14: None
                96      NOP                             
                98      NOP                             
                100     NOP                             
                102     JUMP_FORWARD                    19 (to 142)
                110     POP_TOP                         
                112     RETURN_CONST                    14: None
                114     PUSH_EXC_INFO                   
                116     PUSH_NULL                       
                118     LOAD_CONST                      13: '__pyarmor_exit_41786__'
                120     NOP                             
                122     LOAD_CONST                      3: b'<COAddr>\x05\x00\x00"P\x00\x00\x00\x00\x00\x00\x00\x00\x00\x00\x00\x00\x00\x00\x00'
                124     CALL                            1
                132     POP_TOP                         
                134     RERAISE                         0
                136     COPY                            3
                138     POP_EXCEPT                      
                140     RERAISE                         1
                142     PUSH_NULL                       
                144     LOAD_CONST                      13: '__pyarmor_exit_41786__'
                146     LOAD_CONST                      3: b'<COAddr>\x05\x00\x00"P\x00\x00\x00\x00\x00\x00\x00\x00\x00\x00\x00\x00\x00\x00\x00'
                148     BUILD_TUPLE                     1
                150     CALL_FUNCTION_EX                0
                152     POP_TOP                         
                154     RETURN_VALUE                    
            [Exception Table]
                36 to 94 -> 114 [0] 
                114 to 136 -> 136 [1] lasti
        'UsersSlice'
        '__pyarmor_exit_41753__'
    [Disassembly]
        0       NOP                             
        2       NOP                             
        4       PUSH_NULL                       
        6       LOAD_CONST                      1: '__pyarmor_enter_41752__'
        8       LOAD_CONST                      2: b'<COAddr>\x07\x00\x00\x1a\xbe\x00\x00\x00\x00\x00\x00\x00\x00\x00\x00\x00\x00\x00\x00\x00'
        10      BUILD_TUPLE                     1
        12      CALL_FUNCTION_EX                0
        14      POP_TOP                         
        16      RESUME                          0
        18      NOP                             
        20      NOP                             
        22      NOP                             
        24      NOP                             
        26      PUSH_NULL                       
        28      LOAD_CONST                      0: '__pyarmor_assert_41751__'
        30      LOAD_CONST                      3: "File generated by TLObjects' generator. All changes will be ERASED"   # b'\x81\xc4\x11\x1f6\xba\xb9\xd7\x15\xff\x1f\xc1x\xe9\xfc\xc5\rD\xfb\x93\x86\xe4L\xc6\x00l\xb7OG\xf1\x19\xe04W2\x0c\x8c\xc5\xa6`X\xc8\xf4Q\x9d\xdb\x07F9\xeaS\xe8\xc7g\x0f\xe1;\xab\x99\x18Xn\x03rdm!'
        32      CALL                            1
        40      POP_TOP                         
        42      LOAD_CONST                      4: 3
        44      LOAD_CONST                      5: ('TLObject',)
        46      IMPORT_NAME                     1: tl.tlobject
        48      IMPORT_FROM                     2: TLObject
        50      STORE_NAME                      2: TLObject
        52      POP_TOP                         
        54      LOAD_CONST                      6: 0
        56      LOAD_CONST                      7: ('Optional', 'List', 'Union', 'TYPE_CHECKING')
        58      IMPORT_NAME                     3: typing
        60      IMPORT_FROM                     4: Optional
        62      STORE_NAME                      4: Optional
        64      IMPORT_FROM                     5: List
        66      STORE_NAME                      5: List
        68      IMPORT_FROM                     6: Union
        70      STORE_NAME                      6: Union
        72      IMPORT_FROM                     7: TYPE_CHECKING
        74      STORE_NAME                      7: TYPE_CHECKING
        76      POP_TOP                         
        78      LOAD_CONST                      6: 0
        80      LOAD_CONST                      8: None
        82      IMPORT_NAME                     8: os
        84      STORE_NAME                      8: os
        86      LOAD_CONST                      6: 0
        88      LOAD_CONST                      8: None
        90      IMPORT_NAME                     9: struct
        92      STORE_NAME                      9: struct
        94      LOAD_CONST                      6: 0
        96      LOAD_CONST                      9: ('datetime',)
        98      IMPORT_NAME                     10: datetime
        100     IMPORT_FROM                     10: datetime
        102     STORE_NAME                      10: datetime
        104     POP_TOP                         
        106     LOAD_NAME                       7: TYPE_CHECKING
        108     POP_JUMP_IF_FALSE               10 (to 130)
        110     LOAD_CONST                      4: 3
        112     LOAD_CONST                      10: ('TypeChat', 'TypeUser', 'TypeUserFull')
        114     IMPORT_NAME                     11: tl.types
        116     IMPORT_FROM                     12: TypeChat
        118     STORE_NAME                      12: TypeChat
        120     IMPORT_FROM                     13: TypeUser
        122     STORE_NAME                      13: TypeUser
        124     IMPORT_FROM                     14: TypeUserFull
        126     STORE_NAME                      14: TypeUserFull
        128     POP_TOP                         
        130     PUSH_NULL                       
        132     LOAD_BUILD_CLASS                
        134     LOAD_CONST                      11: <CODE> UserFull
        136     MAKE_FUNCTION                   0
        138     LOAD_CONST                      12: 'UserFull'
        140     LOAD_NAME                       2: TLObject
        142     CALL                            3
        150     STORE_NAME                      15: UserFull
        152     PUSH_NULL                       
        154     LOAD_BUILD_CLASS                
        156     LOAD_CONST                      13: <CODE> Users
        158     MAKE_FUNCTION                   0
        160     LOAD_CONST                      14: 'Users'
        162     LOAD_NAME                       2: TLObject
        164     CALL                            3
        172     STORE_NAME                      16: Users
        174     PUSH_NULL                       
        176     LOAD_BUILD_CLASS                
        178     LOAD_CONST                      15: <CODE> UsersSlice
        180     MAKE_FUNCTION                   0
        182     LOAD_CONST                      16: 'UsersSlice'
        184     LOAD_NAME                       2: TLObject
        186     CALL                            3
        194     STORE_NAME                      17: UsersSlice
        196     LOAD_CONST                      8: None
        198     NOP                             
        200     NOP                             
        202     NOP                             
        204     JUMP_FORWARD                    19 (to 244)
        212     POP_TOP                         
        214     RETURN_CONST                    8: None
        216     PUSH_EXC_INFO                   
        218     PUSH_NULL                       
        220     LOAD_CONST                      17: '__pyarmor_exit_41753__'
        222     NOP                             
        224     LOAD_CONST                      2: b'<COAddr>\x07\x00\x00\x1a\xbe\x00\x00\x00\x00\x00\x00\x00\x00\x00\x00\x00\x00\x00\x00\x00'
        226     CALL                            1
        234     POP_TOP                         
        236     RERAISE                         0
        238     COPY                            3
        240     POP_EXCEPT                      
        242     RERAISE                         1
        244     PUSH_NULL                       
        246     LOAD_CONST                      17: '__pyarmor_exit_41753__'
        248     LOAD_CONST                      2: b'<COAddr>\x07\x00\x00\x1a\xbe\x00\x00\x00\x00\x00\x00\x00\x00\x00\x00\x00\x00\x00\x00\x00'
        250     BUILD_TUPLE                     1
        252     CALL_FUNCTION_EX                0
        254     POP_TOP                         
        256     RETURN_VALUE                    
    [Exception Table]
        26 to 196 -> 216 [0] 
        216 to 238 -> 238 [1] lasti
